Workbook

Sheet Sheet1
A3: Row Labels | B3: Count of Application Long Name | C3: Sum of Current FTC | D3: Sum of Current FTE | E3: Sum of Current MGCC | F3: Sum of Target # of FTC | H3: Reduction by Area
A4: Common Service Platform | B4: 10 | C4: 98.095708 | D4: 35.314583 | E4: 65.37 | F4: 99.390146 | H4: =C4-F4 -> -1.2944375
A5: contract management | B5: 28 | C5: 203.93583 | D5: 26.814167 | E5: 0 | F5: 115.375 | H5: =C5-F5 -> 88.560833
A6: Corporate Related | B6: 33 | C6: 36.744706 | D6: 12.194167 | E6: 1.5 | F6: 25.219436 | H6: =C6-F6 -> 11.52527
A7: Customer Care / Call Center Related | B7: 8 | C7: 55.747917 | D7: 42.233333 | E7: 22.910417 | F7: 60.445833 | H7: =C7-F7 -> -4.6979167
A8: Data Infrastructure | B8: 3 | C8: 64.704594 | D8: 18.825 | E8: 15.991667 | F8: 50.382484 | H8: =C8-F8 -> 14.322109
A9: Fee Management | B9: 5 | C9: 38.147792 | D9: 9.7791667 | E9: 0.58333333 | F9: 24.255146 | H9: =C9-F9 -> 13.892646
A10: Insurance Claims and Benefits Payment Related | B10: 6 | C10: 85.448458 | D10: 13.479167 | E10: 22.645833 | F10: 60.786729 | H10: =C10-F10 -> 24.661729
A11: Marketing/Direct Business Related | B11: 9 | C11: 27.842083 | D11: 7.5270833 | E11: 8.785 | F11: 22.077083 | H11: =C11-F11 -> 5.765
A12: New Contract Related | B12: 12 | C12: 40.463542 | D12: 1.0270833 | E12: 0 | F12: 20.245313 | H12: =C12-F12 -> 20.218229
A13: Sales / Insurance Recruitment | B13: 13 | C13: 267.93104 | D13: 81.104167 | E13: 91.220833 | F13: 219.35698 | H13: =C13-F13 -> 48.574063
A14: Storage and Preservation Related | B14: 15 | C14: 25.462458 | D14: 25.966667 | E14: 11 | F14: 54.453875 | H14: =C14-F14 -> -28.991417
A15: Grand Total | B15: 142 | C15: 944.52413 | D15: 274.26458 | E15: 240.00708 | F15: 751.98803 | H15: =C15-F15 -> 192.53611
H16: =C16-F16 -> 0
H17: =C17-F17 -> 0
H18: =C18-F18 -> 0
A19: Row Labels | B19: Count of Application Long Name | C19: Sum of Current FTC | D19: Sum of Current FTE | E19: Sum of Current MGCC | F19: Sum of Target # of FTC | H19: Reduction by Practice
A20: Cloud | B20: 100 | C20: 618.29037 | D20: 193.12958 | E20: 202.64542 | F20: 529.00096 | H20: =C20-F20 -> 89.289416
A21: Data | B21: 3 | C21: 64.704594 | D21: 18.825 | E21: 15.991667 | F21: 50.382484 | H21: =C21-F21 -> 14.322109
A22: Digital | B22: 5 | C22: 41.781 | D22: 24.322917 | E22: 21.328333 | F22: 43.716125 | H22: =C22-F22 -> -1.935125
A23: Corporate Related | B23: 1 | C23: 2.4426667 | D23: 0.57083333 | E23: 0 | F23: 1.50675 | H23: =C23-F23 -> 0.93591667
A24: Customer Care / Call Center Related | B24: 1 | C24: 9.5833333 | D24: 11.3375 | E24: 7.0833333 | F24: 14.002083 | H24: =C24-F24 -> -4.41875
A25: Himawari | B25: 1 | C25: 9.5833333 | D25: 11.3375 | E25: 7.0833333 | F25: 14.002083 | H25: =C25-F25 -> -4.41875
A26: Fee Management | B26: 1 | F26: 0 | H26: =C26-F26 -> 0
A27: Marketing/Direct Business Related | B27: 1 | C27: 8.9216667 | D27: 2.4104167 | E27: 1.52 | F27: 6.4260417 | H27: =C27-F27 -> 2.495625
A28: Sales / Insurance Recruitment | B28: 1 | C28: 20.833333 | D28: 10.004167 | E28: 12.725 | F28: 21.78125 | H28: =C28-F28 -> -0.94791667
A29: WPSCFC-JPN | B29: 1 | C29: 20.833333 | D29: 10.004167 | E29: 12.725 | F29: 21.78125 | H29: =C29-F29 -> -0.94791667
A30: Mainframe | B30: 28 | C30: 207.90404 | D30: 29.60375 | E30: 0 | F30: 118.7539 | H30: =C30-F30 -> 89.150146
A31: contract management | B31: 26 | C31: 202.76654 | D31: 26.50375 | E31: 0 | F31: 114.63515 | H31: =C31-F31 -> 88.131396
A32: ASP Bridge(H) MF-JPN | B32: 1 | C32: 6.7267083 | D32: 1.4625 | E32: 0 | F32: 4.0946042 | H32: =C32-F32 -> 2.6321042
A33: CCA MF-JPN | B33: 1 | C33: 1.6308333 | D33: 0 | E33: 0 | F33: 0.81541667 | H33: =C33-F33 -> 0.81541667
A34: CT Salary MF-JPN | B34: 1 | C34: 0.2 | D34: 0 | E34: 0 | F34: 0.1 | H34: =C34-F34 -> 0.1
A35: Data Send System for BANC MF-JP | B35: 1 | C35: 9.2697083 | D35: 2.8458333 | E35: 0 | F35: 6.0577708 | H35: =C35-F35 -> 3.2119375
A36: Foreign MF-JPN | B36: 1 | F36: 0 | H36: =C36-F36 -> 0
A37: LC AACOMP MF-JPN | B37: 1 | C37: 13.545708 | D37: 3.14375 | E37: 0 | F37: 8.3447292 | H37: =C37-F37 -> 5.2009792
A38: LC AAPerf MF-JPN | B38: 1 | C38: 10.784167 | D38: 0.74583333 | E38: 0 | F38: 5.765 | H38: =C38-F38 -> 5.0191667
A39: LC Billing MF-JPN | B39: 1 | C39: 20.892167 | D39: 1.85375 | E39: 0 | F39: 11.372958 | H39: =C39-F39 -> 9.5192083
A40: LC Collection MF-JPN | B40: 1 | F40: 0 | H40: =C40-F40 -> 0
A41: LC Corresponding MF-JPN | B41: 1 | C41: 15.953625 | D41: 1.6541667 | E41: 0 | F41: 8.8038958 | H41: =C41-F41 -> 7.1497292
A42: LC GL/SC MF-JPN | B42: 1 | C42: 5.28875 | D42: 1.025 | E42: 0 | F42: 3.156875 | H42: =C42-F42 -> 2.131875
A43: LC Micro MF-JPN | B43: 1 | C43: 2.1175 | D43: 0 | E43: 0 | F43: 1.05875 | H43: =C43-F43 -> 1.05875
A44: LC Payment MF-JPN | B44: 1 | C44: 2.8966667 | D44: 0.025 | E44: 0 | F44: 1.4608333 | H44: =C44-F44 -> 1.4358333
A45: LC POSPMC MF-JPN | B45: 1 | C45: 59.558958 | D45: 7.7541667 | E45: 0 | F45: 33.656562 | H45: =C45-F45 -> 25.902396
A46: LC Reins MF-JPN | B46: 1 | C46: 6.0129167 | D46: 0.25416667 | E46: 0 | F46: 3.1335417 | H46: =C46-F46 -> 2.879375
A47: LC Submit MF-JPN | B47: 1 | C47: 1.9683333 | D47: 0.16458333 | E47: 0 | F47: 1.0664583 | H47: =C47-F47 -> 0.901875
A48: LC UWI MF-JPN | B48: 1 | C48: 8.8045833 | D48: 0.85 | E48: 0 | F48: 4.8272917 | H48: =C48-F48 -> 3.9772917
A49: LC Valuation MF-JPN | B49: 1 | C49: 9.76875 | D49: 1.4833333 | E49: 0 | F49: 5.6260417 | H49: =C49-F49 -> 4.1427083
A50: LINC MF-JPN | B50: 1 | C50: 1.02875 | D50: 0 | E50: 0 | F50: 0.514375 | H50: =C50-F50 -> 0.514375
A51: Maturity MF-JPN | B51: 1 | C51: 4.3783333 | D51: 0.97083333 | E51: 0 | F51: 2.6745833 | H51: =C51-F51 -> 1.70375
A52: MCFA CP DB MF-JPN | B52: 1 | F52: 0 | H52: =C52-F52 -> 0
A53: Policy UWIBATCH MF-JPN | B53: 1 | C53: 12.606875 | D53: 1.1416667 | E53: 0 | F53: 6.8742708 | H53: =C53-F53 -> 5.7326042
A54: PremCollectDBMF-JPN | B54: 1 | F54: 0 | H54: =C54-F54 -> 0
A55: Processor-I MF-JPN | B55: 1 | C55: 7.6683333 | D55: 1.1291667 | E55: 0 | F55: 4.39875 | H55: =C55-F55 -> 3.2695833
A56: SWINGMANAGER MF-JPN | B56: 1 | F56: 0 | H56: =C56-F56 -> 0
A57: TaxCertification MF-JPN | B57: 1 | C57: 1.664875 | D57: 0 | E57: 0 | F57: 0.8324375 | H57: =C57-F57 -> 0.8324375
A58: Corporate Related | B58: 2 | C58: 5.1375 | D58: 3.1 | E58: 0 | F58: 4.11875 | H58: =C58-F58 -> 1.01875
A59: (blank) | B59: 6 | C59: 11.844125 | D59: 8.3833333 | E59: 0.041666667 | F59: 10.134563 | H59: =C59-F59 -> 1.7095625
A60: Grand Total | B60: 142 | C60: 944.52413 | D60: 274.26458 | E60: 240.00708 | F60: 751.98802 | H60: =C60-F60 -> 192.53611

Sheet Sheet3
A3: Count of EAI Application ID | B3: Column Labels
A4: Row Labels | B4: Cloud | C4: Data | D4: Digital | E4: Mainframe | F4: (blank) | G4: Grand Total
A5: Common Service Platform | B5: 9 | F5: 1 | G5: 10
A6: contract management | B6: 2 | E6: 26 | G6: 28
A7: Corporate Related | B7: 29 | D7: 1 | E7: 2 | F7: 1 | G7: 33
A8: Customer Care / Call Center Related | B8: 6 | D8: 1 | F8: 1 | G8: 8
A9: Data Infrastructure | C9: 3 | G9: 3
A10: Fee Management | B10: 4 | D10: 1 | G10: 5
A11: Insurance Claims and Benefits Payment Related | B11: 6 | G11: 6
A12: Marketing/Direct Business Related | B12: 8 | D12: 1 | G12: 9
A13: New Contract Related | B13: 12 | G13: 12
A14: Sales / Insurance Recruitment | B14: 12 | D14: 1 | G14: 13
A15: Storage and Preservation Related | B15: 12 | F15: 3 | G15: 15
A16: Grand Total | B16: 100 | C16: 3 | D16: 5 | E16: 28 | F16: 6 | G16: 142
A18: Y/N | B18: (All)
B20: Column Labels
B21: Cloud | D21: Data | F21: Digital | H21: Mainframe | J21: (blank) | L21: Total Count of EAI Application ID | M21: Total Sum of Total
A22: Row Labels | B22: Count of EAI Application ID | C22: Sum of Total | D22: Count of EAI Application ID | E22: Sum of Total | F22: Count of EAI Application ID | G22: Sum of Total | H22: Count of EAI Application ID | I22: Sum of Total | J22: Count of EAI Application ID | K22: Sum of Total
A23: Common Service Platform | B23: 9 | C23: 198.53029 | J23: 1 | K23: 0.25 | L23: 10 | M23: 198.78029
A24: contract management | B24: 2 | C24: 1.4797083 | H24: 26 | I24: 229.27029 | L24: 28 | M24: 230.75
A25: Corporate Related | B25: 29 | C25: 38.408706 | F25: 1 | G25: 3.0135 | H25: 2 | I25: 8.2375 | J25: 1 | K25: 0.77916667 | L25: 33 | M25: 50.438873
A26: Customer Care / Call Center Related | B26: 6 | C26: 86.485 | F26: 1 | G26: 28.004167 | J26: 1 | K26: 6.4025 | L26: 8 | M26: 120.89167
A27: Data Infrastructure | D27: 3 | E27: 100.76497 | L27: 3 | M27: 100.76497
A28: Fee Management | B28: 4 | C28: 48.510292 | F28: 1 | L28: 5 | M28: 48.510292
A29: Insurance Claims and Benefits Payment Related | B29: 6 | C29: 121.57346 | L29: 6 | M29: 121.57346
A30: Marketing/Direct Business Related | B30: 8 | C30: 31.302083 | F30: 1 | G30: 12.852083 | L30: 9 | M30: 44.154167
A31: New Contract Related | B31: 12 | C31: 40.490625 | L31: 12 | M31: 40.490625
A32: Sales / Insurance Recruitment | B32: 12 | C32: 395.15146 | F32: 1 | G32: 43.5625 | L32: 13 | M32: 438.71396
A33: Storage and Preservation Related | B33: 12 | C33: 96.070292 | J33: 3 | K33: 12.837458 | L33: 15 | M33: 108.90775
A34: Grand Total | B34: 100 | C34: 1058.0019 | D34: 3 | E34: 100.76497 | F34: 5 | G34: 87.43225 | H34: 28 | I34: 237.50779 | J34: 6 | K34: 20.269125 | L34: 142 | M34: 1503.9761

Sheet ApplicationList
AM1: =AM3/AH3 -> 0.56752605 | AN1: Composition of Run | AR1: =SUM(AR3:AS3) -> 5.4512917 | AT1: =SUM(AT3:BA3) -> #REF!
AE3: =SUBTOTAL(9,AE5:AE146) -> 3.7637917 | AF3: =SUBTOTAL(9,AF5:AF146) -> 1.6875 | AG3: =SUBTOTAL(9,AG5:AG146) -> 0 | AH3: =SUBTOTAL(9,AH5:AH146) -> 5.4512917 | AI3: =SUBTOTAL(9,AI5:AI146) -> 1.4892072 | AJ3: =SUBTOTAL(9,AJ5:AJ146) -> 2.7256458 | AK3: =SUBTOTAL(9,AK5:AK146) -> 2.7256458 | AM3: =SUBTOTAL(9,AM5:AM146) -> 3.09375 | AN3: Capgemini Presence | AR3: =SUBTOTAL(9,AR5:AR146) -> 2.3575417 | AS3: =SUBTOTAL(9,AS5:AS146) -> 3.09375 | AT3: =SUBTOTAL(9,AT5:AT146) -> #REF! | AU3: =SUBTOTAL(9,AU5:AU146) -> #REF! | AV3: =SUBTOTAL(9,AV5:AV146) -> #REF! | AW3: =SUBTOTAL(9,AW5:AW146) -> #REF! | AX3: =SUBTOTAL(9,AX5:AX146) -> #REF! | AY3: =SUBTOTAL(9,AY5:AY146) -> #REF! | ... BA3: =SUBTOTAL(9,BA5:BA146) -> #REF!
A4: AD Coverage | B4: AMS Coverage | C4: QA Coverage | D4: Remarks | E4: EAI Application ID | F4: Application | G4: Application Long Name | H4: Application Description | I4: domain | J4: Group | K4: Team | L4: Host Support structure | M4: Application Class | N4: Application Status | O4: Primary Support Team | P4: Critical Application Indicator | Q4: Business Sponsor LOB | R4: Internet Facing Application | S4: Application Hosting | T4: General Application Profile | U4: Operating System/ Platform | V4: Primary Code Language | W4: Application Source Code Ownership | X4: Cloud_Platform | Y4: Cloud_Indicator | Z4: In Scope | AA4: Development | AB4: conservative | AC4: Infrastructure Operation | AD4: Priority Transfer Targets | AE4: Current FTC | AF4: Current FTE | AG4: Current MGCC | AH4: Total | AI4: % of PRJ | AJ4: Target # of FTC | AK4: Target # of FTE/MGCC | AL4: Comments | AM4: RUN FTE (based on %PRJ) | AN4: Y/N | AO4: T3 HC | AP4: CSO_QA ScopeHC | AQ4: in FTE equivalent (basis Billing) | AR4: AD Scope (Assumed) | AS4: AM Scope(Assumed) | AT4: BA | AU4: BSA | AV4: Dev | AW4: Tester | AX4: SRE | AY4: Scrum Master | AZ4: Architects | BA4: AM | BB4: Is Total Changed
A5: Digital | B5: Yes | E5: 9629 | F5: Global Sales Comp - Japan | G5: Global Sales Comp - Japan | H5: Responsible for data integration (ETL) between ICM (11004) and Life-Comm. Runs on US environments. | I5: Fee Management | J5: Core Insurance Systems Group 34956 | K5: Commission Systems Team 34958 | L5: MetLife IT Hosted/Supported | M5: Core Business Application | N5: Production | O5: AD Supported | P5: N | Q5: Asia Region | R5: Yes | S5: Yes | T5: Other#Schduler / orchastration tool call servers batches. | V5: Other#Infomatica workflow Bash shell Dos batch | W5: Non-MetLife Owned Application Code (3rd party/COTS) | X5: Software as a Service (SaaS) | Y5: Yes | Z5: Y | AA5: Y | AB5: Y | AC5: N | AD5: N | AL5: The number of personnel is included in 11004. | AM5: =AH5*(1-AI5) -> 0 | AN5: =VLOOKUP($E5,'Capgemini PResence and HC'!$B$2:$G$143,4,0) -> N | AO5: =VLOOKUP($E5,'Capgemini PResence and HC'!$B$2:$G$143,2,0) -> 0 | AP5: =VLOOKUP($E5,'Capgemini PResence and HC'!$B$2:$G$143,3,0) -> 0 | AQ5: =VLOOKUP($E5,'Capgemini PResence and HC'!$B$2:$G$143,6,0) -> 0 | BB5: =SUM(AE5:AG5)-AH5 -> 0
A6: Mainframe | B6: Yes | E6: 9796 | F6: LC POSPMC MF-JPN | G6: LifeComm POSPMC | H6: A subsystem based on LifeComm (mainframe package). Responsible for transaction processing for the contract management master. As a business domain, it handles contract maintenance (such as name changes, address changes, cancellations, and reductions). We continue to utilize the functions built with assemblers, continuously developing assemblers for new product development, other development projects, and maintenance projects. | I6: contract management | J6: Core Insurance Systems Group 34956 | K6: Policy Admin Systems Team 34957 | L6: MetLife IT Hosted/Supported | M6: Core Business Application | N6: Production | O6: AD Supported | P6: Y | Q6: Global Technology & Operations | R6: No | S6: Yes | T6: Other#Mainframe | V6: Assembler, COBOL, MU(EASYPLUS), JCL | W6: MetLife Owned Application Code | Y6: No | Z6: Y | AA6: Y | AB6: Y | AC6: N | AD6: N | AE6: 59.558958 | AF6: 7.7541667 | AG6: 0 | AH6: 67.313125 | AI6: 0.71176374 | AJ6: 33.656562 | AK6: 33.656563 | AM6: =AH6*(1-AI6) -> 19.402083 | AN6: =VLOOKUP($E6,'Capgemini PResence and HC'!$B$2:$G$143,4,0) -> N | AO6: =VLOOKUP($E6,'Capgemini PResence and HC'!$B$2:$G$143,2,0) -> 0 | AP6: =VLOOKUP($E6,'Capgemini PResence and HC'!$B$2:$G$143,3,0) -> 0 | AQ6: =VLOOKUP($E6,'Capgemini PResence and HC'!$B$2:$G$143,6,0) -> 0 | BB6: =SUM(AE6:AG6)-AH6 -> 0
A7: Mainframe | B7: Yes | E7: 9800 | F7: LC Billing MF-JPN | G7: LifeComm Billing | H7: A subsystem based on LifeComm (mainframe package). As a business domain, it handles insurance premium claims and payment contract protection (such as name changes, address changes, cancellations, and reductions). While we maintain the features built with assembler, our company's main features are developed in COBOL, and except for table modifications, we are not continuously developing assemblers. | I7: contract management | J7: Core Insurance Systems Group 34956 | K7: Policy Admin Systems Team 34957 | L7: MetLife IT Hosted/Supported | M7: Core Business Application | N7: Production | O7: AD Supported | P7: Y | Q7: Global Technology & Operations | R7: No | S7: Yes | T7: Other#Mainframe | V7: COBOL, Assembler, MU(EASYPLUS), JCL | W7: MetLife Owned Application Code | Y7: No | Z7: Y | AA7: Y | AB7: Y | AC7: N | AD7: N | AE7: 20.892167 | AF7: 1.85375 | AG7: 0 | AH7: 22.745917 | AI7: 0.94285788 | AJ7: 11.372958 | AK7: 11.372958 | AM7: =AH7*(1-AI7) -> 1.29975 | AN7: =VLOOKUP($E7,'Capgemini PResence and HC'!$B$2:$G$143,4,0) -> N | AO7: =VLOOKUP($E7,'Capgemini PResence and HC'!$B$2:$G$143,2,0) -> 0 | AP7: =VLOOKUP($E7,'Capgemini PResence and HC'!$B$2:$G$143,3,0) -> 0 | AQ7: =VLOOKUP($E7,'Capgemini PResence and HC'!$B$2:$G$143,6,0) -> 0 | BB7: =SUM(AE7:AG7)-AH7 -> 0
A8: Mainframe | B8: Yes | E8: 9801 | F8: LC Collection MF-JPN | G8: LifeComm Collection | H8: A subsystem based on LifeComm (mainframe package). As a business domain, it handles insurance premium claims and payment contract protection (such as name changes, address changes, cancellations, and reductions). While we maintain the features built with assembler, our company's main features are developed in COBOL, and except for table modifications, we are not continuously developing assemblers. | I8: contract management | J8: Core Insurance Systems Group 34956 | K8: Policy Admin Systems Team 34957 | L8: MetLife IT Hosted/Supported | M8: Core Business Application | N8: Production | O8: AD Supported | P8: Y | Q8: Global Technology & Operations | R8: No | S8: Yes | T8: Other#Mainframe | V8: COBOL, Assembler, MU(EASYPLUS), JCL | W8: MetLife Owned Application Code | Y8: No | Z8: Y | AA8: Y | AB8: Y | AC8: N | AD8: N | AL8: The number of staff is included in the 9,800 | AM8: =AH8*(1-AI8) -> 0 | AN8: =VLOOKUP($E8,'Capgemini PResence and HC'!$B$2:$G$143,4,0) -> N | AO8: =VLOOKUP($E8,'Capgemini PResence and HC'!$B$2:$G$143,2,0) -> 0 | AP8: =VLOOKUP($E8,'Capgemini PResence and HC'!$B$2:$G$143,3,0) -> 0 | AQ8: =VLOOKUP($E8,'Capgemini PResence and HC'!$B$2:$G$143,6,0) -> 0 | BB8: =SUM(AE8:AG8)-AH8 -> 0
A9: Mainframe | B9: Yes | E9: 9802 | F9: LC Corresponding MF-JPN | G9: LifeComm Corresponding | H9: A subsystem based on LifeComm (mainframe package). As a business domain, it is responsible for guidance (form creation). While we maintain the features built with assembler, our company's main features are developed in COBOL, and except for table modifications, we are not continuously developing assemblers. | I9: contract management | J9: Core Insurance Systems Group 34956 | K9: Policy Admin Systems Team 34957 | L9: MetLife IT Hosted/Supported | M9: Core Business Application | N9: Production | O9: AD Supported | P9: Y | Q9: Global Technology & Operations | R9: No | S9: Yes | T9: Other#Mainframe | V9: COBOL, Assembler, MU(EASYPLUS), JCL | W9: MetLife Owned Application Code | Y9: No | Z9: Y | AA9: Y | AB9: Y | AC9: N | AD9: N | AE9: 15.953625 | AF9: 1.6541667 | AG9: 0 | AH9: 17.607792 | AI9: 0.98287217 | AJ9: 8.8038958 | AK9: 8.8038958 | AM9: =AH9*(1-AI9) -> 0.30158333 | AN9: =VLOOKUP($E9,'Capgemini PResence and HC'!$B$2:$G$143,4,0) -> N | AO9: =VLOOKUP($E9,'Capgemini PResence and HC'!$B$2:$G$143,2,0) -> 0 | AP9: =VLOOKUP($E9,'Capgemini PResence and HC'!$B$2:$G$143,3,0) -> 0 | AQ9: =VLOOKUP($E9,'Capgemini PResence and HC'!$B$2:$G$143,6,0) -> 0 | BB9: =SUM(AE9:AG9)-AH9 -> 0
A10: Mainframe | B10: Yes | E10: 9803 | F10: LC UWI MF-JPN | G10: LifeComm UWI | H10: A subsystem based on LifeComm (mainframe package). As a business domain, it handles part of new contracts and contract maintenance (such as price reductions). Some contract preservation functions utilize new contract features, resulting in overlap between EAI:9796 and business domains. We continue to utilize the functions built with assemblers, continuously developing assemblers for new product development, other development projects, and maintenance projects. | I10: contract management | J10: Core Insurance Systems Group 34956 | K10: Policy Admin Systems Team 34957 | L10: MetLife IT Hosted/Supported | M10: Core Business Application | N10: Production | O10: AD Supported | P10: Y | Q10: Global Technology & Operations | R10: No | S10: Yes | T10: Other#Mainframe | V10: Assembler, COBOL, MU(EASYPLUS), JCL | W10: MetLife Owned Application Code | Y10: No | Z10: Y | AA10: Y | AB10: Y | AC10: N | AD10: N | AE10: 8.8045833 | AF10: 0.85 | AG10: 0 | AH10: 9.6545833 | AI10: 0.94821113 | AJ10: 4.8272917 | AK10: 4.8272917 | AM10: =AH10*(1-AI10) -> 0.5 | AN10: =VLOOKUP($E10,'Capgemini PResence and HC'!$B$2:$G$143,4,0) -> N | AO10: =VLOOKUP($E10,'Capgemini PResence and HC'!$B$2:$G$143,2,0) -> 0 | AP10: =VLOOKUP($E10,'Capgemini PResence and HC'!$B$2:$G$143,3,0) -> 0 | AQ10: =VLOOKUP($E10,'Capgemini PResence and HC'!$B$2:$G$143,6,0) -> 0 | BB10: =SUM(AE10:AG10)-AH10 -> 0
A11: Mainframe | B11: Yes | E11: 9804 | F11: LC AAPerf MF-JPN | G11: LifeComm AgentAgencyPerformance | H11: A subsystem based on LifeComm (mainframe package). As a business domain, it is responsible for performance (number of new contract ANPs, number of held ANPs, retention rate, etc.). While we maintain the features built with assembler, our company's main features are developed in COBOL, and except for table modifications, we are not continuously developing assemblers. | I11: contract management | J11: Core Insurance Systems Group 34956 | K11: Policy Admin Systems Team 34957 | L11: MetLife IT Hosted/Supported | M11: Core Business Application | N11: Production | O11: AD Supported | P11: Y | Q11: Asia Region | R11: No | S11: Yes | T11: Other#Mainframe | V11: COBOL, Assembler, MU(EASYPLUS), JCL | W11: MetLife Owned Application Code | Y11: No | Z11: Y | AA11: Y | AB11: Y | AC11: N | AD11: N | AE11: 10.784167 | AF11: 0.74583333 | AG11: 0 | AH11: 11.53 | AI11: 0.83304423 | AJ11: 5.765 | AK11: 5.765 | AM11: =AH11*(1-AI11) -> 1.925 | AN11: =VLOOKUP($E11,'Capgemini PResence and HC'!$B$2:$G$143,4,0) -> N | AO11: =VLOOKUP($E11,'Capgemini PResence and HC'!$B$2:$G$143,2,0) -> 0 | AP11: =VLOOKUP($E11,'Capgemini PResence and HC'!$B$2:$G$143,3,0) -> 0 | AQ11: =VLOOKUP($E11,'Capgemini PResence and HC'!$B$2:$G$143,6,0) -> 0 | BB11: =SUM(AE11:AG11)-AH11 -> 0
A12: Mainframe | B12: Yes | E12: 9805 | F12: LC Payment MF-JPN | G12: LifeComm Payment | H12: A subsystem based on LifeComm (mainframe package). As a business domain, it handles payments. While we maintain the features built with assembler, our company's main features are developed in COBOL, and except for table modifications, we are not continuously developing assemblers. | I12: contract management | J12: Core Insurance Systems Group 34956 | K12: Policy Admin Systems Team 34957 | L12: MetLife IT Hosted/Supported | M12: Core Business Application | N12: Production | O12: AD Supported | P12: Y | Q12: Global Technology & Operations | R12: No | S12: Yes | T12: Other#Mainframe | V12: COBOL, Assembler, MU(EASYPLUS), JCL | W12: MetLife Owned Application Code | Y12: No | Z12: Y | AA12: Y | AB12: Y | AC12: N | AD12: N | AE12: 2.8966667 | AF12: 0.025 | AG12: 0 | AH12: 2.9216667 | AI12: 0.90587564 | AJ12: 1.4608333 | AK12: 1.4608333 | AM12: =AH12*(1-AI12) -> 0.275 | AN12: =VLOOKUP($E12,'Capgemini PResence and HC'!$B$2:$G$143,4,0) -> N | AO12: =VLOOKUP($E12,'Capgemini PResence and HC'!$B$2:$G$143,2,0) -> 0 | AP12: =VLOOKUP($E12,'Capgemini PResence and HC'!$B$2:$G$143,3,0) -> 0 | AQ12: =VLOOKUP($E12,'Capgemini PResence and HC'!$B$2:$G$143,6,0) -> 0 | BB12: =SUM(AE12:AG12)-AH12 -> 0
A13: Mainframe | B13: Yes | E13: 9806 | F13: LC GL/SC MF-JPN | G13: LifeComm GL/SC | H13: A subsystem based on LifeComm (mainframe package). As a business domain, it is responsible for accounting. While we maintain the features built with assembler, our company's main features are developed in COBOL, and except for table modifications, we are not continuously developing assemblers. | I13: contract management | J13: Core Insurance Systems Group 34956 | K13: Policy Admin Systems Team 34957 | L13: MetLife IT Hosted/Supported | M13: Core Business Application | N13: Production | O13: AD Supported | P13: Y | Q13: Financial Management Group | R13: No | S13: Yes | T13: Other#Mainframe | V13: COBOL, Assembler, MU(EASYPLUS), JCL | W13: MetLife Owned Application Code | Y13: No | Z13: Y | AA13: Y | AB13: Y | AC13: N | AD13: N | AE13: 5.28875 | AF13: 1.025 | AG13: 0 | AH13: 6.31375 | AI13: 0.83765591 | AJ13: 3.156875 | AK13: 3.156875 | AM13: =AH13*(1-AI13) -> 1.025 | AN13: =VLOOKUP($E13,'Capgemini PResence and HC'!$B$2:$G$143,4,0) -> N | AO13: =VLOOKUP($E13,'Capgemini PResence and HC'!$B$2:$G$143,2,0) -> 0 | AP13: =VLOOKUP($E13,'Capgemini PResence and HC'!$B$2:$G$143,3,0) -> 0 | AQ13: =VLOOKUP($E13,'Capgemini PResence and HC'!$B$2:$G$143,6,0) -> 0 | BB13: =SUM(AE13:AG13)-AH13 -> 0
A14: Mainframe | B14: Yes | E14: 9807 | F14: LC Valuation MF-JPN | G14: LifeComm Valuation | H14: A subsystem based on LifeComm (mainframe package). As a business domain, it handles asset management (not real estate, but calculating the asset value of our insurance contracts). While we maintain the features built with assembler, our company's main features are developed in COBOL, and except for table modifications, we are not continuously developing assemblers. | I14: contract management | J14: Core Insurance Systems Group 34956 | K14: Policy Admin Systems Team 34957 | L14: MetLife IT Hosted/Supported | M14: Core Business Application | N14: Production | O14: AD Supported | P14: N | Q14: Financial Management Group | R14: No | S14: Yes | T14: Other#Mainframe | V14: COBOL, Assembler, MU(EASYPLUS), JCL | W14: MetLife Owned Application Code | Y14: No | Z14: Y | AA14: Y | AB14: Y | AC14: N | AD14: N | AE14: 9.76875 | AF14: 1.4833333 | AG14: 0 | AH14: 11.252083 | AI14: 0.8563229 | AJ14: 5.6260417 | AK14: 5.6260417 | AM14: =AH14*(1-AI14) -> 1.6166667 | AN14: =VLOOKUP($E14,'Capgemini PResence and HC'!$B$2:$G$143,4,0) -> N | AO14: =VLOOKUP($E14,'Capgemini PResence and HC'!$B$2:$G$143,2,0) -> 0 | AP14: =VLOOKUP($E14,'Capgemini PResence and HC'!$B$2:$G$143,3,0) -> 0 | AQ14: =VLOOKUP($E14,'Capgemini PResence and HC'!$B$2:$G$143,6,0) -> 0 | BB14: =SUM(AE14:AG14)-AH14 -> 0
A15: Mainframe | B15: Yes | E15: 9808 | F15: LC AACOMP MF-JPN | G15: LifeComm AgentAgencyComp | H15: A subsystem based on LifeComm (mainframe package). As a business domain, it handles fees (such as recruiter management, sales staff fees, agency fees, etc.). While we maintain the features built with assembler, our company's main features are developed in COBOL, and except for table modifications, we are not continuously developing assemblers. | I15: contract management | J15: Core Insurance Systems Group 34956 | K15: Policy Admin Systems Team 34957 | L15: MetLife IT Hosted/Supported | M15: Core Business Application | N15: Production | O15: AD Supported | P15: Y | Q15: Asia Region | R15: No | S15: Yes | T15: Other#Mainframe | V15: COBOL, Assembler, MU(EASYPLUS), JCL | W15: MetLife Owned Application Code | Y15: No | Z15: Y | AA15: Y | AB15: Y | AC15: N | AD15: N | AE15: 13.545708 | AF15: 3.14375 | AG15: 0 | AH15: 16.689458 | AI15: 0.72662384 | AJ15: 8.3447292 | AK15: 8.3447292 | AM15: =AH15*(1-AI15) -> 4.5625 | AN15: =VLOOKUP($E15,'Capgemini PResence and HC'!$B$2:$G$143,4,0) -> N | AO15: =VLOOKUP($E15,'Capgemini PResence and HC'!$B$2:$G$143,2,0) -> 0 | AP15: =VLOOKUP($E15,'Capgemini PResence and HC'!$B$2:$G$143,3,0) -> 0 | AQ15: =VLOOKUP($E15,'Capgemini PResence and HC'!$B$2:$G$143,6,0) -> 0 | BB15: =SUM(AE15:AG15)-AH15 -> 0
A16: Mainframe | B16: Yes | E16: 9810 | F16: Processor-I MF-JPN | G16: Claim payment (Processor-I) | H16: A subsystem based on a different package from LifeComm (mainframe package). As a business domain, it is responsible for payment of benefits and insurance claims. It is basically built with COBOL, and except for the LIFECOMM integration part, almost no assembler is used. | I16: contract management | J16: Core Insurance Systems Group 34956 | K16: Policy Admin Systems Team 34957 | L16: MetLife IT Hosted/Supported | M16: Core Business Application | N16: Production | O16: AD Supported | P16: Y | Q16: Global Technology & Operations | R16: No | S16: Yes | T16: Other#Mainframe | V16: COBOL, MU(EASYPLUS), Assembler, JCL | W16: MetLife Owned Application Code | Y16: No | Z16: Y | AA16: Y | AB16: Y | AC16: N | AD16: N | AE16: 7.6683333 | AF16: 1.1291667 | AG16: 0 | AH16: 8.7975 | AI16: 0.75561239 | AJ16: 4.39875 | AK16: 4.39875 | AM16: =AH16*(1-AI16) -> 2.15 | AN16: =VLOOKUP($E16,'Capgemini PResence and HC'!$B$2:$G$143,4,0) -> N | AO16: =VLOOKUP($E16,'Capgemini PResence and HC'!$B$2:$G$143,2,0) -> 0 | AP16: =VLOOKUP($E16,'Capgemini PResence and HC'!$B$2:$G$143,3,0) -> 0 | AQ16: =VLOOKUP($E16,'Capgemini PResence and HC'!$B$2:$G$143,6,0) -> 0 | BB16: =SUM(AE16:AG16)-AH16 -> 0
A17: Mainframe | B17: Yes | E17: 9811 | F17: LC Submit MF-JPN | G17: Submit Online | H17: A subsystem developed in-house. As a business domain, it provides daily performance updates. It is basically built with COBOL, and except for the LIFECOMM integration part, almost no assembler is used. | I17: contract management | J17: Core Insurance Systems Group 34956 | K17: Policy Admin Systems Team 34957 | L17: MetLife IT Hosted/Supported | M17: Core Business Application | N17: Production | O17: AD Supported | P17: Y | Q17: Asia Region | R17: No | S17: Yes | T17: Other#Mainframe | V17: COBOL, MU(EASYPLUS), Assembler, JCL | W17: MetLife Owned Application Code | Y17: No | Z17: Y | AA17: Y | AB17: Y | AC17: N | AD17: N | AE17: 1.9683333 | AF17: 0.16458333 | AG17: 0 | AH17: 2.1329167 | AI17: 0.95311584 | AJ17: 1.0664583 | AK17: 1.0664583 | AM17: =AH17*(1-AI17) -> 0.1 | AN17: =VLOOKUP($E17,'Capgemini PResence and HC'!$B$2:$G$143,4,0) -> N | AO17: =VLOOKUP($E17,'Capgemini PResence and HC'!$B$2:$G$143,2,0) -> 0 | AP17: =VLOOKUP($E17,'Capgemini PResence and HC'!$B$2:$G$143,3,0) -> 0 | AQ17: =VLOOKUP($E17,'Capgemini PResence and HC'!$B$2:$G$143,6,0) -> 0 | BB17: =SUM(AE17:AG17)-AH17 -> 0
A18: Mainframe | B18: Yes | E18: 9813 | F18: LC Micro MF-JPN | G18: Micro-Index | H18: A subsystem developed in-house. It is a collection of numerous detailed functions. It is basically built with COBOL, and except for the LIFECOMM integration part, almost no assembler is used. | I18: contract management | J18: Core Insurance Systems Group 34956 | K18: Policy Admin Systems Team 34957 | L18: MetLife IT Hosted/Supported | M18: Core Business Application | N18: Production | O18: AD Supported | P18: Y | Q18: Asia Region | R18: No | S18: Yes | T18: Other#Mainframe | V18: COBOL, MU(EASYPLUS), Assembler, JCL | W18: MetLife Owned Application Code | Y18: No | Z18: Y | AA18: Y | AB18: Y | AC18: N | AD18: N | AE18: 2.1175 | AF18: 0 | AG18: 0 | AH18: 2.1175 | AI18: 0.64580874 | AJ18: 1.05875 | AK18: 1.05875 | AM18: =AH18*(1-AI18) -> 0.75 | AN18: =VLOOKUP($E18,'Capgemini PResence and HC'!$B$2:$G$143,4,0) -> N | AO18: =VLOOKUP($E18,'Capgemini PResence and HC'!$B$2:$G$143,2,0) -> 0 | AP18: =VLOOKUP($E18,'Capgemini PResence and HC'!$B$2:$G$143,3,0) -> 0 | AQ18: =VLOOKUP($E18,'Capgemini PResence and HC'!$B$2:$G$143,6,0) -> 0 | BB18: =SUM(AE18:AG18)-AH18 -> 0
A19: Mainframe | B19: Yes | E19: 9814 | F19: Foreign MF-JPN | G19: Foreign | H19: A subsystem developed in-house. Responsible for managing foreign contracts. It is basically built with COBOL, and except for the LIFECOMM integration part, almost no assembler is used. | I19: contract management | J19: Core Insurance Systems Group 34956 | K19: Policy Admin Systems Team 34957 | L19: MetLife IT Hosted/Supported | M19: Core Business Application | N19: Production | O19: AD Supported | P19: N | Q19: Global Technology & Operations | R19: No | S19: Yes | T19: Other#Mainframe | V19: COBOL, MU(EASYPLUS), Assembler, JCL | W19: MetLife Owned Application Code | Y19: No | Z19: Y | AA19: Y | AB19: Y | AC19: N | AD19: N | AL19: The number of personnel is included in the 9813 | AM19: =AH19*(1-AI19) -> 0 | AN19: =VLOOKUP($E19,'Capgemini PResence and HC'!$B$2:$G$143,4,0) -> N | AO19: =VLOOKUP($E19,'Capgemini PResence and HC'!$B$2:$G$143,2,0) -> 0 | AP19: =VLOOKUP($E19,'Capgemini PResence and HC'!$B$2:$G$143,3,0) -> 0 | AQ19: =VLOOKUP($E19,'Capgemini PResence and HC'!$B$2:$G$143,6,0) -> 0 | BB19: =SUM(AE19:AG19)-AH19 -> 0
A20: Mainframe | B20: Yes | E20: 9816 | F20: CT Salary MF-JPN | G20: CT Salary System | H20: A subsystem developed in-house. As a business domain, it manages the salaries of our sales staff. However, since salaries based on performance are calculated using EAI:9808, only certain items such as base salary and deductions are covered. It is basically built with COBOL, and except for the LIFECOMM integration part, almost no assembler is used. | I20: contract management | J20: Core Insurance Systems Group 34956 | K20: Policy Admin Systems Team 34957 | L20: MetLife IT Hosted/Supported | M20: Core Business Application | N20: Production | O20: AD Supported | P20: Y | Q20: Asia Region | R20: No | S20: Yes | T20: Other#Mainframe | V20: COBOL, MU(EASYPLUS), Assembler, JCL | W20: MetLife Owned Application Code | Y20: No | Z20: Y | AA20: Y | AB20: Y | AC20: N | AD20: N | AE20: 0.2 | AF20: 0 | AG20: 0 | AH20: 0.2 | AI20: 0 | AJ20: 0.1 | AK20: 0.1 | AM20: =AH20*(1-AI20) -> 0.2 | AN20: =VLOOKUP($E20,'Capgemini PResence and HC'!$B$2:$G$143,4,0) -> N | AO20: =VLOOKUP($E20,'Capgemini PResence and HC'!$B$2:$G$143,2,0) -> 0 | AP20: =VLOOKUP($E20,'Capgemini PResence and HC'!$B$2:$G$143,3,0) -> 0 | AQ20: =VLOOKUP($E20,'Capgemini PResence and HC'!$B$2:$G$143,6,0) -> 0 | BB20: =SUM(AE20:AG20)-AH20 -> 0
A21: Mainframe | B21: Yes | E21: 9817 | F21: TaxCertification MF-JPN | G21: TaxCertification | H21: A subsystem developed in-house. As a business domain, it serves as proof of deductions. It is basically built with COBOL, and except for the LIFECOMM integration part, almost no assembler is used. | I21: contract management | J21: Core Insurance Systems Group 34956 | K21: Policy Admin Systems Team 34957 | L21: MetLife IT Hosted/Supported | M21: Core Business Application | N21: Production | O21: AD Supported | P21: N | Q21: Global Technology & Operations | R21: No | S21: Yes | T21: Other#Mainframe | V21: COBOL, MU(EASYPLUS), Assembler, JCL | W21: MetLife Owned Application Code | Y21: No | Z21: Y | AA21: Y | AB21: Y | AC21: N | AD21: N | AE21: 1.664875 | AF21: 0 | AG21: 0 | AH21: 1.664875 | AI21: 0.40748805 | AJ21: 0.8324375 | AK21: 0.8324375 | AM21: =AH21*(1-AI21) -> 0.98645833 | AN21: =VLOOKUP($E21,'Capgemini PResence and HC'!$B$2:$G$143,4,0) -> N | AO21: =VLOOKUP($E21,'Capgemini PResence and HC'!$B$2:$G$143,2,0) -> 0 | AP21: =VLOOKUP($E21,'Capgemini PResence and HC'!$B$2:$G$143,3,0) -> 0 | AQ21: =VLOOKUP($E21,'Capgemini PResence and HC'!$B$2:$G$143,6,0) -> 0 | BB21: =SUM(AE21:AG21)-AH21 -> 0
A22: Mainframe | B22: Yes | E22: 9818 | F22: SWINGMANAGER MF-JPN | G22: SWING MANAGER | H22: A subsystem developed in-house. He is responsible for managing the savings fund of Universal Life. It is managed together with EAI:9796. It is basically built with COBOL, and except for the LIFECOMM integration part, almost no assembler is used. | I22: contract management | J22: Core Insurance Systems Group 34956 | K22: Policy Admin Systems Team 34957 | L22: MetLife IT Hosted/Supported | M22: Core Business Application | N22: Production | O22: AD Supported | P22: N | Q22: Global Technology & Operations | R22: No | S22: Yes | T22: Other#Mainframe | V22: COBOL, MU(EASYPLUS), Assembler, JCL | W22: MetLife Owned Application Code | Y22: No | Z22: Y | AA22: Y | AB22: Y | AC22: N | AD22: N | AL22: The number of personnel is included in 9796. | AM22: =AH22*(1-AI22) -> 0 | AN22: =VLOOKUP($E22,'Capgemini PResence and HC'!$B$2:$G$143,4,0) -> N | AO22: =VLOOKUP($E22,'Capgemini PResence and HC'!$B$2:$G$143,2,0) -> 0 | AP22: =VLOOKUP($E22,'Capgemini PResence and HC'!$B$2:$G$143,3,0) -> 0 | AQ22: =VLOOKUP($E22,'Capgemini PResence and HC'!$B$2:$G$143,6,0) -> 0 | BB22: =SUM(AE22:AG22)-AH22 -> 0
A23: Mainframe | B23: Yes | E23: 9819 | F23: PremCollectDBMF-JPN | G23: Premium Collection History DB | H23: A subsystem developed in-house. It is responsible for the deposit history function. It is managed together with EAI:9796. It is basically built with COBOL, and except for the LIFECOMM integration part, almost no assembler is used. | I23: contract management | J23: Core Insurance Systems Group 34956 | K23: Policy Admin Systems Team 34957 | L23: MetLife IT Hosted/Supported | M23: Core Business Application | N23: Production | O23: AD Supported | P23: N | Q23: Global Technology & Operations | R23: No | S23: Yes | T23: Other#Mainframe | V23: COBOL, MU(EASYPLUS), Assembler, JCL | W23: MetLife Owned Application Code | Y23: No | Z23: Y | AA23: Y | AB23: Y | AC23: N | AD23: N | AL23: The number of personnel is included in 9796. | AM23: =AH23*(1-AI23) -> 0 | AN23: =VLOOKUP($E23,'Capgemini PResence and HC'!$B$2:$G$143,4,0) -> N | AO23: =VLOOKUP($E23,'Capgemini PResence and HC'!$B$2:$G$143,2,0) -> 0 | AP23: =VLOOKUP($E23,'Capgemini PResence and HC'!$B$2:$G$143,3,0) -> 0 | AQ23: =VLOOKUP($E23,'Capgemini PResence and HC'!$B$2:$G$143,6,0) -> 0 | BB23: =SUM(AE23:AG23)-AH23 -> 0
A24: Mainframe | B24: Yes | E24: 9820 | F24: MCFA CP DB MF-JPN | G24: MCFA Coupon DB | H24: A subsystem developed in-house. It serves as the fixed withdrawal function for MCFA (pension insurance). It is managed together with EAI:9796. It is basically built with COBOL, and except for the LIFECOMM integration part, almost no assembler is used. | I24: contract management | J24: Core Insurance Systems Group 34956 | K24: Policy Admin Systems Team 34957 | L24: MetLife IT Hosted/Supported | M24: Core Business Application | N24: Production | O24: AD Supported | P24: Y | Q24: Global Technology & Operations | R24: No | S24: Yes | T24: Other#Mainframe | V24: COBOL, MU(EASYPLUS), Assembler, JCL | W24: MetLife Owned Application Code | Y24: No | Z24: Y | AA24: Y | AB24: Y | AC24: N | AD24: N | AL24: The number of personnel is included in 9796. | AM24: =AH24*(1-AI24) -> 0 | AN24: =VLOOKUP($E24,'Capgemini PResence and HC'!$B$2:$G$143,4,0) -> N | AO24: =VLOOKUP($E24,'Capgemini PResence and HC'!$B$2:$G$143,2,0) -> 0 | AP24: =VLOOKUP($E24,'Capgemini PResence and HC'!$B$2:$G$143,3,0) -> 0 | AQ24: =VLOOKUP($E24,'Capgemini PResence and HC'!$B$2:$G$143,6,0) -> 0 | BB24: =SUM(AE24:AG24)-AH24 -> 0
A25: Mainframe | B25: Yes | E25: 9821 | F25: Maturity MF-JPN | G25: Payment maturity existing benefit etc | H25: A subsystem developed in-house. As a business domain, it serves as maturity. It is basically built with COBOL, and except for the LIFECOMM integration part, almost no assembler is used. | I25: contract management | J25: Core Insurance Systems Group 34956 | K25: Policy Admin Systems Team 34957 | L25: MetLife IT Hosted/Supported | M25: Core Business Application | N25: Production | O25: AD Supported | P25: Y | Q25: Global Technology & Operations | R25: No | S25: Yes | T25: Other#Mainframe | V25: COBOL, MU(EASYPLUS), Assembler, JCL | W25: MetLife Owned Application Code | Y25: No | Z25: Y | AA25: Y | AB25: Y | AC25: N | AD25: N | AE25: 4.3783333 | AF25: 0.97083333 | AG25: 0 | AH25: 5.3491667 | AI25: 0.62610999 | AJ25: 2.6745833 | AK25: 2.6745833 | AM25: =AH25*(1-AI25) -> 2 | AN25: =VLOOKUP($E25,'Capgemini PResence and HC'!$B$2:$G$143,4,0) -> N | AO25: =VLOOKUP($E25,'Capgemini PResence and HC'!$B$2:$G$143,2,0) -> 0 | AP25: =VLOOKUP($E25,'Capgemini PResence and HC'!$B$2:$G$143,3,0) -> 0 | AQ25: =VLOOKUP($E25,'Capgemini PResence and HC'!$B$2:$G$143,6,0) -> 0 | BB25: =SUM(AE25:AG25)-AH25 -> 0
A26: Mainframe | B26: Yes | E26: 9822 | F26: LC Reins MF-JPN | G26: Reinsurance | H26: A subsystem developed in-house. As a business domain, it handles reinsurance. It is basically built with COBOL, and except for the LIFECOMM integration part, almost no assembler is used. | I26: contract management | J26: Core Insurance Systems Group 34956 | K26: Policy Admin Systems Team 34957 | L26: MetLife IT Hosted/Supported | M26: Core Business Application | N26: Production | O26: AD Supported | P26: N | Q26: Financial Management Group | R26: No | S26: Yes | T26: Other#Mainframe | V26: COBOL, MU(EASYPLUS), Assembler, JCL | W26: MetLife Owned Application Code | Y26: No | Z26: Y | AA26: Y | AB26: Y | AC26: N | AD26: N | AE26: 6.0129167 | AF26: 0.25416667 | AG26: 0 | AH26: 6.2670833 | AI26: 0.78990759 | AJ26: 3.1335417 | AK26: 3.1335417 | AM26: =AH26*(1-AI26) -> 1.3166667 | AN26: =VLOOKUP($E26,'Capgemini PResence and HC'!$B$2:$G$143,4,0) -> N | AO26: =VLOOKUP($E26,'Capgemini PResence and HC'!$B$2:$G$143,2,0) -> 0 | AP26: =VLOOKUP($E26,'Capgemini PResence and HC'!$B$2:$G$143,3,0) -> 0 | AQ26: =VLOOKUP($E26,'Capgemini PResence and HC'!$B$2:$G$143,6,0) -> 0 | BB26: =SUM(AE26:AG26)-AH26 -> 0
A27: Mainframe | B27: Yes | E27: 9823 | F27: ASP Bridge(H) MF-JPN | G27: ASP Bridge (HOST) | H27: A subsystem developed in-house. It handles interfaces (data integration) with EAI:9925 and EAI:12559. It is basically built with COBOL, and except for the LIFECOMM integration part, almost no assembler is used. | I27: contract management | J27: Core Insurance Systems Group 34956 | K27: Policy Admin Systems Team 34957 | L27: MetLife IT Hosted/Supported | M27: Common Service Business Application | N27: Production | O27: AD Supported | P27: Y | Q27: Global Technology & Operations | R27: No | S27: Yes | T27: Other#Mainframe | V27: COBOL, MU(EASYPLUS), Assembler, JCL | W27: MetLife Owned Application Code | Y27: No | Z27: Y | AA27: Y | AB27: Y | AC27: N | AD27: N | AE27: 6.7267083 | AF27: 1.4625 | AG27: 0 | AH27: 8.1892083 | AI27: 0.72808727 | AJ27: 4.0946042 | AK27: 4.0946042 | AM27: =AH27*(1-AI27) -> 2.22675 | AN27: =VLOOKUP($E27,'Capgemini PResence and HC'!$B$2:$G$143,4,0) -> N | AO27: =VLOOKUP($E27,'Capgemini PResence and HC'!$B$2:$G$143,2,0) -> 0 | AP27: =VLOOKUP($E27,'Capgemini PResence and HC'!$B$2:$G$143,3,0) -> 0 | AQ27: =VLOOKUP($E27,'Capgemini PResence and HC'!$B$2:$G$143,6,0) -> 0 | BB27: =SUM(AE27:AG27)-AH27 -> 0
A28: Mainframe | B28: Yes | E28: 9824 | F28: CCA MF-JPN | G28: Client Contract Administration | H28: A subsystem based on a different package from LifeComm (mainframe package). As a business domain, it serves as a customer name impersonation. It is basically built with COBOL, and except for the LIFECOMM integration part, almost no assembler is used. | I28: contract management | J28: Core Insurance Systems Group 34956 | K28: Policy Admin Systems Team 34957 | L28: MetLife IT Hosted/Supported | M28: Core Business Application | N28: Production | O28: AD Supported | P28: Y | Q28: Global Technology & Operations | R28: No | S28: Yes | T28: Other#Mainframe | V28: COBOL, MU(EASYPLUS), Assembler, JCL | W28: MetLife Owned Application Code | Y28: No | Z28: Y | AA28: Y | AB28: Y | AC28: N | AD28: N | AE28: 1.6308333 | AF28: 0 | AG28: 0 | AH28: 1.6308333 | AI28: 0.38681656 | AJ28: 0.81541667 | AK28: 0.81541667 | AM28: =AH28*(1-AI28) -> 1 | AN28: =VLOOKUP($E28,'Capgemini PResence and HC'!$B$2:$G$143,4,0) -> N | AO28: =VLOOKUP($E28,'Capgemini PResence and HC'!$B$2:$G$143,2,0) -> 0 | AP28: =VLOOKUP($E28,'Capgemini PResence and HC'!$B$2:$G$143,3,0) -> 0 | AQ28: =VLOOKUP($E28,'Capgemini PResence and HC'!$B$2:$G$143,6,0) -> 0 | BB28: =SUM(AE28:AG28)-AH28 -> 0
A29: Cloud | B29: Yes | E29: 9833 | F29: C04NWC-JPN | G29: CenterServer | H29: Rule engine for new contract workflows | I29: New Contract Related | J29: Customer Service and Operations Systems Group 34965 | K29: New Business Team 34966 | L29: MetLife IT Hosted/Supported | M29: Core Business Application | N29: Production | O29: AD Supported | P29: N | Q29: Global Technology & Operations | R29: No | S29: Yes | T29: Other#ASP | V29: C/C++ | W29: MetLife Owned Application Code | Y29: No | Z29: Y | AA29: Y | AB29: Y | AC29: N | AD29: N | AE29: 8.7316667 | AF29: 0.11041667 | AG29: 0 | AH29: 8.8420833 | AI29: 0.91687479 | AJ29: 4.4210417 | AK29: 4.4210417 | AM29: =AH29*(1-AI29) -> 0.735 | AN29: =VLOOKUP($E29,'Capgemini PResence and HC'!$B$2:$G$143,4,0) -> Y | AO29: =VLOOKUP($E29,'Capgemini PResence and HC'!$B$2:$G$143,2,0) -> 0 | AP29: =VLOOKUP($E29,'Capgemini PResence and HC'!$B$2:$G$143,3,0) -> 1 | AQ29: =VLOOKUP($E29,'Capgemini PResence and HC'!$B$2:$G$143,6,0) -> 0 | BB29: =SUM(AE29:AG29)-AH29 -> 0
A30: Cloud | B30: Yes | E30: 9834 | F30: C03WRE-JPN | G30: POS Workflow Payment Workflow (Restoring cancelled | H30: Restoring and Cancelled Policy | I30: Storage and Preservation Related | J30: Customer Service and Operations Systems Group 34965 | K30: Policy Servicing Team 34967 | L30: MetLife IT Hosted/Supported | M30: Core Business Application | N30: Production | O30: AD Supported | P30: Y | Q30: Global Technology & Operations | R30: No | S30: Yes | T30: Thick Client | V30: VB.NET | W30: MetLife Owned Application Code | Y30: No | Z30: Y | AA30: Y | AB30: Y | AC30: N | AD30: N | AE30: 0.2 | AF30: 0.2 | AG30: 0 | AH30: 0.37083333 | AI30: 0.3258427 | AJ30: 0.18541667 | AK30: 0.18541667 | AM30: =AH30*(1-AI30) -> 0.25 | AN30: =VLOOKUP($E30,'Capgemini PResence and HC'!$B$2:$G$143,4,0) -> N | AO30: =VLOOKUP($E30,'Capgemini PResence and HC'!$B$2:$G$143,2,0) -> 0 | AP30: =VLOOKUP($E30,'Capgemini PResence and HC'!$B$2:$G$143,3,0) -> 0 | AQ30: =VLOOKUP($E30,'Capgemini PResence and HC'!$B$2:$G$143,6,0) -> 0 | BB30: =SUM(AE30:AG30)-AH30 -> 0.029166667
A31: Cloud | B31: Yes | E31: 9835 | F31: C12WNC-JPN | G31: POS Workflow Payment Workflow (Claim Transaction A | H31: Claim Transaction Automatic Development of Benefit | I31: Insurance Claims and Benefits Payment Related | J31: Customer Service and Operations Systems Group 34965 | K31: Claims Team 34968 | L31: MetLife IT Hosted/Supported | M31: Core Business Application | N31: Production | O31: AD Supported | P31: Y | Q31: Global Technology & Operations | R31: No | S31: Yes | T31: Thick Client | V31: VB.NET; C/C++; JAVA | W31: MetLife Owned Application Code | Y31: No | Z31: Y | AA31: Y | AB31: Y | AC31: N | AD31: N | AE31: 29.379875 | AF31: 5.6166667 | AG31: 0 | AH31: 34.996542 | AI31: 0.90522873 | AJ31: 17.498271 | AK31: 17.498271 | AM31: =AH31*(1-AI31) -> 3.3166667 | AN31: =VLOOKUP($E31,'Capgemini PResence and HC'!$B$2:$G$143,4,0) -> Y | AO31: =VLOOKUP($E31,'Capgemini PResence and HC'!$B$2:$G$143,2,0) -> 0 | AP31: =VLOOKUP($E31,'Capgemini PResence and HC'!$B$2:$G$143,3,0) -> 1 | AQ31: =VLOOKUP($E31,'Capgemini PResence and HC'!$B$2:$G$143,6,0) -> 0 | BB31: =SUM(AE31:AG31)-AH31 -> 0
A32: Cloud | B32: Yes | E32: 9836 | F32: C03WRD-JPN | G32: POS Workflow Payment Workflow (Reduction of paymen | H32: Storage and Maintenance Workflow (Reduction of Payment) | I32: Storage and Preservation Related | J32: Customer Service and Operations Systems Group 34965 | K32: Policy Servicing Team 34967 | L32: MetLife IT Hosted/Supported | M32: Core Business Application | N32: Production | O32: AD Supported | P32: Y | Q32: Global Technology & Operations | R32: No | S32: Yes | T32: Thick Client | V32: VB.NET | W32: MetLife Owned Application Code | Y32: No | Z32: Y | AA32: Y | AB32: Y | AC32: N | AD32: N | AE32: 0.3 | AF32: 0.3 | AG32: 0 | AH32: 2.5258333 | AI32: 0.90102276 | AJ32: 1.2629167 | AK32: 1.2629167 | AM32: =AH32*(1-AI32) -> 0.25 | AN32: =VLOOKUP($E32,'Capgemini PResence and HC'!$B$2:$G$143,4,0) -> Y | AO32: =VLOOKUP($E32,'Capgemini PResence and HC'!$B$2:$G$143,2,0) -> 0 | AP32: =VLOOKUP($E32,'Capgemini PResence and HC'!$B$2:$G$143,3,0) -> 1 | AQ32: =VLOOKUP($E32,'Capgemini PResence and HC'!$B$2:$G$143,6,0) -> 0 | BB32: =SUM(AE32:AG32)-AH32 -> -1.9258333
A33: Cloud | B33: Yes | E33: 9842 | F33: C03PCA-JPN | G33: Add Coverage | H33: Storage and Preservation Special Contract Mid-Term Additional Processing System | I33: Storage and Preservation Related | J33: Customer Service and Operations Systems Group 34965 | K33: Policy Servicing Team 34967 | L33: MetLife IT Hosted/Supported | M33: Core Business Application | N33: Production | O33: AD Supported | P33: N | Q33: Global Technology & Operations | R33: No | S33: Yes | T33: Other#C/S | V33: VB | W33: MetLife Owned Application Code | Y33: No | Z33: Y | AA33: Y | AB33: Y | AC33: N | AD33: N | AE33: 0.3 | AF33: 0.3 | AG33: 0 | AH33: 2.88625 | AI33: 0.90298831 | AJ33: 1.443125 | AK33: 1.443125 | AM33: =AH33*(1-AI33) -> 0.28 | AN33: =VLOOKUP($E33,'Capgemini PResence and HC'!$B$2:$G$143,4,0) -> Y | AO33: =VLOOKUP($E33,'Capgemini PResence and HC'!$B$2:$G$143,2,0) -> 0 | AP33: =VLOOKUP($E33,'Capgemini PResence and HC'!$B$2:$G$143,3,0) -> 1 | AQ33: =VLOOKUP($E33,'Capgemini PResence and HC'!$B$2:$G$143,6,0) -> 0 | BB33: =SUM(AE33:AG33)-AH33 -> -2.28625
A34: Cloud | B34: Yes | E34: 9843 | F34: C10CSS-JPN | G34: FSC Call Support | H34: Application for call centers for bank tellers (call history/case management) | I34: Customer Care / Call Center Related | J34: Customer Service and Operations Systems Group 34965 | K34: Customer Care Team 34969 | L34: MetLife IT Hosted/Supported | M34: Core Business Application | N34: Production | O34: AD Supported | P34: N | Q34: Global Technology & Operations | R34: No | S34: Yes | T34: Web Application Client | V34: VB.NET | W34: MetLife Owned Application Code | Y34: No | Z34: Y | AA34: Y | AB34: Y | AC34: N | AD34: N | AE34: 1.2120833 | AF34: 0.20833333 | AG34: 0 | AH34: 1.4204167 | AI34: 0.63596363 | AJ34: 0.71020833 | AK34: 0.71020833 | AM34: =AH34*(1-AI34) -> 0.51708333 | AN34: =VLOOKUP($E34,'Capgemini PResence and HC'!$B$2:$G$143,4,0) -> Y | AO34: =VLOOKUP($E34,'Capgemini PResence and HC'!$B$2:$G$143,2,0) -> 0 | AP34: =VLOOKUP($E34,'Capgemini PResence and HC'!$B$2:$G$143,3,0) -> 1 | AQ34: =VLOOKUP($E34,'Capgemini PResence and HC'!$B$2:$G$143,6,0) -> 0 | BB34: =SUM(AE34:AG34)-AH34 -> 0
A35: Cloud | B35: Yes | E35: 11011 | F35: WGLWLF-JPN | G35: Watch List Filtering system | H35: To prevent transactions with antisocial forces, internal customer data screening is conducted. It uses Actimize's package. | I35: Corporate Related | J35: Core Insurance Systems Group 34956 | K35: Corporate Systems Team 34959 | L35: MetLife IT Hosted/Supported | M35: Core Business Application | N35: Production | O35: AD Supported | P35: N | Q35: Global Risk Management | R35: No | S35: Yes | T35: Web Application Client | V35: JAVA | W35: MetLife Owned Application Code | Y35: No | Z35: Y | AA35: Y | AB35: Y | AC35: N | AD35: N | AE35: 6.0791667 | AF35: 1.0708333 | AG35: 0 | AH35: 7.15 | AI35: 0.90384615 | AJ35: 3.575 | AK35: 3.575 | AM35: =AH35*(1-AI35) -> 0.6875 | AN35: =VLOOKUP($E35,'Capgemini PResence and HC'!$B$2:$G$143,4,0) -> N | AO35: =VLOOKUP($E35,'Capgemini PResence and HC'!$B$2:$G$143,2,0) -> 0 | AP35: =VLOOKUP($E35,'Capgemini PResence and HC'!$B$2:$G$143,3,0) -> 0 | AQ35: =VLOOKUP($E35,'Capgemini PResence and HC'!$B$2:$G$143,6,0) -> 0 | AR35: =AH35-AS35 -> 6.4625 | AS35: =AM35 -> 0.6875 | AT35: =#REF!*AT$151 -> #REF! | AU35: =#REF!*AU$151 -> #REF! | AV35: =#REF!*AV$151 -> #REF! | AW35: =#REF!*AW$151 -> #REF! | AX35: =#REF!*AX$151 -> #REF! | AY35: =#REF!*AY$151 -> #REF! | AZ35: =#REF!*AZ$151 -> #REF! | BA35: =#REF!*BA$151 -> #REF! | BB35: =SUM(AE35:AG35)-AH35 -> 0
A36: Cloud | B36: Yes | E36: 9845 | F36: C04SYM-JPN | G36: Renewal symap Business Work Flow | H36: Workflow for Contract Renewal Process | I36: New Contract Related | J36: Customer Service and Operations Systems Group 34965 | K36: New Business Team 34966 | L36: MetLife IT Hosted/Supported | M36: Core Business Application | N36: Production | O36: AD Supported | P36: N | Q36: Global Technology & Operations | R36: No | S36: Yes | T36: Other#Thick Client | V36: VB.NET | W36: MetLife Owned Application Code | Y36: No | Z36: Y | AA36: Y | AB36: Y | AC36: N | AD36: N | AE36: 3.4049167 | AF36: 0 | AG36: 0 | AH36: 3.4049167 | AI36: 0.84091632 | AJ36: 1.7024583 | AK36: 1.7024583 | AM36: =AH36*(1-AI36) -> 0.54166667 | AN36: =VLOOKUP($E36,'Capgemini PResence and HC'!$B$2:$G$143,4,0) -> Y | AO36: =VLOOKUP($E36,'Capgemini PResence and HC'!$B$2:$G$143,2,0) -> 0 | AP36: =VLOOKUP($E36,'Capgemini PResence and HC'!$B$2:$G$143,3,0) -> 1 | AQ36: =VLOOKUP($E36,'Capgemini PResence and HC'!$B$2:$G$143,6,0) -> 0 | BB36: =SUM(AE36:AG36)-AH36 -> 0
A37: Cloud | B37: Yes | E37: 9846 | F37: C03VSV-JPN | G37: Variable Annuity Sun View | H37: Call Center Applications / Call History Management Related to Variable Pensions | I37: Customer Care / Call Center Related | J37: Customer Service and Operations Systems Group 34965 | K37: Customer Care Team 34969 | L37: MetLife IT Hosted/Supported | M37: Core Business Application | N37: Production | O37: AD Supported | P37: N | Q37: Global Technology & Operations | R37: No | S37: Yes | T37: Other#C/S | V37: VB.NET | W37: MetLife Owned Application Code | Y37: No | Z37: Y | AA37: Y | AB37: Y | AC37: N | AD37: N | AE37: 0.03125 | AF37: 0.4 | AG37: 0 | AH37: 0.43125 | AI37: 0.92753623 | AJ37: 0.215625 | AK37: 0.215625 | AM37: =AH37*(1-AI37) -> 0.03125 | AN37: =VLOOKUP($E37,'Capgemini PResence and HC'!$B$2:$G$143,4,0) -> Y | AO37: =VLOOKUP($E37,'Capgemini PResence and HC'!$B$2:$G$143,2,0) -> 0 | AP37: =VLOOKUP($E37,'Capgemini PResence and HC'!$B$2:$G$143,3,0) -> 1 | AQ37: =VLOOKUP($E37,'Capgemini PResence and HC'!$B$2:$G$143,6,0) -> 0 | BB37: =SUM(AE37:AG37)-AH37 -> 0
A38: Cloud | B38: Yes | E38: 9847 | F38: PinID tool_JPN | G38: PinID Increase tool | H38: EAI: A subsystem for managing PinID, a unique customer management number for 9925. Currently, it is built with .NET but is under development for migration to web applications. | I38: contract management | J38: Core Insurance Systems Group 34956 | K38: Policy Admin Systems Team 34957 | L38: MetLife IT Hosted/Supported | M38: Core Business Application | N38: Production | O38: AD Supported | P38: N | Q38: Global Technology & Operations | R38: No | S38: Yes | T38: Other#C/S | V38: VB.NET | W38: MetLife Owned Application Code | Y38: No | Z38: Y | AA38: Y | AB38: Y | AC38: N | AD38: N | AE38: 0.152625 | AF38: 0.3 | AG38: 0 | AH38: 0.452625 | AI38: 1 | AJ38: 0.2263125 | AK38: 0.2263125 | AM38: =AH38*(1-AI38) -> 0 | AN38: =VLOOKUP($E38,'Capgemini PResence and HC'!$B$2:$G$143,4,0) -> N | AO38: =VLOOKUP($E38,'Capgemini PResence and HC'!$B$2:$G$143,2,0) -> 0 | AP38: =VLOOKUP($E38,'Capgemini PResence and HC'!$B$2:$G$143,3,0) -> 0 | AQ38: =VLOOKUP($E38,'Capgemini PResence and HC'!$B$2:$G$143,6,0) -> 0 | BB38: =SUM(AE38:AG38)-AH38 -> 0
A39: Cloud | B39: Yes | E39: 9848 | F39: C11VCM-JPN | G39: Deposit Control System | H39: New Contract Related/Deposit Management System | I39: New Contract Related | J39: Customer Service and Operations Systems Group 34965 | K39: New Business Team 34966 | L39: MetLife IT Hosted/Supported | M39: Core Business Application | N39: Production | O39: AD Supported | P39: N | Q39: Global Technology & Operations | R39: No | S39: Yes | T39: Web Application Client | V39: VB.NET | W39: MetLife Owned Application Code | Y39: No | Z39: Y | AA39: Y | AB39: Y | AC39: N | AD39: N | AE39: 0.88541667 | AF39: 0 | AG39: 0 | AH39: 0.88541667 | AI39: 0.83058824 | AJ39: 0.44270833 | AK39: 0.44270833 | AM39: =AH39*(1-AI39) -> 0.15 | AN39: =VLOOKUP($E39,'Capgemini PResence and HC'!$B$2:$G$143,4,0) -> Y | AO39: =VLOOKUP($E39,'Capgemini PResence and HC'!$B$2:$G$143,2,0) -> 0 | AP39: =VLOOKUP($E39,'Capgemini PResence and HC'!$B$2:$G$143,3,0) -> 1 | AQ39: =VLOOKUP($E39,'Capgemini PResence and HC'!$B$2:$G$143,6,0) -> 0 | BB39: =SUM(AE39:AG39)-AH39 -> 0
A40: Cloud | B40: Yes | E40: 9849 | F40: C04OSI-JPN | G40: S Sum Total System(Open) | H40: New Contract Related/Comprehensive Management System | I40: New Contract Related | J40: Customer Service and Operations Systems Group 34965 | K40: New Business Team 34966 | L40: MetLife IT Hosted/Supported | M40: Common Service Business Application | N40: Production | O40: AD Supported | P40: N | Q40: Global Technology & Operations | R40: No | S40: Yes | T40: Web Application Client | V40: JAVA | W40: MetLife Owned Application Code | Y40: No | Z40: Y | AA40: Y | AB40: Y | AC40: N | AD40: N | AE40: 5.18625 | AF40: 0.38333333 | AG40: 0 | AH40: 5.5695833 | AI40: 0.8315254 | AJ40: 2.7847917 | AK40: 2.7847917 | AM40: =AH40*(1-AI40) -> 0.93833333 | AN40: =VLOOKUP($E40,'Capgemini PResence and HC'!$B$2:$G$143,4,0) -> Y | AO40: =VLOOKUP($E40,'Capgemini PResence and HC'!$B$2:$G$143,2,0) -> 0 | AP40: =VLOOKUP($E40,'Capgemini PResence and HC'!$B$2:$G$143,3,0) -> 1 | AQ40: =VLOOKUP($E40,'Capgemini PResence and HC'!$B$2:$G$143,6,0) -> 0 | BB40: =SUM(AE40:AG40)-AH40 -> 0
A41: Cloud | B41: Yes | E41: 13812 | F41: Corporate Batch | G41: OpenBatch system for Corporate | H41: EAI gathered batch processing when rebuilding the Infostation app into AppsPortal. It has the following features Automated email distribution, CRSDB, GIM/DOM, MetLifeSFTP, NVES | I41: Corporate Related | J41: Core Insurance Systems Group 34956 | K41: Corporate Systems Team 34959 | L41: MetLife IT Hosted/Supported | M41: Core Business Application | N41: Production | O41: AD Supported | P41: N | Q41: Global Technology & Operations | R41: No | S41: Yes | T41: Other#Batch | V41: VB.NET | W41: MetLife Owned Application Code | Y41: No | Z41: Y | AA41: Y | AB41: Y | AC41: N | AD41: N | AE41: 2.04 | AF41: 1.7 | AG41: 0 | AH41: 3.74 | AI41: 0.3083779 | AJ41: 1.87 | AK41: 1.87 | AM41: =AH41*(1-AI41) -> 2.5866667 | AN41: =VLOOKUP($E41,'Capgemini PResence and HC'!$B$2:$G$143,4,0) -> N | AO41: =VLOOKUP($E41,'Capgemini PResence and HC'!$B$2:$G$143,2,0) -> 0 | AP41: =VLOOKUP($E41,'Capgemini PResence and HC'!$B$2:$G$143,3,0) -> 0 | AQ41: =VLOOKUP($E41,'Capgemini PResence and HC'!$B$2:$G$143,6,0) -> 0 | AR41: =AH41-AS41 -> 1.1533333 | AS41: =AM41 -> 2.5866667 | AT41: =#REF!*AT$151 -> #REF! | AU41: =#REF!*AU$151 -> #REF! | AV41: =#REF!*AV$151 -> #REF! | AW41: =#REF!*AW$151 -> #REF! | AX41: =#REF!*AX$151 -> #REF! | AY41: =#REF!*AY$151 -> #REF! | AZ41: =#REF!*AZ$151 -> #REF! | BA41: =#REF!*BA$151 -> #REF! | BB41: =SUM(AE41:AG41)-AH41 -> 0
A42: Cloud | B42: Yes | E42: 9964 | F42: WAANSO-JPN | G42: New Submit Online System | H42: NSO (Online Screen System) is a web-based enterprise application that supports MetLife Alico's sales and administrative operations. This system provides various functions such as sales activities, business processing, and data management on an online screen, enabling operational efficiency and information integration. | I42: Corporate Related | J42: Core Insurance Systems Group 34956 | K42: Corporate Systems Team 34959 | L42: MetLife IT Hosted/Supported | M42: Core Business Application | N42: Production | O42: AD Supported | P42: N | Q42: Asia Region | R42: No | S42: Yes | T42: Web Services | V42: JAVA | W42: MetLife Owned Application Code | Y42: No | Z42: Y | AA42: Y | AB42: Y | AC42: N | AD42: N | AE42: 1.9533333 | AF42: 0.3625 | AG42: 0 | AH42: 2.3158333 | AI42: 0.90824037 | AJ42: 1.1579167 | AK42: 1.1579167 | AM42: =AH42*(1-AI42) -> 0.2125 | AN42: =VLOOKUP($E42,'Capgemini PResence and HC'!$B$2:$G$143,4,0) -> N | AO42: =VLOOKUP($E42,'Capgemini PResence and HC'!$B$2:$G$143,2,0) -> 0 | AP42: =VLOOKUP($E42,'Capgemini PResence and HC'!$B$2:$G$143,3,0) -> 0 | AQ42: =VLOOKUP($E42,'Capgemini PResence and HC'!$B$2:$G$143,6,0) -> 0 | AR42: =AH42-AS42 -> 2.1033333 | AS42: =AM42 -> 0.2125 | AT42: =#REF!*AT$151 -> #REF! | AU42: =#REF!*AU$151 -> #REF! | AV42: =#REF!*AV$151 -> #REF! | AW42: =#REF!*AW$151 -> #REF! | AX42: =#REF!*AX$151 -> #REF! | AY42: =#REF!*AY$151 -> #REF! | AZ42: =#REF!*AZ$151 -> #REF! | BA42: =#REF!*BA$151 -> #REF! | BB42: =SUM(AE42:AG42)-AH42 -> 0
A43: Cloud | B43: Yes | E43: 9854 | F43: Z04IMA-JPN | G43: Image Search | H43: New Contract Related / Image File Search System | I43: New Contract Related | J43: Customer Service and Operations Systems Group 34965 | K43: New Business Team 34966 | L43: MetLife IT Hosted/Supported | M43: Core Business Application | N43: Production | O43: AD Supported | P43: N | Q43: Global Technology & Operations | R43: No | S43: Yes | T43: Web Application Client | V43: CSS; JAVA;HTML; VB.NET | W43: MetLife Owned Application Code | Y43: No | Z43: Y | AA43: Y | AB43: Y | AC43: N | AD43: N | AE43: 1.4004167 | AF43: 0 | AG43: 0 | AH43: 1.4004167 | AI43: 0.92859268 | AJ43: 0.70020833 | AK43: 0.70020833 | AM43: =AH43*(1-AI43) -> 0.1 | AN43: =VLOOKUP($E43,'Capgemini PResence and HC'!$B$2:$G$143,4,0) -> Y | AO43: =VLOOKUP($E43,'Capgemini PResence and HC'!$B$2:$G$143,2,0) -> 0 | AP43: =VLOOKUP($E43,'Capgemini PResence and HC'!$B$2:$G$143,3,0) -> 1 | AQ43: =VLOOKUP($E43,'Capgemini PResence and HC'!$B$2:$G$143,6,0) -> 0 | BB43: =SUM(AE43:AG43)-AH43 -> 0
A44: Cloud | B44: Yes | E44: 9857 | F44: W05AMS-JPN | G44: Annuity Information Management System(AIMS) | H44: Pension Information Management System | I44: Insurance Claims and Benefits Payment Related | J44: Customer Service and Operations Systems Group 34965 | K44: Claims Team 34968 | L44: MetLife IT Hosted/Supported | M44: Core Business Application | N44: Production | O44: AD Supported | P44: Y | Q44: Global Technology & Operations | R44: No | S44: Yes | T44: Web Services | V44: JAVA | W44: MetLife Owned Application Code | Y44: No | Z44: Y | AA44: Y | AB44: Y | AC44: N | AD44: N | AE44: 20.211667 | AF44: 1.8166667 | AG44: 0 | AH44: 22.028333 | AI44: 0.92547477 | AJ44: 11.014167 | AK44: 11.014167 | AM44: =AH44*(1-AI44) -> 1.6416667 | AN44: =VLOOKUP($E44,'Capgemini PResence and HC'!$B$2:$G$143,4,0) -> Y | AO44: =VLOOKUP($E44,'Capgemini PResence and HC'!$B$2:$G$143,2,0) -> 0 | AP44: =VLOOKUP($E44,'Capgemini PResence and HC'!$B$2:$G$143,3,0) -> 1 | AQ44: =VLOOKUP($E44,'Capgemini PResence and HC'!$B$2:$G$143,6,0) -> 0 | BB44: =SUM(AE44:AG44)-AH44 -> 0
A45: Cloud | B45: Yes | E45: 9858 | F45: W02OPS-JPN | G45: Insurance Planning for Operator | H45: Insurance Planning for Operator / Insurance Design Application for Direct Business | I45: Marketing/Direct Business Related | J45: Customer and Channel Engineering 34961 | L45: MetLife IT Hosted/Supported | M45: Core Business Application | N45: Production | O45: AD Supported | P45: N | Q45: Asia Region | R45: No | S45: Yes | T45: Web Services; Web Application Client | V45: JAVA | W45: MetLife Owned Application Code | Y45: No | Z45: Y | AA45: Y | AB45: Y | AC45: N | AD45: N | AE45: 4.8333333 | AF45: 1 | AG45: 1.0833333 | AH45: 6.9166667 | AI45: 0.71084337 | AJ45: 3.4583333 | AK45: 3.4583333 | AM45: =AH45*(1-AI45) -> 2 | AN45: =VLOOKUP($E45,'Capgemini PResence and HC'!$B$2:$G$143,4,0) -> Y | AO45: =VLOOKUP($E45,'Capgemini PResence and HC'!$B$2:$G$143,2,0) -> 3 | AP45: =VLOOKUP($E45,'Capgemini PResence and HC'!$B$2:$G$143,3,0) -> 0 | AQ45: =VLOOKUP($E45,'Capgemini PResence and HC'!$B$2:$G$143,6,0) -> 2.3625 | BB45: =SUM(AE45:AG45)-AH45 -> 0
A46: Cloud | B46: Yes | E46: 9861 | F46: W04RRE-JPN | G46: Rule Engine | H46: New Contract Related / Rule Engine | I46: New Contract Related | J46: Customer Service and Operations Systems Group 34965 | K46: New Business Team 34966 | L46: MetLife IT Hosted/Supported | M46: Core Business Application | N46: Production | O46: AD Supported | P46: Y | Q46: Global Technology & Operations | R46: No | S46: Yes | T46: Other#Services in Windows Server | V46: JAVA | W46: MetLife Owned Application Code | Y46: No | Z46: Y | AA46: Y | AB46: Y | AC46: N | AD46: N | AE46: 6.3152917 | AF46: 0 | AG46: 0 | AH46: 6.3152917 | AI46: 0.87325737 | AJ46: 3.1576458 | AK46: 3.1576458 | AM46: =AH46*(1-AI46) -> 0.80041667 | AN46: =VLOOKUP($E46,'Capgemini PResence and HC'!$B$2:$G$143,4,0) -> Y | AO46: =VLOOKUP($E46,'Capgemini PResence and HC'!$B$2:$G$143,2,0) -> 0 | AP46: =VLOOKUP($E46,'Capgemini PResence and HC'!$B$2:$G$143,3,0) -> 1 | AQ46: =VLOOKUP($E46,'Capgemini PResence and HC'!$B$2:$G$143,6,0) -> 0 | BB46: =SUM(AE46:AG46)-AH46 -> 0
A47: Cloud | B47: Yes | E47: 9879 | F47: W03PIU-JPN | G47: IS universal life insurance simulation | H47: IS universal life insurance simulation | I47: Storage and Preservation Related | J47: Customer Service and Operations Systems Group 34965 | K47: Policy Servicing Team 34967 | L47: MetLife IT Hosted/Supported | M47: Core Business Application | N47: Production | O47: AD Supported | P47: N | Q47: Global Technology & Operations | R47: No | S47: Yes | T47: Web Services | V47: JAVA | W47: MetLife Owned Application Code | Y47: No | Z47: Y | AA47: Y | AB47: Y | AC47: N | AD47: N | AE47: 0.2 | AF47: 0.1 | AG47: 0 | AH47: 0.30833333 | AI47: 0.67567568 | AJ47: 0.15416667 | AK47: 0.15416667 | AM47: =AH47*(1-AI47) -> 0.1 | AN47: =VLOOKUP($E47,'Capgemini PResence and HC'!$B$2:$G$143,4,0) -> Y | AO47: =VLOOKUP($E47,'Capgemini PResence and HC'!$B$2:$G$143,2,0) -> 0 | AP47: =VLOOKUP($E47,'Capgemini PResence and HC'!$B$2:$G$143,3,0) -> 1 | AQ47: =VLOOKUP($E47,'Capgemini PResence and HC'!$B$2:$G$143,6,0) -> 0 | BB47: =SUM(AE47:AG47)-AH47 -> -0.0083333333
A48: Cloud | B48: Yes | E48: 10032 | F48: W06TGR-JPN | G48: Group Policy Inquiry System for Intranet | H48: The Group Insurance Inquiry System is a web application system that provides various inquiry functions related to group insurance. It provides integrated inquiry functions for insurance contracts, insured person information, payment information, commissions, and more, supporting efficient execution of duties by business staff. | I48: Corporate Related | J48: Core Insurance Systems Group 34956 | K48: Corporate Systems Team 34959 | L48: MetLife IT Hosted/Supported | M48: Core Business Application | N48: Production | O48: AD Supported | P48: Y | Q48: Global Technology & Operations | R48: No | S48: Yes | T48: Web Services | V48: VB.NET; JAVA | W48: MetLife Owned Application Code | Y48: No | Z48: Y | AA48: Y | AB48: Y | AC48: N | AD48: N | AE48: 1.8583333 | AF48: 0.94166667 | AG48: 0 | AH48: 2.8 | AI48: 0.26934524 | AJ48: 1.4 | AK48: 1.4 | AM48: =AH48*(1-AI48) -> 2.0458333 | AN48: =VLOOKUP($E48,'Capgemini PResence and HC'!$B$2:$G$143,4,0) -> N | AO48: =VLOOKUP($E48,'Capgemini PResence and HC'!$B$2:$G$143,2,0) -> 0 | AP48: =VLOOKUP($E48,'Capgemini PResence and HC'!$B$2:$G$143,3,0) -> 0 | AQ48: =VLOOKUP($E48,'Capgemini PResence and HC'!$B$2:$G$143,6,0) -> 0 | AR48: =AH48-AS48 -> 0.75416667 | AS48: =AM48 -> 2.0458333 | AT48: =#REF!*AT$151 -> #REF! | AU48: =#REF!*AU$151 -> #REF! | AV48: =#REF!*AV$151 -> #REF! | AW48: =#REF!*AW$151 -> #REF! | AX48: =#REF!*AX$151 -> #REF! | AY48: =#REF!*AY$151 -> #REF! | AZ48: =#REF!*AZ$151 -> #REF! | BA48: =#REF!*BA$151 -> #REF! | BB48: =SUM(AE48:AG48)-AH48 -> 0
A49: Cloud | B49: Yes | E49: 9894 | F49: W08NAV-JPN | G49: Branch Marketing Information System | H49: Branch Marketing Information System | I49: Sales / Insurance Recruitment | J49: Customer and Channel Engineering 34961 | K49: Distribution F2F Team 34962 | L49: MetLife IT Hosted/Supported | M49: Core Business Application | N49: Production | O49: AD Supported | P49: N | Q49: Asia Region | R49: No | S49: Yes | T49: Thick Client | V49: VB | W49: MetLife Owned Application Code | Y49: No | Z49: Y | AA49: Y | AB49: Y | AC49: N | AD49: N | AE49: 2.841875 | AF49: 0.35208333 | AG49: 0 | AH49: 3.1939583 | AI49: 0.79192486 | AJ49: 1.5969792 | AK49: 1.5969792 | AM49: =AH49*(1-AI49) -> 0.66458333 | AN49: =VLOOKUP($E49,'Capgemini PResence and HC'!$B$2:$G$143,4,0) -> N | AO49: =VLOOKUP($E49,'Capgemini PResence and HC'!$B$2:$G$143,2,0) -> 0 | AP49: =VLOOKUP($E49,'Capgemini PResence and HC'!$B$2:$G$143,3,0) -> 0 | AQ49: =VLOOKUP($E49,'Capgemini PResence and HC'!$B$2:$G$143,6,0) -> 0 | AR49: =AE49-AS49 -> 2.1772917 | AS49: =AM49 -> 0.66458333 | AT49: =$AR49*AT$151 -> 0.16043202 | AU49: =$AR49*AU$151 -> 0.16043202 | AV49: =$AR49*AV$151 -> 0.84799781 | AW49: =$AR49*AW$151 -> 0.57297149 | AX49: =$AR49*AX$151 -> 0.1145943 | AY49: =$AR49*AY$151 -> 0.16043202 | AZ49: =$AR49*AZ$151 -> 0.16043202 | BA49: =$AS49*BA$151 -> 0.66458333 | BB49: =SUM(AE49:AG49)-AH49 -> 0
A50: Cloud | B50: Yes | E50: 13262 | F50: Business Content Management | G50: Business Content Management | H50: This is an information-sharing platform group designed to provide business-related documents and information for agents and internal users. In addition to BBS006, SharePoint and MetLifeNavi are also related, each responsible for providing users with business manuals, application documents, rules and conditions, and various information. | I50: Corporate Related | J50: Core Insurance Systems Group 34956 | K50: Corporate Systems Team 34959 | L50: Vendor Hosted/MetLife IT Supported | M50: Common Service Business Application | N50: Production | O50: AD Supported | P50: N | Q50: Global Technology & Operations | R50: No | S50: No | T50: Web Application Client | V50: Other#n/a | W50: Non-MetLife Owned Application Code (3rd party/COTS) | X50: Software as a Service (SaaS); Platform as a Service (PaaS) | Y50: Yes | Z50: Y | AA50: Y | AB50: Y | AC50: Y | AD50: N | AE50: 1.5133333 | AF50: 1.75 | AG50: 0.5 | AH50: 3.7633333 | AI50: 0.21147033 | AJ50: 1.8816667 | AK50: 1.8816667 | AM50: =AH50*(1-AI50) -> 2.9675 | AN50: =VLOOKUP($E50,'Capgemini PResence and HC'!$B$2:$G$143,4,0) -> Y | AO50: =VLOOKUP($E50,'Capgemini PResence and HC'!$B$2:$G$143,2,0) -> 2 | AP50: =VLOOKUP($E50,'Capgemini PResence and HC'!$B$2:$G$143,3,0) -> 0 | AQ50: =VLOOKUP($E50,'Capgemini PResence and HC'!$B$2:$G$143,6,0) -> 0.646875 | AR50: =AH50-AS50 -> 0.79583333 | AS50: =AM50 -> 2.9675 | AT50: =#REF!*AT$151 -> #REF! | AU50: =#REF!*AU$151 -> #REF! | AV50: =#REF!*AV$151 -> #REF! | AW50: =#REF!*AW$151 -> #REF! | AX50: =#REF!*AX$151 -> #REF! | AY50: =#REF!*AY$151 -> #REF! | AZ50: =#REF!*AZ$151 -> #REF! | BA50: =#REF!*BA$151 -> #REF! | BB50: =SUM(AE50:AG50)-AH50 -> 0
A51: Cloud | B51: Yes | E51: 9890 | F51: W08HTN-JPN | G51: conservation contact personnel entry system | H51: The Office Management System (OMS) is a web-based system that manages and supports sales activities at MetLife Alico's sales offices. This system provides centralized management of office information, salesperson information, contract information, and various functions necessary for sales activities. | I51: Corporate Related | J51: Core Insurance Systems Group 34956 | K51: Corporate Systems Team 34959 | L51: MetLife IT Hosted/Supported | M51: Core Business Application | N51: Production | O51: AD Supported | P51: N | Q51: Asia Region | R51: No | S51: Yes | T51: Web Services | V51: JAVA | W51: MetLife Owned Application Code | Y51: No | Z51: Y | AA51: Y | AB51: Y | AC51: N | AD51: N | AE51: 1.5054583 | AF51: 0.045833333 | AG51: 0 | AH51: 1.5512917 | AI51: 0.072009884 | AJ51: 0.77564583 | AK51: 0.77564583 | AM51: =AH51*(1-AI51) -> 1.4395833 | AN51: =VLOOKUP($E51,'Capgemini PResence and HC'!$B$2:$G$143,4,0) -> N | AO51: =VLOOKUP($E51,'Capgemini PResence and HC'!$B$2:$G$143,2,0) -> 0 | AP51: =VLOOKUP($E51,'Capgemini PResence and HC'!$B$2:$G$143,3,0) -> 0 | AQ51: =VLOOKUP($E51,'Capgemini PResence and HC'!$B$2:$G$143,6,0) -> 0 | AR51: =AH51-AS51 -> 0.11170833 | AS51: =AM51 -> 1.4395833 | BB51: =SUM(AE51:AG51)-AH51 -> 0
A52: Cloud | B52: Yes | E52: 14930 | F52: Vcalc-JPN | G52: Variable Insurance Guarantee Calculation System | H52: This is a batch processing system that calculates the minimum guaranteed benefit (V) for variable insurance. | I52: Corporate Related | J52: Core Insurance Systems Group 34956 | K52: Corporate Systems Team 34959 | L52: MetLife IT Hosted/Supported | M52: Core Business Application | N52: Development | O52: AD Supported | P52: N | Q52: Financial Management Group | R52: No | S52: Yes | T52: Other#Batch System | V52: JAVA | W52: MetLife Owned Application Code | X52: Platform as a Service (PaaS) | Y52: Yes | Z52: Y | AA52: Y | AB52: Y | AC52: N | AD52: N | AE52: 1.5 | AF52: 0.5 | AG52: 0 | AH52: 2 | AI52: 1 | AJ52: 1 | AK52: 1 | AM52: =AH52*(1-AI52) -> 0 | AN52: =VLOOKUP($E52,'Capgemini PResence and HC'!$B$2:$G$143,4,0) -> N | AO52: =VLOOKUP($E52,'Capgemini PResence and HC'!$B$2:$G$143,2,0) -> 0 | AP52: =VLOOKUP($E52,'Capgemini PResence and HC'!$B$2:$G$143,3,0) -> 0 | AQ52: =VLOOKUP($E52,'Capgemini PResence and HC'!$B$2:$G$143,6,0) -> 0 | AR52: =AH52-AS52 -> 2 | AS52: =AM52 -> 0 | BB52: =SUM(AE52:AG52)-AH52 -> 0
A53: Cloud | B53: Yes | E53: 9906 | F53: W08NAR-JPN | G53: producers information entry system | H53: Recruiter and Agent Information Management System. Web applications running in on-premises environments (IBM WebSphere, Java/JSP, Oracle DB). Staff at headquarters and sales offices use it to manage recruiter and agent information, link data with related systems and the Life Insurance Association (LINC), synchronize bidirectionally with mainframes, and manage related documents. | I53: Corporate Related | J53: Core Insurance Systems Group 34956 | K53: Corporate Systems Team 34959 | L53: MetLife IT Hosted/Supported | M53: Core Business Application | N53: Production | O53: AD Supported | P53: N | Q53: Asia Region | R53: No | S53: Yes | T53: Web Application Client | V53: JAVA | W53: MetLife Owned Application Code | Y53: No | Z53: Y | AA53: Y | AB53: Y | AC53: N | AD53: N | AE53: 1.2860417 | AF53: 0.14541667 | AG53: 0 | AH53: 1.4314583 | AI53: 0.95051666 | AJ53: 0.71572917 | AK53: 0.71572917 | AM53: =AH53*(1-AI53) -> 0.070833333 | AN53: =VLOOKUP($E53,'Capgemini PResence and HC'!$B$2:$G$143,4,0) -> N | AO53: =VLOOKUP($E53,'Capgemini PResence and HC'!$B$2:$G$143,2,0) -> 0 | AP53: =VLOOKUP($E53,'Capgemini PResence and HC'!$B$2:$G$143,3,0) -> 0 | AQ53: =VLOOKUP($E53,'Capgemini PResence and HC'!$B$2:$G$143,6,0) -> 0 | AR53: =AH53-AS53 -> 1.360625 | AS53: =AM53 -> 0.070833333 | AT53: =#REF!*AT$151 -> #REF! | AU53: =#REF!*AU$151 -> #REF! | AV53: =#REF!*AV$151 -> #REF! | AW53: =#REF!*AW$151 -> #REF! | AX53: =#REF!*AX$151 -> #REF! | AY53: =#REF!*AY$151 -> #REF! | AZ53: =#REF!*AZ$151 -> #REF! | BA53: =#REF!*BA$151 -> #REF! | BB53: =SUM(AE53:AG53)-AH53 -> 0
A54: Cloud | B54: Yes | E54: 9910 | F54: P08MMS-JPN | G54: Medical Management System | H54: New Contracts / Medical Assessment Management System | I54: New Contract Related | J54: Customer Service and Operations Systems Group 34965 | K54: New Business Team 34966 | L54: MetLife IT Hosted/Supported | M54: Core Business Application | N54: Production | O54: AD Supported | P54: N | Q54: Global Technology & Operations | R54: No | S54: Yes | T54: Thick Client | V54: VB.NET | W54: MetLife Owned Application Code | Y54: No | Z54: Y | AA54: Y | AB54: Y | AC54: N | AD54: N | AE54: 0.0625 | AF54: 0 | AG54: 0 | AH54: 0.0625 | AI54: 1 | AJ54: 0.03125 | AK54: 0.03125 | AM54: =AH54*(1-AI54) -> 0 | AN54: =VLOOKUP($E54,'Capgemini PResence and HC'!$B$2:$G$143,4,0) -> Y | AO54: =VLOOKUP($E54,'Capgemini PResence and HC'!$B$2:$G$143,2,0) -> 0 | AP54: =VLOOKUP($E54,'Capgemini PResence and HC'!$B$2:$G$143,3,0) -> 1 | AQ54: =VLOOKUP($E54,'Capgemini PResence and HC'!$B$2:$G$143,6,0) -> 0 | AT54: =#REF!*AT$151 -> #REF! | AU54: =#REF!*AU$151 -> #REF! | AV54: =#REF!*AV$151 -> #REF! | AW54: =#REF!*AW$151 -> #REF! | AX54: =#REF!*AX$151 -> #REF! | AY54: =#REF!*AY$151 -> #REF! | AZ54: =#REF!*AZ$151 -> #REF! | BA54: =#REF!*BA$151 -> #REF! | BB54: =SUM(AE54:AG54)-AH54 -> 0
A55: Cloud | B55: Yes | E55: 9920 | F55: WPSYEC-JPN | G55: Direct Marketing Site | H55: To capture prospective customers by providing online insurance simulation, online requests for brochures, online applications, etc. for customers in general. | I55: Marketing/Direct Business Related | J55: Customer and Channel Engineering 34961 | K55: Marketing and Leads Team 34964 | L55: MetLife IT Hosted/Supported | M55: Core Business Application | N55: Production | O55: AD Supported | P55: N | Q55: Global Marketing and Communications | R55: Yes | S55: Yes | T55: Web Services | V55: JAVA | W55: MetLife Owned Application Code | Y55: No | Z55: Y | AA55: Y | AB55: Y | AC55: N | AD55: N | AE55: 10.3375 | AF55: 3.5583333 | AG55: 5.1816667 | AH55: 19.0775 | AI55: 0.93360416 | AJ55: 9.53875 | AK55: 9.53875 | AM55: =AH55*(1-AI55) -> 1.2666667 | AN55: =VLOOKUP($E55,'Capgemini PResence and HC'!$B$2:$G$143,4,0) -> N | AO55: =VLOOKUP($E55,'Capgemini PResence and HC'!$B$2:$G$143,2,0) -> 0 | AP55: =VLOOKUP($E55,'Capgemini PResence and HC'!$B$2:$G$143,3,0) -> 0 | AQ55: =VLOOKUP($E55,'Capgemini PResence and HC'!$B$2:$G$143,6,0) -> 0 | AT55: =#REF!*AT$151 -> #REF! | AU55: =#REF!*AU$151 -> #REF! | AV55: =#REF!*AV$151 -> #REF! | AW55: =#REF!*AW$151 -> #REF! | AX55: =#REF!*AX$151 -> #REF! | AY55: =#REF!*AY$151 -> #REF! | AZ55: =#REF!*AZ$151 -> #REF! | BA55: =#REF!*BA$151 -> #REF! | BB55: =SUM(AE55:AG55)-AH55 -> 0
A56: Cloud | B56: Yes | E56: 9921 | F56: W07IPC-JPN | G56: Internet Prospective Information | H56: Internet Prospective Information | I56: Marketing/Direct Business Related | J56: Customer and Channel Engineering 34961 | K56: Marketing and Leads Team 34964 | L56: MetLife IT Hosted/Supported | M56: Core Business Application | N56: Production | O56: AD Supported | P56: N | Q56: Asia Region | R56: No | S56: Yes | T56: Web Services | V56: JAVA | W56: MetLife Owned Application Code | X56: Platform as a Service (PaaS) | Y56: Yes | Z56: Y | AA56: Y | AB56: Y | AC56: N | AD56: N | AE56: 0.30416667 | AF56: 0.041666667 | AG56: 0 | AH56: 0.34583333 | AI56: 1 | AJ56: 0.17291667 | AK56: 0.17291667 | AM56: =AH56*(1-AI56) -> 0 | AN56: =VLOOKUP($E56,'Capgemini PResence and HC'!$B$2:$G$143,4,0) -> N | AO56: =VLOOKUP($E56,'Capgemini PResence and HC'!$B$2:$G$143,2,0) -> 0 | AP56: =VLOOKUP($E56,'Capgemini PResence and HC'!$B$2:$G$143,3,0) -> 0 | AQ56: =VLOOKUP($E56,'Capgemini PResence and HC'!$B$2:$G$143,6,0) -> 0 | AT56: =#REF!*AT$151 -> #REF! | AU56: =#REF!*AU$151 -> #REF! | AV56: =#REF!*AV$151 -> #REF! | AW56: =#REF!*AW$151 -> #REF! | AX56: =#REF!*AX$151 -> #REF! | AY56: =#REF!*AY$151 -> #REF! | AZ56: =#REF!*AZ$151 -> #REF! | BA56: =#REF!*BA$151 -> #REF! | BB56: =SUM(AE56:AG56)-AH56 -> 0
A57: Cloud | B57: Yes | E57: 9926 | F57: W01LOI-JPN | G57: Japan Authorization / login | H57: This is a system which provides SSO authentication function and control over Portal site menu display for Infostation(Portal site for various Web application) | I57: Common Service Platform | J57: Japan Platform Team 35775 | K57: Japan Platform Team 35775 | L57: MetLife IT Hosted/Supported | M57: Common Service Business Application | N57: Production | O57: AD Supported | P57: N | Q57: Global Technology & Operations | R57: No | S57: Yes | T57: Web Application Client | V57: JAVA | W57: MetLife Owned Application Code | Y57: No | Z57: Y | AA57: Y | AB57: Y | AC57: N | AD57: N | AE57: 0.075 | AF57: 0 | AG57: 0 | AH57: 0.075 | AI57: 0 | AJ57: 0.0375 | AK57: 0.0375 | AM57: =AH57*(1-AI57) -> 0.075 | AN57: =VLOOKUP($E57,'Capgemini PResence and HC'!$B$2:$G$143,4,0) -> N | AO57: =VLOOKUP($E57,'Capgemini PResence and HC'!$B$2:$G$143,2,0) -> 0 | AP57: =VLOOKUP($E57,'Capgemini PResence and HC'!$B$2:$G$143,3,0) -> 0 | AQ57: =VLOOKUP($E57,'Capgemini PResence and HC'!$B$2:$G$143,6,0) -> 0 | AT57: =#REF!*AT$151 -> #REF! | AU57: =#REF!*AU$151 -> #REF! | AV57: =#REF!*AV$151 -> #REF! | AW57: =#REF!*AW$151 -> #REF! | AX57: =#REF!*AX$151 -> #REF! | AY57: =#REF!*AY$151 -> #REF! | AZ57: =#REF!*AZ$151 -> #REF! | BA57: =#REF!*BA$151 -> #REF! | BB57: =SUM(AE57:AG57)-AH57 -> 0
A58: Cloud | B58: Yes | E58: 9928 | F58: W01MAS-JPN | G58: Common Framework(Master4) | H58: Common Framework(Master4) | I58: Common Service Platform | J58: Japan Platform Team 35775 | K58: Japan Platform Team 35775 | L58: MetLife IT Hosted/Supported | M58: Common Service Business Application | N58: Production | O58: AD Supported | P58: N | Q58: Global Technology & Operations | R58: No | S58: Yes | T58: Web Application Client | V58: JAVA | W58: MetLife Owned Application Code | X58: Platform as a Service (PaaS) | Y58: Yes | Z58: Y | AA58: Y | AB58: Y | AC58: N | AD58: N | AE58: 1.3970833 | AF58: 1 | AG58: 0 | AH58: 2.3970833 | AI58: 0.86441856 | AJ58: 1.1985417 | AK58: 1.1985417 | AM58: =AH58*(1-AI58) -> 0.325 | AN58: =VLOOKUP($E58,'Capgemini PResence and HC'!$B$2:$G$143,4,0) -> N | AO58: =VLOOKUP($E58,'Capgemini PResence and HC'!$B$2:$G$143,2,0) -> 0 | AP58: =VLOOKUP($E58,'Capgemini PResence and HC'!$B$2:$G$143,3,0) -> 0 | AQ58: =VLOOKUP($E58,'Capgemini PResence and HC'!$B$2:$G$143,6,0) -> 0 | AT58: =#REF!*AT$151 -> #REF! | AU58: =#REF!*AU$151 -> #REF! | AV58: =#REF!*AV$151 -> #REF! | AW58: =#REF!*AW$151 -> #REF! | AX58: =#REF!*AX$151 -> #REF! | AY58: =#REF!*AY$151 -> #REF! | AZ58: =#REF!*AZ$151 -> #REF! | BA58: =#REF!*BA$151 -> #REF! | BB58: =SUM(AE58:AG58)-AH58 -> 0
A59: Mainframe | B59: Yes | E59: 9930 | F59: A04MMP-JPN | G59: AS400 Mass Marketing System | H59: MM (Mass Marketing)** is a system that integrates MetLife Japan's insurance premium calculation, claims management, and payment processing. The AS/400 works in conjunction with the Windows server to process, manage, and transfer insurance premium data. | I59: Corporate Related | J59: Core Insurance Systems Group 34956 | K59: Corporate Systems Team 34959 | L59: MetLife IT Hosted/Supported | M59: Core Business Application | N59: Production | O59: AD Supported | P59: Y | Q59: Global Technology & Operations | R59: No | S59: Yes | T59: Other#AS400 | V59: Other#RPG | W59: MetLife Owned Application Code | Y59: No | Z59: Y | AA59: Y | AB59: Y | AC59: N | AD59: N | AE59: 2.4083333 | AF59: 0.075 | AG59: 0 | AH59: 2.4833333 | AI59: 0.89932886 | AJ59: 1.2416667 | AK59: 1.2416667 | AM59: =AH59*(1-AI59) -> 0.25 | AN59: =VLOOKUP($E59,'Capgemini PResence and HC'!$B$2:$G$143,4,0) -> N | AO59: =VLOOKUP($E59,'Capgemini PResence and HC'!$B$2:$G$143,2,0) -> 0 | AP59: =VLOOKUP($E59,'Capgemini PResence and HC'!$B$2:$G$143,3,0) -> 0 | AQ59: =VLOOKUP($E59,'Capgemini PResence and HC'!$B$2:$G$143,6,0) -> 0 | AT59: =#REF!*AT$151 -> #REF! | AU59: =#REF!*AU$151 -> #REF! | AV59: =#REF!*AV$151 -> #REF! | AW59: =#REF!*AW$151 -> #REF! | AX59: =#REF!*AX$151 -> #REF! | AY59: =#REF!*AY$151 -> #REF! | AZ59: =#REF!*AZ$151 -> #REF! | BA59: =#REF!*BA$151 -> #REF! | BB59: =SUM(AE59:AG59)-AH59 -> 0
A60: Cloud | B60: Yes | E60: 9931 | F60: P02BKE-JPN | G60: Sales illustration system (based on EXCEL) for BAN | H60: Sales illustration system (based on EXCEL) for BANK | I60: Sales / Insurance Recruitment | J60: Customer and Channel Engineering 34961 | K60: Distribution Banca Team 34963 | L60: MetLife IT Hosted/Supported | M60: Core Business Application | N60: Production | O60: AD Supported | P60: N | Q60: Asia Region | R60: No | S60: Yes | T60: Thick Client | V60: Other#VBA | W60: MetLife Owned Application Code | Y60: No | Z60: Y | AA60: Y | AB60: Y | AC60: N | AD60: N | AE60: 13 | AF60: 2.275 | AG60: 0 | AH60: 15.275 | AI60: 0.91728849 | AJ60: 7.6375 | AK60: 7.6375 | AM60: =AH60*(1-AI60) -> 1.2634183 | AN60: =VLOOKUP($E60,'Capgemini PResence and HC'!$B$2:$G$143,4,0) -> N | AO60: =VLOOKUP($E60,'Capgemini PResence and HC'!$B$2:$G$143,2,0) -> 0 | AP60: =VLOOKUP($E60,'Capgemini PResence and HC'!$B$2:$G$143,3,0) -> 0 | AQ60: =VLOOKUP($E60,'Capgemini PResence and HC'!$B$2:$G$143,6,0) -> 0 | AR60: =AE60-AS60 -> 11.736582 | AS60: =AM60 -> 1.2634183 | AT60: =$AR60*AT$151 -> 0.86480076 | AU60: =$AR60*AU$151 -> 0.86480076 | AV60: =$AR60*AV$151 -> 4.5710897 | AW60: =$AR60*AW$151 -> 3.0885741 | AX60: =$AR60*AX$151 -> 0.61771483 | AY60: =$AR60*AY$151 -> 0.86480076 | AZ60: =$AR60*AZ$151 -> 0.86480076 | BA60: =$AS60*BA$151 -> 1.2634183 | BB60: =SUM(AE60:AG60)-AH60 -> 0
A61: Cloud | B61: Yes | E61: 11010 | F61: ZGLEDQ-JPN | G61: FATCA Oracle EDQ | H61: To comply with the FATCA Act, we process the necessary items of customer information held in our database at the necessary timing, and integrate them into the FATCA Azure system. | I61: Corporate Related | J61: Core Insurance Systems Group 34956 | K61: Corporate Systems Team 34959 | L61: MetLife IT Hosted/Supported | M61: Core Business Application | N61: Production | O61: AD Supported | P61: N | Q61: Financial Management Group | R61: No | S61: Yes | T61: Web Application Client | V61: JAVA; C # | W61: MetLife Owned Application Code | X61: Platform as a Service (PaaS) | Y61: Yes | Z61: Y | AA61: Y | AB61: Y | AC61: Y | AD61: N | AE61: 1.2583333 | AF61: 0.029166667 | AG61: 0.5 | AH61: 1.7875 | AI61: 0.55710956 | AJ61: 0.89375 | AK61: 0.89375 | AM61: =AH61*(1-AI61) -> 0.79166667 | AN61: =VLOOKUP($E61,'Capgemini PResence and HC'!$B$2:$G$143,4,0) -> N | AO61: =VLOOKUP($E61,'Capgemini PResence and HC'!$B$2:$G$143,2,0) -> 0 | AP61: =VLOOKUP($E61,'Capgemini PResence and HC'!$B$2:$G$143,3,0) -> 0 | AQ61: =VLOOKUP($E61,'Capgemini PResence and HC'!$B$2:$G$143,6,0) -> 0 | AR61: =AH61-AS61 -> 0.99583333 | AS61: =AM61 -> 0.79166667 | AT61: =#REF!*AT$151 -> #REF! | AU61: =#REF!*AU$151 -> #REF! | AV61: =#REF!*AV$151 -> #REF! | AW61: =#REF!*AW$151 -> #REF! | AX61: =#REF!*AX$151 -> #REF! | AY61: =#REF!*AY$151 -> #REF! | AZ61: =#REF!*AZ$151 -> #REF! | BA61: =#REF!*BA$151 -> #REF! | BB61: =SUM(AE61:AG61)-AH61 -> 0
A62: Cloud | B62: Yes | E62: 12890 | F62: ASP B_O-JPN | G62: ASP Bridge (OPEN) | H62: The VA-Bridge (OPEN) system is a core system for managing Variable Annuity insurance products. This INDEX aims to help new employees efficiently understand the system and carry out their daily tasks. | I62: Corporate Related | J62: Core Insurance Systems Group 34956 | K62: Corporate Systems Team 34959 | L62: MetLife IT Hosted/Supported | M62: Common Service Business Application | N62: Production | O62: AD Supported | P62: Y | Q62: Global Technology & Operations | R62: No | S62: Yes | T62: Web Services | V62: JAVA; C#; VB.NET | W62: MetLife Owned Application Code | Y62: No | Z62: Y | AA62: Y | AB62: Y | AC62: N | AD62: N | AE62: 1.234625 | AF62: 0.0625 | AG62: 0 | AH62: 1.297125 | AI62: 0.8506312 | AJ62: 0.6485625 | AK62: 0.6485625 | AM62: =AH62*(1-AI62) -> 0.19375 | AN62: =VLOOKUP($E62,'Capgemini PResence and HC'!$B$2:$G$143,4,0) -> N | AO62: =VLOOKUP($E62,'Capgemini PResence and HC'!$B$2:$G$143,2,0) -> 0 | AP62: =VLOOKUP($E62,'Capgemini PResence and HC'!$B$2:$G$143,3,0) -> 0 | AQ62: =VLOOKUP($E62,'Capgemini PResence and HC'!$B$2:$G$143,6,0) -> 0 | AR62: =AH62-AS62 -> 1.103375 | AS62: =AM62 -> 0.19375 | AT62: =#REF!*AT$151 -> #REF! | AU62: =#REF!*AU$151 -> #REF! | AV62: =#REF!*AV$151 -> #REF! | AW62: =#REF!*AW$151 -> #REF! | AX62: =#REF!*AX$151 -> #REF! | AY62: =#REF!*AY$151 -> #REF! | AZ62: =#REF!*AZ$151 -> #REF! | BA62: =#REF!*BA$151 -> #REF! | BB62: =SUM(AE62:AG62)-AH62 -> 0
A63: Cloud | B63: Yes | E63: 9947 | F63: W13WEP-JPN | G63: Web Payment | H63: Web Payment | I63: Storage and Preservation Related | J63: Customer Service and Operations Systems Group 34965 | K63: Policy Servicing Team 34967 | L63: MetLife IT Hosted/Supported | M63: Core Business Application | N63: Production | O63: AD Supported | P63: Y | Q63: Global Technology & Operations | R63: No | S63: Yes | T63: Web Services | V63: JAVA | W63: MetLife Owned Application Code | Y63: No | Z63: Y | AA63: Y | AB63: Y | AC63: N | AD63: N | AE63: 9 | AF63: 1.1541667 | AG63: 0 | AH63: 10 | AI63: 0.75904635 | AJ63: 5 | AK63: 5 | AM63: =AH63*(1-AI63) -> 2.4095365 | AN63: =VLOOKUP($E63,'Capgemini PResence and HC'!$B$2:$G$143,4,0) -> Y | AO63: =VLOOKUP($E63,'Capgemini PResence and HC'!$B$2:$G$143,2,0) -> 0 | AP63: =VLOOKUP($E63,'Capgemini PResence and HC'!$B$2:$G$143,3,0) -> 1 | AQ63: =VLOOKUP($E63,'Capgemini PResence and HC'!$B$2:$G$143,6,0) -> 0 | AT63: =#REF!*AT$151 -> #REF! | AU63: =#REF!*AU$151 -> #REF! | AV63: =#REF!*AV$151 -> #REF! | AW63: =#REF!*AW$151 -> #REF! | AX63: =#REF!*AX$151 -> #REF! | AY63: =#REF!*AY$151 -> #REF! | AZ63: =#REF!*AZ$151 -> #REF! | BA63: =#REF!*BA$151 -> #REF! | BB63: =SUM(AE63:AG63)-AH63 -> 0.15416667
A64: Mainframe | B64: Yes | E64: 9948 | F64: Data Send System for BANC MF-JP | G64: Data Send System for BANC | H64: A subsystem developed in-house. As a business domain, it mainly handles data creation for joint gateways for banks. It is basically built with COBOL, and except for the LIFECOMM integration part, almost no assembler is used. | I64: contract management | J64: Core Insurance Systems Group 34956 | K64: Policy Admin Systems Team 34957 | L64: MetLife IT Hosted/Supported | M64: Core Business Application | N64: Production | O64: AD Supported | P64: Y | Q64: Asia Region | R64: No | S64: Yes | T64: Other#Manframe | V64: COBOL, MU(EASYPLUS), Assembler, JCL | W64: MetLife Owned Application Code | Y64: No | Z64: Y | AA64: Y | AB64: Y | AC64: N | AD64: N | AE64: 9.2697083 | AF64: 2.8458333 | AG64: 0 | AH64: 12.115542 | AI64: 0.77129926 | AJ64: 6.0577708 | AK64: 6.0577708 | AM64: =AH64*(1-AI64) -> 2.7708333 | AN64: =VLOOKUP($E64,'Capgemini PResence and HC'!$B$2:$G$143,4,0) -> N | AO64: =VLOOKUP($E64,'Capgemini PResence and HC'!$B$2:$G$143,2,0) -> 0 | AP64: =VLOOKUP($E64,'Capgemini PResence and HC'!$B$2:$G$143,3,0) -> 0 | AQ64: =VLOOKUP($E64,'Capgemini PResence and HC'!$B$2:$G$143,6,0) -> 0 | AT64: =#REF!*AT$151 -> #REF! | AU64: =#REF!*AU$151 -> #REF! | AV64: =#REF!*AV$151 -> #REF! | AW64: =#REF!*AW$151 -> #REF! | AX64: =#REF!*AX$151 -> #REF! | AY64: =#REF!*AY$151 -> #REF! | AZ64: =#REF!*AZ$151 -> #REF! | BA64: =#REF!*BA$151 -> #REF! | BB64: =SUM(AE64:AG64)-AH64 -> 0
A65: Cloud | B65: Yes | E65: 9899 | F65: W08CIS-JPN | G65: Career Information System | H65: CIS (Customer Information System) is MetLife's customer information management system. This system offers the following key features: - Customer information inquiry and update - Family information management - Housing and commuting information management - Information access control based on permissions - Security log management - Data export function | I65: Corporate Related | J65: Core Insurance Systems Group 34956 | K65: Corporate Systems Team 34959 | L65: MetLife IT Hosted/Supported | M65: Core Business Application | N65: Production | O65: AD Supported | P65: N | Q65: Asia Region | R65: No | S65: Yes | T65: Web Services | V65: JAVA | W65: MetLife Owned Application Code | Y65: No | Z65: Y | AA65: Y | AB65: Y | AC65: N | AD65: N | AE65: 1.204125 | AF65: 0.52916667 | AG65: 0 | AH65: 1.7332917 | AI65: 0.82691892 | AJ65: 0.86664583 | AK65: 0.86664583 | AM65: =AH65*(1-AI65) -> 0.3 | AN65: =VLOOKUP($E65,'Capgemini PResence and HC'!$B$2:$G$143,4,0) -> N | AO65: =VLOOKUP($E65,'Capgemini PResence and HC'!$B$2:$G$143,2,0) -> 0 | AP65: =VLOOKUP($E65,'Capgemini PResence and HC'!$B$2:$G$143,3,0) -> 0 | AQ65: =VLOOKUP($E65,'Capgemini PResence and HC'!$B$2:$G$143,6,0) -> 0 | AR65: =AH65-AS65 -> 1.4332917 | AS65: =AM65 -> 0.3 | AT65: =#REF!*AT$151 -> #REF! | AU65: =#REF!*AU$151 -> #REF! | AV65: =#REF!*AV$151 -> #REF! | AW65: =#REF!*AW$151 -> #REF! | AX65: =#REF!*AX$151 -> #REF! | AY65: =#REF!*AY$151 -> #REF! | AZ65: =#REF!*AZ$151 -> #REF! | BA65: =#REF!*BA$151 -> #REF! | BB65: =SUM(AE65:AG65)-AH65 -> 0
A66: Data | B66: Yes | C66: Yes | D66: Batch integration Tech stack is not yet clear to ascertain if only &D needs to support or also needs Mainframe skills . However this app is marked as Priority Target for Transition. FSI vendor manages this app- Transition Priority # 2 for "Data Platforms" Data validation, ETL testing will be handled by I&D; Non-functional testing by QA Testing team | E66: 9951 | F66: BCMHRP-JPN | G66: Data cooperation | H66: Data cooperation, integration between open system and HOST/AS400. Master data managed by HOST and AS 400 is processed for integration to open type backbone DB. Conversely, data managed by open backbone DB is integrated to HOST. All batch processes are operated by JP1. Other name: HRP(Host Relationship Program) | I66: Data Infrastructure | J66: Data Platforms Team 34980 | K66: Data Platforms Team 34980 | L66: MetLife IT Hosted/Supported | M66: Common Service Business Application | N66: Production | O66: AD Supported | P66: N | Q66: Global Technology & Operations | R66: No | S66: Yes | T66: Other#none. | V66: Other#MS-DOS ,AWK,VBScript,JAVA | W66: MetLife Owned Application Code | X66: Running on both on-premises and Azure. The on-premises version will be decommissioned by the end of 2027. | Y66: No | Z66: Y | AA66: Y | AB66: Y | AC66: N | AD66: Y | AE66: 7 | AF66: 1 | AG66: 0 | AH66: 7.9270417 | AI66: 0.77923668 | AJ66: 3.9635208 | AK66: 3.9635208 | AL66: Considering AMS+AD over 3 years post initial Transition Estimation Approach for AMS - based on assumed # of Incidents, Problem Tickets, SRs and CRs including minor enhancements and YoY AI-driven productivity | AM66: =AH66*(1-AI66) -> 1.75 | AN66: =VLOOKUP($E66,'Capgemini PResence and HC'!$B$2:$G$143,4,0) -> N | AO66: =VLOOKUP($E66,'Capgemini PResence and HC'!$B$2:$G$143,2,0) -> 0 | AP66: =VLOOKUP($E66,'Capgemini PResence and HC'!$B$2:$G$143,3,0) -> 0 | AQ66: =VLOOKUP($E66,'Capgemini PResence and HC'!$B$2:$G$143,6,0) -> 0 | AT66: =#REF!*AT$151 -> #REF! | AU66: =#REF!*AU$151 -> #REF! | AV66: =#REF!*AV$151 -> #REF! | AW66: =#REF!*AW$151 -> #REF! | AX66: =#REF!*AX$151 -> #REF! | AY66: =#REF!*AY$151 -> #REF! | AZ66: =#REF!*AZ$151 -> #REF! | BA66: =#REF!*BA$151 -> #REF! | BB66: =SUM(AE66:AG66)-AH66 -> 0.072958333
A67: Digital | B67: Yes | E67: 9962 | F67: WPSCUS-JPN | G67: Customer Support System | H67: Customer Support System | I67: Marketing/Direct Business Related | J67: Customer and Channel Engineering 34961 | K67: Marketing and Leads Team 34964 | L67: MetLife IT Hosted/Supported | M67: Core Business Application | N67: Production | O67: AD Supported | P67: N | Q67: Asia Region | R67: No | S67: Yes | T67: Web Services | V67: JavaScript; Other#APEX | W67: MetLife Owned Application Code | X67: Platform as a Service (PaaS) | Y67: Yes | Z67: Y | AA67: Y | AB67: Y | AC67: N | AD67: N | AE67: 8.9216667 | AF67: 2.4104167 | AG67: 1.52 | AH67: 12.852083 | AI67: 0.82739504 | AJ67: 6.4260417 | AK67: 6.4260417 | AM67: =AH67*(1-AI67) -> 2.2183333 | AN67: =VLOOKUP($E67,'Capgemini PResence and HC'!$B$2:$G$143,4,0) -> N | AO67: =VLOOKUP($E67,'Capgemini PResence and HC'!$B$2:$G$143,2,0) -> 0 | AP67: =VLOOKUP($E67,'Capgemini PResence and HC'!$B$2:$G$143,3,0) -> 0 | AQ67: =VLOOKUP($E67,'Capgemini PResence and HC'!$B$2:$G$143,6,0) -> 0 | AT67: =#REF!*AT$151 -> #REF! | AU67: =#REF!*AU$151 -> #REF! | AV67: =#REF!*AV$151 -> #REF! | AW67: =#REF!*AW$151 -> #REF! | AX67: =#REF!*AX$151 -> #REF! | AY67: =#REF!*AY$151 -> #REF! | AZ67: =#REF!*AZ$151 -> #REF! | BA67: =#REF!*BA$151 -> #REF! | BB67: =SUM(AE67:AG67)-AH67 -> 0
A68: Cloud | B68: Yes | E68: 9896 | F68: W08SFE-JPN | G68: commission Inquiry | H68: This system is a web application for referencing commission (fee) data of recruiters and agents, as well as contract information necessary for calculating retention rates and net increase rates of holdings. | I68: Corporate Related | J68: Core Insurance Systems Group 34956 | K68: Corporate Systems Team 34959 | L68: MetLife IT Hosted/Supported | M68: Core Business Application | N68: Production | O68: AD Supported | P68: N | Q68: Asia Region | R68: No | S68: Yes | T68: Web Application Client | V68: JAVA | W68: MetLife Owned Application Code | Y68: No | Z68: Y | AA68: Y | AB68: Y | AC68: N | AD68: N | AE68: 1.091375 | AF68: 0.105 | AG68: 0 | AH68: 1.196375 | AI68: 0.98955177 | AJ68: 0.5981875 | AK68: 0.5981875 | AM68: =AH68*(1-AI68) -> 0.0125 | AN68: =VLOOKUP($E68,'Capgemini PResence and HC'!$B$2:$G$143,4,0) -> N | AO68: =VLOOKUP($E68,'Capgemini PResence and HC'!$B$2:$G$143,2,0) -> 0 | AP68: =VLOOKUP($E68,'Capgemini PResence and HC'!$B$2:$G$143,3,0) -> 0 | AQ68: =VLOOKUP($E68,'Capgemini PResence and HC'!$B$2:$G$143,6,0) -> 0 | AR68: =AH68-AS68 -> 1.183875 | AS68: =AM68 -> 0.0125 | AT68: =#REF!*AT$151 -> #REF! | AU68: =#REF!*AU$151 -> #REF! | AV68: =#REF!*AV$151 -> #REF! | AW68: =#REF!*AW$151 -> #REF! | AX68: =#REF!*AX$151 -> #REF! | AY68: =#REF!*AY$151 -> #REF! | AZ68: =#REF!*AZ$151 -> #REF! | BA68: =#REF!*BA$151 -> #REF! | BB68: =SUM(AE68:AG68)-AH68 -> 0
A69: Cloud | B69: Yes | E69: 9941 | F69: B13ITS-JPN | G69: ITS-PCIS(Mutual Fund System(Including Bestway) | H69: BESTWAY/JJ is an integrated package system that supports the sales operations of investment trusts for financial institutions. Developed and provided by Nomura Research Institute (NRI). | I69: Corporate Related | J69: Core Insurance Systems Group 34956 | K69: Corporate Systems Team 34959 | L69: Co-Located / Vendor Supported | M69: Core Business Application | N69: Production | O69: AD Supported | P69: N | Q69: Asia Region | R69: No | S69: Yes | T69: Web Services | V69: JAVA | W69: MetLife Owned Application Code | X69: Software as a Service (SaaS) | Y69: Yes | Z69: Y | AA69: Y | AB69: Y | AC69: N | AD69: N | AE69: 0.92916458 | AF69: 0.0875 | AG69: 0 | AH69: 1.0166646 | AI69: 0.41311355 | AJ69: 0.50833229 | AK69: 0.50833229 | AM69: =AH69*(1-AI69) -> 0.59666667 | AN69: =VLOOKUP($E69,'Capgemini PResence and HC'!$B$2:$G$143,4,0) -> N | AO69: =VLOOKUP($E69,'Capgemini PResence and HC'!$B$2:$G$143,2,0) -> 0 | AP69: =VLOOKUP($E69,'Capgemini PResence and HC'!$B$2:$G$143,3,0) -> 0 | AQ69: =VLOOKUP($E69,'Capgemini PResence and HC'!$B$2:$G$143,6,0) -> 0 | AR69: =AH69-AS69 -> 0.41999792 | AS69: =AM69 -> 0.59666667 | AT69: =#REF!*AT$151 -> #REF! | AU69: =#REF!*AU$151 -> #REF! | AV69: =#REF!*AV$151 -> #REF! | AW69: =#REF!*AW$151 -> #REF! | AX69: =#REF!*AX$151 -> #REF! | AY69: =#REF!*AY$151 -> #REF! | AZ69: =#REF!*AZ$151 -> #REF! | BA69: =#REF!*BA$151 -> #REF! | BB69: =SUM(AE69:AG69)-AH69 -> 0
A70: Cloud | B70: Yes | E70: 9844 | F70: C04VAS-JPN | G70: Voucher Approval System for AS400 | H70: VAS (Voucher Accounting System) is MetLife's voucher approval and issuance system. | I70: Corporate Related | J70: Core Insurance Systems Group 34956 | K70: Corporate Systems Team 34959 | L70: MetLife IT Hosted/Supported | M70: Core Business Application | N70: Production | O70: AD Supported | P70: Y | Q70: Global Technology & Operations | R70: No | S70: Yes | T70: Thick Client | V70: VB.NET | W70: MetLife Owned Application Code | Y70: No | Z70: Y | AA70: Y | AB70: Y | AC70: N | AD70: N | AE70: 0.67083333 | AF70: 0.68333333 | AG70: 0 | AH70: 1.3541667 | AI70: 0.36923077 | AJ70: 0.67708333 | AK70: 0.67708333 | AM70: =AH70*(1-AI70) -> 0.85416667 | AN70: =VLOOKUP($E70,'Capgemini PResence and HC'!$B$2:$G$143,4,0) -> N | AO70: =VLOOKUP($E70,'Capgemini PResence and HC'!$B$2:$G$143,2,0) -> 0 | AP70: =VLOOKUP($E70,'Capgemini PResence and HC'!$B$2:$G$143,3,0) -> 0 | AQ70: =VLOOKUP($E70,'Capgemini PResence and HC'!$B$2:$G$143,6,0) -> 0 | AR70: =AH70-AS70 -> 0.5 | AS70: =AM70 -> 0.85416667 | BB70: =SUM(AE70:AG70)-AH70 -> 0
A71: Cloud | B71: Yes | E71: 9975 | F71: WPMWCC-JPN | G71: Web Contact Center | H71: Web Services for Recruiters (Collection Preservation & Insurance Claims Related) | I71: Customer Care / Call Center Related | J71: Customer Service and Operations Systems Group 34965 | K71: Customer Care Team 34969 | L71: MetLife IT Hosted/Supported | M71: Core Business Application | N71: Production | O71: AD Supported | P71: N | Q71: Global Technology & Operations | R71: No | S71: Yes | T71: Web Application Client | V71: JAVA | W71: MetLife Owned Application Code | Y71: No | Z71: Y | AA71: Y | AB71: Y | AC71: N | AD71: N | AE71: 1.1116667 | AF71: 0 | AG71: 0 | AH71: 1.1116667 | AI71: 0.58508246 | AJ71: 0.55583333 | AK71: 0.55583333 | AM71: =AH71*(1-AI71) -> 0.46125 | AN71: =VLOOKUP($E71,'Capgemini PResence and HC'!$B$2:$G$143,4,0) -> N | AO71: =VLOOKUP($E71,'Capgemini PResence and HC'!$B$2:$G$143,2,0) -> 0 | AP71: =VLOOKUP($E71,'Capgemini PResence and HC'!$B$2:$G$143,3,0) -> 0 | AQ71: =VLOOKUP($E71,'Capgemini PResence and HC'!$B$2:$G$143,6,0) -> 0 | AT71: =#REF!*AT$151 -> #REF! | AU71: =#REF!*AU$151 -> #REF! | AV71: =#REF!*AV$151 -> #REF! | AW71: =#REF!*AW$151 -> #REF! | AX71: =#REF!*AX$151 -> #REF! | AY71: =#REF!*AY$151 -> #REF! | AZ71: =#REF!*AZ$151 -> #REF! | BA71: =#REF!*BA$151 -> #REF! | BB71: =SUM(AE71:AG71)-AH71 -> 0
A72: Cloud | B72: Yes | E72: 9977 | F72: WGLRPC-JPN | G72: ReportConnection | H72: ReportConnection | I72: Sales / Insurance Recruitment | J72: Customer and Channel Engineering 34961 | K72: Distribution F2F Team 34962 | L72: MetLife IT Hosted/Supported | M72: Core Business Application | N72: Production | O72: AD Supported | P72: N | Q72: Asia Region | R72: No | S72: Yes | T72: Web Services | V72: JAVA | W72: MetLife Owned Application Code | Y72: No | Z72: Y | AA72: Y | AB72: Y | AC72: N | AD72: N | AE72: 1 | AF72: 1 | AG72: 0 | AH72: 0.45791667 | AI72: 0 | AJ72: 0.22895833 | AK72: 0.22895833 | AM72: =AH72*(1-AI72) -> 0.45791667 | AN72: =VLOOKUP($E72,'Capgemini PResence and HC'!$B$2:$G$143,4,0) -> N | AO72: =VLOOKUP($E72,'Capgemini PResence and HC'!$B$2:$G$143,2,0) -> 0 | AP72: =VLOOKUP($E72,'Capgemini PResence and HC'!$B$2:$G$143,3,0) -> 0 | AQ72: =VLOOKUP($E72,'Capgemini PResence and HC'!$B$2:$G$143,6,0) -> 0 | AR72: =AE72-AS72 -> 0.54208333 | AS72: =AM72 -> 0.45791667 | AT72: =$AR72*AT$151 -> 0.039942982 | AU72: =$AR72*AU$151 -> 0.039942982 | AV72: =$AR72*AV$151 -> 0.21112719 | AW72: =$AR72*AW$151 -> 0.14265351 | AX72: =$AR72*AX$151 -> 0.028530702 | AY72: =$AR72*AY$151 -> 0.039942982 | AZ72: =$AR72*AZ$151 -> 0.039942982 | BA72: =$AS72*BA$151 -> 0.45791667 | BB72: =SUM(AE72:AG72)-AH72 -> 1.5420833
A73: Mainframe | B73: Yes | E73: 9980 | F73: Policy UWIBATCH MF-JPN | G73: Policy Underwriting and Issue Batch | H73: A subsystem developed in-house. In the business domain, it mainly handles the creation of insurance policies for new contracts. It is basically built with COBOL, and except for the LIFECOMM integration part, almost no assembler is used. | I73: contract management | J73: Core Insurance Systems Group 34956 | K73: Policy Admin Systems Team 34957 | L73: MetLife IT Hosted/Supported | M73: Core Business Application | N73: Production | O73: AD Supported | P73: Y | Q73: Global Technology & Operations | R73: No | S73: Yes | T73: Other#Mainframe | V73: Other#ASM; Cobol | W73: MetLife Owned Application Code | Y73: No | Z73: Y | AA73: Y | AB73: Y | AC73: N | AD73: N | AE73: 12.606875 | AF73: 1.1416667 | AG73: 0 | AH73: 13.748542 | AI73: 0.81496522 | AJ73: 6.8742708 | AK73: 6.8742708 | AM73: =AH73*(1-AI73) -> 2.5439583 | AN73: =VLOOKUP($E73,'Capgemini PResence and HC'!$B$2:$G$143,4,0) -> N | AO73: =VLOOKUP($E73,'Capgemini PResence and HC'!$B$2:$G$143,2,0) -> 0 | AP73: =VLOOKUP($E73,'Capgemini PResence and HC'!$B$2:$G$143,3,0) -> 0 | AQ73: =VLOOKUP($E73,'Capgemini PResence and HC'!$B$2:$G$143,6,0) -> 0 | AT73: =#REF!*AT$151 -> #REF! | AU73: =#REF!*AU$151 -> #REF! | AV73: =#REF!*AV$151 -> #REF! | AW73: =#REF!*AW$151 -> #REF! | AX73: =#REF!*AX$151 -> #REF! | AY73: =#REF!*AY$151 -> #REF! | AZ73: =#REF!*AZ$151 -> #REF! | BA73: =#REF!*BA$151 -> #REF! | BB73: =SUM(AE73:AG73)-AH73 -> 0
A74: Cloud | B74: Yes | E74: 9983 | F74: WAAATF-JPN | G74: Agents Target Following system | H74: Agents Target Following system | I74: Sales / Insurance Recruitment | J74: Customer and Channel Engineering 34961 | K74: Distribution F2F Team 34962 | L74: MetLife IT Hosted/Supported | M74: Core Business Application | N74: Production | O74: AD Supported | P74: N | Q74: Asia Region | R74: No | S74: Yes | T74: Other#(C/S) | V74: JAVA | W74: MetLife Owned Application Code | X74: Platform as a Service (PaaS) | Y74: Yes | Z74: Y | AA74: Y | AB74: Y | AC74: N | AD74: N | AE74: 6.6141667 | AF74: 0.64791667 | AG74: 0 | AH74: 7.2620833 | AI74: 0.93912445 | AJ74: 3.6310417 | AK74: 3.6310417 | AM74: =AH74*(1-AI74) -> 0.44208333 | AN74: =VLOOKUP($E74,'Capgemini PResence and HC'!$B$2:$G$143,4,0) -> N | AO74: =VLOOKUP($E74,'Capgemini PResence and HC'!$B$2:$G$143,2,0) -> 0 | AP74: =VLOOKUP($E74,'Capgemini PResence and HC'!$B$2:$G$143,3,0) -> 0 | AQ74: =VLOOKUP($E74,'Capgemini PResence and HC'!$B$2:$G$143,6,0) -> 0 | AR74: =AE74-AS74 -> 6.1720833 | AS74: =AM74 -> 0.44208333 | AT74: =$AR74*AT$151 -> 0.45478509 | AU74: =$AR74*AU$151 -> 0.45478509 | AV74: =$AR74*AV$151 -> 2.403864 | AW74: =$AR74*AW$151 -> 1.6242325 | AX74: =$AR74*AX$151 -> 0.32484649 | AY74: =$AR74*AY$151 -> 0.45478509 | AZ74: =$AR74*AZ$151 -> 0.45478509 | BA74: =$AS74*BA$151 -> 0.44208333 | BB74: =SUM(AE74:AG74)-AH74 -> 0
A75: Digital | B75: Yes | E75: 9986 | F75: ZGLEST-JPN | G75: eSTATION | H75: eSTATION (9986_MAIN) is MetLife's integrated business management system. This system offers the following key features: - **Employee Profile Management**: Register, update, and delete employee information - **Asset Management**: Manage and track IT equipment and supplies - **Form Supply**: Management and supply of various forms and papers - **Call Management**: Integrated management with phone systems - **Workflow Management**: Various application and approval workflows - **Report Generation**: Output various forms and generate PDFs - **Job Management**: Batch processing and schedule management - **SELS (Self Entry Lifecycle System)**: Self-service portal - **Media Management**: Subsystems for various media - **Print Management**: Manage print services - **EZ-Travel**: Business trip management system | I75: Corporate Related | J75: Core Insurance Systems Group 34956 | K75: Corporate Systems Team 34959 | L75: MetLife IT Hosted/Supported | M75: Core Business Application | N75: Production | O75: AD Supported | P75: N | Q75: Financial Management Group | R75: No | S75: Yes | T75: Web Application Client | V75: JavaScript; VB.NET; C#;HTML | W75: MetLife Owned Application Code | Y75: No | Z75: Y | AA75: Y | AB75: Y | AC75: N | AD75: N | AE75: 2.4426667 | AF75: 0.57083333 | AG75: 0 | AH75: 3.0135 | AI75: 0.27515071 | AJ75: 1.50675 | AK75: 1.50675 | AM75: =AH75*(1-AI75) -> 2.1843333 | AN75: =VLOOKUP($E75,'Capgemini PResence and HC'!$B$2:$G$143,4,0) -> N | AO75: =VLOOKUP($E75,'Capgemini PResence and HC'!$B$2:$G$143,2,0) -> 0 | AP75: =VLOOKUP($E75,'Capgemini PResence and HC'!$B$2:$G$143,3,0) -> 0 | AQ75: =VLOOKUP($E75,'Capgemini PResence and HC'!$B$2:$G$143,6,0) -> 0 | AT75: =#REF!*AT$151 -> #REF! | AU75: =#REF!*AU$151 -> #REF! | AV75: =#REF!*AV$151 -> #REF! | AW75: =#REF!*AW$151 -> #REF! | AX75: =#REF!*AX$151 -> #REF! | AY75: =#REF!*AY$151 -> #REF! | AZ75: =#REF!*AZ$151 -> #REF! | BA75: =#REF!*BA$151 -> #REF! | BB75: =SUM(AE75:AG75)-AH75 -> 0
A76: Cloud | B76: Yes | E76: 9992 | F76: CMESB-JPN | G76: Enterprise Service Bus | H76: Enterprise Service Bus | I76: Common Service Platform | J76: Japan Platform Team 35775 | K76: Japan Platform Team 35775 | L76: MetLife IT Hosted/Supported | M76: Common Service Business Application | N76: Production | O76: AD Supported | P76: N | Q76: Global Technology & Operations | R76: No | S76: Yes | T76: Web Services | V76: JAVA; Other#ESQL | W76: MetLife Owned Application Code | Y76: No | Z76: Y | AA76: Y | AB76: Y | AC76: N | AD76: N | AE76: 7.2083333 | AF76: 2.9958333 | AG76: 2.5208333 | AH76: 12.725 | AI76: 0.93778651 | AJ76: 6.3625 | AK76: 6.3625 | AM76: =AH76*(1-AI76) -> 0.79166667 | AN76: =VLOOKUP($E76,'Capgemini PResence and HC'!$B$2:$G$143,4,0) -> Y | AO76: =VLOOKUP($E76,'Capgemini PResence and HC'!$B$2:$G$143,2,0) -> 12 | AP76: =VLOOKUP($E76,'Capgemini PResence and HC'!$B$2:$G$143,3,0) -> 0 | AQ76: =VLOOKUP($E76,'Capgemini PResence and HC'!$B$2:$G$143,6,0) -> 9.28125 | AT76: =#REF!*AT$151 -> #REF! | AU76: =#REF!*AU$151 -> #REF! | AV76: =#REF!*AV$151 -> #REF! | AW76: =#REF!*AW$151 -> #REF! | AX76: =#REF!*AX$151 -> #REF! | AY76: =#REF!*AY$151 -> #REF! | AZ76: =#REF!*AZ$151 -> #REF! | BA76: =#REF!*BA$151 -> #REF! | BB76: =SUM(AE76:AG76)-AH76 -> 0
A77: Cloud | B77: Yes | E77: 9994 | F77: WPMAUD-JPN | G77: Unknown Address Tracking System | H77: Address Unknown Contract Management System | I77: Storage and Preservation Related | J77: Customer Service and Operations Systems Group 34965 | K77: Policy Servicing Team 34967 | L77: Vendor Hosted/MetLife IT Supported | M77: Core Business Application | N77: Production | O77: AD Supported | P77: N | Q77: Global Technology & Operations | R77: No | S77: No | T77: Web Application Client | V77: JAVA | W77: Non-MetLife Owned Application Code (3rd party/COTS) | X77: Platform as a Service (PaaS) | Y77: Yes | Z77: Y | AA77: Y | AB77: Y | AC77: N | AD77: N | AE77: 0.8 | AF77: 0.2 | AG77: 0 | AH77: 1.1729167 | AI77: 0.42806394 | AJ77: 0.58645833 | AK77: 0.58645833 | AM77: =AH77*(1-AI77) -> 0.67083333 | AN77: =VLOOKUP($E77,'Capgemini PResence and HC'!$B$2:$G$143,4,0) -> Y | AO77: =VLOOKUP($E77,'Capgemini PResence and HC'!$B$2:$G$143,2,0) -> 0 | AP77: =VLOOKUP($E77,'Capgemini PResence and HC'!$B$2:$G$143,3,0) -> 1 | AQ77: =VLOOKUP($E77,'Capgemini PResence and HC'!$B$2:$G$143,6,0) -> 0 | AT77: =#REF!*AT$151 -> #REF! | AU77: =#REF!*AU$151 -> #REF! | AV77: =#REF!*AV$151 -> #REF! | AW77: =#REF!*AW$151 -> #REF! | AX77: =#REF!*AX$151 -> #REF! | AY77: =#REF!*AY$151 -> #REF! | AZ77: =#REF!*AZ$151 -> #REF! | BA77: =#REF!*BA$151 -> #REF! | BB77: =SUM(AE77:AG77)-AH77 -> -0.17291667
B78: Yes | E78: 9995 | F78: WCMPXS-JPN | G78: ProductXpress | H78: Using Hewlett Packard's packaged product ProductXpress as a platform, it provides common computing functions to subsystems. The common calculation function is called only from the ESB via Web Service, and the amounts of premiums and surrender value, calculated based on the business method document, are sent and received in XML format. | I78: Corporate Related | J78: Core Insurance Systems Group 34956 | K78: Corporate Systems Team 34959 | L78: MetLife IT Hosted/Supported | M78: Infrastructure Application | N78: Production | O78: AD Supported | P78: N | Q78: Asia Region | R78: No | S78: Yes | T78: Web Services | V78: Other#Peculiar Language, Implemented in PX designer. | W78: MetLife Owned Application Code | Y78: No | Z78: Y | AA78: Y | AB78: Y | AC78: N | AD78: N | AE78: 0.77916667 | AF78: 0 | AG78: 0 | AH78: 0.77916667 | AI78: 0.67914439 | AJ78: 0.38958333 | AK78: 0.38958333 | AM78: =AH78*(1-AI78) -> 0.25 | AN78: =VLOOKUP($E78,'Capgemini PResence and HC'!$B$2:$G$143,4,0) -> N | AO78: =VLOOKUP($E78,'Capgemini PResence and HC'!$B$2:$G$143,2,0) -> 0 | AP78: =VLOOKUP($E78,'Capgemini PResence and HC'!$B$2:$G$143,3,0) -> 0 | AQ78: =VLOOKUP($E78,'Capgemini PResence and HC'!$B$2:$G$143,6,0) -> 0 | AT78: =#REF!*AT$151 -> #REF! | AU78: =#REF!*AU$151 -> #REF! | AV78: =#REF!*AV$151 -> #REF! | AW78: =#REF!*AW$151 -> #REF! | AX78: =#REF!*AX$151 -> #REF! | AY78: =#REF!*AY$151 -> #REF! | AZ78: =#REF!*AZ$151 -> #REF! | BA78: =#REF!*BA$151 -> #REF! | BB78: =SUM(AE78:AG78)-AH78 -> 0
A79: Cloud | B79: Yes | E79: 9996 | F79: WUIURE-JPN | G79: Pre-Underwriting | H79: By providing an inquiry function for medical underwriting results, this application provides followings. | I79: New Contract Related | J79: Customer Service and Operations Systems Group 34965 | K79: New Business Team 34966 | L79: MetLife IT Hosted/Supported | M79: Core Business Application | N79: Production | O79: AD Supported | P79: N | Q79: Global Technology & Operations | R79: No | S79: Yes | T79: Web Application Client | V79: JAVA | W79: MetLife Owned Application Code | Y79: No | Z79: Y | AA79: Y | AB79: Y | AC79: N | AD79: N | AE79: 0.22625 | AF79: 0 | AG79: 0 | AH79: 0.22625 | AI79: 0.33701657 | AJ79: 0.113125 | AK79: 0.113125 | AM79: =AH79*(1-AI79) -> 0.15 | AN79: =VLOOKUP($E79,'Capgemini PResence and HC'!$B$2:$G$143,4,0) -> Y | AO79: =VLOOKUP($E79,'Capgemini PResence and HC'!$B$2:$G$143,2,0) -> 0 | AP79: =VLOOKUP($E79,'Capgemini PResence and HC'!$B$2:$G$143,3,0) -> 1 | AQ79: =VLOOKUP($E79,'Capgemini PResence and HC'!$B$2:$G$143,6,0) -> 0 | AT79: =#REF!*AT$151 -> #REF! | AU79: =#REF!*AU$151 -> #REF! | AV79: =#REF!*AV$151 -> #REF! | AW79: =#REF!*AW$151 -> #REF! | AX79: =#REF!*AX$151 -> #REF! | AY79: =#REF!*AY$151 -> #REF! | AZ79: =#REF!*AZ$151 -> #REF! | BA79: =#REF!*BA$151 -> #REF! | BB79: =SUM(AE79:AG79)-AH79 -> 0
A80: Mainframe | B80: Yes | E80: 9999 | F80: LINC MF-JPN | G80: LINC | H80: A subsystem developed in-house. As a business domain, it mainly handles LINC integration used at new contracts (a function to check industry-shared contract limits and other functions through collaboration with the Life Insurance Association). It is basically built with COBOL, and except for the LIFECOMM integration part, almost no assembler is used. | I80: contract management | J80: Core Insurance Systems Group 34956 | K80: Policy Admin Systems Team 34957 | L80: MetLife IT Hosted/Supported | M80: Core Business Application | N80: Production | O80: AD Supported | P80: Y | Q80: Global Technology & Operations | R80: No | S80: Yes | T80: Other#Mainframe | V80: COBOL, MU(EASYPLUS), Assembler, JCL | W80: MetLife Owned Application Code | Y80: No | Z80: Y | AA80: Y | AB80: Y | AC80: N | AD80: N | AE80: 1.02875 | AF80: 0 | AG80: 0 | AH80: 1.02875 | AI80: 0.12920211 | AJ80: 0.514375 | AK80: 0.514375 | AM80: =AH80*(1-AI80) -> 0.89583333 | AN80: =VLOOKUP($E80,'Capgemini PResence and HC'!$B$2:$G$143,4,0) -> N | AO80: =VLOOKUP($E80,'Capgemini PResence and HC'!$B$2:$G$143,2,0) -> 0 | AP80: =VLOOKUP($E80,'Capgemini PResence and HC'!$B$2:$G$143,3,0) -> 0 | AQ80: =VLOOKUP($E80,'Capgemini PResence and HC'!$B$2:$G$143,6,0) -> 0 | AT80: =#REF!*AT$151 -> #REF! | AU80: =#REF!*AU$151 -> #REF! | AV80: =#REF!*AV$151 -> #REF! | AW80: =#REF!*AW$151 -> #REF! | AX80: =#REF!*AX$151 -> #REF! | AY80: =#REF!*AY$151 -> #REF! | AZ80: =#REF!*AZ$151 -> #REF! | BA80: =#REF!*BA$151 -> #REF! | BB80: =SUM(AE80:AG80)-AH80 -> 0
A81: Mainframe | B81: Yes | E81: 10001 | F81: A06TOG-JPN | G81: Group Policy Management System | H81: TOGAS is the mainframe system for managing MetLife Japan's insurance contracts. The COBOL/RPG program runs on the AS/400, performing registration, modification, and inquiry of contract information, form output, and batch processing. | I81: Corporate Related | J81: Core Insurance Systems Group 34956 | K81: Corporate Systems Team 34959 | L81: MetLife IT Hosted/Supported | M81: Core Business Application | N81: Production | O81: AD Supported | P81: Y | Q81: Global Technology & Operations | R81: No | S81: Yes | T81: Thick Client | V81: Other#RPG; Cobol | W81: MetLife Owned Application Code | Y81: No | Z81: Y | AA81: Y | AB81: Y | AC81: N | AD81: N | AE81: 2.7291667 | AF81: 3.025 | AG81: 0 | AH81: 5.7541667 | AI81: 0.34540188 | AJ81: 2.8770833 | AK81: 2.8770833 | AM81: =AH81*(1-AI81) -> 3.7666667 | AN81: =VLOOKUP($E81,'Capgemini PResence and HC'!$B$2:$G$143,4,0) -> N | AO81: =VLOOKUP($E81,'Capgemini PResence and HC'!$B$2:$G$143,2,0) -> 0 | AP81: =VLOOKUP($E81,'Capgemini PResence and HC'!$B$2:$G$143,3,0) -> 0 | AQ81: =VLOOKUP($E81,'Capgemini PResence and HC'!$B$2:$G$143,6,0) -> 0 | AT81: =#REF!*AT$151 -> #REF! | AU81: =#REF!*AU$151 -> #REF! | AV81: =#REF!*AV$151 -> #REF! | AW81: =#REF!*AW$151 -> #REF! | AX81: =#REF!*AX$151 -> #REF! | AY81: =#REF!*AY$151 -> #REF! | AZ81: =#REF!*AZ$151 -> #REF! | BA81: =#REF!*BA$151 -> #REF! | BB81: =SUM(AE81:AG81)-AH81 -> 0
A82: Cloud | B82: Yes | E82: 14377 | F82: Commission System Support Tool | G82: Support Tool for Commission System | H82: Reference and update EAI:9808 batch results, commission codes, and rates It has the following features Rate Expert: Registers and updates commission codes and rates. Transfer and Return Information Management System (NORIS): References and updates batch processing results for excellent producer evaluations, early erase returns, and transfer decisions. Non-life Insurance Commission Master Management System: Updates or references the Non-Life Insurance Commission Master. A/A General-Purpose Correction System: Generic references and updates files linked to agent code (files containing agent code as key entries) | I82: Corporate Related | J82: Core Insurance Systems Group 34956 | K82: Corporate Systems Team 34959 | L82: MetLife IT Hosted/Supported | M82: Core Business Application | N82: Production | O82: AD Supported | P82: N | Q82: Asia Region | R82: No | S82: Yes | T82: Other#Client-Server | V82: VB.NET | W82: MetLife Owned Application Code | Y82: No | Z82: Y | AA82: Y | AB82: Y | AC82: N | AD82: N | AE82: 0.59708333 | AF82: 0.12916667 | AG82: 0 | AH82: 0.72625 | AI82: 0.97991968 | AJ82: 0.363125 | AK82: 0.363125 | AM82: =AH82*(1-AI82) -> 0.014583333 | AN82: =VLOOKUP($E82,'Capgemini PResence and HC'!$B$2:$G$143,4,0) -> N | AO82: =VLOOKUP($E82,'Capgemini PResence and HC'!$B$2:$G$143,2,0) -> 0 | AP82: =VLOOKUP($E82,'Capgemini PResence and HC'!$B$2:$G$143,3,0) -> 0 | AQ82: =VLOOKUP($E82,'Capgemini PResence and HC'!$B$2:$G$143,6,0) -> 0 | AR82: =AH82-AS82 -> 0.71166667 | AS82: =AM82 -> 0.014583333 | AT82: =#REF!*AT$151 -> #REF! | AU82: =#REF!*AU$151 -> #REF! | AV82: =#REF!*AV$151 -> #REF! | AW82: =#REF!*AW$151 -> #REF! | AX82: =#REF!*AX$151 -> #REF! | AY82: =#REF!*AY$151 -> #REF! | AZ82: =#REF!*AZ$151 -> #REF! | BA82: =#REF!*BA$151 -> #REF! | BB82: =SUM(AE82:AG82)-AH82 -> 0
A83: Cloud | B83: Yes | E83: 11004 | F83: WAAICM-JPN | G83: ICM | H83: Varicent's package system (Incentive Compensation magement). As a business domain, it is responsible for calculating commissions and reporting them. Development is carried out using a proprietary non-code (GUI) development tool. | I83: Fee Management | J83: Core Insurance Systems Group 34956 | K83: Commission Systems Team 34958 | L83: MetLife IT Hosted/Supported | M83: Core Business Application | N83: Production | O83: AD Supported | P83: N | Q83: Asia Region | R83: No | S83: Yes | T83: Web Services | V83: JAVA; C#; Other#ETL JAVA(ADJP) SQL | W83: MetLife Owned Application Code | X83: Software as a Service (SaaS) | Y83: Yes | Z83: Y | AA83: Y | AB83: Y | AC83: N | AD83: N | AE83: 21.506125 | AF83: 7.7291667 | AG83: 0 | AH83: 29.235292 | AI83: 0.83096913 | AJ83: 14.617646 | AK83: 14.617646 | AM83: =AH83*(1-AI83) -> 4.9416667 | AN83: =VLOOKUP($E83,'Capgemini PResence and HC'!$B$2:$G$143,4,0) -> N | AO83: =VLOOKUP($E83,'Capgemini PResence and HC'!$B$2:$G$143,2,0) -> 0 | AP83: =VLOOKUP($E83,'Capgemini PResence and HC'!$B$2:$G$143,3,0) -> 0 | AQ83: =VLOOKUP($E83,'Capgemini PResence and HC'!$B$2:$G$143,6,0) -> 0 | AT83: =#REF!*AT$151 -> #REF! | AU83: =#REF!*AU$151 -> #REF! | AV83: =#REF!*AV$151 -> #REF! | AW83: =#REF!*AW$151 -> #REF! | AX83: =#REF!*AX$151 -> #REF! | AY83: =#REF!*AY$151 -> #REF! | AZ83: =#REF!*AZ$151 -> #REF! | BA83: =#REF!*BA$151 -> #REF! | BB83: =SUM(AE83:AG83)-AH83 -> 0
A84: Cloud | B84: Yes | E84: 9852 | F84: C03APO-JPN | G84: Apollocs | H84: A system that displays reports created in MainFrame on the Client Viewer screen In addition to the function of viewing and displaying forms, it offers search functions, information processing (for text and CSV output), sticky notes, markers, and other functions. | I84: Corporate Related | J84: Core Insurance Systems Group 34956 | K84: Corporate Systems Team 34959 | L84: MetLife IT Hosted/Supported | M84: Core Business Application | N84: Production | O84: AD Supported | P84: N | Q84: Global Technology & Operations | R84: No | S84: Yes | T84: Other#C/S | V84: Other#APOLLOCS | W84: Non-MetLife Owned Application Code (3rd party/COTS) | Y84: No | Z84: Y | AA84: N | AB84: Y | AC84: N | AD84: N | AE84: 0.50833333 | AF84: 0 | AG84: 0 | AH84: 0.50833333 | AI84: 0.36885246 | AJ84: 0.25416667 | AK84: 0.25416667 | AM84: =AH84*(1-AI84) -> 0.32083333 | AN84: =VLOOKUP($E84,'Capgemini PResence and HC'!$B$2:$G$143,4,0) -> N | AO84: =VLOOKUP($E84,'Capgemini PResence and HC'!$B$2:$G$143,2,0) -> 0 | AP84: =VLOOKUP($E84,'Capgemini PResence and HC'!$B$2:$G$143,3,0) -> 0 | AQ84: =VLOOKUP($E84,'Capgemini PResence and HC'!$B$2:$G$143,6,0) -> 0 | AR84: =AH84-AS84 -> 0.1875 | AS84: =AM84 -> 0.32083333 | BB84: =SUM(AE84:AG84)-AH84 -> 0
A85: Cloud | B85: Yes | E85: 11308 | F85: WGLBSR-JPN | G85: BSRec | H85: BSRec (Balance Sheet Reconciliation) is a balance sheet adjustment support system used within MetLife Japan. This is a web application that ingests balance data from various systems (PeopleSoft, Essbase, HFM, etc.) and streamlines reconciliation and adjustment work at the account level. | I85: Corporate Related | J85: Core Insurance Systems Group 34956 | K85: Corporate Systems Team 34959 | L85: MetLife IT Hosted/Supported | M85: Core Business Application | N85: Production | O85: AD Supported | P85: N | Q85: Financial Management Group | R85: No | S85: Yes | T85: Web Application Client | V85: JAVA | W85: MetLife Owned Application Code | Y85: No | Z85: Y | AA85: Y | AB85: Y | AC85: N | AD85: N | AE85: 0.48125 | AF85: 0.0625 | AG85: 0 | AH85: 0.54375 | AI85: 0.37931034 | AJ85: 0.271875 | AK85: 0.271875 | AM85: =AH85*(1-AI85) -> 0.3375 | AN85: =VLOOKUP($E85,'Capgemini PResence and HC'!$B$2:$G$143,4,0) -> N | AO85: =VLOOKUP($E85,'Capgemini PResence and HC'!$B$2:$G$143,2,0) -> 0 | AP85: =VLOOKUP($E85,'Capgemini PResence and HC'!$B$2:$G$143,3,0) -> 0 | AQ85: =VLOOKUP($E85,'Capgemini PResence and HC'!$B$2:$G$143,6,0) -> 0 | AR85: =AH85-AS85 -> 0.20625 | AS85: =AM85 -> 0.3375 | AT85: =#REF!*AT$151 -> #REF! | AU85: =#REF!*AU$151 -> #REF! | AV85: =#REF!*AV$151 -> #REF! | AW85: =#REF!*AW$151 -> #REF! | AX85: =#REF!*AX$151 -> #REF! | AY85: =#REF!*AY$151 -> #REF! | AZ85: =#REF!*AZ$151 -> #REF! | BA85: =#REF!*BA$151 -> #REF! | BB85: =SUM(AE85:AG85)-AH85 -> 0
A86: Cloud | B86: Yes | E86: 11008 | F86: OMSTAT-JPN | G86: Conservation contract allowance system | H86: Conservation contract allowance system | I86: Marketing/Direct Business Related | J86: Customer and Channel Engineering 34961 | K86: Marketing and Leads Team 34964 | L86: MetLife IT Hosted/Supported | M86: Core Business Application | N86: Production | O86: AD Supported | P86: N | Q86: Asia Region | R86: No | S86: Yes | T86: Web Services | V86: JAVA | W86: MetLife Owned Application Code | Y86: No | Z86: Y | AA86: Y | AB86: Y | AC86: N | AD86: N | AE86: 0.13541667 | AF86: 0.016666667 | AG86: 0 | AH86: 0.15208333 | AI86: 0.52054795 | AJ86: 0.076041667 | AK86: 0.076041667 | AM86: =AH86*(1-AI86) -> 0.072916667 | AN86: =VLOOKUP($E86,'Capgemini PResence and HC'!$B$2:$G$143,4,0) -> N | AO86: =VLOOKUP($E86,'Capgemini PResence and HC'!$B$2:$G$143,2,0) -> 0 | AP86: =VLOOKUP($E86,'Capgemini PResence and HC'!$B$2:$G$143,3,0) -> 0 | AQ86: =VLOOKUP($E86,'Capgemini PResence and HC'!$B$2:$G$143,6,0) -> 0 | AT86: =#REF!*AT$151 -> #REF! | AU86: =#REF!*AU$151 -> #REF! | AV86: =#REF!*AV$151 -> #REF! | AW86: =#REF!*AW$151 -> #REF! | AX86: =#REF!*AX$151 -> #REF! | AY86: =#REF!*AY$151 -> #REF! | AZ86: =#REF!*AZ$151 -> #REF! | BA86: =#REF!*BA$151 -> #REF! | BB86: =SUM(AE86:AG86)-AH86 -> 0
A87: Cloud | B87: Yes | E87: 9940 | F87: WPSC2S-JPN | G87: Call Control System | H87: The outgoing call control system is a system that checks whether a prohibited call number has been registered before making a call. - Consists of four apps: - Outgoing Regulation Confirmation System (C2S) - Outgoing Restricted Telephone Number Inquiry System (C2SREF) - Outgoing Restricted Phone Number Download System (C2SDWL) - Outgoing Regulation Batch System (C2SBAT) | I87: Corporate Related | J87: Core Insurance Systems Group 34956 | K87: Corporate Systems Team 34959 | L87: MetLife IT Hosted/Supported | M87: Core Business Application | N87: Production | O87: AD Supported | P87: N | Q87: Asia Region | R87: No | S87: Yes | T87: Web Services | V87: JAVA | W87: MetLife Owned Application Code | Y87: No | Z87: Y | AA87: Y | AB87: Y | AC87: N | AD87: N | AE87: 0.3875 | AF87: 0.025 | AG87: 0 | AH87: 0.4125 | AI87: 0.81818182 | AJ87: 0.20625 | AK87: 0.20625 | AM87: =AH87*(1-AI87) -> 0.075 | AN87: =VLOOKUP($E87,'Capgemini PResence and HC'!$B$2:$G$143,4,0) -> N | AO87: =VLOOKUP($E87,'Capgemini PResence and HC'!$B$2:$G$143,2,0) -> 0 | AP87: =VLOOKUP($E87,'Capgemini PResence and HC'!$B$2:$G$143,3,0) -> 0 | AQ87: =VLOOKUP($E87,'Capgemini PResence and HC'!$B$2:$G$143,6,0) -> 0 | AR87: =AH87-AS87 -> 0.3375 | AS87: =AM87 -> 0.075 | AT87: =#REF!*AT$151 -> #REF! | AU87: =#REF!*AU$151 -> #REF! | AV87: =#REF!*AV$151 -> #REF! | AW87: =#REF!*AW$151 -> #REF! | AX87: =#REF!*AX$151 -> #REF! | AY87: =#REF!*AY$151 -> #REF! | AZ87: =#REF!*AZ$151 -> #REF! | BA87: =#REF!*BA$151 -> #REF! | BB87: =SUM(AE87:AG87)-AH87 -> 0
A88: Cloud | B88: Yes | E88: 9907 | F88: W13WWF-JPN | G88: Web work flow | H88: This system was developed to eliminate the exchange of forms via fax between headquarters and branches as part of personal information protection measures, and to enable web-based document exchange. | I88: Corporate Related | J88: Core Insurance Systems Group 34956 | K88: Corporate Systems Team 34959 | L88: MetLife IT Hosted/Supported | M88: Core Business Application | N88: Production | O88: AD Supported | P88: N | Q88: Global Technology & Operations | R88: No | S88: Yes | T88: Web Services | V88: JAVA | W88: MetLife Owned Application Code | Y88: No | Z88: Y | AA88: Y | AB88: Y | AC88: N | AD88: N | AE88: 0.38583333 | AF88: 0 | AG88: 0 | AH88: 0.38583333 | AI88: 0.35205184 | AJ88: 0.19291667 | AK88: 0.19291667 | AM88: =AH88*(1-AI88) -> 0.25 | AN88: =VLOOKUP($E88,'Capgemini PResence and HC'!$B$2:$G$143,4,0) -> N | AO88: =VLOOKUP($E88,'Capgemini PResence and HC'!$B$2:$G$143,2,0) -> 0 | AP88: =VLOOKUP($E88,'Capgemini PResence and HC'!$B$2:$G$143,3,0) -> 0 | AQ88: =VLOOKUP($E88,'Capgemini PResence and HC'!$B$2:$G$143,6,0) -> 0 | AR88: =AH88-AS88 -> 0.13583333 | AS88: =AM88 -> 0.25 | AT88: =#REF!*AT$151 -> #REF! | AU88: =#REF!*AU$151 -> #REF! | AV88: =#REF!*AV$151 -> #REF! | AW88: =#REF!*AW$151 -> #REF! | AX88: =#REF!*AX$151 -> #REF! | AY88: =#REF!*AY$151 -> #REF! | AZ88: =#REF!*AZ$151 -> #REF! | BA88: =#REF!*BA$151 -> #REF! | BB88: =SUM(AE88:AG88)-AH88 -> 0
A89: Cloud | B89: Yes | E89: 11012 | F89: WZZMNB-JPN | G89: My number management system | H89: My Number Management System | I89: Insurance Claims and Benefits Payment Related | J89: Customer Service and Operations Systems Group 34965 | K89: Claims Team 34968 | L89: MetLife IT Hosted/Supported | M89: Core Business Application | N89: Production | O89: AD Supported | P89: N | Q89: Global Technology & Operations | R89: No | S89: Yes | T89: Web Application Client | V89: JAVA | W89: MetLife Owned Application Code | Y89: No | Z89: Y | AA89: Y | AB89: Y | AC89: N | AD89: N | AE89: 1.6523333 | AF89: 0.29166667 | AG89: 0 | AH89: 1.944 | AI89: 0.83217593 | AJ89: 0.972 | AK89: 0.972 | AM89: =AH89*(1-AI89) -> 0.32625 | AN89: =VLOOKUP($E89,'Capgemini PResence and HC'!$B$2:$G$143,4,0) -> Y | AO89: =VLOOKUP($E89,'Capgemini PResence and HC'!$B$2:$G$143,2,0) -> 0 | AP89: =VLOOKUP($E89,'Capgemini PResence and HC'!$B$2:$G$143,3,0) -> 1 | AQ89: =VLOOKUP($E89,'Capgemini PResence and HC'!$B$2:$G$143,6,0) -> 0 | AT89: =#REF!*AT$151 -> #REF! | AU89: =#REF!*AU$151 -> #REF! | AV89: =#REF!*AV$151 -> #REF! | AW89: =#REF!*AW$151 -> #REF! | AX89: =#REF!*AX$151 -> #REF! | AY89: =#REF!*AY$151 -> #REF! | AZ89: =#REF!*AZ$151 -> #REF! | BA89: =#REF!*BA$151 -> #REF! | BB89: =SUM(AE89:AG89)-AH89 -> 0
A90: Data | B90: Yes | C90: Yes | D90: Informatica On Prem CDI-PC ETL platform undergoing modernization to Azure Sypanse through different vendor so AMS can be for Informatica Platform , future AD can be taken up post-modernization. Approx 9-10 CG FTCs support this currently. This app is marked as Priority Target for Transition - Transition Priority # 1 for "Data Platforms" Data validation, ETL testing will be handled by I&D; Non-functional testing by QA Testing team | E90: 11014 | F90: BCMETL-JPN | G90: Informatica Platform | H90: Common platform for Informatica for ETL, IDQ & Address Doctor | I90: Data Infrastructure | J90: Data Platforms Team 34980 | K90: Data Platforms Team 34980 | L90: MetLife IT Hosted/Supported | M90: Common Service Business Application | N90: Production | O90: AD Supported | P90: N | Q90: Global Technology & Operations | R90: No | S90: Yes | T90: Other#Informatica PowerCenter | V90: Other#Used UI for development and stored data as XML | W90: MetLife Owned Application Code | Y90: Yes | Z90: Y | AA90: Y | AB90: Y | AC90: Y | AD90: Y | AE90: 29.097917 | AF90: 6.825 | AG90: 6.85 | AH90: 42.772917 | AI90: 0.88284058 | AJ90: 21.386458 | AK90: 21.386458 | AL90: Considering AMS+AD over 3 years post initial Transition 1st Year, more Informatica FTCs% compared to Azure whereas 3rd Year only Azure FTCs Estimation Approach for AMS - based on assumed # of Incidents, Problem Tickets, SRs and CRs including minor enhancements, and YoY AI-driven productivity | AM90: =AH90*(1-AI90) -> 5.01125 | AN90: =VLOOKUP($E90,'Capgemini PResence and HC'!$B$2:$G$143,4,0) -> Y | AO90: =VLOOKUP($E90,'Capgemini PResence and HC'!$B$2:$G$143,2,0) -> 9 | AP90: =VLOOKUP($E90,'Capgemini PResence and HC'!$B$2:$G$143,3,0) -> 0 | AQ90: =VLOOKUP($E90,'Capgemini PResence and HC'!$B$2:$G$143,6,0) -> 9.45 | AT90: =#REF!*AT$151 -> #REF! | AU90: =#REF!*AU$151 -> #REF! | AV90: =#REF!*AV$151 -> #REF! | AW90: =#REF!*AW$151 -> #REF! | AX90: =#REF!*AX$151 -> #REF! | AY90: =#REF!*AY$151 -> #REF! | AZ90: =#REF!*AZ$151 -> #REF! | BA90: =#REF!*BA$151 -> #REF! | BB90: =SUM(AE90:AG90)-AH90 -> 0
A91: Digital | B91: Yes | E91: 11203 | F91: WPSCFC-JPN | G91: c-Force | H91: c-Force(SVD) was built on SFDC platform to improve the activity of sales quality and to promote more effective and efficient supervision of solicitors/agents. | I91: Sales / Insurance Recruitment | J91: Customer and Channel Engineering 34961 | K91: Distribution F2F Team 34962 | L91: MetLife IT Hosted/Supported | M91: Core Business Application | N91: Production | O91: AD Supported | P91: N | Q91: Asia Region | R91: No | S91: No | T91: Web Services | V91: Other#APEX;HTML; JavaScript | W91: Non-MetLife Owned Application Code (3rd party/COTS) | X91: Software as a Service (SaaS) | Y91: Yes | Z91: Y | AA91: Y | AB91: Y | AC91: N | AD91: Y | AE91: 20.833333 | AF91: 10.004167 | AG91: 12.725 | AH91: 43.5625 | AI91: 0.86915352 | AJ91: 21.78125 | AK91: 21.78125 | AL91: BSA, BA, ETL, TestRelated members are in the scope. | AM91: =AH91*(1-AI91) -> 5.7 | AN91: =VLOOKUP($E91,'Capgemini PResence and HC'!$B$2:$G$143,4,0) -> Y | AO91: =VLOOKUP($E91,'Capgemini PResence and HC'!$B$2:$G$143,2,0) -> 14 | AP91: =VLOOKUP($E91,'Capgemini PResence and HC'!$B$2:$G$143,3,0) -> 0 | AQ91: =VLOOKUP($E91,'Capgemini PResence and HC'!$B$2:$G$143,6,0) -> 16.5375 | AR91: =AE91-AS91 -> 15.133333 | AS91: =AM91 -> 5.7 | AT91: =#REF!*AT$151 -> #REF! | AU91: =#REF!*AU$151 -> #REF! | AV91: =#REF!*AV$151 -> #REF! | AW91: =#REF!*AW$151 -> #REF! | AX91: =#REF!*AX$151 -> #REF! | AY91: =#REF!*AY$151 -> #REF! | AZ91: =#REF!*AZ$151 -> #REF! | BA91: =#REF!*BA$151 -> #REF! | BB91: =SUM(AE91:AG91)-AH91 -> 0
A92: Cloud | B92: Yes | E92: 11005 | F92: WAACPS-JPN | G92: Commission and Performance System | H92: CPS (Commission Processing System) is a commission processing system. This system supports all operations related to the calculation, management, and payment processing of fees associated with sales activities. | I92: Corporate Related | J92: Core Insurance Systems Group 34956 | K92: Corporate Systems Team 34959 | L92: MetLife IT Hosted/Supported | M92: Core Business Application | N92: Production | O92: AD Supported | P92: N | Q92: Asia Region | R92: No | S92: Yes | T92: Web Services | V92: JAVA | W92: MetLife Owned Application Code | X92: Platform as a Service (PaaS) | Y92: Yes | Z92: Y | AA92: Y | AB92: Y | AC92: N | AD92: N | AE92: 0.3625 | AF92: 0.041666667 | AG92: 0.5 | AH92: 0.90416667 | AI92: 0.44700461 | AJ92: 0.45208333 | AK92: 0.45208333 | AM92: =AH92*(1-AI92) -> 0.5 | AN92: =VLOOKUP($E92,'Capgemini PResence and HC'!$B$2:$G$143,4,0) -> N | AO92: =VLOOKUP($E92,'Capgemini PResence and HC'!$B$2:$G$143,2,0) -> 0 | AP92: =VLOOKUP($E92,'Capgemini PResence and HC'!$B$2:$G$143,3,0) -> 0 | AQ92: =VLOOKUP($E92,'Capgemini PResence and HC'!$B$2:$G$143,6,0) -> 0 | AR92: =AH92-AS92 -> 0.40416667 | AS92: =AM92 -> 0.5 | AT92: =#REF!*AT$151 -> #REF! | AU92: =#REF!*AU$151 -> #REF! | AV92: =#REF!*AV$151 -> #REF! | AW92: =#REF!*AW$151 -> #REF! | AX92: =#REF!*AX$151 -> #REF! | AY92: =#REF!*AY$151 -> #REF! | AZ92: =#REF!*AZ$151 -> #REF! | BA92: =#REF!*BA$151 -> #REF! | BB92: =SUM(AE92:AG92)-AH92 -> 0
A93: Cloud | B93: Yes | E93: 9969 | F93: EAADRS-JPN | G93: Dr.SUM | H93: It is a packaged product that accumulates performance data such as new contract data, BUDGET data, and ESTIMATION data, as well as solicitation data such as A/A Master, as well as functions for querying and extracting information. | I93: Corporate Related | J93: Core Insurance Systems Group 34956 | K93: Corporate Systems Team 34959 | L93: MetLife IT Hosted/Supported | M93: Core Business Application | N93: Production | O93: AD Supported | P93: N | Q93: Asia Region | R93: No | S93: Yes | T93: Web Services | V93: JAVA | W93: Non-MetLife Owned Application Code (3rd party/COTS) | Y93: No | Z93: Y | AA93: Y | AB93: Y | AC93: N | AD93: N | AE93: 0.312375 | AF93: 0.025 | AG93: 0 | AH93: 0.337375 | AI93: 0.67580585 | AJ93: 0.1686875 | AK93: 0.1686875 | AM93: =AH93*(1-AI93) -> 0.109375 | AN93: =VLOOKUP($E93,'Capgemini PResence and HC'!$B$2:$G$143,4,0) -> N | AO93: =VLOOKUP($E93,'Capgemini PResence and HC'!$B$2:$G$143,2,0) -> 0 | AP93: =VLOOKUP($E93,'Capgemini PResence and HC'!$B$2:$G$143,3,0) -> 0 | AQ93: =VLOOKUP($E93,'Capgemini PResence and HC'!$B$2:$G$143,6,0) -> 0 | AR93: =AH93-AS93 -> 0.228 | AS93: =AM93 -> 0.109375 | AT93: =#REF!*AT$151 -> #REF! | AU93: =#REF!*AU$151 -> #REF! | AV93: =#REF!*AV$151 -> #REF! | AW93: =#REF!*AW$151 -> #REF! | AX93: =#REF!*AX$151 -> #REF! | AY93: =#REF!*AY$151 -> #REF! | AZ93: =#REF!*AZ$151 -> #REF! | BA93: =#REF!*BA$151 -> #REF! | BB93: =SUM(AE93:AG93)-AH93 -> 0
B94: Yes | E94: 11604 | F94: JP-RPASS | G94: JAPAN_BluePrism RPA | H94: Shared Service for Robotic Automatic to support automated data entry for existing business process that use manual data entry | I94: Storage and Preservation Related | J94: Customer Service and Operations Systems Group 34965 | K94: Policy Servicing Team 34967 | L94: MetLife IT Hosted/Supported | M94: Common Service Business Application | N94: Production | O94: AD Supported | P94: N | Q94: Global Technology & Operations | R94: No | S94: Yes | T94: Thick Client | V94: Other#COTS from BluePrism | W94: Non-MetLife Owned Application Code (3rd party/COTS) | Y94: No | Z94: Y | AA94: Y | AB94: Y | AC94: N | AD94: N | AE94: 5.6624583 | AF94: 4.075 | AG94: 0 | AH94: 9.7374583 | AI94: 0.8973038 | AJ94: 4.8687292 | AK94: 4.8687292 | AM94: =AH94*(1-AI94) -> 1 | AN94: =VLOOKUP($E94,'Capgemini PResence and HC'!$B$2:$G$143,4,0) -> N | AO94: =VLOOKUP($E94,'Capgemini PResence and HC'!$B$2:$G$143,2,0) -> 0 | AP94: =VLOOKUP($E94,'Capgemini PResence and HC'!$B$2:$G$143,3,0) -> 0 | AQ94: =VLOOKUP($E94,'Capgemini PResence and HC'!$B$2:$G$143,6,0) -> 0 | AT94: =#REF!*AT$151 -> #REF! | AU94: =#REF!*AU$151 -> #REF! | AV94: =#REF!*AV$151 -> #REF! | AW94: =#REF!*AW$151 -> #REF! | AX94: =#REF!*AX$151 -> #REF! | AY94: =#REF!*AY$151 -> #REF! | AZ94: =#REF!*AZ$151 -> #REF! | BA94: =#REF!*BA$151 -> #REF! | BB94: =SUM(AE94:AG94)-AH94 -> 0
A95: Cloud | B95: Yes | E95: 11893 | F95: W03CCP-JPN | G95: Customer Communication Preferences | H95: Communication preference of notifications for customers(policyholders/beneficiaries) like FX Notification/Annual report etc. The prefernces can be modified by business policy or customer request. | I95: Storage and Preservation Related | J95: Customer Service and Operations Systems Group 34965 | K95: Policy Servicing Team 34967 | L95: MetLife IT Hosted/Supported | M95: Core Business Application | N95: Production | O95: AD Supported | P95: N | Q95: Global Technology & Operations | R95: No | S95: Yes | T95: Web Application Client | V95: JAVA | W95: MetLife Owned Application Code | X95: Platform as a Service (PaaS) | Y95: Yes | Z95: Y | AA95: Y | AB95: Y | AC95: N | AD95: N | AE95: 0.2 | AF95: 0.2 | AG95: 0 | AH95: 0.35416667 | AI95: 0.56470588 | AJ95: 0.17708333 | AK95: 0.17708333 | AM95: =AH95*(1-AI95) -> 0.15416667 | AN95: =VLOOKUP($E95,'Capgemini PResence and HC'!$B$2:$G$143,4,0) -> Y | AO95: =VLOOKUP($E95,'Capgemini PResence and HC'!$B$2:$G$143,2,0) -> 0 | AP95: =VLOOKUP($E95,'Capgemini PResence and HC'!$B$2:$G$143,3,0) -> 1 | AQ95: =VLOOKUP($E95,'Capgemini PResence and HC'!$B$2:$G$143,6,0) -> 0 | AT95: =#REF!*AT$151 -> #REF! | AU95: =#REF!*AU$151 -> #REF! | AV95: =#REF!*AV$151 -> #REF! | AW95: =#REF!*AW$151 -> #REF! | AX95: =#REF!*AX$151 -> #REF! | AY95: =#REF!*AY$151 -> #REF! | AZ95: =#REF!*AZ$151 -> #REF! | BA95: =#REF!*BA$151 -> #REF! | BB95: =SUM(AE95:AG95)-AH95 -> 0.045833333
A96: Cloud | B96: Yes | E96: 11986 | F96: JP-Banca Report | G96: Japan Banca Report | H96: Report Engine creates illustration and application reports in PDF format based on the data sent from the Banca Paperless Front-End(GSSP) and send them back to the GSSP. Also, Report Engine receives requests from ETL which is new contracts interface and creates TIFF files. The report files are stored on the NAS server for reprinting. | I96: Sales / Insurance Recruitment | J96: Customer and Channel Engineering 34961 | K96: Distribution Banca Team 34963 | L96: MetLife IT Hosted/Supported | M96: Common Service Business Application | N96: Production | O96: AD Supported | P96: N | Q96: Asia Region | R96: No | S96: Yes | T96: Web Services | V96: JAVA | W96: MetLife Owned Application Code | X96: Infrastructure as a Service (IaaS); Platform as a Service (PaaS) | Y96: Yes | Z96: Y | AA96: Y | AB96: Y | AC96: N | AD96: N | AE96: 6 | AF96: 6 | AG96: 3 | AH96: 15 | AI96: 1 | AJ96: 7.5 | AK96: 7.5 | AM96: =AH96*(1-AI96) -> 0 | AN96: =VLOOKUP($E96,'Capgemini PResence and HC'!$B$2:$G$143,4,0) -> Y | AO96: =VLOOKUP($E96,'Capgemini PResence and HC'!$B$2:$G$143,2,0) -> 7 | AP96: =VLOOKUP($E96,'Capgemini PResence and HC'!$B$2:$G$143,3,0) -> 0 | AQ96: =VLOOKUP($E96,'Capgemini PResence and HC'!$B$2:$G$143,6,0) -> 8.0875 | AR96: =AE96-AS96 -> 6 | AS96: =AM96 -> 0 | AT96: =$AR96*AT$151 -> 0.44210526 | AU96: =$AR96*AU$151 -> 0.44210526 | AV96: =$AR96*AV$151 -> 2.3368421 | AW96: =$AR96*AW$151 -> 1.5789474 | AX96: =$AR96*AX$151 -> 0.31578947 | AY96: =$AR96*AY$151 -> 0.44210526 | AZ96: =$AR96*AZ$151 -> 0.44210526 | BA96: =$AS96*BA$151 -> 0 | BB96: =SUM(AE96:AG96)-AH96 -> 0
A97: Cloud | B97: Yes | E97: 12021 | F97: LPS-JPN(EUC081) | G97: Life Plan Simulation Japan | H97: Based on the life plan entered or selected for each customer, the simulation result output from the calculation engine in the package is displayed and printed. | I97: Marketing/Direct Business Related | J97: Customer and Channel Engineering 34961 | K97: Marketing and Leads Team 34964 | L97: MetLife IT Hosted/Vendor Supported | M97: Core Business Application | N97: Production | O97: Business Supported | P97: N | Q97: Asia Region | R97: No | S97: Yes | T97: Web Services | V97: PHP | W97: Non-MetLife Owned Application Code (3rd party/COTS) | Y97: No | Z97: Y | AA97: Y | AB97: Y | AC97: N | AD97: N | AM97: =AH97*(1-AI97) -> 0 | AN97: =VLOOKUP($E97,'Capgemini PResence and HC'!$B$2:$G$143,4,0) -> N | AO97: =VLOOKUP($E97,'Capgemini PResence and HC'!$B$2:$G$143,2,0) -> 0 | AP97: =VLOOKUP($E97,'Capgemini PResence and HC'!$B$2:$G$143,3,0) -> 0 | AQ97: =VLOOKUP($E97,'Capgemini PResence and HC'!$B$2:$G$143,6,0) -> 0 | AT97: =#REF!*AT$151 -> #REF! | AU97: =#REF!*AU$151 -> #REF! | AV97: =#REF!*AV$151 -> #REF! | AW97: =#REF!*AW$151 -> #REF! | AX97: =#REF!*AX$151 -> #REF! | AY97: =#REF!*AY$151 -> #REF! | AZ97: =#REF!*AZ$151 -> #REF! | BA97: =#REF!*BA$151 -> #REF! | BB97: =SUM(AE97:AG97)-AH97 -> 0
A98: Cloud | B98: Yes | E98: 12030 | F98: CIT-JPN(EUC082) | G98: Inheritance Tax Simulation | H98: Based on the life plan entered or selected for each customer, a simulation is created from the calculated values in the package. | I98: Marketing/Direct Business Related | J98: Customer and Channel Engineering 34961 | K98: Marketing and Leads Team 34964 | L98: MetLife IT Hosted/Vendor Supported | M98: Core Business Application | N98: Production | O98: Business Supported | P98: N | Q98: Asia Region | R98: No | S98: Yes | T98: Web Services | V98: JAVA | W98: Non-MetLife Owned Application Code (3rd party/COTS) | Y98: No | Z98: Y | AA98: Y | AB98: Y | AC98: N | AD98: N | AM98: =AH98*(1-AI98) -> 0 | AN98: =VLOOKUP($E98,'Capgemini PResence and HC'!$B$2:$G$143,4,0) -> N | AO98: =VLOOKUP($E98,'Capgemini PResence and HC'!$B$2:$G$143,2,0) -> 0 | AP98: =VLOOKUP($E98,'Capgemini PResence and HC'!$B$2:$G$143,3,0) -> 0 | AQ98: =VLOOKUP($E98,'Capgemini PResence and HC'!$B$2:$G$143,6,0) -> 0 | AT98: =#REF!*AT$151 -> #REF! | AU98: =#REF!*AU$151 -> #REF! | AV98: =#REF!*AV$151 -> #REF! | AW98: =#REF!*AW$151 -> #REF! | AX98: =#REF!*AX$151 -> #REF! | AY98: =#REF!*AY$151 -> #REF! | AZ98: =#REF!*AZ$151 -> #REF! | BA98: =#REF!*BA$151 -> #REF! | BB98: =SUM(AE98:AG98)-AH98 -> 0
A99: Cloud | B99: Yes | E99: 12117 | F99: K2 | G99: Japan K2 - Digital Workflows | H99: To provide core function for POS operation global digitization and automation by K2 solutions | I99: Storage and Preservation Related | J99: Customer Service and Operations Systems Group 34965 | K99: Policy Servicing Team 34967 | L99: MetLife IT Hosted/Supported | M99: Core Business Application | N99: Production | O99: AD Supported | P99: Y | Q99: Global Technology & Operations | R99: No | S99: Yes | T99: Web Services | V99: VB.NET | W99: Non-MetLife Owned Application Code (3rd party/COTS) | Y99: No | Z99: Y | AA99: Y | AB99: Y | AC99: N | AD99: N | AE99: 6 | AF99: 15.5375 | AG99: 11 | AH99: 62.642375 | AI99: 0.8631983 | AJ99: 31.321188 | AK99: 31.321188 | AM99: =AH99*(1-AI99) -> 8.5695833 | AN99: =VLOOKUP($E99,'Capgemini PResence and HC'!$B$2:$G$143,4,0) -> Y | AO99: =VLOOKUP($E99,'Capgemini PResence and HC'!$B$2:$G$143,2,0) -> 11 | AP99: =VLOOKUP($E99,'Capgemini PResence and HC'!$B$2:$G$143,3,0) -> 0 | AQ99: =VLOOKUP($E99,'Capgemini PResence and HC'!$B$2:$G$143,6,0) -> 7.228125 | AT99: =#REF!*AT$151 -> #REF! | AU99: =#REF!*AU$151 -> #REF! | AV99: =#REF!*AV$151 -> #REF! | AW99: =#REF!*AW$151 -> #REF! | AX99: =#REF!*AX$151 -> #REF! | AY99: =#REF!*AY$151 -> #REF! | AZ99: =#REF!*AZ$151 -> #REF! | BA99: =#REF!*BA$151 -> #REF! | BB99: =SUM(AE99:AG99)-AH99 -> -30.104875
E100: 12198 | F100: JP-PCI-RPASS | G100: Japan PCI Robotics Process Automation Service | H100: Shared Service for Robotic Automatic to support automated data entry for existing PCI related business process that use manual data entry | I100: Storage and Preservation Related | J100: Customer Service and Operations Systems Group 34965 | K100: Policy Servicing Team 34967 | L100: MetLife IT Hosted/Supported | M100: Common Service Business Application | N100: Production | O100: AD Supported | P100: N | Q100: Global Technology & Operations | R100: No | S100: Yes | T100: Other#Robotics platform | V100: Other#This is coded within blueprism | W100: Non-MetLife Owned Application Code (3rd party/COTS) | Y100: No | Z100: Y | AA100: Y | AB100: Y | AC100: Y | AD100: N | AE100: 1 | AF100: 2 | AG100: 0 | AH100: 3 | AJ100: 1.5 | AK100: 1.5 | AM100: =AH100*(1-AI100) -> 3 | AN100: =VLOOKUP($E100,'Capgemini PResence and HC'!$B$2:$G$143,4,0) -> N | AO100: =VLOOKUP($E100,'Capgemini PResence and HC'!$B$2:$G$143,2,0) -> 0 | AP100: =VLOOKUP($E100,'Capgemini PResence and HC'!$B$2:$G$143,3,0) -> 0 | AQ100: =VLOOKUP($E100,'Capgemini PResence and HC'!$B$2:$G$143,6,0) -> 0 | AT100: =#REF!*AT$151 -> #REF! | AU100: =#REF!*AU$151 -> #REF! | AV100: =#REF!*AV$151 -> #REF! | AW100: =#REF!*AW$151 -> #REF! | AX100: =#REF!*AX$151 -> #REF! | AY100: =#REF!*AY$151 -> #REF! | AZ100: =#REF!*AZ$151 -> #REF! | BA100: =#REF!*BA$151 -> #REF! | BB100: =SUM(AE100:AG100)-AH100 -> 0
A101: Cloud | B101: Yes | E101: 12520 | F101: RBRARS-JPN | G101: RBWF Report Automatic Recognition System | H101: New Contract Workflow for Online Shopping | I101: New Contract Related | J101: Customer Service and Operations Systems Group 34965 | K101: New Business Team 34966 | L101: Vendor Hosted/MetLife IT Supported | M101: Core Business Application | N101: Production | O101: Business Supported | P101: N | Q101: Global Technology & Operations | R101: No | S101: Yes | T101: Web Services | V101: JAVA | W101: MetLife Owned Application Code | Y101: Yes | Z101: Y | AA101: Y | AB101: Y | AC101: N | AD101: N | AE101: 0.125 | AF101: 0 | AG101: 0 | AH101: 0.125 | AI101: 1 | AJ101: 0.0625 | AK101: 0.0625 | AM101: =AH101*(1-AI101) -> 0 | AN101: =VLOOKUP($E101,'Capgemini PResence and HC'!$B$2:$G$143,4,0) -> Y | AO101: =VLOOKUP($E101,'Capgemini PResence and HC'!$B$2:$G$143,2,0) -> 0 | AP101: =VLOOKUP($E101,'Capgemini PResence and HC'!$B$2:$G$143,3,0) -> 1 | AQ101: =VLOOKUP($E101,'Capgemini PResence and HC'!$B$2:$G$143,6,0) -> 0 | AT101: =#REF!*AT$151 -> #REF! | AU101: =#REF!*AU$151 -> #REF! | AV101: =#REF!*AV$151 -> #REF! | AW101: =#REF!*AW$151 -> #REF! | AX101: =#REF!*AX$151 -> #REF! | AY101: =#REF!*AY$151 -> #REF! | AZ101: =#REF!*AZ$151 -> #REF! | BA101: =#REF!*BA$151 -> #REF! | BB101: =SUM(AE101:AG101)-AH101 -> 0
...

Sheet Sheet2

Sheet Capgemini PResence and HC
B1: EAI | C1: T3 HC | D1: CSO_QA ScopeHC | E1: Y/N | F1: CG Assgn | G1: Human momths | I1: This data is from Kiyohara sans sheet. Human Months is FTE equivalent which we will use
B2: 9629 | C2: 0 | D2: 0 | E2: N | F2: 0 | G2: 0
B3: 9796 | C3: 0 | D3: 0 | E3: N | F3: 0 | G3: 0
B4: 9800 | C4: 0 | D4: 0 | E4: N | F4: 0 | G4: 0
B5: 9801 | C5: 0 | D5: 0 | E5: N | F5: 0 | G5: 0
B6: 9802 | C6: 0 | D6: 0 | E6: N | F6: 0 | G6: 0
B7: 9803 | C7: 0 | D7: 0 | E7: N | F7: 0 | G7: 0
B8: 9804 | C8: 0 | D8: 0 | E8: N | F8: 0 | G8: 0
B9: 9805 | C9: 0 | D9: 0 | E9: N | F9: 0 | G9: 0
B10: 9806 | C10: 0 | D10: 0 | E10: N | F10: 0 | G10: 0
B11: 9807 | C11: 0 | D11: 0 | E11: N | F11: 0 | G11: 0
B12: 9808 | C12: 0 | D12: 0 | E12: N | F12: 0 | G12: 0
B13: 9810 | C13: 0 | D13: 0 | E13: N | F13: 0 | G13: 0
... B143: 14930 | C143: 0 | D143: 0 | E143: N | F143: 0 | G143: 0
