Workbook

Sheet README
A1: Insurance Claims and Benefits Payment Related — domain framework v2
A2: Six applications, 121.573 units, and the only 領域 in the estate whose SCOPE CHANGES inside the five years. C12WNC-JPN (POS Workflow) is marked Retire and is 28.8% of the domain; from Year 4 the baseline is 86.577 units. Pega for Claims and MDRS are both Maintain in target state — the earlier claim that they carry a zero Year-3 target was wrong. Two value streams: the Claims Platform runs as an agile pod from day one; Payment & Records runs as a 12-seat team until POS Workflow goes, then converts to pods.
A4: WHAT THIS 領域 IS
B5: Six applications, three archetypes | C5: OpenBatch 43.8 units, POS Workflow 35.0 and Pega 16.7 are archetype D at a 78% offshore ceiling; Annuity Info 22.0 is Japan-locked at 12%; MDRS and My Number are 4.1 units of long tail at 55%.
B6: It splits into a platform and a records estate | C6: VS1 — Pega (SaaS on Pega Cloud, no-code, 99% AD) plus OpenBatch (cloud-flagged, hybrid) — is 60.5 units and holds ALL 22.6 of the domain’s MGCC. VS2 is four Japanese-specification applications, one of them retiring.
B7: The only 領域 with material nearshore | C7: 9.589 units on C12WNC-JPN — roughly half of all the nearshore capacity in the portfolio. Every other 領域 modelled is Tokyo-and-India only. The NEAR rows in this workbook are live, not schema.
B8: FSI holds four applications | C8: 7.0 of the 85.449 vendor units — 8.2%. POS Workflow (9835) 2 · Annuity Info (9857) 2 · OpenBatch (13820) 2 · Pega (14322) 1. Taper 7 / 7 / 7 / 5 / 4, onshore Japan in every year, all inside the streams.
A9: C12WNC-JPN, 35.0 units and the only nearshore capacity in the portfolio at 9.589 units. The baseline drops to 86.577 from Year 4 and nearshore goes to zero with it.
B10: C12WNC-JPN is marked RETIRE, and it is 28.8% of the domain | C10: 35.0 units, business-critical, Japanese specifications, 9.6 units nearshore, and the entire Claims Processing ＆ Adjudication value stream. This model freezes scope at Year 1 as every domain model does, so that exposure is carried, not netted. It is the largest single disposition exposure in the estate and it has to be resolved with MetLife before the price is fixed.
B11: Offshore reaches the re-cut ceiling | C11: 30.0% today — the highest starting position in the estate, because MGCC is 22.6 units on day one. The design delivers 31.3 / 40.7 / 49.0 / 53.4 / 59.8% against a ceiling that re-cuts from 65.27% to 60.13% when POS Workflow leaves. Year 5 lands on it.
B12: The 50:50 closes with NO transfer | C12: Organic convergence alone takes Capgemini from 70.4% of the delivery population to 50.6% by Year 5. The transfer mechanic is left live but set to zero in every year.
A13: 0 / 22.3 / 35.5 / 40.5 / 49.9%, measured against the scope that remains — not against the frozen 121.573, which would read 64.3% and would be claiming MetLife’s retirement as our saving.
B14: MGCC has a HIGHER ceiling than we do here | C14: MGCC 48.60% against Capgemini 44.73%, because MGCC is a build-and-test population and 78.5% of this estate is archetype D — where Build and Test ceilings are the highest in the classifier. Adoption still puts us ahead on committed productivity (44.7% against 38.9% effective), but the underlying capability runs the other way. Worth saying out loud.
B15: The transfer is 11.6 people, and most of it goes to MetLife Japan | C15: Organic convergence only takes the ratio from 70.3% to 66.8% by Year 3 — MetLife's side is small and shrinks slowly. The transfer does the rest. We send 6.4 to MetLife Japan and 5.2 to MGCC rather than the portfolio default 35/65, because 84% of the Capgemini population is in Tokyo and people in Tokyo are re-badged to MetLife Japan.
B16: Headcount 121.6 → 59.3 | C16: Pod Library column K and Horizontal Teams column J are the people you hire for that role across the block. Every one is a whole number or a half — the grid check is clean in all five years. SIT Loading turns them into requisitions.
A17: THE ENGINE
B18: The role line is restated, heavily | C18: Appendix 3 records 82.9% of the vendor line as Developer, 1.00 unit of maintenance, ZERO project management and 0.775 of architecture, against 732 incidents, 1,161 changes and 439 batch jobs a year. We move 20.4 units out of Developer into BSA, Tester, Maintenance, PM and Other. Arithmetically neutral, and the largest restatement in the portfolio. It is the only red on the Change Control sheet.
B19: The Year-4 cliff is scope, not delivery | C19: Headcount falls 78.5 to 51.5 between Years 3 and 4. About 24 of those 27 people are POS Workflow retiring; roughly 3 are productivity. Year 4 pre-loads none of its own in-year gain for exactly that reason.
A20: Every Capgemini role runs across the years it exists with no gaps and no re-banding — a grade is fixed for the life of the seat. Each unit keeps a lead, a bilingual analyst, a tester and a support seat in every year; design authority moves to the horizontal layer in Year 4 when pods shrink to six. Testers and junior builders are E1/E2 and E1 seats exist in all five years.
B21: The role line needs the largest restatement in the estate | C21: Appendix 3 records ZERO project management and 1.00 maintenance unit across six applications carrying 732 incidents and 1,161 changes. 83% of the vendor population is booked as Developer. Restated to 4.50 maintenance, 3.50 PM and 2.50 architecture, taken from the developer line. Arithmetically neutral; MetLife should confirm.
B22: And MetLife's two views of run disagree by a factor of seven | C22: The maintenance role line says 1.00 unit. The AD / AMS effort split in the same spreadsheet implies 6.75. On a 122-person domain that is about six people of exposure, and it sets the AMS price.
B23: The disposition questions are the priority | C23: 44.3% of this 領域 is either marked Retire or carries a zero Year-3 target in MetLife's own model. No other 領域 comes close. Resolve before submission.

Sheet Basis & Assumptions
A1: Where every input comes from, and which ones are ours
A2: v2. Two value streams, a scope that drops 28.8% at Year 4, and 7 FSI seats introduced where v1 modelled no partner. What matters here is the provenance of each input: which are measured, which are restated, and which are domain overrides.
B4: Element | C4: Source | D4: Value used | E4: Status | F4: Note
B5: Baseline | C5: Appendix 3 v5, 6 applications | D5: effort 121.574 · FTC 85.449 · FTE 13.479 · MGCC 22.646 · onshore 71.626 · offshore 4.233 · nearshore 9.589 | E5: SOURCE | F5: Internally consistent: FTC + FTE + MGCC ties exactly to Total, and the three location lines tie exactly to FTC. No unallocated capacity to carry.
B6: Archetypes | C6: Golden Inventory v4, six-rule classifier | D6: D 3 / 95.479 · J 1 / 22.028 · T 2 / 4.067 | E6: SOURCE | F6: AI ceiling 44.71%, offshore ceiling 65.27%. Archetype D is 78.5% of the effort, which is what makes the productivity case; W05AMS-JPN at a 12% offshore ceiling is what caps the location case.
B7: Delivery method | C7: Appendix 3 v5 | D7: VS1 agile from Year 1; VS2 waterfall to Year 3, pods from Year 4 | E7: MEASURED | F7: Holding Payment & Records as a team to Year 3 caps the agile share at 49.7% and costs about 0.6 and 1.9 points of Year-2 and Year-3 capability. It is the conservative reading of a stream whose largest application is being retired.
B8: Adoption factors | C8: Portfolio default | D8: 1.00 / 0.85 / 0.55 / 0.80 — unchanged | E8: STANDARD | F8: No case for raising MetLife's commitment here. Unlike Common Service Platform this is a mostly waterfall, Japanese-specification estate, and MetLife's own staff are only 11.1% of it.
B9: Role line | C9: BSA 5.958 · DEV 70.899 · TEST 6.817 · MNT 1.000 · PM 0.000 · OTH 0.775 | D9: MNT 4.50 · PM 3.50 · OTH 2.50, taken from DEV | E9: RESTATED | F9: ZERO project management across six applications and three value streams, and 1.00 maintenance unit against 732 incidents and 1,161 changes. 83% of the vendor population booked as Developer — the highest in the estate. Arithmetically neutral; the total does not move.
B10: Partner | C10: FSI named FTC supplied by MetLife against four EAI IDs | D10: 7.000 of 85.449 vendor units — 8.2% | E10: DOMAIN DECISION | F10: v1 modelled no partner at all. Introducing 7 FSI splits the Year-1 vendor number into Capgemini 78.5 + FSI 7.0 and switches on the span-of-control drag. Onshore Japan in every year; taper 7 / 7 / 7 / 5 / 4.
B11: Transfer split | C11: Portfolio default 35% to MetLife Japan | D11: 55% to MetLife Japan · 45% to MGCC | E11: DOMAIN OVERRIDE | F11: 71.6 of 85.4 vendor units are in Tokyo — 84%, the most onshore-weighted Capgemini population of the 領域 modelled. The default assumes an offshore-weighted population being re-badged mostly into MGCC. Here that is backwards: people in Tokyo are re-badged to MetLife Japan.
B12: Disposition | C12: EA inventory v5, target-state columns | D12: C12WNC-JPN RETIRE — 34.997 units. Pega and MDRS Maintain. | E12: SOURCE | F12: ACTED ON, unlike v1. The baseline drops to 86.577 from Year 4 and the archetype ceilings re-cut with it. Pega (Maintain — Evolve, Year-3 target 8.4) and MDRS (Maintain — Patch, 1.1) are NOT under a disposition question; the v1 claim that they carry a zero Year-3 target was wrong.
B13: Disposition | C13: New in Appendix 3 v5 | D13: 50% vendor share · 55% per unit · 55% of build-and-test · continuous role coverage | E13: NEW | F13: All held in every year. Tightest single unit 58.3%; tightest build-and-test 56.0% in Year 4, held above the floor by growing the MGCC Application Support line in the horizontal layer from 0.5 to 7.5.
B14: Guardrails | C14: Portfolio standard | D14: ZERO — organic convergence reaches 50.6% on its own | E14: STANDARD | F14: The mechanic is live so a transfer can be priced if MetLife asks, but none is needed.
B15: Scope treatment | C15: Domain override, v2 | D15: Productivity measured on RETAINED scope | E15: DOMAIN OVERRIDE | F15: Year-5 commitment 49.9% on 86.577 units. On the frozen 121.573 baseline the same roster reads 64.3%, and the difference is MetLife’s retirement. Reporting the lower number is the defensible choice.
A17: HOW TO READ THE STATUS COLUMN
B18: • SOURCE — taken directly from Appendix 3 v5 or Golden Application Inventory v4. Not ours to change.
B19: • MEASURED — MetLife has supplied it and we use it as given, where an earlier version made us assume.
B20: • RESTATED — the client figure is internally impossible and we have changed it. Every restatement is arithmetically neutral: people move between role lines, the total does not. These go back to MetLife.
B21: • DOMAIN OVERRIDE — a portfolio default deliberately changed for this 領域, with the reason stated. These are solution decisions and should be defended as such in the review.
B22: • MODELLED — a construct of ours with no direct client source: partner plans, transfer sizing, conversion quarters. The assumptions most worth challenging.

Sheet Change Control
A1: Change control — what must still hold after you edit a seat count
A2: Pod Library column J and Horizontal Teams column I are INPUTS. You may change them. Holding the yearly total is necessary but not sufficient — these are the other things that have to survive the edit. Every check below is live. Note that the headcount target is measured against the SCOPE BASELINE on Logic Tree row 46, which drops from 121.573 to 86.577 in Year 4 when POS Workflow retires.
A4: A. WHERE THESE NUMBERS GO
B5: • Pod Library J and Horizontal Teams I are hard-typed values, not formulas. Nothing upstream computes them — they are the design. Everything downstream is derived from them.
B6: • Seat Ledger reads them cell by cell (912 references to Pod Library, 630 to Horizontal Teams) and multiplies by the unit count on Pod Plan. Team Build-Up, Cost & Commercial, Inherited Workforce and Unit Cost Sensitivity are all SUMIFS over the Seat Ledger. Change a seat and every one of them moves.
B7: • THE ONE THAT SURPRISES PEOPLE: the Logic Tree reads the roster back. Partner seats (row 59) drive the partner share (row 60), the span-of-control factor (row 61), the applied operating-model gain (row 43), capability (row 45) and therefore the HEADCOUNT TARGET itself (row 53). Changing partner seats moves the target you are trying to hit. It converges, but it does not stand still.
B8: • What does NOT move: the effort baseline, the archetype mix, the AI and offshore ceilings, the realisation curve and the agile conversion quarters. Those are inputs on the Logic Tree and Delivery Mode.
A10: B. THE INVARIANTS — all of these must stay green
B11: Check | C11: Y1 | D11: Y2 | E11: Y3 | F11: Y4 | G11: Y5 | H11: Tolerance | I11: Status
B12: Headcount delivered minus Logic Tree target | C12: ='Team Build-Up'!C12 | D12: ='Team Build-Up'!D12 | E12: ='Team Build-Up'!E12 | F12: ='Team Build-Up'!F12 | G12: ='Team Build-Up'!G12 | H12: ± 1.5 | I12: =IF(MAX(ABS(C12),ABS(D12),ABS(E12),ABS(F12),ABS(G12))<=1.5,"OK","CHECK") | J12: The productivity commitment. If you add seats you must remove others.
B13: Capgemini share inside each POD | C13: =IFERROR((SUMIFS('Pod Library'!$J$5:$J$170,'Pod Library'!$B$5:$B$170,1,'Pod Library'!$C$5:$C$170,"POD",'Pod Library'!$I$5:$I$170,"FTC")+SUMIFS('Pod Library'!$J$5:$J$170,'Pod Library'!$B$5:$B$170,1,'Pod Library'!$C$5:$C$170,"POD",'Pod Library'!$I$5:$I$170,"PT"))/(SUMIFS('Pod Library'!$J$5:$J$170,'Pod Library'!$B$5:$B$170,1,'Pod Library'!$C$5:$C$170,"POD")),"n/a") | D13: =IFERROR((SUMIFS('Pod Library'!$J$5:$J$170,'Pod Library'!$B$5:$B$170,2,'Pod Library'!$C$5:$C$170,"POD",'Pod Library'!$I$5:$I$170,"FTC")+SUMIFS('Pod Library'!$J$5:$J$170,'Pod Library'!$B$5:$B$170,2,'Pod Library'!$C$5:$C$170,"POD",'Pod Library'!$I$5:$I$170,"PT"))/(SUMIFS('Pod Library'!$J$5:$J$170,'Pod Library'!$B$5:$B$170,2,'Pod Library'!$C$5:$C$170,"POD")),"n/a") | E13: =IFERROR((SUMIFS('Pod Library'!$J$5:$J$170,'Pod Library'!$B$5:$B$170,3,'Pod Library'!$C$5:$C$170,"POD",'Pod Library'!$I$5:$I$170,"FTC")+SUMIFS('Pod Library'!$J$5:$J$170,'Pod Library'!$B$5:$B$170,3,'Pod Library'!$C$5:$C$170,"POD",'Pod Library'!$I$5:$I$170,"PT"))/(SUMIFS('Pod Library'!$J$5:$J$170,'Pod Library'!$B$5:$B$170,3,'Pod Library'!$C$5:$C$170,"POD")),"n/a") | F13: =IFERROR((SUMIFS('Pod Library'!$J$5:$J$170,'Pod Library'!$B$5:$B$170,4,'Pod Library'!$C$5:$C$170,"POD",'Pod Library'!$I$5:$I$170,"FTC")+SUMIFS('Pod Library'!$J$5:$J$170,'Pod Library'!$B$5:$B$170,4,'Pod Library'!$C$5:$C$170,"POD",'Pod Library'!$I$5:$I$170,"PT"))/(SUMIFS('Pod Library'!$J$5:$J$170,'Pod Library'!$B$5:$B$170,4,'Pod Library'!$C$5:$C$170,"POD")),"n/a") | G13: =IFERROR((SUMIFS('Pod Library'!$J$5:$J$170,'Pod Library'!$B$5:$B$170,5,'Pod Library'!$C$5:$C$170,"POD",'Pod Library'!$I$5:$I$170,"FTC")+SUMIFS('Pod Library'!$J$5:$J$170,'Pod Library'!$B$5:$B$170,5,'Pod Library'!$C$5:$C$170,"POD",'Pod Library'!$I$5:$I$170,"PT"))/(SUMIFS('Pod Library'!$J$5:$J$170,'Pod Library'!$B$5:$B$170,5,'Pod Library'!$C$5:$C$170,"POD")),"n/a") | H13: ≥ 55% | I13: =IF(COUNTIF(C13:G13,"<0.5450")=0,"OK","CHECK") | J13: A POD in which Capgemini is a minority is one whose ways of working we do not set.
B14: Capgemini share inside each TEAM | C14: =IFERROR((SUMIFS('Pod Library'!$J$5:$J$170,'Pod Library'!$B$5:$B$170,1,'Pod Library'!$C$5:$C$170,"TEAM",'Pod Library'!$I$5:$I$170,"FTC")+SUMIFS('Pod Library'!$J$5:$J$170,'Pod Library'!$B$5:$B$170,1,'Pod Library'!$C$5:$C$170,"TEAM",'Pod Library'!$I$5:$I$170,"PT"))/(SUMIFS('Pod Library'!$J$5:$J$170,'Pod Library'!$B$5:$B$170,1,'Pod Library'!$C$5:$C$170,"TEAM")),"n/a") | D14: =IFERROR((SUMIFS('Pod Library'!$J$5:$J$170,'Pod Library'!$B$5:$B$170,2,'Pod Library'!$C$5:$C$170,"TEAM",'Pod Library'!$I$5:$I$170,"FTC")+SUMIFS('Pod Library'!$J$5:$J$170,'Pod Library'!$B$5:$B$170,2,'Pod Library'!$C$5:$C$170,"TEAM",'Pod Library'!$I$5:$I$170,"PT"))/(SUMIFS('Pod Library'!$J$5:$J$170,'Pod Library'!$B$5:$B$170,2,'Pod Library'!$C$5:$C$170,"TEAM")),"n/a") | E14: =IFERROR((SUMIFS('Pod Library'!$J$5:$J$170,'Pod Library'!$B$5:$B$170,3,'Pod Library'!$C$5:$C$170,"TEAM",'Pod Library'!$I$5:$I$170,"FTC")+SUMIFS('Pod Library'!$J$5:$J$170,'Pod Library'!$B$5:$B$170,3,'Pod Library'!$C$5:$C$170,"TEAM",'Pod Library'!$I$5:$I$170,"PT"))/(SUMIFS('Pod Library'!$J$5:$J$170,'Pod Library'!$B$5:$B$170,3,'Pod Library'!$C$5:$C$170,"TEAM")),"n/a") | F14: =IFERROR((SUMIFS('Pod Library'!$J$5:$J$170,'Pod Library'!$B$5:$B$170,4,'Pod Library'!$C$5:$C$170,"TEAM",'Pod Library'!$I$5:$I$170,"FTC")+SUMIFS('Pod Library'!$J$5:$J$170,'Pod Library'!$B$5:$B$170,4,'Pod Library'!$C$5:$C$170,"TEAM",'Pod Library'!$I$5:$I$170,"PT"))/(SUMIFS('Pod Library'!$J$5:$J$170,'Pod Library'!$B$5:$B$170,4,'Pod Library'!$C$5:$C$170,"TEAM")),"n/a") | G14: =IFERROR((SUMIFS('Pod Library'!$J$5:$J$170,'Pod Library'!$B$5:$B$170,5,'Pod Library'!$C$5:$C$170,"TEAM",'Pod Library'!$I$5:$I$170,"FTC")+SUMIFS('Pod Library'!$J$5:$J$170,'Pod Library'!$B$5:$B$170,5,'Pod Library'!$C$5:$C$170,"TEAM",'Pod Library'!$I$5:$I$170,"PT"))/(SUMIFS('Pod Library'!$J$5:$J$170,'Pod Library'!$B$5:$B$170,5,'Pod Library'!$C$5:$C$170,"TEAM")),"n/a") | H14: ≥ 55% | I14: =IF(COUNTIF(C14:G14,"<0.5450")=0,"OK","CHECK") | J14: A TEAM in which Capgemini is a minority is one whose ways of working we do not set. VS2 runs as a team only in Years 1-3, at 91.7% / 91.7% / 91.7%. The POD row covers VS1 in all five years and VS2 from Year 4; the tightest single unit in any year is 58.3%.
B15: Capgemini share of the delivery population | C15: =IFERROR((SUMIFS('Seat Ledger'!$M$5:$M$287,'Seat Ledger'!$B$5:$B$287,1,'Seat Ledger'!$J$5:$J$287,"FTC")+SUMIFS('Seat Ledger'!$M$5:$M$287,'Seat Ledger'!$B$5:$B$287,1,'Seat Ledger'!$J$5:$J$287,"PT"))/(SUMIFS('Seat Ledger'!$M$5:$M$287,'Seat Ledger'!$B$5:$B$287,1)),0) | D15: =IFERROR((SUMIFS('Seat Ledger'!$M$5:$M$287,'Seat Ledger'!$B$5:$B$287,2,'Seat Ledger'!$J$5:$J$287,"FTC")+SUMIFS('Seat Ledger'!$M$5:$M$287,'Seat Ledger'!$B$5:$B$287,2,'Seat Ledger'!$J$5:$J$287,"PT"))/(SUMIFS('Seat Ledger'!$M$5:$M$287,'Seat Ledger'!$B$5:$B$287,2)),0) | E15: =IFERROR((SUMIFS('Seat Ledger'!$M$5:$M$287,'Seat Ledger'!$B$5:$B$287,3,'Seat Ledger'!$J$5:$J$287,"FTC")+SUMIFS('Seat Ledger'!$M$5:$M$287,'Seat Ledger'!$B$5:$B$287,3,'Seat Ledger'!$J$5:$J$287,"PT"))/(SUMIFS('Seat Ledger'!$M$5:$M$287,'Seat Ledger'!$B$5:$B$287,3)),0) | F15: =IFERROR((SUMIFS('Seat Ledger'!$M$5:$M$287,'Seat Ledger'!$B$5:$B$287,4,'Seat Ledger'!$J$5:$J$287,"FTC")+SUMIFS('Seat Ledger'!$M$5:$M$287,'Seat Ledger'!$B$5:$B$287,4,'Seat Ledger'!$J$5:$J$287,"PT"))/(SUMIFS('Seat Ledger'!$M$5:$M$287,'Seat Ledger'!$B$5:$B$287,4)),0) | G15: =IFERROR((SUMIFS('Seat Ledger'!$M$5:$M$287,'Seat Ledger'!$B$5:$B$287,5,'Seat Ledger'!$J$5:$J$287,"FTC")+SUMIFS('Seat Ledger'!$M$5:$M$287,'Seat Ledger'!$B$5:$B$287,5,'Seat Ledger'!$J$5:$J$287,"PT"))/(SUMIFS('Seat Ledger'!$M$5:$M$287,'Seat Ledger'!$B$5:$B$287,5)),0) | H15: ≥ 50% | I15: =IF(COUNTIF(C15:G15,"<0.4950")=0,"OK","CHECK") | J15: Below half the roster we cannot carry a productivity commitment we do not control.
B16: Blocks deploying a non-whole number of people | C16: =SUMPRODUCT(('Pod Library'!$B$5:$B$170=1)*(ABS('Pod Library'!$K$5:$K$170*2-ROUND('Pod Library'!$K$5:$K$170*2,0))>0.01))+SUMPRODUCT(('Horizontal Teams'!$B$5:$B$95=1)*(ABS('Horizontal Teams'!$J$5:$J$95*2-ROUND('Horizontal Teams'!$J$5:$J$95*2,0))>0.01)) | D16: =SUMPRODUCT(('Pod Library'!$B$5:$B$170=2)*(ABS('Pod Library'!$K$5:$K$170*2-ROUND('Pod Library'!$K$5:$K$170*2,0))>0.01))+SUMPRODUCT(('Horizontal Teams'!$B$5:$B$95=2)*(ABS('Horizontal Teams'!$J$5:$J$95*2-ROUND('Horizontal Teams'!$J$5:$J$95*2,0))>0.01)) | E16: =SUMPRODUCT(('Pod Library'!$B$5:$B$170=3)*(ABS('Pod Library'!$K$5:$K$170*2-ROUND('Pod Library'!$K$5:$K$170*2,0))>0.01))+SUMPRODUCT(('Horizontal Teams'!$B$5:$B$95=3)*(ABS('Horizontal Teams'!$J$5:$J$95*2-ROUND('Horizontal Teams'!$J$5:$J$95*2,0))>0.01)) | F16: =SUMPRODUCT(('Pod Library'!$B$5:$B$170=4)*(ABS('Pod Library'!$K$5:$K$170*2-ROUND('Pod Library'!$K$5:$K$170*2,0))>0.01))+SUMPRODUCT(('Horizontal Teams'!$B$5:$B$95=4)*(ABS('Horizontal Teams'!$J$5:$J$95*2-ROUND('Horizontal Teams'!$J$5:$J$95*2,0))>0.01)) | G16: =SUMPRODUCT(('Pod Library'!$B$5:$B$170=5)*(ABS('Pod Library'!$K$5:$K$170*2-ROUND('Pod Library'!$K$5:$K$170*2,0))>0.01))+SUMPRODUCT(('Horizontal Teams'!$B$5:$B$95=5)*(ABS('Horizontal Teams'!$J$5:$J$95*2-ROUND('Horizontal Teams'!$J$5:$J$95*2,0))>0.01)) | H16: =0 | I16: =IF(SUM(C16:G16)=0,"OK","CHECK") | J16: Column K of the Pod Library and column J of Horizontal Teams are the people you hire for that role across the whole block. Every one is a whole number, or a half where one person covers two units INSIDE this domain. The seat ratio beside it is the modelling quantity and will not always be round — on a 28-team block, nine engineers is a ratio of 0.32.
B17: Horizontal roles that have fallen below 0.02 FTE | C17: =COUNTIFS('Horizontal Teams'!$B$5:$B$95,1,'Horizontal Teams'!$I$5:$I$95,"<0.02") | D17: =COUNTIFS('Horizontal Teams'!$B$5:$B$95,2,'Horizontal Teams'!$I$5:$I$95,"<0.02") | E17: =COUNTIFS('Horizontal Teams'!$B$5:$B$95,3,'Horizontal Teams'!$I$5:$I$95,"<0.02") | F17: =COUNTIFS('Horizontal Teams'!$B$5:$B$95,4,'Horizontal Teams'!$I$5:$I$95,"<0.02") | G17: =COUNTIFS('Horizontal Teams'!$B$5:$B$95,5,'Horizontal Teams'!$I$5:$I$95,"<0.02") | H17: =0 | I17: =IF(SUM(C17:G17)=0,"OK","CHECK") | J17: A domain cannot run without a delivery head, a service manager or an architect. If a role must genuinely end, delete the row rather than leaving it at zero.
B18: Year-1 reconciliation to Appendix 3 — worst line | C18: ='Team Build-Up'!E32 | H18: ± 2.6 | I18: =IF(ABS(C18)<=2.6,"OK","CHECK") | J18: Year 1 must reproduce the client's own numbers: effort, the sourcing split, all three locations and all six role lines. The tolerance is ± 2.6 because seats sit on a 0.5 grid and a Year-1 team seat carries a multiplier of 5 — one grid step is 2.5 people. That is the deliberate price of an anatomy that can be staffed. Moving a seat between bands is free; moving it between ROLE, LOCATION or SOURCING is what actually breaks this.
A20: C. WHAT GOES STALE AND WILL NOT WARN YOU
B21: • SOURCING & PRODUCTIVITY is static. It is produced outside Excel by the per-sourcing solver and pasted in. If you change seat counts, the pool ceilings, the organic-convergence table and the transfer solve on that sheet no longer describe this roster. Re-run the solver or treat the sheet as superseded.
B22: • SIT LOADING is static for the same reason. Re-generate it after any seat change, or the requisition plan will not match the ledger.
B23: • The TRANSFER on the Logic Tree is a typed input (rows 65-66), sized on the Year-3 exit position produced by the solver. Change the Year-3 roster materially and the transfer needs re-sizing, or the 50:50 will not land.
B24: • THE RULE OF THUMB. Re-banding a seat, renaming it, or moving it between pods is safe. Changing its ROLE, LOCATION or SOURCING is not — those are the attributes Year 1 reconciles on and the guardrails measure.

Sheet Logic Tree
A1: Logic Tree — ten parametric drivers, five years
A2: Amber cells are inputs. Everything else re-derives. Section F is rebuilt on the measured day-1 position.
A4: A. BASELINE — Appendix 3 v5, read and never edited
B5: Domain | C5: Insurance Claims and Benefits Payment Related
B6: Applications | C6: 6
B7: Total effort (units) | C7: 121.5735
B8: Current FTC reported (Capgemini + partner) | C8: 85.4485
B9: Current FTE | C9: 13.4792
B10: Current MGCC | C10: 22.6458
B11: — of which onshore Tokyo | C11: 71.6261 | J11: 28.87 offshore, 15.99 MGCC and 0.96 nearshore against 35.55 onshore. This domain already delivers most of its work away from Tokyo.
B12: — of which offshore | C12: 4.2333
B13: — of which nearshore | C13: 9.589
B14: — of which onsite | C14: 0
B15: Role: BSA | C15: 5.9583
B16: Role: Developer | C16: 70.8985 | J16: All six role lines are populated for this domain and are used exactly as reported. No restatement was needed.
B17: Role: Tester | C17: 6.8167
B18: Role: Maintenance | C18: 1
B19: Role: PM | C19: 0
B20: Role: Other | C20: 0.775
B21: AD effort (% of PRJ weighted) | C21: 114.8276
B22: Appendix 3 Year-3 target, each side | C22: 60.7868
B23: Ratio today — Capgemini share | C23: =C8/(C8+C9+C10)
B24: OFFSHORE TODAY — whole team, measured | C24: =(C12+C13+C10)/C7 | J24: 45.5% on day one — 28.87 offshore, 0.96 nearshore and 15.99 MGCC. The highest starting position of the eleven domains, which is why the ceiling here is reachable rather than aspirational.
A26: B. ARCHETYPE MIX — from the Golden Application Inventory v4
B27: Archetype | C27: Name | D27: Apps | E27: Effort | F27: Share | G27: AI ceiling | H27: Offshore ceiling
B28: D | C28: Distributed-proven | D28: 3 | E28: 95.4786 | F28: =E28/$E$33 | G28: 0.4825 | H28: 0.78
B29: J | C29: Japan-locked | D29: 1 | E29: 22.0283 | F29: =E29/$E$33 | G29: 0.304 | H29: 0.12
B30: T | C30: Long tail | D30: 2 | E30: 4.0665 | F30: =E30/$E$33 | G30: 0.39 | H30: 0.55
C33: Total | D33: =SUM(D28:D32) | E33: =SUM(E28:E32) | F33: =SUM(F28:F32)
B34: APPLICABLE AI CEILING | C34: =SUMPRODUCT($E$28:$E$32,$G$28:$G$32)/$E$33 | D34: 0.43273793 | E34: ← re-cut for Years 4-5, after POS Workflow leaves | J34: 44.71% on the Years 1-3 mix — three archetype-D applications carry 78.5% of the effort. Once POS Workflow leaves the surviving mix is slightly more Japan-locked as a share, so the ceiling re-cuts to 43.27% for Years 4-5.
B35: APPLICABLE OFFSHORE CEILING | C35: =SUMPRODUCT($E$28:$E$32,$H$28:$H$32)/$E$33 | D35: 0.60126834 | E35: ← re-cut for Years 4-5, after POS Workflow leaves | J35: 65.27% on the Years 1-3 mix, re-cut to 60.13% for Years 4-5. POS Workflow was archetype D at a 78% ceiling, so losing it LOWERS the blend: what remains is Annuity Info at 12% plus two long-tail applications at 55%, against the Claims Platform at 78%.
A37: C. REALISATION AND THE NON-AI COMPONENTS
B38: Driver | C38: Year 1 | D38: Year 2 | E38: Year 3 | F38: Year 4 | G38: Year 5 | H38: Basis
B39: AI realisation — share of ceiling | C39: 0.25 | D39: 0.55 | E39: 0.75 | F39: 0.85 | G39: 0.9 | J39: Adoption, guardrails and substrate maturity. Capped at 90%.
B40: Classical ADM productivity, cumulative | C40: 0.02 | D40: 0.05 | E40: 0.07 | F40: 0.09 | G40: 0.11 | J40: Standardisation, defect reduction, shift-left.
B41: Operating-model productivity, RAW | C41: 0.03 | D41: 0.06 | E41: 0.08 | F41: 0.1 | G41: 0.12 | J41: Pod consolidation and one release train — only available where the stream is agile.
B42: Agile share of the domain → from the Delivery Mode sheet | C42: ='Delivery Mode'!C20 | D42: ='Delivery Mode'!D20 | E42: ='Delivery Mode'!E20 | F42: ='Delivery Mode'!F20 | G42: ='Delivery Mode'!G20
B43: Operating-model productivity, APPLIED = raw × agile share × span-of-control factor | C43: =C41*C42*C61 | D43: =D41*D42*D61 | E43: =E41*E42*E61 | F43: =F41*F42*F61 | G43: =G41*G42*G61 | J43: Scaling by the agile share is what makes the operating-model gain earned rather than assumed. It costs 2.0 points of Year-1 capability: 16.0% unscaled against the 14.1% the model earns.
B44: AI-attributable productivity | C44: =$C$34*C39 | D44: =$C$34*D39 | E44: =$C$34*E39 | F44: =$D$34*F39 | G44: =$D$34*G39
B45: CAPABILITY EARNED by end of year | C45: =1-(1-C44)*(1-C40)*(1-C43) | D45: =1-(1-D44)*(1-D40)*(1-D43) | E45: =1-(1-E44)*(1-E40)*(1-E43) | F45: =1-(1-F44)*(1-F40)*(1-F43) | G45: =1-(1-G44)*(1-G40)*(1-G43)
B46: SCOPE BASELINE (units) — POS Workflow 9835 retires at the end of Year 3 | C46: 121.5735 | D46: 121.5735 | E46: 121.5735 | F46: 86.577 | G46: 86.577 | J46: THE ONLY DOMAIN WITH A SCOPE BREAK. C12WNC-JPN (POS Workflow, EAI 9835) is marked RETIRE in Appendix 3 v5 and is 34.997 of the 121.573 units — 28.8%. Years 1-3 are staffed against the full estate; Years 4 and 5 against the 86.577 units that remain. Productivity is therefore measured on RETAINED SCOPE, not against the frozen 121.573 — the retirement is MetLife’s saving, not ours, and claiming it would read as a 64% commitment we did not earn.
A47: D. CARRY-FORWARD AND PRE-LOAD — what is applied to headcount
B48: Pre-load fraction of the in-year gain | C48: 0.5
C49: Year 1 | D49: Year 2 | E49: Year 3 | F49: Year 4 | G49: Year 5
B50: Banked from the prior year | C50: =0 | D50: =C45 | E50: =D45 | F50: =E45 | G50: =F45
B51: Pre-load of this year's gain (ZERO in Year 4 — the year absorbs the retirement) | C51: =0 | D51: =0.5*(D45-C45) | E51: =0.5*(E45-D45) | F51: =0*(F45-E45) | G51: =0.5*(G45-F45)
B52: APPLIED TO STAFFING | C52: =C50+C51 | D52: =D50+D51 | E52: =E50+E51 | F52: =F50+F51 | G52: =G50+G51
B53: Headcount target = scope baseline x (1 - applied) | C53: =C46*(1-C52) | D53: =D46*(1-D52) | E53: =E46*(1-E52) | F53: =F46*(1-F52) | G53: =G46*(1-G52)
B54: EXIT YEAR 3 — full realisation, the point the transfer is struck | E54: =$E$46*(1-E45)
A56: E. PARTNER — the fourth sourcing type, and what it costs
B57: FSI IS THE NAMED SUB-CONTRACTOR ON FOUR APPLICATIONS, 7.0 of the 85.449 vendor units — 8.2%. POS Workflow (EAI 9835) 2 · Annuity Info (9857) 2 · OpenBatch (13820) 2 · Pega for Claims (14322) 1. Appendix 3 reports them inside the vendor number, so FTC reported = Capgemini + partner. The taper is 7 / 7 / 7 / 5 / 4: the two POS Workflow seats go with the application at the end of Year 3, then one OpenBatch seat in Year 5. All seven are onshore Japan in every year and none sits in a horizontal cell.
B58: Measure | C58: Year 1 | D58: Year 2 | E58: Year 3 | F58: Year 4 | G58: Year 5 | H58: Basis
B59: Partner seats — from the seat ledger | C59: ='Team Build-Up'!C46 | D59: ='Team Build-Up'!D46 | E59: ='Team Build-Up'!E46 | F59: ='Team Build-Up'!F46 | G59: ='Team Build-Up'!G46
B60: Partner share of the delivery population | C60: =IF('Team Build-Up'!C9=0,0,C59/'Team Build-Up'!C9) | D60: =IF('Team Build-Up'!D9=0,0,D59/'Team Build-Up'!D9) | E60: =IF('Team Build-Up'!E9=0,0,E59/'Team Build-Up'!E9) | F60: =IF('Team Build-Up'!F9=0,0,F59/'Team Build-Up'!F9) | G60: =IF('Team Build-Up'!G9=0,0,G59/'Team Build-Up'!G9) | J60: Partner seats cannot transfer to MetLife and they never leave Tokyo. They sit on the Capgemini side of the 50:50 permanently, and at an 8.2% Year-1 share they cost about 0.5 points of the operating-model gain through the span-of-control factor.
B61: Span-of-control factor = 1 − drag × partner share | C61: =1-$C$62*C60 | D61: =1-$C$62*D60 | E61: =1-$C$62*E60 | F61: =1-$C$62*F60 | G61: =1-$C$62*G60
B62: Partner drag — INPUT | C62: 0.6 | J62: A partner seat returns 40% of the operating-model gain a Capgemini seat does: two management chains, a contractual boundary on ways of working, slower standardisation. It costs nothing here because the partner share is zero, but the drag is the number to argue about if one appears.
A64: F. OFFSHORE — a measured start, a re-cut ceiling, and three bases to report on
B65: THE CEILING MOVES WHEN THE SCOPE MOVES. Years 1-3 blend to 65.27%: three archetype-D applications — OpenBatch, POS Workflow and Pega — carry 78.5% of the effort at a 78% ceiling. From Year 4 POS Workflow is gone and the blend re-cuts to 60.13%, because Annuity Info at a 12% ceiling becomes a quarter of what remains. The design reaches 59.8% in Year 5, on the re-cut ceiling.
B66: Driver | C66: Year 1 | D66: Year 2 | E66: Year 3 | F66: Year 4 | G66: Year 5 | H66: Basis
B67: Gap closure — share of (ceiling − today) reached | C67: 0.04 | D67: 0.3 | E67: 0.55 | F67: 0.78 | G67: 0.988 | J67: Year 1 holds the position it inherits. Years 4-5 are measured against the re-cut 60.13% ceiling and Year 5 lands on it: 31.3 / 40.7 / 49.0 / 53.4 / 59.8%. Nearshore — 9.589 units, all of it on POS Workflow and the only nearshore in the portfolio — tapers 9.5 / 6.0 / 3.0 and goes to ZERO in Year 4 with the application.
B68: TARGET OFFSHORE SHARE, whole team | C68: =$C$24+($C$35-$C$24)*C67 | D68: =$C$24+($C$35-$C$24)*D67 | E68: =$C$24+($C$35-$C$24)*E67 | F68: =$C$24+($D$35-$C$24)*F67 | G68: =$C$24+($D$35-$C$24)*G67
B69: Delivered — whole team | C69: ='Team Build-Up'!C54 | D69: ='Team Build-Up'!D54 | E69: ='Team Build-Up'!E54 | F69: ='Team Build-Up'!F54 | G69: ='Team Build-Up'!G54
B70: Delivered — vendor only (Capgemini + partner) | C70: ='Team Build-Up'!C55 | D70: ='Team Build-Up'!D55 | E70: ='Team Build-Up'!E55 | F70: ='Team Build-Up'!F55 | G70: ='Team Build-Up'!G55
B71: Delivered — Capgemini payroll only | C71: ='Team Build-Up'!C56 | D71: ='Team Build-Up'!D56 | E71: ='Team Build-Up'!E56 | F71: ='Team Build-Up'!F56 | G71: ='Team Build-Up'!G56 | J71: THE LINE THAT MATTERS COMMERCIALLY. Capgemini’s own payroll moves from 19.7% away from Tokyo in Year 1 to 58.3% by Year 5. The whole-team number is higher throughout because MGCC is 18.6% of the domain on day one and a third of it by Year 5.
A73: G. TRANSFER OF EMPLOYMENT — one event, end of Year 3, Capgemini payroll only
B74: Transfer in year | C74: Year 1 | D74: Year 2 | E74: Year 3 | F74: Year 4 | G74: Year 5
B75: Capgemini Japan to MetLife Japan (FTE) | C75: 0 | D75: 0 | E75: 0 | F75: 0 | G75: 0 | J75: NO TRANSFER IS NEEDED. Organic convergence takes Capgemini from 70.4% of the delivery population to 50.6% by Year 5 on its own, and the 50% floor is reached without moving a single person. The mechanic is left live so a transfer can be priced if MetLife asks for one.
B76: Capgemini India to MetLife MGCC | C76: 0 | D76: 0 | E76: 0 | F76: 0 | G76: 0
B77: Cumulative transferred | C77: =SUM($C$75:C76) | D77: =SUM($C$75:D76) | E77: =SUM($C$75:E76) | F77: =SUM($C$75:F76) | G77: =SUM($C$75:G76) | J77: Zero in every year. See the note on row 75.
A79: H. COST INDEX — relative only, onshore Tokyo E2 = 1.00
B80: Location | C80: E1 | D80: E2 | E80: E3 | F80: E4 | G80: E5
B81: Onshore Tokyo | C81: 0.72 | D81: 1 | E81: 1.35 | F81: 1.85 | G81: 2.55
B82: Offshore Hyderabad | C82: 0.22 | D82: 0.3 | E82: 0.42 | F82: 0.6 | G82: 0.85
B83: Nearshore | C83: 0.45 | D83: 0.62 | E83: 0.84 | F83: 1.15 | G83: 1.58
B84: Nearshore is ZERO on this domain — every unit is either Tokyo or India. The NEAR rows and the nearshore cost column are carried anyway so that all eleven domain models share one schema. | I84: key | J84: E1 | K84: E2 | L84: E3 | M84: E4 | N84: E5
I85: ON | J85: 0.72 | K85: 1 | L85: 1.35 | M85: 1.85 | N85: 2.55
I86: OFF | J86: 0.22 | K86: 0.3 | L86: 0.42 | M86: 0.6 | N86: 0.85
I87: NEAR | J87: 0.45 | K87: 0.62 | L87: 0.84 | M87: 1.15 | N87: 1.58
I88: Lookup block for the Seat Ledger. Mirrors the table on the left.

Sheet Sourcing & Productivity
A1: Sourcing and productivity — the same chain, applied differently to each population
A2: Productivity is not one number applied to everybody. The four populations do different work and we do not control all four, so each carries its own AI ceiling and its own adoption factor. Regenerated from the two-stream roster, with the ceiling re-cut from Year 4 when POS Workflow retires.
A4: A. WHY ONE RATE CANNOT APPLY TO ALL THREE — the Year-1 role mix
B5: Population | C5: Heads Y1 | D5: BSA | E5: Developer | F5: Tester | G5: Maint.
B6: FTC · Capgemini payroll | C6: 78.5 | D6: 0.10828025 | E6: 0.59235669 | F6: 0.13375796 | G6: 0.070063694 | I6: MetLife's own people are governance, domain SME and product ownership. MGCC is build and test. They are not doing the same work, so they cannot carry the same productivity rate.
B7: PT · Partner (sub-contracted) | C7: 7 | D7: 0.42857143 | E7: 0.57142857 | F7: 0 | G7: 0
B8: FTE · MetLife Japan | C8: 13.5 | D8: 0.25925926 | E8: 0 | F8: 0 | G8: 0.25925926
B9: MGCC · MetLife MGCC | C9: 22.5 | D9: 0 | E9: 0.64444444 | F9: 0.33333333 | G9: 0.022222222
A11: B. EACH POPULATION'S OWN AI CEILING AND ADOPTION — INPUT
B12: Population | C12: Own AI ceiling | D12: Adoption | E12: Effective ceiling | F12: vs domain blend
B13: FTC · Capgemini payroll | C13: 0.4533 | D13: 1 | E13: 0.4533 | F13: 0.0062 | I13: ADOPTION is the share of the ceiling each population can realise, and it is a judgement about AUTHORITY, not capability. We build the tooling and mandate it on our own payroll — so 1.00. Everything below that is somebody else’s decision. The four ceilings are scaled so the Year-1 head-weighted blend reproduces the Logic Tree’s 44.71%, and all four re-cut proportionally from Year 4.
B14: PT · Partner (sub-contracted) | C14: 0.4393 | D14: 0.85 | E14: 0.3734 | F14: -0.0737
B15: FTE · MetLife Japan | C15: 0.3747 | D15: 0.55 | E15: 0.2061 | F15: -0.241
B16: MGCC · MetLife MGCC | C16: 0.4712 | D16: 0.8 | E16: 0.3769 | F16: -0.0701
B17: Domain blended ceiling, Years 1-3 (44.71%; re-cut to 43.27% from Year 4) | C17: 0.4471
B18: Only the AI gate is scaled. Classical ADM productivity attaches to the work and the operating-model gain attaches to the delivery unit, so both flow to every population regardless of employer.
A20: C. WHAT EACH POPULATION IS THEREFORE ASKED TO DELIVER
B21: Applied to staffing | C21: Year 1 | D21: Year 2 | E21: Year 3 | F21: Year 4 | G21: Year 5
B22: FTC · Capgemini payroll | C22: 0 | D22: 0.2254 | E22: 0.3582 | F22: 0.4093 | G22: 0.5028 | I22: The headline commitment is 49.9% by Year 5, measured on RETAINED SCOPE — 86.577 units, not the frozen 121.573. Year 4 pre-loads none of its own in-year gain: that year absorbs the retirement of POS Workflow and the conversion of Payment & Records to pods, and the headcount fall from 78.5 to 51.5 is about 24 people of scope and 3 of productivity.
B23: PT · Partner (sub-contracted) | C23: 0 | D23: 0.1954 | E23: 0.3111 | F23: 0.3556 | G23: 0.4482
B24: FTE · MetLife Japan | C24: 0 | D24: 0.1328 | E24: 0.2125 | F24: 0.2433 | G24: 0.334
B25: MGCC · MetLife MGCC | C25: 0 | D25: 0.1968 | E25: 0.3132 | F25: 0.358 | G25: 0.4507
B26: Whole-domain commitment (the headline) | C26: 0 | D26: 0.223 | E26: 0.3546 | F26: 0.4051 | G26: 0.4986
A28: D. THE THREE-WAY COMMITMENT SPLIT
B29: CAPGEMINI COMMITS | C29: Our own headcount reduction, on our own payroll, on tooling and ways of working we control. This is contractible and we should contract it.
B30: METLIFE MUST DELIVER | C30: The reduction of MetLife Japan and MGCC headcount. We size it, we enable it and we report it — but redeploying MetLife's own people is MetLife's decision, and MGCC runs to its own utilisation targets. This should be a joint commitment with named owners, not a Capgemini SLA.
B31: JOINTLY DEPENDENT | C31: AI adoption on MetLife's side: tooling access, shared standards, common telemetry, and the substrate being used rather than merely available. If adoption lands below the factors in section B, the whole-team headcount misses even if Capgemini delivers in full.
A33: E. ORGANIC CONVERGENCE TO 50:50 — before any transfer
B34: Measure | C34: Year 1 | D34: Year 2 | E34: Year 3 | F34: Year 4 | G34: Year 5
B35: MetLife Japan (FTE) — own curve | C35: 13.5 | D35: 12 | E35: 10 | F35: 9 | G35: 6 | I35: MetLife’s populations follow their own slower curves and MGCC grows as a share — 18.6% of the domain on day one, 35.6% by Year 5. Capgemini absorbs the balance, taking its own book from 70.4% to 50.6% without a single transfer.
B36: MetLife MGCC — own curve | C36: 22.5 | D36: 21.5 | E36: 19.5 | F36: 15.5 | G36: 15.5
B37: Partner — per the partner plan | C37: 7 | D37: 7 | E37: 7 | F37: 5 | G37: 4
B38: Capgemini — absorbs the balance | C38: 78.5 | D38: 54 | E38: 42 | F38: 22 | G38: 18
B39: TOTAL = the headline commitment | C39: 121.5 | D39: 94.5 | E39: 78.5 | F39: 51.5 | G39: 43.5
B40: RATIO — Capgemini share | C40: 0.7037 | D40: 0.6455 | E40: 0.6242 | F40: 0.5243 | G40: 0.5057
B41: — of which productivity-driven | C41: 0 | D41: 0.223 | E41: 0.3546 | F41: 0.4051 | G41: 0.4986
B42: — of which RATIO-DRIVEN: fall in the Capgemini share since Year 1 | C42: 0 | D42: 0.0582 | E42: 0.0795 | F42: 0.1794 | G42: 0.198
B44: This is the mechanism that halves the transfer. Reaching the ratio by shrinking our own book is cheaper, lower-risk and entirely within our control; a transfer of employment is neither.
A46: F. THE GUARDRAILS — where organic convergence has to stop
B47: Test | C47: Year 1 | D47: Year 2 | E47: Year 3 | F47: Year 4 | G47: Year 5 | H47: Floor
B48: Capgemini share of the delivery population | C48: 0.7037 | D48: 0.6455 | E48: 0.6242 | F48: 0.5243 | G48: 0.5057 | H48: 0.5 | I48: THE POINT OF THE FLOOR. The build-and-test line is the tight one here: every MGCC unit in this 領域 sits on OpenBatch and Pega and MGCC is developer- and tester-heavy, so the MGCC Application Support line in the horizontal layer is grown deliberately from 0.5 to 7.0 to keep Capgemini above 55% of build-and-test in Years 4 and 5.
B49: Capgemini share of build-and-test seats | C49: 0.7349 | D49: 0.6885 | E49: 0.6804 | F49: 0.56 | G49: 0.5676 | H49: 0.55
B50: Capgemini share inside every single delivery unit | C50: held | D50: held | E50: held | F50: held | G50: held | H50: 0.55
A52: G. THE TRANSFER — only what organic convergence cannot reach
C53: Value
B54: Exit Year 3 headcount, full realisation | C54: 72.3225
B55: Vendor units at exit, after organic convergence | C55: 45.144
B56: Transferable pool — Capgemini payroll only | C56: 38.6948
B57: 50:50 requires each side to be | C57: 36.1612
B58: TRANSFER REQUIRED | C58: 8.9827
B59: Maximum transferable at the 70% cap | C59: 27.0864
B60: Transfer applied | C60: 0
B61: — to MetLife Japan | C61: 0
B62: — to MGCC | C62: 0
B63: RESIDUAL GAP TO 50:50 | C63: 8.9827
B64: Ratio reached at the Year-3 exit | C64: 0.6242

Sheet Delivery Mode
A1: Delivery mode — two streams, one conversion, one retirement
A2: Appendix 3 v5 gives the development method for every application. The estate is now cut on the line that matters: the Claims Platform (Pega, already agile and on Pega Cloud, plus OpenBatch, hybrid and cloud-flagged) runs as an agile pod from day one; everything else runs as a waterfall team until POS Workflow retires, and converts to pods in Year 4.
A4: A. MODE TODAY AND TARGET, BY VALUE STREAM — INPUT
B5: Value stream | C5: Effort | D5: Archetype | E5: Mode today | F5: Agile from | G5: Why
B6: VS1 · Claims Platform — Pega for Claims (14322) + OpenBatch (13820) | C6: 60.4821 | D6: D | E6: Agile / Hybrid | F6: Q1 | G6: Pega is SaaS on Pega Cloud, no-code, 99% AD, 14,772 lines — the cleanest application in the estate. OpenBatch is 43.8 units, cloud-flagged, hybrid method, and carries all 18.1 of the domain’s MGCC units. Runs as a POD from Year 1. | I6: The mode column is MetLife’s own data. Two streams: Claims Platform (2 applications, 60.482 units, 49.8% of the estate and 69.9% of it once POS Workflow retires) and Payment & Records (4 applications, 61.091 units falling to 26.095). The decision to argue about is not the method — it is whether Payment & Records converts before Year 4.
B7: VS2 · Payment & Records — POS Workflow (9835), Annuity Info (9857), Maturity & Deferral (14423), My Number (11012) | C7: 61.0913 | D7: D / J / T | E7: Waterfall | F7: Y4 | G7: POS Workflow is 35.0 of the 61.1 and is MARKED RETIRE — business-critical, Japanese specifications, and the only nearshore capacity in the portfolio at 9.589 units. Annuity Info behind it is 22.0 units of Japan-locked waterfall at a 12% offshore ceiling. Runs as a 12-seat TEAM to Year 3 and converts to PODs of 6 in Year 4.
B9: Total | C9: =SUM(C6:C7)
A11: B. AGILE SHARE BY YEAR — computed from the quarter each stream converts
B12: Value stream | C12: Year 1 | D12: Year 2 | E12: Year 3 | F12: Year 4 | G12: Year 5
B13: VS1 · Claims Platform | C13: 1 | D13: 1 | E13: 1 | F13: 1 | G13: 1
B14: VS2 · Payment & Records | C14: 0 | D14: 0 | E14: 0 | F14: 1 | G14: 1
B15: CSS
B16: Effort-weighted agile share of the domain | C16: 0.497492 | D16: 0.497492 | E16: 0.497492 | F16: 1 | G16: 1
B18: Delivery units this produces
B19: — agile PODS (VS1 all years; VS2 from Year 4) | C19: 5 | D19: 4 | E19: 3 | F19: 6 | G19: 5
B20: — agile share (feeds the Logic Tree) | C20: =C16 | D20: =D16 | E20: =E16 | F20: =F16 | G20: =G16
B21: — waterfall TEAMS of 12 (VS2, Years 1-3) | C21: 4 | D21: 3 | E21: 3 | F21: 0 | G21: 0
A23: C. WHY THIS MATTERS TO THE NUMBER
B24: • Operating-model productivity is only available where the stream runs as a pod. Payment & Records stays a waterfall team to Year 3, so the agile share is 49.7% for three years and only reaches 1.00 in Year 4. That costs about 0.6 points of Year-2 and 1.9 points of Year-3 capability against a fully converted estate — the price of not putting a pod structure on an application MetLife is retiring.
B25: • The waterfall TEAM is 12 seats with its own test cell and its own nearshore capacity. The agile POD is 10 seats in Year 1, 9, 8, then 6 in Years 4 and 5, with design authority moving to the horizontal layer when the pod shrinks to six. Every VS1 pod carries MGCC seats from day one — all 22.6 MGCC units sit on OpenBatch and Pega.
B26: • Year 4 is the structural break. POS Workflow retires, 34.997 units leave the scope, nearshore goes to zero, the two FSI seats on that application go with it, and Payment & Records converts from three teams of 12 to two pods of 6. Headcount falls 78.5 to 51.5 — about 24 of those 27 people are the retirement.
B27: • DECIDE whether Payment & Records converts earlier. Holding it waterfall to Year 3 is the conservative reading of an estate where the biggest application is being retired, and it is the single assumption most worth arguing.

Sheet AMS & Ticket Load
A1: AMS and ticket load — the run team sized from evidence, for the first time
A2: 732 incidents and 1,161 changes over 32 months, from Appendix 3 v5.
A4: A. RECORDED VOLUMES — 1 Jan 2024 to 31 Aug 2026
B5: Measure | C5: Volume | D5: Per month | E5: Per unit of effort | F5: Share
B6: P1 — critical | C6: 0 | D6: =C6/$C$17 | E6: =C6/'Logic Tree'!$C$7 | F6: =C6/$C$11 | I6: No P1 or P2 incidents at all in 32 months and 71% of incidents at P5. The estate is stable; the cost is in changing it, not in keeping it up.
B7: P2 — high | C7: 1 | D7: =C7/$C$17 | E7: =C7/'Logic Tree'!$C$7 | F7: =C7/$C$11
B8: P3 — medium | C8: 89 | D8: =C8/$C$17 | E8: =C8/'Logic Tree'!$C$7 | F8: =C8/$C$11
B9: P4 — low | C9: 143 | D9: =C9/$C$17 | E9: =C9/'Logic Tree'!$C$7 | F9: =C9/$C$11
B10: P5 — informational | C10: 499 | D10: =C10/$C$17 | E10: =C10/'Logic Tree'!$C$7 | F10: =C10/$C$11
B11: All incidents | C11: =SUM(C6:C10) | D11: =C11/$C$17 | E11: =C11/'Logic Tree'!$C$7
B12: Emergency change | C12: 34 | D12: =C12/$C$17 | E12: =C12/'Logic Tree'!$C$7 | F12: =C12/$C$15 | I12: 84% Standard and 4.3% Emergency. A high-volume, low-severity, highly repeatable change profile — the best automation case in the portfolio.
B13: Normal change | C13: 124 | D13: =C13/$C$17 | E13: =C13/'Logic Tree'!$C$7 | F13: =C13/$C$15
B14: Standard change | C14: 1003 | D14: =C14/$C$17 | E14: =C14/'Logic Tree'!$C$7 | F14: =C14/$C$15
B15: All changes | C15: =SUM(C12:C14) | D15: =C15/$C$17 | E15: =C15/'Logic Tree'!$C$7
B17: Observation window, months | C17: 32
A19: B. SIZING THE RUN TEAM — three independent bases, triangulated
B20: Basis | C20: Value | D20: Reading
B21: A. Maintenance role reported in Appendix 3 v5 | C21: ='Logic Tree'!C18 | D21: MetLife's own HEADCOUNT view. Populated here, unlike Contract Management, so it is usable.
B22: B. Run effort implied by the AD / AMS split = (1 − AD share) x effort | C22: ='Logic Tree'!C7-'Logic Tree'!C21 | D22: MetLife's own EFFORT view: 13.5% of 100.765 units. It implies 2.4 times the run population the role line does, and both numbers come from the same spreadsheet.
B23: Total demand items per month (incidents + changes) | C23: =(C11+C15)/C17 | D23: 2,536 items in 32 months — 25.2 per unit of effort against 14.6 on Sales. High for a three-application estate, and 84% of the changes are Standard.
B24: C. Throughput implied by basis A — items per person per month | C24: =IFERROR(C23/C21,0) | D24: If the role line is right, each run person absorbs this many items a month.
B25: C. Throughput implied by basis B | C25: =IFERROR(C23/C22,0) | D25: If the effort split is right, this is the rate. Industry L2 throughput on a modern data stack is 40 to 80 items per person per month; both of these sit far below it, which says these items carry investigation rather than triage.
B26: Run-facing seats in the Year-1 roster (Maintenance + Tester, all sourcing) | C26: ='Team Build-Up'!C64+'Team Build-Up'!C63 | D26: Model output. Sized on the role line, which is the binding Year-1 reconciliation constraint, and reported here against the other two bases rather than averaged with them.
A28: C. WHAT THE TICKET DATA CHANGES
B29: • MetLife's two views of the run population disagree by a factor of 2.4. The Maintenance role line says 5.67 units; the AD / AMS effort split says 13.64. This model follows the role line, because Year 1 has to reconcile to Appendix 3 line by line — but the difference is 8 people and it is a real commercial exposure. PUT THIS TO METLIFE before the AMS price is fixed.
B30: • The severity profile is benign and the change profile is not. No P1 or P2 incidents in 32 months and 71% of incidents at P5 — this estate is stable. But 1,730 changes on 100.8 units, 84% of them Standard, is a high change rate, and Standard changes on a cloud data platform are exactly what pipeline automation and a release train remove. That is where the operating-model productivity in this domain actually comes from.
B31: • Ticket density is 25.2 items per unit of effort against 14.6 on Sales — the highest of the domains modelled so far. Combined with a 13.5% run share it suggests run work is sitting inside the Developer line, which is the same pattern Sales shows and the reason this cross-check is worth running on every domain.
B32: • DO ask MetLife which of the two run figures governs, and ask for the ticket-to-effort mapping behind the AD / AMS split. On a three-application domain this is a short conversation with a material price attached.

Sheet Inventory
A1: Inventory — the 6 Insurance Claims and Benefits Payment Related applications from Appendix 3 v5
A2: Classified by the six-rule classifier on the Golden Application Inventory v4.
B4: Application | C4: Arch | D4: Effort | E4: FTC | F4: FTE | G4: Onshore | H4: Nearshore | I4: Nearsh % | J4: BSA | K4: Dev | L4: AD % | M4: Crit | N4: Method | O4: Spec lang | P4: Lines of code | Q4: Batches | R4: Incidents | S4: Changes | T4: Primary code language | U4: Value stream | V4: FSI FTC | W4: EAI ID | X4: Target state
B5: Claim Batch | C5: D | D5: 43.782083 | E5: 20.590417 | F5: 5.0458333 | G5: 17.357083 | H5: 0 | I5: =IFERROR($H5/$D5,0) | J5: 1.75 | K5: 12.24875 | L5: 0.9836596 | M5: N | N5: Hybrid | O5: Hybrid | P5: 711101 | Q5: 27 | R5: 46 | S5: 216 | T5: JAVA | U5: VS1 | V5: 2 | W5: 13820 | X5: Maintain
B6: C12WNC-JPN | C6: D | D6: 34.996542 | E6: 29.379875 | F6: 5.6166667 | G6: 19.790833 | H6: 9.5890417 | I6: =IFERROR($H6/$D6,0) | J6: 2 | K6: 27.379875 | L6: 0.90522873 | M6: Y | N6: Waterfall | O6: JP | P6: 0 | Q6: 170 | R6: 581 | S6: 608 | T6: VB.NET;C/C++;JAVA | U6: VS2 | V6: 2 | W6: 9835 | X6: RETIRE
B7: W05AMS-JPN | C7: J | D7: 22.028333 | E7: 20.211667 | F7: 1.8166667 | G7: 20.211667 | H7: 0 | I7: =IFERROR($H7/$D7,0) | J7: 1.9166667 | K7: 18.295 | L7: 0.92547477 | M7: Y | N7: Waterfall | O7: JP | P7: 0 | Q7: 186 | R7: 86 | S7: 272 | T7: JAVA, C#, VC | U7: VS2 | V7: 2 | W7: 9857 | X7: Maintain
B8: Pega for Claims | C8: D | D8: 16.7 | E8: 11.491667 | F8: 0.70833333 | G8: 10.491667 | H8: 0 | I8: =IFERROR($H8/$D8,0) | J8: 0.29166667 | K8: 9.2 | L8: 0.98702595 | M8: N | N8: Agile | O8: EN | P8: 14772 | Q8: 1 | R8: 5 | S8: 9 | T8: JAVA | U8: VS1 | V8: 1 | W8: 14322 | X8: Maintain (Evolve)
B9: MDRS | C9: T | D9: 2.1225 | E9: 2.1225 | F9: 0 | G9: 2.1225 | H9: 0 | I9: =IFERROR($H9/$D9,0) | J9: 0 | K9: 2.1225 | L9: 0.75068708 | M9: Y | N9: Waterfall | O9: JP | P9: 537636 | Q9: 38 | R9: 4 | S9: 37 | T9: VB.NET | U9: VS2 | V9: 0 | W9: 14423 | X9: Maintain (Patch)
B10: WZZMNB-JPN | C10: T | D10: 1.944 | E10: 1.6523333 | F10: 0.29166667 | G10: 1.6523333 | H10: 0 | I10: =IFERROR($H10/$D10,0) | J10: 0 | K10: 1.6523333 | L10: 0.83217593 | M10: N | N10: Waterfall | O10: JP | P10: 0 | Q10: 17 | R10: 10 | S10: 19 | T10: JAVA | U10: VS2 | V10: 0 | W10: 11012 | X10: Maintain
B11: TOTAL | D11: =SUM(D5:D10) | E11: =SUM(E5:E10) | F11: =SUM(F5:F10) | G11: =SUM(G5:G10) | H11: =SUM(H5:H10) | J11: =SUM(J5:J10) | K11: =SUM(K5:K10) | P11: =SUM(P5:P10) | Q11: =SUM(Q5:Q10) | R11: =SUM(R5:R10) | S11: =SUM(S5:S10) | U11: — | V11: =SUM(V5:V10)
B13: All six carry a development method and a specification language. Four run on Japanese specifications, two are cloud-flagged and none is marked 優先引継対象. Code volume totals 1.26 million lines across three applications. ONE application is under a disposition question, not three: C12WNC-JPN (POS Workflow, EAI 9835) is marked RETIRE and is 35.0 of the 121.6 units — 28.8%. Pega for Claims (14322) and MDRS (14423) are BOTH Maintain in all four target-state columns of the EA inventory, with Year-3 targets of 8.4 and 1.1 each side; the earlier claim that they carry a zero Year-3 target was wrong and is corrected here. Columns U-X are new: the value stream, the FSI sub-contracted FTC, the EAI ID and the target-state disposition.

Sheet Value Streams
A1: Delivery streams — two streams, and a scope that shrinks 28.8% at Year 4
A2: RESTATED. The estate is cut on platform versus records: VS1 is Pega for Claims plus OpenBatch — 2 applications, 60.482 units, both archetype D at a 78% offshore ceiling, and the home of all 22.6 MGCC units. VS2 is the other four. POS Workflow inside VS2 is 35.0 units and is marked RETIRE, so from Year 4 VS2 is 26.095 units and the domain baseline is 86.577.
B4: Code | C4: Value stream | D4: Apps | E4: Effort | F4: Arch | G4: Mode today | H4: Agile from | I4: Y1 pods | J4: Y2 | K4: Y3 | L4: Y4 | M4: Y5 | N4: Vendor position today
B5: VS1 | C5: Claims Platform — Pega & OpenBatch | D5: 2 | E5: 60.4821 | F5: D | G5: Agile / Hybrid | H5: Q1 | I5: 5p | J5: 4p | K5: 3p | L5: 4p | M5: 3p | N5: CG 29.1 · FSI 3.0 · MGCC 22.6
B6: VS2 | C6: Payment & Records | D6: 4 | E6: 61.0913 | F6: D / J / T | G6: Waterfall | H6: Y4 | I6: 4t | J6: 3t | K6: 3t | L6: 2p | M6: 2p | N6: CG 49.4 · FSI 4.0
C8: Total | D8: =SUM(D5:D6) | E8: =SUM(E5:E6)
B10: Counts read 'p' for pods and 't' for 12-seat teams. VS1 pod size is 10 / 9 / 8 / 6 / 6; VS2 teams are 12 seats and its Year-4/5 pods are 6. All seven FSI seats sit inside the streams — three in VS1 (OpenBatch 2, Pega 1) and four in VS2 (POS Workflow 2, Annuity Info 2) — onshore Japan, tapering 7 / 7 / 7 / 5 / 4 as POS Workflow retires in Year 4 and one OpenBatch seat comes out in Year 5. Note that every MGCC unit in this 領域 sits on OpenBatch (18.146) and Pega (4.5), which is why the MGCC surplus has to sit in the horizontal layer: at 4.5 per pod it would push Capgemini below the 55% floor inside VS1.

Sheet Pod Library
A1: Pod library — every seat, per value stream, with MetLife’s role taxonomy and four sourcing types
A2: INPUT. Two value streams. VS1 (Pega 14322 + OpenBatch 13820) runs as an agile POD in all five years. VS2 (POS Workflow 9835, Annuity Info 9857, Maturity & Deferral 14423, My Number 11012) runs as a 12-seat TEAM to Year 3 and converts to PODs of 6 in Year 4, once POS Workflow retires. Sourcing FTC = Capgemini payroll · PT = FSI, onshore Japan on four named applications · FTE = MetLife Japan · MGCC. Only FTC can transfer. Column J is the seat ratio inside one unit; column K is the people hired across every instance of that unit in that year, and every one is a whole number or a half.
B4: Year | C4: Unit | D4: Seat | E4: Role detail | F4: Role | G4: Exp | H4: Loc | I4: Sourcing | J4: Count | K4: People in the block
B5: 1 | C5: POD | D5: 1 | E5: MetLife Claims Product Owner | F5: PM | G5: E4 | H5: ON | I5: FTE | J5: 0.6 | K5: =J5*5
B6: 1 | C6: POD | D6: 2 | E6: MetLife Claims SME | F6: BSA | G6: E4 | H6: ON | I6: FTE | J6: 0.4 | K6: =J6*5
B7: 1 | C7: POD | D7: 3 | E7: FSI OpenBatch Developer (JP) — EAI 13820 | F7: DEV | G7: E3 | H7: ON | I7: PT | J7: 0.4 | K7: =J7*5
B8: 1 | C8: POD | D8: 4 | E8: FSI Pega Analyst (JP) — EAI 14322 | F8: BSA | G8: E3 | H8: ON | I8: PT | J8: 0.2 | K8: =J8*5
B9: 1 | C9: POD | D9: 5 | E9: Business Analyst (bilingual) — Claims Platform | F9: BSA | G9: E3 | H9: ON | I9: FTC | J9: 0.6 | K9: =J9*5
B10: 1 | C10: POD | D10: 6 | E10: Pod lead / senior engineer — Claims Platform | F10: DEV | G10: E4 | H10: ON | I10: FTC | J10: 1 | K10: =J10*5
B11: 1 | C11: POD | D11: 7 | E11: Senior Claims Engineer | F11: DEV | G11: E3 | H11: ON | I11: FTC | J11: 1.2 | K11: =J11*5
B12: 1 | C12: POD | D12: 8 | E12: Junior Claims Engineer | F12: DEV | G12: E2 | H12: ON | I12: FTC | J12: 1 | K12: =J12*5
B13: 1 | C13: POD | D13: 9 | E13: Quality Engineer (SDET) | F13: TEST | G13: E2 | H13: ON | I13: FTC | J13: 0.6 | K13: =J13*5
B14: 1 | C14: POD | D14: 10 | E14: Solution Architect — Claims Platform | F14: OTH | G14: E4 | H14: ON | I14: FTC | J14: 0.4 | K14: =J14*5
B15: 1 | C15: POD | D15: 11 | E15: Junior Claims Engineer — offshore | F15: DEV | G15: E2 | H15: OFF | I15: FTC | J15: 0.2 | K15: =J15*5
B16: 1 | C16: POD | D16: 12 | E16: Graduate Claims Engineer — offshore | F16: DEV | G16: E1 | H16: OFF | I16: FTC | J16: 0.2 | K16: =J16*5
... B20: 1 | C20: POD | D20: 16 | E20: MGCC Quality Engineer | F20: TEST | G20: E2 | H20: OFF | I20: MGCC | J20: 1 | K20: =J20*5
D21: POD size — Year 1 · VS1 | J21: =SUM(J5:J20) | K21: =SUM(K5:K20)
B23: 1 | C23: TEAM | D23: 1 | E23: MetLife Payments Product Owner | F23: PM | G23: E4 | H23: ON | I23: FTE | J23: 0.5 | K23: =J23*4
B24: 1 | C24: TEAM | D24: 2 | E24: MetLife Payments Operations Analyst | F24: MNT | G24: E3 | H24: ON | I24: FTE | J24: 0.375 | K24: =J24*4
B25: 1 | C25: TEAM | D25: 3 | E25: FSI POS Workflow Developer (JP) — EAI 9835 | F25: DEV | G25: E3 | H25: ON | I25: PT | J25: 0.5 | K25: =J25*4
B26: 1 | C26: TEAM | D26: 4 | E26: FSI Annuity Info Analyst (JP) — EAI 9857 | F26: BSA | G26: E3 | H26: ON | I26: PT | J26: 0.5 | K26: =J26*4
B27: 1 | C27: TEAM | D27: 5 | E27: Business Analyst (bilingual) — Payments | F27: BSA | G27: E3 | H27: ON | I27: FTC | J27: 0.75 | K27: =J27*4
B28: 1 | C28: TEAM | D28: 6 | E28: Team lead / senior engineer — Payments | F28: DEV | G28: E4 | H28: ON | I28: FTC | J28: 1 | K28: =J28*4
B29: 1 | C29: TEAM | D29: 7 | E29: Senior Application Developer (VB.NET / C++ / Java) | F29: DEV | G29: E3 | H29: ON | I29: FTC | J29: 2.5 | K29: =J29*4
B30: 1 | C30: TEAM | D30: 8 | E30: Junior Application Developer | F30: DEV | G30: E2 | H30: ON | I30: FTC | J30: 1.5 | K30: =J30*4
B31: 1 | C31: TEAM | D31: 9 | E31: Test Analyst | F31: TEST | G31: E3 | H31: ON | I31: FTC | J31: 0.875 | K31: =J31*4
B32: 1 | C32: TEAM | D32: 10 | E32: Application Support (L2) — Tokyo | F32: MNT | G32: E2 | H32: ON | I32: FTC | J32: 0.625 | K32: =J32*4
B33: 1 | C33: TEAM | D33: 11 | E33: Technical Lead / design authority — Payments | F33: OTH | G33: E4 | H33: ON | I33: FTC | J33: 0.25 | K33: =J33*4
B34: 1 | C34: TEAM | D34: 12 | E34: Senior Application Developer — nearshore | F34: DEV | G34: E3 | H34: NEAR | I34: FTC | J34: 1.875 | K34: =J34*4
... B36: 1 | C36: TEAM | D36: 14 | E36: Junior Application Developer — offshore | F36: DEV | G36: E2 | H36: OFF | I36: FTC | J36: 0.25 | K36: =J36*4
D37: TEAM size — Year 1 · VS2 | J37: =SUM(J23:J36) | K37: =SUM(K23:K36)
B39: 2 | C39: POD | D39: 1 | E39: MetLife Claims Product Owner | F39: PM | G39: E4 | H39: ON | I39: FTE | J39: 0.5 | K39: =J39*4
B40: 2 | C40: POD | D40: 2 | E40: MetLife Claims SME | F40: BSA | G40: E4 | H40: ON | I40: FTE | J40: 0.5 | K40: =J40*4
B41: 2 | C41: POD | D41: 3 | E41: FSI OpenBatch Developer (JP) — EAI 13820 | F41: DEV | G41: E3 | H41: ON | I41: PT | J41: 0.5 | K41: =J41*4
B42: 2 | C42: POD | D42: 4 | E42: FSI Pega Analyst (JP) — EAI 14322 | F42: BSA | G42: E3 | H42: ON | I42: PT | J42: 0.25 | K42: =J42*4
B43: 2 | C43: POD | D43: 5 | E43: Business Analyst (bilingual) — Claims Platform | F43: BSA | G43: E3 | H43: ON | I43: FTC | J43: 0.5 | K43: =J43*4
B44: 2 | C44: POD | D44: 6 | E44: Pod lead / senior engineer — Claims Platform | F44: DEV | G44: E4 | H44: ON | I44: FTC | J44: 0.75 | K44: =J44*4
B45: 2 | C45: POD | D45: 7 | E45: Senior Claims Engineer | F45: DEV | G45: E3 | H45: ON | I45: FTC | J45: 0.5 | K45: =J45*4
B46: 2 | C46: POD | D46: 8 | E46: Junior Claims Engineer | F46: DEV | G46: E2 | H46: ON | I46: FTC | J46: 0.5 | K46: =J46*4
B47: 2 | C47: POD | D47: 9 | E47: Quality Engineer (SDET) | F47: TEST | G47: E2 | H47: ON | I47: FTC | J47: 0.25 | K47: =J47*4
B48: 2 | C48: POD | D48: 10 | E48: Solution Architect — Claims Platform | F48: OTH | G48: E4 | H48: ON | I48: FTC | J48: 0.25 | K48: =J48*4
B49: 2 | C49: POD | D49: 11 | E49: Junior Claims Engineer — offshore | F49: DEV | G49: E2 | H49: OFF | I49: FTC | J49: 0.5 | K49: =J49*4
B50: 2 | C50: POD | D50: 12 | E50: Graduate Claims Engineer — offshore | F50: DEV | G50: E1 | H50: OFF | I50: FTC | J50: 0.25 | K50: =J50*4
... B54: 2 | C54: POD | D54: 16 | E54: MGCC Quality Engineer | F54: TEST | G54: E2 | H54: OFF | I54: MGCC | J54: 1 | K54: =J54*4
D55: POD size — Year 2 · VS1 | J55: =SUM(J39:J54) | K55: =SUM(K39:K54)
B57: 2 | C57: TEAM | D57: 1 | E57: MetLife Payments Product Owner | F57: PM | G57: E4 | H57: ON | I57: FTE | J57: 0.5 | K57: =J57*3
B58: 2 | C58: TEAM | D58: 2 | E58: MetLife Payments Operations Analyst | F58: MNT | G58: E3 | H58: ON | I58: FTE | J58: 0.5 | K58: =J58*3
B59: 2 | C59: TEAM | D59: 3 | E59: FSI POS Workflow Developer (JP) — EAI 9835 | F59: DEV | G59: E3 | H59: ON | I59: PT | J59: 0.66666667 | K59: =J59*3
B60: 2 | C60: TEAM | D60: 4 | E60: FSI Annuity Info Analyst (JP) — EAI 9857 | F60: BSA | G60: E3 | H60: ON | I60: PT | J60: 0.66666667 | K60: =J60*3
B61: 2 | C61: TEAM | D61: 5 | E61: Business Analyst (bilingual) — Payments | F61: BSA | G61: E3 | H61: ON | I61: FTC | J61: 0.83333333 | K61: =J61*3
B62: 2 | C62: TEAM | D62: 6 | E62: Team lead / senior engineer — Payments | F62: DEV | G62: E4 | H62: ON | I62: FTC | J62: 1 | K62: =J62*3
B63: 2 | C63: TEAM | D63: 7 | E63: Senior Application Developer (VB.NET / C++ / Java) | F63: DEV | G63: E3 | H63: ON | I63: FTC | J63: 2.1666667 | K63: =J63*3
B64: 2 | C64: TEAM | D64: 8 | E64: Junior Application Developer | F64: DEV | G64: E2 | H64: ON | I64: FTC | J64: 1 | K64: =J64*3
B65: 2 | C65: TEAM | D65: 9 | E65: Test Analyst | F65: TEST | G65: E3 | H65: ON | I65: FTC | J65: 0.83333333 | K65: =J65*3
B66: 2 | C66: TEAM | D66: 10 | E66: Application Support (L2) — Tokyo | F66: MNT | G66: E2 | H66: ON | I66: FTC | J66: 0.5 | K66: =J66*3
B67: 2 | C67: TEAM | D67: 11 | E67: Technical Lead / design authority — Payments | F67: OTH | G67: E4 | H67: ON | I67: FTC | J67: 0.33333333 | K67: =J67*3
B68: 2 | C68: TEAM | D68: 12 | E68: Senior Application Developer — nearshore | F68: DEV | G68: E3 | H68: NEAR | I68: FTC | J68: 1.5 | K68: =J68*3
... B71: 2 | C71: TEAM | D71: 15 | E71: Junior Test Engineer — offshore | F71: TEST | G71: E1 | H71: OFF | I71: FTC | J71: 0.16666667 | K71: =J71*3
D72: TEAM size — Year 2 · VS2 | J72: =SUM(J57:J71) | K72: =SUM(K57:K71)
B74: 3 | C74: POD | D74: 1 | E74: MetLife Claims Product Owner | F74: PM | G74: E4 | H74: ON | I74: FTE | J74: 0.33333333 | K74: =J74*3
B75: 3 | C75: POD | D75: 2 | E75: MetLife Claims SME | F75: BSA | G75: E4 | H75: ON | I75: FTE | J75: 0.16666667 | K75: =J75*3
B76: 3 | C76: POD | D76: 3 | E76: FSI OpenBatch Developer (JP) — EAI 13820 | F76: DEV | G76: E3 | H76: ON | I76: PT | J76: 0.66666667 | K76: =J76*3
B77: 3 | C77: POD | D77: 4 | E77: FSI Pega Analyst (JP) — EAI 14322 | F77: BSA | G77: E3 | H77: ON | I77: PT | J77: 0.33333333 | K77: =J77*3
B78: 3 | C78: POD | D78: 5 | E78: Business Analyst (bilingual) — Claims Platform | F78: BSA | G78: E3 | H78: ON | I78: FTC | J78: 0.33333333 | K78: =J78*3
B79: 3 | C79: POD | D79: 6 | E79: Pod lead / senior engineer — Claims Platform | F79: DEV | G79: E4 | H79: ON | I79: FTC | J79: 0.33333333 | K79: =J79*3
B80: 3 | C80: POD | D80: 7 | E80: Senior Claims Engineer | F80: DEV | G80: E3 | H80: ON | I80: FTC | J80: 0.16666667 | K80: =J80*3
B81: 3 | C81: POD | D81: 8 | E81: Junior Claims Engineer | F81: DEV | G81: E2 | H81: ON | I81: FTC | J81: 0.16666667 | K81: =J81*3
B82: 3 | C82: POD | D82: 9 | E82: Quality Engineer (SDET) | F82: TEST | G82: E2 | H82: ON | I82: FTC | J82: 0.16666667 | K82: =J82*3
B83: 3 | C83: POD | D83: 10 | E83: Solution Architect — Claims Platform | F83: OTH | G83: E4 | H83: ON | I83: FTC | J83: 0.33333333 | K83: =J83*3
B84: 3 | C84: POD | D84: 11 | E84: Junior Claims Engineer — offshore | F84: DEV | G84: E2 | H84: OFF | I84: FTC | J84: 0.83333333 | K84: =J84*3
B85: 3 | C85: POD | D85: 12 | E85: Graduate Claims Engineer — offshore | F85: DEV | G85: E1 | H85: OFF | I85: FTC | J85: 0.33333333 | K85: =J85*3
... B89: 3 | C89: POD | D89: 16 | E89: MGCC Quality Engineer | F89: TEST | G89: E2 | H89: OFF | I89: MGCC | J89: 1 | K89: =J89*3
D90: POD size — Year 3 · VS1 | J90: =SUM(J74:J89) | K90: =SUM(K74:K89)
B92: 3 | C92: TEAM | D92: 1 | E92: MetLife Payments Product Owner | F92: PM | G92: E4 | H92: ON | I92: FTE | J92: 0.5 | K92: =J92*3
B93: 3 | C93: TEAM | D93: 2 | E93: MetLife Payments Operations Analyst | F93: MNT | G93: E3 | H93: ON | I93: FTE | J93: 0.66666667 | K93: =J93*3
B94: 3 | C94: TEAM | D94: 3 | E94: FSI POS Workflow Developer (JP) — EAI 9835 | F94: DEV | G94: E3 | H94: ON | I94: PT | J94: 0.66666667 | K94: =J94*3
B95: 3 | C95: TEAM | D95: 4 | E95: FSI Annuity Info Analyst (JP) — EAI 9857 | F95: BSA | G95: E3 | H95: ON | I95: PT | J95: 0.66666667 | K95: =J95*3
B96: 3 | C96: TEAM | D96: 5 | E96: Business Analyst (bilingual) — Payments | F96: BSA | G96: E3 | H96: ON | I96: FTC | J96: 0.83333333 | K96: =J96*3
B97: 3 | C97: TEAM | D97: 6 | E97: Team lead / senior engineer — Payments | F97: DEV | G97: E4 | H97: ON | I97: FTC | J97: 1 | K97: =J97*3
B98: 3 | C98: TEAM | D98: 7 | E98: Senior Application Developer (VB.NET / C++ / Java) | F98: DEV | G98: E3 | H98: ON | I98: FTC | J98: 1.8333333 | K98: =J98*3
B99: 3 | C99: TEAM | D99: 8 | E99: Junior Application Developer | F99: DEV | G99: E2 | H99: ON | I99: FTC | J99: 0.5 | K99: =J99*3
B100: 3 | C100: TEAM | D100: 9 | E100: Test Analyst | F100: TEST | G100: E3 | H100: ON | I100: FTC | J100: 0.5 | K100: =J100*3
B101: 3 | C101: TEAM | D101: 10 | E101: Application Support (L2) — Tokyo | F101: MNT | G101: E2 | H101: ON | I101: FTC | J101: 0.5 | K101: =J101*3
B102: 3 | C102: TEAM | D102: 11 | E102: Technical Lead / design authority — Payments | F102: OTH | G102: E4 | H102: ON | I102: FTC | J102: 0.33333333 | K102: =J102*3
B103: 3 | C103: TEAM | D103: 12 | E103: Senior Application Developer — nearshore | F103: DEV | G103: E3 | H103: NEAR | I103: FTC | J103: 0.66666667 | K103: =J103*3
... B107: 3 | C107: TEAM | D107: 16 | E107: Application Support — offshore | F107: MNT | G107: E2 | H107: OFF | I107: FTC | J107: 0.66666667 | K107: =J107*3
D108: TEAM size — Year 3 · VS2 | J108: =SUM(J92:J107) | K108: =SUM(K92:K107)
B110: 4 | C110: POD | D110: 1 | E110: MetLife Claims Product Owner | F110: PM | G110: E4 | H110: ON | I110: FTE | J110: 0.25 | K110: =J110*4
B111: 4 | C111: POD | D111: 2 | E111: MetLife Claims SME | F111: BSA | G111: E4 | H111: ON | I111: FTE | J111: 0.125 | K111: =J111*4
B112: 4 | C112: POD | D112: 3 | E112: FSI OpenBatch Developer (JP) — EAI 13820 | F112: DEV | G112: E3 | H112: ON | I112: PT | J112: 0.5 | K112: =J112*4
B113: 4 | C113: POD | D113: 4 | E113: FSI Pega Analyst (JP) — EAI 14322 | F113: BSA | G113: E3 | H113: ON | I113: PT | J113: 0.25 | K113: =J113*4
B114: 4 | C114: POD | D114: 5 | E114: Business Analyst (bilingual) — Claims Platform | F114: BSA | G114: E3 | H114: ON | I114: FTC | J114: 0.25 | K114: =J114*4
B115: 4 | C115: POD | D115: 6 | E115: Pod lead / senior engineer — Claims Platform | F115: DEV | G115: E4 | H115: ON | I115: FTC | J115: 0.25 | K115: =J115*4
B116: 4 | C116: POD | D116: 7 | E116: Senior Claims Engineer | F116: DEV | G116: E3 | H116: ON | I116: FTC | J116: 0.125 | K116: =J116*4
B117: 4 | C117: POD | D117: 8 | E117: Junior Claims Engineer | F117: DEV | G117: E2 | H117: ON | I117: FTC | J117: 0.125 | K117: =J117*4
B118: 4 | C118: POD | D118: 9 | E118: Quality Engineer (SDET) | F118: TEST | G118: E2 | H118: ON | I118: FTC | J118: 0.125 | K118: =J118*4
B119: 4 | C119: POD | D119: 10 | E119: Junior Claims Engineer — offshore | F119: DEV | G119: E2 | H119: OFF | I119: FTC | J119: 0.875 | K119: =J119*4
B120: 4 | C120: POD | D120: 11 | E120: Graduate Claims Engineer — offshore | F120: DEV | G120: E1 | H120: OFF | I120: FTC | J120: 0.25 | K120: =J120*4
B121: 4 | C121: POD | D121: 12 | E121: Junior Quality Engineer — offshore | F121: TEST | G121: E1 | H121: OFF | I121: FTC | J121: 0.375 | K121: =J121*4
... B124: 4 | C124: POD | D124: 15 | E124: MGCC Quality Engineer | F124: TEST | G124: E2 | H124: OFF | I124: MGCC | J124: 0.75 | K124: =J124*4
...

Sheet Pod Plan
A1: Unit plan — how many instances of each value stream’s unit, per year
A2: INPUT. VS1 is an agile POD in every year (10 seats in Year 1, 9, 8, then 6). VS2 is a 12-seat TEAM to Year 3 and a POD of 6 from Year 4, when POS Workflow retires and 35.0 units leave the scope.
B4: Year | C4: VS | D4: Value stream | E4: Pods | F4: Teams | G4: Units | H4: People
B5: 1 | C5: VS1 | D5: Claims Platform — Pega & OpenBatch | E5: 5 | F5: 0 | G5: =E5+F5 | H5: =G5*SUM('Pod Library'!$J$5:$J$20)
B6: 1 | C6: VS2 | D6: Payment & Records | E6: 0 | F6: 4 | G6: =E6+F6 | H6: =G6*SUM('Pod Library'!$J$23:$J$36)
D7: Year 1 total | E7: =SUM(E5:E6) | F7: =SUM(F5:F6) | G7: =SUM(G5:G6) | H7: =SUM(H5:H6)
B9: 2 | C9: VS1 | D9: Claims Platform — Pega & OpenBatch | E9: 4 | F9: 0 | G9: =E9+F9 | H9: =G9*SUM('Pod Library'!$J$39:$J$54)
B10: 2 | C10: VS2 | D10: Payment & Records | E10: 0 | F10: 3 | G10: =E10+F10 | H10: =G10*SUM('Pod Library'!$J$57:$J$71)
D11: Year 2 total | E11: =SUM(E9:E10) | F11: =SUM(F9:F10) | G11: =SUM(G9:G10) | H11: =SUM(H9:H10)
B13: 3 | C13: VS1 | D13: Claims Platform — Pega & OpenBatch | E13: 3 | F13: 0 | G13: =E13+F13 | H13: =G13*SUM('Pod Library'!$J$74:$J$89)
B14: 3 | C14: VS2 | D14: Payment & Records | E14: 0 | F14: 3 | G14: =E14+F14 | H14: =G14*SUM('Pod Library'!$J$92:$J$107)
D15: Year 3 total | E15: =SUM(E13:E14) | F15: =SUM(F13:F14) | G15: =SUM(G13:G14) | H15: =SUM(H13:H14)
B17: 4 | C17: VS1 | D17: Claims Platform — Pega & OpenBatch | E17: 4 | F17: 0 | G17: =E17+F17 | H17: =G17*SUM('Pod Library'!$J$110:$J$124)
B18: 4 | C18: VS2 | D18: Payment & Records | E18: 2 | F18: 0 | G18: =E18+F18 | H18: =G18*SUM('Pod Library'!$J$127:$J$135)
D19: Year 4 total | E19: =SUM(E17:E18) | F19: =SUM(F17:F18) | G19: =SUM(G17:G18) | H19: =SUM(H17:H18)
B21: 5 | C21: VS1 | D21: Claims Platform — Pega & OpenBatch | E21: 3 | F21: 0 | G21: =E21+F21 | H21: =G21*SUM('Pod Library'!$J$138:$J$149)
B22: 5 | C22: VS2 | D22: Payment & Records | E22: 2 | F22: 0 | G22: =E22+F22 | H22: =G22*SUM('Pod Library'!$J$152:$J$160)
D23: Year 5 total | E23: =SUM(E21:E22) | F23: =SUM(F21:F22) | G23: =SUM(G21:G22) | H23: =SUM(H21:H22)

Sheet Horizontal Teams
A1: Horizontal teams — work that is not stream-bounded
A2: INPUT, defined per year. H1 is run and AMS. H2 is quality and payments assurance. H3 is delivery leadership and architecture — and from Year 4 it also holds the Claims Platform design authority, which leaves the pods when they shrink to six seats. No FSI seat sits here: all seven partner seats are inside the value streams.
B4: Year | C4: Team | D4: Role | E4: Role detail | F4: Exp | G4: Loc | H4: Sourcing | I4: Count | J4: People in the block
B5: 1 | C5: H1 | D5: PM | E5: Service Delivery Manager | F5: E5 | G5: ON | H5: FTC | I5: 1 | J5: =I5
B6: 1 | C6: H1 | D6: MNT | E6: Incident & Problem Analyst | F6: E3 | G6: ON | H6: FTC | I6: 2 | J6: =I6
B7: 1 | C7: H1 | D7: MNT | E7: L2 Application Support — offshore | F7: E2 | G7: OFF | H7: FTC | I7: 0.5 | J7: =I7
B8: 1 | C8: H1 | D8: OTH | E8: Observability / AIOps Engineer — offshore | F8: E3 | G8: OFF | H8: FTC | I8: 0.5 | J8: =I8
B9: 1 | C9: H1 | D9: MNT | E9: MetLife Operations Lead | F9: E4 | G9: ON | H9: FTE | I9: 2 | J9: =I9
B10: 1 | C10: H1 | D10: DEV | E10: MGCC Platform SRE | F10: E3 | G10: OFF | H10: MGCC | I10: 4.5 | J10: =I10
B11: 1 | C11: H1 | D11: MNT | E11: MGCC Application Support | F11: E2 | G11: OFF | H11: MGCC | I11: 0.5 | J11: =I11
B12: 1 | C12: H2 | D12: TEST | E12: Quality Lead | F12: E4 | G12: ON | H12: FTC | I12: 1 | J12: =I12
B13: 1 | C13: H2 | D13: TEST | E13: Performance & Batch Test Engineer — offshore | F13: E3 | G13: OFF | H13: FTC | I13: 0.5 | J13: =I13
B14: 1 | C14: H2 | D14: BSA | E14: Payments Assurance Analyst | F14: E3 | G14: ON | H14: FTC | I14: 2 | J14: =I14
B15: 1 | C15: H2 | D15: TEST | E15: MGCC Quality Engineer — regression cell | F15: E2 | G15: OFF | H15: MGCC | I15: 2.5 | J15: =I15
B16: 1 | C16: H2 | D16: BSA | E16: MetLife Payments Assurance Lead | F16: E4 | G16: ON | H16: FTE | I16: 1.5 | J16: =I16
... B21: 1 | C21: H3 | D21: PM | E21: MetLife Portfolio Lead | F21: E4 | G21: ON | H21: FTE | I21: 1.5 | J21: =I21
E22: Year 1 horizontal total | I22: =SUM(I5:I21) | J22: =SUM(J5:J21)
B24: 2 | C24: H1 | D24: PM | E24: Service Delivery Manager | F24: E5 | G24: ON | H24: FTC | I24: 0.5 | J24: =I24
B25: 2 | C25: H1 | D25: MNT | E25: Incident & Problem Analyst | F25: E3 | G25: ON | H25: FTC | I25: 1.5 | J25: =I25
B26: 2 | C26: H1 | D26: MNT | E26: L2 Application Support — offshore | F26: E2 | G26: OFF | H26: FTC | I26: 0.5 | J26: =I26
B27: 2 | C27: H1 | D27: OTH | E27: Observability / AIOps Engineer — offshore | F27: E3 | G27: OFF | H27: FTC | I27: 0.5 | J27: =I27
B28: 2 | C28: H1 | D28: MNT | E28: MetLife Operations Lead | F28: E4 | G28: ON | H28: FTE | I28: 2 | J28: =I28
B29: 2 | C29: H1 | D29: DEV | E29: MGCC Platform SRE | F29: E3 | G29: OFF | H29: MGCC | I29: 4.5 | J29: =I29
B30: 2 | C30: H1 | D30: MNT | E30: MGCC Application Support | F30: E2 | G30: OFF | H30: MGCC | I30: 2.5 | J30: =I30
B31: 2 | C31: H2 | D31: TEST | E31: Quality Lead | F31: E4 | G31: ON | H31: FTC | I31: 0.5 | J31: =I31
B32: 2 | C32: H2 | D32: TEST | E32: Performance & Batch Test Engineer — offshore | F32: E3 | G32: OFF | H32: FTC | I32: 0.5 | J32: =I32
B33: 2 | C33: H2 | D33: BSA | E33: Payments Assurance Analyst | F33: E3 | G33: ON | H33: FTC | I33: 1.5 | J33: =I33
B34: 2 | C34: H2 | D34: TEST | E34: MGCC Quality Engineer — regression cell | F34: E2 | G34: OFF | H34: MGCC | I34: 2.5 | J34: =I34
B35: 2 | C35: H2 | D35: BSA | E35: MetLife Payments Assurance Lead | F35: E4 | G35: ON | H35: FTE | I35: 1.5 | J35: =I35
... B40: 2 | C40: H3 | D40: PM | E40: MetLife Portfolio Lead | F40: E4 | G40: ON | H40: FTE | I40: 1.5 | J40: =I40
E41: Year 2 horizontal total | I41: =SUM(I24:I40) | J41: =SUM(J24:J40)
B43: 3 | C43: H1 | D43: PM | E43: Service Delivery Manager | F43: E5 | G43: ON | H43: FTC | I43: 0.5 | J43: =I43
B44: 3 | C44: H1 | D44: MNT | E44: Incident & Problem Analyst | F44: E3 | G44: ON | H44: FTC | I44: 0.5 | J44: =I44
B45: 3 | C45: H1 | D45: MNT | E45: L2 Application Support — offshore | F45: E2 | G45: OFF | H45: FTC | I45: 0.5 | J45: =I45
B46: 3 | C46: H1 | D46: OTH | E46: Observability / AIOps Engineer — offshore | F46: E3 | G46: OFF | H46: FTC | I46: 0.5 | J46: =I46
B47: 3 | C47: H1 | D47: MNT | E47: MetLife Operations Lead | F47: E4 | G47: ON | H47: FTE | I47: 2 | J47: =I47
B48: 3 | C48: H1 | D48: DEV | E48: MGCC Platform SRE | F48: E3 | G48: OFF | H48: MGCC | I48: 4 | J48: =I48
B49: 3 | C49: H1 | D49: MNT | E49: MGCC Application Support | F49: E2 | G49: OFF | H49: MGCC | I49: 4 | J49: =I49
B50: 3 | C50: H2 | D50: TEST | E50: MGCC Quality Engineer — regression cell | F50: E2 | G50: OFF | H50: MGCC | I50: 2.5 | J50: =I50
B51: 3 | C51: H2 | D51: BSA | E51: MetLife Payments Assurance Lead | F51: E4 | G51: ON | H51: FTE | I51: 1.5 | J51: =I51
B52: 3 | C52: H3 | D52: PM | E52: Domain Delivery Head | F52: E5 | G52: ON | H52: FTC | I52: 0.5 | J52: =I52
B53: 3 | C53: H3 | D53: OTH | E53: Chief Architect — Claims & Payments | F53: E5 | G53: ON | H53: FTC | I53: 0.5 | J53: =I53
B54: 3 | C54: H3 | D54: PM | E54: MetLife Portfolio Lead | F54: E4 | G54: ON | H54: FTE | I54: 1.5 | J54: =I54
E55: Year 3 horizontal total | I55: =SUM(I43:I54) | J55: =SUM(J43:J54)
B57: 4 | C57: H1 | D57: PM | E57: Service Delivery Manager | F57: E5 | G57: ON | H57: FTC | I57: 0.5 | J57: =I57
B58: 4 | C58: H1 | D58: MNT | E58: Incident & Problem Analyst | F58: E3 | G58: ON | H58: FTC | I58: 0.5 | J58: =I58
B59: 4 | C59: H1 | D59: MNT | E59: L2 Application Support — offshore | F59: E2 | G59: OFF | H59: FTC | I59: 0.5 | J59: =I59
B60: 4 | C60: H1 | D60: OTH | E60: Observability / AIOps Engineer — offshore | F60: E3 | G60: OFF | H60: FTC | I60: 0.5 | J60: =I60
B61: 4 | C61: H1 | D61: MNT | E61: MetLife Operations Lead | F61: E4 | G61: ON | H61: FTE | I61: 2 | J61: =I61
B62: 4 | C62: H1 | D62: DEV | E62: MGCC Platform SRE | F62: E3 | G62: OFF | H62: MGCC | I62: 1.5 | J62: =I62
B63: 4 | C63: H1 | D63: MNT | E63: MGCC Application Support | F63: E2 | G63: OFF | H63: MGCC | I63: 4.5 | J63: =I63
B64: 4 | C64: H2 | D64: TEST | E64: MGCC Quality Engineer — regression cell | F64: E2 | G64: OFF | H64: MGCC | I64: 0.5 | J64: =I64
B65: 4 | C65: H2 | D65: BSA | E65: MetLife Payments Assurance Lead | F65: E4 | G65: ON | H65: FTE | I65: 1.5 | J65: =I65
B66: 4 | C66: H3 | D66: PM | E66: Domain Delivery Head | F66: E5 | G66: ON | H66: FTC | I66: 0.5 | J66: =I66
B67: 4 | C67: H3 | D67: OTH | E67: Chief Architect — Claims & Payments | F67: E5 | G67: ON | H67: FTC | I67: 0.5 | J67: =I67
B68: 4 | C68: H3 | D68: OTH | E68: Solution Architect — Claims Platform | F68: E4 | G68: ON | H68: FTC | I68: 1 | J68: =I68
B69: 4 | C69: H3 | D69: PM | E69: MetLife Portfolio Lead | F69: E4 | G69: ON | H69: FTE | I69: 1.5 | J69: =I69
E70: Year 4 horizontal total | I70: =SUM(I57:I69) | J70: =SUM(J57:J69)
B72: 5 | C72: H1 | D72: PM | E72: Service Delivery Manager | F72: E5 | G72: ON | H72: FTC | I72: 0.5 | J72: =I72
B73: 5 | C73: H1 | D73: MNT | E73: MetLife Operations Lead | F73: E4 | G73: ON | H73: FTE | I73: 0.5 | J73: =I73
B74: 5 | C74: H1 | D74: DEV | E74: MGCC Platform SRE | F74: E3 | G74: OFF | H74: MGCC | I74: 1.5 | J74: =I74
B75: 5 | C75: H1 | D75: MNT | E75: MGCC Application Support | F75: E2 | G75: OFF | H75: MGCC | I75: 7.5 | J75: =I75
B76: 5 | C76: H2 | D76: TEST | E76: MGCC Quality Engineer — regression cell | F76: E2 | G76: OFF | H76: MGCC | I76: 0.5 | J76: =I76
B77: 5 | C77: H2 | D77: BSA | E77: MetLife Payments Assurance Lead | F77: E4 | G77: ON | H77: FTE | I77: 0.5 | J77: =I77
B78: 5 | C78: H3 | D78: PM | E78: Domain Delivery Head | F78: E5 | G78: ON | H78: FTC | I78: 0.5 | J78: =I78
B79: 5 | C79: H3 | D79: OTH | E79: Chief Architect — Claims & Payments | F79: E5 | G79: ON | H79: FTC | I79: 0.5 | J79: =I79
B80: 5 | C80: H3 | D80: OTH | E80: Solution Architect — Claims Platform | F80: E4 | G80: ON | H80: FTC | I80: 0.5 | J80: =I80
B81: 5 | C81: H3 | D81: PM | E81: MetLife Portfolio Lead | F81: E4 | G81: ON | H81: FTE | I81: 1 | J81: =I81
E82: Year 5 horizontal total | I82: =SUM(I72:I81) | J82: =SUM(J72:J81)
B84: H1 is sized from the incident and change load on the AMS sheet — 732 incidents, 1,161 changes and 439 batch jobs a year. The MGCC Application Support line grows deliberately from 0.5 to 7.0 across the five years: it is what holds Capgemini above the 55% build-and-test floor once MetLife’s captive centre becomes a third of the domain. H3 carries the architecture and release seats, and from Year 4 the Claims Platform Solution Architect moves here from the pods.

Sheet Team Build-Up
A1: Team build-up — and the Year-1 reconciliation to Appendix 3 v5
A2: Nothing on this sheet is typed. Section B is the test that matters: the roster has to be the client's own Year-1 position on effort, sourcing, location AND role.
A4: A. HEADCOUNT
B5: Measure | C5: Year 1 | D5: Year 2 | E5: Year 3 | F5: Year 4 | G5: Year 5
B6: People in agile pods (VS1 all years; VS2 from Year 4) | C6: =SUMIFS('Seat Ledger'!$M$5:$M$287,'Seat Ledger'!$B$5:$B$287,1,'Seat Ledger'!$C$5:$C$287,"POD") | D6: =SUMIFS('Seat Ledger'!$M$5:$M$287,'Seat Ledger'!$B$5:$B$287,2,'Seat Ledger'!$C$5:$C$287,"POD") | E6: =SUMIFS('Seat Ledger'!$M$5:$M$287,'Seat Ledger'!$B$5:$B$287,3,'Seat Ledger'!$C$5:$C$287,"POD") | F6: =SUMIFS('Seat Ledger'!$M$5:$M$287,'Seat Ledger'!$B$5:$B$287,4,'Seat Ledger'!$C$5:$C$287,"POD") | G6: =SUMIFS('Seat Ledger'!$M$5:$M$287,'Seat Ledger'!$B$5:$B$287,5,'Seat Ledger'!$C$5:$C$287,"POD")
B7: People in waterfall teams of 12 (VS2, Years 1-3) | C7: =SUMIFS('Seat Ledger'!$M$5:$M$287,'Seat Ledger'!$B$5:$B$287,1,'Seat Ledger'!$C$5:$C$287,"TEAM") | D7: =SUMIFS('Seat Ledger'!$M$5:$M$287,'Seat Ledger'!$B$5:$B$287,2,'Seat Ledger'!$C$5:$C$287,"TEAM") | E7: =SUMIFS('Seat Ledger'!$M$5:$M$287,'Seat Ledger'!$B$5:$B$287,3,'Seat Ledger'!$C$5:$C$287,"TEAM") | F7: =SUMIFS('Seat Ledger'!$M$5:$M$287,'Seat Ledger'!$B$5:$B$287,4,'Seat Ledger'!$C$5:$C$287,"TEAM") | G7: =SUMIFS('Seat Ledger'!$M$5:$M$287,'Seat Ledger'!$B$5:$B$287,5,'Seat Ledger'!$C$5:$C$287,"TEAM")
B8: People in horizontal teams | C8: =SUMIFS('Seat Ledger'!$M$5:$M$287,'Seat Ledger'!$B$5:$B$287,1,'Seat Ledger'!$C$5:$C$287,"HZ") | D8: =SUMIFS('Seat Ledger'!$M$5:$M$287,'Seat Ledger'!$B$5:$B$287,2,'Seat Ledger'!$C$5:$C$287,"HZ") | E8: =SUMIFS('Seat Ledger'!$M$5:$M$287,'Seat Ledger'!$B$5:$B$287,3,'Seat Ledger'!$C$5:$C$287,"HZ") | F8: =SUMIFS('Seat Ledger'!$M$5:$M$287,'Seat Ledger'!$B$5:$B$287,4,'Seat Ledger'!$C$5:$C$287,"HZ") | G8: =SUMIFS('Seat Ledger'!$M$5:$M$287,'Seat Ledger'!$B$5:$B$287,5,'Seat Ledger'!$C$5:$C$287,"HZ")
B9: TOTAL PEOPLE | C9: =SUM(C6:C8) | D9: =SUM(D6:D8) | E9: =SUM(E6:E8) | F9: =SUM(F6:F8) | G9: =SUM(G6:G8)
B10: Delivery units — pods / teams | C10: 5 / 4 | D10: 4 / 3 | E10: 3 / 3 | F10: 6 / 0 | G10: 5 / 0
B11: Headcount target from the Logic Tree (scope baseline x 1 - applied) | C11: ='Logic Tree'!C53 | D11: ='Logic Tree'!D53 | E11: ='Logic Tree'!E53 | F11: ='Logic Tree'!F53 | G11: ='Logic Tree'!G53
B12: Variance to target | C12: =C9-C11 | D12: =D9-D11 | E12: =E9-E11 | F12: =F9-F11 | G12: =G9-G11
A14: B. YEAR-1 RECONCILIATION TO APPENDIX 3 v3
B15: Measure | C15: Model Year 1 | D15: Appendix 3 v5 | E15: Variance | H15: Reading
B16: Total effort / people | C16: =C9 | D16: ='Logic Tree'!C7 | E16: =C16-D16 | H16: Whole-domain size. Unchanged since v2.
B17: FTC reported (Capgemini + partner) | C17: =SUMIFS('Seat Ledger'!$M$5:$M$287,'Seat Ledger'!$B$5:$B$287,1,'Seat Ledger'!$J$5:$J$287,"FTC")+SUMIFS('Seat Ledger'!$M$5:$M$287,'Seat Ledger'!$B$5:$B$287,1,'Seat Ledger'!$J$5:$J$287,"PT") | D17: ='Logic Tree'!C8 | E17: =C17-D17 | H17: Appendix 3 reports the vendor as one number. This is the line that has to reconcile.
B18: — of which Capgemini payroll | C18: =SUMIFS('Seat Ledger'!$M$5:$M$287,'Seat Ledger'!$B$5:$B$287,1,'Seat Ledger'!$J$5:$J$287,"FTC") | D18: — | E18: — | H18: Transferable at the end of Year 3.
B19: — of which FSI (four-application partner, onshore Japan) | C19: =SUMIFS('Seat Ledger'!$M$5:$M$287,'Seat Ledger'!$B$5:$B$287,1,'Seat Ledger'!$J$5:$J$287,"PT") | D19: — | E19: — | H19: NOT transferable, and onshore Japan by definition. POS Workflow, Annuity Info, OpenBatch and Pega for Claims.
B20: MetLife Japan FTE | C20: =SUMIFS('Seat Ledger'!$M$5:$M$287,'Seat Ledger'!$B$5:$B$287,1,'Seat Ledger'!$J$5:$J$287,"FTE") | D20: ='Logic Tree'!C9 | E20: =C20-D20 | H20: Product owners, domain SMEs and application owners.
B21: MetLife MGCC | C21: =SUMIFS('Seat Ledger'!$M$5:$M$287,'Seat Ledger'!$B$5:$B$287,1,'Seat Ledger'!$J$5:$J$287,"MGCC") | D21: ='Logic Tree'!C10 | E21: =C21-D21 | H21: 15.99 units on day one — MGCC is already the second largest sourcing pool in this domain.
B22: Vendor onshore Tokyo | C22: =SUMIFS('Seat Ledger'!$M$5:$M$287,'Seat Ledger'!$B$5:$B$287,1,'Seat Ledger'!$J$5:$J$287,"FTC",'Seat Ledger'!$I$5:$I$287,"ON")+SUMIFS('Seat Ledger'!$M$5:$M$287,'Seat Ledger'!$B$5:$B$287,1,'Seat Ledger'!$J$5:$J$287,"PT",'Seat Ledger'!$I$5:$I$287,"ON") | D22: ='Logic Tree'!C11 | E22: =C22-D22 | H22: MEASURED, not assumed.
B23: Vendor nearshore | C23: =SUMIFS('Seat Ledger'!$M$5:$M$287,'Seat Ledger'!$B$5:$B$287,1,'Seat Ledger'!$J$5:$J$287,"FTC",'Seat Ledger'!$I$5:$I$287,"NEAR")+SUMIFS('Seat Ledger'!$M$5:$M$287,'Seat Ledger'!$B$5:$B$287,1,'Seat Ledger'!$J$5:$J$287,"PT",'Seat Ledger'!$I$5:$I$287,"NEAR") | D23: ='Logic Tree'!C13 | E23: =C23-D23 | H23: Zero. There is no nearshore capacity in this 領域.
B24: Vendor offshore | C24: =SUMIFS('Seat Ledger'!$M$5:$M$287,'Seat Ledger'!$B$5:$B$287,1,'Seat Ledger'!$J$5:$J$287,"FTC",'Seat Ledger'!$I$5:$I$287,"OFF")+SUMIFS('Seat Ledger'!$M$5:$M$287,'Seat Ledger'!$B$5:$B$287,1,'Seat Ledger'!$J$5:$J$287,"PT",'Seat Ledger'!$I$5:$I$287,"OFF") | D24: ='Logic Tree'!C12 | E24: =C24-D24 | H24: 28.87 units already offshore — 44% of the Capgemini population on day one. MGCC is excluded: it is MetLife's.
B25: Role — BSA | C25: =SUMIFS('Seat Ledger'!$M$5:$M$287,'Seat Ledger'!$B$5:$B$287,1,'Seat Ledger'!$J$5:$J$287,"FTC",'Seat Ledger'!$G$5:$G$287,"BSA")+SUMIFS('Seat Ledger'!$M$5:$M$287,'Seat Ledger'!$B$5:$B$287,1,'Seat Ledger'!$J$5:$J$287,"PT",'Seat Ledger'!$G$5:$G$287,"BSA") | D25: ='Logic Tree'!C15 | E25: =C25-D25 | H25: Reconciles.
B26: Role — Developer | C26: =SUMIFS('Seat Ledger'!$M$5:$M$287,'Seat Ledger'!$B$5:$B$287,1,'Seat Ledger'!$J$5:$J$287,"FTC",'Seat Ledger'!$G$5:$G$287,"DEV")+SUMIFS('Seat Ledger'!$M$5:$M$287,'Seat Ledger'!$B$5:$B$287,1,'Seat Ledger'!$J$5:$J$287,"PT",'Seat Ledger'!$G$5:$G$287,"DEV") | D26: ='Logic Tree'!C16 | E26: =C26-D26 | H26: As reported. 66% of the vendor population.
B27: Role — Tester | C27: =SUMIFS('Seat Ledger'!$M$5:$M$287,'Seat Ledger'!$B$5:$B$287,1,'Seat Ledger'!$J$5:$J$287,"FTC",'Seat Ledger'!$G$5:$G$287,"TEST")+SUMIFS('Seat Ledger'!$M$5:$M$287,'Seat Ledger'!$B$5:$B$287,1,'Seat Ledger'!$J$5:$J$287,"PT",'Seat Ledger'!$G$5:$G$287,"TEST") | D27: ='Logic Tree'!C17 | E27: =C27-D27 | H27: As reported. The lowest tester share in the portfolio, at 7.9%.
B28: Role — Maintenance | C28: =SUMIFS('Seat Ledger'!$M$5:$M$287,'Seat Ledger'!$B$5:$B$287,1,'Seat Ledger'!$J$5:$J$287,"FTC",'Seat Ledger'!$G$5:$G$287,"MNT")+SUMIFS('Seat Ledger'!$M$5:$M$287,'Seat Ledger'!$B$5:$B$287,1,'Seat Ledger'!$J$5:$J$287,"PT",'Seat Ledger'!$G$5:$G$287,"MNT") | D28: ='Logic Tree'!C18 | E28: =C28-D28 | H28: As reported by MetLife and used unchanged.
B29: Role — PM | C29: =SUMIFS('Seat Ledger'!$M$5:$M$287,'Seat Ledger'!$B$5:$B$287,1,'Seat Ledger'!$J$5:$J$287,"FTC",'Seat Ledger'!$G$5:$G$287,"PM")+SUMIFS('Seat Ledger'!$M$5:$M$287,'Seat Ledger'!$B$5:$B$287,1,'Seat Ledger'!$J$5:$J$287,"PT",'Seat Ledger'!$G$5:$G$287,"PM") | D29: ='Logic Tree'!C19 | E29: =C29-D29 | H29: As reported. Thin at 2.2%, but populated.
B30: Role — Other | C30: =SUMIFS('Seat Ledger'!$M$5:$M$287,'Seat Ledger'!$B$5:$B$287,1,'Seat Ledger'!$J$5:$J$287,"FTC",'Seat Ledger'!$G$5:$G$287,"OTH")+SUMIFS('Seat Ledger'!$M$5:$M$287,'Seat Ledger'!$B$5:$B$287,1,'Seat Ledger'!$J$5:$J$287,"PT",'Seat Ledger'!$G$5:$G$287,"OTH") | D30: ='Logic Tree'!C20 | E30: =C30-D30 | H30: As reported. Architecture and enablement.
B31: Largest variance across every reconciling line | E31: =MAX(ABS(E16),ABS(E17),ABS(E20),ABS(E21),ABS(E22),ABS(E23),ABS(E24),ABS(E25),ABS(E26),ABS(E27),ABS(E28),ABS(E29),ABS(E30)) | G31: Appendix 3 v5 is internally consistent for all six applications: every Total equals its FTC + FTE + MGCC. The 20.4 variance is the deliberate Developer restatement described in section C, not an unreconciled line.
B32: Largest variance excluding the MetLife FTE line (twelve lines) | E32: =MAX(ABS(E16),ABS(E17),ABS(E21),ABS(E22),ABS(E23),ABS(E24),ABS(E25),ABS(E26),ABS(E27),ABS(E28),ABS(E29),ABS(E30)) | G32: Every line — effort, vendor total, MetLife FTE, MGCC, both locations and all six client role lines — reconciles to within a few hundredths of a person after head-grid quantisation.
A33: C. THE ROLE LINE — used exactly as MetLife reports it
B34: Role | C34: Appendix 3 v5 | D34: This model | E34: Difference | H34: Note
B35: BSA | C35: ='Logic Tree'!C15 | D35: =C25 | E35: =D35-C35 | H35: 16.4% of the vendor population after restatement, against 7.0% as MetLife reports it. Bilingual analysis on Japanese-specification payment workflow is the scarcest skill here.
B36: Developer | C36: ='Logic Tree'!C16 | D36: =C26 | E36: =D36-C36 | H36: 59.1% after restatement, against 82.9% as MetLife reports it — the most extreme developer concentration in the portfolio.
B37: Tester | C37: ='Logic Tree'!C17 | D37: =C27 | E37: =D37-C37 | H37: 12.3% after restatement, against 8.0% as reported. 439 batch jobs and 1,161 changes a year cannot be tested by 6.8 people.
B38: Maintenance | C38: ='Logic Tree'!C18 | D38: =C28 | E38: =D38-C38 | H38: RESTATED. One person of run against 732 incidents a year is a coding convention, not a maintenance line.
B39: PM | C39: ='Logic Tree'!C19 | D39: =C29 | E39: =D39-C39 | H39: RESTATED from ZERO. Two value streams, six applications and a retirement cannot be coordinated on nothing.
B40: Other | C40: ='Logic Tree'!C20 | D40: =C30 | E40: =D40-C40 | H40: RESTATED from 0.775. Architecture and enablement on a Pega platform and an OpenBatch estate.
B41: Sum of the six role lines | C41: =SUM(C35:C40) | D41: =SUM(D35:D40) | E41: =D41-C41 | H41: FIVE LINES RESTATED, ARITHMETICALLY NEUTRAL. MetLife reports 82.9% of the vendor line as Developer, 1.00 unit of maintenance, ZERO project management and 0.775 of architecture, against 732 incidents, 1,161 changes and 439 batch jobs a year. We move 20.4 units out of Developer — BSA 20%, Tester 25%, Maintenance 20%, PM 15%, Other 20% — and the total does not change. This is the largest restatement in the portfolio and it goes back to MetLife as a clarification question, not a re-pricing. It is why the Year-1 worst-line check reads 20.4 against a ±2.6 tolerance: deliberate, and the only red on the Change Control sheet.
A43: D. SOURCING, LOCATION AND THE THREE OFFSHORE BASES
B44: Measure | C44: Year 1 | D44: Year 2 | E44: Year 3 | F44: Year 4 | G44: Year 5
B45: Capgemini payroll (FTC) | C45: =SUMIFS('Seat Ledger'!$M$5:$M$287,'Seat Ledger'!$B$5:$B$287,1,'Seat Ledger'!$J$5:$J$287,"FTC") | D45: =SUMIFS('Seat Ledger'!$M$5:$M$287,'Seat Ledger'!$B$5:$B$287,2,'Seat Ledger'!$J$5:$J$287,"FTC") | E45: =SUMIFS('Seat Ledger'!$M$5:$M$287,'Seat Ledger'!$B$5:$B$287,3,'Seat Ledger'!$J$5:$J$287,"FTC") | F45: =SUMIFS('Seat Ledger'!$M$5:$M$287,'Seat Ledger'!$B$5:$B$287,4,'Seat Ledger'!$J$5:$J$287,"FTC") | G45: =SUMIFS('Seat Ledger'!$M$5:$M$287,'Seat Ledger'!$B$5:$B$287,5,'Seat Ledger'!$J$5:$J$287,"FTC")
B46: Incumbent partner (PT) | C46: =SUMIFS('Seat Ledger'!$M$5:$M$287,'Seat Ledger'!$B$5:$B$287,1,'Seat Ledger'!$J$5:$J$287,"PT") | D46: =SUMIFS('Seat Ledger'!$M$5:$M$287,'Seat Ledger'!$B$5:$B$287,2,'Seat Ledger'!$J$5:$J$287,"PT") | E46: =SUMIFS('Seat Ledger'!$M$5:$M$287,'Seat Ledger'!$B$5:$B$287,3,'Seat Ledger'!$J$5:$J$287,"PT") | F46: =SUMIFS('Seat Ledger'!$M$5:$M$287,'Seat Ledger'!$B$5:$B$287,4,'Seat Ledger'!$J$5:$J$287,"PT") | G46: =SUMIFS('Seat Ledger'!$M$5:$M$287,'Seat Ledger'!$B$5:$B$287,5,'Seat Ledger'!$J$5:$J$287,"PT")
B47: VENDOR TOTAL = Appendix 3 FTC | C47: =C45+C46 | D47: =D45+D46 | E47: =E45+E46 | F47: =F45+F46 | G47: =G45+G46
B48: MetLife Japan (FTE) | C48: =SUMIFS('Seat Ledger'!$M$5:$M$287,'Seat Ledger'!$B$5:$B$287,1,'Seat Ledger'!$J$5:$J$287,"FTE") | D48: =SUMIFS('Seat Ledger'!$M$5:$M$287,'Seat Ledger'!$B$5:$B$287,2,'Seat Ledger'!$J$5:$J$287,"FTE") | E48: =SUMIFS('Seat Ledger'!$M$5:$M$287,'Seat Ledger'!$B$5:$B$287,3,'Seat Ledger'!$J$5:$J$287,"FTE") | F48: =SUMIFS('Seat Ledger'!$M$5:$M$287,'Seat Ledger'!$B$5:$B$287,4,'Seat Ledger'!$J$5:$J$287,"FTE") | G48: =SUMIFS('Seat Ledger'!$M$5:$M$287,'Seat Ledger'!$B$5:$B$287,5,'Seat Ledger'!$J$5:$J$287,"FTE")
B49: MetLife MGCC | C49: =SUMIFS('Seat Ledger'!$M$5:$M$287,'Seat Ledger'!$B$5:$B$287,1,'Seat Ledger'!$J$5:$J$287,"MGCC") | D49: =SUMIFS('Seat Ledger'!$M$5:$M$287,'Seat Ledger'!$B$5:$B$287,2,'Seat Ledger'!$J$5:$J$287,"MGCC") | E49: =SUMIFS('Seat Ledger'!$M$5:$M$287,'Seat Ledger'!$B$5:$B$287,3,'Seat Ledger'!$J$5:$J$287,"MGCC") | F49: =SUMIFS('Seat Ledger'!$M$5:$M$287,'Seat Ledger'!$B$5:$B$287,4,'Seat Ledger'!$J$5:$J$287,"MGCC") | G49: =SUMIFS('Seat Ledger'!$M$5:$M$287,'Seat Ledger'!$B$5:$B$287,5,'Seat Ledger'!$J$5:$J$287,"MGCC")
B50: RATIO — vendor share | C50: =IF(C9=0,0,C47/C9) | D50: =IF(D9=0,0,D47/D9) | E50: =IF(E9=0,0,E47/E9) | F50: =IF(F9=0,0,F47/F9) | G50: =IF(G9=0,0,G47/G9)
B51: Onshore Tokyo | C51: =SUMIFS('Seat Ledger'!$M$5:$M$287,'Seat Ledger'!$B$5:$B$287,1,'Seat Ledger'!$I$5:$I$287,"ON") | D51: =SUMIFS('Seat Ledger'!$M$5:$M$287,'Seat Ledger'!$B$5:$B$287,2,'Seat Ledger'!$I$5:$I$287,"ON") | E51: =SUMIFS('Seat Ledger'!$M$5:$M$287,'Seat Ledger'!$B$5:$B$287,3,'Seat Ledger'!$I$5:$I$287,"ON") | F51: =SUMIFS('Seat Ledger'!$M$5:$M$287,'Seat Ledger'!$B$5:$B$287,4,'Seat Ledger'!$I$5:$I$287,"ON") | G51: =SUMIFS('Seat Ledger'!$M$5:$M$287,'Seat Ledger'!$B$5:$B$287,5,'Seat Ledger'!$I$5:$I$287,"ON")
B52: Offshore | C52: =SUMIFS('Seat Ledger'!$M$5:$M$287,'Seat Ledger'!$B$5:$B$287,1,'Seat Ledger'!$I$5:$I$287,"OFF") | D52: =SUMIFS('Seat Ledger'!$M$5:$M$287,'Seat Ledger'!$B$5:$B$287,2,'Seat Ledger'!$I$5:$I$287,"OFF") | E52: =SUMIFS('Seat Ledger'!$M$5:$M$287,'Seat Ledger'!$B$5:$B$287,3,'Seat Ledger'!$I$5:$I$287,"OFF") | F52: =SUMIFS('Seat Ledger'!$M$5:$M$287,'Seat Ledger'!$B$5:$B$287,4,'Seat Ledger'!$I$5:$I$287,"OFF") | G52: =SUMIFS('Seat Ledger'!$M$5:$M$287,'Seat Ledger'!$B$5:$B$287,5,'Seat Ledger'!$I$5:$I$287,"OFF")
B53: Nearshore | C53: =SUMIFS('Seat Ledger'!$M$5:$M$287,'Seat Ledger'!$B$5:$B$287,1,'Seat Ledger'!$I$5:$I$287,"NEAR") | D53: =SUMIFS('Seat Ledger'!$M$5:$M$287,'Seat Ledger'!$B$5:$B$287,2,'Seat Ledger'!$I$5:$I$287,"NEAR") | E53: =SUMIFS('Seat Ledger'!$M$5:$M$287,'Seat Ledger'!$B$5:$B$287,3,'Seat Ledger'!$I$5:$I$287,"NEAR") | F53: =SUMIFS('Seat Ledger'!$M$5:$M$287,'Seat Ledger'!$B$5:$B$287,4,'Seat Ledger'!$I$5:$I$287,"NEAR") | G53: =SUMIFS('Seat Ledger'!$M$5:$M$287,'Seat Ledger'!$B$5:$B$287,5,'Seat Ledger'!$I$5:$I$287,"NEAR")
B54: Offshore share — whole team | C54: =IF(C9=0,0,(C52+C53)/C9) | D54: =IF(D9=0,0,(D52+D53)/D9) | E54: =IF(E9=0,0,(E52+E53)/E9) | F54: =IF(F9=0,0,(F52+F53)/F9) | G54: =IF(G9=0,0,(G52+G53)/G9)
B55: Offshore share — vendor only | C55: =IF(C47=0,0,(SUMIFS('Seat Ledger'!$M$5:$M$287,'Seat Ledger'!$B$5:$B$287,1,'Seat Ledger'!$J$5:$J$287,"FTC",'Seat Ledger'!$I$5:$I$287,"OFF")+SUMIFS('Seat Ledger'!$M$5:$M$287,'Seat Ledger'!$B$5:$B$287,1,'Seat Ledger'!$J$5:$J$287,"FTC",'Seat Ledger'!$I$5:$I$287,"NEAR")+SUMIFS('Seat Ledger'!$M$5:$M$287,'Seat Ledger'!$B$5:$B$287,1,'Seat Ledger'!$J$5:$J$287,"PT",'Seat Ledger'!$I$5:$I$287,"OFF"))/C47) | D55: =IF(D47=0,0,(SUMIFS('Seat Ledger'!$M$5:$M$287,'Seat Ledger'!$B$5:$B$287,2,'Seat Ledger'!$J$5:$J$287,"FTC",'Seat Ledger'!$I$5:$I$287,"OFF")+SUMIFS('Seat Ledger'!$M$5:$M$287,'Seat Ledger'!$B$5:$B$287,2,'Seat Ledger'!$J$5:$J$287,"FTC",'Seat Ledger'!$I$5:$I$287,"NEAR")+SUMIFS('Seat Ledger'!$M$5:$M$287,'Seat Ledger'!$B$5:$B$287,2,'Seat Ledger'!$J$5:$J$287,"PT",'Seat Ledger'!$I$5:$I$287,"OFF"))/D47) | E55: =IF(E47=0,0,(SUMIFS('Seat Ledger'!$M$5:$M$287,'Seat Ledger'!$B$5:$B$287,3,'Seat Ledger'!$J$5:$J$287,"FTC",'Seat Ledger'!$I$5:$I$287,"OFF")+SUMIFS('Seat Ledger'!$M$5:$M$287,'Seat Ledger'!$B$5:$B$287,3,'Seat Ledger'!$J$5:$J$287,"FTC",'Seat Ledger'!$I$5:$I$287,"NEAR")+SUMIFS('Seat Ledger'!$M$5:$M$287,'Seat Ledger'!$B$5:$B$287,3,'Seat Ledger'!$J$5:$J$287,"PT",'Seat Ledger'!$I$5:$I$287,"OFF"))/E47) | F55: =IF(F47=0,0,(SUMIFS('Seat Ledger'!$M$5:$M$287,'Seat Ledger'!$B$5:$B$287,4,'Seat Ledger'!$J$5:$J$287,"FTC",'Seat Ledger'!$I$5:$I$287,"OFF")+SUMIFS('Seat Ledger'!$M$5:$M$287,'Seat Ledger'!$B$5:$B$287,4,'Seat Ledger'!$J$5:$J$287,"FTC",'Seat Ledger'!$I$5:$I$287,"NEAR")+SUMIFS('Seat Ledger'!$M$5:$M$287,'Seat Ledger'!$B$5:$B$287,4,'Seat Ledger'!$J$5:$J$287,"PT",'Seat Ledger'!$I$5:$I$287,"OFF"))/F47) | G55: =IF(G47=0,0,(SUMIFS('Seat Ledger'!$M$5:$M$287,'Seat Ledger'!$B$5:$B$287,5,'Seat Ledger'!$J$5:$J$287,"FTC",'Seat Ledger'!$I$5:$I$287,"OFF")+SUMIFS('Seat Ledger'!$M$5:$M$287,'Seat Ledger'!$B$5:$B$287,5,'Seat Ledger'!$J$5:$J$287,"FTC",'Seat Ledger'!$I$5:$I$287,"NEAR")+SUMIFS('Seat Ledger'!$M$5:$M$287,'Seat Ledger'!$B$5:$B$287,5,'Seat Ledger'!$J$5:$J$287,"PT",'Seat Ledger'!$I$5:$I$287,"OFF"))/G47)
B56: Offshore share — Capgemini payroll only | C56: =IF(C45=0,0,(SUMIFS('Seat Ledger'!$M$5:$M$287,'Seat Ledger'!$B$5:$B$287,1,'Seat Ledger'!$J$5:$J$287,"FTC",'Seat Ledger'!$I$5:$I$287,"OFF")+SUMIFS('Seat Ledger'!$M$5:$M$287,'Seat Ledger'!$B$5:$B$287,1,'Seat Ledger'!$J$5:$J$287,"FTC",'Seat Ledger'!$I$5:$I$287,"NEAR"))/C45) | D56: =IF(D45=0,0,(SUMIFS('Seat Ledger'!$M$5:$M$287,'Seat Ledger'!$B$5:$B$287,2,'Seat Ledger'!$J$5:$J$287,"FTC",'Seat Ledger'!$I$5:$I$287,"OFF")+SUMIFS('Seat Ledger'!$M$5:$M$287,'Seat Ledger'!$B$5:$B$287,2,'Seat Ledger'!$J$5:$J$287,"FTC",'Seat Ledger'!$I$5:$I$287,"NEAR"))/D45) | E56: =IF(E45=0,0,(SUMIFS('Seat Ledger'!$M$5:$M$287,'Seat Ledger'!$B$5:$B$287,3,'Seat Ledger'!$J$5:$J$287,"FTC",'Seat Ledger'!$I$5:$I$287,"OFF")+SUMIFS('Seat Ledger'!$M$5:$M$287,'Seat Ledger'!$B$5:$B$287,3,'Seat Ledger'!$J$5:$J$287,"FTC",'Seat Ledger'!$I$5:$I$287,"NEAR"))/E45) | F56: =IF(F45=0,0,(SUMIFS('Seat Ledger'!$M$5:$M$287,'Seat Ledger'!$B$5:$B$287,4,'Seat Ledger'!$J$5:$J$287,"FTC",'Seat Ledger'!$I$5:$I$287,"OFF")+SUMIFS('Seat Ledger'!$M$5:$M$287,'Seat Ledger'!$B$5:$B$287,4,'Seat Ledger'!$J$5:$J$287,"FTC",'Seat Ledger'!$I$5:$I$287,"NEAR"))/F45) | G56: =IF(G45=0,0,(SUMIFS('Seat Ledger'!$M$5:$M$287,'Seat Ledger'!$B$5:$B$287,5,'Seat Ledger'!$J$5:$J$287,"FTC",'Seat Ledger'!$I$5:$I$287,"OFF")+SUMIFS('Seat Ledger'!$M$5:$M$287,'Seat Ledger'!$B$5:$B$287,5,'Seat Ledger'!$J$5:$J$287,"FTC",'Seat Ledger'!$I$5:$I$287,"NEAR"))/G45) | I56: Rises across the five years and keeps rising through Year 4. Only 5 people transfer, so our own offshore book survives the event — the opposite of Contract Management.
B57: Target from the Logic Tree | C57: ='Logic Tree'!C68 | D57: ='Logic Tree'!D68 | E57: ='Logic Tree'!E68 | F57: ='Logic Tree'!F68 | G57: ='Logic Tree'!G68
A59: E. ROLE MIX — MetLife's taxonomy, all sourcing types
B60: Role | C60: Year 1 | D60: Year 2 | E60: Year 3 | F60: Year 4 | G60: Year 5
B61: BSA — business and systems analysis | C61: =SUMIFS('Seat Ledger'!$M$5:$M$287,'Seat Ledger'!$B$5:$B$287,1,'Seat Ledger'!$G$5:$G$287,"BSA") | D61: =SUMIFS('Seat Ledger'!$M$5:$M$287,'Seat Ledger'!$B$5:$B$287,2,'Seat Ledger'!$G$5:$G$287,"BSA") | E61: =SUMIFS('Seat Ledger'!$M$5:$M$287,'Seat Ledger'!$B$5:$B$287,3,'Seat Ledger'!$G$5:$G$287,"BSA") | F61: =SUMIFS('Seat Ledger'!$M$5:$M$287,'Seat Ledger'!$B$5:$B$287,4,'Seat Ledger'!$G$5:$G$287,"BSA") | G61: =SUMIFS('Seat Ledger'!$M$5:$M$287,'Seat Ledger'!$B$5:$B$287,5,'Seat Ledger'!$G$5:$G$287,"BSA")
B62: Developer | C62: =SUMIFS('Seat Ledger'!$M$5:$M$287,'Seat Ledger'!$B$5:$B$287,1,'Seat Ledger'!$G$5:$G$287,"DEV") | D62: =SUMIFS('Seat Ledger'!$M$5:$M$287,'Seat Ledger'!$B$5:$B$287,2,'Seat Ledger'!$G$5:$G$287,"DEV") | E62: =SUMIFS('Seat Ledger'!$M$5:$M$287,'Seat Ledger'!$B$5:$B$287,3,'Seat Ledger'!$G$5:$G$287,"DEV") | F62: =SUMIFS('Seat Ledger'!$M$5:$M$287,'Seat Ledger'!$B$5:$B$287,4,'Seat Ledger'!$G$5:$G$287,"DEV") | G62: =SUMIFS('Seat Ledger'!$M$5:$M$287,'Seat Ledger'!$B$5:$B$287,5,'Seat Ledger'!$G$5:$G$287,"DEV")
B63: Tester | C63: =SUMIFS('Seat Ledger'!$M$5:$M$287,'Seat Ledger'!$B$5:$B$287,1,'Seat Ledger'!$G$5:$G$287,"TEST") | D63: =SUMIFS('Seat Ledger'!$M$5:$M$287,'Seat Ledger'!$B$5:$B$287,2,'Seat Ledger'!$G$5:$G$287,"TEST") | E63: =SUMIFS('Seat Ledger'!$M$5:$M$287,'Seat Ledger'!$B$5:$B$287,3,'Seat Ledger'!$G$5:$G$287,"TEST") | F63: =SUMIFS('Seat Ledger'!$M$5:$M$287,'Seat Ledger'!$B$5:$B$287,4,'Seat Ledger'!$G$5:$G$287,"TEST") | G63: =SUMIFS('Seat Ledger'!$M$5:$M$287,'Seat Ledger'!$B$5:$B$287,5,'Seat Ledger'!$G$5:$G$287,"TEST")
B64: Maintenance | C64: =SUMIFS('Seat Ledger'!$M$5:$M$287,'Seat Ledger'!$B$5:$B$287,1,'Seat Ledger'!$G$5:$G$287,"MNT") | D64: =SUMIFS('Seat Ledger'!$M$5:$M$287,'Seat Ledger'!$B$5:$B$287,2,'Seat Ledger'!$G$5:$G$287,"MNT") | E64: =SUMIFS('Seat Ledger'!$M$5:$M$287,'Seat Ledger'!$B$5:$B$287,3,'Seat Ledger'!$G$5:$G$287,"MNT") | F64: =SUMIFS('Seat Ledger'!$M$5:$M$287,'Seat Ledger'!$B$5:$B$287,4,'Seat Ledger'!$G$5:$G$287,"MNT") | G64: =SUMIFS('Seat Ledger'!$M$5:$M$287,'Seat Ledger'!$B$5:$B$287,5,'Seat Ledger'!$G$5:$G$287,"MNT")
B65: PM and product ownership | C65: =SUMIFS('Seat Ledger'!$M$5:$M$287,'Seat Ledger'!$B$5:$B$287,1,'Seat Ledger'!$G$5:$G$287,"PM") | D65: =SUMIFS('Seat Ledger'!$M$5:$M$287,'Seat Ledger'!$B$5:$B$287,2,'Seat Ledger'!$G$5:$G$287,"PM") | E65: =SUMIFS('Seat Ledger'!$M$5:$M$287,'Seat Ledger'!$B$5:$B$287,3,'Seat Ledger'!$G$5:$G$287,"PM") | F65: =SUMIFS('Seat Ledger'!$M$5:$M$287,'Seat Ledger'!$B$5:$B$287,4,'Seat Ledger'!$G$5:$G$287,"PM") | G65: =SUMIFS('Seat Ledger'!$M$5:$M$287,'Seat Ledger'!$B$5:$B$287,5,'Seat Ledger'!$G$5:$G$287,"PM")
B66: Other — architecture and enablement | C66: =SUMIFS('Seat Ledger'!$M$5:$M$287,'Seat Ledger'!$B$5:$B$287,1,'Seat Ledger'!$G$5:$G$287,"OTH") | D66: =SUMIFS('Seat Ledger'!$M$5:$M$287,'Seat Ledger'!$B$5:$B$287,2,'Seat Ledger'!$G$5:$G$287,"OTH") | E66: =SUMIFS('Seat Ledger'!$M$5:$M$287,'Seat Ledger'!$B$5:$B$287,3,'Seat Ledger'!$G$5:$G$287,"OTH") | F66: =SUMIFS('Seat Ledger'!$M$5:$M$287,'Seat Ledger'!$B$5:$B$287,4,'Seat Ledger'!$G$5:$G$287,"OTH") | G66: =SUMIFS('Seat Ledger'!$M$5:$M$287,'Seat Ledger'!$B$5:$B$287,5,'Seat Ledger'!$G$5:$G$287,"OTH")
B67: Run-facing share (Maintenance + Tester) | C67: =IF(C9=0,0,(C63+C64)/C9) | D67: =IF(D9=0,0,(D63+D64)/D9) | E67: =IF(E9=0,0,(E63+E64)/E9) | F67: =IF(F9=0,0,(F63+F64)/F9) | G67: =IF(G9=0,0,(G63+G64)/G9) | I67: 15.3% in Year 1 falling to 9.0% by Year 5, as pipeline automation and auto-remediation land.
A69: F. EXPERIENCE MIX
B70: Band | C70: Year 1 | D70: Year 2 | E70: Year 3 | F70: Year 4 | G70: Year 5
B71: E1 | C71: =SUMIFS('Seat Ledger'!$M$5:$M$287,'Seat Ledger'!$B$5:$B$287,1,'Seat Ledger'!$H$5:$H$287,"E1") | D71: =SUMIFS('Seat Ledger'!$M$5:$M$287,'Seat Ledger'!$B$5:$B$287,2,'Seat Ledger'!$H$5:$H$287,"E1") | E71: =SUMIFS('Seat Ledger'!$M$5:$M$287,'Seat Ledger'!$B$5:$B$287,3,'Seat Ledger'!$H$5:$H$287,"E1") | F71: =SUMIFS('Seat Ledger'!$M$5:$M$287,'Seat Ledger'!$B$5:$B$287,4,'Seat Ledger'!$H$5:$H$287,"E1") | G71: =SUMIFS('Seat Ledger'!$M$5:$M$287,'Seat Ledger'!$B$5:$B$287,5,'Seat Ledger'!$H$5:$H$287,"E1")
B72: E2 | C72: =SUMIFS('Seat Ledger'!$M$5:$M$287,'Seat Ledger'!$B$5:$B$287,1,'Seat Ledger'!$H$5:$H$287,"E2") | D72: =SUMIFS('Seat Ledger'!$M$5:$M$287,'Seat Ledger'!$B$5:$B$287,2,'Seat Ledger'!$H$5:$H$287,"E2") | E72: =SUMIFS('Seat Ledger'!$M$5:$M$287,'Seat Ledger'!$B$5:$B$287,3,'Seat Ledger'!$H$5:$H$287,"E2") | F72: =SUMIFS('Seat Ledger'!$M$5:$M$287,'Seat Ledger'!$B$5:$B$287,4,'Seat Ledger'!$H$5:$H$287,"E2") | G72: =SUMIFS('Seat Ledger'!$M$5:$M$287,'Seat Ledger'!$B$5:$B$287,5,'Seat Ledger'!$H$5:$H$287,"E2")
B73: E3 | C73: =SUMIFS('Seat Ledger'!$M$5:$M$287,'Seat Ledger'!$B$5:$B$287,1,'Seat Ledger'!$H$5:$H$287,"E3") | D73: =SUMIFS('Seat Ledger'!$M$5:$M$287,'Seat Ledger'!$B$5:$B$287,2,'Seat Ledger'!$H$5:$H$287,"E3") | E73: =SUMIFS('Seat Ledger'!$M$5:$M$287,'Seat Ledger'!$B$5:$B$287,3,'Seat Ledger'!$H$5:$H$287,"E3") | F73: =SUMIFS('Seat Ledger'!$M$5:$M$287,'Seat Ledger'!$B$5:$B$287,4,'Seat Ledger'!$H$5:$H$287,"E3") | G73: =SUMIFS('Seat Ledger'!$M$5:$M$287,'Seat Ledger'!$B$5:$B$287,5,'Seat Ledger'!$H$5:$H$287,"E3")
B74: E4 | C74: =SUMIFS('Seat Ledger'!$M$5:$M$287,'Seat Ledger'!$B$5:$B$287,1,'Seat Ledger'!$H$5:$H$287,"E4") | D74: =SUMIFS('Seat Ledger'!$M$5:$M$287,'Seat Ledger'!$B$5:$B$287,2,'Seat Ledger'!$H$5:$H$287,"E4") | E74: =SUMIFS('Seat Ledger'!$M$5:$M$287,'Seat Ledger'!$B$5:$B$287,3,'Seat Ledger'!$H$5:$H$287,"E4") | F74: =SUMIFS('Seat Ledger'!$M$5:$M$287,'Seat Ledger'!$B$5:$B$287,4,'Seat Ledger'!$H$5:$H$287,"E4") | G74: =SUMIFS('Seat Ledger'!$M$5:$M$287,'Seat Ledger'!$B$5:$B$287,5,'Seat Ledger'!$H$5:$H$287,"E4")
B75: E5 | C75: =SUMIFS('Seat Ledger'!$M$5:$M$287,'Seat Ledger'!$B$5:$B$287,1,'Seat Ledger'!$H$5:$H$287,"E5") | D75: =SUMIFS('Seat Ledger'!$M$5:$M$287,'Seat Ledger'!$B$5:$B$287,2,'Seat Ledger'!$H$5:$H$287,"E5") | E75: =SUMIFS('Seat Ledger'!$M$5:$M$287,'Seat Ledger'!$B$5:$B$287,3,'Seat Ledger'!$H$5:$H$287,"E5") | F75: =SUMIFS('Seat Ledger'!$M$5:$M$287,'Seat Ledger'!$B$5:$B$287,4,'Seat Ledger'!$H$5:$H$287,"E5") | G75: =SUMIFS('Seat Ledger'!$M$5:$M$287,'Seat Ledger'!$B$5:$B$287,5,'Seat Ledger'!$H$5:$H$287,"E5")
B76: Senior share (E4 + E5) | C76: =IF(C9=0,0,(C74+C75)/C9) | D76: =IF(D9=0,0,(D74+D75)/D9) | E76: =IF(E9=0,0,(E74+E75)/E9) | F76: =IF(F9=0,0,(F74+F75)/F9) | G76: =IF(G9=0,0,(G74+G75)/G9)

Sheet Inherited Workforce
A1: The 20 Capgemini people already on these applications — and why this cohort is the opposite problem
A2: Supply comes from the T3 headcount reconciliation behind Golden Inventory v4. Read the sign on the gap lines before anything else, and read section E against a Year-1 offshore Capgemini demand of only 6.0 seats.
A4: A. WHERE THE NUMBER COMES FROM
B5: Source | C5: Count | D5: What it is used for
B6: Billing details — named individuals | C6: 277 | D6: THE COUNT. 277 de-duplicated employee IDs across T3, DMO and JET, each with a location and a Capgemini grade.
B7: Mapping of current Capgemini staff — billable FTE | C7: 283 | D7: THE ROLE MIX and the grade ladder. Developer → Developer, Cloud Engineer → Maintenance, Testers → Tester, BSA / Scrum Master / Functional Analyst → BSA, Tech Lead / Solution Architect → Other.
B8: EAIs.xlsx — 'CG HC by EAI' | C8: 450 | D8: THE SHAPE of the application-level distribution, rescaled to 277 and capped at each application's own vendor FTC.
B9: EAIs.xlsx Sheet1 — direct EAI tags | C9: 528 | D9: Cross-check only. Double-counts people serving more than one application.
B10: Of the 277, allocated to Insurance Claims and Benefits Payment Related | C10: 38 | D10: 33 in India, 5 in Japan. 45 of the 277 sit in cross-domain teams with no application mapping and are excluded from every domain.
B12: Capgemini grade → experience band: A4/A5 → E1 · B1/B2 → E2 · C1 and Sub-Con → E3 · C2/D1 → E4 · D2/E1 → E5. Location is binary: Japan → onshore, everything else → India / offshore.
A14: B. WHERE THEY SIT TODAY
B15: Application | C15: Archetype | D15: Value stream | E15: CG heads today | F15: Vendor FTC
B16: Annuity ＆ Maturity Payment (3 apps) | C16: D / J / T | D16: Claim Batch, W05AMS-JPN, WZZMNB-JPN | E16: 6 | F16: 42.454 | J16: 6 people against 85.4 vendor units — 7%, and all six sit on Claim Batch. This is the weakest the strongest continuity position of the five 領域 modelled. The split is almost even between the two streams, which is why neither can be treated as a standing start.
B17: Claims Processing ＆ Adjudication (1) | C17: D | D17: C12WNC-JPN — marked Retire | E17: 0 | F17: 29.38
B18: Claims Support Services (2 apps) | C18: D / T | D18: Pega for Claims, MDRS | E18: 0 | F18: 13.614
B19: TOTAL | E19: =SUM(E16:E18) | F19: =SUM(F16:F18)
A21: C. THE EVOLUTION MECHANIC — INPUT
B22: Band | C22: Attrition — offshore | D22: Attrition — onshore | E22: Promotion out of band
B23: E1 | C23: 0.22 | D23: 0.1 | E23: 0.2 | J23: Identical rates to Sales / Insurance v6 and Contract Management v7 — attrition first, promotion to the survivors. The same mechanic, applied to a very different starting shape.
B24: E2 | C24: 0.18 | D24: 0.09 | E24: 0.16
B25: E3 | C25: 0.13 | D25: 0.07 | E25: 0.12
B26: E4 | C26: 0.09 | D26: 0.05 | E26: 0.07
B27: E5 | C27: 0.06 | D27: 0.04 | E27: 0
A29: D. THE COHORT ROLLED FORWARD
B30: Measure | C30: Year 1 | D30: Year 2 | E30: Year 3 | F30: Year 4 | G30: Year 5
B31: Inherited people surviving | C31: 6 | D31: 5.24 | E31: 4.613248 | F31: 4.0916638 | G31: 3.6537367
B32: — E1 | C32: 0 | D32: 0 | E32: 0 | F32: 0 | G32: 0
B33: — E2 | C33: 2 | D33: 1.3776 | E33: 0.94889088 | F33: 0.65359604 | G33: 0.45019695
B34: — E3 | C34: 2 | D34: 1.7936 | E34: 1.5539213 | F34: 1.3141766 | G34: 1.0918854
B35: — E4 | C35: 2 | D35: 1.9386 | E35: 1.8607552 | F35: 1.7660238 | G35: 1.6574404
B36: — E5 | C36: 0 | D36: 0.1302 | E36: 0.24968062 | F36: 0.35786735 | G36: 0.45421395
B37: Senior share (E4 + E5) | C37: 0.33333333 | D37: 0.39480916 | E37: 0.45747288 | F37: 0.51907763 | G37: 0.57794377 | J37: The cohort starts at 28.9% senior (11 of 38 at E4 or E5) and the attrition-and-promotion mechanic seniorises it every year. Row 37 is the number to watch: it drives cost per head, and the design counters it by hiring at E2 and E3 offshore as the team shrinks.
B38: — in Japan | C38: 1 | D38: 0.95 | E38: 0.903165 | F38: 0.85923268 | G38: 0.81796701
B39: — in India | C39: 5 | D39: 4.29 | E39: 3.710083 | F39: 3.2324311 | G39: 2.8357697
A41: E. SUPPLY AGAINST DEMAND — offshore, where 18 of the 20 sit
B42: Measure | C42: Year 1 | D42: Year 2 | E42: Year 3 | F42: Year 4 | G42: Year 5
B43: Offshore Capgemini seats the design asks for | C43: =SUMIFS('Seat Ledger'!$M$5:$M$287,'Seat Ledger'!$B$5:$B$287,1,'Seat Ledger'!$J$5:$J$287,"FTC",'Seat Ledger'!$I$5:$I$287,"OFF")+SUMIFS('Seat Ledger'!$M$5:$M$287,'Seat Ledger'!$B$5:$B$287,1,'Seat Ledger'!$J$5:$J$287,"FTC",'Seat Ledger'!$I$5:$I$287,"NEAR") | D43: =SUMIFS('Seat Ledger'!$M$5:$M$287,'Seat Ledger'!$B$5:$B$287,2,'Seat Ledger'!$J$5:$J$287,"FTC",'Seat Ledger'!$I$5:$I$287,"OFF")+SUMIFS('Seat Ledger'!$M$5:$M$287,'Seat Ledger'!$B$5:$B$287,2,'Seat Ledger'!$J$5:$J$287,"FTC",'Seat Ledger'!$I$5:$I$287,"NEAR") | E43: =SUMIFS('Seat Ledger'!$M$5:$M$287,'Seat Ledger'!$B$5:$B$287,3,'Seat Ledger'!$J$5:$J$287,"FTC",'Seat Ledger'!$I$5:$I$287,"OFF")+SUMIFS('Seat Ledger'!$M$5:$M$287,'Seat Ledger'!$B$5:$B$287,3,'Seat Ledger'!$J$5:$J$287,"FTC",'Seat Ledger'!$I$5:$I$287,"NEAR") | F43: =SUMIFS('Seat Ledger'!$M$5:$M$287,'Seat Ledger'!$B$5:$B$287,4,'Seat Ledger'!$J$5:$J$287,"FTC",'Seat Ledger'!$I$5:$I$287,"OFF")+SUMIFS('Seat Ledger'!$M$5:$M$287,'Seat Ledger'!$B$5:$B$287,4,'Seat Ledger'!$J$5:$J$287,"FTC",'Seat Ledger'!$I$5:$I$287,"NEAR") | G43: =SUMIFS('Seat Ledger'!$M$5:$M$287,'Seat Ledger'!$B$5:$B$287,5,'Seat Ledger'!$J$5:$J$287,"FTC",'Seat Ledger'!$I$5:$I$287,"OFF")+SUMIFS('Seat Ledger'!$M$5:$M$287,'Seat Ledger'!$B$5:$B$287,5,'Seat Ledger'!$J$5:$J$287,"FTC",'Seat Ledger'!$I$5:$I$287,"NEAR")
B44: Inherited people still there | C44: 5 | D44: 4.29 | E44: 3.710083 | F44: 3.2324311 | G44: 2.8357697
B45: Covered by people we already have | C45: =C44/C43 | D45: =D44/D43 | E45: =E44/E43 | F45: =F44/F43 | G45: =G44/G43 | J45: 60% covered in Year 1, against 90% on Sales. This domain has to hire more of its own offshore team from a standing start, and the people it hires must be junior enough to balance a cohort that is already senior.
B46: To hire, redeploy or reskill | C46: =C43-C44 | D46: =D43-D44 | E46: =E43-E44 | F46: =F43-F44 | G46: =G43-G44
A48: F. BAND BY BAND — the seats we designed against the people we hold, offshore
B49: Year 1 | C49: E1 | D49: E2 | E49: E3 | F49: E4 | G49: E5 | H49: Total
B50: Seats the design asks for | C50: =SUMIFS('Seat Ledger'!$M$5:$M$287,'Seat Ledger'!$B$5:$B$287,1,'Seat Ledger'!$J$5:$J$287,"FTC",'Seat Ledger'!$I$5:$I$287,"OFF",'Seat Ledger'!$H$5:$H$287,"E1")+SUMIFS('Seat Ledger'!$M$5:$M$287,'Seat Ledger'!$B$5:$B$287,1,'Seat Ledger'!$J$5:$J$287,"FTC",'Seat Ledger'!$I$5:$I$287,"NEAR",'Seat Ledger'!$H$5:$H$287,"E1") | D50: =SUMIFS('Seat Ledger'!$M$5:$M$287,'Seat Ledger'!$B$5:$B$287,1,'Seat Ledger'!$J$5:$J$287,"FTC",'Seat Ledger'!$I$5:$I$287,"OFF",'Seat Ledger'!$H$5:$H$287,"E2")+SUMIFS('Seat Ledger'!$M$5:$M$287,'Seat Ledger'!$B$5:$B$287,1,'Seat Ledger'!$J$5:$J$287,"FTC",'Seat Ledger'!$I$5:$I$287,"NEAR",'Seat Ledger'!$H$5:$H$287,"E2") | E50: =SUMIFS('Seat Ledger'!$M$5:$M$287,'Seat Ledger'!$B$5:$B$287,1,'Seat Ledger'!$J$5:$J$287,"FTC",'Seat Ledger'!$I$5:$I$287,"OFF",'Seat Ledger'!$H$5:$H$287,"E3")+SUMIFS('Seat Ledger'!$M$5:$M$287,'Seat Ledger'!$B$5:$B$287,1,'Seat Ledger'!$J$5:$J$287,"FTC",'Seat Ledger'!$I$5:$I$287,"NEAR",'Seat Ledger'!$H$5:$H$287,"E3") | F50: =SUMIFS('Seat Ledger'!$M$5:$M$287,'Seat Ledger'!$B$5:$B$287,1,'Seat Ledger'!$J$5:$J$287,"FTC",'Seat Ledger'!$I$5:$I$287,"OFF",'Seat Ledger'!$H$5:$H$287,"E4")+SUMIFS('Seat Ledger'!$M$5:$M$287,'Seat Ledger'!$B$5:$B$287,1,'Seat Ledger'!$J$5:$J$287,"FTC",'Seat Ledger'!$I$5:$I$287,"NEAR",'Seat Ledger'!$H$5:$H$287,"E4") | G50: =SUMIFS('Seat Ledger'!$M$5:$M$287,'Seat Ledger'!$B$5:$B$287,1,'Seat Ledger'!$J$5:$J$287,"FTC",'Seat Ledger'!$I$5:$I$287,"OFF",'Seat Ledger'!$H$5:$H$287,"E5")+SUMIFS('Seat Ledger'!$M$5:$M$287,'Seat Ledger'!$B$5:$B$287,1,'Seat Ledger'!$J$5:$J$287,"FTC",'Seat Ledger'!$I$5:$I$287,"NEAR",'Seat Ledger'!$H$5:$H$287,"E5") | H50: =SUM(C50:G50)
B51: People we already have | C51: 0 | D51: 2 | E51: 2 | F51: 1 | G51: 0 | H51: =SUM(C51:G51)
B52: Gap — positive is a hire | C52: =C50-C51 | D52: =D50-D51 | E52: =E50-E51 | F52: =F50-F51 | G52: =G50-G51 | H52: =SUM(C52:G52)
B54: Year 2 | C54: E1 | D54: E2 | E54: E3 | F54: E4 | G54: E5 | H54: Total
B55: Seats the design asks for | C55: =SUMIFS('Seat Ledger'!$M$5:$M$287,'Seat Ledger'!$B$5:$B$287,2,'Seat Ledger'!$J$5:$J$287,"FTC",'Seat Ledger'!$I$5:$I$287,"OFF",'Seat Ledger'!$H$5:$H$287,"E1")+SUMIFS('Seat Ledger'!$M$5:$M$287,'Seat Ledger'!$B$5:$B$287,2,'Seat Ledger'!$J$5:$J$287,"FTC",'Seat Ledger'!$I$5:$I$287,"NEAR",'Seat Ledger'!$H$5:$H$287,"E1") | D55: =SUMIFS('Seat Ledger'!$M$5:$M$287,'Seat Ledger'!$B$5:$B$287,2,'Seat Ledger'!$J$5:$J$287,"FTC",'Seat Ledger'!$I$5:$I$287,"OFF",'Seat Ledger'!$H$5:$H$287,"E2")+SUMIFS('Seat Ledger'!$M$5:$M$287,'Seat Ledger'!$B$5:$B$287,2,'Seat Ledger'!$J$5:$J$287,"FTC",'Seat Ledger'!$I$5:$I$287,"NEAR",'Seat Ledger'!$H$5:$H$287,"E2") | E55: =SUMIFS('Seat Ledger'!$M$5:$M$287,'Seat Ledger'!$B$5:$B$287,2,'Seat Ledger'!$J$5:$J$287,"FTC",'Seat Ledger'!$I$5:$I$287,"OFF",'Seat Ledger'!$H$5:$H$287,"E3")+SUMIFS('Seat Ledger'!$M$5:$M$287,'Seat Ledger'!$B$5:$B$287,2,'Seat Ledger'!$J$5:$J$287,"FTC",'Seat Ledger'!$I$5:$I$287,"NEAR",'Seat Ledger'!$H$5:$H$287,"E3") | F55: =SUMIFS('Seat Ledger'!$M$5:$M$287,'Seat Ledger'!$B$5:$B$287,2,'Seat Ledger'!$J$5:$J$287,"FTC",'Seat Ledger'!$I$5:$I$287,"OFF",'Seat Ledger'!$H$5:$H$287,"E4")+SUMIFS('Seat Ledger'!$M$5:$M$287,'Seat Ledger'!$B$5:$B$287,2,'Seat Ledger'!$J$5:$J$287,"FTC",'Seat Ledger'!$I$5:$I$287,"NEAR",'Seat Ledger'!$H$5:$H$287,"E4") | G55: =SUMIFS('Seat Ledger'!$M$5:$M$287,'Seat Ledger'!$B$5:$B$287,2,'Seat Ledger'!$J$5:$J$287,"FTC",'Seat Ledger'!$I$5:$I$287,"OFF",'Seat Ledger'!$H$5:$H$287,"E5")+SUMIFS('Seat Ledger'!$M$5:$M$287,'Seat Ledger'!$B$5:$B$287,2,'Seat Ledger'!$J$5:$J$287,"FTC",'Seat Ledger'!$I$5:$I$287,"NEAR",'Seat Ledger'!$H$5:$H$287,"E5") | H55: =SUM(C55:G55)
B56: People we already have | C56: 0 | D56: 1.3776 | E56: 1.7936 | F56: 1.0551 | G56: 0.0637 | H56: =SUM(C56:G56)
B57: Gap — positive is a hire | C57: =C55-C56 | D57: =D55-D56 | E57: =E55-E56 | F57: =F55-F56 | G57: =G55-G56 | H57: =SUM(C57:G57)
B59: Year 3 | C59: E1 | D59: E2 | E59: E3 | F59: E4 | G59: E5 | H59: Total
B60: Seats the design asks for | C60: =SUMIFS('Seat Ledger'!$M$5:$M$287,'Seat Ledger'!$B$5:$B$287,3,'Seat Ledger'!$J$5:$J$287,"FTC",'Seat Ledger'!$I$5:$I$287,"OFF",'Seat Ledger'!$H$5:$H$287,"E1")+SUMIFS('Seat Ledger'!$M$5:$M$287,'Seat Ledger'!$B$5:$B$287,3,'Seat Ledger'!$J$5:$J$287,"FTC",'Seat Ledger'!$I$5:$I$287,"NEAR",'Seat Ledger'!$H$5:$H$287,"E1") | D60: =SUMIFS('Seat Ledger'!$M$5:$M$287,'Seat Ledger'!$B$5:$B$287,3,'Seat Ledger'!$J$5:$J$287,"FTC",'Seat Ledger'!$I$5:$I$287,"OFF",'Seat Ledger'!$H$5:$H$287,"E2")+SUMIFS('Seat Ledger'!$M$5:$M$287,'Seat Ledger'!$B$5:$B$287,3,'Seat Ledger'!$J$5:$J$287,"FTC",'Seat Ledger'!$I$5:$I$287,"NEAR",'Seat Ledger'!$H$5:$H$287,"E2") | E60: =SUMIFS('Seat Ledger'!$M$5:$M$287,'Seat Ledger'!$B$5:$B$287,3,'Seat Ledger'!$J$5:$J$287,"FTC",'Seat Ledger'!$I$5:$I$287,"OFF",'Seat Ledger'!$H$5:$H$287,"E3")+SUMIFS('Seat Ledger'!$M$5:$M$287,'Seat Ledger'!$B$5:$B$287,3,'Seat Ledger'!$J$5:$J$287,"FTC",'Seat Ledger'!$I$5:$I$287,"NEAR",'Seat Ledger'!$H$5:$H$287,"E3") | F60: =SUMIFS('Seat Ledger'!$M$5:$M$287,'Seat Ledger'!$B$5:$B$287,3,'Seat Ledger'!$J$5:$J$287,"FTC",'Seat Ledger'!$I$5:$I$287,"OFF",'Seat Ledger'!$H$5:$H$287,"E4")+SUMIFS('Seat Ledger'!$M$5:$M$287,'Seat Ledger'!$B$5:$B$287,3,'Seat Ledger'!$J$5:$J$287,"FTC",'Seat Ledger'!$I$5:$I$287,"NEAR",'Seat Ledger'!$H$5:$H$287,"E4") | G60: =SUMIFS('Seat Ledger'!$M$5:$M$287,'Seat Ledger'!$B$5:$B$287,3,'Seat Ledger'!$J$5:$J$287,"FTC",'Seat Ledger'!$I$5:$I$287,"OFF",'Seat Ledger'!$H$5:$H$287,"E5")+SUMIFS('Seat Ledger'!$M$5:$M$287,'Seat Ledger'!$B$5:$B$287,3,'Seat Ledger'!$J$5:$J$287,"FTC",'Seat Ledger'!$I$5:$I$287,"NEAR",'Seat Ledger'!$H$5:$H$287,"E5") | H60: =SUM(C60:G60)
B61: People we already have | C61: 0 | D61: 0.94889088 | E61: 1.5539213 | F61: 1.080183 | G61: 0.12708787 | H61: =SUM(C61:G61)
B62: Gap — positive is a hire | C62: =C60-C61 | D62: =D60-D61 | E62: =E60-E61 | F62: =F60-F61 | G62: =G60-G61 | H62: =SUM(C62:G62)
B64: Year 4 | C64: E1 | D64: E2 | E64: E3 | F64: E4 | G64: E5 | H64: Total
B65: Seats the design asks for | C65: =SUMIFS('Seat Ledger'!$M$5:$M$287,'Seat Ledger'!$B$5:$B$287,4,'Seat Ledger'!$J$5:$J$287,"FTC",'Seat Ledger'!$I$5:$I$287,"OFF",'Seat Ledger'!$H$5:$H$287,"E1")+SUMIFS('Seat Ledger'!$M$5:$M$287,'Seat Ledger'!$B$5:$B$287,4,'Seat Ledger'!$J$5:$J$287,"FTC",'Seat Ledger'!$I$5:$I$287,"NEAR",'Seat Ledger'!$H$5:$H$287,"E1") | D65: =SUMIFS('Seat Ledger'!$M$5:$M$287,'Seat Ledger'!$B$5:$B$287,4,'Seat Ledger'!$J$5:$J$287,"FTC",'Seat Ledger'!$I$5:$I$287,"OFF",'Seat Ledger'!$H$5:$H$287,"E2")+SUMIFS('Seat Ledger'!$M$5:$M$287,'Seat Ledger'!$B$5:$B$287,4,'Seat Ledger'!$J$5:$J$287,"FTC",'Seat Ledger'!$I$5:$I$287,"NEAR",'Seat Ledger'!$H$5:$H$287,"E2") | E65: =SUMIFS('Seat Ledger'!$M$5:$M$287,'Seat Ledger'!$B$5:$B$287,4,'Seat Ledger'!$J$5:$J$287,"FTC",'Seat Ledger'!$I$5:$I$287,"OFF",'Seat Ledger'!$H$5:$H$287,"E3")+SUMIFS('Seat Ledger'!$M$5:$M$287,'Seat Ledger'!$B$5:$B$287,4,'Seat Ledger'!$J$5:$J$287,"FTC",'Seat Ledger'!$I$5:$I$287,"NEAR",'Seat Ledger'!$H$5:$H$287,"E3") | F65: =SUMIFS('Seat Ledger'!$M$5:$M$287,'Seat Ledger'!$B$5:$B$287,4,'Seat Ledger'!$J$5:$J$287,"FTC",'Seat Ledger'!$I$5:$I$287,"OFF",'Seat Ledger'!$H$5:$H$287,"E4")+SUMIFS('Seat Ledger'!$M$5:$M$287,'Seat Ledger'!$B$5:$B$287,4,'Seat Ledger'!$J$5:$J$287,"FTC",'Seat Ledger'!$I$5:$I$287,"NEAR",'Seat Ledger'!$H$5:$H$287,"E4") | G65: =SUMIFS('Seat Ledger'!$M$5:$M$287,'Seat Ledger'!$B$5:$B$287,4,'Seat Ledger'!$J$5:$J$287,"FTC",'Seat Ledger'!$I$5:$I$287,"OFF",'Seat Ledger'!$H$5:$H$287,"E5")+SUMIFS('Seat Ledger'!$M$5:$M$287,'Seat Ledger'!$B$5:$B$287,4,'Seat Ledger'!$J$5:$J$287,"FTC",'Seat Ledger'!$I$5:$I$287,"NEAR",'Seat Ledger'!$H$5:$H$287,"E5") | H65: =SUM(C65:G65)
B66: People we already have | C66: 0 | D66: 0.65359604 | E66: 1.3141766 | F66: 1.0763882 | G66: 0.18827025 | H66: =SUM(C66:G66)
B67: Gap — positive is a hire | C67: =C65-C66 | D67: =D65-D66 | E67: =E65-E66 | F67: =F65-F66 | G67: =G65-G66 | H67: =SUM(C67:G67)
B69: Year 5 | C69: E1 | D69: E2 | E69: E3 | F69: E4 | G69: E5 | H69: Total
B70: Seats the design asks for | C70: =SUMIFS('Seat Ledger'!$M$5:$M$287,'Seat Ledger'!$B$5:$B$287,5,'Seat Ledger'!$J$5:$J$287,"FTC",'Seat Ledger'!$I$5:$I$287,"OFF",'Seat Ledger'!$H$5:$H$287,"E1")+SUMIFS('Seat Ledger'!$M$5:$M$287,'Seat Ledger'!$B$5:$B$287,5,'Seat Ledger'!$J$5:$J$287,"FTC",'Seat Ledger'!$I$5:$I$287,"NEAR",'Seat Ledger'!$H$5:$H$287,"E1") | D70: =SUMIFS('Seat Ledger'!$M$5:$M$287,'Seat Ledger'!$B$5:$B$287,5,'Seat Ledger'!$J$5:$J$287,"FTC",'Seat Ledger'!$I$5:$I$287,"OFF",'Seat Ledger'!$H$5:$H$287,"E2")+SUMIFS('Seat Ledger'!$M$5:$M$287,'Seat Ledger'!$B$5:$B$287,5,'Seat Ledger'!$J$5:$J$287,"FTC",'Seat Ledger'!$I$5:$I$287,"NEAR",'Seat Ledger'!$H$5:$H$287,"E2") | E70: =SUMIFS('Seat Ledger'!$M$5:$M$287,'Seat Ledger'!$B$5:$B$287,5,'Seat Ledger'!$J$5:$J$287,"FTC",'Seat Ledger'!$I$5:$I$287,"OFF",'Seat Ledger'!$H$5:$H$287,"E3")+SUMIFS('Seat Ledger'!$M$5:$M$287,'Seat Ledger'!$B$5:$B$287,5,'Seat Ledger'!$J$5:$J$287,"FTC",'Seat Ledger'!$I$5:$I$287,"NEAR",'Seat Ledger'!$H$5:$H$287,"E3") | F70: =SUMIFS('Seat Ledger'!$M$5:$M$287,'Seat Ledger'!$B$5:$B$287,5,'Seat Ledger'!$J$5:$J$287,"FTC",'Seat Ledger'!$I$5:$I$287,"OFF",'Seat Ledger'!$H$5:$H$287,"E4")+SUMIFS('Seat Ledger'!$M$5:$M$287,'Seat Ledger'!$B$5:$B$287,5,'Seat Ledger'!$J$5:$J$287,"FTC",'Seat Ledger'!$I$5:$I$287,"NEAR",'Seat Ledger'!$H$5:$H$287,"E4") | G70: =SUMIFS('Seat Ledger'!$M$5:$M$287,'Seat Ledger'!$B$5:$B$287,5,'Seat Ledger'!$J$5:$J$287,"FTC",'Seat Ledger'!$I$5:$I$287,"OFF",'Seat Ledger'!$H$5:$H$287,"E5")+SUMIFS('Seat Ledger'!$M$5:$M$287,'Seat Ledger'!$B$5:$B$287,5,'Seat Ledger'!$J$5:$J$287,"FTC",'Seat Ledger'!$I$5:$I$287,"NEAR",'Seat Ledger'!$H$5:$H$287,"E5") | H70: =SUM(C70:G70)
B71: People we already have | C71: 0 | D71: 0.45019695 | E71: 1.0918854 | F71: 1.0481474 | G71: 0.24553997 | H71: =SUM(C71:G71)
B72: Gap — positive is a hire | C72: =C70-C71 | D72: =D70-D71 | E72: =E70-E71 | F72: =F70-F71 | G72: =G70-G71 | H72: =SUM(C72:G72)
B74: The shortage is at E2 and E3 in every year, and the surplus is at E5 in every year — the mirror image of Sales. The E5 surplus is small in absolute terms (2.0 people in Year 1 rising to 2.8 by Year 5) but it is 100% of the E5 population, because the design carries no offshore E5 seat at all. Those people belong in the horizontal architecture and quality-lead roles, which is where the seat ledger puts them, or they are a redeployment out of the domain.
A76: G. WHAT THIS MEANS FOR THE SOLUTION
B77: • The continuity argument is the strongest in the portfolio. 33 of the Year-1 Capgemini offshore seats are people already sitting on these applications. The balance are hires onto a Java, JavaScript and API estate — the easiest hiring profile of the five 領域 modelled, onshore or offshore.
B78: • The talent-shape risk is manageable. The cohort is 28.9% senior on day one and seniorises from there. The design counters it by hiring at E2/E3 offshore and by placing surviving seniors in the architecture, quality-lead and pod-lead roles where they earn their band.
B79: • There is no incumbent sub-contractor to displace. Golden v4 names Capgemini on five of the ten applications and NCD on one 1.4-unit application; 13.0 vendor units carry no named vendor at all. That is a due-diligence question, not a modelled partner — and it is why the PT rows in this workbook resolve to zero.
B80: • Five people in Japan against 36.7 onshore vendor units on day one. Every other bilingual Tokyo seat is a hire or a redeployment. Smaller here than elsewhere because the stack is English-specification and the offshore ceiling is only 65.3% and 84% of the vendor population is in Tokyo today.

Sheet Glidepath & 50-50
A1: Glidepath — capability, carry-forward, offshore, and one transfer at the end of Year 3
A2: Year 1 passes nothing through. The transfer is struck on the exit position at full realisation.
A4: A. BASELINE
B5: Measure | C5: Value
B6: Applications | C6: ='Logic Tree'!C6
B7: Total effort (units) | C7: ='Logic Tree'!C7
B8: Capgemini FTC | C8: ='Logic Tree'!C8
B9: MetLife FTE | C9: ='Logic Tree'!C9
B10: MetLife MGCC | C10: ='Logic Tree'!C10
B11: Ratio today — Capgemini share | C11: ='Logic Tree'!C23
B12: Offshore today — whole team, measured | C12: ='Logic Tree'!C24 | I12: 45.5% offshore on day one — 28.87 offshore, 0.96 nearshore and 15.99 MGCC against 100.765 units. A 30.0% start against a 65.3% ceiling — the gap is real but the runway is long.
B13: Appendix 3 Year-3 target, each side | C13: ='Logic Tree'!C22
A15: B. PRODUCTIVITY
B16: Measure | C16: Year 1 | D16: Year 2 | E16: Year 3 | F16: Year 4 | G16: Year 5
B17: Agile share of the domain | C17: ='Delivery Mode'!C20 | D17: ='Delivery Mode'!D20 | E17: ='Delivery Mode'!E20 | F17: ='Delivery Mode'!F20 | G17: ='Delivery Mode'!G20
B18: Capability earned by end of year | C18: ='Logic Tree'!C45 | D18: ='Logic Tree'!D45 | E18: ='Logic Tree'!E45 | F18: ='Logic Tree'!F45 | G18: ='Logic Tree'!G45
B19: Banked from prior year | C19: ='Logic Tree'!C50 | D19: ='Logic Tree'!D50 | E19: ='Logic Tree'!E50 | F19: ='Logic Tree'!F50 | G19: ='Logic Tree'!G50
B20: Pre-load of this year's gain | C20: ='Logic Tree'!C51 | D20: ='Logic Tree'!D51 | E20: ='Logic Tree'!E51 | F20: ='Logic Tree'!F51 | G20: ='Logic Tree'!G51
B21: APPLIED TO STAFFING | C21: ='Logic Tree'!C52 | D21: ='Logic Tree'!D52 | E21: ='Logic Tree'!E52 | F21: ='Logic Tree'!F52 | G21: ='Logic Tree'!G52 | I21: Year 1 applies nothing: the capability the tree allows is consumed by transition, substrate build and the agile conversion itself.
B22: Headcount target | C22: ='Logic Tree'!C53 | D22: ='Logic Tree'!D53 | E22: ='Logic Tree'!E53 | F22: ='Logic Tree'!F53 | G22: ='Logic Tree'!G53
B23: Headcount delivered by the design | C23: ='Team Build-Up'!C9 | D23: ='Team Build-Up'!D9 | E23: ='Team Build-Up'!E9 | F23: ='Team Build-Up'!F9 | G23: ='Team Build-Up'!G9
B24: Variance | C24: ='Team Build-Up'!C12 | D24: ='Team Build-Up'!D12 | E24: ='Team Build-Up'!E12 | F24: ='Team Build-Up'!F12 | G24: ='Team Build-Up'!G12
B25: Delivered productivity vs baseline | C25: =1-C23/$C$7 | D25: =1-D23/$C$7 | E25: =1-E23/$C$7 | F25: =1-F23/$C$7 | G25: =1-G23/$C$7
B26: EXIT YEAR 3 — full realisation, the point the transfer is struck | E26: ='Logic Tree'!E54
A28: C. OFFSHORE
B29: Measure | C29: Year 1 | D29: Year 2 | E29: Year 3 | F29: Year 4 | G29: Year 5
B30: Delivered — bottom-up from seat locations | C30: ='Team Build-Up'!C54 | D30: ='Team Build-Up'!D54 | E30: ='Team Build-Up'!E54 | F30: ='Team Build-Up'!F54 | G30: ='Team Build-Up'!G54
B31: Target — today plus the closed gap | C31: ='Logic Tree'!C68 | D31: ='Logic Tree'!D68 | E31: ='Logic Tree'!E68 | F31: ='Logic Tree'!F68 | G31: ='Logic Tree'!G68
B32: Delivered — Capgemini payroll only | C32: ='Team Build-Up'!C56 | D32: ='Team Build-Up'!D56 | E32: ='Team Build-Up'!E56 | F32: ='Team Build-Up'!F56 | G32: ='Team Build-Up'!G56
B33: Movement from today, in people | C33: =C30*'Team Build-Up'!C9-$C$12*$C$7 | D33: =D30*'Team Build-Up'!D9-$C$12*$C$7 | E33: =E30*'Team Build-Up'!E9-$C$12*$C$7 | F33: =F30*'Team Build-Up'!F9-$C$12*$C$7 | G33: =G30*'Team Build-Up'!G9-$C$12*$C$7 | I33: The offshore SHARE rises every year while the offshore HEADCOUNT falls from Year 2. Both are true and only the second one costs anything.
A35: D. THE 50:50
B36: Measure | C36: Year 1 | D36: Year 2 | E36: Year 3 | F36: Year 4 | G36: Year 5
B37: Total people | C37: ='Team Build-Up'!C9 | D37: ='Team Build-Up'!D9 | E37: ='Team Build-Up'!E9 | F37: ='Team Build-Up'!F9 | G37: ='Team Build-Up'!G9
B38: Vendor total (Capgemini + partner) | C38: ='Team Build-Up'!C47 | D38: ='Team Build-Up'!D47 | E38: ='Team Build-Up'!E47 | F38: ='Team Build-Up'!F47 | G38: ='Team Build-Up'!G47
B39: — Capgemini payroll | C39: ='Team Build-Up'!C45 | D39: ='Team Build-Up'!D45 | E39: ='Team Build-Up'!E45 | F39: ='Team Build-Up'!F45 | G39: ='Team Build-Up'!G45
B40: — named sub-contractor (zero in this 領域) | C40: ='Team Build-Up'!C46 | D40: ='Team Build-Up'!D46 | E40: ='Team Build-Up'!E46 | F40: ='Team Build-Up'!F46 | G40: ='Team Build-Up'!G46
B41: MetLife FTE | C41: ='Team Build-Up'!C48 | D41: ='Team Build-Up'!D48 | E41: ='Team Build-Up'!E48 | F41: ='Team Build-Up'!F48 | G41: ='Team Build-Up'!G48
B42: MetLife MGCC | C42: ='Team Build-Up'!C49 | D42: ='Team Build-Up'!D49 | E42: ='Team Build-Up'!E49 | F42: ='Team Build-Up'!F49 | G42: ='Team Build-Up'!G49
B43: MetLife side total | C43: =C41+C42 | D43: =D41+D42 | E43: =E41+E42 | F43: =F41+F42 | G43: =G41+G42
B44: Transferred this year | C44: ='Logic Tree'!C75+'Logic Tree'!C76 | D44: ='Logic Tree'!D75+'Logic Tree'!D76 | E44: ='Logic Tree'!E75+'Logic Tree'!E76 | F44: ='Logic Tree'!F75+'Logic Tree'!F76 | G44: ='Logic Tree'!G75+'Logic Tree'!G76
B45: RATIO — Capgemini share | C45: =IF(C37=0,0,C38/C37) | D45: =IF(D37=0,0,D38/D37) | E45: =IF(E37=0,0,E38/E37) | F45: =IF(F37=0,0,F38/F37) | G45: =IF(G37=0,0,G38/G37)
I46: Years 1-3 are the pre-transfer position. Year 4 and Year 5 already carry the transferred seats as MetLife, inside the pods.
A48: E. THE TRANSFER SOLVE — Capgemini payroll only, and here it closes
C49: Value
B50: Exit Year 3 headcount, full realisation | C50: =E26 | I50: ZERO. The whole Capgemini population is transferable — there is no sub-contractor — but none of it needs to move, because the ratio is already past 50:50 on day one.
B51: Vendor share at the exit position | C51: =E45
B52: Vendor units at exit, before transfer | C52: =C50*C51
B53: — of which sub-contracted, IMMOVABLE | C53: =E40/E37*C50
B54: — of which Capgemini payroll, the transfer pool | C54: =C52-C53
B55: 50:50 requires each side to be | C55: =C50/2
B56: TRANSFER REQUIRED | C56: =C52-C55 | I56: The requirement computes NEGATIVE — the model is 4.46 people the wrong side of 50:50, in MetLife's favour. Transfer applied is zero, and the row is kept so the arithmetic is visible.
B57: Cap on the transferable pool — solution constraint | C57: =0.7
B58: Maximum transferable from Capgemini payroll | C58: =C54*C57
B59: Transfer applied in the model | C59: ='Logic Tree'!E77
B60: Transfer as a share of the Capgemini pool | C60: =C59/C54
B61: RESIDUAL GAP TO 50:50 | C61: =C56-C59 | I61: The Year-3 exit lands at exactly 50.0% and Years 4 and 5 hold there, because the transferred seats sit inside the pod anatomy rather than being re-solved each year.
B62: Ratio actually reached at the Year-3 exit | C62: =(C52-C59)/C50
A65: F. WHAT THIS DOMAIN SHOWS
B66: • THE 50:50 CLOSES WITH NO TRANSFER AT ALL. Capgemini holds 70.4% of the delivery population on day one — the highest start in the estate. Differential shrinkage takes it to 62.4% by Year 3 and 50.6% by Year 5, and the 50% floor is reached without moving a single person. The transfer rows are set to zero and left live.
B67: • Productivity is 0 / 22.3 / 35.5 / 40.5 / 49.9% on retained scope. Capability earned runs 14.2 / 30.4 / 40.5 / 47.9 / 51.8%. Year 4 applies only what was banked at the end of Year 3 and pre-loads none of its own gain, because that year absorbs the retirement of POS Workflow and the conversion of Payment & Records to pods.
B68: • Offshore reaches the re-cut ceiling. 30.0% today against 65.27% in Years 1-3 and 60.13% from Year 4, and the roster delivers 31.3 / 40.7 / 49.0 / 53.4 / 59.8%. Losing POS Workflow LOWERS the ceiling — it was archetype D at 78% — so Year 5 sits on 60.1% rather than pushing past it.
B69: • The adoption factors are the portfolio defaults: 1.00 Capgemini, 0.85 FSI, 0.80 MGCC, 0.55 MetLife Japan.
B70: • Three things to challenge. First the Developer restatement — 20.4 units, the largest in the portfolio, and the only red check. Second whether Payment & Records should convert to pods before Year 4. Third the retirement itself: the model now takes 34.997 units out of the baseline at Year 4, so if the retirement slips, Years 4 and 5 need re-staffing against 121.573 and the commitment falls from 49.9% to about 40%.
B71: • The one number to challenge is MetLife's own. The Maintenance role line says 1.00 unit of run against 732 incidents and 1,161 changes a year, while the AD / AMS effort split in the same spreadsheet implies 6.75 units — a factor of seven, the widest disagreement of any 領域 modelled. And ZERO project management is recorded across six applications and three value streams. We restate both, arithmetically neutral, and views is about six people of exposure on a 122-person domain. It sets the AMS price, so it should be resolved before submission.

Sheet Cost & Commercial
A1: Cost and commercial position — relative index pending the rate card
A2: Onshore Tokyo E2 = 1.00. Unit cost divides by the frozen baseline effort.
A4: A. TOTAL COST OF DELIVERING THE DOMAIN
B5: Measure | C5: Year 1 | D5: Year 2 | E5: Year 3 | F5: Year 4 | G5: Year 5
B6: Total cost index | C6: =SUMIFS('Seat Ledger'!$N$5:$N$287,'Seat Ledger'!$B$5:$B$287,1) | D6: =SUMIFS('Seat Ledger'!$N$5:$N$287,'Seat Ledger'!$B$5:$B$287,2) | E6: =SUMIFS('Seat Ledger'!$N$5:$N$287,'Seat Ledger'!$B$5:$B$287,3) | F6: =SUMIFS('Seat Ledger'!$N$5:$N$287,'Seat Ledger'!$B$5:$B$287,4) | G6: =SUMIFS('Seat Ledger'!$N$5:$N$287,'Seat Ledger'!$B$5:$B$287,5)
B7: Headcount | C7: ='Team Build-Up'!C9 | D7: ='Team Build-Up'!D9 | E7: ='Team Build-Up'!E9 | F7: ='Team Build-Up'!F9 | G7: ='Team Build-Up'!G9
B8: Average cost per head | C8: =IF(C7=0,0,C6/C7) | D8: =IF(D7=0,0,D6/D7) | E8: =IF(E7=0,0,E6/E7) | F8: =IF(F7=0,0,F6/F7) | G8: =IF(G7=0,0,G6/G7)
B9: Cost per unit of frozen scope | C9: =IF('Glidepath & 50-50'!$C$7=0,0,C6/'Glidepath & 50-50'!$C$7) | D9: =IF('Glidepath & 50-50'!$C$7=0,0,D6/'Glidepath & 50-50'!$C$7) | E9: =IF('Glidepath & 50-50'!$C$7=0,0,E6/'Glidepath & 50-50'!$C$7) | F9: =IF('Glidepath & 50-50'!$C$7=0,0,F6/'Glidepath & 50-50'!$C$7) | G9: =IF('Glidepath & 50-50'!$C$7=0,0,G6/'Glidepath & 50-50'!$C$7)
B10: Unit cost reduction vs Year 1 | C10: =IF($C$9=0,0,1-C9/$C$9) | D10: =IF($C$9=0,0,1-D9/$C$9) | E10: =IF($C$9=0,0,1-E9/$C$9) | F10: =IF($C$9=0,0,1-F9/$C$9) | G10: =IF($C$9=0,0,1-G9/$C$9)
A12: B. CAPGEMINI POSITION
B13: Measure | C13: Year 1 | D13: Year 2 | E13: Year 3 | F13: Year 4 | G13: Year 5
B14: Capgemini heads | C14: ='Team Build-Up'!C45 | D14: ='Team Build-Up'!D45 | E14: ='Team Build-Up'!E45 | F14: ='Team Build-Up'!F45 | G14: ='Team Build-Up'!G45
B15: Capgemini cost index | C15: =SUMIFS('Seat Ledger'!$N$5:$N$287,'Seat Ledger'!$B$5:$B$287,1,'Seat Ledger'!$J$5:$J$287,"FTC") | D15: =SUMIFS('Seat Ledger'!$N$5:$N$287,'Seat Ledger'!$B$5:$B$287,2,'Seat Ledger'!$J$5:$J$287,"FTC") | E15: =SUMIFS('Seat Ledger'!$N$5:$N$287,'Seat Ledger'!$B$5:$B$287,3,'Seat Ledger'!$J$5:$J$287,"FTC") | F15: =SUMIFS('Seat Ledger'!$N$5:$N$287,'Seat Ledger'!$B$5:$B$287,4,'Seat Ledger'!$J$5:$J$287,"FTC") | G15: =SUMIFS('Seat Ledger'!$N$5:$N$287,'Seat Ledger'!$B$5:$B$287,5,'Seat Ledger'!$J$5:$J$287,"FTC")
B16: Capgemini position vs Year 1 | C16: =IF($C$15=0,0,C15/$C$15-1) | D16: =IF($C$15=0,0,D15/$C$15-1) | E16: =IF($C$15=0,0,E15/$C$15-1) | F16: =IF($C$15=0,0,F15/$C$15-1) | G16: =IF($C$15=0,0,G15/$C$15-1)
A18: C. COST BY LOCATION, BAND AND ROLE
B19: Split | C19: Year 1 | D19: Year 2 | E19: Year 3 | F19: Year 4 | G19: Year 5
B20: Onshore Tokyo — cost index | C20: =SUMIFS('Seat Ledger'!$N$5:$N$287,'Seat Ledger'!$B$5:$B$287,1,'Seat Ledger'!$I$5:$I$287,"ON") | D20: =SUMIFS('Seat Ledger'!$N$5:$N$287,'Seat Ledger'!$B$5:$B$287,2,'Seat Ledger'!$I$5:$I$287,"ON") | E20: =SUMIFS('Seat Ledger'!$N$5:$N$287,'Seat Ledger'!$B$5:$B$287,3,'Seat Ledger'!$I$5:$I$287,"ON") | F20: =SUMIFS('Seat Ledger'!$N$5:$N$287,'Seat Ledger'!$B$5:$B$287,4,'Seat Ledger'!$I$5:$I$287,"ON") | G20: =SUMIFS('Seat Ledger'!$N$5:$N$287,'Seat Ledger'!$B$5:$B$287,5,'Seat Ledger'!$I$5:$I$287,"ON")
B21: Offshore — cost index | C21: =SUMIFS('Seat Ledger'!$N$5:$N$287,'Seat Ledger'!$B$5:$B$287,1,'Seat Ledger'!$I$5:$I$287,"OFF") | D21: =SUMIFS('Seat Ledger'!$N$5:$N$287,'Seat Ledger'!$B$5:$B$287,2,'Seat Ledger'!$I$5:$I$287,"OFF") | E21: =SUMIFS('Seat Ledger'!$N$5:$N$287,'Seat Ledger'!$B$5:$B$287,3,'Seat Ledger'!$I$5:$I$287,"OFF") | F21: =SUMIFS('Seat Ledger'!$N$5:$N$287,'Seat Ledger'!$B$5:$B$287,4,'Seat Ledger'!$I$5:$I$287,"OFF") | G21: =SUMIFS('Seat Ledger'!$N$5:$N$287,'Seat Ledger'!$B$5:$B$287,5,'Seat Ledger'!$I$5:$I$287,"OFF")
B22: Nearshore — cost index | C22: =SUMIFS('Seat Ledger'!$N$5:$N$287,'Seat Ledger'!$B$5:$B$287,1,'Seat Ledger'!$I$5:$I$287,"NEAR") | D22: =SUMIFS('Seat Ledger'!$N$5:$N$287,'Seat Ledger'!$B$5:$B$287,2,'Seat Ledger'!$I$5:$I$287,"NEAR") | E22: =SUMIFS('Seat Ledger'!$N$5:$N$287,'Seat Ledger'!$B$5:$B$287,3,'Seat Ledger'!$I$5:$I$287,"NEAR") | F22: =SUMIFS('Seat Ledger'!$N$5:$N$287,'Seat Ledger'!$B$5:$B$287,4,'Seat Ledger'!$I$5:$I$287,"NEAR") | G22: =SUMIFS('Seat Ledger'!$N$5:$N$287,'Seat Ledger'!$B$5:$B$287,5,'Seat Ledger'!$I$5:$I$287,"NEAR")
B23: Onshore share of cost | C23: =IF(SUM(C20:C22)=0,0,C20/SUM(C20:C22)) | D23: =IF(SUM(D20:D22)=0,0,D20/SUM(D20:D22)) | E23: =IF(SUM(E20:E22)=0,0,E20/SUM(E20:E22)) | F23: =IF(SUM(F20:F22)=0,0,F20/SUM(F20:F22)) | G23: =IF(SUM(G20:G22)=0,0,G20/SUM(G20:G22))
B25: BSA — business and systems analysis — cost index | C25: =SUMIFS('Seat Ledger'!$N$5:$N$287,'Seat Ledger'!$B$5:$B$287,1,'Seat Ledger'!$G$5:$G$287,"BSA") | D25: =SUMIFS('Seat Ledger'!$N$5:$N$287,'Seat Ledger'!$B$5:$B$287,2,'Seat Ledger'!$G$5:$G$287,"BSA") | E25: =SUMIFS('Seat Ledger'!$N$5:$N$287,'Seat Ledger'!$B$5:$B$287,3,'Seat Ledger'!$G$5:$G$287,"BSA") | F25: =SUMIFS('Seat Ledger'!$N$5:$N$287,'Seat Ledger'!$B$5:$B$287,4,'Seat Ledger'!$G$5:$G$287,"BSA") | G25: =SUMIFS('Seat Ledger'!$N$5:$N$287,'Seat Ledger'!$B$5:$B$287,5,'Seat Ledger'!$G$5:$G$287,"BSA")
B26: Developer — cost index | C26: =SUMIFS('Seat Ledger'!$N$5:$N$287,'Seat Ledger'!$B$5:$B$287,1,'Seat Ledger'!$G$5:$G$287,"DEV") | D26: =SUMIFS('Seat Ledger'!$N$5:$N$287,'Seat Ledger'!$B$5:$B$287,2,'Seat Ledger'!$G$5:$G$287,"DEV") | E26: =SUMIFS('Seat Ledger'!$N$5:$N$287,'Seat Ledger'!$B$5:$B$287,3,'Seat Ledger'!$G$5:$G$287,"DEV") | F26: =SUMIFS('Seat Ledger'!$N$5:$N$287,'Seat Ledger'!$B$5:$B$287,4,'Seat Ledger'!$G$5:$G$287,"DEV") | G26: =SUMIFS('Seat Ledger'!$N$5:$N$287,'Seat Ledger'!$B$5:$B$287,5,'Seat Ledger'!$G$5:$G$287,"DEV")
B27: Tester — cost index | C27: =SUMIFS('Seat Ledger'!$N$5:$N$287,'Seat Ledger'!$B$5:$B$287,1,'Seat Ledger'!$G$5:$G$287,"TEST") | D27: =SUMIFS('Seat Ledger'!$N$5:$N$287,'Seat Ledger'!$B$5:$B$287,2,'Seat Ledger'!$G$5:$G$287,"TEST") | E27: =SUMIFS('Seat Ledger'!$N$5:$N$287,'Seat Ledger'!$B$5:$B$287,3,'Seat Ledger'!$G$5:$G$287,"TEST") | F27: =SUMIFS('Seat Ledger'!$N$5:$N$287,'Seat Ledger'!$B$5:$B$287,4,'Seat Ledger'!$G$5:$G$287,"TEST") | G27: =SUMIFS('Seat Ledger'!$N$5:$N$287,'Seat Ledger'!$B$5:$B$287,5,'Seat Ledger'!$G$5:$G$287,"TEST")
B28: Maintenance — cost index | C28: =SUMIFS('Seat Ledger'!$N$5:$N$287,'Seat Ledger'!$B$5:$B$287,1,'Seat Ledger'!$G$5:$G$287,"MNT") | D28: =SUMIFS('Seat Ledger'!$N$5:$N$287,'Seat Ledger'!$B$5:$B$287,2,'Seat Ledger'!$G$5:$G$287,"MNT") | E28: =SUMIFS('Seat Ledger'!$N$5:$N$287,'Seat Ledger'!$B$5:$B$287,3,'Seat Ledger'!$G$5:$G$287,"MNT") | F28: =SUMIFS('Seat Ledger'!$N$5:$N$287,'Seat Ledger'!$B$5:$B$287,4,'Seat Ledger'!$G$5:$G$287,"MNT") | G28: =SUMIFS('Seat Ledger'!$N$5:$N$287,'Seat Ledger'!$B$5:$B$287,5,'Seat Ledger'!$G$5:$G$287,"MNT")
B29: PM and product ownership — cost index | C29: =SUMIFS('Seat Ledger'!$N$5:$N$287,'Seat Ledger'!$B$5:$B$287,1,'Seat Ledger'!$G$5:$G$287,"PM") | D29: =SUMIFS('Seat Ledger'!$N$5:$N$287,'Seat Ledger'!$B$5:$B$287,2,'Seat Ledger'!$G$5:$G$287,"PM") | E29: =SUMIFS('Seat Ledger'!$N$5:$N$287,'Seat Ledger'!$B$5:$B$287,3,'Seat Ledger'!$G$5:$G$287,"PM") | F29: =SUMIFS('Seat Ledger'!$N$5:$N$287,'Seat Ledger'!$B$5:$B$287,4,'Seat Ledger'!$G$5:$G$287,"PM") | G29: =SUMIFS('Seat Ledger'!$N$5:$N$287,'Seat Ledger'!$B$5:$B$287,5,'Seat Ledger'!$G$5:$G$287,"PM")
B30: Other — architecture and enablement — cost index | C30: =SUMIFS('Seat Ledger'!$N$5:$N$287,'Seat Ledger'!$B$5:$B$287,1,'Seat Ledger'!$G$5:$G$287,"OTH") | D30: =SUMIFS('Seat Ledger'!$N$5:$N$287,'Seat Ledger'!$B$5:$B$287,2,'Seat Ledger'!$G$5:$G$287,"OTH") | E30: =SUMIFS('Seat Ledger'!$N$5:$N$287,'Seat Ledger'!$B$5:$B$287,3,'Seat Ledger'!$G$5:$G$287,"OTH") | F30: =SUMIFS('Seat Ledger'!$N$5:$N$287,'Seat Ledger'!$B$5:$B$287,4,'Seat Ledger'!$G$5:$G$287,"OTH") | G30: =SUMIFS('Seat Ledger'!$N$5:$N$287,'Seat Ledger'!$B$5:$B$287,5,'Seat Ledger'!$G$5:$G$287,"OTH")
B32: The role view is the one Pricing will want. Unit cost falls 74% from Year 1 to Year 5 on the FROZEN scope denominator — but 28.8% of that is POS Workflow leaving the estate, so the like-for-like reduction on retained scope is about 63%. Average cost per head falls as the roster moves offshore and the senior share comes down from 23.9% to 19.5%.

Sheet Seat Ledger
A1: Seat ledger — every pod-library line multiplied out, plus every horizontal seat
A2: Computed. Every roll-up in this workbook is a SUMIFS over this one table. Do not edit.
B4: Year | C4: Origin | D4: Unit | E4: Type | F4: Role detail | G4: Role | H4: Exp | I4: Loc | J4: Sourcing | K4: Seats/unit | L4: Units | M4: Heads | N4: Cost index
B5: 1 | C5: POD | D5: VS1 | E5: POD | F5: ='Pod Library'!E5 | G5: ='Pod Library'!F5 | H5: ='Pod Library'!G5 | I5: ='Pod Library'!H5 | J5: ='Pod Library'!I5 | K5: ='Pod Library'!J5 | L5: ='Pod Plan'!G5 | M5: =K5*L5 | N5: =M5*INDEX('Logic Tree'!$J$85:$N$87,MATCH(I5,'Logic Tree'!$I$85:$I$87,0),MATCH(H5,'Logic Tree'!$J$84:$N$84,0))
B6: 1 | C6: POD | D6: VS1 | E6: POD | F6: ='Pod Library'!E6 | G6: ='Pod Library'!F6 | H6: ='Pod Library'!G6 | I6: ='Pod Library'!H6 | J6: ='Pod Library'!I6 | K6: ='Pod Library'!J6 | L6: ='Pod Plan'!G5 | M6: =K6*L6 | N6: =M6*INDEX('Logic Tree'!$J$85:$N$87,MATCH(I6,'Logic Tree'!$I$85:$I$87,0),MATCH(H6,'Logic Tree'!$J$84:$N$84,0))
B7: 1 | C7: POD | D7: VS1 | E7: POD | F7: ='Pod Library'!E7 | G7: ='Pod Library'!F7 | H7: ='Pod Library'!G7 | I7: ='Pod Library'!H7 | J7: ='Pod Library'!I7 | K7: ='Pod Library'!J7 | L7: ='Pod Plan'!G5 | M7: =K7*L7 | N7: =M7*INDEX('Logic Tree'!$J$85:$N$87,MATCH(I7,'Logic Tree'!$I$85:$I$87,0),MATCH(H7,'Logic Tree'!$J$84:$N$84,0))
B8: 1 | C8: POD | D8: VS1 | E8: POD | F8: ='Pod Library'!E8 | G8: ='Pod Library'!F8 | H8: ='Pod Library'!G8 | I8: ='Pod Library'!H8 | J8: ='Pod Library'!I8 | K8: ='Pod Library'!J8 | L8: ='Pod Plan'!G5 | M8: =K8*L8 | N8: =M8*INDEX('Logic Tree'!$J$85:$N$87,MATCH(I8,'Logic Tree'!$I$85:$I$87,0),MATCH(H8,'Logic Tree'!$J$84:$N$84,0))
B9: 1 | C9: POD | D9: VS1 | E9: POD | F9: ='Pod Library'!E9 | G9: ='Pod Library'!F9 | H9: ='Pod Library'!G9 | I9: ='Pod Library'!H9 | J9: ='Pod Library'!I9 | K9: ='Pod Library'!J9 | L9: ='Pod Plan'!G5 | M9: =K9*L9 | N9: =M9*INDEX('Logic Tree'!$J$85:$N$87,MATCH(I9,'Logic Tree'!$I$85:$I$87,0),MATCH(H9,'Logic Tree'!$J$84:$N$84,0))
B10: 1 | C10: POD | D10: VS1 | E10: POD | F10: ='Pod Library'!E10 | G10: ='Pod Library'!F10 | H10: ='Pod Library'!G10 | I10: ='Pod Library'!H10 | J10: ='Pod Library'!I10 | K10: ='Pod Library'!J10 | L10: ='Pod Plan'!G5 | M10: =K10*L10 | N10: =M10*INDEX('Logic Tree'!$J$85:$N$87,MATCH(I10,'Logic Tree'!$I$85:$I$87,0),MATCH(H10,'Logic Tree'!$J$84:$N$84,0))
B11: 1 | C11: POD | D11: VS1 | E11: POD | F11: ='Pod Library'!E11 | G11: ='Pod Library'!F11 | H11: ='Pod Library'!G11 | I11: ='Pod Library'!H11 | J11: ='Pod Library'!I11 | K11: ='Pod Library'!J11 | L11: ='Pod Plan'!G5 | M11: =K11*L11 | N11: =M11*INDEX('Logic Tree'!$J$85:$N$87,MATCH(I11,'Logic Tree'!$I$85:$I$87,0),MATCH(H11,'Logic Tree'!$J$84:$N$84,0))
B12: 1 | C12: POD | D12: VS1 | E12: POD | F12: ='Pod Library'!E12 | G12: ='Pod Library'!F12 | H12: ='Pod Library'!G12 | I12: ='Pod Library'!H12 | J12: ='Pod Library'!I12 | K12: ='Pod Library'!J12 | L12: ='Pod Plan'!G5 | M12: =K12*L12 | N12: =M12*INDEX('Logic Tree'!$J$85:$N$87,MATCH(I12,'Logic Tree'!$I$85:$I$87,0),MATCH(H12,'Logic Tree'!$J$84:$N$84,0))
B13: 1 | C13: POD | D13: VS1 | E13: POD | F13: ='Pod Library'!E13 | G13: ='Pod Library'!F13 | H13: ='Pod Library'!G13 | I13: ='Pod Library'!H13 | J13: ='Pod Library'!I13 | K13: ='Pod Library'!J13 | L13: ='Pod Plan'!G5 | M13: =K13*L13 | N13: =M13*INDEX('Logic Tree'!$J$85:$N$87,MATCH(I13,'Logic Tree'!$I$85:$I$87,0),MATCH(H13,'Logic Tree'!$J$84:$N$84,0))
B14: 1 | C14: POD | D14: VS1 | E14: POD | F14: ='Pod Library'!E14 | G14: ='Pod Library'!F14 | H14: ='Pod Library'!G14 | I14: ='Pod Library'!H14 | J14: ='Pod Library'!I14 | K14: ='Pod Library'!J14 | L14: ='Pod Plan'!G5 | M14: =K14*L14 | N14: =M14*INDEX('Logic Tree'!$J$85:$N$87,MATCH(I14,'Logic Tree'!$I$85:$I$87,0),MATCH(H14,'Logic Tree'!$J$84:$N$84,0))
B15: 1 | C15: POD | D15: VS1 | E15: POD | F15: ='Pod Library'!E15 | G15: ='Pod Library'!F15 | H15: ='Pod Library'!G15 | I15: ='Pod Library'!H15 | J15: ='Pod Library'!I15 | K15: ='Pod Library'!J15 | L15: ='Pod Plan'!G5 | M15: =K15*L15 | N15: =M15*INDEX('Logic Tree'!$J$85:$N$87,MATCH(I15,'Logic Tree'!$I$85:$I$87,0),MATCH(H15,'Logic Tree'!$J$84:$N$84,0))
B16: 1 | C16: POD | D16: VS1 | E16: POD | F16: ='Pod Library'!E16 | G16: ='Pod Library'!F16 | H16: ='Pod Library'!G16 | I16: ='Pod Library'!H16 | J16: ='Pod Library'!I16 | K16: ='Pod Library'!J16 | L16: ='Pod Plan'!G5 | M16: =K16*L16 | N16: =M16*INDEX('Logic Tree'!$J$85:$N$87,MATCH(I16,'Logic Tree'!$I$85:$I$87,0),MATCH(H16,'Logic Tree'!$J$84:$N$84,0))
B17: 1 | C17: POD | D17: VS1 | E17: POD | F17: ='Pod Library'!E17 | G17: ='Pod Library'!F17 | H17: ='Pod Library'!G17 | I17: ='Pod Library'!H17 | J17: ='Pod Library'!I17 | K17: ='Pod Library'!J17 | L17: ='Pod Plan'!G5 | M17: =K17*L17 | N17: =M17*INDEX('Logic Tree'!$J$85:$N$87,MATCH(I17,'Logic Tree'!$I$85:$I$87,0),MATCH(H17,'Logic Tree'!$J$84:$N$84,0))
B18: 1 | C18: POD | D18: VS1 | E18: POD | F18: ='Pod Library'!E18 | G18: ='Pod Library'!F18 | H18: ='Pod Library'!G18 | I18: ='Pod Library'!H18 | J18: ='Pod Library'!I18 | K18: ='Pod Library'!J18 | L18: ='Pod Plan'!G5 | M18: =K18*L18 | N18: =M18*INDEX('Logic Tree'!$J$85:$N$87,MATCH(I18,'Logic Tree'!$I$85:$I$87,0),MATCH(H18,'Logic Tree'!$J$84:$N$84,0))
B19: 1 | C19: POD | D19: VS1 | E19: POD | F19: ='Pod Library'!E19 | G19: ='Pod Library'!F19 | H19: ='Pod Library'!G19 | I19: ='Pod Library'!H19 | J19: ='Pod Library'!I19 | K19: ='Pod Library'!J19 | L19: ='Pod Plan'!G5 | M19: =K19*L19 | N19: =M19*INDEX('Logic Tree'!$J$85:$N$87,MATCH(I19,'Logic Tree'!$I$85:$I$87,0),MATCH(H19,'Logic Tree'!$J$84:$N$84,0))
B20: 1 | C20: POD | D20: VS1 | E20: POD | F20: ='Pod Library'!E20 | G20: ='Pod Library'!F20 | H20: ='Pod Library'!G20 | I20: ='Pod Library'!H20 | J20: ='Pod Library'!I20 | K20: ='Pod Library'!J20 | L20: ='Pod Plan'!G5 | M20: =K20*L20 | N20: =M20*INDEX('Logic Tree'!$J$85:$N$87,MATCH(I20,'Logic Tree'!$I$85:$I$87,0),MATCH(H20,'Logic Tree'!$J$84:$N$84,0))
B21: 1 | C21: TEAM | D21: VS2 | E21: TEAM | F21: ='Pod Library'!E23 | G21: ='Pod Library'!F23 | H21: ='Pod Library'!G23 | I21: ='Pod Library'!H23 | J21: ='Pod Library'!I23 | K21: ='Pod Library'!J23 | L21: ='Pod Plan'!G6 | M21: =K21*L21 | N21: =M21*INDEX('Logic Tree'!$J$85:$N$87,MATCH(I21,'Logic Tree'!$I$85:$I$87,0),MATCH(H21,'Logic Tree'!$J$84:$N$84,0))
B22: 1 | C22: TEAM | D22: VS2 | E22: TEAM | F22: ='Pod Library'!E24 | G22: ='Pod Library'!F24 | H22: ='Pod Library'!G24 | I22: ='Pod Library'!H24 | J22: ='Pod Library'!I24 | K22: ='Pod Library'!J24 | L22: ='Pod Plan'!G6 | M22: =K22*L22 | N22: =M22*INDEX('Logic Tree'!$J$85:$N$87,MATCH(I22,'Logic Tree'!$I$85:$I$87,0),MATCH(H22,'Logic Tree'!$J$84:$N$84,0))
B23: 1 | C23: TEAM | D23: VS2 | E23: TEAM | F23: ='Pod Library'!E25 | G23: ='Pod Library'!F25 | H23: ='Pod Library'!G25 | I23: ='Pod Library'!H25 | J23: ='Pod Library'!I25 | K23: ='Pod Library'!J25 | L23: ='Pod Plan'!G6 | M23: =K23*L23 | N23: =M23*INDEX('Logic Tree'!$J$85:$N$87,MATCH(I23,'Logic Tree'!$I$85:$I$87,0),MATCH(H23,'Logic Tree'!$J$84:$N$84,0))
B24: 1 | C24: TEAM | D24: VS2 | E24: TEAM | F24: ='Pod Library'!E26 | G24: ='Pod Library'!F26 | H24: ='Pod Library'!G26 | I24: ='Pod Library'!H26 | J24: ='Pod Library'!I26 | K24: ='Pod Library'!J26 | L24: ='Pod Plan'!G6 | M24: =K24*L24 | N24: =M24*INDEX('Logic Tree'!$J$85:$N$87,MATCH(I24,'Logic Tree'!$I$85:$I$87,0),MATCH(H24,'Logic Tree'!$J$84:$N$84,0))
B25: 1 | C25: TEAM | D25: VS2 | E25: TEAM | F25: ='Pod Library'!E27 | G25: ='Pod Library'!F27 | H25: ='Pod Library'!G27 | I25: ='Pod Library'!H27 | J25: ='Pod Library'!I27 | K25: ='Pod Library'!J27 | L25: ='Pod Plan'!G6 | M25: =K25*L25 | N25: =M25*INDEX('Logic Tree'!$J$85:$N$87,MATCH(I25,'Logic Tree'!$I$85:$I$87,0),MATCH(H25,'Logic Tree'!$J$84:$N$84,0))
B26: 1 | C26: TEAM | D26: VS2 | E26: TEAM | F26: ='Pod Library'!E28 | G26: ='Pod Library'!F28 | H26: ='Pod Library'!G28 | I26: ='Pod Library'!H28 | J26: ='Pod Library'!I28 | K26: ='Pod Library'!J28 | L26: ='Pod Plan'!G6 | M26: =K26*L26 | N26: =M26*INDEX('Logic Tree'!$J$85:$N$87,MATCH(I26,'Logic Tree'!$I$85:$I$87,0),MATCH(H26,'Logic Tree'!$J$84:$N$84,0))
B27: 1 | C27: TEAM | D27: VS2 | E27: TEAM | F27: ='Pod Library'!E29 | G27: ='Pod Library'!F29 | H27: ='Pod Library'!G29 | I27: ='Pod Library'!H29 | J27: ='Pod Library'!I29 | K27: ='Pod Library'!J29 | L27: ='Pod Plan'!G6 | M27: =K27*L27 | N27: =M27*INDEX('Logic Tree'!$J$85:$N$87,MATCH(I27,'Logic Tree'!$I$85:$I$87,0),MATCH(H27,'Logic Tree'!$J$84:$N$84,0))
B28: 1 | C28: TEAM | D28: VS2 | E28: TEAM | F28: ='Pod Library'!E30 | G28: ='Pod Library'!F30 | H28: ='Pod Library'!G30 | I28: ='Pod Library'!H30 | J28: ='Pod Library'!I30 | K28: ='Pod Library'!J30 | L28: ='Pod Plan'!G6 | M28: =K28*L28 | N28: =M28*INDEX('Logic Tree'!$J$85:$N$87,MATCH(I28,'Logic Tree'!$I$85:$I$87,0),MATCH(H28,'Logic Tree'!$J$84:$N$84,0))
B29: 1 | C29: TEAM | D29: VS2 | E29: TEAM | F29: ='Pod Library'!E31 | G29: ='Pod Library'!F31 | H29: ='Pod Library'!G31 | I29: ='Pod Library'!H31 | J29: ='Pod Library'!I31 | K29: ='Pod Library'!J31 | L29: ='Pod Plan'!G6 | M29: =K29*L29 | N29: =M29*INDEX('Logic Tree'!$J$85:$N$87,MATCH(I29,'Logic Tree'!$I$85:$I$87,0),MATCH(H29,'Logic Tree'!$J$84:$N$84,0))
B30: 1 | C30: TEAM | D30: VS2 | E30: TEAM | F30: ='Pod Library'!E32 | G30: ='Pod Library'!F32 | H30: ='Pod Library'!G32 | I30: ='Pod Library'!H32 | J30: ='Pod Library'!I32 | K30: ='Pod Library'!J32 | L30: ='Pod Plan'!G6 | M30: =K30*L30 | N30: =M30*INDEX('Logic Tree'!$J$85:$N$87,MATCH(I30,'Logic Tree'!$I$85:$I$87,0),MATCH(H30,'Logic Tree'!$J$84:$N$84,0))
B31: 1 | C31: TEAM | D31: VS2 | E31: TEAM | F31: ='Pod Library'!E33 | G31: ='Pod Library'!F33 | H31: ='Pod Library'!G33 | I31: ='Pod Library'!H33 | J31: ='Pod Library'!I33 | K31: ='Pod Library'!J33 | L31: ='Pod Plan'!G6 | M31: =K31*L31 | N31: =M31*INDEX('Logic Tree'!$J$85:$N$87,MATCH(I31,'Logic Tree'!$I$85:$I$87,0),MATCH(H31,'Logic Tree'!$J$84:$N$84,0))
B32: 1 | C32: TEAM | D32: VS2 | E32: TEAM | F32: ='Pod Library'!E34 | G32: ='Pod Library'!F34 | H32: ='Pod Library'!G34 | I32: ='Pod Library'!H34 | J32: ='Pod Library'!I34 | K32: ='Pod Library'!J34 | L32: ='Pod Plan'!G6 | M32: =K32*L32 | N32: =M32*INDEX('Logic Tree'!$J$85:$N$87,MATCH(I32,'Logic Tree'!$I$85:$I$87,0),MATCH(H32,'Logic Tree'!$J$84:$N$84,0))
B33: 1 | C33: TEAM | D33: VS2 | E33: TEAM | F33: ='Pod Library'!E35 | G33: ='Pod Library'!F35 | H33: ='Pod Library'!G35 | I33: ='Pod Library'!H35 | J33: ='Pod Library'!I35 | K33: ='Pod Library'!J35 | L33: ='Pod Plan'!G6 | M33: =K33*L33 | N33: =M33*INDEX('Logic Tree'!$J$85:$N$87,MATCH(I33,'Logic Tree'!$I$85:$I$87,0),MATCH(H33,'Logic Tree'!$J$84:$N$84,0))
B34: 1 | C34: TEAM | D34: VS2 | E34: TEAM | F34: ='Pod Library'!E36 | G34: ='Pod Library'!F36 | H34: ='Pod Library'!G36 | I34: ='Pod Library'!H36 | J34: ='Pod Library'!I36 | K34: ='Pod Library'!J36 | L34: ='Pod Plan'!G6 | M34: =K34*L34 | N34: =M34*INDEX('Logic Tree'!$J$85:$N$87,MATCH(I34,'Logic Tree'!$I$85:$I$87,0),MATCH(H34,'Logic Tree'!$J$84:$N$84,0))
B35: 2 | C35: POD | D35: VS1 | E35: POD | F35: ='Pod Library'!E39 | G35: ='Pod Library'!F39 | H35: ='Pod Library'!G39 | I35: ='Pod Library'!H39 | J35: ='Pod Library'!I39 | K35: ='Pod Library'!J39 | L35: ='Pod Plan'!G9 | M35: =K35*L35 | N35: =M35*INDEX('Logic Tree'!$J$85:$N$87,MATCH(I35,'Logic Tree'!$I$85:$I$87,0),MATCH(H35,'Logic Tree'!$J$84:$N$84,0))
B36: 2 | C36: POD | D36: VS1 | E36: POD | F36: ='Pod Library'!E40 | G36: ='Pod Library'!F40 | H36: ='Pod Library'!G40 | I36: ='Pod Library'!H40 | J36: ='Pod Library'!I40 | K36: ='Pod Library'!J40 | L36: ='Pod Plan'!G9 | M36: =K36*L36 | N36: =M36*INDEX('Logic Tree'!$J$85:$N$87,MATCH(I36,'Logic Tree'!$I$85:$I$87,0),MATCH(H36,'Logic Tree'!$J$84:$N$84,0))
B37: 2 | C37: POD | D37: VS1 | E37: POD | F37: ='Pod Library'!E41 | G37: ='Pod Library'!F41 | H37: ='Pod Library'!G41 | I37: ='Pod Library'!H41 | J37: ='Pod Library'!I41 | K37: ='Pod Library'!J41 | L37: ='Pod Plan'!G9 | M37: =K37*L37 | N37: =M37*INDEX('Logic Tree'!$J$85:$N$87,MATCH(I37,'Logic Tree'!$I$85:$I$87,0),MATCH(H37,'Logic Tree'!$J$84:$N$84,0))
B38: 2 | C38: POD | D38: VS1 | E38: POD | F38: ='Pod Library'!E42 | G38: ='Pod Library'!F42 | H38: ='Pod Library'!G42 | I38: ='Pod Library'!H42 | J38: ='Pod Library'!I42 | K38: ='Pod Library'!J42 | L38: ='Pod Plan'!G9 | M38: =K38*L38 | N38: =M38*INDEX('Logic Tree'!$J$85:$N$87,MATCH(I38,'Logic Tree'!$I$85:$I$87,0),MATCH(H38,'Logic Tree'!$J$84:$N$84,0))
B39: 2 | C39: POD | D39: VS1 | E39: POD | F39: ='Pod Library'!E43 | G39: ='Pod Library'!F43 | H39: ='Pod Library'!G43 | I39: ='Pod Library'!H43 | J39: ='Pod Library'!I43 | K39: ='Pod Library'!J43 | L39: ='Pod Plan'!G9 | M39: =K39*L39 | N39: =M39*INDEX('Logic Tree'!$J$85:$N$87,MATCH(I39,'Logic Tree'!$I$85:$I$87,0),MATCH(H39,'Logic Tree'!$J$84:$N$84,0))
B40: 2 | C40: POD | D40: VS1 | E40: POD | F40: ='Pod Library'!E44 | G40: ='Pod Library'!F44 | H40: ='Pod Library'!G44 | I40: ='Pod Library'!H44 | J40: ='Pod Library'!I44 | K40: ='Pod Library'!J44 | L40: ='Pod Plan'!G9 | M40: =K40*L40 | N40: =M40*INDEX('Logic Tree'!$J$85:$N$87,MATCH(I40,'Logic Tree'!$I$85:$I$87,0),MATCH(H40,'Logic Tree'!$J$84:$N$84,0))
B41: 2 | C41: POD | D41: VS1 | E41: POD | F41: ='Pod Library'!E45 | G41: ='Pod Library'!F45 | H41: ='Pod Library'!G45 | I41: ='Pod Library'!H45 | J41: ='Pod Library'!I45 | K41: ='Pod Library'!J45 | L41: ='Pod Plan'!G9 | M41: =K41*L41 | N41: =M41*INDEX('Logic Tree'!$J$85:$N$87,MATCH(I41,'Logic Tree'!$I$85:$I$87,0),MATCH(H41,'Logic Tree'!$J$84:$N$84,0))
B42: 2 | C42: POD | D42: VS1 | E42: POD | F42: ='Pod Library'!E46 | G42: ='Pod Library'!F46 | H42: ='Pod Library'!G46 | I42: ='Pod Library'!H46 | J42: ='Pod Library'!I46 | K42: ='Pod Library'!J46 | L42: ='Pod Plan'!G9 | M42: =K42*L42 | N42: =M42*INDEX('Logic Tree'!$J$85:$N$87,MATCH(I42,'Logic Tree'!$I$85:$I$87,0),MATCH(H42,'Logic Tree'!$J$84:$N$84,0))
B43: 2 | C43: POD | D43: VS1 | E43: POD | F43: ='Pod Library'!E47 | G43: ='Pod Library'!F47 | H43: ='Pod Library'!G47 | I43: ='Pod Library'!H47 | J43: ='Pod Library'!I47 | K43: ='Pod Library'!J47 | L43: ='Pod Plan'!G9 | M43: =K43*L43 | N43: =M43*INDEX('Logic Tree'!$J$85:$N$87,MATCH(I43,'Logic Tree'!$I$85:$I$87,0),MATCH(H43,'Logic Tree'!$J$84:$N$84,0))
B44: 2 | C44: POD | D44: VS1 | E44: POD | F44: ='Pod Library'!E48 | G44: ='Pod Library'!F48 | H44: ='Pod Library'!G48 | I44: ='Pod Library'!H48 | J44: ='Pod Library'!I48 | K44: ='Pod Library'!J48 | L44: ='Pod Plan'!G9 | M44: =K44*L44 | N44: =M44*INDEX('Logic Tree'!$J$85:$N$87,MATCH(I44,'Logic Tree'!$I$85:$I$87,0),MATCH(H44,'Logic Tree'!$J$84:$N$84,0))
B45: 2 | C45: POD | D45: VS1 | E45: POD | F45: ='Pod Library'!E49 | G45: ='Pod Library'!F49 | H45: ='Pod Library'!G49 | I45: ='Pod Library'!H49 | J45: ='Pod Library'!I49 | K45: ='Pod Library'!J49 | L45: ='Pod Plan'!G9 | M45: =K45*L45 | N45: =M45*INDEX('Logic Tree'!$J$85:$N$87,MATCH(I45,'Logic Tree'!$I$85:$I$87,0),MATCH(H45,'Logic Tree'!$J$84:$N$84,0))
B46: 2 | C46: POD | D46: VS1 | E46: POD | F46: ='Pod Library'!E50 | G46: ='Pod Library'!F50 | H46: ='Pod Library'!G50 | I46: ='Pod Library'!H50 | J46: ='Pod Library'!I50 | K46: ='Pod Library'!J50 | L46: ='Pod Plan'!G9 | M46: =K46*L46 | N46: =M46*INDEX('Logic Tree'!$J$85:$N$87,MATCH(I46,'Logic Tree'!$I$85:$I$87,0),MATCH(H46,'Logic Tree'!$J$84:$N$84,0))
B47: 2 | C47: POD | D47: VS1 | E47: POD | F47: ='Pod Library'!E51 | G47: ='Pod Library'!F51 | H47: ='Pod Library'!G51 | I47: ='Pod Library'!H51 | J47: ='Pod Library'!I51 | K47: ='Pod Library'!J51 | L47: ='Pod Plan'!G9 | M47: =K47*L47 | N47: =M47*INDEX('Logic Tree'!$J$85:$N$87,MATCH(I47,'Logic Tree'!$I$85:$I$87,0),MATCH(H47,'Logic Tree'!$J$84:$N$84,0))
B48: 2 | C48: POD | D48: VS1 | E48: POD | F48: ='Pod Library'!E52 | G48: ='Pod Library'!F52 | H48: ='Pod Library'!G52 | I48: ='Pod Library'!H52 | J48: ='Pod Library'!I52 | K48: ='Pod Library'!J52 | L48: ='Pod Plan'!G9 | M48: =K48*L48 | N48: =M48*INDEX('Logic Tree'!$J$85:$N$87,MATCH(I48,'Logic Tree'!$I$85:$I$87,0),MATCH(H48,'Logic Tree'!$J$84:$N$84,0))
B49: 2 | C49: POD | D49: VS1 | E49: POD | F49: ='Pod Library'!E53 | G49: ='Pod Library'!F53 | H49: ='Pod Library'!G53 | I49: ='Pod Library'!H53 | J49: ='Pod Library'!I53 | K49: ='Pod Library'!J53 | L49: ='Pod Plan'!G9 | M49: =K49*L49 | N49: =M49*INDEX('Logic Tree'!$J$85:$N$87,MATCH(I49,'Logic Tree'!$I$85:$I$87,0),MATCH(H49,'Logic Tree'!$J$84:$N$84,0))
B50: 2 | C50: POD | D50: VS1 | E50: POD | F50: ='Pod Library'!E54 | G50: ='Pod Library'!F54 | H50: ='Pod Library'!G54 | I50: ='Pod Library'!H54 | J50: ='Pod Library'!I54 | K50: ='Pod Library'!J54 | L50: ='Pod Plan'!G9 | M50: =K50*L50 | N50: =M50*INDEX('Logic Tree'!$J$85:$N$87,MATCH(I50,'Logic Tree'!$I$85:$I$87,0),MATCH(H50,'Logic Tree'!$J$84:$N$84,0))
B51: 2 | C51: TEAM | D51: VS2 | E51: TEAM | F51: ='Pod Library'!E57 | G51: ='Pod Library'!F57 | H51: ='Pod Library'!G57 | I51: ='Pod Library'!H57 | J51: ='Pod Library'!I57 | K51: ='Pod Library'!J57 | L51: ='Pod Plan'!G10 | M51: =K51*L51 | N51: =M51*INDEX('Logic Tree'!$J$85:$N$87,MATCH(I51,'Logic Tree'!$I$85:$I$87,0),MATCH(H51,'Logic Tree'!$J$84:$N$84,0))
B52: 2 | C52: TEAM | D52: VS2 | E52: TEAM | F52: ='Pod Library'!E58 | G52: ='Pod Library'!F58 | H52: ='Pod Library'!G58 | I52: ='Pod Library'!H58 | J52: ='Pod Library'!I58 | K52: ='Pod Library'!J58 | L52: ='Pod Plan'!G10 | M52: =K52*L52 | N52: =M52*INDEX('Logic Tree'!$J$85:$N$87,MATCH(I52,'Logic Tree'!$I$85:$I$87,0),MATCH(H52,'Logic Tree'!$J$84:$N$84,0))
B53: 2 | C53: TEAM | D53: VS2 | E53: TEAM | F53: ='Pod Library'!E59 | G53: ='Pod Library'!F59 | H53: ='Pod Library'!G59 | I53: ='Pod Library'!H59 | J53: ='Pod Library'!I59 | K53: ='Pod Library'!J59 | L53: ='Pod Plan'!G10 | M53: =K53*L53 | N53: =M53*INDEX('Logic Tree'!$J$85:$N$87,MATCH(I53,'Logic Tree'!$I$85:$I$87,0),MATCH(H53,'Logic Tree'!$J$84:$N$84,0))
B54: 2 | C54: TEAM | D54: VS2 | E54: TEAM | F54: ='Pod Library'!E60 | G54: ='Pod Library'!F60 | H54: ='Pod Library'!G60 | I54: ='Pod Library'!H60 | J54: ='Pod Library'!I60 | K54: ='Pod Library'!J60 | L54: ='Pod Plan'!G10 | M54: =K54*L54 | N54: =M54*INDEX('Logic Tree'!$J$85:$N$87,MATCH(I54,'Logic Tree'!$I$85:$I$87,0),MATCH(H54,'Logic Tree'!$J$84:$N$84,0))
B55: 2 | C55: TEAM | D55: VS2 | E55: TEAM | F55: ='Pod Library'!E61 | G55: ='Pod Library'!F61 | H55: ='Pod Library'!G61 | I55: ='Pod Library'!H61 | J55: ='Pod Library'!I61 | K55: ='Pod Library'!J61 | L55: ='Pod Plan'!G10 | M55: =K55*L55 | N55: =M55*INDEX('Logic Tree'!$J$85:$N$87,MATCH(I55,'Logic Tree'!$I$85:$I$87,0),MATCH(H55,'Logic Tree'!$J$84:$N$84,0))
B56: 2 | C56: TEAM | D56: VS2 | E56: TEAM | F56: ='Pod Library'!E62 | G56: ='Pod Library'!F62 | H56: ='Pod Library'!G62 | I56: ='Pod Library'!H62 | J56: ='Pod Library'!I62 | K56: ='Pod Library'!J62 | L56: ='Pod Plan'!G10 | M56: =K56*L56 | N56: =M56*INDEX('Logic Tree'!$J$85:$N$87,MATCH(I56,'Logic Tree'!$I$85:$I$87,0),MATCH(H56,'Logic Tree'!$J$84:$N$84,0))
B57: 2 | C57: TEAM | D57: VS2 | E57: TEAM | F57: ='Pod Library'!E63 | G57: ='Pod Library'!F63 | H57: ='Pod Library'!G63 | I57: ='Pod Library'!H63 | J57: ='Pod Library'!I63 | K57: ='Pod Library'!J63 | L57: ='Pod Plan'!G10 | M57: =K57*L57 | N57: =M57*INDEX('Logic Tree'!$J$85:$N$87,MATCH(I57,'Logic Tree'!$I$85:$I$87,0),MATCH(H57,'Logic Tree'!$J$84:$N$84,0))
B58: 2 | C58: TEAM | D58: VS2 | E58: TEAM | F58: ='Pod Library'!E64 | G58: ='Pod Library'!F64 | H58: ='Pod Library'!G64 | I58: ='Pod Library'!H64 | J58: ='Pod Library'!I64 | K58: ='Pod Library'!J64 | L58: ='Pod Plan'!G10 | M58: =K58*L58 | N58: =M58*INDEX('Logic Tree'!$J$85:$N$87,MATCH(I58,'Logic Tree'!$I$85:$I$87,0),MATCH(H58,'Logic Tree'!$J$84:$N$84,0))
B59: 2 | C59: TEAM | D59: VS2 | E59: TEAM | F59: ='Pod Library'!E65 | G59: ='Pod Library'!F65 | H59: ='Pod Library'!G65 | I59: ='Pod Library'!H65 | J59: ='Pod Library'!I65 | K59: ='Pod Library'!J65 | L59: ='Pod Plan'!G10 | M59: =K59*L59 | N59: =M59*INDEX('Logic Tree'!$J$85:$N$87,MATCH(I59,'Logic Tree'!$I$85:$I$87,0),MATCH(H59,'Logic Tree'!$J$84:$N$84,0))
B60: 2 | C60: TEAM | D60: VS2 | E60: TEAM | F60: ='Pod Library'!E66 | G60: ='Pod Library'!F66 | H60: ='Pod Library'!G66 | I60: ='Pod Library'!H66 | J60: ='Pod Library'!I66 | K60: ='Pod Library'!J66 | L60: ='Pod Plan'!G10 | M60: =K60*L60 | N60: =M60*INDEX('Logic Tree'!$J$85:$N$87,MATCH(I60,'Logic Tree'!$I$85:$I$87,0),MATCH(H60,'Logic Tree'!$J$84:$N$84,0))
B61: 2 | C61: TEAM | D61: VS2 | E61: TEAM | F61: ='Pod Library'!E67 | G61: ='Pod Library'!F67 | H61: ='Pod Library'!G67 | I61: ='Pod Library'!H67 | J61: ='Pod Library'!I67 | K61: ='Pod Library'!J67 | L61: ='Pod Plan'!G10 | M61: =K61*L61 | N61: =M61*INDEX('Logic Tree'!$J$85:$N$87,MATCH(I61,'Logic Tree'!$I$85:$I$87,0),MATCH(H61,'Logic Tree'!$J$84:$N$84,0))
B62: 2 | C62: TEAM | D62: VS2 | E62: TEAM | F62: ='Pod Library'!E68 | G62: ='Pod Library'!F68 | H62: ='Pod Library'!G68 | I62: ='Pod Library'!H68 | J62: ='Pod Library'!I68 | K62: ='Pod Library'!J68 | L62: ='Pod Plan'!G10 | M62: =K62*L62 | N62: =M62*INDEX('Logic Tree'!$J$85:$N$87,MATCH(I62,'Logic Tree'!$I$85:$I$87,0),MATCH(H62,'Logic Tree'!$J$84:$N$84,0))
B63: 2 | C63: TEAM | D63: VS2 | E63: TEAM | F63: ='Pod Library'!E69 | G63: ='Pod Library'!F69 | H63: ='Pod Library'!G69 | I63: ='Pod Library'!H69 | J63: ='Pod Library'!I69 | K63: ='Pod Library'!J69 | L63: ='Pod Plan'!G10 | M63: =K63*L63 | N63: =M63*INDEX('Logic Tree'!$J$85:$N$87,MATCH(I63,'Logic Tree'!$I$85:$I$87,0),MATCH(H63,'Logic Tree'!$J$84:$N$84,0))
B64: 2 | C64: TEAM | D64: VS2 | E64: TEAM | F64: ='Pod Library'!E70 | G64: ='Pod Library'!F70 | H64: ='Pod Library'!G70 | I64: ='Pod Library'!H70 | J64: ='Pod Library'!I70 | K64: ='Pod Library'!J70 | L64: ='Pod Plan'!G10 | M64: =K64*L64 | N64: =M64*INDEX('Logic Tree'!$J$85:$N$87,MATCH(I64,'Logic Tree'!$I$85:$I$87,0),MATCH(H64,'Logic Tree'!$J$84:$N$84,0))
B65: 2 | C65: TEAM | D65: VS2 | E65: TEAM | F65: ='Pod Library'!E71 | G65: ='Pod Library'!F71 | H65: ='Pod Library'!G71 | I65: ='Pod Library'!H71 | J65: ='Pod Library'!I71 | K65: ='Pod Library'!J71 | L65: ='Pod Plan'!G10 | M65: =K65*L65 | N65: =M65*INDEX('Logic Tree'!$J$85:$N$87,MATCH(I65,'Logic Tree'!$I$85:$I$87,0),MATCH(H65,'Logic Tree'!$J$84:$N$84,0))
B66: 3 | C66: POD | D66: VS1 | E66: POD | F66: ='Pod Library'!E74 | G66: ='Pod Library'!F74 | H66: ='Pod Library'!G74 | I66: ='Pod Library'!H74 | J66: ='Pod Library'!I74 | K66: ='Pod Library'!J74 | L66: ='Pod Plan'!G13 | M66: =K66*L66 | N66: =M66*INDEX('Logic Tree'!$J$85:$N$87,MATCH(I66,'Logic Tree'!$I$85:$I$87,0),MATCH(H66,'Logic Tree'!$J$84:$N$84,0))
B67: 3 | C67: POD | D67: VS1 | E67: POD | F67: ='Pod Library'!E75 | G67: ='Pod Library'!F75 | H67: ='Pod Library'!G75 | I67: ='Pod Library'!H75 | J67: ='Pod Library'!I75 | K67: ='Pod Library'!J75 | L67: ='Pod Plan'!G13 | M67: =K67*L67 | N67: =M67*INDEX('Logic Tree'!$J$85:$N$87,MATCH(I67,'Logic Tree'!$I$85:$I$87,0),MATCH(H67,'Logic Tree'!$J$84:$N$84,0))
B68: 3 | C68: POD | D68: VS1 | E68: POD | F68: ='Pod Library'!E76 | G68: ='Pod Library'!F76 | H68: ='Pod Library'!G76 | I68: ='Pod Library'!H76 | J68: ='Pod Library'!I76 | K68: ='Pod Library'!J76 | L68: ='Pod Plan'!G13 | M68: =K68*L68 | N68: =M68*INDEX('Logic Tree'!$J$85:$N$87,MATCH(I68,'Logic Tree'!$I$85:$I$87,0),MATCH(H68,'Logic Tree'!$J$84:$N$84,0))
B69: 3 | C69: POD | D69: VS1 | E69: POD | F69: ='Pod Library'!E77 | G69: ='Pod Library'!F77 | H69: ='Pod Library'!G77 | I69: ='Pod Library'!H77 | J69: ='Pod Library'!I77 | K69: ='Pod Library'!J77 | L69: ='Pod Plan'!G13 | M69: =K69*L69 | N69: =M69*INDEX('Logic Tree'!$J$85:$N$87,MATCH(I69,'Logic Tree'!$I$85:$I$87,0),MATCH(H69,'Logic Tree'!$J$84:$N$84,0))
B70: 3 | C70: POD | D70: VS1 | E70: POD | F70: ='Pod Library'!E78 | G70: ='Pod Library'!F78 | H70: ='Pod Library'!G78 | I70: ='Pod Library'!H78 | J70: ='Pod Library'!I78 | K70: ='Pod Library'!J78 | L70: ='Pod Plan'!G13 | M70: =K70*L70 | N70: =M70*INDEX('Logic Tree'!$J$85:$N$87,MATCH(I70,'Logic Tree'!$I$85:$I$87,0),MATCH(H70,'Logic Tree'!$J$84:$N$84,0))
B71: 3 | C71: POD | D71: VS1 | E71: POD | F71: ='Pod Library'!E79 | G71: ='Pod Library'!F79 | H71: ='Pod Library'!G79 | I71: ='Pod Library'!H79 | J71: ='Pod Library'!I79 | K71: ='Pod Library'!J79 | L71: ='Pod Plan'!G13 | M71: =K71*L71 | N71: =M71*INDEX('Logic Tree'!$J$85:$N$87,MATCH(I71,'Logic Tree'!$I$85:$I$87,0),MATCH(H71,'Logic Tree'!$J$84:$N$84,0))
B72: 3 | C72: POD | D72: VS1 | E72: POD | F72: ='Pod Library'!E80 | G72: ='Pod Library'!F80 | H72: ='Pod Library'!G80 | I72: ='Pod Library'!H80 | J72: ='Pod Library'!I80 | K72: ='Pod Library'!J80 | L72: ='Pod Plan'!G13 | M72: =K72*L72 | N72: =M72*INDEX('Logic Tree'!$J$85:$N$87,MATCH(I72,'Logic Tree'!$I$85:$I$87,0),MATCH(H72,'Logic Tree'!$J$84:$N$84,0))
B73: 3 | C73: POD | D73: VS1 | E73: POD | F73: ='Pod Library'!E81 | G73: ='Pod Library'!F81 | H73: ='Pod Library'!G81 | I73: ='Pod Library'!H81 | J73: ='Pod Library'!I81 | K73: ='Pod Library'!J81 | L73: ='Pod Plan'!G13 | M73: =K73*L73 | N73: =M73*INDEX('Logic Tree'!$J$85:$N$87,MATCH(I73,'Logic Tree'!$I$85:$I$87,0),MATCH(H73,'Logic Tree'!$J$84:$N$84,0))
B74: 3 | C74: POD | D74: VS1 | E74: POD | F74: ='Pod Library'!E82 | G74: ='Pod Library'!F82 | H74: ='Pod Library'!G82 | I74: ='Pod Library'!H82 | J74: ='Pod Library'!I82 | K74: ='Pod Library'!J82 | L74: ='Pod Plan'!G13 | M74: =K74*L74 | N74: =M74*INDEX('Logic Tree'!$J$85:$N$87,MATCH(I74,'Logic Tree'!$I$85:$I$87,0),MATCH(H74,'Logic Tree'!$J$84:$N$84,0))
B75: 3 | C75: POD | D75: VS1 | E75: POD | F75: ='Pod Library'!E83 | G75: ='Pod Library'!F83 | H75: ='Pod Library'!G83 | I75: ='Pod Library'!H83 | J75: ='Pod Library'!I83 | K75: ='Pod Library'!J83 | L75: ='Pod Plan'!G13 | M75: =K75*L75 | N75: =M75*INDEX('Logic Tree'!$J$85:$N$87,MATCH(I75,'Logic Tree'!$I$85:$I$87,0),MATCH(H75,'Logic Tree'!$J$84:$N$84,0))
B76: 3 | C76: POD | D76: VS1 | E76: POD | F76: ='Pod Library'!E84 | G76: ='Pod Library'!F84 | H76: ='Pod Library'!G84 | I76: ='Pod Library'!H84 | J76: ='Pod Library'!I84 | K76: ='Pod Library'!J84 | L76: ='Pod Plan'!G13 | M76: =K76*L76 | N76: =M76*INDEX('Logic Tree'!$J$85:$N$87,MATCH(I76,'Logic Tree'!$I$85:$I$87,0),MATCH(H76,'Logic Tree'!$J$84:$N$84,0))
B77: 3 | C77: POD | D77: VS1 | E77: POD | F77: ='Pod Library'!E85 | G77: ='Pod Library'!F85 | H77: ='Pod Library'!G85 | I77: ='Pod Library'!H85 | J77: ='Pod Library'!I85 | K77: ='Pod Library'!J85 | L77: ='Pod Plan'!G13 | M77: =K77*L77 | N77: =M77*INDEX('Logic Tree'!$J$85:$N$87,MATCH(I77,'Logic Tree'!$I$85:$I$87,0),MATCH(H77,'Logic Tree'!$J$84:$N$84,0))
B78: 3 | C78: POD | D78: VS1 | E78: POD | F78: ='Pod Library'!E86 | G78: ='Pod Library'!F86 | H78: ='Pod Library'!G86 | I78: ='Pod Library'!H86 | J78: ='Pod Library'!I86 | K78: ='Pod Library'!J86 | L78: ='Pod Plan'!G13 | M78: =K78*L78 | N78: =M78*INDEX('Logic Tree'!$J$85:$N$87,MATCH(I78,'Logic Tree'!$I$85:$I$87,0),MATCH(H78,'Logic Tree'!$J$84:$N$84,0))
B79: 3 | C79: POD | D79: VS1 | E79: POD | F79: ='Pod Library'!E87 | G79: ='Pod Library'!F87 | H79: ='Pod Library'!G87 | I79: ='Pod Library'!H87 | J79: ='Pod Library'!I87 | K79: ='Pod Library'!J87 | L79: ='Pod Plan'!G13 | M79: =K79*L79 | N79: =M79*INDEX('Logic Tree'!$J$85:$N$87,MATCH(I79,'Logic Tree'!$I$85:$I$87,0),MATCH(H79,'Logic Tree'!$J$84:$N$84,0))
B80: 3 | C80: POD | D80: VS1 | E80: POD | F80: ='Pod Library'!E88 | G80: ='Pod Library'!F88 | H80: ='Pod Library'!G88 | I80: ='Pod Library'!H88 | J80: ='Pod Library'!I88 | K80: ='Pod Library'!J88 | L80: ='Pod Plan'!G13 | M80: =K80*L80 | N80: =M80*INDEX('Logic Tree'!$J$85:$N$87,MATCH(I80,'Logic Tree'!$I$85:$I$87,0),MATCH(H80,'Logic Tree'!$J$84:$N$84,0))
B81: 3 | C81: POD | D81: VS1 | E81: POD | F81: ='Pod Library'!E89 | G81: ='Pod Library'!F89 | H81: ='Pod Library'!G89 | I81: ='Pod Library'!H89 | J81: ='Pod Library'!I89 | K81: ='Pod Library'!J89 | L81: ='Pod Plan'!G13 | M81: =K81*L81 | N81: =M81*INDEX('Logic Tree'!$J$85:$N$87,MATCH(I81,'Logic Tree'!$I$85:$I$87,0),MATCH(H81,'Logic Tree'!$J$84:$N$84,0))
B82: 3 | C82: TEAM | D82: VS2 | E82: TEAM | F82: ='Pod Library'!E92 | G82: ='Pod Library'!F92 | H82: ='Pod Library'!G92 | I82: ='Pod Library'!H92 | J82: ='Pod Library'!I92 | K82: ='Pod Library'!J92 | L82: ='Pod Plan'!G14 | M82: =K82*L82 | N82: =M82*INDEX('Logic Tree'!$J$85:$N$87,MATCH(I82,'Logic Tree'!$I$85:$I$87,0),MATCH(H82,'Logic Tree'!$J$84:$N$84,0))
B83: 3 | C83: TEAM | D83: VS2 | E83: TEAM | F83: ='Pod Library'!E93 | G83: ='Pod Library'!F93 | H83: ='Pod Library'!G93 | I83: ='Pod Library'!H93 | J83: ='Pod Library'!I93 | K83: ='Pod Library'!J93 | L83: ='Pod Plan'!G14 | M83: =K83*L83 | N83: =M83*INDEX('Logic Tree'!$J$85:$N$87,MATCH(I83,'Logic Tree'!$I$85:$I$87,0),MATCH(H83,'Logic Tree'!$J$84:$N$84,0))
B84: 3 | C84: TEAM | D84: VS2 | E84: TEAM | F84: ='Pod Library'!E94 | G84: ='Pod Library'!F94 | H84: ='Pod Library'!G94 | I84: ='Pod Library'!H94 | J84: ='Pod Library'!I94 | K84: ='Pod Library'!J94 | L84: ='Pod Plan'!G14 | M84: =K84*L84 | N84: =M84*INDEX('Logic Tree'!$J$85:$N$87,MATCH(I84,'Logic Tree'!$I$85:$I$87,0),MATCH(H84,'Logic Tree'!$J$84:$N$84,0))
B85: 3 | C85: TEAM | D85: VS2 | E85: TEAM | F85: ='Pod Library'!E95 | G85: ='Pod Library'!F95 | H85: ='Pod Library'!G95 | I85: ='Pod Library'!H95 | J85: ='Pod Library'!I95 | K85: ='Pod Library'!J95 | L85: ='Pod Plan'!G14 | M85: =K85*L85 | N85: =M85*INDEX('Logic Tree'!$J$85:$N$87,MATCH(I85,'Logic Tree'!$I$85:$I$87,0),MATCH(H85,'Logic Tree'!$J$84:$N$84,0))
B86: 3 | C86: TEAM | D86: VS2 | E86: TEAM | F86: ='Pod Library'!E96 | G86: ='Pod Library'!F96 | H86: ='Pod Library'!G96 | I86: ='Pod Library'!H96 | J86: ='Pod Library'!I96 | K86: ='Pod Library'!J96 | L86: ='Pod Plan'!G14 | M86: =K86*L86 | N86: =M86*INDEX('Logic Tree'!$J$85:$N$87,MATCH(I86,'Logic Tree'!$I$85:$I$87,0),MATCH(H86,'Logic Tree'!$J$84:$N$84,0))
B87: 3 | C87: TEAM | D87: VS2 | E87: TEAM | F87: ='Pod Library'!E97 | G87: ='Pod Library'!F97 | H87: ='Pod Library'!G97 | I87: ='Pod Library'!H97 | J87: ='Pod Library'!I97 | K87: ='Pod Library'!J97 | L87: ='Pod Plan'!G14 | M87: =K87*L87 | N87: =M87*INDEX('Logic Tree'!$J$85:$N$87,MATCH(I87,'Logic Tree'!$I$85:$I$87,0),MATCH(H87,'Logic Tree'!$J$84:$N$84,0))
B88: 3 | C88: TEAM | D88: VS2 | E88: TEAM | F88: ='Pod Library'!E98 | G88: ='Pod Library'!F98 | H88: ='Pod Library'!G98 | I88: ='Pod Library'!H98 | J88: ='Pod Library'!I98 | K88: ='Pod Library'!J98 | L88: ='Pod Plan'!G14 | M88: =K88*L88 | N88: =M88*INDEX('Logic Tree'!$J$85:$N$87,MATCH(I88,'Logic Tree'!$I$85:$I$87,0),MATCH(H88,'Logic Tree'!$J$84:$N$84,0))
B89: 3 | C89: TEAM | D89: VS2 | E89: TEAM | F89: ='Pod Library'!E99 | G89: ='Pod Library'!F99 | H89: ='Pod Library'!G99 | I89: ='Pod Library'!H99 | J89: ='Pod Library'!I99 | K89: ='Pod Library'!J99 | L89: ='Pod Plan'!G14 | M89: =K89*L89 | N89: =M89*INDEX('Logic Tree'!$J$85:$N$87,MATCH(I89,'Logic Tree'!$I$85:$I$87,0),MATCH(H89,'Logic Tree'!$J$84:$N$84,0))
B90: 3 | C90: TEAM | D90: VS2 | E90: TEAM | F90: ='Pod Library'!E100 | G90: ='Pod Library'!F100 | H90: ='Pod Library'!G100 | I90: ='Pod Library'!H100 | J90: ='Pod Library'!I100 | K90: ='Pod Library'!J100 | L90: ='Pod Plan'!G14 | M90: =K90*L90 | N90: =M90*INDEX('Logic Tree'!$J$85:$N$87,MATCH(I90,'Logic Tree'!$I$85:$I$87,0),MATCH(H90,'Logic Tree'!$J$84:$N$84,0))
B91: 3 | C91: TEAM | D91: VS2 | E91: TEAM | F91: ='Pod Library'!E101 | G91: ='Pod Library'!F101 | H91: ='Pod Library'!G101 | I91: ='Pod Library'!H101 | J91: ='Pod Library'!I101 | K91: ='Pod Library'!J101 | L91: ='Pod Plan'!G14 | M91: =K91*L91 | N91: =M91*INDEX('Logic Tree'!$J$85:$N$87,MATCH(I91,'Logic Tree'!$I$85:$I$87,0),MATCH(H91,'Logic Tree'!$J$84:$N$84,0))
B92: 3 | C92: TEAM | D92: VS2 | E92: TEAM | F92: ='Pod Library'!E102 | G92: ='Pod Library'!F102 | H92: ='Pod Library'!G102 | I92: ='Pod Library'!H102 | J92: ='Pod Library'!I102 | K92: ='Pod Library'!J102 | L92: ='Pod Plan'!G14 | M92: =K92*L92 | N92: =M92*INDEX('Logic Tree'!$J$85:$N$87,MATCH(I92,'Logic Tree'!$I$85:$I$87,0),MATCH(H92,'Logic Tree'!$J$84:$N$84,0))
B93: 3 | C93: TEAM | D93: VS2 | E93: TEAM | F93: ='Pod Library'!E103 | G93: ='Pod Library'!F103 | H93: ='Pod Library'!G103 | I93: ='Pod Library'!H103 | J93: ='Pod Library'!I103 | K93: ='Pod Library'!J103 | L93: ='Pod Plan'!G14 | M93: =K93*L93 | N93: =M93*INDEX('Logic Tree'!$J$85:$N$87,MATCH(I93,'Logic Tree'!$I$85:$I$87,0),MATCH(H93,'Logic Tree'!$J$84:$N$84,0))
B94: 3 | C94: TEAM | D94: VS2 | E94: TEAM | F94: ='Pod Library'!E104 | G94: ='Pod Library'!F104 | H94: ='Pod Library'!G104 | I94: ='Pod Library'!H104 | J94: ='Pod Library'!I104 | K94: ='Pod Library'!J104 | L94: ='Pod Plan'!G14 | M94: =K94*L94 | N94: =M94*INDEX('Logic Tree'!$J$85:$N$87,MATCH(I94,'Logic Tree'!$I$85:$I$87,0),MATCH(H94,'Logic Tree'!$J$84:$N$84,0))
B95: 3 | C95: TEAM | D95: VS2 | E95: TEAM | F95: ='Pod Library'!E105 | G95: ='Pod Library'!F105 | H95: ='Pod Library'!G105 | I95: ='Pod Library'!H105 | J95: ='Pod Library'!I105 | K95: ='Pod Library'!J105 | L95: ='Pod Plan'!G14 | M95: =K95*L95 | N95: =M95*INDEX('Logic Tree'!$J$85:$N$87,MATCH(I95,'Logic Tree'!$I$85:$I$87,0),MATCH(H95,'Logic Tree'!$J$84:$N$84,0))
B96: 3 | C96: TEAM | D96: VS2 | E96: TEAM | F96: ='Pod Library'!E106 | G96: ='Pod Library'!F106 | H96: ='Pod Library'!G106 | I96: ='Pod Library'!H106 | J96: ='Pod Library'!I106 | K96: ='Pod Library'!J106 | L96: ='Pod Plan'!G14 | M96: =K96*L96 | N96: =M96*INDEX('Logic Tree'!$J$85:$N$87,MATCH(I96,'Logic Tree'!$I$85:$I$87,0),MATCH(H96,'Logic Tree'!$J$84:$N$84,0))
B97: 3 | C97: TEAM | D97: VS2 | E97: TEAM | F97: ='Pod Library'!E107 | G97: ='Pod Library'!F107 | H97: ='Pod Library'!G107 | I97: ='Pod Library'!H107 | J97: ='Pod Library'!I107 | K97: ='Pod Library'!J107 | L97: ='Pod Plan'!G14 | M97: =K97*L97 | N97: =M97*INDEX('Logic Tree'!$J$85:$N$87,MATCH(I97,'Logic Tree'!$I$85:$I$87,0),MATCH(H97,'Logic Tree'!$J$84:$N$84,0))
B98: 4 | C98: POD | D98: VS1 | E98: POD | F98: ='Pod Library'!E110 | G98: ='Pod Library'!F110 | H98: ='Pod Library'!G110 | I98: ='Pod Library'!H110 | J98: ='Pod Library'!I110 | K98: ='Pod Library'!J110 | L98: ='Pod Plan'!G17 | M98: =K98*L98 | N98: =M98*INDEX('Logic Tree'!$J$85:$N$87,MATCH(I98,'Logic Tree'!$I$85:$I$87,0),MATCH(H98,'Logic Tree'!$J$84:$N$84,0))
B99: 4 | C99: POD | D99: VS1 | E99: POD | F99: ='Pod Library'!E111 | G99: ='Pod Library'!F111 | H99: ='Pod Library'!G111 | I99: ='Pod Library'!H111 | J99: ='Pod Library'!I111 | K99: ='Pod Library'!J111 | L99: ='Pod Plan'!G17 | M99: =K99*L99 | N99: =M99*INDEX('Logic Tree'!$J$85:$N$87,MATCH(I99,'Logic Tree'!$I$85:$I$87,0),MATCH(H99,'Logic Tree'!$J$84:$N$84,0))
B100: 4 | C100: POD | D100: VS1 | E100: POD | F100: ='Pod Library'!E112 | G100: ='Pod Library'!F112 | H100: ='Pod Library'!G112 | I100: ='Pod Library'!H112 | J100: ='Pod Library'!I112 | K100: ='Pod Library'!J112 | L100: ='Pod Plan'!G17 | M100: =K100*L100 | N100: =M100*INDEX('Logic Tree'!$J$85:$N$87,MATCH(I100,'Logic Tree'!$I$85:$I$87,0),MATCH(H100,'Logic Tree'!$J$84:$N$84,0))
B101: 4 | C101: POD | D101: VS1 | E101: POD | F101: ='Pod Library'!E113 | G101: ='Pod Library'!F113 | H101: ='Pod Library'!G113 | I101: ='Pod Library'!H113 | J101: ='Pod Library'!I113 | K101: ='Pod Library'!J113 | L101: ='Pod Plan'!G17 | M101: =K101*L101 | N101: =M101*INDEX('Logic Tree'!$J$85:$N$87,MATCH(I101,'Logic Tree'!$I$85:$I$87,0),MATCH(H101,'Logic Tree'!$J$84:$N$84,0))
...

Sheet SIT Loading
A1: SIT loading — turning fractional FTE into whole people and whole months
A2: The seat ledger is a demand model, not a roster. Regenerated for the two-stream design: VS1 pods of 10 / 9 / 8 / 6 / 6 and VS2 teams of 12 converting to pods of 6 in Year 4.
A4: A. WHY YOU CANNOT ROUND THE SEAT LEDGER
B5: Approach | C5: Y1 | D5: Y2 | E5: Y3 | F5: Y4 | G5: Y5 | H5: Verdict
B6: Modelled FTE (the commercial number) | C6: 121.5 | D6: 94.5 | E6: 78.5 | F6: 51.5 | G6: 43.5
B7: Round every ledger row UP to whole heads | C7: 129 | D7: 106 | E7: 85 | F7: 60 | G7: 49 | H7: INFLATES Year 1 by 23 people — 19%. 242 ledger rows each round up by up to 0.99 of a person.
B8: Round every ledger row to nearest | C8: 119 | D8: 91 | E8: 77 | F8: 49 | G8: 42 | H8: Total is roughly right but every individual line is wrong, and the FTC / FTE / MGCC split drifts. It also implies each pod has its own dedicated architect, tester and support engineer.
B9: This sheet — aggregate first, then whole people and months | C9: 121.5 | D9: 94.5 | E9: 78.5 | F9: 51.5 | G9: 43.5 | H9: Exact on total, on each sourcing type and on person-months.
A11: B. THE RULE
B12: Aggregate the ledger to the level at which a person is actually hired — year x role x band x location x sourcing — and only then convert to bodies. A pod seat of 0.23 is not a person; the same role summed across six pods is.
B13: Treatment | C13: When it applies | D13: How SIT loads it | E13: Example
B14: RAMPED | C14: Delivery roles — engineers, testers, analysts inside pods and teams. The work is divisible over time and people join and leave pods. | G14: floor(FTE) people for 12 months, plus one person for the remaining months. | J14: 7.73 FTE = 7 people all year + 1 person for 8.7 months
B15: SHARED | C15: Roles that need continuous presence — leads, architects, service delivery managers, PMO — and any line below 0.5 FTE. | G15: One person at a partial allocation for the whole year, the balance of their time on another domain. | J15: 0.95 FTE = 1 Chief Architect at 95%, 5% elsewhere
B16: Both give identical person-months. Neither loads a partial person into a month and neither allocates anybody above 100%. Person-months is the invariant SIT must reproduce: FTE x 12.
A18: C. RECONCILIATION — what SIT must tie back to
B19: Measure | C19: Y1 | D19: Y2 | E19: Y3 | F19: Y4 | G19: Y5 | H19: Note
B20: Modelled FTE | C20: 121.5 | D20: 94.5 | E20: 78.5 | F20: 51.5 | G20: 43.5 | H20: From the seat ledger. This is the commercial number and it does not change.
B21: Person-months = FTE x 12 | C21: 1458 | D21: 1134 | E21: 942 | F21: 618 | G21: 522 | H21: THE INVARIANT. SIT's monthly loading must sum to this.
B22: Bodies to requisition | C22: 129 | D22: 106 | E22: 85 | F22: 60 | G22: 49 | H22: Named people. Higher than FTE because some are part-year or part-allocated.
B23: — of which full-time, all year | C23: 114 | D23: 83 | E23: 72 | F23: 43 | G23: 38 | H23: The core roster. Everything else is a partial assignment.
B24: Average allocation across all bodies | C24: 0.9419 | D24: 0.8915 | E24: 0.9235 | F24: 0.8583 | G24: 0.8878 | H24: If this drops below about 70% the pod design is too fragmented — check it.
A26: D. THE REQUISITION PLAN — load these lines into SIT
B27: Year | C27: Sourcing | D27: Role | E27: Band | F27: Location | G27: Unit type | H27: Modelled FTE | I27: Person-months | J27: Treatment | K27: Full-time heads | L27: +1 head for (months) | M27: Allocation of the part head
B28: 1 | C28: FTC | D28: BSA | E28: E3 | F28: OFF | G28: Horizontal | H28: 0.5 | I28: 6 | J28: SHARED | K28: 0 | L28: 6 | M28: 0.5
B29: 1 | C29: FTC | D29: BSA | E29: E3 | F29: ON | G29: Delivery | H29: 6 | I29: 72 | J29: RAMPED | K29: 6
B30: 1 | C30: FTC | D30: BSA | E30: E3 | F30: ON | G30: Horizontal | H30: 2 | I30: 24 | J30: SHARED | K30: 2
B31: 1 | C31: FTC | D31: DEV | E31: E1 | F31: OFF | G31: Delivery | H31: 1 | I31: 12 | J31: RAMPED | K31: 1
B32: 1 | C32: FTC | D32: DEV | E32: E2 | F32: OFF | G32: Delivery | H32: 2 | I32: 24 | J32: RAMPED | K32: 2
B33: 1 | C33: FTC | D33: DEV | E33: E2 | F33: ON | G33: Delivery | H33: 11 | I33: 132 | J33: RAMPED | K33: 11
B34: 1 | C34: FTC | D34: DEV | E34: E3 | F34: NEAR | G34: Delivery | H34: 7.5 | I34: 90 | J34: RAMPED | K34: 7 | L34: 6
B35: 1 | C35: FTC | D35: DEV | E35: E3 | F35: ON | G35: Delivery | H35: 16 | I35: 192 | J35: RAMPED | K35: 16
B36: 1 | C36: FTC | D36: DEV | E36: E4 | F36: ON | G36: Delivery | H36: 9 | I36: 108 | J36: RAMPED | K36: 9
B37: 1 | C37: FTC | D37: MNT | E37: E2 | F37: OFF | G37: Delivery | H37: 0.5 | I37: 6 | J37: RAMPED | K37: 0 | L37: 6
B38: 1 | C38: FTC | D38: MNT | E38: E2 | F38: OFF | G38: Horizontal | H38: 0.5 | I38: 6 | J38: SHARED | K38: 0 | L38: 6 | M38: 0.5
B39: 1 | C39: FTC | D39: MNT | E39: E2 | F39: ON | G39: Delivery | H39: 2.5 | I39: 30 | J39: RAMPED | K39: 2 | L39: 6
B40: 1 | C40: FTC | D40: MNT | E40: E3 | F40: ON | G40: Horizontal | H40: 2 | I40: 24 | J40: SHARED | K40: 2
B41: 1 | C41: FTC | D41: OTH | E41: E3 | F41: OFF | G41: Horizontal | H41: 0.5 | I41: 6 | J41: SHARED | K41: 0 | L41: 6 | M41: 0.5
B42: 1 | C42: FTC | D42: OTH | E42: E4 | F42: ON | G42: Delivery | H42: 3 | I42: 36 | J42: SHARED | K42: 3
B43: 1 | C43: FTC | D43: OTH | E43: E4 | F43: ON | G43: Horizontal | H43: 1 | I43: 12 | J43: SHARED | K43: 1
B44: 1 | C44: FTC | D44: OTH | E44: E5 | F44: ON | G44: Horizontal | H44: 1 | I44: 12 | J44: SHARED | K44: 1
B45: 1 | C45: FTC | D45: PM | E45: E5 | F45: ON | G45: Horizontal | H45: 2 | I45: 24 | J45: SHARED | K45: 2
B46: 1 | C46: FTC | D46: TEST | E46: E1 | F46: OFF | G46: Delivery | H46: 0.5 | I46: 6 | J46: RAMPED | K46: 0 | L46: 6
B47: 1 | C47: FTC | D47: TEST | E47: E2 | F47: NEAR | G47: Delivery | H47: 2 | I47: 24 | J47: RAMPED | K47: 2
B48: 1 | C48: FTC | D48: TEST | E48: E2 | F48: ON | G48: Delivery | H48: 3 | I48: 36 | J48: RAMPED | K48: 3
B49: 1 | C49: FTC | D49: TEST | E49: E3 | F49: OFF | G49: Horizontal | H49: 0.5 | I49: 6 | J49: SHARED | K49: 0 | L49: 6 | M49: 0.5
B50: 1 | C50: FTC | D50: TEST | E50: E3 | F50: ON | G50: Delivery | H50: 3.5 | I50: 42 | J50: RAMPED | K50: 3 | L50: 6
B51: 1 | C51: FTC | D51: TEST | E51: E4 | F51: ON | G51: Horizontal | H51: 1 | I51: 12 | J51: SHARED | K51: 1
B52: 1 | C52: FTE | D52: BSA | E52: E4 | F52: ON | G52: Delivery | H52: 2 | I52: 24 | J52: RAMPED | K52: 2
B53: 1 | C53: FTE | D53: BSA | E53: E4 | F53: ON | G53: Horizontal | H53: 1.5 | I53: 18 | J53: SHARED | K53: 1 | L53: 6 | M53: 0.5
B54: 1 | C54: FTE | D54: MNT | E54: E3 | F54: ON | G54: Delivery | H54: 1.5 | I54: 18 | J54: RAMPED | K54: 1 | L54: 6
B55: 1 | C55: FTE | D55: MNT | E55: E4 | F55: ON | G55: Horizontal | H55: 2 | I55: 24 | J55: SHARED | K55: 2
B56: 1 | C56: FTE | D56: PM | E56: E4 | F56: ON | G56: Delivery | H56: 5 | I56: 60 | J56: SHARED | K56: 5
B57: 1 | C57: FTE | D57: PM | E57: E4 | F57: ON | G57: Horizontal | H57: 1.5 | I57: 18 | J57: SHARED | K57: 1 | L57: 6 | M57: 0.5
B58: 1 | C58: MGCC | D58: DEV | E58: E3 | F58: OFF | G58: Delivery | H58: 10 | I58: 120 | J58: RAMPED | K58: 10
B59: 1 | C59: MGCC | D59: DEV | E59: E3 | F59: OFF | G59: Horizontal | H59: 4.5 | I59: 54 | J59: SHARED | K59: 4 | L59: 6 | M59: 0.5
B60: 1 | C60: MGCC | D60: MNT | E60: E2 | F60: OFF | G60: Horizontal | H60: 0.5 | I60: 6 | J60: SHARED | K60: 0 | L60: 6 | M60: 0.5
B61: 1 | C61: MGCC | D61: TEST | E61: E2 | F61: OFF | G61: Delivery | H61: 5 | I61: 60 | J61: RAMPED | K61: 5
B62: 1 | C62: MGCC | D62: TEST | E62: E2 | F62: OFF | G62: Horizontal | H62: 2.5 | I62: 30 | J62: SHARED | K62: 2 | L62: 6 | M62: 0.5
B63: 1 | C63: PT | D63: BSA | E63: E3 | F63: ON | G63: Delivery | H63: 3 | I63: 36 | J63: RAMPED | K63: 3
B64: 1 | C64: PT | D64: DEV | E64: E3 | F64: ON | G64: Delivery | H64: 4 | I64: 48 | J64: RAMPED | K64: 4
B65: 2 | C65: FTC | D65: BSA | E65: E3 | F65: OFF | G65: Horizontal | H65: 0.5 | I65: 6 | J65: SHARED | K65: 0 | L65: 6 | M65: 0.5
B66: 2 | C66: FTC | D66: BSA | E66: E3 | F66: ON | G66: Delivery | H66: 4.5 | I66: 54 | J66: RAMPED | K66: 4 | L66: 6
B67: 2 | C67: FTC | D67: BSA | E67: E3 | F67: ON | G67: Horizontal | H67: 1.5 | I67: 18 | J67: SHARED | K67: 1 | L67: 6 | M67: 0.5
B68: 2 | C68: FTC | D68: DEV | E68: E1 | F68: OFF | G68: Delivery | H68: 1 | I68: 12 | J68: RAMPED | K68: 1
B69: 2 | C69: FTC | D69: DEV | E69: E2 | F69: OFF | G69: Delivery | H69: 4.5 | I69: 54 | J69: RAMPED | K69: 4 | L69: 6
B70: 2 | C70: FTC | D70: DEV | E70: E2 | F70: ON | G70: Delivery | H70: 5 | I70: 60 | J70: RAMPED | K70: 5
B71: 2 | C71: FTC | D71: DEV | E71: E3 | F71: NEAR | G71: Delivery | H71: 4.5 | I71: 54 | J71: RAMPED | K71: 4 | L71: 6
B72: 2 | C72: FTC | D72: DEV | E72: E3 | F72: ON | G72: Delivery | H72: 8.5 | I72: 102 | J72: RAMPED | K72: 8 | L72: 6
B73: 2 | C73: FTC | D73: DEV | E73: E4 | F73: ON | G73: Delivery | H73: 6 | I73: 72 | J73: RAMPED | K73: 6
B74: 2 | C74: FTC | D74: MNT | E74: E2 | F74: OFF | G74: Delivery | H74: 1 | I74: 12 | J74: RAMPED | K74: 1
B75: 2 | C75: FTC | D75: MNT | E75: E2 | F75: OFF | G75: Horizontal | H75: 0.5 | I75: 6 | J75: SHARED | K75: 0 | L75: 6 | M75: 0.5
B76: 2 | C76: FTC | D76: MNT | E76: E2 | F76: ON | G76: Delivery | H76: 1.5 | I76: 18 | J76: RAMPED | K76: 1 | L76: 6
B77: 2 | C77: FTC | D77: MNT | E77: E3 | F77: ON | G77: Horizontal | H77: 1.5 | I77: 18 | J77: SHARED | K77: 1 | L77: 6 | M77: 0.5
B78: 2 | C78: FTC | D78: OTH | E78: E3 | F78: OFF | G78: Horizontal | H78: 0.5 | I78: 6 | J78: SHARED | K78: 0 | L78: 6 | M78: 0.5
B79: 2 | C79: FTC | D79: OTH | E79: E4 | F79: ON | G79: Delivery | H79: 2 | I79: 24 | J79: SHARED | K79: 2
B80: 2 | C80: FTC | D80: OTH | E80: E4 | F80: ON | G80: Horizontal | H80: 0.5 | I80: 6 | J80: SHARED | K80: 0 | L80: 6 | M80: 0.5
B81: 2 | C81: FTC | D81: OTH | E81: E5 | F81: ON | G81: Horizontal | H81: 1 | I81: 12 | J81: SHARED | K81: 1
B82: 2 | C82: FTC | D82: PM | E82: E5 | F82: ON | G82: Horizontal | H82: 1 | I82: 12 | J82: SHARED | K82: 1
B83: 2 | C83: FTC | D83: TEST | E83: E1 | F83: OFF | G83: Delivery | H83: 2.5 | I83: 30 | J83: RAMPED | K83: 2 | L83: 6
B84: 2 | C84: FTC | D84: TEST | E84: E2 | F84: NEAR | G84: Delivery | H84: 1.5 | I84: 18 | J84: RAMPED | K84: 1 | L84: 6
B85: 2 | C85: FTC | D85: TEST | E85: E2 | F85: ON | G85: Delivery | H85: 1 | I85: 12 | J85: RAMPED | K85: 1
B86: 2 | C86: FTC | D86: TEST | E86: E3 | F86: OFF | G86: Horizontal | H86: 0.5 | I86: 6 | J86: SHARED | K86: 0 | L86: 6 | M86: 0.5
B87: 2 | C87: FTC | D87: TEST | E87: E3 | F87: ON | G87: Delivery | H87: 2.5 | I87: 30 | J87: RAMPED | K87: 2 | L87: 6
B88: 2 | C88: FTC | D88: TEST | E88: E4 | F88: ON | G88: Horizontal | H88: 0.5 | I88: 6 | J88: SHARED | K88: 0 | L88: 6 | M88: 0.5
B89: 2 | C89: FTE | D89: BSA | E89: E4 | F89: ON | G89: Delivery | H89: 2 | I89: 24 | J89: RAMPED | K89: 2
B90: 2 | C90: FTE | D90: BSA | E90: E4 | F90: ON | G90: Horizontal | H90: 1.5 | I90: 18 | J90: SHARED | K90: 1 | L90: 6 | M90: 0.5
B91: 2 | C91: FTE | D91: MNT | E91: E3 | F91: ON | G91: Delivery | H91: 1.5 | I91: 18 | J91: RAMPED | K91: 1 | L91: 6
B92: 2 | C92: FTE | D92: MNT | E92: E4 | F92: ON | G92: Horizontal | H92: 2 | I92: 24 | J92: SHARED | K92: 2
B93: 2 | C93: FTE | D93: PM | E93: E4 | F93: ON | G93: Delivery | H93: 3.5 | I93: 42 | J93: SHARED | K93: 3 | L93: 6 | M93: 0.5
B94: 2 | C94: FTE | D94: PM | E94: E4 | F94: ON | G94: Horizontal | H94: 1.5 | I94: 18 | J94: SHARED | K94: 1 | L94: 6 | M94: 0.5
B95: 2 | C95: MGCC | D95: DEV | E95: E3 | F95: OFF | G95: Delivery | H95: 8 | I95: 96 | J95: RAMPED | K95: 8
B96: 2 | C96: MGCC | D96: DEV | E96: E3 | F96: OFF | G96: Horizontal | H96: 4.5 | I96: 54 | J96: SHARED | K96: 4 | L96: 6 | M96: 0.5
B97: 2 | C97: MGCC | D97: MNT | E97: E2 | F97: OFF | G97: Horizontal | H97: 2.5 | I97: 30 | J97: SHARED | K97: 2 | L97: 6 | M97: 0.5
B98: 2 | C98: MGCC | D98: TEST | E98: E2 | F98: OFF | G98: Delivery | H98: 4 | I98: 48 | J98: RAMPED | K98: 4
B99: 2 | C99: MGCC | D99: TEST | E99: E2 | F99: OFF | G99: Horizontal | H99: 2.5 | I99: 30 | J99: SHARED | K99: 2 | L99: 6 | M99: 0.5
B100: 2 | C100: PT | D100: BSA | E100: E3 | F100: ON | G100: Delivery | H100: 3 | I100: 36 | J100: RAMPED | K100: 3
B101: 2 | C101: PT | D101: DEV | E101: E3 | F101: ON | G101: Delivery | H101: 4 | I101: 48 | J101: RAMPED | K101: 4
B102: 3 | C102: FTC | D102: BSA | E102: E3 | F102: ON | G102: Delivery | H102: 3.5 | I102: 42 | J102: RAMPED | K102: 3 | L102: 6
B103: 3 | C103: FTC | D103: DEV | E103: E1 | F103: OFF | G103: Delivery | H103: 1 | I103: 12 | J103: RAMPED | K103: 1
B104: 3 | C104: FTC | D104: DEV | E104: E2 | F104: OFF | G104: Delivery | H104: 8 | I104: 96 | J104: RAMPED | K104: 8
...

Sheet Unit Cost Sensitivity
A1: Unit cost sensitivity — four levers now, not three
A2: Productivity, offshore share and seniority, plus the agile conversion, which which the other three all depend on.
A4: A. THE MODEL — unit cost = k x (1 - productivity) x average cost per head
B5: average cost per head = offshore x [senior x OFF_SR + (1-senior) x OFF_JM] + onshore x [senior x ON_SR + (1-senior) x ON_JM]
A7: B. TIER COST PARAMETERS — from the Year-5 roster
B8: Tier | C8: Onshore Tokyo | D8: Offshore
B9: Junior / mid (E1-E3) | C9: =IFERROR((SUMIFS('Seat Ledger'!$N$5:$N$287,'Seat Ledger'!$B$5:$B$287,5,'Seat Ledger'!$I$5:$I$287,"ON",'Seat Ledger'!$H$5:$H$287,"E1") + SUMIFS('Seat Ledger'!$N$5:$N$287,'Seat Ledger'!$B$5:$B$287,5,'Seat Ledger'!$I$5:$I$287,"ON",'Seat Ledger'!$H$5:$H$287,"E2") + SUMIFS('Seat Ledger'!$N$5:$N$287,'Seat Ledger'!$B$5:$B$287,5,'Seat Ledger'!$I$5:$I$287,"ON",'Seat Ledger'!$H$5:$H$287,"E3"))/(SUMIFS('Seat Ledger'!$M$5:$M$287,'Seat Ledger'!$B$5:$B$287,5,'Seat Ledger'!$I$5:$I$287,"ON",'Seat Ledger'!$H$5:$H$287,"E1") + SUMIFS('Seat Ledger'!$M$5:$M$287,'Seat Ledger'!$B$5:$B$287,5,'Seat Ledger'!$I$5:$I$287,"ON",'Seat Ledger'!$H$5:$H$287,"E2") + SUMIFS('Seat Ledger'!$M$5:$M$287,'Seat Ledger'!$B$5:$B$287,5,'Seat Ledger'!$I$5:$I$287,"ON",'Seat Ledger'!$H$5:$H$287,"E3")),0) | D9: =IFERROR((SUMIFS('Seat Ledger'!$N$5:$N$287,'Seat Ledger'!$B$5:$B$287,5,'Seat Ledger'!$I$5:$I$287,"OFF",'Seat Ledger'!$H$5:$H$287,"E1") + SUMIFS('Seat Ledger'!$N$5:$N$287,'Seat Ledger'!$B$5:$B$287,5,'Seat Ledger'!$I$5:$I$287,"OFF",'Seat Ledger'!$H$5:$H$287,"E2") + SUMIFS('Seat Ledger'!$N$5:$N$287,'Seat Ledger'!$B$5:$B$287,5,'Seat Ledger'!$I$5:$I$287,"OFF",'Seat Ledger'!$H$5:$H$287,"E3"))/(SUMIFS('Seat Ledger'!$M$5:$M$287,'Seat Ledger'!$B$5:$B$287,5,'Seat Ledger'!$I$5:$I$287,"OFF",'Seat Ledger'!$H$5:$H$287,"E1") + SUMIFS('Seat Ledger'!$M$5:$M$287,'Seat Ledger'!$B$5:$B$287,5,'Seat Ledger'!$I$5:$I$287,"OFF",'Seat Ledger'!$H$5:$H$287,"E2") + SUMIFS('Seat Ledger'!$M$5:$M$287,'Seat Ledger'!$B$5:$B$287,5,'Seat Ledger'!$I$5:$I$287,"OFF",'Seat Ledger'!$H$5:$H$287,"E3")),0)
B10: Senior (E4-E5) | C10: =IFERROR((SUMIFS('Seat Ledger'!$N$5:$N$287,'Seat Ledger'!$B$5:$B$287,5,'Seat Ledger'!$I$5:$I$287,"ON",'Seat Ledger'!$H$5:$H$287,"E4") + SUMIFS('Seat Ledger'!$N$5:$N$287,'Seat Ledger'!$B$5:$B$287,5,'Seat Ledger'!$I$5:$I$287,"ON",'Seat Ledger'!$H$5:$H$287,"E5"))/(SUMIFS('Seat Ledger'!$M$5:$M$287,'Seat Ledger'!$B$5:$B$287,5,'Seat Ledger'!$I$5:$I$287,"ON",'Seat Ledger'!$H$5:$H$287,"E4") + SUMIFS('Seat Ledger'!$M$5:$M$287,'Seat Ledger'!$B$5:$B$287,5,'Seat Ledger'!$I$5:$I$287,"ON",'Seat Ledger'!$H$5:$H$287,"E5")),0) | D10: =IFERROR((SUMIFS('Seat Ledger'!$N$5:$N$287,'Seat Ledger'!$B$5:$B$287,5,'Seat Ledger'!$I$5:$I$287,"OFF",'Seat Ledger'!$H$5:$H$287,"E4") + SUMIFS('Seat Ledger'!$N$5:$N$287,'Seat Ledger'!$B$5:$B$287,5,'Seat Ledger'!$I$5:$I$287,"OFF",'Seat Ledger'!$H$5:$H$287,"E5"))/(SUMIFS('Seat Ledger'!$M$5:$M$287,'Seat Ledger'!$B$5:$B$287,5,'Seat Ledger'!$I$5:$I$287,"OFF",'Seat Ledger'!$H$5:$H$287,"E4") + SUMIFS('Seat Ledger'!$M$5:$M$287,'Seat Ledger'!$B$5:$B$287,5,'Seat Ledger'!$I$5:$I$287,"OFF",'Seat Ledger'!$H$5:$H$287,"E5")),0)
A12: C. BASE CASE
B13: Measure | C13: Year 1 | D13: Year 2 | E13: Year 3 | F13: Year 4 | G13: Year 5
B14: Delivered productivity | C14: ='Glidepath & 50-50'!C25 | D14: ='Glidepath & 50-50'!D25 | E14: ='Glidepath & 50-50'!E25 | F14: ='Glidepath & 50-50'!F25 | G14: ='Glidepath & 50-50'!G25
B15: Whole-team offshore share | C15: ='Team Build-Up'!C54 | D15: ='Team Build-Up'!D54 | E15: ='Team Build-Up'!E54 | F15: ='Team Build-Up'!F54 | G15: ='Team Build-Up'!G54
B16: Senior share (E4+E5) | C16: ='Team Build-Up'!C76 | D16: ='Team Build-Up'!D76 | E16: ='Team Build-Up'!E76 | F16: ='Team Build-Up'!F76 | G16: ='Team Build-Up'!G76
B17: Agile share | C17: ='Delivery Mode'!C20 | D17: ='Delivery Mode'!D20 | E17: ='Delivery Mode'!E20 | F17: ='Delivery Mode'!F20 | G17: ='Delivery Mode'!G20
B18: Unit cost index — actual | C18: ='Cost & Commercial'!C9 | D18: ='Cost & Commercial'!D9 | E18: ='Cost & Commercial'!E9 | F18: ='Cost & Commercial'!F9 | G18: ='Cost & Commercial'!G9
B19: Unit cost index — two-tier formula | C19: =(1-C14)*(C15*(C16*$D$10+(1-C16)*$D$9)+(1-C15)*(C16*$C$10+(1-C16)*$C$9)) | D19: =(1-D14)*(D15*(D16*$D$10+(1-D16)*$D$9)+(1-D15)*(D16*$C$10+(1-D16)*$C$9)) | E19: =(1-E14)*(E15*(E16*$D$10+(1-E16)*$D$9)+(1-E15)*(E16*$C$10+(1-E16)*$C$9)) | F19: =(1-F14)*(F15*(F16*$D$10+(1-F16)*$D$9)+(1-F15)*(F16*$C$10+(1-F16)*$C$9)) | G19: =(1-G14)*(G15*(G16*$D$10+(1-G16)*$D$9)+(1-G15)*(G16*$C$10+(1-G16)*$C$9))
B20: CALIBRATION k = actual / formula, at Year 5 | G20: =IF(G19=0,1,G18/G19)
A22: D. GRID — offshore share x productivity, at the Year-5 senior share
B23: Offshore v Productivity > | C23: 0.35 | D23: 0.4 | E23: 0.45 | F23: 0.5 | G23: 0.55 | H23: 0.6
B24: 0.45 | C24: =$G$20*(1-C$23)*($B24*($G$16*$D$10+(1-$G$16)*$D$9)+(1-$B24)*($G$16*$C$10+(1-$G$16)*$C$9)) | D24: =$G$20*(1-D$23)*($B24*($G$16*$D$10+(1-$G$16)*$D$9)+(1-$B24)*($G$16*$C$10+(1-$G$16)*$C$9)) | E24: =$G$20*(1-E$23)*($B24*($G$16*$D$10+(1-$G$16)*$D$9)+(1-$B24)*($G$16*$C$10+(1-$G$16)*$C$9)) | F24: =$G$20*(1-F$23)*($B24*($G$16*$D$10+(1-$G$16)*$D$9)+(1-$B24)*($G$16*$C$10+(1-$G$16)*$C$9)) | G24: =$G$20*(1-G$23)*($B24*($G$16*$D$10+(1-$G$16)*$D$9)+(1-$B24)*($G$16*$C$10+(1-$G$16)*$C$9)) | H24: =$G$20*(1-H$23)*($B24*($G$16*$D$10+(1-$G$16)*$D$9)+(1-$B24)*($G$16*$C$10+(1-$G$16)*$C$9))
B25: 0.55 | C25: =$G$20*(1-C$23)*($B25*($G$16*$D$10+(1-$G$16)*$D$9)+(1-$B25)*($G$16*$C$10+(1-$G$16)*$C$9)) | D25: =$G$20*(1-D$23)*($B25*($G$16*$D$10+(1-$G$16)*$D$9)+(1-$B25)*($G$16*$C$10+(1-$G$16)*$C$9)) | E25: =$G$20*(1-E$23)*($B25*($G$16*$D$10+(1-$G$16)*$D$9)+(1-$B25)*($G$16*$C$10+(1-$G$16)*$C$9)) | F25: =$G$20*(1-F$23)*($B25*($G$16*$D$10+(1-$G$16)*$D$9)+(1-$B25)*($G$16*$C$10+(1-$G$16)*$C$9)) | G25: =$G$20*(1-G$23)*($B25*($G$16*$D$10+(1-$G$16)*$D$9)+(1-$B25)*($G$16*$C$10+(1-$G$16)*$C$9)) | H25: =$G$20*(1-H$23)*($B25*($G$16*$D$10+(1-$G$16)*$D$9)+(1-$B25)*($G$16*$C$10+(1-$G$16)*$C$9))
B26: 0.65 | C26: =$G$20*(1-C$23)*($B26*($G$16*$D$10+(1-$G$16)*$D$9)+(1-$B26)*($G$16*$C$10+(1-$G$16)*$C$9)) | D26: =$G$20*(1-D$23)*($B26*($G$16*$D$10+(1-$G$16)*$D$9)+(1-$B26)*($G$16*$C$10+(1-$G$16)*$C$9)) | E26: =$G$20*(1-E$23)*($B26*($G$16*$D$10+(1-$G$16)*$D$9)+(1-$B26)*($G$16*$C$10+(1-$G$16)*$C$9)) | F26: =$G$20*(1-F$23)*($B26*($G$16*$D$10+(1-$G$16)*$D$9)+(1-$B26)*($G$16*$C$10+(1-$G$16)*$C$9)) | G26: =$G$20*(1-G$23)*($B26*($G$16*$D$10+(1-$G$16)*$D$9)+(1-$B26)*($G$16*$C$10+(1-$G$16)*$C$9)) | H26: =$G$20*(1-H$23)*($B26*($G$16*$D$10+(1-$G$16)*$D$9)+(1-$B26)*($G$16*$C$10+(1-$G$16)*$C$9))
B27: 0.75 | C27: =$G$20*(1-C$23)*($B27*($G$16*$D$10+(1-$G$16)*$D$9)+(1-$B27)*($G$16*$C$10+(1-$G$16)*$C$9)) | D27: =$G$20*(1-D$23)*($B27*($G$16*$D$10+(1-$G$16)*$D$9)+(1-$B27)*($G$16*$C$10+(1-$G$16)*$C$9)) | E27: =$G$20*(1-E$23)*($B27*($G$16*$D$10+(1-$G$16)*$D$9)+(1-$B27)*($G$16*$C$10+(1-$G$16)*$C$9)) | F27: =$G$20*(1-F$23)*($B27*($G$16*$D$10+(1-$G$16)*$D$9)+(1-$B27)*($G$16*$C$10+(1-$G$16)*$C$9)) | G27: =$G$20*(1-G$23)*($B27*($G$16*$D$10+(1-$G$16)*$D$9)+(1-$B27)*($G$16*$C$10+(1-$G$16)*$C$9)) | H27: =$G$20*(1-H$23)*($B27*($G$16*$D$10+(1-$G$16)*$D$9)+(1-$B27)*($G$16*$C$10+(1-$G$16)*$C$9))
B28: 0.85 | C28: =$G$20*(1-C$23)*($B28*($G$16*$D$10+(1-$G$16)*$D$9)+(1-$B28)*($G$16*$C$10+(1-$G$16)*$C$9)) | D28: =$G$20*(1-D$23)*($B28*($G$16*$D$10+(1-$G$16)*$D$9)+(1-$B28)*($G$16*$C$10+(1-$G$16)*$C$9)) | E28: =$G$20*(1-E$23)*($B28*($G$16*$D$10+(1-$G$16)*$D$9)+(1-$B28)*($G$16*$C$10+(1-$G$16)*$C$9)) | F28: =$G$20*(1-F$23)*($B28*($G$16*$D$10+(1-$G$16)*$D$9)+(1-$B28)*($G$16*$C$10+(1-$G$16)*$C$9)) | G28: =$G$20*(1-G$23)*($B28*($G$16*$D$10+(1-$G$16)*$D$9)+(1-$B28)*($G$16*$C$10+(1-$G$16)*$C$9)) | H28: =$G$20*(1-H$23)*($B28*($G$16*$D$10+(1-$G$16)*$D$9)+(1-$B28)*($G$16*$C$10+(1-$G$16)*$C$9))
A30: E. TORNADO — one lever at a time, +/- 10 points from the Year-5 base
B31: Lever | C31: -10 points | D31: Base | E31: +10 points | F31: Swing | G31: Reading
B32: Productivity | C32: =$G$20*(1-($G$14-0.1))*(($G$15)*(($G$16)*$D$10+(1-($G$16))*$D$9)+(1-($G$15))*(($G$16)*$C$10+(1-($G$16))*$C$9)) | D32: =$G$20*(1-($G$14))*(($G$15)*(($G$16)*$D$10+(1-($G$16))*$D$9)+(1-($G$15))*(($G$16)*$C$10+(1-($G$16))*$C$9)) | E32: =$G$20*(1-($G$14+0.1))*(($G$15)*(($G$16)*$D$10+(1-($G$16))*$D$9)+(1-($G$15))*(($G$16)*$C$10+(1-($G$16))*$C$9)) | F32: =ABS(E32-C32) | G32: Scales unit cost one for one. The only linear lever.
B33: Offshore share | C33: =$G$20*(1-($G$14))*(($G$15-0.1)*(($G$16)*$D$10+(1-($G$16))*$D$9)+(1-($G$15-0.1))*(($G$16)*$C$10+(1-($G$16))*$C$9)) | D33: =$G$20*(1-($G$14))*(($G$15)*(($G$16)*$D$10+(1-($G$16))*$D$9)+(1-($G$15))*(($G$16)*$C$10+(1-($G$16))*$C$9)) | E33: =$G$20*(1-($G$14))*(($G$15+0.1)*(($G$16)*$D$10+(1-($G$16))*$D$9)+(1-($G$15+0.1))*(($G$16)*$C$10+(1-($G$16))*$C$9)) | F33: =ABS(E33-C33) | G33: Second largest — and now bounded by a measured start rather than an assumed one.
B34: Senior share | C34: =$G$20*(1-($G$14))*(($G$15)*(($G$16-0.1)*$D$10+(1-($G$16-0.1))*$D$9)+(1-($G$15))*(($G$16-0.1)*$C$10+(1-($G$16-0.1))*$C$9)) | D34: =$G$20*(1-($G$14))*(($G$15)*(($G$16)*$D$10+(1-($G$16))*$D$9)+(1-($G$15))*(($G$16)*$C$10+(1-($G$16))*$C$9)) | E34: =$G$20*(1-($G$14))*(($G$15)*(($G$16+0.1)*$D$10+(1-($G$16+0.1))*$D$9)+(1-($G$15))*(($G$16+0.1)*$C$10+(1-($G$16+0.1))*$C$9)) | F34: =ABS(E34-C34) | G34: Works against the other two. A richer shape gives back part of what offshore wins.
B35: Agile conversion — the fourth lever | G35: Not a direct term in the unit-cost formula. It works through productivity: the operating-model component is scaled by the agile share, so a one-year slip in the conversion costs about 5 points of Year-2 capability and roughly 0.05 of the unit cost index. It is the lever with the longest lead time and the least evidence behind it.
B37: Swings are full 20-point ranges. Halve them for a per-ten-point read.
