Workbook

Sheet README
A1: Insurance Claims and Benefits Payment Related — domain framework v1
A2: Six applications, 121.573 units, and the most disposition-exposed 領域 in the estate. One application carrying 28.8% of the domain is marked Retire, two more carry a zero Year-3 target, and Capgemini has six people on the ground against a vendor population of eighty-five.
A4: WHAT THIS 領域 IS
B5: Six applications, three archetypes | C5: Claim Batch 43.8, C12WNC-JPN 35.0 and Pega for Claims 16.7 (D, distributed-proven, 95.5 units between them) · W05AMS-JPN 22.0 (J, Japan-locked) · MDRS and WZZMNB-JPN 4.1 (T, long tail). Three value streams: Annuity ＆ Maturity Payment 67.8, Claims Processing ＆ Adjudication 35.0, Claims Support Services 18.8.
B6: Onshore, and only just starting to move | C6: 71.6 of the 85.4 vendor units are in Tokyo — 84%, the most onshore-weighted Capgemini population of the 領域 modelled. 4.2 units are offshore and 9.6 nearshore. With MGCC, 30.0% of the domain is delivered away from Tokyo against a 65.3% ceiling.
B7: The only 領域 with material nearshore | C7: 9.589 units on C12WNC-JPN — roughly half of all the nearshore capacity in the portfolio. Every other 領域 modelled is Tokyo-and-India only. The NEAR rows in this workbook are live, not schema.
B8: Six Capgemini people are here, and all six sit on one application | C8: Against 85.4 vendor units — 7%, the weakest continuity position of the 領域 modelled. All six are on Claim Batch. On C12WNC-JPN, W05AMS-JPN, Pega, MDRS and WZZMNB-JPN we start from nothing.
A9: THE THREE FINDINGS THAT MATTER COMMERCIALLY
B10: C12WNC-JPN is marked RETIRE, and it is 28.8% of the domain | C10: 35.0 units, business-critical, Japanese specifications, 9.6 units nearshore, and the entire Claims Processing ＆ Adjudication value stream. This model freezes scope at Year 1 as every domain model does, so that exposure is carried, not netted. It is the largest single disposition exposure in the estate and it has to be resolved with MetLife before the price is fixed.
B11: Two more applications carry a ZERO Year-3 target | C11: Pega for Claims 16.7 and MDRS 2.1 — 18.8 units, 15.5% of the domain — are among the nine applications MetLife's own Appendix 3 model takes to zero. Taken with C12WNC-JPN, 44.3% of this 領域 is under a disposition question.
B12: NCD holds 60% of the vendor side, and we absorb it | C12: 51.244 of the 85.449 vendor units — the second-heaviest named-vendor concentration in the estate after FSI on Contract Management. Consistent with the other 領域 modelled we absorb NCD rather than retain them, which puts the whole vendor side into the transferable pool and makes the 50:50 reachable. It also makes Year 1 a large transition. That is a due-diligence decision — see Basis ＆ Assumptions.
A13: THE SHAPE OF THE ANSWER
B14: MGCC has a HIGHER ceiling than we do here | C14: MGCC 48.60% against Capgemini 44.73%, because MGCC is a build-and-test population and 78.5% of this estate is archetype D — where Build and Test ceilings are the highest in the classifier. Adoption still puts us ahead on committed productivity (44.7% against 38.9% effective), but the underlying capability runs the other way. Worth saying out loud.
B15: The transfer is 11.6 people, and most of it goes to MetLife Japan | C15: Organic convergence only takes the ratio from 70.3% to 66.8% by Year 3 — MetLife's side is small and shrinks slowly. The transfer does the rest. We send 6.4 to MetLife Japan and 5.2 to MGCC rather than the portfolio default 35/65, because 84% of the Capgemini population is in Tokyo and people in Tokyo are re-badged to MetLife Japan.
B16: Headcount 121.6 → 59.3 | C16: A 51.2% reduction over five years, in line with the three other 領域 whose five-year plan is fully solved. AI ceiling 44.71%, applied glidepath 0 / 23.0 / 37.6 / 46.2 / 51.2%.
A17: THE ENGINE
B18: Unchanged from the other 領域 modelled | C18: Six-rule archetype classifier → AI and offshore ceilings from Golden Inventory v4 → realisation curve → four-gate capability → carry-forward and pre-load → per-sourcing productivity → organic ratio convergence → guardrails → seat ledger.
B19: Seats deploy whole people | C19: Pod Library column K and Horizontal Teams column J are the people you hire for that role across the block — whole numbers, or halves where one person covers two units inside this 領域. The SIT Loading sheet turns them into requisitions.
A20: WHAT TO RAISE
B21: The role line needs the largest restatement in the estate | C21: Appendix 3 records ZERO project management and 1.00 maintenance unit across six applications carrying 732 incidents and 1,161 changes. 83% of the vendor population is booked as Developer. Restated to 4.50 maintenance, 3.50 PM and 2.50 architecture, taken from the developer line. Arithmetically neutral; MetLife should confirm.
B22: And MetLife's two views of run disagree by a factor of seven | C22: The maintenance role line says 1.00 unit. The AD / AMS effort split in the same spreadsheet implies 6.75. On a 122-person domain that is about six people of exposure, and it sets the AMS price.
B23: The disposition questions are the priority | C23: 44.3% of this 領域 is either marked Retire or carries a zero Year-3 target in MetLife's own model. No other 領域 comes close. Resolve before submission.

Sheet Basis & Assumptions
A1: Where every input comes from, and which ones are ours
A2: This is a first-version model, so there is nothing to change-log. What matters instead is the provenance of each input: which are measured, which are restated, and which are domain overrides.
B4: Element | C4: Source | D4: Value used | E4: Status | F4: Note
B5: Baseline | C5: Appendix 3 v5, 6 applications | D5: effort 121.574 · FTC 85.449 · FTE 13.479 · MGCC 22.646 · onshore 71.626 · offshore 4.233 · nearshore 9.589 | E5: SOURCE | F5: Internally consistent: FTC + FTE + MGCC ties exactly to Total, and the three location lines tie exactly to FTC. No unallocated capacity to carry.
B6: Archetypes | C6: Golden Inventory v4, six-rule classifier | D6: D 3 / 95.479 · J 1 / 22.028 · T 2 / 4.067 | E6: SOURCE | F6: AI ceiling 44.71%, offshore ceiling 65.27%. Archetype D is 78.5% of the effort, which is what makes the productivity case; W05AMS-JPN at a 12% offshore ceiling is what caps the location case.
B7: Delivery method | C7: Appendix 3 v5 | D7: 1 agile · 1 hybrid · 4 waterfall; 16.7 of 121.6 units agile today | E7: MEASURED | F7: Pega for Claims is the only agile application. Claim Batch is hybrid. Four of six run on Japanese specifications.
B8: Adoption factors | C8: Portfolio default | D8: 1.00 / 0.85 / 0.55 / 0.80 — unchanged | E8: STANDARD | F8: No case for raising MetLife's commitment here. Unlike Common Service Platform this is a mostly waterfall, Japanese-specification estate, and MetLife's own staff are only 11.1% of it.
B9: Role line | C9: BSA 5.958 · DEV 70.899 · TEST 6.817 · MNT 1.000 · PM 0.000 · OTH 0.775 | D9: MNT 4.50 · PM 3.50 · OTH 2.50, taken from DEV | E9: RESTATED | F9: ZERO project management across six applications and three value streams, and 1.00 maintenance unit against 732 incidents and 1,161 changes. 83% of the vendor population booked as Developer — the highest in the estate. Arithmetically neutral; the total does not move.
B10: Partner | C10: NCD named on four applications | D10: 51.244 of 85.449 vendor units — 60.0% | E10: DOMAIN DECISION | F10: MODELLED AS ABSORBED, NOT RETAINED. Consistent with the other 領域 modelled, where FSI was retained on entrenched Japanese-specification work and NCD was absorbed everywhere. Absorbing puts all 85.4 vendor units into the transferable pool, which is what makes the 50:50 reachable — if due diligence says NCD must be retained on C12WNC-JPN and W05AMS-JPN, the transfer arithmetic changes materially and the residual reappears. This is the single assumption in this workbook most worth challenging.
B11: Transfer split | C11: Portfolio default 35% to MetLife Japan | D11: 55% to MetLife Japan · 45% to MGCC | E11: DOMAIN OVERRIDE | F11: 71.6 of 85.4 vendor units are in Tokyo — 84%, the most onshore-weighted Capgemini population of the 領域 modelled. The default assumes an offshore-weighted population being re-badged mostly into MGCC. Here that is backwards: people in Tokyo are re-badged to MetLife Japan.
B12: Inherited workforce | C12: T3 reconciliation behind Golden v4 | D12: 6 people, 1 onshore, all on Claim Batch | E12: SOURCE | F12: 7% of the vendor population. The weakest continuity position of the 領域 modelled, and it is concentrated on a single application.
B13: Disposition | C13: New in Appendix 3 v5 | D13: C12WNC-JPN marked Retire — 34.997 units, 28.8% | E13: NEW | F13: Not netted out; the model holds effort frozen at Year 1 as every domain model does. Pega for Claims and MDRS additionally carry a zero Year-3 target in Appendix 3 — a further 18.8 units. Together 44.3% of the 領域 is under a disposition question. See the README.
B14: Guardrails | C14: Portfolio standard | D14: 50% vendor share · 55% per unit · 55% of build-and-test | E14: STANDARD | F14: All held in every year, including the Year-4 dip immediately after the transfer — but only because the transfer split was re-cut to 55/45. At the portfolio default the build-and-test guardrail breaches in Year 4 at 53.5%.
B15: Transfer | C15: One event at the end of Year 3 | D15: 11.6 people — 6.4 to MetLife Japan, 5.2 to MGCC | E15: MODELLED | F15: Organic convergence runs first but only moves the ratio from 70.3% to 66.8%, because MetLife's side is small and shrinks slowly. The transfer carries most of the distance here, unlike the other 領域 modelled.
A17: HOW TO READ THE STATUS COLUMN
B18: • SOURCE — taken directly from Appendix 3 v5 or Golden Application Inventory v4. Not ours to change.
B19: • MEASURED — MetLife has supplied it and we use it as given, where an earlier version made us assume.
B20: • RESTATED — the client figure is internally impossible and we have changed it. Every restatement is arithmetically neutral: people move between role lines, the total does not. These go back to MetLife.
B21: • DOMAIN OVERRIDE — a portfolio default deliberately changed for this 領域, with the reason stated. These are solution decisions and should be defended as such in the review.
B22: • MODELLED — a construct of ours with no direct client source: partner plans, transfer sizing, conversion quarters. The assumptions most worth challenging.

Sheet Change Control
A1: Change control — what must still hold after you edit a seat count
A2: Pod Library column J and Horizontal Teams column I are INPUTS. You may change them. Holding the yearly total is necessary but not sufficient — these are the other things that have to survive the edit. Every check below is live.
A4: A. WHERE THESE NUMBERS GO
B5: • Pod Library J and Horizontal Teams I are hard-typed values, not formulas. Nothing upstream computes them — they are the design. Everything downstream is derived from them.
B6: • Seat Ledger reads them cell by cell (912 references to Pod Library, 630 to Horizontal Teams) and multiplies by the unit count on Pod Plan. Team Build-Up, Cost & Commercial, Inherited Workforce and Unit Cost Sensitivity are all SUMIFS over the Seat Ledger. Change a seat and every one of them moves.
B7: • THE ONE THAT SURPRISES PEOPLE: the Logic Tree reads the roster back. Partner seats (row 59) drive the partner share (row 60), the span-of-control factor (row 61), the applied operating-model gain (row 43), capability (row 45) and therefore the HEADCOUNT TARGET itself (row 53). Changing partner seats moves the target you are trying to hit. It converges, but it does not stand still.
B8: • What does NOT move: the effort baseline, the archetype mix, the AI and offshore ceilings, the realisation curve and the agile conversion quarters. Those are inputs on the Logic Tree and Delivery Mode.
A10: B. THE INVARIANTS — all of these must stay green
B11: Check | C11: Y1 | D11: Y2 | E11: Y3 | F11: Y4 | G11: Y5 | H11: Tolerance | I11: Status
B12: Headcount delivered minus Logic Tree target | C12: ='Team Build-Up'!C12 -> -0.0735 | D12: ='Team Build-Up'!D12 -> -0.097752193 | E12: ='Team Build-Up'!E12 -> 0.11798058 | F12: ='Team Build-Up'!F12 -> 0.063256079 | G12: ='Team Build-Up'!G12 -> 0.1811651 | H12: ± 1.5 | I12: =IF(MAX(ABS(C12),ABS(D12),ABS(E12),ABS(F12),ABS(G12))<=1.5,"OK","CHECK") -> OK | J12: The productivity commitment. If you add seats you must remove others.
B13: Capgemini share inside each POD | C13: =IFERROR((SUMIFS('Pod Library'!$J$5:$J$95,'Pod Library'!$B$5:$B$95,1,'Pod Library'!$C$5:$C$95,"POD",'Pod Library'!$I$5:$I$95,"FTC")+SUMIFS('Pod Library'!$J$5:$J$95,'Pod Library'!$B$5:$B$95,1,'Pod Library'!$C$5:$C$95,"POD",'Pod Library'!$I$5:$I$95,"PT"))/(SUMIFS('Pod Library'!$J$5:$J$95,'Pod Library'!$B$5:$B$95,1,'Pod Library'!$C$5:$C$95,"POD")),"n/a") -> 0.5625 | D13: =IFERROR((SUMIFS('Pod Library'!$J$5:$J$95,'Pod Library'!$B$5:$B$95,2,'Pod Library'!$C$5:$C$95,"POD",'Pod Library'!$I$5:$I$95,"FTC")+SUMIFS('Pod Library'!$J$5:$J$95,'Pod Library'!$B$5:$B$95,2,'Pod Library'!$C$5:$C$95,"POD",'Pod Library'!$I$5:$I$95,"PT"))/(SUMIFS('Pod Library'!$J$5:$J$95,'Pod Library'!$B$5:$B$95,2,'Pod Library'!$C$5:$C$95,"POD")),"n/a") -> 0.6 | E13: =IFERROR((SUMIFS('Pod Library'!$J$5:$J$95,'Pod Library'!$B$5:$B$95,3,'Pod Library'!$C$5:$C$95,"POD",'Pod Library'!$I$5:$I$95,"FTC")+SUMIFS('Pod Library'!$J$5:$J$95,'Pod Library'!$B$5:$B$95,3,'Pod Library'!$C$5:$C$95,"POD",'Pod Library'!$I$5:$I$95,"PT"))/(SUMIFS('Pod Library'!$J$5:$J$95,'Pod Library'!$B$5:$B$95,3,'Pod Library'!$C$5:$C$95,"POD")),"n/a") -> 0.60869565 | F13: =IFERROR((SUMIFS('Pod Library'!$J$5:$J$95,'Pod Library'!$B$5:$B$95,4,'Pod Library'!$C$5:$C$95,"POD",'Pod Library'!$I$5:$I$95,"FTC")+SUMIFS('Pod Library'!$J$5:$J$95,'Pod Library'!$B$5:$B$95,4,'Pod Library'!$C$5:$C$95,"POD",'Pod Library'!$I$5:$I$95,"PT"))/(SUMIFS('Pod Library'!$J$5:$J$95,'Pod Library'!$B$5:$B$95,4,'Pod Library'!$C$5:$C$95,"POD")),"n/a") -> 0.5625 | G13: =IFERROR((SUMIFS('Pod Library'!$J$5:$J$95,'Pod Library'!$B$5:$B$95,5,'Pod Library'!$C$5:$C$95,"POD",'Pod Library'!$I$5:$I$95,"FTC")+SUMIFS('Pod Library'!$J$5:$J$95,'Pod Library'!$B$5:$B$95,5,'Pod Library'!$C$5:$C$95,"POD",'Pod Library'!$I$5:$I$95,"PT"))/(SUMIFS('Pod Library'!$J$5:$J$95,'Pod Library'!$B$5:$B$95,5,'Pod Library'!$C$5:$C$95,"POD")),"n/a") -> 0.56578947 | H13: ≥ 55% | I13: =IF(COUNTIF(C13:G13,"<0.5450")=0,"OK","CHECK") -> OK | J13: A POD in which Capgemini is a minority is one whose ways of working we do not set.
B14: Capgemini share inside each TEAM | C14: =IFERROR((SUMIFS('Pod Library'!$J$5:$J$95,'Pod Library'!$B$5:$B$95,1,'Pod Library'!$C$5:$C$95,"TEAM",'Pod Library'!$I$5:$I$95,"FTC")+SUMIFS('Pod Library'!$J$5:$J$95,'Pod Library'!$B$5:$B$95,1,'Pod Library'!$C$5:$C$95,"TEAM",'Pod Library'!$I$5:$I$95,"PT"))/(SUMIFS('Pod Library'!$J$5:$J$95,'Pod Library'!$B$5:$B$95,1,'Pod Library'!$C$5:$C$95,"TEAM")),"n/a") -> 0.76315789 | D14: =IFERROR((SUMIFS('Pod Library'!$J$5:$J$95,'Pod Library'!$B$5:$B$95,2,'Pod Library'!$C$5:$C$95,"TEAM",'Pod Library'!$I$5:$I$95,"FTC")+SUMIFS('Pod Library'!$J$5:$J$95,'Pod Library'!$B$5:$B$95,2,'Pod Library'!$C$5:$C$95,"TEAM",'Pod Library'!$I$5:$I$95,"PT"))/(SUMIFS('Pod Library'!$J$5:$J$95,'Pod Library'!$B$5:$B$95,2,'Pod Library'!$C$5:$C$95,"TEAM")),"n/a") -> 0.8372093 | E14: =IFERROR((SUMIFS('Pod Library'!$J$5:$J$95,'Pod Library'!$B$5:$B$95,3,'Pod Library'!$C$5:$C$95,"TEAM",'Pod Library'!$I$5:$I$95,"FTC")+SUMIFS('Pod Library'!$J$5:$J$95,'Pod Library'!$B$5:$B$95,3,'Pod Library'!$C$5:$C$95,"TEAM",'Pod Library'!$I$5:$I$95,"PT"))/(SUMIFS('Pod Library'!$J$5:$J$95,'Pod Library'!$B$5:$B$95,3,'Pod Library'!$C$5:$C$95,"TEAM")),"n/a") -> n/a | F14: =IFERROR((SUMIFS('Pod Library'!$J$5:$J$95,'Pod Library'!$B$5:$B$95,4,'Pod Library'!$C$5:$C$95,"TEAM",'Pod Library'!$I$5:$I$95,"FTC")+SUMIFS('Pod Library'!$J$5:$J$95,'Pod Library'!$B$5:$B$95,4,'Pod Library'!$C$5:$C$95,"TEAM",'Pod Library'!$I$5:$I$95,"PT"))/(SUMIFS('Pod Library'!$J$5:$J$95,'Pod Library'!$B$5:$B$95,4,'Pod Library'!$C$5:$C$95,"TEAM")),"n/a") -> n/a | G14: =IFERROR((SUMIFS('Pod Library'!$J$5:$J$95,'Pod Library'!$B$5:$B$95,5,'Pod Library'!$C$5:$C$95,"TEAM",'Pod Library'!$I$5:$I$95,"FTC")+SUMIFS('Pod Library'!$J$5:$J$95,'Pod Library'!$B$5:$B$95,5,'Pod Library'!$C$5:$C$95,"TEAM",'Pod Library'!$I$5:$I$95,"PT"))/(SUMIFS('Pod Library'!$J$5:$J$95,'Pod Library'!$B$5:$B$95,5,'Pod Library'!$C$5:$C$95,"TEAM")),"n/a") -> n/a | H14: ≥ 55% | I14: =IF(COUNTIF(C14:G14,"<0.5450")=0,"OK","CHECK") -> OK | J14: A TEAM in which Capgemini is a minority is one whose ways of working we do not set.
B15: Capgemini share of the delivery population | C15: =IFERROR((SUMIFS('Seat Ledger'!$M$5:$M$287,'Seat Ledger'!$B$5:$B$287,1,'Seat Ledger'!$J$5:$J$287,"FTC")+SUMIFS('Seat Ledger'!$M$5:$M$287,'Seat Ledger'!$B$5:$B$287,1,'Seat Ledger'!$J$5:$J$287,"PT"))/(SUMIFS('Seat Ledger'!$M$5:$M$287,'Seat Ledger'!$B$5:$B$287,1)),0) -> 0.69958848 | D15: =IFERROR((SUMIFS('Seat Ledger'!$M$5:$M$287,'Seat Ledger'!$B$5:$B$287,2,'Seat Ledger'!$J$5:$J$287,"FTC")+SUMIFS('Seat Ledger'!$M$5:$M$287,'Seat Ledger'!$B$5:$B$287,2,'Seat Ledger'!$J$5:$J$287,"PT"))/(SUMIFS('Seat Ledger'!$M$5:$M$287,'Seat Ledger'!$B$5:$B$287,2)),0) -> 0.68449198 | E15: =IFERROR((SUMIFS('Seat Ledger'!$M$5:$M$287,'Seat Ledger'!$B$5:$B$287,3,'Seat Ledger'!$J$5:$J$287,"FTC")+SUMIFS('Seat Ledger'!$M$5:$M$287,'Seat Ledger'!$B$5:$B$287,3,'Seat Ledger'!$J$5:$J$287,"PT"))/(SUMIFS('Seat Ledger'!$M$5:$M$287,'Seat Ledger'!$B$5:$B$287,3)),0) -> 0.67105263 | F15: =IFERROR((SUMIFS('Seat Ledger'!$M$5:$M$287,'Seat Ledger'!$B$5:$B$287,4,'Seat Ledger'!$J$5:$J$287,"FTC")+SUMIFS('Seat Ledger'!$M$5:$M$287,'Seat Ledger'!$B$5:$B$287,4,'Seat Ledger'!$J$5:$J$287,"PT"))/(SUMIFS('Seat Ledger'!$M$5:$M$287,'Seat Ledger'!$B$5:$B$287,4)),0) -> 0.52671756 | G15: =IFERROR((SUMIFS('Seat Ledger'!$M$5:$M$287,'Seat Ledger'!$B$5:$B$287,5,'Seat Ledger'!$J$5:$J$287,"FTC")+SUMIFS('Seat Ledger'!$M$5:$M$287,'Seat Ledger'!$B$5:$B$287,5,'Seat Ledger'!$J$5:$J$287,"PT"))/(SUMIFS('Seat Ledger'!$M$5:$M$287,'Seat Ledger'!$B$5:$B$287,5)),0) -> 0.50420168 | H15: ≥ 50% | I15: =IF(COUNTIF(C15:G15,"<0.4950")=0,"OK","CHECK") -> OK | J15: Below half the roster we cannot carry a productivity commitment we do not control.
B16: Blocks deploying a non-whole number of people | C16: =SUMPRODUCT(('Pod Library'!$B$5:$B$95=1)*(ABS('Pod Library'!$K$5:$K$95*2-ROUND('Pod Library'!$K$5:$K$95*2,0))>0.01))+SUMPRODUCT(('Horizontal Teams'!$B$5:$B$110=1)*(ABS('Horizontal Teams'!$J$5:$J$110*2-ROUND('Horizontal Teams'!$J$5:$J$110*2,0))>0.01)) -> 0 | D16: =SUMPRODUCT(('Pod Library'!$B$5:$B$95=2)*(ABS('Pod Library'!$K$5:$K$95*2-ROUND('Pod Library'!$K$5:$K$95*2,0))>0.01))+SUMPRODUCT(('Horizontal Teams'!$B$5:$B$110=2)*(ABS('Horizontal Teams'!$J$5:$J$110*2-ROUND('Horizontal Teams'!$J$5:$J$110*2,0))>0.01)) -> 0 | E16: =SUMPRODUCT(('Pod Library'!$B$5:$B$95=3)*(ABS('Pod Library'!$K$5:$K$95*2-ROUND('Pod Library'!$K$5:$K$95*2,0))>0.01))+SUMPRODUCT(('Horizontal Teams'!$B$5:$B$110=3)*(ABS('Horizontal Teams'!$J$5:$J$110*2-ROUND('Horizontal Teams'!$J$5:$J$110*2,0))>0.01)) -> 0 | F16: =SUMPRODUCT(('Pod Library'!$B$5:$B$95=4)*(ABS('Pod Library'!$K$5:$K$95*2-ROUND('Pod Library'!$K$5:$K$95*2,0))>0.01))+SUMPRODUCT(('Horizontal Teams'!$B$5:$B$110=4)*(ABS('Horizontal Teams'!$J$5:$J$110*2-ROUND('Horizontal Teams'!$J$5:$J$110*2,0))>0.01)) -> 0 | G16: =SUMPRODUCT(('Pod Library'!$B$5:$B$95=5)*(ABS('Pod Library'!$K$5:$K$95*2-ROUND('Pod Library'!$K$5:$K$95*2,0))>0.01))+SUMPRODUCT(('Horizontal Teams'!$B$5:$B$110=5)*(ABS('Horizontal Teams'!$J$5:$J$110*2-ROUND('Horizontal Teams'!$J$5:$J$110*2,0))>0.01)) -> 0 | H16: =0 -> 0 | I16: =IF(SUM(C16:G16)=0,"OK","CHECK") -> OK | J16: Column K of the Pod Library and column J of Horizontal Teams are the people you hire for that role across the whole block. Every one is a whole number, or a half where one person covers two units INSIDE this domain. The seat ratio beside it is the modelling quantity and will not always be round — on a 28-team block, nine engineers is a ratio of 0.32.
B17: Horizontal roles that have fallen below 0.02 FTE | C17: =COUNTIFS('Horizontal Teams'!$B$5:$B$110,1,'Horizontal Teams'!$I$5:$I$110,"<0.02") -> 0 | D17: =COUNTIFS('Horizontal Teams'!$B$5:$B$110,2,'Horizontal Teams'!$I$5:$I$110,"<0.02") -> 0 | E17: =COUNTIFS('Horizontal Teams'!$B$5:$B$110,3,'Horizontal Teams'!$I$5:$I$110,"<0.02") -> 0 | F17: =COUNTIFS('Horizontal Teams'!$B$5:$B$110,4,'Horizontal Teams'!$I$5:$I$110,"<0.02") -> 0 | G17: =COUNTIFS('Horizontal Teams'!$B$5:$B$110,5,'Horizontal Teams'!$I$5:$I$110,"<0.02") -> 0 | H17: =0 -> 0 | I17: =IF(SUM(C17:G17)=0,"OK","CHECK") -> OK | J17: A domain cannot run without a delivery head, a service manager or an architect. If a role must genuinely end, delete the row rather than leaving it at zero.
B18: Year-1 reconciliation to Appendix 3 — worst line | C18: ='Team Build-Up'!E32 -> 9.8985 | H18: ± 2.6 | I18: =IF(ABS(C18)<=2.6,"OK","CHECK") -> CHECK | J18: Year 1 must reproduce the client's own numbers: effort, the sourcing split, all three locations and all six role lines. The tolerance is ± 2.6 because seats sit on a 0.5 grid and a Year-1 team seat carries a multiplier of 5 — one grid step is 2.5 people. That is the deliberate price of an anatomy that can be staffed. Moving a seat between bands is free; moving it between ROLE, LOCATION or SOURCING is what actually breaks this.
A20: C. WHAT GOES STALE AND WILL NOT WARN YOU
B21: • SOURCING & PRODUCTIVITY is static. It is produced outside Excel by the per-sourcing solver and pasted in. If you change seat counts, the pool ceilings, the organic-convergence table and the transfer solve on that sheet no longer describe this roster. Re-run the solver or treat the sheet as superseded.
B22: • SIT LOADING is static for the same reason. Re-generate it after any seat change, or the requisition plan will not match the ledger.
B23: • The TRANSFER on the Logic Tree is a typed input (rows 65-66), sized on the Year-3 exit position produced by the solver. Change the Year-3 roster materially and the transfer needs re-sizing, or the 50:50 will not land.
B24: • THE RULE OF THUMB. Re-banding a seat, renaming it, or moving it between pods is safe. Changing its ROLE, LOCATION or SOURCING is not — those are the attributes Year 1 reconciles on and the guardrails measure.

Sheet Logic Tree
A1: Logic Tree — ten parametric drivers, five years
A2: Amber cells are inputs. Everything else re-derives. Section F is rebuilt on the measured day-1 position.
A4: A. BASELINE — Appendix 3 v5, read and never edited
B5: Domain | C5: Insurance Claims and Benefits Payment Related
B6: Applications | C6: 6
B7: Total effort (units) | C7: 121.5735
B8: Current FTC reported (Capgemini + partner) | C8: 85.4485
B9: Current FTE | C9: 13.4792
B10: Current MGCC | C10: 22.6458
B11: — of which onshore Tokyo | C11: 71.6261 | J11: 28.87 offshore, 15.99 MGCC and 0.96 nearshore against 35.55 onshore. This domain already delivers most of its work away from Tokyo.
B12: — of which offshore | C12: 4.2333
B13: — of which nearshore | C13: 9.589
B14: — of which onsite | C14: 0
B15: Role: BSA | C15: 5.9583
B16: Role: Developer | C16: 70.8985 | J16: All six role lines are populated for this domain and are used exactly as reported. No restatement was needed.
B17: Role: Tester | C17: 6.8167
B18: Role: Maintenance | C18: 1
B19: Role: PM | C19: 0
B20: Role: Other | C20: 0.775
B21: AD effort (% of PRJ weighted) | C21: 114.8276
B22: Appendix 3 Year-3 target, each side | C22: 60.7868
B23: Ratio today — Capgemini share | C23: =C8/(C8+C9+C10) -> 0.70285465
B24: OFFSHORE TODAY — whole team, measured | C24: =(C12+C13+C10)/C7 -> 0.29996751 | J24: 45.5% on day one — 28.87 offshore, 0.96 nearshore and 15.99 MGCC. The highest starting position of the eleven domains, which is why the ceiling here is reachable rather than aspirational.
A26: B. ARCHETYPE MIX — from the Golden Application Inventory v4
B27: Archetype | C27: Name | D27: Apps | E27: Effort | F27: Share | G27: AI ceiling | H27: Offshore ceiling
B28: D | C28: Distributed-proven | D28: 3 | E28: 95.4786 | F28: =E28/$E$33 -> 0.78535765 | G28: 0.4825 | H28: 0.78
B29: J | C29: Japan-locked | D29: 1 | E29: 22.0283 | F29: =E29/$E$33 -> 0.18119342 | G29: 0.304 | H29: 0.12
B30: T | C30: Long tail | D30: 2 | E30: 4.0665 | F30: =E30/$E$33 -> 0.033448929 | G30: 0.39 | H30: 0.55
C33: Total | D33: =SUM(D28:D32) -> 6 | E33: =SUM(E28:E32) -> 121.5734 | F33: =SUM(F28:F32) -> 1
B34: APPLICABLE AI CEILING | C34: =SUMPRODUCT($E$28:$E$32,$G$28:$G$32)/$E$33 -> 0.44706295 | J34: 46.74% on the golden phase mix — the highest of the eleven domains, because both archetypes present are M and D, the two the classifier treats as most machine-addressable. No domain-specific override is applied.
B35: APPLICABLE OFFSHORE CEILING | C35: =SUMPRODUCT($E$28:$E$32,$H$28:$H$32)/$E$33 -> 0.65271909 | J35: 65.27%. Three archetype-D applications carry 78.5% of the effort at a 78% ceiling, and this domain is nothing but M and D.
A37: C. REALISATION AND THE NON-AI COMPONENTS
B38: Driver | C38: Year 1 | D38: Year 2 | E38: Year 3 | F38: Year 4 | G38: Year 5 | H38: Basis
B39: AI realisation — share of ceiling | C39: 0.25 | D39: 0.55 | E39: 0.75 | F39: 0.85 | G39: 0.9 | J39: Adoption, guardrails and substrate maturity. Capped at 90%.
B40: Classical ADM productivity, cumulative | C40: 0.02 | D40: 0.05 | E40: 0.07 | F40: 0.09 | G40: 0.11 | J40: Standardisation, defect reduction, shift-left.
B41: Operating-model productivity, RAW | C41: 0.03 | D41: 0.06 | E41: 0.08 | F41: 0.1 | G41: 0.12 | J41: Pod consolidation and one release train — only available where the stream is agile.
B42: Agile share of the domain → from the Delivery Mode sheet | C42: ='Delivery Mode'!C20 -> 0.39477447 | D42: ='Delivery Mode'!D20 -> 0.85606843 | E42: ='Delivery Mode'!E20 -> 1 | F42: ='Delivery Mode'!F20 -> 1 | G42: ='Delivery Mode'!G20 -> 1
B43: Operating-model productivity, APPLIED = raw × agile share × span-of-control factor | C43: =C41*C42*C61 -> 0.011843234 | D43: =D41*D42*D61 -> 0.051364106 | E43: =E41*E42*E61 -> 0.08 | F43: =F41*F42*F61 -> 0.1 | G43: =G41*G42*G61 -> 0.12 | J43: Scaling by the agile share is what makes the operating-model gain earned rather than assumed. It costs 2.0 points of Year-1 capability: 16.0% unscaled against the 14.1% the model earns.
B44: AI-attributable productivity | C44: =$C$34*C39 -> 0.11176574 | D44: =$C$34*D39 -> 0.24588462 | E44: =$C$34*E39 -> 0.33529721 | F44: =$C$34*F39 -> 0.38000351 | G44: =$C$34*G39 -> 0.40235665
B45: CAPABILITY EARNED by end of year | C45: =1-(1-C44)*(1-C40)*(1-C43) -> 0.1398396 | D45: =1-(1-D44)*(1-D40)*(1-D43) -> 0.32038813 | E45: =1-(1-E44)*(1-E40)*(1-E43) -> 0.43128029 | F45: =1-(1-F44)*(1-F40)*(1-F43) -> 0.49222287 | G45: =1-(1-G44)*(1-G40)*(1-G43) -> 0.53192573
A47: D. CARRY-FORWARD AND PRE-LOAD — what is applied to headcount
B48: Pre-load fraction of the in-year gain | C48: 0.5
C49: Year 1 | D49: Year 2 | E49: Year 3 | F49: Year 4 | G49: Year 5
B50: Banked from the prior year | C50: =0 -> 0 | D50: =C45 -> 0.1398396 | E50: =D45 -> 0.32038813 | F50: =E45 -> 0.43128029 | G50: =F45 -> 0.49222287
B51: Pre-load of this year's gain | C51: =0 -> 0 | D51: =$C$48*(D45-C45) -> 0.090274266 | E51: =$C$48*(E45-D45) -> 0.055446082 | F51: =$C$48*(F45-E45) -> 0.030471289 | G51: =$C$48*(G45-F45) -> 0.01985143
B52: APPLIED TO STAFFING | C52: =C50+C51 -> 0 | D52: =D50+D51 -> 0.23011386 | E52: =E50+E51 -> 0.37583421 | F52: =F50+F51 -> 0.46175158 | G52: =G50+G51 -> 0.5120743
B53: Headcount target = baseline x (1 - applied) | C53: =$C$7*(1-C52) -> 121.5735 | D53: =$C$7*(1-D52) -> 93.597752 | E53: =$C$7*(1-E52) -> 75.882019 | F53: =$C$7*(1-F52) -> 65.436744 | G53: =$C$7*(1-G52) -> 59.318835
B54: EXIT YEAR 3 — full realisation, the point the transfer is struck | E54: =$C$7*(1-E45) -> 69.141245
A56: E. PARTNER — the fourth sourcing type, and what it costs
B57: THERE IS NO MATERIAL PARTNER IN THIS 領域. Golden v4 names Capgemini on five of the ten applications and NCD on one 1.4-unit application; the remaining 13.0 vendor units carry no named incumbent. Partner seats are therefore modelled at zero and the rows below resolve to zero. The mechanic is kept live so that a sub-contract identified in due diligence can be priced without re-cutting the model.
B58: Measure | C58: Year 1 | D58: Year 2 | E58: Year 3 | F58: Year 4 | G58: Year 5 | H58: Basis
B59: Partner seats — from the seat ledger | C59: ='Team Build-Up'!C46 -> 0 | D59: ='Team Build-Up'!D46 -> 0 | E59: ='Team Build-Up'!E46 -> 0 | F59: ='Team Build-Up'!F46 -> 0 | G59: ='Team Build-Up'!G46 -> 0
B60: Partner share of the delivery population | C60: =IF('Team Build-Up'!C9=0,0,C59/'Team Build-Up'!C9) -> 0 | D60: =IF('Team Build-Up'!D9=0,0,D59/'Team Build-Up'!D9) -> 0 | E60: =IF('Team Build-Up'!E9=0,0,E59/'Team Build-Up'!E9) -> 0 | F60: =IF('Team Build-Up'!F9=0,0,F59/'Team Build-Up'!F9) -> 0 | G60: =IF('Team Build-Up'!G9=0,0,G59/'Team Build-Up'!G9) -> 0 | J60: Partner seats cannot transfer to MetLife. They sit on the Capgemini side of the 50:50 permanently — which is why a partner appearing later makes the ratio harder, not easier.
B61: Span-of-control factor = 1 − drag × partner share | C61: =1-$C$62*C60 -> 1 | D61: =1-$C$62*D60 -> 1 | E61: =1-$C$62*E60 -> 1 | F61: =1-$C$62*F60 -> 1 | G61: =1-$C$62*G60 -> 1
B62: Partner drag — INPUT | C62: 0.6 | J62: A partner seat returns 40% of the operating-model gain a Capgemini seat does: two management chains, a contractual boundary on ways of working, slower standardisation. It costs nothing here because the partner share is zero, but the drag is the number to argue about if one appears.
A64: F. OFFSHORE — a measured start, a re-cut ceiling, and three bases to report on
B65: M and D carry the portfolio's two highest offshore ceilings — 85% and 78% — and between them they are 95.5 of the 121.6 units here at a 78% ceiling, which is what carries the blend. W05AMS-JPN is applications carry Japanese-language specifications, and they total 4.6 units.
B66: Driver | C66: Year 1 | D66: Year 2 | E66: Year 3 | F66: Year 4 | G66: Year 5 | H66: Basis
B67: Gap closure — share of (ceiling − today) reached | C67: 0.04 | D67: 0.3 | E67: 0.55 | F67: 0.72 | G67: 0.84 | J67: Year 1 holds the position it inherits. Years 4 and 5 flatten deliberately — see below.
B68: TARGET OFFSHORE SHARE, whole team | C68: =$C$24+($C$35-$C$24)*C67 -> 0.31407757 | D68: =$C$24+($C$35-$C$24)*D67 -> 0.40579298 | E68: =$C$24+($C$35-$C$24)*E67 -> 0.49398088 | F68: =$C$24+($C$35-$C$24)*F67 -> 0.55394865 | G68: =$C$24+($C$35-$C$24)*G67 -> 0.59627884
B69: Delivered — whole team | C69: ='Team Build-Up'!C54 -> 0.30041152 | D69: ='Team Build-Up'!D54 -> 0.40641711 | E69: ='Team Build-Up'!E54 -> 0.49342105 | F69: ='Team Build-Up'!F54 -> 0.55725191 | G69: ='Team Build-Up'!G54 -> 0.60504202
B70: Delivered — vendor only (Capgemini + partner) | C70: ='Team Build-Up'!C55 -> 0.16470588 | D70: ='Team Build-Up'!D55 -> 0.3125 | E70: ='Team Build-Up'!E55 -> 0.44117647 | F70: ='Team Build-Up'!F55 -> 0.5942029 | G70: ='Team Build-Up'!G55 -> 0.68333333
B71: Delivered — Capgemini payroll only | C71: ='Team Build-Up'!C56 -> 0.16470588 | D71: ='Team Build-Up'!D56 -> 0.3125 | E71: ='Team Build-Up'!E56 -> 0.44117647 | F71: ='Team Build-Up'!F56 -> 0.5942029 | G71: ='Team Build-Up'!G56 -> 0.68333333 | J71: THE LINE THAT MATTERS COMMERCIALLY. Capgemini's own payroll is MORE offshore than the whole team throughout — 51.7% rising to 83.5% — because the onshore seats are disproportionately MetLife's. Unlike Contract Management, the Year-3 transfer does not strip our offshore book: only 7 people move to MGCC, so the Capgemini line keeps climbing after Year 3.
A73: G. TRANSFER OF EMPLOYMENT — one event, end of Year 3, Capgemini payroll only
B74: Transfer in year | C74: Year 1 | D74: Year 2 | E74: Year 3 | F74: Year 4 | G74: Year 5
B75: Capgemini Japan to MetLife Japan (FTE) | C75: 0 | D75: 0 | E75: 0 | F75: 0 | G75: 0 | J75: THE TRANSFER CARRIES MOST OF THE DISTANCE HERE, which is unusual. Organic convergence moves the ratio only from 70.3% to 66.8% by Year 3, because MetLife's side is 36.1 of 121.6 units and shrinks slowly. 11.6 people then move, against 32.3 available at the 70% cap.
B76: Capgemini India to MetLife MGCC | C76: 0 | D76: 0 | E76: 0 | F76: 0 | G76: 0
B77: Cumulative transferred | C77: =SUM($C$75:C76) -> 0 | D77: =SUM($C$75:D76) -> 0 | E77: =SUM($C$75:E76) -> 0 | F77: =SUM($C$75:F76) -> 0 | G77: =SUM($C$75:G76) -> 0 | J77: 6.4 to MetLife Japan and 5.2 to MGCC — a 55/45 split against the portfolio default of 35/65, because 84% of the Capgemini population is in Tokyo and people in Tokyo are re-badged to MetLife Japan, not to a captive centre in India. At the default split the build-and-test guardrail breaches in Year 4.
A79: H. COST INDEX — relative only, onshore Tokyo E2 = 1.00
B80: Location | C80: E1 | D80: E2 | E80: E3 | F80: E4 | G80: E5
B81: Onshore Tokyo | C81: 0.72 | D81: 1 | E81: 1.35 | F81: 1.85 | G81: 2.55
B82: Offshore Hyderabad | C82: 0.22 | D82: 0.3 | E82: 0.42 | F82: 0.6 | G82: 0.85
B83: Nearshore | C83: 0.45 | D83: 0.62 | E83: 0.84 | F83: 1.15 | G83: 1.58
B84: Nearshore is ZERO on this domain — every unit is either Tokyo or India. The NEAR rows and the nearshore cost column are carried anyway so that all eleven domain models share one schema. | I84: key | J84: E1 | K84: E2 | L84: E3 | M84: E4 | N84: E5
I85: ON | J85: 0.72 | K85: 1 | L85: 1.35 | M85: 1.85 | N85: 2.55
I86: OFF | J86: 0.22 | K86: 0.3 | L86: 0.42 | M86: 0.6 | N86: 0.85
I87: NEAR | J87: 0.45 | K87: 0.62 | L87: 0.84 | M87: 1.15 | N87: 1.58
I88: Lookup block for the Seat Ledger. Mirrors the table on the left.

Sheet Sourcing & Productivity
A1: Sourcing and productivity — the same chain, applied differently to each population
A2: Productivity is not one number applied to everybody. The three populations do different work and we do not control all three, so each carries its own AI ceiling and its own adoption factor. This is what makes the 50:50 converge on its own rather than by transfer.
A4: A. WHY ONE RATE CANNOT APPLY TO ALL THREE — the Year-1 role mix
B5: Population | C5: Heads Y1 | D5: BSA | E5: Developer | F5: Tester | G5: Maint.
B6: FTC · Capgemini payroll | C6: 57.702 | D6: 0.093410974 | E6: 0.64380784 | F6: 0.089390316 | G6: 0.098280822 | I6: MetLife's own people are governance, domain SME and product ownership. MGCC is build and test. They are not doing the same work, so they cannot carry the same productivity rate.
B7: PT · Partner (sub-contracted) | C7: 7.68 | D7: 0.24101563 | E7: 0.75898438 | F7: 0 | G7: 0
B8: FTE · MetLife Japan | C8: 19.388 | D8: 0.39374871 | E8: 0 | F8: 0 | G8: 0.23411388
B9: MGCC · MetLife MGCC | C9: 15.993 | D9: 0 | E9: 1 | F9: 0 | G9: 0
A11: B. EACH POPULATION'S OWN AI CEILING AND ADOPTION — INPUT
B12: Population | C12: Own AI ceiling | D12: Adoption | E12: Effective ceiling | F12: vs domain blend
B13: FTC · Capgemini payroll | C13: 0.46171242 | D13: 1 | E13: 0.46171242 | F13: -0.012179166 | I13: ADOPTION is the share of the ceiling each population can actually realise, and it is a judgement about AUTHORITY, not about capability. We build the tooling, set the ways of working and mandate them on our own payroll — so 1.00. Everything below that is somebody else's decision.
B14: PT · Partner (sub-contracted) | C14: 0.4473668 | D14: 0.85 | E14: 0.38026178 | F14: -0.042871216
B15: FTE · MetLife Japan | C15: 0.38163811 | D15: 0.55 | E15: 0.20990096 | F15: -0.18349592
B16: MGCC · MetLife MGCC | C16: 0.47987351 | D16: 0.8 | E16: 0.38389881 | F16: 0.026675973
B17: Domain blended ceiling (unchanged, and still the headline commitment) | C17: 0.46740502
B18: Only the AI gate is scaled. Classical ADM productivity attaches to the work and the operating-model gain attaches to the delivery unit, so both flow to every population regardless of employer.
A20: C. WHAT EACH POPULATION IS THEREFORE ASKED TO DELIVER
B21: Applied to staffing | C21: Year 1 | D21: Year 2 | E21: Year 3 | F21: Year 4 | G21: Year 5
B22: FTC · Capgemini payroll | C22: 0 | D22: 0.23401506 | E22: 0.38388594 | F22: 0.47009789 | G22: 0.5211233 | I22: The headline commitment is UNCHANGED from the previous version. What has changed is that it is no longer assumed to fall equally on all three populations.
B23: PT · Partner (sub-contracted) | C23: 0 | D23: 0.20395522 | E23: 0.3375221 | F23: 0.4154649 | G23: 0.46392092
B24: FTE · MetLife Japan | C24: 0 | D24: 0.14108256 | E24: 0.24054827 | F24: 0.30119543 | G24: 0.34427736
B25: MGCC · MetLife MGCC | C25: 0 | D25: 0.20529749 | E25: 0.33959239 | F25: 0.41790443 | G25: 0.46647518
B26: Whole-domain commitment (the headline) | C26: 0 | D26: 0.23611595 | E26: 0.38712631 | F26: 0.47391621 | G26: 0.52512118
A28: D. THE THREE-WAY COMMITMENT SPLIT
B29: CAPGEMINI COMMITS | C29: Our own headcount reduction, on our own payroll, on tooling and ways of working we control. This is contractible and we should contract it.
B30: METLIFE MUST DELIVER | C30: The reduction of MetLife Japan and MGCC headcount. We size it, we enable it and we report it — but redeploying MetLife's own people is MetLife's decision, and MGCC runs to its own utilisation targets. This should be a joint commitment with named owners, not a Capgemini SLA.
B31: JOINTLY DEPENDENT | C31: AI adoption on MetLife's side: tooling access, shared standards, common telemetry, and the substrate being used rather than merely available. If adoption lands below the factors in section B, the whole-team headcount misses even if Capgemini delivers in full.
A33: E. ORGANIC CONVERGENCE TO 50:50 — before any transfer
B34: Measure | C34: Year 1 | D34: Year 2 | E34: Year 3 | F34: Year 4 | G34: Year 5
B35: MetLife Japan (FTE) — own curve | C35: 19.388 | D35: 16.652691 | E35: 14.72425 | F35: 14.696025 | G35: 13.404314 | I35: MetLife's populations follow their own slower curves. Capgemini takes the balance, which means we shrink our own book faster than productivity alone would justify. That extra reduction is not a productivity claim — it is a deliberate commercial choice to reach the ratio organically instead of by transferring people.
B36: MetLife MGCC — own curve | C36: 15.993 | D36: 12.709677 | E36: 10.561899 | F36: 11.809391 | G36: 10.521268
B37: Partner — per the partner plan | C37: 7.68 | D37: 5.5 | E37: 3.5 | F37: 2 | G37: 1.5
B38: Capgemini — absorbs the balance | C38: 57.704 | D38: 42.110408 | E38: 32.970068 | F38: 24.505417 | G38: 22.425582
B39: TOTAL = the headline commitment | C39: 100.765 | D39: 76.972776 | E39: 61.756217 | F39: 53.010834 | G39: 47.851164
B40: RATIO — Capgemini share | C40: 0.6488761 | D40: 0.61853567 | E40: 0.59054893 | F40: 0.5 | G40: 0.5
B41: — of which productivity-driven | C41: 0 | D41: 0.23401506 | E41: 0.38388594 | F41: 0.47009789 | G41: 0.5211233
B42: — of which RATIO-DRIVEN, over and above productivity | C42: -3.4660844e-05 | D42: 0.036193812 | E42: 0.044728879 | F42: 0.1052129 | G42: 0.090231908
B44: This is the mechanism that halves the transfer. Reaching the ratio by shrinking our own book is cheaper, lower-risk and entirely within our control; a transfer of employment is neither.
A46: F. THE GUARDRAILS — where organic convergence has to stop
B47: Test | C47: Year 1 | D47: Year 2 | E47: Year 3 | F47: Year 4 | G47: Year 5 | H47: Floor
B48: Capgemini share of the delivery population | C48: 0.64886913 | D48: 0.61861963 | E48: 0.5903591 | F48: 0.49985849 | G48: 0.49975956 | H48: 0.5 | I48: THE POINT OF THE FLOOR. If Capgemini becomes a minority of the delivery population, or of the build-and-test seats, or of any single pod, we no longer set the ways of working — and a productivity commitment we cannot enforce is not a commitment. Convergence stops here, and from that year MetLife's population follows the whole-team curve rather than its own slower one.
B49: Capgemini share of build-and-test seats | C49: 0.75061205 | D49: 0.73921432 | E49: 0.74240429 | F49: 0.68716367 | G49: 0.69061809 | H49: 0.55
B50: Capgemini share inside every single delivery unit | C50: held | D50: held | E50: held | F50: held | G50: held | H50: 0.55
A52: G. THE TRANSFER — only what organic convergence cannot reach
C53: Value
B54: Exit Year 3 headcount, full realisation | C54: 56.157319
B55: Vendor units at exit, after organic convergence | C55: 33.163645
B56: Transferable pool — Capgemini payroll only | C56: 29.980959
B57: 50:50 requires each side to be | C57: 28.07866
B58: TRANSFER REQUIRED | C58: 5.0849853
B59: Maximum transferable at the 70% cap | C59: 20.986672
B60: Transfer applied | C60: 5.1
B61: — to MetLife Japan | C61: 1.8
B62: — to MGCC | C62: 3.3
B63: RESIDUAL GAP TO 50:50 | C63: -0.01501473
B64: Ratio reached at the Year-3 exit | C64: 0.49973263

Sheet Delivery Mode
A1: Delivery mode — measured per application, not assumed
A2: Appendix 3 v5 supplies the development method for every application here. Seven of the ten are agile today — 16.7 of 121.6 units. Four of six run on Japanese specifications and only two are cloud-flagged. and the productivity case rests on that.
A4: A. MODE TODAY AND TARGET, BY VALUE STREAM — INPUT
B5: Value stream | C5: Effort | D5: Archetype | E5: Mode today | F5: Agile from | G5: Why
B6: AMP · Annuity ＆ Maturity Payment | C6: 67.7544 | D6: D / J / T | E6: Hybrid | F6: Q3 | G6: Claim Batch is 43.8 of the 67.8 — cloud-flagged, hybrid method, and the only application in the 領域 Capgemini already sits on. W05AMS-JPN behind it is 22.0 units of Japan-locked waterfall. | I6: The mode column is MetLife's own data. MetLife records three value streams here. Claims Support Services already runs agile; Annuity ＆ Maturity Payment is hybrid-led; Claims Processing ＆ single release train and a stable pod shape, not about changing method. The quarter each stream Adjudication is waterfall, Japanese-specification and marked Retire, so it converts late by design: CSS Q2, AMP Q3, CPA Q7.
B7: CPA · Claims Processing & Adjudication | C7: 34.9965 | D7: D | E7: Waterfall | F7: Q7 | G7: C12WNC-JPN alone. Business-critical, Japanese specifications, 9.6 units nearshore, and MARKED RETIRE in Appendix 3 v5. Converted late on purpose.
B8: CSS · Claims Support Services | C8: 18.8225 | D8: D / T | E8: Agile | F8: Q2 | G8: Pega for Claims and MDRS. Already agile, English specifications, cloud-flagged — and both carry a ZERO Year-3 target in MetLife's own Appendix 3 model.
B9: Total | C9: =SUM(C6:C8) -> 121.5734
A11: B. AGILE SHARE BY YEAR — computed from the quarter each stream converts
B12: Value stream | C12: Year 1 | D12: Year 2 | E12: Year 3 | F12: Year 4 | G12: Year 5
B13: AMP | C13: 0.5 | D13: 1 | E13: 1 | F13: 1 | G13: 1
B14: CPA | C14: 0 | D14: 0.5 | E14: 1 | F14: 1 | G14: 1
B15: CSS | C15: 0.75 | D15: 1 | E15: 1 | F15: 1 | G15: 1
B16: Effort-weighted agile share of the domain | C16: =SUMPRODUCT($C$6:$C$8,C13:C15)/$C$9 -> 0.39477447 | D16: =SUMPRODUCT($C$6:$C$8,D13:D15)/$C$9 -> 0.85606843 | E16: =SUMPRODUCT($C$6:$C$8,E13:E15)/$C$9 -> 1 | F16: =SUMPRODUCT($C$6:$C$8,F13:F15)/$C$9 -> 1 | G16: =SUMPRODUCT($C$6:$C$8,G13:G15)/$C$9 -> 1
B18: Delivery units this produces
B19: — agile PODS | C19: 4 | D19: 7 | E19: 9 | F19: 9 | G19: 8
B20: — agile share (feeds the Logic Tree) | C20: =C16 -> 0.39477447 | D20: =D16 -> 0.85606843 | E20: =E16 -> 1 | F20: =F16 -> 1 | G20: =G16 -> 1
B21: — waterfall / hybrid TEAMS | C21: 5 | D21: 2 | E21: 0 | F21: 0 | G21: 0
A23: C. WHY THIS MATTERS TO THE NUMBER
B24: • Operating-model productivity — pod consolidation, one release train, span of control — is only available where the stream actually runs as a pod. Scaling the 3 / 6 / 8 / 10 / 12% curve by the Year-1 agile share of 39.5% cuts it to 1.2%, and that is the whole of the discount: NCD is absorbed rather than retained, so there is no partner share to net off. From Year 3 the domain is fully converted and the curve runs at full value.
B25: • The waterfall / hybrid TEAM is 12 seats with a separate test cell; the agile POD is 10 in Year 1 falling to 6 by Year 4, with test collapsed into SDET seats. Both carry MGCC seats from day one, which is what makes this domain's offshore movement cheap: the substrate is already there.
B26: • Year 1 runs 4 pods and 5 delivery teams. Teams are gone by Year 3 and the pod count runs 4 / 7 / 9 / 9 / 8 — it RISES before it falls, because conversion adds pods before productivity removes them. If Annuity ＆ Maturity Payment slips two quarters the Year-1 agile share falls from 39.5% to 11.7%, which costs nothing in staffing because Year 1 applies zero productivity by construction.
B27: • DECIDE the conversion quarters, not the modes. MetLife has given us the development method for every application, so the only assumption left on this sheet is WHEN each stream reaches the target pod shape — CSS Q2, AMP Q3, CPA Q7. The CPA quarter is the conservative one and it is deliberate — that stream is one them.

Sheet AMS & Ticket Load
A1: AMS and ticket load — the run team sized from evidence, for the first time
A2: 732 incidents and 1,161 changes over 32 months, from Appendix 3 v5.
A4: A. RECORDED VOLUMES — 1 Jan 2024 to 31 Aug 2026
B5: Measure | C5: Volume | D5: Per month | E5: Per unit of effort | F5: Share
B6: P1 — critical | C6: 0 | D6: =C6/$C$17 -> 0 | E6: =C6/'Logic Tree'!$C$7 -> 0 | F6: =C6/$C$11 -> 0 | I6: No P1 or P2 incidents at all in 32 months and 71% of incidents at P5. The estate is stable; the cost is in changing it, not in keeping it up.
B7: P2 — high | C7: 1 | D7: =C7/$C$17 -> 0.03125 | E7: =C7/'Logic Tree'!$C$7 -> 0.0082254768 | F7: =C7/$C$11 -> 0.0013661202
B8: P3 — medium | C8: 89 | D8: =C8/$C$17 -> 2.78125 | E8: =C8/'Logic Tree'!$C$7 -> 0.73206743 | F8: =C8/$C$11 -> 0.1215847
B9: P4 — low | C9: 143 | D9: =C9/$C$17 -> 4.46875 | E9: =C9/'Logic Tree'!$C$7 -> 1.1762432 | F9: =C9/$C$11 -> 0.19535519
B10: P5 — informational | C10: 499 | D10: =C10/$C$17 -> 15.59375 | E10: =C10/'Logic Tree'!$C$7 -> 4.1045129 | F10: =C10/$C$11 -> 0.68169399
B11: All incidents | C11: =SUM(C6:C10) -> 732 | D11: =C11/$C$17 -> 22.875 | E11: =C11/'Logic Tree'!$C$7 -> 6.021049
B12: Emergency change | C12: 34 | D12: =C12/$C$17 -> 1.0625 | E12: =C12/'Logic Tree'!$C$7 -> 0.27966621 | F12: =C12/$C$15 -> 0.029285099 | I12: 84% Standard and 4.3% Emergency. A high-volume, low-severity, highly repeatable change profile — the best automation case in the portfolio.
B13: Normal change | C13: 124 | D13: =C13/$C$17 -> 3.875 | E13: =C13/'Logic Tree'!$C$7 -> 1.0199591 | F13: =C13/$C$15 -> 0.10680448
B14: Standard change | C14: 1003 | D14: =C14/$C$17 -> 31.34375 | E14: =C14/'Logic Tree'!$C$7 -> 8.2501532 | F14: =C14/$C$15 -> 0.86391042
B15: All changes | C15: =SUM(C12:C14) -> 1161 | D15: =C15/$C$17 -> 36.28125 | E15: =C15/'Logic Tree'!$C$7 -> 9.5497785
B17: Observation window, months | C17: 32
A19: B. SIZING THE RUN TEAM — three independent bases, triangulated
B20: Basis | C20: Value | D20: Reading
B21: A. Maintenance role reported in Appendix 3 v5 | C21: ='Logic Tree'!C18 -> 1 | D21: MetLife's own HEADCOUNT view. Populated here, unlike Contract Management, so it is usable.
B22: B. Run effort implied by the AD / AMS split = (1 − AD share) x effort | C22: ='Logic Tree'!C7-'Logic Tree'!C21 -> 6.7459 | D22: MetLife's own EFFORT view: 13.5% of 100.765 units. It implies 2.4 times the run population the role line does, and both numbers come from the same spreadsheet.
B23: Total demand items per month (incidents + changes) | C23: =(C11+C15)/C17 -> 59.15625 | D23: 2,536 items in 32 months — 25.2 per unit of effort against 14.6 on Sales. High for a three-application estate, and 84% of the changes are Standard.
B24: C. Throughput implied by basis A — items per person per month | C24: =IFERROR(C23/C21,0) -> 59.15625 | D24: If the role line is right, each run person absorbs this many items a month.
B25: C. Throughput implied by basis B | C25: =IFERROR(C23/C22,0) -> 8.7692154 | D25: If the effort split is right, this is the rate. Industry L2 throughput on a modern data stack is 40 to 80 items per person per month; both of these sit far below it, which says these items carry investigation rather than triage.
B26: Run-facing seats in the Year-1 roster (Maintenance + Tester, all sourcing) | C26: ='Team Build-Up'!C64+'Team Build-Up'!C63 -> 20 | D26: Model output. Sized on the role line, which is the binding Year-1 reconciliation constraint, and reported here against the other two bases rather than averaged with them.
A28: C. WHAT THE TICKET DATA CHANGES
B29: • MetLife's two views of the run population disagree by a factor of 2.4. The Maintenance role line says 5.67 units; the AD / AMS effort split says 13.64. This model follows the role line, because Year 1 has to reconcile to Appendix 3 line by line — but the difference is 8 people and it is a real commercial exposure. PUT THIS TO METLIFE before the AMS price is fixed.
B30: • The severity profile is benign and the change profile is not. No P1 or P2 incidents in 32 months and 71% of incidents at P5 — this estate is stable. But 1,730 changes on 100.8 units, 84% of them Standard, is a high change rate, and Standard changes on a cloud data platform are exactly what pipeline automation and a release train remove. That is where the operating-model productivity in this domain actually comes from.
B31: • Ticket density is 25.2 items per unit of effort against 14.6 on Sales — the highest of the domains modelled so far. Combined with a 13.5% run share it suggests run work is sitting inside the Developer line, which is the same pattern Sales shows and the reason this cross-check is worth running on every domain.
B32: • DO ask MetLife which of the two run figures governs, and ask for the ticket-to-effort mapping behind the AD / AMS split. On a three-application domain this is a short conversation with a material price attached.

Sheet Inventory
A1: Inventory — the 10 Insurance Claims and Benefits Payment Related applications from Appendix 3 v5
A2: Classified by the six-rule classifier on the Golden Application Inventory v4.
B4: Application | C4: Arch | D4: Effort | E4: FTC | F4: FTE | G4: Onshore | H4: Nearshore | I4: Nearsh % | J4: BSA | K4: Dev | L4: AD % | M4: Crit | N4: Method | O4: Spec lang | P4: Lines of code | Q4: Batches | R4: Incidents | S4: Changes | T4: Primary code language
B5: Claim Batch | C5: D | D5: 43.782083 | E5: 20.590417 | F5: 5.0458333 | G5: 17.357083 | H5: 0 | I5: =IFERROR($H5/$D5,0) -> 0 | J5: 1.75 | K5: 12.24875 | L5: 0.9836596 | M5: N | N5: Hybrid | O5: Hybrid | P5: 711101 | Q5: 27 | R5: 46 | S5: 216 | T5: JAVA
B6: C12WNC-JPN | C6: D | D6: 34.996542 | E6: 29.379875 | F6: 5.6166667 | G6: 19.790833 | H6: 9.5890417 | I6: =IFERROR($H6/$D6,0) -> 0.27399969 | J6: 2 | K6: 27.379875 | L6: 0.90522873 | M6: Y | N6: Waterfall | O6: JP | P6: 0 | Q6: 170 | R6: 581 | S6: 608 | T6: VB.NET;C/C++;JAVA
B7: W05AMS-JPN | C7: J | D7: 22.028333 | E7: 20.211667 | F7: 1.8166667 | G7: 20.211667 | H7: 0 | I7: =IFERROR($H7/$D7,0) -> 0 | J7: 1.9166667 | K7: 18.295 | L7: 0.92547477 | M7: Y | N7: Waterfall | O7: JP | P7: 0 | Q7: 186 | R7: 86 | S7: 272 | T7: JAVA, C#, VC
B8: Pega for Claims | C8: D | D8: 16.7 | E8: 11.491667 | F8: 0.70833333 | G8: 10.491667 | H8: 0 | I8: =IFERROR($H8/$D8,0) -> 0 | J8: 0.29166667 | K8: 9.2 | L8: 0.98702595 | M8: N | N8: Agile | O8: EN | P8: 14772 | Q8: 1 | R8: 5 | S8: 9 | T8: JAVA
B9: MDRS | C9: T | D9: 2.1225 | E9: 2.1225 | F9: 0 | G9: 2.1225 | H9: 0 | I9: =IFERROR($H9/$D9,0) -> 0 | J9: 0 | K9: 2.1225 | L9: 0.75068708 | M9: Y | N9: Waterfall | O9: JP | P9: 537636 | Q9: 38 | R9: 4 | S9: 37 | T9: VB.NET
B10: WZZMNB-JPN | C10: T | D10: 1.944 | E10: 1.6523333 | F10: 0.29166667 | G10: 1.6523333 | H10: 0 | I10: =IFERROR($H10/$D10,0) -> 0 | J10: 0 | K10: 1.6523333 | L10: 0.83217593 | M10: N | N10: Waterfall | O10: JP | P10: 0 | Q10: 17 | R10: 10 | S10: 19 | T10: JAVA
B11: TOTAL | D11: =SUM(D5:D10) -> 121.57346 | E11: =SUM(E5:E10) -> 85.448458 | F11: =SUM(F5:F10) -> 13.479167 | G11: =SUM(G5:G10) -> 71.626083 | H11: =SUM(H5:H10) -> 9.5890417 | J11: =SUM(J5:J10) -> 5.9583333 | K11: =SUM(K5:K10) -> 70.898458 | P11: =SUM(P5:P10) -> 1263509 | Q11: =SUM(Q5:Q10) -> 439 | R11: =SUM(R5:R10) -> 732 | S11: =SUM(S5:S10) -> 1161
B13: All six carry a development method and a specification language. Four run on Japanese specifications, only two are cloud-flagged and none is marked 優先引継対象. Code volume totals 1.26 million lines across three applications. Read the disposition column before anything else: C12WNC-JPN is marked RETIRE and is 35.0 of the 121.6 units, and Pega for Claims and MDRS carry a zero Year-3 target in MetLife's own Appendix 3 model. Together that is 44.3% of the 領域 under a disposition question — the highest exposure of any 領域 modelled, and the first thing to resolve with MetLife.

Sheet Value Streams
A1: Delivery streams — reconciling to 10 applications and 198.780 units
A2: MetLife records THREE value streams here — Annuity ＆ Maturity Payment (3 applications, 67.754 units), Claims Processing ＆ Adjudication (1 application, 34.997) and Claims Support Services (2, 18.823). All three are used as given; no synthetic stream was needed.
B4: Code | C4: Value stream | D4: Apps | E4: Effort | F4: Arch | G4: Mode today | H4: Agile from | I4: Y1 pods | J4: Y2 | K4: Y3 | L4: Y4 | M4: Y5 | N4: Vendor position today
B5: AMP | C5: Annuity ＆ Maturity Payment | D5: 3 | E5: 67.7544 | F5: D / J / T | G5: Hybrid | H5: Q3 | I5: 2 + 3t | J5: 4 + 1t | K5: 5 | L5: 5 | M5: 4 | N5: NCD 21.9 · CG 20.6
B6: CPA | C6: Claims Processing & Adjudication | D6: 1 | E6: 34.9965 | F6: D | G6: Waterfall | H6: Q7 | I6: 0 + 2t | J6: 1 + 1t | K6: 2 | L6: 2 | M6: 2 | N6: NCD 29.4
B7: CSS | C7: Claims Support Services | D7: 2 | E7: 18.8225 | F7: D / T | G7: Agile | H7: Q2 | I7: 2 | J7: 2 | K7: 2 | L7: 2 | M7: 2 | N7: unnamed 13.6
C8: Total | D8: =SUM(D5:D7) -> 6 | E8: =SUM(E5:E7) -> 121.5734
B10: Pod counts read 'pods + teams'. Teams are gone from Year 2 — the fastest conversion in the portfolio, because both streams already run agile. No delivery unit carries a partner seat: there is no named sub-contractor of size in this 領域. Note the MGCC seats inside every pod from Year 1 — 22.6 units, 18.6% of the domain — which is the only capacity already away here cheap and the 50:50 already met.

Sheet Pod Library
A1: Pod library — every seat, with MetLife's own role taxonomy and four sourcing types
A2: INPUT. Sourcing FTC = Capgemini payroll · PT = named sub-contractor, zero in this 領域 · FTE = MetLife Japan · MGCC = MetLife Global Capability Centre. Only FTC can transfer, and here nothing needs to.
B4: Year | C4: Unit | D4: Seat | E4: Role detail | F4: Role | G4: Exp | H4: Loc | I4: Sourcing | J4: Count | K4: People in the block
B5: 1 | C5: POD | D5: 1 | E5: MetLife Claims Product Owner | F5: PM | G5: E4 | H5: ON | I5: FTE | J5: 0.25 | K5: =J5*4 -> 1
B6: 1 | C6: POD | D6: 2 | E6: MetLife Claims SME | F6: BSA | G6: E4 | H6: ON | I6: FTE | J6: 0.25 | K6: =J6*4 -> 1
B7: 1 | C7: POD | D7: 3 | E7: Business Analyst (bilingual) | F7: BSA | G7: E3 | H7: ON | I7: FTC | J7: 0.375 | K7: =J7*4 -> 1.5
B8: 1 | C8: POD | D8: 4 | E8: Pod lead / senior engineer | F8: DEV | G8: E4 | H8: ON | I8: FTC | J8: 2.375 | K8: =J8*4 -> 9.5
B9: 1 | C9: POD | D9: 5 | E9: Claims Engineer | F9: DEV | G9: E3 | H9: OFF | I9: FTC | J9: 0 | K9: =J9*4 -> 0
B10: 1 | C10: POD | D10: 6 | E10: Claims Engineer | F10: DEV | G10: E2 | H10: OFF | I10: FTC | J10: 0.25 | K10: =J10*4 -> 1
B11: 1 | C11: POD | D11: 7 | E11: MGCC Payments Engineer | F11: DEV | G11: E3 | H11: OFF | I11: MGCC | J11: 1.375 | K11: =J11*4 -> 5.5
B12: 1 | C12: POD | D12: 8 | E12: SDET / Automation Engineer | F12: TEST | G12: E3 | H12: OFF | I12: FTC | J12: 0 | K12: =J12*4 -> 0
B13: 1 | C13: POD | D13: 9 | E13: MGCC Quality Engineer | F13: TEST | G13: E2 | H13: OFF | I13: MGCC | J13: 0.75 | K13: =J13*4 -> 3
B14: 1 | C14: POD | D14: 10 | E14: Solution Architect | F14: OTH | G14: E5 | H14: ON | I14: FTC | J14: 0.375 | K14: =J14*4 -> 1.5
D15: POD size — Year 1 | J15: =SUM(J5:J14) -> 6
B17: 1 | C17: TEAM | D17: 1 | E17: MetLife Claims Product Owner | F17: PM | G17: E4 | H17: ON | I17: FTE | J17: 0.7 | K17: =J17*5 -> 3.5
B18: 1 | C18: TEAM | D18: 2 | E18: MetLife Claims SME | F18: BSA | G18: E4 | H18: ON | I18: FTE | J18: 0.8 | K18: =J18*5 -> 4
B19: 1 | C19: TEAM | D19: 3 | E19: MetLife Operations Analyst | F19: MNT | G19: E3 | H19: ON | I19: FTE | J19: 0.2 | K19: =J19*5 -> 1
B20: 1 | C20: TEAM | D20: 4 | E20: Business Analyst (bilingual) | F20: BSA | G20: E3 | H20: ON | I20: FTC | J20: 0.4 | K20: =J20*5 -> 2
B21: 1 | C21: TEAM | D21: 5 | E21: Team lead / senior engineer | F21: DEV | G21: E4 | H21: ON | I21: FTC | J21: 1.7 | K21: =J21*5 -> 8.5
B22: 1 | C22: TEAM | D22: 6 | E22: Application Developer | F22: DEV | G22: E3 | H22: ON | I22: FTC | J22: 3.2 | K22: =J22*5 -> 16
B23: 1 | C23: TEAM | D23: 7 | E23: Application Developer | F23: DEV | G23: E2 | H23: ON | I23: FTC | J23: 3.5 | K23: =J23*5 -> 17.5
B24: 1 | C24: TEAM | D24: 8 | E24: Application Developer | F24: DEV | G24: E3 | H24: NEAR | I24: FTC | J24: 1.6 | K24: =J24*5 -> 8
B25: 1 | C25: TEAM | D25: 9 | E25: Test Analyst | F25: TEST | G25: E3 | H25: ON | I25: FTC | J25: 1 | K25: =J25*5 -> 5
B26: 1 | C26: TEAM | D26: 10 | E26: Test Engineer | F26: TEST | G26: E2 | H26: NEAR | I26: FTC | J26: 0.2 | K26: =J26*5 -> 1
B27: 1 | C27: TEAM | D27: 11 | E27: MGCC Payments Engineer | F27: DEV | G27: E3 | H27: OFF | I27: MGCC | J27: 1.9 | K27: =J27*5 -> 9.5
B28: 1 | C28: TEAM | D28: 12 | E28: Technical Lead | F28: OTH | G28: E4 | H28: ON | I28: FTC | J28: 0 | K28: =J28*5 -> 0
D29: TEAM size — Year 1 | J29: =SUM(J17:J28) -> 15.2
B31: 2 | C31: POD | D31: 1 | E31: MetLife Claims Product Owner | F31: PM | G31: E4 | H31: ON | I31: FTE | J31: 0.57142857 | K31: =J31*7 -> 4
B32: 2 | C32: POD | D32: 2 | E32: MetLife Claims SME | F32: BSA | G32: E4 | H32: ON | I32: FTE | J32: 0.42857143 | K32: =J32*7 -> 3
B33: 2 | C33: POD | D33: 3 | E33: Business Analyst (bilingual) | F33: BSA | G33: E3 | H33: ON | I33: FTC | J33: 1 | K33: =J33*7 -> 7
B34: 2 | C34: POD | D34: 4 | E34: Pod lead / senior engineer | F34: DEV | G34: E4 | H34: ON | I34: FTC | J34: 1.3571429 | K34: =J34*7 -> 9.5
B35: 2 | C35: POD | D35: 5 | E35: Claims Engineer | F35: DEV | G35: E3 | H35: OFF | I35: FTC | J35: 0.64285714 | K35: =J35*7 -> 4.5
B36: 2 | C36: POD | D36: 6 | E36: Claims Engineer | F36: DEV | G36: E2 | H36: OFF | I36: FTC | J36: 0.57142857 | K36: =J36*7 -> 4
B37: 2 | C37: POD | D37: 7 | E37: MGCC Payments Engineer | F37: DEV | G37: E3 | H37: OFF | I37: MGCC | J37: 1.1428571 | K37: =J37*7 -> 8
B38: 2 | C38: POD | D38: 8 | E38: SDET / Automation Engineer | F38: TEST | G38: E3 | H38: OFF | I38: FTC | J38: 0 | K38: =J38*7 -> 0
B39: 2 | C39: POD | D39: 9 | E39: MGCC Quality Engineer | F39: TEST | G39: E2 | H39: OFF | I39: MGCC | J39: 0.71428571 | K39: =J39*7 -> 5
B40: 2 | C40: POD | D40: 10 | E40: Solution Architect | F40: OTH | G40: E5 | H40: ON | I40: FTC | J40: 0.71428571 | K40: =J40*7 -> 5
D41: POD size — Year 2 | J41: =SUM(J31:J40) -> 7.1428571
B43: 2 | C43: TEAM | D43: 1 | E43: MetLife Claims Product Owner | F43: PM | G43: E4 | H43: ON | I43: FTE | J43: 0 | K43: =J43*2 -> 0
B44: 2 | C44: TEAM | D44: 2 | E44: MetLife Claims SME | F44: BSA | G44: E4 | H44: ON | I44: FTE | J44: 0 | K44: =J44*2 -> 0
B45: 2 | C45: TEAM | D45: 3 | E45: MetLife Operations Analyst | F45: MNT | G45: E3 | H45: ON | I45: FTE | J45: 0.5 | K45: =J45*2 -> 1
B46: 2 | C46: TEAM | D46: 4 | E46: Business Analyst (bilingual) | F46: BSA | G46: E3 | H46: ON | I46: FTC | J46: 0.5 | K46: =J46*2 -> 1
B47: 2 | C47: TEAM | D47: 5 | E47: Team lead / senior engineer | F47: DEV | G47: E4 | H47: ON | I47: FTC | J47: 0.5 | K47: =J47*2 -> 1
B48: 2 | C48: TEAM | D48: 6 | E48: Application Developer | F48: DEV | G48: E3 | H48: ON | I48: FTC | J48: 2 | K48: =J48*2 -> 4
B49: 2 | C49: TEAM | D49: 7 | E49: Application Developer | F49: DEV | G49: E2 | H49: ON | I49: FTC | J49: 2.75 | K49: =J49*2 -> 5.5
B50: 2 | C50: TEAM | D50: 8 | E50: Application Developer | F50: DEV | G50: E3 | H50: NEAR | I50: FTC | J50: 0.75 | K50: =J50*2 -> 1.5
B51: 2 | C51: TEAM | D51: 9 | E51: Test Analyst | F51: TEST | G51: E3 | H51: ON | I51: FTC | J51: 1 | K51: =J51*2 -> 2
B52: 2 | C52: TEAM | D52: 10 | E52: Test Engineer | F52: TEST | G52: E2 | H52: NEAR | I52: FTC | J52: 1 | K52: =J52*2 -> 2
B53: 2 | C53: TEAM | D53: 11 | E53: MGCC Payments Engineer | F53: DEV | G53: E3 | H53: OFF | I53: MGCC | J53: 1.25 | K53: =J53*2 -> 2.5
B54: 2 | C54: TEAM | D54: 12 | E54: Technical Lead | F54: OTH | G54: E4 | H54: ON | I54: FTC | J54: 0.5 | K54: =J54*2 -> 1
D55: TEAM size — Year 2 | J55: =SUM(J43:J54) -> 10.75
B57: 3 | C57: POD | D57: 1 | E57: MetLife Claims Product Owner | F57: PM | G57: E4 | H57: ON | I57: FTE | J57: 0.61111111 | K57: =J57*9 -> 5.5
B58: 3 | C58: POD | D58: 2 | E58: MetLife Claims SME | F58: BSA | G58: E4 | H58: ON | I58: FTE | J58: 0.38888889 | K58: =J58*9 -> 3.5
B59: 3 | C59: POD | D59: 3 | E59: Business Analyst (bilingual) | F59: BSA | G59: E3 | H59: ON | I59: FTC | J59: 0.55555556 | K59: =J59*9 -> 5
B60: 3 | C60: POD | D60: 4 | E60: Pod lead / senior engineer | F60: DEV | G60: E4 | H60: ON | I60: FTC | J60: 1 | K60: =J60*9 -> 9
B61: 3 | C61: POD | D61: 5 | E61: Claims Engineer | F61: DEV | G61: E3 | H61: OFF | I61: FTC | J61: 0.94444444 | K61: =J61*9 -> 8.5
B62: 3 | C62: POD | D62: 6 | E62: Claims Engineer | F62: DEV | G62: E2 | H62: OFF | I62: FTC | J62: 0.61111111 | K62: =J62*9 -> 5.5
B63: 3 | C63: POD | D63: 7 | E63: MGCC Payments Engineer | F63: DEV | G63: E3 | H63: OFF | I63: MGCC | J63: 1 | K63: =J63*9 -> 9
B64: 3 | C64: POD | D64: 8 | E64: SDET / Automation Engineer | F64: TEST | G64: E3 | H64: OFF | I64: FTC | J64: 0 | K64: =J64*9 -> 0
B65: 3 | C65: POD | D65: 9 | E65: MGCC Quality Engineer | F65: TEST | G65: E2 | H65: OFF | I65: MGCC | J65: 0.5 | K65: =J65*9 -> 4.5
B66: 3 | C66: POD | D66: 10 | E66: Solution Architect | F66: OTH | G66: E5 | H66: ON | I66: FTC | J66: 0.77777778 | K66: =J66*9 -> 7
D67: POD size — Year 3 | J67: =SUM(J57:J66) -> 6.3888889
B69: 4 | C69: POD | D69: 1 | E69: MetLife Claims Product Owner | F69: PM | G69: E4 | H69: ON | I69: FTE | J69: 0.5 | K69: =J69*9 -> 4.5
B70: 4 | C70: POD | D70: 2 | E70: MetLife Claims SME | F70: BSA | G70: E4 | H70: ON | I70: FTE | J70: 0.61111111 | K70: =J70*9 -> 5.5
B71: 4 | C71: POD | D71: 3 | E71: Business Analyst (bilingual) | F71: BSA | G71: E3 | H71: ON | I71: FTC | J71: 0.44444444 | K71: =J71*9 -> 4
B72: 4 | C72: POD | D72: 4 | E72: Pod lead / senior engineer | F72: DEV | G72: E4 | H72: ON | I72: FTC | J72: 0.55555556 | K72: =J72*9 -> 5
B73: 4 | C73: POD | D73: 5 | E73: Claims Engineer | F73: DEV | G73: E3 | H73: OFF | I73: FTC | J73: 0.5 | K73: =J73*9 -> 4.5
B74: 4 | C74: POD | D74: 6 | E74: Claims Engineer | F74: DEV | G74: E2 | H74: OFF | I74: FTC | J74: 1.1111111 | K74: =J74*9 -> 10
B75: 4 | C75: POD | D75: 7 | E75: MGCC Payments Engineer | F75: DEV | G75: E3 | H75: OFF | I75: MGCC | J75: 0.61111111 | K75: =J75*9 -> 5.5
B76: 4 | C76: POD | D76: 8 | E76: SDET / Automation Engineer | F76: TEST | G76: E3 | H76: OFF | I76: FTC | J76: 0.22222222 | K76: =J76*9 -> 2
B77: 4 | C77: POD | D77: 9 | E77: MGCC Quality Engineer | F77: TEST | G77: E2 | H77: OFF | I77: MGCC | J77: 0.61111111 | K77: =J77*9 -> 5.5
B78: 4 | C78: POD | D78: 10 | E78: Solution Architect | F78: OTH | G78: E5 | H78: ON | I78: FTC | J78: 0.16666667 | K78: =J78*9 -> 1.5
D79: POD size — Year 4 | J79: =SUM(J69:J78) -> 5.3333333
B81: 5 | C81: POD | D81: 1 | E81: MetLife Claims Product Owner | F81: PM | G81: E4 | H81: ON | I81: FTE | J81: 0.5 | K81: =J81*8 -> 4
B82: 5 | C82: POD | D82: 2 | E82: MetLife Claims SME | F82: BSA | G82: E4 | H82: ON | I82: FTE | J82: 0.5 | K82: =J82*8 -> 4
B83: 5 | C83: POD | D83: 3 | E83: Business Analyst (bilingual) | F83: BSA | G83: E3 | H83: ON | I83: FTC | J83: 0.1875 | K83: =J83*8 -> 1.5
B84: 5 | C84: POD | D84: 4 | E84: Pod lead / senior engineer | F84: DEV | G84: E4 | H84: ON | I84: FTC | J84: 0.4375 | K84: =J84*8 -> 3.5
B85: 5 | C85: POD | D85: 5 | E85: Claims Engineer | F85: DEV | G85: E3 | H85: OFF | I85: FTC | J85: 0.5 | K85: =J85*8 -> 4
B86: 5 | C86: POD | D86: 6 | E86: Claims Engineer | F86: DEV | G86: E2 | H86: OFF | I86: FTC | J86: 1.1875 | K86: =J86*8 -> 9.5
B87: 5 | C87: POD | D87: 7 | E87: MGCC Payments Engineer | F87: DEV | G87: E3 | H87: OFF | I87: MGCC | J87: 0.5625 | K87: =J87*8 -> 4.5
B88: 5 | C88: POD | D88: 8 | E88: SDET / Automation Engineer | F88: TEST | G88: E3 | H88: OFF | I88: FTC | J88: 0.375 | K88: =J88*8 -> 3
B89: 5 | C89: POD | D89: 9 | E89: MGCC Quality Engineer | F89: TEST | G89: E2 | H89: OFF | I89: MGCC | J89: 0.5 | K89: =J89*8 -> 4
B90: 5 | C90: POD | D90: 10 | E90: Solution Architect | F90: OTH | G90: E5 | H90: ON | I90: FTC | J90: 0 | K90: =J90*8 -> 0
D91: POD size — Year 5 | J91: =SUM(J81:J90) -> 4.75
B93: Year 1 runs 4 pods and 5 delivery teams — the teams carry Claims Processing ＆ Adjudication and the waterfall half of Annuity ＆ Maturity Payment, and are gone by Year 3. From Year 4 the pod anatomy CONTAINS the transferred MetLife and MGCC seats, which is why the Year-3 transfer shows up in the Year-4 ratio rather than only in the Glidepath solve.
B95: The seat ratio in column J is the modelling quantity — the share of one unit's establishment this role holds. Column K is what you hire: the ratio multiplied by the number of units that year. Every value in column K is a whole number of people, or a half where one person covers two units inside this domain.

Sheet Pod Plan
A1: Pod plan — how many pods and how many waterfall teams, per stream per year
A2: INPUT. This is where productivity shows up in the headcount, and where the agile conversion shows up in the unit mix.
B4: Year | C4: VS | D4: Value stream | E4: Pods | F4: Teams | G4: Units | H4: People
B5: 1 | C5: AMP | D5: Annuity ＆ Maturity Payment | E5: 2 | F5: 3 | G5: =E5+F5 -> 5 | H5: =E5*SUM('Pod Library'!$J$5:$J$14)+F5*SUM('Pod Library'!$J$17:$J$28) -> 57.6
B6: 1 | C6: CPA | D6: Claims Processing & Adjudication | E6: 0 | F6: 2 | G6: =E6+F6 -> 2 | H6: =E6*SUM('Pod Library'!$J$5:$J$14)+F6*SUM('Pod Library'!$J$17:$J$28) -> 30.4
B7: 1 | C7: CSS | D7: Claims Support Services | E7: 2 | F7: 0 | G7: =E7+F7 -> 2 | H7: =E7*SUM('Pod Library'!$J$5:$J$14)+F7*SUM('Pod Library'!$J$17:$J$28) -> 12
D8: Year 1 total | E8: =SUM(E5:E7) -> 4 | F8: =SUM(F5:F7) -> 5 | G8: =SUM(G5:G7) -> 9 | H8: =SUM(H5:H7) -> 100
B10: 2 | C10: AMP | D10: Annuity ＆ Maturity Payment | E10: 4 | F10: 1 | G10: =E10+F10 -> 5 | H10: =E10*SUM('Pod Library'!$J$31:$J$40)+F10*SUM('Pod Library'!$J$43:$J$54) -> 39.321429
B11: 2 | C11: CPA | D11: Claims Processing & Adjudication | E11: 1 | F11: 1 | G11: =E11+F11 -> 2 | H11: =E11*SUM('Pod Library'!$J$31:$J$40)+F11*SUM('Pod Library'!$J$43:$J$54) -> 17.892857
B12: 2 | C12: CSS | D12: Claims Support Services | E12: 2 | F12: 0 | G12: =E12+F12 -> 2 | H12: =E12*SUM('Pod Library'!$J$31:$J$40)+F12*SUM('Pod Library'!$J$43:$J$54) -> 14.285714
D13: Year 2 total | E13: =SUM(E10:E12) -> 7 | F13: =SUM(F10:F12) -> 2 | G13: =SUM(G10:G12) -> 9 | H13: =SUM(H10:H12) -> 71.5
B15: 3 | C15: AMP | D15: Annuity ＆ Maturity Payment | E15: 5 | F15: 0 | G15: =E15+F15 -> 5 | H15: =E15*SUM('Pod Library'!$J$57:$J$66) -> 31.944444
B16: 3 | C16: CPA | D16: Claims Processing & Adjudication | E16: 2 | F16: 0 | G16: =E16+F16 -> 2 | H16: =E16*SUM('Pod Library'!$J$57:$J$66) -> 12.777778
B17: 3 | C17: CSS | D17: Claims Support Services | E17: 2 | F17: 0 | G17: =E17+F17 -> 2 | H17: =E17*SUM('Pod Library'!$J$57:$J$66) -> 12.777778
D18: Year 3 total | E18: =SUM(E15:E17) -> 9 | F18: =SUM(F15:F17) -> 0 | G18: =SUM(G15:G17) -> 9 | H18: =SUM(H15:H17) -> 57.5
B20: 4 | C20: AMP | D20: Annuity ＆ Maturity Payment | E20: 5 | F20: 0 | G20: =E20+F20 -> 5 | H20: =E20*SUM('Pod Library'!$J$69:$J$78) -> 26.666667
B21: 4 | C21: CPA | D21: Claims Processing & Adjudication | E21: 2 | F21: 0 | G21: =E21+F21 -> 2 | H21: =E21*SUM('Pod Library'!$J$69:$J$78) -> 10.666667
B22: 4 | C22: CSS | D22: Claims Support Services | E22: 2 | F22: 0 | G22: =E22+F22 -> 2 | H22: =E22*SUM('Pod Library'!$J$69:$J$78) -> 10.666667
D23: Year 4 total | E23: =SUM(E20:E22) -> 9 | F23: =SUM(F20:F22) -> 0 | G23: =SUM(G20:G22) -> 9 | H23: =SUM(H20:H22) -> 48
B25: 5 | C25: AMP | D25: Annuity ＆ Maturity Payment | E25: 4 | F25: 0 | G25: =E25+F25 -> 4 | H25: =E25*SUM('Pod Library'!$J$81:$J$90) -> 19
B26: 5 | C26: CPA | D26: Claims Processing & Adjudication | E26: 2 | F26: 0 | G26: =E26+F26 -> 2 | H26: =E26*SUM('Pod Library'!$J$81:$J$90) -> 9.5
B27: 5 | C27: CSS | D27: Claims Support Services | E27: 2 | F27: 0 | G27: =E27+F27 -> 2 | H27: =E27*SUM('Pod Library'!$J$81:$J$90) -> 9.5
D28: Year 5 total | E28: =SUM(E25:E27) -> 8 | F28: =SUM(F25:F27) -> 0 | G28: =SUM(G25:G27) -> 8 | H28: =SUM(H25:H27) -> 38

Sheet Horizontal Teams
A1: Horizontal teams — work that is not stream-bounded
A2: INPUT, defined per year rather than scaled, because the partner share and the sourcing mix inside the horizontal layer both change as the estate transitions.
B4: Year | C4: Team | D4: Role | E4: Role detail | F4: Exp | G4: Loc | H4: Sourcing | I4: Count | J4: People in the block
B5: 1 | C5: H1 | D5: PM | E5: Service Delivery Manager | F5: E5 | G5: ON | H5: FTC | I5: 1 | J5: =I5 -> 1
B6: 1 | C6: H1 | D6: MNT | E6: Incident & Problem Analyst | F6: E3 | G6: ON | H6: FTC | I6: 2 | J6: =I6 -> 2
B7: 1 | C7: H1 | D7: MNT | E7: L2 Application Support | F7: E2 | G7: OFF | H7: FTC | I7: 0.5 | J7: =I7 -> 0.5
B8: 1 | C8: H1 | D8: MNT | E8: L2 Application Support | F8: E2 | G8: NEAR | H8: FTC | I8: 0.5 | J8: =I8 -> 0.5
B9: 1 | C9: H1 | D9: OTH | E9: Observability / AIOps Engineer | F9: E3 | G9: OFF | H9: FTC | I9: 0.5 | J9: =I9 -> 0.5
B10: 1 | C10: H1 | D10: MNT | E10: MetLife Operations Lead | F10: E4 | G10: ON | H10: FTE | I10: 2.5 | J10: =I10 -> 2.5
B11: 1 | C11: H2 | D11: TEST | E11: Quality Lead | F11: E4 | G11: ON | H11: FTC | I11: 0.5 | J11: =I11 -> 0.5
B12: 1 | C12: H2 | D12: TEST | E12: Test Automation Engineer | F12: E3 | G12: OFF | H12: FTC | I12: 0.5 | J12: =I12 -> 0.5
B13: 1 | C13: H2 | D13: TEST | E13: Performance & Batch Test Engineer | F13: E3 | G13: OFF | H13: FTC | I13: 0.5 | J13: =I13 -> 0.5
B14: 1 | C14: H2 | D14: TEST | E14: MGCC Quality Engineer | F14: E2 | G14: OFF | H14: MGCC | I14: 3 | J14: =I14 -> 3
B15: 1 | C15: H2 | D15: BSA | E15: Payments Assurance Analyst | F15: E3 | G15: ON | H15: FTC | I15: 1.5 | J15: =I15 -> 1.5
B16: 1 | C16: H3 | D16: OTH | E16: Domain Solution Architect | F16: E5 | G16: ON | H16: FTC | I16: 0.5 | J16: =I16 -> 0.5
... B23: 1 | C23: H3 | D23: DEV | E23: MGCC Engineering Lead | F23: E4 | G23: OFF | H23: MGCC | I23: 1.5 | J23: =I23 -> 1.5
E24: Year 1 horizontal total | I24: =SUM(I5:I23) -> 21.5
B26: 2 | C26: H1 | D26: PM | E26: Service Delivery Manager | F26: E5 | G26: ON | H26: FTC | I26: 0.5 | J26: =I26 -> 0.5
B27: 2 | C27: H1 | D27: MNT | E27: Incident & Problem Analyst | F27: E3 | G27: ON | H27: FTC | I27: 1 | J27: =I27 -> 1
B28: 2 | C28: H1 | D28: MNT | E28: L2 Application Support | F28: E2 | G28: OFF | H28: FTC | I28: 0.5 | J28: =I28 -> 0.5
B29: 2 | C29: H1 | D29: MNT | E29: L2 Application Support | F29: E2 | G29: NEAR | H29: FTC | I29: 0.5 | J29: =I29 -> 0.5
B30: 2 | C30: H1 | D30: OTH | E30: Observability / AIOps Engineer | F30: E3 | G30: OFF | H30: FTC | I30: 1.5 | J30: =I30 -> 1.5
B31: 2 | C31: H1 | D31: MNT | E31: MetLife Operations Lead | F31: E4 | G31: ON | H31: FTE | I31: 2 | J31: =I31 -> 2
B32: 2 | C32: H2 | D32: TEST | E32: Quality Lead | F32: E4 | G32: ON | H32: FTC | I32: 1.5 | J32: =I32 -> 1.5
B33: 2 | C33: H2 | D33: TEST | E33: Test Automation Engineer | F33: E3 | G33: OFF | H33: FTC | I33: 2 | J33: =I33 -> 2
B34: 2 | C34: H2 | D34: TEST | E34: Performance & Batch Test Engineer | F34: E3 | G34: OFF | H34: FTC | I34: 0.5 | J34: =I34 -> 0.5
B35: 2 | C35: H2 | D35: TEST | E35: MGCC Quality Engineer | F35: E2 | G35: OFF | H35: MGCC | I35: 2 | J35: =I35 -> 2
B36: 2 | C36: H2 | D36: BSA | E36: Payments Assurance Analyst | F36: E3 | G36: ON | H36: FTC | I36: 2 | J36: =I36 -> 2
B37: 2 | C37: H3 | D37: OTH | E37: Domain Solution Architect | F37: E5 | G37: ON | H37: FTC | I37: 0.5 | J37: =I37 -> 0.5
... B44: 2 | C44: H3 | D44: DEV | E44: MGCC Engineering Lead | F44: E4 | G44: OFF | H44: MGCC | I44: 0.5 | J44: =I44 -> 0.5
E45: Year 2 horizontal total | I45: =SUM(I26:I44) -> 22
B47: 3 | C47: H1 | D47: PM | E47: Service Delivery Manager | F47: E5 | G47: ON | H47: FTC | I47: 0.5 | J47: =I47 -> 0.5
B48: 3 | C48: H1 | D48: MNT | E48: Incident & Problem Analyst | F48: E3 | G48: ON | H48: FTC | I48: 0.5 | J48: =I48 -> 0.5
B49: 3 | C49: H1 | D49: MNT | E49: L2 Application Support | F49: E2 | G49: OFF | H49: FTC | I49: 2.5 | J49: =I49 -> 2.5
B50: 3 | C50: H1 | D50: MNT | E50: L2 Application Support | F50: E2 | G50: NEAR | H50: FTC | I50: 1 | J50: =I50 -> 1
B51: 3 | C51: H1 | D51: OTH | E51: Observability / AIOps Engineer | F51: E3 | G51: OFF | H51: FTC | I51: 1.5 | J51: =I51 -> 1.5
B52: 3 | C52: H1 | D52: MNT | E52: MetLife Operations Lead | F52: E4 | G52: ON | H52: FTE | I52: 0.5 | J52: =I52 -> 0.5
B53: 3 | C53: H2 | D53: TEST | E53: Quality Lead | F53: E4 | G53: ON | H53: FTC | I53: 1 | J53: =I53 -> 1
B54: 3 | C54: H2 | D54: TEST | E54: Test Automation Engineer | F54: E3 | G54: OFF | H54: FTC | I54: 0.5 | J54: =I54 -> 0.5
B55: 3 | C55: H2 | D55: TEST | E55: Performance & Batch Test Engineer | F55: E3 | G55: OFF | H55: FTC | I55: 0.5 | J55: =I55 -> 0.5
B56: 3 | C56: H2 | D56: TEST | E56: MGCC Quality Engineer | F56: E2 | G56: OFF | H56: MGCC | I56: 0.5 | J56: =I56 -> 0.5
B57: 3 | C57: H2 | D57: BSA | E57: Payments Assurance Analyst | F57: E3 | G57: ON | H57: FTC | I57: 4 | J57: =I57 -> 4
B58: 3 | C58: H3 | D58: OTH | E58: Domain Solution Architect | F58: E5 | G58: ON | H58: FTC | I58: 0.5 | J58: =I58 -> 0.5
... B65: 3 | C65: H3 | D65: DEV | E65: MGCC Engineering Lead | F65: E4 | G65: OFF | H65: MGCC | I65: 1 | J65: =I65 -> 1
E66: Year 3 horizontal total | I66: =SUM(I47:I65) -> 18.5
B68: 4 | C68: H1 | D68: PM | E68: Service Delivery Manager | F68: E5 | G68: ON | H68: FTC | I68: 0.5 | J68: =I68 -> 0.5
B69: 4 | C69: H1 | D69: MNT | E69: Incident & Problem Analyst | F69: E3 | G69: ON | H69: FTC | I69: 0.5 | J69: =I69 -> 0.5
B70: 4 | C70: H1 | D70: MNT | E70: L2 Application Support | F70: E2 | G70: OFF | H70: FTC | I70: 0.5 | J70: =I70 -> 0.5
B71: 4 | C71: H1 | D71: MNT | E71: L2 Application Support | F71: E2 | G71: NEAR | H71: FTC | I71: 0.5 | J71: =I71 -> 0.5
B72: 4 | C72: H1 | D72: OTH | E72: Observability / AIOps Engineer | F72: E3 | G72: OFF | H72: FTC | I72: 0.5 | J72: =I72 -> 0.5
B73: 4 | C73: H1 | D73: MNT | E73: MetLife Operations Lead | F73: E4 | G73: ON | H73: FTE | I73: 2.5 | J73: =I73 -> 2.5
B74: 4 | C74: H2 | D74: TEST | E74: Quality Lead | F74: E4 | G74: ON | H74: FTC | I74: 0.5 | J74: =I74 -> 0.5
B75: 4 | C75: H2 | D75: TEST | E75: Test Automation Engineer | F75: E3 | G75: OFF | H75: FTC | I75: 0.5 | J75: =I75 -> 0.5
B76: 4 | C76: H2 | D76: TEST | E76: Performance & Batch Test Engineer | F76: E3 | G76: OFF | H76: FTC | I76: 0.5 | J76: =I76 -> 0.5
B77: 4 | C77: H2 | D77: TEST | E77: MGCC Quality Engineer | F77: E2 | G77: OFF | H77: MGCC | I77: 4 | J77: =I77 -> 4
B78: 4 | C78: H2 | D78: BSA | E78: Payments Assurance Analyst | F78: E3 | G78: ON | H78: FTC | I78: 0.5 | J78: =I78 -> 0.5
B79: 4 | C79: H3 | D79: OTH | E79: Domain Solution Architect | F79: E5 | G79: ON | H79: FTC | I79: 0.5 | J79: =I79 -> 0.5
... B86: 4 | C86: H3 | D86: DEV | E86: MGCC Engineering Lead | F86: E4 | G86: OFF | H86: MGCC | I86: 1 | J86: =I86 -> 1
E87: Year 4 horizontal total | I87: =SUM(I68:I86) -> 17.5
B89: 5 | C89: H1 | D89: PM | E89: Service Delivery Manager | F89: E5 | G89: ON | H89: FTC | I89: 0.5 | J89: =I89 -> 0.5
B90: 5 | C90: H1 | D90: MNT | E90: Incident & Problem Analyst | F90: E3 | G90: ON | H90: FTC | I90: 1 | J90: =I90 -> 1
B91: 5 | C91: H1 | D91: MNT | E91: L2 Application Support | F91: E2 | G91: OFF | H91: FTC | I91: 0.5 | J91: =I91 -> 0.5
B92: 5 | C92: H1 | D92: MNT | E92: L2 Application Support | F92: E2 | G92: NEAR | H92: FTC | I92: 0.5 | J92: =I92 -> 0.5
B93: 5 | C93: H1 | D93: OTH | E93: Observability / AIOps Engineer | F93: E3 | G93: OFF | H93: FTC | I93: 0.5 | J93: =I93 -> 0.5
B94: 5 | C94: H1 | D94: MNT | E94: MetLife Operations Lead | F94: E4 | G94: ON | H94: FTE | I94: 3 | J94: =I94 -> 3
B95: 5 | C95: H2 | D95: TEST | E95: Quality Lead | F95: E4 | G95: ON | H95: FTC | I95: 0.5 | J95: =I95 -> 0.5
B96: 5 | C96: H2 | D96: TEST | E96: Test Automation Engineer | F96: E3 | G96: OFF | H96: FTC | I96: 0.5 | J96: =I96 -> 0.5
B97: 5 | C97: H2 | D97: TEST | E97: Performance & Batch Test Engineer | F97: E3 | G97: OFF | H97: FTC | I97: 0.5 | J97: =I97 -> 0.5
B98: 5 | C98: H2 | D98: TEST | E98: MGCC Quality Engineer | F98: E2 | G98: OFF | H98: MGCC | I98: 1 | J98: =I98 -> 1
B99: 5 | C99: H2 | D99: BSA | E99: Payments Assurance Analyst | F99: E3 | G99: ON | H99: FTC | I99: 0.5 | J99: =I99 -> 0.5
B100: 5 | C100: H3 | D100: OTH | E100: Domain Solution Architect | F100: E5 | G100: ON | H100: FTC | I100: 1 | J100: =I100 -> 1
... B107: 5 | C107: H3 | D107: DEV | E107: MGCC Engineering Lead | F107: E4 | G107: OFF | H107: MGCC | I107: 6 | J107: =I107 -> 6
E108: Year 5 horizontal total | I108: =SUM(I89:I107) -> 21.5
B110: H1 is sized from the incident and change load on the AMS sheet — 732 incidents and 1,161 changes a year, of which only 4 are P1/P2. H2 is the platform and API assurance function; it is substantial here because Appendix 3 records 24.0 tester units, a quarter of the vendor population. H3 carries the architecture and enablement seats that the restatement created.

Sheet Team Build-Up
A1: Team build-up — and the Year-1 reconciliation to Appendix 3 v5
A2: Nothing on this sheet is typed. Section B is the test that matters: the roster has to be the client's own Year-1 position on effort, sourcing, location AND role.
A4: A. HEADCOUNT
B5: Measure | C5: Year 1 | D5: Year 2 | E5: Year 3 | F5: Year 4 | G5: Year 5
B6: People in agile pods | C6: =SUMIFS('Seat Ledger'!$M$5:$M$287,'Seat Ledger'!$B$5:$B$287,1,'Seat Ledger'!$C$5:$C$287,"POD") -> 24 | D6: =SUMIFS('Seat Ledger'!$M$5:$M$287,'Seat Ledger'!$B$5:$B$287,2,'Seat Ledger'!$C$5:$C$287,"POD") -> 50 | E6: =SUMIFS('Seat Ledger'!$M$5:$M$287,'Seat Ledger'!$B$5:$B$287,3,'Seat Ledger'!$C$5:$C$287,"POD") -> 57.5 | F6: =SUMIFS('Seat Ledger'!$M$5:$M$287,'Seat Ledger'!$B$5:$B$287,4,'Seat Ledger'!$C$5:$C$287,"POD") -> 48 | G6: =SUMIFS('Seat Ledger'!$M$5:$M$287,'Seat Ledger'!$B$5:$B$287,5,'Seat Ledger'!$C$5:$C$287,"POD") -> 38
B7: People in waterfall / hybrid teams | C7: =SUMIFS('Seat Ledger'!$M$5:$M$287,'Seat Ledger'!$B$5:$B$287,1,'Seat Ledger'!$C$5:$C$287,"TEAM") -> 76 | D7: =SUMIFS('Seat Ledger'!$M$5:$M$287,'Seat Ledger'!$B$5:$B$287,2,'Seat Ledger'!$C$5:$C$287,"TEAM") -> 21.5 | E7: =SUMIFS('Seat Ledger'!$M$5:$M$287,'Seat Ledger'!$B$5:$B$287,3,'Seat Ledger'!$C$5:$C$287,"TEAM") -> 0 | F7: =SUMIFS('Seat Ledger'!$M$5:$M$287,'Seat Ledger'!$B$5:$B$287,4,'Seat Ledger'!$C$5:$C$287,"TEAM") -> 0 | G7: =SUMIFS('Seat Ledger'!$M$5:$M$287,'Seat Ledger'!$B$5:$B$287,5,'Seat Ledger'!$C$5:$C$287,"TEAM") -> 0
B8: People in horizontal teams | C8: =SUMIFS('Seat Ledger'!$M$5:$M$287,'Seat Ledger'!$B$5:$B$287,1,'Seat Ledger'!$C$5:$C$287,"HZ") -> 21.5 | D8: =SUMIFS('Seat Ledger'!$M$5:$M$287,'Seat Ledger'!$B$5:$B$287,2,'Seat Ledger'!$C$5:$C$287,"HZ") -> 22 | E8: =SUMIFS('Seat Ledger'!$M$5:$M$287,'Seat Ledger'!$B$5:$B$287,3,'Seat Ledger'!$C$5:$C$287,"HZ") -> 18.5 | F8: =SUMIFS('Seat Ledger'!$M$5:$M$287,'Seat Ledger'!$B$5:$B$287,4,'Seat Ledger'!$C$5:$C$287,"HZ") -> 17.5 | G8: =SUMIFS('Seat Ledger'!$M$5:$M$287,'Seat Ledger'!$B$5:$B$287,5,'Seat Ledger'!$C$5:$C$287,"HZ") -> 21.5
B9: TOTAL PEOPLE | C9: =SUM(C6:C8) -> 121.5 | D9: =SUM(D6:D8) -> 93.5 | E9: =SUM(E6:E8) -> 76 | F9: =SUM(F6:F8) -> 65.5 | G9: =SUM(G6:G8) -> 59.5
B10: Delivery units — pods / teams | C10: ='Delivery Mode'!C19&" / "&'Delivery Mode'!C21 -> 4 / 5 | D10: ='Delivery Mode'!D19&" / "&'Delivery Mode'!D21 -> 7 / 2 | E10: ='Delivery Mode'!E19&" / "&'Delivery Mode'!E21 -> 9 / 0 | F10: ='Delivery Mode'!F19&" / "&'Delivery Mode'!F21 -> 9 / 0 | G10: ='Delivery Mode'!G19&" / "&'Delivery Mode'!G21 -> 8 / 0
B11: Headcount target from the Logic Tree | C11: ='Logic Tree'!C53 -> 121.5735 | D11: ='Logic Tree'!D53 -> 93.597752 | E11: ='Logic Tree'!E53 -> 75.882019 | F11: ='Logic Tree'!F53 -> 65.436744 | G11: ='Logic Tree'!G53 -> 59.318835
B12: Variance to target | C12: =C9-C11 -> -0.0735 | D12: =D9-D11 -> -0.097752193 | E12: =E9-E11 -> 0.11798058 | F12: =F9-F11 -> 0.063256079 | G12: =G9-G11 -> 0.1811651
A14: B. YEAR-1 RECONCILIATION TO APPENDIX 3 v3
B15: Measure | C15: Model Year 1 | D15: Appendix 3 v5 | E15: Variance | H15: Reading
B16: Total effort / people | C16: =C9 -> 121.5 | D16: ='Logic Tree'!C7 -> 121.5735 | E16: =C16-D16 -> -0.0735 | H16: Whole-domain size. Unchanged since v2.
B17: FTC reported (Capgemini + partner) | C17: =SUMIFS('Seat Ledger'!$M$5:$M$287,'Seat Ledger'!$B$5:$B$287,1,'Seat Ledger'!$J$5:$J$287,"FTC")+SUMIFS('Seat Ledger'!$M$5:$M$287,'Seat Ledger'!$B$5:$B$287,1,'Seat Ledger'!$J$5:$J$287,"PT") -> 85 | D17: ='Logic Tree'!C8 -> 85.4485 | E17: =C17-D17 -> -0.4485 | H17: Appendix 3 reports the vendor as one number. This is the line that has to reconcile.
B18: — of which Capgemini payroll | C18: =SUMIFS('Seat Ledger'!$M$5:$M$287,'Seat Ledger'!$B$5:$B$287,1,'Seat Ledger'!$J$5:$J$287,"FTC") -> 85 | D18: — | E18: — | H18: Transferable at the end of Year 3.
B19: — of which named sub-contractor | C19: =SUMIFS('Seat Ledger'!$M$5:$M$287,'Seat Ledger'!$B$5:$B$287,1,'Seat Ledger'!$J$5:$J$287,"PT") -> 0 | D19: — | E19: — | H19: Zero in this 領域. The row is live so a sub-contract found in due diligence can be priced.
B20: MetLife Japan FTE | C20: =SUMIFS('Seat Ledger'!$M$5:$M$287,'Seat Ledger'!$B$5:$B$287,1,'Seat Ledger'!$J$5:$J$287,"FTE") -> 14 | D20: ='Logic Tree'!C9 -> 13.4792 | E20: =C20-D20 -> 0.5208 | H20: Product owners, domain SMEs and application owners.
B21: MetLife MGCC | C21: =SUMIFS('Seat Ledger'!$M$5:$M$287,'Seat Ledger'!$B$5:$B$287,1,'Seat Ledger'!$J$5:$J$287,"MGCC") -> 22.5 | D21: ='Logic Tree'!C10 -> 22.6458 | E21: =C21-D21 -> -0.1458 | H21: 15.99 units on day one — MGCC is already the second largest sourcing pool in this domain.
B22: Vendor onshore Tokyo | C22: =SUMIFS('Seat Ledger'!$M$5:$M$287,'Seat Ledger'!$B$5:$B$287,1,'Seat Ledger'!$J$5:$J$287,"FTC",'Seat Ledger'!$I$5:$I$287,"ON")+SUMIFS('Seat Ledger'!$M$5:$M$287,'Seat Ledger'!$B$5:$B$287,1,'Seat Ledger'!$J$5:$J$287,"PT",'Seat Ledger'!$I$5:$I$287,"ON") -> 71 | D22: ='Logic Tree'!C11 -> 71.6261 | E22: =C22-D22 -> -0.6261 | H22: MEASURED, not assumed.
B23: Vendor nearshore | C23: =SUMIFS('Seat Ledger'!$M$5:$M$287,'Seat Ledger'!$B$5:$B$287,1,'Seat Ledger'!$J$5:$J$287,"FTC",'Seat Ledger'!$I$5:$I$287,"NEAR")+SUMIFS('Seat Ledger'!$M$5:$M$287,'Seat Ledger'!$B$5:$B$287,1,'Seat Ledger'!$J$5:$J$287,"PT",'Seat Ledger'!$I$5:$I$287,"NEAR") -> 9.5 | D23: ='Logic Tree'!C13 -> 9.589 | E23: =C23-D23 -> -0.089 | H23: Zero. There is no nearshore capacity in this 領域.
B24: Vendor offshore | C24: =SUMIFS('Seat Ledger'!$M$5:$M$287,'Seat Ledger'!$B$5:$B$287,1,'Seat Ledger'!$J$5:$J$287,"FTC",'Seat Ledger'!$I$5:$I$287,"OFF")+SUMIFS('Seat Ledger'!$M$5:$M$287,'Seat Ledger'!$B$5:$B$287,1,'Seat Ledger'!$J$5:$J$287,"PT",'Seat Ledger'!$I$5:$I$287,"OFF") -> 4.5 | D24: ='Logic Tree'!C12 -> 4.2333 | E24: =C24-D24 -> 0.2667 | H24: 28.87 units already offshore — 44% of the Capgemini population on day one. MGCC is excluded: it is MetLife's.
B25: Role — BSA | C25: =SUMIFS('Seat Ledger'!$M$5:$M$287,'Seat Ledger'!$B$5:$B$287,1,'Seat Ledger'!$J$5:$J$287,"FTC",'Seat Ledger'!$G$5:$G$287,"BSA")+SUMIFS('Seat Ledger'!$M$5:$M$287,'Seat Ledger'!$B$5:$B$287,1,'Seat Ledger'!$J$5:$J$287,"PT",'Seat Ledger'!$G$5:$G$287,"BSA") -> 5.5 | D25: ='Logic Tree'!C15 -> 5.9583 | E25: =C25-D25 -> -0.4583 | H25: Reconciles.
B26: Role — Developer | C26: =SUMIFS('Seat Ledger'!$M$5:$M$287,'Seat Ledger'!$B$5:$B$287,1,'Seat Ledger'!$J$5:$J$287,"FTC",'Seat Ledger'!$G$5:$G$287,"DEV")+SUMIFS('Seat Ledger'!$M$5:$M$287,'Seat Ledger'!$B$5:$B$287,1,'Seat Ledger'!$J$5:$J$287,"PT",'Seat Ledger'!$G$5:$G$287,"DEV") -> 61 | D26: ='Logic Tree'!C16 -> 70.8985 | E26: =C26-D26 -> -9.8985 | H26: As reported. 66% of the vendor population.
B27: Role — Tester | C27: =SUMIFS('Seat Ledger'!$M$5:$M$287,'Seat Ledger'!$B$5:$B$287,1,'Seat Ledger'!$J$5:$J$287,"FTC",'Seat Ledger'!$G$5:$G$287,"TEST")+SUMIFS('Seat Ledger'!$M$5:$M$287,'Seat Ledger'!$B$5:$B$287,1,'Seat Ledger'!$J$5:$J$287,"PT",'Seat Ledger'!$G$5:$G$287,"TEST") -> 7.5 | D27: ='Logic Tree'!C17 -> 6.8167 | E27: =C27-D27 -> 0.6833 | H27: As reported. The lowest tester share in the portfolio, at 7.9%.
B28: Role — Maintenance | C28: =SUMIFS('Seat Ledger'!$M$5:$M$287,'Seat Ledger'!$B$5:$B$287,1,'Seat Ledger'!$J$5:$J$287,"FTC",'Seat Ledger'!$G$5:$G$287,"MNT")+SUMIFS('Seat Ledger'!$M$5:$M$287,'Seat Ledger'!$B$5:$B$287,1,'Seat Ledger'!$J$5:$J$287,"PT",'Seat Ledger'!$G$5:$G$287,"MNT") -> 3 | D28: ='Logic Tree'!C18 -> 1 | E28: =C28-D28 -> 2 | H28: As reported by MetLife and used unchanged.
B29: Role — PM | C29: =SUMIFS('Seat Ledger'!$M$5:$M$287,'Seat Ledger'!$B$5:$B$287,1,'Seat Ledger'!$J$5:$J$287,"FTC",'Seat Ledger'!$G$5:$G$287,"PM")+SUMIFS('Seat Ledger'!$M$5:$M$287,'Seat Ledger'!$B$5:$B$287,1,'Seat Ledger'!$J$5:$J$287,"PT",'Seat Ledger'!$G$5:$G$287,"PM") -> 4.5 | D29: ='Logic Tree'!C19 -> 0 | E29: =C29-D29 -> 4.5 | H29: As reported. Thin at 2.2%, but populated.
B30: Role — Other | C30: =SUMIFS('Seat Ledger'!$M$5:$M$287,'Seat Ledger'!$B$5:$B$287,1,'Seat Ledger'!$J$5:$J$287,"FTC",'Seat Ledger'!$G$5:$G$287,"OTH")+SUMIFS('Seat Ledger'!$M$5:$M$287,'Seat Ledger'!$B$5:$B$287,1,'Seat Ledger'!$J$5:$J$287,"PT",'Seat Ledger'!$G$5:$G$287,"OTH") -> 3.5 | D30: ='Logic Tree'!C20 -> 0.775 | E30: =C30-D30 -> 2.725 | H30: As reported. Architecture and enablement.
B31: Largest variance across every reconciling line | E31: =MAX(ABS(E16),ABS(E17),ABS(E20),ABS(E21),ABS(E22),ABS(E23),ABS(E24),ABS(E25),ABS(E26),ABS(E27),ABS(E28),ABS(E29),ABS(E30)) -> 9.8985 | G31: Appendix 3 v5 is internally consistent for all ten applications in this 領域: every Total equals its FTC + FTE + MGCC, and every location line sums to the vendor number. There is no unallocated capacity to carry.
B32: Largest variance excluding the MetLife FTE line (twelve lines) | E32: =MAX(ABS(E16),ABS(E17),ABS(E21),ABS(E22),ABS(E23),ABS(E24),ABS(E25),ABS(E26),ABS(E27),ABS(E28),ABS(E29),ABS(E30)) -> 9.8985 | G32: Every line — effort, vendor total, MetLife FTE, MGCC, both locations and all six client role lines — reconciles to within a few hundredths of a person after head-grid quantisation.
A33: C. THE ROLE LINE — used exactly as MetLife reports it
B34: Role | C34: Appendix 3 v5 | D34: This model | E34: Difference | H34: Note
B35: BSA | C35: ='Logic Tree'!C15 -> 5.9583 | D35: =C25 -> 5.5 | E35: =D35-C35 -> -0.4583 | H35: 8.6% of the vendor population. Thin, and consistent with platform work where the requirement comes from the consuming 領域, not from here.
B36: Developer | C36: ='Logic Tree'!C16 -> 70.8985 | D36: =C26 -> 61 | E36: =D36-C36 -> -9.8985 | H36: 53.7% after restatement, against 64.5% as MetLife reports it. Platform and API engineering.
B37: Tester | C37: ='Logic Tree'!C17 -> 6.8167 | D37: =C27 -> 7.5 | E37: =D37-C37 -> 0.6833 | H37: 24.5% — the highest tester share of the five modelled 領域. A shared platform breaks everything downstream when it regresses, and the role line reflects that.
B38: Maintenance | C38: ='Logic Tree'!C18 -> 1 | D38: =C28 -> 3 | E38: =D38-C38 -> 2 | H38: RESTATED to 4.50 from 1.00. One person of run against 732 incidents a year is a coding convention, not a plan.
B39: PM | C39: ='Logic Tree'!C19 -> 0 | D39: =C29 -> 4.5 | E39: =D39-C39 -> 4.5 | H39: RESTATED to 4.00 from 1.30. Two value streams and eighteen pods at peak cannot be run on 1.3 units.
B40: Other | C40: ='Logic Tree'!C20 -> 0.775 | D40: =C30 -> 3.5 | E40: =D40-C40 -> 2.725 | H40: RESTATED to 3.00 from 0.08. Architecture and enablement on the platform every other 領域 consumes.
B41: Sum of the six role lines | C41: =SUM(C35:C40) -> 85.4485 | D41: =SUM(D35:D40) -> 85 | E41: =D41-C41 -> -0.4485 | H41: THREE LINES RESTATED, ARITHMETICALLY NEUTRAL. MetLife reports 1.03 maintenance, 1.30 PM and 0.08 architecture across six applications carrying 732 incidents and 1,161 changes a year. We move 10.58 units out of Developer into Maintenance, PM and Other. The total does not change by a single unit, and the restatement goes back to MetLife as a clarification question.
A43: D. SOURCING, LOCATION AND THE THREE OFFSHORE BASES
B44: Measure | C44: Year 1 | D44: Year 2 | E44: Year 3 | F44: Year 4 | G44: Year 5
B45: Capgemini payroll (FTC) | C45: =SUMIFS('Seat Ledger'!$M$5:$M$287,'Seat Ledger'!$B$5:$B$287,1,'Seat Ledger'!$J$5:$J$287,"FTC") -> 85 | D45: =SUMIFS('Seat Ledger'!$M$5:$M$287,'Seat Ledger'!$B$5:$B$287,2,'Seat Ledger'!$J$5:$J$287,"FTC") -> 64 | E45: =SUMIFS('Seat Ledger'!$M$5:$M$287,'Seat Ledger'!$B$5:$B$287,3,'Seat Ledger'!$J$5:$J$287,"FTC") -> 51 | F45: =SUMIFS('Seat Ledger'!$M$5:$M$287,'Seat Ledger'!$B$5:$B$287,4,'Seat Ledger'!$J$5:$J$287,"FTC") -> 34.5 | G45: =SUMIFS('Seat Ledger'!$M$5:$M$287,'Seat Ledger'!$B$5:$B$287,5,'Seat Ledger'!$J$5:$J$287,"FTC") -> 30
B46: Incumbent partner (PT) | C46: =SUMIFS('Seat Ledger'!$M$5:$M$287,'Seat Ledger'!$B$5:$B$287,1,'Seat Ledger'!$J$5:$J$287,"PT") -> 0 | D46: =SUMIFS('Seat Ledger'!$M$5:$M$287,'Seat Ledger'!$B$5:$B$287,2,'Seat Ledger'!$J$5:$J$287,"PT") -> 0 | E46: =SUMIFS('Seat Ledger'!$M$5:$M$287,'Seat Ledger'!$B$5:$B$287,3,'Seat Ledger'!$J$5:$J$287,"PT") -> 0 | F46: =SUMIFS('Seat Ledger'!$M$5:$M$287,'Seat Ledger'!$B$5:$B$287,4,'Seat Ledger'!$J$5:$J$287,"PT") -> 0 | G46: =SUMIFS('Seat Ledger'!$M$5:$M$287,'Seat Ledger'!$B$5:$B$287,5,'Seat Ledger'!$J$5:$J$287,"PT") -> 0
B47: VENDOR TOTAL = Appendix 3 FTC | C47: =C45+C46 -> 85 | D47: =D45+D46 -> 64 | E47: =E45+E46 -> 51 | F47: =F45+F46 -> 34.5 | G47: =G45+G46 -> 30
B48: MetLife Japan (FTE) | C48: =SUMIFS('Seat Ledger'!$M$5:$M$287,'Seat Ledger'!$B$5:$B$287,1,'Seat Ledger'!$J$5:$J$287,"FTE") -> 14 | D48: =SUMIFS('Seat Ledger'!$M$5:$M$287,'Seat Ledger'!$B$5:$B$287,2,'Seat Ledger'!$J$5:$J$287,"FTE") -> 11.5 | E48: =SUMIFS('Seat Ledger'!$M$5:$M$287,'Seat Ledger'!$B$5:$B$287,3,'Seat Ledger'!$J$5:$J$287,"FTE") -> 10 | F48: =SUMIFS('Seat Ledger'!$M$5:$M$287,'Seat Ledger'!$B$5:$B$287,4,'Seat Ledger'!$J$5:$J$287,"FTE") -> 15 | G48: =SUMIFS('Seat Ledger'!$M$5:$M$287,'Seat Ledger'!$B$5:$B$287,5,'Seat Ledger'!$J$5:$J$287,"FTE") -> 14
B49: MetLife MGCC | C49: =SUMIFS('Seat Ledger'!$M$5:$M$287,'Seat Ledger'!$B$5:$B$287,1,'Seat Ledger'!$J$5:$J$287,"MGCC") -> 22.5 | D49: =SUMIFS('Seat Ledger'!$M$5:$M$287,'Seat Ledger'!$B$5:$B$287,2,'Seat Ledger'!$J$5:$J$287,"MGCC") -> 18 | E49: =SUMIFS('Seat Ledger'!$M$5:$M$287,'Seat Ledger'!$B$5:$B$287,3,'Seat Ledger'!$J$5:$J$287,"MGCC") -> 15 | F49: =SUMIFS('Seat Ledger'!$M$5:$M$287,'Seat Ledger'!$B$5:$B$287,4,'Seat Ledger'!$J$5:$J$287,"MGCC") -> 16 | G49: =SUMIFS('Seat Ledger'!$M$5:$M$287,'Seat Ledger'!$B$5:$B$287,5,'Seat Ledger'!$J$5:$J$287,"MGCC") -> 15.5
B50: RATIO — vendor share | C50: =IF(C9=0,0,C47/C9) -> 0.69958848 | D50: =IF(D9=0,0,D47/D9) -> 0.68449198 | E50: =IF(E9=0,0,E47/E9) -> 0.67105263 | F50: =IF(F9=0,0,F47/F9) -> 0.52671756 | G50: =IF(G9=0,0,G47/G9) -> 0.50420168
B51: Onshore Tokyo | C51: =SUMIFS('Seat Ledger'!$M$5:$M$287,'Seat Ledger'!$B$5:$B$287,1,'Seat Ledger'!$I$5:$I$287,"ON") -> 85 | D51: =SUMIFS('Seat Ledger'!$M$5:$M$287,'Seat Ledger'!$B$5:$B$287,2,'Seat Ledger'!$I$5:$I$287,"ON") -> 55.5 | E51: =SUMIFS('Seat Ledger'!$M$5:$M$287,'Seat Ledger'!$B$5:$B$287,3,'Seat Ledger'!$I$5:$I$287,"ON") -> 38.5 | F51: =SUMIFS('Seat Ledger'!$M$5:$M$287,'Seat Ledger'!$B$5:$B$287,4,'Seat Ledger'!$I$5:$I$287,"ON") -> 29 | G51: =SUMIFS('Seat Ledger'!$M$5:$M$287,'Seat Ledger'!$B$5:$B$287,5,'Seat Ledger'!$I$5:$I$287,"ON") -> 23.5
B52: Offshore | C52: =SUMIFS('Seat Ledger'!$M$5:$M$287,'Seat Ledger'!$B$5:$B$287,1,'Seat Ledger'!$I$5:$I$287,"OFF") -> 27 | D52: =SUMIFS('Seat Ledger'!$M$5:$M$287,'Seat Ledger'!$B$5:$B$287,2,'Seat Ledger'!$I$5:$I$287,"OFF") -> 34 | E52: =SUMIFS('Seat Ledger'!$M$5:$M$287,'Seat Ledger'!$B$5:$B$287,3,'Seat Ledger'!$I$5:$I$287,"OFF") -> 36.5 | F52: =SUMIFS('Seat Ledger'!$M$5:$M$287,'Seat Ledger'!$B$5:$B$287,4,'Seat Ledger'!$I$5:$I$287,"OFF") -> 36 | G52: =SUMIFS('Seat Ledger'!$M$5:$M$287,'Seat Ledger'!$B$5:$B$287,5,'Seat Ledger'!$I$5:$I$287,"OFF") -> 35.5
B53: Nearshore | C53: =SUMIFS('Seat Ledger'!$M$5:$M$287,'Seat Ledger'!$B$5:$B$287,1,'Seat Ledger'!$I$5:$I$287,"NEAR") -> 9.5 | D53: =SUMIFS('Seat Ledger'!$M$5:$M$287,'Seat Ledger'!$B$5:$B$287,2,'Seat Ledger'!$I$5:$I$287,"NEAR") -> 4 | E53: =SUMIFS('Seat Ledger'!$M$5:$M$287,'Seat Ledger'!$B$5:$B$287,3,'Seat Ledger'!$I$5:$I$287,"NEAR") -> 1 | F53: =SUMIFS('Seat Ledger'!$M$5:$M$287,'Seat Ledger'!$B$5:$B$287,4,'Seat Ledger'!$I$5:$I$287,"NEAR") -> 0.5 | G53: =SUMIFS('Seat Ledger'!$M$5:$M$287,'Seat Ledger'!$B$5:$B$287,5,'Seat Ledger'!$I$5:$I$287,"NEAR") -> 0.5
B54: Offshore share — whole team | C54: =IF(C9=0,0,(C52+C53)/C9) -> 0.30041152 | D54: =IF(D9=0,0,(D52+D53)/D9) -> 0.40641711 | E54: =IF(E9=0,0,(E52+E53)/E9) -> 0.49342105 | F54: =IF(F9=0,0,(F52+F53)/F9) -> 0.55725191 | G54: =IF(G9=0,0,(G52+G53)/G9) -> 0.60504202
B55: Offshore share — vendor only | C55: =IF(C47=0,0,(SUMIFS('Seat Ledger'!$M$5:$M$287,'Seat Ledger'!$B$5:$B$287,1,'Seat Ledger'!$J$5:$J$287,"FTC",'Seat Ledger'!$I$5:$I$287,"OFF")+SUMIFS('Seat Ledger'!$M$5:$M$287,'Seat Ledger'!$B$5:$B$287,1,'Seat Ledger'!$J$5:$J$287,"FTC",'Seat Ledger'!$I$5:$I$287,"NEAR")+SUMIFS('Seat Ledger'!$M$5:$M$287,'Seat Ledger'!$B$5:$B$287,1,'Seat Ledger'!$J$5:$J$287,"PT",'Seat Ledger'!$I$5:$I$287,"OFF"))/C47) -> 0.16470588 | D55: =IF(D47=0,0,(SUMIFS('Seat Ledger'!$M$5:$M$287,'Seat Ledger'!$B$5:$B$287,2,'Seat Ledger'!$J$5:$J$287,"FTC",'Seat Ledger'!$I$5:$I$287,"OFF")+SUMIFS('Seat Ledger'!$M$5:$M$287,'Seat Ledger'!$B$5:$B$287,2,'Seat Ledger'!$J$5:$J$287,"FTC",'Seat Ledger'!$I$5:$I$287,"NEAR")+SUMIFS('Seat Ledger'!$M$5:$M$287,'Seat Ledger'!$B$5:$B$287,2,'Seat Ledger'!$J$5:$J$287,"PT",'Seat Ledger'!$I$5:$I$287,"OFF"))/D47) -> 0.3125 | E55: =IF(E47=0,0,(SUMIFS('Seat Ledger'!$M$5:$M$287,'Seat Ledger'!$B$5:$B$287,3,'Seat Ledger'!$J$5:$J$287,"FTC",'Seat Ledger'!$I$5:$I$287,"OFF")+SUMIFS('Seat Ledger'!$M$5:$M$287,'Seat Ledger'!$B$5:$B$287,3,'Seat Ledger'!$J$5:$J$287,"FTC",'Seat Ledger'!$I$5:$I$287,"NEAR")+SUMIFS('Seat Ledger'!$M$5:$M$287,'Seat Ledger'!$B$5:$B$287,3,'Seat Ledger'!$J$5:$J$287,"PT",'Seat Ledger'!$I$5:$I$287,"OFF"))/E47) -> 0.44117647 | F55: =IF(F47=0,0,(SUMIFS('Seat Ledger'!$M$5:$M$287,'Seat Ledger'!$B$5:$B$287,4,'Seat Ledger'!$J$5:$J$287,"FTC",'Seat Ledger'!$I$5:$I$287,"OFF")+SUMIFS('Seat Ledger'!$M$5:$M$287,'Seat Ledger'!$B$5:$B$287,4,'Seat Ledger'!$J$5:$J$287,"FTC",'Seat Ledger'!$I$5:$I$287,"NEAR")+SUMIFS('Seat Ledger'!$M$5:$M$287,'Seat Ledger'!$B$5:$B$287,4,'Seat Ledger'!$J$5:$J$287,"PT",'Seat Ledger'!$I$5:$I$287,"OFF"))/F47) -> 0.5942029 | G55: =IF(G47=0,0,(SUMIFS('Seat Ledger'!$M$5:$M$287,'Seat Ledger'!$B$5:$B$287,5,'Seat Ledger'!$J$5:$J$287,"FTC",'Seat Ledger'!$I$5:$I$287,"OFF")+SUMIFS('Seat Ledger'!$M$5:$M$287,'Seat Ledger'!$B$5:$B$287,5,'Seat Ledger'!$J$5:$J$287,"FTC",'Seat Ledger'!$I$5:$I$287,"NEAR")+SUMIFS('Seat Ledger'!$M$5:$M$287,'Seat Ledger'!$B$5:$B$287,5,'Seat Ledger'!$J$5:$J$287,"PT",'Seat Ledger'!$I$5:$I$287,"OFF"))/G47) -> 0.68333333
B56: Offshore share — Capgemini payroll only | C56: =IF(C45=0,0,(SUMIFS('Seat Ledger'!$M$5:$M$287,'Seat Ledger'!$B$5:$B$287,1,'Seat Ledger'!$J$5:$J$287,"FTC",'Seat Ledger'!$I$5:$I$287,"OFF")+SUMIFS('Seat Ledger'!$M$5:$M$287,'Seat Ledger'!$B$5:$B$287,1,'Seat Ledger'!$J$5:$J$287,"FTC",'Seat Ledger'!$I$5:$I$287,"NEAR"))/C45) -> 0.16470588 | D56: =IF(D45=0,0,(SUMIFS('Seat Ledger'!$M$5:$M$287,'Seat Ledger'!$B$5:$B$287,2,'Seat Ledger'!$J$5:$J$287,"FTC",'Seat Ledger'!$I$5:$I$287,"OFF")+SUMIFS('Seat Ledger'!$M$5:$M$287,'Seat Ledger'!$B$5:$B$287,2,'Seat Ledger'!$J$5:$J$287,"FTC",'Seat Ledger'!$I$5:$I$287,"NEAR"))/D45) -> 0.3125 | E56: =IF(E45=0,0,(SUMIFS('Seat Ledger'!$M$5:$M$287,'Seat Ledger'!$B$5:$B$287,3,'Seat Ledger'!$J$5:$J$287,"FTC",'Seat Ledger'!$I$5:$I$287,"OFF")+SUMIFS('Seat Ledger'!$M$5:$M$287,'Seat Ledger'!$B$5:$B$287,3,'Seat Ledger'!$J$5:$J$287,"FTC",'Seat Ledger'!$I$5:$I$287,"NEAR"))/E45) -> 0.44117647 | F56: =IF(F45=0,0,(SUMIFS('Seat Ledger'!$M$5:$M$287,'Seat Ledger'!$B$5:$B$287,4,'Seat Ledger'!$J$5:$J$287,"FTC",'Seat Ledger'!$I$5:$I$287,"OFF")+SUMIFS('Seat Ledger'!$M$5:$M$287,'Seat Ledger'!$B$5:$B$287,4,'Seat Ledger'!$J$5:$J$287,"FTC",'Seat Ledger'!$I$5:$I$287,"NEAR"))/F45) -> 0.5942029 | G56: =IF(G45=0,0,(SUMIFS('Seat Ledger'!$M$5:$M$287,'Seat Ledger'!$B$5:$B$287,5,'Seat Ledger'!$J$5:$J$287,"FTC",'Seat Ledger'!$I$5:$I$287,"OFF")+SUMIFS('Seat Ledger'!$M$5:$M$287,'Seat Ledger'!$B$5:$B$287,5,'Seat Ledger'!$J$5:$J$287,"FTC",'Seat Ledger'!$I$5:$I$287,"NEAR"))/G45) -> 0.68333333 | I56: Rises across the five years and keeps rising through Year 4. Only 5 people transfer, so our own offshore book survives the event — the opposite of Contract Management.
B57: Target from the Logic Tree | C57: ='Logic Tree'!C68 -> 0.31407757 | D57: ='Logic Tree'!D68 -> 0.40579298 | E57: ='Logic Tree'!E68 -> 0.49398088 | F57: ='Logic Tree'!F68 -> 0.55394865 | G57: ='Logic Tree'!G68 -> 0.59627884
A59: E. ROLE MIX — MetLife's taxonomy, all sourcing types
B60: Role | C60: Year 1 | D60: Year 2 | E60: Year 3 | F60: Year 4 | G60: Year 5
B61: BSA — business and systems analysis | C61: =SUMIFS('Seat Ledger'!$M$5:$M$287,'Seat Ledger'!$B$5:$B$287,1,'Seat Ledger'!$G$5:$G$287,"BSA") -> 10.5 | D61: =SUMIFS('Seat Ledger'!$M$5:$M$287,'Seat Ledger'!$B$5:$B$287,2,'Seat Ledger'!$G$5:$G$287,"BSA") -> 13.5 | E61: =SUMIFS('Seat Ledger'!$M$5:$M$287,'Seat Ledger'!$B$5:$B$287,3,'Seat Ledger'!$G$5:$G$287,"BSA") -> 13.5 | F61: =SUMIFS('Seat Ledger'!$M$5:$M$287,'Seat Ledger'!$B$5:$B$287,4,'Seat Ledger'!$G$5:$G$287,"BSA") -> 10.5 | G61: =SUMIFS('Seat Ledger'!$M$5:$M$287,'Seat Ledger'!$B$5:$B$287,5,'Seat Ledger'!$G$5:$G$287,"BSA") -> 6.5
B62: Developer | C62: =SUMIFS('Seat Ledger'!$M$5:$M$287,'Seat Ledger'!$B$5:$B$287,1,'Seat Ledger'!$G$5:$G$287,"DEV") -> 77.5 | D62: =SUMIFS('Seat Ledger'!$M$5:$M$287,'Seat Ledger'!$B$5:$B$287,2,'Seat Ledger'!$G$5:$G$287,"DEV") -> 43 | E62: =SUMIFS('Seat Ledger'!$M$5:$M$287,'Seat Ledger'!$B$5:$B$287,3,'Seat Ledger'!$G$5:$G$287,"DEV") -> 33.5 | F62: =SUMIFS('Seat Ledger'!$M$5:$M$287,'Seat Ledger'!$B$5:$B$287,4,'Seat Ledger'!$G$5:$G$287,"DEV") -> 26.5 | G62: =SUMIFS('Seat Ledger'!$M$5:$M$287,'Seat Ledger'!$B$5:$B$287,5,'Seat Ledger'!$G$5:$G$287,"DEV") -> 28
B63: Tester | C63: =SUMIFS('Seat Ledger'!$M$5:$M$287,'Seat Ledger'!$B$5:$B$287,1,'Seat Ledger'!$G$5:$G$287,"TEST") -> 13.5 | D63: =SUMIFS('Seat Ledger'!$M$5:$M$287,'Seat Ledger'!$B$5:$B$287,2,'Seat Ledger'!$G$5:$G$287,"TEST") -> 15 | E63: =SUMIFS('Seat Ledger'!$M$5:$M$287,'Seat Ledger'!$B$5:$B$287,3,'Seat Ledger'!$G$5:$G$287,"TEST") -> 7 | F63: =SUMIFS('Seat Ledger'!$M$5:$M$287,'Seat Ledger'!$B$5:$B$287,4,'Seat Ledger'!$G$5:$G$287,"TEST") -> 13 | G63: =SUMIFS('Seat Ledger'!$M$5:$M$287,'Seat Ledger'!$B$5:$B$287,5,'Seat Ledger'!$G$5:$G$287,"TEST") -> 9.5
B64: Maintenance | C64: =SUMIFS('Seat Ledger'!$M$5:$M$287,'Seat Ledger'!$B$5:$B$287,1,'Seat Ledger'!$G$5:$G$287,"MNT") -> 6.5 | D64: =SUMIFS('Seat Ledger'!$M$5:$M$287,'Seat Ledger'!$B$5:$B$287,2,'Seat Ledger'!$G$5:$G$287,"MNT") -> 5 | E64: =SUMIFS('Seat Ledger'!$M$5:$M$287,'Seat Ledger'!$B$5:$B$287,3,'Seat Ledger'!$G$5:$G$287,"MNT") -> 4.5 | F64: =SUMIFS('Seat Ledger'!$M$5:$M$287,'Seat Ledger'!$B$5:$B$287,4,'Seat Ledger'!$G$5:$G$287,"MNT") -> 4 | G64: =SUMIFS('Seat Ledger'!$M$5:$M$287,'Seat Ledger'!$B$5:$B$287,5,'Seat Ledger'!$G$5:$G$287,"MNT") -> 5
B65: PM and product ownership | C65: =SUMIFS('Seat Ledger'!$M$5:$M$287,'Seat Ledger'!$B$5:$B$287,1,'Seat Ledger'!$G$5:$G$287,"PM") -> 10 | D65: =SUMIFS('Seat Ledger'!$M$5:$M$287,'Seat Ledger'!$B$5:$B$287,2,'Seat Ledger'!$G$5:$G$287,"PM") -> 6.5 | E65: =SUMIFS('Seat Ledger'!$M$5:$M$287,'Seat Ledger'!$B$5:$B$287,3,'Seat Ledger'!$G$5:$G$287,"PM") -> 7 | F65: =SUMIFS('Seat Ledger'!$M$5:$M$287,'Seat Ledger'!$B$5:$B$287,4,'Seat Ledger'!$G$5:$G$287,"PM") -> 8 | G65: =SUMIFS('Seat Ledger'!$M$5:$M$287,'Seat Ledger'!$B$5:$B$287,5,'Seat Ledger'!$G$5:$G$287,"PM") -> 8
B66: Other — architecture and enablement | C66: =SUMIFS('Seat Ledger'!$M$5:$M$287,'Seat Ledger'!$B$5:$B$287,1,'Seat Ledger'!$G$5:$G$287,"OTH") -> 3.5 | D66: =SUMIFS('Seat Ledger'!$M$5:$M$287,'Seat Ledger'!$B$5:$B$287,2,'Seat Ledger'!$G$5:$G$287,"OTH") -> 10.5 | E66: =SUMIFS('Seat Ledger'!$M$5:$M$287,'Seat Ledger'!$B$5:$B$287,3,'Seat Ledger'!$G$5:$G$287,"OTH") -> 10.5 | F66: =SUMIFS('Seat Ledger'!$M$5:$M$287,'Seat Ledger'!$B$5:$B$287,4,'Seat Ledger'!$G$5:$G$287,"OTH") -> 3.5 | G66: =SUMIFS('Seat Ledger'!$M$5:$M$287,'Seat Ledger'!$B$5:$B$287,5,'Seat Ledger'!$G$5:$G$287,"OTH") -> 2.5
B67: Run-facing share (Maintenance + Tester) | C67: =IF(C9=0,0,(C63+C64)/C9) -> 0.16460905 | D67: =IF(D9=0,0,(D63+D64)/D9) -> 0.21390374 | E67: =IF(E9=0,0,(E63+E64)/E9) -> 0.15131579 | F67: =IF(F9=0,0,(F63+F64)/F9) -> 0.25954198 | G67: =IF(G9=0,0,(G63+G64)/G9) -> 0.24369748 | I67: 15.3% in Year 1 falling to 9.0% by Year 5, as pipeline automation and auto-remediation land.
A69: F. EXPERIENCE MIX
B70: Band | C70: Year 1 | D70: Year 2 | E70: Year 3 | F70: Year 4 | G70: Year 5
B71: E1 | C71: =SUMIFS('Seat Ledger'!$M$5:$M$287,'Seat Ledger'!$B$5:$B$287,1,'Seat Ledger'!$H$5:$H$287,"E1") -> 0 | D71: =SUMIFS('Seat Ledger'!$M$5:$M$287,'Seat Ledger'!$B$5:$B$287,2,'Seat Ledger'!$H$5:$H$287,"E1") -> 0 | E71: =SUMIFS('Seat Ledger'!$M$5:$M$287,'Seat Ledger'!$B$5:$B$287,3,'Seat Ledger'!$H$5:$H$287,"E1") -> 0 | F71: =SUMIFS('Seat Ledger'!$M$5:$M$287,'Seat Ledger'!$B$5:$B$287,4,'Seat Ledger'!$H$5:$H$287,"E1") -> 0 | G71: =SUMIFS('Seat Ledger'!$M$5:$M$287,'Seat Ledger'!$B$5:$B$287,5,'Seat Ledger'!$H$5:$H$287,"E1") -> 0
B72: E2 | C72: =SUMIFS('Seat Ledger'!$M$5:$M$287,'Seat Ledger'!$B$5:$B$287,1,'Seat Ledger'!$H$5:$H$287,"E2") -> 26.5 | D72: =SUMIFS('Seat Ledger'!$M$5:$M$287,'Seat Ledger'!$B$5:$B$287,2,'Seat Ledger'!$H$5:$H$287,"E2") -> 19.5 | E72: =SUMIFS('Seat Ledger'!$M$5:$M$287,'Seat Ledger'!$B$5:$B$287,3,'Seat Ledger'!$H$5:$H$287,"E2") -> 14 | F72: =SUMIFS('Seat Ledger'!$M$5:$M$287,'Seat Ledger'!$B$5:$B$287,4,'Seat Ledger'!$H$5:$H$287,"E2") -> 20.5 | G72: =SUMIFS('Seat Ledger'!$M$5:$M$287,'Seat Ledger'!$B$5:$B$287,5,'Seat Ledger'!$H$5:$H$287,"E2") -> 15.5
B73: E3 | C73: =SUMIFS('Seat Ledger'!$M$5:$M$287,'Seat Ledger'!$B$5:$B$287,1,'Seat Ledger'!$H$5:$H$287,"E3") -> 54.5 | D73: =SUMIFS('Seat Ledger'!$M$5:$M$287,'Seat Ledger'!$B$5:$B$287,2,'Seat Ledger'!$H$5:$H$287,"E3") -> 39.5 | E73: =SUMIFS('Seat Ledger'!$M$5:$M$287,'Seat Ledger'!$B$5:$B$287,3,'Seat Ledger'!$H$5:$H$287,"E3") -> 31.5 | F73: =SUMIFS('Seat Ledger'!$M$5:$M$287,'Seat Ledger'!$B$5:$B$287,4,'Seat Ledger'!$H$5:$H$287,"E3") -> 19.5 | G73: =SUMIFS('Seat Ledger'!$M$5:$M$287,'Seat Ledger'!$B$5:$B$287,5,'Seat Ledger'!$H$5:$H$287,"E3") -> 17
B74: E4 | C74: =SUMIFS('Seat Ledger'!$M$5:$M$287,'Seat Ledger'!$B$5:$B$287,1,'Seat Ledger'!$H$5:$H$287,"E4") -> 37.5 | D74: =SUMIFS('Seat Ledger'!$M$5:$M$287,'Seat Ledger'!$B$5:$B$287,2,'Seat Ledger'!$H$5:$H$287,"E4") -> 28.5 | E74: =SUMIFS('Seat Ledger'!$M$5:$M$287,'Seat Ledger'!$B$5:$B$287,3,'Seat Ledger'!$H$5:$H$287,"E4") -> 22.5 | F74: =SUMIFS('Seat Ledger'!$M$5:$M$287,'Seat Ledger'!$B$5:$B$287,4,'Seat Ledger'!$H$5:$H$287,"E4") -> 23 | G74: =SUMIFS('Seat Ledger'!$M$5:$M$287,'Seat Ledger'!$B$5:$B$287,5,'Seat Ledger'!$H$5:$H$287,"E4") -> 25.5
B75: E5 | C75: =SUMIFS('Seat Ledger'!$M$5:$M$287,'Seat Ledger'!$B$5:$B$287,1,'Seat Ledger'!$H$5:$H$287,"E5") -> 3 | D75: =SUMIFS('Seat Ledger'!$M$5:$M$287,'Seat Ledger'!$B$5:$B$287,2,'Seat Ledger'!$H$5:$H$287,"E5") -> 6 | E75: =SUMIFS('Seat Ledger'!$M$5:$M$287,'Seat Ledger'!$B$5:$B$287,3,'Seat Ledger'!$H$5:$H$287,"E5") -> 8 | F75: =SUMIFS('Seat Ledger'!$M$5:$M$287,'Seat Ledger'!$B$5:$B$287,4,'Seat Ledger'!$H$5:$H$287,"E5") -> 2.5 | G75: =SUMIFS('Seat Ledger'!$M$5:$M$287,'Seat Ledger'!$B$5:$B$287,5,'Seat Ledger'!$H$5:$H$287,"E5") -> 1.5
B76: Senior share (E4 + E5) | C76: =IF(C9=0,0,(C74+C75)/C9) -> 0.33333333 | D76: =IF(D9=0,0,(D74+D75)/D9) -> 0.36898396 | E76: =IF(E9=0,0,(E74+E75)/E9) -> 0.40131579 | F76: =IF(F9=0,0,(F74+F75)/F9) -> 0.38931298 | G76: =IF(G9=0,0,(G74+G75)/G9) -> 0.45378151

Sheet Inherited Workforce
A1: The 20 Capgemini people already on these applications — and why this cohort is the opposite problem
A2: Supply comes from the T3 headcount reconciliation behind Golden Inventory v4. Demand comes from the seat ledger. The difference is the hiring, promotion and reskilling plan.
A4: A. WHERE THE NUMBER COMES FROM
B5: Source | C5: Count | D5: What it is used for
B6: Billing details — named individuals | C6: 277 | D6: THE COUNT. 277 de-duplicated employee IDs across T3, DMO and JET, each with a location and a Capgemini grade.
B7: Mapping of current Capgemini staff — billable FTE | C7: 283 | D7: THE ROLE MIX and the grade ladder. Developer → Developer, Cloud Engineer → Maintenance, Testers → Tester, BSA / Scrum Master / Functional Analyst → BSA, Tech Lead / Solution Architect → Other.
B8: EAIs.xlsx — 'CG HC by EAI' | C8: 450 | D8: THE SHAPE of the application-level distribution, rescaled to 277 and capped at each application's own vendor FTC.
B9: EAIs.xlsx Sheet1 — direct EAI tags | C9: 528 | D9: Cross-check only. Double-counts people serving more than one application.
B10: Of the 277, allocated to Insurance Claims and Benefits Payment Related | C10: 38 | D10: 33 in India, 5 in Japan. 45 of the 277 sit in cross-domain teams with no application mapping and are excluded from every domain.
B12: Capgemini grade → experience band: A4/A5 → E1 · B1/B2 → E2 · C1 and Sub-Con → E3 · C2/D1 → E4 · D2/E1 → E5. Location is binary: Japan → onshore, everything else → India / offshore.
A14: B. WHERE THEY SIT TODAY
B15: Application | C15: Archetype | D15: Value stream | E15: CG heads today | F15: Vendor FTC
B16: Annuity ＆ Maturity Payment (3 apps) | C16: D / J / T | D16: Claim Batch, W05AMS-JPN, WZZMNB-JPN | E16: 6 | F16: 42.454 | J16: 6 people against 85.4 vendor units — 7%, and all six sit on Claim Batch. This is the weakest the strongest continuity position of the five 領域 modelled. The split is almost even between the two streams, which is why neither can be treated as a standing start.
B17: Claims Processing ＆ Adjudication (1) | C17: D | D17: C12WNC-JPN — marked Retire | E17: 0 | F17: 29.38
B18: Claims Support Services (2 apps) | C18: D / T | D18: Pega for Claims, MDRS | E18: 0 | F18: 13.614
B19: TOTAL | E19: =SUM(E16:E18) -> 6 | F19: =SUM(F16:F18) -> 85.448
A21: C. THE EVOLUTION MECHANIC — INPUT
B22: Band | C22: Attrition — offshore | D22: Attrition — onshore | E22: Promotion out of band
B23: E1 | C23: 0.22 | D23: 0.1 | E23: 0.2 | J23: Identical rates to Sales / Insurance v6 and Contract Management v7 — attrition first, promotion to the survivors. The same mechanic, applied to a very different starting shape.
B24: E2 | C24: 0.18 | D24: 0.09 | E24: 0.16
B25: E3 | C25: 0.13 | D25: 0.07 | E25: 0.12
B26: E4 | C26: 0.09 | D26: 0.05 | E26: 0.07
B27: E5 | C27: 0.06 | D27: 0.04 | E27: 0
A29: D. THE COHORT ROLLED FORWARD
B30: Measure | C30: Year 1 | D30: Year 2 | E30: Year 3 | F30: Year 4 | G30: Year 5
B31: Inherited people surviving | C31: 6 | D31: 5.24 | E31: 4.613248 | F31: 4.0916638 | G31: 3.6537367
B32: — E1 | C32: 0 | D32: 0 | E32: 0 | F32: 0 | G32: 0
B33: — E2 | C33: 2 | D33: 1.3776 | E33: 0.94889088 | F33: 0.65359604 | G33: 0.45019695
B34: — E3 | C34: 2 | D34: 1.7936 | E34: 1.5539213 | F34: 1.3141766 | G34: 1.0918854
B35: — E4 | C35: 2 | D35: 1.9386 | E35: 1.8607552 | F35: 1.7660238 | G35: 1.6574404
B36: — E5 | C36: 0 | D36: 0.1302 | E36: 0.24968062 | F36: 0.35786735 | G36: 0.45421395
B37: Senior share (E4 + E5) | C37: 0.33333333 | D37: 0.39480916 | E37: 0.45747288 | F37: 0.51907763 | G37: 0.57794377 | J37: The cohort starts at 28.9% senior (11 of 38 at E4 or E5) and the attrition-and-promotion mechanic seniorises it every year. Row 37 is the number to watch: it drives cost per head, and the design counters it by hiring at E2 and E3 offshore as the team shrinks.
B38: — in Japan | C38: 1 | D38: 0.95 | E38: 0.903165 | F38: 0.85923268 | G38: 0.81796701
B39: — in India | C39: 5 | D39: 4.29 | E39: 3.710083 | F39: 3.2324311 | G39: 2.8357697
A41: E. SUPPLY AGAINST DEMAND — offshore, where 18 of the 20 sit
B42: Measure | C42: Year 1 | D42: Year 2 | E42: Year 3 | F42: Year 4 | G42: Year 5
B43: Offshore Capgemini seats the design asks for | C43: =SUMIFS('Seat Ledger'!$M$5:$M$287,'Seat Ledger'!$B$5:$B$287,1,'Seat Ledger'!$J$5:$J$287,"FTC",'Seat Ledger'!$I$5:$I$287,"OFF")+SUMIFS('Seat Ledger'!$M$5:$M$287,'Seat Ledger'!$B$5:$B$287,1,'Seat Ledger'!$J$5:$J$287,"FTC",'Seat Ledger'!$I$5:$I$287,"NEAR") -> 14 | D43: =SUMIFS('Seat Ledger'!$M$5:$M$287,'Seat Ledger'!$B$5:$B$287,2,'Seat Ledger'!$J$5:$J$287,"FTC",'Seat Ledger'!$I$5:$I$287,"OFF")+SUMIFS('Seat Ledger'!$M$5:$M$287,'Seat Ledger'!$B$5:$B$287,2,'Seat Ledger'!$J$5:$J$287,"FTC",'Seat Ledger'!$I$5:$I$287,"NEAR") -> 20 | E43: =SUMIFS('Seat Ledger'!$M$5:$M$287,'Seat Ledger'!$B$5:$B$287,3,'Seat Ledger'!$J$5:$J$287,"FTC",'Seat Ledger'!$I$5:$I$287,"OFF")+SUMIFS('Seat Ledger'!$M$5:$M$287,'Seat Ledger'!$B$5:$B$287,3,'Seat Ledger'!$J$5:$J$287,"FTC",'Seat Ledger'!$I$5:$I$287,"NEAR") -> 22.5 | F43: =SUMIFS('Seat Ledger'!$M$5:$M$287,'Seat Ledger'!$B$5:$B$287,4,'Seat Ledger'!$J$5:$J$287,"FTC",'Seat Ledger'!$I$5:$I$287,"OFF")+SUMIFS('Seat Ledger'!$M$5:$M$287,'Seat Ledger'!$B$5:$B$287,4,'Seat Ledger'!$J$5:$J$287,"FTC",'Seat Ledger'!$I$5:$I$287,"NEAR") -> 20.5 | G43: =SUMIFS('Seat Ledger'!$M$5:$M$287,'Seat Ledger'!$B$5:$B$287,5,'Seat Ledger'!$J$5:$J$287,"FTC",'Seat Ledger'!$I$5:$I$287,"OFF")+SUMIFS('Seat Ledger'!$M$5:$M$287,'Seat Ledger'!$B$5:$B$287,5,'Seat Ledger'!$J$5:$J$287,"FTC",'Seat Ledger'!$I$5:$I$287,"NEAR") -> 20.5
B44: Inherited people still there | C44: 5 | D44: 4.29 | E44: 3.710083 | F44: 3.2324311 | G44: 2.8357697
B45: Covered by people we already have | C45: =C44/C43 -> 0.35714286 | D45: =D44/D43 -> 0.2145 | E45: =E44/E43 -> 0.16489258 | F45: =F44/F43 -> 0.15767957 | G45: =G44/G43 -> 0.13833023 | J45: 60% covered in Year 1, against 90% on Sales. This domain has to hire more of its own offshore team from a standing start, and the people it hires must be junior enough to balance a cohort that is already senior.
B46: To hire, redeploy or reskill | C46: =C43-C44 -> 9 | D46: =D43-D44 -> 15.71 | E46: =E43-E44 -> 18.789917 | F46: =F43-F44 -> 17.267569 | G46: =G43-G44 -> 17.66423
A48: F. BAND BY BAND — the seats we designed against the people we hold, offshore
B49: Year 1 | C49: E1 | D49: E2 | E49: E3 | F49: E4 | G49: E5 | H49: Total
B50: Seats the design asks for | C50: =SUMIFS('Seat Ledger'!$M$5:$M$287,'Seat Ledger'!$B$5:$B$287,1,'Seat Ledger'!$J$5:$J$287,"FTC",'Seat Ledger'!$I$5:$I$287,"OFF",'Seat Ledger'!$H$5:$H$287,"E1")+SUMIFS('Seat Ledger'!$M$5:$M$287,'Seat Ledger'!$B$5:$B$287,1,'Seat Ledger'!$J$5:$J$287,"FTC",'Seat Ledger'!$I$5:$I$287,"NEAR",'Seat Ledger'!$H$5:$H$287,"E1") -> 0 | D50: =SUMIFS('Seat Ledger'!$M$5:$M$287,'Seat Ledger'!$B$5:$B$287,1,'Seat Ledger'!$J$5:$J$287,"FTC",'Seat Ledger'!$I$5:$I$287,"OFF",'Seat Ledger'!$H$5:$H$287,"E2")+SUMIFS('Seat Ledger'!$M$5:$M$287,'Seat Ledger'!$B$5:$B$287,1,'Seat Ledger'!$J$5:$J$287,"FTC",'Seat Ledger'!$I$5:$I$287,"NEAR",'Seat Ledger'!$H$5:$H$287,"E2") -> 3 | E50: =SUMIFS('Seat Ledger'!$M$5:$M$287,'Seat Ledger'!$B$5:$B$287,1,'Seat Ledger'!$J$5:$J$287,"FTC",'Seat Ledger'!$I$5:$I$287,"OFF",'Seat Ledger'!$H$5:$H$287,"E3")+SUMIFS('Seat Ledger'!$M$5:$M$287,'Seat Ledger'!$B$5:$B$287,1,'Seat Ledger'!$J$5:$J$287,"FTC",'Seat Ledger'!$I$5:$I$287,"NEAR",'Seat Ledger'!$H$5:$H$287,"E3") -> 10.5 | F50: =SUMIFS('Seat Ledger'!$M$5:$M$287,'Seat Ledger'!$B$5:$B$287,1,'Seat Ledger'!$J$5:$J$287,"FTC",'Seat Ledger'!$I$5:$I$287,"OFF",'Seat Ledger'!$H$5:$H$287,"E4")+SUMIFS('Seat Ledger'!$M$5:$M$287,'Seat Ledger'!$B$5:$B$287,1,'Seat Ledger'!$J$5:$J$287,"FTC",'Seat Ledger'!$I$5:$I$287,"NEAR",'Seat Ledger'!$H$5:$H$287,"E4") -> 0.5 | G50: =SUMIFS('Seat Ledger'!$M$5:$M$287,'Seat Ledger'!$B$5:$B$287,1,'Seat Ledger'!$J$5:$J$287,"FTC",'Seat Ledger'!$I$5:$I$287,"OFF",'Seat Ledger'!$H$5:$H$287,"E5")+SUMIFS('Seat Ledger'!$M$5:$M$287,'Seat Ledger'!$B$5:$B$287,1,'Seat Ledger'!$J$5:$J$287,"FTC",'Seat Ledger'!$I$5:$I$287,"NEAR",'Seat Ledger'!$H$5:$H$287,"E5") -> 0 | H50: =SUM(C50:G50) -> 14
B51: People we already have | C51: 0 | D51: 2 | E51: 2 | F51: 1 | G51: 0 | H51: =SUM(C51:G51) -> 5
B52: Gap — positive is a hire | C52: =C50-C51 -> 0 | D52: =D50-D51 -> 1 | E52: =E50-E51 -> 8.5 | F52: =F50-F51 -> -0.5 | G52: =G50-G51 -> 0 | H52: =SUM(C52:G52) -> 9
B54: Year 2 | C54: E1 | D54: E2 | E54: E3 | F54: E4 | G54: E5 | H54: Total
B55: Seats the design asks for | C55: =SUMIFS('Seat Ledger'!$M$5:$M$287,'Seat Ledger'!$B$5:$B$287,2,'Seat Ledger'!$J$5:$J$287,"FTC",'Seat Ledger'!$I$5:$I$287,"OFF",'Seat Ledger'!$H$5:$H$287,"E1")+SUMIFS('Seat Ledger'!$M$5:$M$287,'Seat Ledger'!$B$5:$B$287,2,'Seat Ledger'!$J$5:$J$287,"FTC",'Seat Ledger'!$I$5:$I$287,"NEAR",'Seat Ledger'!$H$5:$H$287,"E1") -> 0 | D55: =SUMIFS('Seat Ledger'!$M$5:$M$287,'Seat Ledger'!$B$5:$B$287,2,'Seat Ledger'!$J$5:$J$287,"FTC",'Seat Ledger'!$I$5:$I$287,"OFF",'Seat Ledger'!$H$5:$H$287,"E2")+SUMIFS('Seat Ledger'!$M$5:$M$287,'Seat Ledger'!$B$5:$B$287,2,'Seat Ledger'!$J$5:$J$287,"FTC",'Seat Ledger'!$I$5:$I$287,"NEAR",'Seat Ledger'!$H$5:$H$287,"E2") -> 7 | E55: =SUMIFS('Seat Ledger'!$M$5:$M$287,'Seat Ledger'!$B$5:$B$287,2,'Seat Ledger'!$J$5:$J$287,"FTC",'Seat Ledger'!$I$5:$I$287,"OFF",'Seat Ledger'!$H$5:$H$287,"E3")+SUMIFS('Seat Ledger'!$M$5:$M$287,'Seat Ledger'!$B$5:$B$287,2,'Seat Ledger'!$J$5:$J$287,"FTC",'Seat Ledger'!$I$5:$I$287,"NEAR",'Seat Ledger'!$H$5:$H$287,"E3") -> 11 | F55: =SUMIFS('Seat Ledger'!$M$5:$M$287,'Seat Ledger'!$B$5:$B$287,2,'Seat Ledger'!$J$5:$J$287,"FTC",'Seat Ledger'!$I$5:$I$287,"OFF",'Seat Ledger'!$H$5:$H$287,"E4")+SUMIFS('Seat Ledger'!$M$5:$M$287,'Seat Ledger'!$B$5:$B$287,2,'Seat Ledger'!$J$5:$J$287,"FTC",'Seat Ledger'!$I$5:$I$287,"NEAR",'Seat Ledger'!$H$5:$H$287,"E4") -> 2 | G55: =SUMIFS('Seat Ledger'!$M$5:$M$287,'Seat Ledger'!$B$5:$B$287,2,'Seat Ledger'!$J$5:$J$287,"FTC",'Seat Ledger'!$I$5:$I$287,"OFF",'Seat Ledger'!$H$5:$H$287,"E5")+SUMIFS('Seat Ledger'!$M$5:$M$287,'Seat Ledger'!$B$5:$B$287,2,'Seat Ledger'!$J$5:$J$287,"FTC",'Seat Ledger'!$I$5:$I$287,"NEAR",'Seat Ledger'!$H$5:$H$287,"E5") -> 0 | H55: =SUM(C55:G55) -> 20
B56: People we already have | C56: 0 | D56: 1.3776 | E56: 1.7936 | F56: 1.0551 | G56: 0.0637 | H56: =SUM(C56:G56) -> 4.29
B57: Gap — positive is a hire | C57: =C55-C56 -> 0 | D57: =D55-D56 -> 5.6224 | E57: =E55-E56 -> 9.2064 | F57: =F55-F56 -> 0.9449 | G57: =G55-G56 -> -0.0637 | H57: =SUM(C57:G57) -> 15.71
B59: Year 3 | C59: E1 | D59: E2 | E59: E3 | F59: E4 | G59: E5 | H59: Total
B60: Seats the design asks for | C60: =SUMIFS('Seat Ledger'!$M$5:$M$287,'Seat Ledger'!$B$5:$B$287,3,'Seat Ledger'!$J$5:$J$287,"FTC",'Seat Ledger'!$I$5:$I$287,"OFF",'Seat Ledger'!$H$5:$H$287,"E1")+SUMIFS('Seat Ledger'!$M$5:$M$287,'Seat Ledger'!$B$5:$B$287,3,'Seat Ledger'!$J$5:$J$287,"FTC",'Seat Ledger'!$I$5:$I$287,"NEAR",'Seat Ledger'!$H$5:$H$287,"E1") -> 0 | D60: =SUMIFS('Seat Ledger'!$M$5:$M$287,'Seat Ledger'!$B$5:$B$287,3,'Seat Ledger'!$J$5:$J$287,"FTC",'Seat Ledger'!$I$5:$I$287,"OFF",'Seat Ledger'!$H$5:$H$287,"E2")+SUMIFS('Seat Ledger'!$M$5:$M$287,'Seat Ledger'!$B$5:$B$287,3,'Seat Ledger'!$J$5:$J$287,"FTC",'Seat Ledger'!$I$5:$I$287,"NEAR",'Seat Ledger'!$H$5:$H$287,"E2") -> 9 | E60: =SUMIFS('Seat Ledger'!$M$5:$M$287,'Seat Ledger'!$B$5:$B$287,3,'Seat Ledger'!$J$5:$J$287,"FTC",'Seat Ledger'!$I$5:$I$287,"OFF",'Seat Ledger'!$H$5:$H$287,"E3")+SUMIFS('Seat Ledger'!$M$5:$M$287,'Seat Ledger'!$B$5:$B$287,3,'Seat Ledger'!$J$5:$J$287,"FTC",'Seat Ledger'!$I$5:$I$287,"NEAR",'Seat Ledger'!$H$5:$H$287,"E3") -> 13 | F60: =SUMIFS('Seat Ledger'!$M$5:$M$287,'Seat Ledger'!$B$5:$B$287,3,'Seat Ledger'!$J$5:$J$287,"FTC",'Seat Ledger'!$I$5:$I$287,"OFF",'Seat Ledger'!$H$5:$H$287,"E4")+SUMIFS('Seat Ledger'!$M$5:$M$287,'Seat Ledger'!$B$5:$B$287,3,'Seat Ledger'!$J$5:$J$287,"FTC",'Seat Ledger'!$I$5:$I$287,"NEAR",'Seat Ledger'!$H$5:$H$287,"E4") -> 0.5 | G60: =SUMIFS('Seat Ledger'!$M$5:$M$287,'Seat Ledger'!$B$5:$B$287,3,'Seat Ledger'!$J$5:$J$287,"FTC",'Seat Ledger'!$I$5:$I$287,"OFF",'Seat Ledger'!$H$5:$H$287,"E5")+SUMIFS('Seat Ledger'!$M$5:$M$287,'Seat Ledger'!$B$5:$B$287,3,'Seat Ledger'!$J$5:$J$287,"FTC",'Seat Ledger'!$I$5:$I$287,"NEAR",'Seat Ledger'!$H$5:$H$287,"E5") -> 0 | H60: =SUM(C60:G60) -> 22.5
B61: People we already have | C61: 0 | D61: 0.94889088 | E61: 1.5539213 | F61: 1.080183 | G61: 0.12708787 | H61: =SUM(C61:G61) -> 3.710083
B62: Gap — positive is a hire | C62: =C60-C61 -> 0 | D62: =D60-D61 -> 8.0511091 | E62: =E60-E61 -> 11.446079 | F62: =F60-F61 -> -0.58018297 | G62: =G60-G61 -> -0.12708787 | H62: =SUM(C62:G62) -> 18.789917
B64: Year 4 | C64: E1 | D64: E2 | E64: E3 | F64: E4 | G64: E5 | H64: Total
B65: Seats the design asks for | C65: =SUMIFS('Seat Ledger'!$M$5:$M$287,'Seat Ledger'!$B$5:$B$287,4,'Seat Ledger'!$J$5:$J$287,"FTC",'Seat Ledger'!$I$5:$I$287,"OFF",'Seat Ledger'!$H$5:$H$287,"E1")+SUMIFS('Seat Ledger'!$M$5:$M$287,'Seat Ledger'!$B$5:$B$287,4,'Seat Ledger'!$J$5:$J$287,"FTC",'Seat Ledger'!$I$5:$I$287,"NEAR",'Seat Ledger'!$H$5:$H$287,"E1") -> 0 | D65: =SUMIFS('Seat Ledger'!$M$5:$M$287,'Seat Ledger'!$B$5:$B$287,4,'Seat Ledger'!$J$5:$J$287,"FTC",'Seat Ledger'!$I$5:$I$287,"OFF",'Seat Ledger'!$H$5:$H$287,"E2")+SUMIFS('Seat Ledger'!$M$5:$M$287,'Seat Ledger'!$B$5:$B$287,4,'Seat Ledger'!$J$5:$J$287,"FTC",'Seat Ledger'!$I$5:$I$287,"NEAR",'Seat Ledger'!$H$5:$H$287,"E2") -> 11 | E65: =SUMIFS('Seat Ledger'!$M$5:$M$287,'Seat Ledger'!$B$5:$B$287,4,'Seat Ledger'!$J$5:$J$287,"FTC",'Seat Ledger'!$I$5:$I$287,"OFF",'Seat Ledger'!$H$5:$H$287,"E3")+SUMIFS('Seat Ledger'!$M$5:$M$287,'Seat Ledger'!$B$5:$B$287,4,'Seat Ledger'!$J$5:$J$287,"FTC",'Seat Ledger'!$I$5:$I$287,"NEAR",'Seat Ledger'!$H$5:$H$287,"E3") -> 9 | F65: =SUMIFS('Seat Ledger'!$M$5:$M$287,'Seat Ledger'!$B$5:$B$287,4,'Seat Ledger'!$J$5:$J$287,"FTC",'Seat Ledger'!$I$5:$I$287,"OFF",'Seat Ledger'!$H$5:$H$287,"E4")+SUMIFS('Seat Ledger'!$M$5:$M$287,'Seat Ledger'!$B$5:$B$287,4,'Seat Ledger'!$J$5:$J$287,"FTC",'Seat Ledger'!$I$5:$I$287,"NEAR",'Seat Ledger'!$H$5:$H$287,"E4") -> 0.5 | G65: =SUMIFS('Seat Ledger'!$M$5:$M$287,'Seat Ledger'!$B$5:$B$287,4,'Seat Ledger'!$J$5:$J$287,"FTC",'Seat Ledger'!$I$5:$I$287,"OFF",'Seat Ledger'!$H$5:$H$287,"E5")+SUMIFS('Seat Ledger'!$M$5:$M$287,'Seat Ledger'!$B$5:$B$287,4,'Seat Ledger'!$J$5:$J$287,"FTC",'Seat Ledger'!$I$5:$I$287,"NEAR",'Seat Ledger'!$H$5:$H$287,"E5") -> 0 | H65: =SUM(C65:G65) -> 20.5
B66: People we already have | C66: 0 | D66: 0.65359604 | E66: 1.3141766 | F66: 1.0763882 | G66: 0.18827025 | H66: =SUM(C66:G66) -> 3.2324311
B67: Gap — positive is a hire | C67: =C65-C66 -> 0 | D67: =D65-D66 -> 10.346404 | E67: =E65-E66 -> 7.6858234 | F67: =F65-F66 -> -0.57638823 | G67: =G65-G66 -> -0.18827025 | H67: =SUM(C67:G67) -> 17.267569
B69: Year 5 | C69: E1 | D69: E2 | E69: E3 | F69: E4 | G69: E5 | H69: Total
B70: Seats the design asks for | C70: =SUMIFS('Seat Ledger'!$M$5:$M$287,'Seat Ledger'!$B$5:$B$287,5,'Seat Ledger'!$J$5:$J$287,"FTC",'Seat Ledger'!$I$5:$I$287,"OFF",'Seat Ledger'!$H$5:$H$287,"E1")+SUMIFS('Seat Ledger'!$M$5:$M$287,'Seat Ledger'!$B$5:$B$287,5,'Seat Ledger'!$J$5:$J$287,"FTC",'Seat Ledger'!$I$5:$I$287,"NEAR",'Seat Ledger'!$H$5:$H$287,"E1") -> 0 | D70: =SUMIFS('Seat Ledger'!$M$5:$M$287,'Seat Ledger'!$B$5:$B$287,5,'Seat Ledger'!$J$5:$J$287,"FTC",'Seat Ledger'!$I$5:$I$287,"OFF",'Seat Ledger'!$H$5:$H$287,"E2")+SUMIFS('Seat Ledger'!$M$5:$M$287,'Seat Ledger'!$B$5:$B$287,5,'Seat Ledger'!$J$5:$J$287,"FTC",'Seat Ledger'!$I$5:$I$287,"NEAR",'Seat Ledger'!$H$5:$H$287,"E2") -> 10.5 | E70: =SUMIFS('Seat Ledger'!$M$5:$M$287,'Seat Ledger'!$B$5:$B$287,5,'Seat Ledger'!$J$5:$J$287,"FTC",'Seat Ledger'!$I$5:$I$287,"OFF",'Seat Ledger'!$H$5:$H$287,"E3")+SUMIFS('Seat Ledger'!$M$5:$M$287,'Seat Ledger'!$B$5:$B$287,5,'Seat Ledger'!$J$5:$J$287,"FTC",'Seat Ledger'!$I$5:$I$287,"NEAR",'Seat Ledger'!$H$5:$H$287,"E3") -> 9.5 | F70: =SUMIFS('Seat Ledger'!$M$5:$M$287,'Seat Ledger'!$B$5:$B$287,5,'Seat Ledger'!$J$5:$J$287,"FTC",'Seat Ledger'!$I$5:$I$287,"OFF",'Seat Ledger'!$H$5:$H$287,"E4")+SUMIFS('Seat Ledger'!$M$5:$M$287,'Seat Ledger'!$B$5:$B$287,5,'Seat Ledger'!$J$5:$J$287,"FTC",'Seat Ledger'!$I$5:$I$287,"NEAR",'Seat Ledger'!$H$5:$H$287,"E4") -> 0.5 | G70: =SUMIFS('Seat Ledger'!$M$5:$M$287,'Seat Ledger'!$B$5:$B$287,5,'Seat Ledger'!$J$5:$J$287,"FTC",'Seat Ledger'!$I$5:$I$287,"OFF",'Seat Ledger'!$H$5:$H$287,"E5")+SUMIFS('Seat Ledger'!$M$5:$M$287,'Seat Ledger'!$B$5:$B$287,5,'Seat Ledger'!$J$5:$J$287,"FTC",'Seat Ledger'!$I$5:$I$287,"NEAR",'Seat Ledger'!$H$5:$H$287,"E5") -> 0 | H70: =SUM(C70:G70) -> 20.5
B71: People we already have | C71: 0 | D71: 0.45019695 | E71: 1.0918854 | F71: 1.0481474 | G71: 0.24553997 | H71: =SUM(C71:G71) -> 2.8357697
B72: Gap — positive is a hire | C72: =C70-C71 -> 0 | D72: =D70-D71 -> 10.049803 | E72: =E70-E71 -> 8.4081146 | F72: =F70-F71 -> -0.5481474 | G72: =G70-G71 -> -0.24553997 | H72: =SUM(C72:G72) -> 17.66423
B74: The shortage is at E2 and E3 in every year, and the surplus is at E5 in every year — the mirror image of Sales. The E5 surplus is small in absolute terms (2.0 people in Year 1 rising to 2.8 by Year 5) but it is 100% of the E5 population, because the design carries no offshore E5 seat at all. Those people belong in the horizontal architecture and quality-lead roles, which is where the seat ledger puts them, or they are a redeployment out of the domain.
A76: G. WHAT THIS MEANS FOR THE SOLUTION
B77: • The continuity argument is the strongest in the portfolio. 33 of the Year-1 Capgemini offshore seats are people already sitting on these applications. The balance are hires onto a Java, JavaScript and API estate — the easiest hiring profile of the five 領域 modelled, onshore or offshore.
B78: • The talent-shape risk is manageable. The cohort is 28.9% senior on day one and seniorises from there. The design counters it by hiring at E2/E3 offshore and by placing surviving seniors in the architecture, quality-lead and pod-lead roles where they earn their band.
B79: • There is no incumbent sub-contractor to displace. Golden v4 names Capgemini on five of the ten applications and NCD on one 1.4-unit application; 13.0 vendor units carry no named vendor at all. That is a due-diligence question, not a modelled partner — and it is why the PT rows in this workbook resolve to zero.
B80: • Five people in Japan against 36.7 onshore vendor units on day one. Every other bilingual Tokyo seat is a hire or a redeployment. Smaller here than elsewhere because the stack is English-specification and the offshore ceiling is only 65.3% and 84% of the vendor population is in Tokyo today.

Sheet Glidepath & 50-50
A1: Glidepath — capability, carry-forward, offshore, and one transfer at the end of Year 3
A2: Year 1 passes nothing through. The transfer is struck on the exit position at full realisation.
A4: A. BASELINE
B5: Measure | C5: Value
B6: Applications | C6: ='Logic Tree'!C6 -> 6
B7: Total effort (units) | C7: ='Logic Tree'!C7 -> 121.5735
B8: Capgemini FTC | C8: ='Logic Tree'!C8 -> 85.4485
B9: MetLife FTE | C9: ='Logic Tree'!C9 -> 13.4792
B10: MetLife MGCC | C10: ='Logic Tree'!C10 -> 22.6458
B11: Ratio today — Capgemini share | C11: ='Logic Tree'!C23 -> 0.70285465
B12: Offshore today — whole team, measured | C12: ='Logic Tree'!C24 -> 0.29996751 | I12: 45.5% offshore on day one — 28.87 offshore, 0.96 nearshore and 15.99 MGCC against 100.765 units. A 30.0% start against a 65.3% ceiling — the gap is real but the runway is long.
B13: Appendix 3 Year-3 target, each side | C13: ='Logic Tree'!C22 -> 60.7868
A15: B. PRODUCTIVITY
B16: Measure | C16: Year 1 | D16: Year 2 | E16: Year 3 | F16: Year 4 | G16: Year 5
B17: Agile share of the domain | C17: ='Delivery Mode'!C20 -> 0.39477447 | D17: ='Delivery Mode'!D20 -> 0.85606843 | E17: ='Delivery Mode'!E20 -> 1 | F17: ='Delivery Mode'!F20 -> 1 | G17: ='Delivery Mode'!G20 -> 1
B18: Capability earned by end of year | C18: ='Logic Tree'!C45 -> 0.1398396 | D18: ='Logic Tree'!D45 -> 0.32038813 | E18: ='Logic Tree'!E45 -> 0.43128029 | F18: ='Logic Tree'!F45 -> 0.49222287 | G18: ='Logic Tree'!G45 -> 0.53192573
B19: Banked from prior year | C19: ='Logic Tree'!C50 -> 0 | D19: ='Logic Tree'!D50 -> 0.1398396 | E19: ='Logic Tree'!E50 -> 0.32038813 | F19: ='Logic Tree'!F50 -> 0.43128029 | G19: ='Logic Tree'!G50 -> 0.49222287
B20: Pre-load of this year's gain | C20: ='Logic Tree'!C51 -> 0 | D20: ='Logic Tree'!D51 -> 0.090274266 | E20: ='Logic Tree'!E51 -> 0.055446082 | F20: ='Logic Tree'!F51 -> 0.030471289 | G20: ='Logic Tree'!G51 -> 0.01985143
B21: APPLIED TO STAFFING | C21: ='Logic Tree'!C52 -> 0 | D21: ='Logic Tree'!D52 -> 0.23011386 | E21: ='Logic Tree'!E52 -> 0.37583421 | F21: ='Logic Tree'!F52 -> 0.46175158 | G21: ='Logic Tree'!G52 -> 0.5120743 | I21: Year 1 applies nothing: the capability the tree allows is consumed by transition, substrate build and the agile conversion itself.
B22: Headcount target | C22: ='Logic Tree'!C53 -> 121.5735 | D22: ='Logic Tree'!D53 -> 93.597752 | E22: ='Logic Tree'!E53 -> 75.882019 | F22: ='Logic Tree'!F53 -> 65.436744 | G22: ='Logic Tree'!G53 -> 59.318835
B23: Headcount delivered by the design | C23: ='Team Build-Up'!C9 -> 121.5 | D23: ='Team Build-Up'!D9 -> 93.5 | E23: ='Team Build-Up'!E9 -> 76 | F23: ='Team Build-Up'!F9 -> 65.5 | G23: ='Team Build-Up'!G9 -> 59.5
B24: Variance | C24: ='Team Build-Up'!C12 -> -0.0735 | D24: ='Team Build-Up'!D12 -> -0.097752193 | E24: ='Team Build-Up'!E12 -> 0.11798058 | F24: ='Team Build-Up'!F12 -> 0.063256079 | G24: ='Team Build-Up'!G12 -> 0.1811651
B25: Delivered productivity vs baseline | C25: =1-C23/$C$7 -> 0.00060457254 | D25: =1-D23/$C$7 -> 0.23091792 | E25: =1-E23/$C$7 -> 0.37486377 | F25: =1-F23/$C$7 -> 0.46123127 | G25: =1-G23/$C$7 -> 0.51058413
B26: EXIT YEAR 3 — full realisation, the point the transfer is struck | E26: ='Logic Tree'!E54 -> 69.141245
A28: C. OFFSHORE
B29: Measure | C29: Year 1 | D29: Year 2 | E29: Year 3 | F29: Year 4 | G29: Year 5
B30: Delivered — bottom-up from seat locations | C30: ='Team Build-Up'!C54 -> 0.30041152 | D30: ='Team Build-Up'!D54 -> 0.40641711 | E30: ='Team Build-Up'!E54 -> 0.49342105 | F30: ='Team Build-Up'!F54 -> 0.55725191 | G30: ='Team Build-Up'!G54 -> 0.60504202
B31: Target — today plus the closed gap | C31: ='Logic Tree'!C68 -> 0.31407757 | D31: ='Logic Tree'!D68 -> 0.40579298 | E31: ='Logic Tree'!E68 -> 0.49398088 | F31: ='Logic Tree'!F68 -> 0.55394865 | G31: ='Logic Tree'!G68 -> 0.59627884
B32: Delivered — Capgemini payroll only | C32: ='Team Build-Up'!C56 -> 0.16470588 | D32: ='Team Build-Up'!D56 -> 0.3125 | E32: ='Team Build-Up'!E56 -> 0.44117647 | F32: ='Team Build-Up'!F56 -> 0.5942029 | G32: ='Team Build-Up'!G56 -> 0.68333333
B33: Movement from today, in people | C33: =C30*'Team Build-Up'!C9-$C$12*$C$7 -> 0.0319 | D33: =D30*'Team Build-Up'!D9-$C$12*$C$7 -> 1.5319 | E33: =E30*'Team Build-Up'!E9-$C$12*$C$7 -> 1.0319 | F33: =F30*'Team Build-Up'!F9-$C$12*$C$7 -> 0.0319 | G33: =G30*'Team Build-Up'!G9-$C$12*$C$7 -> -0.4681 | I33: The offshore SHARE rises every year while the offshore HEADCOUNT falls from Year 2. Both are true and only the second one costs anything.
A35: D. THE 50:50
B36: Measure | C36: Year 1 | D36: Year 2 | E36: Year 3 | F36: Year 4 | G36: Year 5
B37: Total people | C37: ='Team Build-Up'!C9 -> 121.5 | D37: ='Team Build-Up'!D9 -> 93.5 | E37: ='Team Build-Up'!E9 -> 76 | F37: ='Team Build-Up'!F9 -> 65.5 | G37: ='Team Build-Up'!G9 -> 59.5
B38: Vendor total (Capgemini + partner) | C38: ='Team Build-Up'!C47 -> 85 | D38: ='Team Build-Up'!D47 -> 64 | E38: ='Team Build-Up'!E47 -> 51 | F38: ='Team Build-Up'!F47 -> 34.5 | G38: ='Team Build-Up'!G47 -> 30
B39: — Capgemini payroll | C39: ='Team Build-Up'!C45 -> 85 | D39: ='Team Build-Up'!D45 -> 64 | E39: ='Team Build-Up'!E45 -> 51 | F39: ='Team Build-Up'!F45 -> 34.5 | G39: ='Team Build-Up'!G45 -> 30
B40: — named sub-contractor (zero in this 領域) | C40: ='Team Build-Up'!C46 -> 0 | D40: ='Team Build-Up'!D46 -> 0 | E40: ='Team Build-Up'!E46 -> 0 | F40: ='Team Build-Up'!F46 -> 0 | G40: ='Team Build-Up'!G46 -> 0
B41: MetLife FTE | C41: ='Team Build-Up'!C48 -> 14 | D41: ='Team Build-Up'!D48 -> 11.5 | E41: ='Team Build-Up'!E48 -> 10 | F41: ='Team Build-Up'!F48 -> 15 | G41: ='Team Build-Up'!G48 -> 14
B42: MetLife MGCC | C42: ='Team Build-Up'!C49 -> 22.5 | D42: ='Team Build-Up'!D49 -> 18 | E42: ='Team Build-Up'!E49 -> 15 | F42: ='Team Build-Up'!F49 -> 16 | G42: ='Team Build-Up'!G49 -> 15.5
B43: MetLife side total | C43: =C41+C42 -> 36.5 | D43: =D41+D42 -> 29.5 | E43: =E41+E42 -> 25 | F43: =F41+F42 -> 31 | G43: =G41+G42 -> 29.5
B44: Transferred this year | C44: ='Logic Tree'!C75+'Logic Tree'!C76 -> 0 | D44: ='Logic Tree'!D75+'Logic Tree'!D76 -> 0 | E44: ='Logic Tree'!E75+'Logic Tree'!E76 -> 0 | F44: ='Logic Tree'!F75+'Logic Tree'!F76 -> 0 | G44: ='Logic Tree'!G75+'Logic Tree'!G76 -> 0
B45: RATIO — Capgemini share | C45: =IF(C37=0,0,C38/C37) -> 0.69958848 | D45: =IF(D37=0,0,D38/D37) -> 0.68449198 | E45: =IF(E37=0,0,E38/E37) -> 0.67105263 | F45: =IF(F37=0,0,F38/F37) -> 0.52671756 | G45: =IF(G37=0,0,G38/G37) -> 0.50420168
I46: Years 1-3 are the pre-transfer position. Year 4 and Year 5 already carry the transferred seats as MetLife, inside the pods.
A48: E. THE TRANSFER SOLVE — Capgemini payroll only, and here it closes
C49: Value
B50: Exit Year 3 headcount, full realisation | C50: =E26 -> 69.141245 | I50: ZERO. The whole Capgemini population is transferable — there is no sub-contractor — but none of it needs to move, because the ratio is already past 50:50 on day one.
B51: Vendor share at the exit position | C51: =E45 -> 0.67105263
B52: Vendor units at exit, before transfer | C52: =C50*C51 -> 46.397415
B53: — of which sub-contracted, IMMOVABLE | C53: =E40/E37*C50 -> 0
B54: — of which Capgemini payroll, the transfer pool | C54: =C52-C53 -> 46.397415
B55: 50:50 requires each side to be | C55: =C50/2 -> 34.570623
B56: TRANSFER REQUIRED | C56: =C52-C55 -> 11.826792 | I56: The requirement computes NEGATIVE — the model is 4.46 people the wrong side of 50:50, in MetLife's favour. Transfer applied is zero, and the row is kept so the arithmetic is visible.
B57: Cap on the transferable pool — solution constraint | C57: =0.7 -> 0.7
B58: Maximum transferable from Capgemini payroll | C58: =C54*C57 -> 32.47819
B59: Transfer applied in the model | C59: ='Logic Tree'!E77 -> 0
B60: Transfer as a share of the Capgemini pool | C60: =C59/C54 -> 0
B61: RESIDUAL GAP TO 50:50 | C61: =C56-C59 -> 11.826792 | I61: The Year-3 exit lands at exactly 50.0% and Years 4 and 5 hold there, because the transferred seats sit inside the pod anatomy rather than being re-solved each year.
B62: Ratio actually reached at the Year-3 exit | C62: =(C52-C59)/C50 -> 0.67105263
A65: F. WHAT THIS DOMAIN SHOWS
B66: • THE DISPOSITION EXPOSURE IS THE HEADLINE, NOT THE PRODUCTIVITY. C12WNC-JPN is marked RETIRE in Appendix 3 v5 and it is 35.0 units — 28.8% of this 領域 and the whole of one value stream. Pega for Claims and MDRS carry a zero Year-3 target, another 18.8 units. That is 44.3% of the domain under a disposition question, against 3% on Storage ＆ Preservation and none anywhere else. This model freezes scope at Year 1 as every domain model does, so the exposure is carried rather than netted — and it has to be resolved with MetLife before the price is fixed.
B67: • MGCC HAS A HIGHER CEILING THAN WE DO HERE, and we should say so rather than hide it. MGCC 48.60% against Capgemini 44.73%, because MGCC is a build-and-test population and 78.5% of this estate is archetype D — where Build and Test carry the highest ceilings in the classifier. Adoption still puts us ahead on committed productivity, 44.7% effective against 38.9%, because we mandate the tooling and they do not. But the underlying capability runs the other way, and a sharp reader of the model will find it.
B68: • The transfer does more work here than in any other 領域. Organic convergence moves the ratio only from 70.3% to 66.8% by Year 3, because MetLife holds just 36.1 of the 121.6 units and their side shrinks slowly. 11.6 people then transfer against 32.3 available at the 70% cap — 25% of our own pool. We send 6.4 to MetLife Japan and 5.2 to MGCC rather than the portfolio 35/65, because 84% of the Capgemini population is in Tokyo. At the default split the build-and-test guardrail breaches in Year 4 at 53.5%.
B69: • The productivity case is solid and unremarkable. AI ceiling 44.71% blended, capability 14.0 / 32.0 / 43.1 / 49.2 / 53.2%, applied glidepath 0 / 23.0 / 37.6 / 46.2 / 51.2%. Headcount goes 121.6 → 59.3, a 51.2% reduction in line with the three other 領域 whose five-year plan is fully solved. The offshore case is the weaker half: 30.0% today against a 65.3% ceiling, held down by W05AMS-JPN at 12%, and 84% of the vendor population sits in Tokyo on day one.
B70: • The continuity risk is the highest in the estate. Six Capgemini people against 85.4 vendor units, all six on Claim Batch. On C12WNC-JPN, W05AMS-JPN, Pega, MDRS and WZZMNB-JPN we start from nothing — and NCD, who hold 60% of the vendor side, are modelled as absorbed rather than retained. Year 1 is therefore a large transition on applications where we have no institutional memory, four of which run on Japanese specifications.
B71: • The one number to challenge is MetLife's own. The Maintenance role line says 1.00 unit of run against 732 incidents and 1,161 changes a year, while the AD / AMS effort split in the same spreadsheet implies 6.75 units — a factor of seven, the widest disagreement of any 領域 modelled. And ZERO project management is recorded across six applications and three value streams. We restate both, arithmetically neutral, and views is about six people of exposure on a 122-person domain. It sets the AMS price, so it should be resolved before submission.

Sheet Cost & Commercial
A1: Cost and commercial position — relative index pending the rate card
A2: Onshore Tokyo E2 = 1.00. Unit cost divides by the frozen baseline effort.
A4: A. TOTAL COST OF DELIVERING THE DOMAIN
B5: Measure | C5: Year 1 | D5: Year 2 | E5: Year 3 | F5: Year 4 | G5: Year 5
B6: Total cost index | C6: =SUMIFS('Seat Ledger'!$N$5:$N$287,'Seat Ledger'!$B$5:$B$287,1) -> 148.425 | D6: =SUMIFS('Seat Ledger'!$N$5:$N$287,'Seat Ledger'!$B$5:$B$287,2) -> 109.36 | E6: =SUMIFS('Seat Ledger'!$N$5:$N$287,'Seat Ledger'!$B$5:$B$287,3) -> 86.735 | F6: =SUMIFS('Seat Ledger'!$N$5:$N$287,'Seat Ledger'!$B$5:$B$287,4) -> 66.2 | G6: =SUMIFS('Seat Ledger'!$N$5:$N$287,'Seat Ledger'!$B$5:$B$287,5) -> 57.615
B7: Headcount | C7: ='Team Build-Up'!C9 -> 121.5 | D7: ='Team Build-Up'!D9 -> 93.5 | E7: ='Team Build-Up'!E9 -> 76 | F7: ='Team Build-Up'!F9 -> 65.5 | G7: ='Team Build-Up'!G9 -> 59.5
B8: Average cost per head | C8: =IF(C7=0,0,C6/C7) -> 1.2216049 | D8: =IF(D7=0,0,D6/D7) -> 1.1696257 | E8: =IF(E7=0,0,E6/E7) -> 1.14125 | F8: =IF(F7=0,0,F6/F7) -> 1.010687 | G8: =IF(G7=0,0,G6/G7) -> 0.96831933
B9: Cost per unit of frozen scope | C9: =IF('Glidepath & 50-50'!$C$7=0,0,C6/'Glidepath & 50-50'!$C$7) -> 1.2208664 | D9: =IF('Glidepath & 50-50'!$C$7=0,0,D6/'Glidepath & 50-50'!$C$7) -> 0.89953814 | E9: =IF('Glidepath & 50-50'!$C$7=0,0,E6/'Glidepath & 50-50'!$C$7) -> 0.71343673 | F9: =IF('Glidepath & 50-50'!$C$7=0,0,F6/'Glidepath & 50-50'!$C$7) -> 0.54452656 | G9: =IF('Glidepath & 50-50'!$C$7=0,0,G6/'Glidepath & 50-50'!$C$7) -> 0.47391084
B10: Unit cost reduction vs Year 1 | C10: =IF($C$9=0,0,1-C9/$C$9) -> 0 | D10: =IF($C$9=0,0,1-D9/$C$9) -> 0.2631969 | E10: =IF($C$9=0,0,1-E9/$C$9) -> 0.41563079 | F10: =IF($C$9=0,0,1-F9/$C$9) -> 0.55398349 | G10: =IF($C$9=0,0,1-G9/$C$9) -> 0.61182415
A12: B. CAPGEMINI POSITION
B13: Measure | C13: Year 1 | D13: Year 2 | E13: Year 3 | F13: Year 4 | G13: Year 5
B14: Capgemini heads | C14: ='Team Build-Up'!C45 -> 85 | D14: ='Team Build-Up'!D45 -> 64 | E14: ='Team Build-Up'!E45 -> 51 | F14: ='Team Build-Up'!F45 -> 34.5 | G14: ='Team Build-Up'!G45 -> 30
B15: Capgemini cost index | C15: =SUMIFS('Seat Ledger'!$N$5:$N$287,'Seat Ledger'!$B$5:$B$287,1,'Seat Ledger'!$J$5:$J$287,"FTC") -> 114.025 | D15: =SUMIFS('Seat Ledger'!$N$5:$N$287,'Seat Ledger'!$B$5:$B$287,2,'Seat Ledger'!$J$5:$J$287,"FTC") -> 81.775 | E15: =SUMIFS('Seat Ledger'!$N$5:$N$287,'Seat Ledger'!$B$5:$B$287,3,'Seat Ledger'!$J$5:$J$287,"FTC") -> 62.355 | F15: =SUMIFS('Seat Ledger'!$N$5:$N$287,'Seat Ledger'!$B$5:$B$287,4,'Seat Ledger'!$J$5:$J$287,"FTC") -> 32.69 | G15: =SUMIFS('Seat Ledger'!$N$5:$N$287,'Seat Ledger'!$B$5:$B$287,5,'Seat Ledger'!$J$5:$J$287,"FTC") -> 24.725
B16: Capgemini position vs Year 1 | C16: =IF($C$15=0,0,C15/$C$15-1) -> 0 | D16: =IF($C$15=0,0,D15/$C$15-1) -> -0.28283271 | E16: =IF($C$15=0,0,E15/$C$15-1) -> -0.45314624 | F16: =IF($C$15=0,0,F15/$C$15-1) -> -0.71330848 | G16: =IF($C$15=0,0,G15/$C$15-1) -> -0.78316159
A18: C. COST BY LOCATION, BAND AND ROLE
B19: Split | C19: Year 1 | D19: Year 2 | E19: Year 3 | F19: Year 4 | G19: Year 5
B20: Onshore Tokyo — cost index | C20: =SUMIFS('Seat Ledger'!$N$5:$N$287,'Seat Ledger'!$B$5:$B$287,1,'Seat Ledger'!$I$5:$I$287,"ON") -> 129.975 | D20: =SUMIFS('Seat Ledger'!$N$5:$N$287,'Seat Ledger'!$B$5:$B$287,2,'Seat Ledger'!$I$5:$I$287,"ON") -> 93.2 | E20: =SUMIFS('Seat Ledger'!$N$5:$N$287,'Seat Ledger'!$B$5:$B$287,3,'Seat Ledger'!$I$5:$I$287,"ON") -> 72.075 | F20: =SUMIFS('Seat Ledger'!$N$5:$N$287,'Seat Ledger'!$B$5:$B$287,4,'Seat Ledger'!$I$5:$I$287,"ON") -> 52.9 | G20: =SUMIFS('Seat Ledger'!$N$5:$N$287,'Seat Ledger'!$B$5:$B$287,5,'Seat Ledger'!$I$5:$I$287,"ON") -> 43.025
B21: Offshore — cost index | C21: =SUMIFS('Seat Ledger'!$N$5:$N$287,'Seat Ledger'!$B$5:$B$287,1,'Seat Ledger'!$I$5:$I$287,"OFF") -> 10.8 | D21: =SUMIFS('Seat Ledger'!$N$5:$N$287,'Seat Ledger'!$B$5:$B$287,2,'Seat Ledger'!$I$5:$I$287,"OFF") -> 13.35 | E21: =SUMIFS('Seat Ledger'!$N$5:$N$287,'Seat Ledger'!$B$5:$B$287,3,'Seat Ledger'!$I$5:$I$287,"OFF") -> 14.04 | F21: =SUMIFS('Seat Ledger'!$N$5:$N$287,'Seat Ledger'!$B$5:$B$287,4,'Seat Ledger'!$I$5:$I$287,"OFF") -> 12.99 | G21: =SUMIFS('Seat Ledger'!$N$5:$N$287,'Seat Ledger'!$B$5:$B$287,5,'Seat Ledger'!$I$5:$I$287,"OFF") -> 14.28
B22: Nearshore — cost index | C22: =SUMIFS('Seat Ledger'!$N$5:$N$287,'Seat Ledger'!$B$5:$B$287,1,'Seat Ledger'!$I$5:$I$287,"NEAR") -> 7.65 | D22: =SUMIFS('Seat Ledger'!$N$5:$N$287,'Seat Ledger'!$B$5:$B$287,2,'Seat Ledger'!$I$5:$I$287,"NEAR") -> 2.81 | E22: =SUMIFS('Seat Ledger'!$N$5:$N$287,'Seat Ledger'!$B$5:$B$287,3,'Seat Ledger'!$I$5:$I$287,"NEAR") -> 0.62 | F22: =SUMIFS('Seat Ledger'!$N$5:$N$287,'Seat Ledger'!$B$5:$B$287,4,'Seat Ledger'!$I$5:$I$287,"NEAR") -> 0.31 | G22: =SUMIFS('Seat Ledger'!$N$5:$N$287,'Seat Ledger'!$B$5:$B$287,5,'Seat Ledger'!$I$5:$I$287,"NEAR") -> 0.31
B23: Onshore share of cost | C23: =IF(SUM(C20:C22)=0,0,C20/SUM(C20:C22)) -> 0.8756948 | D23: =IF(SUM(D20:D22)=0,0,D20/SUM(D20:D22)) -> 0.85223116 | E23: =IF(SUM(E20:E22)=0,0,E20/SUM(E20:E22)) -> 0.83097942 | F23: =IF(SUM(F20:F22)=0,0,F20/SUM(F20:F22)) -> 0.79909366 | G23: =IF(SUM(G20:G22)=0,0,G20/SUM(G20:G22)) -> 0.74676733
B25: BSA — business and systems analysis — cost index | C25: =SUMIFS('Seat Ledger'!$N$5:$N$287,'Seat Ledger'!$B$5:$B$287,1,'Seat Ledger'!$G$5:$G$287,"BSA") -> 16.21 | D25: =SUMIFS('Seat Ledger'!$N$5:$N$287,'Seat Ledger'!$B$5:$B$287,2,'Seat Ledger'!$G$5:$G$287,"BSA") -> 19.26 | E25: =SUMIFS('Seat Ledger'!$N$5:$N$287,'Seat Ledger'!$B$5:$B$287,3,'Seat Ledger'!$G$5:$G$287,"BSA") -> 19.045 | F25: =SUMIFS('Seat Ledger'!$N$5:$N$287,'Seat Ledger'!$B$5:$B$287,4,'Seat Ledger'!$G$5:$G$287,"BSA") -> 16.46 | G25: =SUMIFS('Seat Ledger'!$N$5:$N$287,'Seat Ledger'!$B$5:$B$287,5,'Seat Ledger'!$G$5:$G$287,"BSA") -> 10.31
B26: Developer — cost index | C26: =SUMIFS('Seat Ledger'!$N$5:$N$287,'Seat Ledger'!$B$5:$B$287,1,'Seat Ledger'!$G$5:$G$287,"DEV") -> 86.92 | D26: =SUMIFS('Seat Ledger'!$N$5:$N$287,'Seat Ledger'!$B$5:$B$287,2,'Seat Ledger'!$G$5:$G$287,"DEV") -> 40.585 | E26: =SUMIFS('Seat Ledger'!$N$5:$N$287,'Seat Ledger'!$B$5:$B$287,3,'Seat Ledger'!$G$5:$G$287,"DEV") -> 26.55 | F26: =SUMIFS('Seat Ledger'!$N$5:$N$287,'Seat Ledger'!$B$5:$B$287,4,'Seat Ledger'!$G$5:$G$287,"DEV") -> 17.35 | G26: =SUMIFS('Seat Ledger'!$N$5:$N$287,'Seat Ledger'!$B$5:$B$287,5,'Seat Ledger'!$G$5:$G$287,"DEV") -> 16.795
B27: Tester — cost index | C27: =SUMIFS('Seat Ledger'!$N$5:$N$287,'Seat Ledger'!$B$5:$B$287,1,'Seat Ledger'!$G$5:$G$287,"TEST") -> 10.515 | D27: =SUMIFS('Seat Ledger'!$N$5:$N$287,'Seat Ledger'!$B$5:$B$287,2,'Seat Ledger'!$G$5:$G$287,"TEST") -> 9.865 | E27: =SUMIFS('Seat Ledger'!$N$5:$N$287,'Seat Ledger'!$B$5:$B$287,3,'Seat Ledger'!$G$5:$G$287,"TEST") -> 3.77 | F27: =SUMIFS('Seat Ledger'!$N$5:$N$287,'Seat Ledger'!$B$5:$B$287,4,'Seat Ledger'!$G$5:$G$287,"TEST") -> 5.035 | G27: =SUMIFS('Seat Ledger'!$N$5:$N$287,'Seat Ledger'!$B$5:$B$287,5,'Seat Ledger'!$G$5:$G$287,"TEST") -> 4.105
B28: Maintenance — cost index | C28: =SUMIFS('Seat Ledger'!$N$5:$N$287,'Seat Ledger'!$B$5:$B$287,1,'Seat Ledger'!$G$5:$G$287,"MNT") -> 9.135 | D28: =SUMIFS('Seat Ledger'!$N$5:$N$287,'Seat Ledger'!$B$5:$B$287,2,'Seat Ledger'!$G$5:$G$287,"MNT") -> 6.86 | E28: =SUMIFS('Seat Ledger'!$N$5:$N$287,'Seat Ledger'!$B$5:$B$287,3,'Seat Ledger'!$G$5:$G$287,"MNT") -> 2.97 | F28: =SUMIFS('Seat Ledger'!$N$5:$N$287,'Seat Ledger'!$B$5:$B$287,4,'Seat Ledger'!$G$5:$G$287,"MNT") -> 5.76 | G28: =SUMIFS('Seat Ledger'!$N$5:$N$287,'Seat Ledger'!$B$5:$B$287,5,'Seat Ledger'!$G$5:$G$287,"MNT") -> 7.36
B29: PM and product ownership — cost index | C29: =SUMIFS('Seat Ledger'!$N$5:$N$287,'Seat Ledger'!$B$5:$B$287,1,'Seat Ledger'!$G$5:$G$287,"PM") -> 19.2 | D29: =SUMIFS('Seat Ledger'!$N$5:$N$287,'Seat Ledger'!$B$5:$B$287,2,'Seat Ledger'!$G$5:$G$287,"PM") -> 12.375 | E29: =SUMIFS('Seat Ledger'!$N$5:$N$287,'Seat Ledger'!$B$5:$B$287,3,'Seat Ledger'!$G$5:$G$287,"PM") -> 13.3 | F29: =SUMIFS('Seat Ledger'!$N$5:$N$287,'Seat Ledger'!$B$5:$B$287,4,'Seat Ledger'!$G$5:$G$287,"PM") -> 15.15 | G29: =SUMIFS('Seat Ledger'!$N$5:$N$287,'Seat Ledger'!$B$5:$B$287,5,'Seat Ledger'!$G$5:$G$287,"PM") -> 15.15
B30: Other — architecture and enablement — cost index | C30: =SUMIFS('Seat Ledger'!$N$5:$N$287,'Seat Ledger'!$B$5:$B$287,1,'Seat Ledger'!$G$5:$G$287,"OTH") -> 6.445 | D30: =SUMIFS('Seat Ledger'!$N$5:$N$287,'Seat Ledger'!$B$5:$B$287,2,'Seat Ledger'!$G$5:$G$287,"OTH") -> 20.415 | E30: =SUMIFS('Seat Ledger'!$N$5:$N$287,'Seat Ledger'!$B$5:$B$287,3,'Seat Ledger'!$G$5:$G$287,"OTH") -> 21.1 | F30: =SUMIFS('Seat Ledger'!$N$5:$N$287,'Seat Ledger'!$B$5:$B$287,4,'Seat Ledger'!$G$5:$G$287,"OTH") -> 6.445 | G30: =SUMIFS('Seat Ledger'!$N$5:$N$287,'Seat Ledger'!$B$5:$B$287,5,'Seat Ledger'!$G$5:$G$287,"OTH") -> 3.895
B32: The role view is the one Pricing will want: it says what each of MetLife's own six role lines costs, which is the natural unit for a per-role rate card.

Sheet Seat Ledger
A1: Seat ledger — every pod-library line multiplied out, plus every horizontal seat
A2: Computed. Every roll-up in this workbook is a SUMIFS over this one table. Do not edit.
B4: Year | C4: Origin | D4: Unit | E4: Type | F4: Role detail | G4: Role | H4: Exp | I4: Loc | J4: Sourcing | K4: Seats/unit | L4: Units | M4: Heads | N4: Cost index
B5: 1 | C5: POD | D5: AMP | E5: POD | F5: ='Pod Library'!E5 -> MetLife Claims Product Owner | G5: ='Pod Library'!F5 -> PM | H5: ='Pod Library'!G5 -> E4 | I5: ='Pod Library'!H5 -> ON | J5: ='Pod Library'!I5 -> FTE | K5: ='Pod Library'!J5 -> 0.25 | L5: ='Pod Plan'!E5 -> 2 | M5: =K5*L5 -> 0.5 | N5: =M5*INDEX('Logic Tree'!$J$85:$N$87,MATCH(I5,'Logic Tree'!$I$85:$I$87,0),MATCH(H5,'Logic Tree'!$J$84:$N$84,0)) -> 0.925
B6: 1 | C6: POD | D6: AMP | E6: POD | F6: ='Pod Library'!E6 -> MetLife Claims SME | G6: ='Pod Library'!F6 -> BSA | H6: ='Pod Library'!G6 -> E4 | I6: ='Pod Library'!H6 -> ON | J6: ='Pod Library'!I6 -> FTE | K6: ='Pod Library'!J6 -> 0.25 | L6: ='Pod Plan'!E5 -> 2 | M6: =K6*L6 -> 0.5 | N6: =M6*INDEX('Logic Tree'!$J$85:$N$87,MATCH(I6,'Logic Tree'!$I$85:$I$87,0),MATCH(H6,'Logic Tree'!$J$84:$N$84,0)) -> 0.925
B7: 1 | C7: POD | D7: AMP | E7: POD | F7: ='Pod Library'!E7 -> Business Analyst (bilingual) | G7: ='Pod Library'!F7 -> BSA | H7: ='Pod Library'!G7 -> E3 | I7: ='Pod Library'!H7 -> ON | J7: ='Pod Library'!I7 -> FTC | K7: ='Pod Library'!J7 -> 0.375 | L7: ='Pod Plan'!E5 -> 2 | M7: =K7*L7 -> 0.75 | N7: =M7*INDEX('Logic Tree'!$J$85:$N$87,MATCH(I7,'Logic Tree'!$I$85:$I$87,0),MATCH(H7,'Logic Tree'!$J$84:$N$84,0)) -> 1.0125
B8: 1 | C8: POD | D8: AMP | E8: POD | F8: ='Pod Library'!E8 -> Pod lead / senior engineer | G8: ='Pod Library'!F8 -> DEV | H8: ='Pod Library'!G8 -> E4 | I8: ='Pod Library'!H8 -> ON | J8: ='Pod Library'!I8 -> FTC | K8: ='Pod Library'!J8 -> 2.375 | L8: ='Pod Plan'!E5 -> 2 | M8: =K8*L8 -> 4.75 | N8: =M8*INDEX('Logic Tree'!$J$85:$N$87,MATCH(I8,'Logic Tree'!$I$85:$I$87,0),MATCH(H8,'Logic Tree'!$J$84:$N$84,0)) -> 8.7875
B9: 1 | C9: POD | D9: AMP | E9: POD | F9: ='Pod Library'!E9 -> Claims Engineer | G9: ='Pod Library'!F9 -> DEV | H9: ='Pod Library'!G9 -> E3 | I9: ='Pod Library'!H9 -> OFF | J9: ='Pod Library'!I9 -> FTC | K9: ='Pod Library'!J9 -> 0 | L9: ='Pod Plan'!E5 -> 2 | M9: =K9*L9 -> 0 | N9: =M9*INDEX('Logic Tree'!$J$85:$N$87,MATCH(I9,'Logic Tree'!$I$85:$I$87,0),MATCH(H9,'Logic Tree'!$J$84:$N$84,0)) -> 0
B10: 1 | C10: POD | D10: AMP | E10: POD | F10: ='Pod Library'!E10 -> Claims Engineer | G10: ='Pod Library'!F10 -> DEV | H10: ='Pod Library'!G10 -> E2 | I10: ='Pod Library'!H10 -> OFF | J10: ='Pod Library'!I10 -> FTC | K10: ='Pod Library'!J10 -> 0.25 | L10: ='Pod Plan'!E5 -> 2 | M10: =K10*L10 -> 0.5 | N10: =M10*INDEX('Logic Tree'!$J$85:$N$87,MATCH(I10,'Logic Tree'!$I$85:$I$87,0),MATCH(H10,'Logic Tree'!$J$84:$N$84,0)) -> 0.15
B11: 1 | C11: POD | D11: AMP | E11: POD | F11: ='Pod Library'!E11 -> MGCC Payments Engineer | G11: ='Pod Library'!F11 -> DEV | H11: ='Pod Library'!G11 -> E3 | I11: ='Pod Library'!H11 -> OFF | J11: ='Pod Library'!I11 -> MGCC | K11: ='Pod Library'!J11 -> 1.375 | L11: ='Pod Plan'!E5 -> 2 | M11: =K11*L11 -> 2.75 | N11: =M11*INDEX('Logic Tree'!$J$85:$N$87,MATCH(I11,'Logic Tree'!$I$85:$I$87,0),MATCH(H11,'Logic Tree'!$J$84:$N$84,0)) -> 1.155
B12: 1 | C12: POD | D12: AMP | E12: POD | F12: ='Pod Library'!E12 -> SDET / Automation Engineer | G12: ='Pod Library'!F12 -> TEST | H12: ='Pod Library'!G12 -> E3 | I12: ='Pod Library'!H12 -> OFF | J12: ='Pod Library'!I12 -> FTC | K12: ='Pod Library'!J12 -> 0 | L12: ='Pod Plan'!E5 -> 2 | M12: =K12*L12 -> 0 | N12: =M12*INDEX('Logic Tree'!$J$85:$N$87,MATCH(I12,'Logic Tree'!$I$85:$I$87,0),MATCH(H12,'Logic Tree'!$J$84:$N$84,0)) -> 0
B13: 1 | C13: POD | D13: AMP | E13: POD | F13: ='Pod Library'!E13 -> MGCC Quality Engineer | G13: ='Pod Library'!F13 -> TEST | H13: ='Pod Library'!G13 -> E2 | I13: ='Pod Library'!H13 -> OFF | J13: ='Pod Library'!I13 -> MGCC | K13: ='Pod Library'!J13 -> 0.75 | L13: ='Pod Plan'!E5 -> 2 | M13: =K13*L13 -> 1.5 | N13: =M13*INDEX('Logic Tree'!$J$85:$N$87,MATCH(I13,'Logic Tree'!$I$85:$I$87,0),MATCH(H13,'Logic Tree'!$J$84:$N$84,0)) -> 0.45
B14: 1 | C14: POD | D14: AMP | E14: POD | F14: ='Pod Library'!E14 -> Solution Architect | G14: ='Pod Library'!F14 -> OTH | H14: ='Pod Library'!G14 -> E5 | I14: ='Pod Library'!H14 -> ON | J14: ='Pod Library'!I14 -> FTC | K14: ='Pod Library'!J14 -> 0.375 | L14: ='Pod Plan'!E5 -> 2 | M14: =K14*L14 -> 0.75 | N14: =M14*INDEX('Logic Tree'!$J$85:$N$87,MATCH(I14,'Logic Tree'!$I$85:$I$87,0),MATCH(H14,'Logic Tree'!$J$84:$N$84,0)) -> 1.9125
B15: 1 | C15: TEAM | D15: AMP | E15: TEAM | F15: ='Pod Library'!E17 -> MetLife Claims Product Owner | G15: ='Pod Library'!F17 -> PM | H15: ='Pod Library'!G17 -> E4 | I15: ='Pod Library'!H17 -> ON | J15: ='Pod Library'!I17 -> FTE | K15: ='Pod Library'!J17 -> 0.7 | L15: ='Pod Plan'!F5 -> 3 | M15: =K15*L15 -> 2.1 | N15: =M15*INDEX('Logic Tree'!$J$85:$N$87,MATCH(I15,'Logic Tree'!$I$85:$I$87,0),MATCH(H15,'Logic Tree'!$J$84:$N$84,0)) -> 3.885
B16: 1 | C16: TEAM | D16: AMP | E16: TEAM | F16: ='Pod Library'!E18 -> MetLife Claims SME | G16: ='Pod Library'!F18 -> BSA | H16: ='Pod Library'!G18 -> E4 | I16: ='Pod Library'!H18 -> ON | J16: ='Pod Library'!I18 -> FTE | K16: ='Pod Library'!J18 -> 0.8 | L16: ='Pod Plan'!F5 -> 3 | M16: =K16*L16 -> 2.4 | N16: =M16*INDEX('Logic Tree'!$J$85:$N$87,MATCH(I16,'Logic Tree'!$I$85:$I$87,0),MATCH(H16,'Logic Tree'!$J$84:$N$84,0)) -> 4.44
B17: 1 | C17: TEAM | D17: AMP | E17: TEAM | F17: ='Pod Library'!E19 -> MetLife Operations Analyst | G17: ='Pod Library'!F19 -> MNT | H17: ='Pod Library'!G19 -> E3 | I17: ='Pod Library'!H19 -> ON | J17: ='Pod Library'!I19 -> FTE | K17: ='Pod Library'!J19 -> 0.2 | L17: ='Pod Plan'!F5 -> 3 | M17: =K17*L17 -> 0.6 | N17: =M17*INDEX('Logic Tree'!$J$85:$N$87,MATCH(I17,'Logic Tree'!$I$85:$I$87,0),MATCH(H17,'Logic Tree'!$J$84:$N$84,0)) -> 0.81
B18: 1 | C18: TEAM | D18: AMP | E18: TEAM | F18: ='Pod Library'!E20 -> Business Analyst (bilingual) | G18: ='Pod Library'!F20 -> BSA | H18: ='Pod Library'!G20 -> E3 | I18: ='Pod Library'!H20 -> ON | J18: ='Pod Library'!I20 -> FTC | K18: ='Pod Library'!J20 -> 0.4 | L18: ='Pod Plan'!F5 -> 3 | M18: =K18*L18 -> 1.2 | N18: =M18*INDEX('Logic Tree'!$J$85:$N$87,MATCH(I18,'Logic Tree'!$I$85:$I$87,0),MATCH(H18,'Logic Tree'!$J$84:$N$84,0)) -> 1.62
B19: 1 | C19: TEAM | D19: AMP | E19: TEAM | F19: ='Pod Library'!E21 -> Team lead / senior engineer | G19: ='Pod Library'!F21 -> DEV | H19: ='Pod Library'!G21 -> E4 | I19: ='Pod Library'!H21 -> ON | J19: ='Pod Library'!I21 -> FTC | K19: ='Pod Library'!J21 -> 1.7 | L19: ='Pod Plan'!F5 -> 3 | M19: =K19*L19 -> 5.1 | N19: =M19*INDEX('Logic Tree'!$J$85:$N$87,MATCH(I19,'Logic Tree'!$I$85:$I$87,0),MATCH(H19,'Logic Tree'!$J$84:$N$84,0)) -> 9.435
B20: 1 | C20: TEAM | D20: AMP | E20: TEAM | F20: ='Pod Library'!E22 -> Application Developer | G20: ='Pod Library'!F22 -> DEV | H20: ='Pod Library'!G22 -> E3 | I20: ='Pod Library'!H22 -> ON | J20: ='Pod Library'!I22 -> FTC | K20: ='Pod Library'!J22 -> 3.2 | L20: ='Pod Plan'!F5 -> 3 | M20: =K20*L20 -> 9.6 | N20: =M20*INDEX('Logic Tree'!$J$85:$N$87,MATCH(I20,'Logic Tree'!$I$85:$I$87,0),MATCH(H20,'Logic Tree'!$J$84:$N$84,0)) -> 12.96
B21: 1 | C21: TEAM | D21: AMP | E21: TEAM | F21: ='Pod Library'!E23 -> Application Developer | G21: ='Pod Library'!F23 -> DEV | H21: ='Pod Library'!G23 -> E2 | I21: ='Pod Library'!H23 -> ON | J21: ='Pod Library'!I23 -> FTC | K21: ='Pod Library'!J23 -> 3.5 | L21: ='Pod Plan'!F5 -> 3 | M21: =K21*L21 -> 10.5 | N21: =M21*INDEX('Logic Tree'!$J$85:$N$87,MATCH(I21,'Logic Tree'!$I$85:$I$87,0),MATCH(H21,'Logic Tree'!$J$84:$N$84,0)) -> 10.5
B22: 1 | C22: TEAM | D22: AMP | E22: TEAM | F22: ='Pod Library'!E24 -> Application Developer | G22: ='Pod Library'!F24 -> DEV | H22: ='Pod Library'!G24 -> E3 | I22: ='Pod Library'!H24 -> NEAR | J22: ='Pod Library'!I24 -> FTC | K22: ='Pod Library'!J24 -> 1.6 | L22: ='Pod Plan'!F5 -> 3 | M22: =K22*L22 -> 4.8 | N22: =M22*INDEX('Logic Tree'!$J$85:$N$87,MATCH(I22,'Logic Tree'!$I$85:$I$87,0),MATCH(H22,'Logic Tree'!$J$84:$N$84,0)) -> 4.032
B23: 1 | C23: TEAM | D23: AMP | E23: TEAM | F23: ='Pod Library'!E25 -> Test Analyst | G23: ='Pod Library'!F25 -> TEST | H23: ='Pod Library'!G25 -> E3 | I23: ='Pod Library'!H25 -> ON | J23: ='Pod Library'!I25 -> FTC | K23: ='Pod Library'!J25 -> 1 | L23: ='Pod Plan'!F5 -> 3 | M23: =K23*L23 -> 3 | N23: =M23*INDEX('Logic Tree'!$J$85:$N$87,MATCH(I23,'Logic Tree'!$I$85:$I$87,0),MATCH(H23,'Logic Tree'!$J$84:$N$84,0)) -> 4.05
B24: 1 | C24: TEAM | D24: AMP | E24: TEAM | F24: ='Pod Library'!E26 -> Test Engineer | G24: ='Pod Library'!F26 -> TEST | H24: ='Pod Library'!G26 -> E2 | I24: ='Pod Library'!H26 -> NEAR | J24: ='Pod Library'!I26 -> FTC | K24: ='Pod Library'!J26 -> 0.2 | L24: ='Pod Plan'!F5 -> 3 | M24: =K24*L24 -> 0.6 | N24: =M24*INDEX('Logic Tree'!$J$85:$N$87,MATCH(I24,'Logic Tree'!$I$85:$I$87,0),MATCH(H24,'Logic Tree'!$J$84:$N$84,0)) -> 0.372
B25: 1 | C25: TEAM | D25: AMP | E25: TEAM | F25: ='Pod Library'!E27 -> MGCC Payments Engineer | G25: ='Pod Library'!F27 -> DEV | H25: ='Pod Library'!G27 -> E3 | I25: ='Pod Library'!H27 -> OFF | J25: ='Pod Library'!I27 -> MGCC | K25: ='Pod Library'!J27 -> 1.9 | L25: ='Pod Plan'!F5 -> 3 | M25: =K25*L25 -> 5.7 | N25: =M25*INDEX('Logic Tree'!$J$85:$N$87,MATCH(I25,'Logic Tree'!$I$85:$I$87,0),MATCH(H25,'Logic Tree'!$J$84:$N$84,0)) -> 2.394
B26: 1 | C26: TEAM | D26: AMP | E26: TEAM | F26: ='Pod Library'!E28 -> Technical Lead | G26: ='Pod Library'!F28 -> OTH | H26: ='Pod Library'!G28 -> E4 | I26: ='Pod Library'!H28 -> ON | J26: ='Pod Library'!I28 -> FTC | K26: ='Pod Library'!J28 -> 0 | L26: ='Pod Plan'!F5 -> 3 | M26: =K26*L26 -> 0 | N26: =M26*INDEX('Logic Tree'!$J$85:$N$87,MATCH(I26,'Logic Tree'!$I$85:$I$87,0),MATCH(H26,'Logic Tree'!$J$84:$N$84,0)) -> 0
B27: 1 | C27: TEAM | D27: CPA | E27: TEAM | F27: ='Pod Library'!E17 -> MetLife Claims Product Owner | G27: ='Pod Library'!F17 -> PM | H27: ='Pod Library'!G17 -> E4 | I27: ='Pod Library'!H17 -> ON | J27: ='Pod Library'!I17 -> FTE | K27: ='Pod Library'!J17 -> 0.7 | L27: ='Pod Plan'!F6 -> 2 | M27: =K27*L27 -> 1.4 | N27: =M27*INDEX('Logic Tree'!$J$85:$N$87,MATCH(I27,'Logic Tree'!$I$85:$I$87,0),MATCH(H27,'Logic Tree'!$J$84:$N$84,0)) -> 2.59
B28: 1 | C28: TEAM | D28: CPA | E28: TEAM | F28: ='Pod Library'!E18 -> MetLife Claims SME | G28: ='Pod Library'!F18 -> BSA | H28: ='Pod Library'!G18 -> E4 | I28: ='Pod Library'!H18 -> ON | J28: ='Pod Library'!I18 -> FTE | K28: ='Pod Library'!J18 -> 0.8 | L28: ='Pod Plan'!F6 -> 2 | M28: =K28*L28 -> 1.6 | N28: =M28*INDEX('Logic Tree'!$J$85:$N$87,MATCH(I28,'Logic Tree'!$I$85:$I$87,0),MATCH(H28,'Logic Tree'!$J$84:$N$84,0)) -> 2.96
B29: 1 | C29: TEAM | D29: CPA | E29: TEAM | F29: ='Pod Library'!E19 -> MetLife Operations Analyst | G29: ='Pod Library'!F19 -> MNT | H29: ='Pod Library'!G19 -> E3 | I29: ='Pod Library'!H19 -> ON | J29: ='Pod Library'!I19 -> FTE | K29: ='Pod Library'!J19 -> 0.2 | L29: ='Pod Plan'!F6 -> 2 | M29: =K29*L29 -> 0.4 | N29: =M29*INDEX('Logic Tree'!$J$85:$N$87,MATCH(I29,'Logic Tree'!$I$85:$I$87,0),MATCH(H29,'Logic Tree'!$J$84:$N$84,0)) -> 0.54
B30: 1 | C30: TEAM | D30: CPA | E30: TEAM | F30: ='Pod Library'!E20 -> Business Analyst (bilingual) | G30: ='Pod Library'!F20 -> BSA | H30: ='Pod Library'!G20 -> E3 | I30: ='Pod Library'!H20 -> ON | J30: ='Pod Library'!I20 -> FTC | K30: ='Pod Library'!J20 -> 0.4 | L30: ='Pod Plan'!F6 -> 2 | M30: =K30*L30 -> 0.8 | N30: =M30*INDEX('Logic Tree'!$J$85:$N$87,MATCH(I30,'Logic Tree'!$I$85:$I$87,0),MATCH(H30,'Logic Tree'!$J$84:$N$84,0)) -> 1.08
B31: 1 | C31: TEAM | D31: CPA | E31: TEAM | F31: ='Pod Library'!E21 -> Team lead / senior engineer | G31: ='Pod Library'!F21 -> DEV | H31: ='Pod Library'!G21 -> E4 | I31: ='Pod Library'!H21 -> ON | J31: ='Pod Library'!I21 -> FTC | K31: ='Pod Library'!J21 -> 1.7 | L31: ='Pod Plan'!F6 -> 2 | M31: =K31*L31 -> 3.4 | N31: =M31*INDEX('Logic Tree'!$J$85:$N$87,MATCH(I31,'Logic Tree'!$I$85:$I$87,0),MATCH(H31,'Logic Tree'!$J$84:$N$84,0)) -> 6.29
B32: 1 | C32: TEAM | D32: CPA | E32: TEAM | F32: ='Pod Library'!E22 -> Application Developer | G32: ='Pod Library'!F22 -> DEV | H32: ='Pod Library'!G22 -> E3 | I32: ='Pod Library'!H22 -> ON | J32: ='Pod Library'!I22 -> FTC | K32: ='Pod Library'!J22 -> 3.2 | L32: ='Pod Plan'!F6 -> 2 | M32: =K32*L32 -> 6.4 | N32: =M32*INDEX('Logic Tree'!$J$85:$N$87,MATCH(I32,'Logic Tree'!$I$85:$I$87,0),MATCH(H32,'Logic Tree'!$J$84:$N$84,0)) -> 8.64
B33: 1 | C33: TEAM | D33: CPA | E33: TEAM | F33: ='Pod Library'!E23 -> Application Developer | G33: ='Pod Library'!F23 -> DEV | H33: ='Pod Library'!G23 -> E2 | I33: ='Pod Library'!H23 -> ON | J33: ='Pod Library'!I23 -> FTC | K33: ='Pod Library'!J23 -> 3.5 | L33: ='Pod Plan'!F6 -> 2 | M33: =K33*L33 -> 7 | N33: =M33*INDEX('Logic Tree'!$J$85:$N$87,MATCH(I33,'Logic Tree'!$I$85:$I$87,0),MATCH(H33,'Logic Tree'!$J$84:$N$84,0)) -> 7
B34: 1 | C34: TEAM | D34: CPA | E34: TEAM | F34: ='Pod Library'!E24 -> Application Developer | G34: ='Pod Library'!F24 -> DEV | H34: ='Pod Library'!G24 -> E3 | I34: ='Pod Library'!H24 -> NEAR | J34: ='Pod Library'!I24 -> FTC | K34: ='Pod Library'!J24 -> 1.6 | L34: ='Pod Plan'!F6 -> 2 | M34: =K34*L34 -> 3.2 | N34: =M34*INDEX('Logic Tree'!$J$85:$N$87,MATCH(I34,'Logic Tree'!$I$85:$I$87,0),MATCH(H34,'Logic Tree'!$J$84:$N$84,0)) -> 2.688
B35: 1 | C35: TEAM | D35: CPA | E35: TEAM | F35: ='Pod Library'!E25 -> Test Analyst | G35: ='Pod Library'!F25 -> TEST | H35: ='Pod Library'!G25 -> E3 | I35: ='Pod Library'!H25 -> ON | J35: ='Pod Library'!I25 -> FTC | K35: ='Pod Library'!J25 -> 1 | L35: ='Pod Plan'!F6 -> 2 | M35: =K35*L35 -> 2 | N35: =M35*INDEX('Logic Tree'!$J$85:$N$87,MATCH(I35,'Logic Tree'!$I$85:$I$87,0),MATCH(H35,'Logic Tree'!$J$84:$N$84,0)) -> 2.7
B36: 1 | C36: TEAM | D36: CPA | E36: TEAM | F36: ='Pod Library'!E26 -> Test Engineer | G36: ='Pod Library'!F26 -> TEST | H36: ='Pod Library'!G26 -> E2 | I36: ='Pod Library'!H26 -> NEAR | J36: ='Pod Library'!I26 -> FTC | K36: ='Pod Library'!J26 -> 0.2 | L36: ='Pod Plan'!F6 -> 2 | M36: =K36*L36 -> 0.4 | N36: =M36*INDEX('Logic Tree'!$J$85:$N$87,MATCH(I36,'Logic Tree'!$I$85:$I$87,0),MATCH(H36,'Logic Tree'!$J$84:$N$84,0)) -> 0.248
B37: 1 | C37: TEAM | D37: CPA | E37: TEAM | F37: ='Pod Library'!E27 -> MGCC Payments Engineer | G37: ='Pod Library'!F27 -> DEV | H37: ='Pod Library'!G27 -> E3 | I37: ='Pod Library'!H27 -> OFF | J37: ='Pod Library'!I27 -> MGCC | K37: ='Pod Library'!J27 -> 1.9 | L37: ='Pod Plan'!F6 -> 2 | M37: =K37*L37 -> 3.8 | N37: =M37*INDEX('Logic Tree'!$J$85:$N$87,MATCH(I37,'Logic Tree'!$I$85:$I$87,0),MATCH(H37,'Logic Tree'!$J$84:$N$84,0)) -> 1.596
B38: 1 | C38: TEAM | D38: CPA | E38: TEAM | F38: ='Pod Library'!E28 -> Technical Lead | G38: ='Pod Library'!F28 -> OTH | H38: ='Pod Library'!G28 -> E4 | I38: ='Pod Library'!H28 -> ON | J38: ='Pod Library'!I28 -> FTC | K38: ='Pod Library'!J28 -> 0 | L38: ='Pod Plan'!F6 -> 2 | M38: =K38*L38 -> 0 | N38: =M38*INDEX('Logic Tree'!$J$85:$N$87,MATCH(I38,'Logic Tree'!$I$85:$I$87,0),MATCH(H38,'Logic Tree'!$J$84:$N$84,0)) -> 0
B39: 1 | C39: POD | D39: CSS | E39: POD | F39: ='Pod Library'!E5 -> MetLife Claims Product Owner | G39: ='Pod Library'!F5 -> PM | H39: ='Pod Library'!G5 -> E4 | I39: ='Pod Library'!H5 -> ON | J39: ='Pod Library'!I5 -> FTE | K39: ='Pod Library'!J5 -> 0.25 | L39: ='Pod Plan'!E7 -> 2 | M39: =K39*L39 -> 0.5 | N39: =M39*INDEX('Logic Tree'!$J$85:$N$87,MATCH(I39,'Logic Tree'!$I$85:$I$87,0),MATCH(H39,'Logic Tree'!$J$84:$N$84,0)) -> 0.925
B40: 1 | C40: POD | D40: CSS | E40: POD | F40: ='Pod Library'!E6 -> MetLife Claims SME | G40: ='Pod Library'!F6 -> BSA | H40: ='Pod Library'!G6 -> E4 | I40: ='Pod Library'!H6 -> ON | J40: ='Pod Library'!I6 -> FTE | K40: ='Pod Library'!J6 -> 0.25 | L40: ='Pod Plan'!E7 -> 2 | M40: =K40*L40 -> 0.5 | N40: =M40*INDEX('Logic Tree'!$J$85:$N$87,MATCH(I40,'Logic Tree'!$I$85:$I$87,0),MATCH(H40,'Logic Tree'!$J$84:$N$84,0)) -> 0.925
B41: 1 | C41: POD | D41: CSS | E41: POD | F41: ='Pod Library'!E7 -> Business Analyst (bilingual) | G41: ='Pod Library'!F7 -> BSA | H41: ='Pod Library'!G7 -> E3 | I41: ='Pod Library'!H7 -> ON | J41: ='Pod Library'!I7 -> FTC | K41: ='Pod Library'!J7 -> 0.375 | L41: ='Pod Plan'!E7 -> 2 | M41: =K41*L41 -> 0.75 | N41: =M41*INDEX('Logic Tree'!$J$85:$N$87,MATCH(I41,'Logic Tree'!$I$85:$I$87,0),MATCH(H41,'Logic Tree'!$J$84:$N$84,0)) -> 1.0125
B42: 1 | C42: POD | D42: CSS | E42: POD | F42: ='Pod Library'!E8 -> Pod lead / senior engineer | G42: ='Pod Library'!F8 -> DEV | H42: ='Pod Library'!G8 -> E4 | I42: ='Pod Library'!H8 -> ON | J42: ='Pod Library'!I8 -> FTC | K42: ='Pod Library'!J8 -> 2.375 | L42: ='Pod Plan'!E7 -> 2 | M42: =K42*L42 -> 4.75 | N42: =M42*INDEX('Logic Tree'!$J$85:$N$87,MATCH(I42,'Logic Tree'!$I$85:$I$87,0),MATCH(H42,'Logic Tree'!$J$84:$N$84,0)) -> 8.7875
B43: 1 | C43: POD | D43: CSS | E43: POD | F43: ='Pod Library'!E9 -> Claims Engineer | G43: ='Pod Library'!F9 -> DEV | H43: ='Pod Library'!G9 -> E3 | I43: ='Pod Library'!H9 -> OFF | J43: ='Pod Library'!I9 -> FTC | K43: ='Pod Library'!J9 -> 0 | L43: ='Pod Plan'!E7 -> 2 | M43: =K43*L43 -> 0 | N43: =M43*INDEX('Logic Tree'!$J$85:$N$87,MATCH(I43,'Logic Tree'!$I$85:$I$87,0),MATCH(H43,'Logic Tree'!$J$84:$N$84,0)) -> 0
B44: 1 | C44: POD | D44: CSS | E44: POD | F44: ='Pod Library'!E10 -> Claims Engineer | G44: ='Pod Library'!F10 -> DEV | H44: ='Pod Library'!G10 -> E2 | I44: ='Pod Library'!H10 -> OFF | J44: ='Pod Library'!I10 -> FTC | K44: ='Pod Library'!J10 -> 0.25 | L44: ='Pod Plan'!E7 -> 2 | M44: =K44*L44 -> 0.5 | N44: =M44*INDEX('Logic Tree'!$J$85:$N$87,MATCH(I44,'Logic Tree'!$I$85:$I$87,0),MATCH(H44,'Logic Tree'!$J$84:$N$84,0)) -> 0.15
B45: 1 | C45: POD | D45: CSS | E45: POD | F45: ='Pod Library'!E11 -> MGCC Payments Engineer | G45: ='Pod Library'!F11 -> DEV | H45: ='Pod Library'!G11 -> E3 | I45: ='Pod Library'!H11 -> OFF | J45: ='Pod Library'!I11 -> MGCC | K45: ='Pod Library'!J11 -> 1.375 | L45: ='Pod Plan'!E7 -> 2 | M45: =K45*L45 -> 2.75 | N45: =M45*INDEX('Logic Tree'!$J$85:$N$87,MATCH(I45,'Logic Tree'!$I$85:$I$87,0),MATCH(H45,'Logic Tree'!$J$84:$N$84,0)) -> 1.155
B46: 1 | C46: POD | D46: CSS | E46: POD | F46: ='Pod Library'!E12 -> SDET / Automation Engineer | G46: ='Pod Library'!F12 -> TEST | H46: ='Pod Library'!G12 -> E3 | I46: ='Pod Library'!H12 -> OFF | J46: ='Pod Library'!I12 -> FTC | K46: ='Pod Library'!J12 -> 0 | L46: ='Pod Plan'!E7 -> 2 | M46: =K46*L46 -> 0 | N46: =M46*INDEX('Logic Tree'!$J$85:$N$87,MATCH(I46,'Logic Tree'!$I$85:$I$87,0),MATCH(H46,'Logic Tree'!$J$84:$N$84,0)) -> 0
B47: 1 | C47: POD | D47: CSS | E47: POD | F47: ='Pod Library'!E13 -> MGCC Quality Engineer | G47: ='Pod Library'!F13 -> TEST | H47: ='Pod Library'!G13 -> E2 | I47: ='Pod Library'!H13 -> OFF | J47: ='Pod Library'!I13 -> MGCC | K47: ='Pod Library'!J13 -> 0.75 | L47: ='Pod Plan'!E7 -> 2 | M47: =K47*L47 -> 1.5 | N47: =M47*INDEX('Logic Tree'!$J$85:$N$87,MATCH(I47,'Logic Tree'!$I$85:$I$87,0),MATCH(H47,'Logic Tree'!$J$84:$N$84,0)) -> 0.45
B48: 1 | C48: POD | D48: CSS | E48: POD | F48: ='Pod Library'!E14 -> Solution Architect | G48: ='Pod Library'!F14 -> OTH | H48: ='Pod Library'!G14 -> E5 | I48: ='Pod Library'!H14 -> ON | J48: ='Pod Library'!I14 -> FTC | K48: ='Pod Library'!J14 -> 0.375 | L48: ='Pod Plan'!E7 -> 2 | M48: =K48*L48 -> 0.75 | N48: =M48*INDEX('Logic Tree'!$J$85:$N$87,MATCH(I48,'Logic Tree'!$I$85:$I$87,0),MATCH(H48,'Logic Tree'!$J$84:$N$84,0)) -> 1.9125
B49: 1 | C49: HZ | D49: ='Horizontal Teams'!C5 -> H1 | E49: HZ | F49: ='Horizontal Teams'!E5 -> Service Delivery Manager | G49: ='Horizontal Teams'!D5 -> PM | H49: ='Horizontal Teams'!F5 -> E5 | I49: ='Horizontal Teams'!G5 -> ON | J49: ='Horizontal Teams'!H5 -> FTC | K49: ='Horizontal Teams'!I5 -> 1 | L49: 1 | M49: =K49*L49 -> 1 | N49: =M49*INDEX('Logic Tree'!$J$85:$N$87,MATCH(I49,'Logic Tree'!$I$85:$I$87,0),MATCH(H49,'Logic Tree'!$J$84:$N$84,0)) -> 2.55
B50: 1 | C50: HZ | D50: ='Horizontal Teams'!C6 -> H1 | E50: HZ | F50: ='Horizontal Teams'!E6 -> Incident & Problem Analyst | G50: ='Horizontal Teams'!D6 -> MNT | H50: ='Horizontal Teams'!F6 -> E3 | I50: ='Horizontal Teams'!G6 -> ON | J50: ='Horizontal Teams'!H6 -> FTC | K50: ='Horizontal Teams'!I6 -> 2 | L50: 1 | M50: =K50*L50 -> 2 | N50: =M50*INDEX('Logic Tree'!$J$85:$N$87,MATCH(I50,'Logic Tree'!$I$85:$I$87,0),MATCH(H50,'Logic Tree'!$J$84:$N$84,0)) -> 2.7
B51: 1 | C51: HZ | D51: ='Horizontal Teams'!C7 -> H1 | E51: HZ | F51: ='Horizontal Teams'!E7 -> L2 Application Support | G51: ='Horizontal Teams'!D7 -> MNT | H51: ='Horizontal Teams'!F7 -> E2 | I51: ='Horizontal Teams'!G7 -> OFF | J51: ='Horizontal Teams'!H7 -> FTC | K51: ='Horizontal Teams'!I7 -> 0.5 | L51: 1 | M51: =K51*L51 -> 0.5 | N51: =M51*INDEX('Logic Tree'!$J$85:$N$87,MATCH(I51,'Logic Tree'!$I$85:$I$87,0),MATCH(H51,'Logic Tree'!$J$84:$N$84,0)) -> 0.15
B52: 1 | C52: HZ | D52: ='Horizontal Teams'!C8 -> H1 | E52: HZ | F52: ='Horizontal Teams'!E8 -> L2 Application Support | G52: ='Horizontal Teams'!D8 -> MNT | H52: ='Horizontal Teams'!F8 -> E2 | I52: ='Horizontal Teams'!G8 -> NEAR | J52: ='Horizontal Teams'!H8 -> FTC | K52: ='Horizontal Teams'!I8 -> 0.5 | L52: 1 | M52: =K52*L52 -> 0.5 | N52: =M52*INDEX('Logic Tree'!$J$85:$N$87,MATCH(I52,'Logic Tree'!$I$85:$I$87,0),MATCH(H52,'Logic Tree'!$J$84:$N$84,0)) -> 0.31
B53: 1 | C53: HZ | D53: ='Horizontal Teams'!C9 -> H1 | E53: HZ | F53: ='Horizontal Teams'!E9 -> Observability / AIOps Engineer | G53: ='Horizontal Teams'!D9 -> OTH | H53: ='Horizontal Teams'!F9 -> E3 | I53: ='Horizontal Teams'!G9 -> OFF | J53: ='Horizontal Teams'!H9 -> FTC | K53: ='Horizontal Teams'!I9 -> 0.5 | L53: 1 | M53: =K53*L53 -> 0.5 | N53: =M53*INDEX('Logic Tree'!$J$85:$N$87,MATCH(I53,'Logic Tree'!$I$85:$I$87,0),MATCH(H53,'Logic Tree'!$J$84:$N$84,0)) -> 0.21
B54: 1 | C54: HZ | D54: ='Horizontal Teams'!C10 -> H1 | E54: HZ | F54: ='Horizontal Teams'!E10 -> MetLife Operations Lead | G54: ='Horizontal Teams'!D10 -> MNT | H54: ='Horizontal Teams'!F10 -> E4 | I54: ='Horizontal Teams'!G10 -> ON | J54: ='Horizontal Teams'!H10 -> FTE | K54: ='Horizontal Teams'!I10 -> 2.5 | L54: 1 | M54: =K54*L54 -> 2.5 | N54: =M54*INDEX('Logic Tree'!$J$85:$N$87,MATCH(I54,'Logic Tree'!$I$85:$I$87,0),MATCH(H54,'Logic Tree'!$J$84:$N$84,0)) -> 4.625
B55: 1 | C55: HZ | D55: ='Horizontal Teams'!C11 -> H2 | E55: HZ | F55: ='Horizontal Teams'!E11 -> Quality Lead | G55: ='Horizontal Teams'!D11 -> TEST | H55: ='Horizontal Teams'!F11 -> E4 | I55: ='Horizontal Teams'!G11 -> ON | J55: ='Horizontal Teams'!H11 -> FTC | K55: ='Horizontal Teams'!I11 -> 0.5 | L55: 1 | M55: =K55*L55 -> 0.5 | N55: =M55*INDEX('Logic Tree'!$J$85:$N$87,MATCH(I55,'Logic Tree'!$I$85:$I$87,0),MATCH(H55,'Logic Tree'!$J$84:$N$84,0)) -> 0.925
B56: 1 | C56: HZ | D56: ='Horizontal Teams'!C12 -> H2 | E56: HZ | F56: ='Horizontal Teams'!E12 -> Test Automation Engineer | G56: ='Horizontal Teams'!D12 -> TEST | H56: ='Horizontal Teams'!F12 -> E3 | I56: ='Horizontal Teams'!G12 -> OFF | J56: ='Horizontal Teams'!H12 -> FTC | K56: ='Horizontal Teams'!I12 -> 0.5 | L56: 1 | M56: =K56*L56 -> 0.5 | N56: =M56*INDEX('Logic Tree'!$J$85:$N$87,MATCH(I56,'Logic Tree'!$I$85:$I$87,0),MATCH(H56,'Logic Tree'!$J$84:$N$84,0)) -> 0.21
B57: 1 | C57: HZ | D57: ='Horizontal Teams'!C13 -> H2 | E57: HZ | F57: ='Horizontal Teams'!E13 -> Performance & Batch Test Engineer | G57: ='Horizontal Teams'!D13 -> TEST | H57: ='Horizontal Teams'!F13 -> E3 | I57: ='Horizontal Teams'!G13 -> OFF | J57: ='Horizontal Teams'!H13 -> FTC | K57: ='Horizontal Teams'!I13 -> 0.5 | L57: 1 | M57: =K57*L57 -> 0.5 | N57: =M57*INDEX('Logic Tree'!$J$85:$N$87,MATCH(I57,'Logic Tree'!$I$85:$I$87,0),MATCH(H57,'Logic Tree'!$J$84:$N$84,0)) -> 0.21
B58: 1 | C58: HZ | D58: ='Horizontal Teams'!C14 -> H2 | E58: HZ | F58: ='Horizontal Teams'!E14 -> MGCC Quality Engineer | G58: ='Horizontal Teams'!D14 -> TEST | H58: ='Horizontal Teams'!F14 -> E2 | I58: ='Horizontal Teams'!G14 -> OFF | J58: ='Horizontal Teams'!H14 -> MGCC | K58: ='Horizontal Teams'!I14 -> 3 | L58: 1 | M58: =K58*L58 -> 3 | N58: =M58*INDEX('Logic Tree'!$J$85:$N$87,MATCH(I58,'Logic Tree'!$I$85:$I$87,0),MATCH(H58,'Logic Tree'!$J$84:$N$84,0)) -> 0.9
B59: 1 | C59: HZ | D59: ='Horizontal Teams'!C15 -> H2 | E59: HZ | F59: ='Horizontal Teams'!E15 -> Payments Assurance Analyst | G59: ='Horizontal Teams'!D15 -> BSA | H59: ='Horizontal Teams'!F15 -> E3 | I59: ='Horizontal Teams'!G15 -> ON | J59: ='Horizontal Teams'!H15 -> FTC | K59: ='Horizontal Teams'!I15 -> 1.5 | L59: 1 | M59: =K59*L59 -> 1.5 | N59: =M59*INDEX('Logic Tree'!$J$85:$N$87,MATCH(I59,'Logic Tree'!$I$85:$I$87,0),MATCH(H59,'Logic Tree'!$J$84:$N$84,0)) -> 2.025
B60: 1 | C60: HZ | D60: ='Horizontal Teams'!C16 -> H3 | E60: HZ | F60: ='Horizontal Teams'!E16 -> Domain Solution Architect | G60: ='Horizontal Teams'!D16 -> OTH | H60: ='Horizontal Teams'!F16 -> E5 | I60: ='Horizontal Teams'!G16 -> ON | J60: ='Horizontal Teams'!H16 -> FTC | K60: ='Horizontal Teams'!I16 -> 0.5 | L60: 1 | M60: =K60*L60 -> 0.5 | N60: =M60*INDEX('Logic Tree'!$J$85:$N$87,MATCH(I60,'Logic Tree'!$I$85:$I$87,0),MATCH(H60,'Logic Tree'!$J$84:$N$84,0)) -> 1.275
... B67: 1 | C67: HZ | D67: ='Horizontal Teams'!C23 -> H3 | E67: HZ | F67: ='Horizontal Teams'!E23 -> MGCC Engineering Lead | G67: ='Horizontal Teams'!D23 -> DEV | H67: ='Horizontal Teams'!F23 -> E4 | I67: ='Horizontal Teams'!G23 -> OFF | J67: ='Horizontal Teams'!H23 -> MGCC | K67: ='Horizontal Teams'!I23 -> 1.5 | L67: 1 | M67: =K67*L67 -> 1.5 | N67: =M67*INDEX('Logic Tree'!$J$85:$N$87,MATCH(I67,'Logic Tree'!$I$85:$I$87,0),MATCH(H67,'Logic Tree'!$J$84:$N$84,0)) -> 0.9
B68: 2 | C68: POD | D68: AMP | E68: POD | F68: ='Pod Library'!E31 -> MetLife Claims Product Owner | G68: ='Pod Library'!F31 -> PM | H68: ='Pod Library'!G31 -> E4 | I68: ='Pod Library'!H31 -> ON | J68: ='Pod Library'!I31 -> FTE | K68: ='Pod Library'!J31 -> 0.57142857 | L68: ='Pod Plan'!E10 -> 4 | M68: =K68*L68 -> 2.2857143 | N68: =M68*INDEX('Logic Tree'!$J$85:$N$87,MATCH(I68,'Logic Tree'!$I$85:$I$87,0),MATCH(H68,'Logic Tree'!$J$84:$N$84,0)) -> 4.2285714
B69: 2 | C69: POD | D69: AMP | E69: POD | F69: ='Pod Library'!E32 -> MetLife Claims SME | G69: ='Pod Library'!F32 -> BSA | H69: ='Pod Library'!G32 -> E4 | I69: ='Pod Library'!H32 -> ON | J69: ='Pod Library'!I32 -> FTE | K69: ='Pod Library'!J32 -> 0.42857143 | L69: ='Pod Plan'!E10 -> 4 | M69: =K69*L69 -> 1.7142857 | N69: =M69*INDEX('Logic Tree'!$J$85:$N$87,MATCH(I69,'Logic Tree'!$I$85:$I$87,0),MATCH(H69,'Logic Tree'!$J$84:$N$84,0)) -> 3.1714286
B70: 2 | C70: POD | D70: AMP | E70: POD | F70: ='Pod Library'!E33 -> Business Analyst (bilingual) | G70: ='Pod Library'!F33 -> BSA | H70: ='Pod Library'!G33 -> E3 | I70: ='Pod Library'!H33 -> ON | J70: ='Pod Library'!I33 -> FTC | K70: ='Pod Library'!J33 -> 1 | L70: ='Pod Plan'!E10 -> 4 | M70: =K70*L70 -> 4 | N70: =M70*INDEX('Logic Tree'!$J$85:$N$87,MATCH(I70,'Logic Tree'!$I$85:$I$87,0),MATCH(H70,'Logic Tree'!$J$84:$N$84,0)) -> 5.4
B71: 2 | C71: POD | D71: AMP | E71: POD | F71: ='Pod Library'!E34 -> Pod lead / senior engineer | G71: ='Pod Library'!F34 -> DEV | H71: ='Pod Library'!G34 -> E4 | I71: ='Pod Library'!H34 -> ON | J71: ='Pod Library'!I34 -> FTC | K71: ='Pod Library'!J34 -> 1.3571429 | L71: ='Pod Plan'!E10 -> 4 | M71: =K71*L71 -> 5.4285714 | N71: =M71*INDEX('Logic Tree'!$J$85:$N$87,MATCH(I71,'Logic Tree'!$I$85:$I$87,0),MATCH(H71,'Logic Tree'!$J$84:$N$84,0)) -> 10.042857
B72: 2 | C72: POD | D72: AMP | E72: POD | F72: ='Pod Library'!E35 -> Claims Engineer | G72: ='Pod Library'!F35 -> DEV | H72: ='Pod Library'!G35 -> E3 | I72: ='Pod Library'!H35 -> OFF | J72: ='Pod Library'!I35 -> FTC | K72: ='Pod Library'!J35 -> 0.64285714 | L72: ='Pod Plan'!E10 -> 4 | M72: =K72*L72 -> 2.5714286 | N72: =M72*INDEX('Logic Tree'!$J$85:$N$87,MATCH(I72,'Logic Tree'!$I$85:$I$87,0),MATCH(H72,'Logic Tree'!$J$84:$N$84,0)) -> 1.08
B73: 2 | C73: POD | D73: AMP | E73: POD | F73: ='Pod Library'!E36 -> Claims Engineer | G73: ='Pod Library'!F36 -> DEV | H73: ='Pod Library'!G36 -> E2 | I73: ='Pod Library'!H36 -> OFF | J73: ='Pod Library'!I36 -> FTC | K73: ='Pod Library'!J36 -> 0.57142857 | L73: ='Pod Plan'!E10 -> 4 | M73: =K73*L73 -> 2.2857143 | N73: =M73*INDEX('Logic Tree'!$J$85:$N$87,MATCH(I73,'Logic Tree'!$I$85:$I$87,0),MATCH(H73,'Logic Tree'!$J$84:$N$84,0)) -> 0.68571429
B74: 2 | C74: POD | D74: AMP | E74: POD | F74: ='Pod Library'!E37 -> MGCC Payments Engineer | G74: ='Pod Library'!F37 -> DEV | H74: ='Pod Library'!G37 -> E3 | I74: ='Pod Library'!H37 -> OFF | J74: ='Pod Library'!I37 -> MGCC | K74: ='Pod Library'!J37 -> 1.1428571 | L74: ='Pod Plan'!E10 -> 4 | M74: =K74*L74 -> 4.5714286 | N74: =M74*INDEX('Logic Tree'!$J$85:$N$87,MATCH(I74,'Logic Tree'!$I$85:$I$87,0),MATCH(H74,'Logic Tree'!$J$84:$N$84,0)) -> 1.92
B75: 2 | C75: POD | D75: AMP | E75: POD | F75: ='Pod Library'!E38 -> SDET / Automation Engineer | G75: ='Pod Library'!F38 -> TEST | H75: ='Pod Library'!G38 -> E3 | I75: ='Pod Library'!H38 -> OFF | J75: ='Pod Library'!I38 -> FTC | K75: ='Pod Library'!J38 -> 0 | L75: ='Pod Plan'!E10 -> 4 | M75: =K75*L75 -> 0 | N75: =M75*INDEX('Logic Tree'!$J$85:$N$87,MATCH(I75,'Logic Tree'!$I$85:$I$87,0),MATCH(H75,'Logic Tree'!$J$84:$N$84,0)) -> 0
B76: 2 | C76: POD | D76: AMP | E76: POD | F76: ='Pod Library'!E39 -> MGCC Quality Engineer | G76: ='Pod Library'!F39 -> TEST | H76: ='Pod Library'!G39 -> E2 | I76: ='Pod Library'!H39 -> OFF | J76: ='Pod Library'!I39 -> MGCC | K76: ='Pod Library'!J39 -> 0.71428571 | L76: ='Pod Plan'!E10 -> 4 | M76: =K76*L76 -> 2.8571429 | N76: =M76*INDEX('Logic Tree'!$J$85:$N$87,MATCH(I76,'Logic Tree'!$I$85:$I$87,0),MATCH(H76,'Logic Tree'!$J$84:$N$84,0)) -> 0.85714286
B77: 2 | C77: POD | D77: AMP | E77: POD | F77: ='Pod Library'!E40 -> Solution Architect | G77: ='Pod Library'!F40 -> OTH | H77: ='Pod Library'!G40 -> E5 | I77: ='Pod Library'!H40 -> ON | J77: ='Pod Library'!I40 -> FTC | K77: ='Pod Library'!J40 -> 0.71428571 | L77: ='Pod Plan'!E10 -> 4 | M77: =K77*L77 -> 2.8571429 | N77: =M77*INDEX('Logic Tree'!$J$85:$N$87,MATCH(I77,'Logic Tree'!$I$85:$I$87,0),MATCH(H77,'Logic Tree'!$J$84:$N$84,0)) -> 7.2857143
B78: 2 | C78: TEAM | D78: AMP | E78: TEAM | F78: ='Pod Library'!E43 -> MetLife Claims Product Owner | G78: ='Pod Library'!F43 -> PM | H78: ='Pod Library'!G43 -> E4 | I78: ='Pod Library'!H43 -> ON | J78: ='Pod Library'!I43 -> FTE | K78: ='Pod Library'!J43 -> 0 | L78: ='Pod Plan'!F10 -> 1 | M78: =K78*L78 -> 0 | N78: =M78*INDEX('Logic Tree'!$J$85:$N$87,MATCH(I78,'Logic Tree'!$I$85:$I$87,0),MATCH(H78,'Logic Tree'!$J$84:$N$84,0)) -> 0
B79: 2 | C79: TEAM | D79: AMP | E79: TEAM | F79: ='Pod Library'!E44 -> MetLife Claims SME | G79: ='Pod Library'!F44 -> BSA | H79: ='Pod Library'!G44 -> E4 | I79: ='Pod Library'!H44 -> ON | J79: ='Pod Library'!I44 -> FTE | K79: ='Pod Library'!J44 -> 0 | L79: ='Pod Plan'!F10 -> 1 | M79: =K79*L79 -> 0 | N79: =M79*INDEX('Logic Tree'!$J$85:$N$87,MATCH(I79,'Logic Tree'!$I$85:$I$87,0),MATCH(H79,'Logic Tree'!$J$84:$N$84,0)) -> 0
B80: 2 | C80: TEAM | D80: AMP | E80: TEAM | F80: ='Pod Library'!E45 -> MetLife Operations Analyst | G80: ='Pod Library'!F45 -> MNT | H80: ='Pod Library'!G45 -> E3 | I80: ='Pod Library'!H45 -> ON | J80: ='Pod Library'!I45 -> FTE | K80: ='Pod Library'!J45 -> 0.5 | L80: ='Pod Plan'!F10 -> 1 | M80: =K80*L80 -> 0.5 | N80: =M80*INDEX('Logic Tree'!$J$85:$N$87,MATCH(I80,'Logic Tree'!$I$85:$I$87,0),MATCH(H80,'Logic Tree'!$J$84:$N$84,0)) -> 0.675
B81: 2 | C81: TEAM | D81: AMP | E81: TEAM | F81: ='Pod Library'!E46 -> Business Analyst (bilingual) | G81: ='Pod Library'!F46 -> BSA | H81: ='Pod Library'!G46 -> E3 | I81: ='Pod Library'!H46 -> ON | J81: ='Pod Library'!I46 -> FTC | K81: ='Pod Library'!J46 -> 0.5 | L81: ='Pod Plan'!F10 -> 1 | M81: =K81*L81 -> 0.5 | N81: =M81*INDEX('Logic Tree'!$J$85:$N$87,MATCH(I81,'Logic Tree'!$I$85:$I$87,0),MATCH(H81,'Logic Tree'!$J$84:$N$84,0)) -> 0.675
B82: 2 | C82: TEAM | D82: AMP | E82: TEAM | F82: ='Pod Library'!E47 -> Team lead / senior engineer | G82: ='Pod Library'!F47 -> DEV | H82: ='Pod Library'!G47 -> E4 | I82: ='Pod Library'!H47 -> ON | J82: ='Pod Library'!I47 -> FTC | K82: ='Pod Library'!J47 -> 0.5 | L82: ='Pod Plan'!F10 -> 1 | M82: =K82*L82 -> 0.5 | N82: =M82*INDEX('Logic Tree'!$J$85:$N$87,MATCH(I82,'Logic Tree'!$I$85:$I$87,0),MATCH(H82,'Logic Tree'!$J$84:$N$84,0)) -> 0.925
B83: 2 | C83: TEAM | D83: AMP | E83: TEAM | F83: ='Pod Library'!E48 -> Application Developer | G83: ='Pod Library'!F48 -> DEV | H83: ='Pod Library'!G48 -> E3 | I83: ='Pod Library'!H48 -> ON | J83: ='Pod Library'!I48 -> FTC | K83: ='Pod Library'!J48 -> 2 | L83: ='Pod Plan'!F10 -> 1 | M83: =K83*L83 -> 2 | N83: =M83*INDEX('Logic Tree'!$J$85:$N$87,MATCH(I83,'Logic Tree'!$I$85:$I$87,0),MATCH(H83,'Logic Tree'!$J$84:$N$84,0)) -> 2.7
B84: 2 | C84: TEAM | D84: AMP | E84: TEAM | F84: ='Pod Library'!E49 -> Application Developer | G84: ='Pod Library'!F49 -> DEV | H84: ='Pod Library'!G49 -> E2 | I84: ='Pod Library'!H49 -> ON | J84: ='Pod Library'!I49 -> FTC | K84: ='Pod Library'!J49 -> 2.75 | L84: ='Pod Plan'!F10 -> 1 | M84: =K84*L84 -> 2.75 | N84: =M84*INDEX('Logic Tree'!$J$85:$N$87,MATCH(I84,'Logic Tree'!$I$85:$I$87,0),MATCH(H84,'Logic Tree'!$J$84:$N$84,0)) -> 2.75
B85: 2 | C85: TEAM | D85: AMP | E85: TEAM | F85: ='Pod Library'!E50 -> Application Developer | G85: ='Pod Library'!F50 -> DEV | H85: ='Pod Library'!G50 -> E3 | I85: ='Pod Library'!H50 -> NEAR | J85: ='Pod Library'!I50 -> FTC | K85: ='Pod Library'!J50 -> 0.75 | L85: ='Pod Plan'!F10 -> 1 | M85: =K85*L85 -> 0.75 | N85: =M85*INDEX('Logic Tree'!$J$85:$N$87,MATCH(I85,'Logic Tree'!$I$85:$I$87,0),MATCH(H85,'Logic Tree'!$J$84:$N$84,0)) -> 0.63
B86: 2 | C86: TEAM | D86: AMP | E86: TEAM | F86: ='Pod Library'!E51 -> Test Analyst | G86: ='Pod Library'!F51 -> TEST | H86: ='Pod Library'!G51 -> E3 | I86: ='Pod Library'!H51 -> ON | J86: ='Pod Library'!I51 -> FTC | K86: ='Pod Library'!J51 -> 1 | L86: ='Pod Plan'!F10 -> 1 | M86: =K86*L86 -> 1 | N86: =M86*INDEX('Logic Tree'!$J$85:$N$87,MATCH(I86,'Logic Tree'!$I$85:$I$87,0),MATCH(H86,'Logic Tree'!$J$84:$N$84,0)) -> 1.35
B87: 2 | C87: TEAM | D87: AMP | E87: TEAM | F87: ='Pod Library'!E52 -> Test Engineer | G87: ='Pod Library'!F52 -> TEST | H87: ='Pod Library'!G52 -> E2 | I87: ='Pod Library'!H52 -> NEAR | J87: ='Pod Library'!I52 -> FTC | K87: ='Pod Library'!J52 -> 1 | L87: ='Pod Plan'!F10 -> 1 | M87: =K87*L87 -> 1 | N87: =M87*INDEX('Logic Tree'!$J$85:$N$87,MATCH(I87,'Logic Tree'!$I$85:$I$87,0),MATCH(H87,'Logic Tree'!$J$84:$N$84,0)) -> 0.62
B88: 2 | C88: TEAM | D88: AMP | E88: TEAM | F88: ='Pod Library'!E53 -> MGCC Payments Engineer | G88: ='Pod Library'!F53 -> DEV | H88: ='Pod Library'!G53 -> E3 | I88: ='Pod Library'!H53 -> OFF | J88: ='Pod Library'!I53 -> MGCC | K88: ='Pod Library'!J53 -> 1.25 | L88: ='Pod Plan'!F10 -> 1 | M88: =K88*L88 -> 1.25 | N88: =M88*INDEX('Logic Tree'!$J$85:$N$87,MATCH(I88,'Logic Tree'!$I$85:$I$87,0),MATCH(H88,'Logic Tree'!$J$84:$N$84,0)) -> 0.525
B89: 2 | C89: TEAM | D89: AMP | E89: TEAM | F89: ='Pod Library'!E54 -> Technical Lead | G89: ='Pod Library'!F54 -> OTH | H89: ='Pod Library'!G54 -> E4 | I89: ='Pod Library'!H54 -> ON | J89: ='Pod Library'!I54 -> FTC | K89: ='Pod Library'!J54 -> 0.5 | L89: ='Pod Plan'!F10 -> 1 | M89: =K89*L89 -> 0.5 | N89: =M89*INDEX('Logic Tree'!$J$85:$N$87,MATCH(I89,'Logic Tree'!$I$85:$I$87,0),MATCH(H89,'Logic Tree'!$J$84:$N$84,0)) -> 0.925
B90: 2 | C90: POD | D90: CPA | E90: POD | F90: ='Pod Library'!E31 -> MetLife Claims Product Owner | G90: ='Pod Library'!F31 -> PM | H90: ='Pod Library'!G31 -> E4 | I90: ='Pod Library'!H31 -> ON | J90: ='Pod Library'!I31 -> FTE | K90: ='Pod Library'!J31 -> 0.57142857 | L90: ='Pod Plan'!E11 -> 1 | M90: =K90*L90 -> 0.57142857 | N90: =M90*INDEX('Logic Tree'!$J$85:$N$87,MATCH(I90,'Logic Tree'!$I$85:$I$87,0),MATCH(H90,'Logic Tree'!$J$84:$N$84,0)) -> 1.0571429
B91: 2 | C91: POD | D91: CPA | E91: POD | F91: ='Pod Library'!E32 -> MetLife Claims SME | G91: ='Pod Library'!F32 -> BSA | H91: ='Pod Library'!G32 -> E4 | I91: ='Pod Library'!H32 -> ON | J91: ='Pod Library'!I32 -> FTE | K91: ='Pod Library'!J32 -> 0.42857143 | L91: ='Pod Plan'!E11 -> 1 | M91: =K91*L91 -> 0.42857143 | N91: =M91*INDEX('Logic Tree'!$J$85:$N$87,MATCH(I91,'Logic Tree'!$I$85:$I$87,0),MATCH(H91,'Logic Tree'!$J$84:$N$84,0)) -> 0.79285714
B92: 2 | C92: POD | D92: CPA | E92: POD | F92: ='Pod Library'!E33 -> Business Analyst (bilingual) | G92: ='Pod Library'!F33 -> BSA | H92: ='Pod Library'!G33 -> E3 | I92: ='Pod Library'!H33 -> ON | J92: ='Pod Library'!I33 -> FTC | K92: ='Pod Library'!J33 -> 1 | L92: ='Pod Plan'!E11 -> 1 | M92: =K92*L92 -> 1 | N92: =M92*INDEX('Logic Tree'!$J$85:$N$87,MATCH(I92,'Logic Tree'!$I$85:$I$87,0),MATCH(H92,'Logic Tree'!$J$84:$N$84,0)) -> 1.35
B93: 2 | C93: POD | D93: CPA | E93: POD | F93: ='Pod Library'!E34 -> Pod lead / senior engineer | G93: ='Pod Library'!F34 -> DEV | H93: ='Pod Library'!G34 -> E4 | I93: ='Pod Library'!H34 -> ON | J93: ='Pod Library'!I34 -> FTC | K93: ='Pod Library'!J34 -> 1.3571429 | L93: ='Pod Plan'!E11 -> 1 | M93: =K93*L93 -> 1.3571429 | N93: =M93*INDEX('Logic Tree'!$J$85:$N$87,MATCH(I93,'Logic Tree'!$I$85:$I$87,0),MATCH(H93,'Logic Tree'!$J$84:$N$84,0)) -> 2.5107143
B94: 2 | C94: POD | D94: CPA | E94: POD | F94: ='Pod Library'!E35 -> Claims Engineer | G94: ='Pod Library'!F35 -> DEV | H94: ='Pod Library'!G35 -> E3 | I94: ='Pod Library'!H35 -> OFF | J94: ='Pod Library'!I35 -> FTC | K94: ='Pod Library'!J35 -> 0.64285714 | L94: ='Pod Plan'!E11 -> 1 | M94: =K94*L94 -> 0.64285714 | N94: =M94*INDEX('Logic Tree'!$J$85:$N$87,MATCH(I94,'Logic Tree'!$I$85:$I$87,0),MATCH(H94,'Logic Tree'!$J$84:$N$84,0)) -> 0.27
B95: 2 | C95: POD | D95: CPA | E95: POD | F95: ='Pod Library'!E36 -> Claims Engineer | G95: ='Pod Library'!F36 -> DEV | H95: ='Pod Library'!G36 -> E2 | I95: ='Pod Library'!H36 -> OFF | J95: ='Pod Library'!I36 -> FTC | K95: ='Pod Library'!J36 -> 0.57142857 | L95: ='Pod Plan'!E11 -> 1 | M95: =K95*L95 -> 0.57142857 | N95: =M95*INDEX('Logic Tree'!$J$85:$N$87,MATCH(I95,'Logic Tree'!$I$85:$I$87,0),MATCH(H95,'Logic Tree'!$J$84:$N$84,0)) -> 0.17142857
B96: 2 | C96: POD | D96: CPA | E96: POD | F96: ='Pod Library'!E37 -> MGCC Payments Engineer | G96: ='Pod Library'!F37 -> DEV | H96: ='Pod Library'!G37 -> E3 | I96: ='Pod Library'!H37 -> OFF | J96: ='Pod Library'!I37 -> MGCC | K96: ='Pod Library'!J37 -> 1.1428571 | L96: ='Pod Plan'!E11 -> 1 | M96: =K96*L96 -> 1.1428571 | N96: =M96*INDEX('Logic Tree'!$J$85:$N$87,MATCH(I96,'Logic Tree'!$I$85:$I$87,0),MATCH(H96,'Logic Tree'!$J$84:$N$84,0)) -> 0.48
B97: 2 | C97: POD | D97: CPA | E97: POD | F97: ='Pod Library'!E38 -> SDET / Automation Engineer | G97: ='Pod Library'!F38 -> TEST | H97: ='Pod Library'!G38 -> E3 | I97: ='Pod Library'!H38 -> OFF | J97: ='Pod Library'!I38 -> FTC | K97: ='Pod Library'!J38 -> 0 | L97: ='Pod Plan'!E11 -> 1 | M97: =K97*L97 -> 0 | N97: =M97*INDEX('Logic Tree'!$J$85:$N$87,MATCH(I97,'Logic Tree'!$I$85:$I$87,0),MATCH(H97,'Logic Tree'!$J$84:$N$84,0)) -> 0
B98: 2 | C98: POD | D98: CPA | E98: POD | F98: ='Pod Library'!E39 -> MGCC Quality Engineer | G98: ='Pod Library'!F39 -> TEST | H98: ='Pod Library'!G39 -> E2 | I98: ='Pod Library'!H39 -> OFF | J98: ='Pod Library'!I39 -> MGCC | K98: ='Pod Library'!J39 -> 0.71428571 | L98: ='Pod Plan'!E11 -> 1 | M98: =K98*L98 -> 0.71428571 | N98: =M98*INDEX('Logic Tree'!$J$85:$N$87,MATCH(I98,'Logic Tree'!$I$85:$I$87,0),MATCH(H98,'Logic Tree'!$J$84:$N$84,0)) -> 0.21428571
B99: 2 | C99: POD | D99: CPA | E99: POD | F99: ='Pod Library'!E40 -> Solution Architect | G99: ='Pod Library'!F40 -> OTH | H99: ='Pod Library'!G40 -> E5 | I99: ='Pod Library'!H40 -> ON | J99: ='Pod Library'!I40 -> FTC | K99: ='Pod Library'!J40 -> 0.71428571 | L99: ='Pod Plan'!E11 -> 1 | M99: =K99*L99 -> 0.71428571 | N99: =M99*INDEX('Logic Tree'!$J$85:$N$87,MATCH(I99,'Logic Tree'!$I$85:$I$87,0),MATCH(H99,'Logic Tree'!$J$84:$N$84,0)) -> 1.8214286
B100: 2 | C100: TEAM | D100: CPA | E100: TEAM | F100: ='Pod Library'!E43 -> MetLife Claims Product Owner | G100: ='Pod Library'!F43 -> PM | H100: ='Pod Library'!G43 -> E4 | I100: ='Pod Library'!H43 -> ON | J100: ='Pod Library'!I43 -> FTE | K100: ='Pod Library'!J43 -> 0 | L100: ='Pod Plan'!F11 -> 1 | M100: =K100*L100 -> 0 | N100: =M100*INDEX('Logic Tree'!$J$85:$N$87,MATCH(I100,'Logic Tree'!$I$85:$I$87,0),MATCH(H100,'Logic Tree'!$J$84:$N$84,0)) -> 0
B101: 2 | C101: TEAM | D101: CPA | E101: TEAM | F101: ='Pod Library'!E44 -> MetLife Claims SME | G101: ='Pod Library'!F44 -> BSA | H101: ='Pod Library'!G44 -> E4 | I101: ='Pod Library'!H44 -> ON | J101: ='Pod Library'!I44 -> FTE | K101: ='Pod Library'!J44 -> 0 | L101: ='Pod Plan'!F11 -> 1 | M101: =K101*L101 -> 0 | N101: =M101*INDEX('Logic Tree'!$J$85:$N$87,MATCH(I101,'Logic Tree'!$I$85:$I$87,0),MATCH(H101,'Logic Tree'!$J$84:$N$84,0)) -> 0
B102: 2 | C102: TEAM | D102: CPA | E102: TEAM | F102: ='Pod Library'!E45 -> MetLife Operations Analyst | G102: ='Pod Library'!F45 -> MNT | H102: ='Pod Library'!G45 -> E3 | I102: ='Pod Library'!H45 -> ON | J102: ='Pod Library'!I45 -> FTE | K102: ='Pod Library'!J45 -> 0.5 | L102: ='Pod Plan'!F11 -> 1 | M102: =K102*L102 -> 0.5 | N102: =M102*INDEX('Logic Tree'!$J$85:$N$87,MATCH(I102,'Logic Tree'!$I$85:$I$87,0),MATCH(H102,'Logic Tree'!$J$84:$N$84,0)) -> 0.675
B103: 2 | C103: TEAM | D103: CPA | E103: TEAM | F103: ='Pod Library'!E46 -> Business Analyst (bilingual) | G103: ='Pod Library'!F46 -> BSA | H103: ='Pod Library'!G46 -> E3 | I103: ='Pod Library'!H46 -> ON | J103: ='Pod Library'!I46 -> FTC | K103: ='Pod Library'!J46 -> 0.5 | L103: ='Pod Plan'!F11 -> 1 | M103: =K103*L103 -> 0.5 | N103: =M103*INDEX('Logic Tree'!$J$85:$N$87,MATCH(I103,'Logic Tree'!$I$85:$I$87,0),MATCH(H103,'Logic Tree'!$J$84:$N$84,0)) -> 0.675
B104: 2 | C104: TEAM | D104: CPA | E104: TEAM | F104: ='Pod Library'!E47 -> Team lead / senior engineer | G104: ='Pod Library'!F47 -> DEV | H104: ='Pod Library'!G47 -> E4 | I104: ='Pod Library'!H47 -> ON | J104: ='Pod Library'!I47 -> FTC | K104: ='Pod Library'!J47 -> 0.5 | L104: ='Pod Plan'!F11 -> 1 | M104: =K104*L104 -> 0.5 | N104: =M104*INDEX('Logic Tree'!$J$85:$N$87,MATCH(I104,'Logic Tree'!$I$85:$I$87,0),MATCH(H104,'Logic Tree'!$J$84:$N$84,0)) -> 0.925
B105: 2 | C105: TEAM | D105: CPA | E105: TEAM | F105: ='Pod Library'!E48 -> Application Developer | G105: ='Pod Library'!F48 -> DEV | H105: ='Pod Library'!G48 -> E3 | I105: ='Pod Library'!H48 -> ON | J105: ='Pod Library'!I48 -> FTC | K105: ='Pod Library'!J48 -> 2 | L105: ='Pod Plan'!F11 -> 1 | M105: =K105*L105 -> 2 | N105: =M105*INDEX('Logic Tree'!$J$85:$N$87,MATCH(I105,'Logic Tree'!$I$85:$I$87,0),MATCH(H105,'Logic Tree'!$J$84:$N$84,0)) -> 2.7
B106: 2 | C106: TEAM | D106: CPA | E106: TEAM | F106: ='Pod Library'!E49 -> Application Developer | G106: ='Pod Library'!F49 -> DEV | H106: ='Pod Library'!G49 -> E2 | I106: ='Pod Library'!H49 -> ON | J106: ='Pod Library'!I49 -> FTC | K106: ='Pod Library'!J49 -> 2.75 | L106: ='Pod Plan'!F11 -> 1 | M106: =K106*L106 -> 2.75 | N106: =M106*INDEX('Logic Tree'!$J$85:$N$87,MATCH(I106,'Logic Tree'!$I$85:$I$87,0),MATCH(H106,'Logic Tree'!$J$84:$N$84,0)) -> 2.75
B107: 2 | C107: TEAM | D107: CPA | E107: TEAM | F107: ='Pod Library'!E50 -> Application Developer | G107: ='Pod Library'!F50 -> DEV | H107: ='Pod Library'!G50 -> E3 | I107: ='Pod Library'!H50 -> NEAR | J107: ='Pod Library'!I50 -> FTC | K107: ='Pod Library'!J50 -> 0.75 | L107: ='Pod Plan'!F11 -> 1 | M107: =K107*L107 -> 0.75 | N107: =M107*INDEX('Logic Tree'!$J$85:$N$87,MATCH(I107,'Logic Tree'!$I$85:$I$87,0),MATCH(H107,'Logic Tree'!$J$84:$N$84,0)) -> 0.63
...

Sheet SIT Loading
A1: SIT loading — turning fractional FTE into whole people and whole months
A2: The seat ledger is a demand model, not a roster. A line of 1.38 heads is 16.6 person-months of demand spread across several pods. This sheet converts that into something SIT can load without inventing or losing people.
A4: A. WHY YOU CANNOT ROUND THE SEAT LEDGER
B5: Approach | C5: Y1 | D5: Y2 | E5: Y3 | F5: Y4 | G5: Y5 | H5: Verdict
B6: Modelled FTE (the commercial number) | C6: 121.5 | D6: 93.5 | E6: 76 | F6: 65.5 | G6: 59.5
B7: Round every ledger row UP to whole heads | C7: 145 | D7: 118 | E7: 92 | F7: 91 | G7: 73 | H7: INFLATES Year 1 by 23 people — 19%. 242 ledger rows each round up by up to 0.99 of a person.
B8: Round every ledger row to nearest | C8: 116 | D8: 87 | E8: 71 | F8: 53 | G8: 53 | H8: Total is roughly right but every individual line is wrong, and the FTC / FTE / MGCC split drifts. It also implies each pod has its own dedicated architect, tester and support engineer.
B9: This sheet — aggregate first, then whole people and months | C9: 121.5 | D9: 93.5 | E9: 76 | F9: 65.5 | G9: 59.5 | H9: Exact on total, on each sourcing type and on person-months.
A11: B. THE RULE
B12: Aggregate the ledger to the level at which a person is actually hired — year x role x band x location x sourcing — and only then convert to bodies. A pod seat of 0.23 is not a person; the same role summed across six pods is.
B13: Treatment | C13: When it applies | D13: How SIT loads it | E13: Example
B14: RAMPED | C14: Delivery roles — engineers, testers, analysts inside pods and teams. The work is divisible over time and people join and leave pods. | G14: floor(FTE) people for 12 months, plus one person for the remaining months. | J14: 7.73 FTE = 7 people all year + 1 person for 8.7 months
B15: SHARED | C15: Roles that need continuous presence — leads, architects, service delivery managers, PMO — and any line below 0.5 FTE. | G15: One person at a partial allocation for the whole year, the balance of their time on another domain. | J15: 0.95 FTE = 1 Chief Architect at 95%, 5% elsewhere
B16: Both give identical person-months. Neither loads a partial person into a month and neither allocates anybody above 100%. Person-months is the invariant SIT must reproduce: FTE x 12.
A18: C. RECONCILIATION — what SIT must tie back to
B19: Measure | C19: Y1 | D19: Y2 | E19: Y3 | F19: Y4 | G19: Y5 | H19: Note
B20: Modelled FTE | C20: 121.5 | D20: 93.5 | E20: 76 | F20: 65.5 | G20: 59.5 | H20: From the seat ledger. This is the commercial number and it does not change.
B21: Person-months = FTE x 12 | C21: 1458 | D21: 1122 | E21: 912 | F21: 786 | G21: 714 | H21: THE INVARIANT. SIT's monthly loading must sum to this.
B22: Bodies to requisition | C22: 129 | D22: 101 | E22: 84 | F22: 75 | G22: 66 | H22: Named people. Higher than FTE because some are part-year or part-allocated.
B23: — of which full-time, all year | C23: 114 | D23: 86 | E23: 68 | F23: 56 | G23: 53 | H23: The core roster. Everything else is a partial assignment.
B24: Average allocation across all bodies | C24: 0.94186047 | D24: 0.92574257 | E24: 0.9047619 | F24: 0.87333333 | G24: 0.90151515 | H24: If this drops below about 70% the pod design is too fragmented — check it.
A26: D. THE REQUISITION PLAN — load these lines into SIT
B27: Year | C27: Sourcing | D27: Role | E27: Band | F27: Location | G27: Unit type | H27: Modelled FTE | I27: Person-months | J27: Treatment | K27: Full-time heads | L27: +1 head for (months) | M27: Allocation of the part head
B28: 1 | C28: FTC | D28: BSA | E28: E3 | F28: ON | G28: Delivery | H28: 3.5 | I28: 42 | J28: RAMPED | K28: 3 | L28: 6
B29: 1 | C29: FTC | D29: DEV | E29: E2 | F29: OFF | G29: Delivery | H29: 1 | I29: 12 | J29: RAMPED | K29: 1
B30: 1 | C30: FTC | D30: DEV | E30: E2 | F30: ON | G30: Delivery | H30: 17.5 | I30: 210 | J30: RAMPED | K30: 17 | L30: 6
B31: 1 | C31: FTC | D31: DEV | E31: E3 | F31: NEAR | G31: Delivery | H31: 8 | I31: 96 | J31: RAMPED | K31: 8
B32: 1 | C32: FTC | D32: DEV | E32: E3 | F32: OFF | G32: Delivery | H32: 0 | I32: 0 | J32: SHARED | K32: 0
B33: 1 | C33: FTC | D33: DEV | E33: E3 | F33: ON | G33: Delivery | H33: 16 | I33: 192 | J33: RAMPED | K33: 16
B34: 1 | C34: FTC | D34: DEV | E34: E4 | F34: ON | G34: Delivery | H34: 18 | I34: 216 | J34: RAMPED | K34: 18
B35: 1 | C35: FTC | D35: OTH | E35: E4 | F35: ON | G35: Delivery | H35: 0 | I35: 0 | J35: SHARED | K35: 0
B36: 1 | C36: FTC | D36: OTH | E36: E5 | F36: ON | G36: Delivery | H36: 1.5 | I36: 18 | J36: SHARED | K36: 1 | L36: 6 | M36: 0.5
B37: 1 | C37: FTC | D37: TEST | E37: E2 | F37: NEAR | G37: Delivery | H37: 1 | I37: 12 | J37: RAMPED | K37: 1
B38: 1 | C38: FTC | D38: TEST | E38: E3 | F38: OFF | G38: Delivery | H38: 0 | I38: 0 | J38: SHARED | K38: 0
B39: 1 | C39: FTC | D39: TEST | E39: E3 | F39: ON | G39: Delivery | H39: 5 | I39: 60 | J39: RAMPED | K39: 5
B40: 1 | C40: FTC | D40: BSA | E40: E3 | F40: OFF | G40: Horizontal | H40: 0.5 | I40: 6 | J40: SHARED | K40: 0 | L40: 6 | M40: 0.5
B41: 1 | C41: FTC | D41: BSA | E41: E3 | F41: ON | G41: Horizontal | H41: 1.5 | I41: 18 | J41: SHARED | K41: 1 | L41: 6 | M41: 0.5
B42: 1 | C42: FTC | D42: DEV | E42: E4 | F42: OFF | G42: Horizontal | H42: 0.5 | I42: 6 | J42: SHARED | K42: 0 | L42: 6 | M42: 0.5
B43: 1 | C43: FTC | D43: MNT | E43: E2 | F43: NEAR | G43: Horizontal | H43: 0.5 | I43: 6 | J43: SHARED | K43: 0 | L43: 6 | M43: 0.5
B44: 1 | C44: FTC | D44: MNT | E44: E2 | F44: OFF | G44: Horizontal | H44: 0.5 | I44: 6 | J44: SHARED | K44: 0 | L44: 6 | M44: 0.5
B45: 1 | C45: FTC | D45: MNT | E45: E3 | F45: ON | G45: Horizontal | H45: 2 | I45: 24 | J45: SHARED | K45: 2
B46: 1 | C46: FTC | D46: OTH | E46: E3 | F46: OFF | G46: Horizontal | H46: 1 | I46: 12 | J46: SHARED | K46: 1
B47: 1 | C47: FTC | D47: OTH | E47: E4 | F47: ON | G47: Horizontal | H47: 0.5 | I47: 6 | J47: SHARED | K47: 0 | L47: 6 | M47: 0.5
B48: 1 | C48: FTC | D48: OTH | E48: E5 | F48: ON | G48: Horizontal | H48: 0.5 | I48: 6 | J48: SHARED | K48: 0 | L48: 6 | M48: 0.5
B49: 1 | C49: FTC | D49: PM | E49: E4 | F49: ON | G49: Horizontal | H49: 3.5 | I49: 42 | J49: SHARED | K49: 3 | L49: 6 | M49: 0.5
B50: 1 | C50: FTC | D50: PM | E50: E5 | F50: ON | G50: Horizontal | H50: 1 | I50: 12 | J50: SHARED | K50: 1
B51: 1 | C51: FTC | D51: TEST | E51: E3 | F51: OFF | G51: Horizontal | H51: 1 | I51: 12 | J51: SHARED | K51: 1
B52: 1 | C52: FTC | D52: TEST | E52: E4 | F52: ON | G52: Horizontal | H52: 0.5 | I52: 6 | J52: SHARED | K52: 0 | L52: 6 | M52: 0.5
B53: 1 | C53: FTE | D53: BSA | E53: E4 | F53: ON | G53: Delivery | H53: 5 | I53: 60 | J53: RAMPED | K53: 5
B54: 1 | C54: FTE | D54: MNT | E54: E3 | F54: ON | G54: Delivery | H54: 1 | I54: 12 | J54: RAMPED | K54: 1
B55: 1 | C55: FTE | D55: PM | E55: E4 | F55: ON | G55: Delivery | H55: 4.5 | I55: 54 | J55: SHARED | K55: 4 | L55: 6 | M55: 0.5
B56: 1 | C56: FTE | D56: MNT | E56: E4 | F56: ON | G56: Horizontal | H56: 2.5 | I56: 30 | J56: SHARED | K56: 2 | L56: 6 | M56: 0.5
B57: 1 | C57: FTE | D57: PM | E57: E4 | F57: ON | G57: Horizontal | H57: 1 | I57: 12 | J57: SHARED | K57: 1
B58: 1 | C58: MGCC | D58: DEV | E58: E3 | F58: OFF | G58: Delivery | H58: 15 | I58: 180 | J58: RAMPED | K58: 15
B59: 1 | C59: MGCC | D59: TEST | E59: E2 | F59: OFF | G59: Delivery | H59: 3 | I59: 36 | J59: RAMPED | K59: 3
B60: 1 | C60: MGCC | D60: DEV | E60: E4 | F60: OFF | G60: Horizontal | H60: 1.5 | I60: 18 | J60: SHARED | K60: 1 | L60: 6 | M60: 0.5
B61: 1 | C61: MGCC | D61: TEST | E61: E2 | F61: OFF | G61: Horizontal | H61: 3 | I61: 36 | J61: SHARED | K61: 3
B62: 2 | C62: FTC | D62: BSA | E62: E3 | F62: ON | G62: Delivery | H62: 8 | I62: 96 | J62: RAMPED | K62: 8
B63: 2 | C63: FTC | D63: DEV | E63: E2 | F63: OFF | G63: Delivery | H63: 4 | I63: 48 | J63: RAMPED | K63: 4
B64: 2 | C64: FTC | D64: DEV | E64: E2 | F64: ON | G64: Delivery | H64: 5.5 | I64: 66 | J64: RAMPED | K64: 5 | L64: 6
B65: 2 | C65: FTC | D65: DEV | E65: E3 | F65: NEAR | G65: Delivery | H65: 1.5 | I65: 18 | J65: RAMPED | K65: 1 | L65: 6
B66: 2 | C66: FTC | D66: DEV | E66: E3 | F66: OFF | G66: Delivery | H66: 4.5 | I66: 54 | J66: RAMPED | K66: 4 | L66: 6
B67: 2 | C67: FTC | D67: DEV | E67: E3 | F67: ON | G67: Delivery | H67: 4 | I67: 48 | J67: RAMPED | K67: 4
B68: 2 | C68: FTC | D68: DEV | E68: E4 | F68: ON | G68: Delivery | H68: 10.5 | I68: 126 | J68: RAMPED | K68: 10 | L68: 6
B69: 2 | C69: FTC | D69: OTH | E69: E4 | F69: ON | G69: Delivery | H69: 1 | I69: 12 | J69: SHARED | K69: 1
B70: 2 | C70: FTC | D70: OTH | E70: E5 | F70: ON | G70: Delivery | H70: 5 | I70: 60 | J70: SHARED | K70: 5
B71: 2 | C71: FTC | D71: TEST | E71: E2 | F71: NEAR | G71: Delivery | H71: 2 | I71: 24 | J71: RAMPED | K71: 2
B72: 2 | C72: FTC | D72: TEST | E72: E3 | F72: OFF | G72: Delivery | H72: 0 | I72: 0 | J72: SHARED | K72: 0
B73: 2 | C73: FTC | D73: TEST | E73: E3 | F73: ON | G73: Delivery | H73: 2 | I73: 24 | J73: RAMPED | K73: 2
B74: 2 | C74: FTC | D74: BSA | E74: E3 | F74: OFF | G74: Horizontal | H74: 0.5 | I74: 6 | J74: SHARED | K74: 0 | L74: 6 | M74: 0.5
B75: 2 | C75: FTC | D75: BSA | E75: E3 | F75: ON | G75: Horizontal | H75: 2 | I75: 24 | J75: SHARED | K75: 2
B76: 2 | C76: FTC | D76: DEV | E76: E4 | F76: OFF | G76: Horizontal | H76: 2 | I76: 24 | J76: SHARED | K76: 2
B77: 2 | C77: FTC | D77: MNT | E77: E2 | F77: NEAR | G77: Horizontal | H77: 0.5 | I77: 6 | J77: SHARED | K77: 0 | L77: 6 | M77: 0.5
B78: 2 | C78: FTC | D78: MNT | E78: E2 | F78: OFF | G78: Horizontal | H78: 0.5 | I78: 6 | J78: SHARED | K78: 0 | L78: 6 | M78: 0.5
B79: 2 | C79: FTC | D79: MNT | E79: E3 | F79: ON | G79: Horizontal | H79: 1 | I79: 12 | J79: SHARED | K79: 1
B80: 2 | C80: FTC | D80: OTH | E80: E3 | F80: OFF | G80: Horizontal | H80: 2 | I80: 24 | J80: SHARED | K80: 2
B81: 2 | C81: FTC | D81: OTH | E81: E4 | F81: ON | G81: Horizontal | H81: 2 | I81: 24 | J81: SHARED | K81: 2
B82: 2 | C82: FTC | D82: OTH | E82: E5 | F82: ON | G82: Horizontal | H82: 0.5 | I82: 6 | J82: SHARED | K82: 0 | L82: 6 | M82: 0.5
B83: 2 | C83: FTC | D83: PM | E83: E4 | F83: ON | G83: Horizontal | H83: 0.5 | I83: 6 | J83: SHARED | K83: 0 | L83: 6 | M83: 0.5
B84: 2 | C84: FTC | D84: PM | E84: E5 | F84: ON | G84: Horizontal | H84: 0.5 | I84: 6 | J84: SHARED | K84: 0 | L84: 6 | M84: 0.5
B85: 2 | C85: FTC | D85: TEST | E85: E3 | F85: OFF | G85: Horizontal | H85: 2.5 | I85: 30 | J85: SHARED | K85: 2 | L85: 6 | M85: 0.5
B86: 2 | C86: FTC | D86: TEST | E86: E4 | F86: ON | G86: Horizontal | H86: 1.5 | I86: 18 | J86: SHARED | K86: 1 | L86: 6 | M86: 0.5
B87: 2 | C87: FTE | D87: BSA | E87: E4 | F87: ON | G87: Delivery | H87: 3 | I87: 36 | J87: RAMPED | K87: 3
B88: 2 | C88: FTE | D88: MNT | E88: E3 | F88: ON | G88: Delivery | H88: 1 | I88: 12 | J88: RAMPED | K88: 1
B89: 2 | C89: FTE | D89: PM | E89: E4 | F89: ON | G89: Delivery | H89: 4 | I89: 48 | J89: SHARED | K89: 4
B90: 2 | C90: FTE | D90: MNT | E90: E4 | F90: ON | G90: Horizontal | H90: 2 | I90: 24 | J90: SHARED | K90: 2
B91: 2 | C91: FTE | D91: PM | E91: E4 | F91: ON | G91: Horizontal | H91: 1.5 | I91: 18 | J91: SHARED | K91: 1 | L91: 6 | M91: 0.5
B92: 2 | C92: MGCC | D92: DEV | E92: E3 | F92: OFF | G92: Delivery | H92: 10.5 | I92: 126 | J92: RAMPED | K92: 10 | L92: 6
B93: 2 | C93: MGCC | D93: TEST | E93: E2 | F93: OFF | G93: Delivery | H93: 5 | I93: 60 | J93: RAMPED | K93: 5
B94: 2 | C94: MGCC | D94: DEV | E94: E4 | F94: OFF | G94: Horizontal | H94: 0.5 | I94: 6 | J94: SHARED | K94: 0 | L94: 6 | M94: 0.5
B95: 2 | C95: MGCC | D95: TEST | E95: E2 | F95: OFF | G95: Horizontal | H95: 2 | I95: 24 | J95: SHARED | K95: 2
B96: 3 | C96: FTC | D96: BSA | E96: E3 | F96: ON | G96: Delivery | H96: 5 | I96: 60 | J96: RAMPED | K96: 5
B97: 3 | C97: FTC | D97: DEV | E97: E2 | F97: OFF | G97: Delivery | H97: 5.5 | I97: 66 | J97: RAMPED | K97: 5 | L97: 6
B98: 3 | C98: FTC | D98: DEV | E98: E3 | F98: OFF | G98: Delivery | H98: 8.5 | I98: 102 | J98: RAMPED | K98: 8 | L98: 6
B99: 3 | C99: FTC | D99: DEV | E99: E4 | F99: ON | G99: Delivery | H99: 9 | I99: 108 | J99: RAMPED | K99: 9
B100: 3 | C100: FTC | D100: OTH | E100: E5 | F100: ON | G100: Delivery | H100: 7 | I100: 84 | J100: SHARED | K100: 7
B101: 3 | C101: FTC | D101: TEST | E101: E3 | F101: OFF | G101: Delivery | H101: 0 | I101: 0 | J101: SHARED | K101: 0
B102: 3 | C102: FTC | D102: BSA | E102: E3 | F102: OFF | G102: Horizontal | H102: 1 | I102: 12 | J102: SHARED | K102: 1
B103: 3 | C103: FTC | D103: BSA | E103: E3 | F103: ON | G103: Horizontal | H103: 4 | I103: 48 | J103: SHARED | K103: 4
B104: 3 | C104: FTC | D104: DEV | E104: E4 | F104: OFF | G104: Horizontal | H104: 0.5 | I104: 6 | J104: SHARED | K104: 0 | L104: 6 | M104: 0.5
...

Sheet Unit Cost Sensitivity
A1: Unit cost sensitivity — four levers now, not three
A2: Productivity, offshore share and seniority, plus the agile conversion, which which the other three all depend on.
A4: A. THE MODEL — unit cost = k x (1 - productivity) x average cost per head
B5: average cost per head = offshore x [senior x OFF_SR + (1-senior) x OFF_JM] + onshore x [senior x ON_SR + (1-senior) x ON_JM]
A7: B. TIER COST PARAMETERS — from the Year-5 roster
B8: Tier | C8: Onshore Tokyo | D8: Offshore
