Workbook

Sheet README
A1: MetLife Japan | Data Infrastructure — Domain Framework & Pricing Engine
A2: INTERNAL — Capgemini review copy. Three applications, two value streams, MGCC already embedded.
A4: WHAT IS DIFFERENT ABOUT THIS DOMAIN
B5: Scale | C5: Three applications, 100.8 effort units — 6.7% of the portfolio. Contract Management is 28 applications and 230.8 units.
B6: Two value streams | C6: Informatica (BCMETL + BCMHRP, 50.7u) and Azure Synapse (JDPREP, 50.1u). Almost exactly half each.
B7: Sunset asymmetry | C7: Synapse is the go-forward platform. Informatica is on a sunset path, but the modernisation is OUT OF SCOPE of this RFP — so we run it, we do not migrate it, and we do not build an agent estate for it.
B8: MGCC is already here | C8: 16.0 units of MGCC across both platforms. Contract Management had none. That changes the 50:50 arithmetic completely.
B9: The headline finding | C9: Productivity alone crosses 50:50 during Year 3 and lands at 41:59. Year 2 sits just short at 52:48. No transfer of employment is required in this domain — the opposite question arises.
A10: HOW THE MODEL WORKS
B11: Direction of travel | C11: Bottom-up. You define seats in pods; the workbook derives headcount, productivity, offshore share, experience mix and cost. Nothing is asserted.
B12: Realisation is per value stream | C12: Not just per archetype. Informatica realises less of its AI ceiling because we are not investing in a platform being retired.
B13: Offshore is measured on Capgemini effort | C13: The 19 onshore MetLife FTE are their placement decision, not ours. The ceiling governs the work we can place, so the tree is applied to Capgemini seats.
B14: Pod sizes are not a uniform ladder | C14: Synapse 9→7→6, Informatica 8→7→6, and fully-sourced pods differ from co-sourced. See the Pod Library sheet.
B15: Fully-sourced pods carry MetLife too | C15: A product owner, and on Synapse a data architect — fractional in Year 1 where shared across two pods. Full ownership of the output still sits with Capgemini.
A16: CELL COLOUR CONVENTION
B17: Blue text | C17: Input. Change these.
B18: Black text | C18: Formula. Do not overwrite.
B19: Green text | C19: Link to another sheet in this workbook.
B20: Amber fill | C20: Key assumption requiring sign-off before this model is used to price.
A21: SHEET MAP
B22: Logic Tree | C22: Parametric drivers: phase mix, AI ceiling per archetype, realisation per value stream, offshore ceilings, cost index.
B23: Inventory | C23: All 142 applications with derived archetype. Filter to a domain to see its mix.
B24: Value Streams | C24: The two streams, their applications and the AD / run split.
B25: Pod Library | C25: INPUT. Every seat in every pod archetype, by year AND by value stream. Counts may be fractional.
B26: Pod Plan | C26: INPUT. Co-sourced and fully-sourced pod counts per stream per year.
B27: Horizontal Teams | C27: INPUT. The three cross-cutting teams.
B28: Seat Ledger | C28: Computed. Every pod line multiplied out, plus horizontals. All roll-ups read from here.
B29: Team Build-Up | C29: Computed. Headcount by year, sourcing, location, experience band and skill family.
B30: Glidepath & 50-50 | C30: Computed. Productivity and offshore, target vs delivered, and the ratio.
B31: Cost & Commercial | C31: Computed. Cost index, unit cost, and the Capgemini position.
B32: Unit Cost Sensitivity | C32: NEW. How experience mix, offshore share and productivity interact to move unit cost.
A33: ASSUMPTIONS REQUIRING SIGN-OFF
B34: Cost index | C34: Relative only. Onshore Tokyo E2 = 1.00, offshore roughly one third at like-for-like band. Replace with the approved rate card before pricing.
B35: Informatica realisation | C35: 20 / 40 / 55% against its ceiling, versus 25 / 55 / 75% for Synapse. This is the sunset discount and it is a judgement, not a measurement.
B36: Informatica is a priority transfer target | C36: Both BCMETL and BCMHRP carry Priority Transfer Targets = Y. The portfolio bedrock says route archetype C to MGCC. Because this platform is being retired, transferring it builds a capability MetLife will not keep — see the decision on Glidepath & 50-50.

Sheet Logic Tree
A1: Logic Tree — parametric drivers for productivity, offshore and cost
A2: Change the blue cells. Every downstream number re-derives.
A4: A. DOMAIN AND EFFORT BASE
B5: Domain | C5: Data Infrastructure | I5: Must match the Inventory domain column exactly.
B6: Applications in domain | C6: =SUMIFS(Inventory!$U:$U,Inventory!$E:$E,$C$5) -> 3
B7: Total effort (units) | C7: =SUMIFS(Inventory!$AD:$AD,Inventory!$E:$E,$C$5) -> 100.76497
B8: Current FTC | C8: =SUMIFS(Inventory!$AA:$AA,Inventory!$E:$E,$C$5) -> 64.704594
B9: Current FTE | C9: =SUMIFS(Inventory!$AB:$AB,Inventory!$E:$E,$C$5) -> 18.825
B10: Current MGCC | C10: =SUMIFS(Inventory!$AC:$AC,Inventory!$E:$E,$C$5) -> 15.991667
B11: AD effort (%PRJ weighted) | C11: =SUMIFS(Inventory!$AF:$AF,Inventory!$E:$E,$C$5) -> 87.126844
B12: Run effort | C12: =C7-C11 -> 13.638125
B13: AD share of effort | C13: =IF(C7=0,0,C11/C7) -> 0.8646541
A15: B. ARCHETYPE MIX OF THIS DOMAIN
B16: Archetype | C16: Definition | D16: Apps | E16: Effort | F16: Share
B17: A | C17: Language-locked | D17: =SUMIFS(Inventory!$U:$U,Inventory!$E:$E,$C$5,Inventory!$AG:$AG,$B17) -> 0 | E17: =SUMIFS(Inventory!$AD:$AD,Inventory!$E:$E,$C$5,Inventory!$AG:$AG,$B17) -> 0 | F17: =IF($C$7=0,0,E17/$C$7) -> 0
B18: B | C18: Offshore-ready — modern stack, not a transfer target | D18: =SUMIFS(Inventory!$U:$U,Inventory!$E:$E,$C$5,Inventory!$AG:$AG,$B18) -> 1 | E18: =SUMIFS(Inventory!$AD:$AD,Inventory!$E:$E,$C$5,Inventory!$AG:$AG,$B18) -> 50.06501 | F18: =IF($C$7=0,0,E18/$C$7) -> 0.49684936
B19: C | C19: MGCC-destined — Priority Transfer Target = Y | D19: =SUMIFS(Inventory!$U:$U,Inventory!$E:$E,$C$5,Inventory!$AG:$AG,$B19) -> 2 | E19: =SUMIFS(Inventory!$AD:$AD,Inventory!$E:$E,$C$5,Inventory!$AG:$AG,$B19) -> 50.699958 | F19: =IF($C$7=0,0,E19/$C$7) -> 0.50315064
B20: D | C20: Legacy-coupled core | D20: =SUMIFS(Inventory!$U:$U,Inventory!$E:$E,$C$5,Inventory!$AG:$AG,$B20) -> 0 | E20: =SUMIFS(Inventory!$AD:$AD,Inventory!$E:$E,$C$5,Inventory!$AG:$AG,$B20) -> 0 | F20: =IF($C$7=0,0,E20/$C$7) -> 0
B21: Total | D21: =SUM(D17:D20) -> 3 | E21: =SUM(E17:E20) -> 100.76497 | F21: =SUM(F17:F20) -> 1
A23: C. PRODUCTIVITY — GATE 1 : where the effort sits
B24: Delivery phase | C24: Share of effort
B25: Requirements & impact analysis | C25: 0.12
B26: Design & architecture | C26: 0.13
B27: Build & code | C27: 0.3
B28: Test & quality assurance | C28: 0.25
B29: Release & deploy | C29: 0.05
B30: Run, monitor & coordinate | C30: 0.15
B31: Total (must equal 100%) | C31: =SUM(C25:C30) -> 1
A33: D. PRODUCTIVITY — GATE 2 : AI-addressable share per phase, per archetype
B34: Delivery phase | C34: A | D34: B | E34: C | F34: D
B35: Requirements & impact analysis | C35: 0.22 | D35: 0.3 | E35: 0.15 | F35: 0.35 | G35: Potential Metlife internal AI Tools
B36: Design & architecture | C36: 0.2 | D36: 0.35 | E36: 0.12 | F36: 0.22 | G36: MetIQ
B37: Build & code | C37: 0.32 | D37: 0.5 | E37: 0.25 | F37: 0.2 | G37: Github Copilot
B38: Test & quality assurance | C38: 0.38 | D38: 0.6 | E38: 0.3 | F38: 0.4 | G38: Databricks Genie
B39: Release & deploy | C39: 0.3 | D39: 0.35 | E39: 0.1 | F39: 0.25 | G39: MS Foundry
B40: Run, monitor & coordinate | C40: 0.3 | D40: 0.3 | E40: 0.08 | F40: 0.32
B41: Weighted AI ceiling | C41: =SUMPRODUCT($C$25:$C$30,C35:C40) -> 0.3034 | D41: =SUMPRODUCT($C$25:$C$30,D35:D40) -> 0.444 | E41: =SUMPRODUCT($C$25:$C$30,E35:E40) -> 0.2006 | F41: =SUMPRODUCT($C$25:$C$30,F35:F40) -> 0.2911 | G41: Informatica legacy estate's AI-driven productivity is much lesser as it is On-premise and also undergoing modernization so GenAI tools are not fully effective for Archetype C-2 Apps; compared to Modern Azure Stack for Archetype B -1 App
A43: E. GATE 3 : realisation, PER VALUE STREAM — Informatica carries a sunset discount
B44: Value stream | C44: Archetype | D44: Year 1 | E44: Year 2 | F44: Year 3 | G44: Why it differs
B45: VS1 · Informatica | C45: C | D45: 0.2 | E45: 0.4 | F45: 0 | G45: Sunset path — no agent estate is built for a platform being retired
B46: VS2 · Azure Synapse | C46: B | D46: 0.25 | E46: 0.55 | F46: 0.75 | G46: Go-forward platform — full adoption curve
A48: F. GATE 4 : the two non-AI components (cumulative)
B49: Driver | C49: Year 1 | D49: Year 2 | E49: Year 3
B50: Classical ADM productivity | C50: 0.02 | D50: 0.05 | E50: 0.07
B51: Operating-model productivity | C51: 0.03 | D51: 0.06 | E51: 0.08
A53: G. RESULT : gross productivity by value stream, and for the domain
C54: Year 1 | D54: Year 2 | E54: Year 3
B55: VS1 gross productivity | C55: =1-(1-E$41*D45)*(1-C$50)*(1-C$51) -> 0.087538072 | D55: =1-(1-E$41*E45)*(1-D$50)*(1-D$51) -> 0.17865432 | E55: =1-(1-E$41*F45)*(1-E$50)*(1-E$51) -> 0.1444
B56: VS2 gross productivity | C56: =1-(1-D$41*D46)*(1-C$50)*(1-C$51) -> 0.1549166 | D56: =1-(1-D$41*E46)*(1-D$50)*(1-D$51) -> 0.3250706 | E56: =1-(1-D$41*F46)*(1-E$50)*(1-E$51) -> 0.4293148
B57: DOMAIN gross productivity (effort-weighted) | C57: =IF($C$7=0,0,(C55*$E$19+C56*$E$18)/$C$7) -> 0.12101505 | D57: =IF($C$7=0,0,(D55*$E$19+D56*$E$18)/$C$7) -> 0.25140116 | E57: =IF($C$7=0,0,(E55*$E$19+E56*$E$18)/$C$7) -> 0.28595974
A59: H. OFFSHORE — ceiling per value stream, realisation applied to CAPGEMINI effort
C60: Ceiling | D60: Year 1 | E60: Year 2 | F60: Year 3 | G60: Why capped there
B61: VS1 · Informatica | C61: 0.7 | D61: =$C61*D$64 -> 0.525 | E61: =$C61*E$64 -> 0.616 | F61: =$C61*F$64 -> 0.665 | H61: HOST/AS400 integration and Japanese master-data context stay onshore
B62: VS2 · Azure Synapse | C62: 0.78 | D62: =$C62*D$64 -> 0.585 | E62: =$C62*E$64 -> 0.6864 | F62: =$C62*F$64 -> 0.741 | H62: Modern PaaS, no language lock — the archetype B ceiling
B64: Realisation against ceiling | D64: 0.75 | E64: 0.88 | F64: 0.95
B65: DOMAIN offshore target (Capgemini effort) | D65: =IF($C$7=0,0,(D61*$E$19+D62*$E$18)/$C$7) -> 0.55481096 | E65: =IF($C$7=0,0,(E61*$E$19+E62*$E$18)/$C$7) -> 0.6509782 | F65: =IF($C$7=0,0,(F61*$E$19+F62*$E$18)/$C$7) -> 0.70276055
A67: I. TRANSFER OF EMPLOYMENT — none required in this domain. Year 3 is the only year it could occur.
B68: Transfer in year | C68: Year 1 | D68: Year 2 | E68: Year 3
B69: Capgemini to MetLife Japan (FTE) | C69: 0 | D69: 0 | E69: 0
B70: Capgemini to MetLife MGCC | C70: 0 | D70: 0 | E70: 0
B71: Cumulative transferred | C71: =SUM($C$69:C70) -> 0 | D71: =SUM($C$69:D70) -> 0 | E71: =SUM($C$69:E70) -> 0
B72: This domain needs none. Productivity alone crosses 50:50 during Year 3 — Year 2 still sits just short at 52:48.
A74: J. COST INDEX — onshore Tokyo E2 = 1.00
B75: Location | C75: E1 0-3y | D75: E2 3-6y | E75: E3 6-10y | F75: E4 10-15y | G75: E5 15y+
B76: Onshore Tokyo | C76: 0.72 | D76: 1 | E76: 1.35 | F76: 1.85 | G76: 2.55
B77: Offshore Hyderabad | C77: 0.22 | D77: 0.3 | E77: 0.42 | F77: 0.6 | G77: 0.85
I79: key | J79: E1 | K79: E2 | L79: E3 | M79: E4 | N79: E5
I80: ON | J80: =C76 -> 0.72 | K80: =D76 -> 1 | L80: =E76 -> 1.35 | M80: =F76 -> 1.85 | N80: =G76 -> 2.55
I81: OFF | J81: =C77 -> 0.22 | K81: =D77 -> 0.3 | L81: =E77 -> 0.42 | M81: =F77 -> 0.6 | N81: =G77 -> 0.85
I82: Lookup keys for the Seat Ledger. Do not edit.

Sheet Inventory
A1: Application inventory — Appendix 3 v2, with derived archetype and value stream
A2: Archetype applied at build time by the rule: mainframe language → D; else Priority Transfer Target → C; else SaaS → A; else B. Columns AG and AH are literals, re-derived when the model is rebuilt.
A4: # | B4: EAI ID | C4: Application | D4: Long name | E4: Domain | F4: Group | G4: Team | H4: Class | I4: Critical | J4: Hosting | K4: Primary code language | L4: Cloud platform | M4: Priority transfer | N4: Current FTC | O4: Current FTE | P4: Current MGCC | Q4: Total | R4: % of PRJ | S4: Target FTC | T4: Target FTE/MGCC | U4: App count | AA4: FTC | AB4: FTE | AC4: MGCC | AD4: Effort | AE4: AD share | AF4: AD effort | AG4: Archetype | AH4: Value stream
A5: 1 | B5: 9629 | C5: Global Sales Comp - Japan | D5: Global Sales Comp - Japan | E5: Fee Management | F5: Core Insurance Systems Group 34956 | G5: Commission Systems Team 34958 | H5: Core Business Application | I5: N | J5: Yes | K5: Other#Infomatica workflow Bash shell Dos batch | L5: Software as a Service (SaaS) | M5: N | N5: 0 | O5: 0 | P5: 0 | Q5: 0 | R5: 0 | U5: 1 | AA5: =N5 -> 0 | AB5: =O5 -> 0 | AC5: =P5 -> 0 | AD5: =Q5 -> 0 | AE5: =R5 -> 0 | AF5: =Q5*R5 -> 0 | AG5: A
A6: 2 | B6: 9796 | C6: LC POSPMC MF-JPN | D6: LifeComm POSPMC | E6: contract management | F6: Core Insurance Systems Group 34956 | G6: Policy Admin Systems Team 34957 | H6: Core Business Application | I6: Y | J6: Yes | K6: Assembler, COBOL, MU(EASYPLUS), JCL | M6: N | N6: 59.558958 | O6: 7.7541667 | P6: 0 | Q6: 67.313125 | R6: 0.71176374 | S6: 33.656563 | T6: 33.656563 | U6: 1 | AA6: =N6 -> 59.558958 | AB6: =O6 -> 7.7541667 | AC6: =P6 -> 0 | AD6: =Q6 -> 67.313125 | AE6: =R6 -> 0.71176374 | AF6: =Q6*R6 -> 47.911042 | AG6: D
A7: 3 | B7: 9800 | C7: LC Billing MF-JPN | D7: LifeComm Billing | E7: contract management | F7: Core Insurance Systems Group 34956 | G7: Policy Admin Systems Team 34957 | H7: Core Business Application | I7: Y | J7: Yes | K7: COBOL, Assembler, MU(EASYPLUS), JCL | M7: N | N7: 20.892167 | O7: 1.85375 | P7: 0 | Q7: 22.745917 | R7: 0.94285788 | S7: 11.372958 | T7: 11.372958 | U7: 1 | AA7: =N7 -> 20.892167 | AB7: =O7 -> 1.85375 | AC7: =P7 -> 0 | AD7: =Q7 -> 22.745917 | AE7: =R7 -> 0.94285788 | AF7: =Q7*R7 -> 21.446167 | AG7: D
A8: 4 | B8: 9801 | C8: LC Collection MF-JPN | D8: LifeComm Collection | E8: contract management | F8: Core Insurance Systems Group 34956 | G8: Policy Admin Systems Team 34957 | H8: Core Business Application | I8: Y | J8: Yes | K8: COBOL, Assembler, MU(EASYPLUS), JCL | M8: N | N8: 0 | O8: 0 | P8: 0 | Q8: 0 | R8: 0 | U8: 1 | AA8: =N8 -> 0 | AB8: =O8 -> 0 | AC8: =P8 -> 0 | AD8: =Q8 -> 0 | AE8: =R8 -> 0 | AF8: =Q8*R8 -> 0 | AG8: D
A9: 5 | B9: 9802 | C9: LC Corresponding MF-JPN | D9: LifeComm Corresponding | E9: contract management | F9: Core Insurance Systems Group 34956 | G9: Policy Admin Systems Team 34957 | H9: Core Business Application | I9: Y | J9: Yes | K9: COBOL, Assembler, MU(EASYPLUS), JCL | M9: N | N9: 15.953625 | O9: 1.6541667 | P9: 0 | Q9: 17.607792 | R9: 0.98287217 | S9: 8.8038958 | T9: 8.8038958 | U9: 1 | AA9: =N9 -> 15.953625 | AB9: =O9 -> 1.6541667 | AC9: =P9 -> 0 | AD9: =Q9 -> 17.607792 | AE9: =R9 -> 0.98287217 | AF9: =Q9*R9 -> 17.306208 | AG9: D
A10: 6 | B10: 9803 | C10: LC UWI MF-JPN | D10: LifeComm UWI | E10: contract management | F10: Core Insurance Systems Group 34956 | G10: Policy Admin Systems Team 34957 | H10: Core Business Application | I10: Y | J10: Yes | K10: Assembler, COBOL, MU(EASYPLUS), JCL | M10: N | N10: 8.8045833 | O10: 0.85 | P10: 0 | Q10: 9.6545833 | R10: 0.94821113 | S10: 4.8272917 | T10: 4.8272917 | U10: 1 | AA10: =N10 -> 8.8045833 | AB10: =O10 -> 0.85 | AC10: =P10 -> 0 | AD10: =Q10 -> 9.6545833 | AE10: =R10 -> 0.94821113 | AF10: =Q10*R10 -> 9.1545833 | AG10: D
A11: 7 | B11: 9804 | C11: LC AAPerf MF-JPN | D11: LifeComm AgentAgencyPerformance | E11: contract management | F11: Core Insurance Systems Group 34956 | G11: Policy Admin Systems Team 34957 | H11: Core Business Application | I11: Y | J11: Yes | K11: COBOL, Assembler, MU(EASYPLUS), JCL | M11: N | N11: 10.784167 | O11: 0.74583333 | P11: 0 | Q11: 11.53 | R11: 0.83304423 | S11: 5.765 | T11: 5.765 | U11: 1 | AA11: =N11 -> 10.784167 | AB11: =O11 -> 0.74583333 | AC11: =P11 -> 0 | AD11: =Q11 -> 11.53 | AE11: =R11 -> 0.83304423 | AF11: =Q11*R11 -> 9.605 | AG11: D
A12: 8 | B12: 9805 | C12: LC Payment MF-JPN | D12: LifeComm Payment | E12: contract management | F12: Core Insurance Systems Group 34956 | G12: Policy Admin Systems Team 34957 | H12: Core Business Application | I12: Y | J12: Yes | K12: COBOL, Assembler, MU(EASYPLUS), JCL | M12: N | N12: 2.8966667 | O12: 0.025 | P12: 0 | Q12: 2.9216667 | R12: 0.90587564 | S12: 1.4608333 | T12: 1.4608333 | U12: 1 | AA12: =N12 -> 2.8966667 | AB12: =O12 -> 0.025 | AC12: =P12 -> 0 | AD12: =Q12 -> 2.9216667 | AE12: =R12 -> 0.90587564 | AF12: =Q12*R12 -> 2.6466667 | AG12: D
A13: 9 | B13: 9806 | C13: LC GL/SC MF-JPN | D13: LifeComm GL/SC | E13: contract management | F13: Core Insurance Systems Group 34956 | G13: Policy Admin Systems Team 34957 | H13: Core Business Application | I13: Y | J13: Yes | K13: COBOL, Assembler, MU(EASYPLUS), JCL | M13: N | N13: 5.28875 | O13: 1.025 | P13: 0 | Q13: 6.31375 | R13: 0.83765591 | S13: 3.156875 | T13: 3.156875 | U13: 1 | AA13: =N13 -> 5.28875 | AB13: =O13 -> 1.025 | AC13: =P13 -> 0 | AD13: =Q13 -> 6.31375 | AE13: =R13 -> 0.83765591 | AF13: =Q13*R13 -> 5.28875 | AG13: D
A14: 10 | B14: 9807 | C14: LC Valuation MF-JPN | D14: LifeComm Valuation | E14: contract management | F14: Core Insurance Systems Group 34956 | G14: Policy Admin Systems Team 34957 | H14: Core Business Application | I14: N | J14: Yes | K14: COBOL, Assembler, MU(EASYPLUS), JCL | M14: N | N14: 9.76875 | O14: 1.4833333 | P14: 0 | Q14: 11.252083 | R14: 0.8563229 | S14: 5.6260417 | T14: 5.6260417 | U14: 1 | AA14: =N14 -> 9.76875 | AB14: =O14 -> 1.4833333 | AC14: =P14 -> 0 | AD14: =Q14 -> 11.252083 | AE14: =R14 -> 0.8563229 | AF14: =Q14*R14 -> 9.6354167 | AG14: D
A15: 11 | B15: 9808 | C15: LC AACOMP MF-JPN | D15: LifeComm AgentAgencyComp | E15: contract management | F15: Core Insurance Systems Group 34956 | G15: Policy Admin Systems Team 34957 | H15: Core Business Application | I15: Y | J15: Yes | K15: COBOL, Assembler, MU(EASYPLUS), JCL | M15: N | N15: 13.545708 | O15: 3.14375 | P15: 0 | Q15: 16.689458 | R15: 0.72662384 | S15: 8.3447292 | T15: 8.3447292 | U15: 1 | AA15: =N15 -> 13.545708 | AB15: =O15 -> 3.14375 | AC15: =P15 -> 0 | AD15: =Q15 -> 16.689458 | AE15: =R15 -> 0.72662384 | AF15: =Q15*R15 -> 12.126958 | AG15: D
A16: 12 | B16: 9810 | C16: Processor-I MF-JPN | D16: Claim payment (Processor-I) | E16: contract management | F16: Core Insurance Systems Group 34956 | G16: Policy Admin Systems Team 34957 | H16: Core Business Application | I16: Y | J16: Yes | K16: COBOL, MU(EASYPLUS), Assembler, JCL | M16: N | N16: 7.6683333 | O16: 1.1291667 | P16: 0 | Q16: 8.7975 | R16: 0.75561239 | S16: 4.39875 | T16: 4.39875 | U16: 1 | AA16: =N16 -> 7.6683333 | AB16: =O16 -> 1.1291667 | AC16: =P16 -> 0 | AD16: =Q16 -> 8.7975 | AE16: =R16 -> 0.75561239 | AF16: =Q16*R16 -> 6.6475 | AG16: D
A17: 13 | B17: 9811 | C17: LC Submit MF-JPN | D17: Submit Online | E17: contract management | F17: Core Insurance Systems Group 34956 | G17: Policy Admin Systems Team 34957 | H17: Core Business Application | I17: Y | J17: Yes | K17: COBOL, MU(EASYPLUS), Assembler, JCL | M17: N | N17: 1.9683333 | O17: 0.16458333 | P17: 0 | Q17: 2.1329167 | R17: 0.95311584 | S17: 1.0664583 | T17: 1.0664583 | U17: 1 | AA17: =N17 -> 1.9683333 | AB17: =O17 -> 0.16458333 | AC17: =P17 -> 0 | AD17: =Q17 -> 2.1329167 | AE17: =R17 -> 0.95311584 | AF17: =Q17*R17 -> 2.0329167 | AG17: D
A18: 14 | B18: 9813 | C18: LC Micro MF-JPN | D18: Micro-Index | E18: contract management | F18: Core Insurance Systems Group 34956 | G18: Policy Admin Systems Team 34957 | H18: Core Business Application | I18: Y | J18: Yes | K18: COBOL, MU(EASYPLUS), Assembler, JCL | M18: N | N18: 2.1175 | O18: 0 | P18: 0 | Q18: 2.1175 | R18: 0.64580874 | S18: 1.05875 | T18: 1.05875 | U18: 1 | AA18: =N18 -> 2.1175 | AB18: =O18 -> 0 | AC18: =P18 -> 0 | AD18: =Q18 -> 2.1175 | AE18: =R18 -> 0.64580874 | AF18: =Q18*R18 -> 1.3675 | AG18: D
A19: 15 | B19: 9814 | C19: Foreign MF-JPN | D19: Foreign | E19: contract management | F19: Core Insurance Systems Group 34956 | G19: Policy Admin Systems Team 34957 | H19: Core Business Application | I19: N | J19: Yes | K19: COBOL, MU(EASYPLUS), Assembler, JCL | M19: N | N19: 0 | O19: 0 | P19: 0 | Q19: 0 | R19: 0 | U19: 1 | AA19: =N19 -> 0 | AB19: =O19 -> 0 | AC19: =P19 -> 0 | AD19: =Q19 -> 0 | AE19: =R19 -> 0 | AF19: =Q19*R19 -> 0 | AG19: D
A20: 16 | B20: 9816 | C20: CT Salary MF-JPN | D20: CT Salary System | E20: contract management | F20: Core Insurance Systems Group 34956 | G20: Policy Admin Systems Team 34957 | H20: Core Business Application | I20: Y | J20: Yes | K20: COBOL, MU(EASYPLUS), Assembler, JCL | M20: N | N20: 0.2 | O20: 0 | P20: 0 | Q20: 0.2 | R20: 0 | S20: 0.1 | T20: 0.1 | U20: 1 | AA20: =N20 -> 0.2 | AB20: =O20 -> 0 | AC20: =P20 -> 0 | AD20: =Q20 -> 0.2 | AE20: =R20 -> 0 | AF20: =Q20*R20 -> 0 | AG20: D
A21: 17 | B21: 9817 | C21: TaxCertification MF-JPN | D21: TaxCertification | E21: contract management | F21: Core Insurance Systems Group 34956 | G21: Policy Admin Systems Team 34957 | H21: Core Business Application | I21: N | J21: Yes | K21: COBOL, MU(EASYPLUS), Assembler, JCL | M21: N | N21: 1.664875 | O21: 0 | P21: 0 | Q21: 1.664875 | R21: 0.40748805 | S21: 0.8324375 | T21: 0.8324375 | U21: 1 | AA21: =N21 -> 1.664875 | AB21: =O21 -> 0 | AC21: =P21 -> 0 | AD21: =Q21 -> 1.664875 | AE21: =R21 -> 0.40748805 | AF21: =Q21*R21 -> 0.67841667 | AG21: D
A22: 18 | B22: 9818 | C22: SWINGMANAGER MF-JPN | D22: SWING MANAGER | E22: contract management | F22: Core Insurance Systems Group 34956 | G22: Policy Admin Systems Team 34957 | H22: Core Business Application | I22: N | J22: Yes | K22: COBOL, MU(EASYPLUS), Assembler, JCL | M22: N | N22: 0 | O22: 0 | P22: 0 | Q22: 0 | R22: 0 | U22: 1 | AA22: =N22 -> 0 | AB22: =O22 -> 0 | AC22: =P22 -> 0 | AD22: =Q22 -> 0 | AE22: =R22 -> 0 | AF22: =Q22*R22 -> 0 | AG22: D
A23: 19 | B23: 9819 | C23: PremCollectDBMF-JPN | D23: Premium Collection History DB | E23: contract management | F23: Core Insurance Systems Group 34956 | G23: Policy Admin Systems Team 34957 | H23: Core Business Application | I23: N | J23: Yes | K23: COBOL, MU(EASYPLUS), Assembler, JCL | M23: N | N23: 0 | O23: 0 | P23: 0 | Q23: 0 | R23: 0 | U23: 1 | AA23: =N23 -> 0 | AB23: =O23 -> 0 | AC23: =P23 -> 0 | AD23: =Q23 -> 0 | AE23: =R23 -> 0 | AF23: =Q23*R23 -> 0 | AG23: D
A24: 20 | B24: 9820 | C24: MCFA CP DB MF-JPN | D24: MCFA Coupon DB | E24: contract management | F24: Core Insurance Systems Group 34956 | G24: Policy Admin Systems Team 34957 | H24: Core Business Application | I24: Y | J24: Yes | K24: COBOL, MU(EASYPLUS), Assembler, JCL | M24: N | N24: 0 | O24: 0 | P24: 0 | Q24: 0 | R24: 0 | U24: 1 | AA24: =N24 -> 0 | AB24: =O24 -> 0 | AC24: =P24 -> 0 | AD24: =Q24 -> 0 | AE24: =R24 -> 0 | AF24: =Q24*R24 -> 0 | AG24: D
A25: 21 | B25: 9821 | C25: Maturity MF-JPN | D25: Payment maturity existing benefit etc | E25: contract management | F25: Core Insurance Systems Group 34956 | G25: Policy Admin Systems Team 34957 | H25: Core Business Application | I25: Y | J25: Yes | K25: COBOL, MU(EASYPLUS), Assembler, JCL | M25: N | N25: 4.3783333 | O25: 0.97083333 | P25: 0 | Q25: 5.3491667 | R25: 0.62610999 | S25: 2.6745833 | T25: 2.6745833 | U25: 1 | AA25: =N25 -> 4.3783333 | AB25: =O25 -> 0.97083333 | AC25: =P25 -> 0 | AD25: =Q25 -> 5.3491667 | AE25: =R25 -> 0.62610999 | AF25: =Q25*R25 -> 3.3491667 | AG25: D
A26: 22 | B26: 9822 | C26: LC Reins MF-JPN | D26: Reinsurance | E26: contract management | F26: Core Insurance Systems Group 34956 | G26: Policy Admin Systems Team 34957 | H26: Core Business Application | I26: N | J26: Yes | K26: COBOL, MU(EASYPLUS), Assembler, JCL | M26: N | N26: 6.0129167 | O26: 0.25416667 | P26: 0 | Q26: 6.2670833 | R26: 0.78990759 | S26: 3.1335417 | T26: 3.1335417 | U26: 1 | AA26: =N26 -> 6.0129167 | AB26: =O26 -> 0.25416667 | AC26: =P26 -> 0 | AD26: =Q26 -> 6.2670833 | AE26: =R26 -> 0.78990759 | AF26: =Q26*R26 -> 4.9504167 | AG26: D
A27: 23 | B27: 9823 | C27: ASP Bridge(H) MF-JPN | D27: ASP Bridge (HOST) | E27: contract management | F27: Core Insurance Systems Group 34956 | G27: Policy Admin Systems Team 34957 | H27: Common Service Business Application | I27: Y | J27: Yes | K27: COBOL, MU(EASYPLUS), Assembler, JCL | M27: N | N27: 6.7267083 | O27: 1.4625 | P27: 0 | Q27: 8.1892083 | R27: 0.72808727 | S27: 4.0946042 | T27: 4.0946042 | U27: 1 | AA27: =N27 -> 6.7267083 | AB27: =O27 -> 1.4625 | AC27: =P27 -> 0 | AD27: =Q27 -> 8.1892083 | AE27: =R27 -> 0.72808727 | AF27: =Q27*R27 -> 5.9624583 | AG27: D
A28: 24 | B28: 9824 | C28: CCA MF-JPN | D28: Client Contract Administration | E28: contract management | F28: Core Insurance Systems Group 34956 | G28: Policy Admin Systems Team 34957 | H28: Core Business Application | I28: Y | J28: Yes | K28: COBOL, MU(EASYPLUS), Assembler, JCL | M28: N | N28: 1.6308333 | O28: 0 | P28: 0 | Q28: 1.6308333 | R28: 0.38681656 | S28: 0.81541667 | T28: 0.81541667 | U28: 1 | AA28: =N28 -> 1.6308333 | AB28: =O28 -> 0 | AC28: =P28 -> 0 | AD28: =Q28 -> 1.6308333 | AE28: =R28 -> 0.38681656 | AF28: =Q28*R28 -> 0.63083333 | AG28: D
A29: 25 | B29: 9833 | C29: C04NWC-JPN | D29: CenterServer | E29: New Contract Related | F29: Customer Service and Operations Systems Group 34965 | G29: New Business Team 34966 | H29: Core Business Application | I29: N | J29: Yes | K29: C/C++ | M29: N | N29: 8.7316667 | O29: 0.11041667 | P29: 0 | Q29: 8.8420833 | R29: 0.91687479 | S29: 4.4210417 | T29: 4.4210417 | U29: 1 | AA29: =N29 -> 8.7316667 | AB29: =O29 -> 0.11041667 | AC29: =P29 -> 0 | AD29: =Q29 -> 8.8420833 | AE29: =R29 -> 0.91687479 | AF29: =Q29*R29 -> 8.1070833 | AG29: B
A30: 26 | B30: 9834 | C30: C03WRE-JPN | D30: POS Workflow Payment Workflow (Restoring cancelled | E30: Storage and Preservation Related | F30: Customer Service and Operations Systems Group 34965 | G30: Policy Servicing Team 34967 | H30: Core Business Application | I30: Y | J30: Yes | K30: VB.NET | M30: N | N30: 0.2 | O30: 0.2 | P30: 0 | Q30: 0.37083333 | R30: 0.3258427 | S30: 0.18541667 | T30: 0.18541667 | U30: 1 | AA30: =N30 -> 0.2 | AB30: =O30 -> 0.2 | AC30: =P30 -> 0 | AD30: =Q30 -> 0.37083333 | AE30: =R30 -> 0.3258427 | AF30: =Q30*R30 -> 0.12083333 | AG30: B
A31: 27 | B31: 9835 | C31: C12WNC-JPN | D31: POS Workflow Payment Workflow (Claim Transaction A | E31: Insurance Claims and Benefits Payment Related | F31: Customer Service and Operations Systems Group 34965 | G31: Claims Team 34968 | H31: Core Business Application | I31: Y | J31: Yes | K31: VB.NET; C/C++; JAVA | M31: N | N31: 29.379875 | O31: 5.6166667 | P31: 0 | Q31: 34.996542 | R31: 0.90522873 | S31: 17.498271 | T31: 17.498271 | U31: 1 | AA31: =N31 -> 29.379875 | AB31: =O31 -> 5.6166667 | AC31: =P31 -> 0 | AD31: =Q31 -> 34.996542 | AE31: =R31 -> 0.90522873 | AF31: =Q31*R31 -> 31.679875 | AG31: B
A32: 28 | B32: 9836 | C32: C03WRD-JPN | D32: POS Workflow Payment Workflow (Reduction of paymen | E32: Storage and Preservation Related | F32: Customer Service and Operations Systems Group 34965 | G32: Policy Servicing Team 34967 | H32: Core Business Application | I32: Y | J32: Yes | K32: VB.NET | M32: N | N32: 0.3 | O32: 0.3 | P32: 0 | Q32: 2.5258333 | R32: 0.90102276 | S32: 1.2629167 | T32: 1.2629167 | U32: 1 | AA32: =N32 -> 0.3 | AB32: =O32 -> 0.3 | AC32: =P32 -> 0 | AD32: =Q32 -> 2.5258333 | AE32: =R32 -> 0.90102276 | AF32: =Q32*R32 -> 2.2758333 | AG32: B
A33: 29 | B33: 9842 | C33: C03PCA-JPN | D33: Add Coverage | E33: Storage and Preservation Related | F33: Customer Service and Operations Systems Group 34965 | G33: Policy Servicing Team 34967 | H33: Core Business Application | I33: N | J33: Yes | K33: VB | M33: N | N33: 0.3 | O33: 0.3 | P33: 0 | Q33: 2.88625 | R33: 0.90298831 | S33: 1.443125 | T33: 1.443125 | U33: 1 | AA33: =N33 -> 0.3 | AB33: =O33 -> 0.3 | AC33: =P33 -> 0 | AD33: =Q33 -> 2.88625 | AE33: =R33 -> 0.90298831 | AF33: =Q33*R33 -> 2.60625 | AG33: B
A34: 30 | B34: 9843 | C34: C10CSS-JPN | D34: FSC Call Support | E34: Customer Care / Call Center Related | F34: Customer Service and Operations Systems Group 34965 | G34: Customer Care Team 34969 | H34: Core Business Application | I34: N | J34: Yes | K34: VB.NET | M34: N | N34: 1.2120833 | O34: 0.20833333 | P34: 0 | Q34: 1.4204167 | R34: 0.63596363 | S34: 0.71020833 | T34: 0.71020833 | U34: 1 | AA34: =N34 -> 1.2120833 | AB34: =O34 -> 0.20833333 | AC34: =P34 -> 0 | AD34: =Q34 -> 1.4204167 | AE34: =R34 -> 0.63596363 | AF34: =Q34*R34 -> 0.90333333 | AG34: B
A35: 31 | B35: 9844 | C35: C04VAS-JPN | D35: Voucher Approval System for AS400 | E35: Corporate Related | F35: Core Insurance Systems Group 34956 | G35: Corporate Systems Team 34959 | H35: Core Business Application | I35: Y | J35: Yes | K35: VB.NET | M35: N | N35: 0.67083333 | O35: 0.68333333 | P35: 0 | Q35: 1.3541667 | R35: 0.36923077 | S35: 0.67708333 | T35: 0.67708333 | U35: 1 | AA35: =N35 -> 0.67083333 | AB35: =O35 -> 0.68333333 | AC35: =P35 -> 0 | AD35: =Q35 -> 1.3541667 | AE35: =R35 -> 0.36923077 | AF35: =Q35*R35 -> 0.5 | AG35: B
A36: 32 | B36: 9845 | C36: C04SYM-JPN | D36: Renewal symap Business Work Flow | E36: New Contract Related | F36: Customer Service and Operations Systems Group 34965 | G36: New Business Team 34966 | H36: Core Business Application | I36: N | J36: Yes | K36: VB.NET | M36: N | N36: 3.4049167 | O36: 0 | P36: 0 | Q36: 3.4049167 | R36: 0.84091632 | S36: 1.7024583 | T36: 1.7024583 | U36: 1 | AA36: =N36 -> 3.4049167 | AB36: =O36 -> 0 | AC36: =P36 -> 0 | AD36: =Q36 -> 3.4049167 | AE36: =R36 -> 0.84091632 | AF36: =Q36*R36 -> 2.86325 | AG36: B
... A40: 36 | B40: 9849 | C40: C04OSI-JPN | D40: S Sum Total System(Open) | E40: New Contract Related | F40: Customer Service and Operations Systems Group 34965 | G40: New Business Team 34966 | H40: Common Service Business Application | I40: N | J40: Yes | K40: JAVA | M40: N | N40: 5.18625 | O40: 0.38333333 | P40: 0 | Q40: 5.5695833 | R40: 0.8315254 | S40: 2.7847917 | T40: 2.7847917 | U40: 1 | AA40: =N40 -> 5.18625 | AB40: =O40 -> 0.38333333 | AC40: =P40 -> 0 | AD40: =Q40 -> 5.5695833 | AE40: =R40 -> 0.8315254 | AF40: =Q40*R40 -> 4.63125 | AG40: B
A41: 37 | B41: 9851 | C41: W03FIC-JPN | D41: Guidance Refusal Information Administration System | E41: Corporate Related | F41: Core Insurance Systems Group 34956 | G41: Corporate Systems Team 34959 | H41: Core Business Application | I41: N | J41: Yes | K41: JAVA | L41: Platform as a Service (PaaS) | M41: N | N41: 0.29166667 | O41: 0.11666667 | P41: 0 | Q41: 0.40833333 | R41: 0.82653061 | S41: 0.20416667 | T41: 0.20416667 | U41: 1 | AA41: =N41 -> 0.29166667 | AB41: =O41 -> 0.11666667 | AC41: =P41 -> 0 | AD41: =Q41 -> 0.40833333 | AE41: =R41 -> 0.82653061 | AF41: =Q41*R41 -> 0.3375 | AG41: B
A42: 38 | B42: 9852 | C42: C03APO-JPN | D42: Apollocs | E42: Corporate Related | F42: Core Insurance Systems Group 34956 | G42: Corporate Systems Team 34959 | H42: Core Business Application | I42: N | J42: Yes | K42: Other#APOLLOCS | M42: N | N42: 0.50833333 | O42: 0 | P42: 0 | Q42: 0.50833333 | R42: 0.36885246 | S42: 0.25416667 | T42: 0.25416667 | U42: 1 | AA42: =N42 -> 0.50833333 | AB42: =O42 -> 0 | AC42: =P42 -> 0 | AD42: =Q42 -> 0.50833333 | AE42: =R42 -> 0.36885246 | AF42: =Q42*R42 -> 0.1875 | AG42: B
A43: 39 | B43: 9854 | C43: Z04IMA-JPN | D43: Image Search | E43: New Contract Related | F43: Customer Service and Operations Systems Group 34965 | G43: New Business Team 34966 | H43: Core Business Application | I43: N | J43: Yes | K43: CSS; JAVA;HTML; VB.NET | M43: N | N43: 1.4004167 | O43: 0 | P43: 0 | Q43: 1.4004167 | R43: 0.92859268 | S43: 0.70020833 | T43: 0.70020833 | U43: 1 | AA43: =N43 -> 1.4004167 | AB43: =O43 -> 0 | AC43: =P43 -> 0 | AD43: =Q43 -> 1.4004167 | AE43: =R43 -> 0.92859268 | AF43: =Q43*R43 -> 1.3004167 | AG43: B
A44: 40 | B44: 9857 | C44: W05AMS-JPN | D44: Annuity Information Management System(AIMS) | E44: Insurance Claims and Benefits Payment Related | F44: Customer Service and Operations Systems Group 34965 | G44: Claims Team 34968 | H44: Core Business Application | I44: Y | J44: Yes | K44: JAVA | M44: N | N44: 20.211667 | O44: 1.8166667 | P44: 0 | Q44: 22.028333 | R44: 0.92547477 | S44: 11.014167 | T44: 11.014167 | U44: 1 | AA44: =N44 -> 20.211667 | AB44: =O44 -> 1.8166667 | AC44: =P44 -> 0 | AD44: =Q44 -> 22.028333 | AE44: =R44 -> 0.92547477 | AF44: =Q44*R44 -> 20.386667 | AG44: B
A45: 41 | B45: 9858 | C45: W02OPS-JPN | D45: Insurance Planning for Operator | E45: Marketing/Direct Business Related | F45: Customer and Channel Engineering 34961 | H45: Core Business Application | I45: N | J45: Yes | K45: JAVA | M45: N | N45: 4.8333333 | O45: 1 | P45: 1.0833333 | Q45: 6.9166667 | R45: 0.71084337 | S45: 3.4583333 | T45: 3.4583333 | U45: 1 | AA45: =N45 -> 4.8333333 | AB45: =O45 -> 1 | AC45: =P45 -> 1.0833333 | AD45: =Q45 -> 6.9166667 | AE45: =R45 -> 0.71084337 | AF45: =Q45*R45 -> 4.9166667 | AG45: B
A46: 42 | B46: 9861 | C46: W04RRE-JPN | D46: Rule Engine | E46: New Contract Related | F46: Customer Service and Operations Systems Group 34965 | G46: New Business Team 34966 | H46: Core Business Application | I46: Y | J46: Yes | K46: JAVA | M46: N | N46: 6.3152917 | O46: 0 | P46: 0 | Q46: 6.3152917 | R46: 0.87325737 | S46: 3.1576458 | T46: 3.1576458 | U46: 1 | AA46: =N46 -> 6.3152917 | AB46: =O46 -> 0 | AC46: =P46 -> 0 | AD46: =Q46 -> 6.3152917 | AE46: =R46 -> 0.87325737 | AF46: =Q46*R46 -> 5.514875 | AG46: B
A47: 43 | B47: 9879 | C47: W03PIU-JPN | D47: IS universal life insurance simulation | E47: Storage and Preservation Related | F47: Customer Service and Operations Systems Group 34965 | G47: Policy Servicing Team 34967 | H47: Core Business Application | I47: N | J47: Yes | K47: JAVA | M47: N | N47: 0.2 | O47: 0.1 | P47: 0 | Q47: 0.30833333 | R47: 0.67567568 | S47: 0.15416667 | T47: 0.15416667 | U47: 1 | AA47: =N47 -> 0.2 | AB47: =O47 -> 0.1 | AC47: =P47 -> 0 | AD47: =Q47 -> 0.30833333 | AE47: =R47 -> 0.67567568 | AF47: =Q47*R47 -> 0.20833333 | AG47: B
A48: 44 | B48: 9890 | C48: W08HTN-JPN | D48: conservation contact personnel entry system | E48: Corporate Related | F48: Core Insurance Systems Group 34956 | G48: Corporate Systems Team 34959 | H48: Core Business Application | I48: N | J48: Yes | K48: JAVA | M48: N | N48: 1.5054583 | O48: 0.045833333 | P48: 0 | Q48: 1.5512917 | R48: 0.072009884 | S48: 0.77564583 | T48: 0.77564583 | U48: 1 | AA48: =N48 -> 1.5054583 | AB48: =O48 -> 0.045833333 | AC48: =P48 -> 0 | AD48: =Q48 -> 1.5512917 | AE48: =R48 -> 0.072009884 | AF48: =Q48*R48 -> 0.11170833 | AG48: B
A49: 45 | B49: 9894 | C49: W08NAV-JPN | D49: Branch Marketing Information System | E49: Sales / Insurance Recruitment | F49: Customer and Channel Engineering 34961 | G49: Distribution F2F Team 34962 | H49: Core Business Application | I49: N | J49: Yes | K49: VB | M49: N | N49: 2.841875 | O49: 0.35208333 | P49: 0 | Q49: 3.1939583 | R49: 0.79192486 | S49: 1.5969792 | T49: 1.5969792 | U49: 1 | AA49: =N49 -> 2.841875 | AB49: =O49 -> 0.35208333 | AC49: =P49 -> 0 | AD49: =Q49 -> 3.1939583 | AE49: =R49 -> 0.79192486 | AF49: =Q49*R49 -> 2.529375 | AG49: B
A50: 46 | B50: 9896 | C50: W08SFE-JPN | D50: commission Inquiry | E50: Corporate Related | F50: Core Insurance Systems Group 34956 | G50: Corporate Systems Team 34959 | H50: Core Business Application | I50: N | J50: Yes | K50: JAVA | M50: N | N50: 1.091375 | O50: 0.105 | P50: 0 | Q50: 1.196375 | R50: 0.98955177 | S50: 0.5981875 | T50: 0.5981875 | U50: 1 | AA50: =N50 -> 1.091375 | AB50: =O50 -> 0.105 | AC50: =P50 -> 0 | AD50: =Q50 -> 1.196375 | AE50: =R50 -> 0.98955177 | AF50: =Q50*R50 -> 1.183875 | AG50: B
A51: 47 | B51: 9899 | C51: W08CIS-JPN | D51: Career Information System | E51: Corporate Related | F51: Core Insurance Systems Group 34956 | G51: Corporate Systems Team 34959 | H51: Core Business Application | I51: N | J51: Yes | K51: JAVA | M51: N | N51: 1.204125 | O51: 0.52916667 | P51: 0 | Q51: 1.7332917 | R51: 0.82691892 | S51: 0.86664583 | T51: 0.86664583 | U51: 1 | AA51: =N51 -> 1.204125 | AB51: =O51 -> 0.52916667 | AC51: =P51 -> 0 | AD51: =Q51 -> 1.7332917 | AE51: =R51 -> 0.82691892 | AF51: =Q51*R51 -> 1.4332917 | AG51: B
A52: 48 | B52: 9906 | C52: W08NAR-JPN | D52: producers information entry system | E52: Corporate Related | F52: Core Insurance Systems Group 34956 | G52: Corporate Systems Team 34959 | H52: Core Business Application | I52: N | J52: Yes | K52: JAVA | M52: N | N52: 1.2860417 | O52: 0.14541667 | P52: 0 | Q52: 1.4314583 | R52: 0.95051666 | S52: 0.71572917 | T52: 0.71572917 | U52: 1 | AA52: =N52 -> 1.2860417 | AB52: =O52 -> 0.14541667 | AC52: =P52 -> 0 | AD52: =Q52 -> 1.4314583 | AE52: =R52 -> 0.95051666 | AF52: =Q52*R52 -> 1.360625 | AG52: B
A53: 49 | B53: 9907 | C53: W13WWF-JPN | D53: Web work flow | E53: Corporate Related | F53: Core Insurance Systems Group 34956 | G53: Corporate Systems Team 34959 | H53: Core Business Application | I53: N | J53: Yes | K53: JAVA | M53: N | N53: 0.38583333 | O53: 0 | P53: 0 | Q53: 0.38583333 | R53: 0.35205184 | S53: 0.19291667 | T53: 0.19291667 | U53: 1 | AA53: =N53 -> 0.38583333 | AB53: =O53 -> 0 | AC53: =P53 -> 0 | AD53: =Q53 -> 0.38583333 | AE53: =R53 -> 0.35205184 | AF53: =Q53*R53 -> 0.13583333 | AG53: B
A54: 50 | B54: 9910 | C54: P08MMS-JPN | D54: Medical Management System | E54: New Contract Related | F54: Customer Service and Operations Systems Group 34965 | G54: New Business Team 34966 | H54: Core Business Application | I54: N | J54: Yes | K54: VB.NET | M54: N | N54: 0.0625 | O54: 0 | P54: 0 | Q54: 0.0625 | R54: 1 | S54: 0.03125 | T54: 0.03125 | U54: 1 | AA54: =N54 -> 0.0625 | AB54: =O54 -> 0 | AC54: =P54 -> 0 | AD54: =Q54 -> 0.0625 | AE54: =R54 -> 1 | AF54: =Q54*R54 -> 0.0625 | AG54: B
A55: 51 | B55: 9920 | C55: WPSYEC-JPN | D55: Direct Marketing Site | E55: Marketing/Direct Business Related | F55: Customer and Channel Engineering 34961 | G55: Marketing and Leads Team 34964 | H55: Core Business Application | I55: N | J55: Yes | K55: JAVA | M55: N | N55: 10.3375 | O55: 3.5583333 | P55: 5.1816667 | Q55: 19.0775 | R55: 0.93360416 | S55: 9.53875 | T55: 9.53875 | U55: 1 | AA55: =N55 -> 10.3375 | AB55: =O55 -> 3.5583333 | AC55: =P55 -> 5.1816667 | AD55: =Q55 -> 19.0775 | AE55: =R55 -> 0.93360416 | AF55: =Q55*R55 -> 17.810833 | AG55: B
A56: 52 | B56: 9921 | C56: W07IPC-JPN | D56: Internet Prospective Information | E56: Marketing/Direct Business Related | F56: Customer and Channel Engineering 34961 | G56: Marketing and Leads Team 34964 | H56: Core Business Application | I56: N | J56: Yes | K56: JAVA | L56: Platform as a Service (PaaS) | M56: N | N56: 0.30416667 | O56: 0.041666667 | P56: 0 | Q56: 0.34583333 | R56: 1 | S56: 0.17291667 | T56: 0.17291667 | U56: 1 | AA56: =N56 -> 0.30416667 | AB56: =O56 -> 0.041666667 | AC56: =P56 -> 0 | AD56: =Q56 -> 0.34583333 | AE56: =R56 -> 1 | AF56: =Q56*R56 -> 0.34583333 | AG56: B
A57: 53 | B57: 9926 | C57: W01LOI-JPN | D57: Japan Authorization / login | E57: Common Service Platform | F57: Japan Platform Team 35775 | G57: Japan Platform Team 35775 | H57: Common Service Business Application | I57: N | J57: Yes | K57: JAVA | M57: N | N57: 0.075 | O57: 0 | P57: 0 | Q57: 0.075 | R57: 0 | S57: 0.0375 | T57: 0.0375 | U57: 1 | AA57: =N57 -> 0.075 | AB57: =O57 -> 0 | AC57: =P57 -> 0 | AD57: =Q57 -> 0.075 | AE57: =R57 -> 0 | AF57: =Q57*R57 -> 0 | AG57: B
A58: 54 | B58: 9928 | C58: W01MAS-JPN | D58: Common Framework(Master4) | E58: Common Service Platform | F58: Japan Platform Team 35775 | G58: Japan Platform Team 35775 | H58: Common Service Business Application | I58: N | J58: Yes | K58: JAVA | L58: Platform as a Service (PaaS) | M58: N | N58: 1.3970833 | O58: 1 | P58: 0 | Q58: 2.3970833 | R58: 0.86441856 | S58: 1.1985417 | T58: 1.1985417 | U58: 1 | AA58: =N58 -> 1.3970833 | AB58: =O58 -> 1 | AC58: =P58 -> 0 | AD58: =Q58 -> 2.3970833 | AE58: =R58 -> 0.86441856 | AF58: =Q58*R58 -> 2.0720833 | AG58: B
A59: 55 | B59: 9930 | C59: A04MMP-JPN | D59: AS400 Mass Marketing System | E59: Corporate Related | F59: Core Insurance Systems Group 34956 | G59: Corporate Systems Team 34959 | H59: Core Business Application | I59: Y | J59: Yes | K59: Other#RPG | M59: N | N59: 2.4083333 | O59: 0.075 | P59: 0 | Q59: 2.4833333 | R59: 0.89932886 | S59: 1.2416667 | T59: 1.2416667 | U59: 1 | AA59: =N59 -> 2.4083333 | AB59: =O59 -> 0.075 | AC59: =P59 -> 0 | AD59: =Q59 -> 2.4833333 | AE59: =R59 -> 0.89932886 | AF59: =Q59*R59 -> 2.2333333 | AG59: D
A60: 56 | B60: 9931 | C60: P02BKE-JPN | D60: Sales illustration system (based on EXCEL) for BAN | E60: Sales / Insurance Recruitment | F60: Customer and Channel Engineering 34961 | G60: Distribution Banca Team 34963 | H60: Core Business Application | I60: N | J60: Yes | K60: Other#VBA | M60: N | N60: 13 | O60: 2.275 | P60: 0 | Q60: 15.275 | R60: 0.91728849 | S60: 7.6375 | T60: 7.6375 | U60: 1 | AA60: =N60 -> 13 | AB60: =O60 -> 2.275 | AC60: =P60 -> 0 | AD60: =Q60 -> 15.275 | AE60: =R60 -> 0.91728849 | AF60: =Q60*R60 -> 14.011582 | AG60: B
A61: 57 | B61: 9940 | C61: WPSC2S-JPN | D61: Call Control System | E61: Corporate Related | F61: Core Insurance Systems Group 34956 | G61: Corporate Systems Team 34959 | H61: Core Business Application | I61: N | J61: Yes | K61: JAVA | M61: N | N61: 0.3875 | O61: 0.025 | P61: 0 | Q61: 0.4125 | R61: 0.81818182 | S61: 0.20625 | T61: 0.20625 | U61: 1 | AA61: =N61 -> 0.3875 | AB61: =O61 -> 0.025 | AC61: =P61 -> 0 | AD61: =Q61 -> 0.4125 | AE61: =R61 -> 0.81818182 | AF61: =Q61*R61 -> 0.3375 | AG61: B
A62: 58 | B62: 9941 | C62: B13ITS-JPN | D62: ITS-PCIS(Mutual Fund System(Including Bestway) | E62: Corporate Related | F62: Core Insurance Systems Group 34956 | G62: Corporate Systems Team 34959 | H62: Core Business Application | I62: N | J62: Yes | K62: JAVA | L62: Software as a Service (SaaS) | M62: N | N62: 0.92916458 | O62: 0.0875 | P62: 0 | Q62: 1.0166646 | R62: 0.41311355 | S62: 0.50833229 | T62: 0.50833229 | U62: 1 | AA62: =N62 -> 0.92916458 | AB62: =O62 -> 0.0875 | AC62: =P62 -> 0 | AD62: =Q62 -> 1.0166646 | AE62: =R62 -> 0.41311355 | AF62: =Q62*R62 -> 0.41999792 | AG62: A
A63: 59 | B63: 9947 | C63: W13WEP-JPN | D63: Web Payment | E63: Storage and Preservation Related | F63: Customer Service and Operations Systems Group 34965 | G63: Policy Servicing Team 34967 | H63: Core Business Application | I63: Y | J63: Yes | K63: JAVA | M63: N | N63: 9 | O63: 1.1541667 | P63: 0 | Q63: 10 | R63: 0.75904635 | S63: 5 | T63: 5 | U63: 1 | AA63: =N63 -> 9 | AB63: =O63 -> 1.1541667 | AC63: =P63 -> 0 | AD63: =Q63 -> 10 | AE63: =R63 -> 0.75904635 | AF63: =Q63*R63 -> 7.5904635 | AG63: B
A64: 60 | B64: 9948 | C64: Data Send System for BANC MF-JP | D64: Data Send System for BANC | E64: contract management | F64: Core Insurance Systems Group 34956 | G64: Policy Admin Systems Team 34957 | H64: Core Business Application | I64: Y | J64: Yes | K64: COBOL, MU(EASYPLUS), Assembler, JCL | M64: N | N64: 9.2697083 | O64: 2.8458333 | P64: 0 | Q64: 12.115542 | R64: 0.77129926 | S64: 6.0577708 | T64: 6.0577708 | U64: 1 | AA64: =N64 -> 9.2697083 | AB64: =O64 -> 2.8458333 | AC64: =P64 -> 0 | AD64: =Q64 -> 12.115542 | AE64: =R64 -> 0.77129926 | AF64: =Q64*R64 -> 9.3447083 | AG64: D
A65: 61 | B65: 9949 | C65: CCMDNT-JPN | D65: .NET Common Infrastructure | E65: Corporate Related | F65: Core Insurance Systems Group 34956 | G65: Corporate Systems Team 34959 | H65: Common Service Business Application | I65: N | J65: Yes | K65: VB.NET; C # | M65: N | N65: 0.066666667 | O65: 0 | P65: 0 | Q65: 0.066666667 | R65: 0 | S65: 0.033333333 | T65: 0.033333333 | U65: 1 | AA65: =N65 -> 0.066666667 | AB65: =O65 -> 0 | AC65: =P65 -> 0 | AD65: =Q65 -> 0.066666667 | AE65: =R65 -> 0 | AF65: =Q65*R65 -> 0 | AG65: B
A66: 62 | B66: 9951 | C66: BCMHRP-JPN | D66: Data cooperation | E66: Data Infrastructure | F66: Data Platforms Team 34980 | G66: Data Platforms Team 34980 | H66: Common Service Business Application | I66: N | J66: Yes | K66: Other#MS-DOS ,AWK,VBScript,JAVA | L66: Running on both on-premises and Azure. The on-premises version will be decommissioned by the end of 2027. | M66: Y | N66: 7 | O66: 1 | P66: 0 | Q66: 7.9270417 | R66: 0.77923668 | S66: 3.9635208 | T66: 3.9635208 | U66: 1 | AA66: =N66 -> 7 | AB66: =O66 -> 1 | AC66: =P66 -> 0 | AD66: =Q66 -> 7.9270417 | AE66: =R66 -> 0.77923668 | AF66: =Q66*R66 -> 6.1770417 | AG66: C | AH66: VS1
A67: 63 | B67: 9962 | C67: WPSCUS-JPN | D67: Customer Support System | E67: Marketing/Direct Business Related | F67: Customer and Channel Engineering 34961 | G67: Marketing and Leads Team 34964 | H67: Core Business Application | I67: N | J67: Yes | K67: JavaScript; Other#APEX | L67: Platform as a Service (PaaS) | M67: N | N67: 8.9216667 | O67: 2.4104167 | P67: 1.52 | Q67: 12.852083 | R67: 0.82739504 | S67: 6.4260417 | T67: 6.4260417 | U67: 1 | AA67: =N67 -> 8.9216667 | AB67: =O67 -> 2.4104167 | AC67: =P67 -> 1.52 | AD67: =Q67 -> 12.852083 | AE67: =R67 -> 0.82739504 | AF67: =Q67*R67 -> 10.63375 | AG67: B
A68: 64 | B68: 9964 | C68: WAANSO-JPN | D68: New Submit Online System | E68: Corporate Related | F68: Core Insurance Systems Group 34956 | G68: Corporate Systems Team 34959 | H68: Core Business Application | I68: N | J68: Yes | K68: JAVA | M68: N | N68: 1.9533333 | O68: 0.3625 | P68: 0 | Q68: 2.3158333 | R68: 0.90824037 | S68: 1.1579167 | T68: 1.1579167 | U68: 1 | AA68: =N68 -> 1.9533333 | AB68: =O68 -> 0.3625 | AC68: =P68 -> 0 | AD68: =Q68 -> 2.3158333 | AE68: =R68 -> 0.90824037 | AF68: =Q68*R68 -> 2.1033333 | AG68: B
A69: 65 | B69: 9965 | C69: WZZHYO-JPN | D69: Report Template Management System | E69: Corporate Related | F69: Core Insurance Systems Group 34956 | G69: Corporate Systems Team 34959 | H69: Core Business Application | I69: N | J69: Yes | K69: JAVA | M69: N | N69: 0.025 | O69: 0.0375 | P69: 0 | Q69: 0.0625 | R69: 0.2 | S69: 0.03125 | T69: 0.03125 | U69: 1 | AA69: =N69 -> 0.025 | AB69: =O69 -> 0.0375 | AC69: =P69 -> 0 | AD69: =Q69 -> 0.0625 | AE69: =R69 -> 0.2 | AF69: =Q69*R69 -> 0.0125 | AG69: B
A70: 66 | B70: 9969 | C70: EAADRS-JPN | D70: Dr.SUM | E70: Corporate Related | F70: Core Insurance Systems Group 34956 | G70: Corporate Systems Team 34959 | H70: Core Business Application | I70: N | J70: Yes | K70: JAVA | M70: N | N70: 0.312375 | O70: 0.025 | P70: 0 | Q70: 0.337375 | R70: 0.67580585 | S70: 0.1686875 | T70: 0.1686875 | U70: 1 | AA70: =N70 -> 0.312375 | AB70: =O70 -> 0.025 | AC70: =P70 -> 0 | AD70: =Q70 -> 0.337375 | AE70: =R70 -> 0.67580585 | AF70: =Q70*R70 -> 0.228 | AG70: B
A71: 67 | B71: 9975 | C71: WPMWCC-JPN | D71: Web Contact Center | E71: Customer Care / Call Center Related | F71: Customer Service and Operations Systems Group 34965 | G71: Customer Care Team 34969 | H71: Core Business Application | I71: N | J71: Yes | K71: JAVA | M71: N | N71: 1.1116667 | O71: 0 | P71: 0 | Q71: 1.1116667 | R71: 0.58508246 | S71: 0.55583333 | T71: 0.55583333 | U71: 1 | AA71: =N71 -> 1.1116667 | AB71: =O71 -> 0 | AC71: =P71 -> 0 | AD71: =Q71 -> 1.1116667 | AE71: =R71 -> 0.58508246 | AF71: =Q71*R71 -> 0.65041667 | AG71: B
A72: 68 | B72: 9977 | C72: WGLRPC-JPN | D72: ReportConnection | E72: Sales / Insurance Recruitment | F72: Customer and Channel Engineering 34961 | G72: Distribution F2F Team 34962 | H72: Core Business Application | I72: N | J72: Yes | K72: JAVA | M72: N | N72: 1 | O72: 1 | P72: 0 | Q72: 0.45791667 | R72: 0 | S72: 0.22895833 | T72: 0.22895833 | U72: 1 | AA72: =N72 -> 1 | AB72: =O72 -> 1 | AC72: =P72 -> 0 | AD72: =Q72 -> 0.45791667 | AE72: =R72 -> 0 | AF72: =Q72*R72 -> 0 | AG72: B
A73: 69 | B73: 9980 | C73: Policy UWIBATCH MF-JPN | D73: Policy Underwriting and Issue Batch | E73: contract management | F73: Core Insurance Systems Group 34956 | G73: Policy Admin Systems Team 34957 | H73: Core Business Application | I73: Y | J73: Yes | K73: Other#ASM; Cobol | M73: N | N73: 12.606875 | O73: 1.1416667 | P73: 0 | Q73: 13.748542 | R73: 0.81496522 | S73: 6.8742708 | T73: 6.8742708 | U73: 1 | AA73: =N73 -> 12.606875 | AB73: =O73 -> 1.1416667 | AC73: =P73 -> 0 | AD73: =Q73 -> 13.748542 | AE73: =R73 -> 0.81496522 | AF73: =Q73*R73 -> 11.204583 | AG73: D
A74: 70 | B74: 9983 | C74: WAAATF-JPN | D74: Agents Target Following system | E74: Sales / Insurance Recruitment | F74: Customer and Channel Engineering 34961 | G74: Distribution F2F Team 34962 | H74: Core Business Application | I74: N | J74: Yes | K74: JAVA | L74: Platform as a Service (PaaS) | M74: N | N74: 6.6141667 | O74: 0.64791667 | P74: 0 | Q74: 7.2620833 | R74: 0.93912445 | S74: 3.6310417 | T74: 3.6310417 | U74: 1 | AA74: =N74 -> 6.6141667 | AB74: =O74 -> 0.64791667 | AC74: =P74 -> 0 | AD74: =Q74 -> 7.2620833 | AE74: =R74 -> 0.93912445 | AF74: =Q74*R74 -> 6.82 | AG74: B
A75: 71 | B75: 9986 | C75: ZGLEST-JPN | D75: eSTATION | E75: Corporate Related | F75: Core Insurance Systems Group 34956 | G75: Corporate Systems Team 34959 | H75: Core Business Application | I75: N | J75: Yes | K75: JavaScript; VB.NET; C#;HTML | M75: N | N75: 2.4426667 | O75: 0.57083333 | P75: 0 | Q75: 3.0135 | R75: 0.27515071 | S75: 1.50675 | T75: 1.50675 | U75: 1 | AA75: =N75 -> 2.4426667 | AB75: =O75 -> 0.57083333 | AC75: =P75 -> 0 | AD75: =Q75 -> 3.0135 | AE75: =R75 -> 0.27515071 | AF75: =Q75*R75 -> 0.82916667 | AG75: B
A76: 72 | B76: 9992 | C76: CMESB-JPN | D76: Enterprise Service Bus | E76: Common Service Platform | F76: Japan Platform Team 35775 | G76: Japan Platform Team 35775 | H76: Common Service Business Application | I76: N | J76: Yes | K76: JAVA; Other#ESQL | M76: N | N76: 7.2083333 | O76: 2.9958333 | P76: 2.5208333 | Q76: 12.725 | R76: 0.93778651 | S76: 6.3625 | T76: 6.3625 | U76: 1 | AA76: =N76 -> 7.2083333 | AB76: =O76 -> 2.9958333 | AC76: =P76 -> 2.5208333 | AD76: =Q76 -> 12.725 | AE76: =R76 -> 0.93778651 | AF76: =Q76*R76 -> 11.933333 | AG76: B
A77: 73 | B77: 9994 | C77: WPMAUD-JPN | D77: Unknown Address Tracking System | E77: Storage and Preservation Related | F77: Customer Service and Operations Systems Group 34965 | G77: Policy Servicing Team 34967 | H77: Core Business Application | I77: N | J77: No | K77: JAVA | L77: Platform as a Service (PaaS) | M77: N | N77: 0.8 | O77: 0.2 | P77: 0 | Q77: 1.1729167 | R77: 0.42806394 | S77: 0.58645833 | T77: 0.58645833 | U77: 1 | AA77: =N77 -> 0.8 | AB77: =O77 -> 0.2 | AC77: =P77 -> 0 | AD77: =Q77 -> 1.1729167 | AE77: =R77 -> 0.42806394 | AF77: =Q77*R77 -> 0.50208333 | AG77: B
A78: 74 | B78: 9995 | C78: WCMPXS-JPN | D78: ProductXpress | E78: Corporate Related | F78: Core Insurance Systems Group 34956 | G78: Corporate Systems Team 34959 | H78: Infrastructure Application | I78: N | J78: Yes | K78: Other#Peculiar Language, Implemented in PX designer. | M78: N | N78: 0.77916667 | O78: 0 | P78: 0 | Q78: 0.77916667 | R78: 0.67914439 | S78: 0.38958333 | T78: 0.38958333 | U78: 1 | AA78: =N78 -> 0.77916667 | AB78: =O78 -> 0 | AC78: =P78 -> 0 | AD78: =Q78 -> 0.77916667 | AE78: =R78 -> 0.67914439 | AF78: =Q78*R78 -> 0.52916667 | AG78: B
A79: 75 | B79: 9996 | C79: WUIURE-JPN | D79: Pre-Underwriting | E79: New Contract Related | F79: Customer Service and Operations Systems Group 34965 | G79: New Business Team 34966 | H79: Core Business Application | I79: N | J79: Yes | K79: JAVA | M79: N | N79: 0.22625 | O79: 0 | P79: 0 | Q79: 0.22625 | R79: 0.33701657 | S79: 0.113125 | T79: 0.113125 | U79: 1 | AA79: =N79 -> 0.22625 | AB79: =O79 -> 0 | AC79: =P79 -> 0 | AD79: =Q79 -> 0.22625 | AE79: =R79 -> 0.33701657 | AF79: =Q79*R79 -> 0.07625 | AG79: B
A80: 76 | B80: 9999 | C80: LINC MF-JPN | D80: LINC | E80: contract management | F80: Core Insurance Systems Group 34956 | G80: Policy Admin Systems Team 34957 | H80: Core Business Application | I80: Y | J80: Yes | K80: COBOL, MU(EASYPLUS), Assembler, JCL | M80: N | N80: 1.02875 | O80: 0 | P80: 0 | Q80: 1.02875 | R80: 0.12920211 | S80: 0.514375 | T80: 0.514375 | U80: 1 | AA80: =N80 -> 1.02875 | AB80: =O80 -> 0 | AC80: =P80 -> 0 | AD80: =Q80 -> 1.02875 | AE80: =R80 -> 0.12920211 | AF80: =Q80*R80 -> 0.13291667 | AG80: D
A81: 77 | B81: 10001 | C81: A06TOG-JPN | D81: Group Policy Management System | E81: Corporate Related | F81: Core Insurance Systems Group 34956 | G81: Corporate Systems Team 34959 | H81: Core Business Application | I81: Y | J81: Yes | K81: Other#RPG; Cobol | M81: N | N81: 2.7291667 | O81: 3.025 | P81: 0 | Q81: 5.7541667 | R81: 0.34540188 | S81: 2.8770833 | T81: 2.8770833 | U81: 1 | AA81: =N81 -> 2.7291667 | AB81: =O81 -> 3.025 | AC81: =P81 -> 0 | AD81: =Q81 -> 5.7541667 | AE81: =R81 -> 0.34540188 | AF81: =Q81*R81 -> 1.9875 | AG81: D
A82: 78 | B82: 10032 | C82: W06TGR-JPN | D82: Group Policy Inquiry System for Intranet | E82: Corporate Related | F82: Core Insurance Systems Group 34956 | G82: Corporate Systems Team 34959 | H82: Core Business Application | I82: Y | J82: Yes | K82: VB.NET; JAVA | M82: N | N82: 1.8583333 | O82: 0.94166667 | P82: 0 | Q82: 2.8 | R82: 0.26934524 | S82: 1.4 | T82: 1.4 | U82: 1 | AA82: =N82 -> 1.8583333 | AB82: =O82 -> 0.94166667 | AC82: =P82 -> 0 | AD82: =Q82 -> 2.8 | AE82: =R82 -> 0.26934524 | AF82: =Q82*R82 -> 0.75416667 | AG82: B
A83: 79 | B83: 11004 | C83: WAAICM-JPN | D83: ICM | E83: Fee Management | F83: Core Insurance Systems Group 34956 | G83: Commission Systems Team 34958 | H83: Core Business Application | I83: N | J83: Yes | K83: JAVA; C#; Other#ETL JAVA(ADJP) SQL | L83: Software as a Service (SaaS) | M83: N | N83: 21.506125 | O83: 7.7291667 | P83: 0 | Q83: 29.235292 | R83: 0.83096913 | S83: 14.617646 | T83: 14.617646 | U83: 1 | AA83: =N83 -> 21.506125 | AB83: =O83 -> 7.7291667 | AC83: =P83 -> 0 | AD83: =Q83 -> 29.235292 | AE83: =R83 -> 0.83096913 | AF83: =Q83*R83 -> 24.293625 | AG83: A
A84: 80 | B84: 11005 | C84: WAACPS-JPN | D84: Commission and Performance System | E84: Corporate Related | F84: Core Insurance Systems Group 34956 | G84: Corporate Systems Team 34959 | H84: Core Business Application | I84: N | J84: Yes | K84: JAVA | L84: Platform as a Service (PaaS) | M84: N | N84: 0.3625 | O84: 0.041666667 | P84: 0.5 | Q84: 0.90416667 | R84: 0.44700461 | S84: 0.45208333 | T84: 0.45208333 | U84: 1 | AA84: =N84 -> 0.3625 | AB84: =O84 -> 0.041666667 | AC84: =P84 -> 0.5 | AD84: =Q84 -> 0.90416667 | AE84: =R84 -> 0.44700461 | AF84: =Q84*R84 -> 0.40416667 | AG84: B
A85: 81 | B85: 11007 | C85: OMSIKN-JPN | D85: Conservation contract transferring system | E85: Corporate Related | F85: Core Insurance Systems Group 34956 | G85: Corporate Systems Team 34959 | H85: Core Business Application | I85: N | J85: Yes | K85: JAVA | M85: N | N85: 0.23491667 | O85: 0.072916667 | P85: 0 | Q85: 0.30783333 | R85: 0.95939361 | S85: 0.15391667 | T85: 0.15391667 | U85: 1 | AA85: =N85 -> 0.23491667 | AB85: =O85 -> 0.072916667 | AC85: =P85 -> 0 | AD85: =Q85 -> 0.30783333 | AE85: =R85 -> 0.95939361 | AF85: =Q85*R85 -> 0.29533333 | AG85: B
A86: 82 | B86: 11008 | C86: OMSTAT-JPN | D86: Conservation contract allowance system | E86: Marketing/Direct Business Related | F86: Customer and Channel Engineering 34961 | G86: Marketing and Leads Team 34964 | H86: Core Business Application | I86: N | J86: Yes | K86: JAVA | M86: N | N86: 0.13541667 | O86: 0.016666667 | P86: 0 | Q86: 0.15208333 | R86: 0.52054795 | S86: 0.076041667 | T86: 0.076041667 | U86: 1 | AA86: =N86 -> 0.13541667 | AB86: =O86 -> 0.016666667 | AC86: =P86 -> 0 | AD86: =Q86 -> 0.15208333 | AE86: =R86 -> 0.52054795 | AF86: =Q86*R86 -> 0.079166667 | AG86: B
A87: 83 | B87: 11010 | C87: ZGLEDQ-JPN | D87: FATCA Oracle EDQ | E87: Corporate Related | F87: Core Insurance Systems Group 34956 | G87: Corporate Systems Team 34959 | H87: Core Business Application | I87: N | J87: Yes | K87: JAVA; C # | L87: Platform as a Service (PaaS) | M87: N | N87: 1.2583333 | O87: 0.029166667 | P87: 0.5 | Q87: 1.7875 | R87: 0.55710956 | S87: 0.89375 | T87: 0.89375 | U87: 1 | AA87: =N87 -> 1.2583333 | AB87: =O87 -> 0.029166667 | AC87: =P87 -> 0.5 | AD87: =Q87 -> 1.7875 | AE87: =R87 -> 0.55710956 | AF87: =Q87*R87 -> 0.99583333 | AG87: B
A88: 84 | B88: 11011 | C88: WGLWLF-JPN | D88: Watch List Filtering system | E88: Corporate Related | F88: Core Insurance Systems Group 34956 | G88: Corporate Systems Team 34959 | H88: Core Business Application | I88: N | J88: Yes | K88: JAVA | M88: N | N88: 6.0791667 | O88: 1.0708333 | P88: 0 | Q88: 7.15 | R88: 0.90384615 | S88: 3.575 | T88: 3.575 | U88: 1 | AA88: =N88 -> 6.0791667 | AB88: =O88 -> 1.0708333 | AC88: =P88 -> 0 | AD88: =Q88 -> 7.15 | AE88: =R88 -> 0.90384615 | AF88: =Q88*R88 -> 6.4625 | AG88: B
A89: 85 | B89: 11012 | C89: WZZMNB-JPN | D89: My number management system | E89: Insurance Claims and Benefits Payment Related | F89: Customer Service and Operations Systems Group 34965 | G89: Claims Team 34968 | H89: Core Business Application | I89: N | J89: Yes | K89: JAVA | M89: N | N89: 1.6523333 | O89: 0.29166667 | P89: 0 | Q89: 1.944 | R89: 0.83217593 | S89: 0.972 | T89: 0.972 | U89: 1 | AA89: =N89 -> 1.6523333 | AB89: =O89 -> 0.29166667 | AC89: =P89 -> 0 | AD89: =Q89 -> 1.944 | AE89: =R89 -> 0.83217593 | AF89: =Q89*R89 -> 1.61775 | AG89: B
A90: 86 | B90: 11014 | C90: BCMETL-JPN | D90: Informatica Platform | E90: Data Infrastructure | F90: Data Platforms Team 34980 | G90: Data Platforms Team 34980 | H90: Common Service Business Application | I90: N | J90: Yes | K90: Other#Used UI for development and stored data as XML | M90: Y | N90: 29.097917 | O90: 6.825 | P90: 6.85 | Q90: 42.772917 | R90: 0.88284058 | S90: 21.386458 | T90: 21.386458 | U90: 1 | AA90: =N90 -> 29.097917 | AB90: =O90 -> 6.825 | AC90: =P90 -> 6.85 | AD90: =Q90 -> 42.772917 | AE90: =R90 -> 0.88284058 | AF90: =Q90*R90 -> 37.761667 | AG90: C | AH90: VS1
A91: 87 | B91: 11203 | C91: WPSCFC-JPN | D91: c-Force | E91: Sales / Insurance Recruitment | F91: Customer and Channel Engineering 34961 | G91: Distribution F2F Team 34962 | H91: Core Business Application | I91: N | J91: No | K91: Other#APEX;HTML; JavaScript | L91: Software as a Service (SaaS) | M91: Y | N91: 20.833333 | O91: 10.004167 | P91: 12.725 | Q91: 43.5625 | R91: 0.86915352 | S91: 21.78125 | T91: 21.78125 | U91: 1 | AA91: =N91 -> 20.833333 | AB91: =O91 -> 10.004167 | AC91: =P91 -> 12.725 | AD91: =Q91 -> 43.5625 | AE91: =R91 -> 0.86915352 | AF91: =Q91*R91 -> 37.8625 | AG91: C
A92: 88 | B92: 11288 | C92: CGLFJM-JPN | D92: Misconduct Management system | E92: Corporate Related | F92: Core Insurance Systems Group 34956 | G92: Corporate Systems Team 34959 | H92: Core Business Application | I92: N | J92: Yes | K92: VB | M92: N | N92: 0.091666667 | O92: 0 | P92: 0 | Q92: 0.091666667 | R92: 0.27272727 | S92: 0.045833333 | T92: 0.045833333 | U92: 1 | AA92: =N92 -> 0.091666667 | AB92: =O92 -> 0 | AC92: =P92 -> 0 | AD92: =Q92 -> 0.091666667 | AE92: =R92 -> 0.27272727 | AF92: =Q92*R92 -> 0.025 | AG92: B
A93: 89 | B93: 11308 | C93: WGLBSR-JPN | D93: BSRec | E93: Corporate Related | F93: Core Insurance Systems Group 34956 | G93: Corporate Systems Team 34959 | H93: Core Business Application | I93: N | J93: Yes | K93: JAVA | M93: N | N93: 0.48125 | O93: 0.0625 | P93: 0 | Q93: 0.54375 | R93: 0.37931034 | S93: 0.271875 | T93: 0.271875 | U93: 1 | AA93: =N93 -> 0.48125 | AB93: =O93 -> 0.0625 | AC93: =P93 -> 0 | AD93: =Q93 -> 0.54375 | AE93: =R93 -> 0.37931034 | AF93: =Q93*R93 -> 0.20625 | AG93: B
A94: 90 | B94: 11604 | C94: JP-RPASS | D94: JAPAN_BluePrism RPA | E94: Storage and Preservation Related | F94: Customer Service and Operations Systems Group 34965 | G94: Policy Servicing Team 34967 | H94: Common Service Business Application | I94: N | J94: Yes | K94: Other#COTS from BluePrism | M94: N | N94: 5.6624583 | O94: 4.075 | P94: 0 | Q94: 9.7374583 | R94: 0.8973038 | S94: 4.8687292 | T94: 4.8687292 | U94: 1 | AA94: =N94 -> 5.6624583 | AB94: =O94 -> 4.075 | AC94: =P94 -> 0 | AD94: =Q94 -> 9.7374583 | AE94: =R94 -> 0.8973038 | AF94: =Q94*R94 -> 8.7374583 | AG94: B
A95: 91 | B95: 11893 | C95: W03CCP-JPN | D95: Customer Communication Preferences | E95: Storage and Preservation Related | F95: Customer Service and Operations Systems Group 34965 | G95: Policy Servicing Team 34967 | H95: Core Business Application | I95: N | J95: Yes | K95: JAVA | L95: Platform as a Service (PaaS) | M95: N | N95: 0.2 | O95: 0.2 | P95: 0 | Q95: 0.35416667 | R95: 0.56470588 | S95: 0.17708333 | T95: 0.17708333 | U95: 1 | AA95: =N95 -> 0.2 | AB95: =O95 -> 0.2 | AC95: =P95 -> 0 | AD95: =Q95 -> 0.35416667 | AE95: =R95 -> 0.56470588 | AF95: =Q95*R95 -> 0.2 | AG95: B
A96: 92 | B96: 11986 | C96: JP-Banca Report | D96: Japan Banca Report | E96: Sales / Insurance Recruitment | F96: Customer and Channel Engineering 34961 | G96: Distribution Banca Team 34963 | H96: Common Service Business Application | I96: N | J96: Yes | K96: JAVA | L96: Infrastructure as a Service (IaaS); Platform as a Service (PaaS) | M96: N | N96: 6 | O96: 6 | P96: 3 | Q96: 15 | R96: 1 | S96: 7.5 | T96: 7.5 | U96: 1 | AA96: =N96 -> 6 | AB96: =O96 -> 6 | AC96: =P96 -> 3 | AD96: =Q96 -> 15 | AE96: =R96 -> 1 | AF96: =Q96*R96 -> 15 | AG96: B
A97: 93 | B97: 12021 | C97: LPS-JPN(EUC081) | D97: Life Plan Simulation Japan | E97: Marketing/Direct Business Related | F97: Customer and Channel Engineering 34961 | G97: Marketing and Leads Team 34964 | H97: Core Business Application | I97: N | J97: Yes | K97: PHP | M97: N | N97: 0 | O97: 0 | P97: 0 | Q97: 0 | R97: 0 | U97: 1 | AA97: =N97 -> 0 | AB97: =O97 -> 0 | AC97: =P97 -> 0 | AD97: =Q97 -> 0 | AE97: =R97 -> 0 | AF97: =Q97*R97 -> 0 | AG97: B
A98: 94 | B98: 12030 | C98: CIT-JPN(EUC082) | D98: Inheritance Tax Simulation | E98: Marketing/Direct Business Related | F98: Customer and Channel Engineering 34961 | G98: Marketing and Leads Team 34964 | H98: Core Business Application | I98: N | J98: Yes | K98: JAVA | M98: N | N98: 0 | O98: 0 | P98: 0 | Q98: 0 | R98: 0 | U98: 1 | AA98: =N98 -> 0 | AB98: =O98 -> 0 | AC98: =P98 -> 0 | AD98: =Q98 -> 0 | AE98: =R98 -> 0 | AF98: =Q98*R98 -> 0 | AG98: B
A99: 95 | B99: 12038 | C99: CMIAPI-JPN | D99: API Hub | E99: Common Service Platform | F99: Japan Platform Team 35775 | G99: Japan Platform Team 35775 | H99: Common Service Business Application | I99: N | J99: Yes | K99: JAVA | L99: Platform as a Service (PaaS) | M99: N | N99: 19.246667 | O99: 4.1333333 | P99: 16.910417 | Q99: 40.290417 | R99: 0.94847824 | S99: 20.145208 | T99: 20.145208 | U99: 1 | AA99: =N99 -> 19.246667 | AB99: =O99 -> 4.1333333 | AC99: =P99 -> 16.910417 | AD99: =Q99 -> 40.290417 | AE99: =R99 -> 0.94847824 | AF99: =Q99*R99 -> 38.214583 | AG99: B
A100: 96 | B100: 12117 | C100: K2 | D100: Japan K2 - Digital Workflows | E100: Storage and Preservation Related | F100: Customer Service and Operations Systems Group 34965 | G100: Policy Servicing Team 34967 | H100: Core Business Application | I100: Y | J100: Yes | K100: VB.NET | M100: N | N100: 6 | O100: 15.5375 | P100: 11 | Q100: 62.642375 | R100: 0.8631983 | S100: 31.321188 | T100: 31.321188 | U100: 1 | AA100: =N100 -> 6 | AB100: =O100 -> 15.5375 | AC100: =P100 -> 11 | AD100: =Q100 -> 62.642375 | AE100: =R100 -> 0.8631983 | AF100: =Q100*R100 -> 54.072792 | AG100: B
A101: 97 | B101: 12198 | C101: JP-PCI-RPASS | D101: Japan PCI Robotics Process Automation Service | E101: Storage and Preservation Related | F101: Customer Service and Operations Systems Group 34965 | G101: Policy Servicing Team 34967 | H101: Common Service Business Application | I101: N | J101: Yes | K101: Other#This is coded within blueprism | M101: N | N101: 1 | O101: 2 | P101: 0 | Q101: 3 | R101: 0 | S101: 1.5 | T101: 1.5 | U101: 1 | AA101: =N101 -> 1 | AB101: =O101 -> 2 | AC101: =P101 -> 0 | AD101: =Q101 -> 3 | AE101: =R101 -> 0 | AF101: =Q101*R101 -> 0 | AG101: B
A102: 98 | B102: 12520 | C102: RBRARS-JPN | D102: RBWF Report Automatic Recognition System | E102: New Contract Related | F102: Customer Service and Operations Systems Group 34965 | G102: New Business Team 34966 | H102: Core Business Application | I102: N | J102: Yes | K102: JAVA | M102: N | N102: 0.125 | O102: 0 | P102: 0 | Q102: 0.125 | R102: 1 | S102: 0.0625 | T102: 0.0625 | U102: 1 | AA102: =N102 -> 0.125 | AB102: =O102 -> 0 | AC102: =P102 -> 0 | AD102: =Q102 -> 0.125 | AE102: =R102 -> 1 | AF102: =Q102*R102 -> 0.125 | AG102: B
A103: 99 | B103: 12527 | C103: CMEAPI-JP | D103: Japan Partner API | E103: Common Service Platform | F103: Japan Platform Team 35775 | G103: Japan Platform Team 35775 | H103: Common Service Business Application | I103: N | J103: Yes | K103: JAVA | L103: Platform as a Service (PaaS) | M103: N | N103: 0.10833333 | O103: 0 | P103: 0.025 | Q103: 0.13333333 | R103: 1 | S103: 0.066666667 | T103: 0.066666667 | U103: 1 | AA103: =N103 -> 0.10833333 | AB103: =O103 -> 0 | AC103: =P103 -> 0.025 | AD103: =Q103 -> 0.13333333 | AE103: =R103 -> 1 | AF103: =Q103*R103 -> 0.13333333 | AG103: B
A104: 100 | B104: 12607 | C104: JP-WCMAUT | D104: JP Authentication Platform | E104: Common Service Platform | F104: Japan Platform Team 35775 | G104: Japan Platform Team 35775 | H104: Common Service Business Application | I104: N | J104: Yes | K104: JAVA | L104: Platform as a Service (PaaS) | M104: N | N104: 1.3375 | O104: 0 | P104: 1 | Q104: 2.3375 | R104: 1 | S104: 1.16875 | T104: 1.16875 | U104: 1 | AA104: =N104 -> 1.3375 | AB104: =O104 -> 0 | AC104: =P104 -> 1 | AD104: =Q104 -> 2.3375 | AE104: =R104 -> 1 | AF104: =Q104*R104 -> 2.3375 | AG104: B
...

Sheet Value Streams
A1: Data Infrastructure — two value streams
A2: Informatica is the sunset platform; Azure Synapse is go-forward. The modernisation path between them is OUT OF SCOPE of this RFP.
B4: Code | C4: Value stream | D4: Apps | E4: Effort | F4: AD effort | G4: Run effort | H4: AD share | I4: Y1 co-src pods | J4: Y1 full-src pods | K4: Archetype
B5: VS1 | C5: Informatica — ETL, IDQ, Address Doctor & HOST/AS400 data cooperation | D5: =SUMIFS(Inventory!$U:$U,Inventory!$AH:$AH,$B5) -> 2 | E5: =SUMIFS(Inventory!$AD:$AD,Inventory!$AH:$AH,$B5) -> 50.699958 | F5: =SUMIFS(Inventory!$AF:$AF,Inventory!$AH:$AH,$B5) -> 43.938708 | G5: =E5-F5 -> 6.76125 | H5: =IF(E5=0,0,F5/E5) -> 0.8666419 | I5: =SUMIFS('Pod Plan'!$E:$E,'Pod Plan'!$B:$B,1,'Pod Plan'!$C:$C,$B5) -> 4 | J5: =SUMIFS('Pod Plan'!$F:$F,'Pod Plan'!$B:$B,1,'Pod Plan'!$C:$C,$B5) -> 1 | K5: C
B6: VS2 | C6: Azure Synapse — Japan Data Platform & BI/reporting | D6: =SUMIFS(Inventory!$U:$U,Inventory!$AH:$AH,$B6) -> 1 | E6: =SUMIFS(Inventory!$AD:$AD,Inventory!$AH:$AH,$B6) -> 50.06501 | F6: =SUMIFS(Inventory!$AF:$AF,Inventory!$AH:$AH,$B6) -> 43.188135 | G6: =E6-F6 -> 6.876875 | H6: =IF(E6=0,0,F6/E6) -> 0.8626411 | I6: =SUMIFS('Pod Plan'!$E:$E,'Pod Plan'!$B:$B,1,'Pod Plan'!$C:$C,$B6) -> 2 | J6: =SUMIFS('Pod Plan'!$F:$F,'Pod Plan'!$B:$B,1,'Pod Plan'!$C:$C,$B6) -> 2 | K6: B
C7: Total | D7: =SUM(D5:D6) -> 3 | E7: =SUM(E5:E6) -> 100.76497 | F7: =SUM(F5:F6) -> 87.126844 | G7: =SUM(G5:G6) -> 13.638125 | H7: =IF(E7=0,0,F7/E7) -> 0.8646541 | I7: =SUM(I5:I6) -> 6 | J7: =SUM(J5:J6) -> 3
B9: Value stream | C9: Applications and what they are
B10: VS1 | C10: BCMETL-JPN Informatica Platform (42.8u) — common ETL, IDQ and Address Doctor. · BCMHRP-JPN Data cooperation (7.9u) — batch integration between the open estate and HOST/AS400.
B11: VS2 | C11: JDPREP Japan Data Platform and Reporting (50.1u) — Azure PaaS data platform and BI/reporting, Transact-SQL.
B13: Note | C13: Both Informatica applications carry Priority Transfer Targets = Y, so the portfolio bedrock classifies them archetype C and routes engineering to MGCC. Because the platform is being retired, transferring it builds a capability MetLife will not keep. Recommendation on Glidepath & 50-50.

Sheet Pod Library
A1: Pod library — every seat, by year, value stream and pod type
A2: INPUT. Pod sizes are deliberately NOT a uniform ladder: Synapse 9→7→6, Informatica 8→7→6. Counts may be fractional where a MetLife role is shared across two pods.
B4: Year | C4: VS | D4: Pod type | E4: Seat | F4: Role | G4: Skill | H4: Exp | I4: Location | J4: Sourcing | K4: Count
B5: 1 | C5: VS1 | D5: CO | E5: 1 | F5: Product Owner — Informatica Data Platform | G5: LEAD | H5: E4 | I5: ON | J5: FTE | K5: 1
B6: 1 | C6: VS1 | D6: CO | E6: 2 | F6: Data Domain SME | G6: BA | H6: E4 | I6: ON | J6: FTE | K6: 1
B7: 1 | C7: VS1 | D7: CO | E7: 3 | F7: Informatica Lead Engineer | G7: ENG | H7: E3 | I7: OFF | J7: FTC | K7: 1
B8: 1 | C8: VS1 | D8: CO | E8: 4 | F8: Data Modeler | G8: DEV | H8: E3 | I8: OFF | J8: MGCC | K8: 1
B9: 1 | C9: VS1 | D9: CO | E9: 5 | F9: Pod Delivery Lead (Informatica Tech Lead) | G9: LEAD | H9: E4 | I9: ON | J9: FTC | K9: 1
B10: 1 | C10: VS1 | D10: CO | E10: 6 | F10: Senior Informatica Developer | G10: DEV | H10: E3 | I10: ON | J10: FTC | K10: 1
B11: 1 | C11: VS1 | D11: CO | E11: 7 | F11: Informatica Developer | G11: DEV | H11: E2 | I11: OFF | J11: FTC | K11: 1
B12: 1 | C12: VS1 | D12: CO | E12: 8 | F12: Data Tester | G12: TEST | H12: E2 | I12: OFF | J12: FTC | K12: 1
F13: Pod size — Y1 VS1 co-sourced | K13: =SUM(K5:K12) -> 8
B15: 1 | C15: VS1 | D15: FS | E15: 1 | F15: Product Owner- Data Platform | G15: LEAD | H15: E4 | I15: ON | J15: FTE | K15: 1
B16: 1 | C16: VS1 | D16: FS | E16: 2 | F16: Pod Delivery Lead (Informatica Tech Lead) | G16: LEAD | H16: E4 | I16: ON | J16: FTC | K16: 1
B17: 1 | C17: VS1 | D17: FS | E17: 3 | F17: Data Modeler | G17: ENG | H17: E4 | I17: ON | J17: FTC | K17: 1
B18: 1 | C18: VS1 | D18: FS | E18: 4 | F18: Business Analyst (bilingual) | G18: BA | H18: E3 | I18: ON | J18: FTC | K18: 1
B19: 1 | C19: VS1 | D19: FS | E19: 5 | F19: Senior Informatica Developer | G19: DEV | H19: E3 | I19: OFF | J19: FTC | K19: 1
B20: 1 | C20: VS1 | D20: FS | E20: 6 | F20: Informatica Developer | G20: DEV | H20: E2 | I20: OFF | J20: FTC | K20: 2
B21: 1 | C21: VS1 | D21: FS | E21: 7 | F21: Data Tester | G21: TEST | H21: E2 | I21: OFF | J21: FTC | K21: 1
B22: 1 | C22: VS1 | D22: FS | E22: 8 | F22: L2 Data Support | G22: OPS | H22: E2 | I22: OFF | J22: FTC | K22: 0
F23: Pod size — Y1 VS1 fully-sourced | K23: =SUM(K15:K22) -> 8
B25: 1 | C25: VS2 | D25: CO | E25: 1 | F25: Product Owner- Data Platform | G25: LEAD | H25: E4 | I25: ON | J25: FTE | K25: 1
B26: 1 | C26: VS2 | D26: CO | E26: 2 | F26: Azure Data Architect (MetLife) | G26: ENG | H26: E5 | I26: ON | J26: FTE | K26: 1
B27: 1 | C27: VS2 | D27: CO | E27: 3 | F27: BI / Reporting Engineer | G27: DEV | H27: E3 | I27: OFF | J27: FTC | K27: 1
B28: 1 | C28: VS2 | D28: CO | E28: 4 | F28: Synapse Platform Engineer | G28: ENG | H28: E4 | I28: OFF | J28: MGCC | K28: 1
B29: 1 | C29: VS2 | D29: CO | E29: 5 | F29: Azure Data Engineer | G29: DEV | H29: E3 | I29: OFF | J29: MGCC | K29: 1
B30: 1 | C30: VS2 | D30: CO | E30: 6 | F30: Pod Delivery Lead ( Azure Data Engineering) | G30: LEAD | H30: E4 | I30: ON | J30: FTC | K30: 1
B31: 1 | C31: VS2 | D31: CO | E31: 7 | F31: Senior Azure Data Engineer | G31: DEV | H31: E3 | I31: ON | J31: MGCC | K31: 1
B32: 1 | C32: VS2 | D32: CO | E32: 8 | F32: Azure Data Engineer | G32: DEV | H32: E2 | I32: OFF | J32: FTC | K32: 1
B33: 1 | C33: VS2 | D33: CO | E33: 9 | F33: Data Tester | G33: TEST | H33: E2 | I33: OFF | J33: FTC | K33: 1
F34: Pod size — Y1 VS2 co-sourced | K34: =SUM(K25:K33) -> 9
B36: 1 | C36: VS2 | D36: FS | E36: 1 | F36: Product Owner- Data Platform (shared 0.5) | G36: LEAD | H36: E4 | I36: ON | J36: FTE | K36: 0.5
B37: 1 | C37: VS2 | D37: FS | E37: 2 | F37: Azure Data Architect (MetLife)- shared | G37: ENG | H37: E5 | I37: ON | J37: FTE | K37: 0.5
B38: 1 | C38: VS2 | D38: FS | E38: 3 | F38: Pod Delivery Lead ( Azure Data Engineering) | G38: LEAD | H38: E4 | I38: ON | J38: FTC | K38: 1
B39: 1 | C39: VS2 | D39: FS | E39: 4 | F39: Data Modeler | G39: ENG | H39: E4 | I39: OFF | J39: FTC | K39: 1
B40: 1 | C40: VS2 | D40: FS | E40: 5 | F40: Business Analyst (bilingual) | G40: BA | H40: E3 | I40: ON | J40: FTC | K40: 1
B41: 1 | C41: VS2 | D41: FS | E41: 6 | F41: Senior Azure Data Engineer | G41: DEV | H41: E3 | I41: OFF | J41: FTC | K41: 1
B42: 1 | C42: VS2 | D42: FS | E42: 7 | F42: Azure Data Engineer | G42: DEV | H42: E2 | I42: OFF | J42: FTC | K42: 2
B43: 1 | C43: VS2 | D43: FS | E43: 8 | F43: BI / Reporting Engineer | G43: DEV | H43: E3 | I43: OFF | J43: FTC | K43: 1
B44: 1 | C44: VS2 | D44: FS | E44: 9 | F44: Data Tester | G44: TEST | H44: E2 | I44: OFF | J44: FTC | K44: 1
F45: Pod size — Y1 VS2 fully-sourced | K45: =SUM(K36:K44) -> 9
B47: 2 | C47: VS1 | D47: CO | E47: 1 | F47: Product Owner — Informatica Data Platform | G47: LEAD | H47: E4 | I47: ON | J47: FTE | K47: 1
B48: 2 | C48: VS1 | D48: CO | E48: 2 | F48: Data Domain SME | G48: BA | H48: E4 | I48: ON | J48: FTE | K48: 1
B49: 2 | C49: VS1 | D49: CO | E49: 3 | F49: Informatica Lead Engineer | G49: ENG | H49: E4 | I49: OFF | J49: MGCC | K49: 1
B50: 2 | C50: VS1 | D50: CO | E50: 4 | F50: Data Modeler | G50: DEV | H50: E3 | I50: OFF | J50: MGCC | K50: 1
B51: 2 | C51: VS1 | D51: CO | E51: 5 | F51: Pod Delivery Lead (Informatica Tech Lead) | G51: LEAD | H51: E4 | I51: OFF | J51: FTC | K51: 1
B52: 2 | C52: VS1 | D52: CO | E52: 6 | F52: Informatica Developer | G52: DEV | H52: E3 | I52: OFF | J52: FTC | K52: 1
B53: 2 | C53: VS1 | D53: CO | E53: 7 | F53: AI-assisted Data Tester | G53: TEST | H53: E3 | I53: OFF | J53: FTC | K53: 1
F54: Pod size — Y2 VS1 co-sourced | K54: =SUM(K47:K53) -> 7
B56: 2 | C56: VS1 | D56: FS | E56: 1 | F56: Product Owner | G56: LEAD | H56: E4 | I56: ON | J56: FTE | K56: 1
B57: 2 | C57: VS1 | D57: FS | E57: 2 | F57: Pod Delivery Lead (Informatica Tech Lead) | G57: LEAD | H57: E4 | I57: ON | J57: FTC | K57: 1
B58: 2 | C58: VS1 | D58: FS | E58: 3 | F58: Data Modeler | G58: ENG | H58: E4 | I58: OFF | J58: FTC | K58: 1
B59: 2 | C59: VS1 | D59: FS | E59: 4 | F59: Business Analyst (bilingual) | G59: BA | H59: E3 | I59: ON | J59: FTC | K59: 1
B60: 2 | C60: VS1 | D60: FS | E60: 5 | F60: Informatica Developer | G60: DEV | H60: E3 | I60: OFF | J60: FTC | K60: 2
B61: 2 | C61: VS1 | D61: FS | E61: 6 | F61: AI-assisted Data Tester | G61: TEST | H61: E3 | I61: OFF | J61: FTC | K61: 1
B62: 2 | C62: VS1 | D62: FS | E62: 7 | F62: L2 Data Support | G62: OPS | H62: E2 | I62: OFF | J62: FTC | K62: 0
F63: Pod size — Y2 VS1 fully-sourced | K63: =SUM(K56:K62) -> 7
B65: 2 | C65: VS2 | D65: CO | E65: 1 | F65: Product Owner -Azure Data Platform | G65: LEAD | H65: E4 | I65: ON | J65: FTE | K65: 1
B66: 2 | C66: VS2 | D66: CO | E66: 2 | F66: Azure Data Architect (MetLife) | G66: ENG | H66: E5 | I66: ON | J66: FTE | K66: 1
B67: 2 | C67: VS2 | D67: CO | E67: 3 | F67: BI / Reporting Engineer | G67: DEV | H67: E3 | I67: OFF | J67: FTC | K67: 1
B68: 2 | C68: VS2 | D68: CO | E68: 4 | F68: Synapse Platform Engineer | G68: ENG | H68: E4 | I68: OFF | J68: MGCC | K68: 1
B69: 2 | C69: VS2 | D69: CO | E69: 5 | F69: Azure Data Engineer | G69: DEV | H69: E3 | I69: OFF | J69: MGCC | K69: 1
B70: 2 | C70: VS2 | D70: CO | E70: 6 | F70: AI-automation Lead | G70: LEAD | H70: E4 | I70: ON | J70: FTC | K70: 1
B71: 2 | C71: VS2 | D71: CO | E71: 7 | F71: AI-assisted Data Engineer | G71: DEV | H71: E3 | I71: OFF | J71: FTC | K71: 1
F72: Pod size — Y2 VS2 co-sourced | K72: =SUM(K65:K71) -> 7
B74: 2 | C74: VS2 | D74: FS | E74: 1 | F74: Product Owner -Azure Data Platform (shared 0.5) | G74: LEAD | H74: E4 | I74: ON | J74: FTE | K74: 0.5
B75: 2 | C75: VS2 | D75: FS | E75: 2 | F75: Azure Data Architect (MetLife)- shared | G75: ENG | H75: E5 | I75: ON | J75: FTE | K75: 0.5
B76: 2 | C76: VS2 | D76: FS | E76: 3 | F76: Pod Delivery Lead ( Azure Data Engineering) | G76: LEAD | H76: E4 | I76: ON | J76: FTC | K76: 1
B77: 2 | C77: VS2 | D77: FS | E77: 4 | F77: AI-automation Lead | G77: ENG | H77: E4 | I77: ON | J77: FTC | K77: 1
B78: 2 | C78: VS2 | D78: FS | E78: 5 | F78: Business Analyst (bilingual) | G78: BA | H78: E3 | I78: ON | J78: FTC | K78: 1
B79: 2 | C79: VS2 | D79: FS | E79: 6 | F79: AI-assisted Data Engineer | G79: DEV | H79: E3 | I79: OFF | J79: FTC | K79: 2
B80: 2 | C80: VS2 | D80: FS | E80: 7 | F80: BI / Reporting Engineer | G80: DEV | H80: E3 | I80: OFF | J80: FTC | K80: 1
B81: 2 | C81: VS2 | D81: FS | E81: 8 | F81: AI-assisted Data Tester | G81: TEST | H81: E3 | I81: OFF | J81: FTC | K81: 1
F82: Pod size — Y2 VS2 fully-sourced | K82: =SUM(K74:K81) -> 8
B84: 3 | C84: VS1 | D84: CO | E84: 1 | F84: Product Owner — Informatica Data Platform | G84: LEAD | H84: E4 | I84: ON | J84: FTE | K84: 0 | L84: All Informatica Workloads modernized
B85: 3 | C85: VS1 | D85: CO | E85: 2 | F85: Data Domain SME | G85: BA | H85: E4 | I85: ON | J85: FTE | K85: 0
B86: 3 | C86: VS1 | D86: CO | E86: 3 | F86: Data Modeler | G86: ENG | H86: E4 | I86: OFF | J86: MGCC | K86: 0
B87: 3 | C87: VS1 | D87: CO | E87: 4 | F87: Informatica Engineer | G87: DEV | H87: E3 | I87: OFF | J87: MGCC | K87: 0
B88: 3 | C88: VS1 | D88: CO | E88: 5 | F88: Pod Delivery Lead (Informatica Tech Lead) | G88: LEAD | H88: E4 | I88: OFF | J88: FTC | K88: 0
B89: 3 | C89: VS1 | D89: CO | E89: 6 | F89: Informatica Engineer | G89: DEV | H89: E3 | I89: OFF | J89: FTC | K89: 0
F90: Pod size — Y3 VS1 co-sourced | K90: =SUM(K84:K89) -> 0
B92: 3 | C92: VS1 | D92: FS | E92: 1 | F92: Product Owner | G92: LEAD | H92: E4 | I92: ON | J92: FTE | K92: 0 | L92: All Informatica Workloads modernized
B93: 3 | C93: VS1 | D93: FS | E93: 2 | F93: Pod Delivery Lead (Informatica Tech Lead) | G93: LEAD | H93: E4 | I93: OFF | J93: FTC | K93: 0
B94: 3 | C94: VS1 | D94: FS | E94: 3 | F94: Business Analyst (bilingual) | G94: BA | H94: E3 | I94: ON | J94: FTC | K94: 0
B95: 3 | C95: VS1 | D95: FS | E95: 4 | F95: AI automation Lead | G95: ENG | H95: E4 | I95: OFF | J95: FTC | K95: 0
B96: 3 | C96: VS1 | D96: FS | E96: 5 | F96: Informatica Engineer | G96: DEV | H96: E3 | I96: OFF | J96: FTC | K96: 0
B97: 3 | C97: VS1 | D97: FS | E97: 6 | F97: AI-assisted Data Tester | G97: TEST | H97: E3 | I97: OFF | J97: FTC | K97: 0
F98: Pod size — Y3 VS1 fully-sourced | K98: =SUM(K92:K97) -> 0
B100: 3 | C100: VS2 | D100: CO | E100: 1 | F100: Product Owner — Azure Data Platform | G100: LEAD | H100: E4 | I100: ON | J100: FTE | K100: 1
B101: 3 | C101: VS2 | D101: CO | E101: 2 | F101: Azure Data Architect (MetLife) | G101: ENG | H101: E5 | I101: ON | J101: FTE | K101: 1
B102: 3 | C102: VS2 | D102: CO | E102: 3 | F102: BI / Reporting Engineer | G102: DEV | H102: E3 | I102: OFF | J102: FTC | K102: 1
B103: 3 | C103: VS2 | D103: CO | E103: 4 | F103: Synapse Platform Engineer | G103: ENG | H103: E4 | I103: OFF | J103: MGCC | K103: 1
B104: 3 | C104: VS2 | D104: CO | E104: 5 | F104: AI-assisted Data Engineer | G104: DEV | H104: E3 | I104: OFF | J104: MGCC | K104: 1
B105: 3 | C105: VS2 | D105: CO | E105: 5 | F105: AI-assisted Data Tester | G105: TEST | H105: E3 | I105: OFF | J105: MGCC | K105: 1
B106: 3 | C106: VS2 | D106: CO | E106: 6 | F106: AI-automation Lead | G106: LEAD | H106: E4 | I106: ON | J106: FTC | K106: 1
F107: Pod size — Y3 VS2 co-sourced | K107: =SUM(K100:K106) -> 7
B109: 3 | C109: VS2 | D109: FS | E109: 1 | F109: Product Owner -Azure Data Platform (shared 0.5) | G109: LEAD | H109: E4 | I109: ON | J109: FTE | K109: 0.5
B110: 3 | C110: VS2 | D110: FS | E110: 2 | F110: Azure Data Architect (shared 0.5) | G110: ENG | H110: E5 | I110: ON | J110: FTE | K110: 0.5
B111: 3 | C111: VS2 | D111: FS | E111: 3 | F111: Pod Delivery Lead ( Azure Data Engineering) | G111: LEAD | H111: E4 | I111: ON | J111: FTC | K111: 1
B112: 3 | C112: VS2 | D112: FS | E112: 4 | F112: AI-automation Lead | G112: ENG | H112: E4 | I112: OFF | J112: FTC | K112: 1
...

Sheet Pod Plan
A1: Pod plan — pods per value stream per year
A2: INPUT. Fewer pods and smaller pods is how productivity shows up in the headcount.
B4: Year | C4: VS | D4: Value stream | E4: Co-sourced pods | F4: Fully-sourced pods | G4: Pods | H4: People
B5: 1 | C5: VS1 | D5: Informatica — ETL, IDQ, Address Doctor & HOST/AS400 data cooperation | E5: 4 | F5: 1 | G5: =E5+F5 -> 5 | H5: =E5*SUMIFS('Pod Library'!$K:$K,'Pod Library'!$B:$B,$B5,'Pod Library'!$C:$C,$C5,'Pod Library'!$D:$D,"CO")+F5*SUMIFS('Pod Library'!$K:$K,'Pod Library'!$B:$B,$B5,'Pod Library'!$C:$C,$C5,'Pod Library'!$D:$D,"FS") -> 40
B6: 1 | C6: VS2 | D6: Azure Synapse — Japan Data Platform & BI/reporting | E6: 2 | F6: 2 | G6: =E6+F6 -> 4 | H6: =E6*SUMIFS('Pod Library'!$K:$K,'Pod Library'!$B:$B,$B6,'Pod Library'!$C:$C,$C6,'Pod Library'!$D:$D,"CO")+F6*SUMIFS('Pod Library'!$K:$K,'Pod Library'!$B:$B,$B6,'Pod Library'!$C:$C,$C6,'Pod Library'!$D:$D,"FS") -> 36
D7: Year 1 total | E7: =SUM(E5:E6) -> 6 | F7: =SUM(F5:F6) -> 3 | G7: =SUM(G5:G6) -> 9 | H7: =SUM(H5:H6) -> 76
B9: 2 | C9: VS1 | D9: Informatica — ETL, IDQ, Address Doctor & HOST/AS400 data cooperation | E9: 2 | F9: 1 | G9: =E9+F9 -> 3 | H9: =E9*SUMIFS('Pod Library'!$K:$K,'Pod Library'!$B:$B,$B9,'Pod Library'!$C:$C,$C9,'Pod Library'!$D:$D,"CO")+F9*SUMIFS('Pod Library'!$K:$K,'Pod Library'!$B:$B,$B9,'Pod Library'!$C:$C,$C9,'Pod Library'!$D:$D,"FS") -> 21
B10: 2 | C10: VS2 | D10: Azure Synapse — Japan Data Platform & BI/reporting | E10: 3 | F10: 2 | G10: =E10+F10 -> 5 | H10: =E10*SUMIFS('Pod Library'!$K:$K,'Pod Library'!$B:$B,$B10,'Pod Library'!$C:$C,$C10,'Pod Library'!$D:$D,"CO")+F10*SUMIFS('Pod Library'!$K:$K,'Pod Library'!$B:$B,$B10,'Pod Library'!$C:$C,$C10,'Pod Library'!$D:$D,"FS") -> 37
D11: Year 2 total | E11: =SUM(E9:E10) -> 5 | F11: =SUM(F9:F10) -> 3 | G11: =SUM(G9:G10) -> 8 | H11: =SUM(H9:H10) -> 58
B13: 3 | C13: VS1 | D13: Informatica — ETL, IDQ, Address Doctor & HOST/AS400 data cooperation | E13: 0 | F13: 0 | G13: =E13+F13 -> 0 | H13: =E13*SUMIFS('Pod Library'!$K:$K,'Pod Library'!$B:$B,$B13,'Pod Library'!$C:$C,$C13,'Pod Library'!$D:$D,"CO")+F13*SUMIFS('Pod Library'!$K:$K,'Pod Library'!$B:$B,$B13,'Pod Library'!$C:$C,$C13,'Pod Library'!$D:$D,"FS") -> 0 | I13: All Informatica Workloads modernized
B14: 3 | C14: VS2 | D14: Azure Synapse — Japan Data Platform & BI/reporting | E14: 4 | F14: 2 | G14: =E14+F14 -> 6 | H14: =E14*SUMIFS('Pod Library'!$K:$K,'Pod Library'!$B:$B,$B14,'Pod Library'!$C:$C,$C14,'Pod Library'!$D:$D,"CO")+F14*SUMIFS('Pod Library'!$K:$K,'Pod Library'!$B:$B,$B14,'Pod Library'!$C:$C,$C14,'Pod Library'!$D:$D,"FS") -> 42
D15: Year 3 total | E15: =SUM(E13:E14) -> 4 | F15: =SUM(F13:F14) -> 2 | G15: =SUM(G13:G14) -> 6 | H15: =SUM(H13:H14) -> 42

Sheet Horizontal Teams
A1: Horizontal teams — work that is not value-stream bounded
A2: INPUT. As pods consolidate, MetLife seats displaced from them land here — governance and platform operations do not shrink with delivery volume.
B4: Year | C4: Team | D4: Team name | E4: Role | F4: Skill | G4: Exp | H4: Location | I4: Sourcing | J4: Count
B5: 1 | C5: H1 | D5: Platform Operations & Data Reliability | E5: Service Delivery Lead | F5: LEAD | G5: E4 | H5: ON | I5: FTC | J5: 1
B6: 1 | C6: H1 | D6: Platform Operations & Data Reliability | E6: MetLife Data Infrastructure Domain Lead | F6: OPS | G6: E4 | H6: ON | I6: FTE | J6: 1
B7: 1 | C7: H1 | D7: Platform Operations & Data Reliability | E7: L2 Support Data Engr Lead | F7: OPS | G7: E2 | H7: ON | I7: FTC | J7: 1
B8: 1 | C8: H1 | D8: Platform Operations & Data Reliability | E8: L2 Support Data Engr-Informatica and Azure | F8: OPS | G8: E2 | H8: OFF | I8: FTC | J8: 3
B9: 1 | C9: H1 | D9: Platform Operations & Data Reliability | E9: Data Platform SRE | F9: ENG | G9: E3 | H9: OFF | I9: MGCC | J9: 6
E10: H1 total | J10: =SUM(J5:J9) -> 12
B11: 1 | C11: H2 | D11: Data Quality, Test & Environments | E11: Head of Data Platform Testing (MetLife) | F11: LEAD | G11: E5 | H11: ON | I11: FTE | J11: 1
B12: 1 | C12: H2 | D12: Data Quality, Test & Environments | E12: Data Platform Test Lead | F12: TEST | G12: E4 | H12: ON | I12: FTC | J12: 1
B13: 1 | C13: H2 | D13: Data Quality, Test & Environments | E13: Penetration and Data Security Testers | F13: TEST | G13: E2 | H13: OFF | I13: FTC | J13: 2
B14: 1 | C14: H2 | D14: Data Quality, Test & Environments | E14: Stress and Performance Testers | F14: TEST | G14: E2 | H14: OFF | I14: FTC | J14: 2
E15: H2 total | J15: =SUM(J11:J14) -> 6
B16: 1 | C16: H3 | D16: Architecture, Release Train & Governance | E16: Data Domain Delivery Head | F16: LEAD | G16: E5 | H16: ON | I16: FTC | J16: 1
B17: 1 | C17: H3 | D17: Architecture, Release Train & Governance | E17: Chief Data Architect (MetLife) | F17: ENG | G17: E5 | H17: ON | I17: FTE | J17: 1
B18: 1 | C18: H3 | D18: Architecture, Release Train & Governance | E18: DevOps Lead | F18: LEAD | G18: E3 | H18: ON | I18: FTC | J18: 1
B19: 1 | C19: H3 | D19: Architecture, Release Train & Governance | E19: Transition & Substrate Lead | F19: ENG | G19: E5 | H19: ON | I19: FTC | J19: 1
B20: 1 | C20: H3 | D20: Architecture, Release Train & Governance | E20: Business Analyst (MetLife) | F20: BA | G20: E4 | H20: ON | I20: FTE | J20: 2
E21: H3 total | J21: =SUM(J16:J20) -> 6
E22: Year 1 horizontal total | J22: =SUMIFS($J$5:$J$21,$B$5:$B$21,1) -> 24
B24: 2 | C24: H1 | D24: Platform Operations & Data Reliability | E24: Service Delivery Lead | F24: LEAD | G24: E4 | H24: ON | I24: FTC | J24: 1
B25: 2 | C25: H1 | D25: Platform Operations & Data Reliability | E25: MetLife Data Infrastructure Domain Lead | F25: OPS | G25: E4 | H25: ON | I25: FTE | J25: 1
B26: 2 | C26: H1 | D26: Platform Operations & Data Reliability | E26: MetLife Platform Operations Engineers | F26: OPS | G26: E3 | H26: ON | I26: FTE | J26: 1
B27: 2 | C27: H1 | D27: Platform Operations & Data Reliability | E27: Data Platform SRE | F27: ENG | G27: E3 | H27: OFF | I27: MGCC | J27: 3
B28: 2 | C28: H1 | D28: Platform Operations & Data Reliability | E28: L2 Support Data Engr-Informatica | F28: ENG | G28: E3 | H28: OFF | I28: FTC | J28: 2
B29: 2 | C29: H1 | D29: Platform Operations & Data Reliability | E29: L2 Support Data Engr-Azure | F29: ENG | G29: E2 | H29: OFF | I29: FTC | J29: 2
E30: H1 total | J30: =SUM(J24:J29) -> 10
B31: 2 | C31: H2 | D31: Data Quality, Test & Environments | E31: Head of Data Platform Testing (MetLife) | F31: LEAD | G31: E5 | H31: ON | I31: FTE | J31: 1
B32: 2 | C32: H2 | D32: Data Quality, Test & Environments | E32: MetLife Data Reconciliation and Quality Tester | F32: TEST | G32: E3 | H32: ON | I32: FTE | J32: 1
B33: 2 | C33: H2 | D33: Data Quality, Test & Environments | E33: AI Test Automation Engineer | F33: TEST | G33: E3 | H33: OFF | I33: MGCC | J33: 3
B34: 2 | C34: H2 | D34: Data Quality, Test & Environments | E34: Data Platform Test Lead | F34: TEST | G34: E4 | H34: ON | I34: FTC | J34: 1
E35: H2 total | J35: =SUM(J31:J34) -> 6
B36: 2 | C36: H3 | D36: Architecture, Release Train & Governance | E36: Data Domain Delivery Head | F36: LEAD | G36: E5 | H36: ON | I36: FTC | J36: 1
B37: 2 | C37: H3 | D37: Architecture, Release Train & Governance | E37: Chief Data Architect (MetLife) | F37: ENG | G37: E5 | H37: ON | I37: FTE | J37: 1
B38: 2 | C38: H3 | D38: Architecture, Release Train & Governance | E38: DevOps Lead | F38: LEAD | G38: E3 | H38: ON | I38: FTC | J38: 1
B39: 2 | C39: H3 | D39: Architecture, Release Train & Governance | E39: AI Enablement Lead | F39: ENG | G39: E4 | H39: ON | I39: FTC | J39: 1
B40: 2 | C40: H3 | D40: Architecture, Release Train & Governance | E40: Business Analyst (MetLife) | F40: BA | G40: E4 | H40: ON | I40: FTE | J40: 1
E41: H3 total | J41: =SUM(J36:J40) -> 5
E42: Year 2 horizontal total | J42: =SUMIFS($J$24:$J$41,$B$24:$B$41,2) -> 21
B44: 3 | C44: H1 | D44: Platform Operations & Data Reliability | E44: Service Delivery Lead | F44: LEAD | G44: E4 | H44: ON | I44: FTC | J44: 1
B45: 3 | C45: H1 | D45: Platform Operations & Data Reliability | E45: MetLife Data Infrastructure Domain Lead | F45: OPS | G45: E4 | H45: ON | I45: FTE | J45: 1
B46: 3 | C46: H1 | D46: Platform Operations & Data Reliability | E46: MetLife Platform Operations Engineers | F46: OPS | G46: E3 | H46: ON | I46: FTE | J46: 1
B47: 3 | C47: H1 | D47: Platform Operations & Data Reliability | E47: Data Platform SRE | F47: ENG | G47: E3 | H47: OFF | I47: MGCC | J47: 3
B48: 3 | C48: H1 | D48: Platform Operations & Data Reliability | E48: L2 Support Data Engr- Informatica | F48: ENG | G48: E3 | H48: OFF | I48: FTC | J48: 1
B49: 3 | C49: H1 | D49: Platform Operations & Data Reliability | E49: L2 Support Data Engr- Azure | F49: ENG | G49: E2 | H49: OFF | I49: FTC | J49: 2
E50: H1 total | J50: =SUM(J44:J49) -> 9
B51: 3 | C51: H2 | D51: Data Quality, Test & Environments | E51: Head of Data Platform Testing (MetLife) | F51: LEAD | G51: E5 | H51: ON | I51: FTE | J51: 1
B52: 3 | C52: H2 | D52: Data Quality, Test & Environments | E52: MetLife Data Reconciliation and Quality Tester | F52: TEST | G52: E3 | H52: ON | I52: FTE | J52: 2
B53: 3 | C53: H2 | D53: Data Quality, Test & Environments | E53: AI Test Automation Engineer | F53: TEST | G53: E3 | H53: OFF | I53: MGCC | J53: 3
B54: 3 | C54: H2 | D54: Data Quality, Test & Environments | E54: Data Platform Test Lead | F54: TEST | G54: E4 | H54: OFF | I54: FTC | J54: 1
E55: H2 total | J55: =SUM(J51:J54) -> 7
B56: 3 | C56: H3 | D56: Architecture, Release Train & Governance | E56: Data Domain Delivery Head | F56: LEAD | G56: E5 | H56: ON | I56: FTC | J56: 1
B57: 3 | C57: H3 | D57: Architecture, Release Train & Governance | E57: Chief Data Architect (MetLife) | F57: ENG | G57: E5 | H57: ON | I57: FTE | J57: 1
B58: 3 | C58: H3 | D58: Architecture, Release Train & Governance | E58: DevOps Lead | F58: LEAD | G58: E3 | H58: OFF | I58: FTC | J58: 1
B59: 3 | C59: H3 | D59: Architecture, Release Train & Governance | E59: AI Enablement Lead | F59: ENG | G59: E4 | H59: OFF | I59: FTC | J59: 1
B60: 3 | C60: H3 | D60: Architecture, Release Train & Governance | E60: Business Analyst (MetLife) | F60: BA | G60: E4 | H60: ON | I60: FTE | J60: 1
E61: H3 total | J61: =SUM(J56:J60) -> 5
E62: Year 3 horizontal total | J62: =SUMIFS($J$44:$J$61,$B$44:$B$61,3) -> 21

Sheet Team Build-Up
A1: Team build-up — everything derived from the seat ledger
A2: Nothing on this sheet is typed.
A4: A. POD SIZES (read from the Pod Library)
B5: Pod size | C5: VS1 co | D5: VS1 full | E5: VS2 co | F5: VS2 full
B6: Year 1 | C6: =SUMIFS('Pod Library'!$K:$K,'Pod Library'!$B:$B,1,'Pod Library'!$C:$C,"VS1",'Pod Library'!$D:$D,"CO") -> 8 | D6: =SUMIFS('Pod Library'!$K:$K,'Pod Library'!$B:$B,1,'Pod Library'!$C:$C,"VS1",'Pod Library'!$D:$D,"FS") -> 8 | E6: =SUMIFS('Pod Library'!$K:$K,'Pod Library'!$B:$B,1,'Pod Library'!$C:$C,"VS2",'Pod Library'!$D:$D,"CO") -> 9 | F6: =SUMIFS('Pod Library'!$K:$K,'Pod Library'!$B:$B,1,'Pod Library'!$C:$C,"VS2",'Pod Library'!$D:$D,"FS") -> 9
B7: Year 2 | C7: =SUMIFS('Pod Library'!$K:$K,'Pod Library'!$B:$B,2,'Pod Library'!$C:$C,"VS1",'Pod Library'!$D:$D,"CO") -> 7 | D7: =SUMIFS('Pod Library'!$K:$K,'Pod Library'!$B:$B,2,'Pod Library'!$C:$C,"VS1",'Pod Library'!$D:$D,"FS") -> 7 | E7: =SUMIFS('Pod Library'!$K:$K,'Pod Library'!$B:$B,2,'Pod Library'!$C:$C,"VS2",'Pod Library'!$D:$D,"CO") -> 7 | F7: =SUMIFS('Pod Library'!$K:$K,'Pod Library'!$B:$B,2,'Pod Library'!$C:$C,"VS2",'Pod Library'!$D:$D,"FS") -> 8
B8: Year 3 | C8: =SUMIFS('Pod Library'!$K:$K,'Pod Library'!$B:$B,3,'Pod Library'!$C:$C,"VS1",'Pod Library'!$D:$D,"CO") -> 0 | D8: =SUMIFS('Pod Library'!$K:$K,'Pod Library'!$B:$B,3,'Pod Library'!$C:$C,"VS1",'Pod Library'!$D:$D,"FS") -> 0 | E8: =SUMIFS('Pod Library'!$K:$K,'Pod Library'!$B:$B,3,'Pod Library'!$C:$C,"VS2",'Pod Library'!$D:$D,"CO") -> 7 | F8: =SUMIFS('Pod Library'!$K:$K,'Pod Library'!$B:$B,3,'Pod Library'!$C:$C,"VS2",'Pod Library'!$D:$D,"FS") -> 7
A10: B. HEADCOUNT
B11: Measure | C11: Year 1 | D11: Year 2 | E11: Year 3
B12: People in value-stream pods | C12: =SUMIFS('Seat Ledger'!$L$5:$L$138,'Seat Ledger'!$A$5:$A$138,1,'Seat Ledger'!$B$5:$B$138,"POD") -> 76 | D12: =SUMIFS('Seat Ledger'!$L$5:$L$138,'Seat Ledger'!$A$5:$A$138,2,'Seat Ledger'!$B$5:$B$138,"POD") -> 58 | E12: =SUMIFS('Seat Ledger'!$L$5:$L$138,'Seat Ledger'!$A$5:$A$138,3,'Seat Ledger'!$B$5:$B$138,"POD") -> 42
B13: People in horizontal teams | C13: =SUMIFS('Seat Ledger'!$L$5:$L$138,'Seat Ledger'!$A$5:$A$138,1,'Seat Ledger'!$B$5:$B$138,"HZ") -> 24 | D13: =SUMIFS('Seat Ledger'!$L$5:$L$138,'Seat Ledger'!$A$5:$A$138,2,'Seat Ledger'!$B$5:$B$138,"HZ") -> 21 | E13: =SUMIFS('Seat Ledger'!$L$5:$L$138,'Seat Ledger'!$A$5:$A$138,3,'Seat Ledger'!$B$5:$B$138,"HZ") -> 21
B14: TOTAL PEOPLE | C14: =C12+C13 -> 100 | D14: =D12+D13 -> 79 | E14: =E12+E13 -> 63
B15: Number of pods | C15: =SUMIFS('Pod Plan'!$G:$G,'Pod Plan'!$B:$B,1) -> 9 | D15: =SUMIFS('Pod Plan'!$G:$G,'Pod Plan'!$B:$B,2) -> 8 | E15: =SUMIFS('Pod Plan'!$G:$G,'Pod Plan'!$B:$B,3) -> 6
B16: Average pod size | C16: =IF(C15=0,0,C12/C15) -> 8.4444444 | D16: =IF(D15=0,0,D12/D15) -> 7.25 | E16: =IF(E15=0,0,E12/E15) -> 7
A18: C. SOURCING — MetLife FTE and MGCC are more or less held stable at their current level in every year
B19: Measure | C19: Year 1 | D19: Year 2 | E19: Year 3 | G19: Appendix 3 today
B20: Capgemini (FTC) | C20: =SUMIFS('Seat Ledger'!$L$5:$L$138,'Seat Ledger'!$A$5:$A$138,1,'Seat Ledger'!$I$5:$I$138,"FTC") -> 64 | D20: =SUMIFS('Seat Ledger'!$L$5:$L$138,'Seat Ledger'!$A$5:$A$138,2,'Seat Ledger'!$I$5:$I$138,"FTC") -> 44 | E20: =SUMIFS('Seat Ledger'!$L$5:$L$138,'Seat Ledger'!$A$5:$A$138,3,'Seat Ledger'!$I$5:$I$138,"FTC") -> 28 | G20: 64.7 | H20: Y1
B21: MetLife Japan (FTE) | C21: =SUMIFS('Seat Ledger'!$L$5:$L$138,'Seat Ledger'!$A$5:$A$138,1,'Seat Ledger'!$I$5:$I$138,"FTE") -> 20 | D21: =SUMIFS('Seat Ledger'!$L$5:$L$138,'Seat Ledger'!$A$5:$A$138,2,'Seat Ledger'!$I$5:$I$138,"FTE") -> 19 | E21: =SUMIFS('Seat Ledger'!$L$5:$L$138,'Seat Ledger'!$A$5:$A$138,3,'Seat Ledger'!$I$5:$I$138,"FTE") -> 17 | G21: 18.82 | H21: Y1
B22: MetLife MGCC | C22: =SUMIFS('Seat Ledger'!$L$5:$L$138,'Seat Ledger'!$A$5:$A$138,1,'Seat Ledger'!$I$5:$I$138,"MGCC") -> 16 | D22: =SUMIFS('Seat Ledger'!$L$5:$L$138,'Seat Ledger'!$A$5:$A$138,2,'Seat Ledger'!$I$5:$I$138,"MGCC") -> 16 | E22: =SUMIFS('Seat Ledger'!$L$5:$L$138,'Seat Ledger'!$A$5:$A$138,3,'Seat Ledger'!$I$5:$I$138,"MGCC") -> 18 | G22: 15.99 | H22: Y1
B23: Check — sums to total | C23: =C20+C21+C22-C14 -> 0 | D23: =D20+D21+D22-D14 -> 0 | E23: =E20+E21+E22-E14 -> 0
A25: D. LOCATION
B26: Measure | C26: Year 1 | D26: Year 2 | E26: Year 3
B27: Onshore Tokyo | C27: =SUMIFS('Seat Ledger'!$L$5:$L$138,'Seat Ledger'!$A$5:$A$138,1,'Seat Ledger'!$H$5:$H$138,"ON") -> 45 | D27: =SUMIFS('Seat Ledger'!$L$5:$L$138,'Seat Ledger'!$A$5:$A$138,2,'Seat Ledger'!$H$5:$H$138,"ON") -> 35 | E27: =SUMIFS('Seat Ledger'!$L$5:$L$138,'Seat Ledger'!$A$5:$A$138,3,'Seat Ledger'!$H$5:$H$138,"ON") -> 27
B28: Offshore Hyderabad | C28: =SUMIFS('Seat Ledger'!$L$5:$L$138,'Seat Ledger'!$A$5:$A$138,1,'Seat Ledger'!$H$5:$H$138,"OFF") -> 55 | D28: =SUMIFS('Seat Ledger'!$L$5:$L$138,'Seat Ledger'!$A$5:$A$138,2,'Seat Ledger'!$H$5:$H$138,"OFF") -> 44 | E28: =SUMIFS('Seat Ledger'!$L$5:$L$138,'Seat Ledger'!$A$5:$A$138,3,'Seat Ledger'!$H$5:$H$138,"OFF") -> 36
B29: Whole-team offshore share | C29: =IF(C14=0,0,C28/C14) -> 0.55 | D29: =IF(D14=0,0,D28/D14) -> 0.55696203 | E29: =IF(E14=0,0,E28/E14) -> 0.57142857
B30: Capgemini offshore share (what the ceiling governs) | C30: =IF(C20=0,0,SUMIFS('Seat Ledger'!$L$5:$L$138,'Seat Ledger'!$A$5:$A$138,1,'Seat Ledger'!$H$5:$H$138,"OFF",'Seat Ledger'!$I$5:$I$138,"FTC")/C20) -> 0.640625 | D30: =IF(D20=0,0,SUMIFS('Seat Ledger'!$L$5:$L$138,'Seat Ledger'!$A$5:$A$138,2,'Seat Ledger'!$H$5:$H$138,"OFF",'Seat Ledger'!$I$5:$I$138,"FTC")/D20) -> 0.63636364 | E30: =IF(E20=0,0,SUMIFS('Seat Ledger'!$L$5:$L$138,'Seat Ledger'!$A$5:$A$138,3,'Seat Ledger'!$H$5:$H$138,"OFF",'Seat Ledger'!$I$5:$I$138,"FTC")/E20) -> 0.64285714
A32: E. EXPERIENCE MIX — counted from named seats
B33: Experience band | C33: Year 1 | D33: Year 2 | E33: Year 3 | G33: Y1 % | H33: Y2 % | I33: Y3 %
B34: E1 Associate 0-3 years | C34: =SUMIFS('Seat Ledger'!$L$5:$L$138,'Seat Ledger'!$A$5:$A$138,1,'Seat Ledger'!$G$5:$G$138,"E1") -> 0 | D34: =SUMIFS('Seat Ledger'!$L$5:$L$138,'Seat Ledger'!$A$5:$A$138,2,'Seat Ledger'!$G$5:$G$138,"E1") -> 0 | E34: =SUMIFS('Seat Ledger'!$L$5:$L$138,'Seat Ledger'!$A$5:$A$138,3,'Seat Ledger'!$G$5:$G$138,"E1") -> 0 | G34: =IF(C$14=0,0,C34/C$14) -> 0 | H34: =IF(D$14=0,0,D34/D$14) -> 0 | I34: =IF(E$14=0,0,E34/E$14) -> 0
B35: E2 Engineer 3-6 years | C35: =SUMIFS('Seat Ledger'!$L$5:$L$138,'Seat Ledger'!$A$5:$A$138,1,'Seat Ledger'!$G$5:$G$138,"E2") -> 29 | D35: =SUMIFS('Seat Ledger'!$L$5:$L$138,'Seat Ledger'!$A$5:$A$138,2,'Seat Ledger'!$G$5:$G$138,"E2") -> 2 | E35: =SUMIFS('Seat Ledger'!$L$5:$L$138,'Seat Ledger'!$A$5:$A$138,3,'Seat Ledger'!$G$5:$G$138,"E2") -> 6 | G35: =IF(C$14=0,0,C35/C$14) -> 0.29 | H35: =IF(D$14=0,0,D35/D$14) -> 0.025316456 | I35: =IF(E$14=0,0,E35/E$14) -> 0.095238095
B36: E3 Senior 6-10 years | C36: =SUMIFS('Seat Ledger'!$L$5:$L$138,'Seat Ledger'!$A$5:$A$138,1,'Seat Ledger'!$G$5:$G$138,"E3") -> 33 | D36: =SUMIFS('Seat Ledger'!$L$5:$L$138,'Seat Ledger'!$A$5:$A$138,2,'Seat Ledger'!$G$5:$G$138,"E3") -> 40 | E36: =SUMIFS('Seat Ledger'!$L$5:$L$138,'Seat Ledger'!$A$5:$A$138,3,'Seat Ledger'!$G$5:$G$138,"E3") -> 27 | G36: =IF(C$14=0,0,C36/C$14) -> 0.33 | H36: =IF(D$14=0,0,D36/D$14) -> 0.50632911 | I36: =IF(E$14=0,0,E36/E$14) -> 0.42857143
B37: E4 Lead / specialist 10-15 years | C37: =SUMIFS('Seat Ledger'!$L$5:$L$138,'Seat Ledger'!$A$5:$A$138,1,'Seat Ledger'!$G$5:$G$138,"E4") -> 31 | D37: =SUMIFS('Seat Ledger'!$L$5:$L$138,'Seat Ledger'!$A$5:$A$138,2,'Seat Ledger'!$G$5:$G$138,"E4") -> 30 | E37: =SUMIFS('Seat Ledger'!$L$5:$L$138,'Seat Ledger'!$A$5:$A$138,3,'Seat Ledger'!$G$5:$G$138,"E4") -> 22 | G37: =IF(C$14=0,0,C37/C$14) -> 0.31 | H37: =IF(D$14=0,0,D37/D$14) -> 0.37974684 | I37: =IF(E$14=0,0,E37/E$14) -> 0.34920635
B38: E5 Principal / architect 15 years+ | C38: =SUMIFS('Seat Ledger'!$L$5:$L$138,'Seat Ledger'!$A$5:$A$138,1,'Seat Ledger'!$G$5:$G$138,"E5") -> 7 | D38: =SUMIFS('Seat Ledger'!$L$5:$L$138,'Seat Ledger'!$A$5:$A$138,2,'Seat Ledger'!$G$5:$G$138,"E5") -> 7 | E38: =SUMIFS('Seat Ledger'!$L$5:$L$138,'Seat Ledger'!$A$5:$A$138,3,'Seat Ledger'!$G$5:$G$138,"E5") -> 8 | G38: =IF(C$14=0,0,C38/C$14) -> 0.07 | H38: =IF(D$14=0,0,D38/D$14) -> 0.088607595 | I38: =IF(E$14=0,0,E38/E$14) -> 0.12698413
B39: Senior share (E4 + E5) | C39: =IF(C14=0,0,(C37+C38)/C14) -> 0.38 | D39: =IF(D14=0,0,(D37+D38)/D14) -> 0.46835443 | E39: =IF(E14=0,0,(E37+E38)/E14) -> 0.47619048
B40: Talent shape | C40: =IF((C37+C38)/C14>0.58,"Obelisk",IF((C37+C38)/C14>0.42,"Diamond","Pyramid")) -> Pyramid | D40: =IF((D37+D38)/D14>0.58,"Obelisk",IF((D37+D38)/D14>0.42,"Diamond","Pyramid")) -> Diamond | E40: =IF((E37+E38)/E14>0.58,"Obelisk",IF((E37+E38)/E14>0.42,"Diamond","Pyramid")) -> Diamond
A42: F. SKILL DISTRIBUTION
B43: Skill family | C43: Year 1 | D43: Year 2 | E43: Year 3 | G43: Y1 % | H43: Y2 % | I43: Y3 %
B44: Leadership & delivery management | C44: =SUMIFS('Seat Ledger'!$L$5:$L$138,'Seat Ledger'!$A$5:$A$138,1,'Seat Ledger'!$F$5:$F$138,"LEAD") -> 21 | D44: =SUMIFS('Seat Ledger'!$L$5:$L$138,'Seat Ledger'!$A$5:$A$138,2,'Seat Ledger'!$F$5:$F$138,"LEAD") -> 19 | E44: =SUMIFS('Seat Ledger'!$L$5:$L$138,'Seat Ledger'!$A$5:$A$138,3,'Seat Ledger'!$F$5:$F$138,"LEAD") -> 15 | G44: =IF(C$14=0,0,C44/C$14) -> 0.21 | H44: =IF(D$14=0,0,D44/D$14) -> 0.24050633 | I44: =IF(E$14=0,0,E44/E$14) -> 0.23809524
B45: Business analysis & domain | C45: =SUMIFS('Seat Ledger'!$L$5:$L$138,'Seat Ledger'!$A$5:$A$138,1,'Seat Ledger'!$F$5:$F$138,"BA") -> 9 | D45: =SUMIFS('Seat Ledger'!$L$5:$L$138,'Seat Ledger'!$A$5:$A$138,2,'Seat Ledger'!$F$5:$F$138,"BA") -> 6 | E45: =SUMIFS('Seat Ledger'!$L$5:$L$138,'Seat Ledger'!$A$5:$A$138,3,'Seat Ledger'!$F$5:$F$138,"BA") -> 3 | G45: =IF(C$14=0,0,C45/C$14) -> 0.09 | H45: =IF(D$14=0,0,D45/D$14) -> 0.075949367 | I45: =IF(E$14=0,0,E45/E$14) -> 0.047619048
B46: Development | C46: =SUMIFS('Seat Ledger'!$L$5:$L$138,'Seat Ledger'!$A$5:$A$138,1,'Seat Ledger'!$F$5:$F$138,"DEV") -> 31 | D46: =SUMIFS('Seat Ledger'!$L$5:$L$138,'Seat Ledger'!$A$5:$A$138,2,'Seat Ledger'!$F$5:$F$138,"DEV") -> 21 | E46: =SUMIFS('Seat Ledger'!$L$5:$L$138,'Seat Ledger'!$A$5:$A$138,3,'Seat Ledger'!$F$5:$F$138,"DEV") -> 10 | G46: =IF(C$14=0,0,C46/C$14) -> 0.31 | H46: =IF(D$14=0,0,D46/D$14) -> 0.26582278 | I46: =IF(E$14=0,0,E46/E$14) -> 0.15873016
B47: Engineering, AI & platform | C47: =SUMIFS('Seat Ledger'!$L$5:$L$138,'Seat Ledger'!$A$5:$A$138,1,'Seat Ledger'!$F$5:$F$138,"ENG") -> 20 | D47: =SUMIFS('Seat Ledger'!$L$5:$L$138,'Seat Ledger'!$A$5:$A$138,2,'Seat Ledger'!$F$5:$F$138,"ENG") -> 21 | E47: =SUMIFS('Seat Ledger'!$L$5:$L$138,'Seat Ledger'!$A$5:$A$138,3,'Seat Ledger'!$F$5:$F$138,"ENG") -> 19 | G47: =IF(C$14=0,0,C47/C$14) -> 0.2 | H47: =IF(D$14=0,0,D47/D$14) -> 0.26582278 | I47: =IF(E$14=0,0,E47/E$14) -> 0.3015873
B48: Test & data quality | C48: =SUMIFS('Seat Ledger'!$L$5:$L$138,'Seat Ledger'!$A$5:$A$138,1,'Seat Ledger'!$F$5:$F$138,"TEST") -> 14 | D48: =SUMIFS('Seat Ledger'!$L$5:$L$138,'Seat Ledger'!$A$5:$A$138,2,'Seat Ledger'!$F$5:$F$138,"TEST") -> 10 | E48: =SUMIFS('Seat Ledger'!$L$5:$L$138,'Seat Ledger'!$A$5:$A$138,3,'Seat Ledger'!$F$5:$F$138,"TEST") -> 14 | G48: =IF(C$14=0,0,C48/C$14) -> 0.14 | H48: =IF(D$14=0,0,D48/D$14) -> 0.12658228 | I48: =IF(E$14=0,0,E48/E$14) -> 0.22222222
B49: Operations & support | C49: =SUMIFS('Seat Ledger'!$L$5:$L$138,'Seat Ledger'!$A$5:$A$138,1,'Seat Ledger'!$F$5:$F$138,"OPS") -> 5 | D49: =SUMIFS('Seat Ledger'!$L$5:$L$138,'Seat Ledger'!$A$5:$A$138,2,'Seat Ledger'!$F$5:$F$138,"OPS") -> 2 | E49: =SUMIFS('Seat Ledger'!$L$5:$L$138,'Seat Ledger'!$A$5:$A$138,3,'Seat Ledger'!$F$5:$F$138,"OPS") -> 2 | G49: =IF(C$14=0,0,C49/C$14) -> 0.05 | H49: =IF(D$14=0,0,D49/D$14) -> 0.025316456 | I49: =IF(E$14=0,0,E49/E$14) -> 0.031746032
B50: Check — sums to total | C50: =SUM(C44:C49)-C14 -> 0 | D50: =SUM(D44:D49)-D14 -> 0 | E50: =SUM(E44:E49)-E14 -> 0
A52: G. BY VALUE STREAM AND HORIZONTAL TEAM
B53: Unit | C53: Year 1 | D53: Year 2 | E53: Year 3
B54: VS1 Informatica | C54: =SUMIFS('Seat Ledger'!$L$5:$L$138,'Seat Ledger'!$A$5:$A$138,1,'Seat Ledger'!$C$5:$C$138,"VS1") -> 40 | D54: =SUMIFS('Seat Ledger'!$L$5:$L$138,'Seat Ledger'!$A$5:$A$138,2,'Seat Ledger'!$C$5:$C$138,"VS1") -> 21 | E54: =SUMIFS('Seat Ledger'!$L$5:$L$138,'Seat Ledger'!$A$5:$A$138,3,'Seat Ledger'!$C$5:$C$138,"VS1") -> 0
B55: VS2 Azure Synapse | C55: =SUMIFS('Seat Ledger'!$L$5:$L$138,'Seat Ledger'!$A$5:$A$138,1,'Seat Ledger'!$C$5:$C$138,"VS2") -> 36 | D55: =SUMIFS('Seat Ledger'!$L$5:$L$138,'Seat Ledger'!$A$5:$A$138,2,'Seat Ledger'!$C$5:$C$138,"VS2") -> 37 | E55: =SUMIFS('Seat Ledger'!$L$5:$L$138,'Seat Ledger'!$A$5:$A$138,3,'Seat Ledger'!$C$5:$C$138,"VS2") -> 42
B56: H1 Platform Operations & Data Reliability | C56: =SUMIFS('Seat Ledger'!$L$5:$L$138,'Seat Ledger'!$A$5:$A$138,1,'Seat Ledger'!$C$5:$C$138,"H1") -> 12 | D56: =SUMIFS('Seat Ledger'!$L$5:$L$138,'Seat Ledger'!$A$5:$A$138,2,'Seat Ledger'!$C$5:$C$138,"H1") -> 10 | E56: =SUMIFS('Seat Ledger'!$L$5:$L$138,'Seat Ledger'!$A$5:$A$138,3,'Seat Ledger'!$C$5:$C$138,"H1") -> 9
B57: H2 Data Quality, Test & Environments | C57: =SUMIFS('Seat Ledger'!$L$5:$L$138,'Seat Ledger'!$A$5:$A$138,1,'Seat Ledger'!$C$5:$C$138,"H2") -> 6 | D57: =SUMIFS('Seat Ledger'!$L$5:$L$138,'Seat Ledger'!$A$5:$A$138,2,'Seat Ledger'!$C$5:$C$138,"H2") -> 6 | E57: =SUMIFS('Seat Ledger'!$L$5:$L$138,'Seat Ledger'!$A$5:$A$138,3,'Seat Ledger'!$C$5:$C$138,"H2") -> 7
B58: H3 Architecture, Release Train & Governance | C58: =SUMIFS('Seat Ledger'!$L$5:$L$138,'Seat Ledger'!$A$5:$A$138,1,'Seat Ledger'!$C$5:$C$138,"H3") -> 6 | D58: =SUMIFS('Seat Ledger'!$L$5:$L$138,'Seat Ledger'!$A$5:$A$138,2,'Seat Ledger'!$C$5:$C$138,"H3") -> 5 | E58: =SUMIFS('Seat Ledger'!$L$5:$L$138,'Seat Ledger'!$A$5:$A$138,3,'Seat Ledger'!$C$5:$C$138,"H3") -> 5
B59: TOTAL | C59: =SUM(C54:C58) -> 100 | D59: =SUM(D54:D58) -> 79 | E59: =SUM(E54:E58) -> 63

Sheet Glidepath & 50-50
A1: Glidepath — and why this domain needs no transfer of employment
A2: Productivity alone crosses 50:50 during Year 3 without any transfer of employment. The Contract Management problem runs the other way.
A4: A. BASELINE
B5: Measure | C5: Value
B6: Applications | C6: ='Logic Tree'!C6 -> 3
B7: Total effort (units) | C7: ='Logic Tree'!C7 -> 100.76497
B8: Current Capgemini FTC | C8: ='Logic Tree'!C8 -> 64.704594
B9: Current MetLife FTE | C9: ='Logic Tree'!C9 -> 18.825
B10: Current MetLife MGCC | C10: ='Logic Tree'!C10 -> 15.991667
B11: Ratio today FTC : MetLife | C11: =C8/C7 -> 0.64213381 | G11: Data Infra domain starts at 64:36 — MGCC is already here. And CG also partially supports
B12: Appendix 3 Year-3 target FTC (from Inventory) | C12: =SUMIFS(Inventory!$S:$S,Inventory!$E:$E,'Logic Tree'!$C$5) -> 50.382484 | D12: Target FTE/MGCC | E12: =SUMIFS(Inventory!$T:$T,Inventory!$E:$E,'Logic Tree'!$C$5) -> 50.382484 | G12: The two Appendix 3 targets are equal by construction — the client plan halves every application.
A14: B. PRODUCTIVITY — target vs delivered
B15: Measure | C15: Year 1 | D15: Year 2 | E15: Year 3
B16: Headcount delivered by the pod design | C16: ='Team Build-Up'!C14 -> 100 | D16: ='Team Build-Up'!D14 -> 79 | E16: ='Team Build-Up'!E14 -> 63 | G16: Year 1 absorbs the transition. Transition here is fast — modern stack, artefacts exist — but the substrate build still consumes it.
B17: Delivered productivity vs baseline | C17: =IF($C$7=0,0,1-'Team Build-Up'!C14/$C$7) -> 0.007591614 | D17: =IF($C$7=0,0,1-'Team Build-Up'!D14/$C$7) -> 0.21599738 | E17: =IF($C$7=0,0,1-'Team Build-Up'!E14/$C$7) -> 0.37478272
B18: Target from the logic tree | C18: ='Logic Tree'!C57 -> 0.12101505 | D18: ='Logic Tree'!D57 -> 0.25140116 | E18: ='Logic Tree'!E57 -> 0.28595974
B19: Transition & enablement drag | C19: =C18-C17 -> 0.11342344 | D19: =D18-D17 -> 0.03540378 | E19: =E18-E17 -> -0.08882298
A21: C. OFFSHORE — measured on Capgemini-delivered effort
B22: Measure | C22: Year 1 | D22: Year 2 | E22: Year 3
B23: Delivered — Capgemini offshore share | C23: ='Team Build-Up'!C30 -> 0.640625 | D23: ='Team Build-Up'!D30 -> 0.63636364 | E23: ='Team Build-Up'!E30 -> 0.64285714
B24: Target from the logic tree | C24: ='Logic Tree'!D65 -> 0.55481096 | D24: ='Logic Tree'!E65 -> 0.6509782 | E24: ='Logic Tree'!F65 -> 0.70276055
B25: Whole-team offshore share (includes MGCC) | C25: ='Team Build-Up'!C29 -> 0.55 | D25: ='Team Build-Up'!D29 -> 0.55696203 | E25: ='Team Build-Up'!E29 -> 0.57142857
A27: D. THE 50:50 POSITION — no transfer of employment in this domain
B28: MetLife FTE and MGCC are held constant. As the domain shrinks on productivity, their share rises on its own.
B29: Measure | C29: Year 1 | D29: Year 2 | E29: Year 3
B30: Total people | C30: ='Team Build-Up'!C14 -> 100 | D30: ='Team Build-Up'!D14 -> 79 | E30: ='Team Build-Up'!E14 -> 63
B31: Capgemini FTC | C31: ='Team Build-Up'!C20 -> 64 | D31: ='Team Build-Up'!D20 -> 44 | E31: ='Team Build-Up'!E20 -> 28
B32: MetLife FTE | C32: ='Team Build-Up'!C21 -> 20 | D32: ='Team Build-Up'!D21 -> 19 | E32: ='Team Build-Up'!E21 -> 17
B33: MetLife MGCC | C33: ='Team Build-Up'!C22 -> 16 | D33: ='Team Build-Up'!D22 -> 16 | E33: ='Team Build-Up'!E22 -> 18
B34: MetLife side total | C34: =C32+C33 -> 36 | D34: =D32+D33 -> 35 | E34: =E32+E33 -> 35
B35: Transferred this year (Logic Tree) | C35: ='Logic Tree'!C71 -> 0 | D35: ='Logic Tree'!D71 -> 0 | E35: ='Logic Tree'!E71 -> 0
B36: RATIO — Capgemini share | C36: =IF(C30=0,0,(C31-C35)/C30) -> 0.64 | D36: =IF(D30=0,0,(D31-D35)/D30) -> 0.55696203 | E36: =IF(E30=0,0,(E31-E35)/E30) -> 0.44444444
B37: Transfer that would be needed for exactly 50:50 | C37: =C30/2-C34 -> 14 | D37: =D30/2-D34 -> 4.5 | E37: =E30/2-E34 -> -3.5
B38: A NEGATIVE number above means the ratio has already passed 50:50 without any transfer.
A40: E. THE DECISION THIS DOMAIN RAISES INSTEAD
B41: • Data Infrastructure needs ~15 people moved to MetLife to reach 50:50. This domain reaches it on productivity alone, during Year 3 — Year 2 still sits just short at 56:44.
B42: • By Year 3 MetLife holds ~56% of a 65-person domain. Roughly 3-4 MetLife-side people are surplus to the ratio and could be redeployed to a domain that needs them.
B43: • Do not offer a transfer here. Offer the reverse: a redeployment plan that moves MetLife capacity out of Data Infrastructure and into the archetype-D domains where the 50:50 gap is real.
B44: • Both Informatica applications are Priority Transfer Targets, so the bedrock would route them to MGCC. The platform is being retired, so that transfer builds a capability MetLife will not keep. Run it to sunset instead and point MGCC growth at Synapse.

Sheet Cost & Commercial
A1: Cost and commercial position — relative index pending the approved rate card
A2: Onshore Tokyo band E2 = 1.00. Unit cost divides by the frozen baseline effort, because the scope MetLife buys does not change.
A4: A. TOTAL COST OF DELIVERING THE DOMAIN
B5: Measure | C5: Year 1 | D5: Year 2 | E5: Year 3
B6: Total cost index | C6: =SUMIFS('Seat Ledger'!$M$5:$M$138,'Seat Ledger'!$A$5:$A$138,1) -> 102.76 | D6: =SUMIFS('Seat Ledger'!$M$5:$M$138,'Seat Ledger'!$A$5:$A$138,2) -> 86.33 | E6: =SUMIFS('Seat Ledger'!$M$5:$M$138,'Seat Ledger'!$A$5:$A$138,3) -> 68.89
B7: Headcount | C7: ='Team Build-Up'!C14 -> 100 | D7: ='Team Build-Up'!D14 -> 79 | E7: ='Team Build-Up'!E14 -> 63
B8: Average cost per head | C8: =IF(C7=0,0,C6/C7) -> 1.0276 | D8: =IF(D7=0,0,D6/D7) -> 1.0927848 | E8: =IF(E7=0,0,E6/E7) -> 1.0934921 | G8: Average cost per head rises as the shape gets more senior. Offshore movement is what stops it rising faster.
B9: Cost per unit of frozen scope | C9: =IF('Glidepath & 50-50'!$C$7=0,0,C6/'Glidepath & 50-50'!$C$7) -> 1.0197989 | D9: =IF('Glidepath & 50-50'!$C$7=0,0,D6/'Glidepath & 50-50'!$C$7) -> 0.85674616 | E9: =IF('Glidepath & 50-50'!$C$7=0,0,E6/'Glidepath & 50-50'!$C$7) -> 0.68367014
B10: Unit cost reduction vs Year 1 | C10: =IF($C$9=0,0,1-C9/$C$9) -> 0 | D10: =IF($C$9=0,0,1-D9/$C$9) -> 0.15988712 | E10: =IF($C$9=0,0,1-E9/$C$9) -> 0.32960296
A12: B. WHAT MOVED THE UNIT COST — decomposition
B13: Effect | C13: Year 1 → Year 2 | D13: Year 1 → Year 3
B14: Headcount reduction (productivity) | C14: =IF($C$7=0,0,D7/$C$7-1) -> -0.21 | D14: =IF($C$7=0,0,E7/$C$7-1) -> -0.37
B15: Change in average cost per head (mix) | C15: =IF($C$8=0,0,D8/$C$8-1) -> 0.063434031 | D15: =IF($C$8=0,0,E8/$C$8-1) -> 0.064122288
B16: Total change in unit cost | C16: =IF($C$9=0,0,D9/$C$9-1) -> -0.15988712 | D16: =IF($C$9=0,0,E9/$C$9-1) -> -0.32960296 | G16: The two effects multiply, they do not add: (1+headcount change) x (1+mix change) - 1.
A18: C. CAPGEMINI POSITION
B19: Measure | C19: Year 1 | D19: Year 2 | E19: Year 3
B20: Capgemini heads | C20: ='Team Build-Up'!C20 -> 64 | D20: ='Team Build-Up'!D20 -> 44 | E20: ='Team Build-Up'!E20 -> 28
B21: Capgemini cost index | C21: =SUMIFS('Seat Ledger'!$M$5:$M$138,'Seat Ledger'!$A$5:$A$138,1,'Seat Ledger'!$I$5:$I$138,"FTC") -> 53.32 | D21: =SUMIFS('Seat Ledger'!$M$5:$M$138,'Seat Ledger'!$A$5:$A$138,2,'Seat Ledger'!$I$5:$I$138,"FTC") -> 40.36 | E21: =SUMIFS('Seat Ledger'!$M$5:$M$138,'Seat Ledger'!$A$5:$A$138,3,'Seat Ledger'!$I$5:$I$138,"FTC") -> 25.76
B22: Capgemini position vs Year 1 | C22: =IF($C$21=0,0,C21/$C$21-1) -> 0 | D22: =IF($C$21=0,0,D21/$C$21-1) -> -0.24306077 | E22: =IF($C$21=0,0,E21/$C$21-1) -> -0.51687922
A24: D. COST BY LOCATION AND BAND
B25: Split | C25: Year 1 | D25: Year 2 | E25: Year 3
B26: Onshore Tokyo — cost index | C26: =SUMIFS('Seat Ledger'!$M$5:$M$138,'Seat Ledger'!$A$5:$A$138,1,'Seat Ledger'!$H$5:$H$138,"ON") -> 82.3 | D26: =SUMIFS('Seat Ledger'!$M$5:$M$138,'Seat Ledger'!$A$5:$A$138,2,'Seat Ledger'!$H$5:$H$138,"ON") -> 66.65 | E26: =SUMIFS('Seat Ledger'!$M$5:$M$138,'Seat Ledger'!$A$5:$A$138,3,'Seat Ledger'!$H$5:$H$138,"ON") -> 53.05
B27: Offshore Hyderabad — cost index | C27: =SUMIFS('Seat Ledger'!$M$5:$M$138,'Seat Ledger'!$A$5:$A$138,1,'Seat Ledger'!$H$5:$H$138,"OFF") -> 20.46 | D27: =SUMIFS('Seat Ledger'!$M$5:$M$138,'Seat Ledger'!$A$5:$A$138,2,'Seat Ledger'!$H$5:$H$138,"OFF") -> 19.68 | E27: =SUMIFS('Seat Ledger'!$M$5:$M$138,'Seat Ledger'!$A$5:$A$138,3,'Seat Ledger'!$H$5:$H$138,"OFF") -> 15.84
B28: Onshore share of cost | C28: =IF((C26+C27)=0,0,C26/(C26+C27)) -> 0.80089529 | D28: =IF((D26+D27)=0,0,D26/(D26+D27)) -> 0.77203753 | E28: =IF((E26+E27)=0,0,E26/(E26+E27)) -> 0.77006822
B30: E1 — cost index | C30: =SUMIFS('Seat Ledger'!$M$5:$M$138,'Seat Ledger'!$A$5:$A$138,1,'Seat Ledger'!$G$5:$G$138,"E1") -> 0 | D30: =SUMIFS('Seat Ledger'!$M$5:$M$138,'Seat Ledger'!$A$5:$A$138,2,'Seat Ledger'!$G$5:$G$138,"E1") -> 0 | E30: =SUMIFS('Seat Ledger'!$M$5:$M$138,'Seat Ledger'!$A$5:$A$138,3,'Seat Ledger'!$G$5:$G$138,"E1") -> 0
B31: E2 — cost index | C31: =SUMIFS('Seat Ledger'!$M$5:$M$138,'Seat Ledger'!$A$5:$A$138,1,'Seat Ledger'!$G$5:$G$138,"E2") -> 9.4 | D31: =SUMIFS('Seat Ledger'!$M$5:$M$138,'Seat Ledger'!$A$5:$A$138,2,'Seat Ledger'!$G$5:$G$138,"E2") -> 0.6 | E31: =SUMIFS('Seat Ledger'!$M$5:$M$138,'Seat Ledger'!$A$5:$A$138,3,'Seat Ledger'!$G$5:$G$138,"E2") -> 1.8
B32: E3 — cost index | C32: =SUMIFS('Seat Ledger'!$M$5:$M$138,'Seat Ledger'!$A$5:$A$138,1,'Seat Ledger'!$G$5:$G$138,"E3") -> 23.16 | D32: =SUMIFS('Seat Ledger'!$M$5:$M$138,'Seat Ledger'!$A$5:$A$138,2,'Seat Ledger'!$G$5:$G$138,"E3") -> 22.38 | E32: =SUMIFS('Seat Ledger'!$M$5:$M$138,'Seat Ledger'!$A$5:$A$138,3,'Seat Ledger'!$G$5:$G$138,"E3") -> 15.99
B33: E4 — cost index | C33: =SUMIFS('Seat Ledger'!$M$5:$M$138,'Seat Ledger'!$A$5:$A$138,1,'Seat Ledger'!$G$5:$G$138,"E4") -> 52.35 | D33: =SUMIFS('Seat Ledger'!$M$5:$M$138,'Seat Ledger'!$A$5:$A$138,2,'Seat Ledger'!$G$5:$G$138,"E4") -> 45.5 | E33: =SUMIFS('Seat Ledger'!$M$5:$M$138,'Seat Ledger'!$A$5:$A$138,3,'Seat Ledger'!$G$5:$G$138,"E4") -> 30.7
B34: E5 — cost index | C34: =SUMIFS('Seat Ledger'!$M$5:$M$138,'Seat Ledger'!$A$5:$A$138,1,'Seat Ledger'!$G$5:$G$138,"E5") -> 17.85 | D34: =SUMIFS('Seat Ledger'!$M$5:$M$138,'Seat Ledger'!$A$5:$A$138,2,'Seat Ledger'!$G$5:$G$138,"E5") -> 17.85 | E34: =SUMIFS('Seat Ledger'!$M$5:$M$138,'Seat Ledger'!$A$5:$A$138,3,'Seat Ledger'!$G$5:$G$138,"E5") -> 20.4

Sheet Unit Cost Sensitivity
A1: Unit cost sensitivity — how experience mix, offshore share and productivity interact
A2: Three levers move unit cost. Productivity scales it linearly; the other two fight each other inside the average cost per head.
A4: A. THE MODEL — unit cost = calibration × (1 − productivity) × average cost per head
B5: average cost per head = offshore × [senior×OFF_SR + (1−senior)×OFF_JM] + onshore × [senior×ON_SR + (1−senior)×ON_JM]
A7: B. TIER COST PARAMETERS — derived from the Year-3 roster
B8: Tier | C8: Onshore Tokyo | D8: Offshore Hyderabad
B9: Junior / mid (E1–E3) | C9: =IFERROR((SUMIFS('Seat Ledger'!$M$5:$M$138,'Seat Ledger'!$A$5:$A$138,3,'Seat Ledger'!$H$5:$H$138,"ON",'Seat Ledger'!$G$5:$G$138,"E1") + SUMIFS('Seat Ledger'!$M$5:$M$138,'Seat Ledger'!$A$5:$A$138,3,'Seat Ledger'!$H$5:$H$138,"ON",'Seat Ledger'!$G$5:$G$138,"E2") + SUMIFS('Seat Ledger'!$M$5:$M$138,'Seat Ledger'!$A$5:$A$138,3,'Seat Ledger'!$H$5:$H$138,"ON",'Seat Ledger'!$G$5:$G$138,"E3"))/(SUMIFS('Seat Ledger'!$L$5:$L$138,'Seat Ledger'!$A$5:$A$138,3,'Seat Ledger'!$H$5:$H$138,"ON",'Seat Ledger'!$G$5:$G$138,"E1") + SUMIFS('Seat Ledger'!$L$5:$L$138,'Seat Ledger'!$A$5:$A$138,3,'Seat Ledger'!$H$5:$H$138,"ON",'Seat Ledger'!$G$5:$G$138,"E2") + SUMIFS('Seat Ledger'!$L$5:$L$138,'Seat Ledger'!$A$5:$A$138,3,'Seat Ledger'!$H$5:$H$138,"ON",'Seat Ledger'!$G$5:$G$138,"E3")),0) -> 1.35 | D9: =IFERROR((SUMIFS('Seat Ledger'!$M$5:$M$138,'Seat Ledger'!$A$5:$A$138,3,'Seat Ledger'!$H$5:$H$138,"OFF",'Seat Ledger'!$G$5:$G$138,"E1") + SUMIFS('Seat Ledger'!$M$5:$M$138,'Seat Ledger'!$A$5:$A$138,3,'Seat Ledger'!$H$5:$H$138,"OFF",'Seat Ledger'!$G$5:$G$138,"E2") + SUMIFS('Seat Ledger'!$M$5:$M$138,'Seat Ledger'!$A$5:$A$138,3,'Seat Ledger'!$H$5:$H$138,"OFF",'Seat Ledger'!$G$5:$G$138,"E3"))/(SUMIFS('Seat Ledger'!$L$5:$L$138,'Seat Ledger'!$A$5:$A$138,3,'Seat Ledger'!$H$5:$H$138,"OFF",'Seat Ledger'!$G$5:$G$138,"E1") + SUMIFS('Seat Ledger'!$L$5:$L$138,'Seat Ledger'!$A$5:$A$138,3,'Seat Ledger'!$H$5:$H$138,"OFF",'Seat Ledger'!$G$5:$G$138,"E2") + SUMIFS('Seat Ledger'!$L$5:$L$138,'Seat Ledger'!$A$5:$A$138,3,'Seat Ledger'!$H$5:$H$138,"OFF",'Seat Ledger'!$G$5:$G$138,"E3")),0) -> 0.39428571
B10: Senior (E4–E5) | C10: =IFERROR((SUMIFS('Seat Ledger'!$M$5:$M$138,'Seat Ledger'!$A$5:$A$138,3,'Seat Ledger'!$H$5:$H$138,"ON",'Seat Ledger'!$G$5:$G$138,"E4") + SUMIFS('Seat Ledger'!$M$5:$M$138,'Seat Ledger'!$A$5:$A$138,3,'Seat Ledger'!$H$5:$H$138,"ON",'Seat Ledger'!$G$5:$G$138,"E5"))/(SUMIFS('Seat Ledger'!$L$5:$L$138,'Seat Ledger'!$A$5:$A$138,3,'Seat Ledger'!$H$5:$H$138,"ON",'Seat Ledger'!$G$5:$G$138,"E4") + SUMIFS('Seat Ledger'!$L$5:$L$138,'Seat Ledger'!$A$5:$A$138,3,'Seat Ledger'!$H$5:$H$138,"ON",'Seat Ledger'!$G$5:$G$138,"E5")),0) -> 2.1045455 | D10: =IFERROR((SUMIFS('Seat Ledger'!$M$5:$M$138,'Seat Ledger'!$A$5:$A$138,3,'Seat Ledger'!$H$5:$H$138,"OFF",'Seat Ledger'!$G$5:$G$138,"E4") + SUMIFS('Seat Ledger'!$M$5:$M$138,'Seat Ledger'!$A$5:$A$138,3,'Seat Ledger'!$H$5:$H$138,"OFF",'Seat Ledger'!$G$5:$G$138,"E5"))/(SUMIFS('Seat Ledger'!$L$5:$L$138,'Seat Ledger'!$A$5:$A$138,3,'Seat Ledger'!$H$5:$H$138,"OFF",'Seat Ledger'!$G$5:$G$138,"E4") + SUMIFS('Seat Ledger'!$L$5:$L$138,'Seat Ledger'!$A$5:$A$138,3,'Seat Ledger'!$H$5:$H$138,"OFF",'Seat Ledger'!$G$5:$G$138,"E5")),0) -> 0.6
J11: The two-tier approximation collapses five bands into two, so it needs a calibration constant to tie to the full roster.
A13: C. BASE CASE — read from the model
B14: Measure | C14: Year 1 | D14: Year 2 | E14: Year 3
B15: Productivity vs baseline | C15: ='Glidepath & 50-50'!C17 -> 0.007591614 | D15: ='Glidepath & 50-50'!D17 -> 0.21599738 | E15: ='Glidepath & 50-50'!E17 -> 0.37478272
B16: Whole-team offshore share | C16: ='Team Build-Up'!C29 -> 0.55 | D16: ='Team Build-Up'!D29 -> 0.55696203 | E16: ='Team Build-Up'!E29 -> 0.57142857
B17: Senior share (E4+E5) | C17: ='Team Build-Up'!C39 -> 0.38 | D17: ='Team Build-Up'!D39 -> 0.46835443 | E17: ='Team Build-Up'!E39 -> 0.47619048
B18: Unit cost index — actual, from the roster | C18: ='Cost & Commercial'!C9 -> 1.0197989 | D18: ='Cost & Commercial'!D9 -> 0.85674616 | E18: ='Cost & Commercial'!E9 -> 0.68367014
B19: Unit cost index — two-tier formula | C19: =(1-C15)*(C16*(C17*$D$10+(1-C17)*$D$9)+(1-C16)*(C17*$C$10+(1-C17)*$C$9)) -> 0.98881458 | D19: =(1-D15)*(D16*(D17*$D$10+(1-D17)*$D$9)+(1-D16)*(D17*$C$10+(1-D17)*$C$9)) -> 0.80590173 | E19: =(1-E15)*(E16*(E17*$D$10+(1-E17)*$D$9)+(1-E16)*(E17*$C$10+(1-E17)*$C$9)) -> 0.63387223
B20: CALIBRATION k = actual ÷ formula, at Year 3 | E20: =IF(E19=0,1,E18/E19) -> 1.0785614 | J20: Applied to every cell in the grids below so the base case ties exactly.
A22: D. GRID 1 — offshore share × productivity, holding the Year-3 senior share
B23: Unit cost index at the Year-3 senior share of 54%. The Year-3 base case is 0.642.
B24: Offshore ↓ Productivity → | C24: 0.25 | D24: 0.3 | E24: 0.35 | F24: 0.4 | G24: 0.45 | H24: 0.5
B25: 0.35 | C25: =$E$20*(1-C$24)*($B25*($E$17*$D$10+(1-$E$17)*$D$9)+(1-$B25)*($E$17*$C$10+(1-$E$17)*$C$9)) -> 1.0381171 | D25: =$E$20*(1-D$24)*($B25*($E$17*$D$10+(1-$E$17)*$D$9)+(1-$B25)*($E$17*$C$10+(1-$E$17)*$C$9)) -> 0.96890932 | E25: =$E$20*(1-E$24)*($B25*($E$17*$D$10+(1-$E$17)*$D$9)+(1-$B25)*($E$17*$C$10+(1-$E$17)*$C$9)) -> 0.89970151 | F25: =$E$20*(1-F$24)*($B25*($E$17*$D$10+(1-$E$17)*$D$9)+(1-$B25)*($E$17*$C$10+(1-$E$17)*$C$9)) -> 0.83049371 | G25: =$E$20*(1-G$24)*($B25*($E$17*$D$10+(1-$E$17)*$D$9)+(1-$B25)*($E$17*$C$10+(1-$E$17)*$C$9)) -> 0.7612859 | H25: =$E$20*(1-H$24)*($B25*($E$17*$D$10+(1-$E$17)*$D$9)+(1-$B25)*($E$17*$C$10+(1-$E$17)*$C$9)) -> 0.69207809
B26: 0.45 | C26: =$E$20*(1-C$24)*($B26*($E$17*$D$10+(1-$E$17)*$D$9)+(1-$B26)*($E$17*$C$10+(1-$E$17)*$C$9)) -> 0.93966638 | D26: =$E$20*(1-D$24)*($B26*($E$17*$D$10+(1-$E$17)*$D$9)+(1-$B26)*($E$17*$C$10+(1-$E$17)*$C$9)) -> 0.87702196 | E26: =$E$20*(1-E$24)*($B26*($E$17*$D$10+(1-$E$17)*$D$9)+(1-$B26)*($E$17*$C$10+(1-$E$17)*$C$9)) -> 0.81437753 | F26: =$E$20*(1-F$24)*($B26*($E$17*$D$10+(1-$E$17)*$D$9)+(1-$B26)*($E$17*$C$10+(1-$E$17)*$C$9)) -> 0.75173311 | G26: =$E$20*(1-G$24)*($B26*($E$17*$D$10+(1-$E$17)*$D$9)+(1-$B26)*($E$17*$C$10+(1-$E$17)*$C$9)) -> 0.68908868 | H26: =$E$20*(1-H$24)*($B26*($E$17*$D$10+(1-$E$17)*$D$9)+(1-$B26)*($E$17*$C$10+(1-$E$17)*$C$9)) -> 0.62644426
B27: 0.55 | C27: =$E$20*(1-C$24)*($B27*($E$17*$D$10+(1-$E$17)*$D$9)+(1-$B27)*($E$17*$C$10+(1-$E$17)*$C$9)) -> 0.84121564 | D27: =$E$20*(1-D$24)*($B27*($E$17*$D$10+(1-$E$17)*$D$9)+(1-$B27)*($E$17*$C$10+(1-$E$17)*$C$9)) -> 0.78513459 | E27: =$E$20*(1-E$24)*($B27*($E$17*$D$10+(1-$E$17)*$D$9)+(1-$B27)*($E$17*$C$10+(1-$E$17)*$C$9)) -> 0.72905355 | F27: =$E$20*(1-F$24)*($B27*($E$17*$D$10+(1-$E$17)*$D$9)+(1-$B27)*($E$17*$C$10+(1-$E$17)*$C$9)) -> 0.67297251 | G27: =$E$20*(1-G$24)*($B27*($E$17*$D$10+(1-$E$17)*$D$9)+(1-$B27)*($E$17*$C$10+(1-$E$17)*$C$9)) -> 0.61689147 | H27: =$E$20*(1-H$24)*($B27*($E$17*$D$10+(1-$E$17)*$D$9)+(1-$B27)*($E$17*$C$10+(1-$E$17)*$C$9)) -> 0.56081042
B28: 0.65 | C28: =$E$20*(1-C$24)*($B28*($E$17*$D$10+(1-$E$17)*$D$9)+(1-$B28)*($E$17*$C$10+(1-$E$17)*$C$9)) -> 0.74276489 | D28: =$E$20*(1-D$24)*($B28*($E$17*$D$10+(1-$E$17)*$D$9)+(1-$B28)*($E$17*$C$10+(1-$E$17)*$C$9)) -> 0.69324723 | E28: =$E$20*(1-E$24)*($B28*($E$17*$D$10+(1-$E$17)*$D$9)+(1-$B28)*($E$17*$C$10+(1-$E$17)*$C$9)) -> 0.64372957 | F28: =$E$20*(1-F$24)*($B28*($E$17*$D$10+(1-$E$17)*$D$9)+(1-$B28)*($E$17*$C$10+(1-$E$17)*$C$9)) -> 0.59421191 | G28: =$E$20*(1-G$24)*($B28*($E$17*$D$10+(1-$E$17)*$D$9)+(1-$B28)*($E$17*$C$10+(1-$E$17)*$C$9)) -> 0.54469425 | H28: =$E$20*(1-H$24)*($B28*($E$17*$D$10+(1-$E$17)*$D$9)+(1-$B28)*($E$17*$C$10+(1-$E$17)*$C$9)) -> 0.49517659
B29: 0.75 | C29: =$E$20*(1-C$24)*($B29*($E$17*$D$10+(1-$E$17)*$D$9)+(1-$B29)*($E$17*$C$10+(1-$E$17)*$C$9)) -> 0.64431414 | D29: =$E$20*(1-D$24)*($B29*($E$17*$D$10+(1-$E$17)*$D$9)+(1-$B29)*($E$17*$C$10+(1-$E$17)*$C$9)) -> 0.60135987 | E29: =$E$20*(1-E$24)*($B29*($E$17*$D$10+(1-$E$17)*$D$9)+(1-$B29)*($E$17*$C$10+(1-$E$17)*$C$9)) -> 0.55840559 | F29: =$E$20*(1-F$24)*($B29*($E$17*$D$10+(1-$E$17)*$D$9)+(1-$B29)*($E$17*$C$10+(1-$E$17)*$C$9)) -> 0.51545131 | G29: =$E$20*(1-G$24)*($B29*($E$17*$D$10+(1-$E$17)*$D$9)+(1-$B29)*($E$17*$C$10+(1-$E$17)*$C$9)) -> 0.47249704 | H29: =$E$20*(1-H$24)*($B29*($E$17*$D$10+(1-$E$17)*$D$9)+(1-$B29)*($E$17*$C$10+(1-$E$17)*$C$9)) -> 0.42954276
A32: E. GRID 2 — senior share × offshore share, holding Year-3 productivity
B33: This is the interaction the talent-shape decision turns on.
B34: Senior share ↓ Offshore → | C34: 0.35 | D34: 0.45 | E34: 0.55 | F34: 0.65 | G34: 0.75
B35: 0.3 | C35: =$E$20*(1-$E$15)*(C$34*($B35*$D$10+(1-$B35)*$D$9)+(1-C$34)*($B35*$C$10+(1-$B35)*$C$9)) -> 0.79857232 | D35: =$E$20*(1-$E$15)*(D$34*($B35*$D$10+(1-$B35)*$D$9)+(1-D$34)*($B35*$C$10+(1-$B35)*$C$9)) -> 0.72302225 | E35: =$E$20*(1-$E$15)*(E$34*($B35*$D$10+(1-$B35)*$D$9)+(1-E$34)*($B35*$C$10+(1-$B35)*$C$9)) -> 0.64747219 | F35: =$E$20*(1-$E$15)*(F$34*($B35*$D$10+(1-$B35)*$D$9)+(1-F$34)*($B35*$C$10+(1-$B35)*$C$9)) -> 0.57192212 | G35: =$E$20*(1-$E$15)*(G$34*($B35*$D$10+(1-$B35)*$D$9)+(1-G$34)*($B35*$C$10+(1-$B35)*$C$9)) -> 0.49637205
B36: 0.4 | C36: =$E$20*(1-$E$15)*(C$34*($B36*$D$10+(1-$B36)*$D$9)+(1-C$34)*($B36*$C$10+(1-$B36)*$C$9)) -> 0.83650062 | D36: =$E$20*(1-$E$15)*(D$34*($B36*$D$10+(1-$B36)*$D$9)+(1-D$34)*($B36*$C$10+(1-$B36)*$C$9)) -> 0.75724959 | E36: =$E$20*(1-$E$15)*(E$34*($B36*$D$10+(1-$B36)*$D$9)+(1-E$34)*($B36*$C$10+(1-$B36)*$C$9)) -> 0.67799855 | F36: =$E$20*(1-$E$15)*(F$34*($B36*$D$10+(1-$B36)*$D$9)+(1-F$34)*($B36*$C$10+(1-$B36)*$C$9)) -> 0.59874752 | G36: =$E$20*(1-$E$15)*(G$34*($B36*$D$10+(1-$B36)*$D$9)+(1-G$34)*($B36*$C$10+(1-$B36)*$C$9)) -> 0.51949649
B37: 0.5 | C37: =$E$20*(1-$E$15)*(C$34*($B37*$D$10+(1-$B37)*$D$9)+(1-C$34)*($B37*$C$10+(1-$B37)*$C$9)) -> 0.87442891 | D37: =$E$20*(1-$E$15)*(D$34*($B37*$D$10+(1-$B37)*$D$9)+(1-D$34)*($B37*$C$10+(1-$B37)*$C$9)) -> 0.79147692 | E37: =$E$20*(1-$E$15)*(E$34*($B37*$D$10+(1-$B37)*$D$9)+(1-E$34)*($B37*$C$10+(1-$B37)*$C$9)) -> 0.70852492 | F37: =$E$20*(1-$E$15)*(F$34*($B37*$D$10+(1-$B37)*$D$9)+(1-F$34)*($B37*$C$10+(1-$B37)*$C$9)) -> 0.62557293 | G37: =$E$20*(1-$E$15)*(G$34*($B37*$D$10+(1-$B37)*$D$9)+(1-G$34)*($B37*$C$10+(1-$B37)*$C$9)) -> 0.54262094
B38: 0.6 | C38: =$E$20*(1-$E$15)*(C$34*($B38*$D$10+(1-$B38)*$D$9)+(1-C$34)*($B38*$C$10+(1-$B38)*$C$9)) -> 0.9123572 | D38: =$E$20*(1-$E$15)*(D$34*($B38*$D$10+(1-$B38)*$D$9)+(1-D$34)*($B38*$C$10+(1-$B38)*$C$9)) -> 0.82570425 | E38: =$E$20*(1-$E$15)*(E$34*($B38*$D$10+(1-$B38)*$D$9)+(1-E$34)*($B38*$C$10+(1-$B38)*$C$9)) -> 0.73905129 | F38: =$E$20*(1-$E$15)*(F$34*($B38*$D$10+(1-$B38)*$D$9)+(1-F$34)*($B38*$C$10+(1-$B38)*$C$9)) -> 0.65239834 | G38: =$E$20*(1-$E$15)*(G$34*($B38*$D$10+(1-$B38)*$D$9)+(1-G$34)*($B38*$C$10+(1-$B38)*$C$9)) -> 0.56574538
B39: 0.7 | C39: =$E$20*(1-$E$15)*(C$34*($B39*$D$10+(1-$B39)*$D$9)+(1-C$34)*($B39*$C$10+(1-$B39)*$C$9)) -> 0.95028549 | D39: =$E$20*(1-$E$15)*(D$34*($B39*$D$10+(1-$B39)*$D$9)+(1-D$34)*($B39*$C$10+(1-$B39)*$C$9)) -> 0.85993158 | E39: =$E$20*(1-$E$15)*(E$34*($B39*$D$10+(1-$B39)*$D$9)+(1-E$34)*($B39*$C$10+(1-$B39)*$C$9)) -> 0.76957766 | F39: =$E$20*(1-$E$15)*(F$34*($B39*$D$10+(1-$B39)*$D$9)+(1-F$34)*($B39*$C$10+(1-$B39)*$C$9)) -> 0.67922374 | G39: =$E$20*(1-$E$15)*(G$34*($B39*$D$10+(1-$B39)*$D$9)+(1-G$34)*($B39*$C$10+(1-$B39)*$C$9)) -> 0.58886983
A41: F. TORNADO — one lever at a time, ±10 points from the Year-3 base case
B42: Lever | C42: −10 points | D42: Base | E42: +10 points | F42: Swing | G42: Reading
B43: Productivity | C43: =$E$20*(1-($E$15-0.1))*(($E$16)*(($E$17)*$D$10+(1-($E$17))*$D$9)+(1-($E$16))*(($E$17)*$C$10+(1-($E$17))*$C$9)) -> 0.79301934 | D43: =$E$20*(1-($E$15))*(($E$16)*(($E$17)*$D$10+(1-($E$17))*$D$9)+(1-($E$16))*(($E$17)*$C$10+(1-($E$17))*$C$9)) -> 0.68367014 | E43: =$E$20*(1-($E$15+0.1))*(($E$16)*(($E$17)*$D$10+(1-($E$17))*$D$9)+(1-($E$16))*(($E$17)*$C$10+(1-($E$17))*$C$9)) -> 0.57432093 | F43: =ABS(E43-C43) -> 0.21869841 | G43: Scales unit cost one-for-one. The only lever with a linear effect.
B44: Offshore share | C44: =$E$20*(1-($E$15))*(($E$16-0.1)*(($E$17)*$D$10+(1-($E$17))*$D$9)+(1-($E$16-0.1))*(($E$17)*$C$10+(1-($E$17))*$C$9)) -> 0.76574095 | D44: =$E$20*(1-($E$15))*(($E$16)*(($E$17)*$D$10+(1-($E$17))*$D$9)+(1-($E$16))*(($E$17)*$C$10+(1-($E$17))*$C$9)) -> 0.68367014 | E44: =$E$20*(1-($E$15))*(($E$16+0.1)*(($E$17)*$D$10+(1-($E$17))*$D$9)+(1-($E$16+0.1))*(($E$17)*$C$10+(1-($E$17))*$C$9)) -> 0.60159933 | F44: =ABS(E44-C44) -> 0.16414162 | G44: Second largest. Cheap to move early, and it exhausts once the ceiling is reached.
B45: Senior share | C45: =$E$20*(1-($E$15))*(($E$16)*(($E$17-0.1)*$D$10+(1-($E$17-0.1))*$D$9)+(1-($E$16))*(($E$17-0.1)*$C$10+(1-($E$17-0.1))*$C$9)) -> 0.65393683 | D45: =$E$20*(1-($E$15))*(($E$16)*(($E$17)*$D$10+(1-($E$17))*$D$9)+(1-($E$16))*(($E$17)*$C$10+(1-($E$17))*$C$9)) -> 0.68367014 | E45: =$E$20*(1-($E$15))*(($E$16)*(($E$17+0.1)*$D$10+(1-($E$17+0.1))*$D$9)+(1-($E$16))*(($E$17+0.1)*$C$10+(1-($E$17+0.1))*$C$9)) -> 0.71340344 | F45: =ABS(E45-C45) -> 0.059466611 | G45: Works AGAINST the other two. A richer shape gives back part of what offshore wins.
A47: G. WHAT THE NUMBERS SAY
B48: • PRODUCTIVITY IS THE LARGEST LEVER and the only linear one, at 0.110 per ten points on a Year-3 base of 0.642. The tornado swings below are full 20-point ranges, so they read double that.
B49: • OFFSHORE IS SECOND, at 0.074 per ten points, and it is the lever that pays for the talent shape.
B50: • SENIORITY WORKS AGAINST BOTH, at 0.025 per ten points. So ten points of extra seniority is affordable as long as offshore moves at least a third as far in the same period — which is why the shape here is held at a diamond rather than pushed to an obelisk.
B51: • In this domain the offshore move (56% to 71% of Capgemini effort) more than covers the shape change (40% to 54% senior). Average cost per head still rises, from 1.058 to 1.096, but only by 3.5% while unit cost falls 39.5%.
B52: • READ GRID 2 ACROSS A ROW: at fixed productivity, moving from 35% to 75% offshore is worth more than any plausible experience-mix change costs. That is the sequencing argument — offshore first, shape second.

Sheet Seat Ledger
A1: Seat ledger — every pod line multiplied out by the pod plan, plus every horizontal seat
A2: Computed. Every roll-up in this workbook reads from here. Edit Pod Library, Pod Plan or Horizontal Teams instead.
A4: Year | B4: Origin | C4: Unit | D4: Pod type | E4: Role | F4: Skill | G4: Exp | H4: Location | I4: Sourcing | J4: Seats/pod | K4: Pods | L4: Heads | M4: Cost index
A5: 1 | B5: POD | C5: VS1 | D5: CO | E5: ='Pod Library'!F5 -> Product Owner — Informatica Data Platform | F5: ='Pod Library'!G5 -> LEAD | G5: ='Pod Library'!H5 -> E4 | H5: ='Pod Library'!I5 -> ON | I5: ='Pod Library'!J5 -> FTE | J5: ='Pod Library'!K5 -> 1 | K5: =SUMIFS('Pod Plan'!$E:$E,'Pod Plan'!$B:$B,$A5,'Pod Plan'!$C:$C,$C5) -> 4 | L5: =J5*K5 -> 4 | M5: =L5*INDEX('Logic Tree'!$J$80:$N$81,MATCH(H5,'Logic Tree'!$I$80:$I$81,0),MATCH(G5,'Logic Tree'!$J$79:$N$79,0)) -> 7.4
A6: 1 | B6: POD | C6: VS1 | D6: CO | E6: ='Pod Library'!F6 -> Data Domain SME | F6: ='Pod Library'!G6 -> BA | G6: ='Pod Library'!H6 -> E4 | H6: ='Pod Library'!I6 -> ON | I6: ='Pod Library'!J6 -> FTE | J6: ='Pod Library'!K6 -> 1 | K6: =SUMIFS('Pod Plan'!$E:$E,'Pod Plan'!$B:$B,$A6,'Pod Plan'!$C:$C,$C6) -> 4 | L6: =J6*K6 -> 4 | M6: =L6*INDEX('Logic Tree'!$J$80:$N$81,MATCH(H6,'Logic Tree'!$I$80:$I$81,0),MATCH(G6,'Logic Tree'!$J$79:$N$79,0)) -> 7.4
A7: 1 | B7: POD | C7: VS1 | D7: CO | E7: ='Pod Library'!F7 -> Informatica Lead Engineer | F7: ='Pod Library'!G7 -> ENG | G7: ='Pod Library'!H7 -> E3 | H7: ='Pod Library'!I7 -> OFF | I7: ='Pod Library'!J7 -> FTC | J7: ='Pod Library'!K7 -> 1 | K7: =SUMIFS('Pod Plan'!$E:$E,'Pod Plan'!$B:$B,$A7,'Pod Plan'!$C:$C,$C7) -> 4 | L7: =J7*K7 -> 4 | M7: =L7*INDEX('Logic Tree'!$J$80:$N$81,MATCH(H7,'Logic Tree'!$I$80:$I$81,0),MATCH(G7,'Logic Tree'!$J$79:$N$79,0)) -> 1.68
A8: 1 | B8: POD | C8: VS1 | D8: CO | E8: ='Pod Library'!F8 -> Data Modeler | F8: ='Pod Library'!G8 -> DEV | G8: ='Pod Library'!H8 -> E3 | H8: ='Pod Library'!I8 -> OFF | I8: ='Pod Library'!J8 -> MGCC | J8: ='Pod Library'!K8 -> 1 | K8: =SUMIFS('Pod Plan'!$E:$E,'Pod Plan'!$B:$B,$A8,'Pod Plan'!$C:$C,$C8) -> 4 | L8: =J8*K8 -> 4 | M8: =L8*INDEX('Logic Tree'!$J$80:$N$81,MATCH(H8,'Logic Tree'!$I$80:$I$81,0),MATCH(G8,'Logic Tree'!$J$79:$N$79,0)) -> 1.68
A9: 1 | B9: POD | C9: VS1 | D9: CO | E9: ='Pod Library'!F9 -> Pod Delivery Lead (Informatica Tech Lead) | F9: ='Pod Library'!G9 -> LEAD | G9: ='Pod Library'!H9 -> E4 | H9: ='Pod Library'!I9 -> ON | I9: ='Pod Library'!J9 -> FTC | J9: ='Pod Library'!K9 -> 1 | K9: =SUMIFS('Pod Plan'!$E:$E,'Pod Plan'!$B:$B,$A9,'Pod Plan'!$C:$C,$C9) -> 4 | L9: =J9*K9 -> 4 | M9: =L9*INDEX('Logic Tree'!$J$80:$N$81,MATCH(H9,'Logic Tree'!$I$80:$I$81,0),MATCH(G9,'Logic Tree'!$J$79:$N$79,0)) -> 7.4
A10: 1 | B10: POD | C10: VS1 | D10: CO | E10: ='Pod Library'!F10 -> Senior Informatica Developer | F10: ='Pod Library'!G10 -> DEV | G10: ='Pod Library'!H10 -> E3 | H10: ='Pod Library'!I10 -> ON | I10: ='Pod Library'!J10 -> FTC | J10: ='Pod Library'!K10 -> 1 | K10: =SUMIFS('Pod Plan'!$E:$E,'Pod Plan'!$B:$B,$A10,'Pod Plan'!$C:$C,$C10) -> 4 | L10: =J10*K10 -> 4 | M10: =L10*INDEX('Logic Tree'!$J$80:$N$81,MATCH(H10,'Logic Tree'!$I$80:$I$81,0),MATCH(G10,'Logic Tree'!$J$79:$N$79,0)) -> 5.4
A11: 1 | B11: POD | C11: VS1 | D11: CO | E11: ='Pod Library'!F11 -> Informatica Developer | F11: ='Pod Library'!G11 -> DEV | G11: ='Pod Library'!H11 -> E2 | H11: ='Pod Library'!I11 -> OFF | I11: ='Pod Library'!J11 -> FTC | J11: ='Pod Library'!K11 -> 1 | K11: =SUMIFS('Pod Plan'!$E:$E,'Pod Plan'!$B:$B,$A11,'Pod Plan'!$C:$C,$C11) -> 4 | L11: =J11*K11 -> 4 | M11: =L11*INDEX('Logic Tree'!$J$80:$N$81,MATCH(H11,'Logic Tree'!$I$80:$I$81,0),MATCH(G11,'Logic Tree'!$J$79:$N$79,0)) -> 1.2
A12: 1 | B12: POD | C12: VS1 | D12: CO | E12: ='Pod Library'!F12 -> Data Tester | F12: ='Pod Library'!G12 -> TEST | G12: ='Pod Library'!H12 -> E2 | H12: ='Pod Library'!I12 -> OFF | I12: ='Pod Library'!J12 -> FTC | J12: ='Pod Library'!K12 -> 1 | K12: =SUMIFS('Pod Plan'!$E:$E,'Pod Plan'!$B:$B,$A12,'Pod Plan'!$C:$C,$C12) -> 4 | L12: =J12*K12 -> 4 | M12: =L12*INDEX('Logic Tree'!$J$80:$N$81,MATCH(H12,'Logic Tree'!$I$80:$I$81,0),MATCH(G12,'Logic Tree'!$J$79:$N$79,0)) -> 1.2
A13: 1 | B13: POD | C13: VS1 | D13: FS | E13: ='Pod Library'!F15 -> Product Owner- Data Platform | F13: ='Pod Library'!G15 -> LEAD | G13: ='Pod Library'!H15 -> E4 | H13: ='Pod Library'!I15 -> ON | I13: ='Pod Library'!J15 -> FTE | J13: ='Pod Library'!K15 -> 1 | K13: =SUMIFS('Pod Plan'!$F:$F,'Pod Plan'!$B:$B,$A13,'Pod Plan'!$C:$C,$C13) -> 1 | L13: =J13*K13 -> 1 | M13: =L13*INDEX('Logic Tree'!$J$80:$N$81,MATCH(H13,'Logic Tree'!$I$80:$I$81,0),MATCH(G13,'Logic Tree'!$J$79:$N$79,0)) -> 1.85
A14: 1 | B14: POD | C14: VS1 | D14: FS | E14: ='Pod Library'!F16 -> Pod Delivery Lead (Informatica Tech Lead) | F14: ='Pod Library'!G16 -> LEAD | G14: ='Pod Library'!H16 -> E4 | H14: ='Pod Library'!I16 -> ON | I14: ='Pod Library'!J16 -> FTC | J14: ='Pod Library'!K16 -> 1 | K14: =SUMIFS('Pod Plan'!$F:$F,'Pod Plan'!$B:$B,$A14,'Pod Plan'!$C:$C,$C14) -> 1 | L14: =J14*K14 -> 1 | M14: =L14*INDEX('Logic Tree'!$J$80:$N$81,MATCH(H14,'Logic Tree'!$I$80:$I$81,0),MATCH(G14,'Logic Tree'!$J$79:$N$79,0)) -> 1.85
A15: 1 | B15: POD | C15: VS1 | D15: FS | E15: ='Pod Library'!F17 -> Data Modeler | F15: ='Pod Library'!G17 -> ENG | G15: ='Pod Library'!H17 -> E4 | H15: ='Pod Library'!I17 -> ON | I15: ='Pod Library'!J17 -> FTC | J15: ='Pod Library'!K17 -> 1 | K15: =SUMIFS('Pod Plan'!$F:$F,'Pod Plan'!$B:$B,$A15,'Pod Plan'!$C:$C,$C15) -> 1 | L15: =J15*K15 -> 1 | M15: =L15*INDEX('Logic Tree'!$J$80:$N$81,MATCH(H15,'Logic Tree'!$I$80:$I$81,0),MATCH(G15,'Logic Tree'!$J$79:$N$79,0)) -> 1.85
A16: 1 | B16: POD | C16: VS1 | D16: FS | E16: ='Pod Library'!F18 -> Business Analyst (bilingual) | F16: ='Pod Library'!G18 -> BA | G16: ='Pod Library'!H18 -> E3 | H16: ='Pod Library'!I18 -> ON | I16: ='Pod Library'!J18 -> FTC | J16: ='Pod Library'!K18 -> 1 | K16: =SUMIFS('Pod Plan'!$F:$F,'Pod Plan'!$B:$B,$A16,'Pod Plan'!$C:$C,$C16) -> 1 | L16: =J16*K16 -> 1 | M16: =L16*INDEX('Logic Tree'!$J$80:$N$81,MATCH(H16,'Logic Tree'!$I$80:$I$81,0),MATCH(G16,'Logic Tree'!$J$79:$N$79,0)) -> 1.35
A17: 1 | B17: POD | C17: VS1 | D17: FS | E17: ='Pod Library'!F19 -> Senior Informatica Developer | F17: ='Pod Library'!G19 -> DEV | G17: ='Pod Library'!H19 -> E3 | H17: ='Pod Library'!I19 -> OFF | I17: ='Pod Library'!J19 -> FTC | J17: ='Pod Library'!K19 -> 1 | K17: =SUMIFS('Pod Plan'!$F:$F,'Pod Plan'!$B:$B,$A17,'Pod Plan'!$C:$C,$C17) -> 1 | L17: =J17*K17 -> 1 | M17: =L17*INDEX('Logic Tree'!$J$80:$N$81,MATCH(H17,'Logic Tree'!$I$80:$I$81,0),MATCH(G17,'Logic Tree'!$J$79:$N$79,0)) -> 0.42
A18: 1 | B18: POD | C18: VS1 | D18: FS | E18: ='Pod Library'!F20 -> Informatica Developer | F18: ='Pod Library'!G20 -> DEV | G18: ='Pod Library'!H20 -> E2 | H18: ='Pod Library'!I20 -> OFF | I18: ='Pod Library'!J20 -> FTC | J18: ='Pod Library'!K20 -> 2 | K18: =SUMIFS('Pod Plan'!$F:$F,'Pod Plan'!$B:$B,$A18,'Pod Plan'!$C:$C,$C18) -> 1 | L18: =J18*K18 -> 2 | M18: =L18*INDEX('Logic Tree'!$J$80:$N$81,MATCH(H18,'Logic Tree'!$I$80:$I$81,0),MATCH(G18,'Logic Tree'!$J$79:$N$79,0)) -> 0.6
A19: 1 | B19: POD | C19: VS1 | D19: FS | E19: ='Pod Library'!F21 -> Data Tester | F19: ='Pod Library'!G21 -> TEST | G19: ='Pod Library'!H21 -> E2 | H19: ='Pod Library'!I21 -> OFF | I19: ='Pod Library'!J21 -> FTC | J19: ='Pod Library'!K21 -> 1 | K19: =SUMIFS('Pod Plan'!$F:$F,'Pod Plan'!$B:$B,$A19,'Pod Plan'!$C:$C,$C19) -> 1 | L19: =J19*K19 -> 1 | M19: =L19*INDEX('Logic Tree'!$J$80:$N$81,MATCH(H19,'Logic Tree'!$I$80:$I$81,0),MATCH(G19,'Logic Tree'!$J$79:$N$79,0)) -> 0.3
A20: 1 | B20: POD | C20: VS1 | D20: FS | E20: ='Pod Library'!F22 -> L2 Data Support | F20: ='Pod Library'!G22 -> OPS | G20: ='Pod Library'!H22 -> E2 | H20: ='Pod Library'!I22 -> OFF | I20: ='Pod Library'!J22 -> FTC | J20: ='Pod Library'!K22 -> 0 | K20: =SUMIFS('Pod Plan'!$F:$F,'Pod Plan'!$B:$B,$A20,'Pod Plan'!$C:$C,$C20) -> 1 | L20: =J20*K20 -> 0 | M20: =L20*INDEX('Logic Tree'!$J$80:$N$81,MATCH(H20,'Logic Tree'!$I$80:$I$81,0),MATCH(G20,'Logic Tree'!$J$79:$N$79,0)) -> 0
A21: 1 | B21: POD | C21: VS2 | D21: CO | E21: ='Pod Library'!F25 -> Product Owner- Data Platform | F21: ='Pod Library'!G25 -> LEAD | G21: ='Pod Library'!H25 -> E4 | H21: ='Pod Library'!I25 -> ON | I21: ='Pod Library'!J25 -> FTE | J21: ='Pod Library'!K25 -> 1 | K21: =SUMIFS('Pod Plan'!$E:$E,'Pod Plan'!$B:$B,$A21,'Pod Plan'!$C:$C,$C21) -> 2 | L21: =J21*K21 -> 2 | M21: =L21*INDEX('Logic Tree'!$J$80:$N$81,MATCH(H21,'Logic Tree'!$I$80:$I$81,0),MATCH(G21,'Logic Tree'!$J$79:$N$79,0)) -> 3.7
A22: 1 | B22: POD | C22: VS2 | D22: CO | E22: ='Pod Library'!F26 -> Azure Data Architect (MetLife) | F22: ='Pod Library'!G26 -> ENG | G22: ='Pod Library'!H26 -> E5 | H22: ='Pod Library'!I26 -> ON | I22: ='Pod Library'!J26 -> FTE | J22: ='Pod Library'!K26 -> 1 | K22: =SUMIFS('Pod Plan'!$E:$E,'Pod Plan'!$B:$B,$A22,'Pod Plan'!$C:$C,$C22) -> 2 | L22: =J22*K22 -> 2 | M22: =L22*INDEX('Logic Tree'!$J$80:$N$81,MATCH(H22,'Logic Tree'!$I$80:$I$81,0),MATCH(G22,'Logic Tree'!$J$79:$N$79,0)) -> 5.1
A23: 1 | B23: POD | C23: VS2 | D23: CO | E23: ='Pod Library'!F27 -> BI / Reporting Engineer | F23: ='Pod Library'!G27 -> DEV | G23: ='Pod Library'!H27 -> E3 | H23: ='Pod Library'!I27 -> OFF | I23: ='Pod Library'!J27 -> FTC | J23: ='Pod Library'!K27 -> 1 | K23: =SUMIFS('Pod Plan'!$E:$E,'Pod Plan'!$B:$B,$A23,'Pod Plan'!$C:$C,$C23) -> 2 | L23: =J23*K23 -> 2 | M23: =L23*INDEX('Logic Tree'!$J$80:$N$81,MATCH(H23,'Logic Tree'!$I$80:$I$81,0),MATCH(G23,'Logic Tree'!$J$79:$N$79,0)) -> 0.84
A24: 1 | B24: POD | C24: VS2 | D24: CO | E24: ='Pod Library'!F28 -> Synapse Platform Engineer | F24: ='Pod Library'!G28 -> ENG | G24: ='Pod Library'!H28 -> E4 | H24: ='Pod Library'!I28 -> OFF | I24: ='Pod Library'!J28 -> MGCC | J24: ='Pod Library'!K28 -> 1 | K24: =SUMIFS('Pod Plan'!$E:$E,'Pod Plan'!$B:$B,$A24,'Pod Plan'!$C:$C,$C24) -> 2 | L24: =J24*K24 -> 2 | M24: =L24*INDEX('Logic Tree'!$J$80:$N$81,MATCH(H24,'Logic Tree'!$I$80:$I$81,0),MATCH(G24,'Logic Tree'!$J$79:$N$79,0)) -> 1.2
A25: 1 | B25: POD | C25: VS2 | D25: CO | E25: ='Pod Library'!F29 -> Azure Data Engineer | F25: ='Pod Library'!G29 -> DEV | G25: ='Pod Library'!H29 -> E3 | H25: ='Pod Library'!I29 -> OFF | I25: ='Pod Library'!J29 -> MGCC | J25: ='Pod Library'!K29 -> 1 | K25: =SUMIFS('Pod Plan'!$E:$E,'Pod Plan'!$B:$B,$A25,'Pod Plan'!$C:$C,$C25) -> 2 | L25: =J25*K25 -> 2 | M25: =L25*INDEX('Logic Tree'!$J$80:$N$81,MATCH(H25,'Logic Tree'!$I$80:$I$81,0),MATCH(G25,'Logic Tree'!$J$79:$N$79,0)) -> 0.84
A26: 1 | B26: POD | C26: VS2 | D26: CO | E26: ='Pod Library'!F30 -> Pod Delivery Lead ( Azure Data Engineering) | F26: ='Pod Library'!G30 -> LEAD | G26: ='Pod Library'!H30 -> E4 | H26: ='Pod Library'!I30 -> ON | I26: ='Pod Library'!J30 -> FTC | J26: ='Pod Library'!K30 -> 1 | K26: =SUMIFS('Pod Plan'!$E:$E,'Pod Plan'!$B:$B,$A26,'Pod Plan'!$C:$C,$C26) -> 2 | L26: =J26*K26 -> 2 | M26: =L26*INDEX('Logic Tree'!$J$80:$N$81,MATCH(H26,'Logic Tree'!$I$80:$I$81,0),MATCH(G26,'Logic Tree'!$J$79:$N$79,0)) -> 3.7
A27: 1 | B27: POD | C27: VS2 | D27: CO | E27: ='Pod Library'!F31 -> Senior Azure Data Engineer | F27: ='Pod Library'!G31 -> DEV | G27: ='Pod Library'!H31 -> E3 | H27: ='Pod Library'!I31 -> ON | I27: ='Pod Library'!J31 -> MGCC | J27: ='Pod Library'!K31 -> 1 | K27: =SUMIFS('Pod Plan'!$E:$E,'Pod Plan'!$B:$B,$A27,'Pod Plan'!$C:$C,$C27) -> 2 | L27: =J27*K27 -> 2 | M27: =L27*INDEX('Logic Tree'!$J$80:$N$81,MATCH(H27,'Logic Tree'!$I$80:$I$81,0),MATCH(G27,'Logic Tree'!$J$79:$N$79,0)) -> 2.7
A28: 1 | B28: POD | C28: VS2 | D28: CO | E28: ='Pod Library'!F32 -> Azure Data Engineer | F28: ='Pod Library'!G32 -> DEV | G28: ='Pod Library'!H32 -> E2 | H28: ='Pod Library'!I32 -> OFF | I28: ='Pod Library'!J32 -> FTC | J28: ='Pod Library'!K32 -> 1 | K28: =SUMIFS('Pod Plan'!$E:$E,'Pod Plan'!$B:$B,$A28,'Pod Plan'!$C:$C,$C28) -> 2 | L28: =J28*K28 -> 2 | M28: =L28*INDEX('Logic Tree'!$J$80:$N$81,MATCH(H28,'Logic Tree'!$I$80:$I$81,0),MATCH(G28,'Logic Tree'!$J$79:$N$79,0)) -> 0.6
A29: 1 | B29: POD | C29: VS2 | D29: CO | E29: ='Pod Library'!F33 -> Data Tester | F29: ='Pod Library'!G33 -> TEST | G29: ='Pod Library'!H33 -> E2 | H29: ='Pod Library'!I33 -> OFF | I29: ='Pod Library'!J33 -> FTC | J29: ='Pod Library'!K33 -> 1 | K29: =SUMIFS('Pod Plan'!$E:$E,'Pod Plan'!$B:$B,$A29,'Pod Plan'!$C:$C,$C29) -> 2 | L29: =J29*K29 -> 2 | M29: =L29*INDEX('Logic Tree'!$J$80:$N$81,MATCH(H29,'Logic Tree'!$I$80:$I$81,0),MATCH(G29,'Logic Tree'!$J$79:$N$79,0)) -> 0.6
A30: 1 | B30: POD | C30: VS2 | D30: FS | E30: ='Pod Library'!F36 -> Product Owner- Data Platform (shared 0.5) | F30: ='Pod Library'!G36 -> LEAD | G30: ='Pod Library'!H36 -> E4 | H30: ='Pod Library'!I36 -> ON | I30: ='Pod Library'!J36 -> FTE | J30: ='Pod Library'!K36 -> 0.5 | K30: =SUMIFS('Pod Plan'!$F:$F,'Pod Plan'!$B:$B,$A30,'Pod Plan'!$C:$C,$C30) -> 2 | L30: =J30*K30 -> 1 | M30: =L30*INDEX('Logic Tree'!$J$80:$N$81,MATCH(H30,'Logic Tree'!$I$80:$I$81,0),MATCH(G30,'Logic Tree'!$J$79:$N$79,0)) -> 1.85
A31: 1 | B31: POD | C31: VS2 | D31: FS | E31: ='Pod Library'!F37 -> Azure Data Architect (MetLife)- shared | F31: ='Pod Library'!G37 -> ENG | G31: ='Pod Library'!H37 -> E5 | H31: ='Pod Library'!I37 -> ON | I31: ='Pod Library'!J37 -> FTE | J31: ='Pod Library'!K37 -> 0.5 | K31: =SUMIFS('Pod Plan'!$F:$F,'Pod Plan'!$B:$B,$A31,'Pod Plan'!$C:$C,$C31) -> 2 | L31: =J31*K31 -> 1 | M31: =L31*INDEX('Logic Tree'!$J$80:$N$81,MATCH(H31,'Logic Tree'!$I$80:$I$81,0),MATCH(G31,'Logic Tree'!$J$79:$N$79,0)) -> 2.55
A32: 1 | B32: POD | C32: VS2 | D32: FS | E32: ='Pod Library'!F38 -> Pod Delivery Lead ( Azure Data Engineering) | F32: ='Pod Library'!G38 -> LEAD | G32: ='Pod Library'!H38 -> E4 | H32: ='Pod Library'!I38 -> ON | I32: ='Pod Library'!J38 -> FTC | J32: ='Pod Library'!K38 -> 1 | K32: =SUMIFS('Pod Plan'!$F:$F,'Pod Plan'!$B:$B,$A32,'Pod Plan'!$C:$C,$C32) -> 2 | L32: =J32*K32 -> 2 | M32: =L32*INDEX('Logic Tree'!$J$80:$N$81,MATCH(H32,'Logic Tree'!$I$80:$I$81,0),MATCH(G32,'Logic Tree'!$J$79:$N$79,0)) -> 3.7
A33: 1 | B33: POD | C33: VS2 | D33: FS | E33: ='Pod Library'!F39 -> Data Modeler | F33: ='Pod Library'!G39 -> ENG | G33: ='Pod Library'!H39 -> E4 | H33: ='Pod Library'!I39 -> OFF | I33: ='Pod Library'!J39 -> FTC | J33: ='Pod Library'!K39 -> 1 | K33: =SUMIFS('Pod Plan'!$F:$F,'Pod Plan'!$B:$B,$A33,'Pod Plan'!$C:$C,$C33) -> 2 | L33: =J33*K33 -> 2 | M33: =L33*INDEX('Logic Tree'!$J$80:$N$81,MATCH(H33,'Logic Tree'!$I$80:$I$81,0),MATCH(G33,'Logic Tree'!$J$79:$N$79,0)) -> 1.2
A34: 1 | B34: POD | C34: VS2 | D34: FS | E34: ='Pod Library'!F40 -> Business Analyst (bilingual) | F34: ='Pod Library'!G40 -> BA | G34: ='Pod Library'!H40 -> E3 | H34: ='Pod Library'!I40 -> ON | I34: ='Pod Library'!J40 -> FTC | J34: ='Pod Library'!K40 -> 1 | K34: =SUMIFS('Pod Plan'!$F:$F,'Pod Plan'!$B:$B,$A34,'Pod Plan'!$C:$C,$C34) -> 2 | L34: =J34*K34 -> 2 | M34: =L34*INDEX('Logic Tree'!$J$80:$N$81,MATCH(H34,'Logic Tree'!$I$80:$I$81,0),MATCH(G34,'Logic Tree'!$J$79:$N$79,0)) -> 2.7
A35: 1 | B35: POD | C35: VS2 | D35: FS | E35: ='Pod Library'!F41 -> Senior Azure Data Engineer | F35: ='Pod Library'!G41 -> DEV | G35: ='Pod Library'!H41 -> E3 | H35: ='Pod Library'!I41 -> OFF | I35: ='Pod Library'!J41 -> FTC | J35: ='Pod Library'!K41 -> 1 | K35: =SUMIFS('Pod Plan'!$F:$F,'Pod Plan'!$B:$B,$A35,'Pod Plan'!$C:$C,$C35) -> 2 | L35: =J35*K35 -> 2 | M35: =L35*INDEX('Logic Tree'!$J$80:$N$81,MATCH(H35,'Logic Tree'!$I$80:$I$81,0),MATCH(G35,'Logic Tree'!$J$79:$N$79,0)) -> 0.84
A36: 1 | B36: POD | C36: VS2 | D36: FS | E36: ='Pod Library'!F42 -> Azure Data Engineer | F36: ='Pod Library'!G42 -> DEV | G36: ='Pod Library'!H42 -> E2 | H36: ='Pod Library'!I42 -> OFF | I36: ='Pod Library'!J42 -> FTC | J36: ='Pod Library'!K42 -> 2 | K36: =SUMIFS('Pod Plan'!$F:$F,'Pod Plan'!$B:$B,$A36,'Pod Plan'!$C:$C,$C36) -> 2 | L36: =J36*K36 -> 4 | M36: =L36*INDEX('Logic Tree'!$J$80:$N$81,MATCH(H36,'Logic Tree'!$I$80:$I$81,0),MATCH(G36,'Logic Tree'!$J$79:$N$79,0)) -> 1.2
A37: 1 | B37: POD | C37: VS2 | D37: FS | E37: ='Pod Library'!F43 -> BI / Reporting Engineer | F37: ='Pod Library'!G43 -> DEV | G37: ='Pod Library'!H43 -> E3 | H37: ='Pod Library'!I43 -> OFF | I37: ='Pod Library'!J43 -> FTC | J37: ='Pod Library'!K43 -> 1 | K37: =SUMIFS('Pod Plan'!$F:$F,'Pod Plan'!$B:$B,$A37,'Pod Plan'!$C:$C,$C37) -> 2 | L37: =J37*K37 -> 2 | M37: =L37*INDEX('Logic Tree'!$J$80:$N$81,MATCH(H37,'Logic Tree'!$I$80:$I$81,0),MATCH(G37,'Logic Tree'!$J$79:$N$79,0)) -> 0.84
A38: 1 | B38: POD | C38: VS2 | D38: FS | E38: ='Pod Library'!F44 -> Data Tester | F38: ='Pod Library'!G44 -> TEST | G38: ='Pod Library'!H44 -> E2 | H38: ='Pod Library'!I44 -> OFF | I38: ='Pod Library'!J44 -> FTC | J38: ='Pod Library'!K44 -> 1 | K38: =SUMIFS('Pod Plan'!$F:$F,'Pod Plan'!$B:$B,$A38,'Pod Plan'!$C:$C,$C38) -> 2 | L38: =J38*K38 -> 2 | M38: =L38*INDEX('Logic Tree'!$J$80:$N$81,MATCH(H38,'Logic Tree'!$I$80:$I$81,0),MATCH(G38,'Logic Tree'!$J$79:$N$79,0)) -> 0.6
A39: 2 | B39: POD | C39: VS1 | D39: CO | E39: ='Pod Library'!F47 -> Product Owner — Informatica Data Platform | F39: ='Pod Library'!G47 -> LEAD | G39: ='Pod Library'!H47 -> E4 | H39: ='Pod Library'!I47 -> ON | I39: ='Pod Library'!J47 -> FTE | J39: ='Pod Library'!K47 -> 1 | K39: =SUMIFS('Pod Plan'!$E:$E,'Pod Plan'!$B:$B,$A39,'Pod Plan'!$C:$C,$C39) -> 2 | L39: =J39*K39 -> 2 | M39: =L39*INDEX('Logic Tree'!$J$80:$N$81,MATCH(H39,'Logic Tree'!$I$80:$I$81,0),MATCH(G39,'Logic Tree'!$J$79:$N$79,0)) -> 3.7
A40: 2 | B40: POD | C40: VS1 | D40: CO | E40: ='Pod Library'!F48 -> Data Domain SME | F40: ='Pod Library'!G48 -> BA | G40: ='Pod Library'!H48 -> E4 | H40: ='Pod Library'!I48 -> ON | I40: ='Pod Library'!J48 -> FTE | J40: ='Pod Library'!K48 -> 1 | K40: =SUMIFS('Pod Plan'!$E:$E,'Pod Plan'!$B:$B,$A40,'Pod Plan'!$C:$C,$C40) -> 2 | L40: =J40*K40 -> 2 | M40: =L40*INDEX('Logic Tree'!$J$80:$N$81,MATCH(H40,'Logic Tree'!$I$80:$I$81,0),MATCH(G40,'Logic Tree'!$J$79:$N$79,0)) -> 3.7
A41: 2 | B41: POD | C41: VS1 | D41: CO | E41: ='Pod Library'!F49 -> Informatica Lead Engineer | F41: ='Pod Library'!G49 -> ENG | G41: ='Pod Library'!H49 -> E4 | H41: ='Pod Library'!I49 -> OFF | I41: ='Pod Library'!J49 -> MGCC | J41: ='Pod Library'!K49 -> 1 | K41: =SUMIFS('Pod Plan'!$E:$E,'Pod Plan'!$B:$B,$A41,'Pod Plan'!$C:$C,$C41) -> 2 | L41: =J41*K41 -> 2 | M41: =L41*INDEX('Logic Tree'!$J$80:$N$81,MATCH(H41,'Logic Tree'!$I$80:$I$81,0),MATCH(G41,'Logic Tree'!$J$79:$N$79,0)) -> 1.2
A42: 2 | B42: POD | C42: VS1 | D42: CO | E42: ='Pod Library'!F50 -> Data Modeler | F42: ='Pod Library'!G50 -> DEV | G42: ='Pod Library'!H50 -> E3 | H42: ='Pod Library'!I50 -> OFF | I42: ='Pod Library'!J50 -> MGCC | J42: ='Pod Library'!K50 -> 1 | K42: =SUMIFS('Pod Plan'!$E:$E,'Pod Plan'!$B:$B,$A42,'Pod Plan'!$C:$C,$C42) -> 2 | L42: =J42*K42 -> 2 | M42: =L42*INDEX('Logic Tree'!$J$80:$N$81,MATCH(H42,'Logic Tree'!$I$80:$I$81,0),MATCH(G42,'Logic Tree'!$J$79:$N$79,0)) -> 0.84
A43: 2 | B43: POD | C43: VS1 | D43: CO | E43: ='Pod Library'!F51 -> Pod Delivery Lead (Informatica Tech Lead) | F43: ='Pod Library'!G51 -> LEAD | G43: ='Pod Library'!H51 -> E4 | H43: ='Pod Library'!I51 -> OFF | I43: ='Pod Library'!J51 -> FTC | J43: ='Pod Library'!K51 -> 1 | K43: =SUMIFS('Pod Plan'!$E:$E,'Pod Plan'!$B:$B,$A43,'Pod Plan'!$C:$C,$C43) -> 2 | L43: =J43*K43 -> 2 | M43: =L43*INDEX('Logic Tree'!$J$80:$N$81,MATCH(H43,'Logic Tree'!$I$80:$I$81,0),MATCH(G43,'Logic Tree'!$J$79:$N$79,0)) -> 1.2
A44: 2 | B44: POD | C44: VS1 | D44: CO | E44: ='Pod Library'!F52 -> Informatica Developer | F44: ='Pod Library'!G52 -> DEV | G44: ='Pod Library'!H52 -> E3 | H44: ='Pod Library'!I52 -> OFF | I44: ='Pod Library'!J52 -> FTC | J44: ='Pod Library'!K52 -> 1 | K44: =SUMIFS('Pod Plan'!$E:$E,'Pod Plan'!$B:$B,$A44,'Pod Plan'!$C:$C,$C44) -> 2 | L44: =J44*K44 -> 2 | M44: =L44*INDEX('Logic Tree'!$J$80:$N$81,MATCH(H44,'Logic Tree'!$I$80:$I$81,0),MATCH(G44,'Logic Tree'!$J$79:$N$79,0)) -> 0.84
A45: 2 | B45: POD | C45: VS1 | D45: CO | E45: ='Pod Library'!F53 -> AI-assisted Data Tester | F45: ='Pod Library'!G53 -> TEST | G45: ='Pod Library'!H53 -> E3 | H45: ='Pod Library'!I53 -> OFF | I45: ='Pod Library'!J53 -> FTC | J45: ='Pod Library'!K53 -> 1 | K45: =SUMIFS('Pod Plan'!$E:$E,'Pod Plan'!$B:$B,$A45,'Pod Plan'!$C:$C,$C45) -> 2 | L45: =J45*K45 -> 2 | M45: =L45*INDEX('Logic Tree'!$J$80:$N$81,MATCH(H45,'Logic Tree'!$I$80:$I$81,0),MATCH(G45,'Logic Tree'!$J$79:$N$79,0)) -> 0.84
A46: 2 | B46: POD | C46: VS1 | D46: FS | E46: ='Pod Library'!F56 -> Product Owner | F46: ='Pod Library'!G56 -> LEAD | G46: ='Pod Library'!H56 -> E4 | H46: ='Pod Library'!I56 -> ON | I46: ='Pod Library'!J56 -> FTE | J46: ='Pod Library'!K56 -> 1 | K46: =SUMIFS('Pod Plan'!$F:$F,'Pod Plan'!$B:$B,$A46,'Pod Plan'!$C:$C,$C46) -> 1 | L46: =J46*K46 -> 1 | M46: =L46*INDEX('Logic Tree'!$J$80:$N$81,MATCH(H46,'Logic Tree'!$I$80:$I$81,0),MATCH(G46,'Logic Tree'!$J$79:$N$79,0)) -> 1.85
A47: 2 | B47: POD | C47: VS1 | D47: FS | E47: ='Pod Library'!F57 -> Pod Delivery Lead (Informatica Tech Lead) | F47: ='Pod Library'!G57 -> LEAD | G47: ='Pod Library'!H57 -> E4 | H47: ='Pod Library'!I57 -> ON | I47: ='Pod Library'!J57 -> FTC | J47: ='Pod Library'!K57 -> 1 | K47: =SUMIFS('Pod Plan'!$F:$F,'Pod Plan'!$B:$B,$A47,'Pod Plan'!$C:$C,$C47) -> 1 | L47: =J47*K47 -> 1 | M47: =L47*INDEX('Logic Tree'!$J$80:$N$81,MATCH(H47,'Logic Tree'!$I$80:$I$81,0),MATCH(G47,'Logic Tree'!$J$79:$N$79,0)) -> 1.85
A48: 2 | B48: POD | C48: VS1 | D48: FS | E48: ='Pod Library'!F58 -> Data Modeler | F48: ='Pod Library'!G58 -> ENG | G48: ='Pod Library'!H58 -> E4 | H48: ='Pod Library'!I58 -> OFF | I48: ='Pod Library'!J58 -> FTC | J48: ='Pod Library'!K58 -> 1 | K48: =SUMIFS('Pod Plan'!$F:$F,'Pod Plan'!$B:$B,$A48,'Pod Plan'!$C:$C,$C48) -> 1 | L48: =J48*K48 -> 1 | M48: =L48*INDEX('Logic Tree'!$J$80:$N$81,MATCH(H48,'Logic Tree'!$I$80:$I$81,0),MATCH(G48,'Logic Tree'!$J$79:$N$79,0)) -> 0.6
A49: 2 | B49: POD | C49: VS1 | D49: FS | E49: ='Pod Library'!F59 -> Business Analyst (bilingual) | F49: ='Pod Library'!G59 -> BA | G49: ='Pod Library'!H59 -> E3 | H49: ='Pod Library'!I59 -> ON | I49: ='Pod Library'!J59 -> FTC | J49: ='Pod Library'!K59 -> 1 | K49: =SUMIFS('Pod Plan'!$F:$F,'Pod Plan'!$B:$B,$A49,'Pod Plan'!$C:$C,$C49) -> 1 | L49: =J49*K49 -> 1 | M49: =L49*INDEX('Logic Tree'!$J$80:$N$81,MATCH(H49,'Logic Tree'!$I$80:$I$81,0),MATCH(G49,'Logic Tree'!$J$79:$N$79,0)) -> 1.35
A50: 2 | B50: POD | C50: VS1 | D50: FS | E50: ='Pod Library'!F60 -> Informatica Developer | F50: ='Pod Library'!G60 -> DEV | G50: ='Pod Library'!H60 -> E3 | H50: ='Pod Library'!I60 -> OFF | I50: ='Pod Library'!J60 -> FTC | J50: ='Pod Library'!K60 -> 2 | K50: =SUMIFS('Pod Plan'!$F:$F,'Pod Plan'!$B:$B,$A50,'Pod Plan'!$C:$C,$C50) -> 1 | L50: =J50*K50 -> 2 | M50: =L50*INDEX('Logic Tree'!$J$80:$N$81,MATCH(H50,'Logic Tree'!$I$80:$I$81,0),MATCH(G50,'Logic Tree'!$J$79:$N$79,0)) -> 0.84
A51: 2 | B51: POD | C51: VS1 | D51: FS | E51: ='Pod Library'!F61 -> AI-assisted Data Tester | F51: ='Pod Library'!G61 -> TEST | G51: ='Pod Library'!H61 -> E3 | H51: ='Pod Library'!I61 -> OFF | I51: ='Pod Library'!J61 -> FTC | J51: ='Pod Library'!K61 -> 1 | K51: =SUMIFS('Pod Plan'!$F:$F,'Pod Plan'!$B:$B,$A51,'Pod Plan'!$C:$C,$C51) -> 1 | L51: =J51*K51 -> 1 | M51: =L51*INDEX('Logic Tree'!$J$80:$N$81,MATCH(H51,'Logic Tree'!$I$80:$I$81,0),MATCH(G51,'Logic Tree'!$J$79:$N$79,0)) -> 0.42
A52: 2 | B52: POD | C52: VS1 | D52: FS | E52: ='Pod Library'!F62 -> L2 Data Support | F52: ='Pod Library'!G62 -> OPS | G52: ='Pod Library'!H62 -> E2 | H52: ='Pod Library'!I62 -> OFF | I52: ='Pod Library'!J62 -> FTC | J52: ='Pod Library'!K62 -> 0 | K52: =SUMIFS('Pod Plan'!$F:$F,'Pod Plan'!$B:$B,$A52,'Pod Plan'!$C:$C,$C52) -> 1 | L52: =J52*K52 -> 0 | M52: =L52*INDEX('Logic Tree'!$J$80:$N$81,MATCH(H52,'Logic Tree'!$I$80:$I$81,0),MATCH(G52,'Logic Tree'!$J$79:$N$79,0)) -> 0
A53: 2 | B53: POD | C53: VS2 | D53: CO | E53: ='Pod Library'!F65 -> Product Owner -Azure Data Platform | F53: ='Pod Library'!G65 -> LEAD | G53: ='Pod Library'!H65 -> E4 | H53: ='Pod Library'!I65 -> ON | I53: ='Pod Library'!J65 -> FTE | J53: ='Pod Library'!K65 -> 1 | K53: =SUMIFS('Pod Plan'!$E:$E,'Pod Plan'!$B:$B,$A53,'Pod Plan'!$C:$C,$C53) -> 3 | L53: =J53*K53 -> 3 | M53: =L53*INDEX('Logic Tree'!$J$80:$N$81,MATCH(H53,'Logic Tree'!$I$80:$I$81,0),MATCH(G53,'Logic Tree'!$J$79:$N$79,0)) -> 5.55
A54: 2 | B54: POD | C54: VS2 | D54: CO | E54: ='Pod Library'!F66 -> Azure Data Architect (MetLife) | F54: ='Pod Library'!G66 -> ENG | G54: ='Pod Library'!H66 -> E5 | H54: ='Pod Library'!I66 -> ON | I54: ='Pod Library'!J66 -> FTE | J54: ='Pod Library'!K66 -> 1 | K54: =SUMIFS('Pod Plan'!$E:$E,'Pod Plan'!$B:$B,$A54,'Pod Plan'!$C:$C,$C54) -> 3 | L54: =J54*K54 -> 3 | M54: =L54*INDEX('Logic Tree'!$J$80:$N$81,MATCH(H54,'Logic Tree'!$I$80:$I$81,0),MATCH(G54,'Logic Tree'!$J$79:$N$79,0)) -> 7.65
A55: 2 | B55: POD | C55: VS2 | D55: CO | E55: ='Pod Library'!F67 -> BI / Reporting Engineer | F55: ='Pod Library'!G67 -> DEV | G55: ='Pod Library'!H67 -> E3 | H55: ='Pod Library'!I67 -> OFF | I55: ='Pod Library'!J67 -> FTC | J55: ='Pod Library'!K67 -> 1 | K55: =SUMIFS('Pod Plan'!$E:$E,'Pod Plan'!$B:$B,$A55,'Pod Plan'!$C:$C,$C55) -> 3 | L55: =J55*K55 -> 3 | M55: =L55*INDEX('Logic Tree'!$J$80:$N$81,MATCH(H55,'Logic Tree'!$I$80:$I$81,0),MATCH(G55,'Logic Tree'!$J$79:$N$79,0)) -> 1.26
A56: 2 | B56: POD | C56: VS2 | D56: CO | E56: ='Pod Library'!F68 -> Synapse Platform Engineer | F56: ='Pod Library'!G68 -> ENG | G56: ='Pod Library'!H68 -> E4 | H56: ='Pod Library'!I68 -> OFF | I56: ='Pod Library'!J68 -> MGCC | J56: ='Pod Library'!K68 -> 1 | K56: =SUMIFS('Pod Plan'!$E:$E,'Pod Plan'!$B:$B,$A56,'Pod Plan'!$C:$C,$C56) -> 3 | L56: =J56*K56 -> 3 | M56: =L56*INDEX('Logic Tree'!$J$80:$N$81,MATCH(H56,'Logic Tree'!$I$80:$I$81,0),MATCH(G56,'Logic Tree'!$J$79:$N$79,0)) -> 1.8
A57: 2 | B57: POD | C57: VS2 | D57: CO | E57: ='Pod Library'!F69 -> Azure Data Engineer | F57: ='Pod Library'!G69 -> DEV | G57: ='Pod Library'!H69 -> E3 | H57: ='Pod Library'!I69 -> OFF | I57: ='Pod Library'!J69 -> MGCC | J57: ='Pod Library'!K69 -> 1 | K57: =SUMIFS('Pod Plan'!$E:$E,'Pod Plan'!$B:$B,$A57,'Pod Plan'!$C:$C,$C57) -> 3 | L57: =J57*K57 -> 3 | M57: =L57*INDEX('Logic Tree'!$J$80:$N$81,MATCH(H57,'Logic Tree'!$I$80:$I$81,0),MATCH(G57,'Logic Tree'!$J$79:$N$79,0)) -> 1.26
A58: 2 | B58: POD | C58: VS2 | D58: CO | E58: ='Pod Library'!F70 -> AI-automation Lead | F58: ='Pod Library'!G70 -> LEAD | G58: ='Pod Library'!H70 -> E4 | H58: ='Pod Library'!I70 -> ON | I58: ='Pod Library'!J70 -> FTC | J58: ='Pod Library'!K70 -> 1 | K58: =SUMIFS('Pod Plan'!$E:$E,'Pod Plan'!$B:$B,$A58,'Pod Plan'!$C:$C,$C58) -> 3 | L58: =J58*K58 -> 3 | M58: =L58*INDEX('Logic Tree'!$J$80:$N$81,MATCH(H58,'Logic Tree'!$I$80:$I$81,0),MATCH(G58,'Logic Tree'!$J$79:$N$79,0)) -> 5.55
A59: 2 | B59: POD | C59: VS2 | D59: CO | E59: ='Pod Library'!F71 -> AI-assisted Data Engineer | F59: ='Pod Library'!G71 -> DEV | G59: ='Pod Library'!H71 -> E3 | H59: ='Pod Library'!I71 -> OFF | I59: ='Pod Library'!J71 -> FTC | J59: ='Pod Library'!K71 -> 1 | K59: =SUMIFS('Pod Plan'!$E:$E,'Pod Plan'!$B:$B,$A59,'Pod Plan'!$C:$C,$C59) -> 3 | L59: =J59*K59 -> 3 | M59: =L59*INDEX('Logic Tree'!$J$80:$N$81,MATCH(H59,'Logic Tree'!$I$80:$I$81,0),MATCH(G59,'Logic Tree'!$J$79:$N$79,0)) -> 1.26
A60: 2 | B60: POD | C60: VS2 | D60: FS | E60: ='Pod Library'!F74 -> Product Owner -Azure Data Platform (shared 0.5) | F60: ='Pod Library'!G74 -> LEAD | G60: ='Pod Library'!H74 -> E4 | H60: ='Pod Library'!I74 -> ON | I60: ='Pod Library'!J74 -> FTE | J60: ='Pod Library'!K74 -> 0.5 | K60: =SUMIFS('Pod Plan'!$F:$F,'Pod Plan'!$B:$B,$A60,'Pod Plan'!$C:$C,$C60) -> 2 | L60: =J60*K60 -> 1 | M60: =L60*INDEX('Logic Tree'!$J$80:$N$81,MATCH(H60,'Logic Tree'!$I$80:$I$81,0),MATCH(G60,'Logic Tree'!$J$79:$N$79,0)) -> 1.85
A61: 2 | B61: POD | C61: VS2 | D61: FS | E61: ='Pod Library'!F75 -> Azure Data Architect (MetLife)- shared | F61: ='Pod Library'!G75 -> ENG | G61: ='Pod Library'!H75 -> E5 | H61: ='Pod Library'!I75 -> ON | I61: ='Pod Library'!J75 -> FTE | J61: ='Pod Library'!K75 -> 0.5 | K61: =SUMIFS('Pod Plan'!$F:$F,'Pod Plan'!$B:$B,$A61,'Pod Plan'!$C:$C,$C61) -> 2 | L61: =J61*K61 -> 1 | M61: =L61*INDEX('Logic Tree'!$J$80:$N$81,MATCH(H61,'Logic Tree'!$I$80:$I$81,0),MATCH(G61,'Logic Tree'!$J$79:$N$79,0)) -> 2.55
A62: 2 | B62: POD | C62: VS2 | D62: FS | E62: ='Pod Library'!F76 -> Pod Delivery Lead ( Azure Data Engineering) | F62: ='Pod Library'!G76 -> LEAD | G62: ='Pod Library'!H76 -> E4 | H62: ='Pod Library'!I76 -> ON | I62: ='Pod Library'!J76 -> FTC | J62: ='Pod Library'!K76 -> 1 | K62: =SUMIFS('Pod Plan'!$F:$F,'Pod Plan'!$B:$B,$A62,'Pod Plan'!$C:$C,$C62) -> 2 | L62: =J62*K62 -> 2 | M62: =L62*INDEX('Logic Tree'!$J$80:$N$81,MATCH(H62,'Logic Tree'!$I$80:$I$81,0),MATCH(G62,'Logic Tree'!$J$79:$N$79,0)) -> 3.7
A63: 2 | B63: POD | C63: VS2 | D63: FS | E63: ='Pod Library'!F77 -> AI-automation Lead | F63: ='Pod Library'!G77 -> ENG | G63: ='Pod Library'!H77 -> E4 | H63: ='Pod Library'!I77 -> ON | I63: ='Pod Library'!J77 -> FTC | J63: ='Pod Library'!K77 -> 1 | K63: =SUMIFS('Pod Plan'!$F:$F,'Pod Plan'!$B:$B,$A63,'Pod Plan'!$C:$C,$C63) -> 2 | L63: =J63*K63 -> 2 | M63: =L63*INDEX('Logic Tree'!$J$80:$N$81,MATCH(H63,'Logic Tree'!$I$80:$I$81,0),MATCH(G63,'Logic Tree'!$J$79:$N$79,0)) -> 3.7
A64: 2 | B64: POD | C64: VS2 | D64: FS | E64: ='Pod Library'!F78 -> Business Analyst (bilingual) | F64: ='Pod Library'!G78 -> BA | G64: ='Pod Library'!H78 -> E3 | H64: ='Pod Library'!I78 -> ON | I64: ='Pod Library'!J78 -> FTC | J64: ='Pod Library'!K78 -> 1 | K64: =SUMIFS('Pod Plan'!$F:$F,'Pod Plan'!$B:$B,$A64,'Pod Plan'!$C:$C,$C64) -> 2 | L64: =J64*K64 -> 2 | M64: =L64*INDEX('Logic Tree'!$J$80:$N$81,MATCH(H64,'Logic Tree'!$I$80:$I$81,0),MATCH(G64,'Logic Tree'!$J$79:$N$79,0)) -> 2.7
A65: 2 | B65: POD | C65: VS2 | D65: FS | E65: ='Pod Library'!F79 -> AI-assisted Data Engineer | F65: ='Pod Library'!G79 -> DEV | G65: ='Pod Library'!H79 -> E3 | H65: ='Pod Library'!I79 -> OFF | I65: ='Pod Library'!J79 -> FTC | J65: ='Pod Library'!K79 -> 2 | K65: =SUMIFS('Pod Plan'!$F:$F,'Pod Plan'!$B:$B,$A65,'Pod Plan'!$C:$C,$C65) -> 2 | L65: =J65*K65 -> 4 | M65: =L65*INDEX('Logic Tree'!$J$80:$N$81,MATCH(H65,'Logic Tree'!$I$80:$I$81,0),MATCH(G65,'Logic Tree'!$J$79:$N$79,0)) -> 1.68
A66: 2 | B66: POD | C66: VS2 | D66: FS | E66: ='Pod Library'!F80 -> BI / Reporting Engineer | F66: ='Pod Library'!G80 -> DEV | G66: ='Pod Library'!H80 -> E3 | H66: ='Pod Library'!I80 -> OFF | I66: ='Pod Library'!J80 -> FTC | J66: ='Pod Library'!K80 -> 1 | K66: =SUMIFS('Pod Plan'!$F:$F,'Pod Plan'!$B:$B,$A66,'Pod Plan'!$C:$C,$C66) -> 2 | L66: =J66*K66 -> 2 | M66: =L66*INDEX('Logic Tree'!$J$80:$N$81,MATCH(H66,'Logic Tree'!$I$80:$I$81,0),MATCH(G66,'Logic Tree'!$J$79:$N$79,0)) -> 0.84
A67: 2 | B67: POD | C67: VS2 | D67: FS | E67: ='Pod Library'!F81 -> AI-assisted Data Tester | F67: ='Pod Library'!G81 -> TEST | G67: ='Pod Library'!H81 -> E3 | H67: ='Pod Library'!I81 -> OFF | I67: ='Pod Library'!J81 -> FTC | J67: ='Pod Library'!K81 -> 1 | K67: =SUMIFS('Pod Plan'!$F:$F,'Pod Plan'!$B:$B,$A67,'Pod Plan'!$C:$C,$C67) -> 2 | L67: =J67*K67 -> 2 | M67: =L67*INDEX('Logic Tree'!$J$80:$N$81,MATCH(H67,'Logic Tree'!$I$80:$I$81,0),MATCH(G67,'Logic Tree'!$J$79:$N$79,0)) -> 0.84
A68: 3 | B68: POD | C68: VS1 | D68: CO | E68: ='Pod Library'!F84 -> Product Owner — Informatica Data Platform | F68: ='Pod Library'!G84 -> LEAD | G68: ='Pod Library'!H84 -> E4 | H68: ='Pod Library'!I84 -> ON | I68: ='Pod Library'!J84 -> FTE | J68: ='Pod Library'!K84 -> 0 | K68: =SUMIFS('Pod Plan'!$E:$E,'Pod Plan'!$B:$B,$A68,'Pod Plan'!$C:$C,$C68) -> 0 | L68: =J68*K68 -> 0 | M68: =L68*INDEX('Logic Tree'!$J$80:$N$81,MATCH(H68,'Logic Tree'!$I$80:$I$81,0),MATCH(G68,'Logic Tree'!$J$79:$N$79,0)) -> 0
A69: 3 | B69: POD | C69: VS1 | D69: CO | E69: ='Pod Library'!F85 -> Data Domain SME | F69: ='Pod Library'!G85 -> BA | G69: ='Pod Library'!H85 -> E4 | H69: ='Pod Library'!I85 -> ON | I69: ='Pod Library'!J85 -> FTE | J69: ='Pod Library'!K85 -> 0 | K69: =SUMIFS('Pod Plan'!$E:$E,'Pod Plan'!$B:$B,$A69,'Pod Plan'!$C:$C,$C69) -> 0 | L69: =J69*K69 -> 0 | M69: =L69*INDEX('Logic Tree'!$J$80:$N$81,MATCH(H69,'Logic Tree'!$I$80:$I$81,0),MATCH(G69,'Logic Tree'!$J$79:$N$79,0)) -> 0
A70: 3 | B70: POD | C70: VS1 | D70: CO | E70: ='Pod Library'!F86 -> Data Modeler | F70: ='Pod Library'!G86 -> ENG | G70: ='Pod Library'!H86 -> E4 | H70: ='Pod Library'!I86 -> OFF | I70: ='Pod Library'!J86 -> MGCC | J70: ='Pod Library'!K86 -> 0 | K70: =SUMIFS('Pod Plan'!$E:$E,'Pod Plan'!$B:$B,$A70,'Pod Plan'!$C:$C,$C70) -> 0 | L70: =J70*K70 -> 0 | M70: =L70*INDEX('Logic Tree'!$J$80:$N$81,MATCH(H70,'Logic Tree'!$I$80:$I$81,0),MATCH(G70,'Logic Tree'!$J$79:$N$79,0)) -> 0
A71: 3 | B71: POD | C71: VS1 | D71: CO | E71: ='Pod Library'!F87 -> Informatica Engineer | F71: ='Pod Library'!G87 -> DEV | G71: ='Pod Library'!H87 -> E3 | H71: ='Pod Library'!I87 -> OFF | I71: ='Pod Library'!J87 -> MGCC | J71: ='Pod Library'!K87 -> 0 | K71: =SUMIFS('Pod Plan'!$E:$E,'Pod Plan'!$B:$B,$A71,'Pod Plan'!$C:$C,$C71) -> 0 | L71: =J71*K71 -> 0 | M71: =L71*INDEX('Logic Tree'!$J$80:$N$81,MATCH(H71,'Logic Tree'!$I$80:$I$81,0),MATCH(G71,'Logic Tree'!$J$79:$N$79,0)) -> 0
A72: 3 | B72: POD | C72: VS1 | D72: CO | E72: ='Pod Library'!F88 -> Pod Delivery Lead (Informatica Tech Lead) | F72: ='Pod Library'!G88 -> LEAD | G72: ='Pod Library'!H88 -> E4 | H72: ='Pod Library'!I88 -> OFF | I72: ='Pod Library'!J88 -> FTC | J72: ='Pod Library'!K88 -> 0 | K72: =SUMIFS('Pod Plan'!$E:$E,'Pod Plan'!$B:$B,$A72,'Pod Plan'!$C:$C,$C72) -> 0 | L72: =J72*K72 -> 0 | M72: =L72*INDEX('Logic Tree'!$J$80:$N$81,MATCH(H72,'Logic Tree'!$I$80:$I$81,0),MATCH(G72,'Logic Tree'!$J$79:$N$79,0)) -> 0
A73: 3 | B73: POD | C73: VS1 | D73: CO | E73: ='Pod Library'!F89 -> Informatica Engineer | F73: ='Pod Library'!G89 -> DEV | G73: ='Pod Library'!H89 -> E3 | H73: ='Pod Library'!I89 -> OFF | I73: ='Pod Library'!J89 -> FTC | J73: ='Pod Library'!K89 -> 0 | K73: =SUMIFS('Pod Plan'!$E:$E,'Pod Plan'!$B:$B,$A73,'Pod Plan'!$C:$C,$C73) -> 0 | L73: =J73*K73 -> 0 | M73: =L73*INDEX('Logic Tree'!$J$80:$N$81,MATCH(H73,'Logic Tree'!$I$80:$I$81,0),MATCH(G73,'Logic Tree'!$J$79:$N$79,0)) -> 0
A74: 3 | B74: POD | C74: VS1 | D74: FS | E74: ='Pod Library'!F92 -> Product Owner | F74: ='Pod Library'!G92 -> LEAD | G74: ='Pod Library'!H92 -> E4 | H74: ='Pod Library'!I92 -> ON | I74: ='Pod Library'!J92 -> FTE | J74: ='Pod Library'!K92 -> 0 | K74: =SUMIFS('Pod Plan'!$F:$F,'Pod Plan'!$B:$B,$A74,'Pod Plan'!$C:$C,$C74) -> 0 | L74: =J74*K74 -> 0 | M74: =L74*INDEX('Logic Tree'!$J$80:$N$81,MATCH(H74,'Logic Tree'!$I$80:$I$81,0),MATCH(G74,'Logic Tree'!$J$79:$N$79,0)) -> 0
A75: 3 | B75: POD | C75: VS1 | D75: FS | E75: ='Pod Library'!F93 -> Pod Delivery Lead (Informatica Tech Lead) | F75: ='Pod Library'!G93 -> LEAD | G75: ='Pod Library'!H93 -> E4 | H75: ='Pod Library'!I93 -> OFF | I75: ='Pod Library'!J93 -> FTC | J75: ='Pod Library'!K93 -> 0 | K75: =SUMIFS('Pod Plan'!$F:$F,'Pod Plan'!$B:$B,$A75,'Pod Plan'!$C:$C,$C75) -> 0 | L75: =J75*K75 -> 0 | M75: =L75*INDEX('Logic Tree'!$J$80:$N$81,MATCH(H75,'Logic Tree'!$I$80:$I$81,0),MATCH(G75,'Logic Tree'!$J$79:$N$79,0)) -> 0
A76: 3 | B76: POD | C76: VS1 | D76: FS | E76: ='Pod Library'!F94 -> Business Analyst (bilingual) | F76: ='Pod Library'!G94 -> BA | G76: ='Pod Library'!H94 -> E3 | H76: ='Pod Library'!I94 -> ON | I76: ='Pod Library'!J94 -> FTC | J76: ='Pod Library'!K94 -> 0 | K76: =SUMIFS('Pod Plan'!$F:$F,'Pod Plan'!$B:$B,$A76,'Pod Plan'!$C:$C,$C76) -> 0 | L76: =J76*K76 -> 0 | M76: =L76*INDEX('Logic Tree'!$J$80:$N$81,MATCH(H76,'Logic Tree'!$I$80:$I$81,0),MATCH(G76,'Logic Tree'!$J$79:$N$79,0)) -> 0
A77: 3 | B77: POD | C77: VS1 | D77: FS | E77: ='Pod Library'!F95 -> AI automation Lead | F77: ='Pod Library'!G95 -> ENG | G77: ='Pod Library'!H95 -> E4 | H77: ='Pod Library'!I95 -> OFF | I77: ='Pod Library'!J95 -> FTC | J77: ='Pod Library'!K95 -> 0 | K77: =SUMIFS('Pod Plan'!$F:$F,'Pod Plan'!$B:$B,$A77,'Pod Plan'!$C:$C,$C77) -> 0 | L77: =J77*K77 -> 0 | M77: =L77*INDEX('Logic Tree'!$J$80:$N$81,MATCH(H77,'Logic Tree'!$I$80:$I$81,0),MATCH(G77,'Logic Tree'!$J$79:$N$79,0)) -> 0
A78: 3 | B78: POD | C78: VS1 | D78: FS | E78: ='Pod Library'!F96 -> Informatica Engineer | F78: ='Pod Library'!G96 -> DEV | G78: ='Pod Library'!H96 -> E3 | H78: ='Pod Library'!I96 -> OFF | I78: ='Pod Library'!J96 -> FTC | J78: ='Pod Library'!K96 -> 0 | K78: =SUMIFS('Pod Plan'!$F:$F,'Pod Plan'!$B:$B,$A78,'Pod Plan'!$C:$C,$C78) -> 0 | L78: =J78*K78 -> 0 | M78: =L78*INDEX('Logic Tree'!$J$80:$N$81,MATCH(H78,'Logic Tree'!$I$80:$I$81,0),MATCH(G78,'Logic Tree'!$J$79:$N$79,0)) -> 0
A79: 3 | B79: POD | C79: VS1 | D79: FS | E79: ='Pod Library'!F97 -> AI-assisted Data Tester | F79: ='Pod Library'!G97 -> TEST | G79: ='Pod Library'!H97 -> E3 | H79: ='Pod Library'!I97 -> OFF | I79: ='Pod Library'!J97 -> FTC | J79: ='Pod Library'!K97 -> 0 | K79: =SUMIFS('Pod Plan'!$F:$F,'Pod Plan'!$B:$B,$A79,'Pod Plan'!$C:$C,$C79) -> 0 | L79: =J79*K79 -> 0 | M79: =L79*INDEX('Logic Tree'!$J$80:$N$81,MATCH(H79,'Logic Tree'!$I$80:$I$81,0),MATCH(G79,'Logic Tree'!$J$79:$N$79,0)) -> 0
A80: 3 | B80: POD | C80: VS2 | D80: CO | E80: ='Pod Library'!F100 -> Product Owner — Azure Data Platform | F80: ='Pod Library'!G100 -> LEAD | G80: ='Pod Library'!H100 -> E4 | H80: ='Pod Library'!I100 -> ON | I80: ='Pod Library'!J100 -> FTE | J80: ='Pod Library'!K100 -> 1 | K80: =SUMIFS('Pod Plan'!$E:$E,'Pod Plan'!$B:$B,$A80,'Pod Plan'!$C:$C,$C80) -> 4 | L80: =J80*K80 -> 4 | M80: =L80*INDEX('Logic Tree'!$J$80:$N$81,MATCH(H80,'Logic Tree'!$I$80:$I$81,0),MATCH(G80,'Logic Tree'!$J$79:$N$79,0)) -> 7.4
A81: 3 | B81: POD | C81: VS2 | D81: CO | E81: ='Pod Library'!F101 -> Azure Data Architect (MetLife) | F81: ='Pod Library'!G101 -> ENG | G81: ='Pod Library'!H101 -> E5 | H81: ='Pod Library'!I101 -> ON | I81: ='Pod Library'!J101 -> FTE | J81: ='Pod Library'!K101 -> 1 | K81: =SUMIFS('Pod Plan'!$E:$E,'Pod Plan'!$B:$B,$A81,'Pod Plan'!$C:$C,$C81) -> 4 | L81: =J81*K81 -> 4 | M81: =L81*INDEX('Logic Tree'!$J$80:$N$81,MATCH(H81,'Logic Tree'!$I$80:$I$81,0),MATCH(G81,'Logic Tree'!$J$79:$N$79,0)) -> 10.2
A82: 3 | B82: POD | C82: VS2 | D82: CO | E82: ='Pod Library'!F102 -> BI / Reporting Engineer | F82: ='Pod Library'!G102 -> DEV | G82: ='Pod Library'!H102 -> E3 | H82: ='Pod Library'!I102 -> OFF | I82: ='Pod Library'!J102 -> FTC | J82: ='Pod Library'!K102 -> 1 | K82: =SUMIFS('Pod Plan'!$E:$E,'Pod Plan'!$B:$B,$A82,'Pod Plan'!$C:$C,$C82) -> 4 | L82: =J82*K82 -> 4 | M82: =L82*INDEX('Logic Tree'!$J$80:$N$81,MATCH(H82,'Logic Tree'!$I$80:$I$81,0),MATCH(G82,'Logic Tree'!$J$79:$N$79,0)) -> 1.68
A83: 3 | B83: POD | C83: VS2 | D83: CO | E83: ='Pod Library'!F103 -> Synapse Platform Engineer | F83: ='Pod Library'!G103 -> ENG | G83: ='Pod Library'!H103 -> E4 | H83: ='Pod Library'!I103 -> OFF | I83: ='Pod Library'!J103 -> MGCC | J83: ='Pod Library'!K103 -> 1 | K83: =SUMIFS('Pod Plan'!$E:$E,'Pod Plan'!$B:$B,$A83,'Pod Plan'!$C:$C,$C83) -> 4 | L83: =J83*K83 -> 4 | M83: =L83*INDEX('Logic Tree'!$J$80:$N$81,MATCH(H83,'Logic Tree'!$I$80:$I$81,0),MATCH(G83,'Logic Tree'!$J$79:$N$79,0)) -> 2.4
A84: 3 | B84: POD | C84: VS2 | D84: CO | E84: ='Pod Library'!F104 -> AI-assisted Data Engineer | F84: ='Pod Library'!G104 -> DEV | G84: ='Pod Library'!H104 -> E3 | H84: ='Pod Library'!I104 -> OFF | I84: ='Pod Library'!J104 -> MGCC | J84: ='Pod Library'!K104 -> 1 | K84: =SUMIFS('Pod Plan'!$E:$E,'Pod Plan'!$B:$B,$A84,'Pod Plan'!$C:$C,$C84) -> 4 | L84: =J84*K84 -> 4 | M84: =L84*INDEX('Logic Tree'!$J$80:$N$81,MATCH(H84,'Logic Tree'!$I$80:$I$81,0),MATCH(G84,'Logic Tree'!$J$79:$N$79,0)) -> 1.68
A85: 3 | B85: POD | C85: VS2 | D85: CO | E85: ='Pod Library'!F106 -> AI-automation Lead | F85: ='Pod Library'!G106 -> LEAD | G85: ='Pod Library'!H106 -> E4 | H85: ='Pod Library'!I106 -> ON | I85: ='Pod Library'!J106 -> FTC | J85: ='Pod Library'!K106 -> 1 | K85: =SUMIFS('Pod Plan'!$E:$E,'Pod Plan'!$B:$B,$A85,'Pod Plan'!$C:$C,$C85) -> 4 | L85: =J85*K85 -> 4 | M85: =L85*INDEX('Logic Tree'!$J$80:$N$81,MATCH(H85,'Logic Tree'!$I$80:$I$81,0),MATCH(G85,'Logic Tree'!$J$79:$N$79,0)) -> 7.4
A86: 3 | B86: POD | C86: VS2 | D86: CO | E86: ='Pod Library'!F105 -> AI-assisted Data Tester | F86: ='Pod Library'!G105 -> TEST | G86: ='Pod Library'!H105 -> E3 | H86: ='Pod Library'!I105 -> OFF | I86: ='Pod Library'!J105 -> MGCC | J86: ='Pod Library'!K105 -> 1 | K86: =SUMIFS('Pod Plan'!$E:$E,'Pod Plan'!$B:$B,$A86,'Pod Plan'!$C:$C,$C86) -> 4 | L86: =J86*K86 -> 4 | M86: =L86*INDEX('Logic Tree'!$J$80:$N$81,MATCH(H86,'Logic Tree'!$I$80:$I$81,0),MATCH(G86,'Logic Tree'!$J$79:$N$79,0)) -> 1.68
A87: 3 | B87: POD | C87: VS2 | D87: FS | E87: ='Pod Library'!F109 -> Product Owner -Azure Data Platform (shared 0.5) | F87: ='Pod Library'!G109 -> LEAD | G87: ='Pod Library'!H109 -> E4 | H87: ='Pod Library'!I109 -> ON | I87: ='Pod Library'!J109 -> FTE | J87: ='Pod Library'!K109 -> 0.5 | K87: =SUMIFS('Pod Plan'!$F:$F,'Pod Plan'!$B:$B,$A87,'Pod Plan'!$C:$C,$C87) -> 2 | L87: =J87*K87 -> 1 | M87: =L87*INDEX('Logic Tree'!$J$80:$N$81,MATCH(H87,'Logic Tree'!$I$80:$I$81,0),MATCH(G87,'Logic Tree'!$J$79:$N$79,0)) -> 1.85
A88: 3 | B88: POD | C88: VS2 | D88: FS | E88: ='Pod Library'!F110 -> Azure Data Architect (shared 0.5) | F88: ='Pod Library'!G110 -> ENG | G88: ='Pod Library'!H110 -> E5 | H88: ='Pod Library'!I110 -> ON | I88: ='Pod Library'!J110 -> FTE | J88: ='Pod Library'!K110 -> 0.5 | K88: =SUMIFS('Pod Plan'!$F:$F,'Pod Plan'!$B:$B,$A88,'Pod Plan'!$C:$C,$C88) -> 2 | L88: =J88*K88 -> 1 | M88: =L88*INDEX('Logic Tree'!$J$80:$N$81,MATCH(H88,'Logic Tree'!$I$80:$I$81,0),MATCH(G88,'Logic Tree'!$J$79:$N$79,0)) -> 2.55
A89: 3 | B89: POD | C89: VS2 | D89: FS | E89: ='Pod Library'!F111 -> Pod Delivery Lead ( Azure Data Engineering) | F89: ='Pod Library'!G111 -> LEAD | G89: ='Pod Library'!H111 -> E4 | H89: ='Pod Library'!I111 -> ON | I89: ='Pod Library'!J111 -> FTC | J89: ='Pod Library'!K111 -> 1 | K89: =SUMIFS('Pod Plan'!$F:$F,'Pod Plan'!$B:$B,$A89,'Pod Plan'!$C:$C,$C89) -> 2 | L89: =J89*K89 -> 2 | M89: =L89*INDEX('Logic Tree'!$J$80:$N$81,MATCH(H89,'Logic Tree'!$I$80:$I$81,0),MATCH(G89,'Logic Tree'!$J$79:$N$79,0)) -> 3.7
A90: 3 | B90: POD | C90: VS2 | D90: FS | E90: ='Pod Library'!F112 -> AI-automation Lead | F90: ='Pod Library'!G112 -> ENG | G90: ='Pod Library'!H112 -> E4 | H90: ='Pod Library'!I112 -> OFF | I90: ='Pod Library'!J112 -> FTC | J90: ='Pod Library'!K112 -> 1 | K90: =SUMIFS('Pod Plan'!$F:$F,'Pod Plan'!$B:$B,$A90,'Pod Plan'!$C:$C,$C90) -> 2 | L90: =J90*K90 -> 2 | M90: =L90*INDEX('Logic Tree'!$J$80:$N$81,MATCH(H90,'Logic Tree'!$I$80:$I$81,0),MATCH(G90,'Logic Tree'!$J$79:$N$79,0)) -> 1.2
A91: 3 | B91: POD | C91: VS2 | D91: FS | E91: ='Pod Library'!F113 -> Business Analyst (bilingual) | F91: ='Pod Library'!G113 -> BA | G91: ='Pod Library'!H113 -> E3 | H91: ='Pod Library'!I113 -> ON | I91: ='Pod Library'!J113 -> FTC | J91: ='Pod Library'!K113 -> 1 | K91: =SUMIFS('Pod Plan'!$F:$F,'Pod Plan'!$B:$B,$A91,'Pod Plan'!$C:$C,$C91) -> 2 | L91: =J91*K91 -> 2 | M91: =L91*INDEX('Logic Tree'!$J$80:$N$81,MATCH(H91,'Logic Tree'!$I$80:$I$81,0),MATCH(G91,'Logic Tree'!$J$79:$N$79,0)) -> 2.7
A92: 3 | B92: POD | C92: VS2 | D92: FS | E92: ='Pod Library'!F114 -> AI-assisted Data Engineer | F92: ='Pod Library'!G114 -> DEV | G92: ='Pod Library'!H114 -> E3 | H92: ='Pod Library'!I114 -> OFF | I92: ='Pod Library'!J114 -> FTC | J92: ='Pod Library'!K114 -> 1 | K92: =SUMIFS('Pod Plan'!$F:$F,'Pod Plan'!$B:$B,$A92,'Pod Plan'!$C:$C,$C92) -> 2 | L92: =J92*K92 -> 2 | M92: =L92*INDEX('Logic Tree'!$J$80:$N$81,MATCH(H92,'Logic Tree'!$I$80:$I$81,0),MATCH(G92,'Logic Tree'!$J$79:$N$79,0)) -> 0.84
A93: 3 | B93: POD | C93: VS2 | D93: FS | E93: ='Pod Library'!F115 -> BI / Reporting Engineer | F93: ='Pod Library'!G116 -> TEST | G93: ='Pod Library'!H116 -> E2 | H93: ='Pod Library'!I116 -> OFF | I93: ='Pod Library'!J116 -> FTC | J93: ='Pod Library'!K116 -> 1 | K93: =SUMIFS('Pod Plan'!$F:$F,'Pod Plan'!$B:$B,$A93,'Pod Plan'!$C:$C,$C93) -> 2 | L93: =J93*K93 -> 2 | M93: =L93*INDEX('Logic Tree'!$J$80:$N$81,MATCH(H93,'Logic Tree'!$I$80:$I$81,0),MATCH(G93,'Logic Tree'!$J$79:$N$79,0)) -> 0.6
A94: 3 | B94: POD | C94: VS2 | D94: FS | E94: ='Pod Library'!F116 -> AI-assised Data Tester | F94: ='Pod Library'!G116 -> TEST | G94: ='Pod Library'!H116 -> E2 | H94: ='Pod Library'!I116 -> OFF | I94: ='Pod Library'!J116 -> FTC | J94: ='Pod Library'!K116 -> 1 | K94: =SUMIFS('Pod Plan'!$F:$F,'Pod Plan'!$B:$B,$A94,'Pod Plan'!$C:$C,$C94) -> 2 | L94: =J94*K94 -> 2 | M94: =L94*INDEX('Logic Tree'!$J$80:$N$81,MATCH(H94,'Logic Tree'!$I$80:$I$81,0),MATCH(G94,'Logic Tree'!$J$79:$N$79,0)) -> 0.6
A95: ='Horizontal Teams'!B5 -> 1 | B95: HZ | C95: ='Horizontal Teams'!C5 -> H1 | D95: HZ | E95: ='Horizontal Teams'!E5 -> Service Delivery Lead | F95: ='Horizontal Teams'!F5 -> LEAD | G95: ='Horizontal Teams'!G5 -> E4 | H95: ='Horizontal Teams'!H5 -> ON | I95: ='Horizontal Teams'!I5 -> FTC | J95: ='Horizontal Teams'!J5 -> 1 | K95: 1 | L95: =J95*K95 -> 1 | M95: =L95*INDEX('Logic Tree'!$J$80:$N$81,MATCH(H95,'Logic Tree'!$I$80:$I$81,0),MATCH(G95,'Logic Tree'!$J$79:$N$79,0)) -> 1.85
A96: ='Horizontal Teams'!B6 -> 1 | B96: HZ | C96: ='Horizontal Teams'!C6 -> H1 | D96: HZ | E96: ='Horizontal Teams'!E6 -> MetLife Data Infrastructure Domain Lead | F96: ='Horizontal Teams'!F6 -> OPS | G96: ='Horizontal Teams'!G6 -> E4 | H96: ='Horizontal Teams'!H6 -> ON | I96: ='Horizontal Teams'!I6 -> FTE | J96: ='Horizontal Teams'!J6 -> 1 | K96: 1 | L96: =J96*K96 -> 1 | M96: =L96*INDEX('Logic Tree'!$J$80:$N$81,MATCH(H96,'Logic Tree'!$I$80:$I$81,0),MATCH(G96,'Logic Tree'!$J$79:$N$79,0)) -> 1.85
A97: ='Horizontal Teams'!B7 -> 1 | B97: HZ | C97: ='Horizontal Teams'!C7 -> H1 | D97: HZ | E97: ='Horizontal Teams'!E7 -> L2 Support Data Engr Lead | F97: ='Horizontal Teams'!F7 -> OPS | G97: ='Horizontal Teams'!G7 -> E2 | H97: ='Horizontal Teams'!H7 -> ON | I97: ='Horizontal Teams'!I7 -> FTC | J97: ='Horizontal Teams'!J7 -> 1 | K97: 1 | L97: =J97*K97 -> 1 | M97: =L97*INDEX('Logic Tree'!$J$80:$N$81,MATCH(H97,'Logic Tree'!$I$80:$I$81,0),MATCH(G97,'Logic Tree'!$J$79:$N$79,0)) -> 1
A98: ='Horizontal Teams'!B8 -> 1 | B98: HZ | C98: ='Horizontal Teams'!C8 -> H1 | D98: HZ | E98: ='Horizontal Teams'!E8 -> L2 Support Data Engr-Informatica and Azure | F98: ='Horizontal Teams'!F8 -> OPS | G98: ='Horizontal Teams'!G8 -> E2 | H98: ='Horizontal Teams'!H8 -> OFF | I98: ='Horizontal Teams'!I8 -> FTC | J98: ='Horizontal Teams'!J8 -> 3 | K98: 1 | L98: =J98*K98 -> 3 | M98: =L98*INDEX('Logic Tree'!$J$80:$N$81,MATCH(H98,'Logic Tree'!$I$80:$I$81,0),MATCH(G98,'Logic Tree'!$J$79:$N$79,0)) -> 0.9
A99: ='Horizontal Teams'!B9 -> 1 | B99: HZ | C99: ='Horizontal Teams'!C9 -> H1 | D99: HZ | E99: ='Horizontal Teams'!E9 -> Data Platform SRE | F99: ='Horizontal Teams'!F9 -> ENG | G99: ='Horizontal Teams'!G9 -> E3 | H99: ='Horizontal Teams'!H9 -> OFF | I99: ='Horizontal Teams'!I9 -> MGCC | J99: ='Horizontal Teams'!J9 -> 6 | K99: 1 | L99: =J99*K99 -> 6 | M99: =L99*INDEX('Logic Tree'!$J$80:$N$81,MATCH(H99,'Logic Tree'!$I$80:$I$81,0),MATCH(G99,'Logic Tree'!$J$79:$N$79,0)) -> 2.52
A100: ='Horizontal Teams'!B11 -> 1 | B100: HZ | C100: ='Horizontal Teams'!C11 -> H2 | D100: HZ | E100: ='Horizontal Teams'!E11 -> Head of Data Platform Testing (MetLife) | F100: ='Horizontal Teams'!F11 -> LEAD | G100: ='Horizontal Teams'!G11 -> E5 | H100: ='Horizontal Teams'!H11 -> ON | I100: ='Horizontal Teams'!I11 -> FTE | J100: ='Horizontal Teams'!J11 -> 1 | K100: 1 | L100: =J100*K100 -> 1 | M100: =L100*INDEX('Logic Tree'!$J$80:$N$81,MATCH(H100,'Logic Tree'!$I$80:$I$81,0),MATCH(G100,'Logic Tree'!$J$79:$N$79,0)) -> 2.55
A101: ='Horizontal Teams'!B12 -> 1 | B101: HZ | C101: ='Horizontal Teams'!C12 -> H2 | D101: HZ | E101: ='Horizontal Teams'!E12 -> Data Platform Test Lead | F101: ='Horizontal Teams'!F12 -> TEST | G101: ='Horizontal Teams'!G12 -> E4 | H101: ='Horizontal Teams'!H12 -> ON | I101: ='Horizontal Teams'!I12 -> FTC | J101: ='Horizontal Teams'!J12 -> 1 | K101: 1 | L101: =J101*K101 -> 1 | M101: =L101*INDEX('Logic Tree'!$J$80:$N$81,MATCH(H101,'Logic Tree'!$I$80:$I$81,0),MATCH(G101,'Logic Tree'!$J$79:$N$79,0)) -> 1.85
...
