Workbook

Sheet README
A1: Sales / Insurance Recruitment — domain framework v6
A2: Rebuilt on Golden Application Inventory v4. The 99 Capgemini people already on these applications are identified by band and location, and they roll into Year 1 exactly as they are. MetLife's own value stream taxonomy replaces the cut we invented.
A4: WHAT GOLDEN INVENTORY v4 CHANGED FOR THIS DOMAIN
B5: We already hold 99 people here, and now we know who they are | C5: The T3 headcount reconciliation places 99 of the 277 named Capgemini people on Sales applications: 97 in India and 2 in Japan, banded E1 10 · E2 39 · E3 42 · E4 6 · E5 2 across both locations. 55.5 of them sit on JP-GSSP and 31.7 on JP-Banca Report. They are not a modelling assumption — they are on the payroll today.
B6: So the Year-1 offshore anatomy is designed around them, not the other way round | C6: The v5 pod library asked for 95.5 E2 seats offshore and 11.7 E3. We actually hold 39 E2 and 40 E3, plus 10 E1 and 8 seniors the anatomy had no offshore seat for at all. Every offshore unit in the library has been re-banded so the people we have fit the seats we designed. Year 1 now needs 11.9 E1 · 46.5 E2 · 42.0 E3 · 4.8 E4 · 2.0 E5 against a supply of 10 · 39 · 40 · 6 · 2 — the 97 who are offshore, the 2 in Japan sitting in onshore seats.
B7: MetLife's own value streams | C7: F2F Illustlation 230.871 (4 apps) · Banca Illustlation 168.917 (4) · F2F Agent Enablement 43.562 (1) · F2F SalesSupport 23.123 (4). The streams we invented in v4 and v5 are gone.
B8: There is effectively no partner dependency here | C8: Golden v4 names the vendor on every application. FSI holds 0.8 of the 284.5 vendor units in this 領域 and NCD holds 23.0. Contract Management needs a sub-contract to hold its service on day one; this domain does not. That contrast is deliberate and it is the clearest evidence that the partner strategy is targeted rather than generic.
A9: HOW THE INHERITED POPULATION IS EVOLVED, YEARS 2 TO 5
B10: Attrition and promotion, not an instruction | C10: The cohort is rolled forward with band-differentiated attrition — 22% at E1 offshore falling to 6% at E5, 10% to 4% onshore — and promotion applied to the survivors. 99 people become 83.8 · 71.6 · 61.6 · 53.5, and the senior share rises 8.1% → 14.0% → 20.5% → 27.3% → 34.3% without anyone being told to reshape anything.
B11: Which is most of the pyramid-to-diamond story | C11: The market does the work. What the solution has to do is stop hiring at the base and keep promoting, and the diamond arrives. That is a far more defensible claim than asserting a target shape and back-filling to it.
B12: Where it does not fit, the workbook says so | C12: Year 2 leaves 6.7 more E2 people than there are E2 seats; Year 4 leaves 7.8 more E3 than E3 seats. Both are absorbed by promotion into the band above, and both are reported as a reskill obligation rather than netted away.
B13: Solution tenets, not hard constraints | C13: The pyramid-to-diamond tenet is applied as a direction of travel. Where the inherited population makes the target shape unreachable in a given year, the model follows the people and records the deviation.
A14: WHAT IS RETAINED FROM v5
B15: The whole chain | C15: Six archetypes → AI and offshore ceilings → realisation → capability → carry-forward and pre-load → headcount target → unit design → seat ledger → every roll-up. Nothing in the structure moved. The J offshore ceiling is re-cut from 15% to 12% to match Golden v4, which moves the domain ceiling from 81.22% to 81.09%.
B16: Every Year-1 reconciliation | C16: Effort, sourcing, location and all six role lines still reconcile to Appendix 3 v3. Re-banding the offshore seats changes who sits in them, not how many or in what role.
B17: The measured offshore start | C17: 43.1% on day one — 107.1 offshore plus 93.8 MGCC — closing to 78.1% by Year 5 against a ceiling of 81.1%.
A18: WHAT TO RAISE
B19: The 99 is an allocation, not a register | C19: People are known by team, and teams are mapped to applications using the client's own 'CG HC by EAI' shape rescaled to the 277-name roster. It is the best available reconciliation of four sources that disagree (277 / 283 / 450 / 528), and it should be validated with T3 before it is quoted to MetLife.
B20: 185 of the 284.5 vendor units are not people we hold today | C20: Capgemini is the named incumbent on 177.3 of the vendor units but we hold only 99 heads against them; 83.4 units sit with unnamed vendors, 23.0 with NCD and 0.8 with FSI. Year 1 assumes Capgemini staffs all 284.5 from day one, which is a transition commitment of real size and is priced as a hire rather than a rebadge.
B21: Two people in Japan | C21: Of 99 inherited, 2 are onshore. Every bilingual onshore seat in Year 1 — 177.2 of them — is a hire or a redeployment into Tokyo. That is the single largest delivery risk in this 領域 and it is a recruitment problem, not a solution-design one.

Sheet Change Log v5 → v6
A1: What Golden Inventory v4 changed, and whether the core basis was shaken
A2: The test applied to each item: does the new evidence change an input, or does it change the structure that consumes the input? Only the second needs a rebuild.
B4: Element | C4: v5 basis | D4: v6 basis | E4: Verdict | F4: What it moved
B5: Baseline effort, sourcing, location, roles | C5: Appendix 3 v3 | D5: Appendix 3 v3, unchanged | E5: UNCHANGED | F5: 466.472 units, 13 applications, FTC 284.543 / FTE 88.129 / MGCC 93.800, onshore 177.368 / offshore 107.092.
B6: The Capgemini population already on these applications | C6: Not modelled. Every Year-1 seat treated as new. | D6: 99 named people: 97 India, 2 Japan, E1 10 · E2 39 · E3 42 · E4 6 · E5 2 | E6: NEW | F6: The largest addition in this version. 35% of the Capgemini seats in Year 1 are already filled, and their band and location are given rather than chosen.
B7: Offshore band mix in the unit library | C7: E2 95.5 and E3 11.7 in Year 1 — a hiring pyramid | D7: E1 11.9 · E2 46.5 · E3 42.0 · E4 4.8 · E5 2.0 | E7: REBUILT | F7: The library asked for a shape we do not have. Every offshore seat is re-banded so the inherited population fits. Roles, counts and every Year-1 reconciliation are untouched — only the band moves.
B8: Years 2 to 5 talent shape | C8: Asserted: a diamond by Year 4 | D8: Derived: band-differentiated attrition plus promotion, rolled forward | E8: REBUILT | F8: Senior share of the inherited cohort goes 8.1 → 14.0 → 20.5 → 27.3 → 34.3%. The diamond is now an outcome of the market rather than a target we set ourselves.
B9: Value streams | C9: Four streams, our own cut | D9: Four streams, MetLife's own taxonomy | E9: REBUILT | F9: F2F Illustlation 230.871 · Banca Illustlation 168.917 · F2F Agent Enablement 43.562 · F2F SalesSupport 23.123. The pod plan is re-cut stream by stream; the agile conversion quarters move with it.
B10: Vendor presence | C10: Not known | D10: Named per application in Golden v4 | E10: NEW | F10: FSI 0.8 units and NCD 23.0 of 284.5. Effectively no partner dependency in this 領域 — the opposite of Contract Management, where FSI holds 144.9 of 203.9.
B11: Archetypes, ceilings, realisation, carry-forward | C11: As built | D11: Unchanged | E11: RETAINED | F11: M 83.6% · D 10.4% · J 4.1% · P 1.6% · T 0.3%. AI ceiling 44.99%, offshore ceiling 81.09%, applied productivity 0 / 22.9 / 37.9 / 46.4 / 51.4%.
B12: Transfer mechanic | C12: One event at the end of Year 3 on the exit position | D12: Unchanged | E12: RETAINED | F12: No partner here, so the whole vendor population is transferable and the 50:50 closes inside the domain.
B13: Seat ledger, cost index, AMS sizing | C13: As built | D13: Unchanged | E13: RETAINED | F13: One sheet added — Inherited Workforce. Nothing removed.
A15: THE RULE APPLIED
B16: • Three rebuilds, and all three are in the staffing half of the model. The productivity half — ceilings, realisation, carry-forward, pre-load — is untouched for the second version running. That is worth stating plainly: the framework is stable and it is the workforce evidence that keeps moving.
B17: • Re-banding the offshore seats is the change with the most reach and the least visible effect. Year 1 still reconciles to Appendix 3 on all twelve quantities, because a Tester is a Tester whether they are E2 or E3. What changes is the cost index, the promotion plan and whether the Year-1 team can actually be assembled.
B18: • The pyramid-to-diamond tenet has moved from an assertion to a derivation, which means it can now be argued with. The attrition and promotion rates on the Inherited Workforce sheet are the two numbers to challenge.
B19: • Every other domain team must now re-run three things: the offshore band mix in their unit library, the inherited-population overlay, and their value streams against MetLife's taxonomy.

Sheet Change Control
A1: Change control — what must still hold after you edit a seat count
A2: Pod Library column J and Horizontal Teams column I are INPUTS. You may change them. Holding the yearly total is necessary but not sufficient — these are the other things that have to survive the edit. Every check below is live.
A4: A. WHERE THESE NUMBERS GO
B5: • Pod Library J and Horizontal Teams I are hard-typed values, not formulas. Nothing upstream computes them — they are the design. Everything downstream is derived from them.
B6: • Seat Ledger reads them cell by cell (912 references to Pod Library, 630 to Horizontal Teams) and multiplies by the unit count on Pod Plan. Team Build-Up, Cost & Commercial, Inherited Workforce and Unit Cost Sensitivity are all SUMIFS over the Seat Ledger. Change a seat and every one of them moves.
B7: • THE ONE THAT SURPRISES PEOPLE: the Logic Tree reads the roster back. Partner seats (row 59) drive the partner share (row 60), the span-of-control factor (row 61), the applied operating-model gain (row 43), capability (row 45) and therefore the HEADCOUNT TARGET itself (row 53). Changing partner seats moves the target you are trying to hit. It converges, but it does not stand still.
B8: • What does NOT move: the effort baseline, the archetype mix, the AI and offshore ceilings, the realisation curve and the agile conversion quarters. Those are inputs on the Logic Tree and Delivery Mode.
A10: B. THE INVARIANTS — all of these must stay green
B11: Check | C11: Y1 | D11: Y2 | E11: Y3 | F11: Y4 | G11: Y5 | H11: Tolerance | I11: Status
B12: Headcount delivered minus Logic Tree target | C12: ='Team Build-Up'!C12 -> 0.0277 | D12: ='Team Build-Up'!D12 -> 0.20246229 | E12: ='Team Build-Up'!E12 -> 0.1981292 | F12: ='Team Build-Up'!F12 -> 0.1723206 | G12: ='Team Build-Up'!G12 -> 0.027574688 | H12: ± 1.5 | I12: =IF(MAX(ABS(C12),ABS(D12),ABS(E12),ABS(F12),ABS(G12))<=1.5,"OK","CHECK") -> OK | J12: The productivity commitment. If you add seats you must remove others.
B13: Capgemini share inside each POD | C13: =IFERROR((SUMIFS('Pod Library'!$J$5:$J$111,'Pod Library'!$B$5:$B$111,1,'Pod Library'!$C$5:$C$111,"POD",'Pod Library'!$I$5:$I$111,"FTC")+SUMIFS('Pod Library'!$J$5:$J$111,'Pod Library'!$B$5:$B$111,1,'Pod Library'!$C$5:$C$111,"POD",'Pod Library'!$I$5:$I$111,"PT"))/(SUMIFS('Pod Library'!$J$5:$J$111,'Pod Library'!$B$5:$B$111,1,'Pod Library'!$C$5:$C$111,"POD")),"n/a") -> 0.73381295 | D13: =IFERROR((SUMIFS('Pod Library'!$J$5:$J$111,'Pod Library'!$B$5:$B$111,2,'Pod Library'!$C$5:$C$111,"POD",'Pod Library'!$I$5:$I$111,"FTC")+SUMIFS('Pod Library'!$J$5:$J$111,'Pod Library'!$B$5:$B$111,2,'Pod Library'!$C$5:$C$111,"POD",'Pod Library'!$I$5:$I$111,"PT"))/(SUMIFS('Pod Library'!$J$5:$J$111,'Pod Library'!$B$5:$B$111,2,'Pod Library'!$C$5:$C$111,"POD")),"n/a") -> 0.57439199 | E13: =IFERROR((SUMIFS('Pod Library'!$J$5:$J$111,'Pod Library'!$B$5:$B$111,3,'Pod Library'!$C$5:$C$111,"POD",'Pod Library'!$I$5:$I$111,"FTC")+SUMIFS('Pod Library'!$J$5:$J$111,'Pod Library'!$B$5:$B$111,3,'Pod Library'!$C$5:$C$111,"POD",'Pod Library'!$I$5:$I$111,"PT"))/(SUMIFS('Pod Library'!$J$5:$J$111,'Pod Library'!$B$5:$B$111,3,'Pod Library'!$C$5:$C$111,"POD")),"n/a") -> 0.5607759 | F13: =IFERROR((SUMIFS('Pod Library'!$J$5:$J$111,'Pod Library'!$B$5:$B$111,4,'Pod Library'!$C$5:$C$111,"POD",'Pod Library'!$I$5:$I$111,"FTC")+SUMIFS('Pod Library'!$J$5:$J$111,'Pod Library'!$B$5:$B$111,4,'Pod Library'!$C$5:$C$111,"POD",'Pod Library'!$I$5:$I$111,"PT"))/(SUMIFS('Pod Library'!$J$5:$J$111,'Pod Library'!$B$5:$B$111,4,'Pod Library'!$C$5:$C$111,"POD")),"n/a") -> 0.56060751 | G13: =IFERROR((SUMIFS('Pod Library'!$J$5:$J$111,'Pod Library'!$B$5:$B$111,5,'Pod Library'!$C$5:$C$111,"POD",'Pod Library'!$I$5:$I$111,"FTC")+SUMIFS('Pod Library'!$J$5:$J$111,'Pod Library'!$B$5:$B$111,5,'Pod Library'!$C$5:$C$111,"POD",'Pod Library'!$I$5:$I$111,"PT"))/(SUMIFS('Pod Library'!$J$5:$J$111,'Pod Library'!$B$5:$B$111,5,'Pod Library'!$C$5:$C$111,"POD")),"n/a") -> 0.56008695 | H13: ≥ 55% | I13: =IF(COUNTIF(C13:G13,"<0.5495")=0,"OK","CHECK") -> OK | J13: A POD in which Capgemini is a minority is one whose ways of working we do not set.
B14: Capgemini share inside each TEAM | C14: =IFERROR((SUMIFS('Pod Library'!$J$5:$J$111,'Pod Library'!$B$5:$B$111,1,'Pod Library'!$C$5:$C$111,"TEAM",'Pod Library'!$I$5:$I$111,"FTC")+SUMIFS('Pod Library'!$J$5:$J$111,'Pod Library'!$B$5:$B$111,1,'Pod Library'!$C$5:$C$111,"TEAM",'Pod Library'!$I$5:$I$111,"PT"))/(SUMIFS('Pod Library'!$J$5:$J$111,'Pod Library'!$B$5:$B$111,1,'Pod Library'!$C$5:$C$111,"TEAM")),"n/a") -> 0.58796992 | D14: =IFERROR((SUMIFS('Pod Library'!$J$5:$J$111,'Pod Library'!$B$5:$B$111,2,'Pod Library'!$C$5:$C$111,"TEAM",'Pod Library'!$I$5:$I$111,"FTC")+SUMIFS('Pod Library'!$J$5:$J$111,'Pod Library'!$B$5:$B$111,2,'Pod Library'!$C$5:$C$111,"TEAM",'Pod Library'!$I$5:$I$111,"PT"))/(SUMIFS('Pod Library'!$J$5:$J$111,'Pod Library'!$B$5:$B$111,2,'Pod Library'!$C$5:$C$111,"TEAM")),"n/a") -> 0.6 | E14: =IFERROR((SUMIFS('Pod Library'!$J$5:$J$111,'Pod Library'!$B$5:$B$111,3,'Pod Library'!$C$5:$C$111,"TEAM",'Pod Library'!$I$5:$I$111,"FTC")+SUMIFS('Pod Library'!$J$5:$J$111,'Pod Library'!$B$5:$B$111,3,'Pod Library'!$C$5:$C$111,"TEAM",'Pod Library'!$I$5:$I$111,"PT"))/(SUMIFS('Pod Library'!$J$5:$J$111,'Pod Library'!$B$5:$B$111,3,'Pod Library'!$C$5:$C$111,"TEAM")),"n/a") -> n/a | F14: =IFERROR((SUMIFS('Pod Library'!$J$5:$J$111,'Pod Library'!$B$5:$B$111,4,'Pod Library'!$C$5:$C$111,"TEAM",'Pod Library'!$I$5:$I$111,"FTC")+SUMIFS('Pod Library'!$J$5:$J$111,'Pod Library'!$B$5:$B$111,4,'Pod Library'!$C$5:$C$111,"TEAM",'Pod Library'!$I$5:$I$111,"PT"))/(SUMIFS('Pod Library'!$J$5:$J$111,'Pod Library'!$B$5:$B$111,4,'Pod Library'!$C$5:$C$111,"TEAM")),"n/a") -> n/a | G14: =IFERROR((SUMIFS('Pod Library'!$J$5:$J$111,'Pod Library'!$B$5:$B$111,5,'Pod Library'!$C$5:$C$111,"TEAM",'Pod Library'!$I$5:$I$111,"FTC")+SUMIFS('Pod Library'!$J$5:$J$111,'Pod Library'!$B$5:$B$111,5,'Pod Library'!$C$5:$C$111,"TEAM",'Pod Library'!$I$5:$I$111,"PT"))/(SUMIFS('Pod Library'!$J$5:$J$111,'Pod Library'!$B$5:$B$111,5,'Pod Library'!$C$5:$C$111,"TEAM")),"n/a") -> n/a | H14: ≥ 55% | I14: =IF(COUNTIF(C14:G14,"<0.5495")=0,"OK","CHECK") -> OK | J14: A TEAM in which Capgemini is a minority is one whose ways of working we do not set.
B15: Capgemini share of the delivery population | C15: =IFERROR((SUMIFS('Seat Ledger'!$M$5:$M$468,'Seat Ledger'!$B$5:$B$468,1,'Seat Ledger'!$J$5:$J$468,"FTC")+SUMIFS('Seat Ledger'!$M$5:$M$468,'Seat Ledger'!$B$5:$B$468,1,'Seat Ledger'!$J$5:$J$468,"PT"))/(SUMIFS('Seat Ledger'!$M$5:$M$468,'Seat Ledger'!$B$5:$B$468,1)),0) -> 0.60986066 | D15: =IFERROR((SUMIFS('Seat Ledger'!$M$5:$M$468,'Seat Ledger'!$B$5:$B$468,2,'Seat Ledger'!$J$5:$J$468,"FTC")+SUMIFS('Seat Ledger'!$M$5:$M$468,'Seat Ledger'!$B$5:$B$468,2,'Seat Ledger'!$J$5:$J$468,"PT"))/(SUMIFS('Seat Ledger'!$M$5:$M$468,'Seat Ledger'!$B$5:$B$468,2)),0) -> 0.58286986 | E15: =IFERROR((SUMIFS('Seat Ledger'!$M$5:$M$468,'Seat Ledger'!$B$5:$B$468,3,'Seat Ledger'!$J$5:$J$468,"FTC")+SUMIFS('Seat Ledger'!$M$5:$M$468,'Seat Ledger'!$B$5:$B$468,3,'Seat Ledger'!$J$5:$J$468,"PT"))/(SUMIFS('Seat Ledger'!$M$5:$M$468,'Seat Ledger'!$B$5:$B$468,3)),0) -> 0.55701875 | F15: =IFERROR((SUMIFS('Seat Ledger'!$M$5:$M$468,'Seat Ledger'!$B$5:$B$468,4,'Seat Ledger'!$J$5:$J$468,"FTC")+SUMIFS('Seat Ledger'!$M$5:$M$468,'Seat Ledger'!$B$5:$B$468,4,'Seat Ledger'!$J$5:$J$468,"PT"))/(SUMIFS('Seat Ledger'!$M$5:$M$468,'Seat Ledger'!$B$5:$B$468,4)),0) -> 0.51074367 | G15: =IFERROR((SUMIFS('Seat Ledger'!$M$5:$M$468,'Seat Ledger'!$B$5:$B$468,5,'Seat Ledger'!$J$5:$J$468,"FTC")+SUMIFS('Seat Ledger'!$M$5:$M$468,'Seat Ledger'!$B$5:$B$468,5,'Seat Ledger'!$J$5:$J$468,"PT"))/(SUMIFS('Seat Ledger'!$M$5:$M$468,'Seat Ledger'!$B$5:$B$468,5)),0) -> 0.5236415 | H15: ≥ 50% | I15: =IF(COUNTIF(C15:G15,"<0.4995")=0,"OK","CHECK") -> OK | J15: Below half the roster we cannot carry a productivity commitment we do not control.
B16: Blocks deploying a non-whole number of people | C16: =SUMPRODUCT(('Pod Library'!$B$5:$B$111=1)*(ABS('Pod Library'!$K$5:$K$111*2-ROUND('Pod Library'!$K$5:$K$111*2,0))>0.01))+SUMPRODUCT(('Horizontal Teams'!$B$5:$B$165=1)*(ABS('Horizontal Teams'!$J$5:$J$165*2-ROUND('Horizontal Teams'!$J$5:$J$165*2,0))>0.01)) -> 0 | D16: =SUMPRODUCT(('Pod Library'!$B$5:$B$111=2)*(ABS('Pod Library'!$K$5:$K$111*2-ROUND('Pod Library'!$K$5:$K$111*2,0))>0.01))+SUMPRODUCT(('Horizontal Teams'!$B$5:$B$165=2)*(ABS('Horizontal Teams'!$J$5:$J$165*2-ROUND('Horizontal Teams'!$J$5:$J$165*2,0))>0.01)) -> 2 | E16: =SUMPRODUCT(('Pod Library'!$B$5:$B$111=3)*(ABS('Pod Library'!$K$5:$K$111*2-ROUND('Pod Library'!$K$5:$K$111*2,0))>0.01))+SUMPRODUCT(('Horizontal Teams'!$B$5:$B$165=3)*(ABS('Horizontal Teams'!$J$5:$J$165*2-ROUND('Horizontal Teams'!$J$5:$J$165*2,0))>0.01)) -> 6 | F16: =SUMPRODUCT(('Pod Library'!$B$5:$B$111=4)*(ABS('Pod Library'!$K$5:$K$111*2-ROUND('Pod Library'!$K$5:$K$111*2,0))>0.01))+SUMPRODUCT(('Horizontal Teams'!$B$5:$B$165=4)*(ABS('Horizontal Teams'!$J$5:$J$165*2-ROUND('Horizontal Teams'!$J$5:$J$165*2,0))>0.01)) -> 6 | G16: =SUMPRODUCT(('Pod Library'!$B$5:$B$111=5)*(ABS('Pod Library'!$K$5:$K$111*2-ROUND('Pod Library'!$K$5:$K$111*2,0))>0.01))+SUMPRODUCT(('Horizontal Teams'!$B$5:$B$165=5)*(ABS('Horizontal Teams'!$J$5:$J$165*2-ROUND('Horizontal Teams'!$J$5:$J$165*2,0))>0.01)) -> 7 | H16: =0 -> 0 | I16: =IF(SUM(C16:G16)=0,"OK","CHECK") -> CHECK | J16: Column K of the Pod Library and column J of Horizontal Teams are the people you hire for that role across the whole block. Every one is a whole number, or a half where one person covers two units INSIDE this domain. The seat ratio beside it is the modelling quantity and will not always be round — on a 28-team block, nine engineers is a ratio of 0.32.
B17: Horizontal roles that have fallen below 0.02 FTE | C17: =COUNTIFS('Horizontal Teams'!$B$5:$B$165,1,'Horizontal Teams'!$I$5:$I$165,"<0.02") -> 0 | D17: =COUNTIFS('Horizontal Teams'!$B$5:$B$165,2,'Horizontal Teams'!$I$5:$I$165,"<0.02") -> 0 | E17: =COUNTIFS('Horizontal Teams'!$B$5:$B$165,3,'Horizontal Teams'!$I$5:$I$165,"<0.02") -> 0 | F17: =COUNTIFS('Horizontal Teams'!$B$5:$B$165,4,'Horizontal Teams'!$I$5:$I$165,"<0.02") -> 0 | G17: =COUNTIFS('Horizontal Teams'!$B$5:$B$165,5,'Horizontal Teams'!$I$5:$I$165,"<0.02") -> 0 | H17: =0 -> 0 | I17: =IF(SUM(C17:G17)=0,"OK","CHECK") -> OK | J17: A domain cannot run without a delivery head, a service manager or an architect. If a role must genuinely end, delete the row rather than leaving it at zero.
B18: Year-1 reconciliation to Appendix 3 — worst line | C18: ='Team Build-Up'!E28 -> 1.2083 | H18: ± 2.6 | I18: =IF(ABS(C18)<=2.6,"OK","CHECK") -> OK | J18: Year 1 must reproduce the client's own numbers: effort, the sourcing split, all three locations and all six role lines. The tolerance is ± 2.6 because seats sit on a 0.5 grid and a Year-1 team seat carries a multiplier of 5 — one grid step is 2.5 people. That is the deliberate price of an anatomy that can be staffed. Moving a seat between bands is free; moving it between ROLE, LOCATION or SOURCING is what actually breaks this.
A20: C. WHAT GOES STALE AND WILL NOT WARN YOU
B21: • SOURCING & PRODUCTIVITY is static. It is produced outside Excel by the per-sourcing solver and pasted in. If you change seat counts, the pool ceilings, the organic-convergence table and the transfer solve on that sheet no longer describe this roster. Re-run the solver or treat the sheet as superseded.
B22: • SIT LOADING is static for the same reason. Re-generate it after any seat change, or the requisition plan will not match the ledger.
B23: • The TRANSFER on the Logic Tree is a typed input (rows 65-66), sized on the Year-3 exit position produced by the solver. Change the Year-3 roster materially and the transfer needs re-sizing, or the 50:50 will not land.
B24: • THE RULE OF THUMB. Re-banding a seat, renaming it, or moving it between pods is safe. Changing its ROLE, LOCATION or SOURCING is not — those are the attributes Year 1 reconciles on and the guardrails measure.

Sheet Logic Tree
A1: Logic Tree — ten parametric drivers, five years
A2: Amber cells are inputs. Everything else re-derives. Section F is rebuilt on the measured day-1 position.
A4: A. BASELINE — Appendix 3 v3, read and never edited
B5: Domain | C5: sales / insurance recruitment
B6: Applications | C6: 13
B7: Total effort (units) | C7: 466.4723
B8: Current FTC | C8: 284.543
B9: Current FTE | C9: 88.1292
B10: Current MGCC | C10: 93.8
B11: — of which onshore Tokyo | C11: 177.3681 | J11: Location and role come from Appendix 3 v3. Both were Capgemini assumptions in v4.
B12: — of which offshore | C12: 107.0916
B13: — of which nearshore | C13: 0
B14: — of which onsite | C14: 0
B15: Role: BSA | C15: 47.7083
B16: Role: Developer | C16: 114.2306
B17: Role: Tester | C17: 103.9166
B18: Role: Maintenance | C18: 13.1458
B19: Role: PM | C19: 3.7917
B20: Role: Other | C20: 1.75
B21: AD effort (% of PRJ weighted) | C21: 444.5136
B22: Appendix 3 Year-3 target, each side | C22: 233.2362
B23: Ratio today — Capgemini share | C23: =C8/(C8+C9+C10) -> 0.60998919
B24: OFFSHORE TODAY — whole team, measured | C24: =(C12+C13+C10)/C7 -> 0.43066137 | J24: This is the number the offshore glidepath now starts from. In v4 it was assumed to be near zero.
A26: B. ARCHETYPE MIX — from the Golden Application Inventory v4
B27: Archetype | C27: Name | D27: Apps | E27: Effort | F27: Share | G27: AI ceiling | H27: Offshore ceiling
B28: M | C28: MGCC-destined | D28: 7 | E28: 390.1504 | F28: =E28/$E$33 -> 0.83638493 | G28: 0.4525 | H28: 0.85
B29: D | C29: Distributed-proven | D29: 1 | E29: 48.667 | F29: =E29/$E$33 -> 0.10432988 | G29: 0.4825 | H29: 0.78
B30: J | C30: Japan-locked | D30: 2 | E30: 19.0521 | F30: =E30/$E$33 -> 0.04084294 | G30: 0.304 | H30: 0.12
B31: P | C31: Portable, not moved | D31: 1 | E31: 7.2617 | F31: =E31/$E$33 -> 0.015567269 | G31: 0.4825 | H31: 0.78
B32: T | C32: Long tail | D32: 2 | E32: 1.3411 | F32: =E32/$E$33 -> 0.0028749831 | G32: 0.39 | H32: 0.55
C33: Total | D33: =SUM(D28:D32) -> 13 | E33: =SUM(E28:E32) -> 466.4723 | F33: =SUM(F28:F32) -> 1
B34: APPLICABLE AI CEILING | C34: =SUMPRODUCT($E$28:$E$32,$G$28:$G$32)/$E$33 -> 0.44985205 | J34: 44.99% against 44.73% on the four-archetype scheme. The segmentation changed; the answer did not.
B35: APPLICABLE OFFSHORE CEILING | C35: =SUMPRODUCT($E$28:$E$32,$H$28:$H$32)/$E$33 -> 0.81092936
A37: C. REALISATION AND THE NON-AI COMPONENTS
B38: Driver | C38: Year 1 | D38: Year 2 | E38: Year 3 | F38: Year 4 | G38: Year 5 | H38: Basis
B39: AI realisation — share of ceiling | C39: 0.25 | D39: 0.55 | E39: 0.75 | F39: 0.85 | G39: 0.9 | J39: Adoption, guardrails and substrate maturity. Capped at 90%.
B40: Classical ADM productivity, cumulative | C40: 0.02 | D40: 0.05 | E40: 0.07 | F40: 0.09 | G40: 0.11 | J40: Standardisation, defect reduction, shift-left.
B41: Operating-model productivity, RAW | C41: 0.03 | D41: 0.06 | E41: 0.08 | F41: 0.1 | G41: 0.12 | J41: Pod consolidation and one release train — only available where the stream is agile.
B42: Agile share of the domain → from the Delivery Mode sheet | C42: ='Delivery Mode'!C22 -> 0.18425542 | D42: ='Delivery Mode'!D22 -> 0.90947121 | E42: ='Delivery Mode'!E22 -> 1 | F42: ='Delivery Mode'!F22 -> 1 | G42: ='Delivery Mode'!G22 -> 1
B43: Operating-model productivity, APPLIED | C43: =C41*C42 -> 0.0055276626 | D43: =D41*D42 -> 0.054568272 | E43: =E41*E42 -> 0.08 | F43: =F41*F42 -> 0.1 | G43: =G41*G42 -> 0.12 | J43: Scaling by the agile share is what makes the operating-model gain earned rather than assumed. It costs 2.1 points of Year-1 capability.
B44: AI-attributable productivity | C44: =$C$34*C39 -> 0.11246301 | D44: =$C$34*D39 -> 0.24741863 | E44: =$C$34*E39 -> 0.33738904 | F44: =$C$34*F39 -> 0.38237424 | G44: =$C$34*G39 -> 0.40486685
B45: CAPABILITY EARNED by end of year | C45: =1-(1-C44)*(1-C40)*(1-C43) -> 0.13502164 | D45: =1-(1-D44)*(1-D40)*(1-D43) -> 0.32406141 | E45: =1-(1-E44)*(1-E40)*(1-E43) -> 0.43307006 | F45: =1-(1-F44)*(1-F40)*(1-F43) -> 0.49416451 | G45: =1-(1-G44)*(1-G40)*(1-G43) -> 0.53389171
A47: D. CARRY-FORWARD AND PRE-LOAD — what is applied to headcount
B48: Pre-load fraction of the in-year gain | C48: 0.5
C49: Year 1 | D49: Year 2 | E49: Year 3 | F49: Year 4 | G49: Year 5
B50: Banked from the prior year | C50: =0 -> 0 | D50: =C45 -> 0.13502164 | E50: =D45 -> 0.32406141 | F50: =E45 -> 0.43307006 | G50: =F45 -> 0.49416451
B51: Pre-load of this year's gain | C51: =0 -> 0 | D51: =$C$48*(D45-C45) -> 0.094519886 | E51: =$C$48*(E45-D45) -> 0.054504326 | F51: =$C$48*(F45-E45) -> 0.030547222 | G51: =$C$48*(G45-F45) -> 0.019863604
B52: APPLIED TO STAFFING | C52: =C50+C51 -> 0 | D52: =D50+D51 -> 0.22954152 | E52: =E50+E51 -> 0.37856574 | F52: =F50+F51 -> 0.46361728 | G52: =G50+G51 -> 0.51402811
B53: Headcount target = baseline x (1 - applied) | C53: =$C$7*(1-C52) -> 466.4723 | D53: =$C$7*(1-D52) -> 359.39754 | E53: =$C$7*(1-E52) -> 289.88187 | F53: =$C$7*(1-F52) -> 250.20768 | G53: =$C$7*(1-G52) -> 226.69243
B54: EXIT YEAR 3 — full realisation, the point the transfer is struck | E54: =$C$7*(1-E45) -> 264.45711
A56: E. OFFSHORE — REBUILT. A measured start, and a gap that closes.
B57: v4 scaled a ceiling by a realisation curve from an assumed near-zero base. v3 tells us the base. The curve now closes the gap between what is true today and the ceiling.
B58: Driver | C58: Year 1 | D58: Year 2 | E58: Year 3 | F58: Year 4 | G58: Year 5 | H58: Basis
B59: Gap closure — share of (ceiling − today) reached | C59: 0.02 | D59: 0.35 | E59: 0.62 | F59: 0.8 | G59: 0.92 | J59: Year 1 is 2%: the transition year holds the position it inherits. Movement starts in Year 2, gated on substrate coverage per cluster.
B60: TARGET OFFSHORE SHARE, whole team | C60: =$C$24+($C$35-$C$24)*C59 -> 0.43826673 | D60: =$C$24+($C$35-$C$24)*D59 -> 0.56375517 | E60: =$C$24+($C$35-$C$24)*E59 -> 0.66642752 | F60: =$C$24+($C$35-$C$24)*F59 -> 0.73487576 | G60: =$C$24+($C$35-$C$24)*G59 -> 0.78050792
B61: Implied movement from today, in people | C61: =C60*C53-$C$24*$C$7 -> 3.5476897 | D61: =D60*D53-$C$24*$C$7 -> 1.7206186 | E61: =E60*E53-$C$24*$C$7 -> -7.7063429 | F61: =F60*F53-$C$24*$C$7 -> -17.020041 | G61: =G60*G53-$C$24*$C$7 -> -23.956367 | J61: Negative in later years because the team shrinks faster than the offshore share rises.
A63: F. TRANSFER OF EMPLOYMENT — one event, end of Year 3
B64: Transfer in year | C64: Year 1 | D64: Year 2 | E64: Year 3 | F64: Year 4 | G64: Year 5
B65: Capgemini to MetLife Japan (FTE) | C65: 0 | D65: 0 | E65: 5 | F65: 0 | G65: 0 | J65: Nothing moves in Years 1 or 2. Co-sourced seats are the transfer population.
B66: Capgemini to MetLife MGCC | C66: 0 | D66: 0 | E66: 10 | F66: 0 | G66: 0
B67: Cumulative transferred | C67: =SUM($C$65:C66) -> 0 | D67: =SUM($C$65:D66) -> 0 | E67: =SUM($C$65:E66) -> 15 | F67: =SUM($C$65:F66) -> 15 | G67: =SUM($C$65:G66) -> 15
A69: G. COST INDEX — relative only, onshore Tokyo E2 = 1.00
B70: Location | C70: E1 | D70: E2 | E70: E3 | F70: E4 | G70: E5
B71: Onshore Tokyo | C71: 0.72 | D71: 1 | E71: 1.35 | F71: 1.85 | G71: 2.55
B72: Offshore Hyderabad | C72: 0.22 | D72: 0.3 | E72: 0.42 | F72: 0.6 | G72: 0.85
B73: Nearshore | C73: 0.45 | D73: 0.62 | E73: 0.84 | F73: 1.15 | G73: 1.58
B74: Nearshore comes from Appendix 3 v3 and is zero on this domain — 19.7 units across the portfolio. Carried so every domain model uses one schema. | I74: key | J74: E1 | K74: E2 | L74: E3 | M74: E4 | N74: E5
I75: ON | J75: 0.72 | K75: 1 | L75: 1.35 | M75: 1.85 | N75: 2.55
I76: OFF | J76: 0.22 | K76: 0.3 | L76: 0.42 | M76: 0.6 | N76: 0.85
I77: NEAR | J77: 0.45 | K77: 0.62 | L77: 0.84 | M77: 1.15 | N77: 1.58
I78: Lookup block for the Seat Ledger. Mirrors the table on the left.

Sheet Sourcing & Productivity
A1: Sourcing and productivity — the same chain, applied differently to each population
A2: Productivity is not one number applied to everybody. The three populations do different work and we do not control all three, so each carries its own AI ceiling and its own adoption factor. This is what makes the 50:50 converge on its own rather than by transfer.
A4: A. WHY ONE RATE CANNOT APPLY TO ALL THREE — the Year-1 role mix
B5: Population | C5: Heads Y1 | D5: BSA | E5: Developer | F5: Tester | G5: Maint.
B6: FTC · Capgemini payroll | C6: 284.533 | D6: 0.16761149 | E6: 0.40155975 | F6: 0.36525816 | G6: 0.046142275 | I6: MetLife's own people are governance, domain SME and product ownership. MGCC is build and test. They are not doing the same work, so they cannot carry the same productivity rate.
B7: FTE · MetLife Japan | C7: 88.11 | D7: 0.39021677 | E7: 0 | F7: 0.02268755 | G7: 0.20863693
B8: MGCC · MetLife MGCC | C8: 93.787 | D8: 0 | E8: 0.6786335 | F8: 0.3213665 | G8: 0
A10: B. EACH POPULATION'S OWN AI CEILING AND ADOPTION — INPUT
B11: Population | C11: Own AI ceiling | D11: Adoption | E11: Effective ceiling | F11: vs domain blend
B12: FTC · Capgemini payroll | C12: 0.46444913 | D12: 1 | E12: 0.46444913 | F12: 0.032448614 | I12: ADOPTION is the share of the ceiling each population can actually realise, and it is a judgement about AUTHORITY, not about capability. We build the tooling, set the ways of working and mandate them on our own payroll — so 1.00. Everything below that is somebody else's decision.
B13: FTE · MetLife Japan | C13: 0.37804868 | D13: 0.55 | E13: 0.20792677 | F13: -0.15961552
B14: MGCC · MetLife MGCC | C14: 0.48397907 | D14: 0.8 | E14: 0.38718325 | F14: 0.075862751
B15: Domain blended ceiling (unchanged, and still the headline commitment) | C15: 0.44985205
B16: Only the AI gate is scaled. Classical ADM productivity attaches to the work and the operating-model gain attaches to the delivery unit, so both flow to every population regardless of employer.
A18: C. WHAT EACH POPULATION IS THEREFORE ASKED TO DELIVER
B19: Applied to staffing | C19: Year 1 | D19: Year 2 | E19: Year 3 | F19: Year 4 | G19: Year 5
B20: FTC · Capgemini payroll | C20: 0 | D20: 0.23492517 | E20: 0.3868546 | F20: 0.47338163 | G20: 0.52425358 | I20: The headline commitment is UNCHANGED from the previous version. What has changed is that it is no longer assumed to fall equally on all three populations.
B21: FTE · MetLife Japan | C21: 0 | D21: 0.14031539 | E21: 0.24118991 | F21: 0.30178742 | G21: 0.34455582
B22: MGCC · MetLife MGCC | C22: 0 | D22: 0.20642821 | E22: 0.34297963 | F22: 0.42169656 | G22: 0.47012768
B23: Whole-domain commitment (the headline) | C23: 0 | D23: 0.22954152 | E23: 0.37856574 | F23: 0.46361728 | G23: 0.51402811
A25: D. THE THREE-WAY COMMITMENT SPLIT
B26: CAPGEMINI COMMITS | C26: Our own headcount reduction, on our own payroll, on tooling and ways of working we control. This is contractible and we should contract it.
B27: METLIFE MUST DELIVER | C27: The reduction of MetLife Japan and MGCC headcount. We size it, we enable it and we report it — but redeploying MetLife's own people is MetLife's decision, and MGCC runs to its own utilisation targets. This should be a joint commitment with named owners, not a Capgemini SLA.
B28: JOINTLY DEPENDENT | C28: AI adoption on MetLife's side: tooling access, shared standards, common telemetry, and the substrate being used rather than merely available. If adoption lands below the factors in section B, the whole-team headcount misses even if Capgemini delivers in full.
A30: E. ORGANIC CONVERGENCE TO 50:50 — before any transfer
B31: Measure | C31: Year 1 | D31: Year 2 | E31: Year 3 | F31: Year 4 | G31: Year 5
B32: MetLife Japan (FTE) — own curve | C32: 88.11 | D32: 75.746811 | E32: 66.858757 | F32: 64.305437 | G32: 58.948238 | I32: MetLife's populations follow their own slower curves. Capgemini takes the balance, which means we shrink our own book faster than productivity alone would justify. That extra reduction is not a productivity claim — it is a deliberate commercial choice to reach the ratio organically instead of by transferring people.
B33: MetLife MGCC — own curve | C33: 93.787 | D33: 74.426717 | E33: 61.619969 | F33: 60.798403 | G33: 54.397974
B34: Partner — per the partner plan | C34: 0 | D34: 0 | E34: 0 | F34: 0 | G34: 0
B35: Capgemini — absorbs the balance | C35: 284.5753 | D35: 209.22401 | E35: 161.40314 | F35: 125.10384 | G35: 113.34621
B36: TOTAL = the headline commitment | C36: 466.4723 | D36: 359.39754 | E36: 289.88187 | F36: 250.20768 | G36: 226.69243
B37: RATIO — Capgemini share | C37: 0.6100583 | D37: 0.58215204 | E37: 0.55678937 | F37: 0.5 | G37: 0.5
B38: — of which productivity-driven | C38: 0 | D38: 0.23492517 | E38: 0.3868546 | F38: 0.47338163 | G38: 0.52425358
B39: — of which RATIO-DRIVEN, over and above productivity | C39: -0.00014866465 | D39: 0.029750597 | E39: 0.045889076 | F39: 0.086937066 | G39: 0.077387661
B41: This is the mechanism that halves the transfer. Reaching the ratio by shrinking our own book is cheaper, lower-risk and entirely within our control; a transfer of employment is neither.
A43: F. THE GUARDRAILS — where organic convergence has to stop
B44: Test | C44: Year 1 | D44: Year 2 | E44: Year 3 | F44: Year 4 | G44: Year 5 | H44: Floor
B45: Capgemini share of the delivery population | C45: 0.61002294 | D45: 0.58192752 | E45: 0.55690746 | F45: 0.50013783 | G45: 0.50004191 | H45: 0.5 | I45: THE POINT OF THE FLOOR. If Capgemini becomes a minority of the delivery population, or of the build-and-test seats, or of any single pod, we no longer set the ways of working — and a productivity commitment we cannot enforce is not a commitment. Convergence stops here, and from that year MetLife's population follows the whole-team curve rather than its own slower one.
B46: Capgemini share of build-and-test seats | C46: 0.69492087 | D46: 0.66125934 | E46: 0.65582205 | F46: 0.596437 | G46: 0.60016504 | H46: 0.55
B47: Capgemini share inside every single delivery unit | C47: held | D47: held | E47: held | F47: held | G47: held | H47: 0.55
A49: G. THE TRANSFER — only what organic convergence cannot reach
C50: Value
B51: Exit Year 3 headcount, full realisation | C51: 264.45711
B52: Vendor units at exit, after organic convergence | C52: 147.24691
B53: Transferable pool — Capgemini payroll only | C53: 147.24691
B54: 50:50 requires each side to be | C54: 132.22856
B55: TRANSFER REQUIRED | C55: 15.018353
B56: Maximum transferable at the 70% cap | C56: 103.07284
B57: Transfer applied | C57: 15
B58: — to MetLife Japan | C58: 5.3
B59: — to MGCC | C59: 9.7
B60: RESIDUAL GAP TO 50:50 | C60: 0.018352914
B61: Ratio reached at the Year-3 exit | C61: 0.5000694

Sheet Delivery Mode
A1: Delivery mode — not everything is a pod on day one
A2: Only 4 applications in the whole estate are flagged agile, and Sales has no method data at all. This sheet is where that assumption lives, in the open, as an input.
A4: A. MODE TODAY AND TARGET, BY VALUE STREAM — INPUT
B5: Value stream | C5: Effort | D5: Archetype | E5: Mode today | F5: Agile from | G5: Why
B6: F2FILL · F2F Illustlation | C6: 230.8708 | D6: M | E6: Hybrid | F6: Q4 | G6: JP-GSSP is 229.9 of the 230.9. Capgemini is the named incumbent and 55.5 of our 99 inherited people sit here. 1,780 P4 incidents and 669 normal changes in 32 months. | I6: MetLife supplied no development method for any Sales application. These four rows are Capgemini planning assumptions, drawn from the platform each stream runs on. They are the single largest unevidenced input in this workbook.
B7: BANCA · Banca Illustlation | C7: 168.9167 | D7: M / D / J / T | E7: Hybrid | F7: Q6 | G7: JP-BANCA 103.5 is unnamed in the vendor mapping and JP-Banca Report 48.7 is where 31.7 of our people are. The VBA illustration tool P02BKE is NCD's and is the drag.
B8: AGENT · F2F Agent Enablement | C8: 43.5625 | D8: M | E8: Hybrid | F8: Q4 | G8: WPSCFC-JPN. Capgemini-named, single application, 8.8 of our people.
B9: SUPP · F2F SalesSupport | C9: 23.1223 | D9: M / P / J / T | E9: Agile | F9: Q2 | G9: Small, modern, closest to an agile construct already. Remote Closing is ours.
B10: Total | C10: =SUM(C6:C9) -> 466.4723
A12: B. AGILE SHARE BY YEAR — computed from the quarter each stream converts
B13: Value stream | C13: Year 1 | D13: Year 2 | E13: Year 3 | F13: Year 4 | G13: Year 5
B14: F2FILL | C14: 0.25 | D14: 1 | E14: 1 | F14: 1 | G14: 1
B15: BANCA | C15: 0 | D15: 0.75 | E15: 1 | F15: 1 | G15: 1
B16: AGENT | C16: 0.25 | D16: 1 | E16: 1 | F16: 1 | G16: 1
B17: SUPP | C17: 0.75 | D17: 1 | E17: 1 | F17: 1 | G17: 1
B18: Effort-weighted agile share of the domain | C18: =SUMPRODUCT($C$6:$C$9,C14:C17)/$C$10 -> 0.18425542 | D18: =SUMPRODUCT($C$6:$C$9,D14:D17)/$C$10 -> 0.90947121 | E18: =SUMPRODUCT($C$6:$C$9,E14:E17)/$C$10 -> 1 | F18: =SUMPRODUCT($C$6:$C$9,F14:F17)/$C$10 -> 1 | G18: =SUMPRODUCT($C$6:$C$9,G14:G17)/$C$10 -> 1
B20: Delivery units this produces
B21: — agile PODS | C21: 7 | D21: 35 | E21: 36 | F21: 36 | G21: 33
B22: — agile share (feeds the Logic Tree) | C22: =C18 -> 0.18425542 | D22: =D18 -> 0.90947121 | E22: =E18 -> 1 | F22: =F18 -> 1 | G22: =G18 -> 1
B23: — waterfall / hybrid TEAMS | C23: 28 | D23: 3 | E23: 0 | F23: 0 | G23: 0
A25: C. WHY THIS MATTERS TO THE NUMBER
B26: • Operating-model productivity — pod consolidation, one release train, span of control — is only available where the stream actually runs as a pod. Scaling the 3 / 6 / 8 / 10 / 12% curve by the agile share turns it from an assumption into an earned outcome, and costs 2.1 points of Year-1 capability.
B27: • The waterfall TEAM is 12 seats with separate analysis and test cells; the agile POD is 10 with the test cell collapsed into SDET seats. That structural difference is what reproduces the 37% tester share Appendix 3 v3 reports — and what makes it fall as streams convert.
B28: • Year 1 runs 7 pods and 28 teams. Year 2 runs 35 pods and 3 teams. By Year 3 there are no teams left. If the conversion slips a year, Year-2 capability falls from 32.4% to about 27% and the whole glidepath moves with it.
B29: • DECIDE whether we put this profile to MetLife as an assumption to confirm, or ask for the development method data first. Asking is cheap and it removes the largest unevidenced input in the model.

Sheet AMS & Ticket Load
A1: AMS and ticket load — the run team sized from evidence, for the first time
A2: 3,807 incidents and 2,979 changes over 32 months, from Appendix 3 v3.
A4: A. RECORDED VOLUMES — 1 Jan 2024 to 31 Aug 2026
B5: Measure | C5: Volume | D5: Per month | E5: Per unit of effort | F5: Share
B6: P1 — critical | C6: 1 | D6: =C6/$C$17 -> 0.03125 | E6: =C6/'Logic Tree'!$C$7 -> 0.00214375 | F6: =C6/$C$11 -> 0.00026267402 | I6: Six incidents at P1 or P2 in 32 months on a 466-unit domain. The load is overwhelmingly P4 and P5 — high volume, low severity, and the profile automation and AIOps address best.
B7: P2 — high | C7: 5 | D7: =C7/$C$17 -> 0.15625 | E7: =C7/'Logic Tree'!$C$7 -> 0.01071875 | F7: =C7/$C$11 -> 0.0013133701
B8: P3 — medium | C8: 115 | D8: =C8/$C$17 -> 3.59375 | E8: =C8/'Logic Tree'!$C$7 -> 0.24653125 | F8: =C8/$C$11 -> 0.030207512
B9: P4 — low | C9: 1910 | D9: =C9/$C$17 -> 59.6875 | E9: =C9/'Logic Tree'!$C$7 -> 4.0945625 | F9: =C9/$C$11 -> 0.50170738
B10: P5 — informational | C10: 1776 | D10: =C10/$C$17 -> 55.5 | E10: =C10/'Logic Tree'!$C$7 -> 3.8073 | F10: =C10/$C$11 -> 0.46650906
B11: All incidents | C11: =SUM(C6:C10) -> 3807 | D11: =C11/$C$17 -> 118.96875 | E11: =C11/'Logic Tree'!$C$7 -> 8.1612563
B12: Emergency change | C12: 50 | D12: =C12/$C$17 -> 1.5625 | E12: =C12/'Logic Tree'!$C$7 -> 0.1071875 | F12: =C12/$C$15 -> 0.016784156 | I12: 68% of changes are Standard. That is the share a release train and pipeline automation can absorb, and it is the operating-model productivity case in one number.
B13: Normal change | C13: 901 | D13: =C13/$C$17 -> 28.15625 | E13: =C13/'Logic Tree'!$C$7 -> 1.9315188 | F13: =C13/$C$15 -> 0.30245049
B14: Standard change | C14: 2028 | D14: =C14/$C$17 -> 63.375 | E14: =C14/'Logic Tree'!$C$7 -> 4.347525 | F14: =C14/$C$15 -> 0.68076536
B15: All changes | C15: =SUM(C12:C14) -> 2979 | D15: =C15/$C$17 -> 93.09375 | E15: =C15/'Logic Tree'!$C$7 -> 6.3862313
B17: Observation window, months | C17: 32
A19: B. TWO INDEPENDENT SIZINGS OF THE RUN TEAM
B20: Basis | C20: Value | D20: Reading
B21: Tickets per analyst per month — INPUT | C21: 9.05 | D21: SOLVED, not assumed: this is the throughput that makes the ticket-derived run team equal the Maintenance role MetLife reports. It is the output of the cross-check, not an input to it.
B22: Implied run team from incident volume | C22: =C11/C17/C21 -> 13.145718 | D22: Incidents per month divided by throughput per analyst.
B23: Maintenance role reported in Appendix 3 v3 | C23: ='Logic Tree'!C18 -> 13.1458 | D23: MetLife's own count of the Capgemini maintenance population on this domain.
B24: Variance between the two | C24: =C22-C23 -> -8.1767956e-05 | D24: Zero by construction. The question is whether 9.05 tickets per analyst per month is credible — see below.
B25: Maintenance seats in the Year-1 roster | C25: ='Team Build-Up'!C48 -> 31.5 | D25: Model output. Wider than the Maintenance role: it includes the horizontal L2, incident and release seats as well as the in-team support seats.
A27: C. WHAT THE TICKET DATA CHANGES
B28: • THE CROSS-CHECK DOES NOT CLOSE, AND THAT IS THE FINDING. MetLife reports 13.1 Capgemini maintenance units against 119 incidents a month — 9 tickets per analyst per month. Industry L2 throughput is 60 to 100. Either run work is being done by people counted as developers, or these tickets carry far more investigation than a normal L2 queue. Both readings matter for how AMS is priced, and neither can be settled from this pack.
B29: • The severity profile is the automation case. 96.8% of incidents are P4 or P5 and 68% of changes are Standard. Those are the categories where MSP benchmarks put MTTR reduction at 20-40% and technician throughput at 15-25%, and they are why the run-phase AI addressable share is set at 40%.
B30: • Ticket density varies by archetype across the portfolio by a factor of four — 6.8 incidents per unit on distributed-proven applications against 25.6 on the long tail. Sales sits at 8.2, which is why its horizontal layer is 13% of the roster against 22% on Contract Management.
B31: • DO put the throughput question to MetLife. Appendix 3 records 95.3% of this domain's effort as project work and only 4.7% as run, against 3,807 incidents and 2,979 changes in 32 months. Either run work is sitting inside the developer line or the AMS price is wrong. Repeat this cross-check on every domain — Contract Management reports 2,610 incidents against ZERO maintenance units, which cannot be right.

Sheet Inventory
A1: Inventory — the 13 Sales / Insurance Recruitment applications from Appendix 3 v3
A2: Classified by the six-rule classifier on the Golden Application Inventory v4.
B4: Application | C4: Arch | D4: Effort | E4: FTC | F4: FTE | G4: MGCC | H4: Onshore | I4: Offshore | J4: Offsh % | K4: BSA | L4: Dev | M4: Test | N4: Mnt | O4: PM | P4: Oth | Q4: AD % | R4: Crit | S4: Cloud | T4: Prio | U4: Incidents | V4: Changes | W4: Primary code language
B5: JP-GSSP | C5: M | D5: 229.9125 | E5: 151.7708 | F5: 30.9375 | G5: 47.2042 | H5: 102.8125 | I5: 48.9583 | J5: =IFERROR(($I5+$G5)/$D5,0) -> 0.41825695 | K5: 23.7083 | L5: 43.8333 | M5: 67.8333 | N5: 12.1458 | O5: 3.75 | P5: 0.5 | Q5: 0.9472 | R5: Y | S5: Yes | T5: Y | U5: 1973 | V5: 1694 | W5: JAVA;JavaScript
B6: JP-BANCA | C6: M | D6: 103.5083 | E6: 51.3 | F6: 27.2083 | G6: 25 | H6: 21.4583 | I6: 29.8417 | J6: =IFERROR(($I6+$G6)/$D6,0) -> 0.52982901 | K6: 12.6667 | L6: 14.5917 | M6: 22.75 | N6: 0 | O6: 0.0417 | P6: 1.25 | Q6: 0.9924 | R6: N | S6: Yes | T6: Y | U6: 8 | V6: 15 | W6: JavaScript;JAVA
B7: JP-Banca Report | C7: D | D7: 48.6667 | E7: 31.6875 | F7: 11.4 | G7: 5.5792 | H7: 19 | I7: 12.6875 | J7: =IFERROR(($I7+$G7)/$D7,0) -> 0.37534289 | K7: 7.0833 | L7: 18.6042 | M7: 6 | N7: 0 | O7: 0 | P7: 0 | Q7: 1 | R7: N | S7: Yes | T7: N | U7: 29 | V7: 102 | W7: JAVA
B8: WPSCFC-JPN | C8: M | D8: 43.5625 | E8: 20.8333 | F8: 10.0042 | G8: 12.725 | H8: 7.5833 | I8: 13.25 | J8: =IFERROR(($I8+$G8)/$D8,0) -> 0.59626973 | K8: 4.25 | L8: 9.5833 | M8: 6 | N8: 1 | O8: 0 | P8: 0 | Q8: 0.8692 | R8: N | S8: Yes | T8: Y | U8: 1425 | V8: 530 | W8: Other#APEX;HTML;JavaScript
B9: P02BKE-JPN | C9: J | D9: 15.8583 | E9: 13.5833 | F9: 2.275 | G9: 0 | H9: 13.5833 | I9: 0 | J9: =IFERROR(($I9+$G9)/$D9,0) -> 0 | K9: 0 | L9: 13.5833 | M9: 0 | N9: 0 | O9: 0 | P9: 0 | Q9: 0.9173 | R9: N | S9: No | T9: N | U9: 2 | V9: 49 | W9: Other#VBA
B10: JP - Remote Closing | C10: M | D10: 12.2083 | E10: 4.6458 | F10: 4.5625 | G10: 3 | H10: 2.625 | I10: 2.0208 | J10: =IFERROR(($I10+$G10)/$D10,0) -> 0.41126119 | K10: 0 | L10: 3.3125 | M10: 1.3333 | N10: 0 | O10: 0 | P10: 0 | Q10: 1 | R10: N | S10: Yes | T10: Y | U10: 171 | V10: 128 | W10: JAVA
B11: WAAATF-JPN | C11: P | D11: 7.2621 | E11: 6.6142 | F11: 0.6479 | G11: 0 | H11: 6.6142 | I11: 0 | J11: =IFERROR(($I11+$G11)/$D11,0) -> 0 | K11: 0 | L11: 6.6142 | M11: 0 | N11: 0 | O11: 0 | P11: 0 | Q11: 0.9391 | R11: N | S11: Yes | T11: N | U11: 44 | V11: 52 | W11: JAVA
B12: W08NAV-JPN | C12: J | D12: 3.194 | E12: 2.8419 | F12: 0.3521 | G12: 0 | H12: 2.8419 | I12: 0 | J12: =IFERROR(($I12+$G12)/$D12,0) -> 0 | K12: 0 | L12: 2.8419 | M12: 0 | N12: 0 | O12: 0 | P12: 0 | Q12: 0.7919 | R12: N | S12: No | T12: N | U12: 13 | V12: 96 | W12: VB
B13: W09WSD-JPN BIS | C13: T | D13: 0.8833 | E13: 0.8083 | F13: 0.075 | G13: 0 | H13: 0.8083 | I13: 0 | J13: =IFERROR(($I13+$G13)/$D13,0) -> 0 | K13: 0 | L13: 0.8083 | M13: 0 | N13: 0 | O13: 0 | P13: 0 | Q13: 0.4811 | R13: N | S13: No | T13: N | U13: 43 | V13: 204 | W13: VB.NET
B14: Distribution Systems - Internal | C14: M | D14: 0.6667 | E14: 0.3333 | F14: 0.25 | G14: 0.0833 | H14: 0 | I14: 0.3333 | J14: =IFERROR(($I14+$G14)/$D14,0) -> 0.62486876 | K14: 0 | L14: 0.3333 | M14: 0 | N14: 0 | O14: 0 | P14: 0 | Q14: 1 | R14: N | S14: Yes | T14: Y | U14: 43 | V14: 56 | W14: JAVA
B15: WGLRPC-JPN | C15: T | D15: 0.4579 | E15: 0.0413 | F15: 0.4167 | G15: 0 | H15: 0.0413 | I15: 0 | J15: =IFERROR(($I15+$G15)/$D15,0) -> 0 | K15: 0 | L15: 0.0413 | M15: 0 | N15: 0 | O15: 0 | P15: 0 | Q15: 0 | R15: N | S15: No | T15: N | U15: 18 | V15: 5 | W15: JAVA
B16: IVR Tekigosei | C16: M | D16: 0.1667 | E16: 0.0833 | F16: 0 | G16: 0.0833 | H16: 0 | I16: 0 | J16: =IFERROR(($I16+$G16)/$D16,0) -> 0.49970006 | K16: 0 | L16: 0.0833 | M16: 0 | N16: 0 | O16: 0 | P16: 0 | Q16: 1 | R16: N | S16: Yes | T16: Y | U16: 34 | V16: 5 | W16: Other#N/A
B17: WCC | C17: M | D17: 0.125 | E17: 0 | F17: 0 | G17: 0.125 | H17: 0 | I17: 0 | J17: =IFERROR(($I17+$G17)/$D17,0) -> 1 | K17: 0 | L17: 0 | M17: 0 | N17: 0 | O17: 0 | P17: 0 | Q17: 1 | R17: N | S17: Yes | T17: Y | U17: 4 | V17: 43 | W17: JAVA;HTML5;JavaScript
B18: TOTAL | D18: =SUM(D5:D17) -> 466.4723 | E18: =SUM(E5:E17) -> 284.543 | F18: =SUM(F5:F17) -> 88.1292 | G18: =SUM(G5:G17) -> 93.8 | H18: =SUM(H5:H17) -> 177.3681 | I18: =SUM(I5:I17) -> 107.0916 | K18: =SUM(K5:K17) -> 47.7083 | L18: =SUM(L5:L17) -> 114.2306 | M18: =SUM(M5:M17) -> 103.9166 | N18: =SUM(N5:N17) -> 13.1458 | O18: =SUM(O5:O17) -> 3.7917 | P18: =SUM(P5:P17) -> 1.75 | U18: =SUM(U5:U17) -> 3807 | V18: =SUM(V5:V17) -> 2979
B20: Note — development method, specification language, lines of code, screens, batches, APIs and file interfaces are BLANK for all 13 applications in this domain. They are omitted here rather than shown as empty columns. See the README.

Sheet Value Streams
A1: Four value streams — MetLife's own taxonomy, reconciling to 13 applications and 466.472 units
A2: New in v6. The streams we invented in v4 and v5 are replaced by the ones MetLife uses, so the pod plan is readable against the client's own map of the estate.
B4: Code | C4: Value stream | D4: Apps | E4: Effort | F4: Arch | G4: Mode today | H4: Agile from | I4: Y1 pods | J4: Y2 | K4: Y3 | L4: Y4 | M4: Y5 | N4: Vendor today | O4: CG heads today
B5: F2FILL | C5: F2F Illustlation | D5: 4 | E5: 230.8708 | F5: M | G5: Hybrid | H5: Q4 | I5: 5 + 13t | J5: 19 | K5: 18 | L5: 18 | M5: 16 | N5: CG 151.8 · unnamed 0.4 | O5: 55.5
B6: BANCA | C6: Banca Illustlation | D6: 4 | E6: 168.9167 | F6: M / D / J / T | G6: Hybrid | H6: Q6 | I6: 0 + 12t | J6: 10 + 3t | K6: 13 | L6: 13 | M6: 12 | N6: NCD 13.6 · FSI 0.8 · unnamed 83.0 | O6: 32
B7: AGENT | C7: F2F Agent Enablement | D7: 1 | E7: 43.5625 | F7: M | G7: Hybrid | H7: Q4 | I7: 1 + 2t | J7: 4 | K7: 3 | L7: 3 | M7: 3 | N7: CG 20.8 | O7: 8.8
B8: SUPP | C8: F2F SalesSupport | D8: 4 | E8: 23.1223 | F8: M / P / J / T | G8: Agile | H8: Q2 | I8: 1 + 1t | J8: 2 | K8: 2 | L8: 2 | M8: 2 | N8: NCD 9.5 · CG 4.6 · unnamed 0.0 | O8: 2.7
C9: Total | D9: =SUM(D5:D8) -> 13 | E9: =SUM(E5:E8) -> 466.4723 | O9: =SUM(O5:O8) -> 99
B11: Pod counts read 'pods + teams'. A team is a 12-seat waterfall / hybrid delivery cell; a pod is a 10-seat agile unit falling to 6 by Year 4. Teams are gone by Year 3. 'CG heads today' is the inherited Capgemini population from the T3 reconciliation behind Golden Inventory v4 — 99 people, 56% of them on the F2F Illustlation stream and specifically on JP-GSSP.

Sheet Pod Library
A1: Pod library — every seat, with MetLife's own role taxonomy as the primary attribute
A2: INPUT. Role (BSA / DEV / TEST / MNT / PM / OTH) is what Year 1 reconciles on. The detail column is the Capgemini role name and carries no arithmetic.
B4: Year | C4: Unit | D4: Seat | E4: Role detail | F4: Role | G4: Exp | H4: Loc | I4: Sourcing | J4: Count | K4: People in the block
B5: 1 | C5: POD | D5: 1 | E5: MetLife Product Owner | F5: PM | G5: E4 | H5: ON | I5: FTE | J5: 1 | K5: =J5*7 -> 7
B6: 1 | C6: POD | D6: 2 | E6: MGCC Engineer | F6: DEV | G6: E3 | H6: OFF | I6: MGCC | J6: 1.6428571 | K6: =J6*7 -> 11.5
B7: 1 | C7: POD | D7: 3 | E7: Business Analyst (bilingual) | F7: BSA | G7: E3 | H7: ON | I7: FTC | J7: 1 | K7: =J7*7 -> 7
B8: 1 | C8: POD | D8: 4 | E8: Pod lead / senior engineer | F8: DEV | G8: E4 | H8: ON | I8: FTC | J8: 1.5 | K8: =J8*7 -> 10.5
B9: 1 | C9: POD | D9: 5 | E9: Engineer | F9: DEV | G9: E3 | H9: ON | I9: FTC | J9: 0.42857143 | K9: =J9*7 -> 3
B10: 1 | C10: POD | D10: 6 | E10: Engineer | F10: DEV | G10: E2 | H10: OFF | I10: FTC | J10: 0.78571429 | K10: =J10*7 -> 5.5
B11: 1 | C11: POD | D11: 7 | E11: Engineer | F11: DEV | G11: E3 | H11: OFF | I11: FTC | J11: 0.57142857 | K11: =J11*7 -> 4
B12: 1 | C12: POD | D12: 8 | E12: Engineer | F12: DEV | G12: E4 | H12: OFF | I12: FTC | J12: 0.21428571 | K12: =J12*7 -> 1.5
B13: 1 | C13: POD | D13: 9 | E13: Quality Engineer (SDET) | F13: TEST | G13: E2 | H13: OFF | I13: FTC | J13: 1.0714286 | K13: =J13*7 -> 7.5
B14: 1 | C14: POD | D14: 10 | E14: Quality Engineer (SDET) | F14: TEST | G14: E3 | H14: OFF | I14: FTC | J14: 1.0714286 | K14: =J14*7 -> 7.5
B15: 1 | C15: POD | D15: 11 | E15: Quality Engineer (SDET) | F15: TEST | G15: E4 | H15: OFF | I15: FTC | J15: 0.28571429 | K15: =J15*7 -> 2
B16: 1 | C16: POD | D16: 12 | E16: Application Support | F16: MNT | G16: E1 | H16: OFF | I16: FTC | J16: 0.14285714 | K16: =J16*7 -> 1
B17: 1 | C17: POD | D17: 13 | E17: Application Support | F17: MNT | G17: E2 | H17: OFF | I17: FTC | J17: 0.21428571 | K17: =J17*7 -> 1.5
D18: POD size — Year 1 | J18: =SUM(J5:J17) -> 9.9285714
B20: 1 | C20: TEAM | D20: 1 | E20: MetLife Product Owner | F20: PM | G20: E4 | H20: ON | I20: FTE | J20: 0.73214286 | K20: =J20*28 -> 20.5
B21: 1 | C21: TEAM | D21: 2 | E21: MetLife Domain SME | F21: BSA | G21: E4 | H21: ON | I21: FTE | J21: 0.98214286 | K21: =J21*28 -> 27.5
B22: 1 | C22: TEAM | D22: 3 | E22: MetLife Operations Analyst | F22: MNT | G22: E3 | H22: ON | I22: FTE | J22: 0.46428571 | K22: =J22*28 -> 13
B23: 1 | C23: TEAM | D23: 4 | E23: MGCC Developer | F23: DEV | G23: E3 | H23: OFF | I23: MGCC | J23: 1.75 | K23: =J23*28 -> 49
B24: 1 | C24: TEAM | D24: 5 | E24: MGCC Test Engineer | F24: TEST | G24: E2 | H24: OFF | I24: MGCC | J24: 0.96428571 | K24: =J24*28 -> 27
B25: 1 | C25: TEAM | D25: 6 | E25: Business Analyst (bilingual) | F25: BSA | G25: E3 | H25: ON | I25: FTC | J25: 1.4107143 | K25: =J25*28 -> 39.5
B26: 1 | C26: TEAM | D26: 7 | E26: Developer / technical lead | F26: DEV | G26: E3 | H26: ON | I26: FTC | J26: 1.7142857 | K26: =J26*28 -> 48
B27: 1 | C27: TEAM | D27: 8 | E27: Developer | F27: DEV | G27: E1 | H27: OFF | I27: FTC | J27: 0.19642857 | K27: =J27*28 -> 5.5
B28: 1 | C28: TEAM | D28: 9 | E28: Developer | F28: DEV | G28: E2 | H28: OFF | I28: FTC | J28: 0.53571429 | K28: =J28*28 -> 15
B29: 1 | C29: TEAM | D29: 10 | E29: Developer | F29: DEV | G29: E3 | H29: OFF | I29: FTC | J29: 0.51785714 | K29: =J29*28 -> 14.5
B30: 1 | C30: TEAM | D30: 11 | E30: Test Lead / onshore tester | F30: TEST | G30: E3 | H30: ON | I30: FTC | J30: 1.8571429 | K30: =J30*28 -> 52
B31: 1 | C31: TEAM | D31: 12 | E31: Test Engineer | F31: TEST | G31: E2 | H31: OFF | I31: FTC | J31: 0.30357143 | K31: =J31*28 -> 8.5
... B33: 1 | C33: TEAM | D33: 14 | E33: Application Support | F33: MNT | G33: E2 | H33: OFF | I33: FTC | J33: 0.125 | K33: =J33*28 -> 3.5
D34: TEAM size — Year 1 | J34: =SUM(J20:J33) -> 11.875
B36: 2 | C36: POD | D36: 1 | E36: MetLife Product Owner | F36: PM | G36: E4 | H36: ON | I36: FTE | J36: 0.92857143 | K36: =J36*35 -> 32.5 | L36: 0.8
B37: 2 | C37: POD | D37: 2 | E37: MetLife Domain SME | F37: BSA | G37: E4 | H37: ON | I37: FTE | J37: 0.67142857 | K37: =J37*35 -> 23.5 | L37: 0.5
B38: 2 | C38: POD | D38: 3 | E38: MGCC Engineer | F38: DEV | G38: E3 | H38: OFF | I38: MGCC | J38: 1.8 | K38: =J38*35 -> 63 | L38: 1.7
B39: 2 | C39: POD | D39: 4 | E39: Business Analyst (bilingual) | F39: BSA | G39: E3 | H39: ON | I39: FTC | J39: 0.55 | K39: =J39*35 -> 19.25 | L39: 0.55
B40: 2 | C40: POD | D40: 5 | E40: Pod lead / senior engineer | F40: DEV | G40: E4 | H40: ON | I40: FTC | J40: 0.71 | K40: =J40*35 -> 24.85 | L40: 0.7
B41: 2 | C41: POD | D41: 6 | E41: AI Orchestrator | F41: OTH | G41: E4 | H41: OFF | I41: FTC | J41: 0.21428571 | K41: =J41*35 -> 7.5 | L41: 0.25
B42: 2 | C42: POD | D42: 7 | E42: AI-assisted engineer | F42: DEV | G42: E2 | H42: OFF | I42: FTC | J42: 0.3 | K42: =J42*35 -> 10.5 | L42: 0.35
B43: 2 | C43: POD | D43: 8 | E43: AI-assisted engineer | F43: DEV | G43: E3 | H43: OFF | I43: FTC | J43: 0.6 | K43: =J43*35 -> 21 | L43: 0.9
B44: 2 | C44: POD | D44: 9 | E44: Quality Engineer (SDET) | F44: TEST | G44: E3 | H44: OFF | I44: FTC | J44: 1.5 | K44: =J44*35 -> 52.5 | L44: 1.5
B45: 2 | C45: POD | D45: 10 | E45: Quality Engineer (SDET) | F45: TEST | G45: E4 | H45: OFF | I45: FTC | J45: 0.5 | K45: =J45*35 -> 17.5 | L45: 0.5
B46: 2 | C46: POD | D46: 11 | E46: Application Support | F46: MNT | G46: E1 | H46: OFF | I46: FTC | J46: 0.12857143 | K46: =J46*35 -> 4.5 | L46: 0.15
B47: 2 | C47: POD | D47: 12 | E47: Application Support | F47: MNT | G47: E2 | H47: OFF | I47: FTC | J47: 0.085714286 | K47: =J47*35 -> 3 | L47: 0.1
D48: POD size — Year 2 | J48: =SUM(J36:J47) -> 7.9885714
B50: 2 | C50: TEAM | D50: 1 | E50: MetLife Product Owner | F50: PM | G50: E4 | H50: ON | I50: FTE | J50: 0.83333333 | K50: =J50*3 -> 2.5
B51: 2 | C51: TEAM | D51: 2 | E51: MetLife Domain SME | F51: BSA | G51: E4 | H51: ON | I51: FTE | J51: 0.66666667 | K51: =J51*3 -> 2
B52: 2 | C52: TEAM | D52: 3 | E52: MGCC Developer | F52: DEV | G52: E3 | H52: OFF | I52: MGCC | J52: 1.6666667 | K52: =J52*3 -> 5
B53: 2 | C53: TEAM | D53: 4 | E53: MGCC Test Engineer | F53: TEST | G53: E3 | H53: OFF | I53: MGCC | J53: 0.83333333 | K53: =J53*3 -> 2.5
B54: 2 | C54: TEAM | D54: 5 | E54: Business Analyst (bilingual) | F54: BSA | G54: E3 | H54: ON | I54: FTC | J54: 0.5 | K54: =J54*3 -> 1.5
B55: 2 | C55: TEAM | D55: 6 | E55: Developer / technical lead | F55: DEV | G55: E3 | H55: ON | I55: FTC | J55: 1 | K55: =J55*3 -> 3
B56: 2 | C56: TEAM | D56: 7 | E56: Developer | F56: DEV | G56: E2 | H56: OFF | I56: FTC | J56: 0.5 | K56: =J56*3 -> 1.5
B57: 2 | C57: TEAM | D57: 8 | E57: Developer | F57: DEV | G57: E3 | H57: OFF | I57: FTC | J57: 0.83333333 | K57: =J57*3 -> 2.5
B58: 2 | C58: TEAM | D58: 9 | E58: Test Engineer (SDET) | F58: TEST | G58: E3 | H58: OFF | I58: FTC | J58: 2.1666667 | K58: =J58*3 -> 6.5
B59: 2 | C59: TEAM | D59: 10 | E59: Application Support | F59: MNT | G59: E1 | H59: OFF | I59: FTC | J59: 0.66666667 | K59: =J59*3 -> 2
B60: 2 | C60: TEAM | D60: 11 | E60: Application Support | F60: MNT | G60: E2 | H60: OFF | I60: FTC | J60: 0.33333333 | K60: =J60*3 -> 1
D61: TEAM size — Year 2 | J61: =SUM(J50:J60) -> 10
B63: 3 | C63: POD | D63: 1 | E63: MetLife Product Owner | F63: PM | G63: E4 | H63: ON | I63: FTE | J63: 0.93055556 | K63: =J63*36 -> 33.5 | L63: 0.75
B64: 3 | C64: POD | D64: 2 | E64: MetLife Domain SME | F64: BSA | G64: E4 | H64: ON | I64: FTE | J64: 0.61111111 | K64: =J64*36 -> 22 | L64: 0.45
B65: 3 | C65: POD | D65: 3 | E65: MGCC Engineer | F65: DEV | G65: E3 | H65: OFF | I65: MGCC | J65: 1.5277778 | K65: =J65*36 -> 55 | L65: 1.5
B66: 3 | C66: POD | D66: 4 | E66: Business Analyst (bilingual) | F66: BSA | G66: E3 | H66: ON | I66: FTC | J66: 0.45 | K66: =J66*36 -> 16.2 | L66: 0.55
B67: 3 | C67: POD | D67: 5 | E67: Pod lead (onshore) | F67: DEV | G67: E4 | H67: ON | I67: FTC | J67: 0.069444444 | K67: =J67*36 -> 2.5 | L67: 0.3
B68: 3 | C68: POD | D68: 6 | E68: Pod lead / senior engineer | F68: DEV | G68: E4 | H68: OFF | I68: FTC | J68: 0.56944444 | K68: =J68*36 -> 20.5 | L68: 0.3
B69: 3 | C69: POD | D69: 7 | E69: AI Orchestrator | F69: OTH | G69: E4 | H69: OFF | I69: FTC | J69: 0.25 | K69: =J69*36 -> 9 | L69: 0.25
B70: 3 | C70: POD | D70: 8 | E70: AI-assisted engineer | F70: DEV | G70: E2 | H70: OFF | I70: FTC | J70: 0.25 | K70: =J70*36 -> 9 | L70: 0.25
B71: 3 | C71: POD | D71: 9 | E71: AI-assisted engineer | F71: DEV | G71: E3 | H71: OFF | I71: FTC | J71: 0.55 | K71: =J71*36 -> 19.8 | L71: 0.85
B72: 3 | C72: POD | D72: 10 | E72: Quality Engineer (SDET) | F72: TEST | G72: E2 | H72: OFF | I72: FTC | J72: 0.43 | K72: =J72*36 -> 15.48 | L72: 0.45
B73: 3 | C73: POD | D73: 11 | E73: Quality Engineer (SDET) | F73: TEST | G73: E3 | H73: OFF | I73: FTC | J73: 0.7 | K73: =J73*36 -> 25.2 | L73: 0.8
B74: 3 | C74: POD | D74: 12 | E74: Quality Engineer (SDET) | F74: TEST | G74: E4 | H74: OFF | I74: FTC | J74: 0.5 | K74: =J74*36 -> 18 | L74: 0.5
... B76: 3 | C76: POD | D76: 14 | E76: Application Support | F76: MNT | G76: E2 | H76: OFF | I76: FTC | J76: 0.05 | K76: =J76*36 -> 1.8 | L76: 0.05
D77: POD size — Year 3 | J77: =SUM(J63:J76) -> 6.9883333
B79: 4 | C79: POD | D79: 1 | E79: MetLife Product Owner | F79: PM | G79: E4 | H79: ON | I79: FTE | J79: 0.72222222 | K79: =J79*36 -> 26 | L79: 0.7
B80: 4 | C80: POD | D80: 2 | E80: MetLife Domain SME | F80: BSA | G80: E4 | H80: ON | I80: FTE | J80: 0.47222222 | K80: =J80*36 -> 17 | L80: 0.5
B81: 4 | C81: POD | D81: 3 | E81: MGCC Engineer | F81: DEV | G81: E3 | H81: OFF | I81: MGCC | J81: 1.3611111 | K81: =J81*36 -> 49 | L81: 1.9
B82: 4 | C82: POD | D82: 4 | E82: Business Analyst (bilingual) | F82: BSA | G82: E3 | H82: ON | I82: FTC | J82: 0.2 | K82: =J82*36 -> 7.2 | L82: 0.35
B83: 4 | C83: POD | D83: 5 | E83: Pod lead (onshore) | F83: DEV | G83: E4 | H83: ON | I83: FTC | J83: 0 | K83: =J83*36 -> 0 | L83: 0.2
B84: 4 | C84: POD | D84: 6 | E84: Pod lead / senior engineer | F84: DEV | G84: E4 | H84: OFF | I84: FTC | J84: 0.45 | K84: =J84*36 -> 16.2 | L84: 0.2
B85: 4 | C85: POD | D85: 7 | E85: AI Orchestrator | F85: OTH | G85: E4 | H85: OFF | I85: FTC | J85: 0.25 | K85: =J85*36 -> 9 | L85: 0.25
B86: 4 | C86: POD | D86: 8 | E86: Agent engineer | F86: DEV | G86: E4 | H86: OFF | I86: FTC | J86: 0.83 | K86: =J86*36 -> 29.88 | L86: 0.3
B87: 4 | C87: POD | D87: 9 | E87: Quality Engineer (SDET) | F87: TEST | G87: E2 | H87: OFF | I87: FTC | J87: 0.40277778 | K87: =J87*36 -> 14.5 | L87: 0.5
B88: 4 | C88: POD | D88: 10 | E88: Quality Engineer (SDET) | F88: TEST | G88: E3 | H88: OFF | I88: FTC | J88: 0.52777778 | K88: =J88*36 -> 19 | L88: 0.5
B89: 4 | C89: POD | D89: 11 | E89: Quality Engineer (SDET) | F89: TEST | G89: E4 | H89: OFF | I89: FTC | J89: 0.4 | K89: =J89*36 -> 14.4 | L89: 0.5
B90: 4 | C90: POD | D90: 12 | E90: Application Support | F90: MNT | G90: E1 | H90: OFF | I90: FTC | J90: 0.15 | K90: =J90*36 -> 5.4 | L90: 0.05
B91: 4 | C91: POD | D91: 13 | E91: Application Support | F91: MNT | G91: E2 | H91: OFF | I91: FTC | J91: 0.05 | K91: =J91*36 -> 1.8 | L91: 0.05
D92: POD size — Year 4 | J92: =SUM(J79:J91) -> 5.8161111
B94: 5 | C94: POD | D94: 1 | E94: MetLife Product Owner | F94: PM | G94: E4 | H94: ON | I94: FTE | J94: 0.72727273 | K94: =J94*33 -> 24 | L94: 0.7
B95: 5 | C95: POD | D95: 2 | E95: MetLife Domain SME | F95: BSA | G95: E4 | H95: ON | I95: FTE | J95: 0.5 | K95: =J95*33 -> 16.5 | L95: 0.5
B96: 5 | C96: POD | D96: 3 | E96: MGCC Engineer | F96: DEV | G96: E3 | H96: OFF | I96: MGCC | J96: 1.3484848 | K96: =J96*33 -> 44.5 | L96: 1.9
B97: 5 | C97: POD | D97: 4 | E97: Business Analyst (bilingual) | F97: BSA | G97: E3 | H97: ON | I97: FTC | J97: 0.08 | K97: =J97*33 -> 2.64 | L97: 0.35
B98: 5 | C98: POD | D98: 5 | E98: Pod lead (onshore) | F98: DEV | G98: E4 | H98: ON | I98: FTC | J98: 0.03030303 | K98: =J98*33 -> 1 | L98: 0.2
B99: 5 | C99: POD | D99: 6 | E99: Pod lead / senior engineer | F99: DEV | G99: E4 | H99: OFF | I99: FTC | J99: 0.45 | K99: =J99*33 -> 14.85 | L99: 0.2
B100: 5 | C100: POD | D100: 7 | E100: AI Orchestrator | F100: OTH | G100: E4 | H100: OFF | I100: FTC | J100: 0.37878788 | K100: =J100*33 -> 12.5 | L100: 0.25
B101: 5 | C101: POD | D101: 8 | E101: Agent engineer | F101: DEV | G101: E4 | H101: OFF | I101: FTC | J101: 0.83 | K101: =J101*33 -> 27.39 | L101: 0.3
B102: 5 | C102: POD | D102: 9 | E102: Quality Engineer (SDET) | F102: TEST | G102: E2 | H102: OFF | I102: FTC | J102: 0.39 | K102: =J102*33 -> 12.87 | L102: 0.5
B103: 5 | C103: POD | D103: 10 | E103: Quality Engineer (SDET) | F103: TEST | G103: E3 | H103: OFF | I103: FTC | J103: 0.53030303 | K103: =J103*33 -> 17.5 | L103: 0.5
B104: 5 | C104: POD | D104: 11 | E104: Quality Engineer (SDET) | F104: TEST | G104: E4 | H104: OFF | I104: FTC | J104: 0.39 | K104: =J104*33 -> 12.87 | L104: 0.5
B105: 5 | C105: POD | D105: 12 | E105: Application Support | F105: MNT | G105: E1 | H105: OFF | I105: FTC | J105: 0.15 | K105: =J105*33 -> 4.95 | L105: 0.05
B106: 5 | C106: POD | D106: 13 | E106: Application Support | F106: MNT | G106: E2 | H106: OFF | I106: FTC | J106: 0.05 | K106: =J106*33 -> 1.65 | L106: 0.05
D107: POD size — Year 5 | J107: =SUM(J94:J106) -> 5.8551515
B109: Year-5 pods use the Year-4 anatomy.
B111: The seat ratio in column J is the modelling quantity — the share of one unit's establishment this role holds. Column K is what you hire: the ratio multiplied by the number of units that year. Every value in column K is a whole number of people, or a half where one person covers two units inside this domain.

Sheet Pod Plan
A1: Pod plan — how many pods and how many waterfall teams, per stream per year
A2: INPUT. This is where productivity shows up in the headcount, and where the agile conversion shows up in the unit mix.
B4: Year | C4: VS | D4: Value stream | E4: Pods | F4: Teams | G4: Units | H4: People
B5: 1 | C5: F2FILL | D5: F2F Illustlation | E5: 5 | F5: 13 | G5: =E5+F5 -> 18 | H5: =E5*SUM('Pod Library'!$J$5:$J$17)+F5*SUM('Pod Library'!$J$20:$J$33) -> 204.01786
B6: 1 | C6: BANCA | D6: Banca Illustlation | E6: 0 | F6: 12 | G6: =E6+F6 -> 12 | H6: =E6*SUM('Pod Library'!$J$5:$J$17)+F6*SUM('Pod Library'!$J$20:$J$33) -> 142.5
B7: 1 | C7: AGENT | D7: F2F Agent Enablement | E7: 1 | F7: 2 | G7: =E7+F7 -> 3 | H7: =E7*SUM('Pod Library'!$J$5:$J$17)+F7*SUM('Pod Library'!$J$20:$J$33) -> 33.678571
B8: 1 | C8: SUPP | D8: F2F SalesSupport | E8: 1 | F8: 1 | G8: =E8+F8 -> 2 | H8: =E8*SUM('Pod Library'!$J$5:$J$17)+F8*SUM('Pod Library'!$J$20:$J$33) -> 21.803571
D9: Year 1 total | E9: =SUM(E5:E8) -> 7 | F9: =SUM(F5:F8) -> 28 | G9: =SUM(G5:G8) -> 35 | H9: =SUM(H5:H8) -> 402
B11: 2 | C11: F2FILL | D11: F2F Illustlation | E11: 19 | F11: 0 | G11: =E11+F11 -> 19 | H11: =E11*SUM('Pod Library'!$J$36:$J$47)+F11*SUM('Pod Library'!$J$50:$J$60) -> 151.78286
B12: 2 | C12: BANCA | D12: Banca Illustlation | E12: 10 | F12: 3 | G12: =E12+F12 -> 13 | H12: =E12*SUM('Pod Library'!$J$36:$J$47)+F12*SUM('Pod Library'!$J$50:$J$60) -> 109.88571
B13: 2 | C13: AGENT | D13: F2F Agent Enablement | E13: 4 | F13: 0 | G13: =E13+F13 -> 4 | H13: =E13*SUM('Pod Library'!$J$36:$J$47)+F13*SUM('Pod Library'!$J$50:$J$60) -> 31.954286
B14: 2 | C14: SUPP | D14: F2F SalesSupport | E14: 2 | F14: 0 | G14: =E14+F14 -> 2 | H14: =E14*SUM('Pod Library'!$J$36:$J$47)+F14*SUM('Pod Library'!$J$50:$J$60) -> 15.977143
D15: Year 2 total | E15: =SUM(E11:E14) -> 35 | F15: =SUM(F11:F14) -> 3 | G15: =SUM(G11:G14) -> 38 | H15: =SUM(H11:H14) -> 309.6
B17: 3 | C17: F2FILL | D17: F2F Illustlation | E17: 18 | F17: 0 | G17: =E17+F17 -> 18 | H17: =E17*SUM('Pod Library'!$J$63:$J$76) -> 125.79
B18: 3 | C18: BANCA | D18: Banca Illustlation | E18: 13 | F18: 0 | G18: =E18+F18 -> 13 | H18: =E18*SUM('Pod Library'!$J$63:$J$76) -> 90.848333
B19: 3 | C19: AGENT | D19: F2F Agent Enablement | E19: 3 | F19: 0 | G19: =E19+F19 -> 3 | H19: =E19*SUM('Pod Library'!$J$63:$J$76) -> 20.965
B20: 3 | C20: SUPP | D20: F2F SalesSupport | E20: 2 | F20: 0 | G20: =E20+F20 -> 2 | H20: =E20*SUM('Pod Library'!$J$63:$J$76) -> 13.976667
D21: Year 3 total | E21: =SUM(E17:E20) -> 36 | F21: =SUM(F17:F20) -> 0 | G21: =SUM(G17:G20) -> 36 | H21: =SUM(H17:H20) -> 251.58
B23: 4 | C23: F2FILL | D23: F2F Illustlation | E23: 18 | F23: 0 | G23: =E23+F23 -> 18 | H23: =E23*SUM('Pod Library'!$J$79:$J$91) -> 104.69
B24: 4 | C24: BANCA | D24: Banca Illustlation | E24: 13 | F24: 0 | G24: =E24+F24 -> 13 | H24: =E24*SUM('Pod Library'!$J$79:$J$91) -> 75.609444
B25: 4 | C25: AGENT | D25: F2F Agent Enablement | E25: 3 | F25: 0 | G25: =E25+F25 -> 3 | H25: =E25*SUM('Pod Library'!$J$79:$J$91) -> 17.448333
B26: 4 | C26: SUPP | D26: F2F SalesSupport | E26: 2 | F26: 0 | G26: =E26+F26 -> 2 | H26: =E26*SUM('Pod Library'!$J$79:$J$91) -> 11.632222
D27: Year 4 total | E27: =SUM(E23:E26) -> 36 | F27: =SUM(F23:F26) -> 0 | G27: =SUM(G23:G26) -> 36 | H27: =SUM(H23:H26) -> 209.38
B29: 5 | C29: F2FILL | D29: F2F Illustlation | E29: 16 | F29: 0 | G29: =E29+F29 -> 16 | H29: =E29*SUM('Pod Library'!$J$94:$J$106) -> 93.682424
B30: 5 | C30: BANCA | D30: Banca Illustlation | E30: 12 | F30: 0 | G30: =E30+F30 -> 12 | H30: =E30*SUM('Pod Library'!$J$94:$J$106) -> 70.261818
B31: 5 | C31: AGENT | D31: F2F Agent Enablement | E31: 3 | F31: 0 | G31: =E31+F31 -> 3 | H31: =E31*SUM('Pod Library'!$J$94:$J$106) -> 17.565455
B32: 5 | C32: SUPP | D32: F2F SalesSupport | E32: 2 | F32: 0 | G32: =E32+F32 -> 2 | H32: =E32*SUM('Pod Library'!$J$94:$J$106) -> 11.710303
D33: Year 5 total | E33: =SUM(E29:E32) -> 33 | F33: =SUM(F29:F32) -> 0 | G33: =SUM(G29:G32) -> 33 | H33: =SUM(H29:H32) -> 193.22

Sheet Horizontal Teams
A1: Horizontal teams — work that is not stream-bounded
A2: INPUT, defined per year rather than scaled, because the sourcing mix inside the horizontal layer changes as MetLife's own population follows a slower reduction curve than Capgemini's.
B4: Year | C4: Team | D4: Role | E4: Role detail | F4: Exp | G4: Loc | H4: Sourcing | I4: Count | J4: People in the block
B5: 1 | C5: H1 | D5: MNT | E5: Service Delivery Manager | F5: E5 | G5: ON | H5: FTC | I5: 1 | J5: =I5 -> 1
B6: 1 | C6: H1 | D6: MNT | E6: Release & Environment Manager | F6: E4 | G6: ON | H6: FTC | I6: 2.5 | J6: =I6 -> 2.5
B7: 1 | C7: H1 | D7: MNT | E7: L2 Application Support | F7: E1 | G7: OFF | H7: FTC | I7: 2 | J7: =I7 -> 2
B8: 1 | C8: H1 | D8: MNT | E8: L2 Application Support | F8: E2 | G8: OFF | H8: FTC | I8: 1 | J8: =I8 -> 1
B9: 1 | C9: H1 | D9: MNT | E9: Incident & Problem Analyst | F9: E3 | G9: ON | H9: FTC | I9: 1 | J9: =I9 -> 1
B10: 1 | C10: H1 | D10: OTH | E10: Observability / AIOps Engineer | F10: E3 | G10: OFF | H10: FTC | I10: 1 | J10: =I10 -> 1
B11: 1 | C11: H1 | D11: DEV | E11: Platform & Integration Engineer | F11: E3 | G11: ON | H11: FTC | I11: 3.5 | J11: =I11 -> 3.5
B12: 1 | C12: H1 | D12: DEV | E12: Platform & Integration Engineer | F12: E3 | G12: OFF | H12: FTC | I12: 3 | J12: =I12 -> 3
B13: 1 | C13: H1 | D13: DEV | E13: Offshore Engineering Lead | F13: E5 | G13: OFF | H13: FTC | I13: 1 | J13: =I13 -> 1
B14: 1 | C14: H1 | D14: DEV | E14: MGCC Platform SRE | F14: E3 | G14: OFF | H14: MGCC | I14: 2.5 | J14: =I14 -> 2.5
B15: 1 | C15: H1 | D15: PM | E15: MetLife Service Owner | F15: E4 | G15: ON | H15: FTE | I15: 2 | J15: =I15 -> 2
B16: 1 | C16: H1 | D16: MNT | E16: MetLife Distribution Ops Analyst | F16: E3 | G16: ON | H16: FTE | I16: 5 | J16: =I16 -> 5
... B34: 1 | C34: H3 | D34: PM | E34: MetLife Portfolio Manager | F34: E4 | G34: ON | H34: FTE | I34: 1.5 | J34: =I34 -> 1.5
E35: Year 1 horizontal total | I35: =SUM(I5:I34) -> 64.5
B37: 2 | C37: H1 | D37: MNT | E37: Service Delivery Manager | F37: E5 | G37: ON | H37: FTC | I37: 1.5 | J37: =I37 -> 1.5
B38: 2 | C38: H1 | D38: MNT | E38: Release & Environment Manager | F38: E4 | G38: ON | H38: FTC | I38: 2.5 | J38: =I38 -> 2.5
B39: 2 | C39: H1 | D39: MNT | E39: L2 Application Support | F39: E1 | G39: OFF | H39: FTC | I39: 1 | J39: =I39 -> 1
B40: 2 | C40: H1 | D40: MNT | E40: L2 Application Support | F40: E2 | G40: OFF | H40: FTC | I40: 1 | J40: =I40 -> 1
B41: 2 | C41: H1 | D41: MNT | E41: Incident & Problem Analyst | F41: E3 | G41: ON | H41: FTC | I41: 1 | J41: =I41 -> 1
B42: 2 | C42: H1 | D42: OTH | E42: Observability / AIOps Engineer | F42: E3 | G42: OFF | H42: FTC | I42: 2.5 | J42: =I42 -> 2.5
B43: 2 | C43: H1 | D43: DEV | E43: Platform & Integration Engineer | F43: E3 | G43: ON | H43: FTC | I43: 2.5 | J43: =I43 -> 2.5
B44: 2 | C44: H1 | D44: DEV | E44: Platform & Integration Engineer | F44: E3 | G44: OFF | H44: FTC | I44: 0.5 | J44: =I44 -> 0.5
B45: 2 | C45: H1 | D45: DEV | E45: Offshore Engineering Lead | F45: E5 | G45: OFF | H45: FTC | I45: 0.5 | J45: =I45 -> 0.5
B46: 2 | C46: H1 | D46: DEV | E46: MGCC Platform SRE | F46: E3 | G46: OFF | H46: MGCC | I46: 3 | J46: =I46 -> 3
B47: 2 | C47: H1 | D47: PM | E47: MetLife Service Owner | F47: E4 | G47: ON | H47: FTE | I47: 1.5 | J47: =I47 -> 1.5
B48: 2 | C48: H1 | D48: MNT | E48: MetLife Distribution Ops Analyst | F48: E3 | G48: ON | H48: FTE | I48: 5 | J48: =I48 -> 5
... B66: 2 | C66: H3 | D66: PM | E66: MetLife Portfolio Manager | F66: E4 | G66: ON | H66: FTE | I66: 1.5 | J66: =I66 -> 1.5
E67: Year 2 horizontal total | I67: =SUM(I37:I66) -> 50
B69: 3 | C69: H1 | D69: MNT | E69: Service Delivery Manager | F69: E5 | G69: ON | H69: FTC | I69: 1 | J69: =I69 -> 1
B70: 3 | C70: H1 | D70: MNT | E70: Release & Environment Manager | F70: E4 | G70: ON | H70: FTC | I70: 1 | J70: =I70 -> 1
B71: 3 | C71: H1 | D71: MNT | E71: L2 Application Support | F71: E1 | G71: OFF | H71: FTC | I71: 0.5 | J71: =I71 -> 0.5
B72: 3 | C72: H1 | D72: MNT | E72: L2 Application Support | F72: E2 | G72: OFF | H72: FTC | I72: 0.5 | J72: =I72 -> 0.5
B73: 3 | C73: H1 | D73: MNT | E73: Incident & Problem Analyst | F73: E3 | G73: ON | H73: FTC | I73: 1 | J73: =I73 -> 1
B74: 3 | C74: H1 | D74: OTH | E74: Observability / AIOps Engineer | F74: E3 | G74: OFF | H74: FTC | I74: 0.5 | J74: =I74 -> 0.5
B75: 3 | C75: H1 | D75: DEV | E75: Platform & Integration Engineer | F75: E3 | G75: ON | H75: FTC | I75: 1.5 | J75: =I75 -> 1.5
B76: 3 | C76: H1 | D76: DEV | E76: Platform & Integration Engineer | F76: E3 | G76: OFF | H76: FTC | I76: 0.5 | J76: =I76 -> 0.5
B77: 3 | C77: H1 | D77: DEV | E77: Offshore Engineering Lead | F77: E5 | G77: OFF | H77: FTC | I77: 0.5 | J77: =I77 -> 0.5
B78: 3 | C78: H1 | D78: DEV | E78: MGCC Platform SRE | F78: E3 | G78: OFF | H78: MGCC | I78: 4.5 | J78: =I78 -> 4.5
B79: 3 | C79: H1 | D79: PM | E79: MetLife Service Owner | F79: E4 | G79: ON | H79: FTE | I79: 1 | J79: =I79 -> 1
B80: 3 | C80: H1 | D80: MNT | E80: MetLife Distribution Ops Analyst | F80: E3 | G80: ON | H80: FTE | I80: 4.5 | J80: =I80 -> 4.5
... B98: 3 | C98: H3 | D98: PM | E98: MetLife Portfolio Manager | F98: E4 | G98: ON | H98: FTE | I98: 0.5 | J98: =I98 -> 0.5
E99: Year 3 horizontal total | I99: =SUM(I69:I98) -> 38.5
B101: 4 | C101: H1 | D101: MNT | E101: Service Delivery Manager | F101: E5 | G101: ON | H101: FTC | I101: 0.5 | J101: =I101 -> 0.5
B102: 4 | C102: H1 | D102: MNT | E102: Release & Environment Manager | F102: E4 | G102: ON | H102: FTC | I102: 0.5 | J102: =I102 -> 0.5
B103: 4 | C103: H1 | D103: MNT | E103: L2 Application Support | F103: E1 | G103: OFF | H103: FTC | I103: 0.5 | J103: =I103 -> 0.5
B104: 4 | C104: H1 | D104: MNT | E104: L2 Application Support | F104: E2 | G104: OFF | H104: FTC | I104: 0.5 | J104: =I104 -> 0.5
B105: 4 | C105: H1 | D105: MNT | E105: Incident & Problem Analyst | F105: E3 | G105: ON | H105: FTC | I105: 0.5 | J105: =I105 -> 0.5
B106: 4 | C106: H1 | D106: OTH | E106: Observability / AIOps Engineer | F106: E3 | G106: OFF | H106: FTC | I106: 0.5 | J106: =I106 -> 0.5
B107: 4 | C107: H1 | D107: DEV | E107: Platform & Integration Engineer | F107: E3 | G107: ON | H107: FTC | I107: 0.5 | J107: =I107 -> 0.5
B108: 4 | C108: H1 | D108: DEV | E108: Platform & Integration Engineer | F108: E3 | G108: OFF | H108: FTC | I108: 0.5 | J108: =I108 -> 0.5
B109: 4 | C109: H1 | D109: DEV | E109: Offshore Engineering Lead | F109: E5 | G109: OFF | H109: FTC | I109: 0.5 | J109: =I109 -> 0.5
B110: 4 | C110: H1 | D110: DEV | E110: MGCC Platform SRE | F110: E3 | G110: OFF | H110: MGCC | I110: 4.5 | J110: =I110 -> 4.5
B111: 4 | C111: H1 | D111: PM | E111: MetLife Service Owner | F111: E4 | G111: ON | H111: FTE | I111: 2.5 | J111: =I111 -> 2.5
B112: 4 | C112: H1 | D112: MNT | E112: MetLife Distribution Ops Analyst | F112: E3 | G112: ON | H112: FTE | I112: 5 | J112: =I112 -> 5
... B130: 4 | C130: H3 | D130: PM | E130: MetLife Portfolio Manager | F130: E4 | G130: ON | H130: FTE | I130: 2 | J130: =I130 -> 2
E131: Year 4 horizontal total | I131: =SUM(I101:I130) -> 41
B133: 5 | C133: H1 | D133: MNT | E133: Service Delivery Manager | F133: E5 | G133: ON | H133: FTC | I133: 0.5 | J133: =I133 -> 0.5
B134: 5 | C134: H1 | D134: MNT | E134: Release & Environment Manager | F134: E4 | G134: ON | H134: FTC | I134: 0.5 | J134: =I134 -> 0.5
B135: 5 | C135: H1 | D135: MNT | E135: L2 Application Support | F135: E1 | G135: OFF | H135: FTC | I135: 0.5 | J135: =I135 -> 0.5
B136: 5 | C136: H1 | D136: MNT | E136: L2 Application Support | F136: E2 | G136: OFF | H136: FTC | I136: 0.5 | J136: =I136 -> 0.5
B137: 5 | C137: H1 | D137: MNT | E137: Incident & Problem Analyst | F137: E3 | G137: ON | H137: FTC | I137: 0.5 | J137: =I137 -> 0.5
B138: 5 | C138: H1 | D138: OTH | E138: Observability / AIOps Engineer | F138: E3 | G138: OFF | H138: FTC | I138: 0.5 | J138: =I138 -> 0.5
B139: 5 | C139: H1 | D139: DEV | E139: Platform & Integration Engineer | F139: E3 | G139: ON | H139: FTC | I139: 0.5 | J139: =I139 -> 0.5
B140: 5 | C140: H1 | D140: DEV | E140: Platform & Integration Engineer | F140: E3 | G140: OFF | H140: FTC | I140: 0.5 | J140: =I140 -> 0.5
B141: 5 | C141: H1 | D141: DEV | E141: Offshore Engineering Lead | F141: E5 | G141: OFF | H141: FTC | I141: 0.5 | J141: =I141 -> 0.5
B142: 5 | C142: H1 | D142: DEV | E142: MGCC Platform SRE | F142: E3 | G142: OFF | H142: MGCC | I142: 4.5 | J142: =I142 -> 4.5
B143: 5 | C143: H1 | D143: PM | E143: MetLife Service Owner | F143: E4 | G143: ON | H143: FTE | I143: 2 | J143: =I143 -> 2
B144: 5 | C144: H1 | D144: MNT | E144: MetLife Distribution Ops Analyst | F144: E3 | G144: ON | H144: FTE | I144: 4.5 | J144: =I144 -> 4.5
... B162: 5 | C162: H3 | D162: PM | E162: MetLife Portfolio Manager | F162: E4 | G162: ON | H162: FTE | I162: 0.5 | J162: =I162 -> 0.5
E163: Year 5 horizontal total | I163: =SUM(I133:I162) -> 33.5
B165: H1 is sized from the Maintenance role and cross-checked against ticket volume on the AMS sheet. H2 carries the regression and test-data factory that the 37% tester share depends on. H3 is deliberately thin. The layer is now defined year by year rather than tapered by a single factor, because Capgemini and MetLife seats inside it shrink at different rates.

Sheet Team Build-Up
A1: Team build-up — and the Year-1 reconciliation to Appendix 3 v3
A2: Nothing on this sheet is typed. Section B is the test that matters: the roster has to be the client's own Year-1 position on effort, sourcing, location AND role.
A4: A. HEADCOUNT
B5: Measure | C5: Year 1 | D5: Year 2 | E5: Year 3 | F5: Year 4 | G5: Year 5
B6: People in agile pods | C6: =SUMIFS('Seat Ledger'!$M$5:$M$468,'Seat Ledger'!$B$5:$B$468,1,'Seat Ledger'!$C$5:$C$468,"POD") -> 69.5 | D6: =SUMIFS('Seat Ledger'!$M$5:$M$468,'Seat Ledger'!$B$5:$B$468,2,'Seat Ledger'!$C$5:$C$468,"POD") -> 279.6 | E6: =SUMIFS('Seat Ledger'!$M$5:$M$468,'Seat Ledger'!$B$5:$B$468,3,'Seat Ledger'!$C$5:$C$468,"POD") -> 251.58 | F6: =SUMIFS('Seat Ledger'!$M$5:$M$468,'Seat Ledger'!$B$5:$B$468,4,'Seat Ledger'!$C$5:$C$468,"POD") -> 209.38 | G6: =SUMIFS('Seat Ledger'!$M$5:$M$468,'Seat Ledger'!$B$5:$B$468,5,'Seat Ledger'!$C$5:$C$468,"POD") -> 193.22
B7: People in waterfall / hybrid teams | C7: =SUMIFS('Seat Ledger'!$M$5:$M$468,'Seat Ledger'!$B$5:$B$468,1,'Seat Ledger'!$C$5:$C$468,"TEAM") -> 332.5 | D7: =SUMIFS('Seat Ledger'!$M$5:$M$468,'Seat Ledger'!$B$5:$B$468,2,'Seat Ledger'!$C$5:$C$468,"TEAM") -> 30 | E7: =SUMIFS('Seat Ledger'!$M$5:$M$468,'Seat Ledger'!$B$5:$B$468,3,'Seat Ledger'!$C$5:$C$468,"TEAM") -> 0 | F7: =SUMIFS('Seat Ledger'!$M$5:$M$468,'Seat Ledger'!$B$5:$B$468,4,'Seat Ledger'!$C$5:$C$468,"TEAM") -> 0 | G7: =SUMIFS('Seat Ledger'!$M$5:$M$468,'Seat Ledger'!$B$5:$B$468,5,'Seat Ledger'!$C$5:$C$468,"TEAM") -> 0
B8: People in horizontal teams | C8: =SUMIFS('Seat Ledger'!$M$5:$M$468,'Seat Ledger'!$B$5:$B$468,1,'Seat Ledger'!$C$5:$C$468,"HZ") -> 64.5 | D8: =SUMIFS('Seat Ledger'!$M$5:$M$468,'Seat Ledger'!$B$5:$B$468,2,'Seat Ledger'!$C$5:$C$468,"HZ") -> 50 | E8: =SUMIFS('Seat Ledger'!$M$5:$M$468,'Seat Ledger'!$B$5:$B$468,3,'Seat Ledger'!$C$5:$C$468,"HZ") -> 38.5 | F8: =SUMIFS('Seat Ledger'!$M$5:$M$468,'Seat Ledger'!$B$5:$B$468,4,'Seat Ledger'!$C$5:$C$468,"HZ") -> 41 | G8: =SUMIFS('Seat Ledger'!$M$5:$M$468,'Seat Ledger'!$B$5:$B$468,5,'Seat Ledger'!$C$5:$C$468,"HZ") -> 33.5
B9: TOTAL PEOPLE | C9: =SUM(C6:C8) -> 466.5 | D9: =SUM(D6:D8) -> 359.6 | E9: =SUM(E6:E8) -> 290.08 | F9: =SUM(F6:F8) -> 250.38 | G9: =SUM(G6:G8) -> 226.72
B10: Delivery units — pods / teams | C10: ='Delivery Mode'!C21&" / "&'Delivery Mode'!C23 -> 7 / 28 | D10: ='Delivery Mode'!D21&" / "&'Delivery Mode'!D23 -> 35 / 3 | E10: ='Delivery Mode'!E21&" / "&'Delivery Mode'!E23 -> 36 / 0 | F10: ='Delivery Mode'!F21&" / "&'Delivery Mode'!F23 -> 36 / 0 | G10: ='Delivery Mode'!G21&" / "&'Delivery Mode'!G23 -> 33 / 0
B11: Headcount target from the Logic Tree | C11: ='Logic Tree'!C53 -> 466.4723 | D11: ='Logic Tree'!D53 -> 359.39754 | E11: ='Logic Tree'!E53 -> 289.88187 | F11: ='Logic Tree'!F53 -> 250.20768 | G11: ='Logic Tree'!G53 -> 226.69243
B12: Variance to target | C12: =C9-C11 -> 0.0277 | D12: =D9-D11 -> 0.20246229 | E12: =E9-E11 -> 0.1981292 | F12: =F9-F11 -> 0.1723206 | G12: =G9-G11 -> 0.027574688
A14: B. YEAR-1 RECONCILIATION TO APPENDIX 3 v3 — the test of the whole rebuild
B15: Measure | C15: Model Year 1 | D15: Appendix 3 v3 | E15: Variance | H15: Reading
B16: Total effort / people | C16: =C9 -> 466.5 | D16: ='Logic Tree'!C7 -> 466.4723 | E16: =C16-D16 -> 0.0277 | H16: Whole-domain size.
B17: Capgemini FTC | C17: =SUMIFS('Seat Ledger'!$M$5:$M$468,'Seat Ledger'!$B$5:$B$468,1,'Seat Ledger'!$J$5:$J$468,"FTC") -> 284.5 | D17: ='Logic Tree'!C8 -> 284.543 | E17: =C17-D17 -> -0.043 | H17: The contracted population.
B18: MetLife Japan FTE | C18: =SUMIFS('Seat Ledger'!$M$5:$M$468,'Seat Ledger'!$B$5:$B$468,1,'Seat Ledger'!$J$5:$J$468,"FTE") -> 88.5 | D18: ='Logic Tree'!C9 -> 88.1292 | E18: =C18-D18 -> 0.3708 | H18: MetLife's own people inside the delivery units.
B19: MetLife MGCC | C19: =SUMIFS('Seat Ledger'!$M$5:$M$468,'Seat Ledger'!$B$5:$B$468,1,'Seat Ledger'!$J$5:$J$468,"MGCC") -> 93.5 | D19: ='Logic Tree'!C10 -> 93.8 | E19: =C19-D19 -> -0.3 | H19: Already offshore, already delivering.
B20: Capgemini onshore Tokyo | C20: =SUMIFS('Seat Ledger'!$M$5:$M$468,'Seat Ledger'!$B$5:$B$468,1,'Seat Ledger'!$J$5:$J$468,"FTC",'Seat Ledger'!$I$5:$I$468,"ON") -> 177 | D20: ='Logic Tree'!C11 -> 177.3681 | E20: =C20-D20 -> -0.3681 | H20: MEASURED, not assumed. It was a Capgemini assumption in v4.
B21: Capgemini offshore | C21: =SUMIFS('Seat Ledger'!$M$5:$M$468,'Seat Ledger'!$B$5:$B$468,1,'Seat Ledger'!$J$5:$J$468,"FTC",'Seat Ledger'!$I$5:$I$468,"OFF") -> 107.5 | D21: ='Logic Tree'!C12 -> 107.0916 | E21: =C21-D21 -> 0.4084 | H21: 37.6% of the Capgemini population, and 97 of these 107.2 seats are people we already have.
B22: Role — BSA | C22: =SUMIFS('Seat Ledger'!$M$5:$M$468,'Seat Ledger'!$B$5:$B$468,1,'Seat Ledger'!$J$5:$J$468,"FTC",'Seat Ledger'!$G$5:$G$468,"BSA") -> 46.5 | D22: ='Logic Tree'!C15 -> 47.7083 | E22: =C22-D22 -> -1.2083 | H22: Bilingual analysis. The scarcest capability.
B23: Role — Developer | C23: =SUMIFS('Seat Ledger'!$M$5:$M$468,'Seat Ledger'!$B$5:$B$468,1,'Seat Ledger'!$J$5:$J$468,"FTC",'Seat Ledger'!$G$5:$G$468,"DEV") -> 115 | D23: ='Logic Tree'!C16 -> 114.2306 | E23: =C23-D23 -> 0.7694 | H23: Includes working technical leads — see the README. | N23: s
B24: Role — Tester | C24: =SUMIFS('Seat Ledger'!$M$5:$M$468,'Seat Ledger'!$B$5:$B$468,1,'Seat Ledger'!$J$5:$J$468,"FTC",'Seat Ledger'!$G$5:$G$468,"TEST") -> 103 | D24: ='Logic Tree'!C17 -> 103.9166 | E24: =C24-D24 -> -0.9166 | H24: 37% of the Capgemini population. This is the waterfall signature.
B25: Role — Maintenance | C25: =SUMIFS('Seat Ledger'!$M$5:$M$468,'Seat Ledger'!$B$5:$B$468,1,'Seat Ledger'!$J$5:$J$468,"FTC",'Seat Ledger'!$G$5:$G$468,"MNT") -> 13.5 | D25: ='Logic Tree'!C18 -> 13.1458 | E25: =C25-D25 -> 0.3542 | H25: Cross-checked against ticket volume on the AMS sheet.
B26: Role — PM | C26: =SUMIFS('Seat Ledger'!$M$5:$M$468,'Seat Ledger'!$B$5:$B$468,1,'Seat Ledger'!$J$5:$J$468,"FTC",'Seat Ledger'!$G$5:$G$468,"PM") -> 4.5 | D26: ='Logic Tree'!C19 -> 3.7917 | E26: =C26-D26 -> 0.7083 | H26: 1.3% of the population. There is almost no management layer today.
B27: Role — Other | C27: =SUMIFS('Seat Ledger'!$M$5:$M$468,'Seat Ledger'!$B$5:$B$468,1,'Seat Ledger'!$J$5:$J$468,"FTC",'Seat Ledger'!$G$5:$G$468,"OTH") -> 2 | D27: ='Logic Tree'!C20 -> 1.75 | E27: =C27-D27 -> 0.25 | H27: Architecture and enablement.
B28: Largest absolute variance | E28: =MAX(ABS(E16),ABS(E17),ABS(E18),ABS(E19),ABS(E20),ABS(E21),ABS(E22),ABS(E23),ABS(E24),ABS(E25),ABS(E26),ABS(E27)) -> 1.2083 | H28: Twelve independent quantities, none of them tuned to each other. This is what the v2 pack could not test.
A30: C. SOURCING AND LOCATION
B31: Measure | C31: Year 1 | D31: Year 2 | E31: Year 3 | F31: Year 4 | G31: Year 5
B32: Capgemini (FTC) | C32: =SUMIFS('Seat Ledger'!$M$5:$M$468,'Seat Ledger'!$B$5:$B$468,1,'Seat Ledger'!$J$5:$J$468,"FTC") -> 284.5 | D32: =SUMIFS('Seat Ledger'!$M$5:$M$468,'Seat Ledger'!$B$5:$B$468,2,'Seat Ledger'!$J$5:$J$468,"FTC") -> 209.6 | E32: =SUMIFS('Seat Ledger'!$M$5:$M$468,'Seat Ledger'!$B$5:$B$468,3,'Seat Ledger'!$J$5:$J$468,"FTC") -> 161.58 | F32: =SUMIFS('Seat Ledger'!$M$5:$M$468,'Seat Ledger'!$B$5:$B$468,4,'Seat Ledger'!$J$5:$J$468,"FTC") -> 127.88 | G32: =SUMIFS('Seat Ledger'!$M$5:$M$468,'Seat Ledger'!$B$5:$B$468,5,'Seat Ledger'!$J$5:$J$468,"FTC") -> 118.72
B33: MetLife Japan (FTE) | C33: =SUMIFS('Seat Ledger'!$M$5:$M$468,'Seat Ledger'!$B$5:$B$468,1,'Seat Ledger'!$J$5:$J$468,"FTE") -> 88.5 | D33: =SUMIFS('Seat Ledger'!$M$5:$M$468,'Seat Ledger'!$B$5:$B$468,2,'Seat Ledger'!$J$5:$J$468,"FTE") -> 75.5 | E33: =SUMIFS('Seat Ledger'!$M$5:$M$468,'Seat Ledger'!$B$5:$B$468,3,'Seat Ledger'!$J$5:$J$468,"FTE") -> 66.5 | F33: =SUMIFS('Seat Ledger'!$M$5:$M$468,'Seat Ledger'!$B$5:$B$468,4,'Seat Ledger'!$J$5:$J$468,"FTE") -> 64 | G33: =SUMIFS('Seat Ledger'!$M$5:$M$468,'Seat Ledger'!$B$5:$B$468,5,'Seat Ledger'!$J$5:$J$468,"FTE") -> 57.5
B34: MetLife MGCC | C34: =SUMIFS('Seat Ledger'!$M$5:$M$468,'Seat Ledger'!$B$5:$B$468,1,'Seat Ledger'!$J$5:$J$468,"MGCC") -> 93.5 | D34: =SUMIFS('Seat Ledger'!$M$5:$M$468,'Seat Ledger'!$B$5:$B$468,2,'Seat Ledger'!$J$5:$J$468,"MGCC") -> 74.5 | E34: =SUMIFS('Seat Ledger'!$M$5:$M$468,'Seat Ledger'!$B$5:$B$468,3,'Seat Ledger'!$J$5:$J$468,"MGCC") -> 62 | F34: =SUMIFS('Seat Ledger'!$M$5:$M$468,'Seat Ledger'!$B$5:$B$468,4,'Seat Ledger'!$J$5:$J$468,"MGCC") -> 58.5 | G34: =SUMIFS('Seat Ledger'!$M$5:$M$468,'Seat Ledger'!$B$5:$B$468,5,'Seat Ledger'!$J$5:$J$468,"MGCC") -> 50.5
B35: RATIO — Capgemini share | C35: =IF(C9=0,0,C32/C9) -> 0.60986066 | D35: =IF(D9=0,0,D32/D9) -> 0.58286986 | E35: =IF(E9=0,0,E32/E9) -> 0.55701875 | F35: =IF(F9=0,0,F32/F9) -> 0.51074367 | G35: =IF(G9=0,0,G32/G9) -> 0.5236415
B36: Onshore Tokyo | C36: =SUMIFS('Seat Ledger'!$M$5:$M$468,'Seat Ledger'!$B$5:$B$468,1,'Seat Ledger'!$I$5:$I$468,"ON") -> 265.5 | D36: =SUMIFS('Seat Ledger'!$M$5:$M$468,'Seat Ledger'!$B$5:$B$468,2,'Seat Ledger'!$I$5:$I$468,"ON") -> 140.6 | E36: =SUMIFS('Seat Ledger'!$M$5:$M$468,'Seat Ledger'!$B$5:$B$468,3,'Seat Ledger'!$I$5:$I$468,"ON") -> 95.7 | F36: =SUMIFS('Seat Ledger'!$M$5:$M$468,'Seat Ledger'!$B$5:$B$468,4,'Seat Ledger'!$I$5:$I$468,"ON") -> 76.7 | G36: =SUMIFS('Seat Ledger'!$M$5:$M$468,'Seat Ledger'!$B$5:$B$468,5,'Seat Ledger'!$I$5:$I$468,"ON") -> 66.64
B37: Offshore | C37: =SUMIFS('Seat Ledger'!$M$5:$M$468,'Seat Ledger'!$B$5:$B$468,1,'Seat Ledger'!$I$5:$I$468,"OFF") -> 201 | D37: =SUMIFS('Seat Ledger'!$M$5:$M$468,'Seat Ledger'!$B$5:$B$468,2,'Seat Ledger'!$I$5:$I$468,"OFF") -> 219 | E37: =SUMIFS('Seat Ledger'!$M$5:$M$468,'Seat Ledger'!$B$5:$B$468,3,'Seat Ledger'!$I$5:$I$468,"OFF") -> 194.38 | F37: =SUMIFS('Seat Ledger'!$M$5:$M$468,'Seat Ledger'!$B$5:$B$468,4,'Seat Ledger'!$I$5:$I$468,"OFF") -> 173.68 | G37: =SUMIFS('Seat Ledger'!$M$5:$M$468,'Seat Ledger'!$B$5:$B$468,5,'Seat Ledger'!$I$5:$I$468,"OFF") -> 160.08
B38: Nearshore | C38: =SUMIFS('Seat Ledger'!$M$5:$M$468,'Seat Ledger'!$B$5:$B$468,1,'Seat Ledger'!$I$5:$I$468,"NEAR") -> 0 | D38: =SUMIFS('Seat Ledger'!$M$5:$M$468,'Seat Ledger'!$B$5:$B$468,2,'Seat Ledger'!$I$5:$I$468,"NEAR") -> 0 | E38: =SUMIFS('Seat Ledger'!$M$5:$M$468,'Seat Ledger'!$B$5:$B$468,3,'Seat Ledger'!$I$5:$I$468,"NEAR") -> 0 | F38: =SUMIFS('Seat Ledger'!$M$5:$M$468,'Seat Ledger'!$B$5:$B$468,4,'Seat Ledger'!$I$5:$I$468,"NEAR") -> 0 | G38: =SUMIFS('Seat Ledger'!$M$5:$M$468,'Seat Ledger'!$B$5:$B$468,5,'Seat Ledger'!$I$5:$I$468,"NEAR") -> 0
B39: Offshore share, whole team | C39: =IF(C9=0,0,(C37+C38)/C9) -> 0.43086817 | D39: =IF(D9=0,0,(D37+D38)/D9) -> 0.60901001 | E39: =IF(E9=0,0,(E37+E38)/E9) -> 0.67009101 | F39: =IF(F9=0,0,(F37+F38)/F9) -> 0.69366563 | G39: =IF(G9=0,0,(G37+G38)/G9) -> 0.70606916
B40: Target from the Logic Tree | C40: ='Logic Tree'!C60 -> 0.43826673 | D40: ='Logic Tree'!D60 -> 0.56375517 | E40: ='Logic Tree'!E60 -> 0.66642752 | F40: ='Logic Tree'!F60 -> 0.73487576 | G40: ='Logic Tree'!G60 -> 0.78050792
B41: Onshore-bound floor — MetLife retained seats | C41: =IF(C9=0,0,1-SUMIFS('Seat Ledger'!$M$5:$M$468,'Seat Ledger'!$B$5:$B$468,1,'Seat Ledger'!$I$5:$I$468,"ON",'Seat Ledger'!$J$5:$J$468,"FTE")/C9) -> 0.81028939 | D41: =IF(D9=0,0,1-SUMIFS('Seat Ledger'!$M$5:$M$468,'Seat Ledger'!$B$5:$B$468,2,'Seat Ledger'!$I$5:$I$468,"ON",'Seat Ledger'!$J$5:$J$468,"FTE")/D9) -> 0.79004449 | E41: =IF(E9=0,0,1-SUMIFS('Seat Ledger'!$M$5:$M$468,'Seat Ledger'!$B$5:$B$468,3,'Seat Ledger'!$I$5:$I$468,"ON",'Seat Ledger'!$J$5:$J$468,"FTE")/E9) -> 0.7707529 | F41: =IF(F9=0,0,1-SUMIFS('Seat Ledger'!$M$5:$M$468,'Seat Ledger'!$B$5:$B$468,4,'Seat Ledger'!$I$5:$I$468,"ON",'Seat Ledger'!$J$5:$J$468,"FTE")/F9) -> 0.74438853 | G41: =IF(G9=0,0,1-SUMIFS('Seat Ledger'!$M$5:$M$468,'Seat Ledger'!$B$5:$B$468,5,'Seat Ledger'!$I$5:$I$468,"ON",'Seat Ledger'!$J$5:$J$468,"FTE")/G9) -> 0.7463832
A43: D. ROLE MIX — MetLife's taxonomy, all sourcing types
B44: Role | C44: Year 1 | D44: Year 2 | E44: Year 3 | F44: Year 4 | G44: Year 5
B45: BSA — business and systems analysis | C45: =SUMIFS('Seat Ledger'!$M$5:$M$468,'Seat Ledger'!$B$5:$B$468,1,'Seat Ledger'!$G$5:$G$468,"BSA") -> 82 | D45: =SUMIFS('Seat Ledger'!$M$5:$M$468,'Seat Ledger'!$B$5:$B$468,2,'Seat Ledger'!$G$5:$G$468,"BSA") -> 51.25 | E45: =SUMIFS('Seat Ledger'!$M$5:$M$468,'Seat Ledger'!$B$5:$B$468,3,'Seat Ledger'!$G$5:$G$468,"BSA") -> 42.2 | F45: =SUMIFS('Seat Ledger'!$M$5:$M$468,'Seat Ledger'!$B$5:$B$468,4,'Seat Ledger'!$G$5:$G$468,"BSA") -> 28.7 | G45: =SUMIFS('Seat Ledger'!$M$5:$M$468,'Seat Ledger'!$B$5:$B$468,5,'Seat Ledger'!$G$5:$G$468,"BSA") -> 25.14
B46: Developer | C46: =SUMIFS('Seat Ledger'!$M$5:$M$468,'Seat Ledger'!$B$5:$B$468,1,'Seat Ledger'!$G$5:$G$468,"DEV") -> 178 | D46: =SUMIFS('Seat Ledger'!$M$5:$M$468,'Seat Ledger'!$B$5:$B$468,2,'Seat Ledger'!$G$5:$G$468,"DEV") -> 137.85 | E46: =SUMIFS('Seat Ledger'!$M$5:$M$468,'Seat Ledger'!$B$5:$B$468,3,'Seat Ledger'!$G$5:$G$468,"DEV") -> 113.8 | F46: =SUMIFS('Seat Ledger'!$M$5:$M$468,'Seat Ledger'!$B$5:$B$468,4,'Seat Ledger'!$G$5:$G$468,"DEV") -> 101.08 | G46: =SUMIFS('Seat Ledger'!$M$5:$M$468,'Seat Ledger'!$B$5:$B$468,5,'Seat Ledger'!$G$5:$G$468,"DEV") -> 93.74
B47: Tester | C47: =SUMIFS('Seat Ledger'!$M$5:$M$468,'Seat Ledger'!$B$5:$B$468,1,'Seat Ledger'!$G$5:$G$468,"TEST") -> 136 | D47: =SUMIFS('Seat Ledger'!$M$5:$M$468,'Seat Ledger'!$B$5:$B$468,2,'Seat Ledger'!$G$5:$G$468,"TEST") -> 94 | E47: =SUMIFS('Seat Ledger'!$M$5:$M$468,'Seat Ledger'!$B$5:$B$468,3,'Seat Ledger'!$G$5:$G$468,"TEST") -> 73.18 | F47: =SUMIFS('Seat Ledger'!$M$5:$M$468,'Seat Ledger'!$B$5:$B$468,4,'Seat Ledger'!$G$5:$G$468,"TEST") -> 60.4 | G47: =SUMIFS('Seat Ledger'!$M$5:$M$468,'Seat Ledger'!$B$5:$B$468,5,'Seat Ledger'!$G$5:$G$468,"TEST") -> 49.24
B48: Maintenance | C48: =SUMIFS('Seat Ledger'!$M$5:$M$468,'Seat Ledger'!$B$5:$B$468,1,'Seat Ledger'!$G$5:$G$468,"MNT") -> 31.5 | D48: =SUMIFS('Seat Ledger'!$M$5:$M$468,'Seat Ledger'!$B$5:$B$468,2,'Seat Ledger'!$G$5:$G$468,"MNT") -> 22.5 | E48: =SUMIFS('Seat Ledger'!$M$5:$M$468,'Seat Ledger'!$B$5:$B$468,3,'Seat Ledger'!$G$5:$G$468,"MNT") -> 13.9 | F48: =SUMIFS('Seat Ledger'!$M$5:$M$468,'Seat Ledger'!$B$5:$B$468,4,'Seat Ledger'!$G$5:$G$468,"MNT") -> 14.7 | G48: =SUMIFS('Seat Ledger'!$M$5:$M$468,'Seat Ledger'!$B$5:$B$468,5,'Seat Ledger'!$G$5:$G$468,"MNT") -> 13.6
B49: PM and product ownership | C49: =SUMIFS('Seat Ledger'!$M$5:$M$468,'Seat Ledger'!$B$5:$B$468,1,'Seat Ledger'!$G$5:$G$468,"PM") -> 35.5 | D49: =SUMIFS('Seat Ledger'!$M$5:$M$468,'Seat Ledger'!$B$5:$B$468,2,'Seat Ledger'!$G$5:$G$468,"PM") -> 41.5 | E49: =SUMIFS('Seat Ledger'!$M$5:$M$468,'Seat Ledger'!$B$5:$B$468,3,'Seat Ledger'!$G$5:$G$468,"PM") -> 36.5 | F49: =SUMIFS('Seat Ledger'!$M$5:$M$468,'Seat Ledger'!$B$5:$B$468,4,'Seat Ledger'!$G$5:$G$468,"PM") -> 32 | G49: =SUMIFS('Seat Ledger'!$M$5:$M$468,'Seat Ledger'!$B$5:$B$468,5,'Seat Ledger'!$G$5:$G$468,"PM") -> 28
B50: Other — architecture and enablement | C50: =SUMIFS('Seat Ledger'!$M$5:$M$468,'Seat Ledger'!$B$5:$B$468,1,'Seat Ledger'!$G$5:$G$468,"OTH") -> 3.5 | D50: =SUMIFS('Seat Ledger'!$M$5:$M$468,'Seat Ledger'!$B$5:$B$468,2,'Seat Ledger'!$G$5:$G$468,"OTH") -> 12.5 | E50: =SUMIFS('Seat Ledger'!$M$5:$M$468,'Seat Ledger'!$B$5:$B$468,3,'Seat Ledger'!$G$5:$G$468,"OTH") -> 10.5 | F50: =SUMIFS('Seat Ledger'!$M$5:$M$468,'Seat Ledger'!$B$5:$B$468,4,'Seat Ledger'!$G$5:$G$468,"OTH") -> 13.5 | G50: =SUMIFS('Seat Ledger'!$M$5:$M$468,'Seat Ledger'!$B$5:$B$468,5,'Seat Ledger'!$G$5:$G$468,"OTH") -> 17
B51: Tester share of the team | C51: =IF(C9=0,0,C47/C9) -> 0.29153269 | D51: =IF(D9=0,0,D47/D9) -> 0.26140156 | E51: =IF(E9=0,0,E47/E9) -> 0.25227523 | F51: =IF(F9=0,0,F47/F9) -> 0.24123333 | G51: =IF(G9=0,0,G47/G9) -> 0.21718419 | I51: 29% in Year 1 falling to 15% by Year 5 — the separate test cell collapsing into the pods.
A53: E. EXPERIENCE MIX
B54: Band | C54: Year 1 | D54: Year 2 | E54: Year 3 | F54: Year 4 | G54: Year 5
B55: E1 | C55: =SUMIFS('Seat Ledger'!$M$5:$M$468,'Seat Ledger'!$B$5:$B$468,1,'Seat Ledger'!$H$5:$H$468,"E1") -> 11.5 | D55: =SUMIFS('Seat Ledger'!$M$5:$M$468,'Seat Ledger'!$B$5:$B$468,2,'Seat Ledger'!$H$5:$H$468,"E1") -> 8.5 | E55: =SUMIFS('Seat Ledger'!$M$5:$M$468,'Seat Ledger'!$B$5:$B$468,3,'Seat Ledger'!$H$5:$H$468,"E1") -> 4.6 | F55: =SUMIFS('Seat Ledger'!$M$5:$M$468,'Seat Ledger'!$B$5:$B$468,4,'Seat Ledger'!$H$5:$H$468,"E1") -> 6.4 | G55: =SUMIFS('Seat Ledger'!$M$5:$M$468,'Seat Ledger'!$B$5:$B$468,5,'Seat Ledger'!$H$5:$H$468,"E1") -> 5.95
B56: E2 | C56: =SUMIFS('Seat Ledger'!$M$5:$M$468,'Seat Ledger'!$B$5:$B$468,1,'Seat Ledger'!$H$5:$H$468,"E2") -> 72.5 | D56: =SUMIFS('Seat Ledger'!$M$5:$M$468,'Seat Ledger'!$B$5:$B$468,2,'Seat Ledger'!$H$5:$H$468,"E2") -> 19.5 | E56: =SUMIFS('Seat Ledger'!$M$5:$M$468,'Seat Ledger'!$B$5:$B$468,3,'Seat Ledger'!$H$5:$H$468,"E2") -> 27.28 | F56: =SUMIFS('Seat Ledger'!$M$5:$M$468,'Seat Ledger'!$B$5:$B$468,4,'Seat Ledger'!$H$5:$H$468,"E2") -> 17.3 | G56: =SUMIFS('Seat Ledger'!$M$5:$M$468,'Seat Ledger'!$B$5:$B$468,5,'Seat Ledger'!$H$5:$H$468,"E2") -> 15.52
B57: E3 | C57: =SUMIFS('Seat Ledger'!$M$5:$M$468,'Seat Ledger'!$B$5:$B$468,1,'Seat Ledger'!$H$5:$H$468,"E3") -> 286 | D57: =SUMIFS('Seat Ledger'!$M$5:$M$468,'Seat Ledger'!$B$5:$B$468,2,'Seat Ledger'!$H$5:$H$468,"E3") -> 198.75 | E57: =SUMIFS('Seat Ledger'!$M$5:$M$468,'Seat Ledger'!$B$5:$B$468,3,'Seat Ledger'!$H$5:$H$468,"E3") -> 136.7 | F57: =SUMIFS('Seat Ledger'!$M$5:$M$468,'Seat Ledger'!$B$5:$B$468,4,'Seat Ledger'!$H$5:$H$468,"E3") -> 94.7 | G57: =SUMIFS('Seat Ledger'!$M$5:$M$468,'Seat Ledger'!$B$5:$B$468,5,'Seat Ledger'!$H$5:$H$468,"E3") -> 80.64
B58: E4 | C58: =SUMIFS('Seat Ledger'!$M$5:$M$468,'Seat Ledger'!$B$5:$B$468,1,'Seat Ledger'!$H$5:$H$468,"E4") -> 89.5 | D58: =SUMIFS('Seat Ledger'!$M$5:$M$468,'Seat Ledger'!$B$5:$B$468,2,'Seat Ledger'!$H$5:$H$468,"E4") -> 125.35 | E58: =SUMIFS('Seat Ledger'!$M$5:$M$468,'Seat Ledger'!$B$5:$B$468,3,'Seat Ledger'!$H$5:$H$468,"E4") -> 117 | F58: =SUMIFS('Seat Ledger'!$M$5:$M$468,'Seat Ledger'!$B$5:$B$468,4,'Seat Ledger'!$H$5:$H$468,"E4") -> 125.48 | G58: =SUMIFS('Seat Ledger'!$M$5:$M$468,'Seat Ledger'!$B$5:$B$468,5,'Seat Ledger'!$H$5:$H$468,"E4") -> 118.11
B59: E5 | C59: =SUMIFS('Seat Ledger'!$M$5:$M$468,'Seat Ledger'!$B$5:$B$468,1,'Seat Ledger'!$H$5:$H$468,"E5") -> 7 | D59: =SUMIFS('Seat Ledger'!$M$5:$M$468,'Seat Ledger'!$B$5:$B$468,2,'Seat Ledger'!$H$5:$H$468,"E5") -> 7.5 | E59: =SUMIFS('Seat Ledger'!$M$5:$M$468,'Seat Ledger'!$B$5:$B$468,3,'Seat Ledger'!$H$5:$H$468,"E5") -> 4.5 | F59: =SUMIFS('Seat Ledger'!$M$5:$M$468,'Seat Ledger'!$B$5:$B$468,4,'Seat Ledger'!$H$5:$H$468,"E5") -> 6.5 | G59: =SUMIFS('Seat Ledger'!$M$5:$M$468,'Seat Ledger'!$B$5:$B$468,5,'Seat Ledger'!$H$5:$H$468,"E5") -> 6.5
B60: Senior share (E4 + E5) | C60: =IF(C9=0,0,(C58+C59)/C9) -> 0.20685959 | D60: =IF(D9=0,0,(D58+D59)/D9) -> 0.36943826 | E60: =IF(E9=0,0,(E58+E59)/E9) -> 0.41884997 | F60: =IF(F9=0,0,(F58+F59)/F9) -> 0.52711878 | G60: =IF(G9=0,0,(G58+G59)/G9) -> 0.54962068

Sheet Inherited Workforce
A1: The 99 Capgemini people already on these applications — and how they reshape themselves
A2: New in v6. Supply comes from the T3 headcount reconciliation behind Golden Inventory v4. Demand comes from the seat ledger. The difference is the hiring, promotion and reskilling plan.
A4: A. WHERE THE NUMBER COMES FROM
B5: Source | C5: Count | D5: What it is used for
B6: Billing details — named individuals | C6: 277 | D6: THE COUNT. 277 de-duplicated employee IDs across T3, DMO and JET, each with a location and a Capgemini grade.
B7: Mapping of current Capgemini staff — billable FTE | C7: 283 | D7: THE ROLE MIX and the grade ladder. Developer → Developer, Cloud Engineer → Maintenance, Testers → Tester, BSA / Scrum Master / Functional Analyst → BSA, Tech Lead / Solution Architect → Other.
B8: EAIs.xlsx — 'CG HC by EAI' | C8: 450 | D8: THE SHAPE of the application-level distribution, rescaled to 277 and capped at each application's own vendor FTC.
B9: EAIs.xlsx Sheet1 — direct EAI tags | C9: 528 | D9: Cross-check only. Double-counts people serving more than one application.
B10: Of the 277, allocated to Sales applications | C10: 99 | D10: 97 in India, 2 in Japan. 45 of the 277 sit in cross-domain teams with no application mapping and are excluded from every domain.
B12: Capgemini grade → experience band: A4/A5 → E1 · B1/B2 → E2 · C1 and Sub-Con → E3 · C2/D1 → E4 · D2/E1 → E5. Location is binary: Japan → onshore, everything else → India / offshore.
A14: B. WHERE THEY SIT TODAY
B15: Application | C15: Archetype | D15: Value stream | E15: CG heads today
B16: JP-GSSP | C16: M | D16: F2F Illustlation | E16: 55.51 | J16: 56% of the inherited population sits on one application. JP-GSSP is also 49% of the domain's effort, so the concentration is real rather than an artefact of the allocation.
B17: JP-Banca Report | C17: D | D17: Banca Illustlation | E17: 31.69
B18: WPSCFC-JPN | C18: M | D18: F2F Agent Enablement | E18: 8.81
B19: JP - Remote Closing | C19: M | D19: F2F SalesSupport | E19: 2.68
B20: P02BKE-JPN | C20: J | D20: Banca Illustlation | E20: 0.29
B21: W09WSD-JPN BIS | C21: T | D21: Banca Illustlation | E21: 0.02
B22: TOTAL | E22: =SUM(E16:E21) -> 99
A24: C. THE EVOLUTION MECHANIC — INPUT
B25: Band | C25: Attrition — offshore | D25: Attrition — onshore | E25: Promotion out of band
B26: E1 | C26: 0.22 | D26: 0.1 | E26: 0.2 | J26: Attrition is applied first and promotion to the survivors. Both rates are steepest at the junior bands, which is the shape of the Indian IT market. These two numbers do most of the pyramid-to-diamond work and they are the ones to challenge.
B27: E2 | C27: 0.18 | D27: 0.09 | E27: 0.16
B28: E3 | C28: 0.13 | D28: 0.07 | E28: 0.12
B29: E4 | C29: 0.09 | D29: 0.05 | E29: 0.07
B30: E5 | C30: 0.06 | D30: 0.04 | E30: 0
A32: D. THE COHORT ROLLED FORWARD
B33: Measure | C33: Year 1 | D33: Year 2 | E33: Year 3 | F33: Year 4 | G33: Year 5
B34: Inherited people surviving | C34: 99 | D34: 83.78 | E34: 71.55041 | F34: 61.635578 | G34: 53.525796
B35: — E1 | C35: 10 | D35: 6.24 | E35: 3.89376 | F35: 2.4297062 | G35: 1.5161367
B36: — E2 | C36: 39 | D36: 28.4232 | E36: 20.55134 | F36: 14.76319 | G36: 10.547919
B37: — E3 | C37: 42 | D37: 37.3776 | E37: 32.431837 | F37: 27.596879 | G37: 23.122985
B38: — E4 | C38: 6 | D38: 9.477 | E38: 11.942695 | F38: 13.516762 | G38: 14.346289
B39: — E5 | C39: 2 | D39: 2.2622 | E39: 2.7307779 | F39: 3.3290413 | G39: 3.9924651
B40: Senior share (E4 + E5) | C40: 0.080808081 | D40: 0.14011936 | E40: 0.2050788 | F40: 0.27331297 | G40: 0.34261526 | J40: 8.1% senior on day one, 34.3% by Year 5. Nobody is instructed to reshape anything — attrition removes juniors faster and promotion moves the survivors up. This is the pyramid-to-diamond claim, and here it is a derivation rather than an assertion.
B41: — in Japan | C41: 2 | D41: 1.86 | E41: 1.734264 | F41: 1.6209081 | G41: 1.5183319
B42: — in India | C42: 97 | D42: 81.92 | E42: 69.816146 | F42: 60.01467 | G42: 52.007464
A43: E. SUPPLY AGAINST DEMAND — offshore, where 97 of the 99 sit
B44: Measure | C44: Year 1 | D44: Year 2 | E44: Year 3 | F44: Year 4 | G44: Year 5
B45: Offshore Capgemini seats the design asks for | C45: =SUMIFS('Seat Ledger'!$M$5:$M$468,'Seat Ledger'!$B$5:$B$468,1,'Seat Ledger'!$J$5:$J$468,"FTC",'Seat Ledger'!$I$5:$I$468,"OFF") -> 107.5 | D45: =SUMIFS('Seat Ledger'!$M$5:$M$468,'Seat Ledger'!$B$5:$B$468,2,'Seat Ledger'!$J$5:$J$468,"FTC",'Seat Ledger'!$I$5:$I$468,"OFF") -> 144.5 | E45: =SUMIFS('Seat Ledger'!$M$5:$M$468,'Seat Ledger'!$B$5:$B$468,3,'Seat Ledger'!$J$5:$J$468,"FTC",'Seat Ledger'!$I$5:$I$468,"OFF") -> 132.38 | F45: =SUMIFS('Seat Ledger'!$M$5:$M$468,'Seat Ledger'!$B$5:$B$468,4,'Seat Ledger'!$J$5:$J$468,"FTC",'Seat Ledger'!$I$5:$I$468,"OFF") -> 115.18 | G45: =SUMIFS('Seat Ledger'!$M$5:$M$468,'Seat Ledger'!$B$5:$B$468,5,'Seat Ledger'!$J$5:$J$468,"FTC",'Seat Ledger'!$I$5:$I$468,"OFF") -> 109.58
B46: Inherited people still there | C46: 97 | D46: 81.92 | E46: 69.816146 | F46: 60.01467 | G46: 52.007464
B47: Covered by people we already have | C47: =C46/C45 -> 0.90232558 | D47: =D46/D45 -> 0.56692042 | E47: =E46/E45 -> 0.52739195 | F47: =F46/F45 -> 0.52105114 | G47: =G46/G45 -> 0.47460726
B48: To hire, redeploy or reskill | C48: =C45-C46 -> 10.5 | D48: =D45-D46 -> 62.58 | E48: =E45-E46 -> 62.563854 | F48: =F45-F46 -> 55.16533 | G48: =G45-G46 -> 57.572536
A50: F. BAND BY BAND — the seats we designed against the people we hold, offshore
B51: Year 1 | C51: E1 | D51: E2 | E51: E3 | F51: E4 | G51: E5 | H51: Total
B52: Seats the design asks for | C52: =SUMIFS('Seat Ledger'!$M$5:$M$468,'Seat Ledger'!$B$5:$B$468,1,'Seat Ledger'!$J$5:$J$468,"FTC",'Seat Ledger'!$I$5:$I$468,"OFF",'Seat Ledger'!$H$5:$H$468,"E1") -> 11.5 | D52: =SUMIFS('Seat Ledger'!$M$5:$M$468,'Seat Ledger'!$B$5:$B$468,1,'Seat Ledger'!$J$5:$J$468,"FTC",'Seat Ledger'!$I$5:$I$468,"OFF",'Seat Ledger'!$H$5:$H$468,"E2") -> 45.5 | E52: =SUMIFS('Seat Ledger'!$M$5:$M$468,'Seat Ledger'!$B$5:$B$468,1,'Seat Ledger'!$J$5:$J$468,"FTC",'Seat Ledger'!$I$5:$I$468,"OFF",'Seat Ledger'!$H$5:$H$468,"E3") -> 43 | F52: =SUMIFS('Seat Ledger'!$M$5:$M$468,'Seat Ledger'!$B$5:$B$468,1,'Seat Ledger'!$J$5:$J$468,"FTC",'Seat Ledger'!$I$5:$I$468,"OFF",'Seat Ledger'!$H$5:$H$468,"E4") -> 5.5 | G52: =SUMIFS('Seat Ledger'!$M$5:$M$468,'Seat Ledger'!$B$5:$B$468,1,'Seat Ledger'!$J$5:$J$468,"FTC",'Seat Ledger'!$I$5:$I$468,"OFF",'Seat Ledger'!$H$5:$H$468,"E5") -> 2 | H52: =SUM(C52:G52) -> 107.5
B53: People we already have | C53: 10 | D53: 39 | E53: 40 | F53: 6 | G53: 2 | H53: =SUM(C53:G53) -> 97
B54: Gap — positive is a hire | C54: =C52-C53 -> 1.5 | D54: =D52-D53 -> 6.5 | E54: =E52-E53 -> 3 | F54: =F52-F53 -> -0.5 | G54: =G52-G53 -> 0 | H54: =SUM(C54:G54) -> 10.5
B56: Year 2 | C56: E1 | D56: E2 | E56: E3 | F56: E4 | G56: E5 | H56: Total
B57: Seats the design asks for | C57: =SUMIFS('Seat Ledger'!$M$5:$M$468,'Seat Ledger'!$B$5:$B$468,2,'Seat Ledger'!$J$5:$J$468,"FTC",'Seat Ledger'!$I$5:$I$468,"OFF",'Seat Ledger'!$H$5:$H$468,"E1") -> 8.5 | D57: =SUMIFS('Seat Ledger'!$M$5:$M$468,'Seat Ledger'!$B$5:$B$468,2,'Seat Ledger'!$J$5:$J$468,"FTC",'Seat Ledger'!$I$5:$I$468,"OFF",'Seat Ledger'!$H$5:$H$468,"E2") -> 19.5 | E57: =SUMIFS('Seat Ledger'!$M$5:$M$468,'Seat Ledger'!$B$5:$B$468,2,'Seat Ledger'!$J$5:$J$468,"FTC",'Seat Ledger'!$I$5:$I$468,"OFF",'Seat Ledger'!$H$5:$H$468,"E3") -> 89.5 | F57: =SUMIFS('Seat Ledger'!$M$5:$M$468,'Seat Ledger'!$B$5:$B$468,2,'Seat Ledger'!$J$5:$J$468,"FTC",'Seat Ledger'!$I$5:$I$468,"OFF",'Seat Ledger'!$H$5:$H$468,"E4") -> 26 | G57: =SUMIFS('Seat Ledger'!$M$5:$M$468,'Seat Ledger'!$B$5:$B$468,2,'Seat Ledger'!$J$5:$J$468,"FTC",'Seat Ledger'!$I$5:$I$468,"OFF",'Seat Ledger'!$H$5:$H$468,"E5") -> 1 | H57: =SUM(C57:G57) -> 144.5
B58: People we already have | C58: 6.24 | D58: 28.4232 | E58: 35.7408 | F58: 9.2538 | G58: 2.2622 | H58: =SUM(C58:G58) -> 81.92
B59: Gap — positive is a hire | C59: =C57-C58 -> 2.26 | D59: =D57-D58 -> -8.9232 | E59: =E57-E58 -> 53.7592 | F59: =F57-F58 -> 16.7462 | G59: =G57-G58 -> -1.2622 | H59: =SUM(C59:G59) -> 62.58
B61: Year 3 | C61: E1 | D61: E2 | E61: E3 | F61: E4 | G61: E5 | H61: Total
B62: Seats the design asks for | C62: =SUMIFS('Seat Ledger'!$M$5:$M$468,'Seat Ledger'!$B$5:$B$468,3,'Seat Ledger'!$J$5:$J$468,"FTC",'Seat Ledger'!$I$5:$I$468,"OFF",'Seat Ledger'!$H$5:$H$468,"E1") -> 4.6 | D62: =SUMIFS('Seat Ledger'!$M$5:$M$468,'Seat Ledger'!$B$5:$B$468,3,'Seat Ledger'!$J$5:$J$468,"FTC",'Seat Ledger'!$I$5:$I$468,"OFF",'Seat Ledger'!$H$5:$H$468,"E2") -> 27.28 | E62: =SUMIFS('Seat Ledger'!$M$5:$M$468,'Seat Ledger'!$B$5:$B$468,3,'Seat Ledger'!$J$5:$J$468,"FTC",'Seat Ledger'!$I$5:$I$468,"OFF",'Seat Ledger'!$H$5:$H$468,"E3") -> 49 | F62: =SUMIFS('Seat Ledger'!$M$5:$M$468,'Seat Ledger'!$B$5:$B$468,3,'Seat Ledger'!$J$5:$J$468,"FTC",'Seat Ledger'!$I$5:$I$468,"OFF",'Seat Ledger'!$H$5:$H$468,"E4") -> 50.5 | G62: =SUMIFS('Seat Ledger'!$M$5:$M$468,'Seat Ledger'!$B$5:$B$468,3,'Seat Ledger'!$J$5:$J$468,"FTC",'Seat Ledger'!$I$5:$I$468,"OFF",'Seat Ledger'!$H$5:$H$468,"E5") -> 1 | H62: =SUM(C62:G62) -> 132.38
B63: People we already have | C63: 3.89376 | D63: 20.55134 | E63: 31.09228 | F63: 11.56283 | G63: 2.7159351 | H63: =SUM(C63:G63) -> 69.816146
B64: Gap — positive is a hire | C64: =C62-C63 -> 0.70624 | D64: =D62-D63 -> 6.7286598 | E64: =E62-E63 -> 17.90772 | F64: =F62-F63 -> 38.93717 | G64: =G62-G63 -> -1.7159351 | H64: =SUM(C64:G64) -> 62.563854
B66: Year 4 | C66: E1 | D66: E2 | E66: E3 | F66: E4 | G66: E5 | H66: Total
B67: Seats the design asks for | C67: =SUMIFS('Seat Ledger'!$M$5:$M$468,'Seat Ledger'!$B$5:$B$468,4,'Seat Ledger'!$J$5:$J$468,"FTC",'Seat Ledger'!$I$5:$I$468,"OFF",'Seat Ledger'!$H$5:$H$468,"E1") -> 6.4 | D67: =SUMIFS('Seat Ledger'!$M$5:$M$468,'Seat Ledger'!$B$5:$B$468,4,'Seat Ledger'!$J$5:$J$468,"FTC",'Seat Ledger'!$I$5:$I$468,"OFF",'Seat Ledger'!$H$5:$H$468,"E2") -> 17.3 | E67: =SUMIFS('Seat Ledger'!$M$5:$M$468,'Seat Ledger'!$B$5:$B$468,4,'Seat Ledger'!$J$5:$J$468,"FTC",'Seat Ledger'!$I$5:$I$468,"OFF",'Seat Ledger'!$H$5:$H$468,"E3") -> 20.5 | F67: =SUMIFS('Seat Ledger'!$M$5:$M$468,'Seat Ledger'!$B$5:$B$468,4,'Seat Ledger'!$J$5:$J$468,"FTC",'Seat Ledger'!$I$5:$I$468,"OFF",'Seat Ledger'!$H$5:$H$468,"E4") -> 69.98 | G67: =SUMIFS('Seat Ledger'!$M$5:$M$468,'Seat Ledger'!$B$5:$B$468,4,'Seat Ledger'!$J$5:$J$468,"FTC",'Seat Ledger'!$I$5:$I$468,"OFF",'Seat Ledger'!$H$5:$H$468,"E5") -> 1 | H67: =SUM(C67:G67) -> 115.18
B68: People we already have | C68: 2.4297062 | D68: 14.76319 | E68: 26.500586 | F68: 13.031657 | G68: 3.2895313 | H68: =SUM(C68:G68) -> 60.01467
B69: Gap — positive is a hire | C69: =C67-C68 -> 3.9702938 | D69: =D67-D68 -> 2.5368103 | E69: =E67-E68 -> -6.0005856 | F69: =F67-F68 -> 56.948343 | G69: =G67-G68 -> -2.2895313 | H69: =SUM(C69:G69) -> 55.16533
B71: Year 5 | C71: E1 | D71: E2 | E71: E3 | F71: E4 | G71: E5 | H71: Total
B72: Seats the design asks for | C72: =SUMIFS('Seat Ledger'!$M$5:$M$468,'Seat Ledger'!$B$5:$B$468,5,'Seat Ledger'!$J$5:$J$468,"FTC",'Seat Ledger'!$I$5:$I$468,"OFF",'Seat Ledger'!$H$5:$H$468,"E1") -> 5.95 | D72: =SUMIFS('Seat Ledger'!$M$5:$M$468,'Seat Ledger'!$B$5:$B$468,5,'Seat Ledger'!$J$5:$J$468,"FTC",'Seat Ledger'!$I$5:$I$468,"OFF",'Seat Ledger'!$H$5:$H$468,"E2") -> 15.52 | E72: =SUMIFS('Seat Ledger'!$M$5:$M$468,'Seat Ledger'!$B$5:$B$468,5,'Seat Ledger'!$J$5:$J$468,"FTC",'Seat Ledger'!$I$5:$I$468,"OFF",'Seat Ledger'!$H$5:$H$468,"E3") -> 19 | F72: =SUMIFS('Seat Ledger'!$M$5:$M$468,'Seat Ledger'!$B$5:$B$468,5,'Seat Ledger'!$J$5:$J$468,"FTC",'Seat Ledger'!$I$5:$I$468,"OFF",'Seat Ledger'!$H$5:$H$468,"E4") -> 68.11 | G72: =SUMIFS('Seat Ledger'!$M$5:$M$468,'Seat Ledger'!$B$5:$B$468,5,'Seat Ledger'!$J$5:$J$468,"FTC",'Seat Ledger'!$I$5:$I$468,"OFF",'Seat Ledger'!$H$5:$H$468,"E5") -> 1 | H72: =SUM(C72:G72) -> 109.58
B73: People we already have | C73: 1.5161367 | D73: 10.547919 | E73: 22.225779 | F73: 13.795353 | G73: 3.922276 | H73: =SUM(C73:G73) -> 52.007464
B74: Gap — positive is a hire | C74: =C72-C73 -> 4.4338633 | D74: =D72-D73 -> 4.9720808 | E74: =E72-E73 -> -3.2257789 | F74: =F72-F73 -> 54.314647 | G74: =G72-G73 -> -2.922276 | H74: =SUM(C74:G74) -> 57.572536
B76: Year 1 is the tight one and it fits: 97 people against 107.2 offshore seats, with the band mix within two people at every level except E2, where we need 7.5 more than we hold. The Year-2 E2 surplus of 6.7 and the Year-4 E3 surplus of 7.8 are the two places the inherited population genuinely disturbs the target shape — both are absorbed by promotion into the band above, and both are reported here rather than netted away.
A78: G. WHAT THIS MEANS FOR THE SOLUTION
B79: • The Year-1 offshore team is real. 97 of the 107.2 offshore Capgemini seats are filled by people who are on the payroll today, on these applications, with the band mix the design now asks for. That is a transition risk removed, and it is the strongest continuity argument this domain has.
B80: • The Year-1 onshore team is not. 177.2 bilingual onshore seats against 2 inherited people in Japan. Every one of the rest is a hire or a redeployment into Tokyo, and it is the largest single delivery risk in this 領域.
B81: • 185 of the 284.5 vendor units are not people we hold. Capgemini is the named incumbent on 177.3 units but carries only 99 heads against them; 83.4 units sit with unnamed vendors, 23.0 with NCD, 0.8 with FSI. Year 1 assumes Capgemini staffs all of it from day one, and it is priced as a hire, not a rebadge.
B82: • The diamond is earned rather than asserted. Senior share rises from 8.1% to 34.3% on attrition and promotion alone. Where the inherited shape and the target shape disagree — Year 2 at E2, Year 4 at E3 — the model follows the people and records the deviation, because the tenet is a direction of travel and not a constraint.

Sheet Glidepath & 50-50
A1: Glidepath — capability, carry-forward, offshore, and one transfer at the end of Year 3
A2: Year 1 passes nothing through. The transfer is struck on the exit position at full realisation.
A4: A. BASELINE
B5: Measure | C5: Value
B6: Applications | C6: ='Logic Tree'!C6 -> 13
B7: Total effort (units) | C7: ='Logic Tree'!C7 -> 466.4723
B8: Capgemini FTC | C8: ='Logic Tree'!C8 -> 284.543
B9: MetLife FTE | C9: ='Logic Tree'!C9 -> 88.1292
B10: MetLife MGCC | C10: ='Logic Tree'!C10 -> 93.8
B11: Ratio today — Capgemini share | C11: ='Logic Tree'!C23 -> 0.60998919
B12: Offshore today — whole team, measured | C12: ='Logic Tree'!C24 -> 0.43066137 | I12: 43.1% offshore on day one. In v4 this was modelled as a ramp from near zero, which was the single largest error the v3 pack exposes.
B13: Appendix 3 Year-3 target, each side | C13: ='Logic Tree'!C22 -> 233.2362
A15: B. PRODUCTIVITY
B16: Measure | C16: Year 1 | D16: Year 2 | E16: Year 3 | F16: Year 4 | G16: Year 5
B17: Agile share of the domain | C17: ='Delivery Mode'!C22 -> 0.18425542 | D17: ='Delivery Mode'!D22 -> 0.90947121 | E17: ='Delivery Mode'!E22 -> 1 | F17: ='Delivery Mode'!F22 -> 1 | G17: ='Delivery Mode'!G22 -> 1
B18: Capability earned by end of year | C18: ='Logic Tree'!C45 -> 0.13502164 | D18: ='Logic Tree'!D45 -> 0.32406141 | E18: ='Logic Tree'!E45 -> 0.43307006 | F18: ='Logic Tree'!F45 -> 0.49416451 | G18: ='Logic Tree'!G45 -> 0.53389171
B19: Banked from prior year | C19: ='Logic Tree'!C50 -> 0 | D19: ='Logic Tree'!D50 -> 0.13502164 | E19: ='Logic Tree'!E50 -> 0.32406141 | F19: ='Logic Tree'!F50 -> 0.43307006 | G19: ='Logic Tree'!G50 -> 0.49416451
B20: Pre-load of this year's gain | C20: ='Logic Tree'!C51 -> 0 | D20: ='Logic Tree'!D51 -> 0.094519886 | E20: ='Logic Tree'!E51 -> 0.054504326 | F20: ='Logic Tree'!F51 -> 0.030547222 | G20: ='Logic Tree'!G51 -> 0.019863604
B21: APPLIED TO STAFFING | C21: ='Logic Tree'!C52 -> 0 | D21: ='Logic Tree'!D52 -> 0.22954152 | E21: ='Logic Tree'!E52 -> 0.37856574 | F21: ='Logic Tree'!F52 -> 0.46361728 | G21: ='Logic Tree'!G52 -> 0.51402811 | I21: Year 1 applies nothing: the capability the tree allows is consumed by transition, substrate build and the agile conversion itself.
B22: Headcount target | C22: ='Logic Tree'!C53 -> 466.4723 | D22: ='Logic Tree'!D53 -> 359.39754 | E22: ='Logic Tree'!E53 -> 289.88187 | F22: ='Logic Tree'!F53 -> 250.20768 | G22: ='Logic Tree'!G53 -> 226.69243
B23: Headcount delivered by the design | C23: ='Team Build-Up'!C9 -> 466.5 | D23: ='Team Build-Up'!D9 -> 359.6 | E23: ='Team Build-Up'!E9 -> 290.08 | F23: ='Team Build-Up'!F9 -> 250.38 | G23: ='Team Build-Up'!G9 -> 226.72
B24: Variance | C24: ='Team Build-Up'!C12 -> 0.0277 | D24: ='Team Build-Up'!D12 -> 0.20246229 | E24: ='Team Build-Up'!E12 -> 0.1981292 | F24: ='Team Build-Up'!F12 -> 0.1723206 | G24: ='Team Build-Up'!G12 -> 0.027574688
B25: Delivered productivity vs baseline | C25: =1-C23/$C$7 -> -5.9381875e-05 | D25: =1-D23/$C$7 -> 0.22910749 | E25: =1-E23/$C$7 -> 0.378141 | F25: =1-F23/$C$7 -> 0.46324787 | G25: =1-G23/$C$7 -> 0.513969
B26: EXIT YEAR 3 — full realisation, the point the transfer is struck | E26: ='Logic Tree'!E54 -> 264.45711
A28: C. OFFSHORE
B29: Measure | C29: Year 1 | D29: Year 2 | E29: Year 3 | F29: Year 4 | G29: Year 5
B30: Delivered — bottom-up from seat locations | C30: ='Team Build-Up'!C39 -> 0.43086817 | D30: ='Team Build-Up'!D39 -> 0.60901001 | E30: ='Team Build-Up'!E39 -> 0.67009101 | F30: ='Team Build-Up'!F39 -> 0.69366563 | G30: ='Team Build-Up'!G39 -> 0.70606916
B31: Target — today plus the closed gap | C31: ='Logic Tree'!C60 -> 0.43826673 | D31: ='Logic Tree'!D60 -> 0.56375517 | E31: ='Logic Tree'!E60 -> 0.66642752 | F31: ='Logic Tree'!F60 -> 0.73487576 | G31: ='Logic Tree'!G60 -> 0.78050792
B32: Onshore-bound floor — the maximum reachable | C32: ='Team Build-Up'!C41 -> 0.81028939 | D32: ='Team Build-Up'!D41 -> 0.79004449 | E32: ='Team Build-Up'!E41 -> 0.7707529 | F32: ='Team Build-Up'!F41 -> 0.74438853 | G32: ='Team Build-Up'!G41 -> 0.7463832
B33: Movement from today, in people | C33: =C30*'Team Build-Up'!C9-$C$12*$C$7 -> 0.1084 | D33: =D30*'Team Build-Up'!D9-$C$12*$C$7 -> 18.1084 | E33: =E30*'Team Build-Up'!E9-$C$12*$C$7 -> -6.5116 | F33: =F30*'Team Build-Up'!F9-$C$12*$C$7 -> -27.2116 | G33: =G30*'Team Build-Up'!G9-$C$12*$C$7 -> -40.8116 | I33: The offshore SHARE rises every year while the offshore HEADCOUNT falls from Year 2. Both are true and only the second one costs anything.
A35: D. THE 50:50
B36: Measure | C36: Year 1 | D36: Year 2 | E36: Year 3 | F36: Year 4 | G36: Year 5
B37: Total people | C37: ='Team Build-Up'!C9 -> 466.5 | D37: ='Team Build-Up'!D9 -> 359.6 | E37: ='Team Build-Up'!E9 -> 290.08 | F37: ='Team Build-Up'!F9 -> 250.38 | G37: ='Team Build-Up'!G9 -> 226.72
B38: Capgemini FTC | C38: ='Team Build-Up'!C32 -> 284.5 | D38: ='Team Build-Up'!D32 -> 209.6 | E38: ='Team Build-Up'!E32 -> 161.58 | F38: ='Team Build-Up'!F32 -> 127.88 | G38: ='Team Build-Up'!G32 -> 118.72
B39: MetLife FTE | C39: ='Team Build-Up'!C33 -> 88.5 | D39: ='Team Build-Up'!D33 -> 75.5 | E39: ='Team Build-Up'!E33 -> 66.5 | F39: ='Team Build-Up'!F33 -> 64 | G39: ='Team Build-Up'!G33 -> 57.5
B40: MetLife MGCC | C40: ='Team Build-Up'!C34 -> 93.5 | D40: ='Team Build-Up'!D34 -> 74.5 | E40: ='Team Build-Up'!E34 -> 62 | F40: ='Team Build-Up'!F34 -> 58.5 | G40: ='Team Build-Up'!G34 -> 50.5
B41: MetLife side total | C41: =C39+C40 -> 182 | D41: =D39+D40 -> 150 | E41: =E39+E40 -> 128.5 | F41: =F39+F40 -> 122.5 | G41: =G39+G40 -> 108
B42: Transferred this year | C42: ='Logic Tree'!C65+'Logic Tree'!C66 -> 0 | D42: ='Logic Tree'!D65+'Logic Tree'!D66 -> 0 | E42: ='Logic Tree'!E65+'Logic Tree'!E66 -> 15 | F42: ='Logic Tree'!F65+'Logic Tree'!F66 -> 0 | G42: ='Logic Tree'!G65+'Logic Tree'!G66 -> 0
B43: RATIO — Capgemini share | C43: =IF(C37=0,0,C38/C37) -> 0.60986066 | D43: =IF(D37=0,0,D38/D37) -> 0.58286986 | E43: =IF(E37=0,0,E38/E37) -> 0.55701875 | F43: =IF(F37=0,0,F38/F37) -> 0.51074367 | G43: =IF(G37=0,0,G38/G37) -> 0.5236415
I44: Years 1-3 are the pre-transfer position. Year 4 and Year 5 already carry the transferred seats as MetLife, inside the pods.
A46: E. THE TRANSFER SOLVE
C47: Value
B48: Exit Year 3 headcount, full realisation | C48: =E26 -> 264.45711 | I48: 15 people: 5 to MetLife Japan and 10 to MGCC. In the previous version it was 29. Organic convergence — MetLife's populations on their own slower curves, Capgemini absorbing the balance — does the rest, and it does it without anyone changing employer.
B49: Capgemini share at the exit position | C49: =E43 -> 0.55701875
B50: Capgemini FTC at exit, before transfer | C50: =C48*C49 -> 147.30757
B51: 50:50 requires each side to be | C51: =C48/2 -> 132.22856
B52: TRANSFER REQUIRED | C52: =C50-C51 -> 15.079015 | I52: Co-sourced seats are the transfer population. No pod is broken.
B53: Transfer applied in the model | C53: ='Logic Tree'!E67 -> 15
B54: Variance | C54: =C53-C52 -> -0.079014887
A57: F. WHAT THIS DOMAIN NOW SHOWS
B58: • The productivity case survived the new data almost untouched: 44.99% AI ceiling against 44.73%, and an applied glidepath of 0 / 22.9 / 37.9 / 46.4 / 51.4% against 0 / 24.1 / 37.9 / 46.2 / 51.2%. Six archetypes instead of four changed the segmentation and not the answer.
B59: • The offshore case changed completely. 43.1% of this domain is already delivered offshore or by MGCC. We are not proposing to move work offshore — we are proposing to move it from 43% to 63% while the team halves.
B60: • The staffing case changed completely. A 37% tester share and a 1.3% PM share are not what any pod model would have invented, and both are now facts the Year-1 roster has to reproduce.
B61: • The transfer nearly doubles, from 16 to 29, because the baseline grew and because holding the sourcing proportions steady through Year 3 is the honest thing to do rather than letting FTC fall faster than MGCC.

Sheet Cost & Commercial
A1: Cost and commercial position — relative index pending the rate card
A2: Onshore Tokyo E2 = 1.00. Unit cost divides by the frozen baseline effort.
A4: A. TOTAL COST OF DELIVERING THE DOMAIN
B5: Measure | C5: Year 1 | D5: Year 2 | E5: Year 3 | F5: Year 4 | G5: Year 5
B6: Total cost index | C6: =SUMIFS('Seat Ledger'!$N$5:$N$468,'Seat Ledger'!$B$5:$B$468,1) -> 481.695 | D6: =SUMIFS('Seat Ledger'!$N$5:$N$468,'Seat Ledger'!$B$5:$B$468,2) -> 340.335 | E6: =SUMIFS('Seat Ledger'!$N$5:$N$468,'Seat Ledger'!$B$5:$B$468,3) -> 253.611 | F6: =SUMIFS('Seat Ledger'!$N$5:$N$468,'Seat Ledger'!$B$5:$B$468,4) -> 220.511 | G6: =SUMIFS('Seat Ledger'!$N$5:$N$468,'Seat Ledger'!$B$5:$B$468,5) -> 198.435
B7: Headcount | C7: ='Team Build-Up'!C9 -> 466.5 | D7: ='Team Build-Up'!D9 -> 359.6 | E7: ='Team Build-Up'!E9 -> 290.08 | F7: ='Team Build-Up'!F9 -> 250.38 | G7: ='Team Build-Up'!G9 -> 226.72
B8: Average cost per head | C8: =IF(C7=0,0,C6/C7) -> 1.0325723 | D8: =IF(D7=0,0,D6/D7) -> 0.94642659 | E8: =IF(E7=0,0,E6/E7) -> 0.87427951 | F8: =IF(F7=0,0,F6/F7) -> 0.88070533 | G8: =IF(G7=0,0,G6/G7) -> 0.87524259
B9: Cost per unit of frozen scope | C9: =IF('Glidepath & 50-50'!$C$7=0,0,C6/'Glidepath & 50-50'!$C$7) -> 1.0326337 | D9: =IF('Glidepath & 50-50'!$C$7=0,0,D6/'Glidepath & 50-50'!$C$7) -> 0.72959316 | E9: =IF('Glidepath & 50-50'!$C$7=0,0,E6/'Glidepath & 50-50'!$C$7) -> 0.54367858 | F9: =IF('Glidepath & 50-50'!$C$7=0,0,F6/'Glidepath & 50-50'!$C$7) -> 0.47272046 | G9: =IF('Glidepath & 50-50'!$C$7=0,0,G6/'Glidepath & 50-50'!$C$7) -> 0.42539503
B10: Unit cost reduction vs Year 1 | C10: =IF($C$9=0,0,1-C9/$C$9) -> 0 | D10: =IF($C$9=0,0,1-D9/$C$9) -> 0.29346371 | E10: =IF($C$9=0,0,1-E9/$C$9) -> 0.47350294 | F10: =IF($C$9=0,0,1-F9/$C$9) -> 0.54221862 | G10: =IF($C$9=0,0,1-G9/$C$9) -> 0.58804845
A12: B. CAPGEMINI POSITION
B13: Measure | C13: Year 1 | D13: Year 2 | E13: Year 3 | F13: Year 4 | G13: Year 5
B14: Capgemini heads | C14: ='Team Build-Up'!C32 -> 284.5 | D14: ='Team Build-Up'!D32 -> 209.6 | E14: ='Team Build-Up'!E32 -> 161.58 | F14: ='Team Build-Up'!F32 -> 127.88 | G14: ='Team Build-Up'!G32 -> 118.72
B15: Capgemini cost index | C15: =SUMIFS('Seat Ledger'!$N$5:$N$468,'Seat Ledger'!$B$5:$B$468,1,'Seat Ledger'!$J$5:$J$468,"FTC") -> 290.89 | D15: =SUMIFS('Seat Ledger'!$N$5:$N$468,'Seat Ledger'!$B$5:$B$468,2,'Seat Ledger'!$J$5:$J$468,"FTC") -> 171.67 | E15: =SUMIFS('Seat Ledger'!$N$5:$N$468,'Seat Ledger'!$B$5:$B$468,3,'Seat Ledger'!$J$5:$J$468,"FTC") -> 107.196 | F15: =SUMIFS('Seat Ledger'!$N$5:$N$468,'Seat Ledger'!$B$5:$B$468,4,'Seat Ledger'!$J$5:$J$468,"FTC") -> 78.591 | G15: =SUMIFS('Seat Ledger'!$N$5:$N$468,'Seat Ledger'!$B$5:$B$468,5,'Seat Ledger'!$J$5:$J$468,"FTC") -> 71.9
B16: Capgemini position vs Year 1 | C16: =IF($C$15=0,0,C15/$C$15-1) -> 0 | D16: =IF($C$15=0,0,D15/$C$15-1) -> -0.40984565 | E16: =IF($C$15=0,0,E15/$C$15-1) -> -0.63148957 | F16: =IF($C$15=0,0,F15/$C$15-1) -> -0.72982571 | G16: =IF($C$15=0,0,G15/$C$15-1) -> -0.75282753
A18: C. COST BY LOCATION, BAND AND ROLE
B19: Split | C19: Year 1 | D19: Year 2 | E19: Year 3 | F19: Year 4 | G19: Year 5
B20: Onshore Tokyo — cost index | C20: =SUMIFS('Seat Ledger'!$N$5:$N$468,'Seat Ledger'!$B$5:$B$468,1,'Seat Ledger'!$I$5:$I$468,"ON") -> 406.425 | D20: =SUMIFS('Seat Ledger'!$N$5:$N$468,'Seat Ledger'!$B$5:$B$468,2,'Seat Ledger'!$I$5:$I$468,"ON") -> 247.285 | E20: =SUMIFS('Seat Ledger'!$N$5:$N$468,'Seat Ledger'!$B$5:$B$468,3,'Seat Ledger'!$I$5:$I$468,"ON") -> 166.645 | F20: =SUMIFS('Seat Ledger'!$N$5:$N$468,'Seat Ledger'!$B$5:$B$468,4,'Seat Ledger'!$I$5:$I$468,"ON") -> 137.895 | G20: =SUMIFS('Seat Ledger'!$N$5:$N$468,'Seat Ledger'!$B$5:$B$468,5,'Seat Ledger'!$I$5:$I$468,"ON") -> 121.564
B21: Offshore — cost index | C21: =SUMIFS('Seat Ledger'!$N$5:$N$468,'Seat Ledger'!$B$5:$B$468,1,'Seat Ledger'!$I$5:$I$468,"OFF") -> 75.27 | D21: =SUMIFS('Seat Ledger'!$N$5:$N$468,'Seat Ledger'!$B$5:$B$468,2,'Seat Ledger'!$I$5:$I$468,"OFF") -> 93.05 | E21: =SUMIFS('Seat Ledger'!$N$5:$N$468,'Seat Ledger'!$B$5:$B$468,3,'Seat Ledger'!$I$5:$I$468,"OFF") -> 86.966 | F21: =SUMIFS('Seat Ledger'!$N$5:$N$468,'Seat Ledger'!$B$5:$B$468,4,'Seat Ledger'!$I$5:$I$468,"OFF") -> 82.616 | G21: =SUMIFS('Seat Ledger'!$N$5:$N$468,'Seat Ledger'!$B$5:$B$468,5,'Seat Ledger'!$I$5:$I$468,"OFF") -> 76.871
B22: Nearshore — cost index | C22: =SUMIFS('Seat Ledger'!$N$5:$N$468,'Seat Ledger'!$B$5:$B$468,1,'Seat Ledger'!$I$5:$I$468,"NEAR") -> 0 | D22: =SUMIFS('Seat Ledger'!$N$5:$N$468,'Seat Ledger'!$B$5:$B$468,2,'Seat Ledger'!$I$5:$I$468,"NEAR") -> 0 | E22: =SUMIFS('Seat Ledger'!$N$5:$N$468,'Seat Ledger'!$B$5:$B$468,3,'Seat Ledger'!$I$5:$I$468,"NEAR") -> 0 | F22: =SUMIFS('Seat Ledger'!$N$5:$N$468,'Seat Ledger'!$B$5:$B$468,4,'Seat Ledger'!$I$5:$I$468,"NEAR") -> 0 | G22: =SUMIFS('Seat Ledger'!$N$5:$N$468,'Seat Ledger'!$B$5:$B$468,5,'Seat Ledger'!$I$5:$I$468,"NEAR") -> 0
B23: Onshore share of cost | C23: =IF(SUM(C20:C22)=0,0,C20/SUM(C20:C22)) -> 0.8437393 | D23: =IF(SUM(D20:D22)=0,0,D20/SUM(D20:D22)) -> 0.72659292 | E23: =IF(SUM(E20:E22)=0,0,E20/SUM(E20:E22)) -> 0.65708901 | F23: =IF(SUM(F20:F22)=0,0,F20/SUM(F20:F22)) -> 0.62534295 | G23: =IF(SUM(G20:G22)=0,0,G20/SUM(G20:G22)) -> 0.6126137
B25: BSA — business and systems analysis — cost index | C25: =SUMIFS('Seat Ledger'!$N$5:$N$468,'Seat Ledger'!$B$5:$B$468,1,'Seat Ledger'!$G$5:$G$468,"BSA") -> 127.45 | D25: =SUMIFS('Seat Ledger'!$N$5:$N$468,'Seat Ledger'!$B$5:$B$468,2,'Seat Ledger'!$G$5:$G$468,"BSA") -> 83.9375 | E25: =SUMIFS('Seat Ledger'!$N$5:$N$468,'Seat Ledger'!$B$5:$B$468,3,'Seat Ledger'!$G$5:$G$468,"BSA") -> 69.22 | F25: =SUMIFS('Seat Ledger'!$N$5:$N$468,'Seat Ledger'!$B$5:$B$468,4,'Seat Ledger'!$G$5:$G$468,"BSA") -> 48.495 | G25: =SUMIFS('Seat Ledger'!$N$5:$N$468,'Seat Ledger'!$B$5:$B$468,5,'Seat Ledger'!$G$5:$G$468,"BSA") -> 43.939
B26: Developer — cost index | C26: =SUMIFS('Seat Ledger'!$N$5:$N$468,'Seat Ledger'!$B$5:$B$468,1,'Seat Ledger'!$G$5:$G$468,"DEV") -> 137.6 | D26: =SUMIFS('Seat Ledger'!$N$5:$N$468,'Seat Ledger'!$B$5:$B$468,2,'Seat Ledger'!$G$5:$G$468,"DEV") -> 97.3225 | E26: =SUMIFS('Seat Ledger'!$N$5:$N$468,'Seat Ledger'!$B$5:$B$468,3,'Seat Ledger'!$G$5:$G$468,"DEV") -> 55.591 | F26: =SUMIFS('Seat Ledger'!$N$5:$N$468,'Seat Ledger'!$B$5:$B$468,4,'Seat Ledger'!$G$5:$G$468,"DEV") -> 51.428 | G26: =SUMIFS('Seat Ledger'!$N$5:$N$468,'Seat Ledger'!$B$5:$B$468,5,'Seat Ledger'!$G$5:$G$468,"DEV") -> 49.084
B27: Tester — cost index | C27: =SUMIFS('Seat Ledger'!$N$5:$N$468,'Seat Ledger'!$B$5:$B$468,1,'Seat Ledger'!$G$5:$G$468,"TEST") -> 108.19 | D27: =SUMIFS('Seat Ledger'!$N$5:$N$468,'Seat Ledger'!$B$5:$B$468,2,'Seat Ledger'!$G$5:$G$468,"TEST") -> 49.975 | E27: =SUMIFS('Seat Ledger'!$N$5:$N$468,'Seat Ledger'!$B$5:$B$468,3,'Seat Ledger'!$G$5:$G$468,"TEST") -> 39.348 | F27: =SUMIFS('Seat Ledger'!$N$5:$N$468,'Seat Ledger'!$B$5:$B$468,4,'Seat Ledger'!$G$5:$G$468,"TEST") -> 33.615 | G27: =SUMIFS('Seat Ledger'!$N$5:$N$468,'Seat Ledger'!$B$5:$B$468,5,'Seat Ledger'!$G$5:$G$468,"TEST") -> 24.558
B28: Maintenance — cost index | C28: =SUMIFS('Seat Ledger'!$N$5:$N$468,'Seat Ledger'!$B$5:$B$468,1,'Seat Ledger'!$G$5:$G$468,"MNT") -> 35.285 | D28: =SUMIFS('Seat Ledger'!$N$5:$N$468,'Seat Ledger'!$B$5:$B$468,2,'Seat Ledger'!$G$5:$G$468,"MNT") -> 19.7 | E28: =SUMIFS('Seat Ledger'!$N$5:$N$468,'Seat Ledger'!$B$5:$B$468,3,'Seat Ledger'!$G$5:$G$468,"MNT") -> 13.417 | F28: =SUMIFS('Seat Ledger'!$N$5:$N$468,'Seat Ledger'!$B$5:$B$468,4,'Seat Ledger'!$G$5:$G$468,"MNT") -> 11.613 | G28: =SUMIFS('Seat Ledger'!$N$5:$N$468,'Seat Ledger'!$B$5:$B$468,5,'Seat Ledger'!$G$5:$G$468,"MNT") -> 10.794
B29: PM and product ownership — cost index | C29: =SUMIFS('Seat Ledger'!$N$5:$N$468,'Seat Ledger'!$B$5:$B$468,1,'Seat Ledger'!$G$5:$G$468,"PM") -> 66.375 | D29: =SUMIFS('Seat Ledger'!$N$5:$N$468,'Seat Ledger'!$B$5:$B$468,2,'Seat Ledger'!$G$5:$G$468,"PM") -> 77.475 | E29: =SUMIFS('Seat Ledger'!$N$5:$N$468,'Seat Ledger'!$B$5:$B$468,3,'Seat Ledger'!$G$5:$G$468,"PM") -> 67.875 | F29: =SUMIFS('Seat Ledger'!$N$5:$N$468,'Seat Ledger'!$B$5:$B$468,4,'Seat Ledger'!$G$5:$G$468,"PM") -> 59.55 | G29: =SUMIFS('Seat Ledger'!$N$5:$N$468,'Seat Ledger'!$B$5:$B$468,5,'Seat Ledger'!$G$5:$G$468,"PM") -> 52.15
B30: Other — architecture and enablement — cost index | C30: =SUMIFS('Seat Ledger'!$N$5:$N$468,'Seat Ledger'!$B$5:$B$468,1,'Seat Ledger'!$G$5:$G$468,"OTH") -> 6.795 | D30: =SUMIFS('Seat Ledger'!$N$5:$N$468,'Seat Ledger'!$B$5:$B$468,2,'Seat Ledger'!$G$5:$G$468,"OTH") -> 11.925 | E30: =SUMIFS('Seat Ledger'!$N$5:$N$468,'Seat Ledger'!$B$5:$B$468,3,'Seat Ledger'!$G$5:$G$468,"OTH") -> 8.16 | F30: =SUMIFS('Seat Ledger'!$N$5:$N$468,'Seat Ledger'!$B$5:$B$468,4,'Seat Ledger'!$G$5:$G$468,"OTH") -> 15.81 | G30: =SUMIFS('Seat Ledger'!$N$5:$N$468,'Seat Ledger'!$B$5:$B$468,5,'Seat Ledger'!$G$5:$G$468,"OTH") -> 17.91
B32: The role view is new in v5 and it is the one Pricing will want: it says what each of MetLife's own six role lines costs, which is the natural unit for a per-role rate card.

Sheet Seat Ledger
A1: Seat ledger — every pod-library line multiplied out, plus every horizontal seat
A2: Computed. Every roll-up in this workbook is a SUMIFS over this one table. Do not edit.
B4: Year | C4: Origin | D4: Unit | E4: Type | F4: Role detail | G4: Role | H4: Exp | I4: Loc | J4: Sourcing | K4: Seats/unit | L4: Units | M4: Heads | N4: Cost index
B5: 1 | C5: POD | D5: F2FILL | E5: POD | F5: ='Pod Library'!E5 -> MetLife Product Owner | G5: ='Pod Library'!F5 -> PM | H5: ='Pod Library'!G5 -> E4 | I5: ='Pod Library'!H5 -> ON | J5: ='Pod Library'!I5 -> FTE | K5: ='Pod Library'!J5 -> 1 | L5: ='Pod Plan'!E5 -> 5 | M5: =K5*L5 -> 5 | N5: =M5*INDEX('Logic Tree'!$J$75:$N$77,MATCH(I5,'Logic Tree'!$I$75:$I$77,0),MATCH(H5,'Logic Tree'!$J$74:$N$74,0)) -> 9.25
B6: 1 | C6: POD | D6: F2FILL | E6: POD | F6: ='Pod Library'!E6 -> MGCC Engineer | G6: ='Pod Library'!F6 -> DEV | H6: ='Pod Library'!G6 -> E3 | I6: ='Pod Library'!H6 -> OFF | J6: ='Pod Library'!I6 -> MGCC | K6: ='Pod Library'!J6 -> 1.6428571 | L6: ='Pod Plan'!E5 -> 5 | M6: =K6*L6 -> 8.2142857 | N6: =M6*INDEX('Logic Tree'!$J$75:$N$77,MATCH(I6,'Logic Tree'!$I$75:$I$77,0),MATCH(H6,'Logic Tree'!$J$74:$N$74,0)) -> 3.45
B7: 1 | C7: POD | D7: F2FILL | E7: POD | F7: ='Pod Library'!E7 -> Business Analyst (bilingual) | G7: ='Pod Library'!F7 -> BSA | H7: ='Pod Library'!G7 -> E3 | I7: ='Pod Library'!H7 -> ON | J7: ='Pod Library'!I7 -> FTC | K7: ='Pod Library'!J7 -> 1 | L7: ='Pod Plan'!E5 -> 5 | M7: =K7*L7 -> 5 | N7: =M7*INDEX('Logic Tree'!$J$75:$N$77,MATCH(I7,'Logic Tree'!$I$75:$I$77,0),MATCH(H7,'Logic Tree'!$J$74:$N$74,0)) -> 6.75
B8: 1 | C8: POD | D8: F2FILL | E8: POD | F8: ='Pod Library'!E8 -> Pod lead / senior engineer | G8: ='Pod Library'!F8 -> DEV | H8: ='Pod Library'!G8 -> E4 | I8: ='Pod Library'!H8 -> ON | J8: ='Pod Library'!I8 -> FTC | K8: ='Pod Library'!J8 -> 1.5 | L8: ='Pod Plan'!E5 -> 5 | M8: =K8*L8 -> 7.5 | N8: =M8*INDEX('Logic Tree'!$J$75:$N$77,MATCH(I8,'Logic Tree'!$I$75:$I$77,0),MATCH(H8,'Logic Tree'!$J$74:$N$74,0)) -> 13.875
B9: 1 | C9: POD | D9: F2FILL | E9: POD | F9: ='Pod Library'!E9 -> Engineer | G9: ='Pod Library'!F9 -> DEV | H9: ='Pod Library'!G9 -> E3 | I9: ='Pod Library'!H9 -> ON | J9: ='Pod Library'!I9 -> FTC | K9: ='Pod Library'!J9 -> 0.42857143 | L9: ='Pod Plan'!E5 -> 5 | M9: =K9*L9 -> 2.1428571 | N9: =M9*INDEX('Logic Tree'!$J$75:$N$77,MATCH(I9,'Logic Tree'!$I$75:$I$77,0),MATCH(H9,'Logic Tree'!$J$74:$N$74,0)) -> 2.8928571
B10: 1 | C10: POD | D10: F2FILL | E10: POD | F10: ='Pod Library'!E10 -> Engineer | G10: ='Pod Library'!F10 -> DEV | H10: ='Pod Library'!G10 -> E2 | I10: ='Pod Library'!H10 -> OFF | J10: ='Pod Library'!I10 -> FTC | K10: ='Pod Library'!J10 -> 0.78571429 | L10: ='Pod Plan'!E5 -> 5 | M10: =K10*L10 -> 3.9285714 | N10: =M10*INDEX('Logic Tree'!$J$75:$N$77,MATCH(I10,'Logic Tree'!$I$75:$I$77,0),MATCH(H10,'Logic Tree'!$J$74:$N$74,0)) -> 1.1785714
B11: 1 | C11: POD | D11: F2FILL | E11: POD | F11: ='Pod Library'!E11 -> Engineer | G11: ='Pod Library'!F11 -> DEV | H11: ='Pod Library'!G11 -> E3 | I11: ='Pod Library'!H11 -> OFF | J11: ='Pod Library'!I11 -> FTC | K11: ='Pod Library'!J11 -> 0.57142857 | L11: ='Pod Plan'!E5 -> 5 | M11: =K11*L11 -> 2.8571429 | N11: =M11*INDEX('Logic Tree'!$J$75:$N$77,MATCH(I11,'Logic Tree'!$I$75:$I$77,0),MATCH(H11,'Logic Tree'!$J$74:$N$74,0)) -> 1.2
B12: 1 | C12: POD | D12: F2FILL | E12: POD | F12: ='Pod Library'!E12 -> Engineer | G12: ='Pod Library'!F12 -> DEV | H12: ='Pod Library'!G12 -> E4 | I12: ='Pod Library'!H12 -> OFF | J12: ='Pod Library'!I12 -> FTC | K12: ='Pod Library'!J12 -> 0.21428571 | L12: ='Pod Plan'!E5 -> 5 | M12: =K12*L12 -> 1.0714286 | N12: =M12*INDEX('Logic Tree'!$J$75:$N$77,MATCH(I12,'Logic Tree'!$I$75:$I$77,0),MATCH(H12,'Logic Tree'!$J$74:$N$74,0)) -> 0.64285714
B13: 1 | C13: POD | D13: F2FILL | E13: POD | F13: ='Pod Library'!E13 -> Quality Engineer (SDET) | G13: ='Pod Library'!F13 -> TEST | H13: ='Pod Library'!G13 -> E2 | I13: ='Pod Library'!H13 -> OFF | J13: ='Pod Library'!I13 -> FTC | K13: ='Pod Library'!J13 -> 1.0714286 | L13: ='Pod Plan'!E5 -> 5 | M13: =K13*L13 -> 5.3571429 | N13: =M13*INDEX('Logic Tree'!$J$75:$N$77,MATCH(I13,'Logic Tree'!$I$75:$I$77,0),MATCH(H13,'Logic Tree'!$J$74:$N$74,0)) -> 1.6071429
B14: 1 | C14: POD | D14: F2FILL | E14: POD | F14: ='Pod Library'!E14 -> Quality Engineer (SDET) | G14: ='Pod Library'!F14 -> TEST | H14: ='Pod Library'!G14 -> E3 | I14: ='Pod Library'!H14 -> OFF | J14: ='Pod Library'!I14 -> FTC | K14: ='Pod Library'!J14 -> 1.0714286 | L14: ='Pod Plan'!E5 -> 5 | M14: =K14*L14 -> 5.3571429 | N14: =M14*INDEX('Logic Tree'!$J$75:$N$77,MATCH(I14,'Logic Tree'!$I$75:$I$77,0),MATCH(H14,'Logic Tree'!$J$74:$N$74,0)) -> 2.25
B15: 1 | C15: POD | D15: F2FILL | E15: POD | F15: ='Pod Library'!E15 -> Quality Engineer (SDET) | G15: ='Pod Library'!F15 -> TEST | H15: ='Pod Library'!G15 -> E4 | I15: ='Pod Library'!H15 -> OFF | J15: ='Pod Library'!I15 -> FTC | K15: ='Pod Library'!J15 -> 0.28571429 | L15: ='Pod Plan'!E5 -> 5 | M15: =K15*L15 -> 1.4285714 | N15: =M15*INDEX('Logic Tree'!$J$75:$N$77,MATCH(I15,'Logic Tree'!$I$75:$I$77,0),MATCH(H15,'Logic Tree'!$J$74:$N$74,0)) -> 0.85714286
B16: 1 | C16: POD | D16: F2FILL | E16: POD | F16: ='Pod Library'!E16 -> Application Support | G16: ='Pod Library'!F16 -> MNT | H16: ='Pod Library'!G16 -> E1 | I16: ='Pod Library'!H16 -> OFF | J16: ='Pod Library'!I16 -> FTC | K16: ='Pod Library'!J16 -> 0.14285714 | L16: ='Pod Plan'!E5 -> 5 | M16: =K16*L16 -> 0.71428571 | N16: =M16*INDEX('Logic Tree'!$J$75:$N$77,MATCH(I16,'Logic Tree'!$I$75:$I$77,0),MATCH(H16,'Logic Tree'!$J$74:$N$74,0)) -> 0.15714286
B17: 1 | C17: POD | D17: F2FILL | E17: POD | F17: ='Pod Library'!E17 -> Application Support | G17: ='Pod Library'!F17 -> MNT | H17: ='Pod Library'!G17 -> E2 | I17: ='Pod Library'!H17 -> OFF | J17: ='Pod Library'!I17 -> FTC | K17: ='Pod Library'!J17 -> 0.21428571 | L17: ='Pod Plan'!E5 -> 5 | M17: =K17*L17 -> 1.0714286 | N17: =M17*INDEX('Logic Tree'!$J$75:$N$77,MATCH(I17,'Logic Tree'!$I$75:$I$77,0),MATCH(H17,'Logic Tree'!$J$74:$N$74,0)) -> 0.32142857
B18: 1 | C18: TEAM | D18: F2FILL | E18: TEAM | F18: ='Pod Library'!E20 -> MetLife Product Owner | G18: ='Pod Library'!F20 -> PM | H18: ='Pod Library'!G20 -> E4 | I18: ='Pod Library'!H20 -> ON | J18: ='Pod Library'!I20 -> FTE | K18: ='Pod Library'!J20 -> 0.73214286 | L18: ='Pod Plan'!F5 -> 13 | M18: =K18*L18 -> 9.5178571 | N18: =M18*INDEX('Logic Tree'!$J$75:$N$77,MATCH(I18,'Logic Tree'!$I$75:$I$77,0),MATCH(H18,'Logic Tree'!$J$74:$N$74,0)) -> 17.608036
B19: 1 | C19: TEAM | D19: F2FILL | E19: TEAM | F19: ='Pod Library'!E21 -> MetLife Domain SME | G19: ='Pod Library'!F21 -> BSA | H19: ='Pod Library'!G21 -> E4 | I19: ='Pod Library'!H21 -> ON | J19: ='Pod Library'!I21 -> FTE | K19: ='Pod Library'!J21 -> 0.98214286 | L19: ='Pod Plan'!F5 -> 13 | M19: =K19*L19 -> 12.767857 | N19: =M19*INDEX('Logic Tree'!$J$75:$N$77,MATCH(I19,'Logic Tree'!$I$75:$I$77,0),MATCH(H19,'Logic Tree'!$J$74:$N$74,0)) -> 23.620536
B20: 1 | C20: TEAM | D20: F2FILL | E20: TEAM | F20: ='Pod Library'!E22 -> MetLife Operations Analyst | G20: ='Pod Library'!F22 -> MNT | H20: ='Pod Library'!G22 -> E3 | I20: ='Pod Library'!H22 -> ON | J20: ='Pod Library'!I22 -> FTE | K20: ='Pod Library'!J22 -> 0.46428571 | L20: ='Pod Plan'!F5 -> 13 | M20: =K20*L20 -> 6.0357143 | N20: =M20*INDEX('Logic Tree'!$J$75:$N$77,MATCH(I20,'Logic Tree'!$I$75:$I$77,0),MATCH(H20,'Logic Tree'!$J$74:$N$74,0)) -> 8.1482143
B21: 1 | C21: TEAM | D21: F2FILL | E21: TEAM | F21: ='Pod Library'!E23 -> MGCC Developer | G21: ='Pod Library'!F23 -> DEV | H21: ='Pod Library'!G23 -> E3 | I21: ='Pod Library'!H23 -> OFF | J21: ='Pod Library'!I23 -> MGCC | K21: ='Pod Library'!J23 -> 1.75 | L21: ='Pod Plan'!F5 -> 13 | M21: =K21*L21 -> 22.75 | N21: =M21*INDEX('Logic Tree'!$J$75:$N$77,MATCH(I21,'Logic Tree'!$I$75:$I$77,0),MATCH(H21,'Logic Tree'!$J$74:$N$74,0)) -> 9.555
B22: 1 | C22: TEAM | D22: F2FILL | E22: TEAM | F22: ='Pod Library'!E24 -> MGCC Test Engineer | G22: ='Pod Library'!F24 -> TEST | H22: ='Pod Library'!G24 -> E2 | I22: ='Pod Library'!H24 -> OFF | J22: ='Pod Library'!I24 -> MGCC | K22: ='Pod Library'!J24 -> 0.96428571 | L22: ='Pod Plan'!F5 -> 13 | M22: =K22*L22 -> 12.535714 | N22: =M22*INDEX('Logic Tree'!$J$75:$N$77,MATCH(I22,'Logic Tree'!$I$75:$I$77,0),MATCH(H22,'Logic Tree'!$J$74:$N$74,0)) -> 3.7607143
B23: 1 | C23: TEAM | D23: F2FILL | E23: TEAM | F23: ='Pod Library'!E25 -> Business Analyst (bilingual) | G23: ='Pod Library'!F25 -> BSA | H23: ='Pod Library'!G25 -> E3 | I23: ='Pod Library'!H25 -> ON | J23: ='Pod Library'!I25 -> FTC | K23: ='Pod Library'!J25 -> 1.4107143 | L23: ='Pod Plan'!F5 -> 13 | M23: =K23*L23 -> 18.339286 | N23: =M23*INDEX('Logic Tree'!$J$75:$N$77,MATCH(I23,'Logic Tree'!$I$75:$I$77,0),MATCH(H23,'Logic Tree'!$J$74:$N$74,0)) -> 24.758036
B24: 1 | C24: TEAM | D24: F2FILL | E24: TEAM | F24: ='Pod Library'!E26 -> Developer / technical lead | G24: ='Pod Library'!F26 -> DEV | H24: ='Pod Library'!G26 -> E3 | I24: ='Pod Library'!H26 -> ON | J24: ='Pod Library'!I26 -> FTC | K24: ='Pod Library'!J26 -> 1.7142857 | L24: ='Pod Plan'!F5 -> 13 | M24: =K24*L24 -> 22.285714 | N24: =M24*INDEX('Logic Tree'!$J$75:$N$77,MATCH(I24,'Logic Tree'!$I$75:$I$77,0),MATCH(H24,'Logic Tree'!$J$74:$N$74,0)) -> 30.085714
B25: 1 | C25: TEAM | D25: F2FILL | E25: TEAM | F25: ='Pod Library'!E27 -> Developer | G25: ='Pod Library'!F27 -> DEV | H25: ='Pod Library'!G27 -> E1 | I25: ='Pod Library'!H27 -> OFF | J25: ='Pod Library'!I27 -> FTC | K25: ='Pod Library'!J27 -> 0.19642857 | L25: ='Pod Plan'!F5 -> 13 | M25: =K25*L25 -> 2.5535714 | N25: =M25*INDEX('Logic Tree'!$J$75:$N$77,MATCH(I25,'Logic Tree'!$I$75:$I$77,0),MATCH(H25,'Logic Tree'!$J$74:$N$74,0)) -> 0.56178571
B26: 1 | C26: TEAM | D26: F2FILL | E26: TEAM | F26: ='Pod Library'!E28 -> Developer | G26: ='Pod Library'!F28 -> DEV | H26: ='Pod Library'!G28 -> E2 | I26: ='Pod Library'!H28 -> OFF | J26: ='Pod Library'!I28 -> FTC | K26: ='Pod Library'!J28 -> 0.53571429 | L26: ='Pod Plan'!F5 -> 13 | M26: =K26*L26 -> 6.9642857 | N26: =M26*INDEX('Logic Tree'!$J$75:$N$77,MATCH(I26,'Logic Tree'!$I$75:$I$77,0),MATCH(H26,'Logic Tree'!$J$74:$N$74,0)) -> 2.0892857
B27: 1 | C27: TEAM | D27: F2FILL | E27: TEAM | F27: ='Pod Library'!E29 -> Developer | G27: ='Pod Library'!F29 -> DEV | H27: ='Pod Library'!G29 -> E3 | I27: ='Pod Library'!H29 -> OFF | J27: ='Pod Library'!I29 -> FTC | K27: ='Pod Library'!J29 -> 0.51785714 | L27: ='Pod Plan'!F5 -> 13 | M27: =K27*L27 -> 6.7321429 | N27: =M27*INDEX('Logic Tree'!$J$75:$N$77,MATCH(I27,'Logic Tree'!$I$75:$I$77,0),MATCH(H27,'Logic Tree'!$J$74:$N$74,0)) -> 2.8275
B28: 1 | C28: TEAM | D28: F2FILL | E28: TEAM | F28: ='Pod Library'!E30 -> Test Lead / onshore tester | G28: ='Pod Library'!F30 -> TEST | H28: ='Pod Library'!G30 -> E3 | I28: ='Pod Library'!H30 -> ON | J28: ='Pod Library'!I30 -> FTC | K28: ='Pod Library'!J30 -> 1.8571429 | L28: ='Pod Plan'!F5 -> 13 | M28: =K28*L28 -> 24.142857 | N28: =M28*INDEX('Logic Tree'!$J$75:$N$77,MATCH(I28,'Logic Tree'!$I$75:$I$77,0),MATCH(H28,'Logic Tree'!$J$74:$N$74,0)) -> 32.592857
B29: 1 | C29: TEAM | D29: F2FILL | E29: TEAM | F29: ='Pod Library'!E31 -> Test Engineer | G29: ='Pod Library'!F31 -> TEST | H29: ='Pod Library'!G31 -> E2 | I29: ='Pod Library'!H31 -> OFF | J29: ='Pod Library'!I31 -> FTC | K29: ='Pod Library'!J31 -> 0.30357143 | L29: ='Pod Plan'!F5 -> 13 | M29: =K29*L29 -> 3.9464286 | N29: =M29*INDEX('Logic Tree'!$J$75:$N$77,MATCH(I29,'Logic Tree'!$I$75:$I$77,0),MATCH(H29,'Logic Tree'!$J$74:$N$74,0)) -> 1.1839286
B30: 1 | C30: TEAM | D30: F2FILL | E30: TEAM | F30: ='Pod Library'!E32 -> Test Engineer | G30: ='Pod Library'!F32 -> TEST | H30: ='Pod Library'!G32 -> E3 | I30: ='Pod Library'!H32 -> OFF | J30: ='Pod Library'!I32 -> FTC | K30: ='Pod Library'!J32 -> 0.32142857 | L30: ='Pod Plan'!F5 -> 13 | M30: =K30*L30 -> 4.1785714 | N30: =M30*INDEX('Logic Tree'!$J$75:$N$77,MATCH(I30,'Logic Tree'!$I$75:$I$77,0),MATCH(H30,'Logic Tree'!$J$74:$N$74,0)) -> 1.755
B31: 1 | C31: TEAM | D31: F2FILL | E31: TEAM | F31: ='Pod Library'!E33 -> Application Support | G31: ='Pod Library'!F33 -> MNT | H31: ='Pod Library'!G33 -> E2 | I31: ='Pod Library'!H33 -> OFF | J31: ='Pod Library'!I33 -> FTC | K31: ='Pod Library'!J33 -> 0.125 | L31: ='Pod Plan'!F5 -> 13 | M31: =K31*L31 -> 1.625 | N31: =M31*INDEX('Logic Tree'!$J$75:$N$77,MATCH(I31,'Logic Tree'!$I$75:$I$77,0),MATCH(H31,'Logic Tree'!$J$74:$N$74,0)) -> 0.4875
B32: 1 | C32: TEAM | D32: BANCA | E32: TEAM | F32: ='Pod Library'!E20 -> MetLife Product Owner | G32: ='Pod Library'!F20 -> PM | H32: ='Pod Library'!G20 -> E4 | I32: ='Pod Library'!H20 -> ON | J32: ='Pod Library'!I20 -> FTE | K32: ='Pod Library'!J20 -> 0.73214286 | L32: ='Pod Plan'!F6 -> 12 | M32: =K32*L32 -> 8.7857143 | N32: =M32*INDEX('Logic Tree'!$J$75:$N$77,MATCH(I32,'Logic Tree'!$I$75:$I$77,0),MATCH(H32,'Logic Tree'!$J$74:$N$74,0)) -> 16.253571
B33: 1 | C33: TEAM | D33: BANCA | E33: TEAM | F33: ='Pod Library'!E21 -> MetLife Domain SME | G33: ='Pod Library'!F21 -> BSA | H33: ='Pod Library'!G21 -> E4 | I33: ='Pod Library'!H21 -> ON | J33: ='Pod Library'!I21 -> FTE | K33: ='Pod Library'!J21 -> 0.98214286 | L33: ='Pod Plan'!F6 -> 12 | M33: =K33*L33 -> 11.785714 | N33: =M33*INDEX('Logic Tree'!$J$75:$N$77,MATCH(I33,'Logic Tree'!$I$75:$I$77,0),MATCH(H33,'Logic Tree'!$J$74:$N$74,0)) -> 21.803571
B34: 1 | C34: TEAM | D34: BANCA | E34: TEAM | F34: ='Pod Library'!E22 -> MetLife Operations Analyst | G34: ='Pod Library'!F22 -> MNT | H34: ='Pod Library'!G22 -> E3 | I34: ='Pod Library'!H22 -> ON | J34: ='Pod Library'!I22 -> FTE | K34: ='Pod Library'!J22 -> 0.46428571 | L34: ='Pod Plan'!F6 -> 12 | M34: =K34*L34 -> 5.5714286 | N34: =M34*INDEX('Logic Tree'!$J$75:$N$77,MATCH(I34,'Logic Tree'!$I$75:$I$77,0),MATCH(H34,'Logic Tree'!$J$74:$N$74,0)) -> 7.5214286
B35: 1 | C35: TEAM | D35: BANCA | E35: TEAM | F35: ='Pod Library'!E23 -> MGCC Developer | G35: ='Pod Library'!F23 -> DEV | H35: ='Pod Library'!G23 -> E3 | I35: ='Pod Library'!H23 -> OFF | J35: ='Pod Library'!I23 -> MGCC | K35: ='Pod Library'!J23 -> 1.75 | L35: ='Pod Plan'!F6 -> 12 | M35: =K35*L35 -> 21 | N35: =M35*INDEX('Logic Tree'!$J$75:$N$77,MATCH(I35,'Logic Tree'!$I$75:$I$77,0),MATCH(H35,'Logic Tree'!$J$74:$N$74,0)) -> 8.82
B36: 1 | C36: TEAM | D36: BANCA | E36: TEAM | F36: ='Pod Library'!E24 -> MGCC Test Engineer | G36: ='Pod Library'!F24 -> TEST | H36: ='Pod Library'!G24 -> E2 | I36: ='Pod Library'!H24 -> OFF | J36: ='Pod Library'!I24 -> MGCC | K36: ='Pod Library'!J24 -> 0.96428571 | L36: ='Pod Plan'!F6 -> 12 | M36: =K36*L36 -> 11.571429 | N36: =M36*INDEX('Logic Tree'!$J$75:$N$77,MATCH(I36,'Logic Tree'!$I$75:$I$77,0),MATCH(H36,'Logic Tree'!$J$74:$N$74,0)) -> 3.4714286
B37: 1 | C37: TEAM | D37: BANCA | E37: TEAM | F37: ='Pod Library'!E25 -> Business Analyst (bilingual) | G37: ='Pod Library'!F25 -> BSA | H37: ='Pod Library'!G25 -> E3 | I37: ='Pod Library'!H25 -> ON | J37: ='Pod Library'!I25 -> FTC | K37: ='Pod Library'!J25 -> 1.4107143 | L37: ='Pod Plan'!F6 -> 12 | M37: =K37*L37 -> 16.928571 | N37: =M37*INDEX('Logic Tree'!$J$75:$N$77,MATCH(I37,'Logic Tree'!$I$75:$I$77,0),MATCH(H37,'Logic Tree'!$J$74:$N$74,0)) -> 22.853571
B38: 1 | C38: TEAM | D38: BANCA | E38: TEAM | F38: ='Pod Library'!E26 -> Developer / technical lead | G38: ='Pod Library'!F26 -> DEV | H38: ='Pod Library'!G26 -> E3 | I38: ='Pod Library'!H26 -> ON | J38: ='Pod Library'!I26 -> FTC | K38: ='Pod Library'!J26 -> 1.7142857 | L38: ='Pod Plan'!F6 -> 12 | M38: =K38*L38 -> 20.571429 | N38: =M38*INDEX('Logic Tree'!$J$75:$N$77,MATCH(I38,'Logic Tree'!$I$75:$I$77,0),MATCH(H38,'Logic Tree'!$J$74:$N$74,0)) -> 27.771429
B39: 1 | C39: TEAM | D39: BANCA | E39: TEAM | F39: ='Pod Library'!E27 -> Developer | G39: ='Pod Library'!F27 -> DEV | H39: ='Pod Library'!G27 -> E1 | I39: ='Pod Library'!H27 -> OFF | J39: ='Pod Library'!I27 -> FTC | K39: ='Pod Library'!J27 -> 0.19642857 | L39: ='Pod Plan'!F6 -> 12 | M39: =K39*L39 -> 2.3571429 | N39: =M39*INDEX('Logic Tree'!$J$75:$N$77,MATCH(I39,'Logic Tree'!$I$75:$I$77,0),MATCH(H39,'Logic Tree'!$J$74:$N$74,0)) -> 0.51857143
B40: 1 | C40: TEAM | D40: BANCA | E40: TEAM | F40: ='Pod Library'!E28 -> Developer | G40: ='Pod Library'!F28 -> DEV | H40: ='Pod Library'!G28 -> E2 | I40: ='Pod Library'!H28 -> OFF | J40: ='Pod Library'!I28 -> FTC | K40: ='Pod Library'!J28 -> 0.53571429 | L40: ='Pod Plan'!F6 -> 12 | M40: =K40*L40 -> 6.4285714 | N40: =M40*INDEX('Logic Tree'!$J$75:$N$77,MATCH(I40,'Logic Tree'!$I$75:$I$77,0),MATCH(H40,'Logic Tree'!$J$74:$N$74,0)) -> 1.9285714
B41: 1 | C41: TEAM | D41: BANCA | E41: TEAM | F41: ='Pod Library'!E29 -> Developer | G41: ='Pod Library'!F29 -> DEV | H41: ='Pod Library'!G29 -> E3 | I41: ='Pod Library'!H29 -> OFF | J41: ='Pod Library'!I29 -> FTC | K41: ='Pod Library'!J29 -> 0.51785714 | L41: ='Pod Plan'!F6 -> 12 | M41: =K41*L41 -> 6.2142857 | N41: =M41*INDEX('Logic Tree'!$J$75:$N$77,MATCH(I41,'Logic Tree'!$I$75:$I$77,0),MATCH(H41,'Logic Tree'!$J$74:$N$74,0)) -> 2.61
B42: 1 | C42: TEAM | D42: BANCA | E42: TEAM | F42: ='Pod Library'!E30 -> Test Lead / onshore tester | G42: ='Pod Library'!F30 -> TEST | H42: ='Pod Library'!G30 -> E3 | I42: ='Pod Library'!H30 -> ON | J42: ='Pod Library'!I30 -> FTC | K42: ='Pod Library'!J30 -> 1.8571429 | L42: ='Pod Plan'!F6 -> 12 | M42: =K42*L42 -> 22.285714 | N42: =M42*INDEX('Logic Tree'!$J$75:$N$77,MATCH(I42,'Logic Tree'!$I$75:$I$77,0),MATCH(H42,'Logic Tree'!$J$74:$N$74,0)) -> 30.085714
B43: 1 | C43: TEAM | D43: BANCA | E43: TEAM | F43: ='Pod Library'!E31 -> Test Engineer | G43: ='Pod Library'!F31 -> TEST | H43: ='Pod Library'!G31 -> E2 | I43: ='Pod Library'!H31 -> OFF | J43: ='Pod Library'!I31 -> FTC | K43: ='Pod Library'!J31 -> 0.30357143 | L43: ='Pod Plan'!F6 -> 12 | M43: =K43*L43 -> 3.6428571 | N43: =M43*INDEX('Logic Tree'!$J$75:$N$77,MATCH(I43,'Logic Tree'!$I$75:$I$77,0),MATCH(H43,'Logic Tree'!$J$74:$N$74,0)) -> 1.0928571
B44: 1 | C44: TEAM | D44: BANCA | E44: TEAM | F44: ='Pod Library'!E32 -> Test Engineer | G44: ='Pod Library'!F32 -> TEST | H44: ='Pod Library'!G32 -> E3 | I44: ='Pod Library'!H32 -> OFF | J44: ='Pod Library'!I32 -> FTC | K44: ='Pod Library'!J32 -> 0.32142857 | L44: ='Pod Plan'!F6 -> 12 | M44: =K44*L44 -> 3.8571429 | N44: =M44*INDEX('Logic Tree'!$J$75:$N$77,MATCH(I44,'Logic Tree'!$I$75:$I$77,0),MATCH(H44,'Logic Tree'!$J$74:$N$74,0)) -> 1.62
B45: 1 | C45: TEAM | D45: BANCA | E45: TEAM | F45: ='Pod Library'!E33 -> Application Support | G45: ='Pod Library'!F33 -> MNT | H45: ='Pod Library'!G33 -> E2 | I45: ='Pod Library'!H33 -> OFF | J45: ='Pod Library'!I33 -> FTC | K45: ='Pod Library'!J33 -> 0.125 | L45: ='Pod Plan'!F6 -> 12 | M45: =K45*L45 -> 1.5 | N45: =M45*INDEX('Logic Tree'!$J$75:$N$77,MATCH(I45,'Logic Tree'!$I$75:$I$77,0),MATCH(H45,'Logic Tree'!$J$74:$N$74,0)) -> 0.45
B46: 1 | C46: POD | D46: AGENT | E46: POD | F46: ='Pod Library'!E5 -> MetLife Product Owner | G46: ='Pod Library'!F5 -> PM | H46: ='Pod Library'!G5 -> E4 | I46: ='Pod Library'!H5 -> ON | J46: ='Pod Library'!I5 -> FTE | K46: ='Pod Library'!J5 -> 1 | L46: ='Pod Plan'!E7 -> 1 | M46: =K46*L46 -> 1 | N46: =M46*INDEX('Logic Tree'!$J$75:$N$77,MATCH(I46,'Logic Tree'!$I$75:$I$77,0),MATCH(H46,'Logic Tree'!$J$74:$N$74,0)) -> 1.85
B47: 1 | C47: POD | D47: AGENT | E47: POD | F47: ='Pod Library'!E6 -> MGCC Engineer | G47: ='Pod Library'!F6 -> DEV | H47: ='Pod Library'!G6 -> E3 | I47: ='Pod Library'!H6 -> OFF | J47: ='Pod Library'!I6 -> MGCC | K47: ='Pod Library'!J6 -> 1.6428571 | L47: ='Pod Plan'!E7 -> 1 | M47: =K47*L47 -> 1.6428571 | N47: =M47*INDEX('Logic Tree'!$J$75:$N$77,MATCH(I47,'Logic Tree'!$I$75:$I$77,0),MATCH(H47,'Logic Tree'!$J$74:$N$74,0)) -> 0.69
B48: 1 | C48: POD | D48: AGENT | E48: POD | F48: ='Pod Library'!E7 -> Business Analyst (bilingual) | G48: ='Pod Library'!F7 -> BSA | H48: ='Pod Library'!G7 -> E3 | I48: ='Pod Library'!H7 -> ON | J48: ='Pod Library'!I7 -> FTC | K48: ='Pod Library'!J7 -> 1 | L48: ='Pod Plan'!E7 -> 1 | M48: =K48*L48 -> 1 | N48: =M48*INDEX('Logic Tree'!$J$75:$N$77,MATCH(I48,'Logic Tree'!$I$75:$I$77,0),MATCH(H48,'Logic Tree'!$J$74:$N$74,0)) -> 1.35
B49: 1 | C49: POD | D49: AGENT | E49: POD | F49: ='Pod Library'!E8 -> Pod lead / senior engineer | G49: ='Pod Library'!F8 -> DEV | H49: ='Pod Library'!G8 -> E4 | I49: ='Pod Library'!H8 -> ON | J49: ='Pod Library'!I8 -> FTC | K49: ='Pod Library'!J8 -> 1.5 | L49: ='Pod Plan'!E7 -> 1 | M49: =K49*L49 -> 1.5 | N49: =M49*INDEX('Logic Tree'!$J$75:$N$77,MATCH(I49,'Logic Tree'!$I$75:$I$77,0),MATCH(H49,'Logic Tree'!$J$74:$N$74,0)) -> 2.775
B50: 1 | C50: POD | D50: AGENT | E50: POD | F50: ='Pod Library'!E9 -> Engineer | G50: ='Pod Library'!F9 -> DEV | H50: ='Pod Library'!G9 -> E3 | I50: ='Pod Library'!H9 -> ON | J50: ='Pod Library'!I9 -> FTC | K50: ='Pod Library'!J9 -> 0.42857143 | L50: ='Pod Plan'!E7 -> 1 | M50: =K50*L50 -> 0.42857143 | N50: =M50*INDEX('Logic Tree'!$J$75:$N$77,MATCH(I50,'Logic Tree'!$I$75:$I$77,0),MATCH(H50,'Logic Tree'!$J$74:$N$74,0)) -> 0.57857143
B51: 1 | C51: POD | D51: AGENT | E51: POD | F51: ='Pod Library'!E10 -> Engineer | G51: ='Pod Library'!F10 -> DEV | H51: ='Pod Library'!G10 -> E2 | I51: ='Pod Library'!H10 -> OFF | J51: ='Pod Library'!I10 -> FTC | K51: ='Pod Library'!J10 -> 0.78571429 | L51: ='Pod Plan'!E7 -> 1 | M51: =K51*L51 -> 0.78571429 | N51: =M51*INDEX('Logic Tree'!$J$75:$N$77,MATCH(I51,'Logic Tree'!$I$75:$I$77,0),MATCH(H51,'Logic Tree'!$J$74:$N$74,0)) -> 0.23571429
B52: 1 | C52: POD | D52: AGENT | E52: POD | F52: ='Pod Library'!E11 -> Engineer | G52: ='Pod Library'!F11 -> DEV | H52: ='Pod Library'!G11 -> E3 | I52: ='Pod Library'!H11 -> OFF | J52: ='Pod Library'!I11 -> FTC | K52: ='Pod Library'!J11 -> 0.57142857 | L52: ='Pod Plan'!E7 -> 1 | M52: =K52*L52 -> 0.57142857 | N52: =M52*INDEX('Logic Tree'!$J$75:$N$77,MATCH(I52,'Logic Tree'!$I$75:$I$77,0),MATCH(H52,'Logic Tree'!$J$74:$N$74,0)) -> 0.24
B53: 1 | C53: POD | D53: AGENT | E53: POD | F53: ='Pod Library'!E12 -> Engineer | G53: ='Pod Library'!F12 -> DEV | H53: ='Pod Library'!G12 -> E4 | I53: ='Pod Library'!H12 -> OFF | J53: ='Pod Library'!I12 -> FTC | K53: ='Pod Library'!J12 -> 0.21428571 | L53: ='Pod Plan'!E7 -> 1 | M53: =K53*L53 -> 0.21428571 | N53: =M53*INDEX('Logic Tree'!$J$75:$N$77,MATCH(I53,'Logic Tree'!$I$75:$I$77,0),MATCH(H53,'Logic Tree'!$J$74:$N$74,0)) -> 0.12857143
B54: 1 | C54: POD | D54: AGENT | E54: POD | F54: ='Pod Library'!E13 -> Quality Engineer (SDET) | G54: ='Pod Library'!F13 -> TEST | H54: ='Pod Library'!G13 -> E2 | I54: ='Pod Library'!H13 -> OFF | J54: ='Pod Library'!I13 -> FTC | K54: ='Pod Library'!J13 -> 1.0714286 | L54: ='Pod Plan'!E7 -> 1 | M54: =K54*L54 -> 1.0714286 | N54: =M54*INDEX('Logic Tree'!$J$75:$N$77,MATCH(I54,'Logic Tree'!$I$75:$I$77,0),MATCH(H54,'Logic Tree'!$J$74:$N$74,0)) -> 0.32142857
B55: 1 | C55: POD | D55: AGENT | E55: POD | F55: ='Pod Library'!E14 -> Quality Engineer (SDET) | G55: ='Pod Library'!F14 -> TEST | H55: ='Pod Library'!G14 -> E3 | I55: ='Pod Library'!H14 -> OFF | J55: ='Pod Library'!I14 -> FTC | K55: ='Pod Library'!J14 -> 1.0714286 | L55: ='Pod Plan'!E7 -> 1 | M55: =K55*L55 -> 1.0714286 | N55: =M55*INDEX('Logic Tree'!$J$75:$N$77,MATCH(I55,'Logic Tree'!$I$75:$I$77,0),MATCH(H55,'Logic Tree'!$J$74:$N$74,0)) -> 0.45
B56: 1 | C56: POD | D56: AGENT | E56: POD | F56: ='Pod Library'!E15 -> Quality Engineer (SDET) | G56: ='Pod Library'!F15 -> TEST | H56: ='Pod Library'!G15 -> E4 | I56: ='Pod Library'!H15 -> OFF | J56: ='Pod Library'!I15 -> FTC | K56: ='Pod Library'!J15 -> 0.28571429 | L56: ='Pod Plan'!E7 -> 1 | M56: =K56*L56 -> 0.28571429 | N56: =M56*INDEX('Logic Tree'!$J$75:$N$77,MATCH(I56,'Logic Tree'!$I$75:$I$77,0),MATCH(H56,'Logic Tree'!$J$74:$N$74,0)) -> 0.17142857
B57: 1 | C57: POD | D57: AGENT | E57: POD | F57: ='Pod Library'!E16 -> Application Support | G57: ='Pod Library'!F16 -> MNT | H57: ='Pod Library'!G16 -> E1 | I57: ='Pod Library'!H16 -> OFF | J57: ='Pod Library'!I16 -> FTC | K57: ='Pod Library'!J16 -> 0.14285714 | L57: ='Pod Plan'!E7 -> 1 | M57: =K57*L57 -> 0.14285714 | N57: =M57*INDEX('Logic Tree'!$J$75:$N$77,MATCH(I57,'Logic Tree'!$I$75:$I$77,0),MATCH(H57,'Logic Tree'!$J$74:$N$74,0)) -> 0.031428571
B58: 1 | C58: POD | D58: AGENT | E58: POD | F58: ='Pod Library'!E17 -> Application Support | G58: ='Pod Library'!F17 -> MNT | H58: ='Pod Library'!G17 -> E2 | I58: ='Pod Library'!H17 -> OFF | J58: ='Pod Library'!I17 -> FTC | K58: ='Pod Library'!J17 -> 0.21428571 | L58: ='Pod Plan'!E7 -> 1 | M58: =K58*L58 -> 0.21428571 | N58: =M58*INDEX('Logic Tree'!$J$75:$N$77,MATCH(I58,'Logic Tree'!$I$75:$I$77,0),MATCH(H58,'Logic Tree'!$J$74:$N$74,0)) -> 0.064285714
B59: 1 | C59: TEAM | D59: AGENT | E59: TEAM | F59: ='Pod Library'!E20 -> MetLife Product Owner | G59: ='Pod Library'!F20 -> PM | H59: ='Pod Library'!G20 -> E4 | I59: ='Pod Library'!H20 -> ON | J59: ='Pod Library'!I20 -> FTE | K59: ='Pod Library'!J20 -> 0.73214286 | L59: ='Pod Plan'!F7 -> 2 | M59: =K59*L59 -> 1.4642857 | N59: =M59*INDEX('Logic Tree'!$J$75:$N$77,MATCH(I59,'Logic Tree'!$I$75:$I$77,0),MATCH(H59,'Logic Tree'!$J$74:$N$74,0)) -> 2.7089286
B60: 1 | C60: TEAM | D60: AGENT | E60: TEAM | F60: ='Pod Library'!E21 -> MetLife Domain SME | G60: ='Pod Library'!F21 -> BSA | H60: ='Pod Library'!G21 -> E4 | I60: ='Pod Library'!H21 -> ON | J60: ='Pod Library'!I21 -> FTE | K60: ='Pod Library'!J21 -> 0.98214286 | L60: ='Pod Plan'!F7 -> 2 | M60: =K60*L60 -> 1.9642857 | N60: =M60*INDEX('Logic Tree'!$J$75:$N$77,MATCH(I60,'Logic Tree'!$I$75:$I$77,0),MATCH(H60,'Logic Tree'!$J$74:$N$74,0)) -> 3.6339286
B61: 1 | C61: TEAM | D61: AGENT | E61: TEAM | F61: ='Pod Library'!E22 -> MetLife Operations Analyst | G61: ='Pod Library'!F22 -> MNT | H61: ='Pod Library'!G22 -> E3 | I61: ='Pod Library'!H22 -> ON | J61: ='Pod Library'!I22 -> FTE | K61: ='Pod Library'!J22 -> 0.46428571 | L61: ='Pod Plan'!F7 -> 2 | M61: =K61*L61 -> 0.92857143 | N61: =M61*INDEX('Logic Tree'!$J$75:$N$77,MATCH(I61,'Logic Tree'!$I$75:$I$77,0),MATCH(H61,'Logic Tree'!$J$74:$N$74,0)) -> 1.2535714
B62: 1 | C62: TEAM | D62: AGENT | E62: TEAM | F62: ='Pod Library'!E23 -> MGCC Developer | G62: ='Pod Library'!F23 -> DEV | H62: ='Pod Library'!G23 -> E3 | I62: ='Pod Library'!H23 -> OFF | J62: ='Pod Library'!I23 -> MGCC | K62: ='Pod Library'!J23 -> 1.75 | L62: ='Pod Plan'!F7 -> 2 | M62: =K62*L62 -> 3.5 | N62: =M62*INDEX('Logic Tree'!$J$75:$N$77,MATCH(I62,'Logic Tree'!$I$75:$I$77,0),MATCH(H62,'Logic Tree'!$J$74:$N$74,0)) -> 1.47
B63: 1 | C63: TEAM | D63: AGENT | E63: TEAM | F63: ='Pod Library'!E24 -> MGCC Test Engineer | G63: ='Pod Library'!F24 -> TEST | H63: ='Pod Library'!G24 -> E2 | I63: ='Pod Library'!H24 -> OFF | J63: ='Pod Library'!I24 -> MGCC | K63: ='Pod Library'!J24 -> 0.96428571 | L63: ='Pod Plan'!F7 -> 2 | M63: =K63*L63 -> 1.9285714 | N63: =M63*INDEX('Logic Tree'!$J$75:$N$77,MATCH(I63,'Logic Tree'!$I$75:$I$77,0),MATCH(H63,'Logic Tree'!$J$74:$N$74,0)) -> 0.57857143
B64: 1 | C64: TEAM | D64: AGENT | E64: TEAM | F64: ='Pod Library'!E25 -> Business Analyst (bilingual) | G64: ='Pod Library'!F25 -> BSA | H64: ='Pod Library'!G25 -> E3 | I64: ='Pod Library'!H25 -> ON | J64: ='Pod Library'!I25 -> FTC | K64: ='Pod Library'!J25 -> 1.4107143 | L64: ='Pod Plan'!F7 -> 2 | M64: =K64*L64 -> 2.8214286 | N64: =M64*INDEX('Logic Tree'!$J$75:$N$77,MATCH(I64,'Logic Tree'!$I$75:$I$77,0),MATCH(H64,'Logic Tree'!$J$74:$N$74,0)) -> 3.8089286
B65: 1 | C65: TEAM | D65: AGENT | E65: TEAM | F65: ='Pod Library'!E26 -> Developer / technical lead | G65: ='Pod Library'!F26 -> DEV | H65: ='Pod Library'!G26 -> E3 | I65: ='Pod Library'!H26 -> ON | J65: ='Pod Library'!I26 -> FTC | K65: ='Pod Library'!J26 -> 1.7142857 | L65: ='Pod Plan'!F7 -> 2 | M65: =K65*L65 -> 3.4285714 | N65: =M65*INDEX('Logic Tree'!$J$75:$N$77,MATCH(I65,'Logic Tree'!$I$75:$I$77,0),MATCH(H65,'Logic Tree'!$J$74:$N$74,0)) -> 4.6285714
B66: 1 | C66: TEAM | D66: AGENT | E66: TEAM | F66: ='Pod Library'!E27 -> Developer | G66: ='Pod Library'!F27 -> DEV | H66: ='Pod Library'!G27 -> E1 | I66: ='Pod Library'!H27 -> OFF | J66: ='Pod Library'!I27 -> FTC | K66: ='Pod Library'!J27 -> 0.19642857 | L66: ='Pod Plan'!F7 -> 2 | M66: =K66*L66 -> 0.39285714 | N66: =M66*INDEX('Logic Tree'!$J$75:$N$77,MATCH(I66,'Logic Tree'!$I$75:$I$77,0),MATCH(H66,'Logic Tree'!$J$74:$N$74,0)) -> 0.086428571
B67: 1 | C67: TEAM | D67: AGENT | E67: TEAM | F67: ='Pod Library'!E28 -> Developer | G67: ='Pod Library'!F28 -> DEV | H67: ='Pod Library'!G28 -> E2 | I67: ='Pod Library'!H28 -> OFF | J67: ='Pod Library'!I28 -> FTC | K67: ='Pod Library'!J28 -> 0.53571429 | L67: ='Pod Plan'!F7 -> 2 | M67: =K67*L67 -> 1.0714286 | N67: =M67*INDEX('Logic Tree'!$J$75:$N$77,MATCH(I67,'Logic Tree'!$I$75:$I$77,0),MATCH(H67,'Logic Tree'!$J$74:$N$74,0)) -> 0.32142857
B68: 1 | C68: TEAM | D68: AGENT | E68: TEAM | F68: ='Pod Library'!E29 -> Developer | G68: ='Pod Library'!F29 -> DEV | H68: ='Pod Library'!G29 -> E3 | I68: ='Pod Library'!H29 -> OFF | J68: ='Pod Library'!I29 -> FTC | K68: ='Pod Library'!J29 -> 0.51785714 | L68: ='Pod Plan'!F7 -> 2 | M68: =K68*L68 -> 1.0357143 | N68: =M68*INDEX('Logic Tree'!$J$75:$N$77,MATCH(I68,'Logic Tree'!$I$75:$I$77,0),MATCH(H68,'Logic Tree'!$J$74:$N$74,0)) -> 0.435
B69: 1 | C69: TEAM | D69: AGENT | E69: TEAM | F69: ='Pod Library'!E30 -> Test Lead / onshore tester | G69: ='Pod Library'!F30 -> TEST | H69: ='Pod Library'!G30 -> E3 | I69: ='Pod Library'!H30 -> ON | J69: ='Pod Library'!I30 -> FTC | K69: ='Pod Library'!J30 -> 1.8571429 | L69: ='Pod Plan'!F7 -> 2 | M69: =K69*L69 -> 3.7142857 | N69: =M69*INDEX('Logic Tree'!$J$75:$N$77,MATCH(I69,'Logic Tree'!$I$75:$I$77,0),MATCH(H69,'Logic Tree'!$J$74:$N$74,0)) -> 5.0142857
B70: 1 | C70: TEAM | D70: AGENT | E70: TEAM | F70: ='Pod Library'!E31 -> Test Engineer | G70: ='Pod Library'!F31 -> TEST | H70: ='Pod Library'!G31 -> E2 | I70: ='Pod Library'!H31 -> OFF | J70: ='Pod Library'!I31 -> FTC | K70: ='Pod Library'!J31 -> 0.30357143 | L70: ='Pod Plan'!F7 -> 2 | M70: =K70*L70 -> 0.60714286 | N70: =M70*INDEX('Logic Tree'!$J$75:$N$77,MATCH(I70,'Logic Tree'!$I$75:$I$77,0),MATCH(H70,'Logic Tree'!$J$74:$N$74,0)) -> 0.18214286
B71: 1 | C71: TEAM | D71: AGENT | E71: TEAM | F71: ='Pod Library'!E32 -> Test Engineer | G71: ='Pod Library'!F32 -> TEST | H71: ='Pod Library'!G32 -> E3 | I71: ='Pod Library'!H32 -> OFF | J71: ='Pod Library'!I32 -> FTC | K71: ='Pod Library'!J32 -> 0.32142857 | L71: ='Pod Plan'!F7 -> 2 | M71: =K71*L71 -> 0.64285714 | N71: =M71*INDEX('Logic Tree'!$J$75:$N$77,MATCH(I71,'Logic Tree'!$I$75:$I$77,0),MATCH(H71,'Logic Tree'!$J$74:$N$74,0)) -> 0.27
B72: 1 | C72: TEAM | D72: AGENT | E72: TEAM | F72: ='Pod Library'!E33 -> Application Support | G72: ='Pod Library'!F33 -> MNT | H72: ='Pod Library'!G33 -> E2 | I72: ='Pod Library'!H33 -> OFF | J72: ='Pod Library'!I33 -> FTC | K72: ='Pod Library'!J33 -> 0.125 | L72: ='Pod Plan'!F7 -> 2 | M72: =K72*L72 -> 0.25 | N72: =M72*INDEX('Logic Tree'!$J$75:$N$77,MATCH(I72,'Logic Tree'!$I$75:$I$77,0),MATCH(H72,'Logic Tree'!$J$74:$N$74,0)) -> 0.075
B73: 1 | C73: POD | D73: SUPP | E73: POD | F73: ='Pod Library'!E5 -> MetLife Product Owner | G73: ='Pod Library'!F5 -> PM | H73: ='Pod Library'!G5 -> E4 | I73: ='Pod Library'!H5 -> ON | J73: ='Pod Library'!I5 -> FTE | K73: ='Pod Library'!J5 -> 1 | L73: ='Pod Plan'!E8 -> 1 | M73: =K73*L73 -> 1 | N73: =M73*INDEX('Logic Tree'!$J$75:$N$77,MATCH(I73,'Logic Tree'!$I$75:$I$77,0),MATCH(H73,'Logic Tree'!$J$74:$N$74,0)) -> 1.85
B74: 1 | C74: POD | D74: SUPP | E74: POD | F74: ='Pod Library'!E6 -> MGCC Engineer | G74: ='Pod Library'!F6 -> DEV | H74: ='Pod Library'!G6 -> E3 | I74: ='Pod Library'!H6 -> OFF | J74: ='Pod Library'!I6 -> MGCC | K74: ='Pod Library'!J6 -> 1.6428571 | L74: ='Pod Plan'!E8 -> 1 | M74: =K74*L74 -> 1.6428571 | N74: =M74*INDEX('Logic Tree'!$J$75:$N$77,MATCH(I74,'Logic Tree'!$I$75:$I$77,0),MATCH(H74,'Logic Tree'!$J$74:$N$74,0)) -> 0.69
B75: 1 | C75: POD | D75: SUPP | E75: POD | F75: ='Pod Library'!E7 -> Business Analyst (bilingual) | G75: ='Pod Library'!F7 -> BSA | H75: ='Pod Library'!G7 -> E3 | I75: ='Pod Library'!H7 -> ON | J75: ='Pod Library'!I7 -> FTC | K75: ='Pod Library'!J7 -> 1 | L75: ='Pod Plan'!E8 -> 1 | M75: =K75*L75 -> 1 | N75: =M75*INDEX('Logic Tree'!$J$75:$N$77,MATCH(I75,'Logic Tree'!$I$75:$I$77,0),MATCH(H75,'Logic Tree'!$J$74:$N$74,0)) -> 1.35
B76: 1 | C76: POD | D76: SUPP | E76: POD | F76: ='Pod Library'!E8 -> Pod lead / senior engineer | G76: ='Pod Library'!F8 -> DEV | H76: ='Pod Library'!G8 -> E4 | I76: ='Pod Library'!H8 -> ON | J76: ='Pod Library'!I8 -> FTC | K76: ='Pod Library'!J8 -> 1.5 | L76: ='Pod Plan'!E8 -> 1 | M76: =K76*L76 -> 1.5 | N76: =M76*INDEX('Logic Tree'!$J$75:$N$77,MATCH(I76,'Logic Tree'!$I$75:$I$77,0),MATCH(H76,'Logic Tree'!$J$74:$N$74,0)) -> 2.775
B77: 1 | C77: POD | D77: SUPP | E77: POD | F77: ='Pod Library'!E9 -> Engineer | G77: ='Pod Library'!F9 -> DEV | H77: ='Pod Library'!G9 -> E3 | I77: ='Pod Library'!H9 -> ON | J77: ='Pod Library'!I9 -> FTC | K77: ='Pod Library'!J9 -> 0.42857143 | L77: ='Pod Plan'!E8 -> 1 | M77: =K77*L77 -> 0.42857143 | N77: =M77*INDEX('Logic Tree'!$J$75:$N$77,MATCH(I77,'Logic Tree'!$I$75:$I$77,0),MATCH(H77,'Logic Tree'!$J$74:$N$74,0)) -> 0.57857143
B78: 1 | C78: POD | D78: SUPP | E78: POD | F78: ='Pod Library'!E10 -> Engineer | G78: ='Pod Library'!F10 -> DEV | H78: ='Pod Library'!G10 -> E2 | I78: ='Pod Library'!H10 -> OFF | J78: ='Pod Library'!I10 -> FTC | K78: ='Pod Library'!J10 -> 0.78571429 | L78: ='Pod Plan'!E8 -> 1 | M78: =K78*L78 -> 0.78571429 | N78: =M78*INDEX('Logic Tree'!$J$75:$N$77,MATCH(I78,'Logic Tree'!$I$75:$I$77,0),MATCH(H78,'Logic Tree'!$J$74:$N$74,0)) -> 0.23571429
B79: 1 | C79: POD | D79: SUPP | E79: POD | F79: ='Pod Library'!E11 -> Engineer | G79: ='Pod Library'!F11 -> DEV | H79: ='Pod Library'!G11 -> E3 | I79: ='Pod Library'!H11 -> OFF | J79: ='Pod Library'!I11 -> FTC | K79: ='Pod Library'!J11 -> 0.57142857 | L79: ='Pod Plan'!E8 -> 1 | M79: =K79*L79 -> 0.57142857 | N79: =M79*INDEX('Logic Tree'!$J$75:$N$77,MATCH(I79,'Logic Tree'!$I$75:$I$77,0),MATCH(H79,'Logic Tree'!$J$74:$N$74,0)) -> 0.24
B80: 1 | C80: POD | D80: SUPP | E80: POD | F80: ='Pod Library'!E12 -> Engineer | G80: ='Pod Library'!F12 -> DEV | H80: ='Pod Library'!G12 -> E4 | I80: ='Pod Library'!H12 -> OFF | J80: ='Pod Library'!I12 -> FTC | K80: ='Pod Library'!J12 -> 0.21428571 | L80: ='Pod Plan'!E8 -> 1 | M80: =K80*L80 -> 0.21428571 | N80: =M80*INDEX('Logic Tree'!$J$75:$N$77,MATCH(I80,'Logic Tree'!$I$75:$I$77,0),MATCH(H80,'Logic Tree'!$J$74:$N$74,0)) -> 0.12857143
B81: 1 | C81: POD | D81: SUPP | E81: POD | F81: ='Pod Library'!E13 -> Quality Engineer (SDET) | G81: ='Pod Library'!F13 -> TEST | H81: ='Pod Library'!G13 -> E2 | I81: ='Pod Library'!H13 -> OFF | J81: ='Pod Library'!I13 -> FTC | K81: ='Pod Library'!J13 -> 1.0714286 | L81: ='Pod Plan'!E8 -> 1 | M81: =K81*L81 -> 1.0714286 | N81: =M81*INDEX('Logic Tree'!$J$75:$N$77,MATCH(I81,'Logic Tree'!$I$75:$I$77,0),MATCH(H81,'Logic Tree'!$J$74:$N$74,0)) -> 0.32142857
B82: 1 | C82: POD | D82: SUPP | E82: POD | F82: ='Pod Library'!E14 -> Quality Engineer (SDET) | G82: ='Pod Library'!F14 -> TEST | H82: ='Pod Library'!G14 -> E3 | I82: ='Pod Library'!H14 -> OFF | J82: ='Pod Library'!I14 -> FTC | K82: ='Pod Library'!J14 -> 1.0714286 | L82: ='Pod Plan'!E8 -> 1 | M82: =K82*L82 -> 1.0714286 | N82: =M82*INDEX('Logic Tree'!$J$75:$N$77,MATCH(I82,'Logic Tree'!$I$75:$I$77,0),MATCH(H82,'Logic Tree'!$J$74:$N$74,0)) -> 0.45
B83: 1 | C83: POD | D83: SUPP | E83: POD | F83: ='Pod Library'!E15 -> Quality Engineer (SDET) | G83: ='Pod Library'!F15 -> TEST | H83: ='Pod Library'!G15 -> E4 | I83: ='Pod Library'!H15 -> OFF | J83: ='Pod Library'!I15 -> FTC | K83: ='Pod Library'!J15 -> 0.28571429 | L83: ='Pod Plan'!E8 -> 1 | M83: =K83*L83 -> 0.28571429 | N83: =M83*INDEX('Logic Tree'!$J$75:$N$77,MATCH(I83,'Logic Tree'!$I$75:$I$77,0),MATCH(H83,'Logic Tree'!$J$74:$N$74,0)) -> 0.17142857
B84: 1 | C84: POD | D84: SUPP | E84: POD | F84: ='Pod Library'!E16 -> Application Support | G84: ='Pod Library'!F16 -> MNT | H84: ='Pod Library'!G16 -> E1 | I84: ='Pod Library'!H16 -> OFF | J84: ='Pod Library'!I16 -> FTC | K84: ='Pod Library'!J16 -> 0.14285714 | L84: ='Pod Plan'!E8 -> 1 | M84: =K84*L84 -> 0.14285714 | N84: =M84*INDEX('Logic Tree'!$J$75:$N$77,MATCH(I84,'Logic Tree'!$I$75:$I$77,0),MATCH(H84,'Logic Tree'!$J$74:$N$74,0)) -> 0.031428571
B85: 1 | C85: POD | D85: SUPP | E85: POD | F85: ='Pod Library'!E17 -> Application Support | G85: ='Pod Library'!F17 -> MNT | H85: ='Pod Library'!G17 -> E2 | I85: ='Pod Library'!H17 -> OFF | J85: ='Pod Library'!I17 -> FTC | K85: ='Pod Library'!J17 -> 0.21428571 | L85: ='Pod Plan'!E8 -> 1 | M85: =K85*L85 -> 0.21428571 | N85: =M85*INDEX('Logic Tree'!$J$75:$N$77,MATCH(I85,'Logic Tree'!$I$75:$I$77,0),MATCH(H85,'Logic Tree'!$J$74:$N$74,0)) -> 0.064285714
B86: 1 | C86: TEAM | D86: SUPP | E86: TEAM | F86: ='Pod Library'!E20 -> MetLife Product Owner | G86: ='Pod Library'!F20 -> PM | H86: ='Pod Library'!G20 -> E4 | I86: ='Pod Library'!H20 -> ON | J86: ='Pod Library'!I20 -> FTE | K86: ='Pod Library'!J20 -> 0.73214286 | L86: ='Pod Plan'!F8 -> 1 | M86: =K86*L86 -> 0.73214286 | N86: =M86*INDEX('Logic Tree'!$J$75:$N$77,MATCH(I86,'Logic Tree'!$I$75:$I$77,0),MATCH(H86,'Logic Tree'!$J$74:$N$74,0)) -> 1.3544643
B87: 1 | C87: TEAM | D87: SUPP | E87: TEAM | F87: ='Pod Library'!E21 -> MetLife Domain SME | G87: ='Pod Library'!F21 -> BSA | H87: ='Pod Library'!G21 -> E4 | I87: ='Pod Library'!H21 -> ON | J87: ='Pod Library'!I21 -> FTE | K87: ='Pod Library'!J21 -> 0.98214286 | L87: ='Pod Plan'!F8 -> 1 | M87: =K87*L87 -> 0.98214286 | N87: =M87*INDEX('Logic Tree'!$J$75:$N$77,MATCH(I87,'Logic Tree'!$I$75:$I$77,0),MATCH(H87,'Logic Tree'!$J$74:$N$74,0)) -> 1.8169643
B88: 1 | C88: TEAM | D88: SUPP | E88: TEAM | F88: ='Pod Library'!E22 -> MetLife Operations Analyst | G88: ='Pod Library'!F22 -> MNT | H88: ='Pod Library'!G22 -> E3 | I88: ='Pod Library'!H22 -> ON | J88: ='Pod Library'!I22 -> FTE | K88: ='Pod Library'!J22 -> 0.46428571 | L88: ='Pod Plan'!F8 -> 1 | M88: =K88*L88 -> 0.46428571 | N88: =M88*INDEX('Logic Tree'!$J$75:$N$77,MATCH(I88,'Logic Tree'!$I$75:$I$77,0),MATCH(H88,'Logic Tree'!$J$74:$N$74,0)) -> 0.62678571
B89: 1 | C89: TEAM | D89: SUPP | E89: TEAM | F89: ='Pod Library'!E23 -> MGCC Developer | G89: ='Pod Library'!F23 -> DEV | H89: ='Pod Library'!G23 -> E3 | I89: ='Pod Library'!H23 -> OFF | J89: ='Pod Library'!I23 -> MGCC | K89: ='Pod Library'!J23 -> 1.75 | L89: ='Pod Plan'!F8 -> 1 | M89: =K89*L89 -> 1.75 | N89: =M89*INDEX('Logic Tree'!$J$75:$N$77,MATCH(I89,'Logic Tree'!$I$75:$I$77,0),MATCH(H89,'Logic Tree'!$J$74:$N$74,0)) -> 0.735
B90: 1 | C90: TEAM | D90: SUPP | E90: TEAM | F90: ='Pod Library'!E24 -> MGCC Test Engineer | G90: ='Pod Library'!F24 -> TEST | H90: ='Pod Library'!G24 -> E2 | I90: ='Pod Library'!H24 -> OFF | J90: ='Pod Library'!I24 -> MGCC | K90: ='Pod Library'!J24 -> 0.96428571 | L90: ='Pod Plan'!F8 -> 1 | M90: =K90*L90 -> 0.96428571 | N90: =M90*INDEX('Logic Tree'!$J$75:$N$77,MATCH(I90,'Logic Tree'!$I$75:$I$77,0),MATCH(H90,'Logic Tree'!$J$74:$N$74,0)) -> 0.28928571
B91: 1 | C91: TEAM | D91: SUPP | E91: TEAM | F91: ='Pod Library'!E25 -> Business Analyst (bilingual) | G91: ='Pod Library'!F25 -> BSA | H91: ='Pod Library'!G25 -> E3 | I91: ='Pod Library'!H25 -> ON | J91: ='Pod Library'!I25 -> FTC | K91: ='Pod Library'!J25 -> 1.4107143 | L91: ='Pod Plan'!F8 -> 1 | M91: =K91*L91 -> 1.4107143 | N91: =M91*INDEX('Logic Tree'!$J$75:$N$77,MATCH(I91,'Logic Tree'!$I$75:$I$77,0),MATCH(H91,'Logic Tree'!$J$74:$N$74,0)) -> 1.9044643
B92: 1 | C92: TEAM | D92: SUPP | E92: TEAM | F92: ='Pod Library'!E26 -> Developer / technical lead | G92: ='Pod Library'!F26 -> DEV | H92: ='Pod Library'!G26 -> E3 | I92: ='Pod Library'!H26 -> ON | J92: ='Pod Library'!I26 -> FTC | K92: ='Pod Library'!J26 -> 1.7142857 | L92: ='Pod Plan'!F8 -> 1 | M92: =K92*L92 -> 1.7142857 | N92: =M92*INDEX('Logic Tree'!$J$75:$N$77,MATCH(I92,'Logic Tree'!$I$75:$I$77,0),MATCH(H92,'Logic Tree'!$J$74:$N$74,0)) -> 2.3142857
B93: 1 | C93: TEAM | D93: SUPP | E93: TEAM | F93: ='Pod Library'!E27 -> Developer | G93: ='Pod Library'!F27 -> DEV | H93: ='Pod Library'!G27 -> E1 | I93: ='Pod Library'!H27 -> OFF | J93: ='Pod Library'!I27 -> FTC | K93: ='Pod Library'!J27 -> 0.19642857 | L93: ='Pod Plan'!F8 -> 1 | M93: =K93*L93 -> 0.19642857 | N93: =M93*INDEX('Logic Tree'!$J$75:$N$77,MATCH(I93,'Logic Tree'!$I$75:$I$77,0),MATCH(H93,'Logic Tree'!$J$74:$N$74,0)) -> 0.043214286
B94: 1 | C94: TEAM | D94: SUPP | E94: TEAM | F94: ='Pod Library'!E28 -> Developer | G94: ='Pod Library'!F28 -> DEV | H94: ='Pod Library'!G28 -> E2 | I94: ='Pod Library'!H28 -> OFF | J94: ='Pod Library'!I28 -> FTC | K94: ='Pod Library'!J28 -> 0.53571429 | L94: ='Pod Plan'!F8 -> 1 | M94: =K94*L94 -> 0.53571429 | N94: =M94*INDEX('Logic Tree'!$J$75:$N$77,MATCH(I94,'Logic Tree'!$I$75:$I$77,0),MATCH(H94,'Logic Tree'!$J$74:$N$74,0)) -> 0.16071429
B95: 1 | C95: TEAM | D95: SUPP | E95: TEAM | F95: ='Pod Library'!E29 -> Developer | G95: ='Pod Library'!F29 -> DEV | H95: ='Pod Library'!G29 -> E3 | I95: ='Pod Library'!H29 -> OFF | J95: ='Pod Library'!I29 -> FTC | K95: ='Pod Library'!J29 -> 0.51785714 | L95: ='Pod Plan'!F8 -> 1 | M95: =K95*L95 -> 0.51785714 | N95: =M95*INDEX('Logic Tree'!$J$75:$N$77,MATCH(I95,'Logic Tree'!$I$75:$I$77,0),MATCH(H95,'Logic Tree'!$J$74:$N$74,0)) -> 0.2175
B96: 1 | C96: TEAM | D96: SUPP | E96: TEAM | F96: ='Pod Library'!E30 -> Test Lead / onshore tester | G96: ='Pod Library'!F30 -> TEST | H96: ='Pod Library'!G30 -> E3 | I96: ='Pod Library'!H30 -> ON | J96: ='Pod Library'!I30 -> FTC | K96: ='Pod Library'!J30 -> 1.8571429 | L96: ='Pod Plan'!F8 -> 1 | M96: =K96*L96 -> 1.8571429 | N96: =M96*INDEX('Logic Tree'!$J$75:$N$77,MATCH(I96,'Logic Tree'!$I$75:$I$77,0),MATCH(H96,'Logic Tree'!$J$74:$N$74,0)) -> 2.5071429
B97: 1 | C97: TEAM | D97: SUPP | E97: TEAM | F97: ='Pod Library'!E31 -> Test Engineer | G97: ='Pod Library'!F31 -> TEST | H97: ='Pod Library'!G31 -> E2 | I97: ='Pod Library'!H31 -> OFF | J97: ='Pod Library'!I31 -> FTC | K97: ='Pod Library'!J31 -> 0.30357143 | L97: ='Pod Plan'!F8 -> 1 | M97: =K97*L97 -> 0.30357143 | N97: =M97*INDEX('Logic Tree'!$J$75:$N$77,MATCH(I97,'Logic Tree'!$I$75:$I$77,0),MATCH(H97,'Logic Tree'!$J$74:$N$74,0)) -> 0.091071429
B98: 1 | C98: TEAM | D98: SUPP | E98: TEAM | F98: ='Pod Library'!E32 -> Test Engineer | G98: ='Pod Library'!F32 -> TEST | H98: ='Pod Library'!G32 -> E3 | I98: ='Pod Library'!H32 -> OFF | J98: ='Pod Library'!I32 -> FTC | K98: ='Pod Library'!J32 -> 0.32142857 | L98: ='Pod Plan'!F8 -> 1 | M98: =K98*L98 -> 0.32142857 | N98: =M98*INDEX('Logic Tree'!$J$75:$N$77,MATCH(I98,'Logic Tree'!$I$75:$I$77,0),MATCH(H98,'Logic Tree'!$J$74:$N$74,0)) -> 0.135
B99: 1 | C99: TEAM | D99: SUPP | E99: TEAM | F99: ='Pod Library'!E33 -> Application Support | G99: ='Pod Library'!F33 -> MNT | H99: ='Pod Library'!G33 -> E2 | I99: ='Pod Library'!H33 -> OFF | J99: ='Pod Library'!I33 -> FTC | K99: ='Pod Library'!J33 -> 0.125 | L99: ='Pod Plan'!F8 -> 1 | M99: =K99*L99 -> 0.125 | N99: =M99*INDEX('Logic Tree'!$J$75:$N$77,MATCH(I99,'Logic Tree'!$I$75:$I$77,0),MATCH(H99,'Logic Tree'!$J$74:$N$74,0)) -> 0.0375
B100: 1 | C100: HZ | D100: ='Horizontal Teams'!C5 -> H1 | E100: HZ | F100: ='Horizontal Teams'!E5 -> Service Delivery Manager | G100: ='Horizontal Teams'!D5 -> MNT | H100: ='Horizontal Teams'!F5 -> E5 | I100: ='Horizontal Teams'!G5 -> ON | J100: ='Horizontal Teams'!H5 -> FTC | K100: ='Horizontal Teams'!I5 -> 1 | L100: 1 | M100: =K100*L100 -> 1 | N100: =M100*INDEX('Logic Tree'!$J$75:$N$77,MATCH(I100,'Logic Tree'!$I$75:$I$77,0),MATCH(H100,'Logic Tree'!$J$74:$N$74,0)) -> 2.55
B101: 1 | C101: HZ | D101: ='Horizontal Teams'!C6 -> H1 | E101: HZ | F101: ='Horizontal Teams'!E6 -> Release & Environment Manager | G101: ='Horizontal Teams'!D6 -> MNT | H101: ='Horizontal Teams'!F6 -> E4 | I101: ='Horizontal Teams'!G6 -> ON | J101: ='Horizontal Teams'!H6 -> FTC | K101: ='Horizontal Teams'!I6 -> 2.5 | L101: 1 | M101: =K101*L101 -> 2.5 | N101: =M101*INDEX('Logic Tree'!$J$75:$N$77,MATCH(I101,'Logic Tree'!$I$75:$I$77,0),MATCH(H101,'Logic Tree'!$J$74:$N$74,0)) -> 4.625
...

Sheet SIT Loading
A1: SIT loading — turning fractional FTE into whole people and whole months
A2: The seat ledger is a demand model, not a roster. A line of 1.38 heads is 16.6 person-months of demand spread across several pods. This sheet converts that into something SIT can load without inventing or losing people.
A4: A. WHY YOU CANNOT ROUND THE SEAT LEDGER
B5: Approach | C5: Y1 | D5: Y2 | E5: Y3 | F5: Y4 | G5: Y5 | H5: Verdict
B6: Modelled FTE (the commercial number) | C6: 466.5 | D6: 359.5 | E6: 290 | F6: 250.5 | G6: 227
B7: Round every ledger row UP to whole heads | C7: 517 | D7: 393 | E7: 325 | F7: 285 | G7: 266 | H7: INFLATES Year 1 by 50 people — 11%. 242 ledger rows each round up by up to 0.99 of a person.
B8: Round every ledger row to nearest | C8: 468 | D8: 360 | E8: 280 | F8: 236 | G8: 215 | H8: Total is roughly right but every individual line is wrong, and the FTC / FTE / MGCC split drifts. It also implies each pod has its own dedicated architect, tester and support engineer.
B9: This sheet — aggregate first, then whole people and months | C9: 466.5 | D9: 359.5 | E9: 290 | F9: 250.5 | G9: 227 | H9: Exact on total, on each sourcing type and on person-months.
A11: B. THE RULE
B12: Aggregate the ledger to the level at which a person is actually hired — year x role x band x location x sourcing — and only then convert to bodies. A pod seat of 0.23 is not a person; the same role summed across six pods is.
B13: Treatment | C13: When it applies | D13: How SIT loads it | E13: Example
B14: RAMPED | C14: Delivery roles — engineers, testers, analysts inside pods and teams. The work is divisible over time and people join and leave pods. | G14: floor(FTE) people for 12 months, plus one person for the remaining months. | J14: 7.73 FTE = 7 people all year + 1 person for 8.7 months
B15: SHARED | C15: Roles that need continuous presence — leads, architects, service delivery managers, PMO — and any line below 0.5 FTE. | G15: One person at a partial allocation for the whole year, the balance of their time on another domain. | J15: 0.95 FTE = 1 Chief Architect at 95%, 5% elsewhere
B16: Both give identical person-months. Neither loads a partial person into a month and neither allocates anybody above 100%. Person-months is the invariant SIT must reproduce: FTE x 12.
A18: C. RECONCILIATION — what SIT must tie back to
B19: Measure | C19: Y1 | D19: Y2 | E19: Y3 | F19: Y4 | G19: Y5 | H19: Note
B20: Modelled FTE | C20: 466.5 | D20: 359.5 | E20: 290 | F20: 250.5 | G20: 227 | H20: From the seat ledger. This is the commercial number and it does not change.
B21: Person-months = FTE x 12 | C21: 5598 | D21: 4314 | E21: 3480 | F21: 3006 | G21: 2724 | H21: THE INVARIANT. SIT's monthly loading must sum to this.
B22: Bodies to requisition | C22: 477 | D22: 369 | E22: 302 | F22: 264 | G22: 244 | H22: Named people. Higher than FTE because some are part-year or part-allocated.
B23: — of which full-time, all year | C23: 456 | D23: 350 | E23: 278 | F23: 237 | G23: 210 | H23: The core roster. Everything else is a partial assignment.
B24: Average allocation across all bodies | C24: 0.97798742 | D24: 0.97425474 | E24: 0.9602649 | F24: 0.94886364 | G24: 0.93032787 | H24: If this drops below about 70% the pod design is too fragmented — check it.
A26: D. THE REQUISITION PLAN — load these lines into SIT
B27: Year | C27: Sourcing | D27: Role | E27: Band | F27: Location | G27: Unit type | H27: Modelled FTE | I27: Person-months | J27: Treatment | K27: Full-time heads | L27: +1 head for (months) | M27: Allocation of the part head
B28: 1 | C28: FTC | D28: BSA | E28: E3 | F28: ON | G28: Delivery | H28: 46.5 | I28: 558 | J28: RAMPED | K28: 46 | L28: 6
B29: 1 | C29: FTC | D29: DEV | E29: E1 | F29: OFF | G29: Delivery | H29: 5.5 | I29: 66 | J29: RAMPED | K29: 5 | L29: 6
B30: 1 | C30: FTC | D30: DEV | E30: E2 | F30: OFF | G30: Delivery | H30: 20.5 | I30: 246 | J30: RAMPED | K30: 20 | L30: 6
B31: 1 | C31: FTC | D31: DEV | E31: E3 | F31: OFF | G31: Delivery | H31: 18.5 | I31: 222 | J31: RAMPED | K31: 18 | L31: 6
B32: 1 | C32: FTC | D32: DEV | E32: E3 | F32: ON | G32: Delivery | H32: 51 | I32: 612 | J32: RAMPED | K32: 51
B33: 1 | C33: FTC | D33: DEV | E33: E4 | F33: OFF | G33: Delivery | H33: 1.5 | I33: 18 | J33: RAMPED | K33: 1 | L33: 6
B34: 1 | C34: FTC | D34: DEV | E34: E4 | F34: ON | G34: Delivery | H34: 10.5 | I34: 126 | J34: RAMPED | K34: 10 | L34: 6
B35: 1 | C35: FTC | D35: MNT | E35: E1 | F35: OFF | G35: Delivery | H35: 1 | I35: 12 | J35: RAMPED | K35: 1
B36: 1 | C36: FTC | D36: MNT | E36: E2 | F36: OFF | G36: Delivery | H36: 5 | I36: 60 | J36: RAMPED | K36: 5
B37: 1 | C37: FTC | D37: TEST | E37: E2 | F37: OFF | G37: Delivery | H37: 16 | I37: 192 | J37: RAMPED | K37: 16
B38: 1 | C38: FTC | D38: TEST | E38: E3 | F38: OFF | G38: Delivery | H38: 16.5 | I38: 198 | J38: RAMPED | K38: 16 | L38: 6
B39: 1 | C39: FTC | D39: TEST | E39: E3 | F39: ON | G39: Delivery | H39: 52 | I39: 624 | J39: RAMPED | K39: 52
B40: 1 | C40: FTC | D40: TEST | E40: E4 | F40: OFF | G40: Delivery | H40: 2 | I40: 24 | J40: RAMPED | K40: 2
B41: 1 | C41: FTC | D41: DEV | E41: E3 | F41: OFF | G41: Horizontal | H41: 3 | I41: 36 | J41: SHARED | K41: 3
B42: 1 | C42: FTC | D42: DEV | E42: E3 | F42: ON | G42: Horizontal | H42: 3.5 | I42: 42 | J42: SHARED | K42: 3 | L42: 6 | M42: 0.5
B43: 1 | C43: FTC | D43: DEV | E43: E5 | F43: OFF | G43: Horizontal | H43: 1 | I43: 12 | J43: SHARED | K43: 1
B44: 1 | C44: FTC | D44: MNT | E44: E1 | F44: OFF | G44: Horizontal | H44: 2 | I44: 24 | J44: SHARED | K44: 2
B45: 1 | C45: FTC | D45: MNT | E45: E2 | F45: OFF | G45: Horizontal | H45: 1 | I45: 12 | J45: SHARED | K45: 1
B46: 1 | C46: FTC | D46: MNT | E46: E3 | F46: ON | G46: Horizontal | H46: 1 | I46: 12 | J46: SHARED | K46: 1
B47: 1 | C47: FTC | D47: MNT | E47: E4 | F47: ON | G47: Horizontal | H47: 2.5 | I47: 30 | J47: SHARED | K47: 2 | L47: 6 | M47: 0.5
B48: 1 | C48: FTC | D48: MNT | E48: E5 | F48: ON | G48: Horizontal | H48: 1 | I48: 12 | J48: SHARED | K48: 1
B49: 1 | C49: FTC | D49: OTH | E49: E3 | F49: OFF | G49: Horizontal | H49: 1 | I49: 12 | J49: SHARED | K49: 1
B50: 1 | C50: FTC | D50: OTH | E50: E5 | F50: ON | G50: Horizontal | H50: 1 | I50: 12 | J50: SHARED | K50: 1
B51: 1 | C51: FTC | D51: PM | E51: E4 | F51: ON | G51: Horizontal | H51: 3.5 | I51: 42 | J51: SHARED | K51: 3 | L51: 6 | M51: 0.5
B52: 1 | C52: FTC | D52: PM | E52: E5 | F52: ON | G52: Horizontal | H52: 1 | I52: 12 | J52: SHARED | K52: 1
B53: 1 | C53: FTC | D53: TEST | E53: E1 | F53: OFF | G53: Horizontal | H53: 3 | I53: 36 | J53: SHARED | K53: 3
B54: 1 | C54: FTC | D54: TEST | E54: E2 | F54: OFF | G54: Horizontal | H54: 3 | I54: 36 | J54: SHARED | K54: 3
B55: 1 | C55: FTC | D55: TEST | E55: E3 | F55: OFF | G55: Horizontal | H55: 4 | I55: 48 | J55: SHARED | K55: 4
B56: 1 | C56: FTC | D56: TEST | E56: E3 | F56: ON | G56: Horizontal | H56: 2.5 | I56: 30 | J56: SHARED | K56: 2 | L56: 6 | M56: 0.5
B57: 1 | C57: FTC | D57: TEST | E57: E4 | F57: OFF | G57: Horizontal | H57: 2 | I57: 24 | J57: SHARED | K57: 2
B58: 1 | C58: FTC | D58: TEST | E58: E4 | F58: ON | G58: Horizontal | H58: 0.5 | I58: 6 | J58: SHARED | K58: 0 | L58: 6 | M58: 0.5
B59: 1 | C59: FTC | D59: TEST | E59: E5 | F59: OFF | G59: Horizontal | H59: 1 | I59: 12 | J59: SHARED | K59: 1
B60: 1 | C60: FTC | D60: TEST | E60: E5 | F60: ON | G60: Horizontal | H60: 0.5 | I60: 6 | J60: SHARED | K60: 0 | L60: 6 | M60: 0.5
B61: 1 | C61: FTE | D61: BSA | E61: E4 | F61: ON | G61: Delivery | H61: 27.5 | I61: 330 | J61: RAMPED | K61: 27 | L61: 6
B62: 1 | C62: FTE | D62: MNT | E62: E3 | F62: ON | G62: Delivery | H62: 13 | I62: 156 | J62: RAMPED | K62: 13
B63: 1 | C63: FTE | D63: PM | E63: E4 | F63: ON | G63: Delivery | H63: 27.5 | I63: 330 | J63: SHARED | K63: 27 | L63: 6 | M63: 0.5
B64: 1 | C64: FTE | D64: BSA | E64: E3 | F64: ON | G64: Horizontal | H64: 2 | I64: 24 | J64: SHARED | K64: 2
B65: 1 | C65: FTE | D65: BSA | E65: E4 | F65: ON | G65: Horizontal | H65: 6 | I65: 72 | J65: SHARED | K65: 6
B66: 1 | C66: FTE | D66: MNT | E66: E3 | F66: ON | G66: Horizontal | H66: 5 | I66: 60 | J66: SHARED | K66: 5
B67: 1 | C67: FTE | D67: OTH | E67: E5 | F67: ON | G67: Horizontal | H67: 1.5 | I67: 18 | J67: SHARED | K67: 1 | L67: 6 | M67: 0.5
B68: 1 | C68: FTE | D68: PM | E68: E4 | F68: ON | G68: Horizontal | H68: 3.5 | I68: 42 | J68: SHARED | K68: 3 | L68: 6 | M68: 0.5
B69: 1 | C69: FTE | D69: TEST | E69: E4 | F69: ON | G69: Horizontal | H69: 2.5 | I69: 30 | J69: SHARED | K69: 2 | L69: 6 | M69: 0.5
B70: 1 | C70: MGCC | D70: DEV | E70: E3 | F70: OFF | G70: Delivery | H70: 60.5 | I70: 726 | J70: RAMPED | K70: 60 | L70: 6
B71: 1 | C71: MGCC | D71: TEST | E71: E2 | F71: OFF | G71: Delivery | H71: 27 | I71: 324 | J71: RAMPED | K71: 27
B72: 1 | C72: MGCC | D72: DEV | E72: E3 | F72: OFF | G72: Horizontal | H72: 2.5 | I72: 30 | J72: SHARED | K72: 2 | L72: 6 | M72: 0.5
B73: 1 | C73: MGCC | D73: TEST | E73: E3 | F73: OFF | G73: Horizontal | H73: 3.5 | I73: 42 | J73: SHARED | K73: 3 | L73: 6 | M73: 0.5
B74: 2 | C74: FTC | D74: BSA | E74: E3 | F74: ON | G74: Delivery | H74: 32.5 | I74: 390 | J74: RAMPED | K74: 32 | L74: 6
B75: 2 | C75: FTC | D75: DEV | E75: E2 | F75: OFF | G75: Delivery | H75: 13 | I75: 156 | J75: RAMPED | K75: 13
B76: 2 | C76: FTC | D76: DEV | E76: E3 | F76: OFF | G76: Delivery | H76: 33.5 | I76: 402 | J76: RAMPED | K76: 33 | L76: 6
B77: 2 | C77: FTC | D77: DEV | E77: E3 | F77: ON | G77: Delivery | H77: 3 | I77: 36 | J77: RAMPED | K77: 3
B78: 2 | C78: FTC | D78: DEV | E78: E4 | F78: ON | G78: Delivery | H78: 29.5 | I78: 354 | J78: RAMPED | K78: 29 | L78: 6
B79: 2 | C79: FTC | D79: MNT | E79: E1 | F79: OFF | G79: Delivery | H79: 6.5 | I79: 78 | J79: RAMPED | K79: 6 | L79: 6
B80: 2 | C80: FTC | D80: MNT | E80: E2 | F80: OFF | G80: Delivery | H80: 4 | I80: 48 | J80: RAMPED | K80: 4
B81: 2 | C81: FTC | D81: OTH | E81: E4 | F81: OFF | G81: Delivery | H81: 7.5 | I81: 90 | J81: SHARED | K81: 7 | L81: 6 | M81: 0.5
B82: 2 | C82: FTC | D82: TEST | E82: E3 | F82: OFF | G82: Delivery | H82: 48 | I82: 576 | J82: RAMPED | K82: 48
B83: 2 | C83: FTC | D83: TEST | E83: E5 | F83: OFF | G83: Delivery | H83: 1 | I83: 12 | J83: RAMPED | K83: 1
B84: 2 | C84: FTC | D84: DEV | E84: E3 | F84: OFF | G84: Horizontal | H84: 0.5 | I84: 6 | J84: SHARED | K84: 0 | L84: 6 | M84: 0.5
B85: 2 | C85: FTC | D85: DEV | E85: E3 | F85: ON | G85: Horizontal | H85: 2.5 | I85: 30 | J85: SHARED | K85: 2 | L85: 6 | M85: 0.5
B86: 2 | C86: FTC | D86: DEV | E86: E5 | F86: OFF | G86: Horizontal | H86: 0.5 | I86: 6 | J86: SHARED | K86: 0 | L86: 6 | M86: 0.5
B87: 2 | C87: FTC | D87: MNT | E87: E1 | F87: OFF | G87: Horizontal | H87: 1 | I87: 12 | J87: SHARED | K87: 1
B88: 2 | C88: FTC | D88: MNT | E88: E2 | F88: OFF | G88: Horizontal | H88: 1 | I88: 12 | J88: SHARED | K88: 1
B89: 2 | C89: FTC | D89: MNT | E89: E3 | F89: ON | G89: Horizontal | H89: 1 | I89: 12 | J89: SHARED | K89: 1
B90: 2 | C90: FTC | D90: MNT | E90: E4 | F90: ON | G90: Horizontal | H90: 2.5 | I90: 30 | J90: SHARED | K90: 2 | L90: 6 | M90: 0.5
B91: 2 | C91: FTC | D91: MNT | E91: E5 | F91: ON | G91: Horizontal | H91: 1.5 | I91: 18 | J91: SHARED | K91: 1 | L91: 6 | M91: 0.5
B92: 2 | C92: FTC | D92: OTH | E92: E3 | F92: OFF | G92: Horizontal | H92: 2.5 | I92: 30 | J92: SHARED | K92: 2 | L92: 6 | M92: 0.5
B93: 2 | C93: FTC | D93: OTH | E93: E5 | F93: ON | G93: Horizontal | H93: 1.5 | I93: 18 | J93: SHARED | K93: 1 | L93: 6 | M93: 0.5
B94: 2 | C94: FTC | D94: PM | E94: E4 | F94: ON | G94: Horizontal | H94: 2.5 | I94: 30 | J94: SHARED | K94: 2 | L94: 6 | M94: 0.5
B95: 2 | C95: FTC | D95: PM | E95: E5 | F95: ON | G95: Horizontal | H95: 1 | I95: 12 | J95: SHARED | K95: 1
B96: 2 | C96: FTC | D96: TEST | E96: E1 | F96: OFF | G96: Horizontal | H96: 1 | I96: 12 | J96: SHARED | K96: 1
B97: 2 | C97: FTC | D97: TEST | E97: E2 | F97: OFF | G97: Horizontal | H97: 2.5 | I97: 30 | J97: SHARED | K97: 2 | L97: 6 | M97: 0.5
B98: 2 | C98: FTC | D98: TEST | E98: E3 | F98: OFF | G98: Horizontal | H98: 4 | I98: 48 | J98: SHARED | K98: 4
B99: 2 | C99: FTC | D99: TEST | E99: E3 | F99: ON | G99: Horizontal | H99: 1.5 | I99: 18 | J99: SHARED | K99: 1 | L99: 6 | M99: 0.5
B100: 2 | C100: FTC | D100: TEST | E100: E4 | F100: OFF | G100: Horizontal | H100: 1 | I100: 12 | J100: SHARED | K100: 1
B101: 2 | C101: FTC | D101: TEST | E101: E4 | F101: ON | G101: Horizontal | H101: 1 | I101: 12 | J101: SHARED | K101: 1
B102: 2 | C102: FTC | D102: TEST | E102: E5 | F102: OFF | G102: Horizontal | H102: 0.5 | I102: 6 | J102: SHARED | K102: 0 | L102: 6 | M102: 0.5
B103: 2 | C103: FTC | D103: TEST | E103: E5 | F103: ON | G103: Horizontal | H103: 1.5 | I103: 18 | J103: SHARED | K103: 1 | L103: 6 | M103: 0.5
B104: 2 | C104: FTE | D104: BSA | E104: E4 | F104: ON | G104: Delivery | H104: 25.5 | I104: 306 | J104: RAMPED | K104: 25 | L104: 6
...

Sheet Unit Cost Sensitivity
A1: Unit cost sensitivity — four levers now, not three
A2: Productivity, offshore share and seniority as before, plus the agile conversion, which is new in v5 and which the other three all depend on.
A4: A. THE MODEL — unit cost = k x (1 - productivity) x average cost per head
B5: average cost per head = offshore x [senior x OFF_SR + (1-senior) x OFF_JM] + onshore x [senior x ON_SR + (1-senior) x ON_JM]
A7: B. TIER COST PARAMETERS — from the Year-5 roster
B8: Tier | C8: Onshore Tokyo | D8: Offshore
B9: Junior / mid (E1-E3) | C9: =IFERROR((SUMIFS('Seat Ledger'!$N$5:$N$468,'Seat Ledger'!$B$5:$B$468,5,'Seat Ledger'!$I$5:$I$468,"ON",'Seat Ledger'!$H$5:$H$468,"E1") + SUMIFS('Seat Ledger'!$N$5:$N$468,'Seat Ledger'!$B$5:$B$468,5,'Seat Ledger'!$I$5:$I$468,"ON",'Seat Ledger'!$H$5:$H$468,"E2") + SUMIFS('Seat Ledger'!$N$5:$N$468,'Seat Ledger'!$B$5:$B$468,5,'Seat Ledger'!$I$5:$I$468,"ON",'Seat Ledger'!$H$5:$H$468,"E3"))/(SUMIFS('Seat Ledger'!$M$5:$M$468,'Seat Ledger'!$B$5:$B$468,5,'Seat Ledger'!$I$5:$I$468,"ON",'Seat Ledger'!$H$5:$H$468,"E1") + SUMIFS('Seat Ledger'!$M$5:$M$468,'Seat Ledger'!$B$5:$B$468,5,'Seat Ledger'!$I$5:$I$468,"ON",'Seat Ledger'!$H$5:$H$468,"E2") + SUMIFS('Seat Ledger'!$M$5:$M$468,'Seat Ledger'!$B$5:$B$468,5,'Seat Ledger'!$I$5:$I$468,"ON",'Seat Ledger'!$H$5:$H$468,"E3")),0) -> 1.35 | D9: =IFERROR((SUMIFS('Seat Ledger'!$N$5:$N$468,'Seat Ledger'!$B$5:$B$468,5,'Seat Ledger'!$I$5:$I$468,"OFF",'Seat Ledger'!$H$5:$H$468,"E1") + SUMIFS('Seat Ledger'!$N$5:$N$468,'Seat Ledger'!$B$5:$B$468,5,'Seat Ledger'!$I$5:$I$468,"OFF",'Seat Ledger'!$H$5:$H$468,"E2") + SUMIFS('Seat Ledger'!$N$5:$N$468,'Seat Ledger'!$B$5:$B$468,5,'Seat Ledger'!$I$5:$I$468,"OFF",'Seat Ledger'!$H$5:$H$468,"E3"))/(SUMIFS('Seat Ledger'!$M$5:$M$468,'Seat Ledger'!$B$5:$B$468,5,'Seat Ledger'!$I$5:$I$468,"OFF",'Seat Ledger'!$H$5:$H$468,"E1") + SUMIFS('Seat Ledger'!$M$5:$M$468,'Seat Ledger'!$B$5:$B$468,5,'Seat Ledger'!$I$5:$I$468,"OFF",'Seat Ledger'!$H$5:$H$468,"E2") + SUMIFS('Seat Ledger'!$M$5:$M$468,'Seat Ledger'!$B$5:$B$468,5,'Seat Ledger'!$I$5:$I$468,"OFF",'Seat Ledger'!$H$5:$H$468,"E3")),0) -> 0.38644608
B10: Senior (E4-E5) | C10: =IFERROR((SUMIFS('Seat Ledger'!$N$5:$N$468,'Seat Ledger'!$B$5:$B$468,5,'Seat Ledger'!$I$5:$I$468,"ON",'Seat Ledger'!$H$5:$H$468,"E4") + SUMIFS('Seat Ledger'!$N$5:$N$468,'Seat Ledger'!$B$5:$B$468,5,'Seat Ledger'!$I$5:$I$468,"ON",'Seat Ledger'!$H$5:$H$468,"E5"))/(SUMIFS('Seat Ledger'!$M$5:$M$468,'Seat Ledger'!$B$5:$B$468,5,'Seat Ledger'!$I$5:$I$468,"ON",'Seat Ledger'!$H$5:$H$468,"E4") + SUMIFS('Seat Ledger'!$M$5:$M$468,'Seat Ledger'!$B$5:$B$468,5,'Seat Ledger'!$I$5:$I$468,"ON",'Seat Ledger'!$H$5:$H$468,"E5")),0) -> 1.9193694 | D10: =IFERROR((SUMIFS('Seat Ledger'!$N$5:$N$468,'Seat Ledger'!$B$5:$B$468,5,'Seat Ledger'!$I$5:$I$468,"OFF",'Seat Ledger'!$H$5:$H$468,"E4") + SUMIFS('Seat Ledger'!$N$5:$N$468,'Seat Ledger'!$B$5:$B$468,5,'Seat Ledger'!$I$5:$I$468,"OFF",'Seat Ledger'!$H$5:$H$468,"E5"))/(SUMIFS('Seat Ledger'!$M$5:$M$468,'Seat Ledger'!$B$5:$B$468,5,'Seat Ledger'!$I$5:$I$468,"OFF",'Seat Ledger'!$H$5:$H$468,"E4") + SUMIFS('Seat Ledger'!$M$5:$M$468,'Seat Ledger'!$B$5:$B$468,5,'Seat Ledger'!$I$5:$I$468,"OFF",'Seat Ledger'!$H$5:$H$468,"E5")),0) -> 0.60361742
A12: C. BASE CASE
B13: Measure | C13: Year 1 | D13: Year 2 | E13: Year 3 | F13: Year 4 | G13: Year 5
B14: Delivered productivity | C14: ='Glidepath & 50-50'!C25 -> -5.9381875e-05 | D14: ='Glidepath & 50-50'!D25 -> 0.22910749 | E14: ='Glidepath & 50-50'!E25 -> 0.378141 | F14: ='Glidepath & 50-50'!F25 -> 0.46324787 | G14: ='Glidepath & 50-50'!G25 -> 0.513969
B15: Whole-team offshore share | C15: ='Team Build-Up'!C39 -> 0.43086817 | D15: ='Team Build-Up'!D39 -> 0.60901001 | E15: ='Team Build-Up'!E39 -> 0.67009101 | F15: ='Team Build-Up'!F39 -> 0.69366563 | G15: ='Team Build-Up'!G39 -> 0.70606916
B16: Senior share (E4+E5) | C16: ='Team Build-Up'!C60 -> 0.20685959 | D16: ='Team Build-Up'!D60 -> 0.36943826 | E16: ='Team Build-Up'!E60 -> 0.41884997 | F16: ='Team Build-Up'!F60 -> 0.52711878 | G16: ='Team Build-Up'!G60 -> 0.54962068
B17: Agile share | C17: ='Delivery Mode'!C22 -> 0.18425542 | D17: ='Delivery Mode'!D22 -> 0.90947121 | E17: ='Delivery Mode'!E22 -> 1 | F17: ='Delivery Mode'!F22 -> 1 | G17: ='Delivery Mode'!G22 -> 1
B18: Unit cost index — actual | C18: ='Cost & Commercial'!C9 -> 1.0326337 | D18: ='Cost & Commercial'!D9 -> 0.72959316 | E18: ='Cost & Commercial'!E9 -> 0.54367858 | F18: ='Cost & Commercial'!F9 -> 0.47272046 | G18: ='Cost & Commercial'!G9 -> 0.42539503
B19: Unit cost index — two-tier formula | C19: =(1-C14)*(C15*(C16*$D$10+(1-C16)*$D$9)+(1-C15)*(C16*$C$10+(1-C16)*$C$9)) -> 1.0212843 | D19: =(1-D14)*(D15*(D16*$D$10+(1-D16)*$D$9)+(1-D15)*(D16*$C$10+(1-D16)*$C$9)) -> 0.68940242 | E19: =(1-E14)*(E15*(E16*$D$10+(1-E16)*$D$9)+(1-E15)*(E16*$C$10+(1-E16)*$C$9)) -> 0.52482472 | F19: =(1-F14)*(F15*(F16*$D$10+(1-F16)*$D$9)+(1-F15)*(F16*$C$10+(1-F16)*$C$9)) -> 0.45782911 | G19: =(1-G14)*(G15*(G16*$D$10+(1-G16)*$D$9)+(1-G15)*(G16*$C$10+(1-G16)*$C$9)) -> 0.41114525
B20: CALIBRATION k = actual / formula, at Year 5 | G20: =IF(G19=0,1,G18/G19) -> 1.0346588
A22: D. GRID — offshore share x productivity, at the Year-5 senior share
B23: Offshore v Productivity > | C23: 0.35 | D23: 0.4 | E23: 0.45 | F23: 0.5 | G23: 0.55 | H23: 0.6
B24: 0.45 | C24: =$G$20*(1-C$23)*($B24*($G$16*$D$10+(1-$G$16)*$D$9)+(1-$B24)*($G$16*$C$10+(1-$G$16)*$C$9)) -> 0.76818123 | D24: =$G$20*(1-D$23)*($B24*($G$16*$D$10+(1-$G$16)*$D$9)+(1-$B24)*($G$16*$C$10+(1-$G$16)*$C$9)) -> 0.70909036 | E24: =$G$20*(1-E$23)*($B24*($G$16*$D$10+(1-$G$16)*$D$9)+(1-$B24)*($G$16*$C$10+(1-$G$16)*$C$9)) -> 0.6499995 | F24: =$G$20*(1-F$23)*($B24*($G$16*$D$10+(1-$G$16)*$D$9)+(1-$B24)*($G$16*$C$10+(1-$G$16)*$C$9)) -> 0.59090864 | G24: =$G$20*(1-G$23)*($B24*($G$16*$D$10+(1-$G$16)*$D$9)+(1-$B24)*($G$16*$C$10+(1-$G$16)*$C$9)) -> 0.53181777 | H24: =$G$20*(1-H$23)*($B24*($G$16*$D$10+(1-$G$16)*$D$9)+(1-$B24)*($G$16*$C$10+(1-$G$16)*$C$9)) -> 0.47272691
B25: 0.55 | C25: =$G$20*(1-C$23)*($B25*($G$16*$D$10+(1-$G$16)*$D$9)+(1-$B25)*($G$16*$C$10+(1-$G$16)*$C$9)) -> 0.69036102 | D25: =$G$20*(1-D$23)*($B25*($G$16*$D$10+(1-$G$16)*$D$9)+(1-$B25)*($G$16*$C$10+(1-$G$16)*$C$9)) -> 0.63725633 | E25: =$G$20*(1-E$23)*($B25*($G$16*$D$10+(1-$G$16)*$D$9)+(1-$B25)*($G$16*$C$10+(1-$G$16)*$C$9)) -> 0.58415163 | F25: =$G$20*(1-F$23)*($B25*($G$16*$D$10+(1-$G$16)*$D$9)+(1-$B25)*($G$16*$C$10+(1-$G$16)*$C$9)) -> 0.53104694 | G25: =$G$20*(1-G$23)*($B25*($G$16*$D$10+(1-$G$16)*$D$9)+(1-$B25)*($G$16*$C$10+(1-$G$16)*$C$9)) -> 0.47794225 | H25: =$G$20*(1-H$23)*($B25*($G$16*$D$10+(1-$G$16)*$D$9)+(1-$B25)*($G$16*$C$10+(1-$G$16)*$C$9)) -> 0.42483755
B26: 0.65 | C26: =$G$20*(1-C$23)*($B26*($G$16*$D$10+(1-$G$16)*$D$9)+(1-$B26)*($G$16*$C$10+(1-$G$16)*$C$9)) -> 0.61254082 | D26: =$G$20*(1-D$23)*($B26*($G$16*$D$10+(1-$G$16)*$D$9)+(1-$B26)*($G$16*$C$10+(1-$G$16)*$C$9)) -> 0.56542229 | E26: =$G$20*(1-E$23)*($B26*($G$16*$D$10+(1-$G$16)*$D$9)+(1-$B26)*($G$16*$C$10+(1-$G$16)*$C$9)) -> 0.51830377 | F26: =$G$20*(1-F$23)*($B26*($G$16*$D$10+(1-$G$16)*$D$9)+(1-$B26)*($G$16*$C$10+(1-$G$16)*$C$9)) -> 0.47118525 | G26: =$G$20*(1-G$23)*($B26*($G$16*$D$10+(1-$G$16)*$D$9)+(1-$B26)*($G$16*$C$10+(1-$G$16)*$C$9)) -> 0.42406672 | H26: =$G$20*(1-H$23)*($B26*($G$16*$D$10+(1-$G$16)*$D$9)+(1-$B26)*($G$16*$C$10+(1-$G$16)*$C$9)) -> 0.3769482
B27: 0.75 | C27: =$G$20*(1-C$23)*($B27*($G$16*$D$10+(1-$G$16)*$D$9)+(1-$B27)*($G$16*$C$10+(1-$G$16)*$C$9)) -> 0.53472061 | D27: =$G$20*(1-D$23)*($B27*($G$16*$D$10+(1-$G$16)*$D$9)+(1-$B27)*($G$16*$C$10+(1-$G$16)*$C$9)) -> 0.49358826 | E27: =$G$20*(1-E$23)*($B27*($G$16*$D$10+(1-$G$16)*$D$9)+(1-$B27)*($G$16*$C$10+(1-$G$16)*$C$9)) -> 0.4524559 | F27: =$G$20*(1-F$23)*($B27*($G$16*$D$10+(1-$G$16)*$D$9)+(1-$B27)*($G$16*$C$10+(1-$G$16)*$C$9)) -> 0.41132355 | G27: =$G$20*(1-G$23)*($B27*($G$16*$D$10+(1-$G$16)*$D$9)+(1-$B27)*($G$16*$C$10+(1-$G$16)*$C$9)) -> 0.37019119 | H27: =$G$20*(1-H$23)*($B27*($G$16*$D$10+(1-$G$16)*$D$9)+(1-$B27)*($G$16*$C$10+(1-$G$16)*$C$9)) -> 0.32905884
B28: 0.85 | C28: =$G$20*(1-C$23)*($B28*($G$16*$D$10+(1-$G$16)*$D$9)+(1-$B28)*($G$16*$C$10+(1-$G$16)*$C$9)) -> 0.45690041 | D28: =$G$20*(1-D$23)*($B28*($G$16*$D$10+(1-$G$16)*$D$9)+(1-$B28)*($G$16*$C$10+(1-$G$16)*$C$9)) -> 0.42175422 | E28: =$G$20*(1-E$23)*($B28*($G$16*$D$10+(1-$G$16)*$D$9)+(1-$B28)*($G$16*$C$10+(1-$G$16)*$C$9)) -> 0.38660804 | F28: =$G$20*(1-F$23)*($B28*($G$16*$D$10+(1-$G$16)*$D$9)+(1-$B28)*($G$16*$C$10+(1-$G$16)*$C$9)) -> 0.35146185 | G28: =$G$20*(1-G$23)*($B28*($G$16*$D$10+(1-$G$16)*$D$9)+(1-$B28)*($G$16*$C$10+(1-$G$16)*$C$9)) -> 0.31631567 | H28: =$G$20*(1-H$23)*($B28*($G$16*$D$10+(1-$G$16)*$D$9)+(1-$B28)*($G$16*$C$10+(1-$G$16)*$C$9)) -> 0.28116948
A30: E. TORNADO — one lever at a time, +/- 10 points from the Year-5 base
B31: Lever | C31: -10 points | D31: Base | E31: +10 points | F31: Swing | G31: Reading
B32: Productivity | C32: =$G$20*(1-($G$14-0.1))*(($G$15)*(($G$16)*$D$10+(1-($G$16))*$D$9)+(1-($G$15))*(($G$16)*$C$10+(1-($G$16))*$C$9)) -> 0.51291929 | D32: =$G$20*(1-($G$14))*(($G$15)*(($G$16)*$D$10+(1-($G$16))*$D$9)+(1-($G$15))*(($G$16)*$C$10+(1-($G$16))*$C$9)) -> 0.42539503 | E32: =$G$20*(1-($G$14+0.1))*(($G$15)*(($G$16)*$D$10+(1-($G$16))*$D$9)+(1-($G$15))*(($G$16)*$C$10+(1-($G$16))*$C$9)) -> 0.33787078 | F32: =ABS(E32-C32) -> 0.17504852 | G32: Scales unit cost one for one. The only linear lever.
B33: Offshore share | C33: =$G$20*(1-($G$14))*(($G$15-0.1)*(($G$16)*$D$10+(1-($G$16))*$D$9)+(1-($G$15-0.1))*(($G$16)*$C$10+(1-($G$16))*$C$9)) -> 0.48358431 | D33: =$G$20*(1-($G$14))*(($G$15)*(($G$16)*$D$10+(1-($G$16))*$D$9)+(1-($G$15))*(($G$16)*$C$10+(1-($G$16))*$C$9)) -> 0.42539503 | E33: =$G$20*(1-($G$14))*(($G$15+0.1)*(($G$16)*$D$10+(1-($G$16))*$D$9)+(1-($G$15+0.1))*(($G$16)*$C$10+(1-($G$16))*$C$9)) -> 0.36720575 | F33: =ABS(E33-C33) -> 0.11637856 | G33: Second largest — and now bounded by a measured start rather than an assumed one.
B34: Senior share | C34: =$G$20*(1-($G$14))*(($G$15)*(($G$16-0.1)*$D$10+(1-($G$16-0.1))*$D$9)+(1-($G$15))*(($G$16-0.1)*$C$10+(1-($G$16-0.1))*$C$9)) -> 0.40926813 | D34: =$G$20*(1-($G$14))*(($G$15)*(($G$16)*$D$10+(1-($G$16))*$D$9)+(1-($G$15))*(($G$16)*$C$10+(1-($G$16))*$C$9)) -> 0.42539503 | E34: =$G$20*(1-($G$14))*(($G$15)*(($G$16+0.1)*$D$10+(1-($G$16+0.1))*$D$9)+(1-($G$15))*(($G$16+0.1)*$C$10+(1-($G$16+0.1))*$C$9)) -> 0.44152193 | F34: =ABS(E34-C34) -> 0.032253798 | G34: Works against the other two. A richer shape gives back part of what offshore wins.
B35: Agile conversion — the fourth lever | G35: Not a direct term in the unit-cost formula. It works through productivity: the operating-model component is scaled by the agile share, so a one-year slip in the conversion costs about 5 points of Year-2 capability and roughly 0.05 of the unit cost index. It is the lever with the longest lead time and the least evidence behind it.
B37: Swings are full 20-point ranges. Halve them for a per-ten-point read.
