Workbook

Sheet START HERE
A1: Domain framework template — set one cell, everything else re-derives
A2: MetLife Japan Application Development Services. Appendix 3 v5 · Golden Application Inventory v4 · the per-sourcing productivity engine used on Sales / Insurance, Contract Management, Data Infrastructure, Common Service Platform and Storage & Preservation.
B4: STEP 1 — choose your 領域
B5: Domain | C5: Corporate Related | E5: Pick from the drop-down. Every sheet that says (auto) re-derives the moment this changes: the baseline, the archetype mix, the AI and offshore ceilings, the capability chain, the five-year target headcount, the per-sourcing plan, the transfer solve, the value streams and the ticket load. Nothing else on this sheet needs to be touched to get a first cut.
B7: STEP 2 — read what the data says
B8: Measure | C8: Value | E8: What it tells you
B9: Applications in this 領域 | C9: =SUMPRODUCT(--('Inventory v5'!$D$5:$D$146='START HERE'!$C$5)) | E9: How many application lines the SUMIFS are reading. If this is 0 the domain name is misspelt.
B10: Total effort — units of person-capacity | C10: =SUMIFS('Inventory v5'!$J$5:$J$146,'Inventory v5'!$D$5:$D$146,'START HERE'!$C$5) | E10: The frozen scope. Every target in the model is a percentage reduction against this number, and it never changes across the five years.
B11: Vendor today (Appendix 3 'Current FTC') | C11: =SUMIFS('Inventory v5'!$K$5:$K$146,'Inventory v5'!$D$5:$D$146,'START HERE'!$C$5) | E11: Capgemini plus any named sub-contractor. Appendix 3 reports the two as one number, which is why the model carries PT separately.
B12: MetLife Japan today (FTE) | C12: =SUMIFS('Inventory v5'!$L$5:$L$146,'Inventory v5'!$D$5:$D$146,'START HERE'!$C$5) | E12: MetLife's own people. Mostly BSA and PM work — see the Role × Sourcing sheet.
B13: MetLife MGCC today | C13: =SUMIFS('Inventory v5'!$M$5:$M$146,'Inventory v5'!$D$5:$D$146,'START HERE'!$C$5) | E13: MetLife's global capability centre. Mostly build and test.
B14: Capgemini heads on these applications today | C14: ='Logic Tree'!C14 | E14: From the Golden Inventory's application-level Capgemini headcount. The gap to the vendor number is FSI, NCD or unnamed — see the Vendor column on the inventory.
B15: MetLife share of the whole 領域 on day one | C15: =IF(C10=0,0,(C12+C13)/C10) | E15: THE NUMBER THAT SETS YOUR POSTURE. Above 50% and the 50:50 is already met — argue against further convergence. Below 40% and you have a real transfer to size.
B16: Blended AI ceiling | C16: ='Logic Tree'!C38 | E16: Effort-weighted across the archetypes present. This is the ceiling, not the commitment.
B17: Blended offshore ceiling | C17: ='Logic Tree'!C39 | E17: Same weighting, on the offshore ceilings. J applications cap at 12% and drag this down hard.
B18: Delivered offshore or by MGCC today | C18: ='Logic Tree'!C130 | E18: Offshore plus MGCC as a share of total effort. The gap between this and the ceiling is the offshore case.
B20: STEP 3 — make the judgements that are yours
B21: Sheet | C21: What you decide there | E21: Why it matters
B22: Rates & Tables | C22: Adoption factors, realisation curve, classical ADM curve, operating-model curve, pre-load, partner drag, transfer cap, guardrail floors, cost index. | E22: The amber cells here are the solution position, not data. Read the notes before changing any of them. The one most worth thinking about for your 領域 is ADOPTION: how much of the AI ceiling MetLife's own people and MGCC can realistically commit to. Common Service Platform raised them; Storage & Preservation left them at the portfolio default. Both are defensible; neither is automatic.
B23: Value Streams & Delivery Mode | C23: The quarter each stream converts to pod delivery, and the pod / team counts by year. | E23: The stream list, effort and today's method all fill in automatically. What you decide is WHEN each stream converts and how many delivery units you run. Pod and team counts drive the whole seat plan.
B24: Role × Sourcing | C24: How each sourcing pool's headcount splits across the six client roles. | E24: Seeded with the observed split across the five 領域 already modelled — 1,102 units of Year-1 roster. Change it only if you know your 領域 differs, and say why. This matrix is what makes the per-sourcing AI ceilings differ from each other.
B25: Partner plan | C25: On the Logic Tree, section E — the sub-contracted population by year. | E25: Seeded at today's named-vendor figure held flat. If your 領域 has a real incumbent, taper it deliberately: partner seats can never transfer to MetLife, so they make the 50:50 harder.
B26: Seat Planner | C26: The delivery anatomy: every seat in every pod, team and horizontal function. | E26: THIS IS THE WORK. The model tells you how many people of each sourcing type you may have in each year; the anatomy decides who they are. Keep deployed heads on a 0.5 grid and keep sharing inside the 領域 — MetLife may award the eleven 領域 to two or three vendors.
B27: Reconciliation & Checks | C27: Nothing to enter. Read it. | E27: Every invariant the five built models are held to, as live formulas. Green in every year is the bar for a solution review.
B29: HOW WE KNOW THE ENGINE IS RIGHT
B30: • The engine here was tested against two models built independently in Python and already under practice review. Set the domain to Common Service Platform, enter its conversion quarters and pod plan, and raise the two MetLife adoption factors to 0.92 and 0.72 as that 領域 argues for, and the template reproduces the built model to within 0.14 of a person on every sourcing line in every year, and 0.09 of a percentage point on the Capgemini ratio.
B31: • Set it to Storage and Preservation Related, enter its conversion quarters, pod plan and FSI taper, and it reproduces that model to within 0.11 of a person and 0.15 of a percentage point, including the six-person Year-3 transfer.
B32: • The small residual is the role × sourcing matrix: this template seeds it from the portfolio average, while each built model uses its own Year-1 anatomy. That is the one place to tune if you want an exact match to a hand-built model.
B35: WHAT THIS TEMPLATE DOES NOT DO
B36: • It does not solve the seat plan for you. The five built models were fitted numerically: seats were optimised against the per-sourcing targets, the role lines, the location split and three guardrails simultaneously, then quantised onto a 0.5 head grid. Excel cannot do that. What this template does is give you every target the solver was aiming at, and check your hand-built anatomy against all of them.
B37: • It does not carry the inherited Capgemini workforce roll-forward. That needs the billing and staff-mapping files and is domain-specific; the Golden Inventory's CG heads today is carried here as the starting point.
B38: • It does not net out applications marked Retire in the Appendix 3 v5 disposition columns. The baseline is frozen at today's effort in every year, as it is in all five built models. If your 領域 has material retirements, that is an argument to make explicitly, not silently.
B39: • It does not price anything. The cost index is relative, onshore Tokyo E2 = 1.00, and exists so you can see the shape of the cost curve before the rate card lands.

Sheet Logic Tree
A1: Logic tree (auto) — every driver, five years, one domain name
A2: Green figures are derived from the inventory or from the rates tables. Amber cells are the few genuine inputs left on this sheet. Nothing here needs editing to produce a first cut.
A4: A. BASELINE — Appendix 3 v5, read and never edited
B5: Domain | C5: ='START HERE'!$C$5 | I5: The one cell that drives the workbook. Change it on START HERE.
B6: Applications in scope | C6: =SUMPRODUCT(--('Inventory v5'!$D$5:$D$146='START HERE'!$C$5)) | I6: Zero here means the name is misspelt.
B7: TOTAL EFFORT — the frozen scope | C7: =SUMIFS('Inventory v5'!$J$5:$J$146,'Inventory v5'!$D$5:$D$146,'START HERE'!$C$5) | I7: Units of person-capacity. Held constant across all five years: productivity shows as fewer people doing the same scope, never as scope walking out of the model.
B8: Vendor today (Appendix 3 'Current FTC') | C8: =SUMIFS('Inventory v5'!$K$5:$K$146,'Inventory v5'!$D$5:$D$146,'START HERE'!$C$5) | I8: Capgemini plus any named sub-contractor.
B9: MetLife Japan today (FTE) | C9: =SUMIFS('Inventory v5'!$L$5:$L$146,'Inventory v5'!$D$5:$D$146,'START HERE'!$C$5) | I9: Governance, product ownership, domain SME.
B10: MetLife MGCC today | C10: =SUMIFS('Inventory v5'!$M$5:$M$146,'Inventory v5'!$D$5:$D$146,'START HERE'!$C$5) | I10: MetLife's captive delivery centre.
B11: Onshore Tokyo | C11: =SUMIFS('Inventory v5'!$N$5:$N$146,'Inventory v5'!$D$5:$D$146,'START HERE'!$C$5) | I11: Vendor only. MEASURED, not assumed.
B12: Offshore | C12: =SUMIFS('Inventory v5'!$O$5:$O$146,'Inventory v5'!$D$5:$D$146,'START HERE'!$C$5) | I12: Vendor only. MGCC is excluded — it is MetLife's, not ours.
B13: Nearshore | C13: =SUMIFS('Inventory v5'!$P$5:$P$146,'Inventory v5'!$D$5:$D$146,'START HERE'!$C$5) | I13: Zero in most 領域. Carried so every domain model shares one schema.
B14: Capgemini heads on these applications today | C14: =SUMIFS('Inventory v5'!$AN$5:$AN$146,'Inventory v5'!$D$5:$D$146,'START HERE'!$C$5) | I14: From the Golden Inventory v4 workforce reconciliation. The continuity argument starts here.
B16: Rows 7 to 13 are the reconciliation target. A Year-1 seat plan that does not reproduce these numbers is not a plan for this 領域 — it is a plan for a different one.
A18: B. THE ROLE LINE — as reported, and as restated where it is internally impossible
B19: Client role | C19: Appendix 3 v5 | D19: Restated — INPUT | E19: Difference | I19: Note
B20: BSA | C20: =SUMIFS('Inventory v5'!$Q$5:$Q$146,'Inventory v5'!$D$5:$D$146,'START HERE'!$C$5) | D20: 3.67447 | E20: =D20-C20 | I20: Bilingual analysis. Scarce in every 領域.
B21: Developer | C21: =SUMIFS('Inventory v5'!$R$5:$R$146,'Inventory v5'!$D$5:$D$146,'START HERE'!$C$5) | D21: 13.962986 | E21: =D21-C21 | I21: The line restatements are taken FROM here, which is why it is the only one that falls.
B22: Tester | C22: =SUMIFS('Inventory v5'!$S$5:$S$146,'Inventory v5'!$D$5:$D$146,'START HERE'!$C$5) | D22: 6.246599 | E22: =D22-C22 | I22: Where the AI ceiling is highest. A thin tester line understates what is achievable.
B23: Maintenance | C23: =SUMIFS('Inventory v5'!$T$5:$T$146,'Inventory v5'!$D$5:$D$146,'START HERE'!$C$5) | D23: 8.083834 | E23: =D23-C23 | I23: Compare to the ticket load on the AMS sheet. Several 領域 report one person of run against a thousand incidents a year; that is a coding convention, not a plan.
B24: PM | C24: =SUMIFS('Inventory v5'!$U$5:$U$146,'Inventory v5'!$D$5:$D$146,'START HERE'!$C$5) | D24: 2.572129 | E24: =D24-C24 | I24: Compare to the number of delivery units you intend to run.
B25: Other | C25: =SUMIFS('Inventory v5'!$V$5:$V$146,'Inventory v5'!$D$5:$D$146,'START HERE'!$C$5) | D25: 2.204682 | E25: =D25-C25 | I25: Architecture and enablement. Reported as zero in several 領域.
B26: Total — must equal the vendor number, and must not move | C26: =SUM(C20:C25) | D26: =SUM(D20:D25) | E26: =D26-C26
B27: Neutrality check | C27: =IF(ABS(E26)<0.005,"OK — arithmetically neutral","FAIL — the restatement changes the total")
B28: A RESTATEMENT MOVES PEOPLE BETWEEN ROLE LINES. IT NEVER CHANGES THE TOTAL. Overwrite the amber column where MetLife's own figure is internally impossible, take the difference out of Developer, and check that row 27 still says OK. Every restatement goes back to MetLife as a clarification question — we are not silently re-pricing their data.
A30: C. ARCHETYPES — the six-rule classifier, and the two ceilings it sets
B31: Archetype | C31: Apps | D31: Effort | E31: Share of effort | F31: AI ceiling | G31: Offshore ceiling | I31: Note
B32: M | C32: =SUMPRODUCT(--('Inventory v5'!$D$5:$D$146='START HERE'!$C$5),--('Inventory v5'!$G$5:$G$146="M")) | D32: =SUMIFS('Inventory v5'!$J$5:$J$146,'Inventory v5'!$D$5:$D$146,'START HERE'!$C$5,'Inventory v5'!$G$5:$G$146,"M") | E32: =IF($C$7=0,0,D32/$C$7) | F32: ='Rates & Tables'!$I$6 | G32: ='Rates & Tables'!$C$27
B33: L | C33: =SUMPRODUCT(--('Inventory v5'!$D$5:$D$146='START HERE'!$C$5),--('Inventory v5'!$G$5:$G$146="L")) | D33: =SUMIFS('Inventory v5'!$J$5:$J$146,'Inventory v5'!$D$5:$D$146,'START HERE'!$C$5,'Inventory v5'!$G$5:$G$146,"L") | E33: =IF($C$7=0,0,D33/$C$7) | F33: ='Rates & Tables'!$I$7 | G33: ='Rates & Tables'!$C$28
B34: D | C34: =SUMPRODUCT(--('Inventory v5'!$D$5:$D$146='START HERE'!$C$5),--('Inventory v5'!$G$5:$G$146="D")) | D34: =SUMIFS('Inventory v5'!$J$5:$J$146,'Inventory v5'!$D$5:$D$146,'START HERE'!$C$5,'Inventory v5'!$G$5:$G$146,"D") | E34: =IF($C$7=0,0,D34/$C$7) | F34: ='Rates & Tables'!$I$8 | G34: ='Rates & Tables'!$C$29
B35: P | C35: =SUMPRODUCT(--('Inventory v5'!$D$5:$D$146='START HERE'!$C$5),--('Inventory v5'!$G$5:$G$146="P")) | D35: =SUMIFS('Inventory v5'!$J$5:$J$146,'Inventory v5'!$D$5:$D$146,'START HERE'!$C$5,'Inventory v5'!$G$5:$G$146,"P") | E35: =IF($C$7=0,0,D35/$C$7) | F35: ='Rates & Tables'!$I$9 | G35: ='Rates & Tables'!$C$30
B36: J | C36: =SUMPRODUCT(--('Inventory v5'!$D$5:$D$146='START HERE'!$C$5),--('Inventory v5'!$G$5:$G$146="J")) | D36: =SUMIFS('Inventory v5'!$J$5:$J$146,'Inventory v5'!$D$5:$D$146,'START HERE'!$C$5,'Inventory v5'!$G$5:$G$146,"J") | E36: =IF($C$7=0,0,D36/$C$7) | F36: ='Rates & Tables'!$I$10 | G36: ='Rates & Tables'!$C$31
B37: T | C37: =SUMPRODUCT(--('Inventory v5'!$D$5:$D$146='START HERE'!$C$5),--('Inventory v5'!$G$5:$G$146="T")) | D37: =SUMIFS('Inventory v5'!$J$5:$J$146,'Inventory v5'!$D$5:$D$146,'START HERE'!$C$5,'Inventory v5'!$G$5:$G$146,"T") | E37: =IF($C$7=0,0,D37/$C$7) | F37: ='Rates & Tables'!$I$11 | G37: ='Rates & Tables'!$C$32
B38: BLENDED AI CEILING | C38: =IF($C$7=0,0,SUMPRODUCT($D$32:$D$37,$F$32:$F$37)/$C$7) | I38: Effort-weighted. This is what the estate could theoretically support, before realisation, before adoption, and before anyone has to agree to it.
B39: BLENDED OFFSHORE CEILING | C39: =IF($C$7=0,0,SUMPRODUCT($D$32:$D$37,$G$32:$G$37)/$C$7) | I39: The number that decides whether an offshore case exists at all. A 領域 that is mostly J applications cannot be moved, however good the tooling.
A41: D. THE CAPABILITY CHAIN — four gates, compounded, then pre-loaded
B42: Driver | C42: Year 1 | D42: Year 2 | E42: Year 3 | F42: Year 4 | G42: Year 5 | I42: Basis
B43: Agile share of effort | C43: ='Value Streams & Delivery Mode'!D33 | D43: ='Value Streams & Delivery Mode'!E33 | E43: ='Value Streams & Delivery Mode'!F33 | F43: ='Value Streams & Delivery Mode'!G33 | G43: ='Value Streams & Delivery Mode'!H33 | I43: From the Value Streams sheet. Operating-model gain is only available where the stream actually runs as a pod, so this scales it.
B44: Operating-model productivity — pass 1 | C44: ='Rates & Tables'!C47*C43 | D44: ='Rates & Tables'!D47*D43 | E44: ='Rates & Tables'!E47*E43 | F44: ='Rates & Tables'!F47*F43 | G44: ='Rates & Tables'!G47*G43 | I44: Pass one, before the partner discount. It exists only to give the partner share something to divide by.
B45: Blended capability — pass 1 | C45: =1-(1-$C$38*'Rates & Tables'!C45)*(1-'Rates & Tables'!C46)*(1-C44) | D45: =1-(1-$C$38*'Rates & Tables'!D45)*(1-'Rates & Tables'!D46)*(1-D44) | E45: =1-(1-$C$38*'Rates & Tables'!E45)*(1-'Rates & Tables'!E46)*(1-E44) | F45: =1-(1-$C$38*'Rates & Tables'!F45)*(1-'Rates & Tables'!F46)*(1-F44) | G45: =1-(1-$C$38*'Rates & Tables'!G45)*(1-'Rates & Tables'!G46)*(1-G44) | I45: 1 − (1 − ceiling × realisation)(1 − classical)(1 − operating model). The gates are independent, so they compound rather than add.
B46: Applied — pass 1 | C46: =0 | D46: =C45+'Rates & Tables'!$C$51*(D45-C45) | E46: =D45+'Rates & Tables'!$C$51*(E45-D45) | F46: =E45+'Rates & Tables'!$C$51*(F45-E45) | G46: =F45+'Rates & Tables'!$C$51*(G45-F45) | I46: Carry-forward: this year's applied figure is last year's full capability plus the pre-load share of this year's gain. Year 1 applies nothing.
B47: Target headcount — pass 1 | C47: =$C$7*(1-C46) | D47: =$C$7*(1-D46) | E47: =$C$7*(1-E46) | F47: =$C$7*(1-F46) | G47: =$C$7*(1-G46) | I47: Pass one only. Not the commitment.
B48: Partner share of the population | C48: =IF(C47=0,0,C57/C47) | D48: =IF(D47=0,0,D57/D47) | E48: =IF(E47=0,0,E57/E47) | F48: =IF(F47=0,0,F57/F47) | G48: =IF(G47=0,0,G57/G47) | I48: Partner population divided by the pass-one target. This is the step that breaks the circularity: the partner share depends on the target and the target depends on the partner share.
B49: Operating-model productivity — final | C49: ='Rates & Tables'!C47*C43*(1-'Rates & Tables'!$C$52*C48) | D49: ='Rates & Tables'!D47*D43*(1-'Rates & Tables'!$C$52*D48) | E49: ='Rates & Tables'!E47*E43*(1-'Rates & Tables'!$C$52*E48) | F49: ='Rates & Tables'!F47*F43*(1-'Rates & Tables'!$C$52*F48) | G49: ='Rates & Tables'!G47*G43*(1-'Rates & Tables'!$C$52*G48) | I49: Raw curve × agile share × span-of-control factor. On a 領域 with no sub-contractor this equals row 44.
B50: BLENDED CAPABILITY — final | C50: =1-(1-$C$38*'Rates & Tables'!C45)*(1-'Rates & Tables'!C46)*(1-C49) | D50: =1-(1-$C$38*'Rates & Tables'!D45)*(1-'Rates & Tables'!D46)*(1-D49) | E50: =1-(1-$C$38*'Rates & Tables'!E45)*(1-'Rates & Tables'!E46)*(1-E49) | F50: =1-(1-$C$38*'Rates & Tables'!F45)*(1-'Rates & Tables'!F46)*(1-F49) | G50: =1-(1-$C$38*'Rates & Tables'!G45)*(1-'Rates & Tables'!G46)*(1-G49) | I50: The domain commitment, blended across all four sourcing types. Section F then splits it.
B51: APPLIED — carry-forward with pre-load | C51: =0 | D51: =C50+'Rates & Tables'!$C$51*(D50-C50) | E51: =D50+'Rates & Tables'!$C$51*(E50-D50) | F51: =E50+'Rates & Tables'!$C$51*(F50-E50) | G51: =F50+'Rates & Tables'!$C$51*(G50-F50) | I51: Year 1 applies ZERO. Capability earned in Q4 cannot fund a headcount reduction in Q1, and a Year-1 roster that does not match Appendix 3 is not credible.
B52: TARGET HEADCOUNT — the commitment | C52: =$C$7*(1-C51) | D52: =$C$7*(1-D51) | E52: =$C$7*(1-E51) | F52: =$C$7*(1-F51) | G52: =$C$7*(1-G51) | I52: THE NUMBER THE WHOLE MODEL EXISTS TO PRODUCE. Frozen scope × (1 − applied).
A54: E. PARTNER — the fourth sourcing type, and why it makes the 50:50 harder
B55: Measure | C55: Which vendor | D55: Year 2 | E55: Year 3 | F55: Year 4 | G55: Year 5 | I55: Basis
B56: Sub-contracted FTC today — pick the vendor | C56: 5 | D56: FSI | I56: ="FSI "&TEXT(SUMIFS('Inventory v5'!$K$5:$K$146,'Inventory v5'!$D$5:$D$146,'START HERE'!$C$5,'Inventory v5'!$F$5:$F$146,"FSI"),"0.0")&" · NCD "&TEXT(SUMIFS('Inventory v5'!$K$5:$K$146,'Inventory v5'!$D$5:$D$146,'START HERE'!$C$5,'Inventory v5'!$F$5:$F$146,"NCD"),"0.0")&" · NCS "&TEXT(SUMIFS('Inventory v5'!$K$5:$K$146,'Inventory v5'!$D$5:$D$146,'START HERE'!$C$5,'Inventory v5'!$F$5:$F$146,"NCS"),"0.0")&" · Capgemini "&TEXT(SUMIFS('Inventory v5'!$K$5:$K$146,'Inventory v5'!$D$5:$D$146,'START HERE'!$C$5,'Inventory v5'!$F$5:$F$146,"CG"),"0.0")&" · no named vendor "&TEXT(SUMIFS('Inventory v5'!$K$5:$K$146,'Inventory v5'!$D$5:$D$146,'START HERE'!$C$5,'Inventory v5'!$F$5:$F$146,"unnamed"),"0.0") | J56: Vendor FTC in this 領域 from the Golden v4 tags. Zero against every named vendor means no sub-contract of size, and the PT rows resolve to zero.
B57: PARTNER POPULATION BY YEAR — INPUT | C57: 5 | D57: 5 | E57: 4 | F57: 3 | G57: 3 | I57: SEEDED, NOT DECIDED. The default holds the partner at a constant share of a shrinking domain. If you have a real incumbent, taper it deliberately: partner seats can never transfer to MetLife, so every one you keep sits on the Capgemini side of the 50:50 permanently. If you have none, leave it at zero. | J57: DECIDE WHICH NAMED VENDORS YOU ARE RETAINING AS SUB-CONTRACTORS. Not every third party in the 領域 is one: some we sub-contract because they hold irreplaceable knowledge, and some we displace and absorb. The five built models retained FSI where FSI was entrenched on Japanese-specification waterfall applications, and absorbed NCD everywhere. Choose, and be able to say why — the answer changes the 50:50 arithmetic.
B58: Span-of-control factor = 1 − drag × partner share | C58: =1-'Rates & Tables'!$C$52*C48 | D58: =1-'Rates & Tables'!$C$52*D48 | E58: =1-'Rates & Tables'!$C$52*E48 | F58: =1-'Rates & Tables'!$C$52*F48 | G58: =1-'Rates & Tables'!$C$52*G48
B59: A partner seat returns 40% of the operating-model gain a Capgemini seat does — two management chains, a contractual boundary on ways of working, slower standardisation. That is the drag on the Rates sheet, and it is the number to argue about if your 領域 is partner-heavy.
A61: F. PER-SOURCING — the same four gates, on four different populations
B62: Sourcing pool | C62: Year-1 population | D62: Own AI ceiling | E62: Adoption | J62: What this pool does
B63: FTC | C63: =$C$8-$C$57 | D63: ='Role x Sourcing'!$D$40 | E63: ='Rates & Tables'!$C$36 | I63: Capgemini payroll. The vendor number less the named sub-contractor.
B64: PT | C64: =$C$57 | D64: ='Role x Sourcing'!$D$41 | E64: ='Rates & Tables'!$C$37 | I64: Named sub-contractor. Zero in most 領域.
B65: FTE | C65: =$C$9 | D65: ='Role x Sourcing'!$D$42 | E65: ='Rates & Tables'!$C$38 | I65: MetLife Japan. Across the five 領域 modelled this population is 41% BSA and 39% PM — governance work, the least machine-addressable in the estate.
B66: MGCC | C66: =$C$10 | D66: ='Role x Sourcing'!$D$43 | E66: ='Rates & Tables'!$C$39 | I66: MetLife's captive centre. 74% developers and 26% testers — build and test, where the ceiling is highest.
B67: Total — ties to the frozen scope | C67: =SUM(C63:C66)
B68: Day-one vendor share — does the 50% guardrail even apply here? | C68: =IF($C$7=0,0,(C63+C64)/$C$7) | D68: =IF(C68>='Rates & Tables'!$C$55,1,0) | I68: 1 = Capgemini starts in the majority, so the floor is a position we are PROTECTING and it applies from Year 2. 0 = MetLife already holds the majority on day one, so the floor is switched off: we do not manufacture a majority we never had. Common Service Platform is the worked example of the second case.
B70: CAPABILITY BY POOL | C70: Year 1 | D70: Year 2 | E70: Year 3 | F70: Year 4 | G70: Year 5
B71: FTC | C71: =1-(1-$D$63*'Rates & Tables'!C45*$E$63)*(1-'Rates & Tables'!C46)*(1-C49) | D71: =1-(1-$D$63*'Rates & Tables'!D45*$E$63)*(1-'Rates & Tables'!D46)*(1-D49) | E71: =1-(1-$D$63*'Rates & Tables'!E45*$E$63)*(1-'Rates & Tables'!E46)*(1-E49) | F71: =1-(1-$D$63*'Rates & Tables'!F45*$E$63)*(1-'Rates & Tables'!F46)*(1-F49) | G71: =1-(1-$D$63*'Rates & Tables'!G45*$E$63)*(1-'Rates & Tables'!G46)*(1-G49)
B72: PT | C72: =1-(1-$D$64*'Rates & Tables'!C45*$E$64)*(1-'Rates & Tables'!C46)*(1-C49) | D72: =1-(1-$D$64*'Rates & Tables'!D45*$E$64)*(1-'Rates & Tables'!D46)*(1-D49) | E72: =1-(1-$D$64*'Rates & Tables'!E45*$E$64)*(1-'Rates & Tables'!E46)*(1-E49) | F72: =1-(1-$D$64*'Rates & Tables'!F45*$E$64)*(1-'Rates & Tables'!F46)*(1-F49) | G72: =1-(1-$D$64*'Rates & Tables'!G45*$E$64)*(1-'Rates & Tables'!G46)*(1-G49)
B73: FTE | C73: =1-(1-$D$65*'Rates & Tables'!C45*$E$65)*(1-'Rates & Tables'!C46)*(1-C49) | D73: =1-(1-$D$65*'Rates & Tables'!D45*$E$65)*(1-'Rates & Tables'!D46)*(1-D49) | E73: =1-(1-$D$65*'Rates & Tables'!E45*$E$65)*(1-'Rates & Tables'!E46)*(1-E49) | F73: =1-(1-$D$65*'Rates & Tables'!F45*$E$65)*(1-'Rates & Tables'!F46)*(1-F49) | G73: =1-(1-$D$65*'Rates & Tables'!G45*$E$65)*(1-'Rates & Tables'!G46)*(1-G49)
B74: MGCC | C74: =1-(1-$D$66*'Rates & Tables'!C45*$E$66)*(1-'Rates & Tables'!C46)*(1-C49) | D74: =1-(1-$D$66*'Rates & Tables'!D45*$E$66)*(1-'Rates & Tables'!D46)*(1-D49) | E74: =1-(1-$D$66*'Rates & Tables'!E45*$E$66)*(1-'Rates & Tables'!E46)*(1-E49) | F74: =1-(1-$D$66*'Rates & Tables'!F45*$E$66)*(1-'Rates & Tables'!F46)*(1-F49) | G74: =1-(1-$D$66*'Rates & Tables'!G45*$E$66)*(1-'Rates & Tables'!G46)*(1-G49)
B76: APPLIED — carry-forward with pre-load | C76: Year 1 | D76: Year 2 | E76: Year 3 | F76: Year 4 | G76: Year 5
B77: FTC | C77: =0 | D77: =C71+'Rates & Tables'!$C$51*(D71-C71) | E77: =D71+'Rates & Tables'!$C$51*(E71-D71) | F77: =E71+'Rates & Tables'!$C$51*(F71-E71) | G77: =F71+'Rates & Tables'!$C$51*(G71-F71)
B78: PT | C78: =0 | D78: =C72+'Rates & Tables'!$C$51*(D72-C72) | E78: =D72+'Rates & Tables'!$C$51*(E72-D72) | F78: =E72+'Rates & Tables'!$C$51*(F72-E72) | G78: =F72+'Rates & Tables'!$C$51*(G72-F72)
B79: FTE | C79: =0 | D79: =C73+'Rates & Tables'!$C$51*(D73-C73) | E79: =D73+'Rates & Tables'!$C$51*(E73-D73) | F79: =E73+'Rates & Tables'!$C$51*(F73-E73) | G79: =F73+'Rates & Tables'!$C$51*(G73-F73)
B80: MGCC | C80: =0 | D80: =C74+'Rates & Tables'!$C$51*(D74-C74) | E80: =D74+'Rates & Tables'!$C$51*(E74-D74) | F80: =E74+'Rates & Tables'!$C$51*(F74-E74) | G80: =F74+'Rates & Tables'!$C$51*(G74-F74)
B82: NATURAL POPULATION — each pool on its own curve | C82: Year 1 | D82: Year 2 | E82: Year 3 | F82: Year 4 | G82: Year 5
B83: FTC | C83: =$C$63*(1-C77) | D83: =$C$63*(1-D77) | E83: =$C$63*(1-E77) | F83: =$C$63*(1-F77) | G83: =$C$63*(1-G77)
B84: PT | C84: =$C$64*(1-C78) | D84: =$C$64*(1-D78) | E84: =$C$64*(1-E78) | F84: =$C$64*(1-F78) | G84: =$C$64*(1-G78)
B85: FTE | C85: =$C$65*(1-C79) | D85: =$C$65*(1-D79) | E85: =$C$65*(1-E79) | F85: =$C$65*(1-F79) | G85: =$C$65*(1-G79)
B86: MGCC | C86: =$C$66*(1-C80) | D86: =$C$66*(1-D80) | E86: =$C$66*(1-E80) | F86: =$C$66*(1-F80) | G86: =$C$66*(1-G80)
B87: THIS IS THE HEART OF THE MODEL. The headline commitment in row 52 does not change. What changes is who carries it. A pool whose work sits in Test and Build earns a high ceiling; a pool whose work sits in Run and Requirements earns a low one; and the adoption factor then asks how much of that ceiling the pool has the authority to commit to. Apply one blended rate to all four and you are wrong in both directions at once — and most wrong on the population you control least.
A89: G. THE PLAN — MetLife and the partner take their own path, Capgemini absorbs the balance
B90: Measure | C90: Year 1 | D90: Year 2 | E90: Year 3 | F90: Year 4 | G90: Year 5 | I90: Note
B91: Target headcount | C91: =C52 | D91: =D52 | E91: =E52 | F91: =F52 | G91: =G52 | I91: From row 52. Unchanged by anything in this section.
B92: MetLife Japan (FTE) | C92: =C85 | D92: =D85 | E92: =E85 | F92: =F85 | G92: =G85 | I92: Their own slower curve, from row 85. Not the domain average.
B93: MetLife MGCC | C93: =C86 | D93: =D86 | E93: =E86 | F93: =F86 | G93: =G86 | I93: Their own curve, from row 86.
B94: Partner (PT) | C94: =C57 | D94: =D57 | E94: =E57 | F94: =F57 | G94: =G57 | I94: The partner plan from row 57.
B95: Capgemini (FTC) — absorbs the balance | C95: =C91-C92-C93-C94 | D95: =IF(AND($D$68=1,(D91-D92-D93)/D91<'Rates & Tables'!$C$55),'Rates & Tables'!$C$55/(1-'Rates & Tables'!$C$55)*(D92+D93)-D94,D91-D92-D93-D94) | E95: =IF(AND($D$68=1,(E91-E92-E93)/E91<'Rates & Tables'!$C$55),'Rates & Tables'!$C$55/(1-'Rates & Tables'!$C$55)*(E92+E93)-E94,E91-E92-E93-E94) | F95: =IF(AND($D$68=1,(F91-F92-F93)/F91<'Rates & Tables'!$C$55),'Rates & Tables'!$C$55/(1-'Rates & Tables'!$C$55)*(F92+F93)-F94,F91-F92-F93-F94) | G95: =IF(AND($D$68=1,(G91-G92-G93)/G91<'Rates & Tables'!$C$55),'Rates & Tables'!$C$55/(1-'Rates & Tables'!$C$55)*(G92+G93)-G94,G91-G92-G93-G94) | I95: WHAT IS LEFT. This is the mechanic that converges the ratio without anybody changing employer: Capgemini shrinks faster than MetLife because Capgemini's work is more machine-addressable and Capgemini has the authority to act on it.
B96: TOTAL | C96: =C95+C94+C92+C93 | D96: =D95+D94+D92+D93 | E96: =E95+E94+E92+E93 | F96: =F95+F94+F92+F93 | G96: =G95+G94+G92+G93 | I96: Equals row 91 unless the floor has fired.
B97: RATIO — Capgemini + partner share | C97: =IF(C96=0,0,(C95+C94)/C96) | D97: =IF(D96=0,0,(D95+D94)/D96) | E97: =IF(E96=0,0,(E95+E94)/E96) | F97: =IF(F96=0,0,(F95+F94)/F96) | G97: =IF(G96=0,0,(G95+G94)/G96) | I97: Falls every year. That fall is the organic convergence, and it is what makes the Year-3 transfer small.
B98: Floor applied? | C98: 0 | D98: =IF(AND($D$68=1,(D91-D92-D93)/D91<'Rates & Tables'!$C$55),1,0) | E98: =IF(AND($D$68=1,(E91-E92-E93)/E91<'Rates & Tables'!$C$55),1,0) | F98: =IF(AND($D$68=1,(F91-F92-F93)/F91<'Rates & Tables'!$C$55),1,0) | G98: =IF(AND($D$68=1,(G91-G92-G93)/G91<'Rates & Tables'!$C$55),1,0) | I98: 1 = the guardrail bound this year and Capgemini was held above the floor rather than shrinking further. Check row 68 first: if the floor does not apply to your 領域 this will always be 0.
A100: H. THE TRANSFER — struck once, on the Year-3 exit, AFTER organic convergence
B101: Step | C101: Value | J101: Note
B103: Exit Year 3 headcount, at full realisation | C103: =$C$7*(1-E50) | I103: Not the Year-3 target. The transfer is struck on the position the domain exits Year 3 in, which is the full capability rather than the pre-loaded figure.
B104: Scale factor from the Year-3 plan to the exit | C104: =IF(E96=0,0,C103/E96) | I104: The Year-3 plan is re-based onto the exit headcount so the mix is preserved.
B105: Vendor units at the exit | C105: =(E95+E94)*C104 | I105: Capgemini plus partner.
B106: — of which Capgemini payroll, the transfer pool | C106: =E95*C104 | I106: ONLY THIS CAN MOVE. Partner seats are contracted to a third party; they are not ours to transfer.
B107: 50:50 requires each side to be | C107: =C103/2 | I107: Half the exit headcount.
B108: TRANSFER REQUIRED | C108: =C105-C107 | I108: NEGATIVE means the 領域 is already past 50:50 and nothing needs to move — argue against further convergence rather than for it.
B109: Cap on the transferable pool | C109: ='Rates & Tables'!$C$53 | I109: The most of our own population we will put through a transfer of employment.
B110: Maximum transferable | C110: =C106*C109 | I110: The pool times the cap.
B111: TRANSFER APPLIED | C111: =MAX(0,MIN(C108,C110)) | I111: If this is materially below row 108 the 50:50 does not close on transfer alone, and the answer is a different sourcing mix rather than a bigger transfer. Contract Management is the worked example.
B112: — to MetLife Japan | C112: =ROUND(C111*'Rates & Tables'!$C$54,1) | I112: Onshore people to the onshore entity.
B113: — to MGCC | C113: =ROUND(C111-C112,1) | I113: Offshore people to the offshore entity.
...

Sheet Value Streams & Delivery Mode
A1: Value streams and delivery mode — the streams fill in, the conversion is yours
A2: Stream names, application counts, effort and today's development method are read from Appendix 3 v5. What you decide is when each stream converts to pod delivery and how many units you run.
A4: A. THE STREAMS IN THIS 領域 (auto, except the conversion quarter)
B5: # | C5: Value stream | D5: Apps | E5: Effort | F5: Share | G5: Method today | H5: Converts in Q — INPUT
B6: 1 | C6: =IFERROR(INDEX('Stream Catalogue'!$E$5:$E$31,MATCH('START HERE'!$C$5&"|"&$B6,'Stream Catalogue'!$B$5:$B$31,0)),"") | D6: =IFERROR(INDEX('Stream Catalogue'!$F$5:$F$31,MATCH('START HERE'!$C$5&"|"&$B6,'Stream Catalogue'!$B$5:$B$31,0)),"") | E6: =IFERROR(INDEX('Stream Catalogue'!$G$5:$G$31,MATCH('START HERE'!$C$5&"|"&$B6,'Stream Catalogue'!$B$5:$B$31,0)),"") | F6: =IF($E6="","",IF('Logic Tree'!$C$7=0,0,$E6/'Logic Tree'!$C$7)) | G6: =IFERROR(INDEX('Stream Catalogue'!$H$5:$H$31,MATCH('START HERE'!$C$5&"|"&$B6,'Stream Catalogue'!$B$5:$B$31,0)),"") | H6: 1 | J6: Blank rows mean your 領域 has fewer than six value streams — that is normal, most have two or three. If row 13 is not zero, your 領域 has MORE than six and the catalogue needs extending; tell whoever maintains this template.
B7: 2 | C7: =IFERROR(INDEX('Stream Catalogue'!$E$5:$E$31,MATCH('START HERE'!$C$5&"|"&$B7,'Stream Catalogue'!$B$5:$B$31,0)),"") | D7: =IFERROR(INDEX('Stream Catalogue'!$F$5:$F$31,MATCH('START HERE'!$C$5&"|"&$B7,'Stream Catalogue'!$B$5:$B$31,0)),"") | E7: =IFERROR(INDEX('Stream Catalogue'!$G$5:$G$31,MATCH('START HERE'!$C$5&"|"&$B7,'Stream Catalogue'!$B$5:$B$31,0)),"") | F7: =IF($E7="","",IF('Logic Tree'!$C$7=0,0,$E7/'Logic Tree'!$C$7)) | G7: =IFERROR(INDEX('Stream Catalogue'!$H$5:$H$31,MATCH('START HERE'!$C$5&"|"&$B7,'Stream Catalogue'!$B$5:$B$31,0)),"") | H7: 5
B8: 3 | C8: =IFERROR(INDEX('Stream Catalogue'!$E$5:$E$31,MATCH('START HERE'!$C$5&"|"&$B8,'Stream Catalogue'!$B$5:$B$31,0)),"") | D8: =IFERROR(INDEX('Stream Catalogue'!$F$5:$F$31,MATCH('START HERE'!$C$5&"|"&$B8,'Stream Catalogue'!$B$5:$B$31,0)),"") | E8: =IFERROR(INDEX('Stream Catalogue'!$G$5:$G$31,MATCH('START HERE'!$C$5&"|"&$B8,'Stream Catalogue'!$B$5:$B$31,0)),"") | F8: =IF($E8="","",IF('Logic Tree'!$C$7=0,0,$E8/'Logic Tree'!$C$7)) | G8: =IFERROR(INDEX('Stream Catalogue'!$H$5:$H$31,MATCH('START HERE'!$C$5&"|"&$B8,'Stream Catalogue'!$B$5:$B$31,0)),"") | H8: 7
B9: 4 | C9: =IFERROR(INDEX('Stream Catalogue'!$E$5:$E$31,MATCH('START HERE'!$C$5&"|"&$B9,'Stream Catalogue'!$B$5:$B$31,0)),"") | D9: =IFERROR(INDEX('Stream Catalogue'!$F$5:$F$31,MATCH('START HERE'!$C$5&"|"&$B9,'Stream Catalogue'!$B$5:$B$31,0)),"") | E9: =IFERROR(INDEX('Stream Catalogue'!$G$5:$G$31,MATCH('START HERE'!$C$5&"|"&$B9,'Stream Catalogue'!$B$5:$B$31,0)),"") | F9: =IF($E9="","",IF('Logic Tree'!$C$7=0,0,$E9/'Logic Tree'!$C$7)) | G9: =IFERROR(INDEX('Stream Catalogue'!$H$5:$H$31,MATCH('START HERE'!$C$5&"|"&$B9,'Stream Catalogue'!$B$5:$B$31,0)),"") | H9: 9 | J9: THE CONVERSION QUARTER IS THE ASSUMPTION TO ARGUE ABOUT. Q1 means the stream runs as pods from day one; Q9 means it converts at the start of Year 3. A stream that is already recorded Agile in Appendix 3 should convert early — the work is proving the pod shape, not changing method. A Japanese-specification waterfall stream should convert late or not at all.
B10: 5 | C10: =IFERROR(INDEX('Stream Catalogue'!$E$5:$E$31,MATCH('START HERE'!$C$5&"|"&$B10,'Stream Catalogue'!$B$5:$B$31,0)),"") | D10: =IFERROR(INDEX('Stream Catalogue'!$F$5:$F$31,MATCH('START HERE'!$C$5&"|"&$B10,'Stream Catalogue'!$B$5:$B$31,0)),"") | E10: =IFERROR(INDEX('Stream Catalogue'!$G$5:$G$31,MATCH('START HERE'!$C$5&"|"&$B10,'Stream Catalogue'!$B$5:$B$31,0)),"") | F10: =IF($E10="","",IF('Logic Tree'!$C$7=0,0,$E10/'Logic Tree'!$C$7)) | G10: =IFERROR(INDEX('Stream Catalogue'!$H$5:$H$31,MATCH('START HERE'!$C$5&"|"&$B10,'Stream Catalogue'!$B$5:$B$31,0)),"") | H10: 11
B11: 6 | C11: =IFERROR(INDEX('Stream Catalogue'!$E$5:$E$31,MATCH('START HERE'!$C$5&"|"&$B11,'Stream Catalogue'!$B$5:$B$31,0)),"") | D11: =IFERROR(INDEX('Stream Catalogue'!$F$5:$F$31,MATCH('START HERE'!$C$5&"|"&$B11,'Stream Catalogue'!$B$5:$B$31,0)),"") | E11: =IFERROR(INDEX('Stream Catalogue'!$G$5:$G$31,MATCH('START HERE'!$C$5&"|"&$B11,'Stream Catalogue'!$B$5:$B$31,0)),"") | F11: =IF($E11="","",IF('Logic Tree'!$C$7=0,0,$E11/'Logic Tree'!$C$7)) | G11: =IFERROR(INDEX('Stream Catalogue'!$H$5:$H$31,MATCH('START HERE'!$C$5&"|"&$B11,'Stream Catalogue'!$B$5:$B$31,0)),"") | H11: 13
C12: Total — must equal the frozen scope | D12: =SUM(D6:D11) | E12: =SUM(E6:E11) | F12: =IF('Logic Tree'!$C$7=0,0,E12/'Logic Tree'!$C$7)
C13: Reconciliation to the Logic Tree | E13: =E12-'Logic Tree'!$C$7
A15: B. DELIVERY UNITS BY YEAR — INPUT
B16: # | C16: Value stream | D16: Y1 pods | E16: Y1 teams | F16: Y2 pods | G16: Y2 teams | H16: Y3 pods | I16: Y3 teams | J16: Y4 pods | K16: Y4 teams | L16: Y5 pods | M16: Y5 teams
B17: 1 | C17: =C6 | D17: 1 | E17: 0 | F17: 1 | G17: 0 | H17: 1 | I17: 0 | J17: 1 | K17: 0 | L17: 1 | M17: 0 | O17: A POD is a cross-functional unit that owns a stream end to end; a TEAM is the waterfall or hybrid shape with a separate test cell. Across the five 領域 modelled, pods run 10 seats in Year 1 falling to 6 by Year 4, and teams run 11 to 12 with the test cell attached. Enter the counts here; the Seat Planner multiplies them by the seat anatomy you design.
B18: 2 | C18: =C7 | D18: 0 | E18: 1 | F18: 1 | G18: 0 | H18: 1 | I18: 0 | J18: 1 | K18: 0 | L18: 1 | M18: 0
B19: 3 | C19: =C8 | D19: 0 | E19: 1 | F19: 0 | G19: 1 | H19: 1 | I19: 0 | J19: 1 | K19: 0 | L19: 1 | M19: 0
B20: 4 | C20: =C9 | D20: 0 | E20: 0 | F20: 0 | G20: 0 | H20: 0 | I20: 0 | J20: 0 | K20: 0 | L20: 0 | M20: 0 | O20: Teams should disappear as streams convert. If you still have teams in Year 5, either the conversion quarters above are wrong or you are telling MetLife the 領域 never modernises — which may be the right answer for a Japan-locked estate, but say it out loud.
B21: 5 | C21: =C10 | D21: 0 | E21: 0 | F21: 0 | G21: 0 | H21: 0 | I21: 0 | J21: 0 | K21: 0 | L21: 0 | M21: 0
B22: 6 | C22: =C11 | D22: 0 | E22: 0 | F22: 0 | G22: 0 | H22: 0 | I22: 0 | J22: 0 | K22: 0 | L22: 0 | M22: 0
C23: TOTAL DELIVERY UNITS | D23: =SUM(D17:D22) | E23: =SUM(E17:E22) | F23: =SUM(F17:F22) | G23: =SUM(G17:G22) | H23: =SUM(H17:H22) | I23: =SUM(I17:I22) | J23: =SUM(J17:J22) | K23: =SUM(K17:K22) | ... M23: =SUM(M17:M22)
A25: C. AGILE SHARE BY YEAR (auto) — read by the Logic Tree
B26: # | C26: Value stream | D26: Year 1 | E26: Year 2 | F26: Year 3 | G26: Year 4 | H26: Year 5
B27: 1 | C27: =C6 | D27: =IF($C27="",0,MAX(0,MIN(4,4-$H6+1))/4) | E27: =IF($C27="",0,MAX(0,MIN(4,8-$H6+1))/4) | F27: =IF($C27="",0,MAX(0,MIN(4,12-$H6+1))/4) | G27: =IF($C27="",0,MAX(0,MIN(4,16-$H6+1))/4) | H27: =IF($C27="",0,MAX(0,MIN(4,20-$H6+1))/4)
B28: 2 | C28: =C7 | D28: =IF($C28="",0,MAX(0,MIN(4,4-$H7+1))/4) | E28: =IF($C28="",0,MAX(0,MIN(4,8-$H7+1))/4) | F28: =IF($C28="",0,MAX(0,MIN(4,12-$H7+1))/4) | G28: =IF($C28="",0,MAX(0,MIN(4,16-$H7+1))/4) | H28: =IF($C28="",0,MAX(0,MIN(4,20-$H7+1))/4)
B29: 3 | C29: =C8 | D29: =IF($C29="",0,MAX(0,MIN(4,4-$H8+1))/4) | E29: =IF($C29="",0,MAX(0,MIN(4,8-$H8+1))/4) | F29: =IF($C29="",0,MAX(0,MIN(4,12-$H8+1))/4) | G29: =IF($C29="",0,MAX(0,MIN(4,16-$H8+1))/4) | H29: =IF($C29="",0,MAX(0,MIN(4,20-$H8+1))/4)
B30: 4 | C30: =C9 | D30: =IF($C30="",0,MAX(0,MIN(4,4-$H9+1))/4) | E30: =IF($C30="",0,MAX(0,MIN(4,8-$H9+1))/4) | F30: =IF($C30="",0,MAX(0,MIN(4,12-$H9+1))/4) | G30: =IF($C30="",0,MAX(0,MIN(4,16-$H9+1))/4) | H30: =IF($C30="",0,MAX(0,MIN(4,20-$H9+1))/4)
B31: 5 | C31: =C10 | D31: =IF($C31="",0,MAX(0,MIN(4,4-$H10+1))/4) | E31: =IF($C31="",0,MAX(0,MIN(4,8-$H10+1))/4) | F31: =IF($C31="",0,MAX(0,MIN(4,12-$H10+1))/4) | G31: =IF($C31="",0,MAX(0,MIN(4,16-$H10+1))/4) | H31: =IF($C31="",0,MAX(0,MIN(4,20-$H10+1))/4)
B32: 6 | C32: =C11 | D32: =IF($C32="",0,MAX(0,MIN(4,4-$H11+1))/4) | E32: =IF($C32="",0,MAX(0,MIN(4,8-$H11+1))/4) | F32: =IF($C32="",0,MAX(0,MIN(4,12-$H11+1))/4) | G32: =IF($C32="",0,MAX(0,MIN(4,16-$H11+1))/4) | H32: =IF($C32="",0,MAX(0,MIN(4,20-$H11+1))/4)
C33: EFFORT-WEIGHTED AGILE SHARE OF THE 領域 | D33: =IF($E$12=0,0,SUMPRODUCT($E$6:$E$11,D27:D32)/$E$12) | E33: =IF($E$12=0,0,SUMPRODUCT($E$6:$E$11,E27:E32)/$E$12) | F33: =IF($E$12=0,0,SUMPRODUCT($E$6:$E$11,F27:F32)/$E$12) | G33: =IF($E$12=0,0,SUMPRODUCT($E$6:$E$11,G27:G32)/$E$12) | H33: =IF($E$12=0,0,SUMPRODUCT($E$6:$E$11,H27:H32)/$E$12)
B34: This row scales the operating-model gate in the Logic Tree. Pod consolidation, a single release train and a wider span of control are only available where the stream actually runs as a pod, so a 領域 that converts late earns less of that gate — correctly.

Sheet Role x Sourcing
A1: Role × sourcing — why the four populations cannot carry the same commitment
A2: The one place a judgement about MetLife's own people is made explicit. Seeded from the observed Year-1 roster across the five 領域 already modelled — 1,102 units of seat plan.
A4: A. AI CEILING BY CLIENT ROLE, ON THIS 領域'S ARCHETYPE MIX (auto)
B5: Archetype | C5: Share of effort | D5: BSA | E5: Developer | F5: Tester | G5: Maintenance | H5: PM | I5: Other
B6: M | C6: ='Logic Tree'!$E$32 | D6: =SUMPRODUCT('Rates & Tables'!$C$17:$H$17,'Rates & Tables'!$C$6:$H$6) | E6: =SUMPRODUCT('Rates & Tables'!$C$18:$H$18,'Rates & Tables'!$C$6:$H$6) | F6: =SUMPRODUCT('Rates & Tables'!$C$19:$H$19,'Rates & Tables'!$C$6:$H$6) | G6: =SUMPRODUCT('Rates & Tables'!$C$20:$H$20,'Rates & Tables'!$C$6:$H$6) | H6: =SUMPRODUCT('Rates & Tables'!$C$21:$H$21,'Rates & Tables'!$C$6:$H$6) | I6: =SUMPRODUCT('Rates & Tables'!$C$22:$H$22,'Rates & Tables'!$C$6:$H$6)
B7: L | C7: ='Logic Tree'!$E$33 | D7: =SUMPRODUCT('Rates & Tables'!$C$17:$H$17,'Rates & Tables'!$C$7:$H$7) | E7: =SUMPRODUCT('Rates & Tables'!$C$18:$H$18,'Rates & Tables'!$C$7:$H$7) | F7: =SUMPRODUCT('Rates & Tables'!$C$19:$H$19,'Rates & Tables'!$C$7:$H$7) | G7: =SUMPRODUCT('Rates & Tables'!$C$20:$H$20,'Rates & Tables'!$C$7:$H$7) | H7: =SUMPRODUCT('Rates & Tables'!$C$21:$H$21,'Rates & Tables'!$C$7:$H$7) | I7: =SUMPRODUCT('Rates & Tables'!$C$22:$H$22,'Rates & Tables'!$C$7:$H$7)
B8: D | C8: ='Logic Tree'!$E$34 | D8: =SUMPRODUCT('Rates & Tables'!$C$17:$H$17,'Rates & Tables'!$C$8:$H$8) | E8: =SUMPRODUCT('Rates & Tables'!$C$18:$H$18,'Rates & Tables'!$C$8:$H$8) | F8: =SUMPRODUCT('Rates & Tables'!$C$19:$H$19,'Rates & Tables'!$C$8:$H$8) | G8: =SUMPRODUCT('Rates & Tables'!$C$20:$H$20,'Rates & Tables'!$C$8:$H$8) | H8: =SUMPRODUCT('Rates & Tables'!$C$21:$H$21,'Rates & Tables'!$C$8:$H$8) | I8: =SUMPRODUCT('Rates & Tables'!$C$22:$H$22,'Rates & Tables'!$C$8:$H$8)
B9: P | C9: ='Logic Tree'!$E$35 | D9: =SUMPRODUCT('Rates & Tables'!$C$17:$H$17,'Rates & Tables'!$C$9:$H$9) | E9: =SUMPRODUCT('Rates & Tables'!$C$18:$H$18,'Rates & Tables'!$C$9:$H$9) | F9: =SUMPRODUCT('Rates & Tables'!$C$19:$H$19,'Rates & Tables'!$C$9:$H$9) | G9: =SUMPRODUCT('Rates & Tables'!$C$20:$H$20,'Rates & Tables'!$C$9:$H$9) | H9: =SUMPRODUCT('Rates & Tables'!$C$21:$H$21,'Rates & Tables'!$C$9:$H$9) | I9: =SUMPRODUCT('Rates & Tables'!$C$22:$H$22,'Rates & Tables'!$C$9:$H$9)
B10: J | C10: ='Logic Tree'!$E$36 | D10: =SUMPRODUCT('Rates & Tables'!$C$17:$H$17,'Rates & Tables'!$C$10:$H$10) | E10: =SUMPRODUCT('Rates & Tables'!$C$18:$H$18,'Rates & Tables'!$C$10:$H$10) | F10: =SUMPRODUCT('Rates & Tables'!$C$19:$H$19,'Rates & Tables'!$C$10:$H$10) | G10: =SUMPRODUCT('Rates & Tables'!$C$20:$H$20,'Rates & Tables'!$C$10:$H$10) | H10: =SUMPRODUCT('Rates & Tables'!$C$21:$H$21,'Rates & Tables'!$C$10:$H$10) | I10: =SUMPRODUCT('Rates & Tables'!$C$22:$H$22,'Rates & Tables'!$C$10:$H$10)
B11: T | C11: ='Logic Tree'!$E$37 | D11: =SUMPRODUCT('Rates & Tables'!$C$17:$H$17,'Rates & Tables'!$C$11:$H$11) | E11: =SUMPRODUCT('Rates & Tables'!$C$18:$H$18,'Rates & Tables'!$C$11:$H$11) | F11: =SUMPRODUCT('Rates & Tables'!$C$19:$H$19,'Rates & Tables'!$C$11:$H$11) | G11: =SUMPRODUCT('Rates & Tables'!$C$20:$H$20,'Rates & Tables'!$C$11:$H$11) | H11: =SUMPRODUCT('Rates & Tables'!$C$21:$H$21,'Rates & Tables'!$C$11:$H$11) | I11: =SUMPRODUCT('Rates & Tables'!$C$22:$H$22,'Rates & Tables'!$C$11:$H$11)
B12: AI CEILING FOR THIS ROLE | D12: =SUMPRODUCT($C$6:$C$11,D6:D11) | E12: =SUMPRODUCT($C$6:$C$11,E6:E11) | F12: =SUMPRODUCT($C$6:$C$11,F6:F11) | G12: =SUMPRODUCT($C$6:$C$11,G6:G11) | H12: =SUMPRODUCT($C$6:$C$11,H6:H11) | I12: =SUMPRODUCT($C$6:$C$11,I6:I11) | L12: Each role's time distribution run through each archetype's phase ceilings, weighted by how much of this 領域 each archetype is. On a mainframe-heavy 領域 every number here falls; on a cloud 領域 every number rises. Tester is always the highest and PM always the lowest.
A14: B. HOW EACH POOL'S HEADCOUNT SPLITS ACROSS THE SIX ROLES — INPUT
B15: Sourcing pool | D15: BSA | E15: Developer | F15: Tester | G15: Maintenance | H15: PM | I15: Other | J15: Check
B16: FTC | D16: 0.108253 | E16: 0.331456 | F16: 0.176442 | G16: 0.23342 | H16: 0.080962 | I16: 0.06945 | J16: =SUM(D16:I16) | L16: Capgemini payroll. Broad, because we carry the delivery.
B17: PT | D17: 0.0476 | E17: 0.6882 | F17: 0.1291 | G17: 0.1348 | H17: 0.0004 | I17: 0 | J17: =SUM(D17:I17) | L17: Sub-contractor. Overwhelmingly developers with a maintenance tail.
B18: FTE | D18: 0.4082 | E18: 0 | F18: 0.0102 | G18: 0.1827 | H18: 0.3886 | I18: 0.0102 | J18: =SUM(D18:I18) | L18: MetLife Japan. 41% BSA and 39% PM — this is a governance population, not a build one.
B19: MGCC | D19: 0 | E19: 0.7407 | F19: 0.2593 | G19: 0 | H19: 0 | I19: 0 | J19: =SUM(D19:I19) | L19: MGCC. 74% developers, 26% testers, nothing else.
B20: EACH ROW MUST SUM TO 100%. These are shares of that pool's own headcount, not of the 領域. Change them only where you know your 領域 differs from the portfolio pattern, and write down why — this matrix is the entire reason the four populations end up with different productivity commitments, and MetLife will ask about it.
A22: C. THE RESULTING YEAR-1 HEADCOUNT MATRIX (auto)
B23: Sourcing pool | C23: Year-1 population | D23: BSA | E23: Developer | F23: Tester | G23: Maintenance | H23: PM | I23: Other | J23: Total
B24: FTC | C24: ='Logic Tree'!$C$63 | D24: =$C24*D16 | E24: =$C24*E16 | F24: =$C24*F16 | G24: =$C24*G16 | H24: =$C24*H16 | I24: =$C24*I16 | J24: =SUM(D24:I24)
B25: PT | C25: ='Logic Tree'!$C$64 | D25: =$C25*D17 | E25: =$C25*E17 | F25: =$C25*F17 | G25: =$C25*G17 | H25: =$C25*H17 | I25: =$C25*I17 | J25: =SUM(D25:I25)
B26: FTE | C26: ='Logic Tree'!$C$65 | D26: =$C26*D18 | E26: =$C26*E18 | F26: =$C26*F18 | G26: =$C26*G18 | H26: =$C26*H18 | I26: =$C26*I18 | J26: =SUM(D26:I26)
B27: MGCC | C27: ='Logic Tree'!$C$66 | D27: =$C27*D19 | E27: =$C27*E19 | F27: =$C27*F19 | G27: =$C27*G19 | H27: =$C27*H19 | I27: =$C27*I19 | J27: =SUM(D27:I27)
B28: Vendor rows only (FTC + PT) | D28: =D24+D25 | E28: =E24+E25 | F28: =F24+F25 | G28: =G24+G25 | H28: =H24+H25 | I28: =I24+I25 | J28: =SUM(D28:I28)
B29: Appendix 3 v5, restated — the vendor role line | D29: ='Logic Tree'!$D$20 | E29: ='Logic Tree'!$D$21 | F29: ='Logic Tree'!$D$22 | G29: ='Logic Tree'!$D$23 | H29: ='Logic Tree'!$D$24 | I29: ='Logic Tree'!$D$25 | J29: =SUM(D29:I29)
B30: Variance | D30: =D28-D29 | E30: =E28-E29 | F30: =F28-F29 | G30: =G28-G29 | H30: =H28-H29 | I30: =I28-I29 | J30: =D30+E30+F30+G30+H30+I30
B31: Largest single role variance | C31: =MAX(ABS(D30),ABS(E30),ABS(F30),ABS(G30),ABS(H30),ABS(I30))
B32: Row 30 is the honest check on row 16. Appendix 3 tells us the vendor role line but not how it splits between Capgemini and a sub-contractor, and it tells us nothing at all about how MetLife's own people or MGCC are deployed. If row 31 is large, the FTC or PT row above is wrong for your 領域 — tune it until the vendor side reconciles, then leave the MetLife rows alone unless you have evidence.
A34: D. THE PER-SOURCING AI CEILING (auto) — read by the Logic Tree
B35: This is the output of everything above: each pool's own role mix run through each role's own ceiling. It is what makes MGCC a high-ceiling population and MetLife Japan a low-ceiling one — not an opinion about the people, but an observation about the work they do.
B39: Sourcing pool | C39: Dominant roles | D39: AI CEILING | E39: Adoption | F39: Ceiling × adoption | L39: Reading
B40: FTC | C40: =INDEX($D$15:$I$15,MATCH(MAX(D16:I16),D16:I16,0))&" "&TEXT(MAX(D16:I16),"0%") | D40: =SUMPRODUCT($D$12:$I$12,D16:I16) | E40: ='Rates & Tables'!$C$36 | F40: =D40*E40 | L40: Column D is capability — what the work would support. Column E is authority — how much of it that population can actually commit to. Column F is the product, and it is the number that decides how much of the productivity promise sits on Capgemini's side of the contract.
B41: PT | C41: =INDEX($D$15:$I$15,MATCH(MAX(D17:I17),D17:I17,0))&" "&TEXT(MAX(D17:I17),"0%") | D41: =SUMPRODUCT($D$12:$I$12,D17:I17) | E41: ='Rates & Tables'!$C$37 | F41: =D41*E41
B42: FTE | C42: =INDEX($D$15:$I$15,MATCH(MAX(D18:I18),D18:I18,0))&" "&TEXT(MAX(D18:I18),"0%") | D42: =SUMPRODUCT($D$12:$I$12,D18:I18) | E42: ='Rates & Tables'!$C$38 | F42: =D42*E42
B43: MGCC | C43: =INDEX($D$15:$I$15,MATCH(MAX(D19:I19),D19:I19,0))&" "&TEXT(MAX(D19:I19),"0%") | D43: =SUMPRODUCT($D$12:$I$12,D19:I19) | E43: ='Rates & Tables'!$C$39 | F43: =D43*E43

Sheet AMS & Ticket Load
A1: AMS and ticket load (auto) — and the one contradiction to put back to MetLife
A2: Incident and change volumes from Appendix 3 v5, against the maintenance role line and against MetLife's own AD / AMS effort split. In several 領域 the two disagree by a factor of three.
A4: A. THE LOAD (auto)
B5: Measure | C5: Volume | D5: Per application | G5: Note
B6: P1 — critical incidents | C6: =SUMIFS('Inventory v5'!$AE$5:$AE$146,'Inventory v5'!$D$5:$D$146,'START HERE'!$C$5) | D6: =IF('Logic Tree'!$C$6=0,0,C6/'Logic Tree'!$C$6) | G6: Outage-class. A 領域 with P1s needs a named onshore first responder.
B7: P2 — high | C7: =SUMIFS('Inventory v5'!$AF$5:$AF$146,'Inventory v5'!$D$5:$D$146,'START HERE'!$C$5) | D7: =IF('Logic Tree'!$C$6=0,0,C7/'Logic Tree'!$C$6) | G7: Business-impacting.
B8: P3 — medium | C8: =SUMIFS('Inventory v5'!$AG$5:$AG$146,'Inventory v5'!$D$5:$D$146,'START HERE'!$C$5) | D8: =IF('Logic Tree'!$C$6=0,0,C8/'Logic Tree'!$C$6) | G8: The bulk of the analyst load in most 領域.
B9: P4 — low | C9: =SUMIFS('Inventory v5'!$AH$5:$AH$146,'Inventory v5'!$D$5:$D$146,'START HERE'!$C$5) | D9: =IF('Logic Tree'!$C$6=0,0,C9/'Logic Tree'!$C$6)
B10: P5 — cosmetic / request | C10: =SUMIFS('Inventory v5'!$AI$5:$AI$146,'Inventory v5'!$D$5:$D$146,'START HERE'!$C$5) | D10: =IF('Logic Tree'!$C$6=0,0,C10/'Logic Tree'!$C$6) | G10: Often the largest volume and the cheapest to automate away.
B12: Emergency changes | C12: =SUMIFS('Inventory v5'!$AJ$5:$AJ$146,'Inventory v5'!$D$5:$D$146,'START HERE'!$C$5) | D12: =IF('Logic Tree'!$C$6=0,0,C12/'Logic Tree'!$C$6) | G12: Unplanned production change. High volume here signals brittle release practice.
B13: Normal changes | C13: =SUMIFS('Inventory v5'!$AK$5:$AK$146,'Inventory v5'!$D$5:$D$146,'START HERE'!$C$5) | D13: =IF('Logic Tree'!$C$6=0,0,C13/'Logic Tree'!$C$6)
B14: Standard changes | C14: =SUMIFS('Inventory v5'!$AL$5:$AL$146,'Inventory v5'!$D$5:$D$146,'START HERE'!$C$5) | D14: =IF('Logic Tree'!$C$6=0,0,C14/'Logic Tree'!$C$6) | G14: Pre-approved and repeatable — the natural first target for automation.
B16: TOTAL INCIDENTS | C16: =SUM(C6:C10)
B17: TOTAL CHANGES | C17: =SUM(C12:C14)
B18: P1 + P2 as a share of incidents | C18: =IF(C16=0,0,(C6+C7)/C16) | G18: Below 1% and the estate is stable; the AMS case is about volume, not severity. Above 5% and you need an onshore incident cell whatever the offshore ceiling says.
A20: B. WHAT IT TAKES TO SERVE IT — INPUT
B21: Driver | C21: Value | G21: Note
B22: Average handling time — incident (hours) | C22: 3.5 | G22: Across the five 領域 modelled. Weight it up on a mainframe estate and down on a cloud one.
B23: Average handling time — change (hours) | C23: 5 | G23: Build, test and release of a small change.
B24: Productive hours per analyst per year | C24: 1500 | G24: 1,800 gross less leave, training and ceremony. Deliberately conservative.
B25: Share of the load carried by the horizontal AMS function | C25: 0.7 | G25: The rest sits inside the pods, which is where shift-left actually happens.
B26: IMPLIED AMS PEOPLE | C26: =IF(C24=0,0,(C16*C22+C17*C23)/C24) | G26: A SANITY CHECK, NOT A TARGET. It exists so that a maintenance line of one person against a thousand incidents is visibly impossible rather than quietly accepted.
B27: — of which in the horizontal function (H1) | C27: =C26*C25
A29: C. THE TWO METLIFE VIEWS OF RUN — and they disagree (auto)
B30: View | C30: Units of run | G30: Where it comes from
B31: The role line — Maintenance, as restated | C31: ='Logic Tree'!$D$23 | G31: Logic Tree section B. This is the figure the seat plan reconciles to.
B32: The AD / AMS effort split — 1 − % of PRJ | C32: ='Logic Tree'!$C$7-SUMPRODUCT(('Inventory v5'!$D$5:$D$146='START HERE'!$C$5)*'Inventory v5'!$J$5:$J$146*'Inventory v5'!$W$5:$W$146) | G32: Appendix 3's own '% of PRJ' column, applied application by application. Same spreadsheet, different answer.
B33: THE GAP | C33: =C32-C31 | G33: PUT THIS BACK TO METLIFE BEFORE THE AMS PRICE IS FIXED. It is not a modelling choice — it is a contradiction inside the client's own data, and whichever way it resolves it moves the run-side commercial position.

Sheet Seat Planner
A1: Seat planner — the delivery anatomy, and the only sheet you build by hand
A2: One row per seat per unit type per year. Columns L to P are computed. COMPOSITION RULES, applied in this version: every seat has a unique Role detail inside its unit-year block; a grade is fixed for the life of a seat (no seat is re-banded across years); a move between Tokyo and offshore is shown in the seat name, never silently in the Loc column; and the people arriving from the Year-3 transfer sit in their own named seats so the base seats taper monotonically.
B4: Year | C4: Unit | D4: Stream | E4: Seat | F4: Role detail | G4: Role | H4: Exp | I4: Loc | J4: Sourcing | K4: Seats per unit | L4: Units | M4: HEADS | N4: Cost index | O4: Cost | P4: Key
B5: 1 | C5: POD | D5: 1 | E5: 1 | F5: MetLife Product Owner | G5: PM | H5: E4 | I5: ON | J5: FTE | K5: 1 | L5: =IF($B5="",0,IF($C5="HZ",1,IFERROR(INDEX('Value Streams & Delivery Mode'!$D$17:$M$22,MATCH($D5,'Value Streams & Delivery Mode'!$B$17:$B$22,0),($B5-1)*2+IF($C5="POD",1,2)),0))) | M5: =IF($B5="",0,$K5*$L5) | N5: =IF($B5="",0,IFERROR(INDEX('Rates & Tables'!$C$61:$G$63,MATCH($I5,'Rates & Tables'!$J$61:$J$63,0),MATCH($H5,'Rates & Tables'!$C$60:$G$60,0)),0)) | O5: =IF($B5="",0,$M5*$N5) | P5: =IF($B5="","",$B5&"|"&$G5&"|"&$J5)
B6: 1 | C6: POD | D6: 1 | E6: 2 | F6: MetLife Group Policy SME | G6: BSA | H6: E4 | I6: ON | J6: FTE | K6: 1 | L6: =IF($B6="",0,IF($C6="HZ",1,IFERROR(INDEX('Value Streams & Delivery Mode'!$D$17:$M$22,MATCH($D6,'Value Streams & Delivery Mode'!$B$17:$B$22,0),($B6-1)*2+IF($C6="POD",1,2)),0))) | M6: =IF($B6="",0,$K6*$L6) | N6: =IF($B6="",0,IFERROR(INDEX('Rates & Tables'!$C$61:$G$63,MATCH($I6,'Rates & Tables'!$J$61:$J$63,0),MATCH($H6,'Rates & Tables'!$C$60:$G$60,0)),0)) | O6: =IF($B6="",0,$M6*$N6) | P6: =IF($B6="","",$B6&"|"&$G6&"|"&$J6)
B7: 1 | C7: POD | D7: 1 | E7: 3 | F7: FSI Senior Developer (JP) | G7: DEV | H7: E3 | I7: ON | J7: PT | K7: 2 | L7: =IF($B7="",0,IF($C7="HZ",1,IFERROR(INDEX('Value Streams & Delivery Mode'!$D$17:$M$22,MATCH($D7,'Value Streams & Delivery Mode'!$B$17:$B$22,0),($B7-1)*2+IF($C7="POD",1,2)),0))) | M7: =IF($B7="",0,$K7*$L7) | N7: =IF($B7="",0,IFERROR(INDEX('Rates & Tables'!$C$61:$G$63,MATCH($I7,'Rates & Tables'!$J$61:$J$63,0),MATCH($H7,'Rates & Tables'!$C$60:$G$60,0)),0)) | O7: =IF($B7="",0,$M7*$N7) | P7: =IF($B7="","",$B7&"|"&$G7&"|"&$J7)
B8: 1 | C8: POD | D8: 1 | E8: 4 | F8: FSI Application Support | G8: MNT | H8: E2 | I8: ON | J8: PT | K8: 1 | L8: =IF($B8="",0,IF($C8="HZ",1,IFERROR(INDEX('Value Streams & Delivery Mode'!$D$17:$M$22,MATCH($D8,'Value Streams & Delivery Mode'!$B$17:$B$22,0),($B8-1)*2+IF($C8="POD",1,2)),0))) | M8: =IF($B8="",0,$K8*$L8) | N8: =IF($B8="",0,IFERROR(INDEX('Rates & Tables'!$C$61:$G$63,MATCH($I8,'Rates & Tables'!$J$61:$J$63,0),MATCH($H8,'Rates & Tables'!$C$60:$G$60,0)),0)) | O8: =IF($B8="",0,$M8*$N8) | P8: =IF($B8="","",$B8&"|"&$G8&"|"&$J8)
B9: 1 | C9: POD | D9: 1 | E9: 5 | F9: Pod lead / senior engineer | G9: DEV | H9: E3 | I9: ON | J9: FTC | K9: 1 | L9: =IF($B9="",0,IF($C9="HZ",1,IFERROR(INDEX('Value Streams & Delivery Mode'!$D$17:$M$22,MATCH($D9,'Value Streams & Delivery Mode'!$B$17:$B$22,0),($B9-1)*2+IF($C9="POD",1,2)),0))) | M9: =IF($B9="",0,$K9*$L9) | N9: =IF($B9="",0,IFERROR(INDEX('Rates & Tables'!$C$61:$G$63,MATCH($I9,'Rates & Tables'!$J$61:$J$63,0),MATCH($H9,'Rates & Tables'!$C$60:$G$60,0)),0)) | O9: =IF($B9="",0,$M9*$N9) | P9: =IF($B9="","",$B9&"|"&$G9&"|"&$J9)
B10: 1 | C10: POD | D10: 1 | E10: 6 | F10: Business Analyst (bilingual) | G10: BSA | H10: E2 | I10: ON | J10: FTC | K10: 0.5 | L10: =IF($B10="",0,IF($C10="HZ",1,IFERROR(INDEX('Value Streams & Delivery Mode'!$D$17:$M$22,MATCH($D10,'Value Streams & Delivery Mode'!$B$17:$B$22,0),($B10-1)*2+IF($C10="POD",1,2)),0))) | M10: =IF($B10="",0,$K10*$L10) | N10: =IF($B10="",0,IFERROR(INDEX('Rates & Tables'!$C$61:$G$63,MATCH($I10,'Rates & Tables'!$J$61:$J$63,0),MATCH($H10,'Rates & Tables'!$C$60:$G$60,0)),0)) | O10: =IF($B10="",0,$M10*$N10) | P10: =IF($B10="","",$B10&"|"&$G10&"|"&$J10)
B11: 1 | C11: POD | D11: 1 | E11: 7 | F11: Java Developer | G11: DEV | H11: E2 | I11: OFF | J11: FTC | K11: 0.5 | L11: =IF($B11="",0,IF($C11="HZ",1,IFERROR(INDEX('Value Streams & Delivery Mode'!$D$17:$M$22,MATCH($D11,'Value Streams & Delivery Mode'!$B$17:$B$22,0),($B11-1)*2+IF($C11="POD",1,2)),0))) | M11: =IF($B11="",0,$K11*$L11) | N11: =IF($B11="",0,IFERROR(INDEX('Rates & Tables'!$C$61:$G$63,MATCH($I11,'Rates & Tables'!$J$61:$J$63,0),MATCH($H11,'Rates & Tables'!$C$60:$G$60,0)),0)) | O11: =IF($B11="",0,$M11*$N11) | P11: =IF($B11="","",$B11&"|"&$G11&"|"&$J11)
B12: 1 | C12: POD | D12: 1 | E12: 8 | F12: Quality Engineer (SDET) | G12: TEST | H12: E3 | I12: ON | J12: FTC | K12: 1 | L12: =IF($B12="",0,IF($C12="HZ",1,IFERROR(INDEX('Value Streams & Delivery Mode'!$D$17:$M$22,MATCH($D12,'Value Streams & Delivery Mode'!$B$17:$B$22,0),($B12-1)*2+IF($C12="POD",1,2)),0))) | M12: =IF($B12="",0,$K12*$L12) | N12: =IF($B12="",0,IFERROR(INDEX('Rates & Tables'!$C$61:$G$63,MATCH($I12,'Rates & Tables'!$J$61:$J$63,0),MATCH($H12,'Rates & Tables'!$C$60:$G$60,0)),0)) | O12: =IF($B12="",0,$M12*$N12) | P12: =IF($B12="","",$B12&"|"&$G12&"|"&$J12)
B13: 1 | C13: POD | D13: 1 | E13: 9 | F13: Junior Application Support — offshore | G13: MNT | H13: E1 | I13: OFF | J13: FTC | K13: 0.5 | L13: =IF($B13="",0,IF($C13="HZ",1,IFERROR(INDEX('Value Streams & Delivery Mode'!$D$17:$M$22,MATCH($D13,'Value Streams & Delivery Mode'!$B$17:$B$22,0),($B13-1)*2+IF($C13="POD",1,2)),0))) | M13: =IF($B13="",0,$K13*$L13) | N13: =IF($B13="",0,IFERROR(INDEX('Rates & Tables'!$C$61:$G$63,MATCH($I13,'Rates & Tables'!$J$61:$J$63,0),MATCH($H13,'Rates & Tables'!$C$60:$G$60,0)),0)) | O13: =IF($B13="",0,$M13*$N13) | P13: =IF($B13="","",$B13&"|"&$G13&"|"&$J13)
B14: 1 | C14: TEAM | D14: 2 | E14: 1 | F14: MetLife Product Owner | G14: PM | H14: E4 | I14: ON | J14: FTE | K14: 1 | L14: =IF($B14="",0,IF($C14="HZ",1,IFERROR(INDEX('Value Streams & Delivery Mode'!$D$17:$M$22,MATCH($D14,'Value Streams & Delivery Mode'!$B$17:$B$22,0),($B14-1)*2+IF($C14="POD",1,2)),0))) | M14: =IF($B14="",0,$K14*$L14) | N14: =IF($B14="",0,IFERROR(INDEX('Rates & Tables'!$C$61:$G$63,MATCH($I14,'Rates & Tables'!$J$61:$J$63,0),MATCH($H14,'Rates & Tables'!$C$60:$G$60,0)),0)) | O14: =IF($B14="",0,$M14*$N14) | P14: =IF($B14="","",$B14&"|"&$G14&"|"&$J14)
B15: 1 | C15: TEAM | D15: 2 | E15: 2 | F15: MetLife Compliance SME | G15: BSA | H15: E4 | I15: ON | J15: FTE | K15: 1 | L15: =IF($B15="",0,IF($C15="HZ",1,IFERROR(INDEX('Value Streams & Delivery Mode'!$D$17:$M$22,MATCH($D15,'Value Streams & Delivery Mode'!$B$17:$B$22,0),($B15-1)*2+IF($C15="POD",1,2)),0))) | M15: =IF($B15="",0,$K15*$L15) | N15: =IF($B15="",0,IFERROR(INDEX('Rates & Tables'!$C$61:$G$63,MATCH($I15,'Rates & Tables'!$J$61:$J$63,0),MATCH($H15,'Rates & Tables'!$C$60:$G$60,0)),0)) | O15: =IF($B15="",0,$M15*$N15) | P15: =IF($B15="","",$B15&"|"&$G15&"|"&$J15)
B16: 1 | C16: TEAM | D16: 2 | E16: 3 | F16: MetLife Operations Analyst | G16: MNT | H16: E3 | I16: ON | J16: FTE | K16: 0.5 | L16: =IF($B16="",0,IF($C16="HZ",1,IFERROR(INDEX('Value Streams & Delivery Mode'!$D$17:$M$22,MATCH($D16,'Value Streams & Delivery Mode'!$B$17:$B$22,0),($B16-1)*2+IF($C16="POD",1,2)),0))) | M16: =IF($B16="",0,$K16*$L16) | N16: =IF($B16="",0,IFERROR(INDEX('Rates & Tables'!$C$61:$G$63,MATCH($I16,'Rates & Tables'!$J$61:$J$63,0),MATCH($H16,'Rates & Tables'!$C$60:$G$60,0)),0)) | O16: =IF($B16="",0,$M16*$N16) | P16: =IF($B16="","",$B16&"|"&$G16&"|"&$J16)
... B35: 1 | C35: TEAM | D35: 3 | E35: 10 | F35: Batch Monitoring Engineer | G35: MNT | H35: E1 | I35: ON | J35: FTC | K35: 1 | L35: =IF($B35="",0,IF($C35="HZ",1,IFERROR(INDEX('Value Streams & Delivery Mode'!$D$17:$M$22,MATCH($D35,'Value Streams & Delivery Mode'!$B$17:$B$22,0),($B35-1)*2+IF($C35="POD",1,2)),0))) | M35: =IF($B35="",0,$K35*$L35) | N35: =IF($B35="",0,IFERROR(INDEX('Rates & Tables'!$C$61:$G$63,MATCH($I35,'Rates & Tables'!$J$61:$J$63,0),MATCH($H35,'Rates & Tables'!$C$60:$G$60,0)),0)) | O35: =IF($B35="",0,$M35*$N35) | P35: =IF($B35="","",$B35&"|"&$G35&"|"&$J35)
B36: 1 | C36: HZ | D36: H3 | E36: 1 | F36: Domain Service Manager | G36: PM | H36: E5 | I36: ON | J36: FTC | K36: 1 | L36: =IF($B36="",0,IF($C36="HZ",1,IFERROR(INDEX('Value Streams & Delivery Mode'!$D$17:$M$22,MATCH($D36,'Value Streams & Delivery Mode'!$B$17:$B$22,0),($B36-1)*2+IF($C36="POD",1,2)),0))) | M36: =IF($B36="",0,$K36*$L36) | N36: =IF($B36="",0,IFERROR(INDEX('Rates & Tables'!$C$61:$G$63,MATCH($I36,'Rates & Tables'!$J$61:$J$63,0),MATCH($H36,'Rates & Tables'!$C$60:$G$60,0)),0)) | O36: =IF($B36="",0,$M36*$N36) | P36: =IF($B36="","",$B36&"|"&$G36&"|"&$J36)
B37: 1 | C37: HZ | D37: H3 | E37: 2 | F37: Delivery / Project Manager | G37: PM | H37: E3 | I37: ON | J37: FTC | K37: 1.5 | L37: =IF($B37="",0,IF($C37="HZ",1,IFERROR(INDEX('Value Streams & Delivery Mode'!$D$17:$M$22,MATCH($D37,'Value Streams & Delivery Mode'!$B$17:$B$22,0),($B37-1)*2+IF($C37="POD",1,2)),0))) | M37: =IF($B37="",0,$K37*$L37) | N37: =IF($B37="",0,IFERROR(INDEX('Rates & Tables'!$C$61:$G$63,MATCH($I37,'Rates & Tables'!$J$61:$J$63,0),MATCH($H37,'Rates & Tables'!$C$60:$G$60,0)),0)) | O37: =IF($B37="",0,$M37*$N37) | P37: =IF($B37="","",$B37&"|"&$G37&"|"&$J37)
B38: 1 | C38: HZ | D38: H3 | E38: 3 | F38: Lead BSA (bilingual) | G38: BSA | H38: E4 | I38: ON | J38: FTC | K38: 1 | L38: =IF($B38="",0,IF($C38="HZ",1,IFERROR(INDEX('Value Streams & Delivery Mode'!$D$17:$M$22,MATCH($D38,'Value Streams & Delivery Mode'!$B$17:$B$22,0),($B38-1)*2+IF($C38="POD",1,2)),0))) | M38: =IF($B38="",0,$K38*$L38) | N38: =IF($B38="",0,IFERROR(INDEX('Rates & Tables'!$C$61:$G$63,MATCH($I38,'Rates & Tables'!$J$61:$J$63,0),MATCH($H38,'Rates & Tables'!$C$60:$G$60,0)),0)) | O38: =IF($B38="",0,$M38*$N38) | P38: =IF($B38="","",$B38&"|"&$G38&"|"&$J38)
B39: 1 | C39: HZ | D39: H3 | E39: 4 | F39: Solution Architect | G39: OTH | H39: E4 | I39: ON | J39: FTC | K39: 1 | L39: =IF($B39="",0,IF($C39="HZ",1,IFERROR(INDEX('Value Streams & Delivery Mode'!$D$17:$M$22,MATCH($D39,'Value Streams & Delivery Mode'!$B$17:$B$22,0),($B39-1)*2+IF($C39="POD",1,2)),0))) | M39: =IF($B39="",0,$K39*$L39) | N39: =IF($B39="",0,IFERROR(INDEX('Rates & Tables'!$C$61:$G$63,MATCH($I39,'Rates & Tables'!$J$61:$J$63,0),MATCH($H39,'Rates & Tables'!$C$60:$G$60,0)),0)) | O39: =IF($B39="",0,$M39*$N39) | P39: =IF($B39="","",$B39&"|"&$G39&"|"&$J39)
B40: 1 | C40: HZ | D40: H3 | E40: 5 | F40: Release / DevOps engineer | G40: OTH | H40: E2 | I40: ON | J40: FTC | K40: 1.5 | L40: =IF($B40="",0,IF($C40="HZ",1,IFERROR(INDEX('Value Streams & Delivery Mode'!$D$17:$M$22,MATCH($D40,'Value Streams & Delivery Mode'!$B$17:$B$22,0),($B40-1)*2+IF($C40="POD",1,2)),0))) | M40: =IF($B40="",0,$K40*$L40) | N40: =IF($B40="",0,IFERROR(INDEX('Rates & Tables'!$C$61:$G$63,MATCH($I40,'Rates & Tables'!$J$61:$J$63,0),MATCH($H40,'Rates & Tables'!$C$60:$G$60,0)),0)) | O40: =IF($B40="",0,$M40*$N40) | P40: =IF($B40="","",$B40&"|"&$G40&"|"&$J40)
B41: 1 | C41: HZ | D41: H3 | E41: 6 | F41: MetLife Regulatory Liaison | G41: BSA | H41: E4 | I41: ON | J41: FTE | K41: 1.5 | L41: =IF($B41="",0,IF($C41="HZ",1,IFERROR(INDEX('Value Streams & Delivery Mode'!$D$17:$M$22,MATCH($D41,'Value Streams & Delivery Mode'!$B$17:$B$22,0),($B41-1)*2+IF($C41="POD",1,2)),0))) | M41: =IF($B41="",0,$K41*$L41) | N41: =IF($B41="",0,IFERROR(INDEX('Rates & Tables'!$C$61:$G$63,MATCH($I41,'Rates & Tables'!$J$61:$J$63,0),MATCH($H41,'Rates & Tables'!$C$60:$G$60,0)),0)) | O41: =IF($B41="",0,$M41*$N41) | P41: =IF($B41="","",$B41&"|"&$G41&"|"&$J41)
B42: 1 | C42: HZ | D42: H3 | E42: 7 | F42: MetLife Domain Architect | G42: OTH | H42: E4 | I42: ON | J42: FTE | K42: 1.5 | L42: =IF($B42="",0,IF($C42="HZ",1,IFERROR(INDEX('Value Streams & Delivery Mode'!$D$17:$M$22,MATCH($D42,'Value Streams & Delivery Mode'!$B$17:$B$22,0),($B42-1)*2+IF($C42="POD",1,2)),0))) | M42: =IF($B42="",0,$K42*$L42) | N42: =IF($B42="",0,IFERROR(INDEX('Rates & Tables'!$C$61:$G$63,MATCH($I42,'Rates & Tables'!$J$61:$J$63,0),MATCH($H42,'Rates & Tables'!$C$60:$G$60,0)),0)) | O42: =IF($B42="",0,$M42*$N42) | P42: =IF($B42="","",$B42&"|"&$G42&"|"&$J42)
B43: 1 | C43: HZ | D43: H1 | E43: 8 | F43: AMS Team Lead | G43: MNT | H43: E3 | I43: ON | J43: FTC | K43: 1 | L43: =IF($B43="",0,IF($C43="HZ",1,IFERROR(INDEX('Value Streams & Delivery Mode'!$D$17:$M$22,MATCH($D43,'Value Streams & Delivery Mode'!$B$17:$B$22,0),($B43-1)*2+IF($C43="POD",1,2)),0))) | M43: =IF($B43="",0,$K43*$L43) | N43: =IF($B43="",0,IFERROR(INDEX('Rates & Tables'!$C$61:$G$63,MATCH($I43,'Rates & Tables'!$J$61:$J$63,0),MATCH($H43,'Rates & Tables'!$C$60:$G$60,0)),0)) | O43: =IF($B43="",0,$M43*$N43) | P43: =IF($B43="","",$B43&"|"&$G43&"|"&$J43)
B44: 1 | C44: HZ | D44: H1 | E44: 9 | F44: L2/L3 Application Support — Tokyo | G44: MNT | H44: E2 | I44: ON | J44: FTC | K44: 0.5 | L44: =IF($B44="",0,IF($C44="HZ",1,IFERROR(INDEX('Value Streams & Delivery Mode'!$D$17:$M$22,MATCH($D44,'Value Streams & Delivery Mode'!$B$17:$B$22,0),($B44-1)*2+IF($C44="POD",1,2)),0))) | M44: =IF($B44="",0,$K44*$L44) | N44: =IF($B44="",0,IFERROR(INDEX('Rates & Tables'!$C$61:$G$63,MATCH($I44,'Rates & Tables'!$J$61:$J$63,0),MATCH($H44,'Rates & Tables'!$C$60:$G$60,0)),0)) | O44: =IF($B44="",0,$M44*$N44) | P44: =IF($B44="","",$B44&"|"&$G44&"|"&$J44)
B45: 1 | C45: HZ | D45: H1 | E45: 10 | F45: Junior Application Support — offshore | G45: MNT | H45: E1 | I45: OFF | J45: FTC | K45: 0.5 | L45: =IF($B45="",0,IF($C45="HZ",1,IFERROR(INDEX('Value Streams & Delivery Mode'!$D$17:$M$22,MATCH($D45,'Value Streams & Delivery Mode'!$B$17:$B$22,0),($B45-1)*2+IF($C45="POD",1,2)),0))) | M45: =IF($B45="",0,$K45*$L45) | N45: =IF($B45="",0,IFERROR(INDEX('Rates & Tables'!$C$61:$G$63,MATCH($I45,'Rates & Tables'!$J$61:$J$63,0),MATCH($H45,'Rates & Tables'!$C$60:$G$60,0)),0)) | O45: =IF($B45="",0,$M45*$N45) | P45: =IF($B45="","",$B45&"|"&$G45&"|"&$J45)
B46: 1 | C46: HZ | D46: H1 | E46: 11 | F46: Batch Monitoring Engineer | G46: MNT | H46: E1 | I46: ON | J46: FTC | K46: 0.5 | L46: =IF($B46="",0,IF($C46="HZ",1,IFERROR(INDEX('Value Streams & Delivery Mode'!$D$17:$M$22,MATCH($D46,'Value Streams & Delivery Mode'!$B$17:$B$22,0),($B46-1)*2+IF($C46="POD",1,2)),0))) | M46: =IF($B46="",0,$K46*$L46) | N46: =IF($B46="",0,IFERROR(INDEX('Rates & Tables'!$C$61:$G$63,MATCH($I46,'Rates & Tables'!$J$61:$J$63,0),MATCH($H46,'Rates & Tables'!$C$60:$G$60,0)),0)) | O46: =IF($B46="",0,$M46*$N46) | P46: =IF($B46="","",$B46&"|"&$G46&"|"&$J46)
B47: 1 | C47: HZ | D47: H1 | E47: 12 | F47: SaaS Administrator | G47: MNT | H47: E2 | I47: ON | J47: FTC | K47: 1 | L47: =IF($B47="",0,IF($C47="HZ",1,IFERROR(INDEX('Value Streams & Delivery Mode'!$D$17:$M$22,MATCH($D47,'Value Streams & Delivery Mode'!$B$17:$B$22,0),($B47-1)*2+IF($C47="POD",1,2)),0))) | M47: =IF($B47="",0,$K47*$L47) | N47: =IF($B47="",0,IFERROR(INDEX('Rates & Tables'!$C$61:$G$63,MATCH($I47,'Rates & Tables'!$J$61:$J$63,0),MATCH($H47,'Rates & Tables'!$C$60:$G$60,0)),0)) | O47: =IF($B47="",0,$M47*$N47) | P47: =IF($B47="","",$B47&"|"&$G47&"|"&$J47)
... B52: 1 | C52: HZ | D52: H2 | E52: 17 | F52: MGCC Test Engineer | G52: TEST | H52: E2 | I52: OFF | J52: MGCC | K52: 0.5 | L52: =IF($B52="",0,IF($C52="HZ",1,IFERROR(INDEX('Value Streams & Delivery Mode'!$D$17:$M$22,MATCH($D52,'Value Streams & Delivery Mode'!$B$17:$B$22,0),($B52-1)*2+IF($C52="POD",1,2)),0))) | M52: =IF($B52="",0,$K52*$L52) | N52: =IF($B52="",0,IFERROR(INDEX('Rates & Tables'!$C$61:$G$63,MATCH($I52,'Rates & Tables'!$J$61:$J$63,0),MATCH($H52,'Rates & Tables'!$C$60:$G$60,0)),0)) | O52: =IF($B52="",0,$M52*$N52) | P52: =IF($B52="","",$B52&"|"&$G52&"|"&$J52)
B53: 2 | C53: POD | D53: 1 | E53: 1 | F53: MetLife Product Owner | G53: PM | H53: E4 | I53: ON | J53: FTE | K53: 1 | L53: =IF($B53="",0,IF($C53="HZ",1,IFERROR(INDEX('Value Streams & Delivery Mode'!$D$17:$M$22,MATCH($D53,'Value Streams & Delivery Mode'!$B$17:$B$22,0),($B53-1)*2+IF($C53="POD",1,2)),0))) | M53: =IF($B53="",0,$K53*$L53) | N53: =IF($B53="",0,IFERROR(INDEX('Rates & Tables'!$C$61:$G$63,MATCH($I53,'Rates & Tables'!$J$61:$J$63,0),MATCH($H53,'Rates & Tables'!$C$60:$G$60,0)),0)) | O53: =IF($B53="",0,$M53*$N53) | P53: =IF($B53="","",$B53&"|"&$G53&"|"&$J53)
B54: 2 | C54: POD | D54: 1 | E54: 2 | F54: MetLife Group Policy SME | G54: BSA | H54: E4 | I54: ON | J54: FTE | K54: 0.5 | L54: =IF($B54="",0,IF($C54="HZ",1,IFERROR(INDEX('Value Streams & Delivery Mode'!$D$17:$M$22,MATCH($D54,'Value Streams & Delivery Mode'!$B$17:$B$22,0),($B54-1)*2+IF($C54="POD",1,2)),0))) | M54: =IF($B54="",0,$K54*$L54) | N54: =IF($B54="",0,IFERROR(INDEX('Rates & Tables'!$C$61:$G$63,MATCH($I54,'Rates & Tables'!$J$61:$J$63,0),MATCH($H54,'Rates & Tables'!$C$60:$G$60,0)),0)) | O54: =IF($B54="",0,$M54*$N54) | P54: =IF($B54="","",$B54&"|"&$G54&"|"&$J54)
B55: 2 | C55: POD | D55: 1 | E55: 3 | F55: FSI Senior Developer (JP) | G55: DEV | H55: E3 | I55: ON | J55: PT | K55: 2 | L55: =IF($B55="",0,IF($C55="HZ",1,IFERROR(INDEX('Value Streams & Delivery Mode'!$D$17:$M$22,MATCH($D55,'Value Streams & Delivery Mode'!$B$17:$B$22,0),($B55-1)*2+IF($C55="POD",1,2)),0))) | M55: =IF($B55="",0,$K55*$L55) | N55: =IF($B55="",0,IFERROR(INDEX('Rates & Tables'!$C$61:$G$63,MATCH($I55,'Rates & Tables'!$J$61:$J$63,0),MATCH($H55,'Rates & Tables'!$C$60:$G$60,0)),0)) | O55: =IF($B55="",0,$M55*$N55) | P55: =IF($B55="","",$B55&"|"&$G55&"|"&$J55)
B56: 2 | C56: POD | D56: 1 | E56: 4 | F56: FSI Application Support | G56: MNT | H56: E2 | I56: ON | J56: PT | K56: 1 | L56: =IF($B56="",0,IF($C56="HZ",1,IFERROR(INDEX('Value Streams & Delivery Mode'!$D$17:$M$22,MATCH($D56,'Value Streams & Delivery Mode'!$B$17:$B$22,0),($B56-1)*2+IF($C56="POD",1,2)),0))) | M56: =IF($B56="",0,$K56*$L56) | N56: =IF($B56="",0,IFERROR(INDEX('Rates & Tables'!$C$61:$G$63,MATCH($I56,'Rates & Tables'!$J$61:$J$63,0),MATCH($H56,'Rates & Tables'!$C$60:$G$60,0)),0)) | O56: =IF($B56="",0,$M56*$N56) | P56: =IF($B56="","",$B56&"|"&$G56&"|"&$J56)
B57: 2 | C57: POD | D57: 1 | E57: 5 | F57: Pod lead / senior engineer | G57: DEV | H57: E3 | I57: ON | J57: FTC | K57: 1 | L57: =IF($B57="",0,IF($C57="HZ",1,IFERROR(INDEX('Value Streams & Delivery Mode'!$D$17:$M$22,MATCH($D57,'Value Streams & Delivery Mode'!$B$17:$B$22,0),($B57-1)*2+IF($C57="POD",1,2)),0))) | M57: =IF($B57="",0,$K57*$L57) | N57: =IF($B57="",0,IFERROR(INDEX('Rates & Tables'!$C$61:$G$63,MATCH($I57,'Rates & Tables'!$J$61:$J$63,0),MATCH($H57,'Rates & Tables'!$C$60:$G$60,0)),0)) | O57: =IF($B57="",0,$M57*$N57) | P57: =IF($B57="","",$B57&"|"&$G57&"|"&$J57)
B58: 2 | C58: POD | D58: 1 | E58: 6 | F58: Business Analyst (bilingual) | G58: BSA | H58: E2 | I58: ON | J58: FTC | K58: 0.5 | L58: =IF($B58="",0,IF($C58="HZ",1,IFERROR(INDEX('Value Streams & Delivery Mode'!$D$17:$M$22,MATCH($D58,'Value Streams & Delivery Mode'!$B$17:$B$22,0),($B58-1)*2+IF($C58="POD",1,2)),0))) | M58: =IF($B58="",0,$K58*$L58) | N58: =IF($B58="",0,IFERROR(INDEX('Rates & Tables'!$C$61:$G$63,MATCH($I58,'Rates & Tables'!$J$61:$J$63,0),MATCH($H58,'Rates & Tables'!$C$60:$G$60,0)),0)) | O58: =IF($B58="",0,$M58*$N58) | P58: =IF($B58="","",$B58&"|"&$G58&"|"&$J58)
B59: 2 | C59: POD | D59: 1 | E59: 7 | F59: Junior Java Developer — offshore | G59: DEV | H59: E2 | I59: OFF | J59: FTC | K59: 1 | L59: =IF($B59="",0,IF($C59="HZ",1,IFERROR(INDEX('Value Streams & Delivery Mode'!$D$17:$M$22,MATCH($D59,'Value Streams & Delivery Mode'!$B$17:$B$22,0),($B59-1)*2+IF($C59="POD",1,2)),0))) | M59: =IF($B59="",0,$K59*$L59) | N59: =IF($B59="",0,IFERROR(INDEX('Rates & Tables'!$C$61:$G$63,MATCH($I59,'Rates & Tables'!$J$61:$J$63,0),MATCH($H59,'Rates & Tables'!$C$60:$G$60,0)),0)) | O59: =IF($B59="",0,$M59*$N59) | P59: =IF($B59="","",$B59&"|"&$G59&"|"&$J59)
B60: 2 | C60: POD | D60: 1 | E60: 8 | F60: Quality Engineer (SDET) — offshore | G60: TEST | H60: E3 | I60: OFF | J60: FTC | K60: 1 | L60: =IF($B60="",0,IF($C60="HZ",1,IFERROR(INDEX('Value Streams & Delivery Mode'!$D$17:$M$22,MATCH($D60,'Value Streams & Delivery Mode'!$B$17:$B$22,0),($B60-1)*2+IF($C60="POD",1,2)),0))) | M60: =IF($B60="",0,$K60*$L60) | N60: =IF($B60="",0,IFERROR(INDEX('Rates & Tables'!$C$61:$G$63,MATCH($I60,'Rates & Tables'!$J$61:$J$63,0),MATCH($H60,'Rates & Tables'!$C$60:$G$60,0)),0)) | O60: =IF($B60="",0,$M60*$N60) | P60: =IF($B60="","",$B60&"|"&$G60&"|"&$J60)
B61: 2 | C61: POD | D61: 1 | E61: 9 | F61: Junior Application Support — offshore | G61: MNT | H61: E1 | I61: OFF | J61: FTC | K61: 0.5 | L61: =IF($B61="",0,IF($C61="HZ",1,IFERROR(INDEX('Value Streams & Delivery Mode'!$D$17:$M$22,MATCH($D61,'Value Streams & Delivery Mode'!$B$17:$B$22,0),($B61-1)*2+IF($C61="POD",1,2)),0))) | M61: =IF($B61="",0,$K61*$L61) | N61: =IF($B61="",0,IFERROR(INDEX('Rates & Tables'!$C$61:$G$63,MATCH($I61,'Rates & Tables'!$J$61:$J$63,0),MATCH($H61,'Rates & Tables'!$C$60:$G$60,0)),0)) | O61: =IF($B61="",0,$M61*$N61) | P61: =IF($B61="","",$B61&"|"&$G61&"|"&$J61)
B62: 2 | C62: POD | D62: 2 | E62: 1 | F62: MetLife Product Owner | G62: PM | H62: E4 | I62: ON | J62: FTE | K62: 1 | L62: =IF($B62="",0,IF($C62="HZ",1,IFERROR(INDEX('Value Streams & Delivery Mode'!$D$17:$M$22,MATCH($D62,'Value Streams & Delivery Mode'!$B$17:$B$22,0),($B62-1)*2+IF($C62="POD",1,2)),0))) | M62: =IF($B62="",0,$K62*$L62) | N62: =IF($B62="",0,IFERROR(INDEX('Rates & Tables'!$C$61:$G$63,MATCH($I62,'Rates & Tables'!$J$61:$J$63,0),MATCH($H62,'Rates & Tables'!$C$60:$G$60,0)),0)) | O62: =IF($B62="",0,$M62*$N62) | P62: =IF($B62="","",$B62&"|"&$G62&"|"&$J62)
B63: 2 | C63: POD | D63: 2 | E63: 2 | F63: MetLife Compliance SME | G63: BSA | H63: E4 | I63: ON | J63: FTE | K63: 0.5 | L63: =IF($B63="",0,IF($C63="HZ",1,IFERROR(INDEX('Value Streams & Delivery Mode'!$D$17:$M$22,MATCH($D63,'Value Streams & Delivery Mode'!$B$17:$B$22,0),($B63-1)*2+IF($C63="POD",1,2)),0))) | M63: =IF($B63="",0,$K63*$L63) | N63: =IF($B63="",0,IFERROR(INDEX('Rates & Tables'!$C$61:$G$63,MATCH($I63,'Rates & Tables'!$J$61:$J$63,0),MATCH($H63,'Rates & Tables'!$C$60:$G$60,0)),0)) | O63: =IF($B63="",0,$M63*$N63) | P63: =IF($B63="","",$B63&"|"&$G63&"|"&$J63)
B64: 2 | C64: POD | D64: 2 | E64: 3 | F64: FSI Senior Developer (JP) | G64: DEV | H64: E3 | I64: ON | J64: PT | K64: 1.5 | L64: =IF($B64="",0,IF($C64="HZ",1,IFERROR(INDEX('Value Streams & Delivery Mode'!$D$17:$M$22,MATCH($D64,'Value Streams & Delivery Mode'!$B$17:$B$22,0),($B64-1)*2+IF($C64="POD",1,2)),0))) | M64: =IF($B64="",0,$K64*$L64) | N64: =IF($B64="",0,IFERROR(INDEX('Rates & Tables'!$C$61:$G$63,MATCH($I64,'Rates & Tables'!$J$61:$J$63,0),MATCH($H64,'Rates & Tables'!$C$60:$G$60,0)),0)) | O64: =IF($B64="",0,$M64*$N64) | P64: =IF($B64="","",$B64&"|"&$G64&"|"&$J64)
... B83: 2 | C83: TEAM | D83: 3 | E83: 12 | F83: L2/L3 Application Support — Tokyo | G83: MNT | H83: E2 | I83: ON | J83: FTC | K83: 0.5 | L83: =IF($B83="",0,IF($C83="HZ",1,IFERROR(INDEX('Value Streams & Delivery Mode'!$D$17:$M$22,MATCH($D83,'Value Streams & Delivery Mode'!$B$17:$B$22,0),($B83-1)*2+IF($C83="POD",1,2)),0))) | M83: =IF($B83="",0,$K83*$L83) | N83: =IF($B83="",0,IFERROR(INDEX('Rates & Tables'!$C$61:$G$63,MATCH($I83,'Rates & Tables'!$J$61:$J$63,0),MATCH($H83,'Rates & Tables'!$C$60:$G$60,0)),0)) | O83: =IF($B83="",0,$M83*$N83) | P83: =IF($B83="","",$B83&"|"&$G83&"|"&$J83)
B84: 2 | C84: HZ | D84: H3 | E84: 1 | F84: Domain Service Manager | G84: PM | H84: E5 | I84: ON | J84: FTC | K84: 1 | L84: =IF($B84="",0,IF($C84="HZ",1,IFERROR(INDEX('Value Streams & Delivery Mode'!$D$17:$M$22,MATCH($D84,'Value Streams & Delivery Mode'!$B$17:$B$22,0),($B84-1)*2+IF($C84="POD",1,2)),0))) | M84: =IF($B84="",0,$K84*$L84) | N84: =IF($B84="",0,IFERROR(INDEX('Rates & Tables'!$C$61:$G$63,MATCH($I84,'Rates & Tables'!$J$61:$J$63,0),MATCH($H84,'Rates & Tables'!$C$60:$G$60,0)),0)) | O84: =IF($B84="",0,$M84*$N84) | P84: =IF($B84="","",$B84&"|"&$G84&"|"&$J84)
B85: 2 | C85: HZ | D85: H3 | E85: 2 | F85: Delivery / Project Manager | G85: PM | H85: E3 | I85: ON | J85: FTC | K85: 0.5 | L85: =IF($B85="",0,IF($C85="HZ",1,IFERROR(INDEX('Value Streams & Delivery Mode'!$D$17:$M$22,MATCH($D85,'Value Streams & Delivery Mode'!$B$17:$B$22,0),($B85-1)*2+IF($C85="POD",1,2)),0))) | M85: =IF($B85="",0,$K85*$L85) | N85: =IF($B85="",0,IFERROR(INDEX('Rates & Tables'!$C$61:$G$63,MATCH($I85,'Rates & Tables'!$J$61:$J$63,0),MATCH($H85,'Rates & Tables'!$C$60:$G$60,0)),0)) | O85: =IF($B85="",0,$M85*$N85) | P85: =IF($B85="","",$B85&"|"&$G85&"|"&$J85)
B86: 2 | C86: HZ | D86: H3 | E86: 3 | F86: Lead BSA (bilingual) | G86: BSA | H86: E4 | I86: ON | J86: FTC | K86: 1 | L86: =IF($B86="",0,IF($C86="HZ",1,IFERROR(INDEX('Value Streams & Delivery Mode'!$D$17:$M$22,MATCH($D86,'Value Streams & Delivery Mode'!$B$17:$B$22,0),($B86-1)*2+IF($C86="POD",1,2)),0))) | M86: =IF($B86="",0,$K86*$L86) | N86: =IF($B86="",0,IFERROR(INDEX('Rates & Tables'!$C$61:$G$63,MATCH($I86,'Rates & Tables'!$J$61:$J$63,0),MATCH($H86,'Rates & Tables'!$C$60:$G$60,0)),0)) | O86: =IF($B86="",0,$M86*$N86) | P86: =IF($B86="","",$B86&"|"&$G86&"|"&$J86)
B87: 2 | C87: HZ | D87: H3 | E87: 4 | F87: Solution Architect | G87: OTH | H87: E4 | I87: ON | J87: FTC | K87: 0.5 | L87: =IF($B87="",0,IF($C87="HZ",1,IFERROR(INDEX('Value Streams & Delivery Mode'!$D$17:$M$22,MATCH($D87,'Value Streams & Delivery Mode'!$B$17:$B$22,0),($B87-1)*2+IF($C87="POD",1,2)),0))) | M87: =IF($B87="",0,$K87*$L87) | N87: =IF($B87="",0,IFERROR(INDEX('Rates & Tables'!$C$61:$G$63,MATCH($I87,'Rates & Tables'!$J$61:$J$63,0),MATCH($H87,'Rates & Tables'!$C$60:$G$60,0)),0)) | O87: =IF($B87="",0,$M87*$N87) | P87: =IF($B87="","",$B87&"|"&$G87&"|"&$J87)
B88: 2 | C88: HZ | D88: H3 | E88: 5 | F88: Release / DevOps engineer | G88: OTH | H88: E2 | I88: ON | J88: FTC | K88: 1 | L88: =IF($B88="",0,IF($C88="HZ",1,IFERROR(INDEX('Value Streams & Delivery Mode'!$D$17:$M$22,MATCH($D88,'Value Streams & Delivery Mode'!$B$17:$B$22,0),($B88-1)*2+IF($C88="POD",1,2)),0))) | M88: =IF($B88="",0,$K88*$L88) | N88: =IF($B88="",0,IFERROR(INDEX('Rates & Tables'!$C$61:$G$63,MATCH($I88,'Rates & Tables'!$J$61:$J$63,0),MATCH($H88,'Rates & Tables'!$C$60:$G$60,0)),0)) | O88: =IF($B88="",0,$M88*$N88) | P88: =IF($B88="","",$B88&"|"&$G88&"|"&$J88)
B89: 2 | C89: HZ | D89: H3 | E89: 6 | F89: MetLife Regulatory Liaison | G89: BSA | H89: E4 | I89: ON | J89: FTE | K89: 1 | L89: =IF($B89="",0,IF($C89="HZ",1,IFERROR(INDEX('Value Streams & Delivery Mode'!$D$17:$M$22,MATCH($D89,'Value Streams & Delivery Mode'!$B$17:$B$22,0),($B89-1)*2+IF($C89="POD",1,2)),0))) | M89: =IF($B89="",0,$K89*$L89) | N89: =IF($B89="",0,IFERROR(INDEX('Rates & Tables'!$C$61:$G$63,MATCH($I89,'Rates & Tables'!$J$61:$J$63,0),MATCH($H89,'Rates & Tables'!$C$60:$G$60,0)),0)) | O89: =IF($B89="",0,$M89*$N89) | P89: =IF($B89="","",$B89&"|"&$G89&"|"&$J89)
B90: 2 | C90: HZ | D90: H3 | E90: 7 | F90: MetLife Domain Architect | G90: OTH | H90: E4 | I90: ON | J90: FTE | K90: 1 | L90: =IF($B90="",0,IF($C90="HZ",1,IFERROR(INDEX('Value Streams & Delivery Mode'!$D$17:$M$22,MATCH($D90,'Value Streams & Delivery Mode'!$B$17:$B$22,0),($B90-1)*2+IF($C90="POD",1,2)),0))) | M90: =IF($B90="",0,$K90*$L90) | N90: =IF($B90="",0,IFERROR(INDEX('Rates & Tables'!$C$61:$G$63,MATCH($I90,'Rates & Tables'!$J$61:$J$63,0),MATCH($H90,'Rates & Tables'!$C$60:$G$60,0)),0)) | O90: =IF($B90="",0,$M90*$N90) | P90: =IF($B90="","",$B90&"|"&$G90&"|"&$J90)
B91: 2 | C91: HZ | D91: H1 | E91: 8 | F91: AMS Team Lead | G91: MNT | H91: E3 | I91: ON | J91: FTC | K91: 1 | L91: =IF($B91="",0,IF($C91="HZ",1,IFERROR(INDEX('Value Streams & Delivery Mode'!$D$17:$M$22,MATCH($D91,'Value Streams & Delivery Mode'!$B$17:$B$22,0),($B91-1)*2+IF($C91="POD",1,2)),0))) | M91: =IF($B91="",0,$K91*$L91) | N91: =IF($B91="",0,IFERROR(INDEX('Rates & Tables'!$C$61:$G$63,MATCH($I91,'Rates & Tables'!$J$61:$J$63,0),MATCH($H91,'Rates & Tables'!$C$60:$G$60,0)),0)) | O91: =IF($B91="",0,$M91*$N91) | P91: =IF($B91="","",$B91&"|"&$G91&"|"&$J91)
B92: 2 | C92: HZ | D92: H1 | E92: 9 | F92: SaaS Administrator | G92: MNT | H92: E2 | I92: ON | J92: FTC | K92: 0.5 | L92: =IF($B92="",0,IF($C92="HZ",1,IFERROR(INDEX('Value Streams & Delivery Mode'!$D$17:$M$22,MATCH($D92,'Value Streams & Delivery Mode'!$B$17:$B$22,0),($B92-1)*2+IF($C92="POD",1,2)),0))) | M92: =IF($B92="",0,$K92*$L92) | N92: =IF($B92="",0,IFERROR(INDEX('Rates & Tables'!$C$61:$G$63,MATCH($I92,'Rates & Tables'!$J$61:$J$63,0),MATCH($H92,'Rates & Tables'!$C$60:$G$60,0)),0)) | O92: =IF($B92="",0,$M92*$N92) | P92: =IF($B92="","",$B92&"|"&$G92&"|"&$J92)
B93: 2 | C93: HZ | D93: H1 | E93: 10 | F93: Junior Application Support — offshore | G93: MNT | H93: E1 | I93: OFF | J93: FTC | K93: 0.5 | L93: =IF($B93="",0,IF($C93="HZ",1,IFERROR(INDEX('Value Streams & Delivery Mode'!$D$17:$M$22,MATCH($D93,'Value Streams & Delivery Mode'!$B$17:$B$22,0),($B93-1)*2+IF($C93="POD",1,2)),0))) | M93: =IF($B93="",0,$K93*$L93) | N93: =IF($B93="",0,IFERROR(INDEX('Rates & Tables'!$C$61:$G$63,MATCH($I93,'Rates & Tables'!$J$61:$J$63,0),MATCH($H93,'Rates & Tables'!$C$60:$G$60,0)),0)) | O93: =IF($B93="",0,$M93*$N93) | P93: =IF($B93="","",$B93&"|"&$G93&"|"&$J93)
B94: 2 | C94: HZ | D94: H1 | E94: 11 | F94: MetLife Operations Analyst | G94: MNT | H94: E3 | I94: ON | J94: FTE | K94: 2 | L94: =IF($B94="",0,IF($C94="HZ",1,IFERROR(INDEX('Value Streams & Delivery Mode'!$D$17:$M$22,MATCH($D94,'Value Streams & Delivery Mode'!$B$17:$B$22,0),($B94-1)*2+IF($C94="POD",1,2)),0))) | M94: =IF($B94="",0,$K94*$L94) | N94: =IF($B94="",0,IFERROR(INDEX('Rates & Tables'!$C$61:$G$63,MATCH($I94,'Rates & Tables'!$J$61:$J$63,0),MATCH($H94,'Rates & Tables'!$C$60:$G$60,0)),0)) | O94: =IF($B94="",0,$M94*$N94) | P94: =IF($B94="","",$B94&"|"&$G94&"|"&$J94)
B95: 2 | C95: HZ | D95: H1 | E95: 12 | F95: MGCC Application Support | G95: MNT | H95: E2 | I95: OFF | J95: MGCC | K95: 0.5 | L95: =IF($B95="",0,IF($C95="HZ",1,IFERROR(INDEX('Value Streams & Delivery Mode'!$D$17:$M$22,MATCH($D95,'Value Streams & Delivery Mode'!$B$17:$B$22,0),($B95-1)*2+IF($C95="POD",1,2)),0))) | M95: =IF($B95="",0,$K95*$L95) | N95: =IF($B95="",0,IFERROR(INDEX('Rates & Tables'!$C$61:$G$63,MATCH($I95,'Rates & Tables'!$J$61:$J$63,0),MATCH($H95,'Rates & Tables'!$C$60:$G$60,0)),0)) | O95: =IF($B95="",0,$M95*$N95) | P95: =IF($B95="","",$B95&"|"&$G95&"|"&$J95)
... B98: 2 | C98: HZ | D98: H2 | E98: 15 | F98: MGCC Test Engineer | G98: TEST | H98: E2 | I98: OFF | J98: MGCC | K98: 0.5 | L98: =IF($B98="",0,IF($C98="HZ",1,IFERROR(INDEX('Value Streams & Delivery Mode'!$D$17:$M$22,MATCH($D98,'Value Streams & Delivery Mode'!$B$17:$B$22,0),($B98-1)*2+IF($C98="POD",1,2)),0))) | M98: =IF($B98="",0,$K98*$L98) | N98: =IF($B98="",0,IFERROR(INDEX('Rates & Tables'!$C$61:$G$63,MATCH($I98,'Rates & Tables'!$J$61:$J$63,0),MATCH($H98,'Rates & Tables'!$C$60:$G$60,0)),0)) | O98: =IF($B98="",0,$M98*$N98) | P98: =IF($B98="","",$B98&"|"&$G98&"|"&$J98)
B99: 3 | C99: POD | D99: 1 | E99: 1 | F99: MetLife Product Owner | G99: PM | H99: E4 | I99: ON | J99: FTE | K99: 1 | L99: =IF($B99="",0,IF($C99="HZ",1,IFERROR(INDEX('Value Streams & Delivery Mode'!$D$17:$M$22,MATCH($D99,'Value Streams & Delivery Mode'!$B$17:$B$22,0),($B99-1)*2+IF($C99="POD",1,2)),0))) | M99: =IF($B99="",0,$K99*$L99) | N99: =IF($B99="",0,IFERROR(INDEX('Rates & Tables'!$C$61:$G$63,MATCH($I99,'Rates & Tables'!$J$61:$J$63,0),MATCH($H99,'Rates & Tables'!$C$60:$G$60,0)),0)) | O99: =IF($B99="",0,$M99*$N99) | P99: =IF($B99="","",$B99&"|"&$G99&"|"&$J99)
B100: 3 | C100: POD | D100: 1 | E100: 2 | F100: MetLife Group Policy SME | G100: BSA | H100: E4 | I100: ON | J100: FTE | K100: 0.5 | L100: =IF($B100="",0,IF($C100="HZ",1,IFERROR(INDEX('Value Streams & Delivery Mode'!$D$17:$M$22,MATCH($D100,'Value Streams & Delivery Mode'!$B$17:$B$22,0),($B100-1)*2+IF($C100="POD",1,2)),0))) | M100: =IF($B100="",0,$K100*$L100) | N100: =IF($B100="",0,IFERROR(INDEX('Rates & Tables'!$C$61:$G$63,MATCH($I100,'Rates & Tables'!$J$61:$J$63,0),MATCH($H100,'Rates & Tables'!$C$60:$G$60,0)),0)) | O100: =IF($B100="",0,$M100*$N100) | P100: =IF($B100="","",$B100&"|"&$G100&"|"&$J100)
B101: 3 | C101: POD | D101: 1 | E101: 3 | F101: FSI Senior Developer (JP) | G101: DEV | H101: E3 | I101: ON | J101: PT | K101: 2 | L101: =IF($B101="",0,IF($C101="HZ",1,IFERROR(INDEX('Value Streams & Delivery Mode'!$D$17:$M$22,MATCH($D101,'Value Streams & Delivery Mode'!$B$17:$B$22,0),($B101-1)*2+IF($C101="POD",1,2)),0))) | M101: =IF($B101="",0,$K101*$L101) | N101: =IF($B101="",0,IFERROR(INDEX('Rates & Tables'!$C$61:$G$63,MATCH($I101,'Rates & Tables'!$J$61:$J$63,0),MATCH($H101,'Rates & Tables'!$C$60:$G$60,0)),0)) | O101: =IF($B101="",0,$M101*$N101) | P101: =IF($B101="","",$B101&"|"&$G101&"|"&$J101)
B102: 3 | C102: POD | D102: 1 | E102: 4 | F102: FSI Application Support | G102: MNT | H102: E2 | I102: ON | J102: PT | K102: 0.5 | L102: =IF($B102="",0,IF($C102="HZ",1,IFERROR(INDEX('Value Streams & Delivery Mode'!$D$17:$M$22,MATCH($D102,'Value Streams & Delivery Mode'!$B$17:$B$22,0),($B102-1)*2+IF($C102="POD",1,2)),0))) | M102: =IF($B102="",0,$K102*$L102) | N102: =IF($B102="",0,IFERROR(INDEX('Rates & Tables'!$C$61:$G$63,MATCH($I102,'Rates & Tables'!$J$61:$J$63,0),MATCH($H102,'Rates & Tables'!$C$60:$G$60,0)),0)) | O102: =IF($B102="",0,$M102*$N102) | P102: =IF($B102="","",$B102&"|"&$G102&"|"&$J102)
B103: 3 | C103: POD | D103: 1 | E103: 5 | F103: Pod lead / senior engineer | G103: DEV | H103: E3 | I103: ON | J103: FTC | K103: 1 | L103: =IF($B103="",0,IF($C103="HZ",1,IFERROR(INDEX('Value Streams & Delivery Mode'!$D$17:$M$22,MATCH($D103,'Value Streams & Delivery Mode'!$B$17:$B$22,0),($B103-1)*2+IF($C103="POD",1,2)),0))) | M103: =IF($B103="",0,$K103*$L103) | N103: =IF($B103="",0,IFERROR(INDEX('Rates & Tables'!$C$61:$G$63,MATCH($I103,'Rates & Tables'!$J$61:$J$63,0),MATCH($H103,'Rates & Tables'!$C$60:$G$60,0)),0)) | O103: =IF($B103="",0,$M103*$N103) | P103: =IF($B103="","",$B103&"|"&$G103&"|"&$J103)
B104: 3 | C104: POD | D104: 1 | E104: 6 | F104: Junior Java Developer — offshore | G104: DEV | H104: E2 | I104: OFF | J104: FTC | K104: 1 | L104: =IF($B104="",0,IF($C104="HZ",1,IFERROR(INDEX('Value Streams & Delivery Mode'!$D$17:$M$22,MATCH($D104,'Value Streams & Delivery Mode'!$B$17:$B$22,0),($B104-1)*2+IF($C104="POD",1,2)),0))) | M104: =IF($B104="",0,$K104*$L104) | N104: =IF($B104="",0,IFERROR(INDEX('Rates & Tables'!$C$61:$G$63,MATCH($I104,'Rates & Tables'!$J$61:$J$63,0),MATCH($H104,'Rates & Tables'!$C$60:$G$60,0)),0)) | O104: =IF($B104="",0,$M104*$N104) | P104: =IF($B104="","",$B104&"|"&$G104&"|"&$J104)
B105: 3 | C105: POD | D105: 1 | E105: 7 | F105: Quality Engineer (SDET) — offshore | G105: TEST | H105: E3 | I105: OFF | J105: FTC | K105: 1 | L105: =IF($B105="",0,IF($C105="HZ",1,IFERROR(INDEX('Value Streams & Delivery Mode'!$D$17:$M$22,MATCH($D105,'Value Streams & Delivery Mode'!$B$17:$B$22,0),($B105-1)*2+IF($C105="POD",1,2)),0))) | M105: =IF($B105="",0,$K105*$L105) | N105: =IF($B105="",0,IFERROR(INDEX('Rates & Tables'!$C$61:$G$63,MATCH($I105,'Rates & Tables'!$J$61:$J$63,0),MATCH($H105,'Rates & Tables'!$C$60:$G$60,0)),0)) | O105: =IF($B105="",0,$M105*$N105) | P105: =IF($B105="","",$B105&"|"&$G105&"|"&$J105)
B106: 3 | C106: POD | D106: 1 | E106: 8 | F106: Junior Application Support — offshore | G106: MNT | H106: E1 | I106: OFF | J106: FTC | K106: 0.5 | L106: =IF($B106="",0,IF($C106="HZ",1,IFERROR(INDEX('Value Streams & Delivery Mode'!$D$17:$M$22,MATCH($D106,'Value Streams & Delivery Mode'!$B$17:$B$22,0),($B106-1)*2+IF($C106="POD",1,2)),0))) | M106: =IF($B106="",0,$K106*$L106) | N106: =IF($B106="",0,IFERROR(INDEX('Rates & Tables'!$C$61:$G$63,MATCH($I106,'Rates & Tables'!$J$61:$J$63,0),MATCH($H106,'Rates & Tables'!$C$60:$G$60,0)),0)) | O106: =IF($B106="",0,$M106*$N106) | P106: =IF($B106="","",$B106&"|"&$G106&"|"&$J106)
B107: 3 | C107: POD | D107: 2 | E107: 1 | F107: MetLife Product Owner | G107: PM | H107: E4 | I107: ON | J107: FTE | K107: 1 | L107: =IF($B107="",0,IF($C107="HZ",1,IFERROR(INDEX('Value Streams & Delivery Mode'!$D$17:$M$22,MATCH($D107,'Value Streams & Delivery Mode'!$B$17:$B$22,0),($B107-1)*2+IF($C107="POD",1,2)),0))) | M107: =IF($B107="",0,$K107*$L107) | N107: =IF($B107="",0,IFERROR(INDEX('Rates & Tables'!$C$61:$G$63,MATCH($I107,'Rates & Tables'!$J$61:$J$63,0),MATCH($H107,'Rates & Tables'!$C$60:$G$60,0)),0)) | O107: =IF($B107="",0,$M107*$N107) | P107: =IF($B107="","",$B107&"|"&$G107&"|"&$J107)
B108: 3 | C108: POD | D108: 2 | E108: 2 | F108: MetLife Compliance SME | G108: BSA | H108: E4 | I108: ON | J108: FTE | K108: 0.5 | L108: =IF($B108="",0,IF($C108="HZ",1,IFERROR(INDEX('Value Streams & Delivery Mode'!$D$17:$M$22,MATCH($D108,'Value Streams & Delivery Mode'!$B$17:$B$22,0),($B108-1)*2+IF($C108="POD",1,2)),0))) | M108: =IF($B108="",0,$K108*$L108) | N108: =IF($B108="",0,IFERROR(INDEX('Rates & Tables'!$C$61:$G$63,MATCH($I108,'Rates & Tables'!$J$61:$J$63,0),MATCH($H108,'Rates & Tables'!$C$60:$G$60,0)),0)) | O108: =IF($B108="",0,$M108*$N108) | P108: =IF($B108="","",$B108&"|"&$G108&"|"&$J108)
B109: 3 | C109: POD | D109: 2 | E109: 3 | F109: FSI Senior Developer (JP) | G109: DEV | H109: E3 | I109: ON | J109: PT | K109: 1 | L109: =IF($B109="",0,IF($C109="HZ",1,IFERROR(INDEX('Value Streams & Delivery Mode'!$D$17:$M$22,MATCH($D109,'Value Streams & Delivery Mode'!$B$17:$B$22,0),($B109-1)*2+IF($C109="POD",1,2)),0))) | M109: =IF($B109="",0,$K109*$L109) | N109: =IF($B109="",0,IFERROR(INDEX('Rates & Tables'!$C$61:$G$63,MATCH($I109,'Rates & Tables'!$J$61:$J$63,0),MATCH($H109,'Rates & Tables'!$C$60:$G$60,0)),0)) | O109: =IF($B109="",0,$M109*$N109) | P109: =IF($B109="","",$B109&"|"&$G109&"|"&$J109)
B110: 3 | C110: POD | D110: 2 | E110: 4 | F110: FSI Application Support | G110: MNT | H110: E2 | I110: ON | J110: PT | K110: 0.5 | L110: =IF($B110="",0,IF($C110="HZ",1,IFERROR(INDEX('Value Streams & Delivery Mode'!$D$17:$M$22,MATCH($D110,'Value Streams & Delivery Mode'!$B$17:$B$22,0),($B110-1)*2+IF($C110="POD",1,2)),0))) | M110: =IF($B110="",0,$K110*$L110) | N110: =IF($B110="",0,IFERROR(INDEX('Rates & Tables'!$C$61:$G$63,MATCH($I110,'Rates & Tables'!$J$61:$J$63,0),MATCH($H110,'Rates & Tables'!$C$60:$G$60,0)),0)) | O110: =IF($B110="",0,$M110*$N110) | P110: =IF($B110="","",$B110&"|"&$G110&"|"&$J110)
... B123: 3 | C123: POD | D123: 3 | E123: 9 | F123: L2/L3 Application Support — Tokyo | G123: MNT | H123: E2 | I123: ON | J123: FTC | K123: 0.5 | L123: =IF($B123="",0,IF($C123="HZ",1,IFERROR(INDEX('Value Streams & Delivery Mode'!$D$17:$M$22,MATCH($D123,'Value Streams & Delivery Mode'!$B$17:$B$22,0),($B123-1)*2+IF($C123="POD",1,2)),0))) | M123: =IF($B123="",0,$K123*$L123) | N123: =IF($B123="",0,IFERROR(INDEX('Rates & Tables'!$C$61:$G$63,MATCH($I123,'Rates & Tables'!$J$61:$J$63,0),MATCH($H123,'Rates & Tables'!$C$60:$G$60,0)),0)) | O123: =IF($B123="",0,$M123*$N123) | P123: =IF($B123="","",$B123&"|"&$G123&"|"&$J123)
B124: 3 | C124: HZ | D124: H3 | E124: 1 | F124: Domain Service Manager | G124: PM | H124: E5 | I124: ON | J124: FTC | K124: 1 | L124: =IF($B124="",0,IF($C124="HZ",1,IFERROR(INDEX('Value Streams & Delivery Mode'!$D$17:$M$22,MATCH($D124,'Value Streams & Delivery Mode'!$B$17:$B$22,0),($B124-1)*2+IF($C124="POD",1,2)),0))) | M124: =IF($B124="",0,$K124*$L124) | N124: =IF($B124="",0,IFERROR(INDEX('Rates & Tables'!$C$61:$G$63,MATCH($I124,'Rates & Tables'!$J$61:$J$63,0),MATCH($H124,'Rates & Tables'!$C$60:$G$60,0)),0)) | O124: =IF($B124="",0,$M124*$N124) | P124: =IF($B124="","",$B124&"|"&$G124&"|"&$J124)
B125: 3 | C125: HZ | D125: H3 | E125: 2 | F125: Lead BSA (bilingual) | G125: BSA | H125: E4 | I125: ON | J125: FTC | K125: 1 | L125: =IF($B125="",0,IF($C125="HZ",1,IFERROR(INDEX('Value Streams & Delivery Mode'!$D$17:$M$22,MATCH($D125,'Value Streams & Delivery Mode'!$B$17:$B$22,0),($B125-1)*2+IF($C125="POD",1,2)),0))) | M125: =IF($B125="",0,$K125*$L125) | N125: =IF($B125="",0,IFERROR(INDEX('Rates & Tables'!$C$61:$G$63,MATCH($I125,'Rates & Tables'!$J$61:$J$63,0),MATCH($H125,'Rates & Tables'!$C$60:$G$60,0)),0)) | O125: =IF($B125="",0,$M125*$N125) | P125: =IF($B125="","",$B125&"|"&$G125&"|"&$J125)
B126: 3 | C126: HZ | D126: H3 | E126: 3 | F126: Solution Architect | G126: OTH | H126: E4 | I126: ON | J126: FTC | K126: 0.5 | L126: =IF($B126="",0,IF($C126="HZ",1,IFERROR(INDEX('Value Streams & Delivery Mode'!$D$17:$M$22,MATCH($D126,'Value Streams & Delivery Mode'!$B$17:$B$22,0),($B126-1)*2+IF($C126="POD",1,2)),0))) | M126: =IF($B126="",0,$K126*$L126) | N126: =IF($B126="",0,IFERROR(INDEX('Rates & Tables'!$C$61:$G$63,MATCH($I126,'Rates & Tables'!$J$61:$J$63,0),MATCH($H126,'Rates & Tables'!$C$60:$G$60,0)),0)) | O126: =IF($B126="",0,$M126*$N126) | P126: =IF($B126="","",$B126&"|"&$G126&"|"&$J126)
B127: 3 | C127: HZ | D127: H3 | E127: 4 | F127: Release / DevOps engineer | G127: OTH | H127: E2 | I127: ON | J127: FTC | K127: 1 | L127: =IF($B127="",0,IF($C127="HZ",1,IFERROR(INDEX('Value Streams & Delivery Mode'!$D$17:$M$22,MATCH($D127,'Value Streams & Delivery Mode'!$B$17:$B$22,0),($B127-1)*2+IF($C127="POD",1,2)),0))) | M127: =IF($B127="",0,$K127*$L127) | N127: =IF($B127="",0,IFERROR(INDEX('Rates & Tables'!$C$61:$G$63,MATCH($I127,'Rates & Tables'!$J$61:$J$63,0),MATCH($H127,'Rates & Tables'!$C$60:$G$60,0)),0)) | O127: =IF($B127="",0,$M127*$N127) | P127: =IF($B127="","",$B127&"|"&$G127&"|"&$J127)
B128: 3 | C128: HZ | D128: H3 | E128: 5 | F128: MetLife Regulatory Liaison | G128: BSA | H128: E4 | I128: ON | J128: FTE | K128: 1 | L128: =IF($B128="",0,IF($C128="HZ",1,IFERROR(INDEX('Value Streams & Delivery Mode'!$D$17:$M$22,MATCH($D128,'Value Streams & Delivery Mode'!$B$17:$B$22,0),($B128-1)*2+IF($C128="POD",1,2)),0))) | M128: =IF($B128="",0,$K128*$L128) | N128: =IF($B128="",0,IFERROR(INDEX('Rates & Tables'!$C$61:$G$63,MATCH($I128,'Rates & Tables'!$J$61:$J$63,0),MATCH($H128,'Rates & Tables'!$C$60:$G$60,0)),0)) | O128: =IF($B128="",0,$M128*$N128) | P128: =IF($B128="","",$B128&"|"&$G128&"|"&$J128)
B129: 3 | C129: HZ | D129: H3 | E129: 6 | F129: MetLife Domain Architect | G129: OTH | H129: E4 | I129: ON | J129: FTE | K129: 1 | L129: =IF($B129="",0,IF($C129="HZ",1,IFERROR(INDEX('Value Streams & Delivery Mode'!$D$17:$M$22,MATCH($D129,'Value Streams & Delivery Mode'!$B$17:$B$22,0),($B129-1)*2+IF($C129="POD",1,2)),0))) | M129: =IF($B129="",0,$K129*$L129) | N129: =IF($B129="",0,IFERROR(INDEX('Rates & Tables'!$C$61:$G$63,MATCH($I129,'Rates & Tables'!$J$61:$J$63,0),MATCH($H129,'Rates & Tables'!$C$60:$G$60,0)),0)) | O129: =IF($B129="",0,$M129*$N129) | P129: =IF($B129="","",$B129&"|"&$G129&"|"&$J129)
B130: 3 | C130: HZ | D130: H1 | E130: 7 | F130: AMS Team Lead | G130: MNT | H130: E3 | I130: ON | J130: FTC | K130: 1 | L130: =IF($B130="",0,IF($C130="HZ",1,IFERROR(INDEX('Value Streams & Delivery Mode'!$D$17:$M$22,MATCH($D130,'Value Streams & Delivery Mode'!$B$17:$B$22,0),($B130-1)*2+IF($C130="POD",1,2)),0))) | M130: =IF($B130="",0,$K130*$L130) | N130: =IF($B130="",0,IFERROR(INDEX('Rates & Tables'!$C$61:$G$63,MATCH($I130,'Rates & Tables'!$J$61:$J$63,0),MATCH($H130,'Rates & Tables'!$C$60:$G$60,0)),0)) | O130: =IF($B130="",0,$M130*$N130) | P130: =IF($B130="","",$B130&"|"&$G130&"|"&$J130)
B131: 3 | C131: HZ | D131: H1 | E131: 8 | F131: SaaS Administrator — offshore | G131: MNT | H131: E2 | I131: OFF | J131: FTC | K131: 1 | L131: =IF($B131="",0,IF($C131="HZ",1,IFERROR(INDEX('Value Streams & Delivery Mode'!$D$17:$M$22,MATCH($D131,'Value Streams & Delivery Mode'!$B$17:$B$22,0),($B131-1)*2+IF($C131="POD",1,2)),0))) | M131: =IF($B131="",0,$K131*$L131) | N131: =IF($B131="",0,IFERROR(INDEX('Rates & Tables'!$C$61:$G$63,MATCH($I131,'Rates & Tables'!$J$61:$J$63,0),MATCH($H131,'Rates & Tables'!$C$60:$G$60,0)),0)) | O131: =IF($B131="",0,$M131*$N131) | P131: =IF($B131="","",$B131&"|"&$G131&"|"&$J131)
B132: 3 | C132: HZ | D132: H1 | E132: 9 | F132: Junior Application Support — offshore | G132: MNT | H132: E1 | I132: OFF | J132: FTC | K132: 1 | L132: =IF($B132="",0,IF($C132="HZ",1,IFERROR(INDEX('Value Streams & Delivery Mode'!$D$17:$M$22,MATCH($D132,'Value Streams & Delivery Mode'!$B$17:$B$22,0),($B132-1)*2+IF($C132="POD",1,2)),0))) | M132: =IF($B132="",0,$K132*$L132) | N132: =IF($B132="",0,IFERROR(INDEX('Rates & Tables'!$C$61:$G$63,MATCH($I132,'Rates & Tables'!$J$61:$J$63,0),MATCH($H132,'Rates & Tables'!$C$60:$G$60,0)),0)) | O132: =IF($B132="",0,$M132*$N132) | P132: =IF($B132="","",$B132&"|"&$G132&"|"&$J132)
B133: 3 | C133: HZ | D133: H1 | E133: 10 | F133: MetLife Operations Analyst | G133: MNT | H133: E3 | I133: ON | J133: FTE | K133: 1.5 | L133: =IF($B133="",0,IF($C133="HZ",1,IFERROR(INDEX('Value Streams & Delivery Mode'!$D$17:$M$22,MATCH($D133,'Value Streams & Delivery Mode'!$B$17:$B$22,0),($B133-1)*2+IF($C133="POD",1,2)),0))) | M133: =IF($B133="",0,$K133*$L133) | N133: =IF($B133="",0,IFERROR(INDEX('Rates & Tables'!$C$61:$G$63,MATCH($I133,'Rates & Tables'!$J$61:$J$63,0),MATCH($H133,'Rates & Tables'!$C$60:$G$60,0)),0)) | O133: =IF($B133="",0,$M133*$N133) | P133: =IF($B133="","",$B133&"|"&$G133&"|"&$J133)
B134: 3 | C134: HZ | D134: H1 | E134: 11 | F134: MGCC Application Support | G134: MNT | H134: E2 | I134: OFF | J134: MGCC | K134: 0.5 | L134: =IF($B134="",0,IF($C134="HZ",1,IFERROR(INDEX('Value Streams & Delivery Mode'!$D$17:$M$22,MATCH($D134,'Value Streams & Delivery Mode'!$B$17:$B$22,0),($B134-1)*2+IF($C134="POD",1,2)),0))) | M134: =IF($B134="",0,$K134*$L134) | N134: =IF($B134="",0,IFERROR(INDEX('Rates & Tables'!$C$61:$G$63,MATCH($I134,'Rates & Tables'!$J$61:$J$63,0),MATCH($H134,'Rates & Tables'!$C$60:$G$60,0)),0)) | O134: =IF($B134="",0,$M134*$N134) | P134: =IF($B134="","",$B134&"|"&$G134&"|"&$J134)
B135: 3 | C135: HZ | D135: H2 | E135: 12 | F135: Test Lead / QA Manager | G135: TEST | H135: E3 | I135: ON | J135: FTC | K135: 0.5 | L135: =IF($B135="",0,IF($C135="HZ",1,IFERROR(INDEX('Value Streams & Delivery Mode'!$D$17:$M$22,MATCH($D135,'Value Streams & Delivery Mode'!$B$17:$B$22,0),($B135-1)*2+IF($C135="POD",1,2)),0))) | M135: =IF($B135="",0,$K135*$L135) | N135: =IF($B135="",0,IFERROR(INDEX('Rates & Tables'!$C$61:$G$63,MATCH($I135,'Rates & Tables'!$J$61:$J$63,0),MATCH($H135,'Rates & Tables'!$C$60:$G$60,0)),0)) | O135: =IF($B135="",0,$M135*$N135) | P135: =IF($B135="","",$B135&"|"&$G135&"|"&$J135)
... B137: 3 | C137: HZ | D137: H2 | E137: 14 | F137: MGCC Test Engineer | G137: TEST | H137: E2 | I137: OFF | J137: MGCC | K137: 0.5 | L137: =IF($B137="",0,IF($C137="HZ",1,IFERROR(INDEX('Value Streams & Delivery Mode'!$D$17:$M$22,MATCH($D137,'Value Streams & Delivery Mode'!$B$17:$B$22,0),($B137-1)*2+IF($C137="POD",1,2)),0))) | M137: =IF($B137="",0,$K137*$L137) | N137: =IF($B137="",0,IFERROR(INDEX('Rates & Tables'!$C$61:$G$63,MATCH($I137,'Rates & Tables'!$J$61:$J$63,0),MATCH($H137,'Rates & Tables'!$C$60:$G$60,0)),0)) | O137: =IF($B137="",0,$M137*$N137) | P137: =IF($B137="","",$B137&"|"&$G137&"|"&$J137)
B138: 4 | C138: POD | D138: 1 | E138: 1 | F138: MetLife Product Owner | G138: PM | H138: E4 | I138: ON | J138: FTE | K138: 1 | L138: =IF($B138="",0,IF($C138="HZ",1,IFERROR(INDEX('Value Streams & Delivery Mode'!$D$17:$M$22,MATCH($D138,'Value Streams & Delivery Mode'!$B$17:$B$22,0),($B138-1)*2+IF($C138="POD",1,2)),0))) | M138: =IF($B138="",0,$K138*$L138) | N138: =IF($B138="",0,IFERROR(INDEX('Rates & Tables'!$C$61:$G$63,MATCH($I138,'Rates & Tables'!$J$61:$J$63,0),MATCH($H138,'Rates & Tables'!$C$60:$G$60,0)),0)) | O138: =IF($B138="",0,$M138*$N138) | P138: =IF($B138="","",$B138&"|"&$G138&"|"&$J138)
B139: 4 | C139: POD | D139: 1 | E139: 2 | F139: MetLife Group Policy SME | G139: BSA | H139: E4 | I139: ON | J139: FTE | K139: 0.5 | L139: =IF($B139="",0,IF($C139="HZ",1,IFERROR(INDEX('Value Streams & Delivery Mode'!$D$17:$M$22,MATCH($D139,'Value Streams & Delivery Mode'!$B$17:$B$22,0),($B139-1)*2+IF($C139="POD",1,2)),0))) | M139: =IF($B139="",0,$K139*$L139) | N139: =IF($B139="",0,IFERROR(INDEX('Rates & Tables'!$C$61:$G$63,MATCH($I139,'Rates & Tables'!$J$61:$J$63,0),MATCH($H139,'Rates & Tables'!$C$60:$G$60,0)),0)) | O139: =IF($B139="",0,$M139*$N139) | P139: =IF($B139="","",$B139&"|"&$G139&"|"&$J139)
B140: 4 | C140: POD | D140: 1 | E140: 3 | F140: FSI Senior Developer (JP) | G140: DEV | H140: E3 | I140: ON | J140: PT | K140: 2 | L140: =IF($B140="",0,IF($C140="HZ",1,IFERROR(INDEX('Value Streams & Delivery Mode'!$D$17:$M$22,MATCH($D140,'Value Streams & Delivery Mode'!$B$17:$B$22,0),($B140-1)*2+IF($C140="POD",1,2)),0))) | M140: =IF($B140="",0,$K140*$L140) | N140: =IF($B140="",0,IFERROR(INDEX('Rates & Tables'!$C$61:$G$63,MATCH($I140,'Rates & Tables'!$J$61:$J$63,0),MATCH($H140,'Rates & Tables'!$C$60:$G$60,0)),0)) | O140: =IF($B140="",0,$M140*$N140) | P140: =IF($B140="","",$B140&"|"&$G140&"|"&$J140)
B141: 4 | C141: POD | D141: 1 | E141: 4 | F141: Pod lead / senior engineer | G141: DEV | H141: E3 | I141: ON | J141: FTC | K141: 1 | L141: =IF($B141="",0,IF($C141="HZ",1,IFERROR(INDEX('Value Streams & Delivery Mode'!$D$17:$M$22,MATCH($D141,'Value Streams & Delivery Mode'!$B$17:$B$22,0),($B141-1)*2+IF($C141="POD",1,2)),0))) | M141: =IF($B141="",0,$K141*$L141) | N141: =IF($B141="",0,IFERROR(INDEX('Rates & Tables'!$C$61:$G$63,MATCH($I141,'Rates & Tables'!$J$61:$J$63,0),MATCH($H141,'Rates & Tables'!$C$60:$G$60,0)),0)) | O141: =IF($B141="",0,$M141*$N141) | P141: =IF($B141="","",$B141&"|"&$G141&"|"&$J141)
B142: 4 | C142: POD | D142: 1 | E142: 5 | F142: Junior Application Support — offshore | G142: MNT | H142: E1 | I142: OFF | J142: FTC | K142: 0.5 | L142: =IF($B142="",0,IF($C142="HZ",1,IFERROR(INDEX('Value Streams & Delivery Mode'!$D$17:$M$22,MATCH($D142,'Value Streams & Delivery Mode'!$B$17:$B$22,0),($B142-1)*2+IF($C142="POD",1,2)),0))) | M142: =IF($B142="",0,$K142*$L142) | N142: =IF($B142="",0,IFERROR(INDEX('Rates & Tables'!$C$61:$G$63,MATCH($I142,'Rates & Tables'!$J$61:$J$63,0),MATCH($H142,'Rates & Tables'!$C$60:$G$60,0)),0)) | O142: =IF($B142="",0,$M142*$N142) | P142: =IF($B142="","",$B142&"|"&$G142&"|"&$J142)
B143: 4 | C143: POD | D143: 1 | E143: 6 | F143: MGCC Commission Engineer | G143: DEV | H143: E3 | I143: OFF | J143: MGCC | K143: 0.5 | L143: =IF($B143="",0,IF($C143="HZ",1,IFERROR(INDEX('Value Streams & Delivery Mode'!$D$17:$M$22,MATCH($D143,'Value Streams & Delivery Mode'!$B$17:$B$22,0),($B143-1)*2+IF($C143="POD",1,2)),0))) | M143: =IF($B143="",0,$K143*$L143) | N143: =IF($B143="",0,IFERROR(INDEX('Rates & Tables'!$C$61:$G$63,MATCH($I143,'Rates & Tables'!$J$61:$J$63,0),MATCH($H143,'Rates & Tables'!$C$60:$G$60,0)),0)) | O143: =IF($B143="",0,$M143*$N143) | P143: =IF($B143="","",$B143&"|"&$G143&"|"&$J143)
B144: 4 | C144: POD | D144: 1 | E144: 7 | F144: MGCC Test Engineer | G144: TEST | H144: E2 | I144: OFF | J144: MGCC | K144: 0.5 | L144: =IF($B144="",0,IF($C144="HZ",1,IFERROR(INDEX('Value Streams & Delivery Mode'!$D$17:$M$22,MATCH($D144,'Value Streams & Delivery Mode'!$B$17:$B$22,0),($B144-1)*2+IF($C144="POD",1,2)),0))) | M144: =IF($B144="",0,$K144*$L144) | N144: =IF($B144="",0,IFERROR(INDEX('Rates & Tables'!$C$61:$G$63,MATCH($I144,'Rates & Tables'!$J$61:$J$63,0),MATCH($H144,'Rates & Tables'!$C$60:$G$60,0)),0)) | O144: =IF($B144="",0,$M144*$N144) | P144: =IF($B144="","",$B144&"|"&$G144&"|"&$J144)
B145: 4 | C145: POD | D145: 2 | E145: 1 | F145: MetLife Product Owner | G145: PM | H145: E4 | I145: ON | J145: FTE | K145: 1 | L145: =IF($B145="",0,IF($C145="HZ",1,IFERROR(INDEX('Value Streams & Delivery Mode'!$D$17:$M$22,MATCH($D145,'Value Streams & Delivery Mode'!$B$17:$B$22,0),($B145-1)*2+IF($C145="POD",1,2)),0))) | M145: =IF($B145="",0,$K145*$L145) | N145: =IF($B145="",0,IFERROR(INDEX('Rates & Tables'!$C$61:$G$63,MATCH($I145,'Rates & Tables'!$J$61:$J$63,0),MATCH($H145,'Rates & Tables'!$C$60:$G$60,0)),0)) | O145: =IF($B145="",0,$M145*$N145) | P145: =IF($B145="","",$B145&"|"&$G145&"|"&$J145)
B146: 4 | C146: POD | D146: 2 | E146: 2 | F146: MetLife Compliance SME | G146: BSA | H146: E4 | I146: ON | J146: FTE | K146: 0.5 | L146: =IF($B146="",0,IF($C146="HZ",1,IFERROR(INDEX('Value Streams & Delivery Mode'!$D$17:$M$22,MATCH($D146,'Value Streams & Delivery Mode'!$B$17:$B$22,0),($B146-1)*2+IF($C146="POD",1,2)),0))) | M146: =IF($B146="",0,$K146*$L146) | N146: =IF($B146="",0,IFERROR(INDEX('Rates & Tables'!$C$61:$G$63,MATCH($I146,'Rates & Tables'!$J$61:$J$63,0),MATCH($H146,'Rates & Tables'!$C$60:$G$60,0)),0)) | O146: =IF($B146="",0,$M146*$N146) | P146: =IF($B146="","",$B146&"|"&$G146&"|"&$J146)
B147: 4 | C147: POD | D147: 2 | E147: 3 | F147: FSI Senior Developer (JP) | G147: DEV | H147: E3 | I147: ON | J147: PT | K147: 1 | L147: =IF($B147="",0,IF($C147="HZ",1,IFERROR(INDEX('Value Streams & Delivery Mode'!$D$17:$M$22,MATCH($D147,'Value Streams & Delivery Mode'!$B$17:$B$22,0),($B147-1)*2+IF($C147="POD",1,2)),0))) | M147: =IF($B147="",0,$K147*$L147) | N147: =IF($B147="",0,IFERROR(INDEX('Rates & Tables'!$C$61:$G$63,MATCH($I147,'Rates & Tables'!$J$61:$J$63,0),MATCH($H147,'Rates & Tables'!$C$60:$G$60,0)),0)) | O147: =IF($B147="",0,$M147*$N147) | P147: =IF($B147="","",$B147&"|"&$G147&"|"&$J147)
B148: 4 | C148: POD | D148: 2 | E148: 4 | F148: Pod lead / senior engineer | G148: DEV | H148: E4 | I148: ON | J148: FTC | K148: 1 | L148: =IF($B148="",0,IF($C148="HZ",1,IFERROR(INDEX('Value Streams & Delivery Mode'!$D$17:$M$22,MATCH($D148,'Value Streams & Delivery Mode'!$B$17:$B$22,0),($B148-1)*2+IF($C148="POD",1,2)),0))) | M148: =IF($B148="",0,$K148*$L148) | N148: =IF($B148="",0,IFERROR(INDEX('Rates & Tables'!$C$61:$G$63,MATCH($I148,'Rates & Tables'!$J$61:$J$63,0),MATCH($H148,'Rates & Tables'!$C$60:$G$60,0)),0)) | O148: =IF($B148="",0,$M148*$N148) | P148: =IF($B148="","",$B148&"|"&$G148&"|"&$J148)
B149: 4 | C149: POD | D149: 2 | E149: 5 | F149: Junior .NET Developer — offshore | G149: DEV | H149: E2 | I149: OFF | J149: FTC | K149: 1 | L149: =IF($B149="",0,IF($C149="HZ",1,IFERROR(INDEX('Value Streams & Delivery Mode'!$D$17:$M$22,MATCH($D149,'Value Streams & Delivery Mode'!$B$17:$B$22,0),($B149-1)*2+IF($C149="POD",1,2)),0))) | M149: =IF($B149="",0,$K149*$L149) | N149: =IF($B149="",0,IFERROR(INDEX('Rates & Tables'!$C$61:$G$63,MATCH($I149,'Rates & Tables'!$J$61:$J$63,0),MATCH($H149,'Rates & Tables'!$C$60:$G$60,0)),0)) | O149: =IF($B149="",0,$M149*$N149) | P149: =IF($B149="","",$B149&"|"&$G149&"|"&$J149)
... B160: 4 | C160: POD | D160: 3 | E160: 8 | F160: MGCC Test Engineer | G160: TEST | H160: E2 | I160: OFF | J160: MGCC | K160: 0.5 | L160: =IF($B160="",0,IF($C160="HZ",1,IFERROR(INDEX('Value Streams & Delivery Mode'!$D$17:$M$22,MATCH($D160,'Value Streams & Delivery Mode'!$B$17:$B$22,0),($B160-1)*2+IF($C160="POD",1,2)),0))) | M160: =IF($B160="",0,$K160*$L160) | N160: =IF($B160="",0,IFERROR(INDEX('Rates & Tables'!$C$61:$G$63,MATCH($I160,'Rates & Tables'!$J$61:$J$63,0),MATCH($H160,'Rates & Tables'!$C$60:$G$60,0)),0)) | O160: =IF($B160="",0,$M160*$N160) | P160: =IF($B160="","",$B160&"|"&$G160&"|"&$J160)
B161: 4 | C161: HZ | D161: H3 | E161: 1 | F161: Domain Service Manager | G161: PM | H161: E5 | I161: ON | J161: FTC | K161: 1 | L161: =IF($B161="",0,IF($C161="HZ",1,IFERROR(INDEX('Value Streams & Delivery Mode'!$D$17:$M$22,MATCH($D161,'Value Streams & Delivery Mode'!$B$17:$B$22,0),($B161-1)*2+IF($C161="POD",1,2)),0))) | M161: =IF($B161="",0,$K161*$L161) | N161: =IF($B161="",0,IFERROR(INDEX('Rates & Tables'!$C$61:$G$63,MATCH($I161,'Rates & Tables'!$J$61:$J$63,0),MATCH($H161,'Rates & Tables'!$C$60:$G$60,0)),0)) | O161: =IF($B161="",0,$M161*$N161) | P161: =IF($B161="","",$B161&"|"&$G161&"|"&$J161)
B162: 4 | C162: HZ | D162: H3 | E162: 2 | F162: Lead BSA (bilingual) | G162: BSA | H162: E4 | I162: ON | J162: FTC | K162: 1 | L162: =IF($B162="",0,IF($C162="HZ",1,IFERROR(INDEX('Value Streams & Delivery Mode'!$D$17:$M$22,MATCH($D162,'Value Streams & Delivery Mode'!$B$17:$B$22,0),($B162-1)*2+IF($C162="POD",1,2)),0))) | M162: =IF($B162="",0,$K162*$L162) | N162: =IF($B162="",0,IFERROR(INDEX('Rates & Tables'!$C$61:$G$63,MATCH($I162,'Rates & Tables'!$J$61:$J$63,0),MATCH($H162,'Rates & Tables'!$C$60:$G$60,0)),0)) | O162: =IF($B162="",0,$M162*$N162) | P162: =IF($B162="","",$B162&"|"&$G162&"|"&$J162)
B163: 4 | C163: HZ | D163: H3 | E163: 3 | F163: Release & Environments Lead | G163: OTH | H163: E3 | I163: ON | J163: FTC | K163: 0.5 | L163: =IF($B163="",0,IF($C163="HZ",1,IFERROR(INDEX('Value Streams & Delivery Mode'!$D$17:$M$22,MATCH($D163,'Value Streams & Delivery Mode'!$B$17:$B$22,0),($B163-1)*2+IF($C163="POD",1,2)),0))) | M163: =IF($B163="",0,$K163*$L163) | N163: =IF($B163="",0,IFERROR(INDEX('Rates & Tables'!$C$61:$G$63,MATCH($I163,'Rates & Tables'!$J$61:$J$63,0),MATCH($H163,'Rates & Tables'!$C$60:$G$60,0)),0)) | O163: =IF($B163="",0,$M163*$N163) | P163: =IF($B163="","",$B163&"|"&$G163&"|"&$J163)
B164: 4 | C164: HZ | D164: H3 | E164: 4 | F164: MetLife Regulatory Liaison | G164: BSA | H164: E4 | I164: ON | J164: FTE | K164: 1 | L164: =IF($B164="",0,IF($C164="HZ",1,IFERROR(INDEX('Value Streams & Delivery Mode'!$D$17:$M$22,MATCH($D164,'Value Streams & Delivery Mode'!$B$17:$B$22,0),($B164-1)*2+IF($C164="POD",1,2)),0))) | M164: =IF($B164="",0,$K164*$L164) | N164: =IF($B164="",0,IFERROR(INDEX('Rates & Tables'!$C$61:$G$63,MATCH($I164,'Rates & Tables'!$J$61:$J$63,0),MATCH($H164,'Rates & Tables'!$C$60:$G$60,0)),0)) | O164: =IF($B164="",0,$M164*$N164) | P164: =IF($B164="","",$B164&"|"&$G164&"|"&$J164)
B165: 4 | C165: HZ | D165: H3 | E165: 5 | F165: MetLife Domain Architect | G165: OTH | H165: E4 | I165: ON | J165: FTE | K165: 1 | L165: =IF($B165="",0,IF($C165="HZ",1,IFERROR(INDEX('Value Streams & Delivery Mode'!$D$17:$M$22,MATCH($D165,'Value Streams & Delivery Mode'!$B$17:$B$22,0),($B165-1)*2+IF($C165="POD",1,2)),0))) | M165: =IF($B165="",0,$K165*$L165) | N165: =IF($B165="",0,IFERROR(INDEX('Rates & Tables'!$C$61:$G$63,MATCH($I165,'Rates & Tables'!$J$61:$J$63,0),MATCH($H165,'Rates & Tables'!$C$60:$G$60,0)),0)) | O165: =IF($B165="",0,$M165*$N165) | P165: =IF($B165="","",$B165&"|"&$G165&"|"&$J165)
B166: 4 | C166: HZ | D166: H1 | E166: 6 | F166: AMS Team Lead | G166: MNT | H166: E3 | I166: ON | J166: FTC | K166: 1 | L166: =IF($B166="",0,IF($C166="HZ",1,IFERROR(INDEX('Value Streams & Delivery Mode'!$D$17:$M$22,MATCH($D166,'Value Streams & Delivery Mode'!$B$17:$B$22,0),($B166-1)*2+IF($C166="POD",1,2)),0))) | M166: =IF($B166="",0,$K166*$L166) | N166: =IF($B166="",0,IFERROR(INDEX('Rates & Tables'!$C$61:$G$63,MATCH($I166,'Rates & Tables'!$J$61:$J$63,0),MATCH($H166,'Rates & Tables'!$C$60:$G$60,0)),0)) | O166: =IF($B166="",0,$M166*$N166) | P166: =IF($B166="","",$B166&"|"&$G166&"|"&$J166)
...

Sheet Seat Planner — how
A1: How to build the seat plan — and what good looks like
A2: The model tells you how many people of each sourcing type you may have in each year. The anatomy decides who they are. That judgement is the practice team's, not the model's.
A4: THE SHAPE OF A ROW
B5: Year | C5: 1 to 5. A seat that exists in every year needs five rows — the anatomy changes as pods shrink.
B6: Unit | C6: POD, TEAM or HZ. POD and TEAM rows are multiplied by the unit counts on the Value Streams sheet. HZ rows are counted once — a horizontal function is not per-stream.
B7: Stream | C7: For POD and TEAM rows, the stream number from the Value Streams sheet (1 to 6). For HZ rows put the function: H1 for run and support, H2 for quality and assurance, H3 for architecture, release and enablement.
B8: Role | C8: MetLife's own taxonomy: BSA, DEV, TEST, MNT, PM, OTH. Use it exactly — every role-line reconciliation in this workbook depends on it.
B9: Role detail | C9: Your name for the seat. 'Pod lead / senior engineer', 'MGCC Platform Engineer', 'MetLife Product Owner'. This is what the practice team and the resource manager read.
B10: Exp · Loc · Sourcing | C10: E1 to E5 · ON, OFF or NEAR · FTC, PT, FTE or MGCC. Sourcing is the one that carries commercial consequence: only FTC can transfer at the end of Year 3.
B11: Seats per unit | C11: The number you design. Columns L to P then derive units, deployed heads, cost index and cost. Do not type over them.
A12: WHAT GOOD LOOKS LIKE
B13: Deployed heads on a 0.5 grid | C13: Column M — seats × units — should land on whole numbers or halves. A seat ratio of 0.3214 across 28 teams is nine people, which is fine; a deployed head count of 0.094 is not a job. The Reconciliation sheet counts the offenders.
B14: Sharing contained inside the 領域 | C14: Where a half-head is genuinely warranted, share it inside this 領域. MetLife may award the eleven 領域 to two or three vendors, so a role shared across 領域 is a commitment we may not be able to keep.
B15: Reference sizes from the five 領域 already modelled | C15: Year-1 pod 7.7 to 10.4 seats · Year-1 team 11.5 to 14.4 seats · Year-4 pod 5.1 to 8.6 seats. Pods shrink as testing collapses into SDET seats and the release train consolidates; teams do not, which is part of why converting them matters.
B16: Horizontal functions | C16: Between 17 and 30 rows across the five 領域, totalling 15 to 62 units in Year 1. H1 is sized from the ticket load on the AMS sheet. Keep at least one seat in every horizontal role in every year — a design that lets the Release Manager go extinct in Year 4 is a design nobody can staff.
B17: Capgemini majority inside every unit | C17: Not just in aggregate. A pod where Capgemini is a minority is a pod whose ways of working we do not set, which is exactly the thing the productivity commitment rests on.
A18: THE ORDER TO WORK IN
B19: 1 · Year 1 first, and make it reconcile | C19: Year 1 is MEASURED, not designed. It is whatever Appendix 3 says: the same total, the same vendor / FTE / MGCC split, the same role lines, the same location split. Get it to zero variance before touching anything else.
B20: 2 · Then Year 3 | C20: The year the transfer is struck and the year MetLife will look at hardest. Work back to Year 2 and forward to Years 4 and 5 from there.
B21: 3 · Then check, and expect to iterate | C21: The five built models took several passes. The Reconciliation sheet is the same set of tests those models were held to, so if it is green the anatomy is defensible.

Sheet Reconciliation & Checks
A1: Reconciliation and checks (auto) — the bar the five built models were held to
A2: Every test here is a live formula over the Seat Planner. Green in every year is what a solution review should expect to see.
A4: A. YEAR 1 AGAINST APPENDIX 3 v5 — Year 1 is measured, not designed
B5: Measure | C5: Seat plan | D5: Appendix 3 v5 | E5: Variance | F5: Status | I5: Note
B6: Total people | C6: =SUMIFS('Seat Planner'!$M$5:$M$424,'Seat Planner'!$B$5:$B$424,1) | D6: ='Logic Tree'!$C$7 | E6: =C6-D6 | F6: =IF(ABS(E6)<=0.55,"OK","CHECK") | J6: The frozen scope. Everything else is a split of this.
B7: Vendor (Capgemini + partner) | C7: =SUMIFS('Seat Planner'!$M$5:$M$424,'Seat Planner'!$B$5:$B$424,1,'Seat Planner'!$J$5:$J$424,"FTC")+SUMIFS('Seat Planner'!$M$5:$M$424,'Seat Planner'!$B$5:$B$424,1,'Seat Planner'!$J$5:$J$424,"PT") | D7: ='Logic Tree'!$C$8 | E7: =C7-D7 | F7: =IF(ABS(E7)<=0.55,"OK","CHECK") | J7: Appendix 3 reports the two as one number. THE line that has to reconcile.
B8: — Capgemini payroll | C8: =SUMIFS('Seat Planner'!$M$5:$M$424,'Seat Planner'!$B$5:$B$424,1,'Seat Planner'!$J$5:$J$424,"FTC") | D8: ='Logic Tree'!$C$63 | E8: =C8-D8 | F8: =IF(ABS(E8)<=0.55,"OK","CHECK") | J8: Transferable at the end of Year 3.
B9: — named sub-contractor | C9: =SUMIFS('Seat Planner'!$M$5:$M$424,'Seat Planner'!$B$5:$B$424,1,'Seat Planner'!$J$5:$J$424,"PT") | D9: ='Logic Tree'!$C$57 | E9: =C9-D9 | F9: =IF(ABS(E9)<=0.55,"OK","CHECK") | J9: Never transferable.
B10: MetLife Japan (FTE) | C10: =SUMIFS('Seat Planner'!$M$5:$M$424,'Seat Planner'!$B$5:$B$424,1,'Seat Planner'!$J$5:$J$424,"FTE") | D10: ='Logic Tree'!$C$9 | E10: =C10-D10 | F10: =IF(ABS(E10)<=0.55,"OK","CHECK")
B11: MetLife MGCC | C11: =SUMIFS('Seat Planner'!$M$5:$M$424,'Seat Planner'!$B$5:$B$424,1,'Seat Planner'!$J$5:$J$424,"MGCC") | D11: ='Logic Tree'!$C$10 | E11: =C11-D11 | F11: =IF(ABS(E11)<=0.55,"OK","CHECK")
B12: Vendor onshore Tokyo | C12: =SUMIFS('Seat Planner'!$M$5:$M$424,'Seat Planner'!$B$5:$B$424,1,'Seat Planner'!$J$5:$J$424,"FTC",'Seat Planner'!$I$5:$I$424,"ON")+SUMIFS('Seat Planner'!$M$5:$M$424,'Seat Planner'!$B$5:$B$424,1,'Seat Planner'!$J$5:$J$424,"PT",'Seat Planner'!$I$5:$I$424,"ON") | D12: ='Logic Tree'!$C$11 | E12: =C12-D12 | F12: =IF(ABS(E12)<=0.55,"OK","CHECK") | J12: MEASURED. The bilingual hiring risk is the gap between this and the Capgemini heads already in Japan.
B13: Vendor offshore | C13: =SUMIFS('Seat Planner'!$M$5:$M$424,'Seat Planner'!$B$5:$B$424,1,'Seat Planner'!$J$5:$J$424,"FTC",'Seat Planner'!$I$5:$I$424,"OFF")+SUMIFS('Seat Planner'!$M$5:$M$424,'Seat Planner'!$B$5:$B$424,1,'Seat Planner'!$J$5:$J$424,"PT",'Seat Planner'!$I$5:$I$424,"OFF") | D13: ='Logic Tree'!$C$12 | E13: =C13-D13 | F13: =IF(ABS(E13)<=0.55,"OK","CHECK") | J13: MGCC excluded — it is MetLife's.
B14: Vendor nearshore | C14: =SUMIFS('Seat Planner'!$M$5:$M$424,'Seat Planner'!$B$5:$B$424,1,'Seat Planner'!$J$5:$J$424,"FTC",'Seat Planner'!$I$5:$I$424,"NEAR")+SUMIFS('Seat Planner'!$M$5:$M$424,'Seat Planner'!$B$5:$B$424,1,'Seat Planner'!$J$5:$J$424,"PT",'Seat Planner'!$I$5:$I$424,"NEAR") | D14: ='Logic Tree'!$C$13 | E14: =C14-D14 | F14: =IF(ABS(E14)<=0.55,"OK","CHECK")
B15: Role — BSA (vendor) | C15: =SUMIFS('Seat Planner'!$M$5:$M$424,'Seat Planner'!$B$5:$B$424,1,'Seat Planner'!$J$5:$J$424,"FTC",'Seat Planner'!$G$5:$G$424,"BSA")+SUMIFS('Seat Planner'!$M$5:$M$424,'Seat Planner'!$B$5:$B$424,1,'Seat Planner'!$J$5:$J$424,"PT",'Seat Planner'!$G$5:$G$424,"BSA") | D15: ='Logic Tree'!$D$20 | E15: =C15-D15 | F15: =IF(ABS(E15)<=0.55,"OK","CHECK") | J15: Against the RESTATED line, not the reported one.
B16: Role — Developer (vendor) | C16: =SUMIFS('Seat Planner'!$M$5:$M$424,'Seat Planner'!$B$5:$B$424,1,'Seat Planner'!$J$5:$J$424,"FTC",'Seat Planner'!$G$5:$G$424,"DEV")+SUMIFS('Seat Planner'!$M$5:$M$424,'Seat Planner'!$B$5:$B$424,1,'Seat Planner'!$J$5:$J$424,"PT",'Seat Planner'!$G$5:$G$424,"DEV") | D16: ='Logic Tree'!$D$21 | E16: =C16-D16 | F16: =IF(ABS(E16)<=0.55,"OK","CHECK") | J16: Against the RESTATED line, not the reported one.
B17: Role — Tester (vendor) | C17: =SUMIFS('Seat Planner'!$M$5:$M$424,'Seat Planner'!$B$5:$B$424,1,'Seat Planner'!$J$5:$J$424,"FTC",'Seat Planner'!$G$5:$G$424,"TEST")+SUMIFS('Seat Planner'!$M$5:$M$424,'Seat Planner'!$B$5:$B$424,1,'Seat Planner'!$J$5:$J$424,"PT",'Seat Planner'!$G$5:$G$424,"TEST") | D17: ='Logic Tree'!$D$22 | E17: =C17-D17 | F17: =IF(ABS(E17)<=0.55,"OK","CHECK") | J17: Against the RESTATED line, not the reported one.
B18: Role — Maintenance (vendor) | C18: =SUMIFS('Seat Planner'!$M$5:$M$424,'Seat Planner'!$B$5:$B$424,1,'Seat Planner'!$J$5:$J$424,"FTC",'Seat Planner'!$G$5:$G$424,"MNT")+SUMIFS('Seat Planner'!$M$5:$M$424,'Seat Planner'!$B$5:$B$424,1,'Seat Planner'!$J$5:$J$424,"PT",'Seat Planner'!$G$5:$G$424,"MNT") | D18: ='Logic Tree'!$D$23 | E18: =C18-D18 | F18: =IF(ABS(E18)<=0.55,"OK","CHECK") | J18: Against the RESTATED line, not the reported one.
B19: Role — PM (vendor) | C19: =SUMIFS('Seat Planner'!$M$5:$M$424,'Seat Planner'!$B$5:$B$424,1,'Seat Planner'!$J$5:$J$424,"FTC",'Seat Planner'!$G$5:$G$424,"PM")+SUMIFS('Seat Planner'!$M$5:$M$424,'Seat Planner'!$B$5:$B$424,1,'Seat Planner'!$J$5:$J$424,"PT",'Seat Planner'!$G$5:$G$424,"PM") | D19: ='Logic Tree'!$D$24 | E19: =C19-D19 | F19: =IF(ABS(E19)<=0.55,"OK","CHECK") | J19: Against the RESTATED line, not the reported one.
B20: Role — Other (vendor) | C20: =SUMIFS('Seat Planner'!$M$5:$M$424,'Seat Planner'!$B$5:$B$424,1,'Seat Planner'!$J$5:$J$424,"FTC",'Seat Planner'!$G$5:$G$424,"OTH")+SUMIFS('Seat Planner'!$M$5:$M$424,'Seat Planner'!$B$5:$B$424,1,'Seat Planner'!$J$5:$J$424,"PT",'Seat Planner'!$G$5:$G$424,"OTH") | D20: ='Logic Tree'!$D$25 | E20: =C20-D20 | F20: =IF(ABS(E20)<=0.55,"OK","CHECK") | J20: Against the RESTATED line, not the reported one.
B21: Largest variance on any line | C21: =MAX(ABS(E6),ABS(E7),ABS(E8),ABS(E9),ABS(E10),ABS(E11),ABS(E12),ABS(E13),ABS(E14),ABS(E15),ABS(E16),ABS(E17),ABS(E18),ABS(E19),ABS(E20)) | J21: The five built models land inside 0.55 of a person on every line after head-grid quantisation. Anything materially above that is a Year-1 plan for a different 領域.
A23: B. EVERY YEAR AGAINST THE PLAN — Logic Tree section I
B24: Measure | C24: Year 1 | D24: Year 2 | E24: Year 3 | F24: Year 4 | G24: Year 5 | I24: Note
B25: Total people — seat plan | C25: =SUMIFS('Seat Planner'!$M$5:$M$424,'Seat Planner'!$B$5:$B$424,1) | D25: =SUMIFS('Seat Planner'!$M$5:$M$424,'Seat Planner'!$B$5:$B$424,2) | E25: =SUMIFS('Seat Planner'!$M$5:$M$424,'Seat Planner'!$B$5:$B$424,3) | F25: =SUMIFS('Seat Planner'!$M$5:$M$424,'Seat Planner'!$B$5:$B$424,4) | G25: =SUMIFS('Seat Planner'!$M$5:$M$424,'Seat Planner'!$B$5:$B$424,5) | J25: Rows 121 to 125 of the Logic Tree are the target. Years 1 to 3 are the organic plan; Years 4 and 5 carry the transferred seats on MetLife's side.
B26: plan | C26: ='Logic Tree'!C125 | D26: ='Logic Tree'!D125 | E26: ='Logic Tree'!E125 | F26: ='Logic Tree'!F125 | G26: ='Logic Tree'!G125
B27: variance | C27: =C25-C26 | D27: =D25-D26 | E27: =E25-E26 | F27: =F25-F26 | G27: =G25-G26
B29: Capgemini (FTC) — seat plan | C29: =SUMIFS('Seat Planner'!$M$5:$M$424,'Seat Planner'!$B$5:$B$424,1,'Seat Planner'!$J$5:$J$424,"FTC") | D29: =SUMIFS('Seat Planner'!$M$5:$M$424,'Seat Planner'!$B$5:$B$424,2,'Seat Planner'!$J$5:$J$424,"FTC") | E29: =SUMIFS('Seat Planner'!$M$5:$M$424,'Seat Planner'!$B$5:$B$424,3,'Seat Planner'!$J$5:$J$424,"FTC") | F29: =SUMIFS('Seat Planner'!$M$5:$M$424,'Seat Planner'!$B$5:$B$424,4,'Seat Planner'!$J$5:$J$424,"FTC") | G29: =SUMIFS('Seat Planner'!$M$5:$M$424,'Seat Planner'!$B$5:$B$424,5,'Seat Planner'!$J$5:$J$424,"FTC") | J29: If Capgemini is over plan and MetLife under, the anatomy is not shrinking the pools at their own rates — which is the whole mechanic that converges the ratio without a transfer.
B30: plan | C30: ='Logic Tree'!C124 | D30: ='Logic Tree'!D124 | E30: ='Logic Tree'!E124 | F30: ='Logic Tree'!F124 | G30: ='Logic Tree'!G124
B31: variance | C31: =C29-C30 | D31: =D29-D30 | E31: =E29-E30 | F31: =F29-F30 | G31: =G29-G30
B33: Partner (PT) — seat plan | C33: =SUMIFS('Seat Planner'!$M$5:$M$424,'Seat Planner'!$B$5:$B$424,1,'Seat Planner'!$J$5:$J$424,"PT") | D33: =SUMIFS('Seat Planner'!$M$5:$M$424,'Seat Planner'!$B$5:$B$424,2,'Seat Planner'!$J$5:$J$424,"PT") | E33: =SUMIFS('Seat Planner'!$M$5:$M$424,'Seat Planner'!$B$5:$B$424,3,'Seat Planner'!$J$5:$J$424,"PT") | F33: =SUMIFS('Seat Planner'!$M$5:$M$424,'Seat Planner'!$B$5:$B$424,4,'Seat Planner'!$J$5:$J$424,"PT") | G33: =SUMIFS('Seat Planner'!$M$5:$M$424,'Seat Planner'!$B$5:$B$424,5,'Seat Planner'!$J$5:$J$424,"PT")
B34: plan | C34: ='Logic Tree'!C123 | D34: ='Logic Tree'!D123 | E34: ='Logic Tree'!E123 | F34: ='Logic Tree'!F123 | G34: ='Logic Tree'!G123
B35: variance | C35: =C33-C34 | D35: =D33-D34 | E35: =E33-E34 | F35: =F33-F34 | G35: =G33-G34
B37: MetLife Japan (FTE) — seat plan | C37: =SUMIFS('Seat Planner'!$M$5:$M$424,'Seat Planner'!$B$5:$B$424,1,'Seat Planner'!$J$5:$J$424,"FTE") | D37: =SUMIFS('Seat Planner'!$M$5:$M$424,'Seat Planner'!$B$5:$B$424,2,'Seat Planner'!$J$5:$J$424,"FTE") | E37: =SUMIFS('Seat Planner'!$M$5:$M$424,'Seat Planner'!$B$5:$B$424,3,'Seat Planner'!$J$5:$J$424,"FTE") | F37: =SUMIFS('Seat Planner'!$M$5:$M$424,'Seat Planner'!$B$5:$B$424,4,'Seat Planner'!$J$5:$J$424,"FTE") | G37: =SUMIFS('Seat Planner'!$M$5:$M$424,'Seat Planner'!$B$5:$B$424,5,'Seat Planner'!$J$5:$J$424,"FTE")
B38: plan | C38: ='Logic Tree'!C121 | D38: ='Logic Tree'!D121 | E38: ='Logic Tree'!E121 | F38: ='Logic Tree'!F121 | G38: ='Logic Tree'!G121
B39: variance | C39: =C37-C38 | D39: =D37-D38 | E39: =E37-E38 | F39: =F37-F38 | G39: =G37-G38
B41: MetLife MGCC — seat plan | C41: =SUMIFS('Seat Planner'!$M$5:$M$424,'Seat Planner'!$B$5:$B$424,1,'Seat Planner'!$J$5:$J$424,"MGCC") | D41: =SUMIFS('Seat Planner'!$M$5:$M$424,'Seat Planner'!$B$5:$B$424,2,'Seat Planner'!$J$5:$J$424,"MGCC") | E41: =SUMIFS('Seat Planner'!$M$5:$M$424,'Seat Planner'!$B$5:$B$424,3,'Seat Planner'!$J$5:$J$424,"MGCC") | F41: =SUMIFS('Seat Planner'!$M$5:$M$424,'Seat Planner'!$B$5:$B$424,4,'Seat Planner'!$J$5:$J$424,"MGCC") | G41: =SUMIFS('Seat Planner'!$M$5:$M$424,'Seat Planner'!$B$5:$B$424,5,'Seat Planner'!$J$5:$J$424,"MGCC")
B42: plan | C42: ='Logic Tree'!C122 | D42: ='Logic Tree'!D122 | E42: ='Logic Tree'!E122 | F42: ='Logic Tree'!F122 | G42: ='Logic Tree'!G122
B43: variance | C43: =C41-C42 | D43: =D41-D42 | E43: =E41-E42 | F43: =F41-F42 | G43: =G41-G42
A45: C. GUARDRAILS
B46: Test | C46: Year 1 | D46: Year 2 | E46: Year 3 | F46: Year 4 | G46: Year 5 | I46: Floor
B47: Capgemini + partner share of the delivery population | C47: =IF(SUMIFS('Seat Planner'!$M$5:$M$424,'Seat Planner'!$B$5:$B$424,1)=0,0,(SUMIFS('Seat Planner'!$M$5:$M$424,'Seat Planner'!$B$5:$B$424,1,'Seat Planner'!$J$5:$J$424,"FTC")+SUMIFS('Seat Planner'!$M$5:$M$424,'Seat Planner'!$B$5:$B$424,1,'Seat Planner'!$J$5:$J$424,"PT"))/SUMIFS('Seat Planner'!$M$5:$M$424,'Seat Planner'!$B$5:$B$424,1)) | D47: =IF(SUMIFS('Seat Planner'!$M$5:$M$424,'Seat Planner'!$B$5:$B$424,2)=0,0,(SUMIFS('Seat Planner'!$M$5:$M$424,'Seat Planner'!$B$5:$B$424,2,'Seat Planner'!$J$5:$J$424,"FTC")+SUMIFS('Seat Planner'!$M$5:$M$424,'Seat Planner'!$B$5:$B$424,2,'Seat Planner'!$J$5:$J$424,"PT"))/SUMIFS('Seat Planner'!$M$5:$M$424,'Seat Planner'!$B$5:$B$424,2)) | E47: =IF(SUMIFS('Seat Planner'!$M$5:$M$424,'Seat Planner'!$B$5:$B$424,3)=0,0,(SUMIFS('Seat Planner'!$M$5:$M$424,'Seat Planner'!$B$5:$B$424,3,'Seat Planner'!$J$5:$J$424,"FTC")+SUMIFS('Seat Planner'!$M$5:$M$424,'Seat Planner'!$B$5:$B$424,3,'Seat Planner'!$J$5:$J$424,"PT"))/SUMIFS('Seat Planner'!$M$5:$M$424,'Seat Planner'!$B$5:$B$424,3)) | F47: =IF(SUMIFS('Seat Planner'!$M$5:$M$424,'Seat Planner'!$B$5:$B$424,4)=0,0,(SUMIFS('Seat Planner'!$M$5:$M$424,'Seat Planner'!$B$5:$B$424,4,'Seat Planner'!$J$5:$J$424,"FTC")+SUMIFS('Seat Planner'!$M$5:$M$424,'Seat Planner'!$B$5:$B$424,4,'Seat Planner'!$J$5:$J$424,"PT"))/SUMIFS('Seat Planner'!$M$5:$M$424,'Seat Planner'!$B$5:$B$424,4)) | G47: =IF(SUMIFS('Seat Planner'!$M$5:$M$424,'Seat Planner'!$B$5:$B$424,5)=0,0,(SUMIFS('Seat Planner'!$M$5:$M$424,'Seat Planner'!$B$5:$B$424,5,'Seat Planner'!$J$5:$J$424,"FTC")+SUMIFS('Seat Planner'!$M$5:$M$424,'Seat Planner'!$B$5:$B$424,5,'Seat Planner'!$J$5:$J$424,"PT"))/SUMIFS('Seat Planner'!$M$5:$M$424,'Seat Planner'!$B$5:$B$424,5)) | I47: ='Rates & Tables'!$C$55 | J47: Where the Logic Tree says the floor does not apply — MetLife already held the majority on day one — this reads n/a rather than CHECK. A guardrail we cannot meet is not a guardrail; set your own floor on the Rates sheet and write the reason down.
B48: Capgemini share of build and test seats | C48: =IF((SUMIFS('Seat Planner'!$M$5:$M$424,'Seat Planner'!$B$5:$B$424,1,'Seat Planner'!$G$5:$G$424,"DEV")+SUMIFS('Seat Planner'!$M$5:$M$424,'Seat Planner'!$B$5:$B$424,1,'Seat Planner'!$G$5:$G$424,"TEST"))=0,0,(SUMIFS('Seat Planner'!$M$5:$M$424,'Seat Planner'!$B$5:$B$424,1,'Seat Planner'!$G$5:$G$424,"DEV",'Seat Planner'!$J$5:$J$424,"FTC")+SUMIFS('Seat Planner'!$M$5:$M$424,'Seat Planner'!$B$5:$B$424,1,'Seat Planner'!$G$5:$G$424,"TEST",'Seat Planner'!$J$5:$J$424,"FTC")+SUMIFS('Seat Planner'!$M$5:$M$424,'Seat Planner'!$B$5:$B$424,1,'Seat Planner'!$G$5:$G$424,"DEV",'Seat Planner'!$J$5:$J$424,"PT")+SUMIFS('Seat Planner'!$M$5:$M$424,'Seat Planner'!$B$5:$B$424,1,'Seat Planner'!$G$5:$G$424,"TEST",'Seat Planner'!$J$5:$J$424,"PT"))/(SUMIFS('Seat Planner'!$M$5:$M$424,'Seat Planner'!$B$5:$B$424,1,'Seat Planner'!$G$5:$G$424,"DEV")+SUMIFS('Seat Planner'!$M$5:$M$424,'Seat Planner'!$B$5:$B$424,1,'Seat Planner'!$G$5:$G$424,"TEST"))) | D48: =IF((SUMIFS('Seat Planner'!$M$5:$M$424,'Seat Planner'!$B$5:$B$424,2,'Seat Planner'!$G$5:$G$424,"DEV")+SUMIFS('Seat Planner'!$M$5:$M$424,'Seat Planner'!$B$5:$B$424,2,'Seat Planner'!$G$5:$G$424,"TEST"))=0,0,(SUMIFS('Seat Planner'!$M$5:$M$424,'Seat Planner'!$B$5:$B$424,2,'Seat Planner'!$G$5:$G$424,"DEV",'Seat Planner'!$J$5:$J$424,"FTC")+SUMIFS('Seat Planner'!$M$5:$M$424,'Seat Planner'!$B$5:$B$424,2,'Seat Planner'!$G$5:$G$424,"TEST",'Seat Planner'!$J$5:$J$424,"FTC")+SUMIFS('Seat Planner'!$M$5:$M$424,'Seat Planner'!$B$5:$B$424,2,'Seat Planner'!$G$5:$G$424,"DEV",'Seat Planner'!$J$5:$J$424,"PT")+SUMIFS('Seat Planner'!$M$5:$M$424,'Seat Planner'!$B$5:$B$424,2,'Seat Planner'!$G$5:$G$424,"TEST",'Seat Planner'!$J$5:$J$424,"PT"))/(SUMIFS('Seat Planner'!$M$5:$M$424,'Seat Planner'!$B$5:$B$424,2,'Seat Planner'!$G$5:$G$424,"DEV")+SUMIFS('Seat Planner'!$M$5:$M$424,'Seat Planner'!$B$5:$B$424,2,'Seat Planner'!$G$5:$G$424,"TEST"))) | E48: =IF((SUMIFS('Seat Planner'!$M$5:$M$424,'Seat Planner'!$B$5:$B$424,3,'Seat Planner'!$G$5:$G$424,"DEV")+SUMIFS('Seat Planner'!$M$5:$M$424,'Seat Planner'!$B$5:$B$424,3,'Seat Planner'!$G$5:$G$424,"TEST"))=0,0,(SUMIFS('Seat Planner'!$M$5:$M$424,'Seat Planner'!$B$5:$B$424,3,'Seat Planner'!$G$5:$G$424,"DEV",'Seat Planner'!$J$5:$J$424,"FTC")+SUMIFS('Seat Planner'!$M$5:$M$424,'Seat Planner'!$B$5:$B$424,3,'Seat Planner'!$G$5:$G$424,"TEST",'Seat Planner'!$J$5:$J$424,"FTC")+SUMIFS('Seat Planner'!$M$5:$M$424,'Seat Planner'!$B$5:$B$424,3,'Seat Planner'!$G$5:$G$424,"DEV",'Seat Planner'!$J$5:$J$424,"PT")+SUMIFS('Seat Planner'!$M$5:$M$424,'Seat Planner'!$B$5:$B$424,3,'Seat Planner'!$G$5:$G$424,"TEST",'Seat Planner'!$J$5:$J$424,"PT"))/(SUMIFS('Seat Planner'!$M$5:$M$424,'Seat Planner'!$B$5:$B$424,3,'Seat Planner'!$G$5:$G$424,"DEV")+SUMIFS('Seat Planner'!$M$5:$M$424,'Seat Planner'!$B$5:$B$424,3,'Seat Planner'!$G$5:$G$424,"TEST"))) | F48: =IF((SUMIFS('Seat Planner'!$M$5:$M$424,'Seat Planner'!$B$5:$B$424,4,'Seat Planner'!$G$5:$G$424,"DEV")+SUMIFS('Seat Planner'!$M$5:$M$424,'Seat Planner'!$B$5:$B$424,4,'Seat Planner'!$G$5:$G$424,"TEST"))=0,0,(SUMIFS('Seat Planner'!$M$5:$M$424,'Seat Planner'!$B$5:$B$424,4,'Seat Planner'!$G$5:$G$424,"DEV",'Seat Planner'!$J$5:$J$424,"FTC")+SUMIFS('Seat Planner'!$M$5:$M$424,'Seat Planner'!$B$5:$B$424,4,'Seat Planner'!$G$5:$G$424,"TEST",'Seat Planner'!$J$5:$J$424,"FTC")+SUMIFS('Seat Planner'!$M$5:$M$424,'Seat Planner'!$B$5:$B$424,4,'Seat Planner'!$G$5:$G$424,"DEV",'Seat Planner'!$J$5:$J$424,"PT")+SUMIFS('Seat Planner'!$M$5:$M$424,'Seat Planner'!$B$5:$B$424,4,'Seat Planner'!$G$5:$G$424,"TEST",'Seat Planner'!$J$5:$J$424,"PT"))/(SUMIFS('Seat Planner'!$M$5:$M$424,'Seat Planner'!$B$5:$B$424,4,'Seat Planner'!$G$5:$G$424,"DEV")+SUMIFS('Seat Planner'!$M$5:$M$424,'Seat Planner'!$B$5:$B$424,4,'Seat Planner'!$G$5:$G$424,"TEST"))) | G48: =IF((SUMIFS('Seat Planner'!$M$5:$M$424,'Seat Planner'!$B$5:$B$424,5,'Seat Planner'!$G$5:$G$424,"DEV")+SUMIFS('Seat Planner'!$M$5:$M$424,'Seat Planner'!$B$5:$B$424,5,'Seat Planner'!$G$5:$G$424,"TEST"))=0,0,(SUMIFS('Seat Planner'!$M$5:$M$424,'Seat Planner'!$B$5:$B$424,5,'Seat Planner'!$G$5:$G$424,"DEV",'Seat Planner'!$J$5:$J$424,"FTC")+SUMIFS('Seat Planner'!$M$5:$M$424,'Seat Planner'!$B$5:$B$424,5,'Seat Planner'!$G$5:$G$424,"TEST",'Seat Planner'!$J$5:$J$424,"FTC")+SUMIFS('Seat Planner'!$M$5:$M$424,'Seat Planner'!$B$5:$B$424,5,'Seat Planner'!$G$5:$G$424,"DEV",'Seat Planner'!$J$5:$J$424,"PT")+SUMIFS('Seat Planner'!$M$5:$M$424,'Seat Planner'!$B$5:$B$424,5,'Seat Planner'!$G$5:$G$424,"TEST",'Seat Planner'!$J$5:$J$424,"PT"))/(SUMIFS('Seat Planner'!$M$5:$M$424,'Seat Planner'!$B$5:$B$424,5,'Seat Planner'!$G$5:$G$424,"DEV")+SUMIFS('Seat Planner'!$M$5:$M$424,'Seat Planner'!$B$5:$B$424,5,'Seat Planner'!$G$5:$G$424,"TEST"))) | I48: ='Rates & Tables'!$C$56
B49: Offshore share of the whole team (includes MGCC) | C49: =IF(SUMIFS('Seat Planner'!$M$5:$M$424,'Seat Planner'!$B$5:$B$424,1)=0,0,SUMIFS('Seat Planner'!$M$5:$M$424,'Seat Planner'!$B$5:$B$424,1,'Seat Planner'!$I$5:$I$424,"OFF")/SUMIFS('Seat Planner'!$M$5:$M$424,'Seat Planner'!$B$5:$B$424,1)) | D49: =IF(SUMIFS('Seat Planner'!$M$5:$M$424,'Seat Planner'!$B$5:$B$424,2)=0,0,SUMIFS('Seat Planner'!$M$5:$M$424,'Seat Planner'!$B$5:$B$424,2,'Seat Planner'!$I$5:$I$424,"OFF")/SUMIFS('Seat Planner'!$M$5:$M$424,'Seat Planner'!$B$5:$B$424,2)) | E49: =IF(SUMIFS('Seat Planner'!$M$5:$M$424,'Seat Planner'!$B$5:$B$424,3)=0,0,SUMIFS('Seat Planner'!$M$5:$M$424,'Seat Planner'!$B$5:$B$424,3,'Seat Planner'!$I$5:$I$424,"OFF")/SUMIFS('Seat Planner'!$M$5:$M$424,'Seat Planner'!$B$5:$B$424,3)) | F49: =IF(SUMIFS('Seat Planner'!$M$5:$M$424,'Seat Planner'!$B$5:$B$424,4)=0,0,SUMIFS('Seat Planner'!$M$5:$M$424,'Seat Planner'!$B$5:$B$424,4,'Seat Planner'!$I$5:$I$424,"OFF")/SUMIFS('Seat Planner'!$M$5:$M$424,'Seat Planner'!$B$5:$B$424,4)) | G49: =IF(SUMIFS('Seat Planner'!$M$5:$M$424,'Seat Planner'!$B$5:$B$424,5)=0,0,SUMIFS('Seat Planner'!$M$5:$M$424,'Seat Planner'!$B$5:$B$424,5,'Seat Planner'!$I$5:$I$424,"OFF")/SUMIFS('Seat Planner'!$M$5:$M$424,'Seat Planner'!$B$5:$B$424,5)) | I49: ='Logic Tree'!C134
B50: Guardrail status — from Year 2 onward, and only where the floor applies | C50: =IF('Logic Tree'!$D$68=0,"n/a","measured") | D50: =IF('Logic Tree'!$D$68=0,"n/a",IF(AND(D47>='Rates & Tables'!$C$55-0.005,D48>='Rates & Tables'!$C$56-0.005),"OK","CHECK")) | E50: =IF('Logic Tree'!$D$68=0,"n/a",IF(AND(E47>='Rates & Tables'!$C$55-0.005,E48>='Rates & Tables'!$C$56-0.005),"OK","CHECK")) | F50: =IF('Logic Tree'!$D$68=0,"n/a",IF(AND(F47>='Rates & Tables'!$C$55-0.005,F48>='Rates & Tables'!$C$56-0.005),"OK","CHECK")) | G50: =IF('Logic Tree'!$D$68=0,"n/a",IF(AND(G47>='Rates & Tables'!$C$55-0.005,G48>='Rates & Tables'!$C$56-0.005),"OK","CHECK"))
A52: D. CAPGEMINI SHARE INSIDE EVERY SINGLE DELIVERY UNIT
B53: Unit | C53: Year 1 | D53: Year 2 | E53: Year 3 | F53: Year 4 | G53: Year 5 | I53: Note
B54: Stream 1 · POD | C54: =IF(SUMIFS('Seat Planner'!$M$5:$M$424,'Seat Planner'!$B$5:$B$424,1,'Seat Planner'!$C$5:$C$424,"POD",'Seat Planner'!$D$5:$D$424,1)=0,"",(SUMIFS('Seat Planner'!$M$5:$M$424,'Seat Planner'!$B$5:$B$424,1,'Seat Planner'!$C$5:$C$424,"POD",'Seat Planner'!$D$5:$D$424,1,'Seat Planner'!$J$5:$J$424,"FTC")+SUMIFS('Seat Planner'!$M$5:$M$424,'Seat Planner'!$B$5:$B$424,1,'Seat Planner'!$C$5:$C$424,"POD",'Seat Planner'!$D$5:$D$424,1,'Seat Planner'!$J$5:$J$424,"PT"))/SUMIFS('Seat Planner'!$M$5:$M$424,'Seat Planner'!$B$5:$B$424,1,'Seat Planner'!$C$5:$C$424,"POD",'Seat Planner'!$D$5:$D$424,1)) | D54: =IF(SUMIFS('Seat Planner'!$M$5:$M$424,'Seat Planner'!$B$5:$B$424,2,'Seat Planner'!$C$5:$C$424,"POD",'Seat Planner'!$D$5:$D$424,1)=0,"",(SUMIFS('Seat Planner'!$M$5:$M$424,'Seat Planner'!$B$5:$B$424,2,'Seat Planner'!$C$5:$C$424,"POD",'Seat Planner'!$D$5:$D$424,1,'Seat Planner'!$J$5:$J$424,"FTC")+SUMIFS('Seat Planner'!$M$5:$M$424,'Seat Planner'!$B$5:$B$424,2,'Seat Planner'!$C$5:$C$424,"POD",'Seat Planner'!$D$5:$D$424,1,'Seat Planner'!$J$5:$J$424,"PT"))/SUMIFS('Seat Planner'!$M$5:$M$424,'Seat Planner'!$B$5:$B$424,2,'Seat Planner'!$C$5:$C$424,"POD",'Seat Planner'!$D$5:$D$424,1)) | E54: =IF(SUMIFS('Seat Planner'!$M$5:$M$424,'Seat Planner'!$B$5:$B$424,3,'Seat Planner'!$C$5:$C$424,"POD",'Seat Planner'!$D$5:$D$424,1)=0,"",(SUMIFS('Seat Planner'!$M$5:$M$424,'Seat Planner'!$B$5:$B$424,3,'Seat Planner'!$C$5:$C$424,"POD",'Seat Planner'!$D$5:$D$424,1,'Seat Planner'!$J$5:$J$424,"FTC")+SUMIFS('Seat Planner'!$M$5:$M$424,'Seat Planner'!$B$5:$B$424,3,'Seat Planner'!$C$5:$C$424,"POD",'Seat Planner'!$D$5:$D$424,1,'Seat Planner'!$J$5:$J$424,"PT"))/SUMIFS('Seat Planner'!$M$5:$M$424,'Seat Planner'!$B$5:$B$424,3,'Seat Planner'!$C$5:$C$424,"POD",'Seat Planner'!$D$5:$D$424,1)) | F54: =IF(SUMIFS('Seat Planner'!$M$5:$M$424,'Seat Planner'!$B$5:$B$424,4,'Seat Planner'!$C$5:$C$424,"POD",'Seat Planner'!$D$5:$D$424,1)=0,"",(SUMIFS('Seat Planner'!$M$5:$M$424,'Seat Planner'!$B$5:$B$424,4,'Seat Planner'!$C$5:$C$424,"POD",'Seat Planner'!$D$5:$D$424,1,'Seat Planner'!$J$5:$J$424,"FTC")+SUMIFS('Seat Planner'!$M$5:$M$424,'Seat Planner'!$B$5:$B$424,4,'Seat Planner'!$C$5:$C$424,"POD",'Seat Planner'!$D$5:$D$424,1,'Seat Planner'!$J$5:$J$424,"PT"))/SUMIFS('Seat Planner'!$M$5:$M$424,'Seat Planner'!$B$5:$B$424,4,'Seat Planner'!$C$5:$C$424,"POD",'Seat Planner'!$D$5:$D$424,1)) | G54: =IF(SUMIFS('Seat Planner'!$M$5:$M$424,'Seat Planner'!$B$5:$B$424,5,'Seat Planner'!$C$5:$C$424,"POD",'Seat Planner'!$D$5:$D$424,1)=0,"",(SUMIFS('Seat Planner'!$M$5:$M$424,'Seat Planner'!$B$5:$B$424,5,'Seat Planner'!$C$5:$C$424,"POD",'Seat Planner'!$D$5:$D$424,1,'Seat Planner'!$J$5:$J$424,"FTC")+SUMIFS('Seat Planner'!$M$5:$M$424,'Seat Planner'!$B$5:$B$424,5,'Seat Planner'!$C$5:$C$424,"POD",'Seat Planner'!$D$5:$D$424,1,'Seat Planner'!$J$5:$J$424,"PT"))/SUMIFS('Seat Planner'!$M$5:$M$424,'Seat Planner'!$B$5:$B$424,5,'Seat Planner'!$C$5:$C$424,"POD",'Seat Planner'!$D$5:$D$424,1))
B55: Stream 1 · TEAM | C55: =IF(SUMIFS('Seat Planner'!$M$5:$M$424,'Seat Planner'!$B$5:$B$424,1,'Seat Planner'!$C$5:$C$424,"TEAM",'Seat Planner'!$D$5:$D$424,1)=0,"",(SUMIFS('Seat Planner'!$M$5:$M$424,'Seat Planner'!$B$5:$B$424,1,'Seat Planner'!$C$5:$C$424,"TEAM",'Seat Planner'!$D$5:$D$424,1,'Seat Planner'!$J$5:$J$424,"FTC")+SUMIFS('Seat Planner'!$M$5:$M$424,'Seat Planner'!$B$5:$B$424,1,'Seat Planner'!$C$5:$C$424,"TEAM",'Seat Planner'!$D$5:$D$424,1,'Seat Planner'!$J$5:$J$424,"PT"))/SUMIFS('Seat Planner'!$M$5:$M$424,'Seat Planner'!$B$5:$B$424,1,'Seat Planner'!$C$5:$C$424,"TEAM",'Seat Planner'!$D$5:$D$424,1)) | D55: =IF(SUMIFS('Seat Planner'!$M$5:$M$424,'Seat Planner'!$B$5:$B$424,2,'Seat Planner'!$C$5:$C$424,"TEAM",'Seat Planner'!$D$5:$D$424,1)=0,"",(SUMIFS('Seat Planner'!$M$5:$M$424,'Seat Planner'!$B$5:$B$424,2,'Seat Planner'!$C$5:$C$424,"TEAM",'Seat Planner'!$D$5:$D$424,1,'Seat Planner'!$J$5:$J$424,"FTC")+SUMIFS('Seat Planner'!$M$5:$M$424,'Seat Planner'!$B$5:$B$424,2,'Seat Planner'!$C$5:$C$424,"TEAM",'Seat Planner'!$D$5:$D$424,1,'Seat Planner'!$J$5:$J$424,"PT"))/SUMIFS('Seat Planner'!$M$5:$M$424,'Seat Planner'!$B$5:$B$424,2,'Seat Planner'!$C$5:$C$424,"TEAM",'Seat Planner'!$D$5:$D$424,1)) | E55: =IF(SUMIFS('Seat Planner'!$M$5:$M$424,'Seat Planner'!$B$5:$B$424,3,'Seat Planner'!$C$5:$C$424,"TEAM",'Seat Planner'!$D$5:$D$424,1)=0,"",(SUMIFS('Seat Planner'!$M$5:$M$424,'Seat Planner'!$B$5:$B$424,3,'Seat Planner'!$C$5:$C$424,"TEAM",'Seat Planner'!$D$5:$D$424,1,'Seat Planner'!$J$5:$J$424,"FTC")+SUMIFS('Seat Planner'!$M$5:$M$424,'Seat Planner'!$B$5:$B$424,3,'Seat Planner'!$C$5:$C$424,"TEAM",'Seat Planner'!$D$5:$D$424,1,'Seat Planner'!$J$5:$J$424,"PT"))/SUMIFS('Seat Planner'!$M$5:$M$424,'Seat Planner'!$B$5:$B$424,3,'Seat Planner'!$C$5:$C$424,"TEAM",'Seat Planner'!$D$5:$D$424,1)) | F55: =IF(SUMIFS('Seat Planner'!$M$5:$M$424,'Seat Planner'!$B$5:$B$424,4,'Seat Planner'!$C$5:$C$424,"TEAM",'Seat Planner'!$D$5:$D$424,1)=0,"",(SUMIFS('Seat Planner'!$M$5:$M$424,'Seat Planner'!$B$5:$B$424,4,'Seat Planner'!$C$5:$C$424,"TEAM",'Seat Planner'!$D$5:$D$424,1,'Seat Planner'!$J$5:$J$424,"FTC")+SUMIFS('Seat Planner'!$M$5:$M$424,'Seat Planner'!$B$5:$B$424,4,'Seat Planner'!$C$5:$C$424,"TEAM",'Seat Planner'!$D$5:$D$424,1,'Seat Planner'!$J$5:$J$424,"PT"))/SUMIFS('Seat Planner'!$M$5:$M$424,'Seat Planner'!$B$5:$B$424,4,'Seat Planner'!$C$5:$C$424,"TEAM",'Seat Planner'!$D$5:$D$424,1)) | G55: =IF(SUMIFS('Seat Planner'!$M$5:$M$424,'Seat Planner'!$B$5:$B$424,5,'Seat Planner'!$C$5:$C$424,"TEAM",'Seat Planner'!$D$5:$D$424,1)=0,"",(SUMIFS('Seat Planner'!$M$5:$M$424,'Seat Planner'!$B$5:$B$424,5,'Seat Planner'!$C$5:$C$424,"TEAM",'Seat Planner'!$D$5:$D$424,1,'Seat Planner'!$J$5:$J$424,"FTC")+SUMIFS('Seat Planner'!$M$5:$M$424,'Seat Planner'!$B$5:$B$424,5,'Seat Planner'!$C$5:$C$424,"TEAM",'Seat Planner'!$D$5:$D$424,1,'Seat Planner'!$J$5:$J$424,"PT"))/SUMIFS('Seat Planner'!$M$5:$M$424,'Seat Planner'!$B$5:$B$424,5,'Seat Planner'!$C$5:$C$424,"TEAM",'Seat Planner'!$D$5:$D$424,1))
B56: Stream 2 · POD | C56: =IF(SUMIFS('Seat Planner'!$M$5:$M$424,'Seat Planner'!$B$5:$B$424,1,'Seat Planner'!$C$5:$C$424,"POD",'Seat Planner'!$D$5:$D$424,2)=0,"",(SUMIFS('Seat Planner'!$M$5:$M$424,'Seat Planner'!$B$5:$B$424,1,'Seat Planner'!$C$5:$C$424,"POD",'Seat Planner'!$D$5:$D$424,2,'Seat Planner'!$J$5:$J$424,"FTC")+SUMIFS('Seat Planner'!$M$5:$M$424,'Seat Planner'!$B$5:$B$424,1,'Seat Planner'!$C$5:$C$424,"POD",'Seat Planner'!$D$5:$D$424,2,'Seat Planner'!$J$5:$J$424,"PT"))/SUMIFS('Seat Planner'!$M$5:$M$424,'Seat Planner'!$B$5:$B$424,1,'Seat Planner'!$C$5:$C$424,"POD",'Seat Planner'!$D$5:$D$424,2)) | D56: =IF(SUMIFS('Seat Planner'!$M$5:$M$424,'Seat Planner'!$B$5:$B$424,2,'Seat Planner'!$C$5:$C$424,"POD",'Seat Planner'!$D$5:$D$424,2)=0,"",(SUMIFS('Seat Planner'!$M$5:$M$424,'Seat Planner'!$B$5:$B$424,2,'Seat Planner'!$C$5:$C$424,"POD",'Seat Planner'!$D$5:$D$424,2,'Seat Planner'!$J$5:$J$424,"FTC")+SUMIFS('Seat Planner'!$M$5:$M$424,'Seat Planner'!$B$5:$B$424,2,'Seat Planner'!$C$5:$C$424,"POD",'Seat Planner'!$D$5:$D$424,2,'Seat Planner'!$J$5:$J$424,"PT"))/SUMIFS('Seat Planner'!$M$5:$M$424,'Seat Planner'!$B$5:$B$424,2,'Seat Planner'!$C$5:$C$424,"POD",'Seat Planner'!$D$5:$D$424,2)) | E56: =IF(SUMIFS('Seat Planner'!$M$5:$M$424,'Seat Planner'!$B$5:$B$424,3,'Seat Planner'!$C$5:$C$424,"POD",'Seat Planner'!$D$5:$D$424,2)=0,"",(SUMIFS('Seat Planner'!$M$5:$M$424,'Seat Planner'!$B$5:$B$424,3,'Seat Planner'!$C$5:$C$424,"POD",'Seat Planner'!$D$5:$D$424,2,'Seat Planner'!$J$5:$J$424,"FTC")+SUMIFS('Seat Planner'!$M$5:$M$424,'Seat Planner'!$B$5:$B$424,3,'Seat Planner'!$C$5:$C$424,"POD",'Seat Planner'!$D$5:$D$424,2,'Seat Planner'!$J$5:$J$424,"PT"))/SUMIFS('Seat Planner'!$M$5:$M$424,'Seat Planner'!$B$5:$B$424,3,'Seat Planner'!$C$5:$C$424,"POD",'Seat Planner'!$D$5:$D$424,2)) | F56: =IF(SUMIFS('Seat Planner'!$M$5:$M$424,'Seat Planner'!$B$5:$B$424,4,'Seat Planner'!$C$5:$C$424,"POD",'Seat Planner'!$D$5:$D$424,2)=0,"",(SUMIFS('Seat Planner'!$M$5:$M$424,'Seat Planner'!$B$5:$B$424,4,'Seat Planner'!$C$5:$C$424,"POD",'Seat Planner'!$D$5:$D$424,2,'Seat Planner'!$J$5:$J$424,"FTC")+SUMIFS('Seat Planner'!$M$5:$M$424,'Seat Planner'!$B$5:$B$424,4,'Seat Planner'!$C$5:$C$424,"POD",'Seat Planner'!$D$5:$D$424,2,'Seat Planner'!$J$5:$J$424,"PT"))/SUMIFS('Seat Planner'!$M$5:$M$424,'Seat Planner'!$B$5:$B$424,4,'Seat Planner'!$C$5:$C$424,"POD",'Seat Planner'!$D$5:$D$424,2)) | G56: =IF(SUMIFS('Seat Planner'!$M$5:$M$424,'Seat Planner'!$B$5:$B$424,5,'Seat Planner'!$C$5:$C$424,"POD",'Seat Planner'!$D$5:$D$424,2)=0,"",(SUMIFS('Seat Planner'!$M$5:$M$424,'Seat Planner'!$B$5:$B$424,5,'Seat Planner'!$C$5:$C$424,"POD",'Seat Planner'!$D$5:$D$424,2,'Seat Planner'!$J$5:$J$424,"FTC")+SUMIFS('Seat Planner'!$M$5:$M$424,'Seat Planner'!$B$5:$B$424,5,'Seat Planner'!$C$5:$C$424,"POD",'Seat Planner'!$D$5:$D$424,2,'Seat Planner'!$J$5:$J$424,"PT"))/SUMIFS('Seat Planner'!$M$5:$M$424,'Seat Planner'!$B$5:$B$424,5,'Seat Planner'!$C$5:$C$424,"POD",'Seat Planner'!$D$5:$D$424,2))
B57: Stream 2 · TEAM | C57: =IF(SUMIFS('Seat Planner'!$M$5:$M$424,'Seat Planner'!$B$5:$B$424,1,'Seat Planner'!$C$5:$C$424,"TEAM",'Seat Planner'!$D$5:$D$424,2)=0,"",(SUMIFS('Seat Planner'!$M$5:$M$424,'Seat Planner'!$B$5:$B$424,1,'Seat Planner'!$C$5:$C$424,"TEAM",'Seat Planner'!$D$5:$D$424,2,'Seat Planner'!$J$5:$J$424,"FTC")+SUMIFS('Seat Planner'!$M$5:$M$424,'Seat Planner'!$B$5:$B$424,1,'Seat Planner'!$C$5:$C$424,"TEAM",'Seat Planner'!$D$5:$D$424,2,'Seat Planner'!$J$5:$J$424,"PT"))/SUMIFS('Seat Planner'!$M$5:$M$424,'Seat Planner'!$B$5:$B$424,1,'Seat Planner'!$C$5:$C$424,"TEAM",'Seat Planner'!$D$5:$D$424,2)) | D57: =IF(SUMIFS('Seat Planner'!$M$5:$M$424,'Seat Planner'!$B$5:$B$424,2,'Seat Planner'!$C$5:$C$424,"TEAM",'Seat Planner'!$D$5:$D$424,2)=0,"",(SUMIFS('Seat Planner'!$M$5:$M$424,'Seat Planner'!$B$5:$B$424,2,'Seat Planner'!$C$5:$C$424,"TEAM",'Seat Planner'!$D$5:$D$424,2,'Seat Planner'!$J$5:$J$424,"FTC")+SUMIFS('Seat Planner'!$M$5:$M$424,'Seat Planner'!$B$5:$B$424,2,'Seat Planner'!$C$5:$C$424,"TEAM",'Seat Planner'!$D$5:$D$424,2,'Seat Planner'!$J$5:$J$424,"PT"))/SUMIFS('Seat Planner'!$M$5:$M$424,'Seat Planner'!$B$5:$B$424,2,'Seat Planner'!$C$5:$C$424,"TEAM",'Seat Planner'!$D$5:$D$424,2)) | E57: =IF(SUMIFS('Seat Planner'!$M$5:$M$424,'Seat Planner'!$B$5:$B$424,3,'Seat Planner'!$C$5:$C$424,"TEAM",'Seat Planner'!$D$5:$D$424,2)=0,"",(SUMIFS('Seat Planner'!$M$5:$M$424,'Seat Planner'!$B$5:$B$424,3,'Seat Planner'!$C$5:$C$424,"TEAM",'Seat Planner'!$D$5:$D$424,2,'Seat Planner'!$J$5:$J$424,"FTC")+SUMIFS('Seat Planner'!$M$5:$M$424,'Seat Planner'!$B$5:$B$424,3,'Seat Planner'!$C$5:$C$424,"TEAM",'Seat Planner'!$D$5:$D$424,2,'Seat Planner'!$J$5:$J$424,"PT"))/SUMIFS('Seat Planner'!$M$5:$M$424,'Seat Planner'!$B$5:$B$424,3,'Seat Planner'!$C$5:$C$424,"TEAM",'Seat Planner'!$D$5:$D$424,2)) | F57: =IF(SUMIFS('Seat Planner'!$M$5:$M$424,'Seat Planner'!$B$5:$B$424,4,'Seat Planner'!$C$5:$C$424,"TEAM",'Seat Planner'!$D$5:$D$424,2)=0,"",(SUMIFS('Seat Planner'!$M$5:$M$424,'Seat Planner'!$B$5:$B$424,4,'Seat Planner'!$C$5:$C$424,"TEAM",'Seat Planner'!$D$5:$D$424,2,'Seat Planner'!$J$5:$J$424,"FTC")+SUMIFS('Seat Planner'!$M$5:$M$424,'Seat Planner'!$B$5:$B$424,4,'Seat Planner'!$C$5:$C$424,"TEAM",'Seat Planner'!$D$5:$D$424,2,'Seat Planner'!$J$5:$J$424,"PT"))/SUMIFS('Seat Planner'!$M$5:$M$424,'Seat Planner'!$B$5:$B$424,4,'Seat Planner'!$C$5:$C$424,"TEAM",'Seat Planner'!$D$5:$D$424,2)) | G57: =IF(SUMIFS('Seat Planner'!$M$5:$M$424,'Seat Planner'!$B$5:$B$424,5,'Seat Planner'!$C$5:$C$424,"TEAM",'Seat Planner'!$D$5:$D$424,2)=0,"",(SUMIFS('Seat Planner'!$M$5:$M$424,'Seat Planner'!$B$5:$B$424,5,'Seat Planner'!$C$5:$C$424,"TEAM",'Seat Planner'!$D$5:$D$424,2,'Seat Planner'!$J$5:$J$424,"FTC")+SUMIFS('Seat Planner'!$M$5:$M$424,'Seat Planner'!$B$5:$B$424,5,'Seat Planner'!$C$5:$C$424,"TEAM",'Seat Planner'!$D$5:$D$424,2,'Seat Planner'!$J$5:$J$424,"PT"))/SUMIFS('Seat Planner'!$M$5:$M$424,'Seat Planner'!$B$5:$B$424,5,'Seat Planner'!$C$5:$C$424,"TEAM",'Seat Planner'!$D$5:$D$424,2))
B58: Stream 3 · POD | C58: =IF(SUMIFS('Seat Planner'!$M$5:$M$424,'Seat Planner'!$B$5:$B$424,1,'Seat Planner'!$C$5:$C$424,"POD",'Seat Planner'!$D$5:$D$424,3)=0,"",(SUMIFS('Seat Planner'!$M$5:$M$424,'Seat Planner'!$B$5:$B$424,1,'Seat Planner'!$C$5:$C$424,"POD",'Seat Planner'!$D$5:$D$424,3,'Seat Planner'!$J$5:$J$424,"FTC")+SUMIFS('Seat Planner'!$M$5:$M$424,'Seat Planner'!$B$5:$B$424,1,'Seat Planner'!$C$5:$C$424,"POD",'Seat Planner'!$D$5:$D$424,3,'Seat Planner'!$J$5:$J$424,"PT"))/SUMIFS('Seat Planner'!$M$5:$M$424,'Seat Planner'!$B$5:$B$424,1,'Seat Planner'!$C$5:$C$424,"POD",'Seat Planner'!$D$5:$D$424,3)) | D58: =IF(SUMIFS('Seat Planner'!$M$5:$M$424,'Seat Planner'!$B$5:$B$424,2,'Seat Planner'!$C$5:$C$424,"POD",'Seat Planner'!$D$5:$D$424,3)=0,"",(SUMIFS('Seat Planner'!$M$5:$M$424,'Seat Planner'!$B$5:$B$424,2,'Seat Planner'!$C$5:$C$424,"POD",'Seat Planner'!$D$5:$D$424,3,'Seat Planner'!$J$5:$J$424,"FTC")+SUMIFS('Seat Planner'!$M$5:$M$424,'Seat Planner'!$B$5:$B$424,2,'Seat Planner'!$C$5:$C$424,"POD",'Seat Planner'!$D$5:$D$424,3,'Seat Planner'!$J$5:$J$424,"PT"))/SUMIFS('Seat Planner'!$M$5:$M$424,'Seat Planner'!$B$5:$B$424,2,'Seat Planner'!$C$5:$C$424,"POD",'Seat Planner'!$D$5:$D$424,3)) | E58: =IF(SUMIFS('Seat Planner'!$M$5:$M$424,'Seat Planner'!$B$5:$B$424,3,'Seat Planner'!$C$5:$C$424,"POD",'Seat Planner'!$D$5:$D$424,3)=0,"",(SUMIFS('Seat Planner'!$M$5:$M$424,'Seat Planner'!$B$5:$B$424,3,'Seat Planner'!$C$5:$C$424,"POD",'Seat Planner'!$D$5:$D$424,3,'Seat Planner'!$J$5:$J$424,"FTC")+SUMIFS('Seat Planner'!$M$5:$M$424,'Seat Planner'!$B$5:$B$424,3,'Seat Planner'!$C$5:$C$424,"POD",'Seat Planner'!$D$5:$D$424,3,'Seat Planner'!$J$5:$J$424,"PT"))/SUMIFS('Seat Planner'!$M$5:$M$424,'Seat Planner'!$B$5:$B$424,3,'Seat Planner'!$C$5:$C$424,"POD",'Seat Planner'!$D$5:$D$424,3)) | F58: =IF(SUMIFS('Seat Planner'!$M$5:$M$424,'Seat Planner'!$B$5:$B$424,4,'Seat Planner'!$C$5:$C$424,"POD",'Seat Planner'!$D$5:$D$424,3)=0,"",(SUMIFS('Seat Planner'!$M$5:$M$424,'Seat Planner'!$B$5:$B$424,4,'Seat Planner'!$C$5:$C$424,"POD",'Seat Planner'!$D$5:$D$424,3,'Seat Planner'!$J$5:$J$424,"FTC")+SUMIFS('Seat Planner'!$M$5:$M$424,'Seat Planner'!$B$5:$B$424,4,'Seat Planner'!$C$5:$C$424,"POD",'Seat Planner'!$D$5:$D$424,3,'Seat Planner'!$J$5:$J$424,"PT"))/SUMIFS('Seat Planner'!$M$5:$M$424,'Seat Planner'!$B$5:$B$424,4,'Seat Planner'!$C$5:$C$424,"POD",'Seat Planner'!$D$5:$D$424,3)) | G58: =IF(SUMIFS('Seat Planner'!$M$5:$M$424,'Seat Planner'!$B$5:$B$424,5,'Seat Planner'!$C$5:$C$424,"POD",'Seat Planner'!$D$5:$D$424,3)=0,"",(SUMIFS('Seat Planner'!$M$5:$M$424,'Seat Planner'!$B$5:$B$424,5,'Seat Planner'!$C$5:$C$424,"POD",'Seat Planner'!$D$5:$D$424,3,'Seat Planner'!$J$5:$J$424,"FTC")+SUMIFS('Seat Planner'!$M$5:$M$424,'Seat Planner'!$B$5:$B$424,5,'Seat Planner'!$C$5:$C$424,"POD",'Seat Planner'!$D$5:$D$424,3,'Seat Planner'!$J$5:$J$424,"PT"))/SUMIFS('Seat Planner'!$M$5:$M$424,'Seat Planner'!$B$5:$B$424,5,'Seat Planner'!$C$5:$C$424,"POD",'Seat Planner'!$D$5:$D$424,3))
B59: Stream 3 · TEAM | C59: =IF(SUMIFS('Seat Planner'!$M$5:$M$424,'Seat Planner'!$B$5:$B$424,1,'Seat Planner'!$C$5:$C$424,"TEAM",'Seat Planner'!$D$5:$D$424,3)=0,"",(SUMIFS('Seat Planner'!$M$5:$M$424,'Seat Planner'!$B$5:$B$424,1,'Seat Planner'!$C$5:$C$424,"TEAM",'Seat Planner'!$D$5:$D$424,3,'Seat Planner'!$J$5:$J$424,"FTC")+SUMIFS('Seat Planner'!$M$5:$M$424,'Seat Planner'!$B$5:$B$424,1,'Seat Planner'!$C$5:$C$424,"TEAM",'Seat Planner'!$D$5:$D$424,3,'Seat Planner'!$J$5:$J$424,"PT"))/SUMIFS('Seat Planner'!$M$5:$M$424,'Seat Planner'!$B$5:$B$424,1,'Seat Planner'!$C$5:$C$424,"TEAM",'Seat Planner'!$D$5:$D$424,3)) | D59: =IF(SUMIFS('Seat Planner'!$M$5:$M$424,'Seat Planner'!$B$5:$B$424,2,'Seat Planner'!$C$5:$C$424,"TEAM",'Seat Planner'!$D$5:$D$424,3)=0,"",(SUMIFS('Seat Planner'!$M$5:$M$424,'Seat Planner'!$B$5:$B$424,2,'Seat Planner'!$C$5:$C$424,"TEAM",'Seat Planner'!$D$5:$D$424,3,'Seat Planner'!$J$5:$J$424,"FTC")+SUMIFS('Seat Planner'!$M$5:$M$424,'Seat Planner'!$B$5:$B$424,2,'Seat Planner'!$C$5:$C$424,"TEAM",'Seat Planner'!$D$5:$D$424,3,'Seat Planner'!$J$5:$J$424,"PT"))/SUMIFS('Seat Planner'!$M$5:$M$424,'Seat Planner'!$B$5:$B$424,2,'Seat Planner'!$C$5:$C$424,"TEAM",'Seat Planner'!$D$5:$D$424,3)) | E59: =IF(SUMIFS('Seat Planner'!$M$5:$M$424,'Seat Planner'!$B$5:$B$424,3,'Seat Planner'!$C$5:$C$424,"TEAM",'Seat Planner'!$D$5:$D$424,3)=0,"",(SUMIFS('Seat Planner'!$M$5:$M$424,'Seat Planner'!$B$5:$B$424,3,'Seat Planner'!$C$5:$C$424,"TEAM",'Seat Planner'!$D$5:$D$424,3,'Seat Planner'!$J$5:$J$424,"FTC")+SUMIFS('Seat Planner'!$M$5:$M$424,'Seat Planner'!$B$5:$B$424,3,'Seat Planner'!$C$5:$C$424,"TEAM",'Seat Planner'!$D$5:$D$424,3,'Seat Planner'!$J$5:$J$424,"PT"))/SUMIFS('Seat Planner'!$M$5:$M$424,'Seat Planner'!$B$5:$B$424,3,'Seat Planner'!$C$5:$C$424,"TEAM",'Seat Planner'!$D$5:$D$424,3)) | F59: =IF(SUMIFS('Seat Planner'!$M$5:$M$424,'Seat Planner'!$B$5:$B$424,4,'Seat Planner'!$C$5:$C$424,"TEAM",'Seat Planner'!$D$5:$D$424,3)=0,"",(SUMIFS('Seat Planner'!$M$5:$M$424,'Seat Planner'!$B$5:$B$424,4,'Seat Planner'!$C$5:$C$424,"TEAM",'Seat Planner'!$D$5:$D$424,3,'Seat Planner'!$J$5:$J$424,"FTC")+SUMIFS('Seat Planner'!$M$5:$M$424,'Seat Planner'!$B$5:$B$424,4,'Seat Planner'!$C$5:$C$424,"TEAM",'Seat Planner'!$D$5:$D$424,3,'Seat Planner'!$J$5:$J$424,"PT"))/SUMIFS('Seat Planner'!$M$5:$M$424,'Seat Planner'!$B$5:$B$424,4,'Seat Planner'!$C$5:$C$424,"TEAM",'Seat Planner'!$D$5:$D$424,3)) | G59: =IF(SUMIFS('Seat Planner'!$M$5:$M$424,'Seat Planner'!$B$5:$B$424,5,'Seat Planner'!$C$5:$C$424,"TEAM",'Seat Planner'!$D$5:$D$424,3)=0,"",(SUMIFS('Seat Planner'!$M$5:$M$424,'Seat Planner'!$B$5:$B$424,5,'Seat Planner'!$C$5:$C$424,"TEAM",'Seat Planner'!$D$5:$D$424,3,'Seat Planner'!$J$5:$J$424,"FTC")+SUMIFS('Seat Planner'!$M$5:$M$424,'Seat Planner'!$B$5:$B$424,5,'Seat Planner'!$C$5:$C$424,"TEAM",'Seat Planner'!$D$5:$D$424,3,'Seat Planner'!$J$5:$J$424,"PT"))/SUMIFS('Seat Planner'!$M$5:$M$424,'Seat Planner'!$B$5:$B$424,5,'Seat Planner'!$C$5:$C$424,"TEAM",'Seat Planner'!$D$5:$D$424,3))
B60: Stream 4 · POD | C60: =IF(SUMIFS('Seat Planner'!$M$5:$M$424,'Seat Planner'!$B$5:$B$424,1,'Seat Planner'!$C$5:$C$424,"POD",'Seat Planner'!$D$5:$D$424,4)=0,"",(SUMIFS('Seat Planner'!$M$5:$M$424,'Seat Planner'!$B$5:$B$424,1,'Seat Planner'!$C$5:$C$424,"POD",'Seat Planner'!$D$5:$D$424,4,'Seat Planner'!$J$5:$J$424,"FTC")+SUMIFS('Seat Planner'!$M$5:$M$424,'Seat Planner'!$B$5:$B$424,1,'Seat Planner'!$C$5:$C$424,"POD",'Seat Planner'!$D$5:$D$424,4,'Seat Planner'!$J$5:$J$424,"PT"))/SUMIFS('Seat Planner'!$M$5:$M$424,'Seat Planner'!$B$5:$B$424,1,'Seat Planner'!$C$5:$C$424,"POD",'Seat Planner'!$D$5:$D$424,4)) | D60: =IF(SUMIFS('Seat Planner'!$M$5:$M$424,'Seat Planner'!$B$5:$B$424,2,'Seat Planner'!$C$5:$C$424,"POD",'Seat Planner'!$D$5:$D$424,4)=0,"",(SUMIFS('Seat Planner'!$M$5:$M$424,'Seat Planner'!$B$5:$B$424,2,'Seat Planner'!$C$5:$C$424,"POD",'Seat Planner'!$D$5:$D$424,4,'Seat Planner'!$J$5:$J$424,"FTC")+SUMIFS('Seat Planner'!$M$5:$M$424,'Seat Planner'!$B$5:$B$424,2,'Seat Planner'!$C$5:$C$424,"POD",'Seat Planner'!$D$5:$D$424,4,'Seat Planner'!$J$5:$J$424,"PT"))/SUMIFS('Seat Planner'!$M$5:$M$424,'Seat Planner'!$B$5:$B$424,2,'Seat Planner'!$C$5:$C$424,"POD",'Seat Planner'!$D$5:$D$424,4)) | E60: =IF(SUMIFS('Seat Planner'!$M$5:$M$424,'Seat Planner'!$B$5:$B$424,3,'Seat Planner'!$C$5:$C$424,"POD",'Seat Planner'!$D$5:$D$424,4)=0,"",(SUMIFS('Seat Planner'!$M$5:$M$424,'Seat Planner'!$B$5:$B$424,3,'Seat Planner'!$C$5:$C$424,"POD",'Seat Planner'!$D$5:$D$424,4,'Seat Planner'!$J$5:$J$424,"FTC")+SUMIFS('Seat Planner'!$M$5:$M$424,'Seat Planner'!$B$5:$B$424,3,'Seat Planner'!$C$5:$C$424,"POD",'Seat Planner'!$D$5:$D$424,4,'Seat Planner'!$J$5:$J$424,"PT"))/SUMIFS('Seat Planner'!$M$5:$M$424,'Seat Planner'!$B$5:$B$424,3,'Seat Planner'!$C$5:$C$424,"POD",'Seat Planner'!$D$5:$D$424,4)) | F60: =IF(SUMIFS('Seat Planner'!$M$5:$M$424,'Seat Planner'!$B$5:$B$424,4,'Seat Planner'!$C$5:$C$424,"POD",'Seat Planner'!$D$5:$D$424,4)=0,"",(SUMIFS('Seat Planner'!$M$5:$M$424,'Seat Planner'!$B$5:$B$424,4,'Seat Planner'!$C$5:$C$424,"POD",'Seat Planner'!$D$5:$D$424,4,'Seat Planner'!$J$5:$J$424,"FTC")+SUMIFS('Seat Planner'!$M$5:$M$424,'Seat Planner'!$B$5:$B$424,4,'Seat Planner'!$C$5:$C$424,"POD",'Seat Planner'!$D$5:$D$424,4,'Seat Planner'!$J$5:$J$424,"PT"))/SUMIFS('Seat Planner'!$M$5:$M$424,'Seat Planner'!$B$5:$B$424,4,'Seat Planner'!$C$5:$C$424,"POD",'Seat Planner'!$D$5:$D$424,4)) | G60: =IF(SUMIFS('Seat Planner'!$M$5:$M$424,'Seat Planner'!$B$5:$B$424,5,'Seat Planner'!$C$5:$C$424,"POD",'Seat Planner'!$D$5:$D$424,4)=0,"",(SUMIFS('Seat Planner'!$M$5:$M$424,'Seat Planner'!$B$5:$B$424,5,'Seat Planner'!$C$5:$C$424,"POD",'Seat Planner'!$D$5:$D$424,4,'Seat Planner'!$J$5:$J$424,"FTC")+SUMIFS('Seat Planner'!$M$5:$M$424,'Seat Planner'!$B$5:$B$424,5,'Seat Planner'!$C$5:$C$424,"POD",'Seat Planner'!$D$5:$D$424,4,'Seat Planner'!$J$5:$J$424,"PT"))/SUMIFS('Seat Planner'!$M$5:$M$424,'Seat Planner'!$B$5:$B$424,5,'Seat Planner'!$C$5:$C$424,"POD",'Seat Planner'!$D$5:$D$424,4))
B61: Stream 4 · TEAM | C61: =IF(SUMIFS('Seat Planner'!$M$5:$M$424,'Seat Planner'!$B$5:$B$424,1,'Seat Planner'!$C$5:$C$424,"TEAM",'Seat Planner'!$D$5:$D$424,4)=0,"",(SUMIFS('Seat Planner'!$M$5:$M$424,'Seat Planner'!$B$5:$B$424,1,'Seat Planner'!$C$5:$C$424,"TEAM",'Seat Planner'!$D$5:$D$424,4,'Seat Planner'!$J$5:$J$424,"FTC")+SUMIFS('Seat Planner'!$M$5:$M$424,'Seat Planner'!$B$5:$B$424,1,'Seat Planner'!$C$5:$C$424,"TEAM",'Seat Planner'!$D$5:$D$424,4,'Seat Planner'!$J$5:$J$424,"PT"))/SUMIFS('Seat Planner'!$M$5:$M$424,'Seat Planner'!$B$5:$B$424,1,'Seat Planner'!$C$5:$C$424,"TEAM",'Seat Planner'!$D$5:$D$424,4)) | D61: =IF(SUMIFS('Seat Planner'!$M$5:$M$424,'Seat Planner'!$B$5:$B$424,2,'Seat Planner'!$C$5:$C$424,"TEAM",'Seat Planner'!$D$5:$D$424,4)=0,"",(SUMIFS('Seat Planner'!$M$5:$M$424,'Seat Planner'!$B$5:$B$424,2,'Seat Planner'!$C$5:$C$424,"TEAM",'Seat Planner'!$D$5:$D$424,4,'Seat Planner'!$J$5:$J$424,"FTC")+SUMIFS('Seat Planner'!$M$5:$M$424,'Seat Planner'!$B$5:$B$424,2,'Seat Planner'!$C$5:$C$424,"TEAM",'Seat Planner'!$D$5:$D$424,4,'Seat Planner'!$J$5:$J$424,"PT"))/SUMIFS('Seat Planner'!$M$5:$M$424,'Seat Planner'!$B$5:$B$424,2,'Seat Planner'!$C$5:$C$424,"TEAM",'Seat Planner'!$D$5:$D$424,4)) | E61: =IF(SUMIFS('Seat Planner'!$M$5:$M$424,'Seat Planner'!$B$5:$B$424,3,'Seat Planner'!$C$5:$C$424,"TEAM",'Seat Planner'!$D$5:$D$424,4)=0,"",(SUMIFS('Seat Planner'!$M$5:$M$424,'Seat Planner'!$B$5:$B$424,3,'Seat Planner'!$C$5:$C$424,"TEAM",'Seat Planner'!$D$5:$D$424,4,'Seat Planner'!$J$5:$J$424,"FTC")+SUMIFS('Seat Planner'!$M$5:$M$424,'Seat Planner'!$B$5:$B$424,3,'Seat Planner'!$C$5:$C$424,"TEAM",'Seat Planner'!$D$5:$D$424,4,'Seat Planner'!$J$5:$J$424,"PT"))/SUMIFS('Seat Planner'!$M$5:$M$424,'Seat Planner'!$B$5:$B$424,3,'Seat Planner'!$C$5:$C$424,"TEAM",'Seat Planner'!$D$5:$D$424,4)) | F61: =IF(SUMIFS('Seat Planner'!$M$5:$M$424,'Seat Planner'!$B$5:$B$424,4,'Seat Planner'!$C$5:$C$424,"TEAM",'Seat Planner'!$D$5:$D$424,4)=0,"",(SUMIFS('Seat Planner'!$M$5:$M$424,'Seat Planner'!$B$5:$B$424,4,'Seat Planner'!$C$5:$C$424,"TEAM",'Seat Planner'!$D$5:$D$424,4,'Seat Planner'!$J$5:$J$424,"FTC")+SUMIFS('Seat Planner'!$M$5:$M$424,'Seat Planner'!$B$5:$B$424,4,'Seat Planner'!$C$5:$C$424,"TEAM",'Seat Planner'!$D$5:$D$424,4,'Seat Planner'!$J$5:$J$424,"PT"))/SUMIFS('Seat Planner'!$M$5:$M$424,'Seat Planner'!$B$5:$B$424,4,'Seat Planner'!$C$5:$C$424,"TEAM",'Seat Planner'!$D$5:$D$424,4)) | G61: =IF(SUMIFS('Seat Planner'!$M$5:$M$424,'Seat Planner'!$B$5:$B$424,5,'Seat Planner'!$C$5:$C$424,"TEAM",'Seat Planner'!$D$5:$D$424,4)=0,"",(SUMIFS('Seat Planner'!$M$5:$M$424,'Seat Planner'!$B$5:$B$424,5,'Seat Planner'!$C$5:$C$424,"TEAM",'Seat Planner'!$D$5:$D$424,4,'Seat Planner'!$J$5:$J$424,"FTC")+SUMIFS('Seat Planner'!$M$5:$M$424,'Seat Planner'!$B$5:$B$424,5,'Seat Planner'!$C$5:$C$424,"TEAM",'Seat Planner'!$D$5:$D$424,4,'Seat Planner'!$J$5:$J$424,"PT"))/SUMIFS('Seat Planner'!$M$5:$M$424,'Seat Planner'!$B$5:$B$424,5,'Seat Planner'!$C$5:$C$424,"TEAM",'Seat Planner'!$D$5:$D$424,4))
B62: Stream 5 · POD | C62: =IF(SUMIFS('Seat Planner'!$M$5:$M$424,'Seat Planner'!$B$5:$B$424,1,'Seat Planner'!$C$5:$C$424,"POD",'Seat Planner'!$D$5:$D$424,5)=0,"",(SUMIFS('Seat Planner'!$M$5:$M$424,'Seat Planner'!$B$5:$B$424,1,'Seat Planner'!$C$5:$C$424,"POD",'Seat Planner'!$D$5:$D$424,5,'Seat Planner'!$J$5:$J$424,"FTC")+SUMIFS('Seat Planner'!$M$5:$M$424,'Seat Planner'!$B$5:$B$424,1,'Seat Planner'!$C$5:$C$424,"POD",'Seat Planner'!$D$5:$D$424,5,'Seat Planner'!$J$5:$J$424,"PT"))/SUMIFS('Seat Planner'!$M$5:$M$424,'Seat Planner'!$B$5:$B$424,1,'Seat Planner'!$C$5:$C$424,"POD",'Seat Planner'!$D$5:$D$424,5)) | D62: =IF(SUMIFS('Seat Planner'!$M$5:$M$424,'Seat Planner'!$B$5:$B$424,2,'Seat Planner'!$C$5:$C$424,"POD",'Seat Planner'!$D$5:$D$424,5)=0,"",(SUMIFS('Seat Planner'!$M$5:$M$424,'Seat Planner'!$B$5:$B$424,2,'Seat Planner'!$C$5:$C$424,"POD",'Seat Planner'!$D$5:$D$424,5,'Seat Planner'!$J$5:$J$424,"FTC")+SUMIFS('Seat Planner'!$M$5:$M$424,'Seat Planner'!$B$5:$B$424,2,'Seat Planner'!$C$5:$C$424,"POD",'Seat Planner'!$D$5:$D$424,5,'Seat Planner'!$J$5:$J$424,"PT"))/SUMIFS('Seat Planner'!$M$5:$M$424,'Seat Planner'!$B$5:$B$424,2,'Seat Planner'!$C$5:$C$424,"POD",'Seat Planner'!$D$5:$D$424,5)) | E62: =IF(SUMIFS('Seat Planner'!$M$5:$M$424,'Seat Planner'!$B$5:$B$424,3,'Seat Planner'!$C$5:$C$424,"POD",'Seat Planner'!$D$5:$D$424,5)=0,"",(SUMIFS('Seat Planner'!$M$5:$M$424,'Seat Planner'!$B$5:$B$424,3,'Seat Planner'!$C$5:$C$424,"POD",'Seat Planner'!$D$5:$D$424,5,'Seat Planner'!$J$5:$J$424,"FTC")+SUMIFS('Seat Planner'!$M$5:$M$424,'Seat Planner'!$B$5:$B$424,3,'Seat Planner'!$C$5:$C$424,"POD",'Seat Planner'!$D$5:$D$424,5,'Seat Planner'!$J$5:$J$424,"PT"))/SUMIFS('Seat Planner'!$M$5:$M$424,'Seat Planner'!$B$5:$B$424,3,'Seat Planner'!$C$5:$C$424,"POD",'Seat Planner'!$D$5:$D$424,5)) | F62: =IF(SUMIFS('Seat Planner'!$M$5:$M$424,'Seat Planner'!$B$5:$B$424,4,'Seat Planner'!$C$5:$C$424,"POD",'Seat Planner'!$D$5:$D$424,5)=0,"",(SUMIFS('Seat Planner'!$M$5:$M$424,'Seat Planner'!$B$5:$B$424,4,'Seat Planner'!$C$5:$C$424,"POD",'Seat Planner'!$D$5:$D$424,5,'Seat Planner'!$J$5:$J$424,"FTC")+SUMIFS('Seat Planner'!$M$5:$M$424,'Seat Planner'!$B$5:$B$424,4,'Seat Planner'!$C$5:$C$424,"POD",'Seat Planner'!$D$5:$D$424,5,'Seat Planner'!$J$5:$J$424,"PT"))/SUMIFS('Seat Planner'!$M$5:$M$424,'Seat Planner'!$B$5:$B$424,4,'Seat Planner'!$C$5:$C$424,"POD",'Seat Planner'!$D$5:$D$424,5)) | G62: =IF(SUMIFS('Seat Planner'!$M$5:$M$424,'Seat Planner'!$B$5:$B$424,5,'Seat Planner'!$C$5:$C$424,"POD",'Seat Planner'!$D$5:$D$424,5)=0,"",(SUMIFS('Seat Planner'!$M$5:$M$424,'Seat Planner'!$B$5:$B$424,5,'Seat Planner'!$C$5:$C$424,"POD",'Seat Planner'!$D$5:$D$424,5,'Seat Planner'!$J$5:$J$424,"FTC")+SUMIFS('Seat Planner'!$M$5:$M$424,'Seat Planner'!$B$5:$B$424,5,'Seat Planner'!$C$5:$C$424,"POD",'Seat Planner'!$D$5:$D$424,5,'Seat Planner'!$J$5:$J$424,"PT"))/SUMIFS('Seat Planner'!$M$5:$M$424,'Seat Planner'!$B$5:$B$424,5,'Seat Planner'!$C$5:$C$424,"POD",'Seat Planner'!$D$5:$D$424,5))
B63: Stream 5 · TEAM | C63: =IF(SUMIFS('Seat Planner'!$M$5:$M$424,'Seat Planner'!$B$5:$B$424,1,'Seat Planner'!$C$5:$C$424,"TEAM",'Seat Planner'!$D$5:$D$424,5)=0,"",(SUMIFS('Seat Planner'!$M$5:$M$424,'Seat Planner'!$B$5:$B$424,1,'Seat Planner'!$C$5:$C$424,"TEAM",'Seat Planner'!$D$5:$D$424,5,'Seat Planner'!$J$5:$J$424,"FTC")+SUMIFS('Seat Planner'!$M$5:$M$424,'Seat Planner'!$B$5:$B$424,1,'Seat Planner'!$C$5:$C$424,"TEAM",'Seat Planner'!$D$5:$D$424,5,'Seat Planner'!$J$5:$J$424,"PT"))/SUMIFS('Seat Planner'!$M$5:$M$424,'Seat Planner'!$B$5:$B$424,1,'Seat Planner'!$C$5:$C$424,"TEAM",'Seat Planner'!$D$5:$D$424,5)) | D63: =IF(SUMIFS('Seat Planner'!$M$5:$M$424,'Seat Planner'!$B$5:$B$424,2,'Seat Planner'!$C$5:$C$424,"TEAM",'Seat Planner'!$D$5:$D$424,5)=0,"",(SUMIFS('Seat Planner'!$M$5:$M$424,'Seat Planner'!$B$5:$B$424,2,'Seat Planner'!$C$5:$C$424,"TEAM",'Seat Planner'!$D$5:$D$424,5,'Seat Planner'!$J$5:$J$424,"FTC")+SUMIFS('Seat Planner'!$M$5:$M$424,'Seat Planner'!$B$5:$B$424,2,'Seat Planner'!$C$5:$C$424,"TEAM",'Seat Planner'!$D$5:$D$424,5,'Seat Planner'!$J$5:$J$424,"PT"))/SUMIFS('Seat Planner'!$M$5:$M$424,'Seat Planner'!$B$5:$B$424,2,'Seat Planner'!$C$5:$C$424,"TEAM",'Seat Planner'!$D$5:$D$424,5)) | E63: =IF(SUMIFS('Seat Planner'!$M$5:$M$424,'Seat Planner'!$B$5:$B$424,3,'Seat Planner'!$C$5:$C$424,"TEAM",'Seat Planner'!$D$5:$D$424,5)=0,"",(SUMIFS('Seat Planner'!$M$5:$M$424,'Seat Planner'!$B$5:$B$424,3,'Seat Planner'!$C$5:$C$424,"TEAM",'Seat Planner'!$D$5:$D$424,5,'Seat Planner'!$J$5:$J$424,"FTC")+SUMIFS('Seat Planner'!$M$5:$M$424,'Seat Planner'!$B$5:$B$424,3,'Seat Planner'!$C$5:$C$424,"TEAM",'Seat Planner'!$D$5:$D$424,5,'Seat Planner'!$J$5:$J$424,"PT"))/SUMIFS('Seat Planner'!$M$5:$M$424,'Seat Planner'!$B$5:$B$424,3,'Seat Planner'!$C$5:$C$424,"TEAM",'Seat Planner'!$D$5:$D$424,5)) | F63: =IF(SUMIFS('Seat Planner'!$M$5:$M$424,'Seat Planner'!$B$5:$B$424,4,'Seat Planner'!$C$5:$C$424,"TEAM",'Seat Planner'!$D$5:$D$424,5)=0,"",(SUMIFS('Seat Planner'!$M$5:$M$424,'Seat Planner'!$B$5:$B$424,4,'Seat Planner'!$C$5:$C$424,"TEAM",'Seat Planner'!$D$5:$D$424,5,'Seat Planner'!$J$5:$J$424,"FTC")+SUMIFS('Seat Planner'!$M$5:$M$424,'Seat Planner'!$B$5:$B$424,4,'Seat Planner'!$C$5:$C$424,"TEAM",'Seat Planner'!$D$5:$D$424,5,'Seat Planner'!$J$5:$J$424,"PT"))/SUMIFS('Seat Planner'!$M$5:$M$424,'Seat Planner'!$B$5:$B$424,4,'Seat Planner'!$C$5:$C$424,"TEAM",'Seat Planner'!$D$5:$D$424,5)) | G63: =IF(SUMIFS('Seat Planner'!$M$5:$M$424,'Seat Planner'!$B$5:$B$424,5,'Seat Planner'!$C$5:$C$424,"TEAM",'Seat Planner'!$D$5:$D$424,5)=0,"",(SUMIFS('Seat Planner'!$M$5:$M$424,'Seat Planner'!$B$5:$B$424,5,'Seat Planner'!$C$5:$C$424,"TEAM",'Seat Planner'!$D$5:$D$424,5,'Seat Planner'!$J$5:$J$424,"FTC")+SUMIFS('Seat Planner'!$M$5:$M$424,'Seat Planner'!$B$5:$B$424,5,'Seat Planner'!$C$5:$C$424,"TEAM",'Seat Planner'!$D$5:$D$424,5,'Seat Planner'!$J$5:$J$424,"PT"))/SUMIFS('Seat Planner'!$M$5:$M$424,'Seat Planner'!$B$5:$B$424,5,'Seat Planner'!$C$5:$C$424,"TEAM",'Seat Planner'!$D$5:$D$424,5))
B64: Stream 6 · POD | C64: =IF(SUMIFS('Seat Planner'!$M$5:$M$424,'Seat Planner'!$B$5:$B$424,1,'Seat Planner'!$C$5:$C$424,"POD",'Seat Planner'!$D$5:$D$424,6)=0,"",(SUMIFS('Seat Planner'!$M$5:$M$424,'Seat Planner'!$B$5:$B$424,1,'Seat Planner'!$C$5:$C$424,"POD",'Seat Planner'!$D$5:$D$424,6,'Seat Planner'!$J$5:$J$424,"FTC")+SUMIFS('Seat Planner'!$M$5:$M$424,'Seat Planner'!$B$5:$B$424,1,'Seat Planner'!$C$5:$C$424,"POD",'Seat Planner'!$D$5:$D$424,6,'Seat Planner'!$J$5:$J$424,"PT"))/SUMIFS('Seat Planner'!$M$5:$M$424,'Seat Planner'!$B$5:$B$424,1,'Seat Planner'!$C$5:$C$424,"POD",'Seat Planner'!$D$5:$D$424,6)) | D64: =IF(SUMIFS('Seat Planner'!$M$5:$M$424,'Seat Planner'!$B$5:$B$424,2,'Seat Planner'!$C$5:$C$424,"POD",'Seat Planner'!$D$5:$D$424,6)=0,"",(SUMIFS('Seat Planner'!$M$5:$M$424,'Seat Planner'!$B$5:$B$424,2,'Seat Planner'!$C$5:$C$424,"POD",'Seat Planner'!$D$5:$D$424,6,'Seat Planner'!$J$5:$J$424,"FTC")+SUMIFS('Seat Planner'!$M$5:$M$424,'Seat Planner'!$B$5:$B$424,2,'Seat Planner'!$C$5:$C$424,"POD",'Seat Planner'!$D$5:$D$424,6,'Seat Planner'!$J$5:$J$424,"PT"))/SUMIFS('Seat Planner'!$M$5:$M$424,'Seat Planner'!$B$5:$B$424,2,'Seat Planner'!$C$5:$C$424,"POD",'Seat Planner'!$D$5:$D$424,6)) | E64: =IF(SUMIFS('Seat Planner'!$M$5:$M$424,'Seat Planner'!$B$5:$B$424,3,'Seat Planner'!$C$5:$C$424,"POD",'Seat Planner'!$D$5:$D$424,6)=0,"",(SUMIFS('Seat Planner'!$M$5:$M$424,'Seat Planner'!$B$5:$B$424,3,'Seat Planner'!$C$5:$C$424,"POD",'Seat Planner'!$D$5:$D$424,6,'Seat Planner'!$J$5:$J$424,"FTC")+SUMIFS('Seat Planner'!$M$5:$M$424,'Seat Planner'!$B$5:$B$424,3,'Seat Planner'!$C$5:$C$424,"POD",'Seat Planner'!$D$5:$D$424,6,'Seat Planner'!$J$5:$J$424,"PT"))/SUMIFS('Seat Planner'!$M$5:$M$424,'Seat Planner'!$B$5:$B$424,3,'Seat Planner'!$C$5:$C$424,"POD",'Seat Planner'!$D$5:$D$424,6)) | F64: =IF(SUMIFS('Seat Planner'!$M$5:$M$424,'Seat Planner'!$B$5:$B$424,4,'Seat Planner'!$C$5:$C$424,"POD",'Seat Planner'!$D$5:$D$424,6)=0,"",(SUMIFS('Seat Planner'!$M$5:$M$424,'Seat Planner'!$B$5:$B$424,4,'Seat Planner'!$C$5:$C$424,"POD",'Seat Planner'!$D$5:$D$424,6,'Seat Planner'!$J$5:$J$424,"FTC")+SUMIFS('Seat Planner'!$M$5:$M$424,'Seat Planner'!$B$5:$B$424,4,'Seat Planner'!$C$5:$C$424,"POD",'Seat Planner'!$D$5:$D$424,6,'Seat Planner'!$J$5:$J$424,"PT"))/SUMIFS('Seat Planner'!$M$5:$M$424,'Seat Planner'!$B$5:$B$424,4,'Seat Planner'!$C$5:$C$424,"POD",'Seat Planner'!$D$5:$D$424,6)) | G64: =IF(SUMIFS('Seat Planner'!$M$5:$M$424,'Seat Planner'!$B$5:$B$424,5,'Seat Planner'!$C$5:$C$424,"POD",'Seat Planner'!$D$5:$D$424,6)=0,"",(SUMIFS('Seat Planner'!$M$5:$M$424,'Seat Planner'!$B$5:$B$424,5,'Seat Planner'!$C$5:$C$424,"POD",'Seat Planner'!$D$5:$D$424,6,'Seat Planner'!$J$5:$J$424,"FTC")+SUMIFS('Seat Planner'!$M$5:$M$424,'Seat Planner'!$B$5:$B$424,5,'Seat Planner'!$C$5:$C$424,"POD",'Seat Planner'!$D$5:$D$424,6,'Seat Planner'!$J$5:$J$424,"PT"))/SUMIFS('Seat Planner'!$M$5:$M$424,'Seat Planner'!$B$5:$B$424,5,'Seat Planner'!$C$5:$C$424,"POD",'Seat Planner'!$D$5:$D$424,6))
B65: Stream 6 · TEAM | C65: =IF(SUMIFS('Seat Planner'!$M$5:$M$424,'Seat Planner'!$B$5:$B$424,1,'Seat Planner'!$C$5:$C$424,"TEAM",'Seat Planner'!$D$5:$D$424,6)=0,"",(SUMIFS('Seat Planner'!$M$5:$M$424,'Seat Planner'!$B$5:$B$424,1,'Seat Planner'!$C$5:$C$424,"TEAM",'Seat Planner'!$D$5:$D$424,6,'Seat Planner'!$J$5:$J$424,"FTC")+SUMIFS('Seat Planner'!$M$5:$M$424,'Seat Planner'!$B$5:$B$424,1,'Seat Planner'!$C$5:$C$424,"TEAM",'Seat Planner'!$D$5:$D$424,6,'Seat Planner'!$J$5:$J$424,"PT"))/SUMIFS('Seat Planner'!$M$5:$M$424,'Seat Planner'!$B$5:$B$424,1,'Seat Planner'!$C$5:$C$424,"TEAM",'Seat Planner'!$D$5:$D$424,6)) | D65: =IF(SUMIFS('Seat Planner'!$M$5:$M$424,'Seat Planner'!$B$5:$B$424,2,'Seat Planner'!$C$5:$C$424,"TEAM",'Seat Planner'!$D$5:$D$424,6)=0,"",(SUMIFS('Seat Planner'!$M$5:$M$424,'Seat Planner'!$B$5:$B$424,2,'Seat Planner'!$C$5:$C$424,"TEAM",'Seat Planner'!$D$5:$D$424,6,'Seat Planner'!$J$5:$J$424,"FTC")+SUMIFS('Seat Planner'!$M$5:$M$424,'Seat Planner'!$B$5:$B$424,2,'Seat Planner'!$C$5:$C$424,"TEAM",'Seat Planner'!$D$5:$D$424,6,'Seat Planner'!$J$5:$J$424,"PT"))/SUMIFS('Seat Planner'!$M$5:$M$424,'Seat Planner'!$B$5:$B$424,2,'Seat Planner'!$C$5:$C$424,"TEAM",'Seat Planner'!$D$5:$D$424,6)) | E65: =IF(SUMIFS('Seat Planner'!$M$5:$M$424,'Seat Planner'!$B$5:$B$424,3,'Seat Planner'!$C$5:$C$424,"TEAM",'Seat Planner'!$D$5:$D$424,6)=0,"",(SUMIFS('Seat Planner'!$M$5:$M$424,'Seat Planner'!$B$5:$B$424,3,'Seat Planner'!$C$5:$C$424,"TEAM",'Seat Planner'!$D$5:$D$424,6,'Seat Planner'!$J$5:$J$424,"FTC")+SUMIFS('Seat Planner'!$M$5:$M$424,'Seat Planner'!$B$5:$B$424,3,'Seat Planner'!$C$5:$C$424,"TEAM",'Seat Planner'!$D$5:$D$424,6,'Seat Planner'!$J$5:$J$424,"PT"))/SUMIFS('Seat Planner'!$M$5:$M$424,'Seat Planner'!$B$5:$B$424,3,'Seat Planner'!$C$5:$C$424,"TEAM",'Seat Planner'!$D$5:$D$424,6)) | F65: =IF(SUMIFS('Seat Planner'!$M$5:$M$424,'Seat Planner'!$B$5:$B$424,4,'Seat Planner'!$C$5:$C$424,"TEAM",'Seat Planner'!$D$5:$D$424,6)=0,"",(SUMIFS('Seat Planner'!$M$5:$M$424,'Seat Planner'!$B$5:$B$424,4,'Seat Planner'!$C$5:$C$424,"TEAM",'Seat Planner'!$D$5:$D$424,6,'Seat Planner'!$J$5:$J$424,"FTC")+SUMIFS('Seat Planner'!$M$5:$M$424,'Seat Planner'!$B$5:$B$424,4,'Seat Planner'!$C$5:$C$424,"TEAM",'Seat Planner'!$D$5:$D$424,6,'Seat Planner'!$J$5:$J$424,"PT"))/SUMIFS('Seat Planner'!$M$5:$M$424,'Seat Planner'!$B$5:$B$424,4,'Seat Planner'!$C$5:$C$424,"TEAM",'Seat Planner'!$D$5:$D$424,6)) | G65: =IF(SUMIFS('Seat Planner'!$M$5:$M$424,'Seat Planner'!$B$5:$B$424,5,'Seat Planner'!$C$5:$C$424,"TEAM",'Seat Planner'!$D$5:$D$424,6)=0,"",(SUMIFS('Seat Planner'!$M$5:$M$424,'Seat Planner'!$B$5:$B$424,5,'Seat Planner'!$C$5:$C$424,"TEAM",'Seat Planner'!$D$5:$D$424,6,'Seat Planner'!$J$5:$J$424,"FTC")+SUMIFS('Seat Planner'!$M$5:$M$424,'Seat Planner'!$B$5:$B$424,5,'Seat Planner'!$C$5:$C$424,"TEAM",'Seat Planner'!$D$5:$D$424,6,'Seat Planner'!$J$5:$J$424,"PT"))/SUMIFS('Seat Planner'!$M$5:$M$424,'Seat Planner'!$B$5:$B$424,5,'Seat Planner'!$C$5:$C$424,"TEAM",'Seat Planner'!$D$5:$D$424,6))
B66: WORST UNIT IN THE YEAR | C66: =IF(COUNT(C54:C65)=0,"",MIN(C54:C65)) | D66: =IF(COUNT(D54:D65)=0,"",MIN(D54:D65)) | E66: =IF(COUNT(E54:E65)=0,"",MIN(E54:E65)) | F66: =IF(COUNT(F54:F65)=0,"",MIN(F54:F65)) | G66: =IF(COUNT(G54:G65)=0,"",MIN(G54:G65)) | J66: Blank means no unit of that type runs that year — normal once teams have converted. This is the test the aggregate guardrail hides: a 領域 can be 55% Capgemini overall while one pod is 30%, and that pod is one we do not really run.
B67: Status against the per-unit floor | C67: =IF(C66="","",IF(C66>='Rates & Tables'!$C$57-0.005,"OK","CHECK")) | D67: =IF(D66="","",IF(D66>='Rates & Tables'!$C$57-0.005,"OK","CHECK")) | E67: =IF(E66="","",IF(E66>='Rates & Tables'!$C$57-0.005,"OK","CHECK")) | F67: =IF(F66="","",IF(F66>='Rates & Tables'!$C$57-0.005,"OK","CHECK")) | G67: =IF(G66="","",IF(G66>='Rates & Tables'!$C$57-0.005,"OK","CHECK"))
A69: E. STAFFING FEASIBILITY — can these numbers be turned into people?
B70: Test | C70: Result | J70: Note
B71: Seat-plan rows in use | C71: =SUMPRODUCT(--('Seat Planner'!$B$5:$B$424<>"")) | J71: Each row is one seat type in one unit type in one year.
B72: Deployed heads NOT on a 0.5 grid | C72: =SUMPRODUCT(--('Seat Planner'!$B$5:$B$424<>""),--(MOD(ROUND('Seat Planner'!$M$5:$M$424*2,2),1)<>0)) | J72: THE STAFFING TEST. A deployed head count of 1.38 is not a job. Whole numbers, or halves where sharing inside the 領域 is genuinely warranted.
B73: Deployed heads below 0.5 | C73: =SUMPRODUCT(--('Seat Planner'!$B$5:$B$424<>""),--('Seat Planner'!$M$5:$M$424>0),--('Seat Planner'!$M$5:$M$424<0.5)) | J73: Sub-half-person lines. Fold them into a neighbouring seat or into a horizontal function.
B74: Capgemini roles present in Year 3 but extinct in Year 4 | C74: =IF(AND(COUNTIF('Seat Planner'!$P$5:$P$424,"3|BSA|FTC")>0,COUNTIF('Seat Planner'!$P$5:$P$424,"4|BSA|FTC")=0),1,0)+IF(AND(COUNTIF('Seat Planner'!$P$5:$P$424,"3|DEV|FTC")>0,COUNTIF('Seat Planner'!$P$5:$P$424,"4|DEV|FTC")=0),1,0)+IF(AND(COUNTIF('Seat Planner'!$P$5:$P$424,"3|TEST|FTC")>0,COUNTIF('Seat Planner'!$P$5:$P$424,"4|TEST|FTC")=0),1,0)+IF(AND(COUNTIF('Seat Planner'!$P$5:$P$424,"3|MNT|FTC")>0,COUNTIF('Seat Planner'!$P$5:$P$424,"4|MNT|FTC")=0),1,0)+IF(AND(COUNTIF('Seat Planner'!$P$5:$P$424,"3|PM|FTC")>0,COUNTIF('Seat Planner'!$P$5:$P$424,"4|PM|FTC")=0),1,0)+IF(AND(COUNTIF('Seat Planner'!$P$5:$P$424,"3|OTH|FTC")>0,COUNTIF('Seat Planner'!$P$5:$P$424,"4|OTH|FTC")=0),1,0) | J74: A design that lets a Capgemini role disappear between two years is a design nobody can staff. Should be zero.
B75: Total cost index — Year 1 | C75: =SUMIFS('Seat Planner'!$O$5:$O$424,'Seat Planner'!$B$5:$B$424,1) | J75: Relative only, onshore Tokyo E2 = 1.00.
B76: Total cost index — Year 5 | C76: =SUMIFS('Seat Planner'!$O$5:$O$424,'Seat Planner'!$B$5:$B$424,5)
B77: Unit cost reduction, Year 1 to Year 5 | C77: =IF(C75=0,0,1-C76/C75) | J77: The commercial headline, before the rate card. Compare it to the headcount reduction: if cost falls more slowly than headcount, the team is seniorising and the hiring plan needs to say so.

Sheet Rates & Tables
A1: Rates and tables — the solution position, not the client data
A2: Every amber cell here is a Capgemini judgement. The defaults are the portfolio position used on all five 領域 modelled so far. Change them for your 領域 if you can say why, in one sentence, to MetLife.
A4: A. THE GOLDEN PHASE TABLE — how far AI can go, by archetype and delivery phase
B5: Archetype | C5: Requirements | D5: Design | E5: Build | F5: Test | G5: Release | H5: Run | I5: Blended AI ceiling
B6: M · Mainframe-adjacent | C6: 0.35 | D6: 0.3 | E6: 0.5 | F6: 0.55 | G6: 0.45 | H6: 0.4 | I6: =SUMPRODUCT($C$12:$H$12,C6:H6)
B7: L · Legacy core | C7: 0.35 | D7: 0.22 | E7: 0.2 | F7: 0.4 | G7: 0.25 | H7: 0.32 | I7: =SUMPRODUCT($C$12:$H$12,C7:H7)
B8: D · Distributed-proven | C8: 0.35 | D8: 0.3 | E8: 0.55 | F8: 0.6 | G8: 0.5 | H8: 0.4 | I8: =SUMPRODUCT($C$12:$H$12,C8:H8)
B9: P · Cloud-present | C9: 0.35 | D9: 0.3 | E9: 0.55 | F9: 0.6 | G9: 0.5 | H9: 0.4 | I9: =SUMPRODUCT($C$12:$H$12,C9:H9)
B10: J · Japan-locked | C10: 0.22 | D10: 0.2 | E10: 0.32 | F10: 0.38 | G10: 0.3 | H10: 0.3 | I10: =SUMPRODUCT($C$12:$H$12,C10:H10)
B11: T · Long tail | C11: 0.3 | D11: 0.25 | E11: 0.4 | F11: 0.45 | G11: 0.4 | H11: 0.45 | I11: =SUMPRODUCT($C$12:$H$12,C11:H11)
B12: Phase share of a typical application's effort | C12: 0.15 | D12: 0.1 | E12: 0.3 | F12: 0.25 | G12: 0.05 | H12: 0.15 | I12: =SUM(C12:H12)
B13: Column I is derived, not entered: it is the phase weights times that archetype's phase ceilings. That is where 45.25% for M and 30.4% for J come from, and it is why raising the Build ceiling on a mainframe estate does less than people expect — Build is only 30% of the effort.
A15: B. ROLE → PHASE — the bridge between MetLife's role taxonomy and the phase table
B16: Client role | C16: Requirements | D16: Design | E16: Build | F16: Test | G16: Release | H16: Run | I16: Check
B17: BSA | C17: 0.7 | D17: 0.2 | E17: 0 | F17: 0 | G17: 0 | H17: 0.1 | I17: =SUM(C17:H17)
B18: Developer | C18: 0 | D18: 0.15 | E18: 0.7 | F18: 0 | G18: 0.1 | H18: 0.05 | I18: =SUM(C18:H18)
B19: Tester | C19: 0 | D19: 0 | E19: 0 | F19: 0.9 | G19: 0.1 | H19: 0 | I19: =SUM(C19:H19)
B20: Maintenance | C20: 0 | D20: 0 | E20: 0.1 | F20: 0.1 | G20: 0 | H20: 0.8 | I20: =SUM(C20:H20)
B21: PM | C21: 0.2 | D21: 0 | E21: 0 | F21: 0 | G21: 0 | H21: 0.8 | I21: =SUM(C21:H21)
B22: Other | C22: 0 | D22: 0.55 | E22: 0 | F22: 0 | G22: 0.2 | H22: 0.25 | I22: =SUM(C22:H22)
B23: THE ASSUMPTION MOST WORTH CHALLENGING IN THE WHOLE MODEL. It says a Tester spends 90% of their time in Test, where the AI ceiling is highest, and a PM spends 80% in Run, where it is lowest. Change this and every per-sourcing ceiling moves — which is exactly the point: MGCC is 74% developers and MetLife Japan is 41% BSA and 39% PM, so they cannot carry the same commitment.
A25: C. OFFSHORE CEILING BY ARCHETYPE
B26: Archetype | C26: Ceiling | I26: Why
B27: M · Mainframe-adjacent | C27: 0.85 | I27: Mainframe-adjacent modernisation. English-capable interfaces, tooling-heavy work.
B28: L · Legacy core | C28: 0.45 | I28: Legacy core. Japanese business rules and regulator-facing process hold half of it onshore.
B29: D · Distributed-proven | C29: 0.78 | I29: Distributed-proven. Already partly offshore across the portfolio.
B30: P · Cloud-present | C30: 0.78 | I30: Cloud-present. Same shape as D; the substrate does not care where the engineer sits.
B31: J · Japan-locked | C31: 0.12 | I31: Japan-locked. Japanese specifications, Japanese operational interface, Japanese regulator. This is the number that caps whole 領域, and no amount of AI moves it.
B32: T · Long tail | C32: 0.55 | I32: Long tail. Small enough to move, too small to invest in moving.
A34: D. ADOPTION — the share of the AI ceiling each population can actually commit to
B35: Sourcing type | C35: Adoption | I35: What this is a judgement about
B36: FTC · Capgemini payroll | C36: 1 | I36: We build the substrate, we mandate the tooling, we set the ways of working. There is no discount to apply to ourselves.
B37: PT · named sub-contractor | C37: 0.85 | I37: Bound by a sub-contract and one management step removed. Capable, but we direct them through a contract rather than a line.
B38: FTE · MetLife Japan | C38: 0.55 | I38: Governance, domain ownership and product decisions: the least machine-addressable work in the estate, done by people whose redeployment is MetLife's call, not ours. Common Service Platform raises this to 0.72 because the work there is genuinely different.
B39: MGCC · MetLife captive centre | C39: 0.8 | I39: Build and test work, receptive to tooling, but it runs to its own utilisation targets and we do not manage it. Raise this on a modern agile estate — Common Service Platform uses 0.92 — and say why.
B41: ADOPTION IS ABOUT AUTHORITY, NOT CAPABILITY. It is not a claim that MetLife's people are less able. It is a statement about who can mandate a change to how work is done — and it is the single most commercially consequential set of numbers in this workbook, because it decides how much of the productivity commitment sits on Capgemini's side of the contract.
A43: E. THE YEAR CURVES
B44: Driver | C44: Year 1 | D44: Year 2 | E44: Year 3 | F44: Year 4 | G44: Year 5 | I44: Basis
B45: AI realisation — share of the ceiling actually reached | C45: 0.25 | D45: 0.55 | E45: 0.75 | F45: 0.85 | G45: 0.9 | I45: Tooling, data access, guardrails and trust do not arrive on day one. Year 1 is a pilot year.
B46: Classical ADM productivity | C46: 0.02 | D46: 0.05 | E46: 0.07 | F46: 0.09 | G46: 0.11 | I46: Automation, shift-left, defect reduction, knowledge reuse. Attaches to the work, so it applies to every sourcing type equally.
B47: Operating-model productivity — raw | C47: 0.03 | D47: 0.06 | E47: 0.08 | F47: 0.1 | G47: 0.12 | I47: Pod consolidation, one release train, span of control. Scaled by the agile share and by the partner drag before it is used.
A49: F. SCALARS
B50: Parameter | C50: Value | I50: Note
B51: Glidepath pre-load | C51: 0.5 | I51: What share of this year's capability gain is taken this year. The rest carries into next year. 0.50 is deliberate prudence: capability earned in Q4 cannot fund a headcount reduction in Q1.
B52: Partner drag | C52: 0.6 | I52: A partner seat returns 40% of the operating-model gain a Capgemini seat does. Two management chains, a contractual boundary on ways of working, slower standardisation.
B53: Transfer cap — share of the Capgemini pool | C53: 0.7 | I53: The most of our own population we are willing to put through a transfer of employment at the end of Year 3.
B54: Transfer split to MetLife Japan | C54: 0.35 | I54: The rest goes to MGCC. Onshore people to MetLife Japan, offshore people to MGCC.
B55: Guardrail — minimum vendor share | C55: 0.5 | I55: Below this, Capgemini is a minority of its own delivery population. Lower it — with a written reason — only where MetLife already holds the majority on day one; Common Service Platform uses 0.38.
B56: Guardrail — minimum Capgemini share of build and test | C56: 0.55 | I56: We are accountable for the delivery; we should hold the majority of the seats that do it.
B57: Guardrail — minimum Capgemini share inside any one unit | C57: 0.55 | I57: A pod where Capgemini is a minority is a pod whose ways of working we do not set.
A59: G. COST INDEX — relative only, onshore Tokyo E2 = 1.00
B60: Location | C60: E1 | D60: E2 | E60: E3 | F60: E4 | G60: E5
B61: ON · Onshore Tokyo | C61: 0.72 | D61: 1 | E61: 1.35 | F61: 1.85 | G61: 2.55 | J61: ON
B62: OFF · Offshore India | C62: 0.22 | D62: 0.3 | E62: 0.42 | F62: 0.6 | G62: 0.85 | J62: OFF
B63: NEAR · Nearshore | C63: 0.45 | D63: 0.62 | E63: 0.84 | F63: 1.15 | G63: 1.58 | J63: NEAR
B65: Pending the rate card. Use it to see the SHAPE of the cost curve — what happens to cost per head as the team shrinks and seniorises — not to price anything.

Sheet Inventory v5
A1: Appendix 3 v5 — all 142 in-scope applications, all eleven 領域
A2: Read-only. Commercial quantities and the archetype are carried from the Golden Application Inventory v4; the technical profile, ticket load and disposition columns are refreshed from Appendix 3 v5. Every (auto) figure in this workbook is a SUMIFS over this table.
B4: EAI ID | C4: Application | D4: 領域 | E4: Value stream | F4: Vendor | G4: Arch | H4: Archetype name | I4: Rule | J4: Total effort | K4: Current FTC | L4: Current FTE | M4: Current MGCC | N4: Onshore | O4: Offshore | P4: Nearshore | Q4: BSA | R4: Developer | S4: Tester | T4: Maintenance | U4: PM | V4: Other | W4: % of PRJ | X4: Cloud | Y4: Priority | Z4: Critical | AA4: Dev method | AB4: Spec lang | AC4: Lines of code | AD4: Batches | AE4: P1 | AF4: P2 | AG4: P3 | AH4: P4 | AI4: P5 | AJ4: Emergency | AK4: Normal | AL4: Standard | AM4: Disposition | AN4: CG heads today | AO4: Selected?
B5: 13476 | C5: AppsPortal | D5: Common Service Platform | E5: Shared Platform Service | F5: CG | G5: M | H5: MGCC-destined | I5: Rule 1 | J5: 122.53862 | K5: 57.149875 | L5: 23.302083 | M5: 42.086667 | N5: 28.733208 | O5: 28.416667 | P5: 0 | Q5: 5.6291667 | R5: 32.895708 | S5: 16.208333 | T5: 1.0333333 | U5: 1.3 | V5: 0.083333333 | W5: 0.88077909 | X5: Yes | Y5: Y | Z5: N | AA5: 1 | AB5: 3 | AC5: 0 | AD5: 50 | AE5: 0 | AF5: 0 | AG5: 102 | AH5: 217 | AI5: 596 | AJ5: 66 | AK5: 33 | AL5: 966 | AM5: Maintain (Evolve) | AN5: 5 | AO5: =--($D5='START HERE'!$C$5)
B6: 12038 | C6: CMIAPI-JPN | D6: Common Service Platform | E6: API Management | F6: CG | G6: D | H6: Distributed-proven | I6: Rule 4 | J6: 40.290417 | K6: 19.246667 | L6: 4.1333333 | M6: 16.910417 | N6: 2.5466667 | O6: 16.7 | P6: 0 | Q6: 0 | R6: 13.3925 | S6: 5.8541667 | T6: 0 | U6: 0 | V6: 0 | W6: 0.94847824 | X6: Yes | Y6: N | Z6: N | AA6: 1 | AB6: 3 | AC6: 0 | AD6: 10 | AE6: 2 | AF6: 0 | AG6: 28 | AH6: 18 | AI6: 122 | AJ6: 28 | AK6: 98 | AL6: 540 | AM6: Maintain (Evolve) | AN6: 12.313 | AO6: =--($D6='START HERE'!$C$5)
B7: 13676 | C7: ODMoC | D7: Common Service Platform | E7: Shared Platform Service | F7: unnamed | G7: D | H7: Distributed-proven | I7: Rule 4 | J7: 16.041667 | K7: 11.572917 | L7: 2.3333333 | M7: 2.1354167 | N7: 3.11875 | O7: 8.4541667 | P7: 0 | Q7: 2.7875 | R7: 7.00625 | S7: 1.7791667 | T7: 0 | U7: 0 | V7: 0 | W7: 0.93766234 | X7: Yes | Y7: N | Z7: N | AA7: 1 | AB7: 3 | AC7: 0 | AD7: 0 | AE7: 0 | AF7: 1 | AG7: 1 | AH7: 2 | AI7: 9 | AJ7: 1 | AK7: 0 | AL7: 62 | AM7: Maintain (Evolve) | AN7: 11.573 | AO7: =--($D7='START HERE'!$C$5)
B8: 9992 | C8: CMESB-JPN | D8: Common Service Platform | E8: API Management | F8: CG | G8: D | H8: Distributed-proven | I8: Rule 4 | J8: 12.725 | K8: 7.2083333 | L8: 2.9958333 | M8: 2.5208333 | N8: 0.29166667 | O8: 6.9166667 | P8: 0 | Q8: 0 | R8: 7.125 | S8: 0.083333333 | T8: 0 | U8: 0 | V8: 0 | W8: 0.93778651 | X8: No | Y8: N | Z8: N | AA8: 1 | AB8: 3 | AC8: 0 | AD8: 0 | AE8: 0 | AF8: 1 | AG8: 13 | AH8: 16 | AI8: 30 | AJ8: 18 | AK8: 62 | AL8: 316 | AM8: Maintain (Patch) | AN8: 7.208 | AO8: =--($D8='START HERE'!$C$5)
B9: 9928 | C9: W01MAS-JPN | D9: Common Service Platform | E9: Shared Platform Service | F9: NCD | G9: T | H9: Long tail | I9: Rule 3 | J9: 2.3970833 | K9: 1.3970833 | L9: 1 | M9: 0 | N9: 1.3970833 | O9: 0 | P9: 0 | Q9: 0 | R9: 1.3970833 | S9: 0 | T9: 0 | U9: 0 | V9: 0 | W9: 0.86441856 | X9: Yes | Y9: N | Z9: N | AA9: 2 | AB9: 1 | AC9: 0 | AD9: 400 | AE9: 0 | AF9: 0 | AG9: 11 | AH9: 10 | AI9: 40 | AJ9: 15 | AK9: 13 | AL9: 171 | AM9: Maintain (Patch) | AN9: 0.894 | AO9: =--($D9='START HERE'!$C$5)
B10: 12607 | C10: JP-WCMAUT | D10: Common Service Platform | E10: Shared Platform Service | F10: unnamed | G10: T | H10: Long tail | I10: Rule 3 | J10: 2.3375 | K10: 1.3375 | L10: 0 | M10: 1 | N10: 0.5 | O10: 0.8375 | P10: 0 | Q10: 0 | R10: 1.3375 | S10: 0 | T10: 0 | U10: 0 | V10: 0 | W10: 1 | X10: Yes | Y10: N | Z10: N | AA10: 1 | AB10: 3 | AC10: 0 | AD10: 0 | AE10: 0 | AF10: 0 | AG10: 8 | AH10: 2 | AI10: 4 | AJ10: 6 | AK10: 9 | AL10: 77 | AM10: Maintain (Evolve) | AN10: 0.856 | AO10: =--($D10='START HERE'!$C$5)
B11: 13139 | C11: PaymentService | D11: Common Service Platform | E11: API Management | F11: unnamed | G11: T | H11: Long tail | I11: Rule 3 | J11: 1.9916667 | K11: 0 | L11: 1.3 | M11: 0.69166667 | N11: 0 | O11: 0 | P11: 0 | Q11: 0 | R11: 0 | S11: 0 | T11: 0 | U11: 0 | V11: 0 | W11: 1 | X11: Yes | Y11: N | Z11: N | AA11: 1 | AB11: 1 | AC11: 0 | AD11: 0 | AE11: 0 | AF11: 0 | AG11: 4 | AH11: 9 | AI11: 5 | AJ11: 4 | AK11: 2 | AL11: 63 | AM11: Maintain (Evolve) | AN11: 0 | AO11: =--($D11='START HERE'!$C$5)
B12: 12654 | C12: JP-QA Shared Service | D12: Common Service Platform | E12: Shared Platform Service | F12: unnamed | G12: T | H12: Long tail | I12: Rule 3 | J12: 0.25 | K12: 0 | L12: 0.25 | M12: 0 | N12: 0 | O12: 0 | P12: 0 | Q12: 0 | R12: 0 | S12: 0 | T12: 0 | U12: 0 | V12: 0 | W12: 1 | X12: No | Y12: N | Z12: N | AA12: N/A | AB12: N/A | AC12: 0 | AD12: 0 | AE12: 0 | AF12: 0 | AG12: 0 | AH12: 0 | AI12: 0 | AJ12: 0 | AK12: 1 | AL12: 2 | AM12: Maintain (Patch) | AN12: 0 | AO12: =--($D12='START HERE'!$C$5)
B13: 12527 | C13: CMEAPI-JP | D13: Common Service Platform | E13: API Management | F13: CG | G13: T | H13: Long tail | I13: Rule 3 | J13: 0.13333333 | K13: 0.10833333 | L13: 0 | M13: 0.025 | N13: 0 | O13: 0.10833333 | P13: 0 | Q13: 0 | R13: 0 | S13: 0.10833333 | T13: 0 | U13: 0 | V13: 0 | W13: 1 | X13: Yes | Y13: N | Z13: N | AA13: 1 | AB13: 3 | AC13: 0 | AD13: 0 | AE13: 0 | AF13: 0 | AG13: 2 | AH13: 0 | AI13: 0 | AJ13: 1 | AK13: 0 | AL13: 51 | AM13: Maintain (Evolve) | AN13: 0.108 | AO13: =--($D13='START HERE'!$C$5)
B14: 9926 | C14: W01LOI-JPN | D14: Common Service Platform | E14: Shared Platform Service | F14: unnamed | G14: T | H14: Long tail | I14: Rule 3 | J14: 0.075 | K14: 0.075 | L14: 0 | M14: 0 | N14: 0.075 | O14: 0 | P14: 0 | Q14: 0 | R14: 0.075 | S14: 0 | T14: 0 | U14: 0 | V14: 0 | W14: 0 | X14: No | Y14: N | Z14: N | AA14: 2 | AB14: 1 | AC14: 0 | AD14: 0 | AE14: 0 | AF14: 0 | AG14: 2 | AH14: 7 | AI14: 36 | AJ14: 2 | AK14: 1 | AL14: 34 | AM14: Maintain (Patch) | AN14: 0.048 | AO14: =--($D14='START HERE'!$C$5)
B15: 9796 | C15: LC POSPMC MF-JPN | D15: Contract Management | E15: Mainframe Policy Management Cycle | F15: FSI | G15: L | H15: Legacy core | I15: Rule 2 | J15: 67.313125 | K15: 59.558958 | L15: 7.7541667 | M15: 0 | N15: 59.392292 | O15: 0 | P15: 0.16666667 | Q15: 0.25 | R15: 59.308958 | S15: 0 | T15: 0 | U15: 0 | V15: 0 | W15: 0.71176374 | X15: No | Y15: N | Z15: Y | AA15: 3 | AB15: 1 | AC15: 2621006 | AD15: 989 | AE15: 0 | AF15: 0 | AG15: 118 | AH15: 62 | AI15: 491 | AJ15: 62 | AK15: 72 | AL15: 602 | AM15: Maintain (Evolve) | AN15: 0 | AO15: =--($D15='START HERE'!$C$5)
B16: 9800 | C16: LC Billing MF-JPN | D16: Contract Management | E16: Mainframe Lifecomm Sub-systems | F16: FSI | G16: L | H16: Legacy core | I16: Rule 2 | J16: 22.745917 | K16: 20.892167 | L16: 1.85375 | M16: 0 | N16: 20.142167 | O16: 0 | P16: 0.75 | Q16: 0 | R16: 20.892167 | S16: 0 | T16: 0 | U16: 0 | V16: 0 | W16: 0.94285788 | X16: No | Y16: N | Z16: Y | AA16: 3 | AB16: 1 | AC16: 1526471 | AD16: 838 | AE16: 0 | AF16: 0 | AG16: 66 | AH16: 14 | AI16: 80 | AJ16: 48 | AK16: 182 | AL16: 550 | AM16: Maintain (Evolve) | AN16: 0 | AO16: =--($D16='START HERE'!$C$5)
B17: 9802 | C17: LC Corresponding MF-JPN | D17: Contract Management | E17: Mainframe Reporting & Tax | F17: unnamed | G17: L | H17: Legacy core | I17: Rule 2 | J17: 17.607792 | K17: 15.953625 | L17: 1.6541667 | M17: 0 | N17: 15.953625 | O17: 0 | P17: 0 | Q17: 0 | R17: 15.953625 | S17: 0 | T17: 0 | U17: 0 | V17: 0 | W17: 0.98287217 | X17: No | Y17: N | Z17: Y | AA17: 3 | AB17: 1 | AC17: 726045 | AD17: 187 | AE17: 0 | AF17: 0 | AG17: 32 | AH17: 7 | AI17: 30 | AJ17: 17 | AK17: 18 | AL17: 183 | AM17: Maintain (Evolve) | AN17: 0 | AO17: =--($D17='START HERE'!$C$5)
B18: 9808 | C18: LC AACOMP MF-JPN | D18: Contract Management | E18: Mainframe Commision | F18: NCS | G18: L | H18: Legacy core | I18: Rule 2 | J18: 16.689458 | K18: 13.545708 | L18: 3.14375 | M18: 0 | N18: 13.545708 | O18: 0 | P18: 0 | Q18: 0.4375 | R18: 13.108208 | S18: 0 | T18: 0 | U18: 0 | V18: 0 | W18: 0.72662384 | X18: No | Y18: N | Z18: Y | AA18: 3 | AB18: 1 | AC18: 1954166 | AD18: 1335 | AE18: 0 | AF18: 0 | AG18: 135 | AH18: 13 | AI18: 67 | AJ18: 83 | AK18: 83 | AL18: 613 | AM18: Maintain (Evolve) | AN18: 0 | AO18: =--($D18='START HERE'!$C$5)
B19: 9980 | C19: Policy UWIBATCH MF-JPN | D19: Contract Management | E19: Mainframe Reporting & Tax | F19: FSI | G19: L | H19: Legacy core | I19: Rule 2 | J19: 13.748542 | K19: 12.606875 | L19: 1.1416667 | M19: 0 | N19: 12.606875 | O19: 0 | P19: 0 | Q19: 0 | R19: 12.606875 | S19: 0 | T19: 0 | U19: 0 | V19: 0 | W19: 0.81496522 | X19: No | Y19: N | Z19: Y | AA19: 3 | AB19: 1 | AC19: 608760 | AD19: 296 | AE19: 0 | AF19: 0 | AG19: 28 | AH19: 9 | AI19: 16 | AJ19: 19 | AK19: 121 | AL19: 459 | AM19: Maintain (Evolve) | AN19: 0 | AO19: =--($D19='START HERE'!$C$5)
B20: 9948 | C20: Data Send System for BANC MF-JP | D20: Contract Management | E20: Mainframe Commision | F20: NCD | G20: L | H20: Legacy core | I20: Rule 2 | J20: 12.115542 | K20: 9.2697083 | L20: 2.8458333 | M20: 0 | N20: 9.2697083 | O20: 0 | P20: 0 | Q20: 1 | R20: 8.2697083 | S20: 0 | T20: 0 | U20: 0 | V20: 0 | W20: 0.77129926 | X20: No | Y20: N | Z20: Y | AA20: 3 | AB20: 1 | AC20: 244574 | AD20: 257 | AE20: 0 | AF20: 0 | AG20: 112 | AH20: 10 | AI20: 27 | AJ20: 78 | AK20: 10 | AL20: 327 | AM20: Maintain (Evolve) | AN20: 0 | AO20: =--($D20='START HERE'!$C$5)
B21: 9804 | C21: LC AAPerf MF-JPN | D21: Contract Management | E21: Mainframe Commision | F21: FSI | G21: L | H21: Legacy core | I21: Rule 2 | J21: 11.53 | K21: 10.784167 | L21: 0.74583333 | M21: 0 | N21: 8.91125 | O21: 0 | P21: 1.8729167 | Q21: 0 | R21: 10.784167 | S21: 0 | T21: 0 | U21: 0 | V21: 0 | W21: 0.83304423 | X21: No | Y21: N | Z21: Y | AA21: 3 | AB21: 1 | AC21: 760605 | AD21: 356 | AE21: 0 | AF21: 0 | AG21: 20 | AH21: 8 | AI21: 37 | AJ21: 18 | AK21: 37 | AL21: 258 | AM21: Maintain (Evolve) | AN21: 0 | AO21: =--($D21='START HERE'!$C$5)
B22: 9807 | C22: LC Valuation MF-JPN | D22: Contract Management | E22: Mainframe Lifecomm Sub-systems | F22: FSI | G22: L | H22: Legacy core | I22: Rule 2 | J22: 11.252083 | K22: 9.76875 | L22: 1.4833333 | M22: 0 | N22: 9.76875 | O22: 0 | P22: 0 | Q22: 0 | R22: 9.76875 | S22: 0 | T22: 0 | U22: 0 | V22: 0 | W22: 0.8563229 | X22: No | Y22: N | Z22: N | AA22: 3 | AB22: 1 | AC22: 1358360 | AD22: 775 | AE22: 0 | AF22: 0 | AG22: 79 | AH22: 11 | AI22: 33 | AJ22: 30 | AK22: 25 | AL22: 206 | AM22: Maintain (Evolve) | AN22: 0 | AO22: =--($D22='START HERE'!$C$5)
B23: 9803 | C23: LC UWI MF-JPN | D23: Contract Management | E23: Mainframe Lifecomm Sub-systems | F23: FSI | G23: L | H23: Legacy core | I23: Rule 2 | J23: 9.6545833 | K23: 8.8045833 | L23: 0.85 | M23: 0 | N23: 8.8045833 | O23: 0 | P23: 0 | Q23: 0.25 | R23: 8.5545833 | S23: 0 | T23: 0 | U23: 0 | V23: 0 | W23: 0.94821113 | X23: No | Y23: N | Z23: Y | AA23: 3 | AB23: 1 | AC23: 794523 | AD23: 35 | AE23: 0 | AF23: 0 | AG23: 6 | AH23: 19 | AI23: 284 | AJ23: 3 | AK23: 75 | AL23: 128 | AM23: Maintain (Evolve) | AN23: 0 | AO23: =--($D23='START HERE'!$C$5)
B24: 9810 | C24: Processor-I MF-JPN | D24: Contract Management | E24: Mainframe Claim Administration | F24: NCD | G24: L | H24: Legacy core | I24: Rule 2 | J24: 8.7975 | K24: 7.6683333 | L24: 1.1291667 | M24: 0 | N24: 3.985 | O24: 0 | P24: 3.6833333 | Q24: 0 | R24: 7.6683333 | S24: 0 | T24: 0 | U24: 0 | V24: 0 | W24: 0.75561239 | X24: No | Y24: N | Z24: Y | AA24: 3 | AB24: 1 | AC24: 894522 | AD24: 334 | AE24: 0 | AF24: 0 | AG24: 26 | AH24: 10 | AI24: 44 | AJ24: 7 | AK24: 48 | AL24: 149 | AM24: Maintain (Evolve) | AN24: 0 | AO24: =--($D24='START HERE'!$C$5)
... B145: 9879 | C145: W03PIU-JPN | D145: Storage and Preservation Related | E145: Policy Owner Servicing Work Flow | F145: NCD | G145: T | H145: Long tail | I145: Rule 3 | J145: 0.30833333 | K145: 0.20833333 | L145: 0.1 | M145: 0 | N145: 0.20833333 | O145: 0 | P145: 0 | Q145: 0 | R145: 0.20833333 | S145: 0 | T145: 0 | U145: 0 | V145: 0 | W145: 0.67567568 | X145: No | Y145: N | Z145: N | AA145: 3 | AB145: 1 | AC145: 228784 | AD145: 1 | AE145: 0 | AF145: 0 | AG145: 2 | AH145: 0 | AI145: 10 | AJ145: 0 | AK145: 0 | AL145: 22 | AM145: Maintain (Evolve) | AN145: 0.031 | AO145: =--($D145='START HERE'!$C$5)
B146: 12675 | C146: JP-DB2-CONNECT | D146: Storage and Preservation Related | E146: Policy Owner Servicing Work Flow | F146: unnamed | G146: T | H146: Long tail | I146: Rule 3 | J146: 0.1 | K146: 0 | L146: 0.1 | M146: 0 | N146: 0 | O146: 0 | P146: 0 | Q146: 0 | R146: 0 | S146: 0 | T146: 0 | U146: 0 | V146: 0 | W146: 0 | X146: No | Y146: N | Z146: N | AA146: N/A | AB146: N/A | AC146: 0 | AD146: 0 | AE146: 0 | AF146: 0 | AG146: 0 | AH146: 0 | AI146: 0 | AJ146: 0 | AK146: 0 | AL146: 0 | AM146: Maintain (Patch) | AN146: 0 | AO146: =--($D146='START HERE'!$C$5)
B147: PORTFOLIO TOTAL | J147: =SUM(J5:J146) | K147: =SUM(K5:K146) | L147: =SUM(L5:L146) | M147: =SUM(M5:M146) | N147: =SUM(N5:N146) | O147: =SUM(O5:O146) | P147: =SUM(P5:P146) | Q147: =SUM(Q5:Q146) | ... V147: =SUM(V5:V146) | AD147: =SUM(AD5:AD146) | AE147: =SUM(AE5:AE146) | AF147: =SUM(AF5:AF146) | AG147: =SUM(AG5:AG146) | AH147: =SUM(AH5:AH146) | AI147: =SUM(AI5:AI146) | AJ147: =SUM(AJ5:AJ146) | AK147: =SUM(AK5:AK146) | AN147: =SUM(AN5:AN146) | AO147: =SUM(AO5:AO146)
B149: 142 applications, 1,528.907 units. The Contract Management 領域 is 28 applications and the Data Infrastructure 領域 is 3; the SUMIFS do not care. Archetype: M mainframe-adjacent modernisation candidate · L legacy core · D distributed-proven · P cloud-present · J Japan-locked · T long tail. The classifier is six ordered rules and lives in the Golden Application Inventory v4 workbook, column by column, if you need to audit a call.

Sheet Stream Catalogue
A1: Value streams — every 領域, in the order the Value Streams sheet reads them
A2: Read-only. Derived from Appendix 3 v5 by grouping the inventory on 領域 and value stream.
B4: Key | C4: 領域 | D4: # | E4: Value stream | F4: Apps | G4: Effort | H4: Method today | I4: Current FTC | J4: FTE | K4: MGCC | L4: CG heads | M4: Vendor position today
B5: Fee Management|1 | C5: Fee Management | D5: 1 | E5: Commission Processing & Management | F5: 5 | G5: 48.5103 | H5: Waterfall | I5: 38.1478 | J5: 9.7792 | K5: 0.5833 | L5: 1 | M5: none named
B6: Contract Management|1 | C6: Contract Management | D6: 1 | E6: Mainframe Policy Management Cycle | F6: 5 | G6: 67.3131 | H6: Waterfall | I6: 59.559 | J6: 7.7542 | K6: 0 | L6: 0 | M6: FSI 59.6
B7: Contract Management|2 | C7: Contract Management | D7: 2 | E7: Mainframe Lifecomm Sub-systems | F7: 9 | G7: 62.2997 | H7: Waterfall | I7: 56.798 | J7: 5.5017 | K7: 0 | L7: 0 | M7: FSI 55.8
B8: Contract Management|3 | C8: Contract Management | D8: 3 | E8: Mainframe Reporting & Tax | F8: 5 | G8: 35.6808 | H8: Waterfall | I8: 32.885 | J8: 2.7958 | K8: 0 | L8: 0 | M8: FSI 14.2 · CG 1.0
B9: Contract Management|4 | C9: Contract Management | D9: 4 | E9: Mainframe Commision | F9: 5 | G9: 42.6679 | H9: Waterfall | I9: 35.7679 | J9: 6.9 | K9: 0 | L9: 0 | M9: NCS 13.5 · FSI 11.0 · NCD 9.3
B10: Contract Management|5 | C10: Contract Management | D10: 5 | E10: Mainframe Claim Administration | F10: 4 | G10: 22.7885 | H10: Waterfall | I10: 18.926 | J10: 3.8625 | K10: 0 | L10: 0 | M10: NCD 7.7 · FSI 4.4
B11: New Contract Related|1 | C11: New Contract Related | D11: 1 | E11: Underwriting & Interfaces | F11: 8 | G11: 24.1415 | H11: Waterfall | I11: 23.6145 | J11: 0.5271 | K11: 0 | L11: 2.38 | M11: NCD 16.4 · FSI 6.3
B12: Storage and Preservation Related|1 | C12: Storage and Preservation Related | D12: 1 | E12: Policy Owner Servicing Work Flow | F12: 12 | G12: 86.1578 | H12: Agile | I12: 56.7328 | J12: 18.425 | K12: 11 | L12: 39.13 | M12: CG 36.1 · FSI 13.1 · NCD 3.1
B13: Insurance Claims and Benefits Payment Related|1 | C13: Insurance Claims and Benefits Payment Related | D13: 1 | E13: Claims Processing & Adjudication | F13: 1 | G13: 34.9965 | H13: Waterfall | I13: 29.3799 | J13: 5.6167 | K13: 0 | L13: 0 | M13: NCD 29.4
B14: Customer Care / Call Center|1 | C14: Customer Care / Call Center | D14: 1 | E14: Call Backend Service | F14: 6 | G14: 19.2013 | H14: Waterfall | I14: 10.345 | J14: 5.8958 | K14: 2.9604 | L14: 3.11 | M14: NCD 7.7 · CG 2.6 · FSI 0.0
B15: Corporate Related|1 | C15: Corporate Related | D15: 1 | E15: Group Policy Management | F15: 6 | G15: 14.9 | H15: Waterfall | I15: 9.675 | J15: 5.225 | K15: 0 | L15: 0.5 | M15: NCD 6.3 · CG 1.9
B16: New Contract Related|2 | C16: New Contract Related | D16: 2 | E16: Non-F2F New Business | F16: 4 | G16: 16.3491 | H16: Waterfall | I16: 15.8491 | J16: 0.5 | K16: 0 | L16: 1.61 | M16: NCD 3.6
... B31: Insurance Claims and Benefits Payment Related|3 | C31: Insurance Claims and Benefits Payment Related | D31: 3 | E31: Claims Support Services | F31: 2 | G31: 18.8225 | H31: Agile | I31: 13.6142 | J31: 0.7083 | K31: 4.5 | L31: 0 | M31: none named
B34: 'Method today' is the effort-weighted majority development method across the stream's applications, from Appendix 3 v5. Where a 領域 records only one value stream, the Value Streams sheet will show one row — which means the conversion has no granularity and you should say so rather than invent streams.

Sheet Method Note
A1: Method — what this model claims, and what it does not
A2: Read this before defending any number in the workbook to MetLife.
A4: THE FOUR GATES
B5: AI-attributable | C5: An archetype-specific ceiling, run through each role's phase distribution, then multiplied by a realisation curve that starts at 25% and reaches 90%, then multiplied again by an adoption factor that differs by sourcing type. The ceiling is what the work would support. Realisation is how fast we get there. Adoption is who has the authority to commit.
B6: Classical ADM | C6: Automation, shift-left, defect reduction, knowledge reuse. 2% rising to 11%. It attaches to the work rather than the person, so it applies to every sourcing type equally.
B7: Operating model | C7: Pod consolidation, one release train, span of control. 3% rising to 12%, scaled by the share of the 領域 that actually runs as pods and discounted again for any sub-contracted population.
B8: Compounding, not adding | C8: 1 − (1 − a)(1 − b)(1 − c). Three gates of 10% give 27%, not 30%. Adding them is the most common way these models overstate.
A9: THE TWO RULES THAT KEEP IT HONEST
B10: Scope is frozen | C10: Total effort never changes across the five years. Productivity shows up as fewer people doing the same work — never as work quietly leaving the model.
B11: Year 1 applies nothing | C11: The glidepath carries forward: this year's applied figure is last year's full capability plus half of this year's gain. Capability earned in Q4 cannot fund a reduction in Q1, and a Year-1 roster that does not reconcile to Appendix 3 is not credible to anybody.
A12: WHAT PRODUCTIVITY CANNOT DO
B13: It cannot move the ratio on its own | C13: If every population shrinks at the same rate, the 50:50 does not move a single point. Only differential shrinkage or a transfer of employment moves it. That is why the per-sourcing engine exists, and it is the single most useful thing to explain to MetLife.
B14: It cannot move a Japan-locked application offshore | C14: Archetype J caps at a 12% offshore ceiling. Japanese specifications, Japanese operational interface, Japanese regulator. No tooling changes that, and a 領域 built of J applications should not be promised an offshore case.
B15: It cannot shrink Capgemini past the point of control | C15: Below a Capgemini majority of the delivery population — and of the build-and-test seats inside it — the productivity commitment stops being ours to make. That is what the guardrails protect, and it is a commercial argument, not a modelling one.
A16: THE THINGS MOST WORTH CHALLENGING
B17: The role → phase table | C17: Rates & Tables section B. It decides every per-sourcing ceiling in the model, and it is a judgement rather than a measurement.
B18: The adoption factors | C18: Rates & Tables section D. How much of the ceiling MetLife's own people and MGCC can realistically commit to. Raising them shifts commitment away from Capgemini; lowering them concentrates it on us. Both are defensible; neither is automatic.
B19: The conversion quarters | C19: Value Streams sheet. When each stream starts running as a pod. Slipping one stream by two quarters costs about a point of Year-1 capability, which is small — but it changes the whole transition narrative.
B20: The restatements | C20: Logic Tree section B. Where MetLife's own role line is internally impossible we restate it, arithmetically neutral, and put the question back to them. We do not silently re-price their data, and we do not pretend one person can run a thousand incidents.
A21: PROVENANCE
B22: Appendix 3 v5 | C22: 142 in-scope applications, 1,528.907 units. Commercial quantities are unchanged from v3; v5 completed the technical profile and added four disposition columns.
B23: Golden Application Inventory v4 | C23: The six-rule archetype classifier, the value-stream grouping, the named-vendor tags and the application-level Capgemini headcount, reconciled from the billing, staff mapping and EAI files.
