Workbook

Sheet README
A1: MetLife Japan | Golden Application Inventory — archetype classification
A2: The single reference every domain team classifies against. One rule set, applied identically to all 142 applications.
A4: WHAT THIS IS
B5: Purpose | C5: The authoritative archetype classification for all 142 applications in Appendix 3 v2. Every domain model must classify against this sheet rather than re-deriving its own.
B6: Why it exists | C6: The archetype sets three ceilings and one method for every application — the AI ceiling, the offshore ceiling, the transition mechanic and the sourcing construct. If two domains classify the same way differently, their prices are not comparable.
B7: It is live, not a snapshot | C7: The archetype column is a formula, not a value. Change a source field and the classification, the parameters and both summaries re-derive.
A8: HOW TO USE IT — FOR A DOMAIN TEAM
B9: 1 · Filter | C9: Open Golden Inventory and filter column E to your 領域. The sheet has an autofilter on row 4.
B10: 2 · Read your mix | C10: Go to Domain Summary and find your row. It gives your application count, effort, archetype mix and the weighted AI and offshore ceilings for your domain. Those are the starting parameters for your model.
B11: 3 · Cut your value streams | C11: Group your applications into functional value streams. Reconcile to your domain effort exactly before you build any pod.
B12: 4 · Do not re-derive the archetype | C12: If you believe an application is misclassified, use the Override column and record who and why. Do not change the rule.
A13: THE RULE, IN ORDER
B14: Rule 1 → D | C14: Primary code language contains COBOL, Assembler, ASM, RPG, EASYPLUS or PL/I. Mainframe and AS/400 estate.
B15: Rule 2 → C | C15: Not rule 1, and Priority Transfer Targets = Y. The ten applications MetLife has already flagged for transfer.
B16: Rule 3 → B | C16: Not rules 1 or 2, and Cloud Indicator = Yes. Cloud-migrated, so re-platformed, documented and specifiable.
B17: Rule 4 → A | C17: Everything else. On-premises, non-mainframe, not flagged for transfer — where Japanese business context is bound to the application.
B18: Order matters | C18: The rules are exclusive and evaluated top to bottom. An application matching more than one test takes the first.
A19: RECONCILIATION AGAINST SECTION 4.1
B20: Application counts | C20: Match exactly for all four archetypes: A 71, B 33, C 10, D 28.
B21: Effort | C21: B and C match exactly (379.5 and 569.9). A and D differ by 4.7 units in opposite directions — this sheet gives A 317.1 and D 237.5 against Section 4.1's A 321.8 and D 232.8.
B22: Which to use | C22: This sheet. The figures here are reproducible from the source fields; the Section 4.1 A/D split is not. Section 4.1 should be corrected to match.
A23: GOVERNANCE
B24: Owner | C24: Solution architecture. Changes to the rule require agreement across all eleven domain teams, because the rule sets the price.
B25: Overrides | C25: Permitted, but only on the Overrides sheet with a named owner, a date and a reason. An override changes one application, never the rule.
B26: Source | C26: Appendix 3 v2 — "03 [Appendix 3] Target EA Inventory v2.xlsx", sheet ApplicationList. 142 applications, 1,504.0 effort units.
B27: Known data gap | C27: Named supply (FTC + FTE + MGCC) sums to 1,458.8 against 1,504.0 of effort. The 45.2-unit gap sits in 15 applications, mostly Storage & Preservation and Data Infrastructure. Raised as a clarification; not allocated here.

Sheet Classification Rules
A1: Classification rules and the parameters each archetype carries
A2: Blue cells are inputs. The Golden Inventory reads every parameter from this sheet, so changing it here changes it everywhere.
A4: A. THE RULE — evaluated in order, first match wins
B5: Rule | C5: Archetype | D5: Name | E5: Test applied to the source field | F5: Apps | G5: Effort
B6: Rule 1 | C6: D | D6: Legacy-coupled core | E6: Primary code language contains COBOL, Assembler, ASM, RPG, EASYPLUS or PL/I | F6: =COUNTIF('Golden Inventory'!$AA:$AA,$C6) -> 28 | G6: =SUMIF('Golden Inventory'!$AA:$AA,$C6,'Golden Inventory'!$T:$T) -> 237.50779
B7: Rule 2 | C7: C | D7: MGCC-destined | E7: Not rule 1, and Priority Transfer Targets = Y | F7: =COUNTIF('Golden Inventory'!$AA:$AA,$C7) -> 10 | G7: =SUMIF('Golden Inventory'!$AA:$AA,$C7,'Golden Inventory'!$T:$T) -> 569.88025
B8: Rule 3 | C8: B | D8: Offshore-ready | E8: Not rules 1-2, and Cloud Indicator = Yes | F8: =COUNTIF('Golden Inventory'!$AA:$AA,$C8) -> 33 | G8: =SUMIF('Golden Inventory'!$AA:$AA,$C8,'Golden Inventory'!$T:$T) -> 379.50447
B9: Rule 4 | C9: A | D9: Language-locked | E9: Everything else — on premises, not mainframe, not a transfer target | F9: =COUNTIF('Golden Inventory'!$AA:$AA,$C9) -> 71 | G9: =SUMIF('Golden Inventory'!$AA:$AA,$C9,'Golden Inventory'!$T:$T) -> 317.08354
D10: Total | F10: =SUM(F6:F9) -> 142 | G10: =SUM(G6:G9) -> 1503.976
A12: B. WHY EACH ARCHETYPE IS ITS OWN GROUP
B13: D | C13: Legacy-coupled core | D13: Rules hard-coded across modules and design truth is not written down. AI does comprehension here, not generation.
B14: C | C14: MGCC-destined | D14: MetLife has already flagged these for transfer and nine of ten already carry MGCC people. Routing them through a vendor transition pays for the same knowledge transfer twice.
B15: B | C15: Offshore-ready | D15: Cloud migration has already forced re-platforming, documentation and specifiability. Highest AI and offshore ceiling in the estate.
B16: A | C16: Language-locked | D16: On-premises and non-mainframe, so the constraint is not the technology — it is that the business context exists only in Japanese, in few heads.
A18: C. AI CEILING — phase effort mix x AI-addressable share per phase
B19: Delivery phase | C19: Share of effort | D19: A | E19: B | F19: C | G19: D
B20: Requirements & impact analysis | C20: 0.15 | D20: 0.22 | E20: 0.35 | F20: 0.35 | G20: 0.35
B21: Design & architecture | C21: 0.1 | D21: 0.2 | E21: 0.3 | F21: 0.3 | G21: 0.22
B22: Build & code | C22: 0.3 | D22: 0.32 | E22: 0.55 | F22: 0.5 | G22: 0.2
B23: Test & quality assurance | C23: 0.25 | D23: 0.38 | E23: 0.6 | F23: 0.55 | G23: 0.4
B24: Release & deploy | C24: 0.05 | D24: 0.3 | E24: 0.5 | F24: 0.45 | G24: 0.25
B25: Run, monitor & coordinate | C25: 0.15 | D25: 0.3 | E25: 0.4 | F25: 0.4 | G25: 0.32
B26: Phase mix total (must equal 100%) | C26: =SUM(C20:C25) -> 1
B27: WEIGHTED AI CEILING | D27: =SUMPRODUCT($C$20:$C$25,D20:D25) -> 0.304 | E27: =SUMPRODUCT($C$20:$C$25,E20:E25) -> 0.4825 | F27: =SUMPRODUCT($C$20:$C$25,F20:F25) -> 0.4525 | G27: =SUMPRODUCT($C$20:$C$25,G20:G25) -> 0.295
A29: D. REALISATION, AND THE NON-AI COMPONENTS — portfolio defaults
B30: Driver | C30: Year 1 | D30: Year 2 | E30: Year 3 | G30: Note
B31: AI realisation — share of ceiling captured | C31: 0.25 | D31: 0.55 | E31: 0.75 | G31: Domain teams may lower this with a stated reason, e.g. a platform on a sunset path.
B32: Classical ADM productivity (cumulative) | C32: 0.02 | D32: 0.05 | E32: 0.07 | G32: Standardisation, defect reduction, shift-left.
B33: Operating-model productivity (cumulative) | C33: 0.03 | D33: 0.06 | E33: 0.08 | G33: Pod consolidation, span of control, one release train.
A35: E. OFFSHORE CEILING
C36: A | D36: B | E36: C | F36: D
B37: Offshore-able ceiling | C37: 0.15 | D37: 0.78 | E37: 0.85 | F37: 0.58
B38: Applied by policy | C38: 0.15 | D38: 0.78 | E38: 0 | F38: 0.58 | H38: Archetype C is held at zero: we take only the onshore Japanese-language roles while MGCC takes engineering.
B39: Realisation by Year 3 | C39: 0.93
A41: F. DERIVED PARAMETERS — what the Golden Inventory looks up
B42: Archetype | C42: Name | D42: AI ceiling | E42: Productivity by Y3 | F42: Offshore ceiling | G42: Offshore by Y3 | H42: Transition method | I42: Typical duration | J42: Sourcing construct
B43: A | C43: Language-locked | D43: =D$27 -> 0.304 | E43: =1-(1-D$27*$E$31)*(1-$E$32)*(1-$E$33) -> 0.3394768 | F43: =C$38 -> 0.15 | G43: =C$38*$C$39 -> 0.1395 | H43: Full transition into a Japanese-resident pod; knowledge capture is the critical path | I43: 10-14 weeks per cluster | J43: Fully sourced, onshore-weighted
B44: B | C44: Offshore-ready | D44: =E$27 -> 0.4825 | E44: =1-(1-E$27*$E$31)*(1-$E$32)*(1-$E$33) -> 0.45402025 | F44: =D$38 -> 0.78 | G44: =D$38*$C$39 -> 0.7254 | H44: Full transition, fastest ramp; artefacts already exist | I44: 6-8 weeks per cluster | J44: Fully sourced, moving to output units
B45: C | C45: MGCC-destined | D45: =F$27 -> 0.4525 | E45: =1-(1-F$27*$E$31)*(1-$E$32)*(1-$E$33) -> 0.43476925 | F45: =E$38 -> 0 | G45: =E$38*$C$39 -> 0 | H45: Role handover of onshore roles; MGCC takes engineering directly from the incumbents | I45: 6-8 weeks, role handover | J45: Co-sourced with MGCC, permanently
B46: D | C46: Legacy-coupled core | D46: =G$27 -> 0.295 | E46: =1-(1-G$27*$E$31)*(1-$E$32)*(1-$E$33) -> 0.3337015 | F46: =F$38 -> 0.58 | G46: =F$38*$C$39 -> 0.5394 | H46: Deepest and slowest; design truth recovered from source, schedulers and job logs | I46: 14-20 weeks per cluster | J46: Fully sourced, MetLife SMEs paired

Sheet Golden Inventory
A1: Golden inventory — 142 applications, archetype derived live from the source fields
A2: Column F is the Value Stream. Columns L, M and N are the only three fields the rule reads. Columns X to AK are formulas. Column Z is the only place to type.
A4: # | B4: EAI ID | C4: Application | D4: Application long name | E4: 領域 (domain) | F4: Value Stream | G4: Group | H4: Team | I4: Application class | J4: Business critical | K4: Hosting | L4: PRIMARY CODE LANGUAGE | M4: PRIORITY TRANSFER | N4: CLOUD INDICATOR | O4: Cloud platform | P4: Source code owner | Q4: Current FTC | R4: Current FTE | S4: Current MGCC | T4: Total effort | U4: % of PRJ | V4: Target FTC | W4: Target FTE/MGCC | X4: Rule fired | Y4: Derived archetype | Z4: OVERRIDE | AA4: FINAL ARCHETYPE | AB4: Archetype name | AC4: Evidence — what decided it | AD4: Why this archetype | AE4: AI ceiling | AF4: Productivity by Y3 | AG4: Offshore ceiling | AH4: Offshore by Y3 | AI4: Transition method | AJ4: Typical duration | AK4: Sourcing construct
A5: 1 | B5: 9629 | C5: Global Sales Comp - Japan | D5: Global Sales Comp - Japan | E5: Fee Management | F5: VS1: Commission Processing & Management | G5: Core Insurance Systems Group 34956 | H5: Commission Systems Team 34958 | I5: Core Business Application | J5: N | K5: Yes | L5: Other#Infomatica workflow Bash shell Dos batch | M5: N | N5: Yes | O5: Software as a Service (SaaS) | P5: Non-MetLife Owned Application Code (3rd party/COTS) | Q5: 0 | R5: 0 | S5: 0 | T5: 0 | U5: 0 | V5: 0 | W5: 0 | X5: =IF(OR(ISNUMBER(SEARCH("COBOL",$L5)),ISNUMBER(SEARCH("Assembler",$L5)),ISNUMBER(SEARCH("ASM",$L5)),ISNUMBER(SEARCH("RPG",$L5)),ISNUMBER(SEARCH("EASYPLUS",$L5)),ISNUMBER(SEARCH("PL/I",$L5))),"Rule 1",IF($M5="Y","Rule 2",IF($N5="Yes","Rule 3","Rule 4"))) -> Rule 3 | Y5: =IF($X5="Rule 1","D",IF($X5="Rule 2","C",IF($X5="Rule 3","B","A"))) -> B | AA5: =IF($Z5="",$Y5,$Z5) -> B | AB5: =IFERROR(INDEX('Classification Rules'!$C$43:$C$46,MATCH($AA5,'Classification Rules'!$B$43:$B$46,0)),"") -> Offshore-ready | AC5: =IF($X5="Rule 1","Language: "&$L5,IF($X5="Rule 2","Priority Transfer Target = Y",IF($X5="Rule 3","Cloud Indicator = Yes ("&$O5&")","Cloud Indicator = No, not mainframe, not a transfer target"))) -> Cloud Indicator = Yes (Software as a Service (SaaS)) | AD5: =IFERROR(INDEX('Classification Rules'!$D$13:$D$16,MATCH($AA5,'Classification Rules'!$B$13:$B$16,0)),"") -> Cloud migration has already forced re-platforming, documentation and specifiability. Highest AI and offshore ceiling in the estate. | AE5: =IFERROR(INDEX('Classification Rules'!$D$43:$D$46,MATCH($AA5,'Classification Rules'!$B$43:$B$46,0)),"") -> 0.4825 | AF5: =IFERROR(INDEX('Classification Rules'!$E$43:$E$46,MATCH($AA5,'Classification Rules'!$B$43:$B$46,0)),"") -> 0.45402025 | AG5: =IFERROR(INDEX('Classification Rules'!$F$43:$F$46,MATCH($AA5,'Classification Rules'!$B$43:$B$46,0)),"") -> 0.78 | AH5: =IFERROR(INDEX('Classification Rules'!$G$43:$G$46,MATCH($AA5,'Classification Rules'!$B$43:$B$46,0)),"") -> 0.7254 | AI5: =IFERROR(INDEX('Classification Rules'!$I$43:$I$46,MATCH($AA5,'Classification Rules'!$B$43:$B$46,0)),"") -> 6-8 weeks per cluster | AJ5: =IFERROR(INDEX('Classification Rules'!$J$43:$J$46,MATCH($AA5,'Classification Rules'!$B$43:$B$46,0)),"") -> Fully sourced, moving to output units | AK5: =IFERROR(INDEX('Classification Rules'!$K$43:$K$46,MATCH($AA5,'Classification Rules'!$B$43:$B$46,0)),"") -> 0
A6: 2 | B6: 9796 | C6: LC POSPMC MF-JPN | D6: LifeComm POSPMC | E6: contract management | F6: VS1: Policy Administration & Contract Servicing | G6: Core Insurance Systems Group 34956 | H6: Policy Admin Systems Team 34957 | I6: Core Business Application | J6: Y | K6: Yes | L6: Assembler, COBOL, MU(EASYPLUS), JCL | M6: N | N6: No | P6: MetLife Owned Application Code | Q6: 59.558958 | R6: 7.7541667 | S6: 0 | T6: 67.313125 | U6: 0.71176374 | V6: 33.656563 | W6: 33.656563 | X6: =IF(OR(ISNUMBER(SEARCH("COBOL",$L6)),ISNUMBER(SEARCH("Assembler",$L6)),ISNUMBER(SEARCH("ASM",$L6)),ISNUMBER(SEARCH("RPG",$L6)),ISNUMBER(SEARCH("EASYPLUS",$L6)),ISNUMBER(SEARCH("PL/I",$L6))),"Rule 1",IF($M6="Y","Rule 2",IF($N6="Yes","Rule 3","Rule 4"))) -> Rule 1 | Y6: =IF($X6="Rule 1","D",IF($X6="Rule 2","C",IF($X6="Rule 3","B","A"))) -> D | AA6: =IF($Z6="",$Y6,$Z6) -> D | AB6: =IFERROR(INDEX('Classification Rules'!$C$43:$C$46,MATCH($AA6,'Classification Rules'!$B$43:$B$46,0)),"") -> Legacy-coupled core | AC6: =IF($X6="Rule 1","Language: "&$L6,IF($X6="Rule 2","Priority Transfer Target = Y",IF($X6="Rule 3","Cloud Indicator = Yes ("&$O6&")","Cloud Indicator = No, not mainframe, not a transfer target"))) -> Language: Assembler, COBOL, MU(EASYPLUS), JCL | AD6: =IFERROR(INDEX('Classification Rules'!$D$13:$D$16,MATCH($AA6,'Classification Rules'!$B$13:$B$16,0)),"") -> Rules hard-coded across modules and design truth is not written down. AI does comprehension here, not generation. | AE6: =IFERROR(INDEX('Classification Rules'!$D$43:$D$46,MATCH($AA6,'Classification Rules'!$B$43:$B$46,0)),"") -> 0.295 | AF6: =IFERROR(INDEX('Classification Rules'!$E$43:$E$46,MATCH($AA6,'Classification Rules'!$B$43:$B$46,0)),"") -> 0.3337015 | AG6: =IFERROR(INDEX('Classification Rules'!$F$43:$F$46,MATCH($AA6,'Classification Rules'!$B$43:$B$46,0)),"") -> 0.58 | AH6: =IFERROR(INDEX('Classification Rules'!$G$43:$G$46,MATCH($AA6,'Classification Rules'!$B$43:$B$46,0)),"") -> 0.5394 | AI6: =IFERROR(INDEX('Classification Rules'!$I$43:$I$46,MATCH($AA6,'Classification Rules'!$B$43:$B$46,0)),"") -> 14-20 weeks per cluster | AJ6: =IFERROR(INDEX('Classification Rules'!$J$43:$J$46,MATCH($AA6,'Classification Rules'!$B$43:$B$46,0)),"") -> Fully sourced, MetLife SMEs paired | AK6: =IFERROR(INDEX('Classification Rules'!$K$43:$K$46,MATCH($AA6,'Classification Rules'!$B$43:$B$46,0)),"") -> 0
A7: 3 | B7: 9800 | C7: LC Billing MF-JPN | D7: LifeComm Billing | E7: contract management | F7: VS2: Billing, Collections & Payments | G7: Core Insurance Systems Group 34956 | H7: Policy Admin Systems Team 34957 | I7: Core Business Application | J7: Y | K7: Yes | L7: COBOL, Assembler, MU(EASYPLUS), JCL | M7: N | N7: No | P7: MetLife Owned Application Code | Q7: 20.892167 | R7: 1.85375 | S7: 0 | T7: 22.745917 | U7: 0.94285788 | V7: 11.372958 | W7: 11.372958 | X7: =IF(OR(ISNUMBER(SEARCH("COBOL",$L7)),ISNUMBER(SEARCH("Assembler",$L7)),ISNUMBER(SEARCH("ASM",$L7)),ISNUMBER(SEARCH("RPG",$L7)),ISNUMBER(SEARCH("EASYPLUS",$L7)),ISNUMBER(SEARCH("PL/I",$L7))),"Rule 1",IF($M7="Y","Rule 2",IF($N7="Yes","Rule 3","Rule 4"))) -> Rule 1 | Y7: =IF($X7="Rule 1","D",IF($X7="Rule 2","C",IF($X7="Rule 3","B","A"))) -> D | AA7: =IF($Z7="",$Y7,$Z7) -> D | AB7: =IFERROR(INDEX('Classification Rules'!$C$43:$C$46,MATCH($AA7,'Classification Rules'!$B$43:$B$46,0)),"") -> Legacy-coupled core | AC7: =IF($X7="Rule 1","Language: "&$L7,IF($X7="Rule 2","Priority Transfer Target = Y",IF($X7="Rule 3","Cloud Indicator = Yes ("&$O7&")","Cloud Indicator = No, not mainframe, not a transfer target"))) -> Language: COBOL, Assembler, MU(EASYPLUS), JCL | AD7: =IFERROR(INDEX('Classification Rules'!$D$13:$D$16,MATCH($AA7,'Classification Rules'!$B$13:$B$16,0)),"") -> Rules hard-coded across modules and design truth is not written down. AI does comprehension here, not generation. | AE7: =IFERROR(INDEX('Classification Rules'!$D$43:$D$46,MATCH($AA7,'Classification Rules'!$B$43:$B$46,0)),"") -> 0.295 | AF7: =IFERROR(INDEX('Classification Rules'!$E$43:$E$46,MATCH($AA7,'Classification Rules'!$B$43:$B$46,0)),"") -> 0.3337015 | AG7: =IFERROR(INDEX('Classification Rules'!$F$43:$F$46,MATCH($AA7,'Classification Rules'!$B$43:$B$46,0)),"") -> 0.58 | AH7: =IFERROR(INDEX('Classification Rules'!$G$43:$G$46,MATCH($AA7,'Classification Rules'!$B$43:$B$46,0)),"") -> 0.5394 | AI7: =IFERROR(INDEX('Classification Rules'!$I$43:$I$46,MATCH($AA7,'Classification Rules'!$B$43:$B$46,0)),"") -> 14-20 weeks per cluster | AJ7: =IFERROR(INDEX('Classification Rules'!$J$43:$J$46,MATCH($AA7,'Classification Rules'!$B$43:$B$46,0)),"") -> Fully sourced, MetLife SMEs paired | AK7: =IFERROR(INDEX('Classification Rules'!$K$43:$K$46,MATCH($AA7,'Classification Rules'!$B$43:$B$46,0)),"") -> 0
A8: 4 | B8: 9801 | C8: LC Collection MF-JPN | D8: LifeComm Collection | E8: contract management | F8: VS2: Billing, Collections & Payments | G8: Core Insurance Systems Group 34956 | H8: Policy Admin Systems Team 34957 | I8: Core Business Application | J8: Y | K8: Yes | L8: COBOL, Assembler, MU(EASYPLUS), JCL | M8: N | N8: No | P8: MetLife Owned Application Code | Q8: 0 | R8: 0 | S8: 0 | T8: 0 | U8: 0 | V8: 0 | W8: 0 | X8: =IF(OR(ISNUMBER(SEARCH("COBOL",$L8)),ISNUMBER(SEARCH("Assembler",$L8)),ISNUMBER(SEARCH("ASM",$L8)),ISNUMBER(SEARCH("RPG",$L8)),ISNUMBER(SEARCH("EASYPLUS",$L8)),ISNUMBER(SEARCH("PL/I",$L8))),"Rule 1",IF($M8="Y","Rule 2",IF($N8="Yes","Rule 3","Rule 4"))) -> Rule 1 | Y8: =IF($X8="Rule 1","D",IF($X8="Rule 2","C",IF($X8="Rule 3","B","A"))) -> D | AA8: =IF($Z8="",$Y8,$Z8) -> D | AB8: =IFERROR(INDEX('Classification Rules'!$C$43:$C$46,MATCH($AA8,'Classification Rules'!$B$43:$B$46,0)),"") -> Legacy-coupled core | AC8: =IF($X8="Rule 1","Language: "&$L8,IF($X8="Rule 2","Priority Transfer Target = Y",IF($X8="Rule 3","Cloud Indicator = Yes ("&$O8&")","Cloud Indicator = No, not mainframe, not a transfer target"))) -> Language: COBOL, Assembler, MU(EASYPLUS), JCL | AD8: =IFERROR(INDEX('Classification Rules'!$D$13:$D$16,MATCH($AA8,'Classification Rules'!$B$13:$B$16,0)),"") -> Rules hard-coded across modules and design truth is not written down. AI does comprehension here, not generation. | AE8: =IFERROR(INDEX('Classification Rules'!$D$43:$D$46,MATCH($AA8,'Classification Rules'!$B$43:$B$46,0)),"") -> 0.295 | AF8: =IFERROR(INDEX('Classification Rules'!$E$43:$E$46,MATCH($AA8,'Classification Rules'!$B$43:$B$46,0)),"") -> 0.3337015 | AG8: =IFERROR(INDEX('Classification Rules'!$F$43:$F$46,MATCH($AA8,'Classification Rules'!$B$43:$B$46,0)),"") -> 0.58 | AH8: =IFERROR(INDEX('Classification Rules'!$G$43:$G$46,MATCH($AA8,'Classification Rules'!$B$43:$B$46,0)),"") -> 0.5394 | AI8: =IFERROR(INDEX('Classification Rules'!$I$43:$I$46,MATCH($AA8,'Classification Rules'!$B$43:$B$46,0)),"") -> 14-20 weeks per cluster | AJ8: =IFERROR(INDEX('Classification Rules'!$J$43:$J$46,MATCH($AA8,'Classification Rules'!$B$43:$B$46,0)),"") -> Fully sourced, MetLife SMEs paired | AK8: =IFERROR(INDEX('Classification Rules'!$K$43:$K$46,MATCH($AA8,'Classification Rules'!$B$43:$B$46,0)),"") -> 0
A9: 5 | B9: 9802 | C9: LC Corresponding MF-JPN | D9: LifeComm Corresponding | E9: contract management | F9: VS4: Correspondence, Documents & Tax | G9: Core Insurance Systems Group 34956 | H9: Policy Admin Systems Team 34957 | I9: Core Business Application | J9: Y | K9: Yes | L9: COBOL, Assembler, MU(EASYPLUS), JCL | M9: N | N9: No | P9: MetLife Owned Application Code | Q9: 15.953625 | R9: 1.6541667 | S9: 0 | T9: 17.607792 | U9: 0.98287217 | V9: 8.8038958 | W9: 8.8038958 | X9: =IF(OR(ISNUMBER(SEARCH("COBOL",$L9)),ISNUMBER(SEARCH("Assembler",$L9)),ISNUMBER(SEARCH("ASM",$L9)),ISNUMBER(SEARCH("RPG",$L9)),ISNUMBER(SEARCH("EASYPLUS",$L9)),ISNUMBER(SEARCH("PL/I",$L9))),"Rule 1",IF($M9="Y","Rule 2",IF($N9="Yes","Rule 3","Rule 4"))) -> Rule 1 | Y9: =IF($X9="Rule 1","D",IF($X9="Rule 2","C",IF($X9="Rule 3","B","A"))) -> D | AA9: =IF($Z9="",$Y9,$Z9) -> D | AB9: =IFERROR(INDEX('Classification Rules'!$C$43:$C$46,MATCH($AA9,'Classification Rules'!$B$43:$B$46,0)),"") -> Legacy-coupled core | AC9: =IF($X9="Rule 1","Language: "&$L9,IF($X9="Rule 2","Priority Transfer Target = Y",IF($X9="Rule 3","Cloud Indicator = Yes ("&$O9&")","Cloud Indicator = No, not mainframe, not a transfer target"))) -> Language: COBOL, Assembler, MU(EASYPLUS), JCL | AD9: =IFERROR(INDEX('Classification Rules'!$D$13:$D$16,MATCH($AA9,'Classification Rules'!$B$13:$B$16,0)),"") -> Rules hard-coded across modules and design truth is not written down. AI does comprehension here, not generation. | AE9: =IFERROR(INDEX('Classification Rules'!$D$43:$D$46,MATCH($AA9,'Classification Rules'!$B$43:$B$46,0)),"") -> 0.295 | AF9: =IFERROR(INDEX('Classification Rules'!$E$43:$E$46,MATCH($AA9,'Classification Rules'!$B$43:$B$46,0)),"") -> 0.3337015 | AG9: =IFERROR(INDEX('Classification Rules'!$F$43:$F$46,MATCH($AA9,'Classification Rules'!$B$43:$B$46,0)),"") -> 0.58 | AH9: =IFERROR(INDEX('Classification Rules'!$G$43:$G$46,MATCH($AA9,'Classification Rules'!$B$43:$B$46,0)),"") -> 0.5394 | AI9: =IFERROR(INDEX('Classification Rules'!$I$43:$I$46,MATCH($AA9,'Classification Rules'!$B$43:$B$46,0)),"") -> 14-20 weeks per cluster | AJ9: =IFERROR(INDEX('Classification Rules'!$J$43:$J$46,MATCH($AA9,'Classification Rules'!$B$43:$B$46,0)),"") -> Fully sourced, MetLife SMEs paired | AK9: =IFERROR(INDEX('Classification Rules'!$K$43:$K$46,MATCH($AA9,'Classification Rules'!$B$43:$B$46,0)),"") -> 0
A10: 6 | B10: 9803 | C10: LC UWI MF-JPN | D10: LifeComm UWI | E10: contract management | F10: VS5: New Business, Underwriting & Interfaces | G10: Core Insurance Systems Group 34956 | H10: Policy Admin Systems Team 34957 | I10: Core Business Application | J10: Y | K10: Yes | L10: Assembler, COBOL, MU(EASYPLUS), JCL | M10: N | N10: No | P10: MetLife Owned Application Code | Q10: 8.8045833 | R10: 0.85 | S10: 0 | T10: 9.6545833 | U10: 0.94821113 | V10: 4.8272917 | W10: 4.8272917 | X10: =IF(OR(ISNUMBER(SEARCH("COBOL",$L10)),ISNUMBER(SEARCH("Assembler",$L10)),ISNUMBER(SEARCH("ASM",$L10)),ISNUMBER(SEARCH("RPG",$L10)),ISNUMBER(SEARCH("EASYPLUS",$L10)),ISNUMBER(SEARCH("PL/I",$L10))),"Rule 1",IF($M10="Y","Rule 2",IF($N10="Yes","Rule 3","Rule 4"))) -> Rule 1 | Y10: =IF($X10="Rule 1","D",IF($X10="Rule 2","C",IF($X10="Rule 3","B","A"))) -> D | AA10: =IF($Z10="",$Y10,$Z10) -> D | AB10: =IFERROR(INDEX('Classification Rules'!$C$43:$C$46,MATCH($AA10,'Classification Rules'!$B$43:$B$46,0)),"") -> Legacy-coupled core | AC10: =IF($X10="Rule 1","Language: "&$L10,IF($X10="Rule 2","Priority Transfer Target = Y",IF($X10="Rule 3","Cloud Indicator = Yes ("&$O10&")","Cloud Indicator = No, not mainframe, not a transfer target"))) -> Language: Assembler, COBOL, MU(EASYPLUS), JCL | AD10: =IFERROR(INDEX('Classification Rules'!$D$13:$D$16,MATCH($AA10,'Classification Rules'!$B$13:$B$16,0)),"") -> Rules hard-coded across modules and design truth is not written down. AI does comprehension here, not generation. | AE10: =IFERROR(INDEX('Classification Rules'!$D$43:$D$46,MATCH($AA10,'Classification Rules'!$B$43:$B$46,0)),"") -> 0.295 | AF10: =IFERROR(INDEX('Classification Rules'!$E$43:$E$46,MATCH($AA10,'Classification Rules'!$B$43:$B$46,0)),"") -> 0.3337015 | AG10: =IFERROR(INDEX('Classification Rules'!$F$43:$F$46,MATCH($AA10,'Classification Rules'!$B$43:$B$46,0)),"") -> 0.58 | AH10: =IFERROR(INDEX('Classification Rules'!$G$43:$G$46,MATCH($AA10,'Classification Rules'!$B$43:$B$46,0)),"") -> 0.5394 | AI10: =IFERROR(INDEX('Classification Rules'!$I$43:$I$46,MATCH($AA10,'Classification Rules'!$B$43:$B$46,0)),"") -> 14-20 weeks per cluster | AJ10: =IFERROR(INDEX('Classification Rules'!$J$43:$J$46,MATCH($AA10,'Classification Rules'!$B$43:$B$46,0)),"") -> Fully sourced, MetLife SMEs paired | AK10: =IFERROR(INDEX('Classification Rules'!$K$43:$K$46,MATCH($AA10,'Classification Rules'!$B$43:$B$46,0)),"") -> 0
A11: 7 | B11: 9804 | C11: LC AAPerf MF-JPN | D11: LifeComm AgentAgencyPerformance | E11: contract management | F11: VS3: Agency & Commission | G11: Core Insurance Systems Group 34956 | H11: Policy Admin Systems Team 34957 | I11: Core Business Application | J11: Y | K11: Yes | L11: COBOL, Assembler, MU(EASYPLUS), JCL | M11: N | N11: No | P11: MetLife Owned Application Code | Q11: 10.784167 | R11: 0.74583333 | S11: 0 | T11: 11.53 | U11: 0.83304423 | V11: 5.765 | W11: 5.765 | X11: =IF(OR(ISNUMBER(SEARCH("COBOL",$L11)),ISNUMBER(SEARCH("Assembler",$L11)),ISNUMBER(SEARCH("ASM",$L11)),ISNUMBER(SEARCH("RPG",$L11)),ISNUMBER(SEARCH("EASYPLUS",$L11)),ISNUMBER(SEARCH("PL/I",$L11))),"Rule 1",IF($M11="Y","Rule 2",IF($N11="Yes","Rule 3","Rule 4"))) -> Rule 1 | Y11: =IF($X11="Rule 1","D",IF($X11="Rule 2","C",IF($X11="Rule 3","B","A"))) -> D | AA11: =IF($Z11="",$Y11,$Z11) -> D | AB11: =IFERROR(INDEX('Classification Rules'!$C$43:$C$46,MATCH($AA11,'Classification Rules'!$B$43:$B$46,0)),"") -> Legacy-coupled core | AC11: =IF($X11="Rule 1","Language: "&$L11,IF($X11="Rule 2","Priority Transfer Target = Y",IF($X11="Rule 3","Cloud Indicator = Yes ("&$O11&")","Cloud Indicator = No, not mainframe, not a transfer target"))) -> Language: COBOL, Assembler, MU(EASYPLUS), JCL | AD11: =IFERROR(INDEX('Classification Rules'!$D$13:$D$16,MATCH($AA11,'Classification Rules'!$B$13:$B$16,0)),"") -> Rules hard-coded across modules and design truth is not written down. AI does comprehension here, not generation. | AE11: =IFERROR(INDEX('Classification Rules'!$D$43:$D$46,MATCH($AA11,'Classification Rules'!$B$43:$B$46,0)),"") -> 0.295 | AF11: =IFERROR(INDEX('Classification Rules'!$E$43:$E$46,MATCH($AA11,'Classification Rules'!$B$43:$B$46,0)),"") -> 0.3337015 | AG11: =IFERROR(INDEX('Classification Rules'!$F$43:$F$46,MATCH($AA11,'Classification Rules'!$B$43:$B$46,0)),"") -> 0.58 | AH11: =IFERROR(INDEX('Classification Rules'!$G$43:$G$46,MATCH($AA11,'Classification Rules'!$B$43:$B$46,0)),"") -> 0.5394 | AI11: =IFERROR(INDEX('Classification Rules'!$I$43:$I$46,MATCH($AA11,'Classification Rules'!$B$43:$B$46,0)),"") -> 14-20 weeks per cluster | AJ11: =IFERROR(INDEX('Classification Rules'!$J$43:$J$46,MATCH($AA11,'Classification Rules'!$B$43:$B$46,0)),"") -> Fully sourced, MetLife SMEs paired | AK11: =IFERROR(INDEX('Classification Rules'!$K$43:$K$46,MATCH($AA11,'Classification Rules'!$B$43:$B$46,0)),"") -> 0
A12: 8 | B12: 9805 | C12: LC Payment MF-JPN | D12: LifeComm Payment | E12: contract management | F12: VS2: Billing, Collections & Payments | G12: Core Insurance Systems Group 34956 | H12: Policy Admin Systems Team 34957 | I12: Core Business Application | J12: Y | K12: Yes | L12: COBOL, Assembler, MU(EASYPLUS), JCL | M12: N | N12: No | P12: MetLife Owned Application Code | Q12: 2.8966667 | R12: 0.025 | S12: 0 | T12: 2.9216667 | U12: 0.90587564 | V12: 1.4608333 | W12: 1.4608333 | X12: =IF(OR(ISNUMBER(SEARCH("COBOL",$L12)),ISNUMBER(SEARCH("Assembler",$L12)),ISNUMBER(SEARCH("ASM",$L12)),ISNUMBER(SEARCH("RPG",$L12)),ISNUMBER(SEARCH("EASYPLUS",$L12)),ISNUMBER(SEARCH("PL/I",$L12))),"Rule 1",IF($M12="Y","Rule 2",IF($N12="Yes","Rule 3","Rule 4"))) -> Rule 1 | Y12: =IF($X12="Rule 1","D",IF($X12="Rule 2","C",IF($X12="Rule 3","B","A"))) -> D | AA12: =IF($Z12="",$Y12,$Z12) -> D | AB12: =IFERROR(INDEX('Classification Rules'!$C$43:$C$46,MATCH($AA12,'Classification Rules'!$B$43:$B$46,0)),"") -> Legacy-coupled core | AC12: =IF($X12="Rule 1","Language: "&$L12,IF($X12="Rule 2","Priority Transfer Target = Y",IF($X12="Rule 3","Cloud Indicator = Yes ("&$O12&")","Cloud Indicator = No, not mainframe, not a transfer target"))) -> Language: COBOL, Assembler, MU(EASYPLUS), JCL | AD12: =IFERROR(INDEX('Classification Rules'!$D$13:$D$16,MATCH($AA12,'Classification Rules'!$B$13:$B$16,0)),"") -> Rules hard-coded across modules and design truth is not written down. AI does comprehension here, not generation. | AE12: =IFERROR(INDEX('Classification Rules'!$D$43:$D$46,MATCH($AA12,'Classification Rules'!$B$43:$B$46,0)),"") -> 0.295 | AF12: =IFERROR(INDEX('Classification Rules'!$E$43:$E$46,MATCH($AA12,'Classification Rules'!$B$43:$B$46,0)),"") -> 0.3337015 | AG12: =IFERROR(INDEX('Classification Rules'!$F$43:$F$46,MATCH($AA12,'Classification Rules'!$B$43:$B$46,0)),"") -> 0.58 | AH12: =IFERROR(INDEX('Classification Rules'!$G$43:$G$46,MATCH($AA12,'Classification Rules'!$B$43:$B$46,0)),"") -> 0.5394 | AI12: =IFERROR(INDEX('Classification Rules'!$I$43:$I$46,MATCH($AA12,'Classification Rules'!$B$43:$B$46,0)),"") -> 14-20 weeks per cluster | AJ12: =IFERROR(INDEX('Classification Rules'!$J$43:$J$46,MATCH($AA12,'Classification Rules'!$B$43:$B$46,0)),"") -> Fully sourced, MetLife SMEs paired | AK12: =IFERROR(INDEX('Classification Rules'!$K$43:$K$46,MATCH($AA12,'Classification Rules'!$B$43:$B$46,0)),"") -> 0
A13: 9 | B13: 9806 | C13: LC GL/SC MF-JPN | D13: LifeComm GL/SC | E13: contract management | F13: VS6: Finance, Valuation & Reinsurance | G13: Core Insurance Systems Group 34956 | H13: Policy Admin Systems Team 34957 | I13: Core Business Application | J13: Y | K13: Yes | L13: COBOL, Assembler, MU(EASYPLUS), JCL | M13: N | N13: No | P13: MetLife Owned Application Code | Q13: 5.28875 | R13: 1.025 | S13: 0 | T13: 6.31375 | U13: 0.83765591 | V13: 3.156875 | W13: 3.156875 | X13: =IF(OR(ISNUMBER(SEARCH("COBOL",$L13)),ISNUMBER(SEARCH("Assembler",$L13)),ISNUMBER(SEARCH("ASM",$L13)),ISNUMBER(SEARCH("RPG",$L13)),ISNUMBER(SEARCH("EASYPLUS",$L13)),ISNUMBER(SEARCH("PL/I",$L13))),"Rule 1",IF($M13="Y","Rule 2",IF($N13="Yes","Rule 3","Rule 4"))) -> Rule 1 | Y13: =IF($X13="Rule 1","D",IF($X13="Rule 2","C",IF($X13="Rule 3","B","A"))) -> D | AA13: =IF($Z13="",$Y13,$Z13) -> D | AB13: =IFERROR(INDEX('Classification Rules'!$C$43:$C$46,MATCH($AA13,'Classification Rules'!$B$43:$B$46,0)),"") -> Legacy-coupled core | AC13: =IF($X13="Rule 1","Language: "&$L13,IF($X13="Rule 2","Priority Transfer Target = Y",IF($X13="Rule 3","Cloud Indicator = Yes ("&$O13&")","Cloud Indicator = No, not mainframe, not a transfer target"))) -> Language: COBOL, Assembler, MU(EASYPLUS), JCL | AD13: =IFERROR(INDEX('Classification Rules'!$D$13:$D$16,MATCH($AA13,'Classification Rules'!$B$13:$B$16,0)),"") -> Rules hard-coded across modules and design truth is not written down. AI does comprehension here, not generation. | AE13: =IFERROR(INDEX('Classification Rules'!$D$43:$D$46,MATCH($AA13,'Classification Rules'!$B$43:$B$46,0)),"") -> 0.295 | AF13: =IFERROR(INDEX('Classification Rules'!$E$43:$E$46,MATCH($AA13,'Classification Rules'!$B$43:$B$46,0)),"") -> 0.3337015 | AG13: =IFERROR(INDEX('Classification Rules'!$F$43:$F$46,MATCH($AA13,'Classification Rules'!$B$43:$B$46,0)),"") -> 0.58 | AH13: =IFERROR(INDEX('Classification Rules'!$G$43:$G$46,MATCH($AA13,'Classification Rules'!$B$43:$B$46,0)),"") -> 0.5394 | AI13: =IFERROR(INDEX('Classification Rules'!$I$43:$I$46,MATCH($AA13,'Classification Rules'!$B$43:$B$46,0)),"") -> 14-20 weeks per cluster | AJ13: =IFERROR(INDEX('Classification Rules'!$J$43:$J$46,MATCH($AA13,'Classification Rules'!$B$43:$B$46,0)),"") -> Fully sourced, MetLife SMEs paired | AK13: =IFERROR(INDEX('Classification Rules'!$K$43:$K$46,MATCH($AA13,'Classification Rules'!$B$43:$B$46,0)),"") -> 0
A14: 10 | B14: 9807 | C14: LC Valuation MF-JPN | D14: LifeComm Valuation | E14: contract management | F14: VS6: Finance, Valuation & Reinsurance | G14: Core Insurance Systems Group 34956 | H14: Policy Admin Systems Team 34957 | I14: Core Business Application | J14: N | K14: Yes | L14: COBOL, Assembler, MU(EASYPLUS), JCL | M14: N | N14: No | P14: MetLife Owned Application Code | Q14: 9.76875 | R14: 1.4833333 | S14: 0 | T14: 11.252083 | U14: 0.8563229 | V14: 5.6260417 | W14: 5.6260417 | X14: =IF(OR(ISNUMBER(SEARCH("COBOL",$L14)),ISNUMBER(SEARCH("Assembler",$L14)),ISNUMBER(SEARCH("ASM",$L14)),ISNUMBER(SEARCH("RPG",$L14)),ISNUMBER(SEARCH("EASYPLUS",$L14)),ISNUMBER(SEARCH("PL/I",$L14))),"Rule 1",IF($M14="Y","Rule 2",IF($N14="Yes","Rule 3","Rule 4"))) -> Rule 1 | Y14: =IF($X14="Rule 1","D",IF($X14="Rule 2","C",IF($X14="Rule 3","B","A"))) -> D | AA14: =IF($Z14="",$Y14,$Z14) -> D | AB14: =IFERROR(INDEX('Classification Rules'!$C$43:$C$46,MATCH($AA14,'Classification Rules'!$B$43:$B$46,0)),"") -> Legacy-coupled core | AC14: =IF($X14="Rule 1","Language: "&$L14,IF($X14="Rule 2","Priority Transfer Target = Y",IF($X14="Rule 3","Cloud Indicator = Yes ("&$O14&")","Cloud Indicator = No, not mainframe, not a transfer target"))) -> Language: COBOL, Assembler, MU(EASYPLUS), JCL | AD14: =IFERROR(INDEX('Classification Rules'!$D$13:$D$16,MATCH($AA14,'Classification Rules'!$B$13:$B$16,0)),"") -> Rules hard-coded across modules and design truth is not written down. AI does comprehension here, not generation. | AE14: =IFERROR(INDEX('Classification Rules'!$D$43:$D$46,MATCH($AA14,'Classification Rules'!$B$43:$B$46,0)),"") -> 0.295 | AF14: =IFERROR(INDEX('Classification Rules'!$E$43:$E$46,MATCH($AA14,'Classification Rules'!$B$43:$B$46,0)),"") -> 0.3337015 | AG14: =IFERROR(INDEX('Classification Rules'!$F$43:$F$46,MATCH($AA14,'Classification Rules'!$B$43:$B$46,0)),"") -> 0.58 | AH14: =IFERROR(INDEX('Classification Rules'!$G$43:$G$46,MATCH($AA14,'Classification Rules'!$B$43:$B$46,0)),"") -> 0.5394 | AI14: =IFERROR(INDEX('Classification Rules'!$I$43:$I$46,MATCH($AA14,'Classification Rules'!$B$43:$B$46,0)),"") -> 14-20 weeks per cluster | AJ14: =IFERROR(INDEX('Classification Rules'!$J$43:$J$46,MATCH($AA14,'Classification Rules'!$B$43:$B$46,0)),"") -> Fully sourced, MetLife SMEs paired | AK14: =IFERROR(INDEX('Classification Rules'!$K$43:$K$46,MATCH($AA14,'Classification Rules'!$B$43:$B$46,0)),"") -> 0
A15: 11 | B15: 9808 | C15: LC AACOMP MF-JPN | D15: LifeComm AgentAgencyComp | E15: contract management | F15: VS3: Agency & Commission | G15: Core Insurance Systems Group 34956 | H15: Policy Admin Systems Team 34957 | I15: Core Business Application | J15: Y | K15: Yes | L15: COBOL, Assembler, MU(EASYPLUS), JCL | M15: N | N15: No | P15: MetLife Owned Application Code | Q15: 13.545708 | R15: 3.14375 | S15: 0 | T15: 16.689458 | U15: 0.72662384 | V15: 8.3447292 | W15: 8.3447292 | X15: =IF(OR(ISNUMBER(SEARCH("COBOL",$L15)),ISNUMBER(SEARCH("Assembler",$L15)),ISNUMBER(SEARCH("ASM",$L15)),ISNUMBER(SEARCH("RPG",$L15)),ISNUMBER(SEARCH("EASYPLUS",$L15)),ISNUMBER(SEARCH("PL/I",$L15))),"Rule 1",IF($M15="Y","Rule 2",IF($N15="Yes","Rule 3","Rule 4"))) -> Rule 1 | Y15: =IF($X15="Rule 1","D",IF($X15="Rule 2","C",IF($X15="Rule 3","B","A"))) -> D | AA15: =IF($Z15="",$Y15,$Z15) -> D | AB15: =IFERROR(INDEX('Classification Rules'!$C$43:$C$46,MATCH($AA15,'Classification Rules'!$B$43:$B$46,0)),"") -> Legacy-coupled core | AC15: =IF($X15="Rule 1","Language: "&$L15,IF($X15="Rule 2","Priority Transfer Target = Y",IF($X15="Rule 3","Cloud Indicator = Yes ("&$O15&")","Cloud Indicator = No, not mainframe, not a transfer target"))) -> Language: COBOL, Assembler, MU(EASYPLUS), JCL | AD15: =IFERROR(INDEX('Classification Rules'!$D$13:$D$16,MATCH($AA15,'Classification Rules'!$B$13:$B$16,0)),"") -> Rules hard-coded across modules and design truth is not written down. AI does comprehension here, not generation. | AE15: =IFERROR(INDEX('Classification Rules'!$D$43:$D$46,MATCH($AA15,'Classification Rules'!$B$43:$B$46,0)),"") -> 0.295 | AF15: =IFERROR(INDEX('Classification Rules'!$E$43:$E$46,MATCH($AA15,'Classification Rules'!$B$43:$B$46,0)),"") -> 0.3337015 | AG15: =IFERROR(INDEX('Classification Rules'!$F$43:$F$46,MATCH($AA15,'Classification Rules'!$B$43:$B$46,0)),"") -> 0.58 | AH15: =IFERROR(INDEX('Classification Rules'!$G$43:$G$46,MATCH($AA15,'Classification Rules'!$B$43:$B$46,0)),"") -> 0.5394 | AI15: =IFERROR(INDEX('Classification Rules'!$I$43:$I$46,MATCH($AA15,'Classification Rules'!$B$43:$B$46,0)),"") -> 14-20 weeks per cluster | AJ15: =IFERROR(INDEX('Classification Rules'!$J$43:$J$46,MATCH($AA15,'Classification Rules'!$B$43:$B$46,0)),"") -> Fully sourced, MetLife SMEs paired | AK15: =IFERROR(INDEX('Classification Rules'!$K$43:$K$46,MATCH($AA15,'Classification Rules'!$B$43:$B$46,0)),"") -> 0
A16: 12 | B16: 9810 | C16: Processor-I MF-JPN | D16: Claim payment (Processor-I) | E16: contract management | F16: VS2: Billing, Collections & Payments | G16: Core Insurance Systems Group 34956 | H16: Policy Admin Systems Team 34957 | I16: Core Business Application | J16: Y | K16: Yes | L16: COBOL, MU(EASYPLUS), Assembler, JCL | M16: N | N16: No | P16: MetLife Owned Application Code | Q16: 7.6683333 | R16: 1.1291667 | S16: 0 | T16: 8.7975 | U16: 0.75561239 | V16: 4.39875 | W16: 4.39875 | X16: =IF(OR(ISNUMBER(SEARCH("COBOL",$L16)),ISNUMBER(SEARCH("Assembler",$L16)),ISNUMBER(SEARCH("ASM",$L16)),ISNUMBER(SEARCH("RPG",$L16)),ISNUMBER(SEARCH("EASYPLUS",$L16)),ISNUMBER(SEARCH("PL/I",$L16))),"Rule 1",IF($M16="Y","Rule 2",IF($N16="Yes","Rule 3","Rule 4"))) -> Rule 1 | Y16: =IF($X16="Rule 1","D",IF($X16="Rule 2","C",IF($X16="Rule 3","B","A"))) -> D | AA16: =IF($Z16="",$Y16,$Z16) -> D | AB16: =IFERROR(INDEX('Classification Rules'!$C$43:$C$46,MATCH($AA16,'Classification Rules'!$B$43:$B$46,0)),"") -> Legacy-coupled core | AC16: =IF($X16="Rule 1","Language: "&$L16,IF($X16="Rule 2","Priority Transfer Target = Y",IF($X16="Rule 3","Cloud Indicator = Yes ("&$O16&")","Cloud Indicator = No, not mainframe, not a transfer target"))) -> Language: COBOL, MU(EASYPLUS), Assembler, JCL | AD16: =IFERROR(INDEX('Classification Rules'!$D$13:$D$16,MATCH($AA16,'Classification Rules'!$B$13:$B$16,0)),"") -> Rules hard-coded across modules and design truth is not written down. AI does comprehension here, not generation. | AE16: =IFERROR(INDEX('Classification Rules'!$D$43:$D$46,MATCH($AA16,'Classification Rules'!$B$43:$B$46,0)),"") -> 0.295 | AF16: =IFERROR(INDEX('Classification Rules'!$E$43:$E$46,MATCH($AA16,'Classification Rules'!$B$43:$B$46,0)),"") -> 0.3337015 | AG16: =IFERROR(INDEX('Classification Rules'!$F$43:$F$46,MATCH($AA16,'Classification Rules'!$B$43:$B$46,0)),"") -> 0.58 | AH16: =IFERROR(INDEX('Classification Rules'!$G$43:$G$46,MATCH($AA16,'Classification Rules'!$B$43:$B$46,0)),"") -> 0.5394 | AI16: =IFERROR(INDEX('Classification Rules'!$I$43:$I$46,MATCH($AA16,'Classification Rules'!$B$43:$B$46,0)),"") -> 14-20 weeks per cluster | AJ16: =IFERROR(INDEX('Classification Rules'!$J$43:$J$46,MATCH($AA16,'Classification Rules'!$B$43:$B$46,0)),"") -> Fully sourced, MetLife SMEs paired | AK16: =IFERROR(INDEX('Classification Rules'!$K$43:$K$46,MATCH($AA16,'Classification Rules'!$B$43:$B$46,0)),"") -> 0
A17: 13 | B17: 9811 | C17: LC Submit MF-JPN | D17: Submit Online | E17: contract management | F17: VS5: New Business, Underwriting & Interfaces | G17: Core Insurance Systems Group 34956 | H17: Policy Admin Systems Team 34957 | I17: Core Business Application | J17: Y | K17: Yes | L17: COBOL, MU(EASYPLUS), Assembler, JCL | M17: N | N17: No | P17: MetLife Owned Application Code | Q17: 1.9683333 | R17: 0.16458333 | S17: 0 | T17: 2.1329167 | U17: 0.95311584 | V17: 1.0664583 | W17: 1.0664583 | X17: =IF(OR(ISNUMBER(SEARCH("COBOL",$L17)),ISNUMBER(SEARCH("Assembler",$L17)),ISNUMBER(SEARCH("ASM",$L17)),ISNUMBER(SEARCH("RPG",$L17)),ISNUMBER(SEARCH("EASYPLUS",$L17)),ISNUMBER(SEARCH("PL/I",$L17))),"Rule 1",IF($M17="Y","Rule 2",IF($N17="Yes","Rule 3","Rule 4"))) -> Rule 1 | Y17: =IF($X17="Rule 1","D",IF($X17="Rule 2","C",IF($X17="Rule 3","B","A"))) -> D | AA17: =IF($Z17="",$Y17,$Z17) -> D | AB17: =IFERROR(INDEX('Classification Rules'!$C$43:$C$46,MATCH($AA17,'Classification Rules'!$B$43:$B$46,0)),"") -> Legacy-coupled core | AC17: =IF($X17="Rule 1","Language: "&$L17,IF($X17="Rule 2","Priority Transfer Target = Y",IF($X17="Rule 3","Cloud Indicator = Yes ("&$O17&")","Cloud Indicator = No, not mainframe, not a transfer target"))) -> Language: COBOL, MU(EASYPLUS), Assembler, JCL | AD17: =IFERROR(INDEX('Classification Rules'!$D$13:$D$16,MATCH($AA17,'Classification Rules'!$B$13:$B$16,0)),"") -> Rules hard-coded across modules and design truth is not written down. AI does comprehension here, not generation. | AE17: =IFERROR(INDEX('Classification Rules'!$D$43:$D$46,MATCH($AA17,'Classification Rules'!$B$43:$B$46,0)),"") -> 0.295 | AF17: =IFERROR(INDEX('Classification Rules'!$E$43:$E$46,MATCH($AA17,'Classification Rules'!$B$43:$B$46,0)),"") -> 0.3337015 | AG17: =IFERROR(INDEX('Classification Rules'!$F$43:$F$46,MATCH($AA17,'Classification Rules'!$B$43:$B$46,0)),"") -> 0.58 | AH17: =IFERROR(INDEX('Classification Rules'!$G$43:$G$46,MATCH($AA17,'Classification Rules'!$B$43:$B$46,0)),"") -> 0.5394 | AI17: =IFERROR(INDEX('Classification Rules'!$I$43:$I$46,MATCH($AA17,'Classification Rules'!$B$43:$B$46,0)),"") -> 14-20 weeks per cluster | AJ17: =IFERROR(INDEX('Classification Rules'!$J$43:$J$46,MATCH($AA17,'Classification Rules'!$B$43:$B$46,0)),"") -> Fully sourced, MetLife SMEs paired | AK17: =IFERROR(INDEX('Classification Rules'!$K$43:$K$46,MATCH($AA17,'Classification Rules'!$B$43:$B$46,0)),"") -> 0
... A40: 36 | B40: 9849 | C40: C04OSI-JPN | D40: S Sum Total System(Open) | E40: New Contract Related | F40: VS1: New Business Processing | G40: Customer Service and Operations Systems Group 34965 | H40: New Business Team 34966 | I40: Common Service Business Application | J40: N | K40: Yes | L40: JAVA | M40: N | N40: No | P40: MetLife Owned Application Code | Q40: 5.18625 | R40: 0.38333333 | S40: 0 | T40: 5.5695833 | U40: 0.8315254 | V40: 2.7847917 | W40: 2.7847917 | X40: =IF(OR(ISNUMBER(SEARCH("COBOL",$L40)),ISNUMBER(SEARCH("Assembler",$L40)),ISNUMBER(SEARCH("ASM",$L40)),ISNUMBER(SEARCH("RPG",$L40)),ISNUMBER(SEARCH("EASYPLUS",$L40)),ISNUMBER(SEARCH("PL/I",$L40))),"Rule 1",IF($M40="Y","Rule 2",IF($N40="Yes","Rule 3","Rule 4"))) -> Rule 4 | Y40: =IF($X40="Rule 1","D",IF($X40="Rule 2","C",IF($X40="Rule 3","B","A"))) -> A | AA40: =IF($Z40="",$Y40,$Z40) -> A | AB40: =IFERROR(INDEX('Classification Rules'!$C$43:$C$46,MATCH($AA40,'Classification Rules'!$B$43:$B$46,0)),"") -> Language-locked | AC40: =IF($X40="Rule 1","Language: "&$L40,IF($X40="Rule 2","Priority Transfer Target = Y",IF($X40="Rule 3","Cloud Indicator = Yes ("&$O40&")","Cloud Indicator = No, not mainframe, not a transfer target"))) -> Cloud Indicator = No, not mainframe, not a transfer target | AD40: =IFERROR(INDEX('Classification Rules'!$D$13:$D$16,MATCH($AA40,'Classification Rules'!$B$13:$B$16,0)),"") -> On-premises and non-mainframe, so the constraint is not the technology — it is that the business context exists only in Japanese, in few heads. | AE40: =IFERROR(INDEX('Classification Rules'!$D$43:$D$46,MATCH($AA40,'Classification Rules'!$B$43:$B$46,0)),"") -> 0.304 | AF40: =IFERROR(INDEX('Classification Rules'!$E$43:$E$46,MATCH($AA40,'Classification Rules'!$B$43:$B$46,0)),"") -> 0.3394768 | AG40: =IFERROR(INDEX('Classification Rules'!$F$43:$F$46,MATCH($AA40,'Classification Rules'!$B$43:$B$46,0)),"") -> 0.15 | AH40: =IFERROR(INDEX('Classification Rules'!$G$43:$G$46,MATCH($AA40,'Classification Rules'!$B$43:$B$46,0)),"") -> 0.1395 | AI40: =IFERROR(INDEX('Classification Rules'!$I$43:$I$46,MATCH($AA40,'Classification Rules'!$B$43:$B$46,0)),"") -> 10-14 weeks per cluster | AJ40: =IFERROR(INDEX('Classification Rules'!$J$43:$J$46,MATCH($AA40,'Classification Rules'!$B$43:$B$46,0)),"") -> Fully sourced, onshore-weighted | AK40: =IFERROR(INDEX('Classification Rules'!$K$43:$K$46,MATCH($AA40,'Classification Rules'!$B$43:$B$46,0)),"") -> 0
A41: 37 | B41: 9851 | C41: W03FIC-JPN | D41: Guidance Refusal Information Administration System | E41: Corporate Related | F41: VS3: Risk, Compliance & Governance | G41: Core Insurance Systems Group 34956 | H41: Corporate Systems Team 34959 | I41: Core Business Application | J41: N | K41: Yes | L41: JAVA | M41: N | N41: Yes | O41: Platform as a Service (PaaS) | P41: MetLife Owned Application Code | Q41: 0.29166667 | R41: 0.11666667 | S41: 0 | T41: 0.40833333 | U41: 0.82653061 | V41: 0.20416667 | W41: 0.20416667 | X41: =IF(OR(ISNUMBER(SEARCH("COBOL",$L41)),ISNUMBER(SEARCH("Assembler",$L41)),ISNUMBER(SEARCH("ASM",$L41)),ISNUMBER(SEARCH("RPG",$L41)),ISNUMBER(SEARCH("EASYPLUS",$L41)),ISNUMBER(SEARCH("PL/I",$L41))),"Rule 1",IF($M41="Y","Rule 2",IF($N41="Yes","Rule 3","Rule 4"))) -> Rule 3 | Y41: =IF($X41="Rule 1","D",IF($X41="Rule 2","C",IF($X41="Rule 3","B","A"))) -> B | AA41: =IF($Z41="",$Y41,$Z41) -> B | AB41: =IFERROR(INDEX('Classification Rules'!$C$43:$C$46,MATCH($AA41,'Classification Rules'!$B$43:$B$46,0)),"") -> Offshore-ready | AC41: =IF($X41="Rule 1","Language: "&$L41,IF($X41="Rule 2","Priority Transfer Target = Y",IF($X41="Rule 3","Cloud Indicator = Yes ("&$O41&")","Cloud Indicator = No, not mainframe, not a transfer target"))) -> Cloud Indicator = Yes (Platform as a Service (PaaS)) | AD41: =IFERROR(INDEX('Classification Rules'!$D$13:$D$16,MATCH($AA41,'Classification Rules'!$B$13:$B$16,0)),"") -> Cloud migration has already forced re-platforming, documentation and specifiability. Highest AI and offshore ceiling in the estate. | AE41: =IFERROR(INDEX('Classification Rules'!$D$43:$D$46,MATCH($AA41,'Classification Rules'!$B$43:$B$46,0)),"") -> 0.4825 | AF41: =IFERROR(INDEX('Classification Rules'!$E$43:$E$46,MATCH($AA41,'Classification Rules'!$B$43:$B$46,0)),"") -> 0.45402025 | AG41: =IFERROR(INDEX('Classification Rules'!$F$43:$F$46,MATCH($AA41,'Classification Rules'!$B$43:$B$46,0)),"") -> 0.78 | AH41: =IFERROR(INDEX('Classification Rules'!$G$43:$G$46,MATCH($AA41,'Classification Rules'!$B$43:$B$46,0)),"") -> 0.7254 | AI41: =IFERROR(INDEX('Classification Rules'!$I$43:$I$46,MATCH($AA41,'Classification Rules'!$B$43:$B$46,0)),"") -> 6-8 weeks per cluster | AJ41: =IFERROR(INDEX('Classification Rules'!$J$43:$J$46,MATCH($AA41,'Classification Rules'!$B$43:$B$46,0)),"") -> Fully sourced, moving to output units | AK41: =IFERROR(INDEX('Classification Rules'!$K$43:$K$46,MATCH($AA41,'Classification Rules'!$B$43:$B$46,0)),"") -> 0
A42: 38 | B42: 9852 | C42: C03APO-JPN | D42: Apollocs | E42: Corporate Related | F42: VS5: Corporate Integration & Batch Services | G42: Core Insurance Systems Group 34956 | H42: Corporate Systems Team 34959 | I42: Core Business Application | J42: N | K42: Yes | L42: Other#APOLLOCS | M42: N | N42: No | P42: Non-MetLife Owned Application Code (3rd party/COTS) | Q42: 0.50833333 | R42: 0 | S42: 0 | T42: 0.50833333 | U42: 0.36885246 | V42: 0.25416667 | W42: 0.25416667 | X42: =IF(OR(ISNUMBER(SEARCH("COBOL",$L42)),ISNUMBER(SEARCH("Assembler",$L42)),ISNUMBER(SEARCH("ASM",$L42)),ISNUMBER(SEARCH("RPG",$L42)),ISNUMBER(SEARCH("EASYPLUS",$L42)),ISNUMBER(SEARCH("PL/I",$L42))),"Rule 1",IF($M42="Y","Rule 2",IF($N42="Yes","Rule 3","Rule 4"))) -> Rule 4 | Y42: =IF($X42="Rule 1","D",IF($X42="Rule 2","C",IF($X42="Rule 3","B","A"))) -> A | AA42: =IF($Z42="",$Y42,$Z42) -> A | AB42: =IFERROR(INDEX('Classification Rules'!$C$43:$C$46,MATCH($AA42,'Classification Rules'!$B$43:$B$46,0)),"") -> Language-locked | AC42: =IF($X42="Rule 1","Language: "&$L42,IF($X42="Rule 2","Priority Transfer Target = Y",IF($X42="Rule 3","Cloud Indicator = Yes ("&$O42&")","Cloud Indicator = No, not mainframe, not a transfer target"))) -> Cloud Indicator = No, not mainframe, not a transfer target | AD42: =IFERROR(INDEX('Classification Rules'!$D$13:$D$16,MATCH($AA42,'Classification Rules'!$B$13:$B$16,0)),"") -> On-premises and non-mainframe, so the constraint is not the technology — it is that the business context exists only in Japanese, in few heads. | AE42: =IFERROR(INDEX('Classification Rules'!$D$43:$D$46,MATCH($AA42,'Classification Rules'!$B$43:$B$46,0)),"") -> 0.304 | AF42: =IFERROR(INDEX('Classification Rules'!$E$43:$E$46,MATCH($AA42,'Classification Rules'!$B$43:$B$46,0)),"") -> 0.3394768 | AG42: =IFERROR(INDEX('Classification Rules'!$F$43:$F$46,MATCH($AA42,'Classification Rules'!$B$43:$B$46,0)),"") -> 0.15 | AH42: =IFERROR(INDEX('Classification Rules'!$G$43:$G$46,MATCH($AA42,'Classification Rules'!$B$43:$B$46,0)),"") -> 0.1395 | AI42: =IFERROR(INDEX('Classification Rules'!$I$43:$I$46,MATCH($AA42,'Classification Rules'!$B$43:$B$46,0)),"") -> 10-14 weeks per cluster | AJ42: =IFERROR(INDEX('Classification Rules'!$J$43:$J$46,MATCH($AA42,'Classification Rules'!$B$43:$B$46,0)),"") -> Fully sourced, onshore-weighted | AK42: =IFERROR(INDEX('Classification Rules'!$K$43:$K$46,MATCH($AA42,'Classification Rules'!$B$43:$B$46,0)),"") -> 0
A43: 39 | B43: 9854 | C43: Z04IMA-JPN | D43: Image Search | E43: New Contract Related | F43: VS4: Imaging & Document Capture | G43: Customer Service and Operations Systems Group 34965 | H43: New Business Team 34966 | I43: Core Business Application | J43: N | K43: Yes | L43: CSS; JAVA;HTML; VB.NET | M43: N | N43: No | P43: MetLife Owned Application Code | Q43: 1.4004167 | R43: 0 | S43: 0 | T43: 1.4004167 | U43: 0.92859268 | V43: 0.70020833 | W43: 0.70020833 | X43: =IF(OR(ISNUMBER(SEARCH("COBOL",$L43)),ISNUMBER(SEARCH("Assembler",$L43)),ISNUMBER(SEARCH("ASM",$L43)),ISNUMBER(SEARCH("RPG",$L43)),ISNUMBER(SEARCH("EASYPLUS",$L43)),ISNUMBER(SEARCH("PL/I",$L43))),"Rule 1",IF($M43="Y","Rule 2",IF($N43="Yes","Rule 3","Rule 4"))) -> Rule 4 | Y43: =IF($X43="Rule 1","D",IF($X43="Rule 2","C",IF($X43="Rule 3","B","A"))) -> A | AA43: =IF($Z43="",$Y43,$Z43) -> A | AB43: =IFERROR(INDEX('Classification Rules'!$C$43:$C$46,MATCH($AA43,'Classification Rules'!$B$43:$B$46,0)),"") -> Language-locked | AC43: =IF($X43="Rule 1","Language: "&$L43,IF($X43="Rule 2","Priority Transfer Target = Y",IF($X43="Rule 3","Cloud Indicator = Yes ("&$O43&")","Cloud Indicator = No, not mainframe, not a transfer target"))) -> Cloud Indicator = No, not mainframe, not a transfer target | AD43: =IFERROR(INDEX('Classification Rules'!$D$13:$D$16,MATCH($AA43,'Classification Rules'!$B$13:$B$16,0)),"") -> On-premises and non-mainframe, so the constraint is not the technology — it is that the business context exists only in Japanese, in few heads. | AE43: =IFERROR(INDEX('Classification Rules'!$D$43:$D$46,MATCH($AA43,'Classification Rules'!$B$43:$B$46,0)),"") -> 0.304 | AF43: =IFERROR(INDEX('Classification Rules'!$E$43:$E$46,MATCH($AA43,'Classification Rules'!$B$43:$B$46,0)),"") -> 0.3394768 | AG43: =IFERROR(INDEX('Classification Rules'!$F$43:$F$46,MATCH($AA43,'Classification Rules'!$B$43:$B$46,0)),"") -> 0.15 | AH43: =IFERROR(INDEX('Classification Rules'!$G$43:$G$46,MATCH($AA43,'Classification Rules'!$B$43:$B$46,0)),"") -> 0.1395 | AI43: =IFERROR(INDEX('Classification Rules'!$I$43:$I$46,MATCH($AA43,'Classification Rules'!$B$43:$B$46,0)),"") -> 10-14 weeks per cluster | AJ43: =IFERROR(INDEX('Classification Rules'!$J$43:$J$46,MATCH($AA43,'Classification Rules'!$B$43:$B$46,0)),"") -> Fully sourced, onshore-weighted | AK43: =IFERROR(INDEX('Classification Rules'!$K$43:$K$46,MATCH($AA43,'Classification Rules'!$B$43:$B$46,0)),"") -> 0
A44: 40 | B44: 9857 | C44: W05AMS-JPN | D44: Annuity Information Management System(AIMS) | E44: Insurance Claims and Benefits Payment Related | F44: VS2: Pension, Benefits & Maturity Administration | G44: Customer Service and Operations Systems Group 34965 | H44: Claims Team 34968 | I44: Core Business Application | J44: Y | K44: Yes | L44: JAVA | M44: N | N44: No | P44: MetLife Owned Application Code | Q44: 20.211667 | R44: 1.8166667 | S44: 0 | T44: 22.028333 | U44: 0.92547477 | V44: 11.014167 | W44: 11.014167 | X44: =IF(OR(ISNUMBER(SEARCH("COBOL",$L44)),ISNUMBER(SEARCH("Assembler",$L44)),ISNUMBER(SEARCH("ASM",$L44)),ISNUMBER(SEARCH("RPG",$L44)),ISNUMBER(SEARCH("EASYPLUS",$L44)),ISNUMBER(SEARCH("PL/I",$L44))),"Rule 1",IF($M44="Y","Rule 2",IF($N44="Yes","Rule 3","Rule 4"))) -> Rule 4 | Y44: =IF($X44="Rule 1","D",IF($X44="Rule 2","C",IF($X44="Rule 3","B","A"))) -> A | AA44: =IF($Z44="",$Y44,$Z44) -> A | AB44: =IFERROR(INDEX('Classification Rules'!$C$43:$C$46,MATCH($AA44,'Classification Rules'!$B$43:$B$46,0)),"") -> Language-locked | AC44: =IF($X44="Rule 1","Language: "&$L44,IF($X44="Rule 2","Priority Transfer Target = Y",IF($X44="Rule 3","Cloud Indicator = Yes ("&$O44&")","Cloud Indicator = No, not mainframe, not a transfer target"))) -> Cloud Indicator = No, not mainframe, not a transfer target | AD44: =IFERROR(INDEX('Classification Rules'!$D$13:$D$16,MATCH($AA44,'Classification Rules'!$B$13:$B$16,0)),"") -> On-premises and non-mainframe, so the constraint is not the technology — it is that the business context exists only in Japanese, in few heads. | AE44: =IFERROR(INDEX('Classification Rules'!$D$43:$D$46,MATCH($AA44,'Classification Rules'!$B$43:$B$46,0)),"") -> 0.304 | AF44: =IFERROR(INDEX('Classification Rules'!$E$43:$E$46,MATCH($AA44,'Classification Rules'!$B$43:$B$46,0)),"") -> 0.3394768 | AG44: =IFERROR(INDEX('Classification Rules'!$F$43:$F$46,MATCH($AA44,'Classification Rules'!$B$43:$B$46,0)),"") -> 0.15 | AH44: =IFERROR(INDEX('Classification Rules'!$G$43:$G$46,MATCH($AA44,'Classification Rules'!$B$43:$B$46,0)),"") -> 0.1395 | AI44: =IFERROR(INDEX('Classification Rules'!$I$43:$I$46,MATCH($AA44,'Classification Rules'!$B$43:$B$46,0)),"") -> 10-14 weeks per cluster | AJ44: =IFERROR(INDEX('Classification Rules'!$J$43:$J$46,MATCH($AA44,'Classification Rules'!$B$43:$B$46,0)),"") -> Fully sourced, onshore-weighted | AK44: =IFERROR(INDEX('Classification Rules'!$K$43:$K$46,MATCH($AA44,'Classification Rules'!$B$43:$B$46,0)),"") -> 0
A45: 41 | B45: 9858 | C45: W02OPS-JPN | D45: Insurance Planning for Operator | E45: Marketing/Direct Business Related | F45: VS2: Customer Acquisition & Quotation | G45: Customer and Channel Engineering 34961 | I45: Core Business Application | J45: N | K45: Yes | L45: JAVA | M45: N | N45: No | P45: MetLife Owned Application Code | Q45: 4.8333333 | R45: 1 | S45: 1.0833333 | T45: 6.9166667 | U45: 0.71084337 | V45: 3.4583333 | W45: 3.4583333 | X45: =IF(OR(ISNUMBER(SEARCH("COBOL",$L45)),ISNUMBER(SEARCH("Assembler",$L45)),ISNUMBER(SEARCH("ASM",$L45)),ISNUMBER(SEARCH("RPG",$L45)),ISNUMBER(SEARCH("EASYPLUS",$L45)),ISNUMBER(SEARCH("PL/I",$L45))),"Rule 1",IF($M45="Y","Rule 2",IF($N45="Yes","Rule 3","Rule 4"))) -> Rule 4 | Y45: =IF($X45="Rule 1","D",IF($X45="Rule 2","C",IF($X45="Rule 3","B","A"))) -> A | AA45: =IF($Z45="",$Y45,$Z45) -> A | AB45: =IFERROR(INDEX('Classification Rules'!$C$43:$C$46,MATCH($AA45,'Classification Rules'!$B$43:$B$46,0)),"") -> Language-locked | AC45: =IF($X45="Rule 1","Language: "&$L45,IF($X45="Rule 2","Priority Transfer Target = Y",IF($X45="Rule 3","Cloud Indicator = Yes ("&$O45&")","Cloud Indicator = No, not mainframe, not a transfer target"))) -> Cloud Indicator = No, not mainframe, not a transfer target | AD45: =IFERROR(INDEX('Classification Rules'!$D$13:$D$16,MATCH($AA45,'Classification Rules'!$B$13:$B$16,0)),"") -> On-premises and non-mainframe, so the constraint is not the technology — it is that the business context exists only in Japanese, in few heads. | AE45: =IFERROR(INDEX('Classification Rules'!$D$43:$D$46,MATCH($AA45,'Classification Rules'!$B$43:$B$46,0)),"") -> 0.304 | AF45: =IFERROR(INDEX('Classification Rules'!$E$43:$E$46,MATCH($AA45,'Classification Rules'!$B$43:$B$46,0)),"") -> 0.3394768 | AG45: =IFERROR(INDEX('Classification Rules'!$F$43:$F$46,MATCH($AA45,'Classification Rules'!$B$43:$B$46,0)),"") -> 0.15 | AH45: =IFERROR(INDEX('Classification Rules'!$G$43:$G$46,MATCH($AA45,'Classification Rules'!$B$43:$B$46,0)),"") -> 0.1395 | AI45: =IFERROR(INDEX('Classification Rules'!$I$43:$I$46,MATCH($AA45,'Classification Rules'!$B$43:$B$46,0)),"") -> 10-14 weeks per cluster | AJ45: =IFERROR(INDEX('Classification Rules'!$J$43:$J$46,MATCH($AA45,'Classification Rules'!$B$43:$B$46,0)),"") -> Fully sourced, onshore-weighted | AK45: =IFERROR(INDEX('Classification Rules'!$K$43:$K$46,MATCH($AA45,'Classification Rules'!$B$43:$B$46,0)),"") -> 0
A46: 42 | B46: 9861 | C46: W04RRE-JPN | D46: Rule Engine | E46: New Contract Related | F46: VS2: Rules & Decisioning | G46: Customer Service and Operations Systems Group 34965 | H46: New Business Team 34966 | I46: Core Business Application | J46: Y | K46: Yes | L46: JAVA | M46: N | N46: No | P46: MetLife Owned Application Code | Q46: 6.3152917 | R46: 0 | S46: 0 | T46: 6.3152917 | U46: 0.87325737 | V46: 3.1576458 | W46: 3.1576458 | X46: =IF(OR(ISNUMBER(SEARCH("COBOL",$L46)),ISNUMBER(SEARCH("Assembler",$L46)),ISNUMBER(SEARCH("ASM",$L46)),ISNUMBER(SEARCH("RPG",$L46)),ISNUMBER(SEARCH("EASYPLUS",$L46)),ISNUMBER(SEARCH("PL/I",$L46))),"Rule 1",IF($M46="Y","Rule 2",IF($N46="Yes","Rule 3","Rule 4"))) -> Rule 4 | Y46: =IF($X46="Rule 1","D",IF($X46="Rule 2","C",IF($X46="Rule 3","B","A"))) -> A | AA46: =IF($Z46="",$Y46,$Z46) -> A | AB46: =IFERROR(INDEX('Classification Rules'!$C$43:$C$46,MATCH($AA46,'Classification Rules'!$B$43:$B$46,0)),"") -> Language-locked | AC46: =IF($X46="Rule 1","Language: "&$L46,IF($X46="Rule 2","Priority Transfer Target = Y",IF($X46="Rule 3","Cloud Indicator = Yes ("&$O46&")","Cloud Indicator = No, not mainframe, not a transfer target"))) -> Cloud Indicator = No, not mainframe, not a transfer target | AD46: =IFERROR(INDEX('Classification Rules'!$D$13:$D$16,MATCH($AA46,'Classification Rules'!$B$13:$B$16,0)),"") -> On-premises and non-mainframe, so the constraint is not the technology — it is that the business context exists only in Japanese, in few heads. | AE46: =IFERROR(INDEX('Classification Rules'!$D$43:$D$46,MATCH($AA46,'Classification Rules'!$B$43:$B$46,0)),"") -> 0.304 | AF46: =IFERROR(INDEX('Classification Rules'!$E$43:$E$46,MATCH($AA46,'Classification Rules'!$B$43:$B$46,0)),"") -> 0.3394768 | AG46: =IFERROR(INDEX('Classification Rules'!$F$43:$F$46,MATCH($AA46,'Classification Rules'!$B$43:$B$46,0)),"") -> 0.15 | AH46: =IFERROR(INDEX('Classification Rules'!$G$43:$G$46,MATCH($AA46,'Classification Rules'!$B$43:$B$46,0)),"") -> 0.1395 | AI46: =IFERROR(INDEX('Classification Rules'!$I$43:$I$46,MATCH($AA46,'Classification Rules'!$B$43:$B$46,0)),"") -> 10-14 weeks per cluster | AJ46: =IFERROR(INDEX('Classification Rules'!$J$43:$J$46,MATCH($AA46,'Classification Rules'!$B$43:$B$46,0)),"") -> Fully sourced, onshore-weighted | AK46: =IFERROR(INDEX('Classification Rules'!$K$43:$K$46,MATCH($AA46,'Classification Rules'!$B$43:$B$46,0)),"") -> 0
A47: 43 | B47: 9879 | C47: W03PIU-JPN | D47: IS universal life insurance simulation | E47: Storage and Preservation Related | F47: VS2: Digital Payments & Servicing | G47: Customer Service and Operations Systems Group 34965 | H47: Policy Servicing Team 34967 | I47: Core Business Application | J47: N | K47: Yes | L47: JAVA | M47: N | N47: No | P47: MetLife Owned Application Code | Q47: 0.2 | R47: 0.1 | S47: 0 | T47: 0.30833333 | U47: 0.67567568 | V47: 0.15416667 | W47: 0.15416667 | X47: =IF(OR(ISNUMBER(SEARCH("COBOL",$L47)),ISNUMBER(SEARCH("Assembler",$L47)),ISNUMBER(SEARCH("ASM",$L47)),ISNUMBER(SEARCH("RPG",$L47)),ISNUMBER(SEARCH("EASYPLUS",$L47)),ISNUMBER(SEARCH("PL/I",$L47))),"Rule 1",IF($M47="Y","Rule 2",IF($N47="Yes","Rule 3","Rule 4"))) -> Rule 4 | Y47: =IF($X47="Rule 1","D",IF($X47="Rule 2","C",IF($X47="Rule 3","B","A"))) -> A | AA47: =IF($Z47="",$Y47,$Z47) -> A | AB47: =IFERROR(INDEX('Classification Rules'!$C$43:$C$46,MATCH($AA47,'Classification Rules'!$B$43:$B$46,0)),"") -> Language-locked | AC47: =IF($X47="Rule 1","Language: "&$L47,IF($X47="Rule 2","Priority Transfer Target = Y",IF($X47="Rule 3","Cloud Indicator = Yes ("&$O47&")","Cloud Indicator = No, not mainframe, not a transfer target"))) -> Cloud Indicator = No, not mainframe, not a transfer target | AD47: =IFERROR(INDEX('Classification Rules'!$D$13:$D$16,MATCH($AA47,'Classification Rules'!$B$13:$B$16,0)),"") -> On-premises and non-mainframe, so the constraint is not the technology — it is that the business context exists only in Japanese, in few heads. | AE47: =IFERROR(INDEX('Classification Rules'!$D$43:$D$46,MATCH($AA47,'Classification Rules'!$B$43:$B$46,0)),"") -> 0.304 | AF47: =IFERROR(INDEX('Classification Rules'!$E$43:$E$46,MATCH($AA47,'Classification Rules'!$B$43:$B$46,0)),"") -> 0.3394768 | AG47: =IFERROR(INDEX('Classification Rules'!$F$43:$F$46,MATCH($AA47,'Classification Rules'!$B$43:$B$46,0)),"") -> 0.15 | AH47: =IFERROR(INDEX('Classification Rules'!$G$43:$G$46,MATCH($AA47,'Classification Rules'!$B$43:$B$46,0)),"") -> 0.1395 | AI47: =IFERROR(INDEX('Classification Rules'!$I$43:$I$46,MATCH($AA47,'Classification Rules'!$B$43:$B$46,0)),"") -> 10-14 weeks per cluster | AJ47: =IFERROR(INDEX('Classification Rules'!$J$43:$J$46,MATCH($AA47,'Classification Rules'!$B$43:$B$46,0)),"") -> Fully sourced, onshore-weighted | AK47: =IFERROR(INDEX('Classification Rules'!$K$43:$K$46,MATCH($AA47,'Classification Rules'!$B$43:$B$46,0)),"") -> 0
A48: 44 | B48: 9890 | C48: W08HTN-JPN | D48: conservation contact personnel entry system | E48: Corporate Related | F48: VS4: Corporate Workflow & Employee Services | G48: Core Insurance Systems Group 34956 | H48: Corporate Systems Team 34959 | I48: Core Business Application | J48: N | K48: Yes | L48: JAVA | M48: N | N48: No | P48: MetLife Owned Application Code | Q48: 1.5054583 | R48: 0.045833333 | S48: 0 | T48: 1.5512917 | U48: 0.072009884 | V48: 0.77564583 | W48: 0.77564583 | X48: =IF(OR(ISNUMBER(SEARCH("COBOL",$L48)),ISNUMBER(SEARCH("Assembler",$L48)),ISNUMBER(SEARCH("ASM",$L48)),ISNUMBER(SEARCH("RPG",$L48)),ISNUMBER(SEARCH("EASYPLUS",$L48)),ISNUMBER(SEARCH("PL/I",$L48))),"Rule 1",IF($M48="Y","Rule 2",IF($N48="Yes","Rule 3","Rule 4"))) -> Rule 4 | Y48: =IF($X48="Rule 1","D",IF($X48="Rule 2","C",IF($X48="Rule 3","B","A"))) -> A | AA48: =IF($Z48="",$Y48,$Z48) -> A | AB48: =IFERROR(INDEX('Classification Rules'!$C$43:$C$46,MATCH($AA48,'Classification Rules'!$B$43:$B$46,0)),"") -> Language-locked | AC48: =IF($X48="Rule 1","Language: "&$L48,IF($X48="Rule 2","Priority Transfer Target = Y",IF($X48="Rule 3","Cloud Indicator = Yes ("&$O48&")","Cloud Indicator = No, not mainframe, not a transfer target"))) -> Cloud Indicator = No, not mainframe, not a transfer target | AD48: =IFERROR(INDEX('Classification Rules'!$D$13:$D$16,MATCH($AA48,'Classification Rules'!$B$13:$B$16,0)),"") -> On-premises and non-mainframe, so the constraint is not the technology — it is that the business context exists only in Japanese, in few heads. | AE48: =IFERROR(INDEX('Classification Rules'!$D$43:$D$46,MATCH($AA48,'Classification Rules'!$B$43:$B$46,0)),"") -> 0.304 | AF48: =IFERROR(INDEX('Classification Rules'!$E$43:$E$46,MATCH($AA48,'Classification Rules'!$B$43:$B$46,0)),"") -> 0.3394768 | AG48: =IFERROR(INDEX('Classification Rules'!$F$43:$F$46,MATCH($AA48,'Classification Rules'!$B$43:$B$46,0)),"") -> 0.15 | AH48: =IFERROR(INDEX('Classification Rules'!$G$43:$G$46,MATCH($AA48,'Classification Rules'!$B$43:$B$46,0)),"") -> 0.1395 | AI48: =IFERROR(INDEX('Classification Rules'!$I$43:$I$46,MATCH($AA48,'Classification Rules'!$B$43:$B$46,0)),"") -> 10-14 weeks per cluster | AJ48: =IFERROR(INDEX('Classification Rules'!$J$43:$J$46,MATCH($AA48,'Classification Rules'!$B$43:$B$46,0)),"") -> Fully sourced, onshore-weighted | AK48: =IFERROR(INDEX('Classification Rules'!$K$43:$K$46,MATCH($AA48,'Classification Rules'!$B$43:$B$46,0)),"") -> 0
A49: 45 | B49: 9894 | C49: W08NAV-JPN | D49: Branch Marketing Information System | E49: Sales / Insurance Recruitment | F49: VS3: Agency & Producer Enablement | G49: Customer and Channel Engineering 34961 | H49: Distribution F2F Team 34962 | I49: Core Business Application | J49: N | K49: Yes | L49: VB | M49: N | N49: No | P49: MetLife Owned Application Code | Q49: 2.841875 | R49: 0.35208333 | S49: 0 | T49: 3.1939583 | U49: 0.79192486 | V49: 1.5969792 | W49: 1.5969792 | X49: =IF(OR(ISNUMBER(SEARCH("COBOL",$L49)),ISNUMBER(SEARCH("Assembler",$L49)),ISNUMBER(SEARCH("ASM",$L49)),ISNUMBER(SEARCH("RPG",$L49)),ISNUMBER(SEARCH("EASYPLUS",$L49)),ISNUMBER(SEARCH("PL/I",$L49))),"Rule 1",IF($M49="Y","Rule 2",IF($N49="Yes","Rule 3","Rule 4"))) -> Rule 4 | Y49: =IF($X49="Rule 1","D",IF($X49="Rule 2","C",IF($X49="Rule 3","B","A"))) -> A | AA49: =IF($Z49="",$Y49,$Z49) -> A | AB49: =IFERROR(INDEX('Classification Rules'!$C$43:$C$46,MATCH($AA49,'Classification Rules'!$B$43:$B$46,0)),"") -> Language-locked | AC49: =IF($X49="Rule 1","Language: "&$L49,IF($X49="Rule 2","Priority Transfer Target = Y",IF($X49="Rule 3","Cloud Indicator = Yes ("&$O49&")","Cloud Indicator = No, not mainframe, not a transfer target"))) -> Cloud Indicator = No, not mainframe, not a transfer target | AD49: =IFERROR(INDEX('Classification Rules'!$D$13:$D$16,MATCH($AA49,'Classification Rules'!$B$13:$B$16,0)),"") -> On-premises and non-mainframe, so the constraint is not the technology — it is that the business context exists only in Japanese, in few heads. | AE49: =IFERROR(INDEX('Classification Rules'!$D$43:$D$46,MATCH($AA49,'Classification Rules'!$B$43:$B$46,0)),"") -> 0.304 | AF49: =IFERROR(INDEX('Classification Rules'!$E$43:$E$46,MATCH($AA49,'Classification Rules'!$B$43:$B$46,0)),"") -> 0.3394768 | AG49: =IFERROR(INDEX('Classification Rules'!$F$43:$F$46,MATCH($AA49,'Classification Rules'!$B$43:$B$46,0)),"") -> 0.15 | AH49: =IFERROR(INDEX('Classification Rules'!$G$43:$G$46,MATCH($AA49,'Classification Rules'!$B$43:$B$46,0)),"") -> 0.1395 | AI49: =IFERROR(INDEX('Classification Rules'!$I$43:$I$46,MATCH($AA49,'Classification Rules'!$B$43:$B$46,0)),"") -> 10-14 weeks per cluster | AJ49: =IFERROR(INDEX('Classification Rules'!$J$43:$J$46,MATCH($AA49,'Classification Rules'!$B$43:$B$46,0)),"") -> Fully sourced, onshore-weighted | AK49: =IFERROR(INDEX('Classification Rules'!$K$43:$K$46,MATCH($AA49,'Classification Rules'!$B$43:$B$46,0)),"") -> 0
A50: 46 | B50: 9896 | C50: W08SFE-JPN | D50: commission Inquiry | E50: Corporate Related | F50: VS4: Corporate Workflow & Employee Services | G50: Core Insurance Systems Group 34956 | H50: Corporate Systems Team 34959 | I50: Core Business Application | J50: N | K50: Yes | L50: JAVA | M50: N | N50: No | P50: MetLife Owned Application Code | Q50: 1.091375 | R50: 0.105 | S50: 0 | T50: 1.196375 | U50: 0.98955177 | V50: 0.5981875 | W50: 0.5981875 | X50: =IF(OR(ISNUMBER(SEARCH("COBOL",$L50)),ISNUMBER(SEARCH("Assembler",$L50)),ISNUMBER(SEARCH("ASM",$L50)),ISNUMBER(SEARCH("RPG",$L50)),ISNUMBER(SEARCH("EASYPLUS",$L50)),ISNUMBER(SEARCH("PL/I",$L50))),"Rule 1",IF($M50="Y","Rule 2",IF($N50="Yes","Rule 3","Rule 4"))) -> Rule 4 | Y50: =IF($X50="Rule 1","D",IF($X50="Rule 2","C",IF($X50="Rule 3","B","A"))) -> A | AA50: =IF($Z50="",$Y50,$Z50) -> A | AB50: =IFERROR(INDEX('Classification Rules'!$C$43:$C$46,MATCH($AA50,'Classification Rules'!$B$43:$B$46,0)),"") -> Language-locked | AC50: =IF($X50="Rule 1","Language: "&$L50,IF($X50="Rule 2","Priority Transfer Target = Y",IF($X50="Rule 3","Cloud Indicator = Yes ("&$O50&")","Cloud Indicator = No, not mainframe, not a transfer target"))) -> Cloud Indicator = No, not mainframe, not a transfer target | AD50: =IFERROR(INDEX('Classification Rules'!$D$13:$D$16,MATCH($AA50,'Classification Rules'!$B$13:$B$16,0)),"") -> On-premises and non-mainframe, so the constraint is not the technology — it is that the business context exists only in Japanese, in few heads. | AE50: =IFERROR(INDEX('Classification Rules'!$D$43:$D$46,MATCH($AA50,'Classification Rules'!$B$43:$B$46,0)),"") -> 0.304 | AF50: =IFERROR(INDEX('Classification Rules'!$E$43:$E$46,MATCH($AA50,'Classification Rules'!$B$43:$B$46,0)),"") -> 0.3394768 | AG50: =IFERROR(INDEX('Classification Rules'!$F$43:$F$46,MATCH($AA50,'Classification Rules'!$B$43:$B$46,0)),"") -> 0.15 | AH50: =IFERROR(INDEX('Classification Rules'!$G$43:$G$46,MATCH($AA50,'Classification Rules'!$B$43:$B$46,0)),"") -> 0.1395 | AI50: =IFERROR(INDEX('Classification Rules'!$I$43:$I$46,MATCH($AA50,'Classification Rules'!$B$43:$B$46,0)),"") -> 10-14 weeks per cluster | AJ50: =IFERROR(INDEX('Classification Rules'!$J$43:$J$46,MATCH($AA50,'Classification Rules'!$B$43:$B$46,0)),"") -> Fully sourced, onshore-weighted | AK50: =IFERROR(INDEX('Classification Rules'!$K$43:$K$46,MATCH($AA50,'Classification Rules'!$B$43:$B$46,0)),"") -> 0
A51: 47 | B51: 9899 | C51: W08CIS-JPN | D51: Career Information System | E51: Corporate Related | F51: VS4: Corporate Workflow & Employee Services | G51: Core Insurance Systems Group 34956 | H51: Corporate Systems Team 34959 | I51: Core Business Application | J51: N | K51: Yes | L51: JAVA | M51: N | N51: No | P51: MetLife Owned Application Code | Q51: 1.204125 | R51: 0.52916667 | S51: 0 | T51: 1.7332917 | U51: 0.82691892 | V51: 0.86664583 | W51: 0.86664583 | X51: =IF(OR(ISNUMBER(SEARCH("COBOL",$L51)),ISNUMBER(SEARCH("Assembler",$L51)),ISNUMBER(SEARCH("ASM",$L51)),ISNUMBER(SEARCH("RPG",$L51)),ISNUMBER(SEARCH("EASYPLUS",$L51)),ISNUMBER(SEARCH("PL/I",$L51))),"Rule 1",IF($M51="Y","Rule 2",IF($N51="Yes","Rule 3","Rule 4"))) -> Rule 4 | Y51: =IF($X51="Rule 1","D",IF($X51="Rule 2","C",IF($X51="Rule 3","B","A"))) -> A | AA51: =IF($Z51="",$Y51,$Z51) -> A | AB51: =IFERROR(INDEX('Classification Rules'!$C$43:$C$46,MATCH($AA51,'Classification Rules'!$B$43:$B$46,0)),"") -> Language-locked | AC51: =IF($X51="Rule 1","Language: "&$L51,IF($X51="Rule 2","Priority Transfer Target = Y",IF($X51="Rule 3","Cloud Indicator = Yes ("&$O51&")","Cloud Indicator = No, not mainframe, not a transfer target"))) -> Cloud Indicator = No, not mainframe, not a transfer target | AD51: =IFERROR(INDEX('Classification Rules'!$D$13:$D$16,MATCH($AA51,'Classification Rules'!$B$13:$B$16,0)),"") -> On-premises and non-mainframe, so the constraint is not the technology — it is that the business context exists only in Japanese, in few heads. | AE51: =IFERROR(INDEX('Classification Rules'!$D$43:$D$46,MATCH($AA51,'Classification Rules'!$B$43:$B$46,0)),"") -> 0.304 | AF51: =IFERROR(INDEX('Classification Rules'!$E$43:$E$46,MATCH($AA51,'Classification Rules'!$B$43:$B$46,0)),"") -> 0.3394768 | AG51: =IFERROR(INDEX('Classification Rules'!$F$43:$F$46,MATCH($AA51,'Classification Rules'!$B$43:$B$46,0)),"") -> 0.15 | AH51: =IFERROR(INDEX('Classification Rules'!$G$43:$G$46,MATCH($AA51,'Classification Rules'!$B$43:$B$46,0)),"") -> 0.1395 | AI51: =IFERROR(INDEX('Classification Rules'!$I$43:$I$46,MATCH($AA51,'Classification Rules'!$B$43:$B$46,0)),"") -> 10-14 weeks per cluster | AJ51: =IFERROR(INDEX('Classification Rules'!$J$43:$J$46,MATCH($AA51,'Classification Rules'!$B$43:$B$46,0)),"") -> Fully sourced, onshore-weighted | AK51: =IFERROR(INDEX('Classification Rules'!$K$43:$K$46,MATCH($AA51,'Classification Rules'!$B$43:$B$46,0)),"") -> 0
A52: 48 | B52: 9906 | C52: W08NAR-JPN | D52: producers information entry system | E52: Corporate Related | F52: VS4: Corporate Workflow & Employee Services | G52: Core Insurance Systems Group 34956 | H52: Corporate Systems Team 34959 | I52: Core Business Application | J52: N | K52: Yes | L52: JAVA | M52: N | N52: No | P52: MetLife Owned Application Code | Q52: 1.2860417 | R52: 0.14541667 | S52: 0 | T52: 1.4314583 | U52: 0.95051666 | V52: 0.71572917 | W52: 0.71572917 | X52: =IF(OR(ISNUMBER(SEARCH("COBOL",$L52)),ISNUMBER(SEARCH("Assembler",$L52)),ISNUMBER(SEARCH("ASM",$L52)),ISNUMBER(SEARCH("RPG",$L52)),ISNUMBER(SEARCH("EASYPLUS",$L52)),ISNUMBER(SEARCH("PL/I",$L52))),"Rule 1",IF($M52="Y","Rule 2",IF($N52="Yes","Rule 3","Rule 4"))) -> Rule 4 | Y52: =IF($X52="Rule 1","D",IF($X52="Rule 2","C",IF($X52="Rule 3","B","A"))) -> A | AA52: =IF($Z52="",$Y52,$Z52) -> A | AB52: =IFERROR(INDEX('Classification Rules'!$C$43:$C$46,MATCH($AA52,'Classification Rules'!$B$43:$B$46,0)),"") -> Language-locked | AC52: =IF($X52="Rule 1","Language: "&$L52,IF($X52="Rule 2","Priority Transfer Target = Y",IF($X52="Rule 3","Cloud Indicator = Yes ("&$O52&")","Cloud Indicator = No, not mainframe, not a transfer target"))) -> Cloud Indicator = No, not mainframe, not a transfer target | AD52: =IFERROR(INDEX('Classification Rules'!$D$13:$D$16,MATCH($AA52,'Classification Rules'!$B$13:$B$16,0)),"") -> On-premises and non-mainframe, so the constraint is not the technology — it is that the business context exists only in Japanese, in few heads. | AE52: =IFERROR(INDEX('Classification Rules'!$D$43:$D$46,MATCH($AA52,'Classification Rules'!$B$43:$B$46,0)),"") -> 0.304 | AF52: =IFERROR(INDEX('Classification Rules'!$E$43:$E$46,MATCH($AA52,'Classification Rules'!$B$43:$B$46,0)),"") -> 0.3394768 | AG52: =IFERROR(INDEX('Classification Rules'!$F$43:$F$46,MATCH($AA52,'Classification Rules'!$B$43:$B$46,0)),"") -> 0.15 | AH52: =IFERROR(INDEX('Classification Rules'!$G$43:$G$46,MATCH($AA52,'Classification Rules'!$B$43:$B$46,0)),"") -> 0.1395 | AI52: =IFERROR(INDEX('Classification Rules'!$I$43:$I$46,MATCH($AA52,'Classification Rules'!$B$43:$B$46,0)),"") -> 10-14 weeks per cluster | AJ52: =IFERROR(INDEX('Classification Rules'!$J$43:$J$46,MATCH($AA52,'Classification Rules'!$B$43:$B$46,0)),"") -> Fully sourced, onshore-weighted | AK52: =IFERROR(INDEX('Classification Rules'!$K$43:$K$46,MATCH($AA52,'Classification Rules'!$B$43:$B$46,0)),"") -> 0
A53: 49 | B53: 9907 | C53: W13WWF-JPN | D53: Web work flow | E53: Corporate Related | F53: VS4: Corporate Workflow & Employee Services | G53: Core Insurance Systems Group 34956 | H53: Corporate Systems Team 34959 | I53: Core Business Application | J53: N | K53: Yes | L53: JAVA | M53: N | N53: No | P53: MetLife Owned Application Code | Q53: 0.38583333 | R53: 0 | S53: 0 | T53: 0.38583333 | U53: 0.35205184 | V53: 0.19291667 | W53: 0.19291667 | X53: =IF(OR(ISNUMBER(SEARCH("COBOL",$L53)),ISNUMBER(SEARCH("Assembler",$L53)),ISNUMBER(SEARCH("ASM",$L53)),ISNUMBER(SEARCH("RPG",$L53)),ISNUMBER(SEARCH("EASYPLUS",$L53)),ISNUMBER(SEARCH("PL/I",$L53))),"Rule 1",IF($M53="Y","Rule 2",IF($N53="Yes","Rule 3","Rule 4"))) -> Rule 4 | Y53: =IF($X53="Rule 1","D",IF($X53="Rule 2","C",IF($X53="Rule 3","B","A"))) -> A | AA53: =IF($Z53="",$Y53,$Z53) -> A | AB53: =IFERROR(INDEX('Classification Rules'!$C$43:$C$46,MATCH($AA53,'Classification Rules'!$B$43:$B$46,0)),"") -> Language-locked | AC53: =IF($X53="Rule 1","Language: "&$L53,IF($X53="Rule 2","Priority Transfer Target = Y",IF($X53="Rule 3","Cloud Indicator = Yes ("&$O53&")","Cloud Indicator = No, not mainframe, not a transfer target"))) -> Cloud Indicator = No, not mainframe, not a transfer target | AD53: =IFERROR(INDEX('Classification Rules'!$D$13:$D$16,MATCH($AA53,'Classification Rules'!$B$13:$B$16,0)),"") -> On-premises and non-mainframe, so the constraint is not the technology — it is that the business context exists only in Japanese, in few heads. | AE53: =IFERROR(INDEX('Classification Rules'!$D$43:$D$46,MATCH($AA53,'Classification Rules'!$B$43:$B$46,0)),"") -> 0.304 | AF53: =IFERROR(INDEX('Classification Rules'!$E$43:$E$46,MATCH($AA53,'Classification Rules'!$B$43:$B$46,0)),"") -> 0.3394768 | AG53: =IFERROR(INDEX('Classification Rules'!$F$43:$F$46,MATCH($AA53,'Classification Rules'!$B$43:$B$46,0)),"") -> 0.15 | AH53: =IFERROR(INDEX('Classification Rules'!$G$43:$G$46,MATCH($AA53,'Classification Rules'!$B$43:$B$46,0)),"") -> 0.1395 | AI53: =IFERROR(INDEX('Classification Rules'!$I$43:$I$46,MATCH($AA53,'Classification Rules'!$B$43:$B$46,0)),"") -> 10-14 weeks per cluster | AJ53: =IFERROR(INDEX('Classification Rules'!$J$43:$J$46,MATCH($AA53,'Classification Rules'!$B$43:$B$46,0)),"") -> Fully sourced, onshore-weighted | AK53: =IFERROR(INDEX('Classification Rules'!$K$43:$K$46,MATCH($AA53,'Classification Rules'!$B$43:$B$46,0)),"") -> 0
A54: 50 | B54: 9910 | C54: P08MMS-JPN | D54: Medical Management System | E54: New Contract Related | F54: VS3: Medical Underwriting | G54: Customer Service and Operations Systems Group 34965 | H54: New Business Team 34966 | I54: Core Business Application | J54: N | K54: Yes | L54: VB.NET | M54: N | N54: No | P54: MetLife Owned Application Code | Q54: 0.0625 | R54: 0 | S54: 0 | T54: 0.0625 | U54: 1 | V54: 0.03125 | W54: 0.03125 | X54: =IF(OR(ISNUMBER(SEARCH("COBOL",$L54)),ISNUMBER(SEARCH("Assembler",$L54)),ISNUMBER(SEARCH("ASM",$L54)),ISNUMBER(SEARCH("RPG",$L54)),ISNUMBER(SEARCH("EASYPLUS",$L54)),ISNUMBER(SEARCH("PL/I",$L54))),"Rule 1",IF($M54="Y","Rule 2",IF($N54="Yes","Rule 3","Rule 4"))) -> Rule 4 | Y54: =IF($X54="Rule 1","D",IF($X54="Rule 2","C",IF($X54="Rule 3","B","A"))) -> A | AA54: =IF($Z54="",$Y54,$Z54) -> A | AB54: =IFERROR(INDEX('Classification Rules'!$C$43:$C$46,MATCH($AA54,'Classification Rules'!$B$43:$B$46,0)),"") -> Language-locked | AC54: =IF($X54="Rule 1","Language: "&$L54,IF($X54="Rule 2","Priority Transfer Target = Y",IF($X54="Rule 3","Cloud Indicator = Yes ("&$O54&")","Cloud Indicator = No, not mainframe, not a transfer target"))) -> Cloud Indicator = No, not mainframe, not a transfer target | AD54: =IFERROR(INDEX('Classification Rules'!$D$13:$D$16,MATCH($AA54,'Classification Rules'!$B$13:$B$16,0)),"") -> On-premises and non-mainframe, so the constraint is not the technology — it is that the business context exists only in Japanese, in few heads. | AE54: =IFERROR(INDEX('Classification Rules'!$D$43:$D$46,MATCH($AA54,'Classification Rules'!$B$43:$B$46,0)),"") -> 0.304 | AF54: =IFERROR(INDEX('Classification Rules'!$E$43:$E$46,MATCH($AA54,'Classification Rules'!$B$43:$B$46,0)),"") -> 0.3394768 | AG54: =IFERROR(INDEX('Classification Rules'!$F$43:$F$46,MATCH($AA54,'Classification Rules'!$B$43:$B$46,0)),"") -> 0.15 | AH54: =IFERROR(INDEX('Classification Rules'!$G$43:$G$46,MATCH($AA54,'Classification Rules'!$B$43:$B$46,0)),"") -> 0.1395 | AI54: =IFERROR(INDEX('Classification Rules'!$I$43:$I$46,MATCH($AA54,'Classification Rules'!$B$43:$B$46,0)),"") -> 10-14 weeks per cluster | AJ54: =IFERROR(INDEX('Classification Rules'!$J$43:$J$46,MATCH($AA54,'Classification Rules'!$B$43:$B$46,0)),"") -> Fully sourced, onshore-weighted | AK54: =IFERROR(INDEX('Classification Rules'!$K$43:$K$46,MATCH($AA54,'Classification Rules'!$B$43:$B$46,0)),"") -> 0
A55: 51 | B55: 9920 | C55: WPSYEC-JPN | D55: Direct Marketing Site | E55: Marketing/Direct Business Related | F55: VS1: Digital Marketing & Lead Management | G55: Customer and Channel Engineering 34961 | H55: Marketing and Leads Team 34964 | I55: Core Business Application | J55: N | K55: Yes | L55: JAVA | M55: N | N55: No | P55: MetLife Owned Application Code | Q55: 10.3375 | R55: 3.5583333 | S55: 5.1816667 | T55: 19.0775 | U55: 0.93360416 | V55: 9.53875 | W55: 9.53875 | X55: =IF(OR(ISNUMBER(SEARCH("COBOL",$L55)),ISNUMBER(SEARCH("Assembler",$L55)),ISNUMBER(SEARCH("ASM",$L55)),ISNUMBER(SEARCH("RPG",$L55)),ISNUMBER(SEARCH("EASYPLUS",$L55)),ISNUMBER(SEARCH("PL/I",$L55))),"Rule 1",IF($M55="Y","Rule 2",IF($N55="Yes","Rule 3","Rule 4"))) -> Rule 4 | Y55: =IF($X55="Rule 1","D",IF($X55="Rule 2","C",IF($X55="Rule 3","B","A"))) -> A | AA55: =IF($Z55="",$Y55,$Z55) -> A | AB55: =IFERROR(INDEX('Classification Rules'!$C$43:$C$46,MATCH($AA55,'Classification Rules'!$B$43:$B$46,0)),"") -> Language-locked | AC55: =IF($X55="Rule 1","Language: "&$L55,IF($X55="Rule 2","Priority Transfer Target = Y",IF($X55="Rule 3","Cloud Indicator = Yes ("&$O55&")","Cloud Indicator = No, not mainframe, not a transfer target"))) -> Cloud Indicator = No, not mainframe, not a transfer target | AD55: =IFERROR(INDEX('Classification Rules'!$D$13:$D$16,MATCH($AA55,'Classification Rules'!$B$13:$B$16,0)),"") -> On-premises and non-mainframe, so the constraint is not the technology — it is that the business context exists only in Japanese, in few heads. | AE55: =IFERROR(INDEX('Classification Rules'!$D$43:$D$46,MATCH($AA55,'Classification Rules'!$B$43:$B$46,0)),"") -> 0.304 | AF55: =IFERROR(INDEX('Classification Rules'!$E$43:$E$46,MATCH($AA55,'Classification Rules'!$B$43:$B$46,0)),"") -> 0.3394768 | AG55: =IFERROR(INDEX('Classification Rules'!$F$43:$F$46,MATCH($AA55,'Classification Rules'!$B$43:$B$46,0)),"") -> 0.15 | AH55: =IFERROR(INDEX('Classification Rules'!$G$43:$G$46,MATCH($AA55,'Classification Rules'!$B$43:$B$46,0)),"") -> 0.1395 | AI55: =IFERROR(INDEX('Classification Rules'!$I$43:$I$46,MATCH($AA55,'Classification Rules'!$B$43:$B$46,0)),"") -> 10-14 weeks per cluster | AJ55: =IFERROR(INDEX('Classification Rules'!$J$43:$J$46,MATCH($AA55,'Classification Rules'!$B$43:$B$46,0)),"") -> Fully sourced, onshore-weighted | AK55: =IFERROR(INDEX('Classification Rules'!$K$43:$K$46,MATCH($AA55,'Classification Rules'!$B$43:$B$46,0)),"") -> 0
A56: 52 | B56: 9921 | C56: W07IPC-JPN | D56: Internet Prospective Information | E56: Marketing/Direct Business Related | F56: VS1: Digital Marketing & Lead Management | G56: Customer and Channel Engineering 34961 | H56: Marketing and Leads Team 34964 | I56: Core Business Application | J56: N | K56: Yes | L56: JAVA | M56: N | N56: Yes | O56: Platform as a Service (PaaS) | P56: MetLife Owned Application Code | Q56: 0.30416667 | R56: 0.041666667 | S56: 0 | T56: 0.34583333 | U56: 1 | V56: 0.17291667 | W56: 0.17291667 | X56: =IF(OR(ISNUMBER(SEARCH("COBOL",$L56)),ISNUMBER(SEARCH("Assembler",$L56)),ISNUMBER(SEARCH("ASM",$L56)),ISNUMBER(SEARCH("RPG",$L56)),ISNUMBER(SEARCH("EASYPLUS",$L56)),ISNUMBER(SEARCH("PL/I",$L56))),"Rule 1",IF($M56="Y","Rule 2",IF($N56="Yes","Rule 3","Rule 4"))) -> Rule 3 | Y56: =IF($X56="Rule 1","D",IF($X56="Rule 2","C",IF($X56="Rule 3","B","A"))) -> B | AA56: =IF($Z56="",$Y56,$Z56) -> B | AB56: =IFERROR(INDEX('Classification Rules'!$C$43:$C$46,MATCH($AA56,'Classification Rules'!$B$43:$B$46,0)),"") -> Offshore-ready | AC56: =IF($X56="Rule 1","Language: "&$L56,IF($X56="Rule 2","Priority Transfer Target = Y",IF($X56="Rule 3","Cloud Indicator = Yes ("&$O56&")","Cloud Indicator = No, not mainframe, not a transfer target"))) -> Cloud Indicator = Yes (Platform as a Service (PaaS)) | AD56: =IFERROR(INDEX('Classification Rules'!$D$13:$D$16,MATCH($AA56,'Classification Rules'!$B$13:$B$16,0)),"") -> Cloud migration has already forced re-platforming, documentation and specifiability. Highest AI and offshore ceiling in the estate. | AE56: =IFERROR(INDEX('Classification Rules'!$D$43:$D$46,MATCH($AA56,'Classification Rules'!$B$43:$B$46,0)),"") -> 0.4825 | AF56: =IFERROR(INDEX('Classification Rules'!$E$43:$E$46,MATCH($AA56,'Classification Rules'!$B$43:$B$46,0)),"") -> 0.45402025 | AG56: =IFERROR(INDEX('Classification Rules'!$F$43:$F$46,MATCH($AA56,'Classification Rules'!$B$43:$B$46,0)),"") -> 0.78 | AH56: =IFERROR(INDEX('Classification Rules'!$G$43:$G$46,MATCH($AA56,'Classification Rules'!$B$43:$B$46,0)),"") -> 0.7254 | AI56: =IFERROR(INDEX('Classification Rules'!$I$43:$I$46,MATCH($AA56,'Classification Rules'!$B$43:$B$46,0)),"") -> 6-8 weeks per cluster | AJ56: =IFERROR(INDEX('Classification Rules'!$J$43:$J$46,MATCH($AA56,'Classification Rules'!$B$43:$B$46,0)),"") -> Fully sourced, moving to output units | AK56: =IFERROR(INDEX('Classification Rules'!$K$43:$K$46,MATCH($AA56,'Classification Rules'!$B$43:$B$46,0)),"") -> 0
A57: 53 | B57: 9926 | C57: W01LOI-JPN | D57: Japan Authorization / login | E57: Common Service Platform | F57: VS1: Identity & Access Services | G57: Japan Platform Team 35775 | H57: Japan Platform Team 35775 | I57: Common Service Business Application | J57: N | K57: Yes | L57: JAVA | M57: N | N57: No | P57: MetLife Owned Application Code | Q57: 0.075 | R57: 0 | S57: 0 | T57: 0.075 | U57: 0 | V57: 0.0375 | W57: 0.0375 | X57: =IF(OR(ISNUMBER(SEARCH("COBOL",$L57)),ISNUMBER(SEARCH("Assembler",$L57)),ISNUMBER(SEARCH("ASM",$L57)),ISNUMBER(SEARCH("RPG",$L57)),ISNUMBER(SEARCH("EASYPLUS",$L57)),ISNUMBER(SEARCH("PL/I",$L57))),"Rule 1",IF($M57="Y","Rule 2",IF($N57="Yes","Rule 3","Rule 4"))) -> Rule 4 | Y57: =IF($X57="Rule 1","D",IF($X57="Rule 2","C",IF($X57="Rule 3","B","A"))) -> A | AA57: =IF($Z57="",$Y57,$Z57) -> A | AB57: =IFERROR(INDEX('Classification Rules'!$C$43:$C$46,MATCH($AA57,'Classification Rules'!$B$43:$B$46,0)),"") -> Language-locked | AC57: =IF($X57="Rule 1","Language: "&$L57,IF($X57="Rule 2","Priority Transfer Target = Y",IF($X57="Rule 3","Cloud Indicator = Yes ("&$O57&")","Cloud Indicator = No, not mainframe, not a transfer target"))) -> Cloud Indicator = No, not mainframe, not a transfer target | AD57: =IFERROR(INDEX('Classification Rules'!$D$13:$D$16,MATCH($AA57,'Classification Rules'!$B$13:$B$16,0)),"") -> On-premises and non-mainframe, so the constraint is not the technology — it is that the business context exists only in Japanese, in few heads. | AE57: =IFERROR(INDEX('Classification Rules'!$D$43:$D$46,MATCH($AA57,'Classification Rules'!$B$43:$B$46,0)),"") -> 0.304 | AF57: =IFERROR(INDEX('Classification Rules'!$E$43:$E$46,MATCH($AA57,'Classification Rules'!$B$43:$B$46,0)),"") -> 0.3394768 | AG57: =IFERROR(INDEX('Classification Rules'!$F$43:$F$46,MATCH($AA57,'Classification Rules'!$B$43:$B$46,0)),"") -> 0.15 | AH57: =IFERROR(INDEX('Classification Rules'!$G$43:$G$46,MATCH($AA57,'Classification Rules'!$B$43:$B$46,0)),"") -> 0.1395 | AI57: =IFERROR(INDEX('Classification Rules'!$I$43:$I$46,MATCH($AA57,'Classification Rules'!$B$43:$B$46,0)),"") -> 10-14 weeks per cluster | AJ57: =IFERROR(INDEX('Classification Rules'!$J$43:$J$46,MATCH($AA57,'Classification Rules'!$B$43:$B$46,0)),"") -> Fully sourced, onshore-weighted | AK57: =IFERROR(INDEX('Classification Rules'!$K$43:$K$46,MATCH($AA57,'Classification Rules'!$B$43:$B$46,0)),"") -> 0
A58: 54 | B58: 9928 | C58: W01MAS-JPN | D58: Common Framework(Master4) | E58: Common Service Platform | F58: VS2: Portal Services | G58: Japan Platform Team 35775 | H58: Japan Platform Team 35775 | I58: Common Service Business Application | J58: N | K58: Yes | L58: JAVA | M58: N | N58: Yes | O58: Platform as a Service (PaaS) | P58: MetLife Owned Application Code | Q58: 1.3970833 | R58: 1 | S58: 0 | T58: 2.3970833 | U58: 0.86441856 | V58: 1.1985417 | W58: 1.1985417 | X58: =IF(OR(ISNUMBER(SEARCH("COBOL",$L58)),ISNUMBER(SEARCH("Assembler",$L58)),ISNUMBER(SEARCH("ASM",$L58)),ISNUMBER(SEARCH("RPG",$L58)),ISNUMBER(SEARCH("EASYPLUS",$L58)),ISNUMBER(SEARCH("PL/I",$L58))),"Rule 1",IF($M58="Y","Rule 2",IF($N58="Yes","Rule 3","Rule 4"))) -> Rule 3 | Y58: =IF($X58="Rule 1","D",IF($X58="Rule 2","C",IF($X58="Rule 3","B","A"))) -> B | AA58: =IF($Z58="",$Y58,$Z58) -> B | AB58: =IFERROR(INDEX('Classification Rules'!$C$43:$C$46,MATCH($AA58,'Classification Rules'!$B$43:$B$46,0)),"") -> Offshore-ready | AC58: =IF($X58="Rule 1","Language: "&$L58,IF($X58="Rule 2","Priority Transfer Target = Y",IF($X58="Rule 3","Cloud Indicator = Yes ("&$O58&")","Cloud Indicator = No, not mainframe, not a transfer target"))) -> Cloud Indicator = Yes (Platform as a Service (PaaS)) | AD58: =IFERROR(INDEX('Classification Rules'!$D$13:$D$16,MATCH($AA58,'Classification Rules'!$B$13:$B$16,0)),"") -> Cloud migration has already forced re-platforming, documentation and specifiability. Highest AI and offshore ceiling in the estate. | AE58: =IFERROR(INDEX('Classification Rules'!$D$43:$D$46,MATCH($AA58,'Classification Rules'!$B$43:$B$46,0)),"") -> 0.4825 | AF58: =IFERROR(INDEX('Classification Rules'!$E$43:$E$46,MATCH($AA58,'Classification Rules'!$B$43:$B$46,0)),"") -> 0.45402025 | AG58: =IFERROR(INDEX('Classification Rules'!$F$43:$F$46,MATCH($AA58,'Classification Rules'!$B$43:$B$46,0)),"") -> 0.78 | AH58: =IFERROR(INDEX('Classification Rules'!$G$43:$G$46,MATCH($AA58,'Classification Rules'!$B$43:$B$46,0)),"") -> 0.7254 | AI58: =IFERROR(INDEX('Classification Rules'!$I$43:$I$46,MATCH($AA58,'Classification Rules'!$B$43:$B$46,0)),"") -> 6-8 weeks per cluster | AJ58: =IFERROR(INDEX('Classification Rules'!$J$43:$J$46,MATCH($AA58,'Classification Rules'!$B$43:$B$46,0)),"") -> Fully sourced, moving to output units | AK58: =IFERROR(INDEX('Classification Rules'!$K$43:$K$46,MATCH($AA58,'Classification Rules'!$B$43:$B$46,0)),"") -> 0
A59: 55 | B59: 9930 | C59: A04MMP-JPN | D59: AS400 Mass Marketing System | E59: Corporate Related | F59: VS6: Legacy Corporate Platforms | G59: Core Insurance Systems Group 34956 | H59: Corporate Systems Team 34959 | I59: Core Business Application | J59: Y | K59: Yes | L59: Other#RPG | M59: N | N59: No | P59: MetLife Owned Application Code | Q59: 2.4083333 | R59: 0.075 | S59: 0 | T59: 2.4833333 | U59: 0.89932886 | V59: 1.2416667 | W59: 1.2416667 | X59: =IF(OR(ISNUMBER(SEARCH("COBOL",$L59)),ISNUMBER(SEARCH("Assembler",$L59)),ISNUMBER(SEARCH("ASM",$L59)),ISNUMBER(SEARCH("RPG",$L59)),ISNUMBER(SEARCH("EASYPLUS",$L59)),ISNUMBER(SEARCH("PL/I",$L59))),"Rule 1",IF($M59="Y","Rule 2",IF($N59="Yes","Rule 3","Rule 4"))) -> Rule 1 | Y59: =IF($X59="Rule 1","D",IF($X59="Rule 2","C",IF($X59="Rule 3","B","A"))) -> D | AA59: =IF($Z59="",$Y59,$Z59) -> D | AB59: =IFERROR(INDEX('Classification Rules'!$C$43:$C$46,MATCH($AA59,'Classification Rules'!$B$43:$B$46,0)),"") -> Legacy-coupled core | AC59: =IF($X59="Rule 1","Language: "&$L59,IF($X59="Rule 2","Priority Transfer Target = Y",IF($X59="Rule 3","Cloud Indicator = Yes ("&$O59&")","Cloud Indicator = No, not mainframe, not a transfer target"))) -> Language: Other#RPG | AD59: =IFERROR(INDEX('Classification Rules'!$D$13:$D$16,MATCH($AA59,'Classification Rules'!$B$13:$B$16,0)),"") -> Rules hard-coded across modules and design truth is not written down. AI does comprehension here, not generation. | AE59: =IFERROR(INDEX('Classification Rules'!$D$43:$D$46,MATCH($AA59,'Classification Rules'!$B$43:$B$46,0)),"") -> 0.295 | AF59: =IFERROR(INDEX('Classification Rules'!$E$43:$E$46,MATCH($AA59,'Classification Rules'!$B$43:$B$46,0)),"") -> 0.3337015 | AG59: =IFERROR(INDEX('Classification Rules'!$F$43:$F$46,MATCH($AA59,'Classification Rules'!$B$43:$B$46,0)),"") -> 0.58 | AH59: =IFERROR(INDEX('Classification Rules'!$G$43:$G$46,MATCH($AA59,'Classification Rules'!$B$43:$B$46,0)),"") -> 0.5394 | AI59: =IFERROR(INDEX('Classification Rules'!$I$43:$I$46,MATCH($AA59,'Classification Rules'!$B$43:$B$46,0)),"") -> 14-20 weeks per cluster | AJ59: =IFERROR(INDEX('Classification Rules'!$J$43:$J$46,MATCH($AA59,'Classification Rules'!$B$43:$B$46,0)),"") -> Fully sourced, MetLife SMEs paired | AK59: =IFERROR(INDEX('Classification Rules'!$K$43:$K$46,MATCH($AA59,'Classification Rules'!$B$43:$B$46,0)),"") -> 0
A60: 56 | B60: 9931 | C60: P02BKE-JPN | D60: Sales illustration system (based on EXCEL) for BAN | E60: Sales / Insurance Recruitment | F60: VS2: Bancassurance Platforms | G60: Customer and Channel Engineering 34961 | H60: Distribution Banca Team 34963 | I60: Core Business Application | J60: N | K60: Yes | L60: Other#VBA | M60: N | N60: No | P60: MetLife Owned Application Code | Q60: 13 | R60: 2.275 | S60: 0 | T60: 15.275 | U60: 0.91728849 | V60: 7.6375 | W60: 7.6375 | X60: =IF(OR(ISNUMBER(SEARCH("COBOL",$L60)),ISNUMBER(SEARCH("Assembler",$L60)),ISNUMBER(SEARCH("ASM",$L60)),ISNUMBER(SEARCH("RPG",$L60)),ISNUMBER(SEARCH("EASYPLUS",$L60)),ISNUMBER(SEARCH("PL/I",$L60))),"Rule 1",IF($M60="Y","Rule 2",IF($N60="Yes","Rule 3","Rule 4"))) -> Rule 4 | Y60: =IF($X60="Rule 1","D",IF($X60="Rule 2","C",IF($X60="Rule 3","B","A"))) -> A | AA60: =IF($Z60="",$Y60,$Z60) -> A | AB60: =IFERROR(INDEX('Classification Rules'!$C$43:$C$46,MATCH($AA60,'Classification Rules'!$B$43:$B$46,0)),"") -> Language-locked | AC60: =IF($X60="Rule 1","Language: "&$L60,IF($X60="Rule 2","Priority Transfer Target = Y",IF($X60="Rule 3","Cloud Indicator = Yes ("&$O60&")","Cloud Indicator = No, not mainframe, not a transfer target"))) -> Cloud Indicator = No, not mainframe, not a transfer target | AD60: =IFERROR(INDEX('Classification Rules'!$D$13:$D$16,MATCH($AA60,'Classification Rules'!$B$13:$B$16,0)),"") -> On-premises and non-mainframe, so the constraint is not the technology — it is that the business context exists only in Japanese, in few heads. | AE60: =IFERROR(INDEX('Classification Rules'!$D$43:$D$46,MATCH($AA60,'Classification Rules'!$B$43:$B$46,0)),"") -> 0.304 | AF60: =IFERROR(INDEX('Classification Rules'!$E$43:$E$46,MATCH($AA60,'Classification Rules'!$B$43:$B$46,0)),"") -> 0.3394768 | AG60: =IFERROR(INDEX('Classification Rules'!$F$43:$F$46,MATCH($AA60,'Classification Rules'!$B$43:$B$46,0)),"") -> 0.15 | AH60: =IFERROR(INDEX('Classification Rules'!$G$43:$G$46,MATCH($AA60,'Classification Rules'!$B$43:$B$46,0)),"") -> 0.1395 | AI60: =IFERROR(INDEX('Classification Rules'!$I$43:$I$46,MATCH($AA60,'Classification Rules'!$B$43:$B$46,0)),"") -> 10-14 weeks per cluster | AJ60: =IFERROR(INDEX('Classification Rules'!$J$43:$J$46,MATCH($AA60,'Classification Rules'!$B$43:$B$46,0)),"") -> Fully sourced, onshore-weighted | AK60: =IFERROR(INDEX('Classification Rules'!$K$43:$K$46,MATCH($AA60,'Classification Rules'!$B$43:$B$46,0)),"") -> 0
A61: 57 | B61: 9940 | C61: WPSC2S-JPN | D61: Call Control System | E61: Corporate Related | F61: VS4: Corporate Workflow & Employee Services | G61: Core Insurance Systems Group 34956 | H61: Corporate Systems Team 34959 | I61: Core Business Application | J61: N | K61: Yes | L61: JAVA | M61: N | N61: No | P61: MetLife Owned Application Code | Q61: 0.3875 | R61: 0.025 | S61: 0 | T61: 0.4125 | U61: 0.81818182 | V61: 0.20625 | W61: 0.20625 | X61: =IF(OR(ISNUMBER(SEARCH("COBOL",$L61)),ISNUMBER(SEARCH("Assembler",$L61)),ISNUMBER(SEARCH("ASM",$L61)),ISNUMBER(SEARCH("RPG",$L61)),ISNUMBER(SEARCH("EASYPLUS",$L61)),ISNUMBER(SEARCH("PL/I",$L61))),"Rule 1",IF($M61="Y","Rule 2",IF($N61="Yes","Rule 3","Rule 4"))) -> Rule 4 | Y61: =IF($X61="Rule 1","D",IF($X61="Rule 2","C",IF($X61="Rule 3","B","A"))) -> A | AA61: =IF($Z61="",$Y61,$Z61) -> A | AB61: =IFERROR(INDEX('Classification Rules'!$C$43:$C$46,MATCH($AA61,'Classification Rules'!$B$43:$B$46,0)),"") -> Language-locked | AC61: =IF($X61="Rule 1","Language: "&$L61,IF($X61="Rule 2","Priority Transfer Target = Y",IF($X61="Rule 3","Cloud Indicator = Yes ("&$O61&")","Cloud Indicator = No, not mainframe, not a transfer target"))) -> Cloud Indicator = No, not mainframe, not a transfer target | AD61: =IFERROR(INDEX('Classification Rules'!$D$13:$D$16,MATCH($AA61,'Classification Rules'!$B$13:$B$16,0)),"") -> On-premises and non-mainframe, so the constraint is not the technology — it is that the business context exists only in Japanese, in few heads. | AE61: =IFERROR(INDEX('Classification Rules'!$D$43:$D$46,MATCH($AA61,'Classification Rules'!$B$43:$B$46,0)),"") -> 0.304 | AF61: =IFERROR(INDEX('Classification Rules'!$E$43:$E$46,MATCH($AA61,'Classification Rules'!$B$43:$B$46,0)),"") -> 0.3394768 | AG61: =IFERROR(INDEX('Classification Rules'!$F$43:$F$46,MATCH($AA61,'Classification Rules'!$B$43:$B$46,0)),"") -> 0.15 | AH61: =IFERROR(INDEX('Classification Rules'!$G$43:$G$46,MATCH($AA61,'Classification Rules'!$B$43:$B$46,0)),"") -> 0.1395 | AI61: =IFERROR(INDEX('Classification Rules'!$I$43:$I$46,MATCH($AA61,'Classification Rules'!$B$43:$B$46,0)),"") -> 10-14 weeks per cluster | AJ61: =IFERROR(INDEX('Classification Rules'!$J$43:$J$46,MATCH($AA61,'Classification Rules'!$B$43:$B$46,0)),"") -> Fully sourced, onshore-weighted | AK61: =IFERROR(INDEX('Classification Rules'!$K$43:$K$46,MATCH($AA61,'Classification Rules'!$B$43:$B$46,0)),"") -> 0
A62: 58 | B62: 9941 | C62: B13ITS-JPN | D62: ITS-PCIS(Mutual Fund System(Including Bestway) | E62: Corporate Related | F62: VS1: Finance & Accounting Services | G62: Core Insurance Systems Group 34956 | H62: Corporate Systems Team 34959 | I62: Core Business Application | J62: N | K62: Yes | L62: JAVA | M62: N | N62: Yes | O62: Software as a Service (SaaS) | P62: MetLife Owned Application Code | Q62: 0.92916458 | R62: 0.0875 | S62: 0 | T62: 1.0166646 | U62: 0.41311355 | V62: 0.50833229 | W62: 0.50833229 | X62: =IF(OR(ISNUMBER(SEARCH("COBOL",$L62)),ISNUMBER(SEARCH("Assembler",$L62)),ISNUMBER(SEARCH("ASM",$L62)),ISNUMBER(SEARCH("RPG",$L62)),ISNUMBER(SEARCH("EASYPLUS",$L62)),ISNUMBER(SEARCH("PL/I",$L62))),"Rule 1",IF($M62="Y","Rule 2",IF($N62="Yes","Rule 3","Rule 4"))) -> Rule 3 | Y62: =IF($X62="Rule 1","D",IF($X62="Rule 2","C",IF($X62="Rule 3","B","A"))) -> B | AA62: =IF($Z62="",$Y62,$Z62) -> B | AB62: =IFERROR(INDEX('Classification Rules'!$C$43:$C$46,MATCH($AA62,'Classification Rules'!$B$43:$B$46,0)),"") -> Offshore-ready | AC62: =IF($X62="Rule 1","Language: "&$L62,IF($X62="Rule 2","Priority Transfer Target = Y",IF($X62="Rule 3","Cloud Indicator = Yes ("&$O62&")","Cloud Indicator = No, not mainframe, not a transfer target"))) -> Cloud Indicator = Yes (Software as a Service (SaaS)) | AD62: =IFERROR(INDEX('Classification Rules'!$D$13:$D$16,MATCH($AA62,'Classification Rules'!$B$13:$B$16,0)),"") -> Cloud migration has already forced re-platforming, documentation and specifiability. Highest AI and offshore ceiling in the estate. | AE62: =IFERROR(INDEX('Classification Rules'!$D$43:$D$46,MATCH($AA62,'Classification Rules'!$B$43:$B$46,0)),"") -> 0.4825 | AF62: =IFERROR(INDEX('Classification Rules'!$E$43:$E$46,MATCH($AA62,'Classification Rules'!$B$43:$B$46,0)),"") -> 0.45402025 | AG62: =IFERROR(INDEX('Classification Rules'!$F$43:$F$46,MATCH($AA62,'Classification Rules'!$B$43:$B$46,0)),"") -> 0.78 | AH62: =IFERROR(INDEX('Classification Rules'!$G$43:$G$46,MATCH($AA62,'Classification Rules'!$B$43:$B$46,0)),"") -> 0.7254 | AI62: =IFERROR(INDEX('Classification Rules'!$I$43:$I$46,MATCH($AA62,'Classification Rules'!$B$43:$B$46,0)),"") -> 6-8 weeks per cluster | AJ62: =IFERROR(INDEX('Classification Rules'!$J$43:$J$46,MATCH($AA62,'Classification Rules'!$B$43:$B$46,0)),"") -> Fully sourced, moving to output units | AK62: =IFERROR(INDEX('Classification Rules'!$K$43:$K$46,MATCH($AA62,'Classification Rules'!$B$43:$B$46,0)),"") -> 0
A63: 59 | B63: 9947 | C63: W13WEP-JPN | D63: Web Payment | E63: Storage and Preservation Related | F63: VS2: Digital Payments & Servicing | G63: Customer Service and Operations Systems Group 34965 | H63: Policy Servicing Team 34967 | I63: Core Business Application | J63: Y | K63: Yes | L63: JAVA | M63: N | N63: No | P63: MetLife Owned Application Code | Q63: 9 | R63: 1.1541667 | S63: 0 | T63: 10 | U63: 0.75904635 | V63: 5 | W63: 5 | X63: =IF(OR(ISNUMBER(SEARCH("COBOL",$L63)),ISNUMBER(SEARCH("Assembler",$L63)),ISNUMBER(SEARCH("ASM",$L63)),ISNUMBER(SEARCH("RPG",$L63)),ISNUMBER(SEARCH("EASYPLUS",$L63)),ISNUMBER(SEARCH("PL/I",$L63))),"Rule 1",IF($M63="Y","Rule 2",IF($N63="Yes","Rule 3","Rule 4"))) -> Rule 4 | Y63: =IF($X63="Rule 1","D",IF($X63="Rule 2","C",IF($X63="Rule 3","B","A"))) -> A | AA63: =IF($Z63="",$Y63,$Z63) -> A | AB63: =IFERROR(INDEX('Classification Rules'!$C$43:$C$46,MATCH($AA63,'Classification Rules'!$B$43:$B$46,0)),"") -> Language-locked | AC63: =IF($X63="Rule 1","Language: "&$L63,IF($X63="Rule 2","Priority Transfer Target = Y",IF($X63="Rule 3","Cloud Indicator = Yes ("&$O63&")","Cloud Indicator = No, not mainframe, not a transfer target"))) -> Cloud Indicator = No, not mainframe, not a transfer target | AD63: =IFERROR(INDEX('Classification Rules'!$D$13:$D$16,MATCH($AA63,'Classification Rules'!$B$13:$B$16,0)),"") -> On-premises and non-mainframe, so the constraint is not the technology — it is that the business context exists only in Japanese, in few heads. | AE63: =IFERROR(INDEX('Classification Rules'!$D$43:$D$46,MATCH($AA63,'Classification Rules'!$B$43:$B$46,0)),"") -> 0.304 | AF63: =IFERROR(INDEX('Classification Rules'!$E$43:$E$46,MATCH($AA63,'Classification Rules'!$B$43:$B$46,0)),"") -> 0.3394768 | AG63: =IFERROR(INDEX('Classification Rules'!$F$43:$F$46,MATCH($AA63,'Classification Rules'!$B$43:$B$46,0)),"") -> 0.15 | AH63: =IFERROR(INDEX('Classification Rules'!$G$43:$G$46,MATCH($AA63,'Classification Rules'!$B$43:$B$46,0)),"") -> 0.1395 | AI63: =IFERROR(INDEX('Classification Rules'!$I$43:$I$46,MATCH($AA63,'Classification Rules'!$B$43:$B$46,0)),"") -> 10-14 weeks per cluster | AJ63: =IFERROR(INDEX('Classification Rules'!$J$43:$J$46,MATCH($AA63,'Classification Rules'!$B$43:$B$46,0)),"") -> Fully sourced, onshore-weighted | AK63: =IFERROR(INDEX('Classification Rules'!$K$43:$K$46,MATCH($AA63,'Classification Rules'!$B$43:$B$46,0)),"") -> 0
A64: 60 | B64: 9948 | C64: Data Send System for BANC MF-JP | D64: Data Send System for BANC | E64: contract management | F64: VS5: New Business, Underwriting & Interfaces | G64: Core Insurance Systems Group 34956 | H64: Policy Admin Systems Team 34957 | I64: Core Business Application | J64: Y | K64: Yes | L64: COBOL, MU(EASYPLUS), Assembler, JCL | M64: N | N64: No | P64: MetLife Owned Application Code | Q64: 9.2697083 | R64: 2.8458333 | S64: 0 | T64: 12.115542 | U64: 0.77129926 | V64: 6.0577708 | W64: 6.0577708 | X64: =IF(OR(ISNUMBER(SEARCH("COBOL",$L64)),ISNUMBER(SEARCH("Assembler",$L64)),ISNUMBER(SEARCH("ASM",$L64)),ISNUMBER(SEARCH("RPG",$L64)),ISNUMBER(SEARCH("EASYPLUS",$L64)),ISNUMBER(SEARCH("PL/I",$L64))),"Rule 1",IF($M64="Y","Rule 2",IF($N64="Yes","Rule 3","Rule 4"))) -> Rule 1 | Y64: =IF($X64="Rule 1","D",IF($X64="Rule 2","C",IF($X64="Rule 3","B","A"))) -> D | AA64: =IF($Z64="",$Y64,$Z64) -> D | AB64: =IFERROR(INDEX('Classification Rules'!$C$43:$C$46,MATCH($AA64,'Classification Rules'!$B$43:$B$46,0)),"") -> Legacy-coupled core | AC64: =IF($X64="Rule 1","Language: "&$L64,IF($X64="Rule 2","Priority Transfer Target = Y",IF($X64="Rule 3","Cloud Indicator = Yes ("&$O64&")","Cloud Indicator = No, not mainframe, not a transfer target"))) -> Language: COBOL, MU(EASYPLUS), Assembler, JCL | AD64: =IFERROR(INDEX('Classification Rules'!$D$13:$D$16,MATCH($AA64,'Classification Rules'!$B$13:$B$16,0)),"") -> Rules hard-coded across modules and design truth is not written down. AI does comprehension here, not generation. | AE64: =IFERROR(INDEX('Classification Rules'!$D$43:$D$46,MATCH($AA64,'Classification Rules'!$B$43:$B$46,0)),"") -> 0.295 | AF64: =IFERROR(INDEX('Classification Rules'!$E$43:$E$46,MATCH($AA64,'Classification Rules'!$B$43:$B$46,0)),"") -> 0.3337015 | AG64: =IFERROR(INDEX('Classification Rules'!$F$43:$F$46,MATCH($AA64,'Classification Rules'!$B$43:$B$46,0)),"") -> 0.58 | AH64: =IFERROR(INDEX('Classification Rules'!$G$43:$G$46,MATCH($AA64,'Classification Rules'!$B$43:$B$46,0)),"") -> 0.5394 | AI64: =IFERROR(INDEX('Classification Rules'!$I$43:$I$46,MATCH($AA64,'Classification Rules'!$B$43:$B$46,0)),"") -> 14-20 weeks per cluster | AJ64: =IFERROR(INDEX('Classification Rules'!$J$43:$J$46,MATCH($AA64,'Classification Rules'!$B$43:$B$46,0)),"") -> Fully sourced, MetLife SMEs paired | AK64: =IFERROR(INDEX('Classification Rules'!$K$43:$K$46,MATCH($AA64,'Classification Rules'!$B$43:$B$46,0)),"") -> 0
A65: 61 | B65: 9949 | C65: CCMDNT-JPN | D65: .NET Common Infrastructure | E65: Corporate Related | F65: VS5: Corporate Integration & Batch Services | G65: Core Insurance Systems Group 34956 | H65: Corporate Systems Team 34959 | I65: Common Service Business Application | J65: N | K65: Yes | L65: VB.NET; C # | M65: N | N65: No | P65: MetLife Owned Application Code | Q65: 0.066666667 | R65: 0 | S65: 0 | T65: 0.066666667 | U65: 0 | V65: 0.033333333 | W65: 0.033333333 | X65: =IF(OR(ISNUMBER(SEARCH("COBOL",$L65)),ISNUMBER(SEARCH("Assembler",$L65)),ISNUMBER(SEARCH("ASM",$L65)),ISNUMBER(SEARCH("RPG",$L65)),ISNUMBER(SEARCH("EASYPLUS",$L65)),ISNUMBER(SEARCH("PL/I",$L65))),"Rule 1",IF($M65="Y","Rule 2",IF($N65="Yes","Rule 3","Rule 4"))) -> Rule 4 | Y65: =IF($X65="Rule 1","D",IF($X65="Rule 2","C",IF($X65="Rule 3","B","A"))) -> A | AA65: =IF($Z65="",$Y65,$Z65) -> A | AB65: =IFERROR(INDEX('Classification Rules'!$C$43:$C$46,MATCH($AA65,'Classification Rules'!$B$43:$B$46,0)),"") -> Language-locked | AC65: =IF($X65="Rule 1","Language: "&$L65,IF($X65="Rule 2","Priority Transfer Target = Y",IF($X65="Rule 3","Cloud Indicator = Yes ("&$O65&")","Cloud Indicator = No, not mainframe, not a transfer target"))) -> Cloud Indicator = No, not mainframe, not a transfer target | AD65: =IFERROR(INDEX('Classification Rules'!$D$13:$D$16,MATCH($AA65,'Classification Rules'!$B$13:$B$16,0)),"") -> On-premises and non-mainframe, so the constraint is not the technology — it is that the business context exists only in Japanese, in few heads. | AE65: =IFERROR(INDEX('Classification Rules'!$D$43:$D$46,MATCH($AA65,'Classification Rules'!$B$43:$B$46,0)),"") -> 0.304 | AF65: =IFERROR(INDEX('Classification Rules'!$E$43:$E$46,MATCH($AA65,'Classification Rules'!$B$43:$B$46,0)),"") -> 0.3394768 | AG65: =IFERROR(INDEX('Classification Rules'!$F$43:$F$46,MATCH($AA65,'Classification Rules'!$B$43:$B$46,0)),"") -> 0.15 | AH65: =IFERROR(INDEX('Classification Rules'!$G$43:$G$46,MATCH($AA65,'Classification Rules'!$B$43:$B$46,0)),"") -> 0.1395 | AI65: =IFERROR(INDEX('Classification Rules'!$I$43:$I$46,MATCH($AA65,'Classification Rules'!$B$43:$B$46,0)),"") -> 10-14 weeks per cluster | AJ65: =IFERROR(INDEX('Classification Rules'!$J$43:$J$46,MATCH($AA65,'Classification Rules'!$B$43:$B$46,0)),"") -> Fully sourced, onshore-weighted | AK65: =IFERROR(INDEX('Classification Rules'!$K$43:$K$46,MATCH($AA65,'Classification Rules'!$B$43:$B$46,0)),"") -> 0
A66: 62 | B66: 9951 | C66: BCMHRP-JPN | D66: Data cooperation | E66: Data Infrastructure | F66: VS1: Informatica — ETL, IDQ, Address Doctor & HOST/AS400 Data Cooperation | G66: Data Platforms Team 34980 | H66: Data Platforms Team 34980 | I66: Common Service Business Application | J66: N | K66: Yes | L66: Other#MS-DOS ,AWK,VBScript,JAVA | M66: Y | N66: No | O66: Running on both on-premises and Azure. The on-premises version will be decommissioned by the end of 2027. | P66: MetLife Owned Application Code | Q66: 7 | R66: 1 | S66: 0 | T66: 7.9270417 | U66: 0.77923668 | V66: 3.9635208 | W66: 3.9635208 | X66: =IF(OR(ISNUMBER(SEARCH("COBOL",$L66)),ISNUMBER(SEARCH("Assembler",$L66)),ISNUMBER(SEARCH("ASM",$L66)),ISNUMBER(SEARCH("RPG",$L66)),ISNUMBER(SEARCH("EASYPLUS",$L66)),ISNUMBER(SEARCH("PL/I",$L66))),"Rule 1",IF($M66="Y","Rule 2",IF($N66="Yes","Rule 3","Rule 4"))) -> Rule 2 | Y66: =IF($X66="Rule 1","D",IF($X66="Rule 2","C",IF($X66="Rule 3","B","A"))) -> C | AA66: =IF($Z66="",$Y66,$Z66) -> C | AB66: =IFERROR(INDEX('Classification Rules'!$C$43:$C$46,MATCH($AA66,'Classification Rules'!$B$43:$B$46,0)),"") -> MGCC-destined | AC66: =IF($X66="Rule 1","Language: "&$L66,IF($X66="Rule 2","Priority Transfer Target = Y",IF($X66="Rule 3","Cloud Indicator = Yes ("&$O66&")","Cloud Indicator = No, not mainframe, not a transfer target"))) -> Priority Transfer Target = Y | AD66: =IFERROR(INDEX('Classification Rules'!$D$13:$D$16,MATCH($AA66,'Classification Rules'!$B$13:$B$16,0)),"") -> MetLife has already flagged these for transfer and nine of ten already carry MGCC people. Routing them through a vendor transition pays for the same knowledge transfer twice. | AE66: =IFERROR(INDEX('Classification Rules'!$D$43:$D$46,MATCH($AA66,'Classification Rules'!$B$43:$B$46,0)),"") -> 0.4525 | AF66: =IFERROR(INDEX('Classification Rules'!$E$43:$E$46,MATCH($AA66,'Classification Rules'!$B$43:$B$46,0)),"") -> 0.43476925 | AG66: =IFERROR(INDEX('Classification Rules'!$F$43:$F$46,MATCH($AA66,'Classification Rules'!$B$43:$B$46,0)),"") -> 0 | AH66: =IFERROR(INDEX('Classification Rules'!$G$43:$G$46,MATCH($AA66,'Classification Rules'!$B$43:$B$46,0)),"") -> 0 | AI66: =IFERROR(INDEX('Classification Rules'!$I$43:$I$46,MATCH($AA66,'Classification Rules'!$B$43:$B$46,0)),"") -> 6-8 weeks, role handover | AJ66: =IFERROR(INDEX('Classification Rules'!$J$43:$J$46,MATCH($AA66,'Classification Rules'!$B$43:$B$46,0)),"") -> Co-sourced with MGCC, permanently | AK66: =IFERROR(INDEX('Classification Rules'!$K$43:$K$46,MATCH($AA66,'Classification Rules'!$B$43:$B$46,0)),"") -> 0
A67: 63 | B67: 9962 | C67: WPSCUS-JPN | D67: Customer Support System | E67: Marketing/Direct Business Related | F67: VS1: Digital Marketing & Lead Management | G67: Customer and Channel Engineering 34961 | H67: Marketing and Leads Team 34964 | I67: Core Business Application | J67: N | K67: Yes | L67: JavaScript; Other#APEX | M67: N | N67: Yes | O67: Platform as a Service (PaaS) | P67: MetLife Owned Application Code | Q67: 8.9216667 | R67: 2.4104167 | S67: 1.52 | T67: 12.852083 | U67: 0.82739504 | V67: 6.4260417 | W67: 6.4260417 | X67: =IF(OR(ISNUMBER(SEARCH("COBOL",$L67)),ISNUMBER(SEARCH("Assembler",$L67)),ISNUMBER(SEARCH("ASM",$L67)),ISNUMBER(SEARCH("RPG",$L67)),ISNUMBER(SEARCH("EASYPLUS",$L67)),ISNUMBER(SEARCH("PL/I",$L67))),"Rule 1",IF($M67="Y","Rule 2",IF($N67="Yes","Rule 3","Rule 4"))) -> Rule 3 | Y67: =IF($X67="Rule 1","D",IF($X67="Rule 2","C",IF($X67="Rule 3","B","A"))) -> B | AA67: =IF($Z67="",$Y67,$Z67) -> B | AB67: =IFERROR(INDEX('Classification Rules'!$C$43:$C$46,MATCH($AA67,'Classification Rules'!$B$43:$B$46,0)),"") -> Offshore-ready | AC67: =IF($X67="Rule 1","Language: "&$L67,IF($X67="Rule 2","Priority Transfer Target = Y",IF($X67="Rule 3","Cloud Indicator = Yes ("&$O67&")","Cloud Indicator = No, not mainframe, not a transfer target"))) -> Cloud Indicator = Yes (Platform as a Service (PaaS)) | AD67: =IFERROR(INDEX('Classification Rules'!$D$13:$D$16,MATCH($AA67,'Classification Rules'!$B$13:$B$16,0)),"") -> Cloud migration has already forced re-platforming, documentation and specifiability. Highest AI and offshore ceiling in the estate. | AE67: =IFERROR(INDEX('Classification Rules'!$D$43:$D$46,MATCH($AA67,'Classification Rules'!$B$43:$B$46,0)),"") -> 0.4825 | AF67: =IFERROR(INDEX('Classification Rules'!$E$43:$E$46,MATCH($AA67,'Classification Rules'!$B$43:$B$46,0)),"") -> 0.45402025 | AG67: =IFERROR(INDEX('Classification Rules'!$F$43:$F$46,MATCH($AA67,'Classification Rules'!$B$43:$B$46,0)),"") -> 0.78 | AH67: =IFERROR(INDEX('Classification Rules'!$G$43:$G$46,MATCH($AA67,'Classification Rules'!$B$43:$B$46,0)),"") -> 0.7254 | AI67: =IFERROR(INDEX('Classification Rules'!$I$43:$I$46,MATCH($AA67,'Classification Rules'!$B$43:$B$46,0)),"") -> 6-8 weeks per cluster | AJ67: =IFERROR(INDEX('Classification Rules'!$J$43:$J$46,MATCH($AA67,'Classification Rules'!$B$43:$B$46,0)),"") -> Fully sourced, moving to output units | AK67: =IFERROR(INDEX('Classification Rules'!$K$43:$K$46,MATCH($AA67,'Classification Rules'!$B$43:$B$46,0)),"") -> 0
A68: 64 | B68: 9964 | C68: WAANSO-JPN | D68: New Submit Online System | E68: Corporate Related | F68: VS4: Corporate Workflow & Employee Services | G68: Core Insurance Systems Group 34956 | H68: Corporate Systems Team 34959 | I68: Core Business Application | J68: N | K68: Yes | L68: JAVA | M68: N | N68: No | P68: MetLife Owned Application Code | Q68: 1.9533333 | R68: 0.3625 | S68: 0 | T68: 2.3158333 | U68: 0.90824037 | V68: 1.1579167 | W68: 1.1579167 | X68: =IF(OR(ISNUMBER(SEARCH("COBOL",$L68)),ISNUMBER(SEARCH("Assembler",$L68)),ISNUMBER(SEARCH("ASM",$L68)),ISNUMBER(SEARCH("RPG",$L68)),ISNUMBER(SEARCH("EASYPLUS",$L68)),ISNUMBER(SEARCH("PL/I",$L68))),"Rule 1",IF($M68="Y","Rule 2",IF($N68="Yes","Rule 3","Rule 4"))) -> Rule 4 | Y68: =IF($X68="Rule 1","D",IF($X68="Rule 2","C",IF($X68="Rule 3","B","A"))) -> A | AA68: =IF($Z68="",$Y68,$Z68) -> A | AB68: =IFERROR(INDEX('Classification Rules'!$C$43:$C$46,MATCH($AA68,'Classification Rules'!$B$43:$B$46,0)),"") -> Language-locked | AC68: =IF($X68="Rule 1","Language: "&$L68,IF($X68="Rule 2","Priority Transfer Target = Y",IF($X68="Rule 3","Cloud Indicator = Yes ("&$O68&")","Cloud Indicator = No, not mainframe, not a transfer target"))) -> Cloud Indicator = No, not mainframe, not a transfer target | AD68: =IFERROR(INDEX('Classification Rules'!$D$13:$D$16,MATCH($AA68,'Classification Rules'!$B$13:$B$16,0)),"") -> On-premises and non-mainframe, so the constraint is not the technology — it is that the business context exists only in Japanese, in few heads. | AE68: =IFERROR(INDEX('Classification Rules'!$D$43:$D$46,MATCH($AA68,'Classification Rules'!$B$43:$B$46,0)),"") -> 0.304 | AF68: =IFERROR(INDEX('Classification Rules'!$E$43:$E$46,MATCH($AA68,'Classification Rules'!$B$43:$B$46,0)),"") -> 0.3394768 | AG68: =IFERROR(INDEX('Classification Rules'!$F$43:$F$46,MATCH($AA68,'Classification Rules'!$B$43:$B$46,0)),"") -> 0.15 | AH68: =IFERROR(INDEX('Classification Rules'!$G$43:$G$46,MATCH($AA68,'Classification Rules'!$B$43:$B$46,0)),"") -> 0.1395 | AI68: =IFERROR(INDEX('Classification Rules'!$I$43:$I$46,MATCH($AA68,'Classification Rules'!$B$43:$B$46,0)),"") -> 10-14 weeks per cluster | AJ68: =IFERROR(INDEX('Classification Rules'!$J$43:$J$46,MATCH($AA68,'Classification Rules'!$B$43:$B$46,0)),"") -> Fully sourced, onshore-weighted | AK68: =IFERROR(INDEX('Classification Rules'!$K$43:$K$46,MATCH($AA68,'Classification Rules'!$B$43:$B$46,0)),"") -> 0
A69: 65 | B69: 9965 | C69: WZZHYO-JPN | D69: Report Template Management System | E69: Corporate Related | F69: VS2: Corporate Operations & Productivity | G69: Core Insurance Systems Group 34956 | H69: Corporate Systems Team 34959 | I69: Core Business Application | J69: N | K69: Yes | L69: JAVA | M69: N | N69: No | P69: MetLife Owned Application Code | Q69: 0.025 | R69: 0.0375 | S69: 0 | T69: 0.0625 | U69: 0.2 | V69: 0.03125 | W69: 0.03125 | X69: =IF(OR(ISNUMBER(SEARCH("COBOL",$L69)),ISNUMBER(SEARCH("Assembler",$L69)),ISNUMBER(SEARCH("ASM",$L69)),ISNUMBER(SEARCH("RPG",$L69)),ISNUMBER(SEARCH("EASYPLUS",$L69)),ISNUMBER(SEARCH("PL/I",$L69))),"Rule 1",IF($M69="Y","Rule 2",IF($N69="Yes","Rule 3","Rule 4"))) -> Rule 4 | Y69: =IF($X69="Rule 1","D",IF($X69="Rule 2","C",IF($X69="Rule 3","B","A"))) -> A | AA69: =IF($Z69="",$Y69,$Z69) -> A | AB69: =IFERROR(INDEX('Classification Rules'!$C$43:$C$46,MATCH($AA69,'Classification Rules'!$B$43:$B$46,0)),"") -> Language-locked | AC69: =IF($X69="Rule 1","Language: "&$L69,IF($X69="Rule 2","Priority Transfer Target = Y",IF($X69="Rule 3","Cloud Indicator = Yes ("&$O69&")","Cloud Indicator = No, not mainframe, not a transfer target"))) -> Cloud Indicator = No, not mainframe, not a transfer target | AD69: =IFERROR(INDEX('Classification Rules'!$D$13:$D$16,MATCH($AA69,'Classification Rules'!$B$13:$B$16,0)),"") -> On-premises and non-mainframe, so the constraint is not the technology — it is that the business context exists only in Japanese, in few heads. | AE69: =IFERROR(INDEX('Classification Rules'!$D$43:$D$46,MATCH($AA69,'Classification Rules'!$B$43:$B$46,0)),"") -> 0.304 | AF69: =IFERROR(INDEX('Classification Rules'!$E$43:$E$46,MATCH($AA69,'Classification Rules'!$B$43:$B$46,0)),"") -> 0.3394768 | AG69: =IFERROR(INDEX('Classification Rules'!$F$43:$F$46,MATCH($AA69,'Classification Rules'!$B$43:$B$46,0)),"") -> 0.15 | AH69: =IFERROR(INDEX('Classification Rules'!$G$43:$G$46,MATCH($AA69,'Classification Rules'!$B$43:$B$46,0)),"") -> 0.1395 | AI69: =IFERROR(INDEX('Classification Rules'!$I$43:$I$46,MATCH($AA69,'Classification Rules'!$B$43:$B$46,0)),"") -> 10-14 weeks per cluster | AJ69: =IFERROR(INDEX('Classification Rules'!$J$43:$J$46,MATCH($AA69,'Classification Rules'!$B$43:$B$46,0)),"") -> Fully sourced, onshore-weighted | AK69: =IFERROR(INDEX('Classification Rules'!$K$43:$K$46,MATCH($AA69,'Classification Rules'!$B$43:$B$46,0)),"") -> 0
A70: 66 | B70: 9969 | C70: EAADRS-JPN | D70: Dr.SUM | E70: Corporate Related | F70: VS5: Corporate Integration & Batch Services | G70: Core Insurance Systems Group 34956 | H70: Corporate Systems Team 34959 | I70: Core Business Application | J70: N | K70: Yes | L70: JAVA | M70: N | N70: No | P70: Non-MetLife Owned Application Code (3rd party/COTS) | Q70: 0.312375 | R70: 0.025 | S70: 0 | T70: 0.337375 | U70: 0.67580585 | V70: 0.1686875 | W70: 0.1686875 | X70: =IF(OR(ISNUMBER(SEARCH("COBOL",$L70)),ISNUMBER(SEARCH("Assembler",$L70)),ISNUMBER(SEARCH("ASM",$L70)),ISNUMBER(SEARCH("RPG",$L70)),ISNUMBER(SEARCH("EASYPLUS",$L70)),ISNUMBER(SEARCH("PL/I",$L70))),"Rule 1",IF($M70="Y","Rule 2",IF($N70="Yes","Rule 3","Rule 4"))) -> Rule 4 | Y70: =IF($X70="Rule 1","D",IF($X70="Rule 2","C",IF($X70="Rule 3","B","A"))) -> A | AA70: =IF($Z70="",$Y70,$Z70) -> A | AB70: =IFERROR(INDEX('Classification Rules'!$C$43:$C$46,MATCH($AA70,'Classification Rules'!$B$43:$B$46,0)),"") -> Language-locked | AC70: =IF($X70="Rule 1","Language: "&$L70,IF($X70="Rule 2","Priority Transfer Target = Y",IF($X70="Rule 3","Cloud Indicator = Yes ("&$O70&")","Cloud Indicator = No, not mainframe, not a transfer target"))) -> Cloud Indicator = No, not mainframe, not a transfer target | AD70: =IFERROR(INDEX('Classification Rules'!$D$13:$D$16,MATCH($AA70,'Classification Rules'!$B$13:$B$16,0)),"") -> On-premises and non-mainframe, so the constraint is not the technology — it is that the business context exists only in Japanese, in few heads. | AE70: =IFERROR(INDEX('Classification Rules'!$D$43:$D$46,MATCH($AA70,'Classification Rules'!$B$43:$B$46,0)),"") -> 0.304 | AF70: =IFERROR(INDEX('Classification Rules'!$E$43:$E$46,MATCH($AA70,'Classification Rules'!$B$43:$B$46,0)),"") -> 0.3394768 | AG70: =IFERROR(INDEX('Classification Rules'!$F$43:$F$46,MATCH($AA70,'Classification Rules'!$B$43:$B$46,0)),"") -> 0.15 | AH70: =IFERROR(INDEX('Classification Rules'!$G$43:$G$46,MATCH($AA70,'Classification Rules'!$B$43:$B$46,0)),"") -> 0.1395 | AI70: =IFERROR(INDEX('Classification Rules'!$I$43:$I$46,MATCH($AA70,'Classification Rules'!$B$43:$B$46,0)),"") -> 10-14 weeks per cluster | AJ70: =IFERROR(INDEX('Classification Rules'!$J$43:$J$46,MATCH($AA70,'Classification Rules'!$B$43:$B$46,0)),"") -> Fully sourced, onshore-weighted | AK70: =IFERROR(INDEX('Classification Rules'!$K$43:$K$46,MATCH($AA70,'Classification Rules'!$B$43:$B$46,0)),"") -> 0
A71: 67 | B71: 9975 | C71: WPMWCC-JPN | D71: Web Contact Center | E71: Customer Care / Call Center Related | F71: VS4: Care Operations & Batch Services | G71: Customer Service and Operations Systems Group 34965 | H71: Customer Care Team 34969 | I71: Core Business Application | J71: N | K71: Yes | L71: JAVA | M71: N | N71: No | P71: MetLife Owned Application Code | Q71: 1.1116667 | R71: 0 | S71: 0 | T71: 1.1116667 | U71: 0.58508246 | V71: 0.55583333 | W71: 0.55583333 | X71: =IF(OR(ISNUMBER(SEARCH("COBOL",$L71)),ISNUMBER(SEARCH("Assembler",$L71)),ISNUMBER(SEARCH("ASM",$L71)),ISNUMBER(SEARCH("RPG",$L71)),ISNUMBER(SEARCH("EASYPLUS",$L71)),ISNUMBER(SEARCH("PL/I",$L71))),"Rule 1",IF($M71="Y","Rule 2",IF($N71="Yes","Rule 3","Rule 4"))) -> Rule 4 | Y71: =IF($X71="Rule 1","D",IF($X71="Rule 2","C",IF($X71="Rule 3","B","A"))) -> A | AA71: =IF($Z71="",$Y71,$Z71) -> A | AB71: =IFERROR(INDEX('Classification Rules'!$C$43:$C$46,MATCH($AA71,'Classification Rules'!$B$43:$B$46,0)),"") -> Language-locked | AC71: =IF($X71="Rule 1","Language: "&$L71,IF($X71="Rule 2","Priority Transfer Target = Y",IF($X71="Rule 3","Cloud Indicator = Yes ("&$O71&")","Cloud Indicator = No, not mainframe, not a transfer target"))) -> Cloud Indicator = No, not mainframe, not a transfer target | AD71: =IFERROR(INDEX('Classification Rules'!$D$13:$D$16,MATCH($AA71,'Classification Rules'!$B$13:$B$16,0)),"") -> On-premises and non-mainframe, so the constraint is not the technology — it is that the business context exists only in Japanese, in few heads. | AE71: =IFERROR(INDEX('Classification Rules'!$D$43:$D$46,MATCH($AA71,'Classification Rules'!$B$43:$B$46,0)),"") -> 0.304 | AF71: =IFERROR(INDEX('Classification Rules'!$E$43:$E$46,MATCH($AA71,'Classification Rules'!$B$43:$B$46,0)),"") -> 0.3394768 | AG71: =IFERROR(INDEX('Classification Rules'!$F$43:$F$46,MATCH($AA71,'Classification Rules'!$B$43:$B$46,0)),"") -> 0.15 | AH71: =IFERROR(INDEX('Classification Rules'!$G$43:$G$46,MATCH($AA71,'Classification Rules'!$B$43:$B$46,0)),"") -> 0.1395 | AI71: =IFERROR(INDEX('Classification Rules'!$I$43:$I$46,MATCH($AA71,'Classification Rules'!$B$43:$B$46,0)),"") -> 10-14 weeks per cluster | AJ71: =IFERROR(INDEX('Classification Rules'!$J$43:$J$46,MATCH($AA71,'Classification Rules'!$B$43:$B$46,0)),"") -> Fully sourced, onshore-weighted | AK71: =IFERROR(INDEX('Classification Rules'!$K$43:$K$46,MATCH($AA71,'Classification Rules'!$B$43:$B$46,0)),"") -> 0
A72: 68 | B72: 9977 | C72: WGLRPC-JPN | D72: ReportConnection | E72: Sales / Insurance Recruitment | F72: VS5: Sales Support & Distribution Services | G72: Customer and Channel Engineering 34961 | H72: Distribution F2F Team 34962 | I72: Core Business Application | J72: N | K72: Yes | L72: JAVA | M72: N | N72: No | P72: MetLife Owned Application Code | Q72: 1 | R72: 1 | S72: 0 | T72: 0.45791667 | U72: 0 | V72: 0.22895833 | W72: 0.22895833 | X72: =IF(OR(ISNUMBER(SEARCH("COBOL",$L72)),ISNUMBER(SEARCH("Assembler",$L72)),ISNUMBER(SEARCH("ASM",$L72)),ISNUMBER(SEARCH("RPG",$L72)),ISNUMBER(SEARCH("EASYPLUS",$L72)),ISNUMBER(SEARCH("PL/I",$L72))),"Rule 1",IF($M72="Y","Rule 2",IF($N72="Yes","Rule 3","Rule 4"))) -> Rule 4 | Y72: =IF($X72="Rule 1","D",IF($X72="Rule 2","C",IF($X72="Rule 3","B","A"))) -> A | AA72: =IF($Z72="",$Y72,$Z72) -> A | AB72: =IFERROR(INDEX('Classification Rules'!$C$43:$C$46,MATCH($AA72,'Classification Rules'!$B$43:$B$46,0)),"") -> Language-locked | AC72: =IF($X72="Rule 1","Language: "&$L72,IF($X72="Rule 2","Priority Transfer Target = Y",IF($X72="Rule 3","Cloud Indicator = Yes ("&$O72&")","Cloud Indicator = No, not mainframe, not a transfer target"))) -> Cloud Indicator = No, not mainframe, not a transfer target | AD72: =IFERROR(INDEX('Classification Rules'!$D$13:$D$16,MATCH($AA72,'Classification Rules'!$B$13:$B$16,0)),"") -> On-premises and non-mainframe, so the constraint is not the technology — it is that the business context exists only in Japanese, in few heads. | AE72: =IFERROR(INDEX('Classification Rules'!$D$43:$D$46,MATCH($AA72,'Classification Rules'!$B$43:$B$46,0)),"") -> 0.304 | AF72: =IFERROR(INDEX('Classification Rules'!$E$43:$E$46,MATCH($AA72,'Classification Rules'!$B$43:$B$46,0)),"") -> 0.3394768 | AG72: =IFERROR(INDEX('Classification Rules'!$F$43:$F$46,MATCH($AA72,'Classification Rules'!$B$43:$B$46,0)),"") -> 0.15 | AH72: =IFERROR(INDEX('Classification Rules'!$G$43:$G$46,MATCH($AA72,'Classification Rules'!$B$43:$B$46,0)),"") -> 0.1395 | AI72: =IFERROR(INDEX('Classification Rules'!$I$43:$I$46,MATCH($AA72,'Classification Rules'!$B$43:$B$46,0)),"") -> 10-14 weeks per cluster | AJ72: =IFERROR(INDEX('Classification Rules'!$J$43:$J$46,MATCH($AA72,'Classification Rules'!$B$43:$B$46,0)),"") -> Fully sourced, onshore-weighted | AK72: =IFERROR(INDEX('Classification Rules'!$K$43:$K$46,MATCH($AA72,'Classification Rules'!$B$43:$B$46,0)),"") -> 0
A73: 69 | B73: 9980 | C73: Policy UWIBATCH MF-JPN | D73: Policy Underwriting and Issue Batch | E73: contract management | F73: VS5: New Business, Underwriting & Interfaces | G73: Core Insurance Systems Group 34956 | H73: Policy Admin Systems Team 34957 | I73: Core Business Application | J73: Y | K73: Yes | L73: Other#ASM; Cobol | M73: N | N73: No | P73: MetLife Owned Application Code | Q73: 12.606875 | R73: 1.1416667 | S73: 0 | T73: 13.748542 | U73: 0.81496522 | V73: 6.8742708 | W73: 6.8742708 | X73: =IF(OR(ISNUMBER(SEARCH("COBOL",$L73)),ISNUMBER(SEARCH("Assembler",$L73)),ISNUMBER(SEARCH("ASM",$L73)),ISNUMBER(SEARCH("RPG",$L73)),ISNUMBER(SEARCH("EASYPLUS",$L73)),ISNUMBER(SEARCH("PL/I",$L73))),"Rule 1",IF($M73="Y","Rule 2",IF($N73="Yes","Rule 3","Rule 4"))) -> Rule 1 | Y73: =IF($X73="Rule 1","D",IF($X73="Rule 2","C",IF($X73="Rule 3","B","A"))) -> D | AA73: =IF($Z73="",$Y73,$Z73) -> D | AB73: =IFERROR(INDEX('Classification Rules'!$C$43:$C$46,MATCH($AA73,'Classification Rules'!$B$43:$B$46,0)),"") -> Legacy-coupled core | AC73: =IF($X73="Rule 1","Language: "&$L73,IF($X73="Rule 2","Priority Transfer Target = Y",IF($X73="Rule 3","Cloud Indicator = Yes ("&$O73&")","Cloud Indicator = No, not mainframe, not a transfer target"))) -> Language: Other#ASM; Cobol | AD73: =IFERROR(INDEX('Classification Rules'!$D$13:$D$16,MATCH($AA73,'Classification Rules'!$B$13:$B$16,0)),"") -> Rules hard-coded across modules and design truth is not written down. AI does comprehension here, not generation. | AE73: =IFERROR(INDEX('Classification Rules'!$D$43:$D$46,MATCH($AA73,'Classification Rules'!$B$43:$B$46,0)),"") -> 0.295 | AF73: =IFERROR(INDEX('Classification Rules'!$E$43:$E$46,MATCH($AA73,'Classification Rules'!$B$43:$B$46,0)),"") -> 0.3337015 | AG73: =IFERROR(INDEX('Classification Rules'!$F$43:$F$46,MATCH($AA73,'Classification Rules'!$B$43:$B$46,0)),"") -> 0.58 | AH73: =IFERROR(INDEX('Classification Rules'!$G$43:$G$46,MATCH($AA73,'Classification Rules'!$B$43:$B$46,0)),"") -> 0.5394 | AI73: =IFERROR(INDEX('Classification Rules'!$I$43:$I$46,MATCH($AA73,'Classification Rules'!$B$43:$B$46,0)),"") -> 14-20 weeks per cluster | AJ73: =IFERROR(INDEX('Classification Rules'!$J$43:$J$46,MATCH($AA73,'Classification Rules'!$B$43:$B$46,0)),"") -> Fully sourced, MetLife SMEs paired | AK73: =IFERROR(INDEX('Classification Rules'!$K$43:$K$46,MATCH($AA73,'Classification Rules'!$B$43:$B$46,0)),"") -> 0
A74: 70 | B74: 9983 | C74: WAAATF-JPN | D74: Agents Target Following system | E74: Sales / Insurance Recruitment | F74: VS3: Agency & Producer Enablement | G74: Customer and Channel Engineering 34961 | H74: Distribution F2F Team 34962 | I74: Core Business Application | J74: N | K74: Yes | L74: JAVA | M74: N | N74: Yes | O74: Platform as a Service (PaaS) | P74: MetLife Owned Application Code | Q74: 6.6141667 | R74: 0.64791667 | S74: 0 | T74: 7.2620833 | U74: 0.93912445 | V74: 3.6310417 | W74: 3.6310417 | X74: =IF(OR(ISNUMBER(SEARCH("COBOL",$L74)),ISNUMBER(SEARCH("Assembler",$L74)),ISNUMBER(SEARCH("ASM",$L74)),ISNUMBER(SEARCH("RPG",$L74)),ISNUMBER(SEARCH("EASYPLUS",$L74)),ISNUMBER(SEARCH("PL/I",$L74))),"Rule 1",IF($M74="Y","Rule 2",IF($N74="Yes","Rule 3","Rule 4"))) -> Rule 3 | Y74: =IF($X74="Rule 1","D",IF($X74="Rule 2","C",IF($X74="Rule 3","B","A"))) -> B | AA74: =IF($Z74="",$Y74,$Z74) -> B | AB74: =IFERROR(INDEX('Classification Rules'!$C$43:$C$46,MATCH($AA74,'Classification Rules'!$B$43:$B$46,0)),"") -> Offshore-ready | AC74: =IF($X74="Rule 1","Language: "&$L74,IF($X74="Rule 2","Priority Transfer Target = Y",IF($X74="Rule 3","Cloud Indicator = Yes ("&$O74&")","Cloud Indicator = No, not mainframe, not a transfer target"))) -> Cloud Indicator = Yes (Platform as a Service (PaaS)) | AD74: =IFERROR(INDEX('Classification Rules'!$D$13:$D$16,MATCH($AA74,'Classification Rules'!$B$13:$B$16,0)),"") -> Cloud migration has already forced re-platforming, documentation and specifiability. Highest AI and offshore ceiling in the estate. | AE74: =IFERROR(INDEX('Classification Rules'!$D$43:$D$46,MATCH($AA74,'Classification Rules'!$B$43:$B$46,0)),"") -> 0.4825 | AF74: =IFERROR(INDEX('Classification Rules'!$E$43:$E$46,MATCH($AA74,'Classification Rules'!$B$43:$B$46,0)),"") -> 0.45402025 | AG74: =IFERROR(INDEX('Classification Rules'!$F$43:$F$46,MATCH($AA74,'Classification Rules'!$B$43:$B$46,0)),"") -> 0.78 | AH74: =IFERROR(INDEX('Classification Rules'!$G$43:$G$46,MATCH($AA74,'Classification Rules'!$B$43:$B$46,0)),"") -> 0.7254 | AI74: =IFERROR(INDEX('Classification Rules'!$I$43:$I$46,MATCH($AA74,'Classification Rules'!$B$43:$B$46,0)),"") -> 6-8 weeks per cluster | AJ74: =IFERROR(INDEX('Classification Rules'!$J$43:$J$46,MATCH($AA74,'Classification Rules'!$B$43:$B$46,0)),"") -> Fully sourced, moving to output units | AK74: =IFERROR(INDEX('Classification Rules'!$K$43:$K$46,MATCH($AA74,'Classification Rules'!$B$43:$B$46,0)),"") -> 0
A75: 71 | B75: 9986 | C75: ZGLEST-JPN | D75: eSTATION | E75: Corporate Related | F75: VS2: Corporate Operations & Productivity | G75: Core Insurance Systems Group 34956 | H75: Corporate Systems Team 34959 | I75: Core Business Application | J75: N | K75: Yes | L75: JavaScript; VB.NET; C#;HTML | M75: N | N75: No | P75: MetLife Owned Application Code | Q75: 2.4426667 | R75: 0.57083333 | S75: 0 | T75: 3.0135 | U75: 0.27515071 | V75: 1.50675 | W75: 1.50675 | X75: =IF(OR(ISNUMBER(SEARCH("COBOL",$L75)),ISNUMBER(SEARCH("Assembler",$L75)),ISNUMBER(SEARCH("ASM",$L75)),ISNUMBER(SEARCH("RPG",$L75)),ISNUMBER(SEARCH("EASYPLUS",$L75)),ISNUMBER(SEARCH("PL/I",$L75))),"Rule 1",IF($M75="Y","Rule 2",IF($N75="Yes","Rule 3","Rule 4"))) -> Rule 4 | Y75: =IF($X75="Rule 1","D",IF($X75="Rule 2","C",IF($X75="Rule 3","B","A"))) -> A | AA75: =IF($Z75="",$Y75,$Z75) -> A | AB75: =IFERROR(INDEX('Classification Rules'!$C$43:$C$46,MATCH($AA75,'Classification Rules'!$B$43:$B$46,0)),"") -> Language-locked | AC75: =IF($X75="Rule 1","Language: "&$L75,IF($X75="Rule 2","Priority Transfer Target = Y",IF($X75="Rule 3","Cloud Indicator = Yes ("&$O75&")","Cloud Indicator = No, not mainframe, not a transfer target"))) -> Cloud Indicator = No, not mainframe, not a transfer target | AD75: =IFERROR(INDEX('Classification Rules'!$D$13:$D$16,MATCH($AA75,'Classification Rules'!$B$13:$B$16,0)),"") -> On-premises and non-mainframe, so the constraint is not the technology — it is that the business context exists only in Japanese, in few heads. | AE75: =IFERROR(INDEX('Classification Rules'!$D$43:$D$46,MATCH($AA75,'Classification Rules'!$B$43:$B$46,0)),"") -> 0.304 | AF75: =IFERROR(INDEX('Classification Rules'!$E$43:$E$46,MATCH($AA75,'Classification Rules'!$B$43:$B$46,0)),"") -> 0.3394768 | AG75: =IFERROR(INDEX('Classification Rules'!$F$43:$F$46,MATCH($AA75,'Classification Rules'!$B$43:$B$46,0)),"") -> 0.15 | AH75: =IFERROR(INDEX('Classification Rules'!$G$43:$G$46,MATCH($AA75,'Classification Rules'!$B$43:$B$46,0)),"") -> 0.1395 | AI75: =IFERROR(INDEX('Classification Rules'!$I$43:$I$46,MATCH($AA75,'Classification Rules'!$B$43:$B$46,0)),"") -> 10-14 weeks per cluster | AJ75: =IFERROR(INDEX('Classification Rules'!$J$43:$J$46,MATCH($AA75,'Classification Rules'!$B$43:$B$46,0)),"") -> Fully sourced, onshore-weighted | AK75: =IFERROR(INDEX('Classification Rules'!$K$43:$K$46,MATCH($AA75,'Classification Rules'!$B$43:$B$46,0)),"") -> 0
A76: 72 | B76: 9992 | C76: CMESB-JPN | D76: Enterprise Service Bus | E76: Common Service Platform | F76: VS4: Enterprise Integration Services | G76: Japan Platform Team 35775 | H76: Japan Platform Team 35775 | I76: Common Service Business Application | J76: N | K76: Yes | L76: JAVA; Other#ESQL | M76: N | N76: No | P76: MetLife Owned Application Code | Q76: 7.2083333 | R76: 2.9958333 | S76: 2.5208333 | T76: 12.725 | U76: 0.93778651 | V76: 6.3625 | W76: 6.3625 | X76: =IF(OR(ISNUMBER(SEARCH("COBOL",$L76)),ISNUMBER(SEARCH("Assembler",$L76)),ISNUMBER(SEARCH("ASM",$L76)),ISNUMBER(SEARCH("RPG",$L76)),ISNUMBER(SEARCH("EASYPLUS",$L76)),ISNUMBER(SEARCH("PL/I",$L76))),"Rule 1",IF($M76="Y","Rule 2",IF($N76="Yes","Rule 3","Rule 4"))) -> Rule 4 | Y76: =IF($X76="Rule 1","D",IF($X76="Rule 2","C",IF($X76="Rule 3","B","A"))) -> A | AA76: =IF($Z76="",$Y76,$Z76) -> A | AB76: =IFERROR(INDEX('Classification Rules'!$C$43:$C$46,MATCH($AA76,'Classification Rules'!$B$43:$B$46,0)),"") -> Language-locked | AC76: =IF($X76="Rule 1","Language: "&$L76,IF($X76="Rule 2","Priority Transfer Target = Y",IF($X76="Rule 3","Cloud Indicator = Yes ("&$O76&")","Cloud Indicator = No, not mainframe, not a transfer target"))) -> Cloud Indicator = No, not mainframe, not a transfer target | AD76: =IFERROR(INDEX('Classification Rules'!$D$13:$D$16,MATCH($AA76,'Classification Rules'!$B$13:$B$16,0)),"") -> On-premises and non-mainframe, so the constraint is not the technology — it is that the business context exists only in Japanese, in few heads. | AE76: =IFERROR(INDEX('Classification Rules'!$D$43:$D$46,MATCH($AA76,'Classification Rules'!$B$43:$B$46,0)),"") -> 0.304 | AF76: =IFERROR(INDEX('Classification Rules'!$E$43:$E$46,MATCH($AA76,'Classification Rules'!$B$43:$B$46,0)),"") -> 0.3394768 | AG76: =IFERROR(INDEX('Classification Rules'!$F$43:$F$46,MATCH($AA76,'Classification Rules'!$B$43:$B$46,0)),"") -> 0.15 | AH76: =IFERROR(INDEX('Classification Rules'!$G$43:$G$46,MATCH($AA76,'Classification Rules'!$B$43:$B$46,0)),"") -> 0.1395 | AI76: =IFERROR(INDEX('Classification Rules'!$I$43:$I$46,MATCH($AA76,'Classification Rules'!$B$43:$B$46,0)),"") -> 10-14 weeks per cluster | AJ76: =IFERROR(INDEX('Classification Rules'!$J$43:$J$46,MATCH($AA76,'Classification Rules'!$B$43:$B$46,0)),"") -> Fully sourced, onshore-weighted | AK76: =IFERROR(INDEX('Classification Rules'!$K$43:$K$46,MATCH($AA76,'Classification Rules'!$B$43:$B$46,0)),"") -> 0
A77: 73 | B77: 9994 | C77: WPMAUD-JPN | D77: Unknown Address Tracking System | E77: Storage and Preservation Related | F77: VS2: Digital Payments & Servicing | G77: Customer Service and Operations Systems Group 34965 | H77: Policy Servicing Team 34967 | I77: Core Business Application | J77: N | K77: No | L77: JAVA | M77: N | N77: Yes | O77: Platform as a Service (PaaS) | P77: Non-MetLife Owned Application Code (3rd party/COTS) | Q77: 0.8 | R77: 0.2 | S77: 0 | T77: 1.1729167 | U77: 0.42806394 | V77: 0.58645833 | W77: 0.58645833 | X77: =IF(OR(ISNUMBER(SEARCH("COBOL",$L77)),ISNUMBER(SEARCH("Assembler",$L77)),ISNUMBER(SEARCH("ASM",$L77)),ISNUMBER(SEARCH("RPG",$L77)),ISNUMBER(SEARCH("EASYPLUS",$L77)),ISNUMBER(SEARCH("PL/I",$L77))),"Rule 1",IF($M77="Y","Rule 2",IF($N77="Yes","Rule 3","Rule 4"))) -> Rule 3 | Y77: =IF($X77="Rule 1","D",IF($X77="Rule 2","C",IF($X77="Rule 3","B","A"))) -> B | AA77: =IF($Z77="",$Y77,$Z77) -> B | AB77: =IFERROR(INDEX('Classification Rules'!$C$43:$C$46,MATCH($AA77,'Classification Rules'!$B$43:$B$46,0)),"") -> Offshore-ready | AC77: =IF($X77="Rule 1","Language: "&$L77,IF($X77="Rule 2","Priority Transfer Target = Y",IF($X77="Rule 3","Cloud Indicator = Yes ("&$O77&")","Cloud Indicator = No, not mainframe, not a transfer target"))) -> Cloud Indicator = Yes (Platform as a Service (PaaS)) | AD77: =IFERROR(INDEX('Classification Rules'!$D$13:$D$16,MATCH($AA77,'Classification Rules'!$B$13:$B$16,0)),"") -> Cloud migration has already forced re-platforming, documentation and specifiability. Highest AI and offshore ceiling in the estate. | AE77: =IFERROR(INDEX('Classification Rules'!$D$43:$D$46,MATCH($AA77,'Classification Rules'!$B$43:$B$46,0)),"") -> 0.4825 | AF77: =IFERROR(INDEX('Classification Rules'!$E$43:$E$46,MATCH($AA77,'Classification Rules'!$B$43:$B$46,0)),"") -> 0.45402025 | AG77: =IFERROR(INDEX('Classification Rules'!$F$43:$F$46,MATCH($AA77,'Classification Rules'!$B$43:$B$46,0)),"") -> 0.78 | AH77: =IFERROR(INDEX('Classification Rules'!$G$43:$G$46,MATCH($AA77,'Classification Rules'!$B$43:$B$46,0)),"") -> 0.7254 | AI77: =IFERROR(INDEX('Classification Rules'!$I$43:$I$46,MATCH($AA77,'Classification Rules'!$B$43:$B$46,0)),"") -> 6-8 weeks per cluster | AJ77: =IFERROR(INDEX('Classification Rules'!$J$43:$J$46,MATCH($AA77,'Classification Rules'!$B$43:$B$46,0)),"") -> Fully sourced, moving to output units | AK77: =IFERROR(INDEX('Classification Rules'!$K$43:$K$46,MATCH($AA77,'Classification Rules'!$B$43:$B$46,0)),"") -> 0
A78: 74 | B78: 9995 | C78: WCMPXS-JPN | D78: ProductXpress | E78: Corporate Related | F78: VS5: Corporate Integration & Batch Services | G78: Core Insurance Systems Group 34956 | H78: Corporate Systems Team 34959 | I78: Infrastructure Application | J78: N | K78: Yes | L78: Other#Peculiar Language, Implemented in PX designer. | M78: N | N78: No | P78: MetLife Owned Application Code | Q78: 0.77916667 | R78: 0 | S78: 0 | T78: 0.77916667 | U78: 0.67914439 | V78: 0.38958333 | W78: 0.38958333 | X78: =IF(OR(ISNUMBER(SEARCH("COBOL",$L78)),ISNUMBER(SEARCH("Assembler",$L78)),ISNUMBER(SEARCH("ASM",$L78)),ISNUMBER(SEARCH("RPG",$L78)),ISNUMBER(SEARCH("EASYPLUS",$L78)),ISNUMBER(SEARCH("PL/I",$L78))),"Rule 1",IF($M78="Y","Rule 2",IF($N78="Yes","Rule 3","Rule 4"))) -> Rule 4 | Y78: =IF($X78="Rule 1","D",IF($X78="Rule 2","C",IF($X78="Rule 3","B","A"))) -> A | AA78: =IF($Z78="",$Y78,$Z78) -> A | AB78: =IFERROR(INDEX('Classification Rules'!$C$43:$C$46,MATCH($AA78,'Classification Rules'!$B$43:$B$46,0)),"") -> Language-locked | AC78: =IF($X78="Rule 1","Language: "&$L78,IF($X78="Rule 2","Priority Transfer Target = Y",IF($X78="Rule 3","Cloud Indicator = Yes ("&$O78&")","Cloud Indicator = No, not mainframe, not a transfer target"))) -> Cloud Indicator = No, not mainframe, not a transfer target | AD78: =IFERROR(INDEX('Classification Rules'!$D$13:$D$16,MATCH($AA78,'Classification Rules'!$B$13:$B$16,0)),"") -> On-premises and non-mainframe, so the constraint is not the technology — it is that the business context exists only in Japanese, in few heads. | AE78: =IFERROR(INDEX('Classification Rules'!$D$43:$D$46,MATCH($AA78,'Classification Rules'!$B$43:$B$46,0)),"") -> 0.304 | AF78: =IFERROR(INDEX('Classification Rules'!$E$43:$E$46,MATCH($AA78,'Classification Rules'!$B$43:$B$46,0)),"") -> 0.3394768 | AG78: =IFERROR(INDEX('Classification Rules'!$F$43:$F$46,MATCH($AA78,'Classification Rules'!$B$43:$B$46,0)),"") -> 0.15 | AH78: =IFERROR(INDEX('Classification Rules'!$G$43:$G$46,MATCH($AA78,'Classification Rules'!$B$43:$B$46,0)),"") -> 0.1395 | AI78: =IFERROR(INDEX('Classification Rules'!$I$43:$I$46,MATCH($AA78,'Classification Rules'!$B$43:$B$46,0)),"") -> 10-14 weeks per cluster | AJ78: =IFERROR(INDEX('Classification Rules'!$J$43:$J$46,MATCH($AA78,'Classification Rules'!$B$43:$B$46,0)),"") -> Fully sourced, onshore-weighted | AK78: =IFERROR(INDEX('Classification Rules'!$K$43:$K$46,MATCH($AA78,'Classification Rules'!$B$43:$B$46,0)),"") -> 0
A79: 75 | B79: 9996 | C79: WUIURE-JPN | D79: Pre-Underwriting | E79: New Contract Related | F79: VS3: Medical Underwriting | G79: Customer Service and Operations Systems Group 34965 | H79: New Business Team 34966 | I79: Core Business Application | J79: N | K79: Yes | L79: JAVA | M79: N | N79: No | P79: MetLife Owned Application Code | Q79: 0.22625 | R79: 0 | S79: 0 | T79: 0.22625 | U79: 0.33701657 | V79: 0.113125 | W79: 0.113125 | X79: =IF(OR(ISNUMBER(SEARCH("COBOL",$L79)),ISNUMBER(SEARCH("Assembler",$L79)),ISNUMBER(SEARCH("ASM",$L79)),ISNUMBER(SEARCH("RPG",$L79)),ISNUMBER(SEARCH("EASYPLUS",$L79)),ISNUMBER(SEARCH("PL/I",$L79))),"Rule 1",IF($M79="Y","Rule 2",IF($N79="Yes","Rule 3","Rule 4"))) -> Rule 4 | Y79: =IF($X79="Rule 1","D",IF($X79="Rule 2","C",IF($X79="Rule 3","B","A"))) -> A | AA79: =IF($Z79="",$Y79,$Z79) -> A | AB79: =IFERROR(INDEX('Classification Rules'!$C$43:$C$46,MATCH($AA79,'Classification Rules'!$B$43:$B$46,0)),"") -> Language-locked | AC79: =IF($X79="Rule 1","Language: "&$L79,IF($X79="Rule 2","Priority Transfer Target = Y",IF($X79="Rule 3","Cloud Indicator = Yes ("&$O79&")","Cloud Indicator = No, not mainframe, not a transfer target"))) -> Cloud Indicator = No, not mainframe, not a transfer target | AD79: =IFERROR(INDEX('Classification Rules'!$D$13:$D$16,MATCH($AA79,'Classification Rules'!$B$13:$B$16,0)),"") -> On-premises and non-mainframe, so the constraint is not the technology — it is that the business context exists only in Japanese, in few heads. | AE79: =IFERROR(INDEX('Classification Rules'!$D$43:$D$46,MATCH($AA79,'Classification Rules'!$B$43:$B$46,0)),"") -> 0.304 | AF79: =IFERROR(INDEX('Classification Rules'!$E$43:$E$46,MATCH($AA79,'Classification Rules'!$B$43:$B$46,0)),"") -> 0.3394768 | AG79: =IFERROR(INDEX('Classification Rules'!$F$43:$F$46,MATCH($AA79,'Classification Rules'!$B$43:$B$46,0)),"") -> 0.15 | AH79: =IFERROR(INDEX('Classification Rules'!$G$43:$G$46,MATCH($AA79,'Classification Rules'!$B$43:$B$46,0)),"") -> 0.1395 | AI79: =IFERROR(INDEX('Classification Rules'!$I$43:$I$46,MATCH($AA79,'Classification Rules'!$B$43:$B$46,0)),"") -> 10-14 weeks per cluster | AJ79: =IFERROR(INDEX('Classification Rules'!$J$43:$J$46,MATCH($AA79,'Classification Rules'!$B$43:$B$46,0)),"") -> Fully sourced, onshore-weighted | AK79: =IFERROR(INDEX('Classification Rules'!$K$43:$K$46,MATCH($AA79,'Classification Rules'!$B$43:$B$46,0)),"") -> 0
A80: 76 | B80: 9999 | C80: LINC MF-JPN | D80: LINC | E80: contract management | F80: VS5: New Business, Underwriting & Interfaces | G80: Core Insurance Systems Group 34956 | H80: Policy Admin Systems Team 34957 | I80: Core Business Application | J80: Y | K80: Yes | L80: COBOL, MU(EASYPLUS), Assembler, JCL | M80: N | N80: No | P80: MetLife Owned Application Code | Q80: 1.02875 | R80: 0 | S80: 0 | T80: 1.02875 | U80: 0.12920211 | V80: 0.514375 | W80: 0.514375 | X80: =IF(OR(ISNUMBER(SEARCH("COBOL",$L80)),ISNUMBER(SEARCH("Assembler",$L80)),ISNUMBER(SEARCH("ASM",$L80)),ISNUMBER(SEARCH("RPG",$L80)),ISNUMBER(SEARCH("EASYPLUS",$L80)),ISNUMBER(SEARCH("PL/I",$L80))),"Rule 1",IF($M80="Y","Rule 2",IF($N80="Yes","Rule 3","Rule 4"))) -> Rule 1 | Y80: =IF($X80="Rule 1","D",IF($X80="Rule 2","C",IF($X80="Rule 3","B","A"))) -> D | AA80: =IF($Z80="",$Y80,$Z80) -> D | AB80: =IFERROR(INDEX('Classification Rules'!$C$43:$C$46,MATCH($AA80,'Classification Rules'!$B$43:$B$46,0)),"") -> Legacy-coupled core | AC80: =IF($X80="Rule 1","Language: "&$L80,IF($X80="Rule 2","Priority Transfer Target = Y",IF($X80="Rule 3","Cloud Indicator = Yes ("&$O80&")","Cloud Indicator = No, not mainframe, not a transfer target"))) -> Language: COBOL, MU(EASYPLUS), Assembler, JCL | AD80: =IFERROR(INDEX('Classification Rules'!$D$13:$D$16,MATCH($AA80,'Classification Rules'!$B$13:$B$16,0)),"") -> Rules hard-coded across modules and design truth is not written down. AI does comprehension here, not generation. | AE80: =IFERROR(INDEX('Classification Rules'!$D$43:$D$46,MATCH($AA80,'Classification Rules'!$B$43:$B$46,0)),"") -> 0.295 | AF80: =IFERROR(INDEX('Classification Rules'!$E$43:$E$46,MATCH($AA80,'Classification Rules'!$B$43:$B$46,0)),"") -> 0.3337015 | AG80: =IFERROR(INDEX('Classification Rules'!$F$43:$F$46,MATCH($AA80,'Classification Rules'!$B$43:$B$46,0)),"") -> 0.58 | AH80: =IFERROR(INDEX('Classification Rules'!$G$43:$G$46,MATCH($AA80,'Classification Rules'!$B$43:$B$46,0)),"") -> 0.5394 | AI80: =IFERROR(INDEX('Classification Rules'!$I$43:$I$46,MATCH($AA80,'Classification Rules'!$B$43:$B$46,0)),"") -> 14-20 weeks per cluster | AJ80: =IFERROR(INDEX('Classification Rules'!$J$43:$J$46,MATCH($AA80,'Classification Rules'!$B$43:$B$46,0)),"") -> Fully sourced, MetLife SMEs paired | AK80: =IFERROR(INDEX('Classification Rules'!$K$43:$K$46,MATCH($AA80,'Classification Rules'!$B$43:$B$46,0)),"") -> 0
A81: 77 | B81: 10001 | C81: A06TOG-JPN | D81: Group Policy Management System | E81: Corporate Related | F81: VS6: Legacy Corporate Platforms | G81: Core Insurance Systems Group 34956 | H81: Corporate Systems Team 34959 | I81: Core Business Application | J81: Y | K81: Yes | L81: Other#RPG; Cobol | M81: N | N81: No | P81: MetLife Owned Application Code | Q81: 2.7291667 | R81: 3.025 | S81: 0 | T81: 5.7541667 | U81: 0.34540188 | V81: 2.8770833 | W81: 2.8770833 | X81: =IF(OR(ISNUMBER(SEARCH("COBOL",$L81)),ISNUMBER(SEARCH("Assembler",$L81)),ISNUMBER(SEARCH("ASM",$L81)),ISNUMBER(SEARCH("RPG",$L81)),ISNUMBER(SEARCH("EASYPLUS",$L81)),ISNUMBER(SEARCH("PL/I",$L81))),"Rule 1",IF($M81="Y","Rule 2",IF($N81="Yes","Rule 3","Rule 4"))) -> Rule 1 | Y81: =IF($X81="Rule 1","D",IF($X81="Rule 2","C",IF($X81="Rule 3","B","A"))) -> D | AA81: =IF($Z81="",$Y81,$Z81) -> D | AB81: =IFERROR(INDEX('Classification Rules'!$C$43:$C$46,MATCH($AA81,'Classification Rules'!$B$43:$B$46,0)),"") -> Legacy-coupled core | AC81: =IF($X81="Rule 1","Language: "&$L81,IF($X81="Rule 2","Priority Transfer Target = Y",IF($X81="Rule 3","Cloud Indicator = Yes ("&$O81&")","Cloud Indicator = No, not mainframe, not a transfer target"))) -> Language: Other#RPG; Cobol | AD81: =IFERROR(INDEX('Classification Rules'!$D$13:$D$16,MATCH($AA81,'Classification Rules'!$B$13:$B$16,0)),"") -> Rules hard-coded across modules and design truth is not written down. AI does comprehension here, not generation. | AE81: =IFERROR(INDEX('Classification Rules'!$D$43:$D$46,MATCH($AA81,'Classification Rules'!$B$43:$B$46,0)),"") -> 0.295 | AF81: =IFERROR(INDEX('Classification Rules'!$E$43:$E$46,MATCH($AA81,'Classification Rules'!$B$43:$B$46,0)),"") -> 0.3337015 | AG81: =IFERROR(INDEX('Classification Rules'!$F$43:$F$46,MATCH($AA81,'Classification Rules'!$B$43:$B$46,0)),"") -> 0.58 | AH81: =IFERROR(INDEX('Classification Rules'!$G$43:$G$46,MATCH($AA81,'Classification Rules'!$B$43:$B$46,0)),"") -> 0.5394 | AI81: =IFERROR(INDEX('Classification Rules'!$I$43:$I$46,MATCH($AA81,'Classification Rules'!$B$43:$B$46,0)),"") -> 14-20 weeks per cluster | AJ81: =IFERROR(INDEX('Classification Rules'!$J$43:$J$46,MATCH($AA81,'Classification Rules'!$B$43:$B$46,0)),"") -> Fully sourced, MetLife SMEs paired | AK81: =IFERROR(INDEX('Classification Rules'!$K$43:$K$46,MATCH($AA81,'Classification Rules'!$B$43:$B$46,0)),"") -> 0
A82: 78 | B82: 10032 | C82: W06TGR-JPN | D82: Group Policy Inquiry System for Intranet | E82: Corporate Related | F82: VS4: Corporate Workflow & Employee Services | G82: Core Insurance Systems Group 34956 | H82: Corporate Systems Team 34959 | I82: Core Business Application | J82: Y | K82: Yes | L82: VB.NET; JAVA | M82: N | N82: No | P82: MetLife Owned Application Code | Q82: 1.8583333 | R82: 0.94166667 | S82: 0 | T82: 2.8 | U82: 0.26934524 | V82: 1.4 | W82: 1.4 | X82: =IF(OR(ISNUMBER(SEARCH("COBOL",$L82)),ISNUMBER(SEARCH("Assembler",$L82)),ISNUMBER(SEARCH("ASM",$L82)),ISNUMBER(SEARCH("RPG",$L82)),ISNUMBER(SEARCH("EASYPLUS",$L82)),ISNUMBER(SEARCH("PL/I",$L82))),"Rule 1",IF($M82="Y","Rule 2",IF($N82="Yes","Rule 3","Rule 4"))) -> Rule 4 | Y82: =IF($X82="Rule 1","D",IF($X82="Rule 2","C",IF($X82="Rule 3","B","A"))) -> A | AA82: =IF($Z82="",$Y82,$Z82) -> A | AB82: =IFERROR(INDEX('Classification Rules'!$C$43:$C$46,MATCH($AA82,'Classification Rules'!$B$43:$B$46,0)),"") -> Language-locked | AC82: =IF($X82="Rule 1","Language: "&$L82,IF($X82="Rule 2","Priority Transfer Target = Y",IF($X82="Rule 3","Cloud Indicator = Yes ("&$O82&")","Cloud Indicator = No, not mainframe, not a transfer target"))) -> Cloud Indicator = No, not mainframe, not a transfer target | AD82: =IFERROR(INDEX('Classification Rules'!$D$13:$D$16,MATCH($AA82,'Classification Rules'!$B$13:$B$16,0)),"") -> On-premises and non-mainframe, so the constraint is not the technology — it is that the business context exists only in Japanese, in few heads. | AE82: =IFERROR(INDEX('Classification Rules'!$D$43:$D$46,MATCH($AA82,'Classification Rules'!$B$43:$B$46,0)),"") -> 0.304 | AF82: =IFERROR(INDEX('Classification Rules'!$E$43:$E$46,MATCH($AA82,'Classification Rules'!$B$43:$B$46,0)),"") -> 0.3394768 | AG82: =IFERROR(INDEX('Classification Rules'!$F$43:$F$46,MATCH($AA82,'Classification Rules'!$B$43:$B$46,0)),"") -> 0.15 | AH82: =IFERROR(INDEX('Classification Rules'!$G$43:$G$46,MATCH($AA82,'Classification Rules'!$B$43:$B$46,0)),"") -> 0.1395 | AI82: =IFERROR(INDEX('Classification Rules'!$I$43:$I$46,MATCH($AA82,'Classification Rules'!$B$43:$B$46,0)),"") -> 10-14 weeks per cluster | AJ82: =IFERROR(INDEX('Classification Rules'!$J$43:$J$46,MATCH($AA82,'Classification Rules'!$B$43:$B$46,0)),"") -> Fully sourced, onshore-weighted | AK82: =IFERROR(INDEX('Classification Rules'!$K$43:$K$46,MATCH($AA82,'Classification Rules'!$B$43:$B$46,0)),"") -> 0
A83: 79 | B83: 11004 | C83: WAAICM-JPN | D83: ICM | E83: Fee Management | F83: VS1: Commission Processing & Management | G83: Core Insurance Systems Group 34956 | H83: Commission Systems Team 34958 | I83: Core Business Application | J83: N | K83: Yes | L83: JAVA; C#; Other#ETL JAVA(ADJP) SQL | M83: N | N83: Yes | O83: Software as a Service (SaaS) | P83: MetLife Owned Application Code | Q83: 21.506125 | R83: 7.7291667 | S83: 0 | T83: 29.235292 | U83: 0.83096913 | V83: 14.617646 | W83: 14.617646 | X83: =IF(OR(ISNUMBER(SEARCH("COBOL",$L83)),ISNUMBER(SEARCH("Assembler",$L83)),ISNUMBER(SEARCH("ASM",$L83)),ISNUMBER(SEARCH("RPG",$L83)),ISNUMBER(SEARCH("EASYPLUS",$L83)),ISNUMBER(SEARCH("PL/I",$L83))),"Rule 1",IF($M83="Y","Rule 2",IF($N83="Yes","Rule 3","Rule 4"))) -> Rule 3 | Y83: =IF($X83="Rule 1","D",IF($X83="Rule 2","C",IF($X83="Rule 3","B","A"))) -> B | AA83: =IF($Z83="",$Y83,$Z83) -> B | AB83: =IFERROR(INDEX('Classification Rules'!$C$43:$C$46,MATCH($AA83,'Classification Rules'!$B$43:$B$46,0)),"") -> Offshore-ready | AC83: =IF($X83="Rule 1","Language: "&$L83,IF($X83="Rule 2","Priority Transfer Target = Y",IF($X83="Rule 3","Cloud Indicator = Yes ("&$O83&")","Cloud Indicator = No, not mainframe, not a transfer target"))) -> Cloud Indicator = Yes (Software as a Service (SaaS)) | AD83: =IFERROR(INDEX('Classification Rules'!$D$13:$D$16,MATCH($AA83,'Classification Rules'!$B$13:$B$16,0)),"") -> Cloud migration has already forced re-platforming, documentation and specifiability. Highest AI and offshore ceiling in the estate. | AE83: =IFERROR(INDEX('Classification Rules'!$D$43:$D$46,MATCH($AA83,'Classification Rules'!$B$43:$B$46,0)),"") -> 0.4825 | AF83: =IFERROR(INDEX('Classification Rules'!$E$43:$E$46,MATCH($AA83,'Classification Rules'!$B$43:$B$46,0)),"") -> 0.45402025 | AG83: =IFERROR(INDEX('Classification Rules'!$F$43:$F$46,MATCH($AA83,'Classification Rules'!$B$43:$B$46,0)),"") -> 0.78 | AH83: =IFERROR(INDEX('Classification Rules'!$G$43:$G$46,MATCH($AA83,'Classification Rules'!$B$43:$B$46,0)),"") -> 0.7254 | AI83: =IFERROR(INDEX('Classification Rules'!$I$43:$I$46,MATCH($AA83,'Classification Rules'!$B$43:$B$46,0)),"") -> 6-8 weeks per cluster | AJ83: =IFERROR(INDEX('Classification Rules'!$J$43:$J$46,MATCH($AA83,'Classification Rules'!$B$43:$B$46,0)),"") -> Fully sourced, moving to output units | AK83: =IFERROR(INDEX('Classification Rules'!$K$43:$K$46,MATCH($AA83,'Classification Rules'!$B$43:$B$46,0)),"") -> 0
A84: 80 | B84: 11005 | C84: WAACPS-JPN | D84: Commission and Performance System | E84: Corporate Related | F84: VS4: Corporate Workflow & Employee Services | G84: Core Insurance Systems Group 34956 | H84: Corporate Systems Team 34959 | I84: Core Business Application | J84: N | K84: Yes | L84: JAVA | M84: N | N84: Yes | O84: Platform as a Service (PaaS) | P84: MetLife Owned Application Code | Q84: 0.3625 | R84: 0.041666667 | S84: 0.5 | T84: 0.90416667 | U84: 0.44700461 | V84: 0.45208333 | W84: 0.45208333 | X84: =IF(OR(ISNUMBER(SEARCH("COBOL",$L84)),ISNUMBER(SEARCH("Assembler",$L84)),ISNUMBER(SEARCH("ASM",$L84)),ISNUMBER(SEARCH("RPG",$L84)),ISNUMBER(SEARCH("EASYPLUS",$L84)),ISNUMBER(SEARCH("PL/I",$L84))),"Rule 1",IF($M84="Y","Rule 2",IF($N84="Yes","Rule 3","Rule 4"))) -> Rule 3 | Y84: =IF($X84="Rule 1","D",IF($X84="Rule 2","C",IF($X84="Rule 3","B","A"))) -> B | AA84: =IF($Z84="",$Y84,$Z84) -> B | AB84: =IFERROR(INDEX('Classification Rules'!$C$43:$C$46,MATCH($AA84,'Classification Rules'!$B$43:$B$46,0)),"") -> Offshore-ready | AC84: =IF($X84="Rule 1","Language: "&$L84,IF($X84="Rule 2","Priority Transfer Target = Y",IF($X84="Rule 3","Cloud Indicator = Yes ("&$O84&")","Cloud Indicator = No, not mainframe, not a transfer target"))) -> Cloud Indicator = Yes (Platform as a Service (PaaS)) | AD84: =IFERROR(INDEX('Classification Rules'!$D$13:$D$16,MATCH($AA84,'Classification Rules'!$B$13:$B$16,0)),"") -> Cloud migration has already forced re-platforming, documentation and specifiability. Highest AI and offshore ceiling in the estate. | AE84: =IFERROR(INDEX('Classification Rules'!$D$43:$D$46,MATCH($AA84,'Classification Rules'!$B$43:$B$46,0)),"") -> 0.4825 | AF84: =IFERROR(INDEX('Classification Rules'!$E$43:$E$46,MATCH($AA84,'Classification Rules'!$B$43:$B$46,0)),"") -> 0.45402025 | AG84: =IFERROR(INDEX('Classification Rules'!$F$43:$F$46,MATCH($AA84,'Classification Rules'!$B$43:$B$46,0)),"") -> 0.78 | AH84: =IFERROR(INDEX('Classification Rules'!$G$43:$G$46,MATCH($AA84,'Classification Rules'!$B$43:$B$46,0)),"") -> 0.7254 | AI84: =IFERROR(INDEX('Classification Rules'!$I$43:$I$46,MATCH($AA84,'Classification Rules'!$B$43:$B$46,0)),"") -> 6-8 weeks per cluster | AJ84: =IFERROR(INDEX('Classification Rules'!$J$43:$J$46,MATCH($AA84,'Classification Rules'!$B$43:$B$46,0)),"") -> Fully sourced, moving to output units | AK84: =IFERROR(INDEX('Classification Rules'!$K$43:$K$46,MATCH($AA84,'Classification Rules'!$B$43:$B$46,0)),"") -> 0
A85: 81 | B85: 11007 | C85: OMSIKN-JPN | D85: Conservation contract transferring system | E85: Corporate Related | F85: VS4: Corporate Workflow & Employee Services | G85: Core Insurance Systems Group 34956 | H85: Corporate Systems Team 34959 | I85: Core Business Application | J85: N | K85: Yes | L85: JAVA | M85: N | N85: No | P85: MetLife Owned Application Code | Q85: 0.23491667 | R85: 0.072916667 | S85: 0 | T85: 0.30783333 | U85: 0.95939361 | V85: 0.15391667 | W85: 0.15391667 | X85: =IF(OR(ISNUMBER(SEARCH("COBOL",$L85)),ISNUMBER(SEARCH("Assembler",$L85)),ISNUMBER(SEARCH("ASM",$L85)),ISNUMBER(SEARCH("RPG",$L85)),ISNUMBER(SEARCH("EASYPLUS",$L85)),ISNUMBER(SEARCH("PL/I",$L85))),"Rule 1",IF($M85="Y","Rule 2",IF($N85="Yes","Rule 3","Rule 4"))) -> Rule 4 | Y85: =IF($X85="Rule 1","D",IF($X85="Rule 2","C",IF($X85="Rule 3","B","A"))) -> A | AA85: =IF($Z85="",$Y85,$Z85) -> A | AB85: =IFERROR(INDEX('Classification Rules'!$C$43:$C$46,MATCH($AA85,'Classification Rules'!$B$43:$B$46,0)),"") -> Language-locked | AC85: =IF($X85="Rule 1","Language: "&$L85,IF($X85="Rule 2","Priority Transfer Target = Y",IF($X85="Rule 3","Cloud Indicator = Yes ("&$O85&")","Cloud Indicator = No, not mainframe, not a transfer target"))) -> Cloud Indicator = No, not mainframe, not a transfer target | AD85: =IFERROR(INDEX('Classification Rules'!$D$13:$D$16,MATCH($AA85,'Classification Rules'!$B$13:$B$16,0)),"") -> On-premises and non-mainframe, so the constraint is not the technology — it is that the business context exists only in Japanese, in few heads. | AE85: =IFERROR(INDEX('Classification Rules'!$D$43:$D$46,MATCH($AA85,'Classification Rules'!$B$43:$B$46,0)),"") -> 0.304 | AF85: =IFERROR(INDEX('Classification Rules'!$E$43:$E$46,MATCH($AA85,'Classification Rules'!$B$43:$B$46,0)),"") -> 0.3394768 | AG85: =IFERROR(INDEX('Classification Rules'!$F$43:$F$46,MATCH($AA85,'Classification Rules'!$B$43:$B$46,0)),"") -> 0.15 | AH85: =IFERROR(INDEX('Classification Rules'!$G$43:$G$46,MATCH($AA85,'Classification Rules'!$B$43:$B$46,0)),"") -> 0.1395 | AI85: =IFERROR(INDEX('Classification Rules'!$I$43:$I$46,MATCH($AA85,'Classification Rules'!$B$43:$B$46,0)),"") -> 10-14 weeks per cluster | AJ85: =IFERROR(INDEX('Classification Rules'!$J$43:$J$46,MATCH($AA85,'Classification Rules'!$B$43:$B$46,0)),"") -> Fully sourced, onshore-weighted | AK85: =IFERROR(INDEX('Classification Rules'!$K$43:$K$46,MATCH($AA85,'Classification Rules'!$B$43:$B$46,0)),"") -> 0
A86: 82 | B86: 11008 | C86: OMSTAT-JPN | D86: Conservation contract allowance system | E86: Marketing/Direct Business Related | F86: VS3: Campaign Processing & Batch Services | G86: Customer and Channel Engineering 34961 | H86: Marketing and Leads Team 34964 | I86: Core Business Application | J86: N | K86: Yes | L86: JAVA | M86: N | N86: No | P86: MetLife Owned Application Code | Q86: 0.13541667 | R86: 0.016666667 | S86: 0 | T86: 0.15208333 | U86: 0.52054795 | V86: 0.076041667 | W86: 0.076041667 | X86: =IF(OR(ISNUMBER(SEARCH("COBOL",$L86)),ISNUMBER(SEARCH("Assembler",$L86)),ISNUMBER(SEARCH("ASM",$L86)),ISNUMBER(SEARCH("RPG",$L86)),ISNUMBER(SEARCH("EASYPLUS",$L86)),ISNUMBER(SEARCH("PL/I",$L86))),"Rule 1",IF($M86="Y","Rule 2",IF($N86="Yes","Rule 3","Rule 4"))) -> Rule 4 | Y86: =IF($X86="Rule 1","D",IF($X86="Rule 2","C",IF($X86="Rule 3","B","A"))) -> A | AA86: =IF($Z86="",$Y86,$Z86) -> A | AB86: =IFERROR(INDEX('Classification Rules'!$C$43:$C$46,MATCH($AA86,'Classification Rules'!$B$43:$B$46,0)),"") -> Language-locked | AC86: =IF($X86="Rule 1","Language: "&$L86,IF($X86="Rule 2","Priority Transfer Target = Y",IF($X86="Rule 3","Cloud Indicator = Yes ("&$O86&")","Cloud Indicator = No, not mainframe, not a transfer target"))) -> Cloud Indicator = No, not mainframe, not a transfer target | AD86: =IFERROR(INDEX('Classification Rules'!$D$13:$D$16,MATCH($AA86,'Classification Rules'!$B$13:$B$16,0)),"") -> On-premises and non-mainframe, so the constraint is not the technology — it is that the business context exists only in Japanese, in few heads. | AE86: =IFERROR(INDEX('Classification Rules'!$D$43:$D$46,MATCH($AA86,'Classification Rules'!$B$43:$B$46,0)),"") -> 0.304 | AF86: =IFERROR(INDEX('Classification Rules'!$E$43:$E$46,MATCH($AA86,'Classification Rules'!$B$43:$B$46,0)),"") -> 0.3394768 | AG86: =IFERROR(INDEX('Classification Rules'!$F$43:$F$46,MATCH($AA86,'Classification Rules'!$B$43:$B$46,0)),"") -> 0.15 | AH86: =IFERROR(INDEX('Classification Rules'!$G$43:$G$46,MATCH($AA86,'Classification Rules'!$B$43:$B$46,0)),"") -> 0.1395 | AI86: =IFERROR(INDEX('Classification Rules'!$I$43:$I$46,MATCH($AA86,'Classification Rules'!$B$43:$B$46,0)),"") -> 10-14 weeks per cluster | AJ86: =IFERROR(INDEX('Classification Rules'!$J$43:$J$46,MATCH($AA86,'Classification Rules'!$B$43:$B$46,0)),"") -> Fully sourced, onshore-weighted | AK86: =IFERROR(INDEX('Classification Rules'!$K$43:$K$46,MATCH($AA86,'Classification Rules'!$B$43:$B$46,0)),"") -> 0
A87: 83 | B87: 11010 | C87: ZGLEDQ-JPN | D87: FATCA Oracle EDQ | E87: Corporate Related | F87: VS1: Finance & Accounting Services | G87: Core Insurance Systems Group 34956 | H87: Corporate Systems Team 34959 | I87: Core Business Application | J87: N | K87: Yes | L87: JAVA; C # | M87: N | N87: Yes | O87: Platform as a Service (PaaS) | P87: MetLife Owned Application Code | Q87: 1.2583333 | R87: 0.029166667 | S87: 0.5 | T87: 1.7875 | U87: 0.55710956 | V87: 0.89375 | W87: 0.89375 | X87: =IF(OR(ISNUMBER(SEARCH("COBOL",$L87)),ISNUMBER(SEARCH("Assembler",$L87)),ISNUMBER(SEARCH("ASM",$L87)),ISNUMBER(SEARCH("RPG",$L87)),ISNUMBER(SEARCH("EASYPLUS",$L87)),ISNUMBER(SEARCH("PL/I",$L87))),"Rule 1",IF($M87="Y","Rule 2",IF($N87="Yes","Rule 3","Rule 4"))) -> Rule 3 | Y87: =IF($X87="Rule 1","D",IF($X87="Rule 2","C",IF($X87="Rule 3","B","A"))) -> B | AA87: =IF($Z87="",$Y87,$Z87) -> B | AB87: =IFERROR(INDEX('Classification Rules'!$C$43:$C$46,MATCH($AA87,'Classification Rules'!$B$43:$B$46,0)),"") -> Offshore-ready | AC87: =IF($X87="Rule 1","Language: "&$L87,IF($X87="Rule 2","Priority Transfer Target = Y",IF($X87="Rule 3","Cloud Indicator = Yes ("&$O87&")","Cloud Indicator = No, not mainframe, not a transfer target"))) -> Cloud Indicator = Yes (Platform as a Service (PaaS)) | AD87: =IFERROR(INDEX('Classification Rules'!$D$13:$D$16,MATCH($AA87,'Classification Rules'!$B$13:$B$16,0)),"") -> Cloud migration has already forced re-platforming, documentation and specifiability. Highest AI and offshore ceiling in the estate. | AE87: =IFERROR(INDEX('Classification Rules'!$D$43:$D$46,MATCH($AA87,'Classification Rules'!$B$43:$B$46,0)),"") -> 0.4825 | AF87: =IFERROR(INDEX('Classification Rules'!$E$43:$E$46,MATCH($AA87,'Classification Rules'!$B$43:$B$46,0)),"") -> 0.45402025 | AG87: =IFERROR(INDEX('Classification Rules'!$F$43:$F$46,MATCH($AA87,'Classification Rules'!$B$43:$B$46,0)),"") -> 0.78 | AH87: =IFERROR(INDEX('Classification Rules'!$G$43:$G$46,MATCH($AA87,'Classification Rules'!$B$43:$B$46,0)),"") -> 0.7254 | AI87: =IFERROR(INDEX('Classification Rules'!$I$43:$I$46,MATCH($AA87,'Classification Rules'!$B$43:$B$46,0)),"") -> 6-8 weeks per cluster | AJ87: =IFERROR(INDEX('Classification Rules'!$J$43:$J$46,MATCH($AA87,'Classification Rules'!$B$43:$B$46,0)),"") -> Fully sourced, moving to output units | AK87: =IFERROR(INDEX('Classification Rules'!$K$43:$K$46,MATCH($AA87,'Classification Rules'!$B$43:$B$46,0)),"") -> 0
A88: 84 | B88: 11011 | C88: WGLWLF-JPN | D88: Watch List Filtering system | E88: Corporate Related | F88: VS3: Risk, Compliance & Governance | G88: Core Insurance Systems Group 34956 | H88: Corporate Systems Team 34959 | I88: Core Business Application | J88: N | K88: Yes | L88: JAVA | M88: N | N88: No | P88: MetLife Owned Application Code | Q88: 6.0791667 | R88: 1.0708333 | S88: 0 | T88: 7.15 | U88: 0.90384615 | V88: 3.575 | W88: 3.575 | X88: =IF(OR(ISNUMBER(SEARCH("COBOL",$L88)),ISNUMBER(SEARCH("Assembler",$L88)),ISNUMBER(SEARCH("ASM",$L88)),ISNUMBER(SEARCH("RPG",$L88)),ISNUMBER(SEARCH("EASYPLUS",$L88)),ISNUMBER(SEARCH("PL/I",$L88))),"Rule 1",IF($M88="Y","Rule 2",IF($N88="Yes","Rule 3","Rule 4"))) -> Rule 4 | Y88: =IF($X88="Rule 1","D",IF($X88="Rule 2","C",IF($X88="Rule 3","B","A"))) -> A | AA88: =IF($Z88="",$Y88,$Z88) -> A | AB88: =IFERROR(INDEX('Classification Rules'!$C$43:$C$46,MATCH($AA88,'Classification Rules'!$B$43:$B$46,0)),"") -> Language-locked | AC88: =IF($X88="Rule 1","Language: "&$L88,IF($X88="Rule 2","Priority Transfer Target = Y",IF($X88="Rule 3","Cloud Indicator = Yes ("&$O88&")","Cloud Indicator = No, not mainframe, not a transfer target"))) -> Cloud Indicator = No, not mainframe, not a transfer target | AD88: =IFERROR(INDEX('Classification Rules'!$D$13:$D$16,MATCH($AA88,'Classification Rules'!$B$13:$B$16,0)),"") -> On-premises and non-mainframe, so the constraint is not the technology — it is that the business context exists only in Japanese, in few heads. | AE88: =IFERROR(INDEX('Classification Rules'!$D$43:$D$46,MATCH($AA88,'Classification Rules'!$B$43:$B$46,0)),"") -> 0.304 | AF88: =IFERROR(INDEX('Classification Rules'!$E$43:$E$46,MATCH($AA88,'Classification Rules'!$B$43:$B$46,0)),"") -> 0.3394768 | AG88: =IFERROR(INDEX('Classification Rules'!$F$43:$F$46,MATCH($AA88,'Classification Rules'!$B$43:$B$46,0)),"") -> 0.15 | AH88: =IFERROR(INDEX('Classification Rules'!$G$43:$G$46,MATCH($AA88,'Classification Rules'!$B$43:$B$46,0)),"") -> 0.1395 | AI88: =IFERROR(INDEX('Classification Rules'!$I$43:$I$46,MATCH($AA88,'Classification Rules'!$B$43:$B$46,0)),"") -> 10-14 weeks per cluster | AJ88: =IFERROR(INDEX('Classification Rules'!$J$43:$J$46,MATCH($AA88,'Classification Rules'!$B$43:$B$46,0)),"") -> Fully sourced, onshore-weighted | AK88: =IFERROR(INDEX('Classification Rules'!$K$43:$K$46,MATCH($AA88,'Classification Rules'!$B$43:$B$46,0)),"") -> 0
A89: 85 | B89: 11012 | C89: WZZMNB-JPN | D89: My number management system | E89: Insurance Claims and Benefits Payment Related | F89: VS3: Claims Support Services | G89: Customer Service and Operations Systems Group 34965 | H89: Claims Team 34968 | I89: Core Business Application | J89: N | K89: Yes | L89: JAVA | M89: N | N89: No | P89: MetLife Owned Application Code | Q89: 1.6523333 | R89: 0.29166667 | S89: 0 | T89: 1.944 | U89: 0.83217593 | V89: 0.972 | W89: 0.972 | X89: =IF(OR(ISNUMBER(SEARCH("COBOL",$L89)),ISNUMBER(SEARCH("Assembler",$L89)),ISNUMBER(SEARCH("ASM",$L89)),ISNUMBER(SEARCH("RPG",$L89)),ISNUMBER(SEARCH("EASYPLUS",$L89)),ISNUMBER(SEARCH("PL/I",$L89))),"Rule 1",IF($M89="Y","Rule 2",IF($N89="Yes","Rule 3","Rule 4"))) -> Rule 4 | Y89: =IF($X89="Rule 1","D",IF($X89="Rule 2","C",IF($X89="Rule 3","B","A"))) -> A | AA89: =IF($Z89="",$Y89,$Z89) -> A | AB89: =IFERROR(INDEX('Classification Rules'!$C$43:$C$46,MATCH($AA89,'Classification Rules'!$B$43:$B$46,0)),"") -> Language-locked | AC89: =IF($X89="Rule 1","Language: "&$L89,IF($X89="Rule 2","Priority Transfer Target = Y",IF($X89="Rule 3","Cloud Indicator = Yes ("&$O89&")","Cloud Indicator = No, not mainframe, not a transfer target"))) -> Cloud Indicator = No, not mainframe, not a transfer target | AD89: =IFERROR(INDEX('Classification Rules'!$D$13:$D$16,MATCH($AA89,'Classification Rules'!$B$13:$B$16,0)),"") -> On-premises and non-mainframe, so the constraint is not the technology — it is that the business context exists only in Japanese, in few heads. | AE89: =IFERROR(INDEX('Classification Rules'!$D$43:$D$46,MATCH($AA89,'Classification Rules'!$B$43:$B$46,0)),"") -> 0.304 | AF89: =IFERROR(INDEX('Classification Rules'!$E$43:$E$46,MATCH($AA89,'Classification Rules'!$B$43:$B$46,0)),"") -> 0.3394768 | AG89: =IFERROR(INDEX('Classification Rules'!$F$43:$F$46,MATCH($AA89,'Classification Rules'!$B$43:$B$46,0)),"") -> 0.15 | AH89: =IFERROR(INDEX('Classification Rules'!$G$43:$G$46,MATCH($AA89,'Classification Rules'!$B$43:$B$46,0)),"") -> 0.1395 | AI89: =IFERROR(INDEX('Classification Rules'!$I$43:$I$46,MATCH($AA89,'Classification Rules'!$B$43:$B$46,0)),"") -> 10-14 weeks per cluster | AJ89: =IFERROR(INDEX('Classification Rules'!$J$43:$J$46,MATCH($AA89,'Classification Rules'!$B$43:$B$46,0)),"") -> Fully sourced, onshore-weighted | AK89: =IFERROR(INDEX('Classification Rules'!$K$43:$K$46,MATCH($AA89,'Classification Rules'!$B$43:$B$46,0)),"") -> 0
A90: 86 | B90: 11014 | C90: BCMETL-JPN | D90: Informatica Platform | E90: Data Infrastructure | F90: VS1: Informatica — ETL, IDQ, Address Doctor & HOST/AS400 Data Cooperation | G90: Data Platforms Team 34980 | H90: Data Platforms Team 34980 | I90: Common Service Business Application | J90: N | K90: Yes | L90: Other#Used UI for development and stored data as XML | M90: Y | N90: Yes | P90: MetLife Owned Application Code | Q90: 29.097917 | R90: 6.825 | S90: 6.85 | T90: 42.772917 | U90: 0.88284058 | V90: 21.386458 | W90: 21.386458 | X90: =IF(OR(ISNUMBER(SEARCH("COBOL",$L90)),ISNUMBER(SEARCH("Assembler",$L90)),ISNUMBER(SEARCH("ASM",$L90)),ISNUMBER(SEARCH("RPG",$L90)),ISNUMBER(SEARCH("EASYPLUS",$L90)),ISNUMBER(SEARCH("PL/I",$L90))),"Rule 1",IF($M90="Y","Rule 2",IF($N90="Yes","Rule 3","Rule 4"))) -> Rule 2 | Y90: =IF($X90="Rule 1","D",IF($X90="Rule 2","C",IF($X90="Rule 3","B","A"))) -> C | AA90: =IF($Z90="",$Y90,$Z90) -> C | AB90: =IFERROR(INDEX('Classification Rules'!$C$43:$C$46,MATCH($AA90,'Classification Rules'!$B$43:$B$46,0)),"") -> MGCC-destined | AC90: =IF($X90="Rule 1","Language: "&$L90,IF($X90="Rule 2","Priority Transfer Target = Y",IF($X90="Rule 3","Cloud Indicator = Yes ("&$O90&")","Cloud Indicator = No, not mainframe, not a transfer target"))) -> Priority Transfer Target = Y | AD90: =IFERROR(INDEX('Classification Rules'!$D$13:$D$16,MATCH($AA90,'Classification Rules'!$B$13:$B$16,0)),"") -> MetLife has already flagged these for transfer and nine of ten already carry MGCC people. Routing them through a vendor transition pays for the same knowledge transfer twice. | AE90: =IFERROR(INDEX('Classification Rules'!$D$43:$D$46,MATCH($AA90,'Classification Rules'!$B$43:$B$46,0)),"") -> 0.4525 | AF90: =IFERROR(INDEX('Classification Rules'!$E$43:$E$46,MATCH($AA90,'Classification Rules'!$B$43:$B$46,0)),"") -> 0.43476925 | AG90: =IFERROR(INDEX('Classification Rules'!$F$43:$F$46,MATCH($AA90,'Classification Rules'!$B$43:$B$46,0)),"") -> 0 | AH90: =IFERROR(INDEX('Classification Rules'!$G$43:$G$46,MATCH($AA90,'Classification Rules'!$B$43:$B$46,0)),"") -> 0 | AI90: =IFERROR(INDEX('Classification Rules'!$I$43:$I$46,MATCH($AA90,'Classification Rules'!$B$43:$B$46,0)),"") -> 6-8 weeks, role handover | AJ90: =IFERROR(INDEX('Classification Rules'!$J$43:$J$46,MATCH($AA90,'Classification Rules'!$B$43:$B$46,0)),"") -> Co-sourced with MGCC, permanently | AK90: =IFERROR(INDEX('Classification Rules'!$K$43:$K$46,MATCH($AA90,'Classification Rules'!$B$43:$B$46,0)),"") -> 0
A91: 87 | B91: 11203 | C91: WPSCFC-JPN | D91: c-Force | E91: Sales / Insurance Recruitment | F91: VS3: Agency & Producer Enablement | G91: Customer and Channel Engineering 34961 | H91: Distribution F2F Team 34962 | I91: Core Business Application | J91: N | K91: No | L91: Other#APEX;HTML; JavaScript | M91: Y | N91: Yes | O91: Software as a Service (SaaS) | P91: Non-MetLife Owned Application Code (3rd party/COTS) | Q91: 20.833333 | R91: 10.004167 | S91: 12.725 | T91: 43.5625 | U91: 0.86915352 | V91: 21.78125 | W91: 21.78125 | X91: =IF(OR(ISNUMBER(SEARCH("COBOL",$L91)),ISNUMBER(SEARCH("Assembler",$L91)),ISNUMBER(SEARCH("ASM",$L91)),ISNUMBER(SEARCH("RPG",$L91)),ISNUMBER(SEARCH("EASYPLUS",$L91)),ISNUMBER(SEARCH("PL/I",$L91))),"Rule 1",IF($M91="Y","Rule 2",IF($N91="Yes","Rule 3","Rule 4"))) -> Rule 2 | Y91: =IF($X91="Rule 1","D",IF($X91="Rule 2","C",IF($X91="Rule 3","B","A"))) -> C | AA91: =IF($Z91="",$Y91,$Z91) -> C | AB91: =IFERROR(INDEX('Classification Rules'!$C$43:$C$46,MATCH($AA91,'Classification Rules'!$B$43:$B$46,0)),"") -> MGCC-destined | AC91: =IF($X91="Rule 1","Language: "&$L91,IF($X91="Rule 2","Priority Transfer Target = Y",IF($X91="Rule 3","Cloud Indicator = Yes ("&$O91&")","Cloud Indicator = No, not mainframe, not a transfer target"))) -> Priority Transfer Target = Y | AD91: =IFERROR(INDEX('Classification Rules'!$D$13:$D$16,MATCH($AA91,'Classification Rules'!$B$13:$B$16,0)),"") -> MetLife has already flagged these for transfer and nine of ten already carry MGCC people. Routing them through a vendor transition pays for the same knowledge transfer twice. | AE91: =IFERROR(INDEX('Classification Rules'!$D$43:$D$46,MATCH($AA91,'Classification Rules'!$B$43:$B$46,0)),"") -> 0.4525 | AF91: =IFERROR(INDEX('Classification Rules'!$E$43:$E$46,MATCH($AA91,'Classification Rules'!$B$43:$B$46,0)),"") -> 0.43476925 | AG91: =IFERROR(INDEX('Classification Rules'!$F$43:$F$46,MATCH($AA91,'Classification Rules'!$B$43:$B$46,0)),"") -> 0 | AH91: =IFERROR(INDEX('Classification Rules'!$G$43:$G$46,MATCH($AA91,'Classification Rules'!$B$43:$B$46,0)),"") -> 0 | AI91: =IFERROR(INDEX('Classification Rules'!$I$43:$I$46,MATCH($AA91,'Classification Rules'!$B$43:$B$46,0)),"") -> 6-8 weeks, role handover | AJ91: =IFERROR(INDEX('Classification Rules'!$J$43:$J$46,MATCH($AA91,'Classification Rules'!$B$43:$B$46,0)),"") -> Co-sourced with MGCC, permanently | AK91: =IFERROR(INDEX('Classification Rules'!$K$43:$K$46,MATCH($AA91,'Classification Rules'!$B$43:$B$46,0)),"") -> 0
A92: 88 | B92: 11288 | C92: CGLFJM-JPN | D92: Misconduct Management system | E92: Corporate Related | F92: VS3: Risk, Compliance & Governance | G92: Core Insurance Systems Group 34956 | H92: Corporate Systems Team 34959 | I92: Core Business Application | J92: N | K92: Yes | L92: VB | M92: N | N92: No | P92: MetLife Owned Application Code | Q92: 0.091666667 | R92: 0 | S92: 0 | T92: 0.091666667 | U92: 0.27272727 | V92: 0.045833333 | W92: 0.045833333 | X92: =IF(OR(ISNUMBER(SEARCH("COBOL",$L92)),ISNUMBER(SEARCH("Assembler",$L92)),ISNUMBER(SEARCH("ASM",$L92)),ISNUMBER(SEARCH("RPG",$L92)),ISNUMBER(SEARCH("EASYPLUS",$L92)),ISNUMBER(SEARCH("PL/I",$L92))),"Rule 1",IF($M92="Y","Rule 2",IF($N92="Yes","Rule 3","Rule 4"))) -> Rule 4 | Y92: =IF($X92="Rule 1","D",IF($X92="Rule 2","C",IF($X92="Rule 3","B","A"))) -> A | AA92: =IF($Z92="",$Y92,$Z92) -> A | AB92: =IFERROR(INDEX('Classification Rules'!$C$43:$C$46,MATCH($AA92,'Classification Rules'!$B$43:$B$46,0)),"") -> Language-locked | AC92: =IF($X92="Rule 1","Language: "&$L92,IF($X92="Rule 2","Priority Transfer Target = Y",IF($X92="Rule 3","Cloud Indicator = Yes ("&$O92&")","Cloud Indicator = No, not mainframe, not a transfer target"))) -> Cloud Indicator = No, not mainframe, not a transfer target | AD92: =IFERROR(INDEX('Classification Rules'!$D$13:$D$16,MATCH($AA92,'Classification Rules'!$B$13:$B$16,0)),"") -> On-premises and non-mainframe, so the constraint is not the technology — it is that the business context exists only in Japanese, in few heads. | AE92: =IFERROR(INDEX('Classification Rules'!$D$43:$D$46,MATCH($AA92,'Classification Rules'!$B$43:$B$46,0)),"") -> 0.304 | AF92: =IFERROR(INDEX('Classification Rules'!$E$43:$E$46,MATCH($AA92,'Classification Rules'!$B$43:$B$46,0)),"") -> 0.3394768 | AG92: =IFERROR(INDEX('Classification Rules'!$F$43:$F$46,MATCH($AA92,'Classification Rules'!$B$43:$B$46,0)),"") -> 0.15 | AH92: =IFERROR(INDEX('Classification Rules'!$G$43:$G$46,MATCH($AA92,'Classification Rules'!$B$43:$B$46,0)),"") -> 0.1395 | AI92: =IFERROR(INDEX('Classification Rules'!$I$43:$I$46,MATCH($AA92,'Classification Rules'!$B$43:$B$46,0)),"") -> 10-14 weeks per cluster | AJ92: =IFERROR(INDEX('Classification Rules'!$J$43:$J$46,MATCH($AA92,'Classification Rules'!$B$43:$B$46,0)),"") -> Fully sourced, onshore-weighted | AK92: =IFERROR(INDEX('Classification Rules'!$K$43:$K$46,MATCH($AA92,'Classification Rules'!$B$43:$B$46,0)),"") -> 0
A93: 89 | B93: 11308 | C93: WGLBSR-JPN | D93: BSRec | E93: Corporate Related | F93: VS1: Finance & Accounting Services | G93: Core Insurance Systems Group 34956 | H93: Corporate Systems Team 34959 | I93: Core Business Application | J93: N | K93: Yes | L93: JAVA | M93: N | N93: No | P93: MetLife Owned Application Code | Q93: 0.48125 | R93: 0.0625 | S93: 0 | T93: 0.54375 | U93: 0.37931034 | V93: 0.271875 | W93: 0.271875 | X93: =IF(OR(ISNUMBER(SEARCH("COBOL",$L93)),ISNUMBER(SEARCH("Assembler",$L93)),ISNUMBER(SEARCH("ASM",$L93)),ISNUMBER(SEARCH("RPG",$L93)),ISNUMBER(SEARCH("EASYPLUS",$L93)),ISNUMBER(SEARCH("PL/I",$L93))),"Rule 1",IF($M93="Y","Rule 2",IF($N93="Yes","Rule 3","Rule 4"))) -> Rule 4 | Y93: =IF($X93="Rule 1","D",IF($X93="Rule 2","C",IF($X93="Rule 3","B","A"))) -> A | AA93: =IF($Z93="",$Y93,$Z93) -> A | AB93: =IFERROR(INDEX('Classification Rules'!$C$43:$C$46,MATCH($AA93,'Classification Rules'!$B$43:$B$46,0)),"") -> Language-locked | AC93: =IF($X93="Rule 1","Language: "&$L93,IF($X93="Rule 2","Priority Transfer Target = Y",IF($X93="Rule 3","Cloud Indicator = Yes ("&$O93&")","Cloud Indicator = No, not mainframe, not a transfer target"))) -> Cloud Indicator = No, not mainframe, not a transfer target | AD93: =IFERROR(INDEX('Classification Rules'!$D$13:$D$16,MATCH($AA93,'Classification Rules'!$B$13:$B$16,0)),"") -> On-premises and non-mainframe, so the constraint is not the technology — it is that the business context exists only in Japanese, in few heads. | AE93: =IFERROR(INDEX('Classification Rules'!$D$43:$D$46,MATCH($AA93,'Classification Rules'!$B$43:$B$46,0)),"") -> 0.304 | AF93: =IFERROR(INDEX('Classification Rules'!$E$43:$E$46,MATCH($AA93,'Classification Rules'!$B$43:$B$46,0)),"") -> 0.3394768 | AG93: =IFERROR(INDEX('Classification Rules'!$F$43:$F$46,MATCH($AA93,'Classification Rules'!$B$43:$B$46,0)),"") -> 0.15 | AH93: =IFERROR(INDEX('Classification Rules'!$G$43:$G$46,MATCH($AA93,'Classification Rules'!$B$43:$B$46,0)),"") -> 0.1395 | AI93: =IFERROR(INDEX('Classification Rules'!$I$43:$I$46,MATCH($AA93,'Classification Rules'!$B$43:$B$46,0)),"") -> 10-14 weeks per cluster | AJ93: =IFERROR(INDEX('Classification Rules'!$J$43:$J$46,MATCH($AA93,'Classification Rules'!$B$43:$B$46,0)),"") -> Fully sourced, onshore-weighted | AK93: =IFERROR(INDEX('Classification Rules'!$K$43:$K$46,MATCH($AA93,'Classification Rules'!$B$43:$B$46,0)),"") -> 0
A94: 90 | B94: 11604 | C94: JP-RPASS | D94: JAPAN_BluePrism RPA | E94: Storage and Preservation Related | F94: VS3: RPA & Robotics Services | G94: Customer Service and Operations Systems Group 34965 | H94: Policy Servicing Team 34967 | I94: Common Service Business Application | J94: N | K94: Yes | L94: Other#COTS from BluePrism | M94: N | N94: No | P94: Non-MetLife Owned Application Code (3rd party/COTS) | Q94: 5.6624583 | R94: 4.075 | S94: 0 | T94: 9.7374583 | U94: 0.8973038 | V94: 4.8687292 | W94: 4.8687292 | X94: =IF(OR(ISNUMBER(SEARCH("COBOL",$L94)),ISNUMBER(SEARCH("Assembler",$L94)),ISNUMBER(SEARCH("ASM",$L94)),ISNUMBER(SEARCH("RPG",$L94)),ISNUMBER(SEARCH("EASYPLUS",$L94)),ISNUMBER(SEARCH("PL/I",$L94))),"Rule 1",IF($M94="Y","Rule 2",IF($N94="Yes","Rule 3","Rule 4"))) -> Rule 4 | Y94: =IF($X94="Rule 1","D",IF($X94="Rule 2","C",IF($X94="Rule 3","B","A"))) -> A | AA94: =IF($Z94="",$Y94,$Z94) -> A | AB94: =IFERROR(INDEX('Classification Rules'!$C$43:$C$46,MATCH($AA94,'Classification Rules'!$B$43:$B$46,0)),"") -> Language-locked | AC94: =IF($X94="Rule 1","Language: "&$L94,IF($X94="Rule 2","Priority Transfer Target = Y",IF($X94="Rule 3","Cloud Indicator = Yes ("&$O94&")","Cloud Indicator = No, not mainframe, not a transfer target"))) -> Cloud Indicator = No, not mainframe, not a transfer target | AD94: =IFERROR(INDEX('Classification Rules'!$D$13:$D$16,MATCH($AA94,'Classification Rules'!$B$13:$B$16,0)),"") -> On-premises and non-mainframe, so the constraint is not the technology — it is that the business context exists only in Japanese, in few heads. | AE94: =IFERROR(INDEX('Classification Rules'!$D$43:$D$46,MATCH($AA94,'Classification Rules'!$B$43:$B$46,0)),"") -> 0.304 | AF94: =IFERROR(INDEX('Classification Rules'!$E$43:$E$46,MATCH($AA94,'Classification Rules'!$B$43:$B$46,0)),"") -> 0.3394768 | AG94: =IFERROR(INDEX('Classification Rules'!$F$43:$F$46,MATCH($AA94,'Classification Rules'!$B$43:$B$46,0)),"") -> 0.15 | AH94: =IFERROR(INDEX('Classification Rules'!$G$43:$G$46,MATCH($AA94,'Classification Rules'!$B$43:$B$46,0)),"") -> 0.1395 | AI94: =IFERROR(INDEX('Classification Rules'!$I$43:$I$46,MATCH($AA94,'Classification Rules'!$B$43:$B$46,0)),"") -> 10-14 weeks per cluster | AJ94: =IFERROR(INDEX('Classification Rules'!$J$43:$J$46,MATCH($AA94,'Classification Rules'!$B$43:$B$46,0)),"") -> Fully sourced, onshore-weighted | AK94: =IFERROR(INDEX('Classification Rules'!$K$43:$K$46,MATCH($AA94,'Classification Rules'!$B$43:$B$46,0)),"") -> 0
A95: 91 | B95: 11893 | C95: W03CCP-JPN | D95: Customer Communication Preferences | E95: Storage and Preservation Related | F95: VS4: Document Processing & Imaging | G95: Customer Service and Operations Systems Group 34965 | H95: Policy Servicing Team 34967 | I95: Core Business Application | J95: N | K95: Yes | L95: JAVA | M95: N | N95: Yes | O95: Platform as a Service (PaaS) | P95: MetLife Owned Application Code | Q95: 0.2 | R95: 0.2 | S95: 0 | T95: 0.35416667 | U95: 0.56470588 | V95: 0.17708333 | W95: 0.17708333 | X95: =IF(OR(ISNUMBER(SEARCH("COBOL",$L95)),ISNUMBER(SEARCH("Assembler",$L95)),ISNUMBER(SEARCH("ASM",$L95)),ISNUMBER(SEARCH("RPG",$L95)),ISNUMBER(SEARCH("EASYPLUS",$L95)),ISNUMBER(SEARCH("PL/I",$L95))),"Rule 1",IF($M95="Y","Rule 2",IF($N95="Yes","Rule 3","Rule 4"))) -> Rule 3 | Y95: =IF($X95="Rule 1","D",IF($X95="Rule 2","C",IF($X95="Rule 3","B","A"))) -> B | AA95: =IF($Z95="",$Y95,$Z95) -> B | AB95: =IFERROR(INDEX('Classification Rules'!$C$43:$C$46,MATCH($AA95,'Classification Rules'!$B$43:$B$46,0)),"") -> Offshore-ready | AC95: =IF($X95="Rule 1","Language: "&$L95,IF($X95="Rule 2","Priority Transfer Target = Y",IF($X95="Rule 3","Cloud Indicator = Yes ("&$O95&")","Cloud Indicator = No, not mainframe, not a transfer target"))) -> Cloud Indicator = Yes (Platform as a Service (PaaS)) | AD95: =IFERROR(INDEX('Classification Rules'!$D$13:$D$16,MATCH($AA95,'Classification Rules'!$B$13:$B$16,0)),"") -> Cloud migration has already forced re-platforming, documentation and specifiability. Highest AI and offshore ceiling in the estate. | AE95: =IFERROR(INDEX('Classification Rules'!$D$43:$D$46,MATCH($AA95,'Classification Rules'!$B$43:$B$46,0)),"") -> 0.4825 | AF95: =IFERROR(INDEX('Classification Rules'!$E$43:$E$46,MATCH($AA95,'Classification Rules'!$B$43:$B$46,0)),"") -> 0.45402025 | AG95: =IFERROR(INDEX('Classification Rules'!$F$43:$F$46,MATCH($AA95,'Classification Rules'!$B$43:$B$46,0)),"") -> 0.78 | AH95: =IFERROR(INDEX('Classification Rules'!$G$43:$G$46,MATCH($AA95,'Classification Rules'!$B$43:$B$46,0)),"") -> 0.7254 | AI95: =IFERROR(INDEX('Classification Rules'!$I$43:$I$46,MATCH($AA95,'Classification Rules'!$B$43:$B$46,0)),"") -> 6-8 weeks per cluster | AJ95: =IFERROR(INDEX('Classification Rules'!$J$43:$J$46,MATCH($AA95,'Classification Rules'!$B$43:$B$46,0)),"") -> Fully sourced, moving to output units | AK95: =IFERROR(INDEX('Classification Rules'!$K$43:$K$46,MATCH($AA95,'Classification Rules'!$B$43:$B$46,0)),"") -> 0
A96: 92 | B96: 11986 | C96: JP-Banca Report | D96: Japan Banca Report | E96: Sales / Insurance Recruitment | F96: VS2: Bancassurance Platforms | G96: Customer and Channel Engineering 34961 | H96: Distribution Banca Team 34963 | I96: Common Service Business Application | J96: N | K96: Yes | L96: JAVA | M96: N | N96: Yes | O96: Infrastructure as a Service (IaaS); Platform as a Service (PaaS) | P96: MetLife Owned Application Code | Q96: 6 | R96: 6 | S96: 3 | T96: 15 | U96: 1 | V96: 7.5 | W96: 7.5 | X96: =IF(OR(ISNUMBER(SEARCH("COBOL",$L96)),ISNUMBER(SEARCH("Assembler",$L96)),ISNUMBER(SEARCH("ASM",$L96)),ISNUMBER(SEARCH("RPG",$L96)),ISNUMBER(SEARCH("EASYPLUS",$L96)),ISNUMBER(SEARCH("PL/I",$L96))),"Rule 1",IF($M96="Y","Rule 2",IF($N96="Yes","Rule 3","Rule 4"))) -> Rule 3 | Y96: =IF($X96="Rule 1","D",IF($X96="Rule 2","C",IF($X96="Rule 3","B","A"))) -> B | AA96: =IF($Z96="",$Y96,$Z96) -> B | AB96: =IFERROR(INDEX('Classification Rules'!$C$43:$C$46,MATCH($AA96,'Classification Rules'!$B$43:$B$46,0)),"") -> Offshore-ready | AC96: =IF($X96="Rule 1","Language: "&$L96,IF($X96="Rule 2","Priority Transfer Target = Y",IF($X96="Rule 3","Cloud Indicator = Yes ("&$O96&")","Cloud Indicator = No, not mainframe, not a transfer target"))) -> Cloud Indicator = Yes (Infrastructure as a Service (IaaS); Platform as a Service (PaaS)) | AD96: =IFERROR(INDEX('Classification Rules'!$D$13:$D$16,MATCH($AA96,'Classification Rules'!$B$13:$B$16,0)),"") -> Cloud migration has already forced re-platforming, documentation and specifiability. Highest AI and offshore ceiling in the estate. | AE96: =IFERROR(INDEX('Classification Rules'!$D$43:$D$46,MATCH($AA96,'Classification Rules'!$B$43:$B$46,0)),"") -> 0.4825 | AF96: =IFERROR(INDEX('Classification Rules'!$E$43:$E$46,MATCH($AA96,'Classification Rules'!$B$43:$B$46,0)),"") -> 0.45402025 | AG96: =IFERROR(INDEX('Classification Rules'!$F$43:$F$46,MATCH($AA96,'Classification Rules'!$B$43:$B$46,0)),"") -> 0.78 | AH96: =IFERROR(INDEX('Classification Rules'!$G$43:$G$46,MATCH($AA96,'Classification Rules'!$B$43:$B$46,0)),"") -> 0.7254 | AI96: =IFERROR(INDEX('Classification Rules'!$I$43:$I$46,MATCH($AA96,'Classification Rules'!$B$43:$B$46,0)),"") -> 6-8 weeks per cluster | AJ96: =IFERROR(INDEX('Classification Rules'!$J$43:$J$46,MATCH($AA96,'Classification Rules'!$B$43:$B$46,0)),"") -> Fully sourced, moving to output units | AK96: =IFERROR(INDEX('Classification Rules'!$K$43:$K$46,MATCH($AA96,'Classification Rules'!$B$43:$B$46,0)),"") -> 0
A97: 93 | B97: 12021 | C97: LPS-JPN(EUC081) | D97: Life Plan Simulation Japan | E97: Marketing/Direct Business Related | F97: VS2: Customer Acquisition & Quotation | G97: Customer and Channel Engineering 34961 | H97: Marketing and Leads Team 34964 | I97: Core Business Application | J97: N | K97: Yes | L97: PHP | M97: N | N97: No | P97: Non-MetLife Owned Application Code (3rd party/COTS) | Q97: 0 | R97: 0 | S97: 0 | T97: 0 | U97: 0 | V97: 0 | W97: 0 | X97: =IF(OR(ISNUMBER(SEARCH("COBOL",$L97)),ISNUMBER(SEARCH("Assembler",$L97)),ISNUMBER(SEARCH("ASM",$L97)),ISNUMBER(SEARCH("RPG",$L97)),ISNUMBER(SEARCH("EASYPLUS",$L97)),ISNUMBER(SEARCH("PL/I",$L97))),"Rule 1",IF($M97="Y","Rule 2",IF($N97="Yes","Rule 3","Rule 4"))) -> Rule 4 | Y97: =IF($X97="Rule 1","D",IF($X97="Rule 2","C",IF($X97="Rule 3","B","A"))) -> A | AA97: =IF($Z97="",$Y97,$Z97) -> A | AB97: =IFERROR(INDEX('Classification Rules'!$C$43:$C$46,MATCH($AA97,'Classification Rules'!$B$43:$B$46,0)),"") -> Language-locked | AC97: =IF($X97="Rule 1","Language: "&$L97,IF($X97="Rule 2","Priority Transfer Target = Y",IF($X97="Rule 3","Cloud Indicator = Yes ("&$O97&")","Cloud Indicator = No, not mainframe, not a transfer target"))) -> Cloud Indicator = No, not mainframe, not a transfer target | AD97: =IFERROR(INDEX('Classification Rules'!$D$13:$D$16,MATCH($AA97,'Classification Rules'!$B$13:$B$16,0)),"") -> On-premises and non-mainframe, so the constraint is not the technology — it is that the business context exists only in Japanese, in few heads. | AE97: =IFERROR(INDEX('Classification Rules'!$D$43:$D$46,MATCH($AA97,'Classification Rules'!$B$43:$B$46,0)),"") -> 0.304 | AF97: =IFERROR(INDEX('Classification Rules'!$E$43:$E$46,MATCH($AA97,'Classification Rules'!$B$43:$B$46,0)),"") -> 0.3394768 | AG97: =IFERROR(INDEX('Classification Rules'!$F$43:$F$46,MATCH($AA97,'Classification Rules'!$B$43:$B$46,0)),"") -> 0.15 | AH97: =IFERROR(INDEX('Classification Rules'!$G$43:$G$46,MATCH($AA97,'Classification Rules'!$B$43:$B$46,0)),"") -> 0.1395 | AI97: =IFERROR(INDEX('Classification Rules'!$I$43:$I$46,MATCH($AA97,'Classification Rules'!$B$43:$B$46,0)),"") -> 10-14 weeks per cluster | AJ97: =IFERROR(INDEX('Classification Rules'!$J$43:$J$46,MATCH($AA97,'Classification Rules'!$B$43:$B$46,0)),"") -> Fully sourced, onshore-weighted | AK97: =IFERROR(INDEX('Classification Rules'!$K$43:$K$46,MATCH($AA97,'Classification Rules'!$B$43:$B$46,0)),"") -> 0
A98: 94 | B98: 12030 | C98: CIT-JPN(EUC082) | D98: Inheritance Tax Simulation | E98: Marketing/Direct Business Related | F98: VS2: Customer Acquisition & Quotation | G98: Customer and Channel Engineering 34961 | H98: Marketing and Leads Team 34964 | I98: Core Business Application | J98: N | K98: Yes | L98: JAVA | M98: N | N98: No | P98: Non-MetLife Owned Application Code (3rd party/COTS) | Q98: 0 | R98: 0 | S98: 0 | T98: 0 | U98: 0 | V98: 0 | W98: 0 | X98: =IF(OR(ISNUMBER(SEARCH("COBOL",$L98)),ISNUMBER(SEARCH("Assembler",$L98)),ISNUMBER(SEARCH("ASM",$L98)),ISNUMBER(SEARCH("RPG",$L98)),ISNUMBER(SEARCH("EASYPLUS",$L98)),ISNUMBER(SEARCH("PL/I",$L98))),"Rule 1",IF($M98="Y","Rule 2",IF($N98="Yes","Rule 3","Rule 4"))) -> Rule 4 | Y98: =IF($X98="Rule 1","D",IF($X98="Rule 2","C",IF($X98="Rule 3","B","A"))) -> A | AA98: =IF($Z98="",$Y98,$Z98) -> A | AB98: =IFERROR(INDEX('Classification Rules'!$C$43:$C$46,MATCH($AA98,'Classification Rules'!$B$43:$B$46,0)),"") -> Language-locked | AC98: =IF($X98="Rule 1","Language: "&$L98,IF($X98="Rule 2","Priority Transfer Target = Y",IF($X98="Rule 3","Cloud Indicator = Yes ("&$O98&")","Cloud Indicator = No, not mainframe, not a transfer target"))) -> Cloud Indicator = No, not mainframe, not a transfer target | AD98: =IFERROR(INDEX('Classification Rules'!$D$13:$D$16,MATCH($AA98,'Classification Rules'!$B$13:$B$16,0)),"") -> On-premises and non-mainframe, so the constraint is not the technology — it is that the business context exists only in Japanese, in few heads. | AE98: =IFERROR(INDEX('Classification Rules'!$D$43:$D$46,MATCH($AA98,'Classification Rules'!$B$43:$B$46,0)),"") -> 0.304 | AF98: =IFERROR(INDEX('Classification Rules'!$E$43:$E$46,MATCH($AA98,'Classification Rules'!$B$43:$B$46,0)),"") -> 0.3394768 | AG98: =IFERROR(INDEX('Classification Rules'!$F$43:$F$46,MATCH($AA98,'Classification Rules'!$B$43:$B$46,0)),"") -> 0.15 | AH98: =IFERROR(INDEX('Classification Rules'!$G$43:$G$46,MATCH($AA98,'Classification Rules'!$B$43:$B$46,0)),"") -> 0.1395 | AI98: =IFERROR(INDEX('Classification Rules'!$I$43:$I$46,MATCH($AA98,'Classification Rules'!$B$43:$B$46,0)),"") -> 10-14 weeks per cluster | AJ98: =IFERROR(INDEX('Classification Rules'!$J$43:$J$46,MATCH($AA98,'Classification Rules'!$B$43:$B$46,0)),"") -> Fully sourced, onshore-weighted | AK98: =IFERROR(INDEX('Classification Rules'!$K$43:$K$46,MATCH($AA98,'Classification Rules'!$B$43:$B$46,0)),"") -> 0
A99: 95 | B99: 12038 | C99: CMIAPI-JPN | D99: API Hub | E99: Common Service Platform | F99: VS3: API Management & Partner Integration | G99: Japan Platform Team 35775 | H99: Japan Platform Team 35775 | I99: Common Service Business Application | J99: N | K99: Yes | L99: JAVA | M99: N | N99: Yes | O99: Platform as a Service (PaaS) | P99: MetLife Owned Application Code | Q99: 19.246667 | R99: 4.1333333 | S99: 16.910417 | T99: 40.290417 | U99: 0.94847824 | V99: 20.145208 | W99: 20.145208 | X99: =IF(OR(ISNUMBER(SEARCH("COBOL",$L99)),ISNUMBER(SEARCH("Assembler",$L99)),ISNUMBER(SEARCH("ASM",$L99)),ISNUMBER(SEARCH("RPG",$L99)),ISNUMBER(SEARCH("EASYPLUS",$L99)),ISNUMBER(SEARCH("PL/I",$L99))),"Rule 1",IF($M99="Y","Rule 2",IF($N99="Yes","Rule 3","Rule 4"))) -> Rule 3 | Y99: =IF($X99="Rule 1","D",IF($X99="Rule 2","C",IF($X99="Rule 3","B","A"))) -> B | AA99: =IF($Z99="",$Y99,$Z99) -> B | AB99: =IFERROR(INDEX('Classification Rules'!$C$43:$C$46,MATCH($AA99,'Classification Rules'!$B$43:$B$46,0)),"") -> Offshore-ready | AC99: =IF($X99="Rule 1","Language: "&$L99,IF($X99="Rule 2","Priority Transfer Target = Y",IF($X99="Rule 3","Cloud Indicator = Yes ("&$O99&")","Cloud Indicator = No, not mainframe, not a transfer target"))) -> Cloud Indicator = Yes (Platform as a Service (PaaS)) | AD99: =IFERROR(INDEX('Classification Rules'!$D$13:$D$16,MATCH($AA99,'Classification Rules'!$B$13:$B$16,0)),"") -> Cloud migration has already forced re-platforming, documentation and specifiability. Highest AI and offshore ceiling in the estate. | AE99: =IFERROR(INDEX('Classification Rules'!$D$43:$D$46,MATCH($AA99,'Classification Rules'!$B$43:$B$46,0)),"") -> 0.4825 | AF99: =IFERROR(INDEX('Classification Rules'!$E$43:$E$46,MATCH($AA99,'Classification Rules'!$B$43:$B$46,0)),"") -> 0.45402025 | AG99: =IFERROR(INDEX('Classification Rules'!$F$43:$F$46,MATCH($AA99,'Classification Rules'!$B$43:$B$46,0)),"") -> 0.78 | AH99: =IFERROR(INDEX('Classification Rules'!$G$43:$G$46,MATCH($AA99,'Classification Rules'!$B$43:$B$46,0)),"") -> 0.7254 | AI99: =IFERROR(INDEX('Classification Rules'!$I$43:$I$46,MATCH($AA99,'Classification Rules'!$B$43:$B$46,0)),"") -> 6-8 weeks per cluster | AJ99: =IFERROR(INDEX('Classification Rules'!$J$43:$J$46,MATCH($AA99,'Classification Rules'!$B$43:$B$46,0)),"") -> Fully sourced, moving to output units | AK99: =IFERROR(INDEX('Classification Rules'!$K$43:$K$46,MATCH($AA99,'Classification Rules'!$B$43:$B$46,0)),"") -> 0
A100: 96 | B100: 12117 | C100: K2 | D100: Japan K2 - Digital Workflows | E100: Storage and Preservation Related | F100: VS1: Digital Workflow & Process Automation | G100: Customer Service and Operations Systems Group 34965 | H100: Policy Servicing Team 34967 | I100: Core Business Application | J100: Y | K100: Yes | L100: VB.NET | M100: N | N100: No | P100: Non-MetLife Owned Application Code (3rd party/COTS) | Q100: 6 | R100: 15.5375 | S100: 11 | T100: 62.642375 | U100: 0.8631983 | V100: 31.321188 | W100: 31.321188 | X100: =IF(OR(ISNUMBER(SEARCH("COBOL",$L100)),ISNUMBER(SEARCH("Assembler",$L100)),ISNUMBER(SEARCH("ASM",$L100)),ISNUMBER(SEARCH("RPG",$L100)),ISNUMBER(SEARCH("EASYPLUS",$L100)),ISNUMBER(SEARCH("PL/I",$L100))),"Rule 1",IF($M100="Y","Rule 2",IF($N100="Yes","Rule 3","Rule 4"))) -> Rule 4 | Y100: =IF($X100="Rule 1","D",IF($X100="Rule 2","C",IF($X100="Rule 3","B","A"))) -> A | AA100: =IF($Z100="",$Y100,$Z100) -> A | AB100: =IFERROR(INDEX('Classification Rules'!$C$43:$C$46,MATCH($AA100,'Classification Rules'!$B$43:$B$46,0)),"") -> Language-locked | AC100: =IF($X100="Rule 1","Language: "&$L100,IF($X100="Rule 2","Priority Transfer Target = Y",IF($X100="Rule 3","Cloud Indicator = Yes ("&$O100&")","Cloud Indicator = No, not mainframe, not a transfer target"))) -> Cloud Indicator = No, not mainframe, not a transfer target | AD100: =IFERROR(INDEX('Classification Rules'!$D$13:$D$16,MATCH($AA100,'Classification Rules'!$B$13:$B$16,0)),"") -> On-premises and non-mainframe, so the constraint is not the technology — it is that the business context exists only in Japanese, in few heads. | AE100: =IFERROR(INDEX('Classification Rules'!$D$43:$D$46,MATCH($AA100,'Classification Rules'!$B$43:$B$46,0)),"") -> 0.304 | AF100: =IFERROR(INDEX('Classification Rules'!$E$43:$E$46,MATCH($AA100,'Classification Rules'!$B$43:$B$46,0)),"") -> 0.3394768 | AG100: =IFERROR(INDEX('Classification Rules'!$F$43:$F$46,MATCH($AA100,'Classification Rules'!$B$43:$B$46,0)),"") -> 0.15 | AH100: =IFERROR(INDEX('Classification Rules'!$G$43:$G$46,MATCH($AA100,'Classification Rules'!$B$43:$B$46,0)),"") -> 0.1395 | AI100: =IFERROR(INDEX('Classification Rules'!$I$43:$I$46,MATCH($AA100,'Classification Rules'!$B$43:$B$46,0)),"") -> 10-14 weeks per cluster | AJ100: =IFERROR(INDEX('Classification Rules'!$J$43:$J$46,MATCH($AA100,'Classification Rules'!$B$43:$B$46,0)),"") -> Fully sourced, onshore-weighted | AK100: =IFERROR(INDEX('Classification Rules'!$K$43:$K$46,MATCH($AA100,'Classification Rules'!$B$43:$B$46,0)),"") -> 0
A101: 97 | B101: 12198 | C101: JP-PCI-RPASS | D101: Japan PCI Robotics Process Automation Service | E101: Storage and Preservation Related | F101: VS3: RPA & Robotics Services | G101: Customer Service and Operations Systems Group 34965 | H101: Policy Servicing Team 34967 | I101: Common Service Business Application | J101: N | K101: Yes | L101: Other#This is coded within blueprism | M101: N | N101: No | P101: Non-MetLife Owned Application Code (3rd party/COTS) | Q101: 1 | R101: 2 | S101: 0 | T101: 3 | U101: 0 | V101: 1.5 | W101: 1.5 | X101: =IF(OR(ISNUMBER(SEARCH("COBOL",$L101)),ISNUMBER(SEARCH("Assembler",$L101)),ISNUMBER(SEARCH("ASM",$L101)),ISNUMBER(SEARCH("RPG",$L101)),ISNUMBER(SEARCH("EASYPLUS",$L101)),ISNUMBER(SEARCH("PL/I",$L101))),"Rule 1",IF($M101="Y","Rule 2",IF($N101="Yes","Rule 3","Rule 4"))) -> Rule 4 | Y101: =IF($X101="Rule 1","D",IF($X101="Rule 2","C",IF($X101="Rule 3","B","A"))) -> A | AA101: =IF($Z101="",$Y101,$Z101) -> A | AB101: =IFERROR(INDEX('Classification Rules'!$C$43:$C$46,MATCH($AA101,'Classification Rules'!$B$43:$B$46,0)),"") -> Language-locked | AC101: =IF($X101="Rule 1","Language: "&$L101,IF($X101="Rule 2","Priority Transfer Target = Y",IF($X101="Rule 3","Cloud Indicator = Yes ("&$O101&")","Cloud Indicator = No, not mainframe, not a transfer target"))) -> Cloud Indicator = No, not mainframe, not a transfer target | AD101: =IFERROR(INDEX('Classification Rules'!$D$13:$D$16,MATCH($AA101,'Classification Rules'!$B$13:$B$16,0)),"") -> On-premises and non-mainframe, so the constraint is not the technology — it is that the business context exists only in Japanese, in few heads. | AE101: =IFERROR(INDEX('Classification Rules'!$D$43:$D$46,MATCH($AA101,'Classification Rules'!$B$43:$B$46,0)),"") -> 0.304 | AF101: =IFERROR(INDEX('Classification Rules'!$E$43:$E$46,MATCH($AA101,'Classification Rules'!$B$43:$B$46,0)),"") -> 0.3394768 | AG101: =IFERROR(INDEX('Classification Rules'!$F$43:$F$46,MATCH($AA101,'Classification Rules'!$B$43:$B$46,0)),"") -> 0.15 | AH101: =IFERROR(INDEX('Classification Rules'!$G$43:$G$46,MATCH($AA101,'Classification Rules'!$B$43:$B$46,0)),"") -> 0.1395 | AI101: =IFERROR(INDEX('Classification Rules'!$I$43:$I$46,MATCH($AA101,'Classification Rules'!$B$43:$B$46,0)),"") -> 10-14 weeks per cluster | AJ101: =IFERROR(INDEX('Classification Rules'!$J$43:$J$46,MATCH($AA101,'Classification Rules'!$B$43:$B$46,0)),"") -> Fully sourced, onshore-weighted | AK101: =IFERROR(INDEX('Classification Rules'!$K$43:$K$46,MATCH($AA101,'Classification Rules'!$B$43:$B$46,0)),"") -> 0
A102: 98 | B102: 12520 | C102: RBRARS-JPN | D102: RBWF Report Automatic Recognition System | E102: New Contract Related | F102: VS5: New Business Batch Processing | G102: Customer Service and Operations Systems Group 34965 | H102: New Business Team 34966 | I102: Core Business Application | J102: N | K102: Yes | L102: JAVA | M102: N | N102: Yes | P102: MetLife Owned Application Code | Q102: 0.125 | R102: 0 | S102: 0 | T102: 0.125 | U102: 1 | V102: 0.0625 | W102: 0.0625 | X102: =IF(OR(ISNUMBER(SEARCH("COBOL",$L102)),ISNUMBER(SEARCH("Assembler",$L102)),ISNUMBER(SEARCH("ASM",$L102)),ISNUMBER(SEARCH("RPG",$L102)),ISNUMBER(SEARCH("EASYPLUS",$L102)),ISNUMBER(SEARCH("PL/I",$L102))),"Rule 1",IF($M102="Y","Rule 2",IF($N102="Yes","Rule 3","Rule 4"))) -> Rule 3 | Y102: =IF($X102="Rule 1","D",IF($X102="Rule 2","C",IF($X102="Rule 3","B","A"))) -> B | AA102: =IF($Z102="",$Y102,$Z102) -> B | AB102: =IFERROR(INDEX('Classification Rules'!$C$43:$C$46,MATCH($AA102,'Classification Rules'!$B$43:$B$46,0)),"") -> Offshore-ready | AC102: =IF($X102="Rule 1","Language: "&$L102,IF($X102="Rule 2","Priority Transfer Target = Y",IF($X102="Rule 3","Cloud Indicator = Yes ("&$O102&")","Cloud Indicator = No, not mainframe, not a transfer target"))) -> Cloud Indicator = Yes () | AD102: =IFERROR(INDEX('Classification Rules'!$D$13:$D$16,MATCH($AA102,'Classification Rules'!$B$13:$B$16,0)),"") -> Cloud migration has already forced re-platforming, documentation and specifiability. Highest AI and offshore ceiling in the estate. | AE102: =IFERROR(INDEX('Classification Rules'!$D$43:$D$46,MATCH($AA102,'Classification Rules'!$B$43:$B$46,0)),"") -> 0.4825 | AF102: =IFERROR(INDEX('Classification Rules'!$E$43:$E$46,MATCH($AA102,'Classification Rules'!$B$43:$B$46,0)),"") -> 0.45402025 | AG102: =IFERROR(INDEX('Classification Rules'!$F$43:$F$46,MATCH($AA102,'Classification Rules'!$B$43:$B$46,0)),"") -> 0.78 | AH102: =IFERROR(INDEX('Classification Rules'!$G$43:$G$46,MATCH($AA102,'Classification Rules'!$B$43:$B$46,0)),"") -> 0.7254 | AI102: =IFERROR(INDEX('Classification Rules'!$I$43:$I$46,MATCH($AA102,'Classification Rules'!$B$43:$B$46,0)),"") -> 6-8 weeks per cluster | AJ102: =IFERROR(INDEX('Classification Rules'!$J$43:$J$46,MATCH($AA102,'Classification Rules'!$B$43:$B$46,0)),"") -> Fully sourced, moving to output units | AK102: =IFERROR(INDEX('Classification Rules'!$K$43:$K$46,MATCH($AA102,'Classification Rules'!$B$43:$B$46,0)),"") -> 0
A103: 99 | B103: 12527 | C103: CMEAPI-JP | D103: Japan Partner API | E103: Common Service Platform | F103: VS3: API Management & Partner Integration | G103: Japan Platform Team 35775 | H103: Japan Platform Team 35775 | I103: Common Service Business Application | J103: N | K103: Yes | L103: JAVA | M103: N | N103: Yes | O103: Platform as a Service (PaaS) | P103: MetLife Owned Application Code | Q103: 0.10833333 | R103: 0 | S103: 0.025 | T103: 0.13333333 | U103: 1 | V103: 0.066666667 | W103: 0.066666667 | X103: =IF(OR(ISNUMBER(SEARCH("COBOL",$L103)),ISNUMBER(SEARCH("Assembler",$L103)),ISNUMBER(SEARCH("ASM",$L103)),ISNUMBER(SEARCH("RPG",$L103)),ISNUMBER(SEARCH("EASYPLUS",$L103)),ISNUMBER(SEARCH("PL/I",$L103))),"Rule 1",IF($M103="Y","Rule 2",IF($N103="Yes","Rule 3","Rule 4"))) -> Rule 3 | Y103: =IF($X103="Rule 1","D",IF($X103="Rule 2","C",IF($X103="Rule 3","B","A"))) -> B | AA103: =IF($Z103="",$Y103,$Z103) -> B | AB103: =IFERROR(INDEX('Classification Rules'!$C$43:$C$46,MATCH($AA103,'Classification Rules'!$B$43:$B$46,0)),"") -> Offshore-ready | AC103: =IF($X103="Rule 1","Language: "&$L103,IF($X103="Rule 2","Priority Transfer Target = Y",IF($X103="Rule 3","Cloud Indicator = Yes ("&$O103&")","Cloud Indicator = No, not mainframe, not a transfer target"))) -> Cloud Indicator = Yes (Platform as a Service (PaaS)) | AD103: =IFERROR(INDEX('Classification Rules'!$D$13:$D$16,MATCH($AA103,'Classification Rules'!$B$13:$B$16,0)),"") -> Cloud migration has already forced re-platforming, documentation and specifiability. Highest AI and offshore ceiling in the estate. | AE103: =IFERROR(INDEX('Classification Rules'!$D$43:$D$46,MATCH($AA103,'Classification Rules'!$B$43:$B$46,0)),"") -> 0.4825 | AF103: =IFERROR(INDEX('Classification Rules'!$E$43:$E$46,MATCH($AA103,'Classification Rules'!$B$43:$B$46,0)),"") -> 0.45402025 | AG103: =IFERROR(INDEX('Classification Rules'!$F$43:$F$46,MATCH($AA103,'Classification Rules'!$B$43:$B$46,0)),"") -> 0.78 | AH103: =IFERROR(INDEX('Classification Rules'!$G$43:$G$46,MATCH($AA103,'Classification Rules'!$B$43:$B$46,0)),"") -> 0.7254 | AI103: =IFERROR(INDEX('Classification Rules'!$I$43:$I$46,MATCH($AA103,'Classification Rules'!$B$43:$B$46,0)),"") -> 6-8 weeks per cluster | AJ103: =IFERROR(INDEX('Classification Rules'!$J$43:$J$46,MATCH($AA103,'Classification Rules'!$B$43:$B$46,0)),"") -> Fully sourced, moving to output units | AK103: =IFERROR(INDEX('Classification Rules'!$K$43:$K$46,MATCH($AA103,'Classification Rules'!$B$43:$B$46,0)),"") -> 0
A104: 100 | B104: 12607 | C104: JP-WCMAUT | D104: JP Authentication Platform | E104: Common Service Platform | F104: VS1: Identity & Access Services | G104: Japan Platform Team 35775 | H104: Japan Platform Team 35775 | I104: Common Service Business Application | J104: N | K104: Yes | L104: JAVA | M104: N | N104: Yes | O104: Platform as a Service (PaaS) | P104: MetLife Owned Application Code | Q104: 1.3375 | R104: 0 | S104: 1 | T104: 2.3375 | U104: 1 | V104: 1.16875 | W104: 1.16875 | X104: =IF(OR(ISNUMBER(SEARCH("COBOL",$L104)),ISNUMBER(SEARCH("Assembler",$L104)),ISNUMBER(SEARCH("ASM",$L104)),ISNUMBER(SEARCH("RPG",$L104)),ISNUMBER(SEARCH("EASYPLUS",$L104)),ISNUMBER(SEARCH("PL/I",$L104))),"Rule 1",IF($M104="Y","Rule 2",IF($N104="Yes","Rule 3","Rule 4"))) -> Rule 3 | Y104: =IF($X104="Rule 1","D",IF($X104="Rule 2","C",IF($X104="Rule 3","B","A"))) -> B | AA104: =IF($Z104="",$Y104,$Z104) -> B | AB104: =IFERROR(INDEX('Classification Rules'!$C$43:$C$46,MATCH($AA104,'Classification Rules'!$B$43:$B$46,0)),"") -> Offshore-ready | AC104: =IF($X104="Rule 1","Language: "&$L104,IF($X104="Rule 2","Priority Transfer Target = Y",IF($X104="Rule 3","Cloud Indicator = Yes ("&$O104&")","Cloud Indicator = No, not mainframe, not a transfer target"))) -> Cloud Indicator = Yes (Platform as a Service (PaaS)) | AD104: =IFERROR(INDEX('Classification Rules'!$D$13:$D$16,MATCH($AA104,'Classification Rules'!$B$13:$B$16,0)),"") -> Cloud migration has already forced re-platforming, documentation and specifiability. Highest AI and offshore ceiling in the estate. | AE104: =IFERROR(INDEX('Classification Rules'!$D$43:$D$46,MATCH($AA104,'Classification Rules'!$B$43:$B$46,0)),"") -> 0.4825 | AF104: =IFERROR(INDEX('Classification Rules'!$E$43:$E$46,MATCH($AA104,'Classification Rules'!$B$43:$B$46,0)),"") -> 0.45402025 | AG104: =IFERROR(INDEX('Classification Rules'!$F$43:$F$46,MATCH($AA104,'Classification Rules'!$B$43:$B$46,0)),"") -> 0.78 | AH104: =IFERROR(INDEX('Classification Rules'!$G$43:$G$46,MATCH($AA104,'Classification Rules'!$B$43:$B$46,0)),"") -> 0.7254 | AI104: =IFERROR(INDEX('Classification Rules'!$I$43:$I$46,MATCH($AA104,'Classification Rules'!$B$43:$B$46,0)),"") -> 6-8 weeks per cluster | AJ104: =IFERROR(INDEX('Classification Rules'!$J$43:$J$46,MATCH($AA104,'Classification Rules'!$B$43:$B$46,0)),"") -> Fully sourced, moving to output units | AK104: =IFERROR(INDEX('Classification Rules'!$K$43:$K$46,MATCH($AA104,'Classification Rules'!$B$43:$B$46,0)),"") -> 0
