Workbook

Sheet README
A1: Storage and Preservation Related — domain framework v2
A2: A two-speed 領域, and now modelled as one. K2 is 62.6 of the 106.1 units — agile, hybrid-specification, distributed-proven — and is a value stream on its own. The other fourteen applications are 43.4 units of Japanese-specification waterfall and are the second. There are no pods: every delivery unit is a 12-seat TEAM, 4 + 3 in Year 1 falling to 3 + 1 by Year 4. Productivity lands at 44.6% by Year 5 and offshore at 54.7%, which is the blended archetype ceiling exactly.
A4: WHAT THIS 領域 IS
B5: Fifteen applications, three archetypes | C5: K2 62.6 units (D, distributed-proven, agile, hybrid specifications) · five Japan-locked applications totalling 34.2 · nine long-tail applications totalling 9.3. Two value streams: Policy Owner Servicing Work Flow 86.2 and Payment 19.9.
B6: It is really two domains | C6: K2 is 59.05% of the effort and is modern. Everything else is waterfall with Japanese-language specifications, and five of those are Japan-locked at a 12% offshore ceiling. The two value streams are drawn on exactly that line.
B7: 41 Capgemini people are already here | C7: 36.1 of them on K2 alone. Four are onshore. Banded E2 12 · E3 16 · E4 11 — mid-to-senior, and concentrated on the one modern application.
B8: FSI holds four applications | C8: 7.0 of the 69.426 vendor units — 10.1%. K2 (EAI 12117) 2 · POS-IMS (13453) 2 · W13WEP-JPN (9947) 2 · JP-RPASS (11604) 1. Tapers 7 / 7 / 6 / 5 / 4. Five of the seven sit in the Payment & Records team and two in the Work Flow team; 2 more (1 from Year 4) are held in horizontal H1 as a control cell.
B9: Two applications are marked Retire | C9: C03WRE-JPN and JP-PCI-RPASS, 3.3 units between them, from the disposition columns new in Appendix 3 v5.
A10: THE SHAPE OF THE ANSWER
B11: Offshore closes in full | C11: 16.9% today against a 54.73% ceiling. The design reaches 54.7%: 18.4 / 30.0 / 39.3 / 47.3 / 54.7%. Year 5 gets there by halving the K2 bilingual analyst to 0.5 per team; the onshore technical lead, the Tokyo L2 support hand and design authority are held in every year.
B12: The 50:50 closes with a small transfer | C12: Organic convergence takes Capgemini from 65.1% to 55.2% by Year 3 on its own; a transfer of 3.5 people — 1.5 to MetLife Japan, 2.0 to MGCC — closes the rest and lands the ratio at 49.99%.
B13: K2 is the whole modernisation case | C13: 62.6 units, agile already, a 78% offshore ceiling, and most of our inherited people. If K2 moves, the domain moves — and because the other fourteen never convert, K2 is also the ceiling on how far productivity can go here.
A14: THE ENGINE
B15: Unchanged from Sales / Insurance and Contract Management | C15: Six-rule archetype classifier → AI and offshore ceilings from Golden Inventory v4 → realisation curve → four-gate capability → carry-forward and pre-load → per-sourcing productivity → organic ratio convergence → guardrails → seat ledger.
B16: Seats deploy whole people | C16: Pod Library column K and Horizontal Teams column J are the people you hire for that role across the block. Every one is a whole number or a half — the 0.5-grid check on Change Control is clean in all five years. The SIT Loading sheet turns them into requisitions.
A17: WHAT TO RAISE
B18: The role line is restated | C18: Appendix 3 records 0.14 project-management units and ZERO architecture across fifteen applications, against 1,145 incidents and 2,071 changes. Restated to 5.0 maintenance, 3.0 PM and 2.5 architecture, taken from the developer line — far less than Contract Management needed.
B19: K2 concentration is the delivery risk | C19: 62.6 units and 36.1 of our 41 people on one application. That is the modernisation opportunity and the single point of failure in the same place.
B20: The retirement question | C20: 3.3 units leave the estate. The model holds effort frozen at the Year-1 baseline; if retirement is real the Year-4 and Year-5 baselines should shrink. Decide whether that is a saving we claim or a scope reduction MetLife prices out.
B21: Two streams, teams only | C21: v2 change. K2 is its own value stream; the other fourteen applications are the second, renamed Policy Owner Servicing Payment & Records. Every delivery unit is a 12-seat TEAM: 7 instances in Year 1, then 6, 5, 4 and 4. Headcount 106.0 → 85.0 → 72.5 → 64.5 → 58.5 against Logic Tree targets of 106.08 / 85.15 / 72.30 / 64.30 / 58.77.
B22: Composition is continuous | C22: v3, Capgemini seats only. Every Capgemini role in both team anatomies runs continuously across the five years with a monotone seat ratio — no seat appears, disappears and reappears. Each team keeps a technical lead, a bilingual analyst, a tester, a support seat and design authority in every year. Testers and junior builders are banded E1/E2 and E1 seats exist in all five years. NO SEAT IS EVER RE-BANDED: a grade is fixed for the life of the seat, so the senior share moves only because the number and size of the units move. MetLife FTE, MGCC and FSI seats are byte-identical to v2.

Sheet Basis & Assumptions
A1: Where every input comes from, and which ones are ours
A2: v2. The domain has been restated to two value streams — K2 alone, and the fourteen satellites — running as 12-seat TEAMS only, with no pods in any year. What matters here is the provenance of each input: which are measured, which are restated, and which are domain overrides.
B4: Element | C4: Source | D4: Value used | E4: Status | F4: Note
B5: Baseline | C5: Appendix 3 v5, 15 applications | D5: effort 106.080 · FTC 69.426 · FTE 25.654 · MGCC 11.000 · onshore 62.464 · offshore 6.963 | E5: SOURCE | F5: K2 is row 100; the duplicate K2 line at row 101 is excluded, as MetLife's own total does.
B6: Archetypes | C6: Golden Inventory v4, six-rule classifier | D6: D 1 / 62.642 · J 5 / 34.161 · T 9 / 9.277 | E6: SOURCE | F6: AI ceiling 41.69%, offshore ceiling 54.73%. Five Japan-locked applications at a 12% ceiling are what hold the blend down.
B7: Delivery method | C7: Appendix 3 v5 | D7: K2 agile 62.6 units; the other fourteen waterfall 43.4, and they never convert | E7: MEASURED | F7: Specification language splits the same way: 67.9 hybrid, 38.1 Japanese. Holding Payment & Records as waterfall to Year 5 caps the agile share at 59.05% and is the single biggest brake on the productivity number.
B8: Adoption factors | C8: Portfolio default | D8: 1.00 / 0.85 / 0.80 / 0.55 — unchanged | E8: STANDARD | F8: A largely waterfall, Japanese-language estate. No case for raising MetLife's commitment here.
B9: Role line | C9: BSA 8.642 · DEV 45.389 · TEST 11.775 · MNT 3.483 · PM 0.138 · OTH 0.000 | D9: MNT 5.00 · PM 3.00 · OTH 2.50, taken from DEV | E9: RESTATED | F9: 0.14 PM units and zero architecture across fifteen applications against 1,145 incidents. Arithmetically neutral and far smaller than Contract Management needed.
B10: Partner | C10: FSI named FTC supplied by MetLife against four EAI IDs | D10: 7.000 of 69.426 vendor units — 10.1% | E10: MODELLED | F10: K2 (EAI 12117) 2 · POS-IMS (13453) 2 · W13WEP-JPN (9947) 2 · JP-RPASS (11604) 1, as supplied by MetLife. Tapered 7 / 7 / 6 / 5 / 4. Five sit in the Payment & Records team, two in the Work Flow team, and 2 (1 from Year 4) in horizontal H1 as a control cell.
B11: Inherited workforce | C11: T3 reconciliation behind Golden v4 | D11: 41 people, 4 onshore, 36.1 on K2 | E11: SOURCE | F11: Banded E2 12 · E3 16 · E4 11.
B12: Disposition | C12: New in Appendix 3 v5 | D12: C03WRE-JPN and JP-PCI-RPASS marked Retire — 3.3 units | E12: NEW | F12: Not yet reflected in the baseline; the model holds effort frozen at Year 1. See the README.
B13: Guardrails | C13: Portfolio standard | D13: 50% vendor share · 55% per team · 55% of build-and-test · continuous role coverage | E13: STANDARD | F13: All held in every year. Tightest single team 58.3%. Added in v3: every Capgemini role runs continuously with a monotone ratio, each team holds a lead, an analyst, a tester, support and design authority in all five years, and no seat is re-banded across years — a grade is fixed for the life of the seat.
B14: Transfer | C14: One event at the end of Year 3 | D14: 3.5 people — 1.5 to MetLife Japan, 2.0 to MGCC | E14: MODELLED | F14: Organic convergence runs first, taking Capgemini from 65.1% to 55.2% before anyone moves. Ratio lands at 49.99%.
B15: Delivery structure | C15: Domain override, v2 | D15: TEAMS of 12 only — 4+3 / 4+2 / 3+2 / 3+1 / 3+1 instances | E15: DOMAIN OVERRIDE | F15: No pods anywhere, and team size never moves; instances retire instead. The horizontal layer flexes to reconcile to the Logic Tree target and rises in Year 4 as the last Payment & Records team retires into AMS.
A16: HOW TO READ THE STATUS COLUMN
B17: • SOURCE — taken directly from Appendix 3 v5 or Golden Application Inventory v4. Not ours to change.
B18: • MEASURED — MetLife has supplied it and we use it as given, where an earlier version made us assume.
B19: • RESTATED — the client figure is internally impossible and we have changed it. Every restatement is arithmetically neutral: people move between role lines, the total does not. These go back to MetLife.
B20: • DOMAIN OVERRIDE — a portfolio default deliberately changed for this 領域, with the reason stated. These are solution decisions and should be defended as such in the review.
B21: • MODELLED — a construct of ours with no direct client source: partner plans, transfer sizing, conversion quarters. The assumptions most worth challenging.

Sheet Change Control
A1: Change control — what must still hold after you edit a seat count
A2: Pod Library column J and Horizontal Teams column I are INPUTS. You may change them. Holding the yearly total is necessary but not sufficient — these are the other things that have to survive the edit. Every check below is live. This domain has no PODs, so the POD row reads n/a by construction.
A4: A. WHERE THESE NUMBERS GO
B5: • Pod Library J and Horizontal Teams I are hard-typed values, not formulas. Nothing upstream computes them — they are the design. Everything downstream is derived from them.
B6: • Seat Ledger reads them cell by cell (912 references to Pod Library, 630 to Horizontal Teams) and multiplies by the unit count on Pod Plan. Team Build-Up, Cost & Commercial, Inherited Workforce and Unit Cost Sensitivity are all SUMIFS over the Seat Ledger. Change a seat and every one of them moves.
B7: • THE ONE THAT SURPRISES PEOPLE: the Logic Tree reads the roster back. Partner seats (row 59) drive the partner share (row 60), the span-of-control factor (row 61), the applied operating-model gain (row 43), capability (row 45) and therefore the HEADCOUNT TARGET itself (row 53). Changing partner seats moves the target you are trying to hit. It converges, but it does not stand still.
B8: • What does NOT move: the effort baseline, the archetype mix, the AI and offshore ceilings, the realisation curve and the agile conversion quarters. Those are inputs on the Logic Tree and Delivery Mode.
A10: B. THE INVARIANTS — all of these must stay green
B11: Check | C11: Y1 | D11: Y2 | E11: Y3 | F11: Y4 | G11: Y5 | H11: Tolerance | I11: Status
B12: Headcount delivered minus Logic Tree target | C12: ='Team Build-Up'!C12 | D12: ='Team Build-Up'!D12 | E12: ='Team Build-Up'!E12 | F12: ='Team Build-Up'!F12 | G12: ='Team Build-Up'!G12 | H12: ± 1.5 | I12: =IF(MAX(ABS(C12),ABS(D12),ABS(E12),ABS(F12),ABS(G12))<=1.5,"OK","CHECK") | J12: The productivity commitment. If you add seats you must remove others.
B13: Capgemini share inside each POD | C13: =IFERROR((SUMIFS('Pod Library'!$J$5:$J$160,'Pod Library'!$B$5:$B$160,1,'Pod Library'!$C$5:$C$160,"POD",'Pod Library'!$I$5:$I$160,"FTC")+SUMIFS('Pod Library'!$J$5:$J$160,'Pod Library'!$B$5:$B$160,1,'Pod Library'!$C$5:$C$160,"POD",'Pod Library'!$I$5:$I$160,"PT"))/(SUMIFS('Pod Library'!$J$5:$J$160,'Pod Library'!$B$5:$B$160,1,'Pod Library'!$C$5:$C$160,"POD")),"n/a") | D13: =IFERROR((SUMIFS('Pod Library'!$J$5:$J$160,'Pod Library'!$B$5:$B$160,2,'Pod Library'!$C$5:$C$160,"POD",'Pod Library'!$I$5:$I$160,"FTC")+SUMIFS('Pod Library'!$J$5:$J$160,'Pod Library'!$B$5:$B$160,2,'Pod Library'!$C$5:$C$160,"POD",'Pod Library'!$I$5:$I$160,"PT"))/(SUMIFS('Pod Library'!$J$5:$J$160,'Pod Library'!$B$5:$B$160,2,'Pod Library'!$C$5:$C$160,"POD")),"n/a") | E13: =IFERROR((SUMIFS('Pod Library'!$J$5:$J$160,'Pod Library'!$B$5:$B$160,3,'Pod Library'!$C$5:$C$160,"POD",'Pod Library'!$I$5:$I$160,"FTC")+SUMIFS('Pod Library'!$J$5:$J$160,'Pod Library'!$B$5:$B$160,3,'Pod Library'!$C$5:$C$160,"POD",'Pod Library'!$I$5:$I$160,"PT"))/(SUMIFS('Pod Library'!$J$5:$J$160,'Pod Library'!$B$5:$B$160,3,'Pod Library'!$C$5:$C$160,"POD")),"n/a") | F13: =IFERROR((SUMIFS('Pod Library'!$J$5:$J$160,'Pod Library'!$B$5:$B$160,4,'Pod Library'!$C$5:$C$160,"POD",'Pod Library'!$I$5:$I$160,"FTC")+SUMIFS('Pod Library'!$J$5:$J$160,'Pod Library'!$B$5:$B$160,4,'Pod Library'!$C$5:$C$160,"POD",'Pod Library'!$I$5:$I$160,"PT"))/(SUMIFS('Pod Library'!$J$5:$J$160,'Pod Library'!$B$5:$B$160,4,'Pod Library'!$C$5:$C$160,"POD")),"n/a") | G13: =IFERROR((SUMIFS('Pod Library'!$J$5:$J$160,'Pod Library'!$B$5:$B$160,5,'Pod Library'!$C$5:$C$160,"POD",'Pod Library'!$I$5:$I$160,"FTC")+SUMIFS('Pod Library'!$J$5:$J$160,'Pod Library'!$B$5:$B$160,5,'Pod Library'!$C$5:$C$160,"POD",'Pod Library'!$I$5:$I$160,"PT"))/(SUMIFS('Pod Library'!$J$5:$J$160,'Pod Library'!$B$5:$B$160,5,'Pod Library'!$C$5:$C$160,"POD")),"n/a") | H13: ≥ 55% | I13: =IF(COUNTIF(C13:G13,"<0.5450")=0,"OK","CHECK") | J13: A POD in which Capgemini is a minority is one whose ways of working we do not set.
B14: Capgemini share inside each TEAM | C14: =IFERROR((SUMIFS('Pod Library'!$J$5:$J$160,'Pod Library'!$B$5:$B$160,1,'Pod Library'!$C$5:$C$160,"TEAM",'Pod Library'!$I$5:$I$160,"FTC")+SUMIFS('Pod Library'!$J$5:$J$160,'Pod Library'!$B$5:$B$160,1,'Pod Library'!$C$5:$C$160,"TEAM",'Pod Library'!$I$5:$I$160,"PT"))/(SUMIFS('Pod Library'!$J$5:$J$160,'Pod Library'!$B$5:$B$160,1,'Pod Library'!$C$5:$C$160,"TEAM")),"n/a") | D14: =IFERROR((SUMIFS('Pod Library'!$J$5:$J$160,'Pod Library'!$B$5:$B$160,2,'Pod Library'!$C$5:$C$160,"TEAM",'Pod Library'!$I$5:$I$160,"FTC")+SUMIFS('Pod Library'!$J$5:$J$160,'Pod Library'!$B$5:$B$160,2,'Pod Library'!$C$5:$C$160,"TEAM",'Pod Library'!$I$5:$I$160,"PT"))/(SUMIFS('Pod Library'!$J$5:$J$160,'Pod Library'!$B$5:$B$160,2,'Pod Library'!$C$5:$C$160,"TEAM")),"n/a") | E14: =IFERROR((SUMIFS('Pod Library'!$J$5:$J$160,'Pod Library'!$B$5:$B$160,3,'Pod Library'!$C$5:$C$160,"TEAM",'Pod Library'!$I$5:$I$160,"FTC")+SUMIFS('Pod Library'!$J$5:$J$160,'Pod Library'!$B$5:$B$160,3,'Pod Library'!$C$5:$C$160,"TEAM",'Pod Library'!$I$5:$I$160,"PT"))/(SUMIFS('Pod Library'!$J$5:$J$160,'Pod Library'!$B$5:$B$160,3,'Pod Library'!$C$5:$C$160,"TEAM")),"n/a") | F14: =IFERROR((SUMIFS('Pod Library'!$J$5:$J$160,'Pod Library'!$B$5:$B$160,4,'Pod Library'!$C$5:$C$160,"TEAM",'Pod Library'!$I$5:$I$160,"FTC")+SUMIFS('Pod Library'!$J$5:$J$160,'Pod Library'!$B$5:$B$160,4,'Pod Library'!$C$5:$C$160,"TEAM",'Pod Library'!$I$5:$I$160,"PT"))/(SUMIFS('Pod Library'!$J$5:$J$160,'Pod Library'!$B$5:$B$160,4,'Pod Library'!$C$5:$C$160,"TEAM")),"n/a") | G14: =IFERROR((SUMIFS('Pod Library'!$J$5:$J$160,'Pod Library'!$B$5:$B$160,5,'Pod Library'!$C$5:$C$160,"TEAM",'Pod Library'!$I$5:$I$160,"FTC")+SUMIFS('Pod Library'!$J$5:$J$160,'Pod Library'!$B$5:$B$160,5,'Pod Library'!$C$5:$C$160,"TEAM",'Pod Library'!$I$5:$I$160,"PT"))/(SUMIFS('Pod Library'!$J$5:$J$160,'Pod Library'!$B$5:$B$160,5,'Pod Library'!$C$5:$C$160,"TEAM")),"n/a") | H14: ≥ 55% | I14: =IF(COUNTIF(C14:G14,"<0.5450")=0,"OK","CHECK") | J14: A TEAM in which Capgemini is a minority is one whose ways of working we do not set. Measured across both value-stream anatomies together. Individually: 66.7% / 83.3% (Y1), 58.3% / 70.8% (Y2), 58.3% / 62.5% (Y3), 58.3% / 62.5% (Y4) and 58.3% / 58.3% (Y5). Sourcing mix per team is unchanged from v2 — only the Capgemini (FTC) seat anatomy was re-cut.
B15: Capgemini share of the delivery population | C15: =IFERROR((SUMIFS('Seat Ledger'!$M$5:$M$235,'Seat Ledger'!$B$5:$B$235,1,'Seat Ledger'!$J$5:$J$235,"FTC")+SUMIFS('Seat Ledger'!$M$5:$M$235,'Seat Ledger'!$B$5:$B$235,1,'Seat Ledger'!$J$5:$J$235,"PT"))/(SUMIFS('Seat Ledger'!$M$5:$M$235,'Seat Ledger'!$B$5:$B$235,1)),0) | D15: =IFERROR((SUMIFS('Seat Ledger'!$M$5:$M$235,'Seat Ledger'!$B$5:$B$235,2,'Seat Ledger'!$J$5:$J$235,"FTC")+SUMIFS('Seat Ledger'!$M$5:$M$235,'Seat Ledger'!$B$5:$B$235,2,'Seat Ledger'!$J$5:$J$235,"PT"))/(SUMIFS('Seat Ledger'!$M$5:$M$235,'Seat Ledger'!$B$5:$B$235,2)),0) | E15: =IFERROR((SUMIFS('Seat Ledger'!$M$5:$M$235,'Seat Ledger'!$B$5:$B$235,3,'Seat Ledger'!$J$5:$J$235,"FTC")+SUMIFS('Seat Ledger'!$M$5:$M$235,'Seat Ledger'!$B$5:$B$235,3,'Seat Ledger'!$J$5:$J$235,"PT"))/(SUMIFS('Seat Ledger'!$M$5:$M$235,'Seat Ledger'!$B$5:$B$235,3)),0) | F15: =IFERROR((SUMIFS('Seat Ledger'!$M$5:$M$235,'Seat Ledger'!$B$5:$B$235,4,'Seat Ledger'!$J$5:$J$235,"FTC")+SUMIFS('Seat Ledger'!$M$5:$M$235,'Seat Ledger'!$B$5:$B$235,4,'Seat Ledger'!$J$5:$J$235,"PT"))/(SUMIFS('Seat Ledger'!$M$5:$M$235,'Seat Ledger'!$B$5:$B$235,4)),0) | G15: =IFERROR((SUMIFS('Seat Ledger'!$M$5:$M$235,'Seat Ledger'!$B$5:$B$235,5,'Seat Ledger'!$J$5:$J$235,"FTC")+SUMIFS('Seat Ledger'!$M$5:$M$235,'Seat Ledger'!$B$5:$B$235,5,'Seat Ledger'!$J$5:$J$235,"PT"))/(SUMIFS('Seat Ledger'!$M$5:$M$235,'Seat Ledger'!$B$5:$B$235,5)),0) | H15: ≥ 50% | I15: =IF(COUNTIF(C15:G15,"<0.4950")=0,"OK","CHECK") | J15: Below half the roster we cannot carry a productivity commitment we do not control.
B16: Blocks deploying a non-whole number of people | C16: =SUMPRODUCT(('Pod Library'!$B$5:$B$160=1)*(ABS('Pod Library'!$K$5:$K$160*2-ROUND('Pod Library'!$K$5:$K$160*2,0))>0.01))+SUMPRODUCT(('Horizontal Teams'!$B$5:$B$120=1)*(ABS('Horizontal Teams'!$J$5:$J$120*2-ROUND('Horizontal Teams'!$J$5:$J$120*2,0))>0.01)) | D16: =SUMPRODUCT(('Pod Library'!$B$5:$B$160=2)*(ABS('Pod Library'!$K$5:$K$160*2-ROUND('Pod Library'!$K$5:$K$160*2,0))>0.01))+SUMPRODUCT(('Horizontal Teams'!$B$5:$B$120=2)*(ABS('Horizontal Teams'!$J$5:$J$120*2-ROUND('Horizontal Teams'!$J$5:$J$120*2,0))>0.01)) | E16: =SUMPRODUCT(('Pod Library'!$B$5:$B$160=3)*(ABS('Pod Library'!$K$5:$K$160*2-ROUND('Pod Library'!$K$5:$K$160*2,0))>0.01))+SUMPRODUCT(('Horizontal Teams'!$B$5:$B$120=3)*(ABS('Horizontal Teams'!$J$5:$J$120*2-ROUND('Horizontal Teams'!$J$5:$J$120*2,0))>0.01)) | F16: =SUMPRODUCT(('Pod Library'!$B$5:$B$160=4)*(ABS('Pod Library'!$K$5:$K$160*2-ROUND('Pod Library'!$K$5:$K$160*2,0))>0.01))+SUMPRODUCT(('Horizontal Teams'!$B$5:$B$120=4)*(ABS('Horizontal Teams'!$J$5:$J$120*2-ROUND('Horizontal Teams'!$J$5:$J$120*2,0))>0.01)) | G16: =SUMPRODUCT(('Pod Library'!$B$5:$B$160=5)*(ABS('Pod Library'!$K$5:$K$160*2-ROUND('Pod Library'!$K$5:$K$160*2,0))>0.01))+SUMPRODUCT(('Horizontal Teams'!$B$5:$B$120=5)*(ABS('Horizontal Teams'!$J$5:$J$120*2-ROUND('Horizontal Teams'!$J$5:$J$120*2,0))>0.01)) | H16: =0 | I16: =IF(SUM(C16:G16)=0,"OK","CHECK") | J16: Column K of the Pod Library and column J of Horizontal Teams are the people you hire for that role across the whole block. Every one is a whole number, or a half where one person covers two units INSIDE this domain. The seat ratio beside it is the modelling quantity and will not always be round — on a 28-team block, nine engineers is a ratio of 0.32.
B17: Horizontal roles that have fallen below 0.02 FTE | C17: =COUNTIFS('Horizontal Teams'!$B$5:$B$120,1,'Horizontal Teams'!$I$5:$I$120,"<0.02") | D17: =COUNTIFS('Horizontal Teams'!$B$5:$B$120,2,'Horizontal Teams'!$I$5:$I$120,"<0.02") | E17: =COUNTIFS('Horizontal Teams'!$B$5:$B$120,3,'Horizontal Teams'!$I$5:$I$120,"<0.02") | F17: =COUNTIFS('Horizontal Teams'!$B$5:$B$120,4,'Horizontal Teams'!$I$5:$I$120,"<0.02") | G17: =COUNTIFS('Horizontal Teams'!$B$5:$B$120,5,'Horizontal Teams'!$I$5:$I$120,"<0.02") | H17: =0 | I17: =IF(SUM(C17:G17)=0,"OK","CHECK") | J17: A domain cannot run without a delivery head, a service manager or an architect. If a role must genuinely end, delete the row rather than leaving it at zero.
B18: Year-1 reconciliation to Appendix 3 — worst line | C18: ='Team Build-Up'!E32 | H18: ± 2.6 | I18: =IF(ABS(C18)<=2.6,"OK","CHECK") | J18: Year 1 must reproduce the client's own numbers: effort, the sourcing split, all three locations and all six role lines. The tolerance is ± 2.6 because seats sit on a 0.5 grid and a Year-1 team seat carries a multiplier of 5 — one grid step is 2.5 people. That is the deliberate price of an anatomy that can be staffed. Moving a seat between bands is free; moving it between ROLE, LOCATION or SOURCING is what actually breaks this.
A20: C. WHAT GOES STALE AND WILL NOT WARN YOU
B21: • SOURCING & PRODUCTIVITY is static. It is produced outside Excel by the per-sourcing solver and pasted in. If you change seat counts, the pool ceilings, the organic-convergence table and the transfer solve on that sheet no longer describe this roster. Re-run the solver or treat the sheet as superseded.
B22: • SIT LOADING is static for the same reason. Re-generate it after any seat change, or the requisition plan will not match the ledger.
B23: • The TRANSFER on the Logic Tree is a typed input (rows 65-66), sized on the Year-3 exit position produced by the solver. Change the Year-3 roster materially and the transfer needs re-sizing, or the 50:50 will not land.
B24: • THE RULE OF THUMB. Re-banding a seat, renaming it, or moving it between pods is safe. Changing its ROLE, LOCATION or SOURCING is not — those are the attributes Year 1 reconciles on and the guardrails measure.

Sheet Logic Tree
A1: Logic Tree — ten parametric drivers, five years
A2: Amber cells are inputs. Everything else re-derives. Section F is rebuilt on the measured day-1 position.
A4: A. BASELINE — Appendix 3 v5, read and never edited
B5: Domain | C5: Storage and Preservation Related
B6: Applications | C6: 15
B7: Total effort (units) | C7: 106.0802
B8: Current FTC reported (Capgemini + partner) | C8: 69.4261 | D8: 7 | E8: — of which FSI (partner) | J8: FSI IS 7.0 OF THE 69.4261. Appendix 3 v5 reports the vendor as a single FTC number, so the partner sits inside it. The seven seats are EAI 12117 (K2) 2 · 13453 (POS-IMS) 2 · 9947 (W13WEP-JPN) 2 · 11604 (JP-RPASS) 1. Two of the seven are held in the horizontal control cell in Years 1-3 and one in Years 4-5; the rest sit in the value-stream team that owns the application.
B9: Current FTE | C9: 25.6542
B10: Current MGCC | C10: 11
B11: — of which onshore Tokyo | C11: 62.4636 | J11: 17.96 of the 106.08 units are already away from Tokyo — 6.96 offshore on the Capgemini side and 11.00 in MGCC. 62.46 vendor units are in Tokyo today, and eleven of the fifteen applications run on Japanese-language specifications.
B12: — of which offshore | C12: 6.9625
B13: — of which nearshore | C13: 0
B14: — of which onsite | C14: 0
B15: Role: BSA | C15: 8.6415
B16: Role: Developer | C16: 45.3887 | J16: All six role lines are populated for this domain and are used exactly as reported. No restatement was needed.
B17: Role: Tester | C17: 11.775
B18: Role: Maintenance | C18: 3.4833
B19: Role: PM | C19: 0.1375
B20: Role: Other | C20: 0
B21: AD effort (% of PRJ weighted) | C21: 88.4585
B22: Appendix 3 Year-3 target, each side | C22: 53.0464
B23: Ratio today — Capgemini share | C23: =C8/(C8+C9+C10)
B24: OFFSHORE TODAY — whole team, measured | C24: =(C12+C13+C10)/C7 | J24: 16.94% on day one. That is the measured start, not an assumption, and it is the number the whole offshore case has to move. The design closes the entire gap to the 54.73% ceiling by Year 5.
A26: B. ARCHETYPE MIX — from the Golden Application Inventory v4
B27: Archetype | C27: Name | D27: Apps | E27: Effort | F27: Share | G27: AI ceiling | H27: Offshore ceiling
B28: D | C28: Distributed-proven | D28: 1 | E28: 62.6424 | F28: =E28/$E$33 | G28: 0.4825 | H28: 0.78
B29: J | C29: Japan-locked | D29: 5 | E29: 34.1612 | F29: =E29/$E$33 | G29: 0.304 | H29: 0.12
B30: T | C30: Long tail | D30: 9 | E30: 9.2767 | F30: =E30/$E$33 | G30: 0.39 | H30: 0.55
C33: Total | D33: =SUM(D28:D32) | E33: =SUM(E28:E32) | F33: =SUM(F28:F32)
B34: APPLICABLE AI CEILING | C34: =SUMPRODUCT($E$28:$E$32,$G$28:$G$32)/$E$33 | J34: 41.69% on the golden phase mix. One D application at a 48.25% ceiling carries 59% of the effort; the five J applications behind it carry 30.4% and the nine T applications 39%. No domain-specific override is applied.
B35: APPLICABLE OFFSHORE CEILING | C35: =SUMPRODUCT($E$28:$E$32,$H$28:$H$32)/$E$33 | J35: 54.73%. K2 alone carries a 78% ceiling, but the five Japan-locked applications carry 12% and the long tail 55%. This is the hard constraint in this 領域 and the design now closes all of it.
A37: C. REALISATION AND THE NON-AI COMPONENTS
B38: Driver | C38: Year 1 | D38: Year 2 | E38: Year 3 | F38: Year 4 | G38: Year 5 | H38: Basis
B39: AI realisation — share of ceiling | C39: 0.22 | D39: 0.5 | E39: 0.68 | F39: 0.79 | G39: 0.86 | J39: Adoption, guardrails and substrate maturity, held DELIBERATELY BELOW the portfolio curve. K2 is 59% of this domain and its rules are carried in Japanese-language specifications and a hand-built VB.NET workflow; the constraint on AI realisation here is domain knowledge, not tooling. Capped at 86% in Year 5 rather than 90%.
B40: Classical ADM productivity, cumulative | C40: 0.02 | D40: 0.05 | E40: 0.07 | F40: 0.09 | G40: 0.11 | J40: Standardisation, defect reduction, shift-left.
B41: Operating-model productivity, RAW | C41: 0.03 | D41: 0.06 | E41: 0.08 | F41: 0.1 | G41: 0.12 | J41: Pod consolidation and one release train — only available where the stream is agile.
B42: Agile share of the domain → from the Delivery Mode sheet | C42: ='Delivery Mode'!C18 | D42: ='Delivery Mode'!D18 | E42: ='Delivery Mode'!E18 | F42: ='Delivery Mode'!F18 | G42: ='Delivery Mode'!G18
B43: Operating-model productivity, APPLIED = raw × agile share × span-of-control factor | C43: =C41*C42*C61 | D43: =D41*D42*D61 | E43: =E41*E42*E61 | F43: =F41*F42*F61 | G43: =G41*G42*G61 | J43: Scaling by the agile share is what makes the operating-model gain earned rather than assumed. Payment & Records never converts — fourteen Japanese-specification waterfall applications run as a waterfall team to Year 5 — so the agile share can never exceed K2’s 59.05% share of the estate. That caps the operating-model gain at 7.1% of its raw value by Year 5.
B44: AI-attributable productivity | C44: =$C$34*C39 | D44: =$C$34*D39 | E44: =$C$34*E39 | F44: =$C$34*F39 | G44: =$C$34*G39
B45: CAPABILITY EARNED by end of year | C45: =1-(1-C44)*(1-C40)*(1-C43) | D45: =1-(1-D44)*(1-D40)*(1-D43) | E45: =1-(1-E44)*(1-E40)*(1-E43) | F45: =1-(1-F44)*(1-F40)*(1-F43) | G45: =1-(1-G44)*(1-G40)*(1-G43)
A47: D. CARRY-FORWARD AND PRE-LOAD — what is applied to headcount
B48: Pre-load fraction of the in-year gain | C48: 0.5
C49: Year 1 | D49: Year 2 | E49: Year 3 | F49: Year 4 | G49: Year 5
B50: Banked from the prior year | C50: =0 | D50: =C45 | E50: =D45 | F50: =E45 | G50: =F45
B51: Pre-load of this year's gain | C51: =0 | D51: =$C$48*(D45-C45) | E51: =$C$48*(E45-D45) | F51: =$C$48*(F45-E45) | G51: =$C$48*(G45-F45)
B52: APPLIED TO STAFFING | C52: =C50+C51 | D52: =D50+D51 | E52: =E50+E51 | F52: =F50+F51 | G52: =G50+G51
B53: Headcount target = baseline x (1 - applied) | C53: =$C$7*(1-C52) | D53: =$C$7*(1-D52) | E53: =$C$7*(1-E52) | F53: =$C$7*(1-F52) | G53: =$C$7*(1-G52)
B54: EXIT YEAR 3 — full realisation, the point the transfer is struck | E54: =$C$7*(1-E45)
A56: E. PARTNER — the fourth sourcing type, and what it costs
B57: FSI is the named incumbent on four applications — K2 (EAI 12117), POS-IMS (13453), W13WEP-JPN (9947) and JP-RPASS (11604) — 7.0 of the 69.426 vendor units, or 10.1%. Three of the four are waterfall, Japanese-specification and Japan-locked; the fourth is K2 itself. Appendix 3 reports them inside the vendor number, so FTC reported = Capgemini + partner. The taper is 7 / 7 / 6 / 5 / 4.
B58: Measure | C58: Year 1 | D58: Year 2 | E58: Year 3 | F58: Year 4 | G58: Year 5 | H58: Basis
B59: Partner seats — from the seat ledger | C59: ='Team Build-Up'!C46 | D59: ='Team Build-Up'!D46 | E59: ='Team Build-Up'!E46 | F59: ='Team Build-Up'!F46 | G59: ='Team Build-Up'!G46
B60: Partner share of the delivery population | C60: =IF('Team Build-Up'!C9=0,0,C59/'Team Build-Up'!C9) | D60: =IF('Team Build-Up'!D9=0,0,D59/'Team Build-Up'!D9) | E60: =IF('Team Build-Up'!E9=0,0,E59/'Team Build-Up'!E9) | F60: =IF('Team Build-Up'!F9=0,0,F59/'Team Build-Up'!F9) | G60: =IF('Team Build-Up'!G9=0,0,G59/'Team Build-Up'!G9) | J60: Partner seats cannot transfer to MetLife. They sit on the Capgemini side of the 50:50 permanently, which is why the plan tapers FSI 7 → 7 → 6 → 5 → 4 rather than holding it flat. Two of the seven are held in the horizontal control cell in Years 1-3 and one in Years 4-5, so the partner relationship is governed and not only consumed.
B61: Span-of-control factor = 1 − drag × partner share | C61: =1-$C$62*C60 | D61: =1-$C$62*D60 | E61: =1-$C$62*E60 | F61: =1-$C$62*F60 | G61: =1-$C$62*G60
B62: Partner drag — INPUT | C62: 0.6 | J62: A partner seat returns 40% of the operating-model gain a Capgemini seat does: two management chains, a contractual boundary on ways of working, slower standardisation. At an 18.9% Year-1 partner share this costs real capability, and the drag is the one number to argue about here.
A64: F. OFFSHORE — a measured start, a re-cut ceiling, and three bases to report on
B65: THIS IS THE CONSTRAINED CASE, AND THE DESIGN CLOSES IT IN FULL. K2 is archetype D and carries a 78% ceiling, but the five J applications behind it carry 12% and the nine T applications 55%. Eleven of the fifteen applications run on Japanese-language specifications. The blended ceiling is 54.73% against a measured 16.94% today, and Year 5 lands on the ceiling while still holding an onshore technical lead in every team.
B66: Driver | C66: Year 1 | D66: Year 2 | E66: Year 3 | F66: Year 4 | G66: Year 5 | H66: Basis
B67: Gap closure — share of (ceiling − today) reached | C67: 0.03 | D67: 0.35 | E67: 0.6 | F67: 0.8031 | G67: 1 | J67: Year 1 holds the position it inherits. Year 5 closes the WHOLE gap and sits on the blended ceiling. Year 4 is set to what the roster delivers (47.3%) rather than to the ceiling, because the Year-4 anatomy keeps a full onshore technical lead in every K2 team, an onshore bilingual analyst in both streams and a Tokyo support hand on the Japan-locked satellites. In Year 5 the K2 bilingual analyst halves to 0.5 per team — one analyst across two teams — which is what buys the last 2.6 points.
B68: TARGET OFFSHORE SHARE, whole team | C68: =$C$24+($C$35-$C$24)*C67 | D68: =$C$24+($C$35-$C$24)*D67 | E68: =$C$24+($C$35-$C$24)*E67 | F68: =$C$24+($C$35-$C$24)*F67 | G68: =$C$24+($C$35-$C$24)*G67
B69: Delivered — whole team | C69: ='Team Build-Up'!C54 | D69: ='Team Build-Up'!D54 | E69: ='Team Build-Up'!E54 | F69: ='Team Build-Up'!F54 | G69: ='Team Build-Up'!G54
B70: Delivered — vendor only (Capgemini + partner) | C70: ='Team Build-Up'!C55 | D70: ='Team Build-Up'!D55 | E70: ='Team Build-Up'!E55 | F70: ='Team Build-Up'!F55 | G70: ='Team Build-Up'!G55
B71: Delivered — Capgemini payroll only | C71: ='Team Build-Up'!C56 | D71: ='Team Build-Up'!D56 | E71: ='Team Build-Up'!E56 | F71: ='Team Build-Up'!F56 | G71: ='Team Build-Up'!G56 | J71: THE LINE THAT MATTERS COMMERCIALLY. Capgemini’s own payroll is far more offshore than the whole team throughout, because the onshore seats are disproportionately MetLife’s and FSI’s. The Year-3 transfer moves only 6 people, so the Capgemini offshore book survives the event and keeps climbing after it.
A73: G. TRANSFER OF EMPLOYMENT — one event, end of Year 3, Capgemini payroll only
B74: Transfer in year | C74: Year 1 | D74: Year 2 | E74: Year 3 | F74: Year 4 | G74: Year 5
B75: Capgemini Japan to MetLife Japan (FTE) | C75: 0 | D75: 0 | E75: 1.5 | F75: 0 | G75: 0 | J75: FSI SEATS CANNOT MOVE. The whole transfer comes out of Capgemini payroll, which at the Year-3 exit is 31.7 of the 37.2 vendor units — FSI holds 5.6 by then. 3.5 people is 11% of our own population here, comfortably inside the 70% cap, and it lands the ratio at 49.99%.
B76: Capgemini India to MetLife MGCC | C76: 0 | D76: 0 | E76: 2 | F76: 0 | G76: 0
B77: Cumulative transferred | C77: =SUM($C$75:C76) | D77: =SUM($C$75:D76) | E77: =SUM($C$75:E76) | F77: =SUM($C$75:F76) | G77: =SUM($C$75:G76) | J77: 1.5 to MetLife Japan from the Capgemini Japan population; 2.0 to MGCC from the Capgemini India population. MGCC runs 11.0 units here on day one and grows to 13.5 by Year 5 — it is the main vehicle for the offshore move, which is why only a small transfer is needed to close the ratio.
A79: H. COST INDEX — relative only, onshore Tokyo E2 = 1.00
B80: Location | C80: E1 | D80: E2 | E80: E3 | F80: E4 | G80: E5
B81: Onshore Tokyo | C81: 0.72 | D81: 1 | E81: 1.35 | F81: 1.85 | G81: 2.55
B82: Offshore Hyderabad | C82: 0.22 | D82: 0.3 | E82: 0.42 | F82: 0.6 | G82: 0.85
B83: Nearshore | C83: 0.45 | D83: 0.62 | E83: 0.84 | F83: 1.15 | G83: 1.58
B84: Nearshore is ZERO on this domain — every unit is either Tokyo or India, and 62.5 of the 69.4 vendor units are Tokyo today. The NEAR rows are carried so all eleven domain models share one schema. | I84: key | J84: E1 | K84: E2 | L84: E3 | M84: E4 | N84: E5
I85: ON | J85: 0.72 | K85: 1 | L85: 1.35 | M85: 1.85 | N85: 2.55
I86: OFF | J86: 0.22 | K86: 0.3 | L86: 0.42 | M86: 0.6 | N86: 0.85
I87: NEAR | J87: 0.45 | K87: 0.62 | L87: 0.84 | M87: 1.15 | N87: 1.58
I88: Lookup block for the Seat Ledger. Mirrors the table on the left.

Sheet Sourcing & Productivity
A1: Sourcing and productivity — the same chain, applied differently to each population
A2: Productivity is not one number applied to everybody. The four populations do different work and we do not control all four, so each carries its own AI ceiling and its own adoption factor. This sheet is regenerated from the restated two-stream, team-only roster.
A4: A. WHY ONE RATE CANNOT APPLY TO ALL THREE — the Year-1 role mix
B5: Population | C5: Heads Y1 | D5: BSA | E5: Developer | F5: Tester | G5: Maint.
B6: FTC · Capgemini payroll | C6: 62 | D6: 0.11290323 | E6: 0.52419355 | F6: 0.20967742 | G6: 0.072580645 | I6: MetLife’s own people are governance, domain SME and product ownership. MGCC is build, test and application support. FSI is Japanese-specification development and analysis on four named applications. They are not doing the same work, so they cannot carry the same productivity rate.
B7: PT · Partner (sub-contracted) | C7: 7 | D7: 0.21428571 | E7: 0.5 | F7: 0 | G7: 0.28571429
B8: FTE · MetLife Japan | C8: 26 | D8: 0.28846154 | E8: 0 | F8: 0 | G8: 0.19230769
B9: MGCC · MetLife MGCC | C9: 11 | D9: 0 | E9: 0.81818182 | F9: 0.18181818 | G9: 0
A11: B. EACH POPULATION'S OWN AI CEILING AND ADOPTION — INPUT
B12: Population | C12: Own AI ceiling | D12: Adoption | E12: Effective ceiling | F12: vs domain blend
B13: FTC · Capgemini payroll | C13: 0.4345 | D13: 1 | E13: 0.4345 | F13: 0.0176 | I13: ADOPTION is the share of the ceiling each population can actually realise, and it is a judgement about AUTHORITY, not capability. We build the tooling, set the ways of working and mandate them on our own payroll — so 1.00. Everything below that is somebody else’s decision. The four ceilings are scaled so that the Year-1 head-weighted blend reproduces the Logic Tree’s 41.69%.
B14: PT · Partner (sub-contracted) | C14: 0.4211 | D14: 0.85 | E14: 0.3579 | F14: -0.059
B15: FTE · MetLife Japan | C15: 0.3591 | D15: 0.55 | E15: 0.1975 | F15: -0.2194
B16: MGCC · MetLife MGCC | C16: 0.4517 | D16: 0.8 | E16: 0.3613 | F16: -0.0556
B17: Domain blended ceiling (the headline commitment, from the Logic Tree) | C17: 0.4169
B18: Only the AI gate is scaled. Classical ADM productivity attaches to the work and the operating-model gain attaches to the delivery unit, so both flow to every population regardless of employer.
A20: C. WHAT EACH POPULATION IS THEREFORE ASKED TO DELIVER
B21: Applied to staffing | C21: Year 1 | D21: Year 2 | E21: Year 3 | F21: Year 4 | G21: Year 5
B22: FTC · Capgemini payroll | C22: 0 | D22: 0.2032 | E22: 0.3278 | F22: 0.4051 | G22: 0.4583 | I22: The headline commitment is 44.6% by Year 5 — deliberately below the portfolio, because K2 is 59% of this domain and its business rules live in Japanese-language specifications, and because the fourteen satellites never convert to agile. What has changed is that the commitment is no longer assumed to fall equally on all four populations.
B23: PT · Partner (sub-contracted) | C23: 0 | D23: 0.1775 | E23: 0.2871 | F23: 0.356 | G23: 0.4049
B24: FTE · MetLife Japan | C24: 0 | D24: 0.1236 | E24: 0.2019 | F24: 0.2532 | G24: 0.2933
B25: MGCC · MetLife MGCC | C25: 0 | D25: 0.1786 | E25: 0.2889 | F25: 0.3582 | G25: 0.4073
B26: Whole-domain commitment (the headline) | C26: 0 | D26: 0.1973 | E26: 0.3185 | F26: 0.3938 | G26: 0.446
A28: D. THE THREE-WAY COMMITMENT SPLIT
B29: CAPGEMINI COMMITS | C29: Our own headcount reduction, on our own payroll, on tooling and ways of working we control. This is contractible and we should contract it.
B30: METLIFE MUST DELIVER | C30: The reduction of MetLife Japan and MGCC headcount. We size it, we enable it and we report it — but redeploying MetLife's own people is MetLife's decision, and MGCC runs to its own utilisation targets. This should be a joint commitment with named owners, not a Capgemini SLA.
B31: JOINTLY DEPENDENT | C31: AI adoption on MetLife's side: tooling access, shared standards, common telemetry, and the substrate being used rather than merely available. If adoption lands below the factors in section B, the whole-team headcount misses even if Capgemini delivers in full.
A33: E. ORGANIC CONVERGENCE TO 50:50 — before any transfer
B34: Measure | C34: Year 1 | D34: Year 2 | E34: Year 3 | F34: Year 4 | G34: Year 5
B35: MetLife Japan (FTE) — own curve | C35: 26 | D35: 21 | E35: 17.5 | F35: 17.5 | G35: 14 | I35: MetLife’s populations follow their own slower curves; MGCC grows as a share as offshore work lands there. Capgemini absorbs the balance, which means we shrink our own book faster than productivity alone would justify. That extra reduction is a deliberate commercial choice to reach the ratio organically rather than by transferring people.
B36: MetLife MGCC — own curve | C36: 11 | D36: 13 | E36: 15 | F36: 14 | G36: 13.5
B37: Partner — per the partner plan | C37: 7 | D37: 7 | E37: 6 | F37: 5 | G37: 4
B38: Capgemini — absorbs the balance | C38: 62 | D38: 44 | E38: 34 | F38: 28 | G38: 27
B39: TOTAL = the headline commitment | C39: 106 | D39: 85 | E39: 72.5 | F39: 64.5 | G39: 58.5
B40: RATIO — Capgemini share | C40: 0.6509 | D40: 0.6 | E40: 0.5517 | F40: 0.5116 | G40: 0.5299
B41: — of which productivity-driven | C41: 0 | D41: 0.1973 | E41: 0.3185 | F41: 0.3938 | G41: 0.446
B42: — of which RATIO-DRIVEN: fall in the Capgemini share since Year 1 | C42: 0 | D42: 0.0509 | E42: 0.0992 | F42: 0.1393 | G42: 0.121
B44: This is the mechanism that halves the transfer. Reaching the ratio by shrinking our own book is cheaper, lower-risk and entirely within our control; a transfer of employment is neither.
A46: F. THE GUARDRAILS — where organic convergence has to stop
B47: Test | C47: Year 1 | D47: Year 2 | E47: Year 3 | F47: Year 4 | G47: Year 5 | H47: Floor
B48: Capgemini share of the delivery population | C48: 0.6509 | D48: 0.6 | E48: 0.5517 | F48: 0.5116 | G48: 0.5299 | H48: 0.5 | I48: THE POINT OF THE FLOOR. If Capgemini becomes a minority of the delivery population, or of the build-and-test seats, or of any single team, we no longer set the ways of working — and a productivity commitment we cannot enforce is not a commitment. The tightest single team in any year is 58.3%.
B49: Capgemini share of build-and-test seats | C49: 0.8167 | D49: 0.7363 | E49: 0.7027 | F49: 0.619 | G49: 0.619 | H49: 0.55
B50: Capgemini share inside every single delivery unit | C50: held | D50: held | E50: held | F50: held | G50: held | H50: 0.55
A52: G. THE TRANSFER — only what organic convergence cannot reach
C53: Value
B54: Exit Year 3 headcount, full realisation | C54: 67.5115
B55: Vendor units at exit, after organic convergence | C55: 37.2477
B56: Transferable pool — Capgemini payroll only | C56: 31.6605
B57: 50:50 requires each side to be | C57: 33.7557
B58: TRANSFER REQUIRED | C58: 3.492
B59: Maximum transferable at the 70% cap | C59: 22.1624
B60: Transfer applied | C60: 3.5
B61: — to MetLife Japan | C61: 1.5
B62: — to MGCC | C62: 2
B63: RESIDUAL GAP TO 50:50 | C63: -0.008
B64: Ratio reached at the Year-3 exit | C64: 0.4999

Sheet Delivery Mode
A1: Delivery mode — measured per application, and the conversion that never happens
A2: Appendix 3 v5 supplies the development method for fourteen of the fifteen applications. K2 and DSP are agile — 63.6 of the 106.1 units — and the other twelve are waterfall. The domain is now modelled on that split: K2 is its own stream and converts at Q2; the fourteen satellites are one waterfall team that runs to Year 5 without converting at all.
A4: A. MODE TODAY AND TARGET, BY VALUE STREAM — INPUT
B5: Value stream | C5: Effort | D5: Archetype | E5: Mode today | F5: Agile from | G5: Why
B6: POSW · Policy Owner Servicing Work Flow (K2 only) | C6: 62.6424 | D6: D | E6: Agile | F6: Q2 | G6: K2 is 59.05% of the domain on its own and carries 34.1 of our inherited people. Agile already, hybrid specifications, 78% offshore ceiling. | I6: The mode column is MetLife’s own data. The two streams are now K2 (1 application, 62.642 units) and everything else (14 applications, 43.438 units). K2 converts at Q2. The satellites do not convert — that is the input to argue about, and it is the reason productivity here is capped below the portfolio.
B7: POSR · Policy Owner Servicing Payment & Records (14 applications) | C7: 43.4378 | D7: J / T | E7: Waterfall | F7: never | G7: Eleven Japanese-specification applications, five of them Japan-locked at a 12% offshore ceiling, two marked Retire. Runs as a waterfall team for all five years.
B8: Total | C8: =SUM(C6:C7)
A10: B. AGILE SHARE BY YEAR — computed from the quarter each stream converts
B11: Value stream | C11: Year 1 | D11: Year 2 | E11: Year 3 | F11: Year 4 | G11: Year 5
B12: POSW | C12: 0.75 | D12: 1 | E12: 1 | F12: 1 | G12: 1
B13: POSP | C13: 0 | D13: 0 | E13: 0 | F13: 0 | G13: 0
B14: Effort-weighted agile share of the domain | C14: =SUMPRODUCT($C$6:$C$7,C12:C13)/$C$8 | D14: =SUMPRODUCT($C$6:$C$7,D12:D13)/$C$8 | E14: =SUMPRODUCT($C$6:$C$7,E12:E13)/$C$8 | F14: =SUMPRODUCT($C$6:$C$7,F12:F13)/$C$8 | G14: =SUMPRODUCT($C$6:$C$7,G12:G13)/$C$8
B16: Delivery units this produces
B17: — agile PODS (none in this domain) | C17: 0 | D17: 0 | E17: 0 | F17: 0 | G17: 0
B18: — agile share (feeds the Logic Tree) | C18: =C14 | D18: =D14 | E18: =E14 | F18: =F14 | G18: =G14
B19: — TEAMS of 12 (instances) | C19: 7 | D19: 6 | E19: 5 | F19: 4 | G19: 4
A21: C. WHY THIS MATTERS TO THE NUMBER
B22: • Operating-model productivity — pod consolidation, one release train, span of control — is only available where the stream actually runs agile, and here that is K2 and nothing else. Scaling the 3 / 6 / 8 / 10 / 12% curve by the agile share (44.3% in Year 1, 59.05% thereafter) and by the span-of-control factor cuts the Year-5 gain from 12.0% to 7.0%. This is the single largest reason the productivity commitment here is 44.6% and not 50%.
B23: • Every delivery unit is a TEAM of 12 seats, in every year, in both streams. Team size never moves; instances retire instead — 4+3 in Year 1, then 4+2, 3+2, 3+1 and 3+1. Both anatomies carry MGCC seats from day one, which is what makes this domain’s offshore movement cheap: the substrate is already there.
B24: • Year 4 is the structural break: the last Payment & Records team retires and its residual run work moves to the horizontal layer, which is why horizontal rises from 12.5 to 16.5 that year before falling to 10.5 in Year 5.
B25: • DECIDE whether Payment & Records ever converts. Holding it as waterfall to Year 5 is the conservative reading and costs about 4 points of Year-5 capability. If MetLife will accept agile on even half of those fourteen applications from Year 3, the commitment moves back above 47%.

Sheet AMS & Ticket Load
A1: AMS and ticket load — the run team sized from evidence, for the first time
A2: 1,145 incidents and 2,071 changes over 32 months, from Appendix 3 v5.
A4: A. RECORDED VOLUMES — 1 Jan 2024 to 31 Aug 2026
B5: Measure | C5: Volume | D5: Per month | E5: Per unit of effort | F5: Share
B6: P1 — critical | C6: 0 | D6: =C6/$C$17 | E6: =C6/'Logic Tree'!$C$7 | F6: =C6/$C$11 | I6: No P1 or P2 incidents at all in 32 months and 71% of incidents at P5. The estate is stable; the cost is in changing it, not in keeping it up.
B7: P2 — high | C7: 0 | D7: =C7/$C$17 | E7: =C7/'Logic Tree'!$C$7 | F7: =C7/$C$11
B8: P3 — medium | C8: 179 | D8: =C8/$C$17 | E8: =C8/'Logic Tree'!$C$7 | F8: =C8/$C$11
B9: P4 — low | C9: 153 | D9: =C9/$C$17 | E9: =C9/'Logic Tree'!$C$7 | F9: =C9/$C$11
B10: P5 — informational | C10: 813 | D10: =C10/$C$17 | E10: =C10/'Logic Tree'!$C$7 | F10: =C10/$C$11
B11: All incidents | C11: =SUM(C6:C10) | D11: =C11/$C$17 | E11: =C11/'Logic Tree'!$C$7
B12: Emergency change | C12: 115 | D12: =C12/$C$17 | E12: =C12/'Logic Tree'!$C$7 | F12: =C12/$C$15 | I12: 84% Standard and 4.3% Emergency. A high-volume, low-severity, highly repeatable change profile — the best automation case in the portfolio.
B13: Normal change | C13: 233 | D13: =C13/$C$17 | E13: =C13/'Logic Tree'!$C$7 | F13: =C13/$C$15
B14: Standard change | C14: 1723 | D14: =C14/$C$17 | E14: =C14/'Logic Tree'!$C$7 | F14: =C14/$C$15
B15: All changes | C15: =SUM(C12:C14) | D15: =C15/$C$17 | E15: =C15/'Logic Tree'!$C$7
B17: Observation window, months | C17: 32
A19: B. SIZING THE RUN TEAM — three independent bases, triangulated
B20: Basis | C20: Value | D20: Reading
B21: A. Maintenance role reported in Appendix 3 v5 | C21: ='Logic Tree'!C18 | D21: MetLife's own HEADCOUNT view. Populated here, unlike Contract Management, so it is usable.
B22: B. Run effort implied by the AD / AMS split = (1 − AD share) x effort | C22: ='Logic Tree'!C7-'Logic Tree'!C21 | D22: MetLife's own EFFORT view: 13.5% of 100.765 units. It implies 2.4 times the run population the role line does, and both numbers come from the same spreadsheet.
B23: Total demand items per month (incidents + changes) | C23: =(C11+C15)/C17 | D23: 2,536 items in 32 months — 25.2 per unit of effort against 14.6 on Sales. High for a three-application estate, and 84% of the changes are Standard.
B24: C. Throughput implied by basis A — items per person per month | C24: =IFERROR(C23/C21,0) | D24: If the role line is right, each run person absorbs this many items a month.
B25: C. Throughput implied by basis B | C25: =IFERROR(C23/C22,0) | D25: If the effort split is right, this is the rate. Industry L2 throughput on a modern data stack is 40 to 80 items per person per month; both of these sit far below it, which says these items carry investigation rather than triage.
B26: Run-facing seats in the Year-1 roster (Maintenance + Tester, all sourcing) | C26: ='Team Build-Up'!C64+'Team Build-Up'!C63 | D26: Model output. Sized on the role line, which is the binding Year-1 reconciliation constraint, and reported here against the other two bases rather than averaged with them.
A28: C. WHAT THE TICKET DATA CHANGES
B29: • MetLife's two views of the run population disagree by a factor of 2.4. The Maintenance role line says 5.67 units; the AD / AMS effort split says 13.64. This model follows the role line, because Year 1 has to reconcile to Appendix 3 line by line — but the difference is 8 people and it is a real commercial exposure. PUT THIS TO METLIFE before the AMS price is fixed.
B30: • The severity profile is benign and the change profile is not. No P1 or P2 incidents in 32 months and 71% of incidents at P5 — this estate is stable. But 1,730 changes on 100.8 units, 84% of them Standard, is a high change rate, and Standard changes on a cloud data platform are exactly what pipeline automation and a release train remove. That is where the operating-model productivity in this domain actually comes from.
B31: • Ticket density is 25.2 items per unit of effort against 14.6 on Sales — the highest of the domains modelled so far. Combined with a 13.5% run share it suggests run work is sitting inside the Developer line, which is the same pattern Sales shows and the reason this cross-check is worth running on every domain.
B32: • DO ask MetLife which of the two run figures governs, and ask for the ticket-to-effort mapping behind the AD / AMS split. On a three-application domain this is a short conversation with a material price attached.

Sheet Inventory
A1: Inventory — the 15 Storage and Preservation Related applications from Appendix 3 v5
A2: Classified by the six-rule classifier on the Golden Application Inventory v4.
B4: Application | C4: Arch | D4: Effort | E4: FTC | F4: FTE | G4: Onshore | H4: Nearshore | I4: Nearsh % | J4: BSA | K4: Dev | L4: AD % | M4: Crit | N4: Method | O4: Spec lang | P4: Lines of code | Q4: Batches | R4: Incidents | S4: Changes | T4: Primary code language | U4: Value stream | V4: FSI FTC | W4: EAI ID
B5: K2 | C5: D | D5: 62.6424 | E5: 36.1049 | F5: 15.5375 | G5: 29.959 | H5: 0 | I5: =IFERROR($H5/$D5,0) | J5: 8.6415 | K5: 13.1092 | L5: 0.8631983 | M5: Y | N5: Agile | O5: Hybrid | P5: 0 | Q5: 37 | R5: 350 | S5: 794 | T5: VB.NET | U5: POSW | V5: 2 | W5: 12117
B6: POS-IMS | C6: J | D6: 9.9625 | E6: 9.6625 | F6: 0.3 | G6: 9.6625 | H6: 0 | I6: =IFERROR($H6/$D6,0) | J6: 0 | K6: 8.8625 | L6: 0.90440252 | M6: N | N6: Waterfall | O6: JP | P6: 1972920 | Q6: 57 | R6: 124 | S6: 199 | T6: VB.NET; JAVA | U6: POSR | V6: 2 | W6: 13453
B7: JP-RPASS | C7: J | D7: 9.7375 | E7: 5.6625 | F7: 4.075 | G7: 5.6625 | H7: 0 | I7: =IFERROR($H7/$D7,0) | J7: 0 | K7: 5.6625 | L7: 0.8973038 | M7: N | N7: Waterfall | O7: JP | P7: 0 | Q7: 44 | R7: 147 | S7: 254 | T7: Other#COTS from BluePrism | U7: POSR | V7: 1 | W7: 11604
B8: W13WEP-JPN | C8: J | D8: 7.185 | E8: 6.0308 | F8: 1.1542 | G8: 6.0308 | H8: 0 | I8: =IFERROR($H8/$D8,0) | J8: 0 | K8: 6.0308 | L8: 0.75904635 | M8: Y | N8: Waterfall | O8: JP | P8: 585527 | Q8: 57 | R8: 216 | S8: 389 | T8: JAVA | U8: POSR | V8: 2 | W8: 9947
B9: POS Batch | C9: J | D9: 4.2762 | E9: 4.0262 | F9: 0.25 | G9: 3.2512 | H9: 0 | I9: =IFERROR($H9/$D9,0) | J9: 0 | K9: 4.0262 | L9: 0.90909091 | M9: N | N9: Waterfall | O9: Hybrid | P9: 0 | Q9: 0 | R9: 8 | S9: 41 | T9: JAVA | U9: POSR | V9: 0
B10: JP-PCI-RPASS | C10: J | D10: 3 | E10: 1 | F10: 2 | G10: 1 | H10: 0 | I10: =IFERROR($H10/$D10,0) | J10: 0 | K10: 1 | L10: 0 | M10: N | N10: Waterfall | O10: JP | P10: 0 | Q10: 0 | R10: 0 | S10: 3 | T10: Other#This is coded within blueprism | U10: POSR | V10: 0
B11: C03PCA-JPN | C11: T | D11: 2.8862 | E11: 2.6362 | F11: 0.25 | G11: 2.6363 | H11: 0 | I11: =IFERROR($H11/$D11,0) | J11: 0 | K11: 2.6363 | L11: 0.90298831 | M11: N | N11: Waterfall | O11: JP | P11: 311649 | Q11: 9 | R11: 45 | S11: 38 | T11: VB | U11: POSR | V11: 0
B12: C03WRD-JPN | C12: T | D12: 2.5258 | E12: 2.2883 | F12: 0.2375 | G12: 2.2883 | H12: 0 | I12: =IFERROR($H12/$D12,0) | J12: 0 | K12: 2.1883 | L12: 0.90102276 | M12: Y | N12: Waterfall | O12: JP | P12: 125022 | Q12: 0 | R12: 58 | S12: 32 | T12: VB.NET | U12: POSR | V12: 0
B13: WPMAUD-JPN | C13: T | D13: 1.1729 | E13: 1.0229 | F13: 0.15 | G13: 1.0229 | H13: 0 | I13: =IFERROR($H13/$D13,0) | J13: 0 | K13: 1.0229 | L13: 0.42806394 | M13: N | N13: Waterfall | O13: JP | P13: 649133 | Q13: 32 | R13: 108 | S13: 196 | T13: JAVA | U13: POSR | V13: 0
B14: DSP | C14: T | D14: 1 | E14: 0 | F14: 1 | G14: 0 | H14: 0 | I14: =IFERROR($H14/$D14,0) | J14: 0 | K14: 0 | L14: 1 | M14: N | N14: Agile | O14: Hybrid | P14: 0 | Q14: 0 | R14: 1 | S14: 2 | T14: PL/SQL | U14: POSR | V14: 0
B15: Scan Manager | C15: T | D15: 0.5958 | E15: 0.3958 | F15: 0.2 | G15: 0.3542 | H15: 0 | I15: =IFERROR($H15/$D15,0) | J15: 0 | K15: 0.3542 | L15: 0.66433566 | M15: N | N15: Waterfall | O15: JP | P15: 16693 | Q15: 4 | R15: 3 | S15: 7 | T15: VB.NET | U15: POSR | V15: 0
B16: W03CCP-JPN | C16: T | D16: 0.3542 | E16: 0.2542 | F16: 0.1 | G16: 0.2542 | H16: 0 | I16: =IFERROR($H16/$D16,0) | J16: 0 | K16: 0.2542 | L16: 0.56470588 | M16: N | N16: Waterfall | O16: JP | P16: 22000 | Q16: 7 | R16: 4 | S16: 51 | T16: JAVA | U16: POSR | V16: 0
B17: C03WRE-JPN | C17: T | D17: 0.3333 | E17: 0.1333 | F17: 0.2 | G17: 0.1333 | H17: 0 | I17: =IFERROR($H17/$D17,0) | J17: 0 | K17: 0.0333 | L17: 0.3258427 | M17: Y | N17: Waterfall | O17: JP | P17: 183197 | Q17: 21 | R17: 69 | S17: 43 | T17: VB.NET | U17: POSR | V17: 0
B18: W03PIU-JPN | C18: T | D18: 0.3083 | E18: 0.2083 | F18: 0.1 | G18: 0.2083 | H18: 0 | I18: =IFERROR($H18/$D18,0) | J18: 0 | K18: 0.2083 | L18: 0.67567568 | M18: N | N18: Waterfall | O18: JP | P18: 228784 | Q18: 1 | R18: 12 | S18: 22 | T18: JAVA | U18: POSR | V18: 0
B19: JP-DB2-CONNECT | C19: T | D19: 0.1 | E19: 0 | F19: 0.1 | G19: 0 | H19: 0 | I19: =IFERROR($H19/$D19,0) | J19: 0 | K19: 0 | L19: 0 | M19: N | N19: N/A | O19: N/A | P19: 0 | Q19: 0 | R19: 0 | S19: 0 | T19: Other#COTS | U19: POSR | V19: 0
B20: TOTAL | D20: =SUM(D5:D19) | E20: =SUM(E5:E19) | F20: =SUM(F5:F19) | G20: =SUM(G5:G19) | H20: =SUM(H5:H19) | J20: =SUM(J5:J19) | K20: =SUM(K5:K19) | P20: =SUM(P5:P19) | Q20: =SUM(Q5:Q19) | R20: =SUM(R5:R19) | S20: =SUM(S5:S19) | U20: — | V20: =SUM(V5:V19)
B22: Fourteen of the fifteen carry a development method and a specification language; JP-DB2-CONNECT is a 0.10-unit MetLife-only line with neither. Eleven run on Japanese specifications and only two are cloud-flagged — the least modern stack of the 領域 modelled. Code volume totals 4.09 million lines, 48% of it in POS-IMS. K2 alone is 62.6 of the 106.1 units, which is why it is now a value stream on its own and the other fourteen are the second. Columns U-W are new: the stream each application sits in, the FSI sub-contracted FTC on it, and the EAI ID for the four applications FSI holds. Note that Appendix 3 v5 lists K2 twice; the duplicate line is excluded here, as MetLife’s own total does. Two applications — JP-PCI-RPASS and C03WRE-JPN, 3.3 units between them — are marked Retire in the new disposition columns; see the README.

Sheet Value Streams
A1: Delivery streams — two streams: K2, and the fourteen satellites
A2: RESTATED. The estate splits on the one thing that actually differentiates it: K2 or not K2. Policy Owner Servicing Work Flow now carries K2 alone — one application, 62.642 units, 59.05% of the domain, the only archetype-D and the only agile line. Policy Owner Servicing Payment & Records carries the other fourteen — 43.438 units of Japanese-specification waterfall. Both run as TEAMS; there are no pods in this domain.
B4: Code | C4: Value stream | D4: Apps | E4: Effort | F4: Arch | G4: Mode today | H4: Agile from | I4: Y1 pods | J4: Y2 | K4: Y3 | L4: Y4 | M4: Y5 | N4: Vendor position today
B5: POSW | C5: Policy Owner Servicing Work Flow | D5: 1 | E5: 62.6424 | F5: D | G5: Agile | H5: Q2 | I5: 4t | J5: 4t | K5: 3t | L5: 3t | M5: 3t | N5: CG 34.1 · FSI 2.0
B6: POSR | C6: Policy Owner Servicing Payment & Records | D6: 14 | E6: 43.4378 | F6: J / T | G6: Waterfall | H6: n/a | I6: 3t | J6: 2t | K6: 2t | L6: 1t | M6: 1t | N6: CG 28.3 · FSI 5.0
C7: Total | D7: =SUM(D5:D6) | E7: =SUM(E5:E6)
B9: Counts read 'team instances'. Every instance is 12 seats, in every year. K2 converts to agile at Q2 and the fourteen satellites never convert — which is the honest reading of eleven Japanese-specification waterfall applications and is what holds this domain’s productivity to 44.6% rather than the portfolio’s 50%+. Five of the seven FSI seats sit in the Payment & Records team (POS-IMS, W13WEP-JPN, JP-RPASS) and two in the Work Flow team (K2); a further 2 partner seats in Years 1-3, 1 in Years 4-5, are held in horizontal team H1 as a control cell.

Sheet Pod Library
A1: Pod library — every TEAM seat, per value stream, with MetLife’s role taxonomy and four sourcing types
A2: INPUT. This domain runs TEAMS only — no pods, in any year. Each value stream carries its own 12-seat team anatomy, instantiated 4+3 / 4+2 / 3+2 / 3+1 / 3+1 times across the five years. Sourcing FTC = Capgemini payroll · PT = FSI, the named incumbent on K2, POS-IMS, W13WEP-JPN and JP-RPASS · FTE = MetLife Japan · MGCC. Only FTC can transfer at the end of Year 3. Column J is the seat ratio inside one team; column K is the people you actually hire across every instance of that team in that year, and every one of them is a whole number or a half.
B4: Year | C4: Unit | D4: Seat | E4: Role detail | F4: Role | G4: Exp | H4: Loc | I4: Sourcing | J4: Count | K4: People in the block
B5: 1 | C5: TEAM | D5: 1 | E5: MetLife Product Owner — K2 | F5: PM | G5: E4 | H5: ON | I5: FTE | J5: 1 | K5: =J5*4
B6: 1 | C6: TEAM | D6: 2 | E6: MetLife Servicing SME — K2 | F6: BSA | G6: E4 | H6: ON | I6: FTE | J6: 1 | K6: =J6*4
B7: 1 | C7: TEAM | D7: 3 | E7: FSI K2 Developer (JP) — EAI 12117 | F7: DEV | G7: E3 | H7: ON | I7: PT | J7: 0.5 | K7: =J7*4
B8: 1 | C8: TEAM | D8: 4 | E8: Business Analyst (bilingual) — K2 | F8: BSA | G8: E3 | H8: ON | I8: FTC | J8: 1 | K8: =J8*4
B9: 1 | C9: TEAM | D9: 5 | E9: Team lead / senior engineer — K2 | F9: DEV | G9: E4 | H9: ON | I9: FTC | J9: 1 | K9: =J9*4
B10: 1 | C10: TEAM | D10: 6 | E10: Solution Architect — K2 | F10: OTH | G10: E4 | H10: ON | I10: FTC | J10: 0.5 | K10: =J10*4
B11: 1 | C11: TEAM | D11: 7 | E11: Senior Workflow Developer (VB.NET) — K2 | F11: DEV | G11: E3 | H11: ON | I11: FTC | J11: 1.5 | K11: =J11*4
B12: 1 | C12: TEAM | D12: 8 | E12: Junior Workflow Developer (VB.NET) — K2 | F12: DEV | G12: E2 | H12: ON | I12: FTC | J12: 1 | K12: =J12*4
B13: 1 | C13: TEAM | D13: 9 | E13: Quality Engineer — K2 | F13: TEST | G13: E2 | H13: ON | I13: FTC | J13: 1 | K13: =J13*4
B14: 1 | C14: TEAM | D14: 10 | E14: Junior Workflow Developer — offshore | F14: DEV | G14: E2 | H14: OFF | I14: FTC | J14: 0.5 | K14: =J14*4
B15: 1 | C15: TEAM | D15: 11 | E15: Junior Quality Engineer — offshore | F15: TEST | G15: E1 | H15: OFF | I15: FTC | J15: 0.5 | K15: =J15*4
B16: 1 | C16: TEAM | D16: 12 | E16: Application Support — offshore | F16: MNT | G16: E2 | H16: OFF | I16: FTC | J16: 0.5 | K16: =J16*4
... B18: 1 | C18: TEAM | D18: 14 | E18: MGCC Test Engineer | F18: TEST | G18: E2 | H18: OFF | I18: MGCC | J18: 0.5 | K18: =J18*4
D19: TEAM size — Year 1 · POSW | J19: =SUM(J5:J18) | K19: =SUM(K5:K18)
B21: 1 | C21: TEAM | D21: 1 | E21: MetLife Application Owner | F21: PM | G21: E4 | H21: ON | I21: FTE | J21: 1 | K21: =J21*3
B22: 1 | C22: TEAM | D22: 2 | E22: MetLife Operations Analyst | F22: MNT | G22: E3 | H22: ON | I22: FTE | J22: 1 | K22: =J22*3
B23: 1 | C23: TEAM | D23: 3 | E23: FSI Senior Developer (JP) — EAI 13453 / 9947 | F23: DEV | G23: E3 | H23: ON | I23: PT | J23: 0.5 | K23: =J23*3
B24: 1 | C24: TEAM | D24: 4 | E24: FSI Business Analyst (JP) — EAI 11604 | F24: BSA | G24: E3 | H24: ON | I24: PT | J24: 0.5 | K24: =J24*3
B25: 1 | C25: TEAM | D25: 5 | E25: Team lead / technical lead | F25: DEV | G25: E4 | H25: ON | I25: FTC | J25: 1 | K25: =J25*3
B26: 1 | C26: TEAM | D26: 6 | E26: Business Analyst (bilingual) | F26: BSA | G26: E3 | H26: ON | I26: FTC | J26: 1 | K26: =J26*3
B27: 1 | C27: TEAM | D27: 7 | E27: Senior Application Developer (VB.NET / Java) | F27: DEV | G27: E3 | H27: ON | I27: FTC | J27: 2.5 | K27: =J27*3
B28: 1 | C28: TEAM | D28: 8 | E28: Junior Application Developer (VB.NET / Java) | F28: DEV | G28: E2 | H28: ON | I28: FTC | J28: 1.5 | K28: =J28*3
B29: 1 | C29: TEAM | D29: 9 | E29: Test Engineer — Tokyo | F29: TEST | G29: E2 | H29: ON | I29: FTC | J29: 2 | K29: =J29*3
B30: 1 | C30: TEAM | D30: 10 | E30: Application Support (L2) — Tokyo | F30: MNT | G30: E2 | H30: ON | I30: FTC | J30: 0.5 | K30: =J30*3
B31: 1 | C31: TEAM | D31: 11 | E31: Junior Application Developer — offshore | F31: DEV | G31: E2 | H31: OFF | I31: FTC | J31: 0.5 | K31: =J31*3
D32: TEAM size — Year 1 · POSR | J32: =SUM(J21:J31) | K32: =SUM(K21:K31)
B34: 2 | C34: TEAM | D34: 1 | E34: MetLife Product Owner — K2 | F34: PM | G34: E4 | H34: ON | I34: FTE | J34: 1 | K34: =J34*4
B35: 2 | C35: TEAM | D35: 2 | E35: MetLife Servicing SME — K2 | F35: BSA | G35: E4 | H35: ON | I35: FTE | J35: 1.5 | K35: =J35*4
B36: 2 | C36: TEAM | D36: 3 | E36: FSI K2 Developer (JP) — EAI 12117 | F36: DEV | G36: E3 | H36: ON | I36: PT | J36: 0.5 | K36: =J36*4
B37: 2 | C37: TEAM | D37: 4 | E37: Business Analyst (bilingual) — K2 | F37: BSA | G37: E3 | H37: ON | I37: FTC | J37: 1 | K37: =J37*4
B38: 2 | C38: TEAM | D38: 5 | E38: Team lead / senior engineer — K2 | F38: DEV | G38: E4 | H38: ON | I38: FTC | J38: 1 | K38: =J38*4
B39: 2 | C39: TEAM | D39: 6 | E39: Solution Architect — K2 | F39: OTH | G39: E4 | H39: ON | I39: FTC | J39: 0.5 | K39: =J39*4
B40: 2 | C40: TEAM | D40: 7 | E40: Senior Workflow Developer (VB.NET) — K2 | F40: DEV | G40: E3 | H40: ON | I40: FTC | J40: 1 | K40: =J40*4
B41: 2 | C41: TEAM | D41: 8 | E41: Junior Workflow Developer (VB.NET) — K2 | F41: DEV | G41: E2 | H41: ON | I41: FTC | J41: 0.5 | K41: =J41*4
B42: 2 | C42: TEAM | D42: 9 | E42: Quality Engineer — K2 | F42: TEST | G42: E2 | H42: ON | I42: FTC | J42: 0.5 | K42: =J42*4
B43: 2 | C43: TEAM | D43: 10 | E43: Junior Workflow Developer — offshore | F43: DEV | G43: E2 | H43: OFF | I43: FTC | J43: 1 | K43: =J43*4
B44: 2 | C44: TEAM | D44: 11 | E44: Junior Quality Engineer — offshore | F44: TEST | G44: E1 | H44: OFF | I44: FTC | J44: 0.5 | K44: =J44*4
B45: 2 | C45: TEAM | D45: 12 | E45: Application Support — offshore | F45: MNT | G45: E2 | H45: OFF | I45: FTC | J45: 0.5 | K45: =J45*4
B46: 2 | C46: TEAM | D46: 13 | E46: MGCC K2 Engineer | F46: DEV | G46: E3 | H46: OFF | I46: MGCC | J46: 2 | K46: =J46*4
B47: 2 | C47: TEAM | D47: 14 | E47: MGCC Test Engineer | F47: TEST | G47: E2 | H47: OFF | I47: MGCC | J47: 0.5 | K47: =J47*4 | L47: 7.25 | M47: 43.5
D48: TEAM size — Year 2 · POSW | J48: =SUM(J34:J47) | K48: =SUM(K34:K47)
B50: 2 | C50: TEAM | D50: 1 | E50: MetLife Application Owner | F50: PM | G50: E4 | H50: ON | I50: FTE | J50: 1.5 | K50: =J50*2
B51: 2 | C51: TEAM | D51: 2 | E51: MetLife Operations Analyst | F51: MNT | G51: E3 | H51: ON | I51: FTE | J51: 1.5 | K51: =J51*2
B52: 2 | C52: TEAM | D52: 3 | E52: FSI Senior Developer (JP) — EAI 13453 / 9947 | F52: DEV | G52: E3 | H52: ON | I52: PT | J52: 1 | K52: =J52*2
B53: 2 | C53: TEAM | D53: 4 | E53: FSI Business Analyst (JP) — EAI 11604 | F53: BSA | G53: E3 | H53: ON | I53: PT | J53: 0.5 | K53: =J53*2
B54: 2 | C54: TEAM | D54: 5 | E54: Team lead / technical lead | F54: DEV | G54: E4 | H54: ON | I54: FTC | J54: 1 | K54: =J54*2
B55: 2 | C55: TEAM | D55: 6 | E55: Business Analyst (bilingual) | F55: BSA | G55: E3 | H55: ON | I55: FTC | J55: 1 | K55: =J55*2
B56: 2 | C56: TEAM | D56: 7 | E56: Senior Application Developer (VB.NET / Java) | F56: DEV | G56: E3 | H56: ON | I56: FTC | J56: 1.5 | K56: =J56*2
B57: 2 | C57: TEAM | D57: 8 | E57: Junior Application Developer (VB.NET / Java) | F57: DEV | G57: E2 | H57: ON | I57: FTC | J57: 0.75 | K57: =J57*2
B58: 2 | C58: TEAM | D58: 9 | E58: Test Engineer — Tokyo | F58: TEST | G58: E2 | H58: ON | I58: FTC | J58: 0.5 | K58: =J58*2
B59: 2 | C59: TEAM | D59: 10 | E59: Application Support (L2) — Tokyo | F59: MNT | G59: E2 | H59: ON | I59: FTC | J59: 0.5 | K59: =J59*2
B60: 2 | C60: TEAM | D60: 11 | E60: Junior Application Developer — offshore | F60: DEV | G60: E2 | H60: OFF | I60: FTC | J60: 1.25 | K60: =J60*2
B61: 2 | C61: TEAM | D61: 12 | E61: Junior Test Engineer — offshore | F61: TEST | G61: E1 | H61: OFF | I61: FTC | J61: 0.5 | K61: =J61*2
B62: 2 | C62: TEAM | D62: 13 | E62: MGCC Batch & Support Engineer | F62: MNT | G62: E2 | H62: OFF | I62: MGCC | J62: 0.5 | K62: =J62*2
D63: TEAM size — Year 2 · POSR | J63: =SUM(J50:J62) | K63: =SUM(K50:K62)
B65: 3 | C65: TEAM | D65: 1 | E65: MetLife Product Owner — K2 | F65: PM | G65: E4 | H65: ON | I65: FTE | J65: 1 | K65: =J65*3 | M65: 1.21 | N65: =M65*7
B66: 3 | C66: TEAM | D66: 2 | E66: MetLife Servicing SME — K2 | F66: BSA | G66: E4 | H66: ON | I66: FTE | J66: 1 | K66: =J66*3 | M66: 1 | N66: =M66*7
B67: 3 | C67: TEAM | D67: 3 | E67: FSI K2 Developer (JP) — EAI 12117 | F67: DEV | G67: E3 | H67: ON | I67: PT | J67: 0.5 | K67: =J67*3 | M67: 0.71 | N67: =M67*7
B68: 3 | C68: TEAM | D68: 4 | E68: Business Analyst (bilingual) — K2 | F68: BSA | G68: E3 | H68: ON | I68: FTC | J68: 1 | K68: =J68*3 | M68: 0.64 | N68: =M68*7
B69: 3 | C69: TEAM | D69: 5 | E69: Team lead / senior engineer — K2 | F69: DEV | G69: E4 | H69: ON | I69: FTC | J69: 1 | K69: =J69*3 | M69: 0.29 | N69: =M69*7
B70: 3 | C70: TEAM | D70: 6 | E70: Solution Architect — K2 | F70: OTH | G70: E4 | H70: ON | I70: FTC | J70: 0.5 | K70: =J70*3 | M70: 0.14 | N70: =M70*7
B71: 3 | C71: TEAM | D71: 7 | E71: Senior Workflow Developer (VB.NET) — K2 | F71: DEV | G71: E3 | H71: ON | I71: FTC | J71: 1 | K71: =J71*3 | M71: 1.07 | N71: =M71*7
B72: 3 | C72: TEAM | D72: 8 | E72: Senior Workflow Developer — offshore | F72: DEV | G72: E3 | H72: OFF | I72: FTC | J72: 0.5 | K72: =J72*3 | M72: 0.5 | N72: =M72*7
B73: 3 | C73: TEAM | D73: 9 | E73: Junior Workflow Developer — offshore | F73: DEV | G73: E2 | H73: OFF | I73: FTC | J73: 1 | K73: =J73*3 | M73: 0.43 | N73: =M73*7
B74: 3 | C74: TEAM | D74: 10 | E74: Junior Quality Engineer — offshore | F74: TEST | G74: E1 | H74: OFF | I74: FTC | J74: 1 | K74: =J74*3 | M74: 0.14 | N74: =M74*7
B75: 3 | C75: TEAM | D75: 11 | E75: Application Support — offshore | F75: MNT | G75: E2 | H75: OFF | I75: FTC | J75: 0.5 | K75: =J75*3 | M75: 0.57 | N75: =M75*7
B76: 3 | C76: TEAM | D76: 12 | E76: MGCC K2 Engineer | F76: DEV | G76: E3 | H76: OFF | I76: MGCC | J76: 2 | K76: =J76*3 | M76: =SUM(M65:M75) | N76: =SUM(N65:N75)
B77: 3 | C77: TEAM | D77: 13 | E77: MGCC Test Engineer | F77: TEST | G77: E2 | H77: OFF | I77: MGCC | J77: 1 | K77: =J77*3
D78: TEAM size — Year 3 · POSW | J78: =SUM(J65:J77) | K78: =SUM(K65:K77)
B80: 3 | C80: TEAM | D80: 1 | E80: MetLife Application Owner | F80: PM | G80: E4 | H80: ON | I80: FTE | J80: 1.5 | K80: =J80*2
B81: 3 | C81: TEAM | D81: 2 | E81: MetLife Operations Analyst | F81: MNT | G81: E3 | H81: ON | I81: FTE | J81: 1 | K81: =J81*2
B82: 3 | C82: TEAM | D82: 3 | E82: FSI Senior Developer (JP) — EAI 13453 / 9947 | F82: DEV | G82: E3 | H82: ON | I82: PT | J82: 0.75 | K82: =J82*2
B83: 3 | C83: TEAM | D83: 4 | E83: FSI Business Analyst (JP) — EAI 11604 | F83: BSA | G83: E3 | H83: ON | I83: PT | J83: 0.5 | K83: =J83*2
B84: 3 | C84: TEAM | D84: 5 | E84: Team lead / technical lead | F84: DEV | G84: E4 | H84: ON | I84: FTC | J84: 1 | K84: =J84*2
B85: 3 | C85: TEAM | D85: 6 | E85: Business Analyst (bilingual) | F85: BSA | G85: E3 | H85: ON | I85: FTC | J85: 1 | K85: =J85*2
B86: 3 | C86: TEAM | D86: 7 | E86: Senior Application Developer (VB.NET / Java) | F86: DEV | G86: E3 | H86: ON | I86: FTC | J86: 1 | K86: =J86*2
B87: 3 | C87: TEAM | D87: 8 | E87: Junior Application Developer (VB.NET / Java) | F87: DEV | G87: E2 | H87: ON | I87: FTC | J87: 0.25 | K87: =J87*2
B88: 3 | C88: TEAM | D88: 9 | E88: Test Engineer — Tokyo | F88: TEST | G88: E2 | H88: ON | I88: FTC | J88: 0.5 | K88: =J88*2
B89: 3 | C89: TEAM | D89: 10 | E89: Application Support (L2) — Tokyo | F89: MNT | G89: E2 | H89: ON | I89: FTC | J89: 0.5 | K89: =J89*2
B90: 3 | C90: TEAM | D90: 11 | E90: Junior Application Developer — offshore | F90: DEV | G90: E2 | H90: OFF | I90: FTC | J90: 1.5 | K90: =J90*2
B91: 3 | C91: TEAM | D91: 12 | E91: Junior Test Engineer — offshore | F91: TEST | G91: E1 | H91: OFF | I91: FTC | J91: 0.5 | K91: =J91*2
B92: 3 | C92: TEAM | D92: 13 | E92: MGCC Batch & Support Engineer | F92: MNT | G92: E2 | H92: OFF | I92: MGCC | J92: 2 | K92: =J92*2
D93: TEAM size — Year 3 · POSR | J93: =SUM(J80:J92) | K93: =SUM(K80:K92)
M94: 0.64285714 | N94: =M94*7
B95: 4 | C95: TEAM | D95: 1 | E95: MetLife Product Owner — K2 | F95: PM | G95: E4 | H95: ON | I95: FTE | J95: 1 | K95: =J95*3 | M95: 0.71428571 | N95: =M95*7
B96: 4 | C96: TEAM | D96: 2 | E96: MetLife Servicing SME — K2 | F96: BSA | G96: E4 | H96: ON | I96: FTE | J96: 1 | K96: =J96*3 | M96: 0.35714286 | N96: =M96*7
B97: 4 | C97: TEAM | D97: 3 | E97: FSI K2 Developer (JP) — EAI 12117 | F97: DEV | G97: E3 | H97: ON | I97: PT | J97: 0.5 | K97: =J97*3 | M97: 0.42857143 | N97: =M97*7
B98: 4 | C98: TEAM | D98: 4 | E98: Business Analyst (bilingual) — K2 | F98: BSA | G98: E3 | H98: ON | I98: FTC | J98: 1 | K98: =J98*3 | M98: 0 | N98: =M98*7
B99: 4 | C99: TEAM | D99: 5 | E99: Team lead / senior engineer — K2 | F99: DEV | G99: E4 | H99: ON | I99: FTC | J99: 1 | K99: =J99*3 | M99: 0.21428571 | N99: =M99*7
B100: 4 | C100: TEAM | D100: 6 | E100: Solution Architect — K2 | F100: OTH | G100: E4 | H100: ON | I100: FTC | J100: 0.5 | K100: =J100*3 | M100: 1 | N100: =M100*7
B101: 4 | C101: TEAM | D101: 7 | E101: Senior Workflow Developer — offshore | F101: DEV | G101: E3 | H101: OFF | I101: FTC | J101: 1 | K101: =J101*3 | M101: 0.78571429 | N101: =M101*7
B102: 4 | C102: TEAM | D102: 8 | E102: Junior Workflow Developer — offshore | F102: DEV | G102: E2 | H102: OFF | I102: FTC | J102: 1.5 | K102: =J102*3 | M102: 0.21428571 | N102: =M102*7
B103: 4 | C103: TEAM | D103: 9 | E103: Junior Quality Engineer — offshore | F103: TEST | G103: E1 | H103: OFF | I103: FTC | J103: 1 | K103: =J103*3 | M103: 0.14285714 | N103: =M103*7
B104: 4 | C104: TEAM | D104: 10 | E104: Application Support — offshore | F104: MNT | G104: E2 | H104: OFF | I104: FTC | J104: 0.5 | K104: =J104*3 | M104: 0.42857143 | N104: =M104*7
B105: 4 | C105: TEAM | D105: 11 | E105: MGCC K2 Engineer | F105: DEV | G105: E3 | H105: OFF | I105: MGCC | J105: 2 | K105: =J105*3 | M105: =SUM(M94:M104) | N105: =SUM(N94:N104)
B106: 4 | C106: TEAM | D106: 12 | E106: MGCC Test Engineer | F106: TEST | G106: E2 | H106: OFF | I106: MGCC | J106: 1 | K106: =J106*3
D107: TEAM size — Year 4 · POSW | J107: =SUM(J95:J106) | K107: =SUM(K95:K106)
...

Sheet Pod Plan
A1: Team plan — how many instances of each value stream’s 12-seat team, per year
A2: INPUT. There are no pods in this domain. Productivity shows up here as instances retiring — 7 teams in Year 1, 6, 5, then 4 for Years 4 and 5 — and never as a team being shrunk below 12 seats.
B4: Year | C4: VS | D4: Value stream | E4: Teams (unused) | F4: Team instances | G4: Units | H4: People
B5: 1 | C5: POSW | D5: Policy Owner Servicing Work Flow | E5: 0 | F5: 4 | G5: =E5+F5 | H5: =F5*SUM('Pod Library'!$J$5:$J$18)
B6: 1 | C6: POSR | D6: Policy Owner Servicing Payment & Records | E6: 0 | F6: 3 | G6: =E6+F6 | H6: =F6*SUM('Pod Library'!$J$21:$J$31)
D7: Year 1 total | E7: =SUM(E5:E6) | F7: =SUM(F5:F6) | G7: =SUM(G5:G6) | H7: =SUM(H5:H6)
B9: 2 | C9: POSW | D9: Policy Owner Servicing Work Flow | E9: 0 | F9: 4 | G9: =E9+F9 | H9: =F9*SUM('Pod Library'!$J$34:$J$47)
B10: 2 | C10: POSR | D10: Policy Owner Servicing Payment & Records | E10: 0 | F10: 2 | G10: =E10+F10 | H10: =F10*SUM('Pod Library'!$J$50:$J$62)
D11: Year 2 total | E11: =SUM(E9:E10) | F11: =SUM(F9:F10) | G11: =SUM(G9:G10) | H11: =SUM(H9:H10)
B13: 3 | C13: POSW | D13: Policy Owner Servicing Work Flow | E13: 0 | F13: 3 | G13: =E13+F13 | H13: =F13*SUM('Pod Library'!$J$65:$J$77)
B14: 3 | C14: POSR | D14: Policy Owner Servicing Payment & Records | E14: 0 | F14: 2 | G14: =E14+F14 | H14: =F14*SUM('Pod Library'!$J$80:$J$92)
D15: Year 3 total | E15: =SUM(E13:E14) | F15: =SUM(F13:F14) | G15: =SUM(G13:G14) | H15: =SUM(H13:H14)
B17: 4 | C17: POSW | D17: Policy Owner Servicing Work Flow | E17: 0 | F17: 3 | G17: =E17+F17 | H17: =F17*SUM('Pod Library'!$J$95:$J$106)
B18: 4 | C18: POSR | D18: Policy Owner Servicing Payment & Records | E18: 0 | F18: 1 | G18: =E18+F18 | H18: =F18*SUM('Pod Library'!$J$109:$J$119)
D19: Year 4 total | E19: =SUM(E17:E18) | F19: =SUM(F17:F18) | G19: =SUM(G17:G18) | H19: =SUM(H17:H18)
B21: 5 | C21: POSW | D21: Policy Owner Servicing Work Flow | E21: 0 | F21: 3 | G21: =E21+F21 | H21: =F21*SUM('Pod Library'!$J$122:$J$133)
B22: 5 | C22: POSR | D22: Policy Owner Servicing Payment & Records | E22: 0 | F22: 1 | G22: =E22+F22 | H22: =F22*SUM('Pod Library'!$J$136:$J$146)
D23: Year 5 total | E23: =SUM(E21:E22) | F23: =SUM(F21:F22) | G23: =SUM(G21:G22) | H23: =SUM(H21:H22)

Sheet Horizontal Teams
A1: Horizontal teams — work that is not stream-bounded
A2: INPUT, defined per year rather than scaled. H1 is run and AMS, and carries the FSI control cell — 2 partner seats in Years 1-3 and 1 in Years 4-5, held outside the delivery teams deliberately so the partner relationship is governed rather than only consumed. H2 is records and quality governance. H3 is delivery leadership and architecture. Year 4 is the year the last Payment & Records team retires and its residual run work lands here, which is why the layer rises that year before falling again in Year 5.
B4: Year | C4: Team | D4: Role | E4: Role detail | F4: Exp | G4: Loc | H4: Sourcing | I4: Count | J4: People in the block
B5: 1 | C5: H1 | D5: MNT | E5: MetLife Operations Analyst | F5: E3 | G5: ON | H5: FTE | I5: 2 | J5: =I5
B6: 1 | C6: H1 | D6: MNT | E6: FSI Production Control cell — K2 / POS-IMS | F6: E3 | G6: ON | H6: PT | I6: 2 | J6: =I6
B7: 1 | C7: H1 | D7: PM | E7: Service Delivery Manager | F7: E5 | G7: ON | H7: FTC | I7: 1 | J7: =I7
B8: 1 | C8: H1 | D8: MNT | E8: Incident & Problem Analyst | F8: E3 | G8: ON | H8: FTC | I8: 1 | J8: =I8
B9: 1 | C9: H1 | D9: OTH | E9: Observability / AIOps Engineer | F9: E3 | G9: OFF | H9: FTC | I9: 1 | J9: =I9
B10: 1 | C10: H1 | D10: DEV | E10: MGCC Platform SRE | F10: E3 | G10: OFF | H10: MGCC | I10: 3 | J10: =I10
B11: 1 | C11: H2 | D11: BSA | E11: MetLife Servicing Governance | F11: E4 | G11: ON | H11: FTE | I11: 1.5 | J11: =I11
B12: 1 | C12: H2 | D12: TEST | E12: Head of Quality Engineering | F12: E4 | G12: ON | H12: FTC | I12: 1 | J12: =I12
B13: 1 | C13: H3 | D13: BSA | E13: MetLife Servicing Owner | F13: E5 | G13: ON | H13: FTE | I13: 2 | J13: =I13
B14: 1 | C14: H3 | D14: PM | E14: MetLife Portfolio Manager | F14: E4 | G14: ON | H14: FTE | I14: 2.5 | J14: =I14
B15: 1 | C15: H3 | D15: PM | E15: MetLife Application Owners — satellites | F15: E4 | G15: ON | H15: FTE | I15: 4 | J15: =I15
B16: 1 | C16: H3 | D16: PM | E16: Domain Delivery Head | F16: E5 | G16: ON | H16: FTC | I16: 0.5 | J16: =I16
B17: 1 | C17: H3 | D17: OTH | E17: Chief Architect — Servicing | F17: E5 | G17: ON | H17: FTC | I17: 0.5 | J17: =I17
E18: Year 1 horizontal total | I18: =SUM(I5:I17) | J18: =SUM(J5:J17)
B20: 2 | C20: H1 | D20: MNT | E20: MetLife Operations Analyst | F20: E3 | G20: ON | H20: FTE | I20: 1 | J20: =I20
B21: 2 | C21: H1 | D21: MNT | E21: FSI Production Control cell — K2 / POS-IMS | F21: E3 | G21: ON | H21: PT | I21: 2 | J21: =I21
B22: 2 | C22: H1 | D22: PM | E22: Service Delivery Manager | F22: E5 | G22: ON | H22: FTC | I22: 0.5 | J22: =I22
B23: 2 | C23: H1 | D23: MNT | E23: Incident & Problem Analyst | F23: E3 | G23: ON | H23: FTC | I23: 1 | J23: =I23
B24: 2 | C24: H1 | D24: OTH | E24: Observability / AIOps Engineer | F24: E3 | G24: OFF | H24: FTC | I24: 1 | J24: =I24
B25: 2 | C25: H1 | D25: DEV | E25: MGCC Platform SRE | F25: E3 | G25: OFF | H25: MGCC | I25: 2 | J25: =I25
B26: 2 | C26: H2 | D26: BSA | E26: MetLife Servicing Governance | F26: E4 | G26: ON | H26: FTE | I26: 1 | J26: =I26
B27: 2 | C27: H2 | D27: TEST | E27: Head of Quality Engineering | F27: E4 | G27: ON | H27: FTC | I27: 0.5 | J27: =I27
B28: 2 | C28: H3 | D28: BSA | E28: MetLife Servicing Owner | F28: E5 | G28: ON | H28: FTE | I28: 1.5 | J28: =I28
B29: 2 | C29: H3 | D29: PM | E29: MetLife Portfolio Manager | F29: E4 | G29: ON | H29: FTE | I29: 1.5 | J29: =I29
B30: 2 | C30: H3 | D30: PM | E30: Domain Delivery Head | F30: E5 | G30: ON | H30: FTC | I30: 0.5 | J30: =I30
B31: 2 | C31: H3 | D31: OTH | E31: Chief Architect — Servicing | F31: E5 | G31: ON | H31: FTC | I31: 0.5 | J31: =I31
E32: Year 2 horizontal total | I32: =SUM(I20:I31) | J32: =SUM(J20:J31)
B34: 3 | C34: H1 | D34: MNT | E34: MetLife Operations Analyst | F34: E3 | G34: ON | H34: FTE | I34: 2 | J34: =I34
B35: 3 | C35: H1 | D35: MNT | E35: FSI Production Control cell — K2 / POS-IMS | F35: E3 | G35: ON | H35: PT | I35: 2 | J35: =I35
B36: 3 | C36: H1 | D36: PM | E36: Service Delivery Manager | F36: E5 | G36: ON | H36: FTC | I36: 0.5 | J36: =I36
B37: 3 | C37: H1 | D37: OTH | E37: Observability / AIOps Engineer | F37: E3 | G37: OFF | H37: FTC | I37: 0.5 | J37: =I37
B38: 3 | C38: H1 | D38: DEV | E38: MGCC Platform SRE | F38: E3 | G38: OFF | H38: MGCC | I38: 2 | J38: =I38
B39: 3 | C39: H2 | D39: BSA | E39: MetLife Servicing Governance | F39: E4 | G39: ON | H39: FTE | I39: 1.5 | J39: =I39
B40: 3 | C40: H3 | D40: BSA | E40: MetLife Servicing Owner | F40: E5 | G40: ON | H40: FTE | I40: 1.5 | J40: =I40
B41: 3 | C41: H3 | D41: PM | E41: MetLife Portfolio Manager | F41: E4 | G41: ON | H41: FTE | I41: 1.5 | J41: =I41
B42: 3 | C42: H3 | D42: PM | E42: Domain Delivery Head | F42: E5 | G42: ON | H42: FTC | I42: 0.5 | J42: =I42
B43: 3 | C43: H3 | D43: OTH | E43: Chief Architect — Servicing | F43: E5 | G43: ON | H43: FTC | I43: 0.5 | J43: =I43
E44: Year 3 horizontal total | I44: =SUM(I34:I43) | J44: =SUM(J34:J43)
B46: 4 | C46: H1 | D46: MNT | E46: MetLife Operations Analyst | F46: E3 | G46: ON | H46: FTE | I46: 3 | J46: =I46
B47: 4 | C47: H1 | D47: MNT | E47: FSI Production Control cell — K2 / POS-IMS | F47: E3 | G47: ON | H47: PT | I47: 1 | J47: =I47
B48: 4 | C48: H1 | D48: PM | E48: Service Delivery Manager | F48: E5 | G48: ON | H48: FTC | I48: 0.5 | J48: =I48
B49: 4 | C49: H1 | D49: OTH | E49: Observability / AIOps Engineer | F49: E3 | G49: OFF | H49: FTC | I49: 0.5 | J49: =I49
B50: 4 | C50: H1 | D50: MNT | E50: AMS & run consolidation cell — offshore | F50: E2 | G50: OFF | H50: FTC | I50: 1.5 | J50: =I50
B51: 4 | C51: H1 | D51: DEV | E51: MGCC Platform SRE | F51: E3 | G51: OFF | H51: MGCC | I51: 3 | J51: =I51
B52: 4 | C52: H2 | D52: BSA | E52: MetLife Servicing Governance | F52: E4 | G52: ON | H52: FTE | I52: 1.5 | J52: =I52
B53: 4 | C53: H3 | D53: BSA | E53: MetLife Servicing Owner | F53: E5 | G53: ON | H53: FTE | I53: 2 | J53: =I53
B54: 4 | C54: H3 | D54: PM | E54: MetLife Portfolio Manager | F54: E4 | G54: ON | H54: FTE | I54: 2.5 | J54: =I54
B55: 4 | C55: H3 | D55: PM | E55: Domain Delivery Head | F55: E5 | G55: ON | H55: FTC | I55: 0.5 | J55: =I55
B56: 4 | C56: H3 | D56: OTH | E56: Chief Architect — Servicing | F56: E5 | G56: ON | H56: FTC | I56: 0.5 | J56: =I56
E57: Year 4 horizontal total | I57: =SUM(I46:I56) | J57: =SUM(J46:J56)
B59: 5 | C59: H1 | D59: MNT | E59: MetLife Operations Analyst | F59: E3 | G59: ON | H59: FTE | I59: 1.5 | J59: =I59
B60: 5 | C60: H1 | D60: MNT | E60: FSI Production Control cell — K2 / POS-IMS | F60: E3 | G60: ON | H60: PT | I60: 1 | J60: =I60
B61: 5 | C61: H1 | D61: PM | E61: Service Delivery Manager | F61: E5 | G61: ON | H61: FTC | I61: 0.5 | J61: =I61
B62: 5 | C62: H1 | D62: OTH | E62: Observability / AIOps Engineer | F62: E3 | G62: OFF | H62: FTC | I62: 0.5 | J62: =I62
B63: 5 | C63: H1 | D63: DEV | E63: MGCC Platform SRE | F63: E3 | G63: OFF | H63: MGCC | I63: 1.5 | J63: =I63
B64: 5 | C64: H2 | D64: BSA | E64: MetLife Servicing Governance | F64: E4 | G64: ON | H64: FTE | I64: 1.5 | J64: =I64
B65: 5 | C65: H3 | D65: BSA | E65: MetLife Servicing Owner | F65: E5 | G65: ON | H65: FTE | I65: 1.5 | J65: =I65
B66: 5 | C66: H3 | D66: PM | E66: MetLife Portfolio Manager | F66: E4 | G66: ON | H66: FTE | I66: 1.5 | J66: =I66
B67: 5 | C67: H3 | D67: PM | E67: Domain Delivery Head | F67: E5 | G67: ON | H67: FTC | I67: 0.5 | J67: =I67
B68: 5 | C68: H3 | D68: OTH | E68: Chief Architect — Servicing | F68: E5 | G68: ON | H68: FTC | I68: 0.5 | J68: =I68
E69: Year 5 horizontal total | I69: =SUM(I59:I68) | J69: =SUM(J59:J68)
B71: H1 is sized from the incident and change load on the AMS sheet — 1,145 incidents and 2,071 changes a year — and holds the FSI control cell covering K2 (EAI 12117), POS-IMS (13453), W13WEP-JPN (9947) and JP-RPASS (11604). The remaining FSI seats sit inside the two value-stream teams that own those applications, which is where the work is.

Sheet Team Build-Up
A1: Team build-up — and the Year-1 reconciliation to Appendix 3 v5
A2: Nothing on this sheet is typed. Section B is the test that matters: the roster has to be the client's own Year-1 position on effort, sourcing, location AND role.
A4: A. HEADCOUNT
B5: Measure | C5: Year 1 | D5: Year 2 | E5: Year 3 | F5: Year 4 | G5: Year 5
B6: People in agile pods (none in this domain) | C6: =SUMIFS('Seat Ledger'!$M$5:$M$235,'Seat Ledger'!$B$5:$B$235,1,'Seat Ledger'!$C$5:$C$235,"POD") | D6: =SUMIFS('Seat Ledger'!$M$5:$M$235,'Seat Ledger'!$B$5:$B$235,2,'Seat Ledger'!$C$5:$C$235,"POD") | E6: =SUMIFS('Seat Ledger'!$M$5:$M$235,'Seat Ledger'!$B$5:$B$235,3,'Seat Ledger'!$C$5:$C$235,"POD") | F6: =SUMIFS('Seat Ledger'!$M$5:$M$235,'Seat Ledger'!$B$5:$B$235,4,'Seat Ledger'!$C$5:$C$235,"POD") | G6: =SUMIFS('Seat Ledger'!$M$5:$M$235,'Seat Ledger'!$B$5:$B$235,5,'Seat Ledger'!$C$5:$C$235,"POD")
B7: People in value-stream TEAMS of 12 | C7: =SUMIFS('Seat Ledger'!$M$5:$M$235,'Seat Ledger'!$B$5:$B$235,1,'Seat Ledger'!$C$5:$C$235,"TEAM") | D7: =SUMIFS('Seat Ledger'!$M$5:$M$235,'Seat Ledger'!$B$5:$B$235,2,'Seat Ledger'!$C$5:$C$235,"TEAM") | E7: =SUMIFS('Seat Ledger'!$M$5:$M$235,'Seat Ledger'!$B$5:$B$235,3,'Seat Ledger'!$C$5:$C$235,"TEAM") | F7: =SUMIFS('Seat Ledger'!$M$5:$M$235,'Seat Ledger'!$B$5:$B$235,4,'Seat Ledger'!$C$5:$C$235,"TEAM") | G7: =SUMIFS('Seat Ledger'!$M$5:$M$235,'Seat Ledger'!$B$5:$B$235,5,'Seat Ledger'!$C$5:$C$235,"TEAM")
B8: People in horizontal teams | C8: =SUMIFS('Seat Ledger'!$M$5:$M$235,'Seat Ledger'!$B$5:$B$235,1,'Seat Ledger'!$C$5:$C$235,"HZ") | D8: =SUMIFS('Seat Ledger'!$M$5:$M$235,'Seat Ledger'!$B$5:$B$235,2,'Seat Ledger'!$C$5:$C$235,"HZ") | E8: =SUMIFS('Seat Ledger'!$M$5:$M$235,'Seat Ledger'!$B$5:$B$235,3,'Seat Ledger'!$C$5:$C$235,"HZ") | F8: =SUMIFS('Seat Ledger'!$M$5:$M$235,'Seat Ledger'!$B$5:$B$235,4,'Seat Ledger'!$C$5:$C$235,"HZ") | G8: =SUMIFS('Seat Ledger'!$M$5:$M$235,'Seat Ledger'!$B$5:$B$235,5,'Seat Ledger'!$C$5:$C$235,"HZ")
B9: TOTAL PEOPLE | C9: =SUM(C6:C8) | D9: =SUM(D6:D8) | E9: =SUM(E6:E8) | F9: =SUM(F6:F8) | G9: =SUM(G6:G8)
B10: Delivery units — team instances (POSW + POSR) | C10: 4 + 3 | D10: 4 + 2 | E10: 3 + 2 | F10: 3 + 1 | G10: 3 + 1
B11: Headcount target from the Logic Tree | C11: ='Logic Tree'!C53 | D11: ='Logic Tree'!D53 | E11: ='Logic Tree'!E53 | F11: ='Logic Tree'!F53 | G11: ='Logic Tree'!G53
B12: Variance to target | C12: =C9-C11 | D12: =D9-D11 | E12: =E9-E11 | F12: =F9-F11 | G12: =G9-G11
A14: B. YEAR-1 RECONCILIATION TO APPENDIX 3 v3
B15: Measure | C15: Model Year 1 | D15: Appendix 3 v5 | E15: Variance | H15: Reading
B16: Total effort / people | C16: =C9 | D16: ='Logic Tree'!C7 | E16: =C16-D16 | H16: Whole-domain size. Unchanged since v2.
B17: FTC reported (Capgemini + partner) | C17: =SUMIFS('Seat Ledger'!$M$5:$M$235,'Seat Ledger'!$B$5:$B$235,1,'Seat Ledger'!$J$5:$J$235,"FTC")+SUMIFS('Seat Ledger'!$M$5:$M$235,'Seat Ledger'!$B$5:$B$235,1,'Seat Ledger'!$J$5:$J$235,"PT") | D17: ='Logic Tree'!C8 | E17: =C17-D17 | H17: Appendix 3 reports the vendor as one number. This is the line that has to reconcile.
B18: — of which Capgemini payroll | C18: =SUMIFS('Seat Ledger'!$M$5:$M$235,'Seat Ledger'!$B$5:$B$235,1,'Seat Ledger'!$J$5:$J$235,"FTC") | D18: — | E18: — | H18: Transferable at the end of Year 3.
B19: — of which FSI (four-application partner cell) | C19: =SUMIFS('Seat Ledger'!$M$5:$M$235,'Seat Ledger'!$B$5:$B$235,1,'Seat Ledger'!$J$5:$J$235,"PT") | D19: — | E19: — | H19: NOT transferable, and onshore Japan by definition. K2, POS-IMS, W13WEP-JPN and JP-RPASS.
B20: MetLife Japan FTE | C20: =SUMIFS('Seat Ledger'!$M$5:$M$235,'Seat Ledger'!$B$5:$B$235,1,'Seat Ledger'!$J$5:$J$235,"FTE") | D20: ='Logic Tree'!C9 | E20: =C20-D20 | H20: Product owners, domain SMEs and application owners.
B21: MetLife MGCC | C21: =SUMIFS('Seat Ledger'!$M$5:$M$235,'Seat Ledger'!$B$5:$B$235,1,'Seat Ledger'!$J$5:$J$235,"MGCC") | D21: ='Logic Tree'!C10 | E21: =C21-D21 | H21: 15.99 units on day one — MGCC is already the second largest sourcing pool in this domain.
B22: Vendor onshore Tokyo | C22: =SUMIFS('Seat Ledger'!$M$5:$M$235,'Seat Ledger'!$B$5:$B$235,1,'Seat Ledger'!$J$5:$J$235,"FTC",'Seat Ledger'!$I$5:$I$235,"ON")+SUMIFS('Seat Ledger'!$M$5:$M$235,'Seat Ledger'!$B$5:$B$235,1,'Seat Ledger'!$J$5:$J$235,"PT",'Seat Ledger'!$I$5:$I$235,"ON") | D22: ='Logic Tree'!C11 | E22: =C22-D22 | H22: MEASURED, not assumed.
B23: Vendor nearshore | C23: =SUMIFS('Seat Ledger'!$M$5:$M$235,'Seat Ledger'!$B$5:$B$235,1,'Seat Ledger'!$J$5:$J$235,"FTC",'Seat Ledger'!$I$5:$I$235,"NEAR")+SUMIFS('Seat Ledger'!$M$5:$M$235,'Seat Ledger'!$B$5:$B$235,1,'Seat Ledger'!$J$5:$J$235,"PT",'Seat Ledger'!$I$5:$I$235,"NEAR") | D23: ='Logic Tree'!C13 | E23: =C23-D23 | H23: Zero. There is no nearshore capacity in this 領域.
B24: Vendor offshore | C24: =SUMIFS('Seat Ledger'!$M$5:$M$235,'Seat Ledger'!$B$5:$B$235,1,'Seat Ledger'!$J$5:$J$235,"FTC",'Seat Ledger'!$I$5:$I$235,"OFF")+SUMIFS('Seat Ledger'!$M$5:$M$235,'Seat Ledger'!$B$5:$B$235,1,'Seat Ledger'!$J$5:$J$235,"PT",'Seat Ledger'!$I$5:$I$235,"OFF") | D24: ='Logic Tree'!C12 | E24: =C24-D24 | H24: 28.87 units already offshore — 44% of the Capgemini population on day one. MGCC is excluded: it is MetLife's.
B25: Role — BSA | C25: =SUMIFS('Seat Ledger'!$M$5:$M$235,'Seat Ledger'!$B$5:$B$235,1,'Seat Ledger'!$J$5:$J$235,"FTC",'Seat Ledger'!$G$5:$G$235,"BSA")+SUMIFS('Seat Ledger'!$M$5:$M$235,'Seat Ledger'!$B$5:$B$235,1,'Seat Ledger'!$J$5:$J$235,"PT",'Seat Ledger'!$G$5:$G$235,"BSA") | D25: ='Logic Tree'!C15 | E25: =C25-D25 | H25: Reconciles.
B26: Role — Developer | C26: =SUMIFS('Seat Ledger'!$M$5:$M$235,'Seat Ledger'!$B$5:$B$235,1,'Seat Ledger'!$J$5:$J$235,"FTC",'Seat Ledger'!$G$5:$G$235,"DEV")+SUMIFS('Seat Ledger'!$M$5:$M$235,'Seat Ledger'!$B$5:$B$235,1,'Seat Ledger'!$J$5:$J$235,"PT",'Seat Ledger'!$G$5:$G$235,"DEV") | D26: ='Logic Tree'!C16 | E26: =C26-D26 | H26: As reported. 66% of the vendor population.
B27: Role — Tester | C27: =SUMIFS('Seat Ledger'!$M$5:$M$235,'Seat Ledger'!$B$5:$B$235,1,'Seat Ledger'!$J$5:$J$235,"FTC",'Seat Ledger'!$G$5:$G$235,"TEST")+SUMIFS('Seat Ledger'!$M$5:$M$235,'Seat Ledger'!$B$5:$B$235,1,'Seat Ledger'!$J$5:$J$235,"PT",'Seat Ledger'!$G$5:$G$235,"TEST") | D27: ='Logic Tree'!C17 | E27: =C27-D27 | H27: As reported. The lowest tester share in the portfolio, at 7.9%.
B28: Role — Maintenance | C28: =SUMIFS('Seat Ledger'!$M$5:$M$235,'Seat Ledger'!$B$5:$B$235,1,'Seat Ledger'!$J$5:$J$235,"FTC",'Seat Ledger'!$G$5:$G$235,"MNT")+SUMIFS('Seat Ledger'!$M$5:$M$235,'Seat Ledger'!$B$5:$B$235,1,'Seat Ledger'!$J$5:$J$235,"PT",'Seat Ledger'!$G$5:$G$235,"MNT") | D28: ='Logic Tree'!C18 | E28: =C28-D28 | H28: As reported by MetLife and used unchanged.
B29: Role — PM | C29: =SUMIFS('Seat Ledger'!$M$5:$M$235,'Seat Ledger'!$B$5:$B$235,1,'Seat Ledger'!$J$5:$J$235,"FTC",'Seat Ledger'!$G$5:$G$235,"PM")+SUMIFS('Seat Ledger'!$M$5:$M$235,'Seat Ledger'!$B$5:$B$235,1,'Seat Ledger'!$J$5:$J$235,"PT",'Seat Ledger'!$G$5:$G$235,"PM") | D29: ='Logic Tree'!C19 | E29: =C29-D29 | H29: As reported. Thin at 2.2%, but populated.
B30: Role — Other | C30: =SUMIFS('Seat Ledger'!$M$5:$M$235,'Seat Ledger'!$B$5:$B$235,1,'Seat Ledger'!$J$5:$J$235,"FTC",'Seat Ledger'!$G$5:$G$235,"OTH")+SUMIFS('Seat Ledger'!$M$5:$M$235,'Seat Ledger'!$B$5:$B$235,1,'Seat Ledger'!$J$5:$J$235,"PT",'Seat Ledger'!$G$5:$G$235,"OTH") | D30: ='Logic Tree'!C20 | E30: =C30-D30 | H30: As reported. Architecture and enablement.
B31: Largest variance across every reconciling line | E31: =MAX(ABS(E16),ABS(E17),ABS(E20),ABS(E21),ABS(E22),ABS(E23),ABS(E24),ABS(E25),ABS(E26),ABS(E27),ABS(E28),ABS(E29),ABS(E30)) | G31: Appendix 3 v5 is internally consistent for all fifteen applications once the duplicate K2 line is excluded: every Total equals its FTC + FTE + MGCC. There is no unallocated capacity to carry.
B32: Largest variance excluding the MetLife FTE line (twelve lines) | E32: =MAX(ABS(E16),ABS(E17),ABS(E21),ABS(E22),ABS(E23),ABS(E24),ABS(E25),ABS(E26),ABS(E27),ABS(E28),ABS(E29),ABS(E30)) | G32: Every line — effort, vendor total, MetLife FTE, MGCC, both locations and all six client role lines — reconciles to within a few hundredths of a person after head-grid quantisation.
A33: C. THE ROLE LINE — used exactly as MetLife reports it
B34: Role | C34: Appendix 3 v5 | D34: This model | E34: Difference | H34: Note
B35: BSA | C35: ='Logic Tree'!C15 | D35: =C25 | E35: =D35-C35 | H35: 12.4% of the vendor population, all of it on K2. Bilingual analysis against Japanese business rules is the scarcest skill in this 領域.
B36: Developer | C36: ='Logic Tree'!C16 | D36: =C26 | E36: =D36-C36 | H36: 55.5% after restatement, against 65.4% as MetLife reports it. VB.NET, Java and a COTS RPA product.
B37: Tester | C37: ='Logic Tree'!C17 | D37: =C27 | E37: =D37-C37 | H37: 17.0%, and every tester unit sits on K2. The fourteen satellites carry no test capacity at all in MetLife's own data.
B38: Maintenance | C38: ='Logic Tree'!C18 | D38: =C28 | E38: =D38-C38 | H38: RESTATED to 5.00 from 3.48. 1,145 incidents and 2,071 changes a year cannot be run on 3.5 people.
B39: PM | C39: ='Logic Tree'!C19 | D39: =C29 | E39: =D39-C39 | H39: RESTATED to 3.00 from 0.14. Fifteen applications, two value streams and a named sub-contractor cannot be coordinated on 0.14 units.
B40: Other | C40: ='Logic Tree'!C20 | D40: =C30 | E40: =D40-C40 | H40: RESTATED to 2.50 from ZERO. MetLife records no architecture or enablement capacity anywhere in this 領域.
B41: Sum of the six role lines | C41: =SUM(C35:C40) | D41: =SUM(D35:D40) | E41: =D41-C41 | H41: THREE LINES RESTATED, ARITHMETICALLY NEUTRAL. MetLife reports 3.48 maintenance, 0.14 PM and zero architecture across fifteen applications carrying 1,145 incidents and 2,071 changes a year. We move 6.88 units out of Developer into Maintenance, PM and Other. The total does not change by a single unit. This is a smaller correction than Contract Management needed, and it goes back to MetLife as a clarification question rather than a re-pricing.
A43: D. SOURCING, LOCATION AND THE THREE OFFSHORE BASES
B44: Measure | C44: Year 1 | D44: Year 2 | E44: Year 3 | F44: Year 4 | G44: Year 5
B45: Capgemini payroll (FTC) | C45: =SUMIFS('Seat Ledger'!$M$5:$M$235,'Seat Ledger'!$B$5:$B$235,1,'Seat Ledger'!$J$5:$J$235,"FTC") | D45: =SUMIFS('Seat Ledger'!$M$5:$M$235,'Seat Ledger'!$B$5:$B$235,2,'Seat Ledger'!$J$5:$J$235,"FTC") | E45: =SUMIFS('Seat Ledger'!$M$5:$M$235,'Seat Ledger'!$B$5:$B$235,3,'Seat Ledger'!$J$5:$J$235,"FTC") | F45: =SUMIFS('Seat Ledger'!$M$5:$M$235,'Seat Ledger'!$B$5:$B$235,4,'Seat Ledger'!$J$5:$J$235,"FTC") | G45: =SUMIFS('Seat Ledger'!$M$5:$M$235,'Seat Ledger'!$B$5:$B$235,5,'Seat Ledger'!$J$5:$J$235,"FTC")
B46: Incumbent partner (PT) | C46: =SUMIFS('Seat Ledger'!$M$5:$M$235,'Seat Ledger'!$B$5:$B$235,1,'Seat Ledger'!$J$5:$J$235,"PT") | D46: =SUMIFS('Seat Ledger'!$M$5:$M$235,'Seat Ledger'!$B$5:$B$235,2,'Seat Ledger'!$J$5:$J$235,"PT") | E46: =SUMIFS('Seat Ledger'!$M$5:$M$235,'Seat Ledger'!$B$5:$B$235,3,'Seat Ledger'!$J$5:$J$235,"PT") | F46: =SUMIFS('Seat Ledger'!$M$5:$M$235,'Seat Ledger'!$B$5:$B$235,4,'Seat Ledger'!$J$5:$J$235,"PT") | G46: =SUMIFS('Seat Ledger'!$M$5:$M$235,'Seat Ledger'!$B$5:$B$235,5,'Seat Ledger'!$J$5:$J$235,"PT")
B47: VENDOR TOTAL = Appendix 3 FTC | C47: =C45+C46 | D47: =D45+D46 | E47: =E45+E46 | F47: =F45+F46 | G47: =G45+G46
B48: MetLife Japan (FTE) | C48: =SUMIFS('Seat Ledger'!$M$5:$M$235,'Seat Ledger'!$B$5:$B$235,1,'Seat Ledger'!$J$5:$J$235,"FTE") | D48: =SUMIFS('Seat Ledger'!$M$5:$M$235,'Seat Ledger'!$B$5:$B$235,2,'Seat Ledger'!$J$5:$J$235,"FTE") | E48: =SUMIFS('Seat Ledger'!$M$5:$M$235,'Seat Ledger'!$B$5:$B$235,3,'Seat Ledger'!$J$5:$J$235,"FTE") | F48: =SUMIFS('Seat Ledger'!$M$5:$M$235,'Seat Ledger'!$B$5:$B$235,4,'Seat Ledger'!$J$5:$J$235,"FTE") | G48: =SUMIFS('Seat Ledger'!$M$5:$M$235,'Seat Ledger'!$B$5:$B$235,5,'Seat Ledger'!$J$5:$J$235,"FTE")
B49: MetLife MGCC | C49: =SUMIFS('Seat Ledger'!$M$5:$M$235,'Seat Ledger'!$B$5:$B$235,1,'Seat Ledger'!$J$5:$J$235,"MGCC") | D49: =SUMIFS('Seat Ledger'!$M$5:$M$235,'Seat Ledger'!$B$5:$B$235,2,'Seat Ledger'!$J$5:$J$235,"MGCC") | E49: =SUMIFS('Seat Ledger'!$M$5:$M$235,'Seat Ledger'!$B$5:$B$235,3,'Seat Ledger'!$J$5:$J$235,"MGCC") | F49: =SUMIFS('Seat Ledger'!$M$5:$M$235,'Seat Ledger'!$B$5:$B$235,4,'Seat Ledger'!$J$5:$J$235,"MGCC") | G49: =SUMIFS('Seat Ledger'!$M$5:$M$235,'Seat Ledger'!$B$5:$B$235,5,'Seat Ledger'!$J$5:$J$235,"MGCC")
B50: RATIO — vendor share | C50: =IF(C9=0,0,C47/C9) | D50: =IF(D9=0,0,D47/D9) | E50: =IF(E9=0,0,E47/E9) | F50: =IF(F9=0,0,F47/F9) | G50: =IF(G9=0,0,G47/G9)
B51: Onshore Tokyo | C51: =SUMIFS('Seat Ledger'!$M$5:$M$235,'Seat Ledger'!$B$5:$B$235,1,'Seat Ledger'!$I$5:$I$235,"ON") | D51: =SUMIFS('Seat Ledger'!$M$5:$M$235,'Seat Ledger'!$B$5:$B$235,2,'Seat Ledger'!$I$5:$I$235,"ON") | E51: =SUMIFS('Seat Ledger'!$M$5:$M$235,'Seat Ledger'!$B$5:$B$235,3,'Seat Ledger'!$I$5:$I$235,"ON") | F51: =SUMIFS('Seat Ledger'!$M$5:$M$235,'Seat Ledger'!$B$5:$B$235,4,'Seat Ledger'!$I$5:$I$235,"ON") | G51: =SUMIFS('Seat Ledger'!$M$5:$M$235,'Seat Ledger'!$B$5:$B$235,5,'Seat Ledger'!$I$5:$I$235,"ON")
B52: Offshore | C52: =SUMIFS('Seat Ledger'!$M$5:$M$235,'Seat Ledger'!$B$5:$B$235,1,'Seat Ledger'!$I$5:$I$235,"OFF") | D52: =SUMIFS('Seat Ledger'!$M$5:$M$235,'Seat Ledger'!$B$5:$B$235,2,'Seat Ledger'!$I$5:$I$235,"OFF") | E52: =SUMIFS('Seat Ledger'!$M$5:$M$235,'Seat Ledger'!$B$5:$B$235,3,'Seat Ledger'!$I$5:$I$235,"OFF") | F52: =SUMIFS('Seat Ledger'!$M$5:$M$235,'Seat Ledger'!$B$5:$B$235,4,'Seat Ledger'!$I$5:$I$235,"OFF") | G52: =SUMIFS('Seat Ledger'!$M$5:$M$235,'Seat Ledger'!$B$5:$B$235,5,'Seat Ledger'!$I$5:$I$235,"OFF")
B53: Nearshore | C53: =SUMIFS('Seat Ledger'!$M$5:$M$235,'Seat Ledger'!$B$5:$B$235,1,'Seat Ledger'!$I$5:$I$235,"NEAR") | D53: =SUMIFS('Seat Ledger'!$M$5:$M$235,'Seat Ledger'!$B$5:$B$235,2,'Seat Ledger'!$I$5:$I$235,"NEAR") | E53: =SUMIFS('Seat Ledger'!$M$5:$M$235,'Seat Ledger'!$B$5:$B$235,3,'Seat Ledger'!$I$5:$I$235,"NEAR") | F53: =SUMIFS('Seat Ledger'!$M$5:$M$235,'Seat Ledger'!$B$5:$B$235,4,'Seat Ledger'!$I$5:$I$235,"NEAR") | G53: =SUMIFS('Seat Ledger'!$M$5:$M$235,'Seat Ledger'!$B$5:$B$235,5,'Seat Ledger'!$I$5:$I$235,"NEAR")
B54: Offshore share — whole team | C54: =IF(C9=0,0,(C52+C53)/C9) | D54: =IF(D9=0,0,(D52+D53)/D9) | E54: =IF(E9=0,0,(E52+E53)/E9) | F54: =IF(F9=0,0,(F52+F53)/F9) | G54: =IF(G9=0,0,(G52+G53)/G9)
B55: Offshore share — vendor only | C55: =IF(C47=0,0,(SUMIFS('Seat Ledger'!$M$5:$M$235,'Seat Ledger'!$B$5:$B$235,1,'Seat Ledger'!$J$5:$J$235,"FTC",'Seat Ledger'!$I$5:$I$235,"OFF")+SUMIFS('Seat Ledger'!$M$5:$M$235,'Seat Ledger'!$B$5:$B$235,1,'Seat Ledger'!$J$5:$J$235,"FTC",'Seat Ledger'!$I$5:$I$235,"NEAR")+SUMIFS('Seat Ledger'!$M$5:$M$235,'Seat Ledger'!$B$5:$B$235,1,'Seat Ledger'!$J$5:$J$235,"PT",'Seat Ledger'!$I$5:$I$235,"OFF"))/C47) | D55: =IF(D47=0,0,(SUMIFS('Seat Ledger'!$M$5:$M$235,'Seat Ledger'!$B$5:$B$235,2,'Seat Ledger'!$J$5:$J$235,"FTC",'Seat Ledger'!$I$5:$I$235,"OFF")+SUMIFS('Seat Ledger'!$M$5:$M$235,'Seat Ledger'!$B$5:$B$235,2,'Seat Ledger'!$J$5:$J$235,"FTC",'Seat Ledger'!$I$5:$I$235,"NEAR")+SUMIFS('Seat Ledger'!$M$5:$M$235,'Seat Ledger'!$B$5:$B$235,2,'Seat Ledger'!$J$5:$J$235,"PT",'Seat Ledger'!$I$5:$I$235,"OFF"))/D47) | E55: =IF(E47=0,0,(SUMIFS('Seat Ledger'!$M$5:$M$235,'Seat Ledger'!$B$5:$B$235,3,'Seat Ledger'!$J$5:$J$235,"FTC",'Seat Ledger'!$I$5:$I$235,"OFF")+SUMIFS('Seat Ledger'!$M$5:$M$235,'Seat Ledger'!$B$5:$B$235,3,'Seat Ledger'!$J$5:$J$235,"FTC",'Seat Ledger'!$I$5:$I$235,"NEAR")+SUMIFS('Seat Ledger'!$M$5:$M$235,'Seat Ledger'!$B$5:$B$235,3,'Seat Ledger'!$J$5:$J$235,"PT",'Seat Ledger'!$I$5:$I$235,"OFF"))/E47) | F55: =IF(F47=0,0,(SUMIFS('Seat Ledger'!$M$5:$M$235,'Seat Ledger'!$B$5:$B$235,4,'Seat Ledger'!$J$5:$J$235,"FTC",'Seat Ledger'!$I$5:$I$235,"OFF")+SUMIFS('Seat Ledger'!$M$5:$M$235,'Seat Ledger'!$B$5:$B$235,4,'Seat Ledger'!$J$5:$J$235,"FTC",'Seat Ledger'!$I$5:$I$235,"NEAR")+SUMIFS('Seat Ledger'!$M$5:$M$235,'Seat Ledger'!$B$5:$B$235,4,'Seat Ledger'!$J$5:$J$235,"PT",'Seat Ledger'!$I$5:$I$235,"OFF"))/F47) | G55: =IF(G47=0,0,(SUMIFS('Seat Ledger'!$M$5:$M$235,'Seat Ledger'!$B$5:$B$235,5,'Seat Ledger'!$J$5:$J$235,"FTC",'Seat Ledger'!$I$5:$I$235,"OFF")+SUMIFS('Seat Ledger'!$M$5:$M$235,'Seat Ledger'!$B$5:$B$235,5,'Seat Ledger'!$J$5:$J$235,"FTC",'Seat Ledger'!$I$5:$I$235,"NEAR")+SUMIFS('Seat Ledger'!$M$5:$M$235,'Seat Ledger'!$B$5:$B$235,5,'Seat Ledger'!$J$5:$J$235,"PT",'Seat Ledger'!$I$5:$I$235,"OFF"))/G47)
B56: Offshore share — Capgemini payroll only | C56: =IF(C45=0,0,(SUMIFS('Seat Ledger'!$M$5:$M$235,'Seat Ledger'!$B$5:$B$235,1,'Seat Ledger'!$J$5:$J$235,"FTC",'Seat Ledger'!$I$5:$I$235,"OFF")+SUMIFS('Seat Ledger'!$M$5:$M$235,'Seat Ledger'!$B$5:$B$235,1,'Seat Ledger'!$J$5:$J$235,"FTC",'Seat Ledger'!$I$5:$I$235,"NEAR"))/C45) | D56: =IF(D45=0,0,(SUMIFS('Seat Ledger'!$M$5:$M$235,'Seat Ledger'!$B$5:$B$235,2,'Seat Ledger'!$J$5:$J$235,"FTC",'Seat Ledger'!$I$5:$I$235,"OFF")+SUMIFS('Seat Ledger'!$M$5:$M$235,'Seat Ledger'!$B$5:$B$235,2,'Seat Ledger'!$J$5:$J$235,"FTC",'Seat Ledger'!$I$5:$I$235,"NEAR"))/D45) | E56: =IF(E45=0,0,(SUMIFS('Seat Ledger'!$M$5:$M$235,'Seat Ledger'!$B$5:$B$235,3,'Seat Ledger'!$J$5:$J$235,"FTC",'Seat Ledger'!$I$5:$I$235,"OFF")+SUMIFS('Seat Ledger'!$M$5:$M$235,'Seat Ledger'!$B$5:$B$235,3,'Seat Ledger'!$J$5:$J$235,"FTC",'Seat Ledger'!$I$5:$I$235,"NEAR"))/E45) | F56: =IF(F45=0,0,(SUMIFS('Seat Ledger'!$M$5:$M$235,'Seat Ledger'!$B$5:$B$235,4,'Seat Ledger'!$J$5:$J$235,"FTC",'Seat Ledger'!$I$5:$I$235,"OFF")+SUMIFS('Seat Ledger'!$M$5:$M$235,'Seat Ledger'!$B$5:$B$235,4,'Seat Ledger'!$J$5:$J$235,"FTC",'Seat Ledger'!$I$5:$I$235,"NEAR"))/F45) | G56: =IF(G45=0,0,(SUMIFS('Seat Ledger'!$M$5:$M$235,'Seat Ledger'!$B$5:$B$235,5,'Seat Ledger'!$J$5:$J$235,"FTC",'Seat Ledger'!$I$5:$I$235,"OFF")+SUMIFS('Seat Ledger'!$M$5:$M$235,'Seat Ledger'!$B$5:$B$235,5,'Seat Ledger'!$J$5:$J$235,"FTC",'Seat Ledger'!$I$5:$I$235,"NEAR"))/G45) | I56: Rises across the five years and keeps rising through Year 4. Only 5 people transfer, so our own offshore book survives the event — the opposite of Contract Management.
B57: Target from the Logic Tree | C57: ='Logic Tree'!C68 | D57: ='Logic Tree'!D68 | E57: ='Logic Tree'!E68 | F57: ='Logic Tree'!F68 | G57: ='Logic Tree'!G68
A59: E. ROLE MIX — MetLife's taxonomy, all sourcing types
B60: Role | C60: Year 1 | D60: Year 2 | E60: Year 3 | F60: Year 4 | G60: Year 5
B61: BSA — business and systems analysis | C61: =SUMIFS('Seat Ledger'!$M$5:$M$235,'Seat Ledger'!$B$5:$B$235,1,'Seat Ledger'!$G$5:$G$235,"BSA") | D61: =SUMIFS('Seat Ledger'!$M$5:$M$235,'Seat Ledger'!$B$5:$B$235,2,'Seat Ledger'!$G$5:$G$235,"BSA") | E61: =SUMIFS('Seat Ledger'!$M$5:$M$235,'Seat Ledger'!$B$5:$B$235,3,'Seat Ledger'!$G$5:$G$235,"BSA") | F61: =SUMIFS('Seat Ledger'!$M$5:$M$235,'Seat Ledger'!$B$5:$B$235,4,'Seat Ledger'!$G$5:$G$235,"BSA") | G61: =SUMIFS('Seat Ledger'!$M$5:$M$235,'Seat Ledger'!$B$5:$B$235,5,'Seat Ledger'!$G$5:$G$235,"BSA")
B62: Developer | C62: =SUMIFS('Seat Ledger'!$M$5:$M$235,'Seat Ledger'!$B$5:$B$235,1,'Seat Ledger'!$G$5:$G$235,"DEV") | D62: =SUMIFS('Seat Ledger'!$M$5:$M$235,'Seat Ledger'!$B$5:$B$235,2,'Seat Ledger'!$G$5:$G$235,"DEV") | E62: =SUMIFS('Seat Ledger'!$M$5:$M$235,'Seat Ledger'!$B$5:$B$235,3,'Seat Ledger'!$G$5:$G$235,"DEV") | F62: =SUMIFS('Seat Ledger'!$M$5:$M$235,'Seat Ledger'!$B$5:$B$235,4,'Seat Ledger'!$G$5:$G$235,"DEV") | G62: =SUMIFS('Seat Ledger'!$M$5:$M$235,'Seat Ledger'!$B$5:$B$235,5,'Seat Ledger'!$G$5:$G$235,"DEV")
B63: Tester | C63: =SUMIFS('Seat Ledger'!$M$5:$M$235,'Seat Ledger'!$B$5:$B$235,1,'Seat Ledger'!$G$5:$G$235,"TEST") | D63: =SUMIFS('Seat Ledger'!$M$5:$M$235,'Seat Ledger'!$B$5:$B$235,2,'Seat Ledger'!$G$5:$G$235,"TEST") | E63: =SUMIFS('Seat Ledger'!$M$5:$M$235,'Seat Ledger'!$B$5:$B$235,3,'Seat Ledger'!$G$5:$G$235,"TEST") | F63: =SUMIFS('Seat Ledger'!$M$5:$M$235,'Seat Ledger'!$B$5:$B$235,4,'Seat Ledger'!$G$5:$G$235,"TEST") | G63: =SUMIFS('Seat Ledger'!$M$5:$M$235,'Seat Ledger'!$B$5:$B$235,5,'Seat Ledger'!$G$5:$G$235,"TEST")
B64: Maintenance | C64: =SUMIFS('Seat Ledger'!$M$5:$M$235,'Seat Ledger'!$B$5:$B$235,1,'Seat Ledger'!$G$5:$G$235,"MNT") | D64: =SUMIFS('Seat Ledger'!$M$5:$M$235,'Seat Ledger'!$B$5:$B$235,2,'Seat Ledger'!$G$5:$G$235,"MNT") | E64: =SUMIFS('Seat Ledger'!$M$5:$M$235,'Seat Ledger'!$B$5:$B$235,3,'Seat Ledger'!$G$5:$G$235,"MNT") | F64: =SUMIFS('Seat Ledger'!$M$5:$M$235,'Seat Ledger'!$B$5:$B$235,4,'Seat Ledger'!$G$5:$G$235,"MNT") | G64: =SUMIFS('Seat Ledger'!$M$5:$M$235,'Seat Ledger'!$B$5:$B$235,5,'Seat Ledger'!$G$5:$G$235,"MNT")
B65: PM and product ownership | C65: =SUMIFS('Seat Ledger'!$M$5:$M$235,'Seat Ledger'!$B$5:$B$235,1,'Seat Ledger'!$G$5:$G$235,"PM") | D65: =SUMIFS('Seat Ledger'!$M$5:$M$235,'Seat Ledger'!$B$5:$B$235,2,'Seat Ledger'!$G$5:$G$235,"PM") | E65: =SUMIFS('Seat Ledger'!$M$5:$M$235,'Seat Ledger'!$B$5:$B$235,3,'Seat Ledger'!$G$5:$G$235,"PM") | F65: =SUMIFS('Seat Ledger'!$M$5:$M$235,'Seat Ledger'!$B$5:$B$235,4,'Seat Ledger'!$G$5:$G$235,"PM") | G65: =SUMIFS('Seat Ledger'!$M$5:$M$235,'Seat Ledger'!$B$5:$B$235,5,'Seat Ledger'!$G$5:$G$235,"PM")
B66: Other — architecture and enablement | C66: =SUMIFS('Seat Ledger'!$M$5:$M$235,'Seat Ledger'!$B$5:$B$235,1,'Seat Ledger'!$G$5:$G$235,"OTH") | D66: =SUMIFS('Seat Ledger'!$M$5:$M$235,'Seat Ledger'!$B$5:$B$235,2,'Seat Ledger'!$G$5:$G$235,"OTH") | E66: =SUMIFS('Seat Ledger'!$M$5:$M$235,'Seat Ledger'!$B$5:$B$235,3,'Seat Ledger'!$G$5:$G$235,"OTH") | F66: =SUMIFS('Seat Ledger'!$M$5:$M$235,'Seat Ledger'!$B$5:$B$235,4,'Seat Ledger'!$G$5:$G$235,"OTH") | G66: =SUMIFS('Seat Ledger'!$M$5:$M$235,'Seat Ledger'!$B$5:$B$235,5,'Seat Ledger'!$G$5:$G$235,"OTH")
B67: Run-facing share (Maintenance + Tester) | C67: =IF(C9=0,0,(C63+C64)/C9) | D67: =IF(D9=0,0,(D63+D64)/D9) | E67: =IF(E9=0,0,(E63+E64)/E9) | F67: =IF(F9=0,0,(F63+F64)/F9) | G67: =IF(G9=0,0,(G63+G64)/G9) | I67: 15.3% in Year 1 falling to 9.0% by Year 5, as pipeline automation and auto-remediation land.
A69: F. EXPERIENCE MIX
B70: Band | C70: Year 1 | D70: Year 2 | E70: Year 3 | F70: Year 4 | G70: Year 5
B71: E1 | C71: =SUMIFS('Seat Ledger'!$M$5:$M$235,'Seat Ledger'!$B$5:$B$235,1,'Seat Ledger'!$H$5:$H$235,"E1") | D71: =SUMIFS('Seat Ledger'!$M$5:$M$235,'Seat Ledger'!$B$5:$B$235,2,'Seat Ledger'!$H$5:$H$235,"E1") | E71: =SUMIFS('Seat Ledger'!$M$5:$M$235,'Seat Ledger'!$B$5:$B$235,3,'Seat Ledger'!$H$5:$H$235,"E1") | F71: =SUMIFS('Seat Ledger'!$M$5:$M$235,'Seat Ledger'!$B$5:$B$235,4,'Seat Ledger'!$H$5:$H$235,"E1") | G71: =SUMIFS('Seat Ledger'!$M$5:$M$235,'Seat Ledger'!$B$5:$B$235,5,'Seat Ledger'!$H$5:$H$235,"E1")
B72: E2 | C72: =SUMIFS('Seat Ledger'!$M$5:$M$235,'Seat Ledger'!$B$5:$B$235,1,'Seat Ledger'!$H$5:$H$235,"E2") | D72: =SUMIFS('Seat Ledger'!$M$5:$M$235,'Seat Ledger'!$B$5:$B$235,2,'Seat Ledger'!$H$5:$H$235,"E2") | E72: =SUMIFS('Seat Ledger'!$M$5:$M$235,'Seat Ledger'!$B$5:$B$235,3,'Seat Ledger'!$H$5:$H$235,"E2") | F72: =SUMIFS('Seat Ledger'!$M$5:$M$235,'Seat Ledger'!$B$5:$B$235,4,'Seat Ledger'!$H$5:$H$235,"E2") | G72: =SUMIFS('Seat Ledger'!$M$5:$M$235,'Seat Ledger'!$B$5:$B$235,5,'Seat Ledger'!$H$5:$H$235,"E2")
B73: E3 | C73: =SUMIFS('Seat Ledger'!$M$5:$M$235,'Seat Ledger'!$B$5:$B$235,1,'Seat Ledger'!$H$5:$H$235,"E3") | D73: =SUMIFS('Seat Ledger'!$M$5:$M$235,'Seat Ledger'!$B$5:$B$235,2,'Seat Ledger'!$H$5:$H$235,"E3") | E73: =SUMIFS('Seat Ledger'!$M$5:$M$235,'Seat Ledger'!$B$5:$B$235,3,'Seat Ledger'!$H$5:$H$235,"E3") | F73: =SUMIFS('Seat Ledger'!$M$5:$M$235,'Seat Ledger'!$B$5:$B$235,4,'Seat Ledger'!$H$5:$H$235,"E3") | G73: =SUMIFS('Seat Ledger'!$M$5:$M$235,'Seat Ledger'!$B$5:$B$235,5,'Seat Ledger'!$H$5:$H$235,"E3")
B74: E4 | C74: =SUMIFS('Seat Ledger'!$M$5:$M$235,'Seat Ledger'!$B$5:$B$235,1,'Seat Ledger'!$H$5:$H$235,"E4") | D74: =SUMIFS('Seat Ledger'!$M$5:$M$235,'Seat Ledger'!$B$5:$B$235,2,'Seat Ledger'!$H$5:$H$235,"E4") | E74: =SUMIFS('Seat Ledger'!$M$5:$M$235,'Seat Ledger'!$B$5:$B$235,3,'Seat Ledger'!$H$5:$H$235,"E4") | F74: =SUMIFS('Seat Ledger'!$M$5:$M$235,'Seat Ledger'!$B$5:$B$235,4,'Seat Ledger'!$H$5:$H$235,"E4") | G74: =SUMIFS('Seat Ledger'!$M$5:$M$235,'Seat Ledger'!$B$5:$B$235,5,'Seat Ledger'!$H$5:$H$235,"E4")
B75: E5 | C75: =SUMIFS('Seat Ledger'!$M$5:$M$235,'Seat Ledger'!$B$5:$B$235,1,'Seat Ledger'!$H$5:$H$235,"E5") | D75: =SUMIFS('Seat Ledger'!$M$5:$M$235,'Seat Ledger'!$B$5:$B$235,2,'Seat Ledger'!$H$5:$H$235,"E5") | E75: =SUMIFS('Seat Ledger'!$M$5:$M$235,'Seat Ledger'!$B$5:$B$235,3,'Seat Ledger'!$H$5:$H$235,"E5") | F75: =SUMIFS('Seat Ledger'!$M$5:$M$235,'Seat Ledger'!$B$5:$B$235,4,'Seat Ledger'!$H$5:$H$235,"E5") | G75: =SUMIFS('Seat Ledger'!$M$5:$M$235,'Seat Ledger'!$B$5:$B$235,5,'Seat Ledger'!$H$5:$H$235,"E5")
B76: Senior share (E4 + E5) | C76: =IF(C9=0,0,(C74+C75)/C9) | D76: =IF(D9=0,0,(D74+D75)/D9) | E76: =IF(E9=0,0,(E74+E75)/E9) | F76: =IF(F9=0,0,(F74+F75)/F9) | G76: =IF(G9=0,0,(G74+G75)/G9)

Sheet Inherited Workforce
A1: The 20 Capgemini people already on these applications — and why this cohort is the opposite problem
A2: Supply comes from the T3 headcount reconciliation behind Golden Inventory v4. THE POSITION HERE IS A SURPLUS, NOT A SHORTAGE: 37 of the 41 inherited people are offshore, and the design asks for only 8.5 offshore Capgemini seats in Year 1. This is a redeployment and bench problem in the early years, and it only becomes a hiring problem at E1/E2 once the offshore build scales.
A4: A. WHERE THE NUMBER COMES FROM
B5: Source | C5: Count | D5: What it is used for
B6: Billing details — named individuals | C6: 277 | D6: THE COUNT. 277 de-duplicated employee IDs across T3, DMO and JET, each with a location and a Capgemini grade.
B7: Mapping of current Capgemini staff — billable FTE | C7: 283 | D7: THE ROLE MIX and the grade ladder. Developer → Developer, Cloud Engineer → Maintenance, Testers → Tester, BSA / Scrum Master / Functional Analyst → BSA, Tech Lead / Solution Architect → Other.
B8: EAIs.xlsx — 'CG HC by EAI' | C8: 450 | D8: THE SHAPE of the application-level distribution, rescaled to 277 and capped at each application's own vendor FTC.
B9: EAIs.xlsx Sheet1 — direct EAI tags | C9: 528 | D9: Cross-check only. Double-counts people serving more than one application.
B10: Of the 277, allocated to Storage and Preservation | C10: 41 | D10: 37 in India, 4 in Japan. 45 of the 277 sit in cross-domain teams with no application mapping and are excluded from every domain.
B12: Capgemini grade → experience band: A4/A5 → E1 · B1/B2 → E2 · C1 and Sub-Con → E3 · C2/D1 → E4 · D2/E1 → E5. Location is binary: Japan → onshore, everything else → India / offshore.
A14: B. WHERE THEY SIT TODAY
B15: Application | C15: Archetype | D15: Value stream | E15: CG heads today | F15: Vendor FTC
B16: K2 | C16: D | D16: Policy Owner Servicing Work Flow (K2 only) | E16: 36.1 | F16: 36.105 | J16: 41 people against 69.4 vendor units, and 36.1 of them sit on K2 alone. The concentration is the point: we have deep continuity on the one application that matters and almost none on the fourteen satellites — which is precisely why FSI holds four of them as a service cell.
B17: Satellites, Payment & Records (14 apps) | C17: J / T | D17: Policy Owner Servicing Payment & Records | E17: 4.9 | F17: 33.321
B19: TOTAL | E19: =SUM(E16:E18) | F19: =SUM(F16:F18)
A21: C. THE EVOLUTION MECHANIC — INPUT
B22: Band | C22: Attrition — offshore | D22: Attrition — onshore | E22: Promotion out of band
B23: E1 | C23: 0.22 | D23: 0.1 | E23: 0.2 | J23: Identical rates to Sales / Insurance v6 and Contract Management v7 — attrition first, promotion to the survivors. The same mechanic, applied to a very different starting shape.
B24: E2 | C24: 0.18 | D24: 0.09 | E24: 0.16
B25: E3 | C25: 0.13 | D25: 0.07 | E25: 0.12
B26: E4 | C26: 0.09 | D26: 0.05 | E26: 0.07
B27: E5 | C27: 0.06 | D27: 0.04 | E27: 0
A29: D. THE COHORT ROLLED FORWARD
B30: Measure | C30: Year 1 | D30: Year 2 | E30: Year 3 | F30: Year 4 | G30: Year 5
B31: Inherited people surviving | C31: 41 | D31: 35.51 | E31: 31.009655 | F31: 27.287091 | G31: 24.180578
B32: — E1 | C32: 2 | D32: 1.248 | E32: 0.778752 | F32: 0.48594125 | G32: 0.30322734
B33: — E2 | C33: 12 | D33: 8.5776 | E33: 6.1029389 | F33: 4.3251896 | G33: 3.0549974
B34: — E3 | C34: 16 | D34: 13.8768 | E34: 11.792671 | F34: 9.8645386 | G34: 8.1486978
B35: — E4 | C35: 11 | D35: 11.0985 | E35: 10.950041 | F35: 10.597174 | G35: 10.088179
B36: — E5 | C36: 0 | D36: 0.7091 | E36: 1.3852523 | F36: 2.0142474 | G36: 2.5854756
B37: Senior share (E4 + E5) | C37: 0.26829268 | D37: 0.33251478 | E37: 0.3977888 | F37: 0.46217538 | G37: 0.5241254 | J37: The cohort starts at 26.8% senior (11 of 41 at E4, none at E5) and the attrition-and-promotion mechanic seniorises it every year. Row 37 is the number to watch: it drives cost per head, and the design counters it by hiring at E2 and E3 offshore as the team shrinks.
B38: — in Japan | C38: 4 | D38: 3.78 | E38: 3.576627 | F38: 3.3881521 | G38: 3.213067
B39: — in India | C39: 37 | D39: 31.73 | E39: 27.433028 | F39: 23.898939 | G39: 20.967511
A41: E. SUPPLY AGAINST DEMAND — offshore, where 18 of the 20 sit
B42: Measure | C42: Year 1 | D42: Year 2 | E42: Year 3 | F42: Year 4 | G42: Year 5
B43: Offshore Capgemini seats the design asks for | C43: =SUMIFS('Seat Ledger'!$M$5:$M$235,'Seat Ledger'!$B$5:$B$235,1,'Seat Ledger'!$J$5:$J$235,"FTC",'Seat Ledger'!$I$5:$I$235,"OFF")+SUMIFS('Seat Ledger'!$M$5:$M$235,'Seat Ledger'!$B$5:$B$235,1,'Seat Ledger'!$J$5:$J$235,"FTC",'Seat Ledger'!$I$5:$I$235,"NEAR") | D43: =SUMIFS('Seat Ledger'!$M$5:$M$235,'Seat Ledger'!$B$5:$B$235,2,'Seat Ledger'!$J$5:$J$235,"FTC",'Seat Ledger'!$I$5:$I$235,"OFF")+SUMIFS('Seat Ledger'!$M$5:$M$235,'Seat Ledger'!$B$5:$B$235,2,'Seat Ledger'!$J$5:$J$235,"FTC",'Seat Ledger'!$I$5:$I$235,"NEAR") | E43: =SUMIFS('Seat Ledger'!$M$5:$M$235,'Seat Ledger'!$B$5:$B$235,3,'Seat Ledger'!$J$5:$J$235,"FTC",'Seat Ledger'!$I$5:$I$235,"OFF")+SUMIFS('Seat Ledger'!$M$5:$M$235,'Seat Ledger'!$B$5:$B$235,3,'Seat Ledger'!$J$5:$J$235,"FTC",'Seat Ledger'!$I$5:$I$235,"NEAR") | F43: =SUMIFS('Seat Ledger'!$M$5:$M$235,'Seat Ledger'!$B$5:$B$235,4,'Seat Ledger'!$J$5:$J$235,"FTC",'Seat Ledger'!$I$5:$I$235,"OFF")+SUMIFS('Seat Ledger'!$M$5:$M$235,'Seat Ledger'!$B$5:$B$235,4,'Seat Ledger'!$J$5:$J$235,"FTC",'Seat Ledger'!$I$5:$I$235,"NEAR") | G43: =SUMIFS('Seat Ledger'!$M$5:$M$235,'Seat Ledger'!$B$5:$B$235,5,'Seat Ledger'!$J$5:$J$235,"FTC",'Seat Ledger'!$I$5:$I$235,"OFF")+SUMIFS('Seat Ledger'!$M$5:$M$235,'Seat Ledger'!$B$5:$B$235,5,'Seat Ledger'!$J$5:$J$235,"FTC",'Seat Ledger'!$I$5:$I$235,"NEAR")
B44: Inherited people still there | C44: 37 | D44: 31.73 | E44: 27.433028 | F44: 23.898939 | G44: 20.967511
B45: Covered by people we already have | C45: =C44/C43 | D45: =D44/D43 | E45: =E44/E43 | F45: =F44/F43 | G45: =G44/G43 | J45: 60% covered in Year 1, against 90% on Sales. This domain has to hire more of its own offshore team from a standing start, and the people it hires must be junior enough to balance a cohort that is already senior.
B46: To hire, redeploy or reskill | C46: =C43-C44 | D46: =D43-D44 | E46: =E43-E44 | F46: =F43-F44 | G46: =G43-G44
A48: F. BAND BY BAND — the seats we designed against the people we hold, offshore
B49: Year 1 | C49: E1 | D49: E2 | E49: E3 | F49: E4 | G49: E5 | H49: Total
B50: Seats the design asks for | C50: =SUMIFS('Seat Ledger'!$M$5:$M$235,'Seat Ledger'!$B$5:$B$235,1,'Seat Ledger'!$J$5:$J$235,"FTC",'Seat Ledger'!$I$5:$I$235,"OFF",'Seat Ledger'!$H$5:$H$235,"E1")+SUMIFS('Seat Ledger'!$M$5:$M$235,'Seat Ledger'!$B$5:$B$235,1,'Seat Ledger'!$J$5:$J$235,"FTC",'Seat Ledger'!$I$5:$I$235,"NEAR",'Seat Ledger'!$H$5:$H$235,"E1") | D50: =SUMIFS('Seat Ledger'!$M$5:$M$235,'Seat Ledger'!$B$5:$B$235,1,'Seat Ledger'!$J$5:$J$235,"FTC",'Seat Ledger'!$I$5:$I$235,"OFF",'Seat Ledger'!$H$5:$H$235,"E2")+SUMIFS('Seat Ledger'!$M$5:$M$235,'Seat Ledger'!$B$5:$B$235,1,'Seat Ledger'!$J$5:$J$235,"FTC",'Seat Ledger'!$I$5:$I$235,"NEAR",'Seat Ledger'!$H$5:$H$235,"E2") | E50: =SUMIFS('Seat Ledger'!$M$5:$M$235,'Seat Ledger'!$B$5:$B$235,1,'Seat Ledger'!$J$5:$J$235,"FTC",'Seat Ledger'!$I$5:$I$235,"OFF",'Seat Ledger'!$H$5:$H$235,"E3")+SUMIFS('Seat Ledger'!$M$5:$M$235,'Seat Ledger'!$B$5:$B$235,1,'Seat Ledger'!$J$5:$J$235,"FTC",'Seat Ledger'!$I$5:$I$235,"NEAR",'Seat Ledger'!$H$5:$H$235,"E3") | F50: =SUMIFS('Seat Ledger'!$M$5:$M$235,'Seat Ledger'!$B$5:$B$235,1,'Seat Ledger'!$J$5:$J$235,"FTC",'Seat Ledger'!$I$5:$I$235,"OFF",'Seat Ledger'!$H$5:$H$235,"E4")+SUMIFS('Seat Ledger'!$M$5:$M$235,'Seat Ledger'!$B$5:$B$235,1,'Seat Ledger'!$J$5:$J$235,"FTC",'Seat Ledger'!$I$5:$I$235,"NEAR",'Seat Ledger'!$H$5:$H$235,"E4") | G50: =SUMIFS('Seat Ledger'!$M$5:$M$235,'Seat Ledger'!$B$5:$B$235,1,'Seat Ledger'!$J$5:$J$235,"FTC",'Seat Ledger'!$I$5:$I$235,"OFF",'Seat Ledger'!$H$5:$H$235,"E5")+SUMIFS('Seat Ledger'!$M$5:$M$235,'Seat Ledger'!$B$5:$B$235,1,'Seat Ledger'!$J$5:$J$235,"FTC",'Seat Ledger'!$I$5:$I$235,"NEAR",'Seat Ledger'!$H$5:$H$235,"E5") | H50: =SUM(C50:G50)
B51: People we already have | C51: 2 | D51: 12 | E51: 15 | F51: 8 | G51: 0 | H51: =SUM(C51:G51)
B52: Gap — positive is a hire | C52: =C50-C51 | D52: =D50-D51 | E52: =E50-E51 | F52: =F50-F51 | G52: =G50-G51 | H52: =SUM(C52:G52)
B54: Year 2 | C54: E1 | D54: E2 | E54: E3 | F54: E4 | G54: E5 | H54: Total
B55: Seats the design asks for | C55: =SUMIFS('Seat Ledger'!$M$5:$M$235,'Seat Ledger'!$B$5:$B$235,2,'Seat Ledger'!$J$5:$J$235,"FTC",'Seat Ledger'!$I$5:$I$235,"OFF",'Seat Ledger'!$H$5:$H$235,"E1")+SUMIFS('Seat Ledger'!$M$5:$M$235,'Seat Ledger'!$B$5:$B$235,2,'Seat Ledger'!$J$5:$J$235,"FTC",'Seat Ledger'!$I$5:$I$235,"NEAR",'Seat Ledger'!$H$5:$H$235,"E1") | D55: =SUMIFS('Seat Ledger'!$M$5:$M$235,'Seat Ledger'!$B$5:$B$235,2,'Seat Ledger'!$J$5:$J$235,"FTC",'Seat Ledger'!$I$5:$I$235,"OFF",'Seat Ledger'!$H$5:$H$235,"E2")+SUMIFS('Seat Ledger'!$M$5:$M$235,'Seat Ledger'!$B$5:$B$235,2,'Seat Ledger'!$J$5:$J$235,"FTC",'Seat Ledger'!$I$5:$I$235,"NEAR",'Seat Ledger'!$H$5:$H$235,"E2") | E55: =SUMIFS('Seat Ledger'!$M$5:$M$235,'Seat Ledger'!$B$5:$B$235,2,'Seat Ledger'!$J$5:$J$235,"FTC",'Seat Ledger'!$I$5:$I$235,"OFF",'Seat Ledger'!$H$5:$H$235,"E3")+SUMIFS('Seat Ledger'!$M$5:$M$235,'Seat Ledger'!$B$5:$B$235,2,'Seat Ledger'!$J$5:$J$235,"FTC",'Seat Ledger'!$I$5:$I$235,"NEAR",'Seat Ledger'!$H$5:$H$235,"E3") | F55: =SUMIFS('Seat Ledger'!$M$5:$M$235,'Seat Ledger'!$B$5:$B$235,2,'Seat Ledger'!$J$5:$J$235,"FTC",'Seat Ledger'!$I$5:$I$235,"OFF",'Seat Ledger'!$H$5:$H$235,"E4")+SUMIFS('Seat Ledger'!$M$5:$M$235,'Seat Ledger'!$B$5:$B$235,2,'Seat Ledger'!$J$5:$J$235,"FTC",'Seat Ledger'!$I$5:$I$235,"NEAR",'Seat Ledger'!$H$5:$H$235,"E4") | G55: =SUMIFS('Seat Ledger'!$M$5:$M$235,'Seat Ledger'!$B$5:$B$235,2,'Seat Ledger'!$J$5:$J$235,"FTC",'Seat Ledger'!$I$5:$I$235,"OFF",'Seat Ledger'!$H$5:$H$235,"E5")+SUMIFS('Seat Ledger'!$M$5:$M$235,'Seat Ledger'!$B$5:$B$235,2,'Seat Ledger'!$J$5:$J$235,"FTC",'Seat Ledger'!$I$5:$I$235,"NEAR",'Seat Ledger'!$H$5:$H$235,"E5") | H55: =SUM(C55:G55)
B56: People we already have | C56: 1.248 | D56: 8.5776 | E56: 13.0584 | F56: 8.3364 | G56: 0.5096 | H56: =SUM(C56:G56)
B57: Gap — positive is a hire | C57: =C55-C56 | D57: =D55-D56 | E57: =E55-E56 | F57: =F55-F56 | G57: =G55-G56 | H57: =SUM(C57:G57)
B59: Year 3 | C59: E1 | D59: E2 | E59: E3 | F59: E4 | G59: E5 | H59: Total
B60: Seats the design asks for | C60: =SUMIFS('Seat Ledger'!$M$5:$M$235,'Seat Ledger'!$B$5:$B$235,3,'Seat Ledger'!$J$5:$J$235,"FTC",'Seat Ledger'!$I$5:$I$235,"OFF",'Seat Ledger'!$H$5:$H$235,"E1")+SUMIFS('Seat Ledger'!$M$5:$M$235,'Seat Ledger'!$B$5:$B$235,3,'Seat Ledger'!$J$5:$J$235,"FTC",'Seat Ledger'!$I$5:$I$235,"NEAR",'Seat Ledger'!$H$5:$H$235,"E1") | D60: =SUMIFS('Seat Ledger'!$M$5:$M$235,'Seat Ledger'!$B$5:$B$235,3,'Seat Ledger'!$J$5:$J$235,"FTC",'Seat Ledger'!$I$5:$I$235,"OFF",'Seat Ledger'!$H$5:$H$235,"E2")+SUMIFS('Seat Ledger'!$M$5:$M$235,'Seat Ledger'!$B$5:$B$235,3,'Seat Ledger'!$J$5:$J$235,"FTC",'Seat Ledger'!$I$5:$I$235,"NEAR",'Seat Ledger'!$H$5:$H$235,"E2") | E60: =SUMIFS('Seat Ledger'!$M$5:$M$235,'Seat Ledger'!$B$5:$B$235,3,'Seat Ledger'!$J$5:$J$235,"FTC",'Seat Ledger'!$I$5:$I$235,"OFF",'Seat Ledger'!$H$5:$H$235,"E3")+SUMIFS('Seat Ledger'!$M$5:$M$235,'Seat Ledger'!$B$5:$B$235,3,'Seat Ledger'!$J$5:$J$235,"FTC",'Seat Ledger'!$I$5:$I$235,"NEAR",'Seat Ledger'!$H$5:$H$235,"E3") | F60: =SUMIFS('Seat Ledger'!$M$5:$M$235,'Seat Ledger'!$B$5:$B$235,3,'Seat Ledger'!$J$5:$J$235,"FTC",'Seat Ledger'!$I$5:$I$235,"OFF",'Seat Ledger'!$H$5:$H$235,"E4")+SUMIFS('Seat Ledger'!$M$5:$M$235,'Seat Ledger'!$B$5:$B$235,3,'Seat Ledger'!$J$5:$J$235,"FTC",'Seat Ledger'!$I$5:$I$235,"NEAR",'Seat Ledger'!$H$5:$H$235,"E4") | G60: =SUMIFS('Seat Ledger'!$M$5:$M$235,'Seat Ledger'!$B$5:$B$235,3,'Seat Ledger'!$J$5:$J$235,"FTC",'Seat Ledger'!$I$5:$I$235,"OFF",'Seat Ledger'!$H$5:$H$235,"E5")+SUMIFS('Seat Ledger'!$M$5:$M$235,'Seat Ledger'!$B$5:$B$235,3,'Seat Ledger'!$J$5:$J$235,"FTC",'Seat Ledger'!$I$5:$I$235,"NEAR",'Seat Ledger'!$H$5:$H$235,"E5") | H60: =SUM(C60:G60)
B61: People we already have | C61: 0.778752 | D61: 6.1029389 | E61: 11.122892 | F61: 8.4183923 | G61: 1.0100527 | H61: =SUM(C61:G61)
B62: Gap — positive is a hire | C62: =C60-C61 | D62: =D60-D61 | E62: =E60-E61 | F62: =F60-F61 | G62: =G60-G61 | H62: =SUM(C62:G62)
B64: Year 4 | C64: E1 | D64: E2 | E64: E3 | F64: E4 | G64: E5 | H64: Total
B65: Seats the design asks for | C65: =SUMIFS('Seat Ledger'!$M$5:$M$235,'Seat Ledger'!$B$5:$B$235,4,'Seat Ledger'!$J$5:$J$235,"FTC",'Seat Ledger'!$I$5:$I$235,"OFF",'Seat Ledger'!$H$5:$H$235,"E1")+SUMIFS('Seat Ledger'!$M$5:$M$235,'Seat Ledger'!$B$5:$B$235,4,'Seat Ledger'!$J$5:$J$235,"FTC",'Seat Ledger'!$I$5:$I$235,"NEAR",'Seat Ledger'!$H$5:$H$235,"E1") | D65: =SUMIFS('Seat Ledger'!$M$5:$M$235,'Seat Ledger'!$B$5:$B$235,4,'Seat Ledger'!$J$5:$J$235,"FTC",'Seat Ledger'!$I$5:$I$235,"OFF",'Seat Ledger'!$H$5:$H$235,"E2")+SUMIFS('Seat Ledger'!$M$5:$M$235,'Seat Ledger'!$B$5:$B$235,4,'Seat Ledger'!$J$5:$J$235,"FTC",'Seat Ledger'!$I$5:$I$235,"NEAR",'Seat Ledger'!$H$5:$H$235,"E2") | E65: =SUMIFS('Seat Ledger'!$M$5:$M$235,'Seat Ledger'!$B$5:$B$235,4,'Seat Ledger'!$J$5:$J$235,"FTC",'Seat Ledger'!$I$5:$I$235,"OFF",'Seat Ledger'!$H$5:$H$235,"E3")+SUMIFS('Seat Ledger'!$M$5:$M$235,'Seat Ledger'!$B$5:$B$235,4,'Seat Ledger'!$J$5:$J$235,"FTC",'Seat Ledger'!$I$5:$I$235,"NEAR",'Seat Ledger'!$H$5:$H$235,"E3") | F65: =SUMIFS('Seat Ledger'!$M$5:$M$235,'Seat Ledger'!$B$5:$B$235,4,'Seat Ledger'!$J$5:$J$235,"FTC",'Seat Ledger'!$I$5:$I$235,"OFF",'Seat Ledger'!$H$5:$H$235,"E4")+SUMIFS('Seat Ledger'!$M$5:$M$235,'Seat Ledger'!$B$5:$B$235,4,'Seat Ledger'!$J$5:$J$235,"FTC",'Seat Ledger'!$I$5:$I$235,"NEAR",'Seat Ledger'!$H$5:$H$235,"E4") | G65: =SUMIFS('Seat Ledger'!$M$5:$M$235,'Seat Ledger'!$B$5:$B$235,4,'Seat Ledger'!$J$5:$J$235,"FTC",'Seat Ledger'!$I$5:$I$235,"OFF",'Seat Ledger'!$H$5:$H$235,"E5")+SUMIFS('Seat Ledger'!$M$5:$M$235,'Seat Ledger'!$B$5:$B$235,4,'Seat Ledger'!$J$5:$J$235,"FTC",'Seat Ledger'!$I$5:$I$235,"NEAR",'Seat Ledger'!$H$5:$H$235,"E5") | H65: =SUM(C65:G65)
B66: People we already have | C66: 0.48594125 | D66: 4.3251896 | E66: 9.3163918 | F66: 8.2857153 | G66: 1.4857011 | H66: =SUM(C66:G66)
B67: Gap — positive is a hire | C67: =C65-C66 | D67: =D65-D66 | E67: =E65-E66 | F67: =F65-F66 | G67: =G65-G66 | H67: =SUM(C67:G67)
B69: Year 5 | C69: E1 | D69: E2 | E69: E3 | F69: E4 | G69: E5 | H69: Total
B70: Seats the design asks for | C70: =SUMIFS('Seat Ledger'!$M$5:$M$235,'Seat Ledger'!$B$5:$B$235,5,'Seat Ledger'!$J$5:$J$235,"FTC",'Seat Ledger'!$I$5:$I$235,"OFF",'Seat Ledger'!$H$5:$H$235,"E1")+SUMIFS('Seat Ledger'!$M$5:$M$235,'Seat Ledger'!$B$5:$B$235,5,'Seat Ledger'!$J$5:$J$235,"FTC",'Seat Ledger'!$I$5:$I$235,"NEAR",'Seat Ledger'!$H$5:$H$235,"E1") | D70: =SUMIFS('Seat Ledger'!$M$5:$M$235,'Seat Ledger'!$B$5:$B$235,5,'Seat Ledger'!$J$5:$J$235,"FTC",'Seat Ledger'!$I$5:$I$235,"OFF",'Seat Ledger'!$H$5:$H$235,"E2")+SUMIFS('Seat Ledger'!$M$5:$M$235,'Seat Ledger'!$B$5:$B$235,5,'Seat Ledger'!$J$5:$J$235,"FTC",'Seat Ledger'!$I$5:$I$235,"NEAR",'Seat Ledger'!$H$5:$H$235,"E2") | E70: =SUMIFS('Seat Ledger'!$M$5:$M$235,'Seat Ledger'!$B$5:$B$235,5,'Seat Ledger'!$J$5:$J$235,"FTC",'Seat Ledger'!$I$5:$I$235,"OFF",'Seat Ledger'!$H$5:$H$235,"E3")+SUMIFS('Seat Ledger'!$M$5:$M$235,'Seat Ledger'!$B$5:$B$235,5,'Seat Ledger'!$J$5:$J$235,"FTC",'Seat Ledger'!$I$5:$I$235,"NEAR",'Seat Ledger'!$H$5:$H$235,"E3") | F70: =SUMIFS('Seat Ledger'!$M$5:$M$235,'Seat Ledger'!$B$5:$B$235,5,'Seat Ledger'!$J$5:$J$235,"FTC",'Seat Ledger'!$I$5:$I$235,"OFF",'Seat Ledger'!$H$5:$H$235,"E4")+SUMIFS('Seat Ledger'!$M$5:$M$235,'Seat Ledger'!$B$5:$B$235,5,'Seat Ledger'!$J$5:$J$235,"FTC",'Seat Ledger'!$I$5:$I$235,"NEAR",'Seat Ledger'!$H$5:$H$235,"E4") | G70: =SUMIFS('Seat Ledger'!$M$5:$M$235,'Seat Ledger'!$B$5:$B$235,5,'Seat Ledger'!$J$5:$J$235,"FTC",'Seat Ledger'!$I$5:$I$235,"OFF",'Seat Ledger'!$H$5:$H$235,"E5")+SUMIFS('Seat Ledger'!$M$5:$M$235,'Seat Ledger'!$B$5:$B$235,5,'Seat Ledger'!$J$5:$J$235,"FTC",'Seat Ledger'!$I$5:$I$235,"NEAR",'Seat Ledger'!$H$5:$H$235,"E5") | H70: =SUM(C70:G70)
B71: People we already have | C71: 0.30322734 | D71: 3.0549974 | E71: 7.7000945 | F71: 7.9848322 | G71: 1.9243591 | H71: =SUM(C71:G71)
B72: Gap — positive is a hire | C72: =C70-C71 | D72: =D70-D71 | E72: =E70-E71 | F72: =F70-F71 | G72: =G70-G71 | H72: =SUM(C72:G72)
B74: READ THE SIGN. The gap line is negative in every band in Year 1 — the design asks for 28.5 fewer Capgemini seats than the inherited cohort contains, because 37 of the 41 people sit offshore against a Year-1 offshore Capgemini demand of 8.5. By Year 5 the aggregate gap has closed to −2.5 and the shape has inverted: a surplus of 6.0 at E2 and 1.8 at E3 against a genuine shortfall of 8.0 at E4 and 1.9 at E5. The early-year problem is redeployment off this domain; the late-year problem is senior bilingual scarcity.
A76: G. WHAT THIS MEANS FOR THE SOLUTION
B77: • The continuity argument is strong and the capacity argument runs the other way. 37 of our 41 inherited people are offshore and 34.1 of the 41 sit on K2, against a Year-1 offshore Capgemini demand of 8.5 seats. Continuity on K2 is therefore free; the surplus has to be redeployed to other 領域 or released, and that plan belongs in the transition response, not here.
B78: • The talent-shape risk is at the top, not the bottom. The cohort is 26.8% senior on day one with no E5 at all, and seniorises by attrition and promotion to 52.4% by Year 5, while the design takes the roster the other way — 31.1% senior falling to 27.4%, with E1 seats present in every year so juniors have somewhere to land. The mismatch is a promotion-and-placement problem, and the architecture, lead and BSA seats are where the surviving seniors go.
B79: • FSI is 10.1% of vendor capacity and precisely located: K2 (EAI 12117), POS-IMS (13453), W13WEP-JPN (9947) and JP-RPASS (11604) — 7.000 units. Three of the four are waterfall and Japanese-specification; the fourth is K2 itself. The plan tapers them 7 → 7 → 6 → 5 → 4, and holds 2 seats (1 from Year 4) in the horizontal control cell so the partner relationship is governed rather than only consumed.
B80: • Four people in Japan against 60.5 onshore vendor units on day one — the worst continuity ratio in the portfolio. Eleven of fifteen applications run on Japanese specifications, so almost every Tokyo seat is a hire or a transfer. The design protects the three that matter most and holds them to Year 5: an onshore technical lead in every K2 team, an onshore bilingual analyst in both streams, and a Tokyo L2 support hand on the Japan-locked satellites.

Sheet Glidepath & 50-50
A1: Glidepath — capability, carry-forward, offshore, and one transfer at the end of Year 3
A2: Year 1 passes nothing through. The transfer is struck on the exit position at full realisation.
A4: A. BASELINE
B5: Measure | C5: Value
B6: Applications | C6: ='Logic Tree'!C6
B7: Total effort (units) | C7: ='Logic Tree'!C7
B8: Capgemini FTC | C8: ='Logic Tree'!C8 | D8: CG + Others | E8: 41 + 28.427
B9: MetLife FTE | C9: ='Logic Tree'!C9
B10: MetLife MGCC | C10: ='Logic Tree'!C10
B11: Ratio today — Capgemini share | C11: ='Logic Tree'!C23
B12: Offshore today — whole team, measured | C12: ='Logic Tree'!C24 | I12: 45.5% offshore on day one — 28.87 offshore, 0.96 nearshore and 15.99 MGCC against 100.765 units. The easiest starting point in the portfolio, and the reason the 81.5% ceiling is credible.
B13: Appendix 3 Year-3 target, each side | C13: ='Logic Tree'!C22
A15: B. PRODUCTIVITY
B16: Measure | C16: Year 1 | D16: Year 2 | E16: Year 3 | F16: Year 4 | G16: Year 5
B17: Agile share of the domain | C17: ='Delivery Mode'!C18 | D17: ='Delivery Mode'!D18 | E17: ='Delivery Mode'!E18 | F17: ='Delivery Mode'!F18 | G17: ='Delivery Mode'!G18
B18: Capability earned by end of year | C18: ='Logic Tree'!C45 | D18: ='Logic Tree'!D45 | E18: ='Logic Tree'!E45 | F18: ='Logic Tree'!F45 | G18: ='Logic Tree'!G45
B19: Banked from prior year | C19: ='Logic Tree'!C50 | D19: ='Logic Tree'!D50 | E19: ='Logic Tree'!E50 | F19: ='Logic Tree'!F50 | G19: ='Logic Tree'!G50
B20: Pre-load of this year's gain | C20: ='Logic Tree'!C51 | D20: ='Logic Tree'!D51 | E20: ='Logic Tree'!E51 | F20: ='Logic Tree'!F51 | G20: ='Logic Tree'!G51
B21: APPLIED TO STAFFING | C21: ='Logic Tree'!C52 | D21: ='Logic Tree'!D52 | E21: ='Logic Tree'!E52 | F21: ='Logic Tree'!F52 | G21: ='Logic Tree'!G52 | I21: Year 1 applies nothing: the capability the tree allows is consumed by transition, substrate build and the agile conversion itself.
B22: Headcount target | C22: ='Logic Tree'!C53 | D22: ='Logic Tree'!D53 | E22: ='Logic Tree'!E53 | F22: ='Logic Tree'!F53 | G22: ='Logic Tree'!G53
B23: Headcount delivered by the design | C23: ='Team Build-Up'!C9 | D23: ='Team Build-Up'!D9 | E23: ='Team Build-Up'!E9 | F23: ='Team Build-Up'!F9 | G23: ='Team Build-Up'!G9
B24: Variance | C24: ='Team Build-Up'!C12 | D24: ='Team Build-Up'!D12 | E24: ='Team Build-Up'!E12 | F24: ='Team Build-Up'!F12 | G24: ='Team Build-Up'!G12
B25: Delivered productivity vs baseline | C25: =1-C23/$C$7 | D25: =1-D23/$C$7 | E25: =1-E23/$C$7 | F25: =1-F23/$C$7 | G25: =1-G23/$C$7
B26: EXIT YEAR 3 — full realisation, the point the transfer is struck | E26: ='Logic Tree'!E54
A28: C. OFFSHORE
B29: Measure | C29: Year 1 | D29: Year 2 | E29: Year 3 | F29: Year 4 | G29: Year 5
B30: Delivered — bottom-up from seat locations | C30: ='Team Build-Up'!C54 | D30: ='Team Build-Up'!D54 | E30: ='Team Build-Up'!E54 | F30: ='Team Build-Up'!F54 | G30: ='Team Build-Up'!G54
B31: Target — today plus the closed gap | C31: ='Logic Tree'!C68 | D31: ='Logic Tree'!D68 | E31: ='Logic Tree'!E68 | F31: ='Logic Tree'!F68 | G31: ='Logic Tree'!G68
B32: Delivered — Capgemini payroll only | C32: ='Team Build-Up'!C56 | D32: ='Team Build-Up'!D56 | E32: ='Team Build-Up'!E56 | F32: ='Team Build-Up'!F56 | G32: ='Team Build-Up'!G56
B33: Movement from today, in people | C33: =C30*'Team Build-Up'!C9-$C$12*$C$7 | D33: =D30*'Team Build-Up'!D9-$C$12*$C$7 | E33: =E30*'Team Build-Up'!E9-$C$12*$C$7 | F33: =F30*'Team Build-Up'!F9-$C$12*$C$7 | G33: =G30*'Team Build-Up'!G9-$C$12*$C$7 | I33: The offshore SHARE rises every year while the offshore HEADCOUNT falls from Year 2. Both are true and only the second one costs anything.
A35: D. THE 50:50
B36: Measure | C36: Year 1 | D36: Year 2 | E36: Year 3 | F36: Year 4 | G36: Year 5
B37: Total people | C37: ='Team Build-Up'!C9 | D37: ='Team Build-Up'!D9 | E37: ='Team Build-Up'!E9 | F37: ='Team Build-Up'!F9 | G37: ='Team Build-Up'!G9
B38: Vendor total (Capgemini + partner) | C38: ='Team Build-Up'!C47 | D38: ='Team Build-Up'!D47 | E38: ='Team Build-Up'!E47 | F38: ='Team Build-Up'!F47 | G38: ='Team Build-Up'!G47
B39: — Capgemini payroll | C39: ='Team Build-Up'!C45 | D39: ='Team Build-Up'!D45 | E39: ='Team Build-Up'!E45 | F39: ='Team Build-Up'!F45 | G39: ='Team Build-Up'!G45
B40: — FSI (four-application service cell) | C40: ='Team Build-Up'!C46 | D40: ='Team Build-Up'!D46 | E40: ='Team Build-Up'!E46 | F40: ='Team Build-Up'!F46 | G40: ='Team Build-Up'!G46
B41: MetLife FTE | C41: ='Team Build-Up'!C48 | D41: ='Team Build-Up'!D48 | E41: ='Team Build-Up'!E48 | F41: ='Team Build-Up'!F48 | G41: ='Team Build-Up'!G48
B42: MetLife MGCC | C42: ='Team Build-Up'!C49 | D42: ='Team Build-Up'!D49 | E42: ='Team Build-Up'!E49 | F42: ='Team Build-Up'!F49 | G42: ='Team Build-Up'!G49
B43: MetLife side total | C43: =C41+C42 | D43: =D41+D42 | E43: =E41+E42 | F43: =F41+F42 | G43: =G41+G42
B44: Transferred this year | C44: ='Logic Tree'!C75+'Logic Tree'!C76 | D44: ='Logic Tree'!D75+'Logic Tree'!D76 | E44: ='Logic Tree'!E75+'Logic Tree'!E76 | F44: ='Logic Tree'!F75+'Logic Tree'!F76 | G44: ='Logic Tree'!G75+'Logic Tree'!G76
B45: RATIO — Capgemini share | C45: =IF(C37=0,0,C38/C37) | D45: =IF(D37=0,0,D38/D37) | E45: =IF(E37=0,0,E38/E37) | F45: =IF(F37=0,0,F38/F37) | G45: =IF(G37=0,0,G38/G37)
I46: Years 1-3 are the pre-transfer position. Year 4 and Year 5 already carry the transferred seats as MetLife, inside the pods.
A48: E. THE TRANSFER SOLVE — Capgemini payroll only, and here it closes
C49: Value
B50: Exit Year 3 headcount, full realisation | C50: =E26 | I50: 6.2 people: 2.2 from Capgemini Japan to MetLife Japan and 4.0 from Capgemini India to MGCC. The pool is 31.1 against a vendor side of 37.5, because FSI holds 6.4 by then and cannot move.
B51: Vendor share at the exit position | C51: =E45
B52: Vendor units at exit, before transfer | C52: =C50*C51
B53: — of which FSI, IMMOVABLE | C53: =E40/E37*C50
B54: — of which Capgemini payroll, the transfer pool | C54: =C52-C53
B55: 50:50 requires each side to be | C55: =C50/2
B56: TRANSFER REQUIRED | C56: =C52-C55 | I56: 6.2 required against 21.8 available at the 70% cap. Organic convergence has already taken the ratio from 65.4% to 59.9% before anyone changes employer, so the transfer is 20% of the pool, not 70%.
B57: Cap on the transferable pool — solution constraint | C57: =0.7
B58: Maximum transferable from Capgemini payroll | C58: =C54*C57
B59: Transfer applied in the model | C59: ='Logic Tree'!E77
B60: Transfer as a share of the Capgemini pool | C60: =C59/C54
B61: RESIDUAL GAP TO 50:50 | C61: =C56-C59 | I61: The exit lands at 50.0%. Years 4 and 5 hold at 50.0% because the transferred seats sit inside the pod anatomy rather than being re-solved each year.
B62: Ratio actually reached at the Year-3 exit | C62: =(C52-C59)/C50
A65: F. WHAT THIS DOMAIN SHOWS
B66: • THE 50:50 CLOSES, AND IT CLOSES MOSTLY WITHOUT A TRANSFER. Capgemini holds 65.1% of this 領域 on day one. Differential shrinkage — FTC absorbing more of the reduction than FTE or MGCC — takes that to 55.2% by the end of Year 3 on its own. Only 3.5 people then have to move: 1.5 to MetLife Japan and 2.0 to MGCC, 11% of the transferable Capgemini pool against a 70% cap. The ratio lands at 49.99%.
B67: • The productivity case is deliberately the most conservative in the portfolio. AI ceiling 41.69% blended, capability 12.1 / 27.3 / 36.4 / 42.4 / 46.8%, applied glidepath 0 / 19.7 / 31.9 / 39.4 / 44.6%. Headcount goes 106.1 → 58.5. Two things hold it down and both are real: K2 is 59% of the domain and its business rules live in Japanese-language specifications, so AI realisation is capped at 86% rather than 90%; and the fourteen satellites never convert to agile, so the operating-model gain is only ever available on 59.05% of the estate.
B68: • The offshore case closes in full. 16.94% is delivered offshore or by MGCC today against a blended ceiling of 54.73%, and the design reaches 54.70% in Year 5: 18.4 / 30.0 / 39.3 / 47.3 / 54.7%. The last 2.6 points come from halving the K2 bilingual analyst to 0.5 per team in Year 5 — one analyst across two teams — while the onshore technical lead, the Tokyo L2 support hand and design authority all stay. J applications carry a 12% offshore ceiling, so nothing above this line is available without moving Japanese-specification work out of Japan.
B69: • The adoption factors are left at the portfolio defaults: 1.00 Capgemini, 0.85 FSI, 0.80 MGCC, 0.55 MetLife Japan. Unlike Common Service Platform, there is no case for asking MetLife to carry more of the commitment on a largely waterfall, Japanese-language estate where their own people are in governance rather than build roles.
B70: • Three things to challenge. First, MetLife's own maintenance line: 3.48 units of run against 1,145 incidents and 2,071 changes a year. Second, whether Payment & Records ever converts to agile — holding it waterfall to Year 5 costs about 4 points of Year-5 capability and is the single assumption most worth arguing. Third, the Year-4 horizontal step: the layer rises from 12.5 to 16.5 as the last satellite team retires into AMS, and whether that residual work is really 4 people is a transition-planning question, not a modelling one.

Sheet Cost & Commercial
A1: Cost and commercial position — relative index pending the rate card
A2: Onshore Tokyo E2 = 1.00. Unit cost divides by the frozen baseline effort.
A4: A. TOTAL COST OF DELIVERING THE DOMAIN
B5: Measure | C5: Year 1 | D5: Year 2 | E5: Year 3 | F5: Year 4 | G5: Year 5
B6: Total cost index | C6: =SUMIFS('Seat Ledger'!$N$5:$N$235,'Seat Ledger'!$B$5:$B$235,1) | D6: =SUMIFS('Seat Ledger'!$N$5:$N$235,'Seat Ledger'!$B$5:$B$235,2) | E6: =SUMIFS('Seat Ledger'!$N$5:$N$235,'Seat Ledger'!$B$5:$B$235,3) | F6: =SUMIFS('Seat Ledger'!$N$5:$N$235,'Seat Ledger'!$B$5:$B$235,4) | G6: =SUMIFS('Seat Ledger'!$N$5:$N$235,'Seat Ledger'!$B$5:$B$235,5)
B7: Headcount | C7: ='Team Build-Up'!C9 | D7: ='Team Build-Up'!D9 | E7: ='Team Build-Up'!E9 | F7: ='Team Build-Up'!F9 | G7: ='Team Build-Up'!G9
B8: Average cost per head | C8: =IF(C7=0,0,C6/C7) | D8: =IF(D7=0,0,D6/D7) | E8: =IF(E7=0,0,E6/E7) | F8: =IF(F7=0,0,F6/F7) | G8: =IF(G7=0,0,G6/G7)
B9: Cost per unit of frozen scope | C9: =IF('Glidepath & 50-50'!$C$7=0,0,C6/'Glidepath & 50-50'!$C$7) | D9: =IF('Glidepath & 50-50'!$C$7=0,0,D6/'Glidepath & 50-50'!$C$7) | E9: =IF('Glidepath & 50-50'!$C$7=0,0,E6/'Glidepath & 50-50'!$C$7) | F9: =IF('Glidepath & 50-50'!$C$7=0,0,F6/'Glidepath & 50-50'!$C$7) | G9: =IF('Glidepath & 50-50'!$C$7=0,0,G6/'Glidepath & 50-50'!$C$7)
B10: Unit cost reduction vs Year 1 | C10: =IF($C$9=0,0,1-C9/$C$9) | D10: =IF($C$9=0,0,1-D9/$C$9) | E10: =IF($C$9=0,0,1-E9/$C$9) | F10: =IF($C$9=0,0,1-F9/$C$9) | G10: =IF($C$9=0,0,1-G9/$C$9)
A12: B. CAPGEMINI POSITION
B13: Measure | C13: Year 1 | D13: Year 2 | E13: Year 3 | F13: Year 4 | G13: Year 5
B14: Capgemini heads | C14: ='Team Build-Up'!C45 | D14: ='Team Build-Up'!D45 | E14: ='Team Build-Up'!E45 | F14: ='Team Build-Up'!F45 | G14: ='Team Build-Up'!G45
B15: Capgemini cost index | C15: =SUMIFS('Seat Ledger'!$N$5:$N$235,'Seat Ledger'!$B$5:$B$235,1,'Seat Ledger'!$J$5:$J$235,"FTC") | D15: =SUMIFS('Seat Ledger'!$N$5:$N$235,'Seat Ledger'!$B$5:$B$235,2,'Seat Ledger'!$J$5:$J$235,"FTC") | E15: =SUMIFS('Seat Ledger'!$N$5:$N$235,'Seat Ledger'!$B$5:$B$235,3,'Seat Ledger'!$J$5:$J$235,"FTC") | F15: =SUMIFS('Seat Ledger'!$N$5:$N$235,'Seat Ledger'!$B$5:$B$235,4,'Seat Ledger'!$J$5:$J$235,"FTC") | G15: =SUMIFS('Seat Ledger'!$N$5:$N$235,'Seat Ledger'!$B$5:$B$235,5,'Seat Ledger'!$J$5:$J$235,"FTC")
B16: Capgemini position vs Year 1 | C16: =IF($C$15=0,0,C15/$C$15-1) | D16: =IF($C$15=0,0,D15/$C$15-1) | E16: =IF($C$15=0,0,E15/$C$15-1) | F16: =IF($C$15=0,0,F15/$C$15-1) | G16: =IF($C$15=0,0,G15/$C$15-1)
A18: C. COST BY LOCATION, BAND AND ROLE
B19: Split | C19: Year 1 | D19: Year 2 | E19: Year 3 | F19: Year 4 | G19: Year 5
B20: Onshore Tokyo — cost index | C20: =SUMIFS('Seat Ledger'!$N$5:$N$235,'Seat Ledger'!$B$5:$B$235,1,'Seat Ledger'!$I$5:$I$235,"ON") | D20: =SUMIFS('Seat Ledger'!$N$5:$N$235,'Seat Ledger'!$B$5:$B$235,2,'Seat Ledger'!$I$5:$I$235,"ON") | E20: =SUMIFS('Seat Ledger'!$N$5:$N$235,'Seat Ledger'!$B$5:$B$235,3,'Seat Ledger'!$I$5:$I$235,"ON") | F20: =SUMIFS('Seat Ledger'!$N$5:$N$235,'Seat Ledger'!$B$5:$B$235,4,'Seat Ledger'!$I$5:$I$235,"ON") | G20: =SUMIFS('Seat Ledger'!$N$5:$N$235,'Seat Ledger'!$B$5:$B$235,5,'Seat Ledger'!$I$5:$I$235,"ON")
B21: Offshore — cost index | C21: =SUMIFS('Seat Ledger'!$N$5:$N$235,'Seat Ledger'!$B$5:$B$235,1,'Seat Ledger'!$I$5:$I$235,"OFF") | D21: =SUMIFS('Seat Ledger'!$N$5:$N$235,'Seat Ledger'!$B$5:$B$235,2,'Seat Ledger'!$I$5:$I$235,"OFF") | E21: =SUMIFS('Seat Ledger'!$N$5:$N$235,'Seat Ledger'!$B$5:$B$235,3,'Seat Ledger'!$I$5:$I$235,"OFF") | F21: =SUMIFS('Seat Ledger'!$N$5:$N$235,'Seat Ledger'!$B$5:$B$235,4,'Seat Ledger'!$I$5:$I$235,"OFF") | G21: =SUMIFS('Seat Ledger'!$N$5:$N$235,'Seat Ledger'!$B$5:$B$235,5,'Seat Ledger'!$I$5:$I$235,"OFF")
B22: Nearshore — cost index | C22: =SUMIFS('Seat Ledger'!$N$5:$N$235,'Seat Ledger'!$B$5:$B$235,1,'Seat Ledger'!$I$5:$I$235,"NEAR") | D22: =SUMIFS('Seat Ledger'!$N$5:$N$235,'Seat Ledger'!$B$5:$B$235,2,'Seat Ledger'!$I$5:$I$235,"NEAR") | E22: =SUMIFS('Seat Ledger'!$N$5:$N$235,'Seat Ledger'!$B$5:$B$235,3,'Seat Ledger'!$I$5:$I$235,"NEAR") | F22: =SUMIFS('Seat Ledger'!$N$5:$N$235,'Seat Ledger'!$B$5:$B$235,4,'Seat Ledger'!$I$5:$I$235,"NEAR") | G22: =SUMIFS('Seat Ledger'!$N$5:$N$235,'Seat Ledger'!$B$5:$B$235,5,'Seat Ledger'!$I$5:$I$235,"NEAR")
B23: Onshore share of cost | C23: =IF(SUM(C20:C22)=0,0,C20/SUM(C20:C22)) | D23: =IF(SUM(D20:D22)=0,0,D20/SUM(D20:D22)) | E23: =IF(SUM(E20:E22)=0,0,E20/SUM(E20:E22)) | F23: =IF(SUM(F20:F22)=0,0,F20/SUM(F20:F22)) | G23: =IF(SUM(G20:G22)=0,0,G20/SUM(G20:G22))
B25: BSA — business and systems analysis — cost index | C25: =SUMIFS('Seat Ledger'!$N$5:$N$235,'Seat Ledger'!$B$5:$B$235,1,'Seat Ledger'!$G$5:$G$235,"BSA") | D25: =SUMIFS('Seat Ledger'!$N$5:$N$235,'Seat Ledger'!$B$5:$B$235,2,'Seat Ledger'!$G$5:$G$235,"BSA") | E25: =SUMIFS('Seat Ledger'!$N$5:$N$235,'Seat Ledger'!$B$5:$B$235,3,'Seat Ledger'!$G$5:$G$235,"BSA") | F25: =SUMIFS('Seat Ledger'!$N$5:$N$235,'Seat Ledger'!$B$5:$B$235,4,'Seat Ledger'!$G$5:$G$235,"BSA") | G25: =SUMIFS('Seat Ledger'!$N$5:$N$235,'Seat Ledger'!$B$5:$B$235,5,'Seat Ledger'!$G$5:$G$235,"BSA")
B26: Developer — cost index | C26: =SUMIFS('Seat Ledger'!$N$5:$N$235,'Seat Ledger'!$B$5:$B$235,1,'Seat Ledger'!$G$5:$G$235,"DEV") | D26: =SUMIFS('Seat Ledger'!$N$5:$N$235,'Seat Ledger'!$B$5:$B$235,2,'Seat Ledger'!$G$5:$G$235,"DEV") | E26: =SUMIFS('Seat Ledger'!$N$5:$N$235,'Seat Ledger'!$B$5:$B$235,3,'Seat Ledger'!$G$5:$G$235,"DEV") | F26: =SUMIFS('Seat Ledger'!$N$5:$N$235,'Seat Ledger'!$B$5:$B$235,4,'Seat Ledger'!$G$5:$G$235,"DEV") | G26: =SUMIFS('Seat Ledger'!$N$5:$N$235,'Seat Ledger'!$B$5:$B$235,5,'Seat Ledger'!$G$5:$G$235,"DEV")
B27: Tester — cost index | C27: =SUMIFS('Seat Ledger'!$N$5:$N$235,'Seat Ledger'!$B$5:$B$235,1,'Seat Ledger'!$G$5:$G$235,"TEST") | D27: =SUMIFS('Seat Ledger'!$N$5:$N$235,'Seat Ledger'!$B$5:$B$235,2,'Seat Ledger'!$G$5:$G$235,"TEST") | E27: =SUMIFS('Seat Ledger'!$N$5:$N$235,'Seat Ledger'!$B$5:$B$235,3,'Seat Ledger'!$G$5:$G$235,"TEST") | F27: =SUMIFS('Seat Ledger'!$N$5:$N$235,'Seat Ledger'!$B$5:$B$235,4,'Seat Ledger'!$G$5:$G$235,"TEST") | G27: =SUMIFS('Seat Ledger'!$N$5:$N$235,'Seat Ledger'!$B$5:$B$235,5,'Seat Ledger'!$G$5:$G$235,"TEST")
B28: Maintenance — cost index | C28: =SUMIFS('Seat Ledger'!$N$5:$N$235,'Seat Ledger'!$B$5:$B$235,1,'Seat Ledger'!$G$5:$G$235,"MNT") | D28: =SUMIFS('Seat Ledger'!$N$5:$N$235,'Seat Ledger'!$B$5:$B$235,2,'Seat Ledger'!$G$5:$G$235,"MNT") | E28: =SUMIFS('Seat Ledger'!$N$5:$N$235,'Seat Ledger'!$B$5:$B$235,3,'Seat Ledger'!$G$5:$G$235,"MNT") | F28: =SUMIFS('Seat Ledger'!$N$5:$N$235,'Seat Ledger'!$B$5:$B$235,4,'Seat Ledger'!$G$5:$G$235,"MNT") | G28: =SUMIFS('Seat Ledger'!$N$5:$N$235,'Seat Ledger'!$B$5:$B$235,5,'Seat Ledger'!$G$5:$G$235,"MNT")
B29: PM and product ownership — cost index | C29: =SUMIFS('Seat Ledger'!$N$5:$N$235,'Seat Ledger'!$B$5:$B$235,1,'Seat Ledger'!$G$5:$G$235,"PM") | D29: =SUMIFS('Seat Ledger'!$N$5:$N$235,'Seat Ledger'!$B$5:$B$235,2,'Seat Ledger'!$G$5:$G$235,"PM") | E29: =SUMIFS('Seat Ledger'!$N$5:$N$235,'Seat Ledger'!$B$5:$B$235,3,'Seat Ledger'!$G$5:$G$235,"PM") | F29: =SUMIFS('Seat Ledger'!$N$5:$N$235,'Seat Ledger'!$B$5:$B$235,4,'Seat Ledger'!$G$5:$G$235,"PM") | G29: =SUMIFS('Seat Ledger'!$N$5:$N$235,'Seat Ledger'!$B$5:$B$235,5,'Seat Ledger'!$G$5:$G$235,"PM")
B30: Other — architecture and enablement — cost index | C30: =SUMIFS('Seat Ledger'!$N$5:$N$235,'Seat Ledger'!$B$5:$B$235,1,'Seat Ledger'!$G$5:$G$235,"OTH") | D30: =SUMIFS('Seat Ledger'!$N$5:$N$235,'Seat Ledger'!$B$5:$B$235,2,'Seat Ledger'!$G$5:$G$235,"OTH") | E30: =SUMIFS('Seat Ledger'!$N$5:$N$235,'Seat Ledger'!$B$5:$B$235,3,'Seat Ledger'!$G$5:$G$235,"OTH") | F30: =SUMIFS('Seat Ledger'!$N$5:$N$235,'Seat Ledger'!$B$5:$B$235,4,'Seat Ledger'!$G$5:$G$235,"OTH") | G30: =SUMIFS('Seat Ledger'!$N$5:$N$235,'Seat Ledger'!$B$5:$B$235,5,'Seat Ledger'!$G$5:$G$235,"OTH")
B32: The role view is the one Pricing will want: it says what each role costs, not just what it does. Unit cost falls 59.2% from Year 1 to Year 5 — 1.294 to 0.528 on the frozen scope — and average cost per head falls 26%, from 1.295 to 0.958, as the roster moves offshore and the senior share comes down.

Sheet Seat Ledger
A1: Seat ledger — every pod-library line multiplied out, plus every horizontal seat
A2: Computed. Every roll-up in this workbook is a SUMIFS over this one table. Do not edit.
B4: Year | C4: Origin | D4: Unit | E4: Type | F4: Role detail | G4: Role | H4: Exp | I4: Loc | J4: Sourcing | K4: Seats/unit | L4: Units | M4: Heads | N4: Cost index
B5: 1 | C5: TEAM | D5: POSW | E5: TEAM | F5: ='Pod Library'!E5 | G5: ='Pod Library'!F5 | H5: ='Pod Library'!G5 | I5: ='Pod Library'!H5 | J5: ='Pod Library'!I5 | K5: ='Pod Library'!J5 | L5: ='Pod Plan'!F5 | M5: =K5*L5 | N5: =M5*INDEX('Logic Tree'!$J$85:$N$87,MATCH(I5,'Logic Tree'!$I$85:$I$87,0),MATCH(H5,'Logic Tree'!$J$84:$N$84,0))
B6: 1 | C6: TEAM | D6: POSW | E6: TEAM | F6: ='Pod Library'!E6 | G6: ='Pod Library'!F6 | H6: ='Pod Library'!G6 | I6: ='Pod Library'!H6 | J6: ='Pod Library'!I6 | K6: ='Pod Library'!J6 | L6: ='Pod Plan'!F5 | M6: =K6*L6 | N6: =M6*INDEX('Logic Tree'!$J$85:$N$87,MATCH(I6,'Logic Tree'!$I$85:$I$87,0),MATCH(H6,'Logic Tree'!$J$84:$N$84,0))
B7: 1 | C7: TEAM | D7: POSW | E7: TEAM | F7: ='Pod Library'!E7 | G7: ='Pod Library'!F7 | H7: ='Pod Library'!G7 | I7: ='Pod Library'!H7 | J7: ='Pod Library'!I7 | K7: ='Pod Library'!J7 | L7: ='Pod Plan'!F5 | M7: =K7*L7 | N7: =M7*INDEX('Logic Tree'!$J$85:$N$87,MATCH(I7,'Logic Tree'!$I$85:$I$87,0),MATCH(H7,'Logic Tree'!$J$84:$N$84,0))
B8: 1 | C8: TEAM | D8: POSW | E8: TEAM | F8: ='Pod Library'!E8 | G8: ='Pod Library'!F8 | H8: ='Pod Library'!G8 | I8: ='Pod Library'!H8 | J8: ='Pod Library'!I8 | K8: ='Pod Library'!J8 | L8: ='Pod Plan'!F5 | M8: =K8*L8 | N8: =M8*INDEX('Logic Tree'!$J$85:$N$87,MATCH(I8,'Logic Tree'!$I$85:$I$87,0),MATCH(H8,'Logic Tree'!$J$84:$N$84,0))
B9: 1 | C9: TEAM | D9: POSW | E9: TEAM | F9: ='Pod Library'!E9 | G9: ='Pod Library'!F9 | H9: ='Pod Library'!G9 | I9: ='Pod Library'!H9 | J9: ='Pod Library'!I9 | K9: ='Pod Library'!J9 | L9: ='Pod Plan'!F5 | M9: =K9*L9 | N9: =M9*INDEX('Logic Tree'!$J$85:$N$87,MATCH(I9,'Logic Tree'!$I$85:$I$87,0),MATCH(H9,'Logic Tree'!$J$84:$N$84,0))
B10: 1 | C10: TEAM | D10: POSW | E10: TEAM | F10: ='Pod Library'!E10 | G10: ='Pod Library'!F10 | H10: ='Pod Library'!G10 | I10: ='Pod Library'!H10 | J10: ='Pod Library'!I10 | K10: ='Pod Library'!J10 | L10: ='Pod Plan'!F5 | M10: =K10*L10 | N10: =M10*INDEX('Logic Tree'!$J$85:$N$87,MATCH(I10,'Logic Tree'!$I$85:$I$87,0),MATCH(H10,'Logic Tree'!$J$84:$N$84,0))
B11: 1 | C11: TEAM | D11: POSW | E11: TEAM | F11: ='Pod Library'!E11 | G11: ='Pod Library'!F11 | H11: ='Pod Library'!G11 | I11: ='Pod Library'!H11 | J11: ='Pod Library'!I11 | K11: ='Pod Library'!J11 | L11: ='Pod Plan'!F5 | M11: =K11*L11 | N11: =M11*INDEX('Logic Tree'!$J$85:$N$87,MATCH(I11,'Logic Tree'!$I$85:$I$87,0),MATCH(H11,'Logic Tree'!$J$84:$N$84,0))
B12: 1 | C12: TEAM | D12: POSW | E12: TEAM | F12: ='Pod Library'!E12 | G12: ='Pod Library'!F12 | H12: ='Pod Library'!G12 | I12: ='Pod Library'!H12 | J12: ='Pod Library'!I12 | K12: ='Pod Library'!J12 | L12: ='Pod Plan'!F5 | M12: =K12*L12 | N12: =M12*INDEX('Logic Tree'!$J$85:$N$87,MATCH(I12,'Logic Tree'!$I$85:$I$87,0),MATCH(H12,'Logic Tree'!$J$84:$N$84,0))
B13: 1 | C13: TEAM | D13: POSW | E13: TEAM | F13: ='Pod Library'!E13 | G13: ='Pod Library'!F13 | H13: ='Pod Library'!G13 | I13: ='Pod Library'!H13 | J13: ='Pod Library'!I13 | K13: ='Pod Library'!J13 | L13: ='Pod Plan'!F5 | M13: =K13*L13 | N13: =M13*INDEX('Logic Tree'!$J$85:$N$87,MATCH(I13,'Logic Tree'!$I$85:$I$87,0),MATCH(H13,'Logic Tree'!$J$84:$N$84,0))
B14: 1 | C14: TEAM | D14: POSW | E14: TEAM | F14: ='Pod Library'!E14 | G14: ='Pod Library'!F14 | H14: ='Pod Library'!G14 | I14: ='Pod Library'!H14 | J14: ='Pod Library'!I14 | K14: ='Pod Library'!J14 | L14: ='Pod Plan'!F5 | M14: =K14*L14 | N14: =M14*INDEX('Logic Tree'!$J$85:$N$87,MATCH(I14,'Logic Tree'!$I$85:$I$87,0),MATCH(H14,'Logic Tree'!$J$84:$N$84,0))
B15: 1 | C15: TEAM | D15: POSW | E15: TEAM | F15: ='Pod Library'!E15 | G15: ='Pod Library'!F15 | H15: ='Pod Library'!G15 | I15: ='Pod Library'!H15 | J15: ='Pod Library'!I15 | K15: ='Pod Library'!J15 | L15: ='Pod Plan'!F5 | M15: =K15*L15 | N15: =M15*INDEX('Logic Tree'!$J$85:$N$87,MATCH(I15,'Logic Tree'!$I$85:$I$87,0),MATCH(H15,'Logic Tree'!$J$84:$N$84,0))
B16: 1 | C16: TEAM | D16: POSW | E16: TEAM | F16: ='Pod Library'!E16 | G16: ='Pod Library'!F16 | H16: ='Pod Library'!G16 | I16: ='Pod Library'!H16 | J16: ='Pod Library'!I16 | K16: ='Pod Library'!J16 | L16: ='Pod Plan'!F5 | M16: =K16*L16 | N16: =M16*INDEX('Logic Tree'!$J$85:$N$87,MATCH(I16,'Logic Tree'!$I$85:$I$87,0),MATCH(H16,'Logic Tree'!$J$84:$N$84,0))
B17: 1 | C17: TEAM | D17: POSW | E17: TEAM | F17: ='Pod Library'!E17 | G17: ='Pod Library'!F17 | H17: ='Pod Library'!G17 | I17: ='Pod Library'!H17 | J17: ='Pod Library'!I17 | K17: ='Pod Library'!J17 | L17: ='Pod Plan'!F5 | M17: =K17*L17 | N17: =M17*INDEX('Logic Tree'!$J$85:$N$87,MATCH(I17,'Logic Tree'!$I$85:$I$87,0),MATCH(H17,'Logic Tree'!$J$84:$N$84,0))
B18: 1 | C18: TEAM | D18: POSW | E18: TEAM | F18: ='Pod Library'!E18 | G18: ='Pod Library'!F18 | H18: ='Pod Library'!G18 | I18: ='Pod Library'!H18 | J18: ='Pod Library'!I18 | K18: ='Pod Library'!J18 | L18: ='Pod Plan'!F5 | M18: =K18*L18 | N18: =M18*INDEX('Logic Tree'!$J$85:$N$87,MATCH(I18,'Logic Tree'!$I$85:$I$87,0),MATCH(H18,'Logic Tree'!$J$84:$N$84,0))
B19: 1 | C19: TEAM | D19: POSR | E19: TEAM | F19: ='Pod Library'!E21 | G19: ='Pod Library'!F21 | H19: ='Pod Library'!G21 | I19: ='Pod Library'!H21 | J19: ='Pod Library'!I21 | K19: ='Pod Library'!J21 | L19: ='Pod Plan'!F6 | M19: =K19*L19 | N19: =M19*INDEX('Logic Tree'!$J$85:$N$87,MATCH(I19,'Logic Tree'!$I$85:$I$87,0),MATCH(H19,'Logic Tree'!$J$84:$N$84,0))
B20: 1 | C20: TEAM | D20: POSR | E20: TEAM | F20: ='Pod Library'!E22 | G20: ='Pod Library'!F22 | H20: ='Pod Library'!G22 | I20: ='Pod Library'!H22 | J20: ='Pod Library'!I22 | K20: ='Pod Library'!J22 | L20: ='Pod Plan'!F6 | M20: =K20*L20 | N20: =M20*INDEX('Logic Tree'!$J$85:$N$87,MATCH(I20,'Logic Tree'!$I$85:$I$87,0),MATCH(H20,'Logic Tree'!$J$84:$N$84,0))
B21: 1 | C21: TEAM | D21: POSR | E21: TEAM | F21: ='Pod Library'!E23 | G21: ='Pod Library'!F23 | H21: ='Pod Library'!G23 | I21: ='Pod Library'!H23 | J21: ='Pod Library'!I23 | K21: ='Pod Library'!J23 | L21: ='Pod Plan'!F6 | M21: =K21*L21 | N21: =M21*INDEX('Logic Tree'!$J$85:$N$87,MATCH(I21,'Logic Tree'!$I$85:$I$87,0),MATCH(H21,'Logic Tree'!$J$84:$N$84,0))
B22: 1 | C22: TEAM | D22: POSR | E22: TEAM | F22: ='Pod Library'!E24 | G22: ='Pod Library'!F24 | H22: ='Pod Library'!G24 | I22: ='Pod Library'!H24 | J22: ='Pod Library'!I24 | K22: ='Pod Library'!J24 | L22: ='Pod Plan'!F6 | M22: =K22*L22 | N22: =M22*INDEX('Logic Tree'!$J$85:$N$87,MATCH(I22,'Logic Tree'!$I$85:$I$87,0),MATCH(H22,'Logic Tree'!$J$84:$N$84,0))
B23: 1 | C23: TEAM | D23: POSR | E23: TEAM | F23: ='Pod Library'!E25 | G23: ='Pod Library'!F25 | H23: ='Pod Library'!G25 | I23: ='Pod Library'!H25 | J23: ='Pod Library'!I25 | K23: ='Pod Library'!J25 | L23: ='Pod Plan'!F6 | M23: =K23*L23 | N23: =M23*INDEX('Logic Tree'!$J$85:$N$87,MATCH(I23,'Logic Tree'!$I$85:$I$87,0),MATCH(H23,'Logic Tree'!$J$84:$N$84,0))
B24: 1 | C24: TEAM | D24: POSR | E24: TEAM | F24: ='Pod Library'!E26 | G24: ='Pod Library'!F26 | H24: ='Pod Library'!G26 | I24: ='Pod Library'!H26 | J24: ='Pod Library'!I26 | K24: ='Pod Library'!J26 | L24: ='Pod Plan'!F6 | M24: =K24*L24 | N24: =M24*INDEX('Logic Tree'!$J$85:$N$87,MATCH(I24,'Logic Tree'!$I$85:$I$87,0),MATCH(H24,'Logic Tree'!$J$84:$N$84,0))
B25: 1 | C25: TEAM | D25: POSR | E25: TEAM | F25: ='Pod Library'!E27 | G25: ='Pod Library'!F27 | H25: ='Pod Library'!G27 | I25: ='Pod Library'!H27 | J25: ='Pod Library'!I27 | K25: ='Pod Library'!J27 | L25: ='Pod Plan'!F6 | M25: =K25*L25 | N25: =M25*INDEX('Logic Tree'!$J$85:$N$87,MATCH(I25,'Logic Tree'!$I$85:$I$87,0),MATCH(H25,'Logic Tree'!$J$84:$N$84,0))
B26: 1 | C26: TEAM | D26: POSR | E26: TEAM | F26: ='Pod Library'!E28 | G26: ='Pod Library'!F28 | H26: ='Pod Library'!G28 | I26: ='Pod Library'!H28 | J26: ='Pod Library'!I28 | K26: ='Pod Library'!J28 | L26: ='Pod Plan'!F6 | M26: =K26*L26 | N26: =M26*INDEX('Logic Tree'!$J$85:$N$87,MATCH(I26,'Logic Tree'!$I$85:$I$87,0),MATCH(H26,'Logic Tree'!$J$84:$N$84,0))
B27: 1 | C27: TEAM | D27: POSR | E27: TEAM | F27: ='Pod Library'!E29 | G27: ='Pod Library'!F29 | H27: ='Pod Library'!G29 | I27: ='Pod Library'!H29 | J27: ='Pod Library'!I29 | K27: ='Pod Library'!J29 | L27: ='Pod Plan'!F6 | M27: =K27*L27 | N27: =M27*INDEX('Logic Tree'!$J$85:$N$87,MATCH(I27,'Logic Tree'!$I$85:$I$87,0),MATCH(H27,'Logic Tree'!$J$84:$N$84,0))
B28: 1 | C28: TEAM | D28: POSR | E28: TEAM | F28: ='Pod Library'!E30 | G28: ='Pod Library'!F30 | H28: ='Pod Library'!G30 | I28: ='Pod Library'!H30 | J28: ='Pod Library'!I30 | K28: ='Pod Library'!J30 | L28: ='Pod Plan'!F6 | M28: =K28*L28 | N28: =M28*INDEX('Logic Tree'!$J$85:$N$87,MATCH(I28,'Logic Tree'!$I$85:$I$87,0),MATCH(H28,'Logic Tree'!$J$84:$N$84,0))
B29: 1 | C29: TEAM | D29: POSR | E29: TEAM | F29: ='Pod Library'!E31 | G29: ='Pod Library'!F31 | H29: ='Pod Library'!G31 | I29: ='Pod Library'!H31 | J29: ='Pod Library'!I31 | K29: ='Pod Library'!J31 | L29: ='Pod Plan'!F6 | M29: =K29*L29 | N29: =M29*INDEX('Logic Tree'!$J$85:$N$87,MATCH(I29,'Logic Tree'!$I$85:$I$87,0),MATCH(H29,'Logic Tree'!$J$84:$N$84,0))
B30: 2 | C30: TEAM | D30: POSW | E30: TEAM | F30: ='Pod Library'!E34 | G30: ='Pod Library'!F34 | H30: ='Pod Library'!G34 | I30: ='Pod Library'!H34 | J30: ='Pod Library'!I34 | K30: ='Pod Library'!J34 | L30: ='Pod Plan'!F9 | M30: =K30*L30 | N30: =M30*INDEX('Logic Tree'!$J$85:$N$87,MATCH(I30,'Logic Tree'!$I$85:$I$87,0),MATCH(H30,'Logic Tree'!$J$84:$N$84,0))
B31: 2 | C31: TEAM | D31: POSW | E31: TEAM | F31: ='Pod Library'!E35 | G31: ='Pod Library'!F35 | H31: ='Pod Library'!G35 | I31: ='Pod Library'!H35 | J31: ='Pod Library'!I35 | K31: ='Pod Library'!J35 | L31: ='Pod Plan'!F9 | M31: =K31*L31 | N31: =M31*INDEX('Logic Tree'!$J$85:$N$87,MATCH(I31,'Logic Tree'!$I$85:$I$87,0),MATCH(H31,'Logic Tree'!$J$84:$N$84,0))
B32: 2 | C32: TEAM | D32: POSW | E32: TEAM | F32: ='Pod Library'!E36 | G32: ='Pod Library'!F36 | H32: ='Pod Library'!G36 | I32: ='Pod Library'!H36 | J32: ='Pod Library'!I36 | K32: ='Pod Library'!J36 | L32: ='Pod Plan'!F9 | M32: =K32*L32 | N32: =M32*INDEX('Logic Tree'!$J$85:$N$87,MATCH(I32,'Logic Tree'!$I$85:$I$87,0),MATCH(H32,'Logic Tree'!$J$84:$N$84,0))
B33: 2 | C33: TEAM | D33: POSW | E33: TEAM | F33: ='Pod Library'!E37 | G33: ='Pod Library'!F37 | H33: ='Pod Library'!G37 | I33: ='Pod Library'!H37 | J33: ='Pod Library'!I37 | K33: ='Pod Library'!J37 | L33: ='Pod Plan'!F9 | M33: =K33*L33 | N33: =M33*INDEX('Logic Tree'!$J$85:$N$87,MATCH(I33,'Logic Tree'!$I$85:$I$87,0),MATCH(H33,'Logic Tree'!$J$84:$N$84,0))
B34: 2 | C34: TEAM | D34: POSW | E34: TEAM | F34: ='Pod Library'!E38 | G34: ='Pod Library'!F38 | H34: ='Pod Library'!G38 | I34: ='Pod Library'!H38 | J34: ='Pod Library'!I38 | K34: ='Pod Library'!J38 | L34: ='Pod Plan'!F9 | M34: =K34*L34 | N34: =M34*INDEX('Logic Tree'!$J$85:$N$87,MATCH(I34,'Logic Tree'!$I$85:$I$87,0),MATCH(H34,'Logic Tree'!$J$84:$N$84,0))
B35: 2 | C35: TEAM | D35: POSW | E35: TEAM | F35: ='Pod Library'!E39 | G35: ='Pod Library'!F39 | H35: ='Pod Library'!G39 | I35: ='Pod Library'!H39 | J35: ='Pod Library'!I39 | K35: ='Pod Library'!J39 | L35: ='Pod Plan'!F9 | M35: =K35*L35 | N35: =M35*INDEX('Logic Tree'!$J$85:$N$87,MATCH(I35,'Logic Tree'!$I$85:$I$87,0),MATCH(H35,'Logic Tree'!$J$84:$N$84,0))
B36: 2 | C36: TEAM | D36: POSW | E36: TEAM | F36: ='Pod Library'!E40 | G36: ='Pod Library'!F40 | H36: ='Pod Library'!G40 | I36: ='Pod Library'!H40 | J36: ='Pod Library'!I40 | K36: ='Pod Library'!J40 | L36: ='Pod Plan'!F9 | M36: =K36*L36 | N36: =M36*INDEX('Logic Tree'!$J$85:$N$87,MATCH(I36,'Logic Tree'!$I$85:$I$87,0),MATCH(H36,'Logic Tree'!$J$84:$N$84,0))
B37: 2 | C37: TEAM | D37: POSW | E37: TEAM | F37: ='Pod Library'!E41 | G37: ='Pod Library'!F41 | H37: ='Pod Library'!G41 | I37: ='Pod Library'!H41 | J37: ='Pod Library'!I41 | K37: ='Pod Library'!J41 | L37: ='Pod Plan'!F9 | M37: =K37*L37 | N37: =M37*INDEX('Logic Tree'!$J$85:$N$87,MATCH(I37,'Logic Tree'!$I$85:$I$87,0),MATCH(H37,'Logic Tree'!$J$84:$N$84,0))
B38: 2 | C38: TEAM | D38: POSW | E38: TEAM | F38: ='Pod Library'!E42 | G38: ='Pod Library'!F42 | H38: ='Pod Library'!G42 | I38: ='Pod Library'!H42 | J38: ='Pod Library'!I42 | K38: ='Pod Library'!J42 | L38: ='Pod Plan'!F9 | M38: =K38*L38 | N38: =M38*INDEX('Logic Tree'!$J$85:$N$87,MATCH(I38,'Logic Tree'!$I$85:$I$87,0),MATCH(H38,'Logic Tree'!$J$84:$N$84,0))
B39: 2 | C39: TEAM | D39: POSW | E39: TEAM | F39: ='Pod Library'!E43 | G39: ='Pod Library'!F43 | H39: ='Pod Library'!G43 | I39: ='Pod Library'!H43 | J39: ='Pod Library'!I43 | K39: ='Pod Library'!J43 | L39: ='Pod Plan'!F9 | M39: =K39*L39 | N39: =M39*INDEX('Logic Tree'!$J$85:$N$87,MATCH(I39,'Logic Tree'!$I$85:$I$87,0),MATCH(H39,'Logic Tree'!$J$84:$N$84,0))
B40: 2 | C40: TEAM | D40: POSW | E40: TEAM | F40: ='Pod Library'!E44 | G40: ='Pod Library'!F44 | H40: ='Pod Library'!G44 | I40: ='Pod Library'!H44 | J40: ='Pod Library'!I44 | K40: ='Pod Library'!J44 | L40: ='Pod Plan'!F9 | M40: =K40*L40 | N40: =M40*INDEX('Logic Tree'!$J$85:$N$87,MATCH(I40,'Logic Tree'!$I$85:$I$87,0),MATCH(H40,'Logic Tree'!$J$84:$N$84,0))
B41: 2 | C41: TEAM | D41: POSW | E41: TEAM | F41: ='Pod Library'!E45 | G41: ='Pod Library'!F45 | H41: ='Pod Library'!G45 | I41: ='Pod Library'!H45 | J41: ='Pod Library'!I45 | K41: ='Pod Library'!J45 | L41: ='Pod Plan'!F9 | M41: =K41*L41 | N41: =M41*INDEX('Logic Tree'!$J$85:$N$87,MATCH(I41,'Logic Tree'!$I$85:$I$87,0),MATCH(H41,'Logic Tree'!$J$84:$N$84,0))
B42: 2 | C42: TEAM | D42: POSW | E42: TEAM | F42: ='Pod Library'!E46 | G42: ='Pod Library'!F46 | H42: ='Pod Library'!G46 | I42: ='Pod Library'!H46 | J42: ='Pod Library'!I46 | K42: ='Pod Library'!J46 | L42: ='Pod Plan'!F9 | M42: =K42*L42 | N42: =M42*INDEX('Logic Tree'!$J$85:$N$87,MATCH(I42,'Logic Tree'!$I$85:$I$87,0),MATCH(H42,'Logic Tree'!$J$84:$N$84,0))
B43: 2 | C43: TEAM | D43: POSW | E43: TEAM | F43: ='Pod Library'!E47 | G43: ='Pod Library'!F47 | H43: ='Pod Library'!G47 | I43: ='Pod Library'!H47 | J43: ='Pod Library'!I47 | K43: ='Pod Library'!J47 | L43: ='Pod Plan'!F9 | M43: =K43*L43 | N43: =M43*INDEX('Logic Tree'!$J$85:$N$87,MATCH(I43,'Logic Tree'!$I$85:$I$87,0),MATCH(H43,'Logic Tree'!$J$84:$N$84,0))
B44: 2 | C44: TEAM | D44: POSR | E44: TEAM | F44: ='Pod Library'!E50 | G44: ='Pod Library'!F50 | H44: ='Pod Library'!G50 | I44: ='Pod Library'!H50 | J44: ='Pod Library'!I50 | K44: ='Pod Library'!J50 | L44: ='Pod Plan'!F10 | M44: =K44*L44 | N44: =M44*INDEX('Logic Tree'!$J$85:$N$87,MATCH(I44,'Logic Tree'!$I$85:$I$87,0),MATCH(H44,'Logic Tree'!$J$84:$N$84,0))
B45: 2 | C45: TEAM | D45: POSR | E45: TEAM | F45: ='Pod Library'!E51 | G45: ='Pod Library'!F51 | H45: ='Pod Library'!G51 | I45: ='Pod Library'!H51 | J45: ='Pod Library'!I51 | K45: ='Pod Library'!J51 | L45: ='Pod Plan'!F10 | M45: =K45*L45 | N45: =M45*INDEX('Logic Tree'!$J$85:$N$87,MATCH(I45,'Logic Tree'!$I$85:$I$87,0),MATCH(H45,'Logic Tree'!$J$84:$N$84,0))
B46: 2 | C46: TEAM | D46: POSR | E46: TEAM | F46: ='Pod Library'!E52 | G46: ='Pod Library'!F52 | H46: ='Pod Library'!G52 | I46: ='Pod Library'!H52 | J46: ='Pod Library'!I52 | K46: ='Pod Library'!J52 | L46: ='Pod Plan'!F10 | M46: =K46*L46 | N46: =M46*INDEX('Logic Tree'!$J$85:$N$87,MATCH(I46,'Logic Tree'!$I$85:$I$87,0),MATCH(H46,'Logic Tree'!$J$84:$N$84,0))
B47: 2 | C47: TEAM | D47: POSR | E47: TEAM | F47: ='Pod Library'!E53 | G47: ='Pod Library'!F53 | H47: ='Pod Library'!G53 | I47: ='Pod Library'!H53 | J47: ='Pod Library'!I53 | K47: ='Pod Library'!J53 | L47: ='Pod Plan'!F10 | M47: =K47*L47 | N47: =M47*INDEX('Logic Tree'!$J$85:$N$87,MATCH(I47,'Logic Tree'!$I$85:$I$87,0),MATCH(H47,'Logic Tree'!$J$84:$N$84,0))
B48: 2 | C48: TEAM | D48: POSR | E48: TEAM | F48: ='Pod Library'!E54 | G48: ='Pod Library'!F54 | H48: ='Pod Library'!G54 | I48: ='Pod Library'!H54 | J48: ='Pod Library'!I54 | K48: ='Pod Library'!J54 | L48: ='Pod Plan'!F10 | M48: =K48*L48 | N48: =M48*INDEX('Logic Tree'!$J$85:$N$87,MATCH(I48,'Logic Tree'!$I$85:$I$87,0),MATCH(H48,'Logic Tree'!$J$84:$N$84,0))
B49: 2 | C49: TEAM | D49: POSR | E49: TEAM | F49: ='Pod Library'!E55 | G49: ='Pod Library'!F55 | H49: ='Pod Library'!G55 | I49: ='Pod Library'!H55 | J49: ='Pod Library'!I55 | K49: ='Pod Library'!J55 | L49: ='Pod Plan'!F10 | M49: =K49*L49 | N49: =M49*INDEX('Logic Tree'!$J$85:$N$87,MATCH(I49,'Logic Tree'!$I$85:$I$87,0),MATCH(H49,'Logic Tree'!$J$84:$N$84,0))
B50: 2 | C50: TEAM | D50: POSR | E50: TEAM | F50: ='Pod Library'!E56 | G50: ='Pod Library'!F56 | H50: ='Pod Library'!G56 | I50: ='Pod Library'!H56 | J50: ='Pod Library'!I56 | K50: ='Pod Library'!J56 | L50: ='Pod Plan'!F10 | M50: =K50*L50 | N50: =M50*INDEX('Logic Tree'!$J$85:$N$87,MATCH(I50,'Logic Tree'!$I$85:$I$87,0),MATCH(H50,'Logic Tree'!$J$84:$N$84,0))
B51: 2 | C51: TEAM | D51: POSR | E51: TEAM | F51: ='Pod Library'!E57 | G51: ='Pod Library'!F57 | H51: ='Pod Library'!G57 | I51: ='Pod Library'!H57 | J51: ='Pod Library'!I57 | K51: ='Pod Library'!J57 | L51: ='Pod Plan'!F10 | M51: =K51*L51 | N51: =M51*INDEX('Logic Tree'!$J$85:$N$87,MATCH(I51,'Logic Tree'!$I$85:$I$87,0),MATCH(H51,'Logic Tree'!$J$84:$N$84,0))
B52: 2 | C52: TEAM | D52: POSR | E52: TEAM | F52: ='Pod Library'!E58 | G52: ='Pod Library'!F58 | H52: ='Pod Library'!G58 | I52: ='Pod Library'!H58 | J52: ='Pod Library'!I58 | K52: ='Pod Library'!J58 | L52: ='Pod Plan'!F10 | M52: =K52*L52 | N52: =M52*INDEX('Logic Tree'!$J$85:$N$87,MATCH(I52,'Logic Tree'!$I$85:$I$87,0),MATCH(H52,'Logic Tree'!$J$84:$N$84,0))
B53: 2 | C53: TEAM | D53: POSR | E53: TEAM | F53: ='Pod Library'!E59 | G53: ='Pod Library'!F59 | H53: ='Pod Library'!G59 | I53: ='Pod Library'!H59 | J53: ='Pod Library'!I59 | K53: ='Pod Library'!J59 | L53: ='Pod Plan'!F10 | M53: =K53*L53 | N53: =M53*INDEX('Logic Tree'!$J$85:$N$87,MATCH(I53,'Logic Tree'!$I$85:$I$87,0),MATCH(H53,'Logic Tree'!$J$84:$N$84,0))
B54: 2 | C54: TEAM | D54: POSR | E54: TEAM | F54: ='Pod Library'!E60 | G54: ='Pod Library'!F60 | H54: ='Pod Library'!G60 | I54: ='Pod Library'!H60 | J54: ='Pod Library'!I60 | K54: ='Pod Library'!J60 | L54: ='Pod Plan'!F10 | M54: =K54*L54 | N54: =M54*INDEX('Logic Tree'!$J$85:$N$87,MATCH(I54,'Logic Tree'!$I$85:$I$87,0),MATCH(H54,'Logic Tree'!$J$84:$N$84,0))
B55: 2 | C55: TEAM | D55: POSR | E55: TEAM | F55: ='Pod Library'!E61 | G55: ='Pod Library'!F61 | H55: ='Pod Library'!G61 | I55: ='Pod Library'!H61 | J55: ='Pod Library'!I61 | K55: ='Pod Library'!J61 | L55: ='Pod Plan'!F10 | M55: =K55*L55 | N55: =M55*INDEX('Logic Tree'!$J$85:$N$87,MATCH(I55,'Logic Tree'!$I$85:$I$87,0),MATCH(H55,'Logic Tree'!$J$84:$N$84,0))
B56: 2 | C56: TEAM | D56: POSR | E56: TEAM | F56: ='Pod Library'!E62 | G56: ='Pod Library'!F62 | H56: ='Pod Library'!G62 | I56: ='Pod Library'!H62 | J56: ='Pod Library'!I62 | K56: ='Pod Library'!J62 | L56: ='Pod Plan'!F10 | M56: =K56*L56 | N56: =M56*INDEX('Logic Tree'!$J$85:$N$87,MATCH(I56,'Logic Tree'!$I$85:$I$87,0),MATCH(H56,'Logic Tree'!$J$84:$N$84,0))
B57: 3 | C57: TEAM | D57: POSW | E57: TEAM | F57: ='Pod Library'!E65 | G57: ='Pod Library'!F65 | H57: ='Pod Library'!G65 | I57: ='Pod Library'!H65 | J57: ='Pod Library'!I65 | K57: ='Pod Library'!J65 | L57: ='Pod Plan'!F13 | M57: =K57*L57 | N57: =M57*INDEX('Logic Tree'!$J$85:$N$87,MATCH(I57,'Logic Tree'!$I$85:$I$87,0),MATCH(H57,'Logic Tree'!$J$84:$N$84,0))
B58: 3 | C58: TEAM | D58: POSW | E58: TEAM | F58: ='Pod Library'!E66 | G58: ='Pod Library'!F66 | H58: ='Pod Library'!G66 | I58: ='Pod Library'!H66 | J58: ='Pod Library'!I66 | K58: ='Pod Library'!J66 | L58: ='Pod Plan'!F13 | M58: =K58*L58 | N58: =M58*INDEX('Logic Tree'!$J$85:$N$87,MATCH(I58,'Logic Tree'!$I$85:$I$87,0),MATCH(H58,'Logic Tree'!$J$84:$N$84,0))
B59: 3 | C59: TEAM | D59: POSW | E59: TEAM | F59: ='Pod Library'!E67 | G59: ='Pod Library'!F67 | H59: ='Pod Library'!G67 | I59: ='Pod Library'!H67 | J59: ='Pod Library'!I67 | K59: ='Pod Library'!J67 | L59: ='Pod Plan'!F13 | M59: =K59*L59 | N59: =M59*INDEX('Logic Tree'!$J$85:$N$87,MATCH(I59,'Logic Tree'!$I$85:$I$87,0),MATCH(H59,'Logic Tree'!$J$84:$N$84,0))
B60: 3 | C60: TEAM | D60: POSW | E60: TEAM | F60: ='Pod Library'!E68 | G60: ='Pod Library'!F68 | H60: ='Pod Library'!G68 | I60: ='Pod Library'!H68 | J60: ='Pod Library'!I68 | K60: ='Pod Library'!J68 | L60: ='Pod Plan'!F13 | M60: =K60*L60 | N60: =M60*INDEX('Logic Tree'!$J$85:$N$87,MATCH(I60,'Logic Tree'!$I$85:$I$87,0),MATCH(H60,'Logic Tree'!$J$84:$N$84,0))
B61: 3 | C61: TEAM | D61: POSW | E61: TEAM | F61: ='Pod Library'!E69 | G61: ='Pod Library'!F69 | H61: ='Pod Library'!G69 | I61: ='Pod Library'!H69 | J61: ='Pod Library'!I69 | K61: ='Pod Library'!J69 | L61: ='Pod Plan'!F13 | M61: =K61*L61 | N61: =M61*INDEX('Logic Tree'!$J$85:$N$87,MATCH(I61,'Logic Tree'!$I$85:$I$87,0),MATCH(H61,'Logic Tree'!$J$84:$N$84,0))
B62: 3 | C62: TEAM | D62: POSW | E62: TEAM | F62: ='Pod Library'!E70 | G62: ='Pod Library'!F70 | H62: ='Pod Library'!G70 | I62: ='Pod Library'!H70 | J62: ='Pod Library'!I70 | K62: ='Pod Library'!J70 | L62: ='Pod Plan'!F13 | M62: =K62*L62 | N62: =M62*INDEX('Logic Tree'!$J$85:$N$87,MATCH(I62,'Logic Tree'!$I$85:$I$87,0),MATCH(H62,'Logic Tree'!$J$84:$N$84,0))
B63: 3 | C63: TEAM | D63: POSW | E63: TEAM | F63: ='Pod Library'!E71 | G63: ='Pod Library'!F71 | H63: ='Pod Library'!G71 | I63: ='Pod Library'!H71 | J63: ='Pod Library'!I71 | K63: ='Pod Library'!J71 | L63: ='Pod Plan'!F13 | M63: =K63*L63 | N63: =M63*INDEX('Logic Tree'!$J$85:$N$87,MATCH(I63,'Logic Tree'!$I$85:$I$87,0),MATCH(H63,'Logic Tree'!$J$84:$N$84,0))
B64: 3 | C64: TEAM | D64: POSW | E64: TEAM | F64: ='Pod Library'!E72 | G64: ='Pod Library'!F72 | H64: ='Pod Library'!G72 | I64: ='Pod Library'!H72 | J64: ='Pod Library'!I72 | K64: ='Pod Library'!J72 | L64: ='Pod Plan'!F13 | M64: =K64*L64 | N64: =M64*INDEX('Logic Tree'!$J$85:$N$87,MATCH(I64,'Logic Tree'!$I$85:$I$87,0),MATCH(H64,'Logic Tree'!$J$84:$N$84,0))
B65: 3 | C65: TEAM | D65: POSW | E65: TEAM | F65: ='Pod Library'!E73 | G65: ='Pod Library'!F73 | H65: ='Pod Library'!G73 | I65: ='Pod Library'!H73 | J65: ='Pod Library'!I73 | K65: ='Pod Library'!J73 | L65: ='Pod Plan'!F13 | M65: =K65*L65 | N65: =M65*INDEX('Logic Tree'!$J$85:$N$87,MATCH(I65,'Logic Tree'!$I$85:$I$87,0),MATCH(H65,'Logic Tree'!$J$84:$N$84,0))
B66: 3 | C66: TEAM | D66: POSW | E66: TEAM | F66: ='Pod Library'!E74 | G66: ='Pod Library'!F74 | H66: ='Pod Library'!G74 | I66: ='Pod Library'!H74 | J66: ='Pod Library'!I74 | K66: ='Pod Library'!J74 | L66: ='Pod Plan'!F13 | M66: =K66*L66 | N66: =M66*INDEX('Logic Tree'!$J$85:$N$87,MATCH(I66,'Logic Tree'!$I$85:$I$87,0),MATCH(H66,'Logic Tree'!$J$84:$N$84,0))
B67: 3 | C67: TEAM | D67: POSW | E67: TEAM | F67: ='Pod Library'!E75 | G67: ='Pod Library'!F75 | H67: ='Pod Library'!G75 | I67: ='Pod Library'!H75 | J67: ='Pod Library'!I75 | K67: ='Pod Library'!J75 | L67: ='Pod Plan'!F13 | M67: =K67*L67 | N67: =M67*INDEX('Logic Tree'!$J$85:$N$87,MATCH(I67,'Logic Tree'!$I$85:$I$87,0),MATCH(H67,'Logic Tree'!$J$84:$N$84,0))
B68: 3 | C68: TEAM | D68: POSW | E68: TEAM | F68: ='Pod Library'!E76 | G68: ='Pod Library'!F76 | H68: ='Pod Library'!G76 | I68: ='Pod Library'!H76 | J68: ='Pod Library'!I76 | K68: ='Pod Library'!J76 | L68: ='Pod Plan'!F13 | M68: =K68*L68 | N68: =M68*INDEX('Logic Tree'!$J$85:$N$87,MATCH(I68,'Logic Tree'!$I$85:$I$87,0),MATCH(H68,'Logic Tree'!$J$84:$N$84,0))
B69: 3 | C69: TEAM | D69: POSW | E69: TEAM | F69: ='Pod Library'!E77 | G69: ='Pod Library'!F77 | H69: ='Pod Library'!G77 | I69: ='Pod Library'!H77 | J69: ='Pod Library'!I77 | K69: ='Pod Library'!J77 | L69: ='Pod Plan'!F13 | M69: =K69*L69 | N69: =M69*INDEX('Logic Tree'!$J$85:$N$87,MATCH(I69,'Logic Tree'!$I$85:$I$87,0),MATCH(H69,'Logic Tree'!$J$84:$N$84,0))
B70: 3 | C70: TEAM | D70: POSR | E70: TEAM | F70: ='Pod Library'!E80 | G70: ='Pod Library'!F80 | H70: ='Pod Library'!G80 | I70: ='Pod Library'!H80 | J70: ='Pod Library'!I80 | K70: ='Pod Library'!J80 | L70: ='Pod Plan'!F14 | M70: =K70*L70 | N70: =M70*INDEX('Logic Tree'!$J$85:$N$87,MATCH(I70,'Logic Tree'!$I$85:$I$87,0),MATCH(H70,'Logic Tree'!$J$84:$N$84,0))
B71: 3 | C71: TEAM | D71: POSR | E71: TEAM | F71: ='Pod Library'!E81 | G71: ='Pod Library'!F81 | H71: ='Pod Library'!G81 | I71: ='Pod Library'!H81 | J71: ='Pod Library'!I81 | K71: ='Pod Library'!J81 | L71: ='Pod Plan'!F14 | M71: =K71*L71 | N71: =M71*INDEX('Logic Tree'!$J$85:$N$87,MATCH(I71,'Logic Tree'!$I$85:$I$87,0),MATCH(H71,'Logic Tree'!$J$84:$N$84,0))
B72: 3 | C72: TEAM | D72: POSR | E72: TEAM | F72: ='Pod Library'!E82 | G72: ='Pod Library'!F82 | H72: ='Pod Library'!G82 | I72: ='Pod Library'!H82 | J72: ='Pod Library'!I82 | K72: ='Pod Library'!J82 | L72: ='Pod Plan'!F14 | M72: =K72*L72 | N72: =M72*INDEX('Logic Tree'!$J$85:$N$87,MATCH(I72,'Logic Tree'!$I$85:$I$87,0),MATCH(H72,'Logic Tree'!$J$84:$N$84,0))
B73: 3 | C73: TEAM | D73: POSR | E73: TEAM | F73: ='Pod Library'!E83 | G73: ='Pod Library'!F83 | H73: ='Pod Library'!G83 | I73: ='Pod Library'!H83 | J73: ='Pod Library'!I83 | K73: ='Pod Library'!J83 | L73: ='Pod Plan'!F14 | M73: =K73*L73 | N73: =M73*INDEX('Logic Tree'!$J$85:$N$87,MATCH(I73,'Logic Tree'!$I$85:$I$87,0),MATCH(H73,'Logic Tree'!$J$84:$N$84,0))
B74: 3 | C74: TEAM | D74: POSR | E74: TEAM | F74: ='Pod Library'!E84 | G74: ='Pod Library'!F84 | H74: ='Pod Library'!G84 | I74: ='Pod Library'!H84 | J74: ='Pod Library'!I84 | K74: ='Pod Library'!J84 | L74: ='Pod Plan'!F14 | M74: =K74*L74 | N74: =M74*INDEX('Logic Tree'!$J$85:$N$87,MATCH(I74,'Logic Tree'!$I$85:$I$87,0),MATCH(H74,'Logic Tree'!$J$84:$N$84,0))
B75: 3 | C75: TEAM | D75: POSR | E75: TEAM | F75: ='Pod Library'!E85 | G75: ='Pod Library'!F85 | H75: ='Pod Library'!G85 | I75: ='Pod Library'!H85 | J75: ='Pod Library'!I85 | K75: ='Pod Library'!J85 | L75: ='Pod Plan'!F14 | M75: =K75*L75 | N75: =M75*INDEX('Logic Tree'!$J$85:$N$87,MATCH(I75,'Logic Tree'!$I$85:$I$87,0),MATCH(H75,'Logic Tree'!$J$84:$N$84,0))
B76: 3 | C76: TEAM | D76: POSR | E76: TEAM | F76: ='Pod Library'!E86 | G76: ='Pod Library'!F86 | H76: ='Pod Library'!G86 | I76: ='Pod Library'!H86 | J76: ='Pod Library'!I86 | K76: ='Pod Library'!J86 | L76: ='Pod Plan'!F14 | M76: =K76*L76 | N76: =M76*INDEX('Logic Tree'!$J$85:$N$87,MATCH(I76,'Logic Tree'!$I$85:$I$87,0),MATCH(H76,'Logic Tree'!$J$84:$N$84,0))
B77: 3 | C77: TEAM | D77: POSR | E77: TEAM | F77: ='Pod Library'!E87 | G77: ='Pod Library'!F87 | H77: ='Pod Library'!G87 | I77: ='Pod Library'!H87 | J77: ='Pod Library'!I87 | K77: ='Pod Library'!J87 | L77: ='Pod Plan'!F14 | M77: =K77*L77 | N77: =M77*INDEX('Logic Tree'!$J$85:$N$87,MATCH(I77,'Logic Tree'!$I$85:$I$87,0),MATCH(H77,'Logic Tree'!$J$84:$N$84,0))
B78: 3 | C78: TEAM | D78: POSR | E78: TEAM | F78: ='Pod Library'!E88 | G78: ='Pod Library'!F88 | H78: ='Pod Library'!G88 | I78: ='Pod Library'!H88 | J78: ='Pod Library'!I88 | K78: ='Pod Library'!J88 | L78: ='Pod Plan'!F14 | M78: =K78*L78 | N78: =M78*INDEX('Logic Tree'!$J$85:$N$87,MATCH(I78,'Logic Tree'!$I$85:$I$87,0),MATCH(H78,'Logic Tree'!$J$84:$N$84,0))
B79: 3 | C79: TEAM | D79: POSR | E79: TEAM | F79: ='Pod Library'!E89 | G79: ='Pod Library'!F89 | H79: ='Pod Library'!G89 | I79: ='Pod Library'!H89 | J79: ='Pod Library'!I89 | K79: ='Pod Library'!J89 | L79: ='Pod Plan'!F14 | M79: =K79*L79 | N79: =M79*INDEX('Logic Tree'!$J$85:$N$87,MATCH(I79,'Logic Tree'!$I$85:$I$87,0),MATCH(H79,'Logic Tree'!$J$84:$N$84,0))
B80: 3 | C80: TEAM | D80: POSR | E80: TEAM | F80: ='Pod Library'!E90 | G80: ='Pod Library'!F90 | H80: ='Pod Library'!G90 | I80: ='Pod Library'!H90 | J80: ='Pod Library'!I90 | K80: ='Pod Library'!J90 | L80: ='Pod Plan'!F14 | M80: =K80*L80 | N80: =M80*INDEX('Logic Tree'!$J$85:$N$87,MATCH(I80,'Logic Tree'!$I$85:$I$87,0),MATCH(H80,'Logic Tree'!$J$84:$N$84,0))
B81: 3 | C81: TEAM | D81: POSR | E81: TEAM | F81: ='Pod Library'!E91 | G81: ='Pod Library'!F91 | H81: ='Pod Library'!G91 | I81: ='Pod Library'!H91 | J81: ='Pod Library'!I91 | K81: ='Pod Library'!J91 | L81: ='Pod Plan'!F14 | M81: =K81*L81 | N81: =M81*INDEX('Logic Tree'!$J$85:$N$87,MATCH(I81,'Logic Tree'!$I$85:$I$87,0),MATCH(H81,'Logic Tree'!$J$84:$N$84,0))
B82: 3 | C82: TEAM | D82: POSR | E82: TEAM | F82: ='Pod Library'!E92 | G82: ='Pod Library'!F92 | H82: ='Pod Library'!G92 | I82: ='Pod Library'!H92 | J82: ='Pod Library'!I92 | K82: ='Pod Library'!J92 | L82: ='Pod Plan'!F14 | M82: =K82*L82 | N82: =M82*INDEX('Logic Tree'!$J$85:$N$87,MATCH(I82,'Logic Tree'!$I$85:$I$87,0),MATCH(H82,'Logic Tree'!$J$84:$N$84,0))
B83: 4 | C83: TEAM | D83: POSW | E83: TEAM | F83: ='Pod Library'!E95 | G83: ='Pod Library'!F95 | H83: ='Pod Library'!G95 | I83: ='Pod Library'!H95 | J83: ='Pod Library'!I95 | K83: ='Pod Library'!J95 | L83: ='Pod Plan'!F17 | M83: =K83*L83 | N83: =M83*INDEX('Logic Tree'!$J$85:$N$87,MATCH(I83,'Logic Tree'!$I$85:$I$87,0),MATCH(H83,'Logic Tree'!$J$84:$N$84,0))
B84: 4 | C84: TEAM | D84: POSW | E84: TEAM | F84: ='Pod Library'!E96 | G84: ='Pod Library'!F96 | H84: ='Pod Library'!G96 | I84: ='Pod Library'!H96 | J84: ='Pod Library'!I96 | K84: ='Pod Library'!J96 | L84: ='Pod Plan'!F17 | M84: =K84*L84 | N84: =M84*INDEX('Logic Tree'!$J$85:$N$87,MATCH(I84,'Logic Tree'!$I$85:$I$87,0),MATCH(H84,'Logic Tree'!$J$84:$N$84,0))
B85: 4 | C85: TEAM | D85: POSW | E85: TEAM | F85: ='Pod Library'!E97 | G85: ='Pod Library'!F97 | H85: ='Pod Library'!G97 | I85: ='Pod Library'!H97 | J85: ='Pod Library'!I97 | K85: ='Pod Library'!J97 | L85: ='Pod Plan'!F17 | M85: =K85*L85 | N85: =M85*INDEX('Logic Tree'!$J$85:$N$87,MATCH(I85,'Logic Tree'!$I$85:$I$87,0),MATCH(H85,'Logic Tree'!$J$84:$N$84,0))
B86: 4 | C86: TEAM | D86: POSW | E86: TEAM | F86: ='Pod Library'!E98 | G86: ='Pod Library'!F98 | H86: ='Pod Library'!G98 | I86: ='Pod Library'!H98 | J86: ='Pod Library'!I98 | K86: ='Pod Library'!J98 | L86: ='Pod Plan'!F17 | M86: =K86*L86 | N86: =M86*INDEX('Logic Tree'!$J$85:$N$87,MATCH(I86,'Logic Tree'!$I$85:$I$87,0),MATCH(H86,'Logic Tree'!$J$84:$N$84,0))
B87: 4 | C87: TEAM | D87: POSW | E87: TEAM | F87: ='Pod Library'!E99 | G87: ='Pod Library'!F99 | H87: ='Pod Library'!G99 | I87: ='Pod Library'!H99 | J87: ='Pod Library'!I99 | K87: ='Pod Library'!J99 | L87: ='Pod Plan'!F17 | M87: =K87*L87 | N87: =M87*INDEX('Logic Tree'!$J$85:$N$87,MATCH(I87,'Logic Tree'!$I$85:$I$87,0),MATCH(H87,'Logic Tree'!$J$84:$N$84,0))
B88: 4 | C88: TEAM | D88: POSW | E88: TEAM | F88: ='Pod Library'!E100 | G88: ='Pod Library'!F100 | H88: ='Pod Library'!G100 | I88: ='Pod Library'!H100 | J88: ='Pod Library'!I100 | K88: ='Pod Library'!J100 | L88: ='Pod Plan'!F17 | M88: =K88*L88 | N88: =M88*INDEX('Logic Tree'!$J$85:$N$87,MATCH(I88,'Logic Tree'!$I$85:$I$87,0),MATCH(H88,'Logic Tree'!$J$84:$N$84,0))
B89: 4 | C89: TEAM | D89: POSW | E89: TEAM | F89: ='Pod Library'!E101 | G89: ='Pod Library'!F101 | H89: ='Pod Library'!G101 | I89: ='Pod Library'!H101 | J89: ='Pod Library'!I101 | K89: ='Pod Library'!J101 | L89: ='Pod Plan'!F17 | M89: =K89*L89 | N89: =M89*INDEX('Logic Tree'!$J$85:$N$87,MATCH(I89,'Logic Tree'!$I$85:$I$87,0),MATCH(H89,'Logic Tree'!$J$84:$N$84,0))
B90: 4 | C90: TEAM | D90: POSW | E90: TEAM | F90: ='Pod Library'!E102 | G90: ='Pod Library'!F102 | H90: ='Pod Library'!G102 | I90: ='Pod Library'!H102 | J90: ='Pod Library'!I102 | K90: ='Pod Library'!J102 | L90: ='Pod Plan'!F17 | M90: =K90*L90 | N90: =M90*INDEX('Logic Tree'!$J$85:$N$87,MATCH(I90,'Logic Tree'!$I$85:$I$87,0),MATCH(H90,'Logic Tree'!$J$84:$N$84,0))
B91: 4 | C91: TEAM | D91: POSW | E91: TEAM | F91: ='Pod Library'!E103 | G91: ='Pod Library'!F103 | H91: ='Pod Library'!G103 | I91: ='Pod Library'!H103 | J91: ='Pod Library'!I103 | K91: ='Pod Library'!J103 | L91: ='Pod Plan'!F17 | M91: =K91*L91 | N91: =M91*INDEX('Logic Tree'!$J$85:$N$87,MATCH(I91,'Logic Tree'!$I$85:$I$87,0),MATCH(H91,'Logic Tree'!$J$84:$N$84,0))
B92: 4 | C92: TEAM | D92: POSW | E92: TEAM | F92: ='Pod Library'!E104 | G92: ='Pod Library'!F104 | H92: ='Pod Library'!G104 | I92: ='Pod Library'!H104 | J92: ='Pod Library'!I104 | K92: ='Pod Library'!J104 | L92: ='Pod Plan'!F17 | M92: =K92*L92 | N92: =M92*INDEX('Logic Tree'!$J$85:$N$87,MATCH(I92,'Logic Tree'!$I$85:$I$87,0),MATCH(H92,'Logic Tree'!$J$84:$N$84,0))
B93: 4 | C93: TEAM | D93: POSW | E93: TEAM | F93: ='Pod Library'!E105 | G93: ='Pod Library'!F105 | H93: ='Pod Library'!G105 | I93: ='Pod Library'!H105 | J93: ='Pod Library'!I105 | K93: ='Pod Library'!J105 | L93: ='Pod Plan'!F17 | M93: =K93*L93 | N93: =M93*INDEX('Logic Tree'!$J$85:$N$87,MATCH(I93,'Logic Tree'!$I$85:$I$87,0),MATCH(H93,'Logic Tree'!$J$84:$N$84,0))
B94: 4 | C94: TEAM | D94: POSW | E94: TEAM | F94: ='Pod Library'!E106 | G94: ='Pod Library'!F106 | H94: ='Pod Library'!G106 | I94: ='Pod Library'!H106 | J94: ='Pod Library'!I106 | K94: ='Pod Library'!J106 | L94: ='Pod Plan'!F17 | M94: =K94*L94 | N94: =M94*INDEX('Logic Tree'!$J$85:$N$87,MATCH(I94,'Logic Tree'!$I$85:$I$87,0),MATCH(H94,'Logic Tree'!$J$84:$N$84,0))
B95: 4 | C95: TEAM | D95: POSR | E95: TEAM | F95: ='Pod Library'!E109 | G95: ='Pod Library'!F109 | H95: ='Pod Library'!G109 | I95: ='Pod Library'!H109 | J95: ='Pod Library'!I109 | K95: ='Pod Library'!J109 | L95: ='Pod Plan'!F18 | M95: =K95*L95 | N95: =M95*INDEX('Logic Tree'!$J$85:$N$87,MATCH(I95,'Logic Tree'!$I$85:$I$87,0),MATCH(H95,'Logic Tree'!$J$84:$N$84,0))
B96: 4 | C96: TEAM | D96: POSR | E96: TEAM | F96: ='Pod Library'!E110 | G96: ='Pod Library'!F110 | H96: ='Pod Library'!G110 | I96: ='Pod Library'!H110 | J96: ='Pod Library'!I110 | K96: ='Pod Library'!J110 | L96: ='Pod Plan'!F18 | M96: =K96*L96 | N96: =M96*INDEX('Logic Tree'!$J$85:$N$87,MATCH(I96,'Logic Tree'!$I$85:$I$87,0),MATCH(H96,'Logic Tree'!$J$84:$N$84,0))
B97: 4 | C97: TEAM | D97: POSR | E97: TEAM | F97: ='Pod Library'!E111 | G97: ='Pod Library'!F111 | H97: ='Pod Library'!G111 | I97: ='Pod Library'!H111 | J97: ='Pod Library'!I111 | K97: ='Pod Library'!J111 | L97: ='Pod Plan'!F18 | M97: =K97*L97 | N97: =M97*INDEX('Logic Tree'!$J$85:$N$87,MATCH(I97,'Logic Tree'!$I$85:$I$87,0),MATCH(H97,'Logic Tree'!$J$84:$N$84,0))
B98: 4 | C98: TEAM | D98: POSR | E98: TEAM | F98: ='Pod Library'!E112 | G98: ='Pod Library'!F112 | H98: ='Pod Library'!G112 | I98: ='Pod Library'!H112 | J98: ='Pod Library'!I112 | K98: ='Pod Library'!J112 | L98: ='Pod Plan'!F18 | M98: =K98*L98 | N98: =M98*INDEX('Logic Tree'!$J$85:$N$87,MATCH(I98,'Logic Tree'!$I$85:$I$87,0),MATCH(H98,'Logic Tree'!$J$84:$N$84,0))
B99: 4 | C99: TEAM | D99: POSR | E99: TEAM | F99: ='Pod Library'!E113 | G99: ='Pod Library'!F113 | H99: ='Pod Library'!G113 | I99: ='Pod Library'!H113 | J99: ='Pod Library'!I113 | K99: ='Pod Library'!J113 | L99: ='Pod Plan'!F18 | M99: =K99*L99 | N99: =M99*INDEX('Logic Tree'!$J$85:$N$87,MATCH(I99,'Logic Tree'!$I$85:$I$87,0),MATCH(H99,'Logic Tree'!$J$84:$N$84,0))
B100: 4 | C100: TEAM | D100: POSR | E100: TEAM | F100: ='Pod Library'!E114 | G100: ='Pod Library'!F114 | H100: ='Pod Library'!G114 | I100: ='Pod Library'!H114 | J100: ='Pod Library'!I114 | K100: ='Pod Library'!J114 | L100: ='Pod Plan'!F18 | M100: =K100*L100 | N100: =M100*INDEX('Logic Tree'!$J$85:$N$87,MATCH(I100,'Logic Tree'!$I$85:$I$87,0),MATCH(H100,'Logic Tree'!$J$84:$N$84,0))
B101: 4 | C101: TEAM | D101: POSR | E101: TEAM | F101: ='Pod Library'!E115 | G101: ='Pod Library'!F115 | H101: ='Pod Library'!G115 | I101: ='Pod Library'!H115 | J101: ='Pod Library'!I115 | K101: ='Pod Library'!J115 | L101: ='Pod Plan'!F18 | M101: =K101*L101 | N101: =M101*INDEX('Logic Tree'!$J$85:$N$87,MATCH(I101,'Logic Tree'!$I$85:$I$87,0),MATCH(H101,'Logic Tree'!$J$84:$N$84,0))
...

Sheet SIT Loading
A1: SIT loading — turning fractional FTE into whole people and whole months
A2: The seat ledger is a demand model, not a roster. Regenerated for the restated two-stream, team-only design: every delivery unit is a 12-seat TEAM, 7 of them in Year 1 falling to 4 by Year 4.
A4: A. WHY YOU CANNOT ROUND THE SEAT LEDGER
B5: Approach | C5: Y1 | D5: Y2 | E5: Y3 | F5: Y4 | G5: Y5 | H5: Verdict
B6: Modelled FTE (the commercial number) | C6: 106 | D6: 85 | E6: 72.5 | F6: 64.5 | G6: 58.5
B7: Round every ledger row UP to whole heads | C7: 111 | D7: 88 | E7: 77 | F7: 69 | G7: 68 | H7: INFLATES Year 1 by 16 people — 15%. 242 ledger rows each round up by up to 0.99 of a person.
B8: Round every ledger row to nearest | C8: 108 | D8: 85 | E8: 74 | F8: 64 | G8: 60 | H8: Total is roughly right but every individual line is wrong, and the FTC / FTE / MGCC split drifts. It also implies each pod has its own dedicated architect, tester and support engineer.
B9: This sheet — aggregate first, then whole people and months | C9: 106 | D9: 85 | E9: 72.5 | F9: 64.5 | G9: 58.5 | H9: Exact on total, on each sourcing type and on person-months.
A11: B. THE RULE
B12: Aggregate the ledger to the level at which a person is actually hired — year x role x band x location x sourcing — and only then convert to bodies. A pod seat of 0.23 is not a person; the same role summed across six pods is.
B13: Treatment | C13: When it applies | D13: How SIT loads it | E13: Example
B14: RAMPED | C14: Delivery roles — engineers, testers, analysts inside pods and teams. The work is divisible over time and people join and leave pods. | G14: floor(FTE) people for 12 months, plus one person for the remaining months. | J14: 7.73 FTE = 7 people all year + 1 person for 8.7 months
B15: SHARED | C15: Roles that need continuous presence — leads, architects, service delivery managers, PMO — and any line below 0.5 FTE. | G15: One person at a partial allocation for the whole year, the balance of their time on another domain. | J15: 0.95 FTE = 1 Chief Architect at 95%, 5% elsewhere
B16: Both give identical person-months. Neither loads a partial person into a month and neither allocates anybody above 100%. Person-months is the invariant SIT must reproduce: FTE x 12.
A18: C. RECONCILIATION — what SIT must tie back to
B19: Measure | C19: Y1 | D19: Y2 | E19: Y3 | F19: Y4 | G19: Y5 | H19: Note
B20: Modelled FTE | C20: 106 | D20: 85 | E20: 72.5 | F20: 64.5 | G20: 58.5 | H20: From the seat ledger. This is the commercial number and it does not change.
B21: Person-months = FTE x 12 | C21: 1272 | D21: 1020 | E21: 870 | F21: 774 | G21: 702 | H21: THE INVARIANT. SIT's monthly loading must sum to this.
B22: Bodies to requisition | C22: 111 | D22: 88 | E22: 77 | F22: 69 | G22: 68 | H22: Named people. Higher than FTE because some are part-year or part-allocated.
B23: — of which full-time, all year | C23: 101 | D23: 82 | E23: 68 | F23: 60 | G23: 49 | H23: The core roster. Everything else is a partial assignment.
B24: Average allocation across all bodies | C24: 0.955 | D24: 0.9659 | E24: 0.9416 | F24: 0.9348 | G24: 0.8603 | H24: If this drops below about 70% the pod design is too fragmented — check it.
A26: D. THE REQUISITION PLAN — load these lines into SIT
B27: Year | C27: Sourcing | D27: Role | E27: Band | F27: Location | G27: Unit type | H27: Modelled FTE | I27: Person-months | J27: Treatment | K27: Full-time heads | L27: +1 head for (months) | M27: Allocation of the part head
B28: 1 | C28: FTC | D28: BSA | E28: E3 | F28: ON | G28: Delivery | H28: 7 | I28: 84 | J28: RAMPED | K28: 7
B29: 1 | C29: FTC | D29: DEV | E29: E2 | F29: OFF | G29: Delivery | H29: 3.5 | I29: 42 | J29: RAMPED | K29: 3 | L29: 6
B30: 1 | C30: FTC | D30: DEV | E30: E2 | F30: ON | G30: Delivery | H30: 8.5 | I30: 102 | J30: RAMPED | K30: 8 | L30: 6
B31: 1 | C31: FTC | D31: DEV | E31: E3 | F31: ON | G31: Delivery | H31: 13.5 | I31: 162 | J31: RAMPED | K31: 13 | L31: 6
B32: 1 | C32: FTC | D32: DEV | E32: E4 | F32: ON | G32: Delivery | H32: 7 | I32: 84 | J32: RAMPED | K32: 7
B33: 1 | C33: FTC | D33: MNT | E33: E2 | F33: OFF | G33: Delivery | H33: 2 | I33: 24 | J33: RAMPED | K33: 2
B34: 1 | C34: FTC | D34: MNT | E34: E2 | F34: ON | G34: Delivery | H34: 1.5 | I34: 18 | J34: RAMPED | K34: 1 | L34: 6
B35: 1 | C35: FTC | D35: MNT | E35: E3 | F35: ON | G35: Horizontal | H35: 1 | I35: 12 | J35: SHARED | K35: 1
B36: 1 | C36: FTC | D36: OTH | E36: E3 | F36: OFF | G36: Horizontal | H36: 1 | I36: 12 | J36: SHARED | K36: 1
B37: 1 | C37: FTC | D37: OTH | E37: E4 | F37: ON | G37: Delivery | H37: 2 | I37: 24 | J37: SHARED | K37: 2
B38: 1 | C38: FTC | D38: OTH | E38: E5 | F38: ON | G38: Horizontal | H38: 0.5 | I38: 6 | J38: SHARED | K38: 0 | L38: 6 | M38: 0.5
B39: 1 | C39: FTC | D39: PM | E39: E5 | F39: ON | G39: Horizontal | H39: 1.5 | I39: 18 | J39: SHARED | K39: 1 | L39: 6 | M39: 0.5
B40: 1 | C40: FTC | D40: TEST | E40: E1 | F40: OFF | G40: Delivery | H40: 2 | I40: 24 | J40: RAMPED | K40: 2
B41: 1 | C41: FTC | D41: TEST | E41: E2 | F41: ON | G41: Delivery | H41: 10 | I41: 120 | J41: RAMPED | K41: 10
B42: 1 | C42: FTC | D42: TEST | E42: E4 | F42: ON | G42: Horizontal | H42: 1 | I42: 12 | J42: SHARED | K42: 1
B43: 1 | C43: FTE | D43: BSA | E43: E4 | F43: ON | G43: Delivery | H43: 4 | I43: 48 | J43: RAMPED | K43: 4
B44: 1 | C44: FTE | D44: BSA | E44: E4 | F44: ON | G44: Horizontal | H44: 1.5 | I44: 18 | J44: SHARED | K44: 1 | L44: 6 | M44: 0.5
B45: 1 | C45: FTE | D45: BSA | E45: E5 | F45: ON | G45: Horizontal | H45: 2 | I45: 24 | J45: SHARED | K45: 2
B46: 1 | C46: FTE | D46: MNT | E46: E3 | F46: ON | G46: Delivery | H46: 3 | I46: 36 | J46: RAMPED | K46: 3
B47: 1 | C47: FTE | D47: MNT | E47: E3 | F47: ON | G47: Horizontal | H47: 2 | I47: 24 | J47: SHARED | K47: 2
B48: 1 | C48: FTE | D48: PM | E48: E4 | F48: ON | G48: Delivery | H48: 7 | I48: 84 | J48: SHARED | K48: 7
B49: 1 | C49: FTE | D49: PM | E49: E4 | F49: ON | G49: Horizontal | H49: 6.5 | I49: 78 | J49: SHARED | K49: 6 | L49: 6 | M49: 0.5
B50: 1 | C50: MGCC | D50: DEV | E50: E3 | F50: OFF | G50: Delivery | H50: 6 | I50: 72 | J50: RAMPED | K50: 6
B51: 1 | C51: MGCC | D51: DEV | E51: E3 | F51: OFF | G51: Horizontal | H51: 3 | I51: 36 | J51: SHARED | K51: 3
B52: 1 | C52: MGCC | D52: TEST | E52: E2 | F52: OFF | G52: Delivery | H52: 2 | I52: 24 | J52: RAMPED | K52: 2
B53: 1 | C53: PT | D53: BSA | E53: E3 | F53: ON | G53: Delivery | H53: 1.5 | I53: 18 | J53: RAMPED | K53: 1 | L53: 6
B54: 1 | C54: PT | D54: DEV | E54: E3 | F54: ON | G54: Delivery | H54: 3.5 | I54: 42 | J54: RAMPED | K54: 3 | L54: 6
B55: 1 | C55: PT | D55: MNT | E55: E3 | F55: ON | G55: Horizontal | H55: 2 | I55: 24 | J55: SHARED | K55: 2
B56: 2 | C56: FTC | D56: BSA | E56: E3 | F56: ON | G56: Delivery | H56: 6 | I56: 72 | J56: RAMPED | K56: 6
B57: 2 | C57: FTC | D57: DEV | E57: E2 | F57: OFF | G57: Delivery | H57: 6.5 | I57: 78 | J57: RAMPED | K57: 6 | L57: 6
B58: 2 | C58: FTC | D58: DEV | E58: E2 | F58: ON | G58: Delivery | H58: 3.5 | I58: 42 | J58: RAMPED | K58: 3 | L58: 6
B59: 2 | C59: FTC | D59: DEV | E59: E3 | F59: ON | G59: Delivery | H59: 7 | I59: 84 | J59: RAMPED | K59: 7
B60: 2 | C60: FTC | D60: DEV | E60: E4 | F60: ON | G60: Delivery | H60: 6 | I60: 72 | J60: RAMPED | K60: 6
B61: 2 | C61: FTC | D61: MNT | E61: E2 | F61: OFF | G61: Delivery | H61: 2 | I61: 24 | J61: RAMPED | K61: 2
B62: 2 | C62: FTC | D62: MNT | E62: E2 | F62: ON | G62: Delivery | H62: 1 | I62: 12 | J62: RAMPED | K62: 1
B63: 2 | C63: FTC | D63: MNT | E63: E3 | F63: ON | G63: Horizontal | H63: 1 | I63: 12 | J63: SHARED | K63: 1
B64: 2 | C64: FTC | D64: OTH | E64: E3 | F64: OFF | G64: Horizontal | H64: 1 | I64: 12 | J64: SHARED | K64: 1
B65: 2 | C65: FTC | D65: OTH | E65: E4 | F65: ON | G65: Delivery | H65: 2 | I65: 24 | J65: SHARED | K65: 2
B66: 2 | C66: FTC | D66: OTH | E66: E5 | F66: ON | G66: Horizontal | H66: 0.5 | I66: 6 | J66: SHARED | K66: 0 | L66: 6 | M66: 0.5
B67: 2 | C67: FTC | D67: PM | E67: E5 | F67: ON | G67: Horizontal | H67: 1 | I67: 12 | J67: SHARED | K67: 1
B68: 2 | C68: FTC | D68: TEST | E68: E1 | F68: OFF | G68: Delivery | H68: 3 | I68: 36 | J68: RAMPED | K68: 3
B69: 2 | C69: FTC | D69: TEST | E69: E2 | F69: ON | G69: Delivery | H69: 3 | I69: 36 | J69: RAMPED | K69: 3
B70: 2 | C70: FTC | D70: TEST | E70: E4 | F70: ON | G70: Horizontal | H70: 0.5 | I70: 6 | J70: SHARED | K70: 0 | L70: 6 | M70: 0.5
B71: 2 | C71: FTE | D71: BSA | E71: E4 | F71: ON | G71: Delivery | H71: 6 | I71: 72 | J71: RAMPED | K71: 6
B72: 2 | C72: FTE | D72: BSA | E72: E4 | F72: ON | G72: Horizontal | H72: 1 | I72: 12 | J72: SHARED | K72: 1
B73: 2 | C73: FTE | D73: BSA | E73: E5 | F73: ON | G73: Horizontal | H73: 1.5 | I73: 18 | J73: SHARED | K73: 1 | L73: 6 | M73: 0.5
B74: 2 | C74: FTE | D74: MNT | E74: E3 | F74: ON | G74: Delivery | H74: 3 | I74: 36 | J74: RAMPED | K74: 3
B75: 2 | C75: FTE | D75: MNT | E75: E3 | F75: ON | G75: Horizontal | H75: 1 | I75: 12 | J75: SHARED | K75: 1
B76: 2 | C76: FTE | D76: PM | E76: E4 | F76: ON | G76: Delivery | H76: 7 | I76: 84 | J76: SHARED | K76: 7
B77: 2 | C77: FTE | D77: PM | E77: E4 | F77: ON | G77: Horizontal | H77: 1.5 | I77: 18 | J77: SHARED | K77: 1 | L77: 6 | M77: 0.5
B78: 2 | C78: MGCC | D78: DEV | E78: E3 | F78: OFF | G78: Delivery | H78: 8 | I78: 96 | J78: RAMPED | K78: 8
B79: 2 | C79: MGCC | D79: DEV | E79: E3 | F79: OFF | G79: Horizontal | H79: 2 | I79: 24 | J79: SHARED | K79: 2
B80: 2 | C80: MGCC | D80: MNT | E80: E2 | F80: OFF | G80: Delivery | H80: 1 | I80: 12 | J80: RAMPED | K80: 1
B81: 2 | C81: MGCC | D81: TEST | E81: E2 | F81: OFF | G81: Delivery | H81: 2 | I81: 24 | J81: RAMPED | K81: 2
B82: 2 | C82: PT | D82: BSA | E82: E3 | F82: ON | G82: Delivery | H82: 1 | I82: 12 | J82: RAMPED | K82: 1
B83: 2 | C83: PT | D83: DEV | E83: E3 | F83: ON | G83: Delivery | H83: 4 | I83: 48 | J83: RAMPED | K83: 4
B84: 2 | C84: PT | D84: MNT | E84: E3 | F84: ON | G84: Horizontal | H84: 2 | I84: 24 | J84: SHARED | K84: 2
B85: 3 | C85: FTC | D85: BSA | E85: E3 | F85: ON | G85: Delivery | H85: 5 | I85: 60 | J85: RAMPED | K85: 5
B86: 3 | C86: FTC | D86: DEV | E86: E2 | F86: OFF | G86: Delivery | H86: 6 | I86: 72 | J86: RAMPED | K86: 6
B87: 3 | C87: FTC | D87: DEV | E87: E2 | F87: ON | G87: Delivery | H87: 0.5 | I87: 6 | J87: RAMPED | K87: 0 | L87: 6
B88: 3 | C88: FTC | D88: DEV | E88: E3 | F88: OFF | G88: Delivery | H88: 1.5 | I88: 18 | J88: RAMPED | K88: 1 | L88: 6
B89: 3 | C89: FTC | D89: DEV | E89: E3 | F89: ON | G89: Delivery | H89: 5 | I89: 60 | J89: RAMPED | K89: 5
B90: 3 | C90: FTC | D90: DEV | E90: E4 | F90: ON | G90: Delivery | H90: 5 | I90: 60 | J90: RAMPED | K90: 5
B91: 3 | C91: FTC | D91: MNT | E91: E2 | F91: OFF | G91: Delivery | H91: 1.5 | I91: 18 | J91: RAMPED | K91: 1 | L91: 6
B92: 3 | C92: FTC | D92: MNT | E92: E2 | F92: ON | G92: Delivery | H92: 1 | I92: 12 | J92: RAMPED | K92: 1
B93: 3 | C93: FTC | D93: OTH | E93: E3 | F93: OFF | G93: Horizontal | H93: 0.5 | I93: 6 | J93: SHARED | K93: 0 | L93: 6 | M93: 0.5
B94: 3 | C94: FTC | D94: OTH | E94: E4 | F94: ON | G94: Delivery | H94: 1.5 | I94: 18 | J94: SHARED | K94: 1 | L94: 6 | M94: 0.5
B95: 3 | C95: FTC | D95: OTH | E95: E5 | F95: ON | G95: Horizontal | H95: 0.5 | I95: 6 | J95: SHARED | K95: 0 | L95: 6 | M95: 0.5
B96: 3 | C96: FTC | D96: PM | E96: E5 | F96: ON | G96: Horizontal | H96: 1 | I96: 12 | J96: SHARED | K96: 1
B97: 3 | C97: FTC | D97: TEST | E97: E1 | F97: OFF | G97: Delivery | H97: 4 | I97: 48 | J97: RAMPED | K97: 4
B98: 3 | C98: FTC | D98: TEST | E98: E2 | F98: ON | G98: Delivery | H98: 1 | I98: 12 | J98: RAMPED | K98: 1
B99: 3 | C99: FTE | D99: BSA | E99: E4 | F99: ON | G99: Delivery | H99: 3 | I99: 36 | J99: RAMPED | K99: 3
B100: 3 | C100: FTE | D100: BSA | E100: E4 | F100: ON | G100: Horizontal | H100: 1.5 | I100: 18 | J100: SHARED | K100: 1 | L100: 6 | M100: 0.5
B101: 3 | C101: FTE | D101: BSA | E101: E5 | F101: ON | G101: Horizontal | H101: 1.5 | I101: 18 | J101: SHARED | K101: 1 | L101: 6 | M101: 0.5
B102: 3 | C102: FTE | D102: MNT | E102: E3 | F102: ON | G102: Delivery | H102: 2 | I102: 24 | J102: RAMPED | K102: 2
B103: 3 | C103: FTE | D103: MNT | E103: E3 | F103: ON | G103: Horizontal | H103: 2 | I103: 24 | J103: SHARED | K103: 2
B104: 3 | C104: FTE | D104: PM | E104: E4 | F104: ON | G104: Delivery | H104: 6 | I104: 72 | J104: SHARED | K104: 6
...

Sheet Unit Cost Sensitivity
A1: Unit cost sensitivity — four levers now, not three
A2: Productivity, offshore share and seniority, plus the agile conversion, which which the other three all depend on.
A4: A. THE MODEL — unit cost = k x (1 - productivity) x average cost per head
B5: average cost per head = offshore x [senior x OFF_SR + (1-senior) x OFF_JM] + onshore x [senior x ON_SR + (1-senior) x ON_JM]
A7: B. TIER COST PARAMETERS — from the Year-5 roster
B8: Tier | C8: Onshore Tokyo | D8: Offshore
B9: Junior / mid (E1-E3) | C9: =IFERROR((SUMIFS('Seat Ledger'!$N$5:$N$235,'Seat Ledger'!$B$5:$B$235,5,'Seat Ledger'!$I$5:$I$235,"ON",'Seat Ledger'!$H$5:$H$235,"E1") + SUMIFS('Seat Ledger'!$N$5:$N$235,'Seat Ledger'!$B$5:$B$235,5,'Seat Ledger'!$I$5:$I$235,"ON",'Seat Ledger'!$H$5:$H$235,"E2") + SUMIFS('Seat Ledger'!$N$5:$N$235,'Seat Ledger'!$B$5:$B$235,5,'Seat Ledger'!$I$5:$I$235,"ON",'Seat Ledger'!$H$5:$H$235,"E3"))/(SUMIFS('Seat Ledger'!$M$5:$M$235,'Seat Ledger'!$B$5:$B$235,5,'Seat Ledger'!$I$5:$I$235,"ON",'Seat Ledger'!$H$5:$H$235,"E1") + SUMIFS('Seat Ledger'!$M$5:$M$235,'Seat Ledger'!$B$5:$B$235,5,'Seat Ledger'!$I$5:$I$235,"ON",'Seat Ledger'!$H$5:$H$235,"E2") + SUMIFS('Seat Ledger'!$M$5:$M$235,'Seat Ledger'!$B$5:$B$235,5,'Seat Ledger'!$I$5:$I$235,"ON",'Seat Ledger'!$H$5:$H$235,"E3")),0) | D9: =IFERROR((SUMIFS('Seat Ledger'!$N$5:$N$235,'Seat Ledger'!$B$5:$B$235,5,'Seat Ledger'!$I$5:$I$235,"OFF",'Seat Ledger'!$H$5:$H$235,"E1") + SUMIFS('Seat Ledger'!$N$5:$N$235,'Seat Ledger'!$B$5:$B$235,5,'Seat Ledger'!$I$5:$I$235,"OFF",'Seat Ledger'!$H$5:$H$235,"E2") + SUMIFS('Seat Ledger'!$N$5:$N$235,'Seat Ledger'!$B$5:$B$235,5,'Seat Ledger'!$I$5:$I$235,"OFF",'Seat Ledger'!$H$5:$H$235,"E3"))/(SUMIFS('Seat Ledger'!$M$5:$M$235,'Seat Ledger'!$B$5:$B$235,5,'Seat Ledger'!$I$5:$I$235,"OFF",'Seat Ledger'!$H$5:$H$235,"E1") + SUMIFS('Seat Ledger'!$M$5:$M$235,'Seat Ledger'!$B$5:$B$235,5,'Seat Ledger'!$I$5:$I$235,"OFF",'Seat Ledger'!$H$5:$H$235,"E2") + SUMIFS('Seat Ledger'!$M$5:$M$235,'Seat Ledger'!$B$5:$B$235,5,'Seat Ledger'!$I$5:$I$235,"OFF",'Seat Ledger'!$H$5:$H$235,"E3")),0)
B10: Senior (E4-E5) | C10: =IFERROR((SUMIFS('Seat Ledger'!$N$5:$N$235,'Seat Ledger'!$B$5:$B$235,5,'Seat Ledger'!$I$5:$I$235,"ON",'Seat Ledger'!$H$5:$H$235,"E4") + SUMIFS('Seat Ledger'!$N$5:$N$235,'Seat Ledger'!$B$5:$B$235,5,'Seat Ledger'!$I$5:$I$235,"ON",'Seat Ledger'!$H$5:$H$235,"E5"))/(SUMIFS('Seat Ledger'!$M$5:$M$235,'Seat Ledger'!$B$5:$B$235,5,'Seat Ledger'!$I$5:$I$235,"ON",'Seat Ledger'!$H$5:$H$235,"E4") + SUMIFS('Seat Ledger'!$M$5:$M$235,'Seat Ledger'!$B$5:$B$235,5,'Seat Ledger'!$I$5:$I$235,"ON",'Seat Ledger'!$H$5:$H$235,"E5")),0) | D10: =IFERROR((SUMIFS('Seat Ledger'!$N$5:$N$235,'Seat Ledger'!$B$5:$B$235,5,'Seat Ledger'!$I$5:$I$235,"OFF",'Seat Ledger'!$H$5:$H$235,"E4") + SUMIFS('Seat Ledger'!$N$5:$N$235,'Seat Ledger'!$B$5:$B$235,5,'Seat Ledger'!$I$5:$I$235,"OFF",'Seat Ledger'!$H$5:$H$235,"E5"))/(SUMIFS('Seat Ledger'!$M$5:$M$235,'Seat Ledger'!$B$5:$B$235,5,'Seat Ledger'!$I$5:$I$235,"OFF",'Seat Ledger'!$H$5:$H$235,"E4") + SUMIFS('Seat Ledger'!$M$5:$M$235,'Seat Ledger'!$B$5:$B$235,5,'Seat Ledger'!$I$5:$I$235,"OFF",'Seat Ledger'!$H$5:$H$235,"E5")),0)
A12: C. BASE CASE
B13: Measure | C13: Year 1 | D13: Year 2 | E13: Year 3 | F13: Year 4 | G13: Year 5
B14: Delivered productivity | C14: ='Glidepath & 50-50'!C25 | D14: ='Glidepath & 50-50'!D25 | E14: ='Glidepath & 50-50'!E25 | F14: ='Glidepath & 50-50'!F25 | G14: ='Glidepath & 50-50'!G25
B15: Whole-team offshore share | C15: ='Team Build-Up'!C54 | D15: ='Team Build-Up'!D54 | E15: ='Team Build-Up'!E54 | F15: ='Team Build-Up'!F54 | G15: ='Team Build-Up'!G54
B16: Senior share (E4+E5) | C16: ='Team Build-Up'!C76 | D16: ='Team Build-Up'!D76 | E16: ='Team Build-Up'!E76 | F16: ='Team Build-Up'!F76 | G16: ='Team Build-Up'!G76
B17: Agile share | C17: ='Delivery Mode'!C18 | D17: ='Delivery Mode'!D18 | E17: ='Delivery Mode'!E18 | F17: ='Delivery Mode'!F18 | G17: ='Delivery Mode'!G18
B18: Unit cost index — actual | C18: ='Cost & Commercial'!C9 | D18: ='Cost & Commercial'!D9 | E18: ='Cost & Commercial'!E9 | F18: ='Cost & Commercial'!F9 | G18: ='Cost & Commercial'!G9
B19: Unit cost index — two-tier formula | C19: =(1-C14)*(C15*(C16*$D$10+(1-C16)*$D$9)+(1-C15)*(C16*$C$10+(1-C16)*$C$9)) | D19: =(1-D14)*(D15*(D16*$D$10+(1-D16)*$D$9)+(1-D15)*(D16*$C$10+(1-D16)*$C$9)) | E19: =(1-E14)*(E15*(E16*$D$10+(1-E16)*$D$9)+(1-E15)*(E16*$C$10+(1-E16)*$C$9)) | F19: =(1-F14)*(F15*(F16*$D$10+(1-F16)*$D$9)+(1-F15)*(F16*$C$10+(1-F16)*$C$9)) | G19: =(1-G14)*(G15*(G16*$D$10+(1-G16)*$D$9)+(1-G15)*(G16*$C$10+(1-G16)*$C$9))
B20: CALIBRATION k = actual / formula, at Year 5 | G20: =IF(G19=0,1,G18/G19)
A22: D. GRID — offshore share x productivity, at the Year-5 senior share
B23: Offshore v Productivity > | C23: 0.35 | D23: 0.4 | E23: 0.45 | F23: 0.5 | G23: 0.55 | H23: 0.6
B24: 0.45 | C24: =$G$20*(1-C$23)*($B24*($G$16*$D$10+(1-$G$16)*$D$9)+(1-$B24)*($G$16*$C$10+(1-$G$16)*$C$9)) | D24: =$G$20*(1-D$23)*($B24*($G$16*$D$10+(1-$G$16)*$D$9)+(1-$B24)*($G$16*$C$10+(1-$G$16)*$C$9)) | E24: =$G$20*(1-E$23)*($B24*($G$16*$D$10+(1-$G$16)*$D$9)+(1-$B24)*($G$16*$C$10+(1-$G$16)*$C$9)) | F24: =$G$20*(1-F$23)*($B24*($G$16*$D$10+(1-$G$16)*$D$9)+(1-$B24)*($G$16*$C$10+(1-$G$16)*$C$9)) | G24: =$G$20*(1-G$23)*($B24*($G$16*$D$10+(1-$G$16)*$D$9)+(1-$B24)*($G$16*$C$10+(1-$G$16)*$C$9)) | H24: =$G$20*(1-H$23)*($B24*($G$16*$D$10+(1-$G$16)*$D$9)+(1-$B24)*($G$16*$C$10+(1-$G$16)*$C$9))
B25: 0.55 | C25: =$G$20*(1-C$23)*($B25*($G$16*$D$10+(1-$G$16)*$D$9)+(1-$B25)*($G$16*$C$10+(1-$G$16)*$C$9)) | D25: =$G$20*(1-D$23)*($B25*($G$16*$D$10+(1-$G$16)*$D$9)+(1-$B25)*($G$16*$C$10+(1-$G$16)*$C$9)) | E25: =$G$20*(1-E$23)*($B25*($G$16*$D$10+(1-$G$16)*$D$9)+(1-$B25)*($G$16*$C$10+(1-$G$16)*$C$9)) | F25: =$G$20*(1-F$23)*($B25*($G$16*$D$10+(1-$G$16)*$D$9)+(1-$B25)*($G$16*$C$10+(1-$G$16)*$C$9)) | G25: =$G$20*(1-G$23)*($B25*($G$16*$D$10+(1-$G$16)*$D$9)+(1-$B25)*($G$16*$C$10+(1-$G$16)*$C$9)) | H25: =$G$20*(1-H$23)*($B25*($G$16*$D$10+(1-$G$16)*$D$9)+(1-$B25)*($G$16*$C$10+(1-$G$16)*$C$9))
B26: 0.65 | C26: =$G$20*(1-C$23)*($B26*($G$16*$D$10+(1-$G$16)*$D$9)+(1-$B26)*($G$16*$C$10+(1-$G$16)*$C$9)) | D26: =$G$20*(1-D$23)*($B26*($G$16*$D$10+(1-$G$16)*$D$9)+(1-$B26)*($G$16*$C$10+(1-$G$16)*$C$9)) | E26: =$G$20*(1-E$23)*($B26*($G$16*$D$10+(1-$G$16)*$D$9)+(1-$B26)*($G$16*$C$10+(1-$G$16)*$C$9)) | F26: =$G$20*(1-F$23)*($B26*($G$16*$D$10+(1-$G$16)*$D$9)+(1-$B26)*($G$16*$C$10+(1-$G$16)*$C$9)) | G26: =$G$20*(1-G$23)*($B26*($G$16*$D$10+(1-$G$16)*$D$9)+(1-$B26)*($G$16*$C$10+(1-$G$16)*$C$9)) | H26: =$G$20*(1-H$23)*($B26*($G$16*$D$10+(1-$G$16)*$D$9)+(1-$B26)*($G$16*$C$10+(1-$G$16)*$C$9))
B27: 0.75 | C27: =$G$20*(1-C$23)*($B27*($G$16*$D$10+(1-$G$16)*$D$9)+(1-$B27)*($G$16*$C$10+(1-$G$16)*$C$9)) | D27: =$G$20*(1-D$23)*($B27*($G$16*$D$10+(1-$G$16)*$D$9)+(1-$B27)*($G$16*$C$10+(1-$G$16)*$C$9)) | E27: =$G$20*(1-E$23)*($B27*($G$16*$D$10+(1-$G$16)*$D$9)+(1-$B27)*($G$16*$C$10+(1-$G$16)*$C$9)) | F27: =$G$20*(1-F$23)*($B27*($G$16*$D$10+(1-$G$16)*$D$9)+(1-$B27)*($G$16*$C$10+(1-$G$16)*$C$9)) | G27: =$G$20*(1-G$23)*($B27*($G$16*$D$10+(1-$G$16)*$D$9)+(1-$B27)*($G$16*$C$10+(1-$G$16)*$C$9)) | H27: =$G$20*(1-H$23)*($B27*($G$16*$D$10+(1-$G$16)*$D$9)+(1-$B27)*($G$16*$C$10+(1-$G$16)*$C$9))
B28: 0.85 | C28: =$G$20*(1-C$23)*($B28*($G$16*$D$10+(1-$G$16)*$D$9)+(1-$B28)*($G$16*$C$10+(1-$G$16)*$C$9)) | D28: =$G$20*(1-D$23)*($B28*($G$16*$D$10+(1-$G$16)*$D$9)+(1-$B28)*($G$16*$C$10+(1-$G$16)*$C$9)) | E28: =$G$20*(1-E$23)*($B28*($G$16*$D$10+(1-$G$16)*$D$9)+(1-$B28)*($G$16*$C$10+(1-$G$16)*$C$9)) | F28: =$G$20*(1-F$23)*($B28*($G$16*$D$10+(1-$G$16)*$D$9)+(1-$B28)*($G$16*$C$10+(1-$G$16)*$C$9)) | G28: =$G$20*(1-G$23)*($B28*($G$16*$D$10+(1-$G$16)*$D$9)+(1-$B28)*($G$16*$C$10+(1-$G$16)*$C$9)) | H28: =$G$20*(1-H$23)*($B28*($G$16*$D$10+(1-$G$16)*$D$9)+(1-$B28)*($G$16*$C$10+(1-$G$16)*$C$9))
A30: E. TORNADO — one lever at a time, +/- 10 points from the Year-5 base
B31: Lever | C31: -10 points | D31: Base | E31: +10 points | F31: Swing | G31: Reading
B32: Productivity | C32: =$G$20*(1-($G$14-0.1))*(($G$15)*(($G$16)*$D$10+(1-($G$16))*$D$9)+(1-($G$15))*(($G$16)*$C$10+(1-($G$16))*$C$9)) | D32: =$G$20*(1-($G$14))*(($G$15)*(($G$16)*$D$10+(1-($G$16))*$D$9)+(1-($G$15))*(($G$16)*$C$10+(1-($G$16))*$C$9)) | E32: =$G$20*(1-($G$14+0.1))*(($G$15)*(($G$16)*$D$10+(1-($G$16))*$D$9)+(1-($G$15))*(($G$16)*$C$10+(1-($G$16))*$C$9)) | F32: =ABS(E32-C32) | G32: Scales unit cost one for one. The only linear lever.
B33: Offshore share | C33: =$G$20*(1-($G$14))*(($G$15-0.1)*(($G$16)*$D$10+(1-($G$16))*$D$9)+(1-($G$15-0.1))*(($G$16)*$C$10+(1-($G$16))*$C$9)) | D33: =$G$20*(1-($G$14))*(($G$15)*(($G$16)*$D$10+(1-($G$16))*$D$9)+(1-($G$15))*(($G$16)*$C$10+(1-($G$16))*$C$9)) | E33: =$G$20*(1-($G$14))*(($G$15+0.1)*(($G$16)*$D$10+(1-($G$16))*$D$9)+(1-($G$15+0.1))*(($G$16)*$C$10+(1-($G$16))*$C$9)) | F33: =ABS(E33-C33) | G33: Second largest — and now bounded by a measured start rather than an assumed one.
B34: Senior share | C34: =$G$20*(1-($G$14))*(($G$15)*(($G$16-0.1)*$D$10+(1-($G$16-0.1))*$D$9)+(1-($G$15))*(($G$16-0.1)*$C$10+(1-($G$16-0.1))*$C$9)) | D34: =$G$20*(1-($G$14))*(($G$15)*(($G$16)*$D$10+(1-($G$16))*$D$9)+(1-($G$15))*(($G$16)*$C$10+(1-($G$16))*$C$9)) | E34: =$G$20*(1-($G$14))*(($G$15)*(($G$16+0.1)*$D$10+(1-($G$16+0.1))*$D$9)+(1-($G$15))*(($G$16+0.1)*$C$10+(1-($G$16+0.1))*$C$9)) | F34: =ABS(E34-C34) | G34: Works against the other two. A richer shape gives back part of what offshore wins.
B35: Agile conversion — the fourth lever | G35: Not a direct term in the unit-cost formula. It works through productivity: the operating-model component is scaled by the agile share, so a one-year slip in the conversion costs about 5 points of Year-2 capability and roughly 0.05 of the unit cost index. It is the lever with the longest lead time and the least evidence behind it.
B37: Swings are full 20-point ranges. Halve them for a per-ten-point read.
