Workbook

Sheet README
A1: MetLife Japan | Fee Management — Operating Model & Pricing Engine
A2: INTERNAL — Capgemini review copy. Not for issue to MetLife. Domain filtered from Appendix 3 v2 (142 apps / 1,504.0 units); this domain is 5 apps / 48.5 units.
A4: HOW THIS WORKBOOK IS BUILT
B5: Direction of travel | C5: Everything is bottom-up. You define seats in pods; the workbook derives headcount, productivity, offshore share, experience mix and cost. Nothing is asserted.
B6: The two logic trees | C6: 'Logic Tree' derives a TARGET productivity and offshore % for any domain from its archetype mix. 'Glidepath & 50-50' compares that target against what the pod design actually delivers. The gap is the transition & enablement drag.
B7: Re-using for another domain | C7: Change the domain on 'Logic Tree' cell C5. The archetype mix, effort base and target percentages re-derive from 'Inventory'. The pod library and pod plan must then be re-cut for that domain's value streams.
A8: CELL COLOUR CONVENTION
B9: Blue text | C9: Input. Change these.
B10: Black text | C10: Formula. Do not overwrite.
B11: Green text | C11: Link to another sheet in this workbook.
B12: Amber fill | C12: Key assumption requiring sign-off before this model is used to price.
A13: SHEET MAP
B14: Logic Tree | C14: Parametric drivers. Phase effort mix, AI-addressable ceiling per archetype, realisation curve, offshore ceiling, re-badge plan, cost index.
B15: Inventory | C15: All 142 applications with derived archetype. Filter to a domain to see its mix.
B16: Value Streams | C16: The three functional value streams inside Fee Management and the AD / AMS split of each.
B17: Pod Library | C17: INPUT. Every seat in every pod archetype, for Y1 / Y2 / Y3. Role, skill family, experience band, location, sourcing.
B18: Pod Plan | C18: INPUT. How many co-sourced and fully-sourced pods each value stream runs in each year.
B19: Horizontal Teams | C19: INPUT. Seats in the three cross-cutting teams that are not value-stream bounded.
B20: Seat Ledger | C20: Computed. Every pod-library line multiplied out by the pod plan, plus the horizontal seats. All roll-ups read from here.
B21: Team Build-Up | C21: Computed. Headcount by year, by value stream, by sourcing, by location, by experience band and by skill family.
B22: Glidepath & 50-50 | C22: Computed. Productivity target vs delivered, offshore target vs delivered, and the re-badge volume needed to reach 50:50.
B23: Cost & Commercial | C23: Computed. Cost index, cost per unit of original scope, and the Capgemini billable position after re-badging.
A24: ASSUMPTIONS THAT NEED SIGN-OFF
B25: Cost index | C25: Relative only. Onshore Tokyo E2 = 1.00, offshore at roughly one third at like-for-like band. Replace with the approved rate card before pricing.
B26: AI-addressable ceilings | C26: Derived from published evidence, not from a Capgemini delivery baseline. See the sources block on the Logic Tree sheet.
B27: Re-badge feasibility | C27: Assumes transfer of employment (転籍) is achievable with individual consent and that MetLife will accept the receiving cost base. Not tested.
B28: Effort unit = one person | C28: Appendix 3 states effort in FTE-equivalents. One unit is treated as one seat throughout.
B30: Built | C30: September 2026 · Capgemini · Fee Management domain model v1

Sheet Logic Tree
A1: Logic Tree — parametric drivers for productivity and offshore share
A2: Change the blue cells. Every downstream number re-derives. Amber cells need sign-off.
A4: A. DOMAIN SELECTION AND EFFORT BASE
B5: Domain | C5: fee management | I5: Type any domain name from the Inventory sheet, lower case.
B6: Applications in domain | C6: =SUMIFS(Inventory!$U:$U,Inventory!$E:$E,$C$5) -> 5
B7: Total effort (units) | C7: =SUMIFS(Inventory!$AD:$AD,Inventory!$E:$E,$C$5) -> 48.510292
B8: Current FTC | C8: =SUMIFS(Inventory!$AA:$AA,Inventory!$E:$E,$C$5) -> 38.147792
B9: Current FTE | C9: =SUMIFS(Inventory!$AB:$AB,Inventory!$E:$E,$C$5) -> 9.7791667
B10: Current MGCC | C10: =SUMIFS(Inventory!$AC:$AC,Inventory!$E:$E,$C$5) -> 0.58333333
B11: AD effort (%PRJ weighted) | C11: =SUMIFS(Inventory!$AF:$AF,Inventory!$E:$E,$C$5) -> 43.118625
B12: AMS effort | C12: =C7-C11 -> 5.3916667
B13: AD share of effort | C13: =IF(C7=0,0,C11/C7) -> 0.8888552
A15: B. ARCHETYPE MIX OF THE SELECTED DOMAIN — this is what drives the applicable percentages
B16: Archetype | C16: Definition | D16: Apps | E16: Effort | F16: Share of effort
B17: A | C17: Language-locked — Japanese business content bound to the application | D17: =SUMIFS(Inventory!$U:$U,Inventory!$E:$E,$C$5,Inventory!$AG:$AG,$B17) -> 2 | E17: =SUMIFS(Inventory!$AD:$AD,Inventory!$E:$E,$C$5,Inventory!$AG:$AG,$B17) -> 29.235292 | F17: =IF($C$7=0,0,E17/$C$7) -> 0.60266163
B18: B | C18: Offshore-ready — modern stack, documented, no language lock | D18: =SUMIFS(Inventory!$U:$U,Inventory!$E:$E,$C$5,Inventory!$AG:$AG,$B18) -> 3 | E18: =SUMIFS(Inventory!$AD:$AD,Inventory!$E:$E,$C$5,Inventory!$AG:$AG,$B18) -> 19.275 | F18: =IF($C$7=0,0,E18/$C$7) -> 0.39733837
B19: C | C19: MGCC-destined — flagged Priority Transfer Target | D19: =SUMIFS(Inventory!$U:$U,Inventory!$E:$E,$C$5,Inventory!$AG:$AG,$B19) -> 0 | E19: =SUMIFS(Inventory!$AD:$AD,Inventory!$E:$E,$C$5,Inventory!$AG:$AG,$B19) -> 0 | F19: =IF($C$7=0,0,E19/$C$7) -> 0
B20: D | C20: Legacy-coupled core — mainframe / AS400, COBOL / Assembler | D20: =SUMIFS(Inventory!$U:$U,Inventory!$E:$E,$C$5,Inventory!$AG:$AG,$B20) -> 0 | E20: =SUMIFS(Inventory!$AD:$AD,Inventory!$E:$E,$C$5,Inventory!$AG:$AG,$B20) -> 0 | F20: =IF($C$7=0,0,E20/$C$7) -> 0
B21: Total | D21: =SUM(D17:D20) -> 5 | E21: =SUM(E17:E20) -> 48.510292 | F21: =SUM(F17:F20) -> 1
A23: C. PRODUCTIVITY TREE — LEVEL 1 : where the effort sits across the delivery lifecycle
B24: Delivery phase | C24: Share of effort
B25: Requirements & impact analysis | C25: 0.15
B26: Design & architecture | C26: 0.1
B27: Build & code | C27: 0.3
B28: Test & quality assurance | C28: 0.25
B29: Release & deploy | C29: 0.05
B30: Run, monitor & coordinate | C30: 0.15
B31: Total (must equal 100%) | C31: =SUM(C25:C30) -> 1
A33: D. PRODUCTIVITY TREE — LEVEL 2 : how much of each phase AI can address, by archetype
B34: The ceiling if the capability were fully mature and fully adopted. Not a forecast.
B35: Delivery phase | C35: A | D35: B | E35: C | F35: D
B36: Requirements & impact analysis | C36: 0.22 | D36: 0.35 | E36: 0.35 | F36: 0.35
B37: Design & architecture | C37: 0.2 | D37: 0.3 | E37: 0.3 | F37: 0.22
B38: Build & code | C38: 0.32 | D38: 0.55 | E38: 0.5 | F38: 0.2
B39: Test & quality assurance | C39: 0.38 | D39: 0.6 | E39: 0.55 | F39: 0.4
B40: Release & deploy | C40: 0.3 | D40: 0.5 | E40: 0.45 | F40: 0.25
B41: Run, monitor & coordinate | C41: 0.3 | D41: 0.4 | E41: 0.4 | F41: 0.32
B42: Weighted AI ceiling by archetype | C42: =SUMPRODUCT($C$25:$C$30,C36:C41) -> 0.304 | D42: =SUMPRODUCT($C$25:$C$30,D36:D41) -> 0.4825 | E42: =SUMPRODUCT($C$25:$C$30,E36:E41) -> 0.4525 | F42: =SUMPRODUCT($C$25:$C$30,F36:F41) -> 0.295
B43: Applicable AI ceiling for THIS domain | C43: =IF($C$7=0,0,(C42*$E$17+D42*$E$18+E42*$E$19+F42*$E$20)/$C$7) -> 0.3749249
A46: E. PRODUCTIVITY TREE — LEVEL 3 : realisation curve, and the two non-AI components
B47: Driver | C47: Year 1 | D47: Year 2 | E47: Year 3 | F47: Basis
B48: AI realisation — share of ceiling captured | C48: 0.25 | D48: 0.55 | E48: 0.75 | F48: Adoption, guardrails and substrate maturity. Not a tool licence count.
B49: Classical ADM productivity (cumulative) | C49: 0.02 | D49: 0.05 | E49: 0.07 | F49: Standardisation, defect reduction, shift-left. Industry contractual norm 4-6% p.a.
B50: Operating-model productivity (cumulative) | C50: 0.03 | D50: 0.06 | E50: 0.08 | F50: Pod consolidation, span of control, one release train instead of many.
B52: AI-attributable productivity | C52: =$C$43*C$48 -> 0.093731225 | D52: =$C$43*D$48 -> 0.20620869 | E52: =$C$43*E$48 -> 0.28119367
B53: Gross productivity = 1 - (1-AI) x (1-classical) x (1-operating model) | C53: =1-(1-C52)*(1-C$49)*(1-C$50) -> 0.1385009 | D53: =1-(1-D52)*(1-D$49)*(1-D$50) -> 0.29114436 | E53: =1-(1-E52)*(1-E$49)*(1-E$50) -> 0.38498931
A55: F. OFFSHORE TREE
B56: Driver | C56: A | D56: B | E56: C | F56: D
B57: Offshore-able ceiling of the archetype | C57: 0.15 | D57: 0.78 | E57: 0.85 | F57: 0.58
B58: Applicable offshore ceiling for THIS domain | C58: =IF($C$7=0,0,(C57*$E$17+D57*$E$18+E57*$E$19+F57*$E$20)/$C$7) -> 0.40032317
B60: Driver | C60: Year 1 | D60: Year 2 | E60: Year 3
B61: Offshore realisation — share of ceiling reached | C61: 0.57 | D61: 0.85 | E61: 0.93
B62: Target offshore share | C62: =$C$58*C61 -> 0.22818421 | D62: =$C$58*D61 -> 0.34027469 | E62: =$C$58*E61 -> 0.37230055
A64: Set to zero pending review: the generic transfer-of-employment schedule inherited from Contract Management (0/6/9 FTE, 0/14/21 MGCC) was sized for a domain far larger than this one's Year-3 Capgemini FTC. Applied here it drives Capgemini FTC negative from Year 2 (33 -> 3 -> -37). Glidepath & 50-50 section D shows what pod-and-horizontal-design productivity alone delivers against this domain's real headcount; size a transfer here once you've reviewed it — same precedent as Corporate Related, New Contract Related and Customer Care / Call Center Related.
B65: Productivity shrinks both sides of the ratio, so it cannot move it. Transfer of employment can.
B66: Transfer in year | C66: Year 1 | D66: Year 2 | E66: Year 3
B67: Capgemini to MetLife Japan (FTE) | C67: 0 | D67: 0 | E67: 0
B68: Capgemini to MetLife MGCC Hyderabad | C68: 0 | D68: 0 | E68: 0
B69: Cumulative transferred | C69: =SUM($C$67:C68) -> 0 | D69: =SUM($C$67:D68) -> 0 | E69: =SUM($C$67:E68) -> 0
A71: H. COST INDEX — relative only, onshore Tokyo band E2 = 1.00
B72: Location | C72: E1 0-3y | D72: E2 3-6y | E72: E3 6-10y | F72: E4 10-15y | G72: E5 15y+ | I72: key | J72: E1 | K72: E2 | L72: E3 | M72: E4 | N72: E5
B73: Onshore Tokyo | C73: 0.72 | D73: 1 | E73: 1.35 | F73: 1.85 | G73: 2.55 | I73: ON | J73: =C73 -> 0.72 | K73: =D73 -> 1 | L73: =E73 -> 1.35 | M73: =F73 -> 1.85 | N73: =G73 -> 2.55
B74: Offshore Hyderabad | C74: 0.22 | D74: 0.3 | E74: 0.42 | F74: 0.6 | G74: 0.85 | I74: OFF | J74: =C74 -> 0.22 | K74: =D74 -> 0.3 | L74: =E74 -> 0.42 | M74: =F74 -> 0.6 | N74: =G74 -> 0.85
I75: Lookup keys for the Seat Ledger. Do not edit — mirrors the block on the left.
A76: I. EVIDENCE BASE FOR THE AI CEILINGS
B77: • | C77: Bain Technology Report 2025 — team-level productivity gain from AI coding assistants 10-15%, materially below task-level results.
B78: • | C78: Randomised field experiment, 4,867 developers at Microsoft, Accenture and a Fortune 100 firm — 26.1% increase in completed tasks.
B79: • | C79: METR randomised controlled trial 2025 — experienced developers were 19% SLOWER with AI on large unfamiliar codebases. This is why archetype D build is capped at 20%.
B80: • | C80: DORA State of AI-assisted Software Development 2025 — AI improves throughput but degrades stability without automated testing and fast feedback. Drives the QE horizontal.
B81: • | C81: Keyhole Software COBOL to Spring Batch migration — 20-30% acceleration on a bounded legacy scope.
B82: • | C82: Deloitte 2026 Software Industry Outlook — 30-35% projected across the SDLC. A projection, not a measurement.
B83: • | C83: MSP AI benchmarks 2026 — 20-40% MTTR reduction on tier-one categories, 15-25% technician throughput. Drives the run and support ceilings.

Sheet Inventory
A1: Application inventory — Appendix 3 v2, with derived archetype and value stream
A2: Archetype is DERIVED, not asserted: mainframe language → D; else Priority Transfer Target → C; else SaaS → A; else B.
A4: # | B4: EAI ID | C4: Application | D4: Long name | E4: Domain | F4: Group | G4: Team | H4: Class | I4: Critical | J4: Hosting | K4: Primary code language | L4: Cloud platform | M4: Priority transfer | N4: Current FTC | O4: Current FTE | P4: Current MGCC | Q4: Total | R4: % of PRJ | S4: Target FTC | T4: Target FTE/MGCC | U4: App count | AA4: FTC | AB4: FTE | AC4: MGCC | AD4: Effort | AE4: AD share | AF4: AD effort | AG4: Archetype | AH4: Value stream
A5: 1 | B5: 9629 | C5: Global Sales Comp - Japan | D5: Global Sales Comp - Japan | E5: fee management | F5: Core Insurance Systems Group 34956 | G5: Commission Systems Team 34958 | H5: Core Business Application | I5: N | J5: Yes | K5: Other#Infomatica workflow Bash shell Dos batch | L5: Software as a Service (SaaS) | M5: N | N5: 0 | O5: 0 | P5: 0 | Q5: 0 | R5: 0 | U5: 1 | AA5: =N5 -> 0 | AB5: =O5 -> 0 | AC5: =P5 -> 0 | AD5: =Q5 -> 0 | AE5: =R5 -> 0 | AF5: =Q5*R5 -> 0 | AG5: A | AH5: VS1
A6: 2 | B6: 9796 | C6: LC POSPMC MF-JPN | D6: LifeComm POSPMC | E6: contract management | F6: Core Insurance Systems Group 34956 | G6: Policy Admin Systems Team 34957 | H6: Core Business Application | I6: Y | J6: Yes | K6: Assembler, COBOL, MU(EASYPLUS), JCL | M6: N | N6: 59.558958 | O6: 7.7541667 | P6: 0 | Q6: 67.313125 | R6: 0.71176374 | S6: 33.656562 | T6: 33.656562 | U6: 1 | AA6: =N6 -> 59.558958 | AB6: =O6 -> 7.7541667 | AC6: =P6 -> 0 | AD6: =Q6 -> 67.313125 | AE6: =R6 -> 0.71176374 | AF6: =Q6*R6 -> 47.911042 | AG6: D | AH6: VS1
A7: 3 | B7: 9800 | C7: LC Billing MF-JPN | D7: LifeComm Billing | E7: contract management | F7: Core Insurance Systems Group 34956 | G7: Policy Admin Systems Team 34957 | H7: Core Business Application | I7: Y | J7: Yes | K7: COBOL, Assembler, MU(EASYPLUS), JCL | M7: N | N7: 20.892167 | O7: 1.85375 | P7: 0 | Q7: 22.745917 | R7: 0.94285788 | S7: 11.372958 | T7: 11.372958 | U7: 1 | AA7: =N7 -> 20.892167 | AB7: =O7 -> 1.85375 | AC7: =P7 -> 0 | AD7: =Q7 -> 22.745917 | AE7: =R7 -> 0.94285788 | AF7: =Q7*R7 -> 21.446167 | AG7: D | AH7: VS2
A8: 4 | B8: 9801 | C8: LC Collection MF-JPN | D8: LifeComm Collection | E8: contract management | F8: Core Insurance Systems Group 34956 | G8: Policy Admin Systems Team 34957 | H8: Core Business Application | I8: Y | J8: Yes | K8: COBOL, Assembler, MU(EASYPLUS), JCL | M8: N | N8: 0 | O8: 0 | P8: 0 | Q8: 0 | R8: 0 | U8: 1 | AA8: =N8 -> 0 | AB8: =O8 -> 0 | AC8: =P8 -> 0 | AD8: =Q8 -> 0 | AE8: =R8 -> 0 | AF8: =Q8*R8 -> 0 | AG8: D | AH8: VS2
A9: 5 | B9: 9802 | C9: LC Corresponding MF-JPN | D9: LifeComm Corresponding | E9: contract management | F9: Core Insurance Systems Group 34956 | G9: Policy Admin Systems Team 34957 | H9: Core Business Application | I9: Y | J9: Yes | K9: COBOL, Assembler, MU(EASYPLUS), JCL | M9: N | N9: 15.953625 | O9: 1.6541667 | P9: 0 | Q9: 17.607792 | R9: 0.98287217 | S9: 8.8038958 | T9: 8.8038958 | U9: 1 | AA9: =N9 -> 15.953625 | AB9: =O9 -> 1.6541667 | AC9: =P9 -> 0 | AD9: =Q9 -> 17.607792 | AE9: =R9 -> 0.98287217 | AF9: =Q9*R9 -> 17.306208 | AG9: D | AH9: VS4
A10: 6 | B10: 9803 | C10: LC UWI MF-JPN | D10: LifeComm UWI | E10: contract management | F10: Core Insurance Systems Group 34956 | G10: Policy Admin Systems Team 34957 | H10: Core Business Application | I10: Y | J10: Yes | K10: Assembler, COBOL, MU(EASYPLUS), JCL | M10: N | N10: 8.8045833 | O10: 0.85 | P10: 0 | Q10: 9.6545833 | R10: 0.94821113 | S10: 4.8272917 | T10: 4.8272917 | U10: 1 | AA10: =N10 -> 8.8045833 | AB10: =O10 -> 0.85 | AC10: =P10 -> 0 | AD10: =Q10 -> 9.6545833 | AE10: =R10 -> 0.94821113 | AF10: =Q10*R10 -> 9.1545833 | AG10: D | AH10: VS1
A11: 7 | B11: 9804 | C11: LC AAPerf MF-JPN | D11: LifeComm AgentAgencyPerformance | E11: contract management | F11: Core Insurance Systems Group 34956 | G11: Policy Admin Systems Team 34957 | H11: Core Business Application | I11: Y | J11: Yes | K11: COBOL, Assembler, MU(EASYPLUS), JCL | M11: N | N11: 10.784167 | O11: 0.74583333 | P11: 0 | Q11: 11.53 | R11: 0.83304423 | S11: 5.765 | T11: 5.765 | U11: 1 | AA11: =N11 -> 10.784167 | AB11: =O11 -> 0.74583333 | AC11: =P11 -> 0 | AD11: =Q11 -> 11.53 | AE11: =R11 -> 0.83304423 | AF11: =Q11*R11 -> 9.605 | AG11: D | AH11: VS3
A12: 8 | B12: 9805 | C12: LC Payment MF-JPN | D12: LifeComm Payment | E12: contract management | F12: Core Insurance Systems Group 34956 | G12: Policy Admin Systems Team 34957 | H12: Core Business Application | I12: Y | J12: Yes | K12: COBOL, Assembler, MU(EASYPLUS), JCL | M12: N | N12: 2.8966667 | O12: 0.025 | P12: 0 | Q12: 2.9216667 | R12: 0.90587564 | S12: 1.4608333 | T12: 1.4608333 | U12: 1 | AA12: =N12 -> 2.8966667 | AB12: =O12 -> 0.025 | AC12: =P12 -> 0 | AD12: =Q12 -> 2.9216667 | AE12: =R12 -> 0.90587564 | AF12: =Q12*R12 -> 2.6466667 | AG12: D | AH12: VS2
A13: 9 | B13: 9806 | C13: LC GL/SC MF-JPN | D13: LifeComm GL/SC | E13: contract management | F13: Core Insurance Systems Group 34956 | G13: Policy Admin Systems Team 34957 | H13: Core Business Application | I13: Y | J13: Yes | K13: COBOL, Assembler, MU(EASYPLUS), JCL | M13: N | N13: 5.28875 | O13: 1.025 | P13: 0 | Q13: 6.31375 | R13: 0.83765591 | S13: 3.156875 | T13: 3.156875 | U13: 1 | AA13: =N13 -> 5.28875 | AB13: =O13 -> 1.025 | AC13: =P13 -> 0 | AD13: =Q13 -> 6.31375 | AE13: =R13 -> 0.83765591 | AF13: =Q13*R13 -> 5.28875 | AG13: D | AH13: VS6
A14: 10 | B14: 9807 | C14: LC Valuation MF-JPN | D14: LifeComm Valuation | E14: contract management | F14: Core Insurance Systems Group 34956 | G14: Policy Admin Systems Team 34957 | H14: Core Business Application | I14: N | J14: Yes | K14: COBOL, Assembler, MU(EASYPLUS), JCL | M14: N | N14: 9.76875 | O14: 1.4833333 | P14: 0 | Q14: 11.252083 | R14: 0.8563229 | S14: 5.6260417 | T14: 5.6260417 | U14: 1 | AA14: =N14 -> 9.76875 | AB14: =O14 -> 1.4833333 | AC14: =P14 -> 0 | AD14: =Q14 -> 11.252083 | AE14: =R14 -> 0.8563229 | AF14: =Q14*R14 -> 9.6354167 | AG14: D | AH14: VS6
A15: 11 | B15: 9808 | C15: LC AACOMP MF-JPN | D15: LifeComm AgentAgencyComp | E15: contract management | F15: Core Insurance Systems Group 34956 | G15: Policy Admin Systems Team 34957 | H15: Core Business Application | I15: Y | J15: Yes | K15: COBOL, Assembler, MU(EASYPLUS), JCL | M15: N | N15: 13.545708 | O15: 3.14375 | P15: 0 | Q15: 16.689458 | R15: 0.72662384 | S15: 8.3447292 | T15: 8.3447292 | U15: 1 | AA15: =N15 -> 13.545708 | AB15: =O15 -> 3.14375 | AC15: =P15 -> 0 | AD15: =Q15 -> 16.689458 | AE15: =R15 -> 0.72662384 | AF15: =Q15*R15 -> 12.126958 | AG15: D | AH15: VS3
A16: 12 | B16: 9810 | C16: Processor-I MF-JPN | D16: Claim payment (Processor-I) | E16: contract management | F16: Core Insurance Systems Group 34956 | G16: Policy Admin Systems Team 34957 | H16: Core Business Application | I16: Y | J16: Yes | K16: COBOL, MU(EASYPLUS), Assembler, JCL | M16: N | N16: 7.6683333 | O16: 1.1291667 | P16: 0 | Q16: 8.7975 | R16: 0.75561239 | S16: 4.39875 | T16: 4.39875 | U16: 1 | AA16: =N16 -> 7.6683333 | AB16: =O16 -> 1.1291667 | AC16: =P16 -> 0 | AD16: =Q16 -> 8.7975 | AE16: =R16 -> 0.75561239 | AF16: =Q16*R16 -> 6.6475 | AG16: D | AH16: VS2
A17: 13 | B17: 9811 | C17: LC Submit MF-JPN | D17: Submit Online | E17: contract management | F17: Core Insurance Systems Group 34956 | G17: Policy Admin Systems Team 34957 | H17: Core Business Application | I17: Y | J17: Yes | K17: COBOL, MU(EASYPLUS), Assembler, JCL | M17: N | N17: 1.9683333 | O17: 0.16458333 | P17: 0 | Q17: 2.1329167 | R17: 0.95311584 | S17: 1.0664583 | T17: 1.0664583 | U17: 1 | AA17: =N17 -> 1.9683333 | AB17: =O17 -> 0.16458333 | AC17: =P17 -> 0 | AD17: =Q17 -> 2.1329167 | AE17: =R17 -> 0.95311584 | AF17: =Q17*R17 -> 2.0329167 | AG17: D | AH17: VS1
A18: 14 | B18: 9813 | C18: LC Micro MF-JPN | D18: Micro-Index | E18: contract management | F18: Core Insurance Systems Group 34956 | G18: Policy Admin Systems Team 34957 | H18: Core Business Application | I18: Y | J18: Yes | K18: COBOL, MU(EASYPLUS), Assembler, JCL | M18: N | N18: 2.1175 | O18: 0 | P18: 0 | Q18: 2.1175 | R18: 0.64580874 | S18: 1.05875 | T18: 1.05875 | U18: 1 | AA18: =N18 -> 2.1175 | AB18: =O18 -> 0 | AC18: =P18 -> 0 | AD18: =Q18 -> 2.1175 | AE18: =R18 -> 0.64580874 | AF18: =Q18*R18 -> 1.3675 | AG18: D | AH18: VS1
A19: 15 | B19: 9814 | C19: Foreign MF-JPN | D19: Foreign | E19: contract management | F19: Core Insurance Systems Group 34956 | G19: Policy Admin Systems Team 34957 | H19: Core Business Application | I19: N | J19: Yes | K19: COBOL, MU(EASYPLUS), Assembler, JCL | M19: N | N19: 0 | O19: 0 | P19: 0 | Q19: 0 | R19: 0 | U19: 1 | AA19: =N19 -> 0 | AB19: =O19 -> 0 | AC19: =P19 -> 0 | AD19: =Q19 -> 0 | AE19: =R19 -> 0 | AF19: =Q19*R19 -> 0 | AG19: D | AH19: VS1
A20: 16 | B20: 9816 | C20: CT Salary MF-JPN | D20: CT Salary System | E20: contract management | F20: Core Insurance Systems Group 34956 | G20: Policy Admin Systems Team 34957 | H20: Core Business Application | I20: Y | J20: Yes | K20: COBOL, MU(EASYPLUS), Assembler, JCL | M20: N | N20: 0.2 | O20: 0 | P20: 0 | Q20: 0.2 | R20: 0 | S20: 0.1 | T20: 0.1 | U20: 1 | AA20: =N20 -> 0.2 | AB20: =O20 -> 0 | AC20: =P20 -> 0 | AD20: =Q20 -> 0.2 | AE20: =R20 -> 0 | AF20: =Q20*R20 -> 0 | AG20: D | AH20: VS6
A21: 17 | B21: 9817 | C21: TaxCertification MF-JPN | D21: TaxCertification | E21: contract management | F21: Core Insurance Systems Group 34956 | G21: Policy Admin Systems Team 34957 | H21: Core Business Application | I21: N | J21: Yes | K21: COBOL, MU(EASYPLUS), Assembler, JCL | M21: N | N21: 1.664875 | O21: 0 | P21: 0 | Q21: 1.664875 | R21: 0.40748805 | S21: 0.8324375 | T21: 0.8324375 | U21: 1 | AA21: =N21 -> 1.664875 | AB21: =O21 -> 0 | AC21: =P21 -> 0 | AD21: =Q21 -> 1.664875 | AE21: =R21 -> 0.40748805 | AF21: =Q21*R21 -> 0.67841667 | AG21: D | AH21: VS4
A22: 18 | B22: 9818 | C22: SWINGMANAGER MF-JPN | D22: SWING MANAGER | E22: contract management | F22: Core Insurance Systems Group 34956 | G22: Policy Admin Systems Team 34957 | H22: Core Business Application | I22: N | J22: Yes | K22: COBOL, MU(EASYPLUS), Assembler, JCL | M22: N | N22: 0 | O22: 0 | P22: 0 | Q22: 0 | R22: 0 | U22: 1 | AA22: =N22 -> 0 | AB22: =O22 -> 0 | AC22: =P22 -> 0 | AD22: =Q22 -> 0 | AE22: =R22 -> 0 | AF22: =Q22*R22 -> 0 | AG22: D | AH22: VS1
A23: 19 | B23: 9819 | C23: PremCollectDBMF-JPN | D23: Premium Collection History DB | E23: contract management | F23: Core Insurance Systems Group 34956 | G23: Policy Admin Systems Team 34957 | H23: Core Business Application | I23: N | J23: Yes | K23: COBOL, MU(EASYPLUS), Assembler, JCL | M23: N | N23: 0 | O23: 0 | P23: 0 | Q23: 0 | R23: 0 | U23: 1 | AA23: =N23 -> 0 | AB23: =O23 -> 0 | AC23: =P23 -> 0 | AD23: =Q23 -> 0 | AE23: =R23 -> 0 | AF23: =Q23*R23 -> 0 | AG23: D | AH23: VS1
A24: 20 | B24: 9820 | C24: MCFA CP DB MF-JPN | D24: MCFA Coupon DB | E24: contract management | F24: Core Insurance Systems Group 34956 | G24: Policy Admin Systems Team 34957 | H24: Core Business Application | I24: Y | J24: Yes | K24: COBOL, MU(EASYPLUS), Assembler, JCL | M24: N | N24: 0 | O24: 0 | P24: 0 | Q24: 0 | R24: 0 | U24: 1 | AA24: =N24 -> 0 | AB24: =O24 -> 0 | AC24: =P24 -> 0 | AD24: =Q24 -> 0 | AE24: =R24 -> 0 | AF24: =Q24*R24 -> 0 | AG24: D | AH24: VS1
A25: 21 | B25: 9821 | C25: Maturity MF-JPN | D25: Payment maturity existing benefit etc | E25: contract management | F25: Core Insurance Systems Group 34956 | G25: Policy Admin Systems Team 34957 | H25: Core Business Application | I25: Y | J25: Yes | K25: COBOL, MU(EASYPLUS), Assembler, JCL | M25: N | N25: 4.3783333 | O25: 0.97083333 | P25: 0 | Q25: 5.3491667 | R25: 0.62610999 | S25: 2.6745833 | T25: 2.6745833 | U25: 1 | AA25: =N25 -> 4.3783333 | AB25: =O25 -> 0.97083333 | AC25: =P25 -> 0 | AD25: =Q25 -> 5.3491667 | AE25: =R25 -> 0.62610999 | AF25: =Q25*R25 -> 3.3491667 | AG25: D | AH25: VS2
A26: 22 | B26: 9822 | C26: LC Reins MF-JPN | D26: Reinsurance | E26: contract management | F26: Core Insurance Systems Group 34956 | G26: Policy Admin Systems Team 34957 | H26: Core Business Application | I26: N | J26: Yes | K26: COBOL, MU(EASYPLUS), Assembler, JCL | M26: N | N26: 6.0129167 | O26: 0.25416667 | P26: 0 | Q26: 6.2670833 | R26: 0.78990759 | S26: 3.1335417 | T26: 3.1335417 | U26: 1 | AA26: =N26 -> 6.0129167 | AB26: =O26 -> 0.25416667 | AC26: =P26 -> 0 | AD26: =Q26 -> 6.2670833 | AE26: =R26 -> 0.78990759 | AF26: =Q26*R26 -> 4.9504167 | AG26: D | AH26: VS6
A27: 23 | B27: 9823 | C27: ASP Bridge(H) MF-JPN | D27: ASP Bridge (HOST) | E27: contract management | F27: Core Insurance Systems Group 34956 | G27: Policy Admin Systems Team 34957 | H27: Common Service Business Application | I27: Y | J27: Yes | K27: COBOL, MU(EASYPLUS), Assembler, JCL | M27: N | N27: 6.7267083 | O27: 1.4625 | P27: 0 | Q27: 8.1892083 | R27: 0.72808727 | S27: 4.0946042 | T27: 4.0946042 | U27: 1 | AA27: =N27 -> 6.7267083 | AB27: =O27 -> 1.4625 | AC27: =P27 -> 0 | AD27: =Q27 -> 8.1892083 | AE27: =R27 -> 0.72808727 | AF27: =Q27*R27 -> 5.9624583 | AG27: D | AH27: VS5
A28: 24 | B28: 9824 | C28: CCA MF-JPN | D28: Client Contract Administration | E28: contract management | F28: Core Insurance Systems Group 34956 | G28: Policy Admin Systems Team 34957 | H28: Core Business Application | I28: Y | J28: Yes | K28: COBOL, MU(EASYPLUS), Assembler, JCL | M28: N | N28: 1.6308333 | O28: 0 | P28: 0 | Q28: 1.6308333 | R28: 0.38681656 | S28: 0.81541667 | T28: 0.81541667 | U28: 1 | AA28: =N28 -> 1.6308333 | AB28: =O28 -> 0 | AC28: =P28 -> 0 | AD28: =Q28 -> 1.6308333 | AE28: =R28 -> 0.38681656 | AF28: =Q28*R28 -> 0.63083333 | AG28: D | AH28: VS1
A29: 25 | B29: 9833 | C29: C04NWC-JPN | D29: CenterServer | E29: new contract related | F29: Customer Service and Operations Systems Group 34965 | G29: New Business Team 34966 | H29: Core Business Application | I29: N | J29: Yes | K29: C/C++ | M29: N | N29: 8.7316667 | O29: 0.11041667 | P29: 0 | Q29: 8.8420833 | R29: 0.91687479 | S29: 4.4210417 | T29: 4.4210417 | U29: 1 | AA29: =N29 -> 8.7316667 | AB29: =O29 -> 0.11041667 | AC29: =P29 -> 0 | AD29: =Q29 -> 8.8420833 | AE29: =R29 -> 0.91687479 | AF29: =Q29*R29 -> 8.1070833 | AG29: B | AH29: VS2
A30: 26 | B30: 9834 | C30: C03WRE-JPN | D30: POS Workflow Payment Workflow (Restoring cancelled | E30: storage and preservation related | F30: Customer Service and Operations Systems Group 34965 | G30: Policy Servicing Team 34967 | H30: Core Business Application | I30: Y | J30: Yes | K30: VB.NET | M30: N | N30: 0.2 | O30: 0.2 | P30: 0 | Q30: 0.37083333 | R30: 0.3258427 | S30: 0.18541667 | T30: 0.18541667 | U30: 1 | AA30: =N30 -> 0.2 | AB30: =O30 -> 0.2 | AC30: =P30 -> 0 | AD30: =Q30 -> 0.37083333 | AE30: =R30 -> 0.3258427 | AF30: =Q30*R30 -> 0.12083333 | AG30: B | AH30: VS1
A31: 27 | B31: 9835 | C31: C12WNC-JPN | D31: POS Workflow Payment Workflow (Claim Transaction A | E31: insurance claims and benefits payment related | F31: Customer Service and Operations Systems Group 34965 | G31: Claims Team 34968 | H31: Core Business Application | I31: Y | J31: Yes | K31: VB.NET; C/C++; JAVA | M31: N | N31: 29.379875 | O31: 5.6166667 | P31: 0 | Q31: 34.996542 | R31: 0.90522873 | S31: 17.498271 | T31: 17.498271 | U31: 1 | AA31: =N31 -> 29.379875 | AB31: =O31 -> 5.6166667 | AC31: =P31 -> 0 | AD31: =Q31 -> 34.996542 | AE31: =R31 -> 0.90522873 | AF31: =Q31*R31 -> 31.679875 | AG31: B | AH31: VS1
A32: 28 | B32: 9836 | C32: C03WRD-JPN | D32: POS Workflow Payment Workflow (Reduction of paymen | E32: storage and preservation related | F32: Customer Service and Operations Systems Group 34965 | G32: Policy Servicing Team 34967 | H32: Core Business Application | I32: Y | J32: Yes | K32: VB.NET | M32: N | N32: 0.3 | O32: 0.3 | P32: 0 | Q32: 2.5258333 | R32: 0.90102276 | S32: 1.2629167 | T32: 1.2629167 | U32: 1 | AA32: =N32 -> 0.3 | AB32: =O32 -> 0.3 | AC32: =P32 -> 0 | AD32: =Q32 -> 2.5258333 | AE32: =R32 -> 0.90102276 | AF32: =Q32*R32 -> 2.2758333 | AG32: B | AH32: VS1
A33: 29 | B33: 9842 | C33: C03PCA-JPN | D33: Add Coverage | E33: storage and preservation related | F33: Customer Service and Operations Systems Group 34965 | G33: Policy Servicing Team 34967 | H33: Core Business Application | I33: N | J33: Yes | K33: VB | M33: N | N33: 0.3 | O33: 0.3 | P33: 0 | Q33: 2.88625 | R33: 0.90298831 | S33: 1.443125 | T33: 1.443125 | U33: 1 | AA33: =N33 -> 0.3 | AB33: =O33 -> 0.3 | AC33: =P33 -> 0 | AD33: =Q33 -> 2.88625 | AE33: =R33 -> 0.90298831 | AF33: =Q33*R33 -> 2.60625 | AG33: B | AH33: VS2
A34: 30 | B34: 9843 | C34: C10CSS-JPN | D34: FSC Call Support | E34: customer care / call center related | F34: Customer Service and Operations Systems Group 34965 | G34: Customer Care Team 34969 | H34: Core Business Application | I34: N | J34: Yes | K34: VB.NET | M34: N | N34: 1.2120833 | O34: 0.20833333 | P34: 0 | Q34: 1.4204167 | R34: 0.63596363 | S34: 0.71020833 | T34: 0.71020833 | U34: 1 | AA34: =N34 -> 1.2120833 | AB34: =O34 -> 0.20833333 | AC34: =P34 -> 0 | AD34: =Q34 -> 1.4204167 | AE34: =R34 -> 0.63596363 | AF34: =Q34*R34 -> 0.90333333 | AG34: B | AH34: VS2
A35: 31 | B35: 9844 | C35: C04VAS-JPN | D35: Voucher Approval System for AS400 | E35: corporate related | F35: Core Insurance Systems Group 34956 | G35: Corporate Systems Team 34959 | H35: Core Business Application | I35: Y | J35: Yes | K35: VB.NET | M35: N | N35: 0.67083333 | O35: 0.68333333 | P35: 0 | Q35: 1.3541667 | R35: 0.36923077 | S35: 0.67708333 | T35: 0.67708333 | U35: 1 | AA35: =N35 -> 0.67083333 | AB35: =O35 -> 0.68333333 | AC35: =P35 -> 0 | AD35: =Q35 -> 1.3541667 | AE35: =R35 -> 0.36923077 | AF35: =Q35*R35 -> 0.5 | AG35: B | AH35: VS6
A36: 32 | B36: 9845 | C36: C04SYM-JPN | D36: Renewal symap Business Work Flow | E36: new contract related | F36: Customer Service and Operations Systems Group 34965 | G36: New Business Team 34966 | H36: Core Business Application | I36: N | J36: Yes | K36: VB.NET | M36: N | N36: 3.4049167 | O36: 0 | P36: 0 | Q36: 3.4049167 | R36: 0.84091632 | S36: 1.7024583 | T36: 1.7024583 | U36: 1 | AA36: =N36 -> 3.4049167 | AB36: =O36 -> 0 | AC36: =P36 -> 0 | AD36: =Q36 -> 3.4049167 | AE36: =R36 -> 0.84091632 | AF36: =Q36*R36 -> 2.86325 | AG36: B | AH36: VS4
... A40: 36 | B40: 9849 | C40: C04OSI-JPN | D40: S Sum Total System(Open) | E40: new contract related | F40: Customer Service and Operations Systems Group 34965 | G40: New Business Team 34966 | H40: Common Service Business Application | I40: N | J40: Yes | K40: JAVA | M40: N | N40: 5.18625 | O40: 0.38333333 | P40: 0 | Q40: 5.5695833 | R40: 0.8315254 | S40: 2.7847917 | T40: 2.7847917 | U40: 1 | AA40: =N40 -> 5.18625 | AB40: =O40 -> 0.38333333 | AC40: =P40 -> 0 | AD40: =Q40 -> 5.5695833 | AE40: =R40 -> 0.8315254 | AF40: =Q40*R40 -> 4.63125 | AG40: B | AH40: VS1
A41: 37 | B41: 9851 | C41: W03FIC-JPN | D41: Guidance Refusal Information Administration System | E41: corporate related | F41: Core Insurance Systems Group 34956 | G41: Corporate Systems Team 34959 | H41: Core Business Application | I41: N | J41: Yes | K41: JAVA | L41: Platform as a Service (PaaS) | M41: N | N41: 0.29166667 | O41: 0.11666667 | P41: 0 | Q41: 0.40833333 | R41: 0.82653061 | S41: 0.20416667 | T41: 0.20416667 | U41: 1 | AA41: =N41 -> 0.29166667 | AB41: =O41 -> 0.11666667 | AC41: =P41 -> 0 | AD41: =Q41 -> 0.40833333 | AE41: =R41 -> 0.82653061 | AF41: =Q41*R41 -> 0.3375 | AG41: B | AH41: VS3
A42: 38 | B42: 9852 | C42: C03APO-JPN | D42: Apollocs | E42: corporate related | F42: Core Insurance Systems Group 34956 | G42: Corporate Systems Team 34959 | H42: Core Business Application | I42: N | J42: Yes | K42: Other#APOLLOCS | M42: N | N42: 0.50833333 | O42: 0 | P42: 0 | Q42: 0.50833333 | R42: 0.36885246 | S42: 0.25416667 | T42: 0.25416667 | U42: 1 | AA42: =N42 -> 0.50833333 | AB42: =O42 -> 0 | AC42: =P42 -> 0 | AD42: =Q42 -> 0.50833333 | AE42: =R42 -> 0.36885246 | AF42: =Q42*R42 -> 0.1875 | AG42: B | AH42: VS5
A43: 39 | B43: 9854 | C43: Z04IMA-JPN | D43: Image Search | E43: new contract related | F43: Customer Service and Operations Systems Group 34965 | G43: New Business Team 34966 | H43: Core Business Application | I43: N | J43: Yes | K43: CSS; JAVA;HTML; VB.NET | M43: N | N43: 1.4004167 | O43: 0 | P43: 0 | Q43: 1.4004167 | R43: 0.92859268 | S43: 0.70020833 | T43: 0.70020833 | U43: 1 | AA43: =N43 -> 1.4004167 | AB43: =O43 -> 0 | AC43: =P43 -> 0 | AD43: =Q43 -> 1.4004167 | AE43: =R43 -> 0.92859268 | AF43: =Q43*R43 -> 1.3004167 | AG43: B | AH43: VS4
A44: 40 | B44: 9857 | C44: W05AMS-JPN | D44: Annuity Information Management System(AIMS) | E44: insurance claims and benefits payment related | F44: Customer Service and Operations Systems Group 34965 | G44: Claims Team 34968 | H44: Core Business Application | I44: Y | J44: Yes | K44: JAVA | M44: N | N44: 20.211667 | O44: 1.8166667 | P44: 0 | Q44: 22.028333 | R44: 0.92547477 | S44: 11.014167 | T44: 11.014167 | U44: 1 | AA44: =N44 -> 20.211667 | AB44: =O44 -> 1.8166667 | AC44: =P44 -> 0 | AD44: =Q44 -> 22.028333 | AE44: =R44 -> 0.92547477 | AF44: =Q44*R44 -> 20.386667 | AG44: B | AH44: VS2
A45: 41 | B45: 9858 | C45: W02OPS-JPN | D45: Insurance Planning for Operator | E45: marketing/direct business related | F45: Customer and Channel Engineering 34961 | H45: Core Business Application | I45: N | J45: Yes | K45: JAVA | M45: N | N45: 4.8333333 | O45: 1 | P45: 1.0833333 | Q45: 6.9166667 | R45: 0.71084337 | S45: 3.4583333 | T45: 3.4583333 | U45: 1 | AA45: =N45 -> 4.8333333 | AB45: =O45 -> 1 | AC45: =P45 -> 1.0833333 | AD45: =Q45 -> 6.9166667 | AE45: =R45 -> 0.71084337 | AF45: =Q45*R45 -> 4.9166667 | AG45: B | AH45: VS2
A46: 42 | B46: 9861 | C46: W04RRE-JPN | D46: Rule Engine | E46: new contract related | F46: Customer Service and Operations Systems Group 34965 | G46: New Business Team 34966 | H46: Core Business Application | I46: Y | J46: Yes | K46: JAVA | M46: N | N46: 6.3152917 | O46: 0 | P46: 0 | Q46: 6.3152917 | R46: 0.87325737 | S46: 3.1576458 | T46: 3.1576458 | U46: 1 | AA46: =N46 -> 6.3152917 | AB46: =O46 -> 0 | AC46: =P46 -> 0 | AD46: =Q46 -> 6.3152917 | AE46: =R46 -> 0.87325737 | AF46: =Q46*R46 -> 5.514875 | AG46: B | AH46: VS2
A47: 43 | B47: 9879 | C47: W03PIU-JPN | D47: IS universal life insurance simulation | E47: storage and preservation related | F47: Customer Service and Operations Systems Group 34965 | G47: Policy Servicing Team 34967 | H47: Core Business Application | I47: N | J47: Yes | K47: JAVA | M47: N | N47: 0.2 | O47: 0.1 | P47: 0 | Q47: 0.30833333 | R47: 0.67567568 | S47: 0.15416667 | T47: 0.15416667 | U47: 1 | AA47: =N47 -> 0.2 | AB47: =O47 -> 0.1 | AC47: =P47 -> 0 | AD47: =Q47 -> 0.30833333 | AE47: =R47 -> 0.67567568 | AF47: =Q47*R47 -> 0.20833333 | AG47: B | AH47: VS2
A48: 44 | B48: 9890 | C48: W08HTN-JPN | D48: conservation contact personnel entry system | E48: corporate related | F48: Core Insurance Systems Group 34956 | G48: Corporate Systems Team 34959 | H48: Core Business Application | I48: N | J48: Yes | K48: JAVA | M48: N | N48: 1.5054583 | O48: 0.045833333 | P48: 0 | Q48: 1.5512917 | R48: 0.072009884 | S48: 0.77564583 | T48: 0.77564583 | U48: 1 | AA48: =N48 -> 1.5054583 | AB48: =O48 -> 0.045833333 | AC48: =P48 -> 0 | AD48: =Q48 -> 1.5512917 | AE48: =R48 -> 0.072009884 | AF48: =Q48*R48 -> 0.11170833 | AG48: B | AH48: VS4
A49: 45 | B49: 9894 | C49: W08NAV-JPN | D49: Branch Marketing Information System | E49: sales / insurance recruitment | F49: Customer and Channel Engineering 34961 | G49: Distribution F2F Team 34962 | H49: Core Business Application | I49: N | J49: Yes | K49: VB | M49: N | N49: 2.841875 | O49: 0.35208333 | P49: 0 | Q49: 3.1939583 | R49: 0.79192486 | S49: 1.5969792 | T49: 1.5969792 | U49: 1 | AA49: =N49 -> 2.841875 | AB49: =O49 -> 0.35208333 | AC49: =P49 -> 0 | AD49: =Q49 -> 3.1939583 | AE49: =R49 -> 0.79192486 | AF49: =Q49*R49 -> 2.529375 | AG49: B | AH49: VS3
A50: 46 | B50: 9896 | C50: W08SFE-JPN | D50: commission Inquiry | E50: corporate related | F50: Core Insurance Systems Group 34956 | G50: Corporate Systems Team 34959 | H50: Core Business Application | I50: N | J50: Yes | K50: JAVA | M50: N | N50: 1.091375 | O50: 0.105 | P50: 0 | Q50: 1.196375 | R50: 0.98955177 | S50: 0.5981875 | T50: 0.5981875 | U50: 1 | AA50: =N50 -> 1.091375 | AB50: =O50 -> 0.105 | AC50: =P50 -> 0 | AD50: =Q50 -> 1.196375 | AE50: =R50 -> 0.98955177 | AF50: =Q50*R50 -> 1.183875 | AG50: B | AH50: VS4
A51: 47 | B51: 9899 | C51: W08CIS-JPN | D51: Career Information System | E51: corporate related | F51: Core Insurance Systems Group 34956 | G51: Corporate Systems Team 34959 | H51: Core Business Application | I51: N | J51: Yes | K51: JAVA | M51: N | N51: 1.204125 | O51: 0.52916667 | P51: 0 | Q51: 1.7332917 | R51: 0.82691892 | S51: 0.86664583 | T51: 0.86664583 | U51: 1 | AA51: =N51 -> 1.204125 | AB51: =O51 -> 0.52916667 | AC51: =P51 -> 0 | AD51: =Q51 -> 1.7332917 | AE51: =R51 -> 0.82691892 | AF51: =Q51*R51 -> 1.4332917 | AG51: B | AH51: VS4
A52: 48 | B52: 9906 | C52: W08NAR-JPN | D52: producers information entry system | E52: corporate related | F52: Core Insurance Systems Group 34956 | G52: Corporate Systems Team 34959 | H52: Core Business Application | I52: N | J52: Yes | K52: JAVA | M52: N | N52: 1.2860417 | O52: 0.14541667 | P52: 0 | Q52: 1.4314583 | R52: 0.95051666 | S52: 0.71572917 | T52: 0.71572917 | U52: 1 | AA52: =N52 -> 1.2860417 | AB52: =O52 -> 0.14541667 | AC52: =P52 -> 0 | AD52: =Q52 -> 1.4314583 | AE52: =R52 -> 0.95051666 | AF52: =Q52*R52 -> 1.360625 | AG52: B | AH52: VS4
A53: 49 | B53: 9907 | C53: W13WWF-JPN | D53: Web work flow | E53: corporate related | F53: Core Insurance Systems Group 34956 | G53: Corporate Systems Team 34959 | H53: Core Business Application | I53: N | J53: Yes | K53: JAVA | M53: N | N53: 0.38583333 | O53: 0 | P53: 0 | Q53: 0.38583333 | R53: 0.35205184 | S53: 0.19291667 | T53: 0.19291667 | U53: 1 | AA53: =N53 -> 0.38583333 | AB53: =O53 -> 0 | AC53: =P53 -> 0 | AD53: =Q53 -> 0.38583333 | AE53: =R53 -> 0.35205184 | AF53: =Q53*R53 -> 0.13583333 | AG53: B | AH53: VS4
A54: 50 | B54: 9910 | C54: P08MMS-JPN | D54: Medical Management System | E54: new contract related | F54: Customer Service and Operations Systems Group 34965 | G54: New Business Team 34966 | H54: Core Business Application | I54: N | J54: Yes | K54: VB.NET | M54: N | N54: 0.0625 | O54: 0 | P54: 0 | Q54: 0.0625 | R54: 1 | S54: 0.03125 | T54: 0.03125 | U54: 1 | AA54: =N54 -> 0.0625 | AB54: =O54 -> 0 | AC54: =P54 -> 0 | AD54: =Q54 -> 0.0625 | AE54: =R54 -> 1 | AF54: =Q54*R54 -> 0.0625 | AG54: B | AH54: VS3
A55: 51 | B55: 9920 | C55: WPSYEC-JPN | D55: Direct Marketing Site | E55: marketing/direct business related | F55: Customer and Channel Engineering 34961 | G55: Marketing and Leads Team 34964 | H55: Core Business Application | I55: N | J55: Yes | K55: JAVA | M55: N | N55: 10.3375 | O55: 3.5583333 | P55: 5.1816667 | Q55: 19.0775 | R55: 0.93360416 | S55: 9.53875 | T55: 9.53875 | U55: 1 | AA55: =N55 -> 10.3375 | AB55: =O55 -> 3.5583333 | AC55: =P55 -> 5.1816667 | AD55: =Q55 -> 19.0775 | AE55: =R55 -> 0.93360416 | AF55: =Q55*R55 -> 17.810833 | AG55: B | AH55: VS1
A56: 52 | B56: 9921 | C56: W07IPC-JPN | D56: Internet Prospective Information | E56: marketing/direct business related | F56: Customer and Channel Engineering 34961 | G56: Marketing and Leads Team 34964 | H56: Core Business Application | I56: N | J56: Yes | K56: JAVA | L56: Platform as a Service (PaaS) | M56: N | N56: 0.30416667 | O56: 0.041666667 | P56: 0 | Q56: 0.34583333 | R56: 1 | S56: 0.17291667 | T56: 0.17291667 | U56: 1 | AA56: =N56 -> 0.30416667 | AB56: =O56 -> 0.041666667 | AC56: =P56 -> 0 | AD56: =Q56 -> 0.34583333 | AE56: =R56 -> 1 | AF56: =Q56*R56 -> 0.34583333 | AG56: B | AH56: VS1
A57: 53 | B57: 9926 | C57: W01LOI-JPN | D57: Japan Authorization / login | E57: common service platform | F57: Japan Platform Team 35775 | G57: Japan Platform Team 35775 | H57: Common Service Business Application | I57: N | J57: Yes | K57: JAVA | M57: N | N57: 0.075 | O57: 0 | P57: 0 | Q57: 0.075 | R57: 0 | S57: 0.0375 | T57: 0.0375 | U57: 1 | AA57: =N57 -> 0.075 | AB57: =O57 -> 0 | AC57: =P57 -> 0 | AD57: =Q57 -> 0.075 | AE57: =R57 -> 0 | AF57: =Q57*R57 -> 0 | AG57: B | AH57: VS1
A58: 54 | B58: 9928 | C58: W01MAS-JPN | D58: Common Framework(Master4) | E58: common service platform | F58: Japan Platform Team 35775 | G58: Japan Platform Team 35775 | H58: Common Service Business Application | I58: N | J58: Yes | K58: JAVA | L58: Platform as a Service (PaaS) | M58: N | N58: 1.3970833 | O58: 1 | P58: 0 | Q58: 2.3970833 | R58: 0.86441856 | S58: 1.1985417 | T58: 1.1985417 | U58: 1 | AA58: =N58 -> 1.3970833 | AB58: =O58 -> 1 | AC58: =P58 -> 0 | AD58: =Q58 -> 2.3970833 | AE58: =R58 -> 0.86441856 | AF58: =Q58*R58 -> 2.0720833 | AG58: B | AH58: VS2
A59: 55 | B59: 9930 | C59: A04MMP-JPN | D59: AS400 Mass Marketing System | E59: corporate related | F59: Core Insurance Systems Group 34956 | G59: Corporate Systems Team 34959 | H59: Core Business Application | I59: Y | J59: Yes | K59: Other#RPG | M59: N | N59: 2.4083333 | O59: 0.075 | P59: 0 | Q59: 2.4833333 | R59: 0.89932886 | S59: 1.2416667 | T59: 1.2416667 | U59: 1 | AA59: =N59 -> 2.4083333 | AB59: =O59 -> 0.075 | AC59: =P59 -> 0 | AD59: =Q59 -> 2.4833333 | AE59: =R59 -> 0.89932886 | AF59: =Q59*R59 -> 2.2333333 | AG59: D | AH59: VS6
A60: 56 | B60: 9931 | C60: P02BKE-JPN | D60: Sales illustration system (based on EXCEL) for BAN | E60: sales / insurance recruitment | F60: Customer and Channel Engineering 34961 | G60: Distribution Banca Team 34963 | H60: Core Business Application | I60: N | J60: Yes | K60: Other#VBA | M60: N | N60: 13 | O60: 2.275 | P60: 0 | Q60: 15.275 | R60: 0.91728849 | S60: 7.6375 | T60: 7.6375 | U60: 1 | AA60: =N60 -> 13 | AB60: =O60 -> 2.275 | AC60: =P60 -> 0 | AD60: =Q60 -> 15.275 | AE60: =R60 -> 0.91728849 | AF60: =Q60*R60 -> 14.011582 | AG60: B | AH60: VS2
A61: 57 | B61: 9940 | C61: WPSC2S-JPN | D61: Call Control System | E61: corporate related | F61: Core Insurance Systems Group 34956 | G61: Corporate Systems Team 34959 | H61: Core Business Application | I61: N | J61: Yes | K61: JAVA | M61: N | N61: 0.3875 | O61: 0.025 | P61: 0 | Q61: 0.4125 | R61: 0.81818182 | S61: 0.20625 | T61: 0.20625 | U61: 1 | AA61: =N61 -> 0.3875 | AB61: =O61 -> 0.025 | AC61: =P61 -> 0 | AD61: =Q61 -> 0.4125 | AE61: =R61 -> 0.81818182 | AF61: =Q61*R61 -> 0.3375 | AG61: B | AH61: VS4
A62: 58 | B62: 9941 | C62: B13ITS-JPN | D62: ITS-PCIS(Mutual Fund System(Including Bestway) | E62: corporate related | F62: Core Insurance Systems Group 34956 | G62: Corporate Systems Team 34959 | H62: Core Business Application | I62: N | J62: Yes | K62: JAVA | L62: Software as a Service (SaaS) | M62: N | N62: 0.92916458 | O62: 0.0875 | P62: 0 | Q62: 1.0166646 | R62: 0.41311355 | S62: 0.50833229 | T62: 0.50833229 | U62: 1 | AA62: =N62 -> 0.92916458 | AB62: =O62 -> 0.0875 | AC62: =P62 -> 0 | AD62: =Q62 -> 1.0166646 | AE62: =R62 -> 0.41311355 | AF62: =Q62*R62 -> 0.41999792 | AG62: A | AH62: VS1
A63: 59 | B63: 9947 | C63: W13WEP-JPN | D63: Web Payment | E63: storage and preservation related | F63: Customer Service and Operations Systems Group 34965 | G63: Policy Servicing Team 34967 | H63: Core Business Application | I63: Y | J63: Yes | K63: JAVA | M63: N | N63: 9 | O63: 1.1541667 | P63: 0 | Q63: 10 | R63: 0.75904635 | S63: 5 | T63: 5 | U63: 1 | AA63: =N63 -> 9 | AB63: =O63 -> 1.1541667 | AC63: =P63 -> 0 | AD63: =Q63 -> 10 | AE63: =R63 -> 0.75904635 | AF63: =Q63*R63 -> 7.5904635 | AG63: B | AH63: VS2
A64: 60 | B64: 9948 | C64: Data Send System for BANC MF-JP | D64: Data Send System for BANC | E64: contract management | F64: Core Insurance Systems Group 34956 | G64: Policy Admin Systems Team 34957 | H64: Core Business Application | I64: Y | J64: Yes | K64: COBOL, MU(EASYPLUS), Assembler, JCL | M64: N | N64: 9.2697083 | O64: 2.8458333 | P64: 0 | Q64: 12.115542 | R64: 0.77129926 | S64: 6.0577708 | T64: 6.0577708 | U64: 1 | AA64: =N64 -> 9.2697083 | AB64: =O64 -> 2.8458333 | AC64: =P64 -> 0 | AD64: =Q64 -> 12.115542 | AE64: =R64 -> 0.77129926 | AF64: =Q64*R64 -> 9.3447083 | AG64: D | AH64: VS5
A65: 61 | B65: 9949 | C65: CCMDNT-JPN | D65: .NET Common Infrastructure | E65: corporate related | F65: Core Insurance Systems Group 34956 | G65: Corporate Systems Team 34959 | H65: Common Service Business Application | I65: N | J65: Yes | K65: VB.NET; C # | M65: N | N65: 0.066666667 | O65: 0 | P65: 0 | Q65: 0.066666667 | R65: 0 | S65: 0.033333333 | T65: 0.033333333 | U65: 1 | AA65: =N65 -> 0.066666667 | AB65: =O65 -> 0 | AC65: =P65 -> 0 | AD65: =Q65 -> 0.066666667 | AE65: =R65 -> 0 | AF65: =Q65*R65 -> 0 | AG65: B | AH65: VS5
A66: 62 | B66: 9951 | C66: BCMHRP-JPN | D66: Data cooperation | E66: data infrastructure | F66: Data Platforms Team 34980 | G66: Data Platforms Team 34980 | H66: Common Service Business Application | I66: N | J66: Yes | K66: Other#MS-DOS ,AWK,VBScript,JAVA | L66: Running on both on-premises and Azure. The on-premises version will be decommissioned by the end of 2027. | M66: Y | N66: 7 | O66: 1 | P66: 0 | Q66: 7.9270417 | R66: 0.77923668 | S66: 3.9635208 | T66: 3.9635208 | U66: 1 | AA66: =N66 -> 7 | AB66: =O66 -> 1 | AC66: =P66 -> 0 | AD66: =Q66 -> 7.9270417 | AE66: =R66 -> 0.77923668 | AF66: =Q66*R66 -> 6.1770417 | AG66: C | AH66: VS1
A67: 63 | B67: 9962 | C67: WPSCUS-JPN | D67: Customer Support System | E67: marketing/direct business related | F67: Customer and Channel Engineering 34961 | G67: Marketing and Leads Team 34964 | H67: Core Business Application | I67: N | J67: Yes | K67: JavaScript; Other#APEX | L67: Platform as a Service (PaaS) | M67: N | N67: 8.9216667 | O67: 2.4104167 | P67: 1.52 | Q67: 12.852083 | R67: 0.82739504 | S67: 6.4260417 | T67: 6.4260417 | U67: 1 | AA67: =N67 -> 8.9216667 | AB67: =O67 -> 2.4104167 | AC67: =P67 -> 1.52 | AD67: =Q67 -> 12.852083 | AE67: =R67 -> 0.82739504 | AF67: =Q67*R67 -> 10.63375 | AG67: B | AH67: VS1
A68: 64 | B68: 9964 | C68: WAANSO-JPN | D68: New Submit Online System | E68: corporate related | F68: Core Insurance Systems Group 34956 | G68: Corporate Systems Team 34959 | H68: Core Business Application | I68: N | J68: Yes | K68: JAVA | M68: N | N68: 1.9533333 | O68: 0.3625 | P68: 0 | Q68: 2.3158333 | R68: 0.90824037 | S68: 1.1579167 | T68: 1.1579167 | U68: 1 | AA68: =N68 -> 1.9533333 | AB68: =O68 -> 0.3625 | AC68: =P68 -> 0 | AD68: =Q68 -> 2.3158333 | AE68: =R68 -> 0.90824037 | AF68: =Q68*R68 -> 2.1033333 | AG68: B | AH68: VS4
A69: 65 | B69: 9965 | C69: WZZHYO-JPN | D69: Report Template Management System | E69: corporate related | F69: Core Insurance Systems Group 34956 | G69: Corporate Systems Team 34959 | H69: Core Business Application | I69: N | J69: Yes | K69: JAVA | M69: N | N69: 0.025 | O69: 0.0375 | P69: 0 | Q69: 0.0625 | R69: 0.2 | S69: 0.03125 | T69: 0.03125 | U69: 1 | AA69: =N69 -> 0.025 | AB69: =O69 -> 0.0375 | AC69: =P69 -> 0 | AD69: =Q69 -> 0.0625 | AE69: =R69 -> 0.2 | AF69: =Q69*R69 -> 0.0125 | AG69: B | AH69: VS2
A70: 66 | B70: 9969 | C70: EAADRS-JPN | D70: Dr.SUM | E70: corporate related | F70: Core Insurance Systems Group 34956 | G70: Corporate Systems Team 34959 | H70: Core Business Application | I70: N | J70: Yes | K70: JAVA | M70: N | N70: 0.312375 | O70: 0.025 | P70: 0 | Q70: 0.337375 | R70: 0.67580585 | S70: 0.1686875 | T70: 0.1686875 | U70: 1 | AA70: =N70 -> 0.312375 | AB70: =O70 -> 0.025 | AC70: =P70 -> 0 | AD70: =Q70 -> 0.337375 | AE70: =R70 -> 0.67580585 | AF70: =Q70*R70 -> 0.228 | AG70: B | AH70: VS5
A71: 67 | B71: 9975 | C71: WPMWCC-JPN | D71: Web Contact Center | E71: customer care / call center related | F71: Customer Service and Operations Systems Group 34965 | G71: Customer Care Team 34969 | H71: Core Business Application | I71: N | J71: Yes | K71: JAVA | M71: N | N71: 1.1116667 | O71: 0 | P71: 0 | Q71: 1.1116667 | R71: 0.58508246 | S71: 0.55583333 | T71: 0.55583333 | U71: 1 | AA71: =N71 -> 1.1116667 | AB71: =O71 -> 0 | AC71: =P71 -> 0 | AD71: =Q71 -> 1.1116667 | AE71: =R71 -> 0.58508246 | AF71: =Q71*R71 -> 0.65041667 | AG71: B | AH71: VS4
A72: 68 | B72: 9977 | C72: WGLRPC-JPN | D72: ReportConnection | E72: sales / insurance recruitment | F72: Customer and Channel Engineering 34961 | G72: Distribution F2F Team 34962 | H72: Core Business Application | I72: N | J72: Yes | K72: JAVA | M72: N | N72: 1 | O72: 1 | P72: 0 | Q72: 0.45791667 | R72: 0 | S72: 0.22895833 | T72: 0.22895833 | U72: 1 | AA72: =N72 -> 1 | AB72: =O72 -> 1 | AC72: =P72 -> 0 | AD72: =Q72 -> 0.45791667 | AE72: =R72 -> 0 | AF72: =Q72*R72 -> 0 | AG72: B | AH72: VS5
A73: 69 | B73: 9980 | C73: Policy UWIBATCH MF-JPN | D73: Policy Underwriting and Issue Batch | E73: contract management | F73: Core Insurance Systems Group 34956 | G73: Policy Admin Systems Team 34957 | H73: Core Business Application | I73: Y | J73: Yes | K73: Other#ASM; Cobol | M73: N | N73: 12.606875 | O73: 1.1416667 | P73: 0 | Q73: 13.748542 | R73: 0.81496522 | S73: 6.8742708 | T73: 6.8742708 | U73: 1 | AA73: =N73 -> 12.606875 | AB73: =O73 -> 1.1416667 | AC73: =P73 -> 0 | AD73: =Q73 -> 13.748542 | AE73: =R73 -> 0.81496522 | AF73: =Q73*R73 -> 11.204583 | AG73: D | AH73: VS5
A74: 70 | B74: 9983 | C74: WAAATF-JPN | D74: Agents Target Following system | E74: sales / insurance recruitment | F74: Customer and Channel Engineering 34961 | G74: Distribution F2F Team 34962 | H74: Core Business Application | I74: N | J74: Yes | K74: JAVA | L74: Platform as a Service (PaaS) | M74: N | N74: 6.6141667 | O74: 0.64791667 | P74: 0 | Q74: 7.2620833 | R74: 0.93912445 | S74: 3.6310417 | T74: 3.6310417 | U74: 1 | AA74: =N74 -> 6.6141667 | AB74: =O74 -> 0.64791667 | AC74: =P74 -> 0 | AD74: =Q74 -> 7.2620833 | AE74: =R74 -> 0.93912445 | AF74: =Q74*R74 -> 6.82 | AG74: B | AH74: VS3
A75: 71 | B75: 9986 | C75: ZGLEST-JPN | D75: eSTATION | E75: corporate related | F75: Core Insurance Systems Group 34956 | G75: Corporate Systems Team 34959 | H75: Core Business Application | I75: N | J75: Yes | K75: JavaScript; VB.NET; C#;HTML | M75: N | N75: 2.4426667 | O75: 0.57083333 | P75: 0 | Q75: 3.0135 | R75: 0.27515071 | S75: 1.50675 | T75: 1.50675 | U75: 1 | AA75: =N75 -> 2.4426667 | AB75: =O75 -> 0.57083333 | AC75: =P75 -> 0 | AD75: =Q75 -> 3.0135 | AE75: =R75 -> 0.27515071 | AF75: =Q75*R75 -> 0.82916667 | AG75: B | AH75: VS2
A76: 72 | B76: 9992 | C76: CMESB-JPN | D76: Enterprise Service Bus | E76: common service platform | F76: Japan Platform Team 35775 | G76: Japan Platform Team 35775 | H76: Common Service Business Application | I76: N | J76: Yes | K76: JAVA; Other#ESQL | M76: N | N76: 7.2083333 | O76: 2.9958333 | P76: 2.5208333 | Q76: 12.725 | R76: 0.93778651 | S76: 6.3625 | T76: 6.3625 | U76: 1 | AA76: =N76 -> 7.2083333 | AB76: =O76 -> 2.9958333 | AC76: =P76 -> 2.5208333 | AD76: =Q76 -> 12.725 | AE76: =R76 -> 0.93778651 | AF76: =Q76*R76 -> 11.933333 | AG76: B | AH76: VS4
A77: 73 | B77: 9994 | C77: WPMAUD-JPN | D77: Unknown Address Tracking System | E77: storage and preservation related | F77: Customer Service and Operations Systems Group 34965 | G77: Policy Servicing Team 34967 | H77: Core Business Application | I77: N | J77: No | K77: JAVA | L77: Platform as a Service (PaaS) | M77: N | N77: 0.8 | O77: 0.2 | P77: 0 | Q77: 1.1729167 | R77: 0.42806394 | S77: 0.58645833 | T77: 0.58645833 | U77: 1 | AA77: =N77 -> 0.8 | AB77: =O77 -> 0.2 | AC77: =P77 -> 0 | AD77: =Q77 -> 1.1729167 | AE77: =R77 -> 0.42806394 | AF77: =Q77*R77 -> 0.50208333 | AG77: B | AH77: VS2
A78: 74 | B78: 9995 | C78: WCMPXS-JPN | D78: ProductXpress | E78: corporate related | F78: Core Insurance Systems Group 34956 | G78: Corporate Systems Team 34959 | H78: Infrastructure Application | I78: N | J78: Yes | K78: Other#Peculiar Language, Implemented in PX designer. | M78: N | N78: 0.77916667 | O78: 0 | P78: 0 | Q78: 0.77916667 | R78: 0.67914439 | S78: 0.38958333 | T78: 0.38958333 | U78: 1 | AA78: =N78 -> 0.77916667 | AB78: =O78 -> 0 | AC78: =P78 -> 0 | AD78: =Q78 -> 0.77916667 | AE78: =R78 -> 0.67914439 | AF78: =Q78*R78 -> 0.52916667 | AG78: B | AH78: VS5
A79: 75 | B79: 9996 | C79: WUIURE-JPN | D79: Pre-Underwriting | E79: new contract related | F79: Customer Service and Operations Systems Group 34965 | G79: New Business Team 34966 | H79: Core Business Application | I79: N | J79: Yes | K79: JAVA | M79: N | N79: 0.22625 | O79: 0 | P79: 0 | Q79: 0.22625 | R79: 0.33701657 | S79: 0.113125 | T79: 0.113125 | U79: 1 | AA79: =N79 -> 0.22625 | AB79: =O79 -> 0 | AC79: =P79 -> 0 | AD79: =Q79 -> 0.22625 | AE79: =R79 -> 0.33701657 | AF79: =Q79*R79 -> 0.07625 | AG79: B | AH79: VS3
A80: 76 | B80: 9999 | C80: LINC MF-JPN | D80: LINC | E80: contract management | F80: Core Insurance Systems Group 34956 | G80: Policy Admin Systems Team 34957 | H80: Core Business Application | I80: Y | J80: Yes | K80: COBOL, MU(EASYPLUS), Assembler, JCL | M80: N | N80: 1.02875 | O80: 0 | P80: 0 | Q80: 1.02875 | R80: 0.12920211 | S80: 0.514375 | T80: 0.514375 | U80: 1 | AA80: =N80 -> 1.02875 | AB80: =O80 -> 0 | AC80: =P80 -> 0 | AD80: =Q80 -> 1.02875 | AE80: =R80 -> 0.12920211 | AF80: =Q80*R80 -> 0.13291667 | AG80: D | AH80: VS1
A81: 77 | B81: 10001 | C81: A06TOG-JPN | D81: Group Policy Management System | E81: corporate related | F81: Core Insurance Systems Group 34956 | G81: Corporate Systems Team 34959 | H81: Core Business Application | I81: Y | J81: Yes | K81: Other#RPG; Cobol | M81: N | N81: 2.7291667 | O81: 3.025 | P81: 0 | Q81: 5.7541667 | R81: 0.34540188 | S81: 2.8770833 | T81: 2.8770833 | U81: 1 | AA81: =N81 -> 2.7291667 | AB81: =O81 -> 3.025 | AC81: =P81 -> 0 | AD81: =Q81 -> 5.7541667 | AE81: =R81 -> 0.34540188 | AF81: =Q81*R81 -> 1.9875 | AG81: D | AH81: VS6
A82: 78 | B82: 10032 | C82: W06TGR-JPN | D82: Group Policy Inquiry System for Intranet | E82: corporate related | F82: Core Insurance Systems Group 34956 | G82: Corporate Systems Team 34959 | H82: Core Business Application | I82: Y | J82: Yes | K82: VB.NET; JAVA | M82: N | N82: 1.8583333 | O82: 0.94166667 | P82: 0 | Q82: 2.8 | R82: 0.26934524 | S82: 1.4 | T82: 1.4 | U82: 1 | AA82: =N82 -> 1.8583333 | AB82: =O82 -> 0.94166667 | AC82: =P82 -> 0 | AD82: =Q82 -> 2.8 | AE82: =R82 -> 0.26934524 | AF82: =Q82*R82 -> 0.75416667 | AG82: B | AH82: VS4
A83: 79 | B83: 11004 | C83: WAAICM-JPN | D83: ICM | E83: fee management | F83: Core Insurance Systems Group 34956 | G83: Commission Systems Team 34958 | H83: Core Business Application | I83: N | J83: Yes | K83: JAVA; C#; Other#ETL JAVA(ADJP) SQL | L83: Software as a Service (SaaS) | M83: N | N83: 21.506125 | O83: 7.7291667 | P83: 0 | Q83: 29.235292 | R83: 0.83096913 | S83: 14.617646 | T83: 14.617646 | U83: 1 | AA83: =N83 -> 21.506125 | AB83: =O83 -> 7.7291667 | AC83: =P83 -> 0 | AD83: =Q83 -> 29.235292 | AE83: =R83 -> 0.83096913 | AF83: =Q83*R83 -> 24.293625 | AG83: A | AH83: VS1
A84: 80 | B84: 11005 | C84: WAACPS-JPN | D84: Commission and Performance System | E84: corporate related | F84: Core Insurance Systems Group 34956 | G84: Corporate Systems Team 34959 | H84: Core Business Application | I84: N | J84: Yes | K84: JAVA | L84: Platform as a Service (PaaS) | M84: N | N84: 0.3625 | O84: 0.041666667 | P84: 0.5 | Q84: 0.90416667 | R84: 0.44700461 | S84: 0.45208333 | T84: 0.45208333 | U84: 1 | AA84: =N84 -> 0.3625 | AB84: =O84 -> 0.041666667 | AC84: =P84 -> 0.5 | AD84: =Q84 -> 0.90416667 | AE84: =R84 -> 0.44700461 | AF84: =Q84*R84 -> 0.40416667 | AG84: B | AH84: VS4
A85: 81 | B85: 11007 | C85: OMSIKN-JPN | D85: Conservation contract transferring system | E85: corporate related | F85: Core Insurance Systems Group 34956 | G85: Corporate Systems Team 34959 | H85: Core Business Application | I85: N | J85: Yes | K85: JAVA | M85: N | N85: 0.23491667 | O85: 0.072916667 | P85: 0 | Q85: 0.30783333 | R85: 0.95939361 | S85: 0.15391667 | T85: 0.15391667 | U85: 1 | AA85: =N85 -> 0.23491667 | AB85: =O85 -> 0.072916667 | AC85: =P85 -> 0 | AD85: =Q85 -> 0.30783333 | AE85: =R85 -> 0.95939361 | AF85: =Q85*R85 -> 0.29533333 | AG85: B | AH85: VS4
A86: 82 | B86: 11008 | C86: OMSTAT-JPN | D86: Conservation contract allowance system | E86: marketing/direct business related | F86: Customer and Channel Engineering 34961 | G86: Marketing and Leads Team 34964 | H86: Core Business Application | I86: N | J86: Yes | K86: JAVA | M86: N | N86: 0.13541667 | O86: 0.016666667 | P86: 0 | Q86: 0.15208333 | R86: 0.52054795 | S86: 0.076041667 | T86: 0.076041667 | U86: 1 | AA86: =N86 -> 0.13541667 | AB86: =O86 -> 0.016666667 | AC86: =P86 -> 0 | AD86: =Q86 -> 0.15208333 | AE86: =R86 -> 0.52054795 | AF86: =Q86*R86 -> 0.079166667 | AG86: B | AH86: VS3
A87: 83 | B87: 11010 | C87: ZGLEDQ-JPN | D87: FATCA Oracle EDQ | E87: corporate related | F87: Core Insurance Systems Group 34956 | G87: Corporate Systems Team 34959 | H87: Core Business Application | I87: N | J87: Yes | K87: JAVA; C # | L87: Platform as a Service (PaaS) | M87: N | N87: 1.2583333 | O87: 0.029166667 | P87: 0.5 | Q87: 1.7875 | R87: 0.55710956 | S87: 0.89375 | T87: 0.89375 | U87: 1 | AA87: =N87 -> 1.2583333 | AB87: =O87 -> 0.029166667 | AC87: =P87 -> 0.5 | AD87: =Q87 -> 1.7875 | AE87: =R87 -> 0.55710956 | AF87: =Q87*R87 -> 0.99583333 | AG87: B | AH87: VS1
A88: 84 | B88: 11011 | C88: WGLWLF-JPN | D88: Watch List Filtering system | E88: corporate related | F88: Core Insurance Systems Group 34956 | G88: Corporate Systems Team 34959 | H88: Core Business Application | I88: N | J88: Yes | K88: JAVA | M88: N | N88: 6.0791667 | O88: 1.0708333 | P88: 0 | Q88: 7.15 | R88: 0.90384615 | S88: 3.575 | T88: 3.575 | U88: 1 | AA88: =N88 -> 6.0791667 | AB88: =O88 -> 1.0708333 | AC88: =P88 -> 0 | AD88: =Q88 -> 7.15 | AE88: =R88 -> 0.90384615 | AF88: =Q88*R88 -> 6.4625 | AG88: B | AH88: VS3
A89: 85 | B89: 11012 | C89: WZZMNB-JPN | D89: My number management system | E89: insurance claims and benefits payment related | F89: Customer Service and Operations Systems Group 34965 | G89: Claims Team 34968 | H89: Core Business Application | I89: N | J89: Yes | K89: JAVA | M89: N | N89: 1.6523333 | O89: 0.29166667 | P89: 0 | Q89: 1.944 | R89: 0.83217593 | S89: 0.972 | T89: 0.972 | U89: 1 | AA89: =N89 -> 1.6523333 | AB89: =O89 -> 0.29166667 | AC89: =P89 -> 0 | AD89: =Q89 -> 1.944 | AE89: =R89 -> 0.83217593 | AF89: =Q89*R89 -> 1.61775 | AG89: B | AH89: VS3
A90: 86 | B90: 11014 | C90: BCMETL-JPN | D90: Informatica Platform | E90: data infrastructure | F90: Data Platforms Team 34980 | G90: Data Platforms Team 34980 | H90: Common Service Business Application | I90: N | J90: Yes | K90: Other#Used UI for development and stored data as XML | M90: Y | N90: 29.097917 | O90: 6.825 | P90: 6.85 | Q90: 42.772917 | R90: 0.88284058 | S90: 21.386458 | T90: 21.386458 | U90: 1 | AA90: =N90 -> 29.097917 | AB90: =O90 -> 6.825 | AC90: =P90 -> 6.85 | AD90: =Q90 -> 42.772917 | AE90: =R90 -> 0.88284058 | AF90: =Q90*R90 -> 37.761667 | AG90: C | AH90: VS1
A91: 87 | B91: 11203 | C91: WPSCFC-JPN | D91: c-Force | E91: sales / insurance recruitment | F91: Customer and Channel Engineering 34961 | G91: Distribution F2F Team 34962 | H91: Core Business Application | I91: N | J91: No | K91: Other#APEX;HTML; JavaScript | L91: Software as a Service (SaaS) | M91: Y | N91: 20.833333 | O91: 10.004167 | P91: 12.725 | Q91: 43.5625 | R91: 0.86915352 | S91: 21.78125 | T91: 21.78125 | U91: 1 | AA91: =N91 -> 20.833333 | AB91: =O91 -> 10.004167 | AC91: =P91 -> 12.725 | AD91: =Q91 -> 43.5625 | AE91: =R91 -> 0.86915352 | AF91: =Q91*R91 -> 37.8625 | AG91: C | AH91: VS3
A92: 88 | B92: 11288 | C92: CGLFJM-JPN | D92: Misconduct Management system | E92: corporate related | F92: Core Insurance Systems Group 34956 | G92: Corporate Systems Team 34959 | H92: Core Business Application | I92: N | J92: Yes | K92: VB | M92: N | N92: 0.091666667 | O92: 0 | P92: 0 | Q92: 0.091666667 | R92: 0.27272727 | S92: 0.045833333 | T92: 0.045833333 | U92: 1 | AA92: =N92 -> 0.091666667 | AB92: =O92 -> 0 | AC92: =P92 -> 0 | AD92: =Q92 -> 0.091666667 | AE92: =R92 -> 0.27272727 | AF92: =Q92*R92 -> 0.025 | AG92: B | AH92: VS3
A93: 89 | B93: 11308 | C93: WGLBSR-JPN | D93: BSRec | E93: corporate related | F93: Core Insurance Systems Group 34956 | G93: Corporate Systems Team 34959 | H93: Core Business Application | I93: N | J93: Yes | K93: JAVA | M93: N | N93: 0.48125 | O93: 0.0625 | P93: 0 | Q93: 0.54375 | R93: 0.37931034 | S93: 0.271875 | T93: 0.271875 | U93: 1 | AA93: =N93 -> 0.48125 | AB93: =O93 -> 0.0625 | AC93: =P93 -> 0 | AD93: =Q93 -> 0.54375 | AE93: =R93 -> 0.37931034 | AF93: =Q93*R93 -> 0.20625 | AG93: B | AH93: VS1
A94: 90 | B94: 11604 | C94: JP-RPASS | D94: JAPAN_BluePrism RPA | E94: storage and preservation related | F94: Customer Service and Operations Systems Group 34965 | G94: Policy Servicing Team 34967 | H94: Common Service Business Application | I94: N | J94: Yes | K94: Other#COTS from BluePrism | M94: N | N94: 5.6624583 | O94: 4.075 | P94: 0 | Q94: 9.7374583 | R94: 0.8973038 | S94: 4.8687292 | T94: 4.8687292 | U94: 1 | AA94: =N94 -> 5.6624583 | AB94: =O94 -> 4.075 | AC94: =P94 -> 0 | AD94: =Q94 -> 9.7374583 | AE94: =R94 -> 0.8973038 | AF94: =Q94*R94 -> 8.7374583 | AG94: B | AH94: VS3
A95: 91 | B95: 11893 | C95: W03CCP-JPN | D95: Customer Communication Preferences | E95: storage and preservation related | F95: Customer Service and Operations Systems Group 34965 | G95: Policy Servicing Team 34967 | H95: Core Business Application | I95: N | J95: Yes | K95: JAVA | L95: Platform as a Service (PaaS) | M95: N | N95: 0.2 | O95: 0.2 | P95: 0 | Q95: 0.35416667 | R95: 0.56470588 | S95: 0.17708333 | T95: 0.17708333 | U95: 1 | AA95: =N95 -> 0.2 | AB95: =O95 -> 0.2 | AC95: =P95 -> 0 | AD95: =Q95 -> 0.35416667 | AE95: =R95 -> 0.56470588 | AF95: =Q95*R95 -> 0.2 | AG95: B | AH95: VS4
A96: 92 | B96: 11986 | C96: JP-Banca Report | D96: Japan Banca Report | E96: sales / insurance recruitment | F96: Customer and Channel Engineering 34961 | G96: Distribution Banca Team 34963 | H96: Common Service Business Application | I96: N | J96: Yes | K96: JAVA | L96: Infrastructure as a Service (IaaS); Platform as a Service (PaaS) | M96: N | N96: 6 | O96: 6 | P96: 3 | Q96: 15 | R96: 1 | S96: 7.5 | T96: 7.5 | U96: 1 | AA96: =N96 -> 6 | AB96: =O96 -> 6 | AC96: =P96 -> 3 | AD96: =Q96 -> 15 | AE96: =R96 -> 1 | AF96: =Q96*R96 -> 15 | AG96: B | AH96: VS2
A97: 93 | B97: 12021 | C97: LPS-JPN(EUC081) | D97: Life Plan Simulation Japan | E97: marketing/direct business related | F97: Customer and Channel Engineering 34961 | G97: Marketing and Leads Team 34964 | H97: Core Business Application | I97: N | J97: Yes | K97: PHP | M97: N | N97: 0 | O97: 0 | P97: 0 | Q97: 0 | R97: 0 | U97: 1 | AA97: =N97 -> 0 | AB97: =O97 -> 0 | AC97: =P97 -> 0 | AD97: =Q97 -> 0 | AE97: =R97 -> 0 | AF97: =Q97*R97 -> 0 | AG97: B | AH97: VS2
A98: 94 | B98: 12030 | C98: CIT-JPN(EUC082) | D98: Inheritance Tax Simulation | E98: marketing/direct business related | F98: Customer and Channel Engineering 34961 | G98: Marketing and Leads Team 34964 | H98: Core Business Application | I98: N | J98: Yes | K98: JAVA | M98: N | N98: 0 | O98: 0 | P98: 0 | Q98: 0 | R98: 0 | U98: 1 | AA98: =N98 -> 0 | AB98: =O98 -> 0 | AC98: =P98 -> 0 | AD98: =Q98 -> 0 | AE98: =R98 -> 0 | AF98: =Q98*R98 -> 0 | AG98: B | AH98: VS2
A99: 95 | B99: 12038 | C99: CMIAPI-JPN | D99: API Hub | E99: common service platform | F99: Japan Platform Team 35775 | G99: Japan Platform Team 35775 | H99: Common Service Business Application | I99: N | J99: Yes | K99: JAVA | L99: Platform as a Service (PaaS) | M99: N | N99: 19.246667 | O99: 4.1333333 | P99: 16.910417 | Q99: 40.290417 | R99: 0.94847824 | S99: 20.145208 | T99: 20.145208 | U99: 1 | AA99: =N99 -> 19.246667 | AB99: =O99 -> 4.1333333 | AC99: =P99 -> 16.910417 | AD99: =Q99 -> 40.290417 | AE99: =R99 -> 0.94847824 | AF99: =Q99*R99 -> 38.214583 | AG99: B | AH99: VS3
A100: 96 | B100: 12117 | C100: K2 | D100: Japan K2 - Digital Workflows | E100: storage and preservation related | F100: Customer Service and Operations Systems Group 34965 | G100: Policy Servicing Team 34967 | H100: Core Business Application | I100: Y | J100: Yes | K100: VB.NET | M100: N | N100: 6 | O100: 15.5375 | P100: 11 | Q100: 62.642375 | R100: 0.8631983 | S100: 31.321188 | T100: 31.321188 | U100: 1 | AA100: =N100 -> 6 | AB100: =O100 -> 15.5375 | AC100: =P100 -> 11 | AD100: =Q100 -> 62.642375 | AE100: =R100 -> 0.8631983 | AF100: =Q100*R100 -> 54.072792 | AG100: B | AH100: VS1
A101: 97 | B101: 12198 | C101: JP-PCI-RPASS | D101: Japan PCI Robotics Process Automation Service | E101: storage and preservation related | F101: Customer Service and Operations Systems Group 34965 | G101: Policy Servicing Team 34967 | H101: Common Service Business Application | I101: N | J101: Yes | K101: Other#This is coded within blueprism | M101: N | N101: 1 | O101: 2 | P101: 0 | Q101: 3 | R101: 0 | S101: 1.5 | T101: 1.5 | U101: 1 | AA101: =N101 -> 1 | AB101: =O101 -> 2 | AC101: =P101 -> 0 | AD101: =Q101 -> 3 | AE101: =R101 -> 0 | AF101: =Q101*R101 -> 0 | AG101: B | AH101: VS3
A102: 98 | B102: 12520 | C102: RBRARS-JPN | D102: RBWF Report Automatic Recognition System | E102: new contract related | F102: Customer Service and Operations Systems Group 34965 | G102: New Business Team 34966 | H102: Core Business Application | I102: N | J102: Yes | K102: JAVA | M102: N | N102: 0.125 | O102: 0 | P102: 0 | Q102: 0.125 | R102: 1 | S102: 0.0625 | T102: 0.0625 | U102: 1 | AA102: =N102 -> 0.125 | AB102: =O102 -> 0 | AC102: =P102 -> 0 | AD102: =Q102 -> 0.125 | AE102: =R102 -> 1 | AF102: =Q102*R102 -> 0.125 | AG102: B | AH102: VS5
A103: 99 | B103: 12527 | C103: CMEAPI-JP | D103: Japan Partner API | E103: common service platform | F103: Japan Platform Team 35775 | G103: Japan Platform Team 35775 | H103: Common Service Business Application | I103: N | J103: Yes | K103: JAVA | L103: Platform as a Service (PaaS) | M103: N | N103: 0.10833333 | O103: 0 | P103: 0.025 | Q103: 0.13333333 | R103: 1 | S103: 0.066666667 | T103: 0.066666667 | U103: 1 | AA103: =N103 -> 0.10833333 | AB103: =O103 -> 0 | AC103: =P103 -> 0.025 | AD103: =Q103 -> 0.13333333 | AE103: =R103 -> 1 | AF103: =Q103*R103 -> 0.13333333 | AG103: B | AH103: VS3
A104: 100 | B104: 12607 | C104: JP-WCMAUT | D104: JP Authentication Platform | E104: common service platform | F104: Japan Platform Team 35775 | G104: Japan Platform Team 35775 | H104: Common Service Business Application | I104: N | J104: Yes | K104: JAVA | L104: Platform as a Service (PaaS) | M104: N | N104: 1.3375 | O104: 0 | P104: 1 | Q104: 2.3375 | R104: 1 | S104: 1.16875 | T104: 1.16875 | U104: 1 | AA104: =N104 -> 1.3375 | AB104: =O104 -> 0 | AC104: =P104 -> 1 | AD104: =Q104 -> 2.3375 | AE104: =R104 -> 1 | AF104: =Q104*R104 -> 2.3375 | AG104: B | AH104: VS1
...

Sheet Value Streams
A1: Fee management — three functional value streams
A2: Reconciles to the fee management domain's 5 applications and 48.5 effort units. Every application sits in one and only one stream. Two apps (Global Sales Comp - Japan, Commission Calculation Service) carry zero current effort and reconcile here but add no pod headcount.
B4: Code | C4: Value stream | D4: Apps | E4: Effort | F4: AD effort | G4: AMS effort | H4: AD share | I4: Y1 co-src pods | J4: Y1 full-src pods | K4: Y1 people
B5: VS1 | C5: Incentive Compensation Calculation | D5: =SUMIFS(Inventory!$U:$U,Inventory!$E:$E,"fee management",Inventory!$AH:$AH,$B5) -> 2 | E5: =SUMIFS(Inventory!$AD:$AD,Inventory!$E:$E,"fee management",Inventory!$AH:$AH,$B5) -> 29.235292 | F5: =SUMIFS(Inventory!$AF:$AF,Inventory!$E:$E,"fee management",Inventory!$AH:$AH,$B5) -> 24.293625 | G5: =E5-F5 -> 4.9416667 | H5: =IF(E5=0,0,F5/E5) -> 0.83096913 | I5: =SUMIFS('Pod Plan'!$E:$E,'Pod Plan'!$B:$B,1,'Pod Plan'!$C:$C,$B5) -> 3 | J5: =SUMIFS('Pod Plan'!$F:$F,'Pod Plan'!$B:$B,1,'Pod Plan'!$C:$C,$B5) -> 2 | K5: ='Pod Plan'!H5 -> 26
B6: VS2 | C6: Compensation Administration & Reporting | D6: =SUMIFS(Inventory!$U:$U,Inventory!$E:$E,"fee management",Inventory!$AH:$AH,$B6) -> 1 | E6: =SUMIFS(Inventory!$AD:$AD,Inventory!$E:$E,"fee management",Inventory!$AH:$AH,$B6) -> 16.316667 | F6: =SUMIFS(Inventory!$AF:$AF,Inventory!$E:$E,"fee management",Inventory!$AH:$AH,$B6) -> 16.116667 | G6: =E6-F6 -> 0.2 | H6: =IF(E6=0,0,F6/E6) -> 0.98774259 | I6: =SUMIFS('Pod Plan'!$E:$E,'Pod Plan'!$B:$B,1,'Pod Plan'!$C:$C,$B6) -> 2 | J6: =SUMIFS('Pod Plan'!$F:$F,'Pod Plan'!$B:$B,1,'Pod Plan'!$C:$C,$B6) -> 1 | K6: ='Pod Plan'!H6 -> 16
B7: VS3 | C7: Distributor Portal & Commission Services | D7: =SUMIFS(Inventory!$U:$U,Inventory!$E:$E,"fee management",Inventory!$AH:$AH,$B7) -> 2 | E7: =SUMIFS(Inventory!$AD:$AD,Inventory!$E:$E,"fee management",Inventory!$AH:$AH,$B7) -> 2.9583333 | F7: =SUMIFS(Inventory!$AF:$AF,Inventory!$E:$E,"fee management",Inventory!$AH:$AH,$B7) -> 2.7083333 | G7: =E7-F7 -> 0.25 | H7: =IF(E7=0,0,F7/E7) -> 0.91549296 | I7: =SUMIFS('Pod Plan'!$E:$E,'Pod Plan'!$B:$B,1,'Pod Plan'!$C:$C,$B7) -> 0 | J7: =SUMIFS('Pod Plan'!$F:$F,'Pod Plan'!$B:$B,1,'Pod Plan'!$C:$C,$B7) -> 1 | K7: ='Pod Plan'!H7 -> 3
C8: Total | D8: =SUM(D5:D7) -> 5 | E8: =SUM(E5:E7) -> 48.510292 | F8: =SUM(F5:F7) -> 43.118625 | G8: =SUM(G5:G7) -> 5.3916667 | H8: =IF(E8=0,0,F8/E8) -> 0.8888552 | I8: =SUM(I5:I7) -> 5 | J8: =SUM(J5:J7) -> 4 | K8: =SUM(K5:K7) -> 45
C13: Application-to-value-stream mapping
B14: Value stream | C14: Applications
B15: VS1 | C15: ITS-PCIS (Mutual Fund System, incl. Bestway) · FATCA Oracle EDQ · BSRec · Variable Insurance Guarantee Calculation System (Vcalc)
B16: VS2 | C16: Report Template Management System · eSTATION · Japan Payroll System · Business Content Management · kintone and paperlogic electronic contract system · Commission System Support Tool
B17: VS3 | C17: Guidance Refusal Information Administration System · Watch List Filtering system · Misconduct Management system
B18: VS4 | C18: Conservation Contact Personnel Entry System · Commission Inquiry · Career Information System · Producers Information Entry System · Web Work Flow · Call Control System · New Submit Online System · Group Policy Inquiry System for Intranet · Commission and Performance System · Conservation Contract Transferring System
B19: VS5 | C19: Apollocs · .NET Common Infrastructure · Dr.SUM · ProductXpress · ASP Bridge (Open) · OpenBatch System for Corporate · Retirement Allowance Payment System
B20: VS6 | C20: Voucher Approval System for AS400 · AS400 Mass Marketing System · Group Policy Management System

Sheet Pod Library
A1: Pod library — every seat, by year, value stream and pod type
A2: INPUT. One shared seat template per value stream per pod type per year; Pod Plan's co-sourced/fully-sourced pod counts multiply it out. VS1 and VS2 use the standard modern-stack CO/FS templates, sized to their real effort share. VS3's real footprint is tiny (2.96 effort units, one live app) so it gets a single lean fully-sourced pod instead — no co-sourced pod, no dedicated product-owner seats. The one MGCC seat sits in VS3, reflecting External Portal's real current MGCC use; VS1/VS2 stay FTC/FTE only, matching this domain's near-zero real MGCC baseline.
B4: Year | C4: VS | D4: Pod type | E4: Role | F4: Skill | G4: Exp | H4: Location | I4: Sourcing | J4: Count
B5: 1 | C5: VS1 | D5: CO | E5: Product Owner | F5: LEAD | G5: E4 | H5: ON | I5: FTE | J5: 1
B6: 1 | C6: VS1 | D6: CO | E6: Incentive Compensation SME | F6: BA | G6: E4 | H6: ON | I6: FTE | J6: 1
B7: 1 | C7: VS1 | D7: CO | E7: Application Owner (Technical) | F7: ENG | G7: E4 | H7: ON | I7: FTE | J7: 1
B8: 1 | C8: VS1 | D8: CO | E8: Pod Delivery Lead | F8: LEAD | G8: E4 | H8: ON | I8: FTC | J8: 1
B9: 1 | C9: VS1 | D9: CO | E9: Senior Developer | F9: DEV | G9: E3 | H9: OFF | I9: FTC | J9: 1
B10: 1 | C10: VS1 | D10: CO | E10: QA / Test Engineer | F10: TEST | G10: E2 | H10: OFF | I10: FTC | J10: 1
E11: Pod size — Year 1 VS1 co-sourced | J11: =SUM(J5:J10) -> 6
B12: 1 | C12: VS1 | D12: FS | E12: Pod Lead (output owner) | F12: LEAD | G12: E4 | H12: ON | I12: FTC | J12: 1
B13: 1 | C13: VS1 | D13: FS | E13: Developer | F13: DEV | G13: E3 | H13: OFF | I13: FTC | J13: 1
B14: 1 | C14: VS1 | D14: FS | E14: Developer | F14: DEV | G14: E2 | H14: OFF | I14: FTC | J14: 1
B15: 1 | C15: VS1 | D15: FS | E15: QA Engineer | F15: TEST | G15: E2 | H15: OFF | I15: FTC | J15: 1
E16: Pod size — Year 1 VS1 fully-sourced | J16: =SUM(J12:J15) -> 4
B18: 1 | C18: VS2 | D18: CO | E18: Product Owner | F18: LEAD | G18: E4 | H18: ON | I18: FTE | J18: 1
B19: 1 | C19: VS2 | D19: CO | E19: Compensation Administration SME | F19: BA | G19: E4 | H19: ON | I19: FTE | J19: 1
B20: 1 | C20: VS2 | D20: CO | E20: Application Owner (Technical) | F20: ENG | G20: E4 | H20: ON | I20: FTE | J20: 1
B21: 1 | C21: VS2 | D21: CO | E21: Pod Delivery Lead | F21: LEAD | G21: E4 | H21: ON | I21: FTC | J21: 1
B22: 1 | C22: VS2 | D22: CO | E22: Senior Developer | F22: DEV | G22: E3 | H22: OFF | I22: FTC | J22: 1
B23: 1 | C23: VS2 | D23: CO | E23: QA / Test Engineer | F23: TEST | G23: E2 | H23: OFF | I23: FTC | J23: 1
E24: Pod size — Year 1 VS2 co-sourced | J24: =SUM(J18:J23) -> 6
B25: 1 | C25: VS2 | D25: FS | E25: Pod Lead (output owner) | F25: LEAD | G25: E4 | H25: ON | I25: FTC | J25: 1
B26: 1 | C26: VS2 | D26: FS | E26: Developer | F26: DEV | G26: E3 | H26: OFF | I26: FTC | J26: 1
B27: 1 | C27: VS2 | D27: FS | E27: Developer | F27: DEV | G27: E2 | H27: OFF | I27: FTC | J27: 1
B28: 1 | C28: VS2 | D28: FS | E28: QA Engineer | F28: TEST | G28: E2 | H28: OFF | I28: FTC | J28: 1
E29: Pod size — Year 1 VS2 fully-sourced | J29: =SUM(J25:J28) -> 4
B31: 1 | C31: VS3 | D31: FS | E31: Pod Lead (output owner) | F31: LEAD | G31: E4 | H31: ON | I31: FTC | J31: 1
B32: 1 | C32: VS3 | D32: FS | E32: Developer — MGCC Hyderabad | F32: DEV | G32: E3 | H32: OFF | I32: MGCC | J32: 1
B33: 1 | C33: VS3 | D33: FS | E33: QA Engineer | F33: TEST | G33: E2 | H33: OFF | I33: FTC | J33: 1
E34: Pod size — Year 1 VS3 fully-sourced | J34: =SUM(J31:J33) -> 3
B36: 2 | C36: VS1 | D36: CO | E36: Product Owner | F36: LEAD | G36: E4 | H36: ON | I36: FTE | J36: 1
B37: 2 | C37: VS1 | D37: CO | E37: Incentive Compensation SME | F37: BA | G37: E4 | H37: ON | I37: FTE | J37: 1
B38: 2 | C38: VS1 | D38: CO | E38: Application Owner (Technical) | F38: ENG | G38: E4 | H38: ON | I38: FTE | J38: 1
B39: 2 | C39: VS1 | D39: CO | E39: AI-assisted Developer | F39: DEV | G39: E3 | H39: OFF | I39: FTC | J39: 1
B40: 2 | C40: VS1 | D40: CO | E40: Quality Engineer (SDET) | F40: TEST | G40: E3 | H40: OFF | I40: FTC | J40: 1
E41: Pod size — Year 2 VS1 co-sourced | J41: =SUM(J36:J40) -> 5
B42: 2 | C42: VS1 | D42: FS | E42: Pod Lead / AI Orchestrator | F42: LEAD | G42: E4 | H42: OFF | I42: FTC | J42: 1
B43: 2 | C43: VS1 | D43: FS | E43: AI-assisted Developer | F43: DEV | G43: E3 | H43: OFF | I43: FTC | J43: 1
B44: 2 | C44: VS1 | D44: FS | E44: QA Engineer | F44: TEST | G44: E2 | H44: OFF | I44: FTC | J44: 1
E45: Pod size — Year 2 VS1 fully-sourced | J45: =SUM(J42:J44) -> 3
B47: 2 | C47: VS2 | D47: CO | E47: Product Owner | F47: LEAD | G47: E4 | H47: ON | I47: FTE | J47: 1
B48: 2 | C48: VS2 | D48: CO | E48: Compensation Administration SME | F48: BA | G48: E4 | H48: ON | I48: FTE | J48: 1
B49: 2 | C49: VS2 | D49: CO | E49: Application Owner (Technical) | F49: ENG | G49: E4 | H49: ON | I49: FTE | J49: 1
B50: 2 | C50: VS2 | D50: CO | E50: AI-assisted Developer | F50: DEV | G50: E3 | H50: OFF | I50: FTC | J50: 1
B51: 2 | C51: VS2 | D51: CO | E51: Quality Engineer (SDET) | F51: TEST | G51: E3 | H51: OFF | I51: FTC | J51: 1
E52: Pod size — Year 2 VS2 co-sourced | J52: =SUM(J47:J51) -> 5
B53: 2 | C53: VS2 | D53: FS | E53: Pod Lead / AI Orchestrator | F53: LEAD | G53: E4 | H53: OFF | I53: FTC | J53: 1
B54: 2 | C54: VS2 | D54: FS | E54: AI-assisted Developer | F54: DEV | G54: E3 | H54: OFF | I54: FTC | J54: 1
B55: 2 | C55: VS2 | D55: FS | E55: QA Engineer | F55: TEST | G55: E2 | H55: OFF | I55: FTC | J55: 1
E56: Pod size — Year 2 VS2 fully-sourced | J56: =SUM(J53:J55) -> 3
B58: 2 | C58: VS3 | D58: FS | E58: Pod Lead / AI Orchestrator | F58: LEAD | G58: E4 | H58: OFF | I58: FTC | J58: 1
B59: 2 | C59: VS3 | D59: FS | E59: AI-assisted Developer — MGCC Hyderabad | F59: DEV | G59: E3 | H59: OFF | I59: MGCC | J59: 1
E60: Pod size — Year 2 VS3 fully-sourced | J60: =SUM(J58:J59) -> 2
B62: 3 | C62: VS1 | D62: CO | E62: Product Owner | F62: LEAD | G62: E4 | H62: ON | I62: FTE | J62: 1
B63: 3 | C63: VS1 | D63: CO | E63: Incentive Compensation SME | F63: BA | G63: E4 | H63: ON | I63: FTE | J63: 1
B64: 3 | C64: VS1 | D64: CO | E64: Application Owner (Technical) | F64: ENG | G64: E4 | H64: ON | I64: FTE | J64: 1
B65: 3 | C65: VS1 | D65: CO | E65: AI Orchestrator / Developer | F65: ENG | G65: E3 | H65: OFF | I65: FTC | J65: 1
E66: Pod size — Year 3 VS1 co-sourced | J66: =SUM(J62:J65) -> 4
B67: 3 | C67: VS1 | D67: FS | E67: AI Orchestrator | F67: ENG | G67: E4 | H67: OFF | I67: FTC | J67: 1
B68: 3 | C68: VS1 | D68: FS | E68: AI-assisted Developer | F68: DEV | G68: E3 | H68: OFF | I68: FTC | J68: 1
E69: Pod size — Year 3 VS1 fully-sourced | J69: =SUM(J67:J68) -> 2
B71: 3 | C71: VS2 | D71: CO | E71: Product Owner | F71: LEAD | G71: E4 | H71: ON | I71: FTE | J71: 1
B72: 3 | C72: VS2 | D72: CO | E72: Compensation Administration SME | F72: BA | G72: E4 | H72: ON | I72: FTE | J72: 1
B73: 3 | C73: VS2 | D73: CO | E73: Application Owner (Technical) | F73: ENG | G73: E4 | H73: ON | I73: FTE | J73: 1
B74: 3 | C74: VS2 | D74: CO | E74: AI Orchestrator / Developer | F74: ENG | G74: E3 | H74: OFF | I74: FTC | J74: 1
E75: Pod size — Year 3 VS2 co-sourced | J75: =SUM(J71:J74) -> 4
B76: 3 | C76: VS2 | D76: FS | E76: AI Orchestrator | F76: ENG | G76: E4 | H76: OFF | I76: FTC | J76: 1
B77: 3 | C77: VS2 | D77: FS | E77: AI-assisted Developer | F77: DEV | G77: E3 | H77: OFF | I77: FTC | J77: 1
E78: Pod size — Year 3 VS2 fully-sourced | J78: =SUM(J76:J77) -> 2
B80: 3 | C80: VS3 | D80: FS | E80: AI Orchestrator — MGCC Hyderabad | F80: ENG | G80: E3 | H80: OFF | I80: MGCC | J80: 1
E81: Pod size — Year 3 VS3 fully-sourced | J81: =SUM(J80:J80) -> 1

Sheet Pod Plan
A1: Pod plan — how many pods each value stream runs, each year
A2: INPUT SHEET. Fewer pods and smaller pods is how productivity shows up in the headcount. Nothing else reduces it.
B4: Year | C4: VS | D4: Value stream | E4: Co-sourced pods | F4: Fully-sourced pods | G4: Pods | H4: People
B5: 1 | C5: VS1 | D5: Incentive Compensation Calculation | E5: 3 | F5: 2 | G5: =E5+F5 -> 5 | H5: =E5*SUMIFS('Pod Library'!$J:$J,'Pod Library'!$B:$B,$B5,'Pod Library'!$C:$C,$C5,'Pod Library'!$D:$D,"CO")+F5*SUMIFS('Pod Library'!$J:$J,'Pod Library'!$B:$B,$B5,'Pod Library'!$C:$C,$C5,'Pod Library'!$D:$D,"FS") -> 26
B6: 1 | C6: VS2 | D6: Compensation Administration & Reporting | E6: 2 | F6: 1 | G6: =E6+F6 -> 3 | H6: =E6*SUMIFS('Pod Library'!$J:$J,'Pod Library'!$B:$B,$B6,'Pod Library'!$C:$C,$C6,'Pod Library'!$D:$D,"CO")+F6*SUMIFS('Pod Library'!$J:$J,'Pod Library'!$B:$B,$B6,'Pod Library'!$C:$C,$C6,'Pod Library'!$D:$D,"FS") -> 16
B7: 1 | C7: VS3 | D7: Distributor Portal & Commission Services | E7: 0 | F7: 1 | G7: =E7+F7 -> 1 | H7: =E7*SUMIFS('Pod Library'!$J:$J,'Pod Library'!$B:$B,$B7,'Pod Library'!$C:$C,$C7,'Pod Library'!$D:$D,"CO")+F7*SUMIFS('Pod Library'!$J:$J,'Pod Library'!$B:$B,$B7,'Pod Library'!$C:$C,$C7,'Pod Library'!$D:$D,"FS") -> 3
D8: Year 1 total | E8: =SUM(E5:E7) -> 5 | F8: =SUM(F5:F7) -> 4 | G8: =SUM(G5:G7) -> 9 | H8: =SUM(H5:H7) -> 45
B10: 2 | C10: VS1 | D10: Incentive Compensation Calculation | E10: 3 | F10: 2 | G10: =E10+F10 -> 5 | H10: =E10*SUMIFS('Pod Library'!$J:$J,'Pod Library'!$B:$B,$B10,'Pod Library'!$C:$C,$C10,'Pod Library'!$D:$D,"CO")+F10*SUMIFS('Pod Library'!$J:$J,'Pod Library'!$B:$B,$B10,'Pod Library'!$C:$C,$C10,'Pod Library'!$D:$D,"FS") -> 21
B11: 2 | C11: VS2 | D11: Compensation Administration & Reporting | E11: 2 | F11: 1 | G11: =E11+F11 -> 3 | H11: =E11*SUMIFS('Pod Library'!$J:$J,'Pod Library'!$B:$B,$B11,'Pod Library'!$C:$C,$C11,'Pod Library'!$D:$D,"CO")+F11*SUMIFS('Pod Library'!$J:$J,'Pod Library'!$B:$B,$B11,'Pod Library'!$C:$C,$C11,'Pod Library'!$D:$D,"FS") -> 13
B12: 2 | C12: VS3 | D12: Distributor Portal & Commission Services | E12: 0 | F12: 1 | G12: =E12+F12 -> 1 | H12: =E12*SUMIFS('Pod Library'!$J:$J,'Pod Library'!$B:$B,$B12,'Pod Library'!$C:$C,$C12,'Pod Library'!$D:$D,"CO")+F12*SUMIFS('Pod Library'!$J:$J,'Pod Library'!$B:$B,$B12,'Pod Library'!$C:$C,$C12,'Pod Library'!$D:$D,"FS") -> 2
D13: Year 2 total | E13: =SUM(E10:E12) -> 5 | F13: =SUM(F10:F12) -> 4 | G13: =SUM(G10:G12) -> 9 | H13: =SUM(H10:H12) -> 36
B15: 3 | C15: VS1 | D15: Incentive Compensation Calculation | E15: 3 | F15: 2 | G15: =E15+F15 -> 5 | H15: =E15*SUMIFS('Pod Library'!$J:$J,'Pod Library'!$B:$B,$B15,'Pod Library'!$C:$C,$C15,'Pod Library'!$D:$D,"CO")+F15*SUMIFS('Pod Library'!$J:$J,'Pod Library'!$B:$B,$B15,'Pod Library'!$C:$C,$C15,'Pod Library'!$D:$D,"FS") -> 16
B16: 3 | C16: VS2 | D16: Compensation Administration & Reporting | E16: 2 | F16: 1 | G16: =E16+F16 -> 3 | H16: =E16*SUMIFS('Pod Library'!$J:$J,'Pod Library'!$B:$B,$B16,'Pod Library'!$C:$C,$C16,'Pod Library'!$D:$D,"CO")+F16*SUMIFS('Pod Library'!$J:$J,'Pod Library'!$B:$B,$B16,'Pod Library'!$C:$C,$C16,'Pod Library'!$D:$D,"FS") -> 10
B17: 3 | C17: VS3 | D17: Distributor Portal & Commission Services | E17: 0 | F17: 1 | G17: =E17+F17 -> 1 | H17: =E17*SUMIFS('Pod Library'!$J:$J,'Pod Library'!$B:$B,$B17,'Pod Library'!$C:$C,$C17,'Pod Library'!$D:$D,"CO")+F17*SUMIFS('Pod Library'!$J:$J,'Pod Library'!$B:$B,$B17,'Pod Library'!$C:$C,$C17,'Pod Library'!$D:$D,"FS") -> 1
D18: Year 3 total | E18: =SUM(E15:E17) -> 5 | F18: =SUM(F15:F17) -> 4 | G18: =SUM(G15:G17) -> 9 | H18: =SUM(H15:H17) -> 27

Sheet Horizontal Teams
A1: Horizontal teams — work that is not value-stream bounded
A2: INPUT. Real cross-stream functions for a fee/compensation domain: compensation plan administration & governance, calculation QA & audit, regulatory/compliance support for fee and commission rules, and a small architecture & governance core. Kept lean given this domain's small overall scale.
B5: 1 | C5: H1 | D5: Compensation Plan Administration & Governance | E5: Compensation Plan Administration Lead | F5: LEAD | G5: E4 | H5: ON | I5: FTC | J5: 1
E6: H1 total | J6: =SUM(J5:J5) -> 1
B7: 1 | C7: H2 | D7: Calculation QA & Audit | E7: Calculation QA & Audit Analyst | F7: TEST | G7: E3 | H7: OFF | I7: FTC | J7: 1
E8: H2 total | J8: =SUM(J7:J7) -> 1
B9: 1 | C9: H3 | D9: Regulatory / Compliance Support | E9: Compliance & Regulatory Analyst (Fee & Commission Rules) | F9: BA | G9: E3 | H9: ON | I9: FTC | J9: 1
E10: H3 total | J10: =SUM(J9:J9) -> 1
B11: 1 | C11: H4 | D11: Architecture & Governance | E11: Domain Delivery Head | F11: LEAD | G11: E5 | H11: ON | I11: FTC | J11: 1
B12: 1 | C12: H4 | D12: Architecture & Governance | E12: Chief Fee Systems Architect (MetLife) | F12: ENG | G12: E5 | H12: ON | I12: FTE | J12: 1
E13: H4 total | J13: =SUM(J11:J12) -> 2
E14: Year 1 horizontal total | J14: =SUMIFS($J$5:$J$13,$B$5:$B$13,1) -> 5
B16: 2 | C16: H1 | D16: Compensation Plan Administration & Governance | E16: Compensation Plan Administration Lead | F16: LEAD | G16: E4 | H16: ON | I16: FTC | J16: 1
E17: H1 total | J17: =SUM(J16:J16) -> 1
B18: 2 | C18: H2 | D18: Calculation QA & Audit | E18: Calculation QA & Audit Analyst | F18: TEST | G18: E3 | H18: OFF | I18: FTC | J18: 1
E19: H2 total | J19: =SUM(J18:J18) -> 1
B20: 2 | C20: H4 | D20: Architecture & Governance | E20: Domain Delivery Head | F20: LEAD | G20: E5 | H20: ON | I20: FTC | J20: 1
B21: 2 | C21: H4 | D21: Architecture & Governance | E21: Chief Fee Systems Architect (MetLife) | F21: ENG | G21: E5 | H21: ON | I21: FTE | J21: 1
E22: H4 total | J22: =SUM(J20:J21) -> 2
E23: Year 2 horizontal total | J23: =SUMIFS($J$16:$J$22,$B$16:$B$22,2) -> 4
B25: 3 | C25: H1 | D25: Compensation Plan Administration & Governance | E25: Compensation Plan Administration Lead | F25: LEAD | G25: E4 | H25: OFF | I25: FTC | J25: 1
E26: H1 total | J26: =SUM(J25:J25) -> 1
B27: 3 | C27: H4 | D27: Architecture & Governance | E27: Domain Delivery Head | F27: LEAD | G27: E5 | H27: OFF | I27: FTC | J27: 1
B28: 3 | C28: H4 | D28: Architecture & Governance | E28: Chief Fee Systems Architect (MetLife) | F28: ENG | G28: E5 | H28: ON | I28: FTE | J28: 1
E29: H4 total | J29: =SUM(J27:J28) -> 2
E30: Year 3 horizontal total | J30: =SUMIFS($J$25:$J$29,$B$25:$B$29,3) -> 3

Sheet Team Build-Up
A1: Team build-up — headcount, sourcing, location, experience and skill, all derived from the seat ledger
A2: Nothing on this sheet is typed. Change a seat on Pod Library or a pod count on Pod Plan and every figure here moves.
A4: A. POD SIZES (read from the Pod Library)
B5: Pod size (avg per VS running that pod type — CO: 2, FS: 3) | C5: Y1 co-src | D5: Y1 full-src | E5: Y2 co-src | F5: Y2 full-src | G5: Y3 co-src | H5: Y3 full-src
B6: Seats per pod | C6: =SUMIFS('Pod Library'!$J:$J,'Pod Library'!$B:$B,1,'Pod Library'!$D:$D,"CO")/2 -> 6 | D6: =SUMIFS('Pod Library'!$J:$J,'Pod Library'!$B:$B,1,'Pod Library'!$D:$D,"FS")/3 -> 3.6666667 | E6: =SUMIFS('Pod Library'!$J:$J,'Pod Library'!$B:$B,2,'Pod Library'!$D:$D,"CO")/2 -> 5 | F6: =SUMIFS('Pod Library'!$J:$J,'Pod Library'!$B:$B,2,'Pod Library'!$D:$D,"FS")/3 -> 2.6666667 | G6: =SUMIFS('Pod Library'!$J:$J,'Pod Library'!$B:$B,3,'Pod Library'!$D:$D,"CO")/2 -> 4 | H6: =SUMIFS('Pod Library'!$J:$J,'Pod Library'!$B:$B,3,'Pod Library'!$D:$D,"FS")/3 -> 1.6666667
A8: B. HEADCOUNT
B9: Measure | C9: Year 1 | D9: Year 2 | E9: Year 3
B10: People in value-stream pods | C10: =SUMIFS('Seat Ledger'!$L$5:$L$70,'Seat Ledger'!$A$5:$A$70,1,'Seat Ledger'!$B$5:$B$70,"POD") -> 45 | D10: =SUMIFS('Seat Ledger'!$L$5:$L$70,'Seat Ledger'!$A$5:$A$70,2,'Seat Ledger'!$B$5:$B$70,"POD") -> 36 | E10: =SUMIFS('Seat Ledger'!$L$5:$L$70,'Seat Ledger'!$A$5:$A$70,3,'Seat Ledger'!$B$5:$B$70,"POD") -> 27
B11: People in horizontal teams | C11: =SUMIFS('Seat Ledger'!$L$5:$L$70,'Seat Ledger'!$A$5:$A$70,1,'Seat Ledger'!$B$5:$B$70,"HZ") -> 5 | D11: =SUMIFS('Seat Ledger'!$L$5:$L$70,'Seat Ledger'!$A$5:$A$70,2,'Seat Ledger'!$B$5:$B$70,"HZ") -> 4 | E11: =SUMIFS('Seat Ledger'!$L$5:$L$70,'Seat Ledger'!$A$5:$A$70,3,'Seat Ledger'!$B$5:$B$70,"HZ") -> 3
B12: TOTAL PEOPLE | C12: =C10+C11 -> 50 | D12: =D10+D11 -> 40 | E12: =E10+E11 -> 30
B13: Number of pods | C13: =SUMIFS('Pod Plan'!$G:$G,'Pod Plan'!$B:$B,1) -> 9 | D13: =SUMIFS('Pod Plan'!$G:$G,'Pod Plan'!$B:$B,2) -> 9 | E13: =SUMIFS('Pod Plan'!$G:$G,'Pod Plan'!$B:$B,3) -> 9
B14: Average pod size | C14: =IF(C13=0,0,C10/C13) -> 5 | D14: =IF(D13=0,0,D10/D13) -> 4 | E14: =IF(E13=0,0,E10/E13) -> 3
A16: C. SOURCING — before any transfer of employment
B17: Measure | C17: Year 1 | D17: Year 2 | E17: Year 3
B18: Capgemini (FTC) | C18: =SUMIFS('Seat Ledger'!$L$5:$L$70,'Seat Ledger'!$A$5:$A$70,1,'Seat Ledger'!$I$5:$I$70,"FTC") -> 33 | D18: =SUMIFS('Seat Ledger'!$L$5:$L$70,'Seat Ledger'!$A$5:$A$70,2,'Seat Ledger'!$I$5:$I$70,"FTC") -> 23 | E18: =SUMIFS('Seat Ledger'!$L$5:$L$70,'Seat Ledger'!$A$5:$A$70,3,'Seat Ledger'!$I$5:$I$70,"FTC") -> 13
B19: MetLife Japan (FTE) | C19: =SUMIFS('Seat Ledger'!$L$5:$L$70,'Seat Ledger'!$A$5:$A$70,1,'Seat Ledger'!$I$5:$I$70,"FTE") -> 16 | D19: =SUMIFS('Seat Ledger'!$L$5:$L$70,'Seat Ledger'!$A$5:$A$70,2,'Seat Ledger'!$I$5:$I$70,"FTE") -> 16 | E19: =SUMIFS('Seat Ledger'!$L$5:$L$70,'Seat Ledger'!$A$5:$A$70,3,'Seat Ledger'!$I$5:$I$70,"FTE") -> 16
B20: MetLife MGCC (Hyderabad) | C20: =SUMIFS('Seat Ledger'!$L$5:$L$70,'Seat Ledger'!$A$5:$A$70,1,'Seat Ledger'!$I$5:$I$70,"MGCC") -> 1 | D20: =SUMIFS('Seat Ledger'!$L$5:$L$70,'Seat Ledger'!$A$5:$A$70,2,'Seat Ledger'!$I$5:$I$70,"MGCC") -> 1 | E20: =SUMIFS('Seat Ledger'!$L$5:$L$70,'Seat Ledger'!$A$5:$A$70,3,'Seat Ledger'!$I$5:$I$70,"MGCC") -> 1
B21: Check — sums to total | C21: =C18+C19+C20-C12 -> 0 | D21: =D18+D19+D20-D12 -> 0 | E21: =E18+E19+E20-E12 -> 0
A23: D. LOCATION
B24: Measure | C24: Year 1 | D24: Year 2 | E24: Year 3
B25: Onshore Tokyo | C25: =SUMIFS('Seat Ledger'!$L$5:$L$70,'Seat Ledger'!$A$5:$A$70,1,'Seat Ledger'!$H$5:$H$70,"ON") -> 28 | D25: =SUMIFS('Seat Ledger'!$L$5:$L$70,'Seat Ledger'!$A$5:$A$70,2,'Seat Ledger'!$H$5:$H$70,"ON") -> 18 | E25: =SUMIFS('Seat Ledger'!$L$5:$L$70,'Seat Ledger'!$A$5:$A$70,3,'Seat Ledger'!$H$5:$H$70,"ON") -> 16
B26: Offshore Hyderabad | C26: =SUMIFS('Seat Ledger'!$L$5:$L$70,'Seat Ledger'!$A$5:$A$70,1,'Seat Ledger'!$H$5:$H$70,"OFF") -> 22 | D26: =SUMIFS('Seat Ledger'!$L$5:$L$70,'Seat Ledger'!$A$5:$A$70,2,'Seat Ledger'!$H$5:$H$70,"OFF") -> 22 | E26: =SUMIFS('Seat Ledger'!$L$5:$L$70,'Seat Ledger'!$A$5:$A$70,3,'Seat Ledger'!$H$5:$H$70,"OFF") -> 14
B27: Offshore share (delivered, bottom-up) | C27: =IF(C12=0,0,C26/C12) -> 0.44 | D27: =IF(D12=0,0,D26/D12) -> 0.55 | E27: =IF(E12=0,0,E26/E12) -> 0.46666667
A29: E. EXPERIENCE MIX — built grounds-up from named seats, not applied as a percentage
B30: Experience band | C30: Year 1 | D30: Year 2 | E30: Year 3 | G30: Y1 % | H30: Y2 % | I30: Y3 %
B31: E1 Associate 0-3 years | C31: =SUMIFS('Seat Ledger'!$L$5:$L$70,'Seat Ledger'!$A$5:$A$70,1,'Seat Ledger'!$G$5:$G$70,"E1") -> 0 | D31: =SUMIFS('Seat Ledger'!$L$5:$L$70,'Seat Ledger'!$A$5:$A$70,2,'Seat Ledger'!$G$5:$G$70,"E1") -> 0 | E31: =SUMIFS('Seat Ledger'!$L$5:$L$70,'Seat Ledger'!$A$5:$A$70,3,'Seat Ledger'!$G$5:$G$70,"E1") -> 0 | G31: =IF(C$12=0,0,C31/C$12) -> 0 | H31: =IF(D$12=0,0,D31/D$12) -> 0 | I31: =IF(E$12=0,0,E31/E$12) -> 0
B32: E2 Engineer 3-6 years | C32: =SUMIFS('Seat Ledger'!$L$5:$L$70,'Seat Ledger'!$A$5:$A$70,1,'Seat Ledger'!$G$5:$G$70,"E2") -> 12 | D32: =SUMIFS('Seat Ledger'!$L$5:$L$70,'Seat Ledger'!$A$5:$A$70,2,'Seat Ledger'!$G$5:$G$70,"E2") -> 3 | E32: =SUMIFS('Seat Ledger'!$L$5:$L$70,'Seat Ledger'!$A$5:$A$70,3,'Seat Ledger'!$G$5:$G$70,"E2") -> 0 | G32: =IF(C$12=0,0,C32/C$12) -> 0.24 | H32: =IF(D$12=0,0,D32/D$12) -> 0.075 | I32: =IF(E$12=0,0,E32/E$12) -> 0
B33: E3 Senior 6-10 years | C33: =SUMIFS('Seat Ledger'!$L$5:$L$70,'Seat Ledger'!$A$5:$A$70,1,'Seat Ledger'!$G$5:$G$70,"E3") -> 11 | D33: =SUMIFS('Seat Ledger'!$L$5:$L$70,'Seat Ledger'!$A$5:$A$70,2,'Seat Ledger'!$G$5:$G$70,"E3") -> 15 | E33: =SUMIFS('Seat Ledger'!$L$5:$L$70,'Seat Ledger'!$A$5:$A$70,3,'Seat Ledger'!$G$5:$G$70,"E3") -> 9 | G33: =IF(C$12=0,0,C33/C$12) -> 0.22 | H33: =IF(D$12=0,0,D33/D$12) -> 0.375 | I33: =IF(E$12=0,0,E33/E$12) -> 0.3
B34: E4 Lead / specialist 10-15 years | C34: =SUMIFS('Seat Ledger'!$L$5:$L$70,'Seat Ledger'!$A$5:$A$70,1,'Seat Ledger'!$G$5:$G$70,"E4") -> 25 | D34: =SUMIFS('Seat Ledger'!$L$5:$L$70,'Seat Ledger'!$A$5:$A$70,2,'Seat Ledger'!$G$5:$G$70,"E4") -> 20 | E34: =SUMIFS('Seat Ledger'!$L$5:$L$70,'Seat Ledger'!$A$5:$A$70,3,'Seat Ledger'!$G$5:$G$70,"E4") -> 19 | G34: =IF(C$12=0,0,C34/C$12) -> 0.5 | H34: =IF(D$12=0,0,D34/D$12) -> 0.5 | I34: =IF(E$12=0,0,E34/E$12) -> 0.63333333
B35: E5 Principal / architect 15 years+ | C35: =SUMIFS('Seat Ledger'!$L$5:$L$70,'Seat Ledger'!$A$5:$A$70,1,'Seat Ledger'!$G$5:$G$70,"E5") -> 2 | D35: =SUMIFS('Seat Ledger'!$L$5:$L$70,'Seat Ledger'!$A$5:$A$70,2,'Seat Ledger'!$G$5:$G$70,"E5") -> 2 | E35: =SUMIFS('Seat Ledger'!$L$5:$L$70,'Seat Ledger'!$A$5:$A$70,3,'Seat Ledger'!$G$5:$G$70,"E5") -> 2 | G35: =IF(C$12=0,0,C35/C$12) -> 0.04 | H35: =IF(D$12=0,0,D35/D$12) -> 0.05 | I35: =IF(E$12=0,0,E35/E$12) -> 0.066666667
B36: Talent shape | C36: =IF((C34+C35)/C12>0.55,"Obelisk",IF((C34+C35)/C12>0.4,"Diamond","Pyramid")) -> Diamond | D36: =IF((D34+D35)/D12>0.55,"Obelisk",IF((D34+D35)/D12>0.4,"Diamond","Pyramid")) -> Diamond | E36: =IF((E34+E35)/E12>0.55,"Obelisk",IF((E34+E35)/E12>0.4,"Diamond","Pyramid")) -> Obelisk
B37: Senior share (E4 + E5) | C37: =IF(C12=0,0,(C34+C35)/C12) -> 0.54 | D37: =IF(D12=0,0,(D34+D35)/D12) -> 0.55 | E37: =IF(E12=0,0,(E34+E35)/E12) -> 0.7
A39: F. SKILL DISTRIBUTION — also grounds-up
B40: Skill family | C40: Year 1 | D40: Year 2 | E40: Year 3 | G40: Y1 % | H40: Y2 % | I40: Y3 %
B41: Leadership & delivery management | C41: =SUMIFS('Seat Ledger'!$L$5:$L$70,'Seat Ledger'!$A$5:$A$70,1,'Seat Ledger'!$F$5:$F$70,"LEAD") -> 16 | D41: =SUMIFS('Seat Ledger'!$L$5:$L$70,'Seat Ledger'!$A$5:$A$70,2,'Seat Ledger'!$F$5:$F$70,"LEAD") -> 11 | E41: =SUMIFS('Seat Ledger'!$L$5:$L$70,'Seat Ledger'!$A$5:$A$70,3,'Seat Ledger'!$F$5:$F$70,"LEAD") -> 7 | G41: =IF(C$12=0,0,C41/C$12) -> 0.32 | H41: =IF(D$12=0,0,D41/D$12) -> 0.275 | I41: =IF(E$12=0,0,E41/E$12) -> 0.23333333
B42: Business analysis & domain | C42: =SUMIFS('Seat Ledger'!$L$5:$L$70,'Seat Ledger'!$A$5:$A$70,1,'Seat Ledger'!$F$5:$F$70,"BA") -> 6 | D42: =SUMIFS('Seat Ledger'!$L$5:$L$70,'Seat Ledger'!$A$5:$A$70,2,'Seat Ledger'!$F$5:$F$70,"BA") -> 5 | E42: =SUMIFS('Seat Ledger'!$L$5:$L$70,'Seat Ledger'!$A$5:$A$70,3,'Seat Ledger'!$F$5:$F$70,"BA") -> 5 | G42: =IF(C$12=0,0,C42/C$12) -> 0.12 | H42: =IF(D$12=0,0,D42/D$12) -> 0.125 | I42: =IF(E$12=0,0,E42/E$12) -> 0.16666667
B43: Development | C43: =SUMIFS('Seat Ledger'!$L$5:$L$70,'Seat Ledger'!$A$5:$A$70,1,'Seat Ledger'!$F$5:$F$70,"DEV") -> 12 | D43: =SUMIFS('Seat Ledger'!$L$5:$L$70,'Seat Ledger'!$A$5:$A$70,2,'Seat Ledger'!$F$5:$F$70,"DEV") -> 9 | E43: =SUMIFS('Seat Ledger'!$L$5:$L$70,'Seat Ledger'!$A$5:$A$70,3,'Seat Ledger'!$F$5:$F$70,"DEV") -> 3 | G43: =IF(C$12=0,0,C43/C$12) -> 0.24 | H43: =IF(D$12=0,0,D43/D$12) -> 0.225 | I43: =IF(E$12=0,0,E43/E$12) -> 0.1
B44: Engineering, AI & platform | C44: =SUMIFS('Seat Ledger'!$L$5:$L$70,'Seat Ledger'!$A$5:$A$70,1,'Seat Ledger'!$F$5:$F$70,"ENG") -> 6 | D44: =SUMIFS('Seat Ledger'!$L$5:$L$70,'Seat Ledger'!$A$5:$A$70,2,'Seat Ledger'!$F$5:$F$70,"ENG") -> 6 | E44: =SUMIFS('Seat Ledger'!$L$5:$L$70,'Seat Ledger'!$A$5:$A$70,3,'Seat Ledger'!$F$5:$F$70,"ENG") -> 15 | G44: =IF(C$12=0,0,C44/C$12) -> 0.12 | H44: =IF(D$12=0,0,D44/D$12) -> 0.15 | I44: =IF(E$12=0,0,E44/E$12) -> 0.5
B45: Test & quality engineering | C45: =SUMIFS('Seat Ledger'!$L$5:$L$70,'Seat Ledger'!$A$5:$A$70,1,'Seat Ledger'!$F$5:$F$70,"TEST") -> 10 | D45: =SUMIFS('Seat Ledger'!$L$5:$L$70,'Seat Ledger'!$A$5:$A$70,2,'Seat Ledger'!$F$5:$F$70,"TEST") -> 9 | E45: =SUMIFS('Seat Ledger'!$L$5:$L$70,'Seat Ledger'!$A$5:$A$70,3,'Seat Ledger'!$F$5:$F$70,"TEST") -> 0 | G45: =IF(C$12=0,0,C45/C$12) -> 0.2 | H45: =IF(D$12=0,0,D45/D$12) -> 0.225 | I45: =IF(E$12=0,0,E45/E$12) -> 0
B46: Operations & production support | C46: =SUMIFS('Seat Ledger'!$L$5:$L$70,'Seat Ledger'!$A$5:$A$70,1,'Seat Ledger'!$F$5:$F$70,"OPS") -> 0 | D46: =SUMIFS('Seat Ledger'!$L$5:$L$70,'Seat Ledger'!$A$5:$A$70,2,'Seat Ledger'!$F$5:$F$70,"OPS") -> 0 | E46: =SUMIFS('Seat Ledger'!$L$5:$L$70,'Seat Ledger'!$A$5:$A$70,3,'Seat Ledger'!$F$5:$F$70,"OPS") -> 0 | G46: =IF(C$12=0,0,C46/C$12) -> 0 | H46: =IF(D$12=0,0,D46/D$12) -> 0 | I46: =IF(E$12=0,0,E46/E$12) -> 0
B47: Check — sums to total | C47: =SUM(C41:C46)-C12 -> 0 | D47: =SUM(D41:D46)-D12 -> 0 | E47: =SUM(E41:E46)-E12 -> 0
A49: G. BY VALUE STREAM AND HORIZONTAL TEAM
B50: Unit | C50: Year 1 | D50: Year 2 | E50: Year 3 | G50: Y1 co-src pods | H50: Y1 pods | I50: Y3 pods
B51: VS1 Policy Administration & Contract Servicing | C51: =SUMIFS('Seat Ledger'!$L$5:$L$70,'Seat Ledger'!$A$5:$A$70,1,'Seat Ledger'!$C$5:$C$70,"VS1") -> 26 | D51: =SUMIFS('Seat Ledger'!$L$5:$L$70,'Seat Ledger'!$A$5:$A$70,2,'Seat Ledger'!$C$5:$C$70,"VS1") -> 21 | E51: =SUMIFS('Seat Ledger'!$L$5:$L$70,'Seat Ledger'!$A$5:$A$70,3,'Seat Ledger'!$C$5:$C$70,"VS1") -> 16 | G51: =SUMIFS('Pod Plan'!$E:$E,'Pod Plan'!$B:$B,1,'Pod Plan'!$C:$C,"VS1") -> 3 | H51: =SUMIFS('Pod Plan'!$G:$G,'Pod Plan'!$B:$B,1,'Pod Plan'!$C:$C,"VS1") -> 5 | I51: =SUMIFS('Pod Plan'!$G:$G,'Pod Plan'!$B:$B,3,'Pod Plan'!$C:$C,"VS1") -> 5
B52: VS2 Billing, Collections & Payments | C52: =SUMIFS('Seat Ledger'!$L$5:$L$70,'Seat Ledger'!$A$5:$A$70,1,'Seat Ledger'!$C$5:$C$70,"VS2") -> 16 | D52: =SUMIFS('Seat Ledger'!$L$5:$L$70,'Seat Ledger'!$A$5:$A$70,2,'Seat Ledger'!$C$5:$C$70,"VS2") -> 13 | E52: =SUMIFS('Seat Ledger'!$L$5:$L$70,'Seat Ledger'!$A$5:$A$70,3,'Seat Ledger'!$C$5:$C$70,"VS2") -> 10 | G52: =SUMIFS('Pod Plan'!$E:$E,'Pod Plan'!$B:$B,1,'Pod Plan'!$C:$C,"VS2") -> 2 | H52: =SUMIFS('Pod Plan'!$G:$G,'Pod Plan'!$B:$B,1,'Pod Plan'!$C:$C,"VS2") -> 3 | I52: =SUMIFS('Pod Plan'!$G:$G,'Pod Plan'!$B:$B,3,'Pod Plan'!$C:$C,"VS2") -> 3
B53: VS3 Agency & Commission | C53: =SUMIFS('Seat Ledger'!$L$5:$L$70,'Seat Ledger'!$A$5:$A$70,1,'Seat Ledger'!$C$5:$C$70,"VS3") -> 3 | D53: =SUMIFS('Seat Ledger'!$L$5:$L$70,'Seat Ledger'!$A$5:$A$70,2,'Seat Ledger'!$C$5:$C$70,"VS3") -> 2 | E53: =SUMIFS('Seat Ledger'!$L$5:$L$70,'Seat Ledger'!$A$5:$A$70,3,'Seat Ledger'!$C$5:$C$70,"VS3") -> 1 | G53: =SUMIFS('Pod Plan'!$E:$E,'Pod Plan'!$B:$B,1,'Pod Plan'!$C:$C,"VS3") -> 0 | H53: =SUMIFS('Pod Plan'!$G:$G,'Pod Plan'!$B:$B,1,'Pod Plan'!$C:$C,"VS3") -> 1 | I53: =SUMIFS('Pod Plan'!$G:$G,'Pod Plan'!$B:$B,3,'Pod Plan'!$C:$C,"VS3") -> 1
B54: VS4 Correspondence, Documents & Tax | C54: =SUMIFS('Seat Ledger'!$L$5:$L$70,'Seat Ledger'!$A$5:$A$70,1,'Seat Ledger'!$C$5:$C$70,"VS4") -> 0 | D54: =SUMIFS('Seat Ledger'!$L$5:$L$70,'Seat Ledger'!$A$5:$A$70,2,'Seat Ledger'!$C$5:$C$70,"VS4") -> 0 | E54: =SUMIFS('Seat Ledger'!$L$5:$L$70,'Seat Ledger'!$A$5:$A$70,3,'Seat Ledger'!$C$5:$C$70,"VS4") -> 0 | G54: =SUMIFS('Pod Plan'!$E:$E,'Pod Plan'!$B:$B,1,'Pod Plan'!$C:$C,"VS4") -> 0 | H54: =SUMIFS('Pod Plan'!$G:$G,'Pod Plan'!$B:$B,1,'Pod Plan'!$C:$C,"VS4") -> 0 | I54: =SUMIFS('Pod Plan'!$G:$G,'Pod Plan'!$B:$B,3,'Pod Plan'!$C:$C,"VS4") -> 0
B55: VS5 New Business, Underwriting & Interfaces | C55: =SUMIFS('Seat Ledger'!$L$5:$L$70,'Seat Ledger'!$A$5:$A$70,1,'Seat Ledger'!$C$5:$C$70,"VS5") -> 0 | D55: =SUMIFS('Seat Ledger'!$L$5:$L$70,'Seat Ledger'!$A$5:$A$70,2,'Seat Ledger'!$C$5:$C$70,"VS5") -> 0 | E55: =SUMIFS('Seat Ledger'!$L$5:$L$70,'Seat Ledger'!$A$5:$A$70,3,'Seat Ledger'!$C$5:$C$70,"VS5") -> 0 | G55: =SUMIFS('Pod Plan'!$E:$E,'Pod Plan'!$B:$B,1,'Pod Plan'!$C:$C,"VS5") -> 0 | H55: =SUMIFS('Pod Plan'!$G:$G,'Pod Plan'!$B:$B,1,'Pod Plan'!$C:$C,"VS5") -> 0 | I55: =SUMIFS('Pod Plan'!$G:$G,'Pod Plan'!$B:$B,3,'Pod Plan'!$C:$C,"VS5") -> 0
B56: VS6 Finance, Valuation & Reinsurance | C56: =SUMIFS('Seat Ledger'!$L$5:$L$70,'Seat Ledger'!$A$5:$A$70,1,'Seat Ledger'!$C$5:$C$70,"VS6") -> 0 | D56: =SUMIFS('Seat Ledger'!$L$5:$L$70,'Seat Ledger'!$A$5:$A$70,2,'Seat Ledger'!$C$5:$C$70,"VS6") -> 0 | E56: =SUMIFS('Seat Ledger'!$L$5:$L$70,'Seat Ledger'!$A$5:$A$70,3,'Seat Ledger'!$C$5:$C$70,"VS6") -> 0 | G56: =SUMIFS('Pod Plan'!$E:$E,'Pod Plan'!$B:$B,1,'Pod Plan'!$C:$C,"VS6") -> 0 | H56: =SUMIFS('Pod Plan'!$G:$G,'Pod Plan'!$B:$B,1,'Pod Plan'!$C:$C,"VS6") -> 0 | I56: =SUMIFS('Pod Plan'!$G:$G,'Pod Plan'!$B:$B,3,'Pod Plan'!$C:$C,"VS6") -> 0
B57: H1 Production & Batch Operations Command | C57: =SUMIFS('Seat Ledger'!$L$5:$L$70,'Seat Ledger'!$A$5:$A$70,1,'Seat Ledger'!$C$5:$C$70,"H1") -> 1 | D57: =SUMIFS('Seat Ledger'!$L$5:$L$70,'Seat Ledger'!$A$5:$A$70,2,'Seat Ledger'!$C$5:$C$70,"H1") -> 1 | E57: =SUMIFS('Seat Ledger'!$L$5:$L$70,'Seat Ledger'!$A$5:$A$70,3,'Seat Ledger'!$C$5:$C$70,"H1") -> 1
B58: H2 Quality Engineering & Test Data Factory | C58: =SUMIFS('Seat Ledger'!$L$5:$L$70,'Seat Ledger'!$A$5:$A$70,1,'Seat Ledger'!$C$5:$C$70,"H2") -> 1 | D58: =SUMIFS('Seat Ledger'!$L$5:$L$70,'Seat Ledger'!$A$5:$A$70,2,'Seat Ledger'!$C$5:$C$70,"H2") -> 1 | E58: =SUMIFS('Seat Ledger'!$L$5:$L$70,'Seat Ledger'!$A$5:$A$70,3,'Seat Ledger'!$C$5:$C$70,"H2") -> 0
B59: H3 Domain Architecture, Release Train & Governance | C59: =SUMIFS('Seat Ledger'!$L$5:$L$70,'Seat Ledger'!$A$5:$A$70,1,'Seat Ledger'!$C$5:$C$70,"H3") -> 1 | D59: =SUMIFS('Seat Ledger'!$L$5:$L$70,'Seat Ledger'!$A$5:$A$70,2,'Seat Ledger'!$C$5:$C$70,"H3") -> 0 | E59: =SUMIFS('Seat Ledger'!$L$5:$L$70,'Seat Ledger'!$A$5:$A$70,3,'Seat Ledger'!$C$5:$C$70,"H3") -> 0
B60: TOTAL | C60: =SUM(C51:C59) -> 48 | D60: =SUM(D51:D59) -> 38 | E60: =SUM(E51:E59) -> 28

Sheet Glidepath & 50-50
A1: Glidepath — target from the logic tree, delivered from the pod design, and the transfer needed for 50:50
A2: The tree says what the archetype mix should allow. The pod design says what we have actually staffed to. The gap is transition drag.
A4: A. BASELINE — MetLife current state for this domain
B5: Measure | C5: Value
B6: Applications | C6: ='Logic Tree'!C6 -> 5
B7: Total effort (units) | C7: ='Logic Tree'!C7 -> 48.510292
B8: Current Capgemini FTC | C8: ='Logic Tree'!C8 -> 38.147792
B9: Current MetLife FTE | C9: ='Logic Tree'!C9 -> 9.7791667
B10: Current MetLife MGCC | C10: ='Logic Tree'!C10 -> 0.58333333
B11: MetLife Appendix 3 Year-3 target FTC | C11: ='Logic Tree'!C7/2 -> 24.255146
B12: Implied MetLife productivity assumption | C12: =0 -> 0 | H12: Appendix 3 v2 halves every application and leaves the portfolio unchanged, so it assumes zero productivity.
A14: B. PRODUCTIVITY — target vs delivered
B15: Measure | C15: Year 1 | D15: Year 2 | E15: Year 3
B16: Headcount delivered by the pod design | C16: ='Team Build-Up'!C12 -> 50 | D16: ='Team Build-Up'!D12 -> 40 | E16: ='Team Build-Up'!E12 -> 30 | H16: Year 1 absorbs the whole of the drag: knowledge acquisition, substrate build and dual running are real work that consumes the productivity earned.
B17: Delivered productivity vs baseline | C17: =IF($C$7=0,0,1-'Team Build-Up'!C12/$C$7) -> -0.030709119 | D17: =IF($C$7=0,0,1-'Team Build-Up'!D12/$C$7) -> 0.1754327 | E17: =IF($C$7=0,0,1-'Team Build-Up'!E12/$C$7) -> 0.38157453
B18: Target productivity from the logic tree | C18: ='Logic Tree'!C53 -> 0.1385009 | D18: ='Logic Tree'!D53 -> 0.29114436 | E18: ='Logic Tree'!E53 -> 0.38498931
B19: Transition & enablement drag (target less delivered) | C19: =C18-C17 -> 0.16921002 | D19: =D18-D17 -> 0.11571166 | E19: =E18-E17 -> 0.0034147788
A22: C. OFFSHORE — target vs delivered
B23: Measure | C23: Year 1 | D23: Year 2 | E23: Year 3
B24: Delivered offshore share (bottom-up from seats) | C24: ='Team Build-Up'!C27 -> 0.44 | D24: ='Team Build-Up'!D27 -> 0.55 | E24: ='Team Build-Up'!E27 -> 0.46666667
B25: Target offshore share from the logic tree | C25: ='Logic Tree'!C62 -> 0.22818421 | D25: ='Logic Tree'!D62 -> 0.34027469 | E25: ='Logic Tree'!E62 -> 0.37230055
B26: Variance | C26: =C24-C25 -> 0.21181579 | D26: =D24-D25 -> 0.20972531 | E26: =E24-E25 -> 0.094366118
A28: D. THE 50:50 SOLVE
B29: Productivity shrinks the Capgemini side and the MetLife side together, so it cannot move the ratio. Only transfer of employment can.
B30: Measure | C30: Year 1 | D30: Year 2 | E30: Year 3
B31: Total people | C31: ='Team Build-Up'!C12 -> 50 | D31: ='Team Build-Up'!D12 -> 40 | E31: ='Team Build-Up'!E12 -> 30
B32: Capgemini FTC before transfer | C32: ='Team Build-Up'!C18 -> 33 | D32: ='Team Build-Up'!D18 -> 23 | E32: ='Team Build-Up'!E18 -> 13
B33: MetLife FTE before transfer | C33: ='Team Build-Up'!C19 -> 16 | D33: ='Team Build-Up'!D19 -> 16 | E33: ='Team Build-Up'!E19 -> 16
B34: MetLife MGCC before transfer | C34: ='Team Build-Up'!C20 -> 1 | D34: ='Team Build-Up'!D20 -> 1 | E34: ='Team Build-Up'!E20 -> 1
B35: Ratio before transfer FTC : MetLife | C35: =IF(C31=0,0,C32/C31) -> 0.66 | D35: =IF(D31=0,0,D32/D31) -> 0.575 | E35: =IF(E31=0,0,E32/E31) -> 0.43333333
B36: Transferred to MetLife FTE this year | C36: ='Logic Tree'!C67 -> 0 | D36: ='Logic Tree'!D67 -> 0 | E36: ='Logic Tree'!E67 -> 0
B37: Transferred to MetLife MGCC this year | C37: ='Logic Tree'!C68 -> 0 | D37: ='Logic Tree'!D68 -> 0 | E37: ='Logic Tree'!E68 -> 0
B38: Cumulative transferred | C38: ='Logic Tree'!C69 -> 0 | D38: ='Logic Tree'!D69 -> 0 | E38: ='Logic Tree'!E69 -> 0
B39: Capgemini FTC after transfer | C39: =C32-C38 -> 33 | D39: =D32-D38 -> 23 | E39: =E32-E38 -> 13
B40: MetLife side after transfer | C40: =C33+C34+C38 -> 17 | D40: =D33+D34+D38 -> 17 | E40: =E33+E34+E38 -> 17
B41: RATIO ACHIEVED — Capgemini share | C41: =IF(C31=0,0,C39/C31) -> 0.66 | D41: =IF(D31=0,0,D39/D31) -> 0.575 | E41: =IF(E31=0,0,E39/E31) -> 0.43333333 | H41: A negative shortfall means the plan transfers more than 50:50 requires.
B42: Transfer required for exactly 50:50 (cumulative) | C42: =C31/2-C33-C34 -> 8 | D42: =D31/2-D33-D34 -> 3 | E42: =E31/2-E33-E34 -> -2
B43: Shortfall against 50:50 | C43: =C42-C38 -> 8 | D43: =D42-D38 -> 3 | E43: =E42-E38 -> -2
B45: Of the fall in the Capgemini population from Year 1 to Year 3:
B46: attributable to productivity and offshore mix | C46: =C32-E32 -> 20 | H46: Transfer moves revenue rather than creating efficiency. It has to be priced separately.
B47: attributable to transfer of employment | C47: =E38 -> 0
B48: total reduction in Capgemini headcount | C48: =C32-E39 -> 20

Sheet Cost & Commercial
A1: Cost and commercial position — relative index only, pending the approved rate card
A2: Onshore Tokyo band E2 = 1.00. Every figure moves if the cost index on the Logic Tree changes.
A4: A. TOTAL COST OF DELIVERING THE DOMAIN (MetLife view — all three sourcing types)
B5: Measure | C5: Year 1 | D5: Year 2 | E5: Year 3
B6: Total cost index | C6: =SUMIFS('Seat Ledger'!$M$5:$M$70,'Seat Ledger'!$A$5:$A$70,1) -> 60.5 | D6: =SUMIFS('Seat Ledger'!$M$5:$M$70,'Seat Ledger'!$A$5:$A$70,2) -> 44.3 | E6: =SUMIFS('Seat Ledger'!$M$5:$M$70,'Seat Ledger'!$A$5:$A$70,3) -> 37.33
B7: Headcount | C7: ='Team Build-Up'!C12 -> 50 | D7: ='Team Build-Up'!D12 -> 40 | E7: ='Team Build-Up'!E12 -> 30
B8: Average cost per head | C8: =IF(C7=0,0,C6/C7) -> 1.21 | D8: =IF(D7=0,0,D6/D7) -> 1.1075 | E8: =IF(E7=0,0,E6/E7) -> 1.2443333 | G8: Watch this line. Average cost per head falls in Year 2 on offshore leverage, then rises in Year 3 as juniors leave and the shape turns obelisk.
B9: Cost per unit of original scope | C9: =IF('Glidepath & 50-50'!$C$7=0,0,C6/'Glidepath & 50-50'!$C$7) -> 1.247158 | D9: =IF('Glidepath & 50-50'!$C$7=0,0,D6/'Glidepath & 50-50'!$C$7) -> 0.91320828 | E9: =IF('Glidepath & 50-50'!$C$7=0,0,E6/'Glidepath & 50-50'!$C$7) -> 0.76952743
B10: Unit cost reduction vs Year 1 | C10: =IF($C$9=0,0,1-C9/$C$9) -> 0 | D10: =IF($C$9=0,0,1-D9/$C$9) -> 0.2677686 | E10: =IF($C$9=0,0,1-E9/$C$9) -> 0.38297521 | G10: This is the number to quote commercially, not the headcount reduction.
A12: B. CAPGEMINI BILLABLE POSITION (after transfer of employment)
B13: Measure | C13: Year 1 | D13: Year 2 | E13: Year 3
B14: Capgemini heads billed | C14: ='Glidepath & 50-50'!C39 -> 33 | D14: ='Glidepath & 50-50'!D39 -> 23 | E14: ='Glidepath & 50-50'!E39 -> 13
B15: Capgemini cost index (approximate — transfers assumed at average band) | C15: =SUMIFS('Seat Ledger'!$M$5:$M$70,'Seat Ledger'!$A$5:$A$70,1,'Seat Ledger'!$I$5:$I$70,"FTC")*IF(SUMIFS('Seat Ledger'!$L$5:$L$70,'Seat Ledger'!$A$5:$A$70,1,'Seat Ledger'!$I$5:$I$70,"FTC")=0,0,C14/SUMIFS('Seat Ledger'!$L$5:$L$70,'Seat Ledger'!$A$5:$A$70,1,'Seat Ledger'!$I$5:$I$70,"FTC")) -> 29.78 | D15: =SUMIFS('Seat Ledger'!$M$5:$M$70,'Seat Ledger'!$A$5:$A$70,2,'Seat Ledger'!$I$5:$I$70,"FTC")*IF(SUMIFS('Seat Ledger'!$L$5:$L$70,'Seat Ledger'!$A$5:$A$70,2,'Seat Ledger'!$I$5:$I$70,"FTC")=0,0,D14/SUMIFS('Seat Ledger'!$L$5:$L$70,'Seat Ledger'!$A$5:$A$70,2,'Seat Ledger'!$I$5:$I$70,"FTC")) -> 13.58 | E15: =SUMIFS('Seat Ledger'!$M$5:$M$70,'Seat Ledger'!$A$5:$A$70,3,'Seat Ledger'!$I$5:$I$70,"FTC")*IF(SUMIFS('Seat Ledger'!$L$5:$L$70,'Seat Ledger'!$A$5:$A$70,3,'Seat Ledger'!$I$5:$I$70,"FTC")=0,0,E14/SUMIFS('Seat Ledger'!$L$5:$L$70,'Seat Ledger'!$A$5:$A$70,3,'Seat Ledger'!$I$5:$I$70,"FTC")) -> 6.61
B16: Capgemini position vs Year 1 | C16: =IF($C$15=0,0,C15/$C$15-1) -> 0 | D16: =IF($C$15=0,0,D15/$C$15-1) -> -0.54398925 | E16: =IF($C$15=0,0,E15/$C$15-1) -> -0.77803895 | G16: The Capgemini revenue base falls far faster than the domain cost base. Productivity plus transfer, compounding in the same direction.
A18: C. COST BY LOCATION AND BY EXPERIENCE BAND
B19: Split | C19: Year 1 | D19: Year 2 | E19: Year 3
B20: Onshore Tokyo — cost index | C20: =SUMIFS('Seat Ledger'!$M$5:$M$70,'Seat Ledger'!$A$5:$A$70,1,'Seat Ledger'!$H$5:$H$70,"ON") -> 52.7 | D20: =SUMIFS('Seat Ledger'!$M$5:$M$70,'Seat Ledger'!$A$5:$A$70,2,'Seat Ledger'!$H$5:$H$70,"ON") -> 34.7 | E20: =SUMIFS('Seat Ledger'!$M$5:$M$70,'Seat Ledger'!$A$5:$A$70,3,'Seat Ledger'!$H$5:$H$70,"ON") -> 30.3
B21: Offshore Hyderabad — cost index | C21: =SUMIFS('Seat Ledger'!$M$5:$M$70,'Seat Ledger'!$A$5:$A$70,1,'Seat Ledger'!$H$5:$H$70,"OFF") -> 7.8 | D21: =SUMIFS('Seat Ledger'!$M$5:$M$70,'Seat Ledger'!$A$5:$A$70,2,'Seat Ledger'!$H$5:$H$70,"OFF") -> 9.6 | E21: =SUMIFS('Seat Ledger'!$M$5:$M$70,'Seat Ledger'!$A$5:$A$70,3,'Seat Ledger'!$H$5:$H$70,"OFF") -> 7.03
B22: Onshore share of cost | C22: =IF((C20+C21)=0,0,C20/(C20+C21)) -> 0.87107438 | D22: =IF((D20+D21)=0,0,D20/(D20+D21)) -> 0.78329571 | E22: =IF((E20+E21)=0,0,E20/(E20+E21)) -> 0.81167961
B24: E1 — cost index | C24: =SUMIFS('Seat Ledger'!$M$5:$M$70,'Seat Ledger'!$A$5:$A$70,1,'Seat Ledger'!$G$5:$G$70,"E1") -> 0 | D24: =SUMIFS('Seat Ledger'!$M$5:$M$70,'Seat Ledger'!$A$5:$A$70,2,'Seat Ledger'!$G$5:$G$70,"E1") -> 0 | E24: =SUMIFS('Seat Ledger'!$M$5:$M$70,'Seat Ledger'!$A$5:$A$70,3,'Seat Ledger'!$G$5:$G$70,"E1") -> 0
B25: E2 — cost index | C25: =SUMIFS('Seat Ledger'!$M$5:$M$70,'Seat Ledger'!$A$5:$A$70,1,'Seat Ledger'!$G$5:$G$70,"E2") -> 3.6 | D25: =SUMIFS('Seat Ledger'!$M$5:$M$70,'Seat Ledger'!$A$5:$A$70,2,'Seat Ledger'!$G$5:$G$70,"E2") -> 0.9 | E25: =SUMIFS('Seat Ledger'!$M$5:$M$70,'Seat Ledger'!$A$5:$A$70,3,'Seat Ledger'!$G$5:$G$70,"E2") -> 0
B26: E3 — cost index | C26: =SUMIFS('Seat Ledger'!$M$5:$M$70,'Seat Ledger'!$A$5:$A$70,1,'Seat Ledger'!$G$5:$G$70,"E3") -> 5.55 | D26: =SUMIFS('Seat Ledger'!$M$5:$M$70,'Seat Ledger'!$A$5:$A$70,2,'Seat Ledger'!$G$5:$G$70,"E3") -> 6.3 | E26: =SUMIFS('Seat Ledger'!$M$5:$M$70,'Seat Ledger'!$A$5:$A$70,3,'Seat Ledger'!$G$5:$G$70,"E3") -> 3.78
B27: E4 — cost index | C27: =SUMIFS('Seat Ledger'!$M$5:$M$70,'Seat Ledger'!$A$5:$A$70,1,'Seat Ledger'!$G$5:$G$70,"E4") -> 46.25 | D27: =SUMIFS('Seat Ledger'!$M$5:$M$70,'Seat Ledger'!$A$5:$A$70,2,'Seat Ledger'!$G$5:$G$70,"E4") -> 32 | E27: =SUMIFS('Seat Ledger'!$M$5:$M$70,'Seat Ledger'!$A$5:$A$70,3,'Seat Ledger'!$G$5:$G$70,"E4") -> 30.15
B28: E5 — cost index | C28: =SUMIFS('Seat Ledger'!$M$5:$M$70,'Seat Ledger'!$A$5:$A$70,1,'Seat Ledger'!$G$5:$G$70,"E5") -> 5.1 | D28: =SUMIFS('Seat Ledger'!$M$5:$M$70,'Seat Ledger'!$A$5:$A$70,2,'Seat Ledger'!$G$5:$G$70,"E5") -> 5.1 | E28: =SUMIFS('Seat Ledger'!$M$5:$M$70,'Seat Ledger'!$A$5:$A$70,3,'Seat Ledger'!$G$5:$G$70,"E5") -> 3.4
A30: D. WHAT THIS MEANS FOR THE PRICING SUBMISSION
B31: • Appendix 5 is priced by 領域. Contract Management is 99.4% archetype D, the hardest archetype in the portfolio.
B32: • The portfolio-wide productivity commitment cannot be applied uniformly across domains. Applying it here under-prices this domain.
B33: • Transfer of employment is a commercial event, not a delivery efficiency. Price the transition and the substrate build in Years 1 and 2, when the revenue is still there.
B34: • The Year 3 exit revenue for this domain is roughly a third of Day 1. Everything that has to be recovered must be recovered early.

Sheet Seat Ledger
A5: 1 | B5: POD | C5: VS1 | D5: CO | E5: ='Pod Library'!E5 -> Product Owner | F5: ='Pod Library'!F5 -> LEAD | G5: ='Pod Library'!G5 -> E4 | H5: ='Pod Library'!H5 -> ON | I5: ='Pod Library'!I5 -> FTE | J5: ='Pod Library'!J5 -> 1 | K5: =SUMIFS('Pod Plan'!$E:$E,'Pod Plan'!$B:$B,$A5,'Pod Plan'!$C:$C,$C5) -> 3 | L5: =J5*K5 -> 3 | M5: =L5*INDEX('Logic Tree'!$J$73:$N$74,MATCH(H5,'Logic Tree'!$I$73:$I$74,0),MATCH(G5,'Logic Tree'!$J$72:$N$72,0)) -> 5.55
A6: 1 | B6: POD | C6: VS1 | D6: CO | E6: ='Pod Library'!E6 -> Incentive Compensation SME | F6: ='Pod Library'!F6 -> BA | G6: ='Pod Library'!G6 -> E4 | H6: ='Pod Library'!H6 -> ON | I6: ='Pod Library'!I6 -> FTE | J6: ='Pod Library'!J6 -> 1 | K6: =SUMIFS('Pod Plan'!$E:$E,'Pod Plan'!$B:$B,$A6,'Pod Plan'!$C:$C,$C6) -> 3 | L6: =J6*K6 -> 3 | M6: =L6*INDEX('Logic Tree'!$J$73:$N$74,MATCH(H6,'Logic Tree'!$I$73:$I$74,0),MATCH(G6,'Logic Tree'!$J$72:$N$72,0)) -> 5.55
A7: 1 | B7: POD | C7: VS1 | D7: CO | E7: ='Pod Library'!E7 -> Application Owner (Technical) | F7: ='Pod Library'!F7 -> ENG | G7: ='Pod Library'!G7 -> E4 | H7: ='Pod Library'!H7 -> ON | I7: ='Pod Library'!I7 -> FTE | J7: ='Pod Library'!J7 -> 1 | K7: =SUMIFS('Pod Plan'!$E:$E,'Pod Plan'!$B:$B,$A7,'Pod Plan'!$C:$C,$C7) -> 3 | L7: =J7*K7 -> 3 | M7: =L7*INDEX('Logic Tree'!$J$73:$N$74,MATCH(H7,'Logic Tree'!$I$73:$I$74,0),MATCH(G7,'Logic Tree'!$J$72:$N$72,0)) -> 5.55
A8: 1 | B8: POD | C8: VS1 | D8: CO | E8: ='Pod Library'!E8 -> Pod Delivery Lead | F8: ='Pod Library'!F8 -> LEAD | G8: ='Pod Library'!G8 -> E4 | H8: ='Pod Library'!H8 -> ON | I8: ='Pod Library'!I8 -> FTC | J8: ='Pod Library'!J8 -> 1 | K8: =SUMIFS('Pod Plan'!$E:$E,'Pod Plan'!$B:$B,$A8,'Pod Plan'!$C:$C,$C8) -> 3 | L8: =J8*K8 -> 3 | M8: =L8*INDEX('Logic Tree'!$J$73:$N$74,MATCH(H8,'Logic Tree'!$I$73:$I$74,0),MATCH(G8,'Logic Tree'!$J$72:$N$72,0)) -> 5.55
A9: 1 | B9: POD | C9: VS1 | D9: CO | E9: ='Pod Library'!E9 -> Senior Developer | F9: ='Pod Library'!F9 -> DEV | G9: ='Pod Library'!G9 -> E3 | H9: ='Pod Library'!H9 -> OFF | I9: ='Pod Library'!I9 -> FTC | J9: ='Pod Library'!J9 -> 1 | K9: =SUMIFS('Pod Plan'!$E:$E,'Pod Plan'!$B:$B,$A9,'Pod Plan'!$C:$C,$C9) -> 3 | L9: =J9*K9 -> 3 | M9: =L9*INDEX('Logic Tree'!$J$73:$N$74,MATCH(H9,'Logic Tree'!$I$73:$I$74,0),MATCH(G9,'Logic Tree'!$J$72:$N$72,0)) -> 1.26
A10: 1 | B10: POD | C10: VS1 | D10: CO | E10: ='Pod Library'!E10 -> QA / Test Engineer | F10: ='Pod Library'!F10 -> TEST | G10: ='Pod Library'!G10 -> E2 | H10: ='Pod Library'!H10 -> OFF | I10: ='Pod Library'!I10 -> FTC | J10: ='Pod Library'!J10 -> 1 | K10: =SUMIFS('Pod Plan'!$E:$E,'Pod Plan'!$B:$B,$A10,'Pod Plan'!$C:$C,$C10) -> 3 | L10: =J10*K10 -> 3 | M10: =L10*INDEX('Logic Tree'!$J$73:$N$74,MATCH(H10,'Logic Tree'!$I$73:$I$74,0),MATCH(G10,'Logic Tree'!$J$72:$N$72,0)) -> 0.9
A11: 1 | B11: POD | C11: VS1 | D11: FS | E11: ='Pod Library'!E12 -> Pod Lead (output owner) | F11: ='Pod Library'!F12 -> LEAD | G11: ='Pod Library'!G12 -> E4 | H11: ='Pod Library'!H12 -> ON | I11: ='Pod Library'!I12 -> FTC | J11: ='Pod Library'!J12 -> 1 | K11: =SUMIFS('Pod Plan'!$F:$F,'Pod Plan'!$B:$B,$A11,'Pod Plan'!$C:$C,$C11) -> 2 | L11: =J11*K11 -> 2 | M11: =L11*INDEX('Logic Tree'!$J$73:$N$74,MATCH(H11,'Logic Tree'!$I$73:$I$74,0),MATCH(G11,'Logic Tree'!$J$72:$N$72,0)) -> 3.7
A12: 1 | B12: POD | C12: VS1 | D12: FS | E12: ='Pod Library'!E13 -> Developer | F12: ='Pod Library'!F13 -> DEV | G12: ='Pod Library'!G13 -> E3 | H12: ='Pod Library'!H13 -> OFF | I12: ='Pod Library'!I13 -> FTC | J12: ='Pod Library'!J13 -> 1 | K12: =SUMIFS('Pod Plan'!$F:$F,'Pod Plan'!$B:$B,$A12,'Pod Plan'!$C:$C,$C12) -> 2 | L12: =J12*K12 -> 2 | M12: =L12*INDEX('Logic Tree'!$J$73:$N$74,MATCH(H12,'Logic Tree'!$I$73:$I$74,0),MATCH(G12,'Logic Tree'!$J$72:$N$72,0)) -> 0.84
A13: 1 | B13: POD | C13: VS1 | D13: FS | E13: ='Pod Library'!E14 -> Developer | F13: ='Pod Library'!F14 -> DEV | G13: ='Pod Library'!G14 -> E2 | H13: ='Pod Library'!H14 -> OFF | I13: ='Pod Library'!I14 -> FTC | J13: ='Pod Library'!J14 -> 1 | K13: =SUMIFS('Pod Plan'!$F:$F,'Pod Plan'!$B:$B,$A13,'Pod Plan'!$C:$C,$C13) -> 2 | L13: =J13*K13 -> 2 | M13: =L13*INDEX('Logic Tree'!$J$73:$N$74,MATCH(H13,'Logic Tree'!$I$73:$I$74,0),MATCH(G13,'Logic Tree'!$J$72:$N$72,0)) -> 0.6
A14: 1 | B14: POD | C14: VS1 | D14: FS | E14: ='Pod Library'!E15 -> QA Engineer | F14: ='Pod Library'!F15 -> TEST | G14: ='Pod Library'!G15 -> E2 | H14: ='Pod Library'!H15 -> OFF | I14: ='Pod Library'!I15 -> FTC | J14: ='Pod Library'!J15 -> 1 | K14: =SUMIFS('Pod Plan'!$F:$F,'Pod Plan'!$B:$B,$A14,'Pod Plan'!$C:$C,$C14) -> 2 | L14: =J14*K14 -> 2 | M14: =L14*INDEX('Logic Tree'!$J$73:$N$74,MATCH(H14,'Logic Tree'!$I$73:$I$74,0),MATCH(G14,'Logic Tree'!$J$72:$N$72,0)) -> 0.6
A15: 1 | B15: POD | C15: VS2 | D15: CO | E15: ='Pod Library'!E18 -> Product Owner | F15: ='Pod Library'!F18 -> LEAD | G15: ='Pod Library'!G18 -> E4 | H15: ='Pod Library'!H18 -> ON | I15: ='Pod Library'!I18 -> FTE | J15: ='Pod Library'!J18 -> 1 | K15: =SUMIFS('Pod Plan'!$E:$E,'Pod Plan'!$B:$B,$A15,'Pod Plan'!$C:$C,$C15) -> 2 | L15: =J15*K15 -> 2 | M15: =L15*INDEX('Logic Tree'!$J$73:$N$74,MATCH(H15,'Logic Tree'!$I$73:$I$74,0),MATCH(G15,'Logic Tree'!$J$72:$N$72,0)) -> 3.7
A16: 1 | B16: POD | C16: VS2 | D16: CO | E16: ='Pod Library'!E19 -> Compensation Administration SME | F16: ='Pod Library'!F19 -> BA | G16: ='Pod Library'!G19 -> E4 | H16: ='Pod Library'!H19 -> ON | I16: ='Pod Library'!I19 -> FTE | J16: ='Pod Library'!J19 -> 1 | K16: =SUMIFS('Pod Plan'!$E:$E,'Pod Plan'!$B:$B,$A16,'Pod Plan'!$C:$C,$C16) -> 2 | L16: =J16*K16 -> 2 | M16: =L16*INDEX('Logic Tree'!$J$73:$N$74,MATCH(H16,'Logic Tree'!$I$73:$I$74,0),MATCH(G16,'Logic Tree'!$J$72:$N$72,0)) -> 3.7
A17: 1 | B17: POD | C17: VS2 | D17: CO | E17: ='Pod Library'!E20 -> Application Owner (Technical) | F17: ='Pod Library'!F20 -> ENG | G17: ='Pod Library'!G20 -> E4 | H17: ='Pod Library'!H20 -> ON | I17: ='Pod Library'!I20 -> FTE | J17: ='Pod Library'!J20 -> 1 | K17: =SUMIFS('Pod Plan'!$E:$E,'Pod Plan'!$B:$B,$A17,'Pod Plan'!$C:$C,$C17) -> 2 | L17: =J17*K17 -> 2 | M17: =L17*INDEX('Logic Tree'!$J$73:$N$74,MATCH(H17,'Logic Tree'!$I$73:$I$74,0),MATCH(G17,'Logic Tree'!$J$72:$N$72,0)) -> 3.7
A18: 1 | B18: POD | C18: VS2 | D18: CO | E18: ='Pod Library'!E21 -> Pod Delivery Lead | F18: ='Pod Library'!F21 -> LEAD | G18: ='Pod Library'!G21 -> E4 | H18: ='Pod Library'!H21 -> ON | I18: ='Pod Library'!I21 -> FTC | J18: ='Pod Library'!J21 -> 1 | K18: =SUMIFS('Pod Plan'!$E:$E,'Pod Plan'!$B:$B,$A18,'Pod Plan'!$C:$C,$C18) -> 2 | L18: =J18*K18 -> 2 | M18: =L18*INDEX('Logic Tree'!$J$73:$N$74,MATCH(H18,'Logic Tree'!$I$73:$I$74,0),MATCH(G18,'Logic Tree'!$J$72:$N$72,0)) -> 3.7
A19: 1 | B19: POD | C19: VS2 | D19: CO | E19: ='Pod Library'!E22 -> Senior Developer | F19: ='Pod Library'!F22 -> DEV | G19: ='Pod Library'!G22 -> E3 | H19: ='Pod Library'!H22 -> OFF | I19: ='Pod Library'!I22 -> FTC | J19: ='Pod Library'!J22 -> 1 | K19: =SUMIFS('Pod Plan'!$E:$E,'Pod Plan'!$B:$B,$A19,'Pod Plan'!$C:$C,$C19) -> 2 | L19: =J19*K19 -> 2 | M19: =L19*INDEX('Logic Tree'!$J$73:$N$74,MATCH(H19,'Logic Tree'!$I$73:$I$74,0),MATCH(G19,'Logic Tree'!$J$72:$N$72,0)) -> 0.84
A20: 1 | B20: POD | C20: VS2 | D20: CO | E20: ='Pod Library'!E23 -> QA / Test Engineer | F20: ='Pod Library'!F23 -> TEST | G20: ='Pod Library'!G23 -> E2 | H20: ='Pod Library'!H23 -> OFF | I20: ='Pod Library'!I23 -> FTC | J20: ='Pod Library'!J23 -> 1 | K20: =SUMIFS('Pod Plan'!$E:$E,'Pod Plan'!$B:$B,$A20,'Pod Plan'!$C:$C,$C20) -> 2 | L20: =J20*K20 -> 2 | M20: =L20*INDEX('Logic Tree'!$J$73:$N$74,MATCH(H20,'Logic Tree'!$I$73:$I$74,0),MATCH(G20,'Logic Tree'!$J$72:$N$72,0)) -> 0.6
A21: 1 | B21: POD | C21: VS2 | D21: FS | E21: ='Pod Library'!E25 -> Pod Lead (output owner) | F21: ='Pod Library'!F25 -> LEAD | G21: ='Pod Library'!G25 -> E4 | H21: ='Pod Library'!H25 -> ON | I21: ='Pod Library'!I25 -> FTC | J21: ='Pod Library'!J25 -> 1 | K21: =SUMIFS('Pod Plan'!$F:$F,'Pod Plan'!$B:$B,$A21,'Pod Plan'!$C:$C,$C21) -> 1 | L21: =J21*K21 -> 1 | M21: =L21*INDEX('Logic Tree'!$J$73:$N$74,MATCH(H21,'Logic Tree'!$I$73:$I$74,0),MATCH(G21,'Logic Tree'!$J$72:$N$72,0)) -> 1.85
A22: 1 | B22: POD | C22: VS2 | D22: FS | E22: ='Pod Library'!E26 -> Developer | F22: ='Pod Library'!F26 -> DEV | G22: ='Pod Library'!G26 -> E3 | H22: ='Pod Library'!H26 -> OFF | I22: ='Pod Library'!I26 -> FTC | J22: ='Pod Library'!J26 -> 1 | K22: =SUMIFS('Pod Plan'!$F:$F,'Pod Plan'!$B:$B,$A22,'Pod Plan'!$C:$C,$C22) -> 1 | L22: =J22*K22 -> 1 | M22: =L22*INDEX('Logic Tree'!$J$73:$N$74,MATCH(H22,'Logic Tree'!$I$73:$I$74,0),MATCH(G22,'Logic Tree'!$J$72:$N$72,0)) -> 0.42
A23: 1 | B23: POD | C23: VS2 | D23: FS | E23: ='Pod Library'!E27 -> Developer | F23: ='Pod Library'!F27 -> DEV | G23: ='Pod Library'!G27 -> E2 | H23: ='Pod Library'!H27 -> OFF | I23: ='Pod Library'!I27 -> FTC | J23: ='Pod Library'!J27 -> 1 | K23: =SUMIFS('Pod Plan'!$F:$F,'Pod Plan'!$B:$B,$A23,'Pod Plan'!$C:$C,$C23) -> 1 | L23: =J23*K23 -> 1 | M23: =L23*INDEX('Logic Tree'!$J$73:$N$74,MATCH(H23,'Logic Tree'!$I$73:$I$74,0),MATCH(G23,'Logic Tree'!$J$72:$N$72,0)) -> 0.3
A24: 1 | B24: POD | C24: VS2 | D24: FS | E24: ='Pod Library'!E28 -> QA Engineer | F24: ='Pod Library'!F28 -> TEST | G24: ='Pod Library'!G28 -> E2 | H24: ='Pod Library'!H28 -> OFF | I24: ='Pod Library'!I28 -> FTC | J24: ='Pod Library'!J28 -> 1 | K24: =SUMIFS('Pod Plan'!$F:$F,'Pod Plan'!$B:$B,$A24,'Pod Plan'!$C:$C,$C24) -> 1 | L24: =J24*K24 -> 1 | M24: =L24*INDEX('Logic Tree'!$J$73:$N$74,MATCH(H24,'Logic Tree'!$I$73:$I$74,0),MATCH(G24,'Logic Tree'!$J$72:$N$72,0)) -> 0.3
A25: 1 | B25: POD | C25: VS3 | D25: FS | E25: ='Pod Library'!E31 -> Pod Lead (output owner) | F25: ='Pod Library'!F31 -> LEAD | G25: ='Pod Library'!G31 -> E4 | H25: ='Pod Library'!H31 -> ON | I25: ='Pod Library'!I31 -> FTC | J25: ='Pod Library'!J31 -> 1 | K25: =SUMIFS('Pod Plan'!$F:$F,'Pod Plan'!$B:$B,$A25,'Pod Plan'!$C:$C,$C25) -> 1 | L25: =J25*K25 -> 1 | M25: =L25*INDEX('Logic Tree'!$J$73:$N$74,MATCH(H25,'Logic Tree'!$I$73:$I$74,0),MATCH(G25,'Logic Tree'!$J$72:$N$72,0)) -> 1.85
A26: 1 | B26: POD | C26: VS3 | D26: FS | E26: ='Pod Library'!E32 -> Developer — MGCC Hyderabad | F26: ='Pod Library'!F32 -> DEV | G26: ='Pod Library'!G32 -> E3 | H26: ='Pod Library'!H32 -> OFF | I26: ='Pod Library'!I32 -> MGCC | J26: ='Pod Library'!J32 -> 1 | K26: =SUMIFS('Pod Plan'!$F:$F,'Pod Plan'!$B:$B,$A26,'Pod Plan'!$C:$C,$C26) -> 1 | L26: =J26*K26 -> 1 | M26: =L26*INDEX('Logic Tree'!$J$73:$N$74,MATCH(H26,'Logic Tree'!$I$73:$I$74,0),MATCH(G26,'Logic Tree'!$J$72:$N$72,0)) -> 0.42
A27: 1 | B27: POD | C27: VS3 | D27: FS | E27: ='Pod Library'!E33 -> QA Engineer | F27: ='Pod Library'!F33 -> TEST | G27: ='Pod Library'!G33 -> E2 | H27: ='Pod Library'!H33 -> OFF | I27: ='Pod Library'!I33 -> FTC | J27: ='Pod Library'!J33 -> 1 | K27: =SUMIFS('Pod Plan'!$F:$F,'Pod Plan'!$B:$B,$A27,'Pod Plan'!$C:$C,$C27) -> 1 | L27: =J27*K27 -> 1 | M27: =L27*INDEX('Logic Tree'!$J$73:$N$74,MATCH(H27,'Logic Tree'!$I$73:$I$74,0),MATCH(G27,'Logic Tree'!$J$72:$N$72,0)) -> 0.3
A28: 2 | B28: POD | C28: VS1 | D28: CO | E28: ='Pod Library'!E36 -> Product Owner | F28: ='Pod Library'!F36 -> LEAD | G28: ='Pod Library'!G36 -> E4 | H28: ='Pod Library'!H36 -> ON | I28: ='Pod Library'!I36 -> FTE | J28: ='Pod Library'!J36 -> 1 | K28: =SUMIFS('Pod Plan'!$E:$E,'Pod Plan'!$B:$B,$A28,'Pod Plan'!$C:$C,$C28) -> 3 | L28: =J28*K28 -> 3 | M28: =L28*INDEX('Logic Tree'!$J$73:$N$74,MATCH(H28,'Logic Tree'!$I$73:$I$74,0),MATCH(G28,'Logic Tree'!$J$72:$N$72,0)) -> 5.55
A29: 2 | B29: POD | C29: VS1 | D29: CO | E29: ='Pod Library'!E37 -> Incentive Compensation SME | F29: ='Pod Library'!F37 -> BA | G29: ='Pod Library'!G37 -> E4 | H29: ='Pod Library'!H37 -> ON | I29: ='Pod Library'!I37 -> FTE | J29: ='Pod Library'!J37 -> 1 | K29: =SUMIFS('Pod Plan'!$E:$E,'Pod Plan'!$B:$B,$A29,'Pod Plan'!$C:$C,$C29) -> 3 | L29: =J29*K29 -> 3 | M29: =L29*INDEX('Logic Tree'!$J$73:$N$74,MATCH(H29,'Logic Tree'!$I$73:$I$74,0),MATCH(G29,'Logic Tree'!$J$72:$N$72,0)) -> 5.55
A30: 2 | B30: POD | C30: VS1 | D30: CO | E30: ='Pod Library'!E38 -> Application Owner (Technical) | F30: ='Pod Library'!F38 -> ENG | G30: ='Pod Library'!G38 -> E4 | H30: ='Pod Library'!H38 -> ON | I30: ='Pod Library'!I38 -> FTE | J30: ='Pod Library'!J38 -> 1 | K30: =SUMIFS('Pod Plan'!$E:$E,'Pod Plan'!$B:$B,$A30,'Pod Plan'!$C:$C,$C30) -> 3 | L30: =J30*K30 -> 3 | M30: =L30*INDEX('Logic Tree'!$J$73:$N$74,MATCH(H30,'Logic Tree'!$I$73:$I$74,0),MATCH(G30,'Logic Tree'!$J$72:$N$72,0)) -> 5.55
A31: 2 | B31: POD | C31: VS1 | D31: CO | E31: ='Pod Library'!E39 -> AI-assisted Developer | F31: ='Pod Library'!F39 -> DEV | G31: ='Pod Library'!G39 -> E3 | H31: ='Pod Library'!H39 -> OFF | I31: ='Pod Library'!I39 -> FTC | J31: ='Pod Library'!J39 -> 1 | K31: =SUMIFS('Pod Plan'!$E:$E,'Pod Plan'!$B:$B,$A31,'Pod Plan'!$C:$C,$C31) -> 3 | L31: =J31*K31 -> 3 | M31: =L31*INDEX('Logic Tree'!$J$73:$N$74,MATCH(H31,'Logic Tree'!$I$73:$I$74,0),MATCH(G31,'Logic Tree'!$J$72:$N$72,0)) -> 1.26
A32: 2 | B32: POD | C32: VS1 | D32: CO | E32: ='Pod Library'!E40 -> Quality Engineer (SDET) | F32: ='Pod Library'!F40 -> TEST | G32: ='Pod Library'!G40 -> E3 | H32: ='Pod Library'!H40 -> OFF | I32: ='Pod Library'!I40 -> FTC | J32: ='Pod Library'!J40 -> 1 | K32: =SUMIFS('Pod Plan'!$E:$E,'Pod Plan'!$B:$B,$A32,'Pod Plan'!$C:$C,$C32) -> 3 | L32: =J32*K32 -> 3 | M32: =L32*INDEX('Logic Tree'!$J$73:$N$74,MATCH(H32,'Logic Tree'!$I$73:$I$74,0),MATCH(G32,'Logic Tree'!$J$72:$N$72,0)) -> 1.26
A33: 2 | B33: POD | C33: VS1 | D33: FS | E33: ='Pod Library'!E42 -> Pod Lead / AI Orchestrator | F33: ='Pod Library'!F42 -> LEAD | G33: ='Pod Library'!G42 -> E4 | H33: ='Pod Library'!H42 -> OFF | I33: ='Pod Library'!I42 -> FTC | J33: ='Pod Library'!J42 -> 1 | K33: =SUMIFS('Pod Plan'!$F:$F,'Pod Plan'!$B:$B,$A33,'Pod Plan'!$C:$C,$C33) -> 2 | L33: =J33*K33 -> 2 | M33: =L33*INDEX('Logic Tree'!$J$73:$N$74,MATCH(H33,'Logic Tree'!$I$73:$I$74,0),MATCH(G33,'Logic Tree'!$J$72:$N$72,0)) -> 1.2
A34: 2 | B34: POD | C34: VS1 | D34: FS | E34: ='Pod Library'!E43 -> AI-assisted Developer | F34: ='Pod Library'!F43 -> DEV | G34: ='Pod Library'!G43 -> E3 | H34: ='Pod Library'!H43 -> OFF | I34: ='Pod Library'!I43 -> FTC | J34: ='Pod Library'!J43 -> 1 | K34: =SUMIFS('Pod Plan'!$F:$F,'Pod Plan'!$B:$B,$A34,'Pod Plan'!$C:$C,$C34) -> 2 | L34: =J34*K34 -> 2 | M34: =L34*INDEX('Logic Tree'!$J$73:$N$74,MATCH(H34,'Logic Tree'!$I$73:$I$74,0),MATCH(G34,'Logic Tree'!$J$72:$N$72,0)) -> 0.84
A35: 2 | B35: POD | C35: VS1 | D35: FS | E35: ='Pod Library'!E44 -> QA Engineer | F35: ='Pod Library'!F44 -> TEST | G35: ='Pod Library'!G44 -> E2 | H35: ='Pod Library'!H44 -> OFF | I35: ='Pod Library'!I44 -> FTC | J35: ='Pod Library'!J44 -> 1 | K35: =SUMIFS('Pod Plan'!$F:$F,'Pod Plan'!$B:$B,$A35,'Pod Plan'!$C:$C,$C35) -> 2 | L35: =J35*K35 -> 2 | M35: =L35*INDEX('Logic Tree'!$J$73:$N$74,MATCH(H35,'Logic Tree'!$I$73:$I$74,0),MATCH(G35,'Logic Tree'!$J$72:$N$72,0)) -> 0.6
A36: 2 | B36: POD | C36: VS2 | D36: CO | E36: ='Pod Library'!E47 -> Product Owner | F36: ='Pod Library'!F47 -> LEAD | G36: ='Pod Library'!G47 -> E4 | H36: ='Pod Library'!H47 -> ON | I36: ='Pod Library'!I47 -> FTE | J36: ='Pod Library'!J47 -> 1 | K36: =SUMIFS('Pod Plan'!$E:$E,'Pod Plan'!$B:$B,$A36,'Pod Plan'!$C:$C,$C36) -> 2 | L36: =J36*K36 -> 2 | M36: =L36*INDEX('Logic Tree'!$J$73:$N$74,MATCH(H36,'Logic Tree'!$I$73:$I$74,0),MATCH(G36,'Logic Tree'!$J$72:$N$72,0)) -> 3.7
A37: 2 | B37: POD | C37: VS2 | D37: CO | E37: ='Pod Library'!E48 -> Compensation Administration SME | F37: ='Pod Library'!F48 -> BA | G37: ='Pod Library'!G48 -> E4 | H37: ='Pod Library'!H48 -> ON | I37: ='Pod Library'!I48 -> FTE | J37: ='Pod Library'!J48 -> 1 | K37: =SUMIFS('Pod Plan'!$E:$E,'Pod Plan'!$B:$B,$A37,'Pod Plan'!$C:$C,$C37) -> 2 | L37: =J37*K37 -> 2 | M37: =L37*INDEX('Logic Tree'!$J$73:$N$74,MATCH(H37,'Logic Tree'!$I$73:$I$74,0),MATCH(G37,'Logic Tree'!$J$72:$N$72,0)) -> 3.7
A38: 2 | B38: POD | C38: VS2 | D38: CO | E38: ='Pod Library'!E49 -> Application Owner (Technical) | F38: ='Pod Library'!F49 -> ENG | G38: ='Pod Library'!G49 -> E4 | H38: ='Pod Library'!H49 -> ON | I38: ='Pod Library'!I49 -> FTE | J38: ='Pod Library'!J49 -> 1 | K38: =SUMIFS('Pod Plan'!$E:$E,'Pod Plan'!$B:$B,$A38,'Pod Plan'!$C:$C,$C38) -> 2 | L38: =J38*K38 -> 2 | M38: =L38*INDEX('Logic Tree'!$J$73:$N$74,MATCH(H38,'Logic Tree'!$I$73:$I$74,0),MATCH(G38,'Logic Tree'!$J$72:$N$72,0)) -> 3.7
A39: 2 | B39: POD | C39: VS2 | D39: CO | E39: ='Pod Library'!E50 -> AI-assisted Developer | F39: ='Pod Library'!F50 -> DEV | G39: ='Pod Library'!G50 -> E3 | H39: ='Pod Library'!H50 -> OFF | I39: ='Pod Library'!I50 -> FTC | J39: ='Pod Library'!J50 -> 1 | K39: =SUMIFS('Pod Plan'!$E:$E,'Pod Plan'!$B:$B,$A39,'Pod Plan'!$C:$C,$C39) -> 2 | L39: =J39*K39 -> 2 | M39: =L39*INDEX('Logic Tree'!$J$73:$N$74,MATCH(H39,'Logic Tree'!$I$73:$I$74,0),MATCH(G39,'Logic Tree'!$J$72:$N$72,0)) -> 0.84
A40: 2 | B40: POD | C40: VS2 | D40: CO | E40: ='Pod Library'!E51 -> Quality Engineer (SDET) | F40: ='Pod Library'!F51 -> TEST | G40: ='Pod Library'!G51 -> E3 | H40: ='Pod Library'!H51 -> OFF | I40: ='Pod Library'!I51 -> FTC | J40: ='Pod Library'!J51 -> 1 | K40: =SUMIFS('Pod Plan'!$E:$E,'Pod Plan'!$B:$B,$A40,'Pod Plan'!$C:$C,$C40) -> 2 | L40: =J40*K40 -> 2 | M40: =L40*INDEX('Logic Tree'!$J$73:$N$74,MATCH(H40,'Logic Tree'!$I$73:$I$74,0),MATCH(G40,'Logic Tree'!$J$72:$N$72,0)) -> 0.84
A41: 2 | B41: POD | C41: VS2 | D41: FS | E41: ='Pod Library'!E53 -> Pod Lead / AI Orchestrator | F41: ='Pod Library'!F53 -> LEAD | G41: ='Pod Library'!G53 -> E4 | H41: ='Pod Library'!H53 -> OFF | I41: ='Pod Library'!I53 -> FTC | J41: ='Pod Library'!J53 -> 1 | K41: =SUMIFS('Pod Plan'!$F:$F,'Pod Plan'!$B:$B,$A41,'Pod Plan'!$C:$C,$C41) -> 1 | L41: =J41*K41 -> 1 | M41: =L41*INDEX('Logic Tree'!$J$73:$N$74,MATCH(H41,'Logic Tree'!$I$73:$I$74,0),MATCH(G41,'Logic Tree'!$J$72:$N$72,0)) -> 0.6
A42: 2 | B42: POD | C42: VS2 | D42: FS | E42: ='Pod Library'!E54 -> AI-assisted Developer | F42: ='Pod Library'!F54 -> DEV | G42: ='Pod Library'!G54 -> E3 | H42: ='Pod Library'!H54 -> OFF | I42: ='Pod Library'!I54 -> FTC | J42: ='Pod Library'!J54 -> 1 | K42: =SUMIFS('Pod Plan'!$F:$F,'Pod Plan'!$B:$B,$A42,'Pod Plan'!$C:$C,$C42) -> 1 | L42: =J42*K42 -> 1 | M42: =L42*INDEX('Logic Tree'!$J$73:$N$74,MATCH(H42,'Logic Tree'!$I$73:$I$74,0),MATCH(G42,'Logic Tree'!$J$72:$N$72,0)) -> 0.42
A43: 2 | B43: POD | C43: VS2 | D43: FS | E43: ='Pod Library'!E55 -> QA Engineer | F43: ='Pod Library'!F55 -> TEST | G43: ='Pod Library'!G55 -> E2 | H43: ='Pod Library'!H55 -> OFF | I43: ='Pod Library'!I55 -> FTC | J43: ='Pod Library'!J55 -> 1 | K43: =SUMIFS('Pod Plan'!$F:$F,'Pod Plan'!$B:$B,$A43,'Pod Plan'!$C:$C,$C43) -> 1 | L43: =J43*K43 -> 1 | M43: =L43*INDEX('Logic Tree'!$J$73:$N$74,MATCH(H43,'Logic Tree'!$I$73:$I$74,0),MATCH(G43,'Logic Tree'!$J$72:$N$72,0)) -> 0.3
A44: 2 | B44: POD | C44: VS3 | D44: FS | E44: ='Pod Library'!E58 -> Pod Lead / AI Orchestrator | F44: ='Pod Library'!F58 -> LEAD | G44: ='Pod Library'!G58 -> E4 | H44: ='Pod Library'!H58 -> OFF | I44: ='Pod Library'!I58 -> FTC | J44: ='Pod Library'!J58 -> 1 | K44: =SUMIFS('Pod Plan'!$F:$F,'Pod Plan'!$B:$B,$A44,'Pod Plan'!$C:$C,$C44) -> 1 | L44: =J44*K44 -> 1 | M44: =L44*INDEX('Logic Tree'!$J$73:$N$74,MATCH(H44,'Logic Tree'!$I$73:$I$74,0),MATCH(G44,'Logic Tree'!$J$72:$N$72,0)) -> 0.6
A45: 2 | B45: POD | C45: VS3 | D45: FS | E45: ='Pod Library'!E59 -> AI-assisted Developer — MGCC Hyderabad | F45: ='Pod Library'!F59 -> DEV | G45: ='Pod Library'!G59 -> E3 | H45: ='Pod Library'!H59 -> OFF | I45: ='Pod Library'!I59 -> MGCC | J45: ='Pod Library'!J59 -> 1 | K45: =SUMIFS('Pod Plan'!$F:$F,'Pod Plan'!$B:$B,$A45,'Pod Plan'!$C:$C,$C45) -> 1 | L45: =J45*K45 -> 1 | M45: =L45*INDEX('Logic Tree'!$J$73:$N$74,MATCH(H45,'Logic Tree'!$I$73:$I$74,0),MATCH(G45,'Logic Tree'!$J$72:$N$72,0)) -> 0.42
A46: 3 | B46: POD | C46: VS1 | D46: CO | E46: ='Pod Library'!E62 -> Product Owner | F46: ='Pod Library'!F62 -> LEAD | G46: ='Pod Library'!G62 -> E4 | H46: ='Pod Library'!H62 -> ON | I46: ='Pod Library'!I62 -> FTE | J46: ='Pod Library'!J62 -> 1 | K46: =SUMIFS('Pod Plan'!$E:$E,'Pod Plan'!$B:$B,$A46,'Pod Plan'!$C:$C,$C46) -> 3 | L46: =J46*K46 -> 3 | M46: =L46*INDEX('Logic Tree'!$J$73:$N$74,MATCH(H46,'Logic Tree'!$I$73:$I$74,0),MATCH(G46,'Logic Tree'!$J$72:$N$72,0)) -> 5.55
A47: 3 | B47: POD | C47: VS1 | D47: CO | E47: ='Pod Library'!E63 -> Incentive Compensation SME | F47: ='Pod Library'!F63 -> BA | G47: ='Pod Library'!G63 -> E4 | H47: ='Pod Library'!H63 -> ON | I47: ='Pod Library'!I63 -> FTE | J47: ='Pod Library'!J63 -> 1 | K47: =SUMIFS('Pod Plan'!$E:$E,'Pod Plan'!$B:$B,$A47,'Pod Plan'!$C:$C,$C47) -> 3 | L47: =J47*K47 -> 3 | M47: =L47*INDEX('Logic Tree'!$J$73:$N$74,MATCH(H47,'Logic Tree'!$I$73:$I$74,0),MATCH(G47,'Logic Tree'!$J$72:$N$72,0)) -> 5.55
A48: 3 | B48: POD | C48: VS1 | D48: CO | E48: ='Pod Library'!E64 -> Application Owner (Technical) | F48: ='Pod Library'!F64 -> ENG | G48: ='Pod Library'!G64 -> E4 | H48: ='Pod Library'!H64 -> ON | I48: ='Pod Library'!I64 -> FTE | J48: ='Pod Library'!J64 -> 1 | K48: =SUMIFS('Pod Plan'!$E:$E,'Pod Plan'!$B:$B,$A48,'Pod Plan'!$C:$C,$C48) -> 3 | L48: =J48*K48 -> 3 | M48: =L48*INDEX('Logic Tree'!$J$73:$N$74,MATCH(H48,'Logic Tree'!$I$73:$I$74,0),MATCH(G48,'Logic Tree'!$J$72:$N$72,0)) -> 5.55
A49: 3 | B49: POD | C49: VS1 | D49: CO | E49: ='Pod Library'!E65 -> AI Orchestrator / Developer | F49: ='Pod Library'!F65 -> ENG | G49: ='Pod Library'!G65 -> E3 | H49: ='Pod Library'!H65 -> OFF | I49: ='Pod Library'!I65 -> FTC | J49: ='Pod Library'!J65 -> 1 | K49: =SUMIFS('Pod Plan'!$E:$E,'Pod Plan'!$B:$B,$A49,'Pod Plan'!$C:$C,$C49) -> 3 | L49: =J49*K49 -> 3 | M49: =L49*INDEX('Logic Tree'!$J$73:$N$74,MATCH(H49,'Logic Tree'!$I$73:$I$74,0),MATCH(G49,'Logic Tree'!$J$72:$N$72,0)) -> 1.26
A50: 3 | B50: POD | C50: VS1 | D50: FS | E50: ='Pod Library'!E67 -> AI Orchestrator | F50: ='Pod Library'!F67 -> ENG | G50: ='Pod Library'!G67 -> E4 | H50: ='Pod Library'!H67 -> OFF | I50: ='Pod Library'!I67 -> FTC | J50: ='Pod Library'!J67 -> 1 | K50: =SUMIFS('Pod Plan'!$F:$F,'Pod Plan'!$B:$B,$A50,'Pod Plan'!$C:$C,$C50) -> 2 | L50: =J50*K50 -> 2 | M50: =L50*INDEX('Logic Tree'!$J$73:$N$74,MATCH(H50,'Logic Tree'!$I$73:$I$74,0),MATCH(G50,'Logic Tree'!$J$72:$N$72,0)) -> 1.2
A51: 3 | B51: POD | C51: VS1 | D51: FS | E51: ='Pod Library'!E68 -> AI-assisted Developer | F51: ='Pod Library'!F68 -> DEV | G51: ='Pod Library'!G68 -> E3 | H51: ='Pod Library'!H68 -> OFF | I51: ='Pod Library'!I68 -> FTC | J51: ='Pod Library'!J68 -> 1 | K51: =SUMIFS('Pod Plan'!$F:$F,'Pod Plan'!$B:$B,$A51,'Pod Plan'!$C:$C,$C51) -> 2 | L51: =J51*K51 -> 2 | M51: =L51*INDEX('Logic Tree'!$J$73:$N$74,MATCH(H51,'Logic Tree'!$I$73:$I$74,0),MATCH(G51,'Logic Tree'!$J$72:$N$72,0)) -> 0.84
A52: 3 | B52: POD | C52: VS2 | D52: CO | E52: ='Pod Library'!E71 -> Product Owner | F52: ='Pod Library'!F71 -> LEAD | G52: ='Pod Library'!G71 -> E4 | H52: ='Pod Library'!H71 -> ON | I52: ='Pod Library'!I71 -> FTE | J52: ='Pod Library'!J71 -> 1 | K52: =SUMIFS('Pod Plan'!$E:$E,'Pod Plan'!$B:$B,$A52,'Pod Plan'!$C:$C,$C52) -> 2 | L52: =J52*K52 -> 2 | M52: =L52*INDEX('Logic Tree'!$J$73:$N$74,MATCH(H52,'Logic Tree'!$I$73:$I$74,0),MATCH(G52,'Logic Tree'!$J$72:$N$72,0)) -> 3.7
A53: 3 | B53: POD | C53: VS2 | D53: CO | E53: ='Pod Library'!E72 -> Compensation Administration SME | F53: ='Pod Library'!F72 -> BA | G53: ='Pod Library'!G72 -> E4 | H53: ='Pod Library'!H72 -> ON | I53: ='Pod Library'!I72 -> FTE | J53: ='Pod Library'!J72 -> 1 | K53: =SUMIFS('Pod Plan'!$E:$E,'Pod Plan'!$B:$B,$A53,'Pod Plan'!$C:$C,$C53) -> 2 | L53: =J53*K53 -> 2 | M53: =L53*INDEX('Logic Tree'!$J$73:$N$74,MATCH(H53,'Logic Tree'!$I$73:$I$74,0),MATCH(G53,'Logic Tree'!$J$72:$N$72,0)) -> 3.7
A54: 3 | B54: POD | C54: VS2 | D54: CO | E54: ='Pod Library'!E73 -> Application Owner (Technical) | F54: ='Pod Library'!F73 -> ENG | G54: ='Pod Library'!G73 -> E4 | H54: ='Pod Library'!H73 -> ON | I54: ='Pod Library'!I73 -> FTE | J54: ='Pod Library'!J73 -> 1 | K54: =SUMIFS('Pod Plan'!$E:$E,'Pod Plan'!$B:$B,$A54,'Pod Plan'!$C:$C,$C54) -> 2 | L54: =J54*K54 -> 2 | M54: =L54*INDEX('Logic Tree'!$J$73:$N$74,MATCH(H54,'Logic Tree'!$I$73:$I$74,0),MATCH(G54,'Logic Tree'!$J$72:$N$72,0)) -> 3.7
A55: 3 | B55: POD | C55: VS2 | D55: CO | E55: ='Pod Library'!E74 -> AI Orchestrator / Developer | F55: ='Pod Library'!F74 -> ENG | G55: ='Pod Library'!G74 -> E3 | H55: ='Pod Library'!H74 -> OFF | I55: ='Pod Library'!I74 -> FTC | J55: ='Pod Library'!J74 -> 1 | K55: =SUMIFS('Pod Plan'!$E:$E,'Pod Plan'!$B:$B,$A55,'Pod Plan'!$C:$C,$C55) -> 2 | L55: =J55*K55 -> 2 | M55: =L55*INDEX('Logic Tree'!$J$73:$N$74,MATCH(H55,'Logic Tree'!$I$73:$I$74,0),MATCH(G55,'Logic Tree'!$J$72:$N$72,0)) -> 0.84
A56: 3 | B56: POD | C56: VS2 | D56: FS | E56: ='Pod Library'!E76 -> AI Orchestrator | F56: ='Pod Library'!F76 -> ENG | G56: ='Pod Library'!G76 -> E4 | H56: ='Pod Library'!H76 -> OFF | I56: ='Pod Library'!I76 -> FTC | J56: ='Pod Library'!J76 -> 1 | K56: =SUMIFS('Pod Plan'!$F:$F,'Pod Plan'!$B:$B,$A56,'Pod Plan'!$C:$C,$C56) -> 1 | L56: =J56*K56 -> 1 | M56: =L56*INDEX('Logic Tree'!$J$73:$N$74,MATCH(H56,'Logic Tree'!$I$73:$I$74,0),MATCH(G56,'Logic Tree'!$J$72:$N$72,0)) -> 0.6
A57: 3 | B57: POD | C57: VS2 | D57: FS | E57: ='Pod Library'!E77 -> AI-assisted Developer | F57: ='Pod Library'!F77 -> DEV | G57: ='Pod Library'!G77 -> E3 | H57: ='Pod Library'!H77 -> OFF | I57: ='Pod Library'!I77 -> FTC | J57: ='Pod Library'!J77 -> 1 | K57: =SUMIFS('Pod Plan'!$F:$F,'Pod Plan'!$B:$B,$A57,'Pod Plan'!$C:$C,$C57) -> 1 | L57: =J57*K57 -> 1 | M57: =L57*INDEX('Logic Tree'!$J$73:$N$74,MATCH(H57,'Logic Tree'!$I$73:$I$74,0),MATCH(G57,'Logic Tree'!$J$72:$N$72,0)) -> 0.42
A58: 3 | B58: POD | C58: VS3 | D58: FS | E58: ='Pod Library'!E80 -> AI Orchestrator — MGCC Hyderabad | F58: ='Pod Library'!F80 -> ENG | G58: ='Pod Library'!G80 -> E3 | H58: ='Pod Library'!H80 -> OFF | I58: ='Pod Library'!I80 -> MGCC | J58: ='Pod Library'!J80 -> 1 | K58: =SUMIFS('Pod Plan'!$F:$F,'Pod Plan'!$B:$B,$A58,'Pod Plan'!$C:$C,$C58) -> 1 | L58: =J58*K58 -> 1 | M58: =L58*INDEX('Logic Tree'!$J$73:$N$74,MATCH(H58,'Logic Tree'!$I$73:$I$74,0),MATCH(G58,'Logic Tree'!$J$72:$N$72,0)) -> 0.42
A59: ='Horizontal Teams'!B5 -> 1 | B59: HZ | C59: ='Horizontal Teams'!C5 -> H1 | D59: HZ | E59: ='Horizontal Teams'!E5 -> Compensation Plan Administration Lead | F59: ='Horizontal Teams'!F5 -> LEAD | G59: ='Horizontal Teams'!G5 -> E4 | H59: ='Horizontal Teams'!H5 -> ON | I59: ='Horizontal Teams'!I5 -> FTC | J59: ='Horizontal Teams'!J5 -> 1 | K59: 1 | L59: =IF(ISNUMBER(J59),J59*K59,0) -> 1 | M59: =IFERROR(L59*INDEX('Logic Tree'!$J$73:$N$74,MATCH(H59,'Logic Tree'!$I$73:$I$74,0),MATCH(G59,'Logic Tree'!$J$72:$N$72,0)),0) -> 1.85
A60: ='Horizontal Teams'!B7 -> 1 | B60: HZ | C60: ='Horizontal Teams'!C7 -> H2 | D60: HZ | E60: ='Horizontal Teams'!E7 -> Calculation QA & Audit Analyst | F60: ='Horizontal Teams'!F7 -> TEST | G60: ='Horizontal Teams'!G7 -> E3 | H60: ='Horizontal Teams'!H7 -> OFF | I60: ='Horizontal Teams'!I7 -> FTC | J60: ='Horizontal Teams'!J7 -> 1 | K60: 1 | L60: =IF(ISNUMBER(J60),J60*K60,0) -> 1 | M60: =IFERROR(L60*INDEX('Logic Tree'!$J$73:$N$74,MATCH(H60,'Logic Tree'!$I$73:$I$74,0),MATCH(G60,'Logic Tree'!$J$72:$N$72,0)),0) -> 0.42
A61: ='Horizontal Teams'!B9 -> 1 | B61: HZ | C61: ='Horizontal Teams'!C9 -> H3 | D61: HZ | E61: ='Horizontal Teams'!E9 -> Compliance & Regulatory Analyst (Fee & Commission Rules) | F61: ='Horizontal Teams'!F9 -> BA | G61: ='Horizontal Teams'!G9 -> E3 | H61: ='Horizontal Teams'!H9 -> ON | I61: ='Horizontal Teams'!I9 -> FTC | J61: ='Horizontal Teams'!J9 -> 1 | K61: 1 | L61: =IF(ISNUMBER(J61),J61*K61,0) -> 1 | M61: =IFERROR(L61*INDEX('Logic Tree'!$J$73:$N$74,MATCH(H61,'Logic Tree'!$I$73:$I$74,0),MATCH(G61,'Logic Tree'!$J$72:$N$72,0)),0) -> 1.35
A62: ='Horizontal Teams'!B11 -> 1 | B62: HZ | C62: ='Horizontal Teams'!C11 -> H4 | D62: HZ | E62: ='Horizontal Teams'!E11 -> Domain Delivery Head | F62: ='Horizontal Teams'!F11 -> LEAD | G62: ='Horizontal Teams'!G11 -> E5 | H62: ='Horizontal Teams'!H11 -> ON | I62: ='Horizontal Teams'!I11 -> FTC | J62: ='Horizontal Teams'!J11 -> 1 | K62: 1 | L62: =IF(ISNUMBER(J62),J62*K62,0) -> 1 | M62: =IFERROR(L62*INDEX('Logic Tree'!$J$73:$N$74,MATCH(H62,'Logic Tree'!$I$73:$I$74,0),MATCH(G62,'Logic Tree'!$J$72:$N$72,0)),0) -> 2.55
A63: ='Horizontal Teams'!B12 -> 1 | B63: HZ | C63: ='Horizontal Teams'!C12 -> H4 | D63: HZ | E63: ='Horizontal Teams'!E12 -> Chief Fee Systems Architect (MetLife) | F63: ='Horizontal Teams'!F12 -> ENG | G63: ='Horizontal Teams'!G12 -> E5 | H63: ='Horizontal Teams'!H12 -> ON | I63: ='Horizontal Teams'!I12 -> FTE | J63: ='Horizontal Teams'!J12 -> 1 | K63: 1 | L63: =IF(ISNUMBER(J63),J63*K63,0) -> 1 | M63: =IFERROR(L63*INDEX('Logic Tree'!$J$73:$N$74,MATCH(H63,'Logic Tree'!$I$73:$I$74,0),MATCH(G63,'Logic Tree'!$J$72:$N$72,0)),0) -> 2.55
A64: ='Horizontal Teams'!B16 -> 2 | B64: HZ | C64: ='Horizontal Teams'!C16 -> H1 | D64: HZ | E64: ='Horizontal Teams'!E16 -> Compensation Plan Administration Lead | F64: ='Horizontal Teams'!F16 -> LEAD | G64: ='Horizontal Teams'!G16 -> E4 | H64: ='Horizontal Teams'!H16 -> ON | I64: ='Horizontal Teams'!I16 -> FTC | J64: ='Horizontal Teams'!J16 -> 1 | K64: 1 | L64: =IF(ISNUMBER(J64),J64*K64,0) -> 1 | M64: =IFERROR(L64*INDEX('Logic Tree'!$J$73:$N$74,MATCH(H64,'Logic Tree'!$I$73:$I$74,0),MATCH(G64,'Logic Tree'!$J$72:$N$72,0)),0) -> 1.85
A65: ='Horizontal Teams'!B18 -> 2 | B65: HZ | C65: ='Horizontal Teams'!C18 -> H2 | D65: HZ | E65: ='Horizontal Teams'!E18 -> Calculation QA & Audit Analyst | F65: ='Horizontal Teams'!F18 -> TEST | G65: ='Horizontal Teams'!G18 -> E3 | H65: ='Horizontal Teams'!H18 -> OFF | I65: ='Horizontal Teams'!I18 -> FTC | J65: ='Horizontal Teams'!J18 -> 1 | K65: 1 | L65: =IF(ISNUMBER(J65),J65*K65,0) -> 1 | M65: =IFERROR(L65*INDEX('Logic Tree'!$J$73:$N$74,MATCH(H65,'Logic Tree'!$I$73:$I$74,0),MATCH(G65,'Logic Tree'!$J$72:$N$72,0)),0) -> 0.42
A66: ='Horizontal Teams'!B20 -> 2 | B66: HZ | C66: ='Horizontal Teams'!C20 -> H4 | D66: HZ | E66: ='Horizontal Teams'!E20 -> Domain Delivery Head | F66: ='Horizontal Teams'!F20 -> LEAD | G66: ='Horizontal Teams'!G20 -> E5 | H66: ='Horizontal Teams'!H20 -> ON | I66: ='Horizontal Teams'!I20 -> FTC | J66: ='Horizontal Teams'!J20 -> 1 | K66: 1 | L66: =IF(ISNUMBER(J66),J66*K66,0) -> 1 | M66: =IFERROR(L66*INDEX('Logic Tree'!$J$73:$N$74,MATCH(H66,'Logic Tree'!$I$73:$I$74,0),MATCH(G66,'Logic Tree'!$J$72:$N$72,0)),0) -> 2.55
A67: ='Horizontal Teams'!B21 -> 2 | B67: HZ | C67: ='Horizontal Teams'!C21 -> H4 | D67: HZ | E67: ='Horizontal Teams'!E21 -> Chief Fee Systems Architect (MetLife) | F67: ='Horizontal Teams'!F21 -> ENG | G67: ='Horizontal Teams'!G21 -> E5 | H67: ='Horizontal Teams'!H21 -> ON | I67: ='Horizontal Teams'!I21 -> FTE | J67: ='Horizontal Teams'!J21 -> 1 | K67: 1 | L67: =IF(ISNUMBER(J67),J67*K67,0) -> 1 | M67: =IFERROR(L67*INDEX('Logic Tree'!$J$73:$N$74,MATCH(H67,'Logic Tree'!$I$73:$I$74,0),MATCH(G67,'Logic Tree'!$J$72:$N$72,0)),0) -> 2.55
A68: ='Horizontal Teams'!B25 -> 3 | B68: HZ | C68: ='Horizontal Teams'!C25 -> H1 | D68: HZ | E68: ='Horizontal Teams'!E25 -> Compensation Plan Administration Lead | F68: ='Horizontal Teams'!F25 -> LEAD | G68: ='Horizontal Teams'!G25 -> E4 | H68: ='Horizontal Teams'!H25 -> OFF | I68: ='Horizontal Teams'!I25 -> FTC | J68: ='Horizontal Teams'!J25 -> 1 | K68: 1 | L68: =IF(ISNUMBER(J68),J68*K68,0) -> 1 | M68: =IFERROR(L68*INDEX('Logic Tree'!$J$73:$N$74,MATCH(H68,'Logic Tree'!$I$73:$I$74,0),MATCH(G68,'Logic Tree'!$J$72:$N$72,0)),0) -> 0.6
A69: ='Horizontal Teams'!B27 -> 3 | B69: HZ | C69: ='Horizontal Teams'!C27 -> H4 | D69: HZ | E69: ='Horizontal Teams'!E27 -> Domain Delivery Head | F69: ='Horizontal Teams'!F27 -> LEAD | G69: ='Horizontal Teams'!G27 -> E5 | H69: ='Horizontal Teams'!H27 -> OFF | I69: ='Horizontal Teams'!I27 -> FTC | J69: ='Horizontal Teams'!J27 -> 1 | K69: 1 | L69: =IF(ISNUMBER(J69),J69*K69,0) -> 1 | M69: =IFERROR(L69*INDEX('Logic Tree'!$J$73:$N$74,MATCH(H69,'Logic Tree'!$I$73:$I$74,0),MATCH(G69,'Logic Tree'!$J$72:$N$72,0)),0) -> 0.85
A70: ='Horizontal Teams'!B28 -> 3 | B70: HZ | C70: ='Horizontal Teams'!C28 -> H4 | D70: HZ | E70: ='Horizontal Teams'!E28 -> Chief Fee Systems Architect (MetLife) | F70: ='Horizontal Teams'!F28 -> ENG | G70: ='Horizontal Teams'!G28 -> E5 | H70: ='Horizontal Teams'!H28 -> ON | I70: ='Horizontal Teams'!I28 -> FTE | J70: ='Horizontal Teams'!J28 -> 1 | K70: 1 | L70: =IF(ISNUMBER(J70),J70*K70,0) -> 1 | M70: =IFERROR(L70*INDEX('Logic Tree'!$J$73:$N$74,MATCH(H70,'Logic Tree'!$I$73:$I$74,0),MATCH(G70,'Logic Tree'!$J$72:$N$72,0)),0) -> 2.55
